{"job_id": "GwFWalkwPzlQGA7rAAAAAA==", "employer_name": "GHX", "employer_logo": "https://www.ghx.com/Themes/GHXDesign2021/Assets/img/GHX-logo.svg", "employer_website": "https://www.ghx.com", "employer_company_type": null, "job_publisher": "Media Bistro", "job_employment_type": "FULLTIME", "job_title": "Senior Data Scientist \u2013 UI, Visualization Focus", "job_apply_link": "https://www.mediabistro.com/jobs/176325504-senior-data-scientist-ui-visualization-focus", "job_apply_is_direct": false, "job_apply_quality_score": 0.6591, "apply_options": [{"publisher": "Media Bistro", "apply_link": "https://www.mediabistro.com/jobs/176325504-senior-data-scientist-ui-visualization-focus", "is_direct": false}, {"publisher": "Colorado Jobs - Tarta.ai", "apply_link": "https://colorado.tarta.ai/j/uoLSZo0BcRajQcTjBRkg0124-senior-data-scientist-ui-visualization-focus-greater-boulder-area-co-or-remote-in-louisville-at-ghx", "is_direct": false}], "job_description": "The Sr. Data Scientist is a highly skilled scientist and software developer reporting to the Director of Data Science with a broad skill set who will be responsible for developing advanced UI and Visualization capabilities that leverage modern, advanced data science techniques to the challenges GHX faces in helping to bend the cost curve in healthcare. The Sr. Data Scientist will leverage Generative AI solutions combined with internal and external data, to produce Co-Pilot applications to solve Healthcare Supply Chain problems.The Sr. Data Scientist will need to be adept at producing intelligence that serves multiple stakeholders simultaneously, including the traditional GHX customer base of hospitals, manufacturers, and distributors, as well as patients, physicians, payors, government, and the investment community. In addition, the role will support internal GHX departments in making data-driven decisions.The Sr. Data Scientist will have high level of expertise in UI design and visualization, as well as experience in full stack development and AI, Machine Learning and Data Science. They should have relevant experience in applying such tools to producing practical, scalable solutions. This person will work collaboratively within a team of data scientists as well as with end users, product management, development, and other stakeholder groups.This person will need to work from our Louisville, CO office one day per week.Key ResponsibilitiesCreate UI components to support continuous improvement through HITL and RLHF solutions that fit naturally in existing workflows.Work closely with end users and other stake holders to create solutions that are rapidly adopted.Envision and create UX components and workflows to optimize processes.Integrate existing internal API capabilities as well as existing and future AI and GenAI capabilities.Design, recommend and implement novel solutions for complex business problems and apply appropriate architectures.Assess the effectiveness and accuracy of machine learning methods and techniques.Design solutions that integrate with existing workflows that may include human-machine partnerships.Coordinate and mentor junior Data Scientists.Provide quality feedback and insightful guidance to cross-functional teams to design optimal solutions.Adhere to sound software engineering practices.Independently and collaboratively develop solutions and strategies to solve key business problems with minimal to no guidance.Develop diagnostic tools related to understand and optimize the healthcare supply chain.Take problem from idea to production ready monitored application.Develop robust reusable software infrastructure.Develop processes and tools to build, monitor and analyze model performance.Share results with all stakeholders and broader community in an easily accessible and understandable way.Build solutions that may combine many different data science methods such as: clustering, parameter inference, feature design, feature discovery, feature engineering, classification, regression, visualization, etc.Key CompetenciesAdept with a wide range of visualization methods to facilitate targeted analysis.Expert in UI development and visualization.Expertise in one or more machine learning or advanced statistical domains and their real-world applications, advantages, and drawbacks (e.g. clustering, decision tree learning, artificial neural networks, Bayesian methods, Graphical Models, etc.).Creativity in solving challenging problems with uncertain solutions.Adaptability and flexibility. Ability to juggle multiple projects serving a diverse array of stakeholders.Excellent verbal and written communication skills. Ability to present findings clearly to both technical and non-technical audiences.Excellent problem-solving skills applicable to internal and external needs.Experience with at least one database technology (e.g. Tabular, Graph, Document, Vector, etc.)Proficiency in at least one statistical and data-oriented programming language (e.g. Python, R, etc.).Experience working with and creating data structures, abstract data types, domain models.Demonstrated ability to work both independently and collaboratively.Required Education, Certifications, and ExperienceBS in computer science or related technical field.3+ years of experience building front end solutions for AI, ML, Data Science applications.2+ years\u2019 experience using statistical computer languages (R, Python, SQL, Julia, etc.)3+ years\u2019 experience using a variety of data science and/or machine learning methods.Preferred QualificationsExperience with UI development within Salesforce.Experience with AngularExperience/background in healthcare and/or supply chain management.Experience with AWS ecosystem.Experience with GenAI models and solutions.Experience working with multiple database technologies (e.g. Tabular, Graph, Document, Vector, etc.)Key DifferentiatorsInsatiable curiosity with an orientation towards finding creative ways to add value to customers and other stakeholdersA drive to learn and master new technologies and techniquesA creative thought leader who challenges orthodoxyHighly collaborative personalityEstimated salary range: $122,900 - $163,800The base salary range represents the anticipated low and high end of the GHX\u2019s salary range for this position. Actual salaries will vary and will be based on various factors, such as candidate\u2019s qualifications, skills, competencies and proficiency for the role. The base salary is one component of GHX\u2019s total compensation package for employees. Other rewards and benefits include: health, vision, and dental insurance, accident and life insurance, 401k matching, paid-time off, and education reimbursement, to name a few. To view more details of our benefits, visit us here: https://www.ghx.com/about/careers/GHX: It's the way you do business in healthcareGlobal Healthcare Exchange (GHX) enables better patient care and billions in savings for the healthcare community by maximizing automation, efficiency and accuracy of business processes.GHX is a healthcare business and data automation company, empowering healthcare organizations to enable better patient care and maximize industry savings using our world class cloud-based supply chain technology exchange platform, solutions, analytics and services. We bring together healthcare providers and manufacturers and distributors in North America and Europe - who rely on smart, secure healthcare-focused technology and comprehensive data to automate their business processes and make more informed decisions.It is our passion and vision for a more operationally efficient healthcare supply chain, helping organizations reduce - not shift - the cost of doing business, paving the way to delivering patient care more effectively. Together we take more than a billion dollars out of the cost of delivering healthcare every year. GHX is privately owned, operates in the United States, Canada and Europe, and employs more than 1000 people worldwide. Our corporate headquarters is in Colorado, with additional offices in Europe, Illinois, Florida, and Nebraska.DisclaimerGlobal Healthcare Exchange, LLC and its North American subsidiaries (collectively, \u201cGHX\u201d) provides equal employment opportunities (EEO) to all employees and applicants for employment without regard to race, color, national origin, sex, sexual orientation, gender identity, religion, age, genetic information, disability, veteran status or any other status protected by applicable law. All qualified applicants will receive consideration for employment without regard to any status protected by applicable law. This EEO policy applies to all terms, conditions, and privileges of employment, including hiring, training and development, promotion, transfer, compensation, benefits, educational assistance, termination, layoffs, social and recreational programs, and retirement.GHX believes that employees should be provided with a working environment which enables each employee to be productive and to work to the best of his or her ability. We do not condone or tolerate an atmosphere of intimidation or harassment based on race, color, national origin, sex, sexual orientation, gender identity, religion, age, genetic information, disability, veteran status or any other status protected by applicable law. GHX expects and requires the cooperation of all employees in maintaining a discrimination and harassment-free atmosphere. Improper interference with the ability of GHX\u2019s employees to perform their expected job duties is absolutely not tolerated.#J-18808-Ljbffr", "job_is_remote": false, "job_posted_at_timestamp": 1707670800, "job_posted_at_datetime_utc": "2024-02-11T17:00:00.000Z", "job_city": null, "job_state": null, "job_country": "US", "job_latitude": 37.09024, "job_longitude": -95.71289, "job_benefits": ["dental_coverage", "retirement_savings", "paid_time_off", "health_insurance"], "job_google_link": "https://www.google.com/search?gl=us&hl=en&rciv=jb&q=senior+data+scientist&start=60&ibp=htl;jobs#fpstate=tldetail&htivrt=jobs&htiq=senior+data+scientist&htidocid=GwFWalkwPzlQGA7rAAAAAA%3D%3D", "job_offer_expiration_datetime_utc": null, "job_offer_expiration_timestamp": null, "job_required_experience": {"no_experience_required": false, "required_experience_in_months": null, "experience_mentioned": true, "experience_preferred": true}, "job_required_skills": null, "job_required_education": {"postgraduate_degree": false, "professional_certification": false, "high_school": false, "associates_degree": false, "bachelors_degree": false, "degree_mentioned": true, "degree_preferred": false, "professional_certification_mentioned": true}, "job_experience_in_place_of_education": false, "job_min_salary": null, "job_max_salary": null, "job_salary_currency": null, "job_salary_period": null, "job_highlights": {"Qualifications": ["They should have relevant experience in applying such tools to producing practical, scalable solutions", "Expertise in one or more machine learning or advanced statistical domains and their real-world applications, advantages, and drawbacks (e.g. clustering, decision tree learning, artificial neural networks, Bayesian methods, Graphical Models, etc.).Creativity in solving challenging problems with uncertain solutions", "Adaptability and flexibility", "Ability to juggle multiple projects serving a diverse array of stakeholders", "Excellent verbal and written communication skills", "Ability to present findings clearly to both technical and non-technical audiences", "Excellent problem-solving skills applicable to internal and external needs", "Experience with at least one database technology (e.g", "Tabular, Graph, Document, Vector, etc.)Proficiency in at least one statistical and data-oriented programming language (e.g. Python, R, etc.).Experience working with and creating data structures, abstract data types, domain models", "Demonstrated ability to work both independently and collaboratively", "Required Education, Certifications, and ExperienceBS in computer science or related technical field.3+ years of experience building front end solutions for AI, ML, Data Science applications.2+ years\u2019 experience using statistical computer languages (R, Python, SQL, Julia, etc.)3+ years\u2019 experience using a variety of data science and/or machine learning methods", "Experience with AngularExperience/background in healthcare and/or supply chain management", "Experience with AWS ecosystem", "Experience with GenAI models and solutions", "Experience working with multiple database technologies (e.g", "Tabular, Graph, Document, Vector, etc.)Key DifferentiatorsInsatiable curiosity with an orientation towards finding creative ways to add value to customers and other stakeholdersA drive to learn and master new technologies and techniquesA creative thought leader who challenges orthodoxy", "Highly collaborative personality"], "Responsibilities": ["Data Scientist will leverage Generative AI solutions combined with internal and external data, to produce Co-Pilot applications to solve Healthcare Supply Chain problems", "Data Scientist will need to be adept at producing intelligence that serves multiple stakeholders simultaneously, including the traditional GHX customer base of hospitals, manufacturers, and distributors, as well as patients, physicians, payors, government, and the investment community", "Data Scientist will have high level of expertise in UI design and visualization, as well as experience in full stack development and AI, Machine Learning and Data Science", "This person will work collaboratively within a team of data scientists as well as with end users, product management, development, and other stakeholder groups", "This person will need to work from our Louisville, CO office one day per week", "Key ResponsibilitiesCreate UI components to support continuous improvement through HITL and RLHF solutions that fit naturally in existing workflows", "Work closely with end users and other stake holders to create solutions that are rapidly adopted", "Envision and create UX components and workflows to optimize processes", "Integrate existing internal API capabilities as well as existing and future AI and GenAI capabilities.Design, recommend and implement novel solutions for complex business problems and apply appropriate architectures", "Assess the effectiveness and accuracy of machine learning methods and techniques", "Design solutions that integrate with existing workflows that may include human-machine partnerships", "Coordinate and mentor junior Data Scientists", "Provide quality feedback and insightful guidance to cross-functional teams to design optimal solutions", "Adhere to sound software engineering practices", "Independently and collaboratively develop solutions and strategies to solve key business problems with minimal to no guidance", "Develop diagnostic tools related to understand and optimize the healthcare supply chain", "Take problem from idea to production ready monitored application", "Develop robust reusable software infrastructure", "Develop processes and tools to build, monitor and analyze model performance", "Share results with all stakeholders and broader community in an easily accessible and understandable way", "Build solutions that may combine many different data science methods such as: clustering, parameter inference, feature design, feature discovery, feature engineering, classification, regression, visualization, etc", "Key CompetenciesAdept with a wide range of visualization methods to facilitate targeted analysis"], "Benefits": ["Estimated salary range: $122,900 - $163,800The base salary range represents the anticipated low and high end of the GHX\u2019s salary range for this position", "The base salary is one component of GHX\u2019s total compensation package for employees", "Other rewards and benefits include: health, vision, and dental insurance, accident and life insurance, 401k matching, paid-time off, and education reimbursement, to name a few"]}, "job_job_title": "Data scientist", "job_posting_language": "en", "job_onet_soc": "15111100", "job_onet_job_zone": "5"}