{"job_id": "vwykOsjtPWicleEOAAAAAA==", "employer_name": "Ivy Tech Community College of Indiana", "employer_logo": "https://www.ivytech.edu/content/img/logos/ivy-tech-horiz-white.png", "employer_website": "http://www.ivytech.edu", "employer_company_type": "Education", "job_publisher": "Workday", "job_employment_type": "PARTTIME", "job_title": "Marketing PT Support", "job_apply_link": "https://ivytech.wd1.myworkdayjobs.com/en-US/Ivy_Tech_Careers/job/Marketing-PT-Support_JR0000101273", "job_apply_is_direct": false, "job_apply_quality_score": 0.8812, "apply_options": [{"publisher": "Workday", "apply_link": "https://ivytech.wd1.myworkdayjobs.com/en-US/Ivy_Tech_Careers/job/Marketing-PT-Support_JR0000101273", "is_direct": false}], "job_description": "Fulfills support responsibilities for Marketing and Communications. Videography/Photography Produce campus promotional, recruitment and development materials and publications \u2013 both print and electronic. Create, edit, and utilize video for departments, events, and marketing campaigns. Implement marketing posts through social media platforms. Data entry for web and social media. Web Site Serves a contact for all aspects of the organizations website(s), handling a range of responsibilities that may include web design and development, routine site and content maintenance, and various updates to ensure sites align with the goals and objectives of the company. Edits the South Bend and Elkhart sites. May attend Systems Office trainings for the website and facilitates necessary communication to the Marketing Team in order to be shared out with the college. This role also provides analytics and reporting on websites for leadership. Content Creator Assisting the marketing team with the design of promotional materials. Using social media to engage consumers, respond to questions or complaints, and to promote company initiatives. Collaborating with internal departments to establish campaign objectives, complete tasks, and identify and solve problems. Monitoring social media and company website metrics. This is not to be construed as an exhaustive list. Other duties logically associated with this position may be assigned. All responsibilities will be conducted within the parameters of the Family Educational Rights and Privacy Act (FERPA), other applicable regulatory requirements, and professional standards. Flexible Scheduling $15.00 per hour Minimum high school diploma, GED, or equivalent required. One to two years related work experience required. Knowledge of basic camera operations. Software proficiency required: MS Office Suite and Adobe Suite. Strong computer skills are necessary. Excellent verbal and written skills required. Strong grammatical and spelling skills required. Must be a self-starter, able to work without direct supervision, and able to respond to the needs of the college in a timely and professional manner. Must be able to handle confidential information. Must be able to work under deadline with several projects at once. Ivy Tech Community College is an accredited, equal opportunity/affirmative action employer. All qualified applicants will receive consideration for employment without regard to race, color, ethnicity, national origin, marital status, religion, sex, gender, sexual orientation, gender identity, disability, age or veteran status. As required by Title IX of the Education Amendments of 1972, Ivy Tech Community College does not discriminate on the basis of sex, including sexual harassment in its educational programs and activities, including employment and admissions. Questions specific to Title IX may be referred to the College\u2019s Title IX Coordinator or to the US Department of Education Office of Civil Rights. Ivy Tech is the largest singly accredited community college system in the nation. Offering services to the entire state of Indiana, we\u2019re here to educate, motivate, and inspire students every day. We do that by featuring some of the most advanced technologies and training facilities, making higher education accessible through more affordable tuition, and providing smaller class sizes for more individualized attention. By sharing our joy of learning, we hope to ignite the curiosity and passion in our students that will help them discover their greatest potential. We\u2019re highly collaborative, with a friendly and helpful culture that is very different from a four-year college. Innovation is another value that sets us apart \u2014 we are always looking for ways to make things better for our students, faculty, and staff. One of our key goals is to foster creativity and innovation in employees. More than anything, you\u2019ll find yourself inspired each day by the camaraderie, positivity, and dedication that surrounds you at Ivy Tech.", "job_is_remote": true, "job_posted_at_timestamp": 1705536000, "job_posted_at_datetime_utc": "2024-01-18T00:00:00.000Z", "job_city": "South Bend", "job_state": "IN", "job_country": "US", "job_latitude": 41.676353, "job_longitude": -86.25199, "job_benefits": null, "job_google_link": "https://www.google.com/search?gl=us&hl=en&rciv=jb&q=marketing&start=80&ibp=htl;jobs#fpstate=tldetail&htivrt=jobs&htiq=marketing&htidocid=vwykOsjtPWicleEOAAAAAA%3D%3D", "job_offer_expiration_datetime_utc": null, "job_offer_expiration_timestamp": null, "job_required_experience": {"no_experience_required": false, "required_experience_in_months": 12, "experience_mentioned": true, "experience_preferred": false}, "job_required_skills": null, "job_required_education": {"postgraduate_degree": false, "professional_certification": false, "high_school": false, "associates_degree": false, "bachelors_degree": false, "degree_mentioned": false, "degree_preferred": false, "professional_certification_mentioned": false}, "job_experience_in_place_of_education": false, "job_min_salary": null, "job_max_salary": null, "job_salary_currency": null, "job_salary_period": null, "job_highlights": {"Qualifications": ["Flexible Scheduling $15.00 per hour Minimum high school diploma, GED, or equivalent required", "One to two years related work experience required", "Knowledge of basic camera operations", "Software proficiency required: MS Office Suite and Adobe Suite", "Strong computer skills are necessary", "Excellent verbal and written skills required", "Strong grammatical and spelling skills required", "Must be a self-starter, able to work without direct supervision, and able to respond to the needs of the college in a timely and professional manner", "Must be able to handle confidential information", "Must be able to work under deadline with several projects at once"], "Responsibilities": ["Fulfills support responsibilities for Marketing and Communications", "Videography/Photography Produce campus promotional, recruitment and development materials and publications \u2013 both print and electronic", "Create, edit, and utilize video for departments, events, and marketing campaigns", "Implement marketing posts through social media platforms", "Data entry for web and social media", "May attend Systems Office trainings for the website and facilitates necessary communication to the Marketing Team in order to be shared out with the college", "This role also provides analytics and reporting on websites for leadership", "Content Creator Assisting the marketing team with the design of promotional materials", "Using social media to engage consumers, respond to questions or complaints, and to promote company initiatives", "Collaborating with internal departments to establish campaign objectives, complete tasks, and identify and solve problems", "Monitoring social media and company website metrics", "All responsibilities will be conducted within the parameters of the Family Educational Rights and Privacy Act (FERPA), other applicable regulatory requirements, and professional standards"]}, "job_job_title": "Marketing", "job_posting_language": "en", "job_onet_soc": "13116100", "job_onet_job_zone": "4", "job_naics_code": "61", "job_naics_name": "Education"}