{"job_id": "Vbb2k5ohH7zrRMoiAAAAAA==", "employer_name": "Certara", "employer_logo": null, "employer_website": "http://www.certara.com", "employer_company_type": null, "job_publisher": "Certara Careers", "job_employment_type": "FULLTIME", "job_title": "Director Business Development, IDD", "job_apply_link": "https://careers.certara.com/jobs/1867?lang=en-us", "job_apply_is_direct": true, "job_apply_quality_score": 0.8245, "apply_options": [{"publisher": "Certara Careers", "apply_link": "https://careers.certara.com/jobs/1867?lang=en-us", "is_direct": true}, {"publisher": "Snagajob", "apply_link": "https://www.snagajob.com/jobs/912965188", "is_direct": false}, {"publisher": "ZipRecruiter", "apply_link": "https://www.ziprecruiter.com/c/Certara/Job/Director-Business-Development,-IDD/-in-Menlo-Park,CA?jid=4ebf156a0957e421", "is_direct": false}, {"publisher": "LinkedIn", "apply_link": "https://www.linkedin.com/jobs/view/director-business-development-idd-at-certara-3849801635", "is_direct": false}, {"publisher": "DiversityJobs", "apply_link": "https://diversityjobs.com/career/7523726/Director-Business-Development-Idd-California-Menlo-Park", "is_direct": false}, {"publisher": "Ladders", "apply_link": "https://www.theladders.com/job/director-business-development-idd-certara-menlo-park-ca_68989722", "is_direct": false}, {"publisher": "SimplyHired", "apply_link": "https://www.simplyhired.com/job/AAwKPHBhsDD4Oqu9mjlbsUJjhea3uCtuZ14ZAVYKUrzcpZRtFC8BDw", "is_direct": false}, {"publisher": "Offered.AI", "apply_link": "https://www.offered.ai/jobs/cltmppvzr1c8gt94ldd0v4am5", "is_direct": false}], "job_description": "Overview\n\nThe base salary range for this position is $159,000 - $215,000 annually. This position is also subject to a performance based variable compensation plan.\n\nCommitted to scientific, regulatory and commercial advancement, Certara has organized its capabilities to create impactful patient-focused solutions to optimize the drug development, regulatory and commercial success of its clients. The largest and most comprehensive provider of strategic drug development, modeling and simulation and regulatory science services, Certara partners with its clients for optimizing drug development decisions. We are dedicated to helping our clients develop new therapies and target unmet medical needs, expand the benefits of existing therapies to other populations, communicate scientific information in the language of regulatory success, balance risk profiles, differentiate drugs from a competitive perspective, and unlock millions in R&D savings.\n\nThe company includes a total global work force of ~1,300 employees with more than 450 PhD, PharmD, and MD scientists and regulatory writers, working on key drug development projects for biopharmaceutical companies. With each engagement, we provide the data-driven and regulatory science backbone regarding a drug\u2019s safety, efficacy, risk/benefit, and comparative effectiveness to increase our client\u2019s probability of regulatory and commercial success.\n\nAs an integral member of Certara\u2019s business development team, your work as Director of Business Development will involve identifying and building relationships with key decision makers both internally and externally. In this role, you will engage with potential drug development executives across the entire drug development continuum, and other key executives to illustrate the competitive advantage that Certara brings to help advance the clients program(s).\n\nThe Director can represent the entire range of Certara Services solutions to pharmaceutical, biotechnology and medical device companies within a designated region.\n\nThis is a highly consultative role requiring the Director to uncover customer needs through a deep understanding of their corporate, program-specific, and personal goals and design a customizable solution.\n\nResponsibilities\n\nCertara has openings in its exciting and transformational organization for highly motivated and energetic Business Development Professionals with a proven and demonstrated \u201cHunter\u201d track record for identifying and developing strategic business in new accounts.\n\nOur Director Business Development will be partnering with the BD Team Leaders and with world-class expert drug development consultants in client engagements and be supported during the Business Development process by required expert teams.\n\nOur Director Business Development will be responsible for:\n\u2022 Identifying, qualifying and pursuing strategic business within the assigned territory:\n\u2022 Understanding their internal resource expertise, capabilities and capacity, corporate objectives\n\u2022 Understanding their development program(s) focus, objectives and priorities\n\u2022 Understanding their critical decisions and challenges and service outsourcing strategies.\n\u2022 Facilitate and maintain mutual CDA and MSA contract execution for all accounts identified by Director Business Development or scientific consultants.\n\u2022 Present and refresh Certara capabilities overview to all existing accounts.\n\u2022 Actively engage with existing account decision makers in closing all CDDS business opportunities\n\u2022 Informs Commercial leadership on proposal and price quotation development efforts that best address the prospect\u2019s needs, while coordinating the involvement of all necessary personnel.\n\u2022 Within guidelines established by the Head of Business Development, s/he delivers and negotiates proposals and other legal agreements required to achieve sales targets while maintaining appropriate margin levels for each opportunity.\n\u2022 Presents new/expanded solutions options to prospects by identifying best-fit opportunities for Certara DDS solutions against the prospect\u2019s Need-to-Buy, and by developing strategies to communicate an appropriate, compelling message to the prospect.\n\u2022 Coordinates the seamless transition of newly contracted agreements within existing accounts to the CDDS teams respectively\n\u2022 Proactively assesses, clarifies, and validates assigned prospects\u2019 needs on an ongoing basis.\n\u2022 Proactively informs the team as to progress against monthly, quarterly and annual performance objectives, financial targets, and critical sales plan milestones.\n\u2022 Coordinates the involvement of Subject Matter Experts, including Regulatory, and Drug Development Services, Works closely with Proposals and Contracts team, and management resources, in order to meet sales performance objectives and prospects\u2019 expectations.\n\nOther Responsibilities:\n\u2022 To develop the appropriate strategy for discovering existing business opportunities to inform proposal creation.\n\u2022 Work as a member of the larger Certara Commercial team, including Marketing, Proposals & Contracts, Lead Generation.\n\u2022 Represent the Company at trade symposia and other professional associations, to promote services, engage with clients and prospects, and collect competitive intelligence.\n\u2022 Work with the CDDS team to engage subject matter expertise in the pre-sales process leading up to closure, post-close project delivery, and larger account management.\n\u2022 Work as a self-starter who will collaborate with other Commercial and Services functions that are dispersed globally.\n\u2022 Coordinate across other Certara businesses including Software, Simcyp, and, Evidence and Access to leverage the Certara\u2019s relationships and solutions\n\nQualifications\n\nQualifications\n\u2022 The ideal candidate has a passion for our industry, is solution-oriented, a creative problem solver, and has a tenacious desire to identify and close deals.\n\u2022 Minimum 3-5 years of outside sales experience in a consultative business-to-business sales environment\n\u2022 A seasoned and well-rounded biopharmaceutical executive is required with minimum combined business development experience of 3-5 years in a consultative business-to-business sales environment, representing the life sciences vertical, ideally with pharmaceutical drug development experience.\n\u2022 Able to lead strategic business planning process based on an understanding of industry trends and opportunities and effectively solve strategic challenges.\n\u2022 Proven ability to lead initiatives: work collaboratively with teams to achieve objectives. Achieves organizational focus on key priorities. Provides clear direction, delegates, actively communicates. Superior project management skills.\n\u2022 Proven success in working collaboratively with cross functional commercialization teams with a strong business orientation and ability to view issues from multiple functional perspectives.\n\u2022 Experienced and adept in a variety of negotiating settings. Able to engage effectively; establishes a clear negotiation strategy and manages a tight process. Proven experience in identifying, evaluating, and pursuing business development opportunities within new and existing key markets.\n\u2022 Experience with developing business cases to recommend and rationalize investments and other strategic actions.\n\u2022 Demonstrated ability to gain credibility through successful leadership in a matrix environment, across a range of functions, position levels and geography.\n\u2022 Understanding of pharmaceutical service organizations and their revenue drivers is strongly preferred.\n\u2022 Strong communication and influencing skills.\n\u2022 Ability and willingness to travel, domestically and internationally. This position will require frequent travel across the US, Canada, and possibly Europe (candidates must have a valid passport and driver\u2019s license).\n\u2022 Fluent in English. Additional language skills are desirable.\n\nPERSONAL ATTRIBUTES\n\u2022 High ethical standards and personal integrity\n\u2022 Highly energetic individual who welcomes accountability, a solid work ethic, and a commitment to quality while constantly looking for ways to contribute\n\u2022 Strategic thinking and ability to constructively challenge and influence the decision-making process.\n\u2022 Establishes clear expectations and priorities, drives initiatives to completion. Sets goals and consistently delivers against objectives. Monitors progress and proactively addresses issues and obstacles.\n\u2022 Ability to effectively translate overall strategies into actionable operational plans and assure implementation.\n\u2022 Ability to simplify and convey complex concepts and strategies orally and in writing and influence key decision makers.\n\u2022 Strong analytical skills with a data-driven focus\n\u2022 Ability to create and share a vision based on corporate mission.\n\u2022 Flexible and able to adapt to a quickly changing environment.", "job_is_remote": false, "job_posted_at_timestamp": 1709930340, "job_posted_at_datetime_utc": "2024-03-08T20:39:00.000Z", "job_city": "San Diego", "job_state": "CA", "job_country": "US", "job_latitude": 32.715736, "job_longitude": -117.16109, "job_benefits": null, "job_google_link": "https://www.google.com/search?gl=us&hl=en&rciv=jb&q=director+of+business+development&start=0&ibp=htl;jobs#fpstate=tldetail&htivrt=jobs&htiq=director+of+business+development&htidocid=Vbb2k5ohH7zrRMoiAAAAAA%3D%3D", "job_offer_expiration_datetime_utc": "2025-03-08T20:40:02.000Z", "job_offer_expiration_timestamp": 1741466402, "job_required_experience": {"no_experience_required": false, "required_experience_in_months": 36, "experience_mentioned": true, "experience_preferred": true}, "job_required_skills": ["UNAVAILABLE"], "job_required_education": {"postgraduate_degree": false, "professional_certification": false, "high_school": false, "associates_degree": false, "bachelors_degree": false, "degree_mentioned": true, "degree_preferred": false, "professional_certification_mentioned": false}, "job_experience_in_place_of_education": false, "job_min_salary": null, "job_max_salary": null, "job_salary_currency": null, "job_salary_period": null, "job_highlights": {"Qualifications": ["The ideal candidate has a passion for our industry, is solution-oriented, a creative problem solver, and has a tenacious desire to identify and close deals", "A seasoned and well-rounded biopharmaceutical executive is required with minimum combined business development experience of 3-5 years in a consultative business-to-business sales environment, representing the life sciences vertical, ideally with pharmaceutical drug development experience", "Able to lead strategic business planning process based on an understanding of industry trends and opportunities and effectively solve strategic challenges", "Proven ability to lead initiatives: work collaboratively with teams to achieve objectives", "Proven success in working collaboratively with cross functional commercialization teams with a strong business orientation and ability to view issues from multiple functional perspectives", "Experienced and adept in a variety of negotiating settings", "Able to engage effectively; establishes a clear negotiation strategy and manages a tight process", "Proven experience in identifying, evaluating, and pursuing business development opportunities within new and existing key markets", "Demonstrated ability to gain credibility through successful leadership in a matrix environment, across a range of functions, position levels and geography", "Strong communication and influencing skills", "Ability and willingness to travel, domestically and internationally", "This position will require frequent travel across the US, Canada, and possibly Europe (candidates must have a valid passport and driver\u2019s license)", "Fluent in English", "High ethical standards and personal integrity", "Highly energetic individual who welcomes accountability, a solid work ethic, and a commitment to quality while constantly looking for ways to contribute", "Strategic thinking and ability to constructively challenge and influence the decision-making process", "Establishes clear expectations and priorities, drives initiatives to completion", "Ability to simplify and convey complex concepts and strategies orally and in writing and influence key decision makers", "Strong analytical skills with a data-driven focus", "Ability to create and share a vision based on corporate mission"], "Responsibilities": ["As an integral member of Certara\u2019s business development team, your work as Director of Business Development will involve identifying and building relationships with key decision makers both internally and externally", "In this role, you will engage with potential drug development executives across the entire drug development continuum, and other key executives to illustrate the competitive advantage that Certara brings to help advance the clients program(s)", "The Director can represent the entire range of Certara Services solutions to pharmaceutical, biotechnology and medical device companies within a designated region", "This is a highly consultative role requiring the Director to uncover customer needs through a deep understanding of their corporate, program-specific, and personal goals and design a customizable solution", "Our Director Business Development will be partnering with the BD Team Leaders and with world-class expert drug development consultants in client engagements and be supported during the Business Development process by required expert teams", "Identifying, qualifying and pursuing strategic business within the assigned territory:", "Understanding their internal resource expertise, capabilities and capacity, corporate objectives", "Understanding their development program(s) focus, objectives and priorities", "Understanding their critical decisions and challenges and service outsourcing strategies", "Facilitate and maintain mutual CDA and MSA contract execution for all accounts identified by Director Business Development or scientific consultants", "Present and refresh Certara capabilities overview to all existing accounts", "Actively engage with existing account decision makers in closing all CDDS business opportunities", "Informs Commercial leadership on proposal and price quotation development efforts that best address the prospect\u2019s needs, while coordinating the involvement of all necessary personnel", "Within guidelines established by the Head of Business Development, s/he delivers and negotiates proposals and other legal agreements required to achieve sales targets while maintaining appropriate margin levels for each opportunity", "Presents new/expanded solutions options to prospects by identifying best-fit opportunities for Certara DDS solutions against the prospect\u2019s Need-to-Buy, and by developing strategies to communicate an appropriate, compelling message to the prospect", "Coordinates the seamless transition of newly contracted agreements within existing accounts to the CDDS teams respectively", "Proactively assesses, clarifies, and validates assigned prospects\u2019 needs on an ongoing basis", "Proactively informs the team as to progress against monthly, quarterly and annual performance objectives, financial targets, and critical sales plan milestones", "Coordinates the involvement of Subject Matter Experts, including Regulatory, and Drug Development Services, Works closely with Proposals and Contracts team, and management resources, in order to meet sales performance objectives and prospects\u2019 expectations", "To develop the appropriate strategy for discovering existing business opportunities to inform proposal creation", "Work as a member of the larger Certara Commercial team, including Marketing, Proposals & Contracts, Lead Generation", "Represent the Company at trade symposia and other professional associations, to promote services, engage with clients and prospects, and collect competitive intelligence", "Work with the CDDS team to engage subject matter expertise in the pre-sales process leading up to closure, post-close project delivery, and larger account management", "Work as a self-starter who will collaborate with other Commercial and Services functions that are dispersed globally", "Coordinate across other Certara businesses including Software, Simcyp, and, Evidence and Access to leverage the Certara\u2019s relationships and solutions", "Achieves organizational focus on key priorities", "Provides clear direction, delegates, actively communicates", "Sets goals and consistently delivers against objectives", "Monitors progress and proactively addresses issues and obstacles"], "Benefits": ["The base salary range for this position is $159,000 - $215,000 annually", "This position is also subject to a performance based variable compensation plan"]}, "job_job_title": "Director business", "job_posting_language": "en", "job_onet_soc": "11202100", "job_onet_job_zone": "4"}