{"job_id": "VQDq7cQ1du2gaB64AAAAAA==", "employer_name": "Google", "employer_logo": null, "employer_website": "http://www.google.com", "employer_company_type": "Information", "job_publisher": "Sams Social Media Club", "job_employment_type": "FULLTIME", "job_title": "Marketing Analytics Manager, Platforms and Ecosystems Marketing", "job_apply_link": "https://www.samssocialmediaclub.com/job/marketing-analytics-manager-platforms-and-ecosystems-marketing/", "job_apply_is_direct": true, "job_apply_quality_score": 0.6609, "apply_options": [{"publisher": "Sams Social Media Club", "apply_link": "https://www.samssocialmediaclub.com/job/marketing-analytics-manager-platforms-and-ecosystems-marketing/", "is_direct": true}], "job_description": "Sam\u2019s Social Media Club is helping Google find a Marketing Analytics Manager, Platforms and Ecosystems Marketing.\n\nNote: By applying to this position you will have an opportunity to share your preferred working location from the following: New York, NY, USA; Mountain View, CA, USA; San Francisco, CA, USA.\n\nMinimum qualifications:\n\u2022 Bachelor\u2019s degree in a quantitative field, business field, or equivalent practical experience.\n\u2022 3 years of experience working in analytical roles in marketing, data science, or financial services.\n\u2022 Experience with using data and analytics, SQL, R, or similar statistical programming languages to make decisions.\n\nPreferred qualifications:\n\u2022 3 years of experience in marketing analytics with design experiments, developing statistical models, measuring campaigns, and identifying optimization opportunities, or using data and analytics in technology or financial services.\n\u2022 Experience in performing analytics on mobile applications or app marketplaces.\n\u2022 Experience in processing and analyzing data from datasets.\n\u2022 Experience with cross-functional stakeholder management.\n\u2022 Knowledge of performance marketing or partner marketing.\n\u2022 Ability to multi-task in a fast-paced and constantly evolving environment supporting multiple products/teams concurrently.\n\nAbout the job\n\nAt its core, marketing at Google starts with technology and ends with the user, bringing both together in unconventional ways. Our job is to demonstrate how Google\u2019s products solve problems.\n\nIn this role, you will manage analytics of various marketing programs for products within Google Platforms and Ecosystems. You will develop methodologies to understand the impact from engagement marketing, direct response, and strategic programs within marketing. You will also identify the right metrics for success and develop measurement techniques to make investment recommendations. You will work with various internal stakeholders to support development of new programs that will improve customer engagement and business growth. This is an opportunity to guide impactful decisions that will improve the experience of users globally.\n\nThe US base salary range for this full-time position is $105,000-$154,000 + bonus + equity + benefits. Our salary ranges are determined by role, level, and location. The range displayed on each job posting reflects the minimum and maximum target for new hire salaries for the position across all US locations. Within the range, individual pay is determined by work location and additional factors, including job-related skills, experience, and relevant education or training. Your recruiter can share more about the specific salary range for your preferred location during the hiring process.\n\nPlease note that the compensation details listed in US role postings reflect the base salary only, and do not include bonus, equity, or benefits. Learn more about benefits at Google.\n\nResponsibilities\n\u2022 Manage marketing analytics for products like Google Play or Google Chrome. Establish metrics and measurement plans that explain the incremental impact of marketing campaigns.\n\u2022 Translate business questions into appropriate analytical projects that will inform strategic and tactical business decisions. Conduct end-to-end analysis autonomously and communicate insights.\n\u2022 Drive analytic insights and recommendations in structured and unstructured data environments, working with data sets or developing decision making frameworks in situations with limited data.\n\u2022 Partner cross-functionally with a wide variety of teams and stakeholders including product marketing managers, analysts, and engineers to execute high impact initiatives.\n\u2022 Identify and communicate insights to senior management and cross-functional stakeholders for better decision making.\n\nInformation collected and processed as part of your Google Careers profile, and any job applications that you choose to submit are subject to Google\u2019s applicant and candidate privacy policy.\n\nGoogle is proud to be an equal opportunity and affirmative action employer. We are committed to building a workforce that is representative of the users we serve, creating a culture of belonging and providing an equal employment opportunity regardless of race, creed, colour, religion, gender, sexual orientation, gender identity/expression, national origin, disability, age, genetic information, veteran status, marital status, pregnancy or related condition (including breastfeeding), expecting or parents-to-be, criminal histories consistent with legal requirements or any other basis protected by law. See also Google\u2019s EEO Policy, Know your rights: workplace discrimination is illegal, Belonging at Google and How we hire.\n\nIf you have a need that requires accommodation, please let us know by completing our Accommodations for Applicants form.\n\nGoogle is a global company and, in order to facilitate efficient collaboration and communication globally, English proficiency is a requirement for all roles unless stated otherwise in the job posting.\n\nTo all recruitment agencies: Google does not accept agency CVs. Please do not forward CVs to our jobs alias, Google employees or any other organisation location. Google is not responsible for any fees related to unsolicited CVs.", "job_is_remote": false, "job_posted_at_timestamp": 1704295318, "job_posted_at_datetime_utc": "2024-01-03T15:21:58.000Z", "job_city": null, "job_state": null, "job_country": "US", "job_latitude": 37.09024, "job_longitude": -95.71289, "job_benefits": ["health_insurance"], "job_google_link": "https://www.google.com/search?gl=us&hl=en&rciv=jb&q=manager+of+marketing+analytics&start=0&ibp=htl;jobs#fpstate=tldetail&htivrt=jobs&htiq=manager+of+marketing+analytics&htidocid=VQDq7cQ1du2gaB64AAAAAA%3D%3D", "job_offer_expiration_datetime_utc": null, "job_offer_expiration_timestamp": null, "job_required_experience": {"no_experience_required": false, "required_experience_in_months": 36, "experience_mentioned": true, "experience_preferred": true}, "job_required_skills": null, "job_required_education": {"postgraduate_degree": false, "professional_certification": false, "high_school": false, "associates_degree": false, "bachelors_degree": false, "degree_mentioned": true, "degree_preferred": true, "professional_certification_mentioned": false}, "job_experience_in_place_of_education": false, "job_min_salary": null, "job_max_salary": null, "job_salary_currency": null, "job_salary_period": null, "job_highlights": {"Qualifications": ["Bachelor\u2019s degree in a quantitative field, business field, or equivalent practical experience", "3 years of experience working in analytical roles in marketing, data science, or financial services", "Experience with using data and analytics, SQL, R, or similar statistical programming languages to make decisions"], "Responsibilities": ["In this role, you will manage analytics of various marketing programs for products within Google Platforms and Ecosystems", "You will develop methodologies to understand the impact from engagement marketing, direct response, and strategic programs within marketing", "You will also identify the right metrics for success and develop measurement techniques to make investment recommendations", "You will work with various internal stakeholders to support development of new programs that will improve customer engagement and business growth", "This is an opportunity to guide impactful decisions that will improve the experience of users globally", "Manage marketing analytics for products like Google Play or Google Chrome", "Establish metrics and measurement plans that explain the incremental impact of marketing campaigns", "Translate business questions into appropriate analytical projects that will inform strategic and tactical business decisions", "Conduct end-to-end analysis autonomously and communicate insights", "Drive analytic insights and recommendations in structured and unstructured data environments, working with data sets or developing decision making frameworks in situations with limited data", "Partner cross-functionally with a wide variety of teams and stakeholders including product marketing managers, analysts, and engineers to execute high impact initiatives", "Identify and communicate insights to senior management and cross-functional stakeholders for better decision making"], "Benefits": ["The US base salary range for this full-time position is $105,000-$154,000 + bonus + equity + benefits", "Our salary ranges are determined by role, level, and location"]}, "job_job_title": "Analytics manager", "job_posting_language": "en", "job_onet_soc": "11202100", "job_onet_job_zone": "4", "job_naics_code": "519130", "job_naics_name": "Internet Publishing and Broadcasting and Web Search Portals"}