{"job_id": "c52EI9GWXgoy2LJGAAAAAA==", "employer_name": "Dave & Buster\u2019s I, L.P.", "employer_logo": null, "employer_website": null, "employer_company_type": null, "job_publisher": "Workday", "job_employment_type": "FULLTIME", "job_title": "Brand Partnerships Manager", "job_apply_link": "https://daveandbusters.wd1.myworkdayjobs.com/Dave_and_Busters_Careers/job/CORP0000---SSC/Brand-Partnerships-Manager_R-1003467", "job_apply_is_direct": false, "job_apply_quality_score": 0.6399, "apply_options": [{"publisher": "Workday", "apply_link": "https://daveandbusters.wd1.myworkdayjobs.com/Dave_and_Busters_Careers/job/CORP0000---SSC/Brand-Partnerships-Manager_R-1003467", "is_direct": false}], "job_description": "Job Description: Brand Partnerships Manager Are you always the first to know about the hottest thing going on in culture, or what\u2019s going to be the next viral trend on social media? Are you well-versed in trending or up and coming brands and would want to work on collab projects? Want to join a dynamic team and make a big impact at a rapidly growing company? Ready to spend your workday thinking about how to deliver fun experiences to our 50MM+ annual guests? If so, we\u2019d love to talk to you! Dave & Buster\u2019s is seeking an experienced Manager of Brand Partnerships who can help take our marketing plans to the next level with seriously cool collaborations with strong brand, influencer, or celebrity partnerships. We are looking for someone who keeps an eye on the latest trends and can recommend partnership activations that build brand relevance, and a creative thinker that isn\u2019t afraid to push the bounds of entertainment to come up with big, bold ideas. \u00b7 Work with Sr. Director of Brand Marketing to build brand partnership strategy across all business streams \u2013 Eat, Drink, Play and Watch \u2013 to build brand relevance. \u00b7 Stay on top of trends in culture and proactively recommend partnership and/or activation ideas; be the brand steward and advocate of \u2018culture hijacking.\u2019 \u00b7 Maintain relationships with existing partners, and cultivate new relationships with emerging brands that would be a good partner fit for D&B. \u00b7 Negotiate and manage all aspects of partnership agreements to ensure flawless execution including trade and deal terms. \u00b7 Create business briefs for partnership activations that help creative, media, and digital teams to create strong go-to-market marketing campaigns. \u00b7 Serve as day-to-day project manager on partnership initiatives with the oversight of the Sr. Director, Brand Marketing. Effectively communicate and manage cross-functional teams and/or agency partners on project goals and deliverables. Responsible for on-time and on-budget delivery, contingency plans, and post-mortem learnings. \u00b7 Act as a brand steward, having a deep knowledge of the brand architecture, positioning, and guest targets, and applying this consistently across all marketing activities. We\u2019d love to hear from people who: \u00b7 Dream big \u2013 we'll be counting on you to keep a pulse on the latest trends and think creatively about how to take Dave & Buster\u2019s to the next level. \u00b7 Act like a team player \u2013 you'll be working with lots of internal and external partners to bring projects to life. \u00b7 Thrive in a fast-paced environment and are comfortable navigating ambiguity. \u00b7 Believe that work should be fun! You\u2019ll be joining a team that works hard but has fun along the way. Qualifications, Skills, & Abilities \u00b7 5+ years of experience in a partnerships role within a client organization or at a marketing agency \u00b7 Experience working in the restaurant / hospitality industry is preffered \u00b7 Strong organization, planning and presentation skills \u00b7 Highly creative with strong skills in organizing teams into action \u00b7 Ability to sell new ideas to leadership team \u00b7 Ability to balance multiple priorities and meet deadlines \u00b7 Strong analytical skills \u00b7 Strong foundation of marketing and marketing fundamentals \u00b7 Attention to detail \u2013 ability to flawlessly manage multiple programs. \u00b7 Ability to work in fast-paced environment; accountable and flexible \u00b7 Strong problem solving abilities; works well with ambiguity \u00b7 Demonstrates the ability to balance immediate and long-term priorities: seeks to meet critical objectives while considering the impact of those decisions and activities on the ability to achieve long-term goals WHAT\u2019S IN IT FOR ME?: Dave & Buster\u2019s / Main Event is an imaginative and dynamic company dedicated to creating innovative entertainment experiences that bring joy, laughter, and excitement to people of all ages. Our mission is to foster a culture of fun and creativity, and we take pride in our commitment to delivering memorable and unique entertainment solutions. Exclusive discounts on food and games at Dave & Buster\u2019s / Main Event Paid Time Off (PTO) that increases with tenure. 11 Company Holidays (Includes your Birthday) & 2 Floating Holidays per year. Medical, dental, vision and voluntary benefits Part Time/Full Time benefits available Sub Benefits: Livongo, SurgeryPlus, and Telehealth benefits 401k with company match following 6 months of employment. Buster\u2019s Legacy Fund (Support Team Members during difficult Times) Employee Assistance Program (EAP) Offerings. Work out facility on-site. Employee Power Card | Free Video Games. We work hard, play hard and have FUN! Salary Range: 80640 - 107520 We are an equal opportunity employer and participate in E-Verify in states where required. Dave & Buster\u2019s is different from everywhere else. No two days are ever the same. Time will fly by serving hundreds of people with flexible schedules you can accommodate school or other jobs. Plus your co-workers are awesome!", "job_is_remote": true, "job_posted_at_timestamp": 1709251200, "job_posted_at_datetime_utc": "2024-03-01T00:00:00.000Z", "job_city": null, "job_state": null, "job_country": "US", "job_latitude": 37.09024, "job_longitude": -95.71289, "job_benefits": ["retirement_savings", "dental_coverage", "health_insurance", "paid_time_off"], "job_google_link": "https://www.google.com/search?gl=us&hl=en&rciv=jb&q=director+of+brand+partnerships&start=20&ibp=htl;jobs#fpstate=tldetail&htivrt=jobs&htiq=director+of+brand+partnerships&htidocid=c52EI9GWXgoy2LJGAAAAAA%3D%3D", "job_offer_expiration_datetime_utc": null, "job_offer_expiration_timestamp": null, "job_required_experience": {"no_experience_required": false, "required_experience_in_months": 60, "experience_mentioned": true, "experience_preferred": false}, "job_required_skills": null, "job_required_education": {"postgraduate_degree": false, "professional_certification": false, "high_school": false, "associates_degree": false, "bachelors_degree": false, "degree_mentioned": false, "degree_preferred": false, "professional_certification_mentioned": false}, "job_experience_in_place_of_education": false, "job_min_salary": null, "job_max_salary": null, "job_salary_currency": null, "job_salary_period": null, "job_highlights": {"Qualifications": ["5+ years of experience in a partnerships role within a client organization or at a marketing agency", "Experience working in the restaurant / hospitality industry is preffered", "Strong organization, planning and presentation skills", "Highly creative with strong skills in organizing teams into action", "Ability to sell new ideas to leadership team", "Ability to balance multiple priorities and meet deadlines", "Strong analytical skills", "Strong foundation of marketing and marketing fundamentals", "Attention to detail \u2013 ability to flawlessly manage multiple programs", "Ability to work in fast-paced environment; accountable and flexible", "Strong problem solving abilities; works well with ambiguity", "Demonstrates the ability to balance immediate and long-term priorities: seeks to meet critical objectives while considering the impact of those decisions and activities on the ability to achieve long-term goals WHAT\u2019S IN IT FOR ME?: Dave & Buster\u2019s / Main Event is an imaginative and dynamic company dedicated to creating innovative entertainment experiences that bring joy, laughter, and excitement to people of all ages"], "Responsibilities": ["Director of Brand Marketing to build brand partnership strategy across all business streams \u2013 Eat, Drink, Play and Watch \u2013 to build brand relevance", "Stay on top of trends in culture and proactively recommend partnership and/or activation ideas; be the brand steward and advocate of \u2018culture hijacking.\u2019", "Maintain relationships with existing partners, and cultivate new relationships with emerging brands that would be a good partner fit for D&B", "Negotiate and manage all aspects of partnership agreements to ensure flawless execution including trade and deal terms", "Create business briefs for partnership activations that help creative, media, and digital teams to create strong go-to-market marketing campaigns", "Serve as day-to-day project manager on partnership initiatives with the oversight of the Sr", "Effectively communicate and manage cross-functional teams and/or agency partners on project goals and deliverables", "Responsible for on-time and on-budget delivery, contingency plans, and post-mortem learnings", "Act as a brand steward, having a deep knowledge of the brand architecture, positioning, and guest targets, and applying this consistently across all marketing activities", "Thrive in a fast-paced environment and are comfortable navigating ambiguity"], "Benefits": ["Exclusive discounts on food and games at Dave & Buster\u2019s / Main Event Paid Time Off (PTO) that increases with tenure", "11 Company Holidays (Includes your Birthday) & 2 Floating Holidays per year", "Medical, dental, vision and voluntary benefits Part Time/Full Time benefits available Sub Benefits: Livongo, SurgeryPlus, and Telehealth benefits 401k with company match following 6 months of employment", "Buster\u2019s Legacy Fund (Support Team Members during difficult Times) Employee Assistance Program (EAP) Offerings", "Work out facility on-site"]}, "job_job_title": "Partnerships manager", "job_posting_language": "en", "job_onet_soc": "11202100", "job_onet_job_zone": "4"}