{"job_id": "_MAzbk6kM8bsqd7xAAAAAA==", "employer_name": "CYPHER Learning", "employer_logo": "https://mma.prnewswire.com/media/1651912/Cypher_Learning_logo_2020_Logo.jpg?p=twitter", "employer_website": "http://www.cypherlearning.com", "employer_company_type": null, "job_publisher": "LinkedIn", "job_employment_type": "FULLTIME", "job_title": "Channel and Partnerships Marketing Manager", "job_apply_link": "https://www.linkedin.com/jobs/view/channel-and-partnerships-marketing-manager-at-cypher-learning-3848586631", "job_apply_is_direct": false, "job_apply_quality_score": 0.736, "apply_options": [{"publisher": "LinkedIn", "apply_link": "https://www.linkedin.com/jobs/view/channel-and-partnerships-marketing-manager-at-cypher-learning-3848586631", "is_direct": false}, {"publisher": "Indeed", "apply_link": "https://www.indeed.com/viewjob?jk=ce8ec5f481e0e0ab", "is_direct": true}, {"publisher": "Glassdoor", "apply_link": "https://www.glassdoor.com/job-listing/channel-and-partnerships-marketing-manager-cypher-learning-JV_KO0,42_KE43,58.htm?jl=1009152501040", "is_direct": true}, {"publisher": "Jobright AI", "apply_link": "https://jobright.ai/jobs/info/65eae7334c7c8532d7c82203", "is_direct": false}], "job_description": "Company Description:\n\nCYPHER Learning is leading the necessary disruption of learning platforms to unleash human potential with modern learning experiences. We exist to ignite lifelong learning passions through personalized, engaging, and limitless learning experiences for all, giving L&D pros and educators more time to teach and train, building human connection into everything we do, and delivering tailored learning experiences that are meaningful and measurable. We are a fast-growing company with a passion for education and technology.\n\nPosition Overview:\n\nWe are seeking a passionate and proven Channel and Partnerships Marketing Manager to support our global Channel Partners with effective marketing in driving awareness, engagement, and demand for our partner business and solutions. The ideal candidate is a strong collaborator who can work with key stakeholders internally and within the partners to drive the marketing strategy and achieve business results. This individual will have experience working with Channel Partners in the technology space and be familiar with strategies for marketing to, through and with partners. The individual will be an active participant in developing and driving the partnership and recommending marketing strategies and programs that deliver value to our shared customers.\n\nWhat You\u2019ll Do:\n\u2022 Develop, implement, and evaluate channel marketing plans, programs, and campaigns with the goals of generating leads, acquiring new clients, and expanding market share.\n\u2022 Drive all asset and collateral generation to highlight benefits of CYPHER Learning solutions and partner integrations, including presentations, solutions briefs, case studies, sales tools, and webinars. You make cool stuff that our channel partners want to use to drive their own growth!\n\u2022 Provide strategic direction in the CYPHER Learning product launch process as the channel partner stakeholder lead, including collaboration in launch plans and content.\n\u2022 Create campaign strategies promoting CYPHER Learning solutions and partner integrations with and through our channel partners.\n\u2022 Sales enablement \u2013 communicate the value proposition of CYPHER Learning solutions and integrations to the channel partner sales team and develop the sales tools that support the selling process.\n\u2022 Discover and drive opportunities to collaborate with partner marketing counterparts to deliver mutually successful programs.\n\u2022 Work cross-functionally to develop the strategy, focus, growth marketing strategies to drive revenue to, though, and with our Channel Partners.\n\u2022 Establish channel-specific Key Performance Indicators (KPIs), evaluate and report on the impact of campaigns, plans and programs in achieving their stated objectives.\n\u2022 Ensure that value-add content is up-to-date and relevant for audiences in the assigned channel and generate ideas for new content as industry dynamics and the needs of the channel change.\n\u2022 Partner with internal/eternal design team to assure that required presentations and print collateral materials are available for use in marketing campaigns and programs.\n\u2022 Write creative briefs and work with the content and design teams to develop ideas for, draft and create new sales support pieces for the channel to use with existing / prospective clients.\n\u2022 Facilitate with existing or prospective clients, as requested by channel leadership.\n\u2022 Own joint go-to-market marketing strategy with partners. This includes marketing to the partner and with the partner to end users.\n\u2022 Monitor, assess, and report on partner marketing program's performance metrics and provide strategic direction and guidance based on analysis of results.\n\nYour Skills & Experience:\n\u2022 Bachelor\u2019s degree in marketing, communications, business, or related area.\n\u2022 5+ years of global partner marketing experience.\n\u2022 Solid experience executing channel marketing strategies across diverse channels (resellers, VARs, alliance partners) with a proven track record of success in driving leads, revenue, and market share through partner programs.\n\u2022 Experience executing with B2B partners and their customer audiences.\n\u2022 Experience in both scaling large companies and fast growth startups is preferred.\n\u2022 Results-driven and customer-focused team player that understands what is required to gain preference and win in the marketplace.\n\u2022 Ability to define marketing objectives, execute integrated campaigns, and track and evaluate results.\n\u2022 Must have exceptional communication and writing skills.\n\u2022 Experienced in collaborating and communicating with senior executives.\n\u2022 Track-record of successful collaboration with customers, sales organizations, partners, and internal stakeholder organizations.\n\u2022 Excellent people and management skills to interact with colleagues and cross-functional team members (managing upwards and sideways).\n\u2022 Adept at looking around corners and anticipating needs of partners and stakeholders.\n\u2022 Understanding of partner ecosystems, including GSI and SI models\n\u2022 Ability to work independently, establish priorities, and demonstrate good judgment.\n\u2022 Strategic and creative thinker who can deliver results consistently.\n\u2022 Willing to travel as necessary.\n\nOur Values:\n\u2022 Curiosity: Continues learning to stay agile and innovative.\n\u2022 Connection: Embracing and celebrating our differences.\n\u2022 Empowerment: Rewarding positive people-centric behaviors and decisions.\n\u2022 Potential: Challenging status quo and pushing for what\u2019s possible.\n\u2022 Impact: Making a positive impact for our clients and communities around the world.\n\nIn addition to our core values, CYPHER LEARNING is committed to diversity and inclusion in the workplace and is proud to be an affirmative action and equal-opportunity employer. All qualified applicants will receive consideration for employment at CYPHER LEARNING without regard to race, creed, color, religion, national origin, sex, age, disability, sexual orientation, gender identity or expression, genetic predisposition or carrier status, veteran, marital, or citizenship status, or any other status protected by law.", "job_is_remote": true, "job_posted_at_timestamp": 1709860063, "job_posted_at_datetime_utc": "2024-03-08T01:07:43.000Z", "job_city": null, "job_state": null, "job_country": "US", "job_latitude": 37.09024, "job_longitude": -95.71289, "job_benefits": null, "job_google_link": "https://www.google.com/search?gl=us&hl=en&rciv=jb&q=manager+of+brand+partnerships&start=80&ibp=htl;jobs#fpstate=tldetail&htivrt=jobs&htiq=manager+of+brand+partnerships&htidocid=_MAzbk6kM8bsqd7xAAAAAA%3D%3D", "job_offer_expiration_datetime_utc": "2024-04-07T01:07:43.000Z", "job_offer_expiration_timestamp": 1712452063, "job_required_experience": {"no_experience_required": false, "required_experience_in_months": 60, "experience_mentioned": true, "experience_preferred": true}, "job_required_skills": ["Marketing Campaigns", "Print Collateral", "Writing", "Job Skills", "Marketing Strategy", "Case Studies", "Campaigns", "Presentations", "Communication", "Campaign Strategies"], "job_required_education": {"postgraduate_degree": false, "professional_certification": false, "high_school": false, "associates_degree": false, "bachelors_degree": true, "degree_mentioned": true, "degree_preferred": true, "professional_certification_mentioned": false}, "job_experience_in_place_of_education": false, "job_min_salary": null, "job_max_salary": null, "job_salary_currency": null, "job_salary_period": null, "job_highlights": {"Qualifications": ["Bachelor\u2019s degree in marketing, communications, business, or related area", "5+ years of global partner marketing experience", "Solid experience executing channel marketing strategies across diverse channels (resellers, VARs, alliance partners) with a proven track record of success in driving leads, revenue, and market share through partner programs", "Experience executing with B2B partners and their customer audiences", "Results-driven and customer-focused team player that understands what is required to gain preference and win in the marketplace", "Ability to define marketing objectives, execute integrated campaigns, and track and evaluate results", "Must have exceptional communication and writing skills", "Experienced in collaborating and communicating with senior executives", "Track-record of successful collaboration with customers, sales organizations, partners, and internal stakeholder organizations", "Excellent people and management skills to interact with colleagues and cross-functional team members (managing upwards and sideways)", "Adept at looking around corners and anticipating needs of partners and stakeholders", "Understanding of partner ecosystems, including GSI and SI models", "Ability to work independently, establish priorities, and demonstrate good judgment", "Strategic and creative thinker who can deliver results consistently", "Willing to travel as necessary", "Empowerment: Rewarding positive people-centric behaviors and decisions", "Potential: Challenging status quo and pushing for what\u2019s possible"], "Responsibilities": ["The ideal candidate is a strong collaborator who can work with key stakeholders internally and within the partners to drive the marketing strategy and achieve business results", "This individual will have experience working with Channel Partners in the technology space and be familiar with strategies for marketing to, through and with partners", "The individual will be an active participant in developing and driving the partnership and recommending marketing strategies and programs that deliver value to our shared customers", "Develop, implement, and evaluate channel marketing plans, programs, and campaigns with the goals of generating leads, acquiring new clients, and expanding market share", "Drive all asset and collateral generation to highlight benefits of CYPHER Learning solutions and partner integrations, including presentations, solutions briefs, case studies, sales tools, and webinars", "You make cool stuff that our channel partners want to use to drive their own growth!", "Provide strategic direction in the CYPHER Learning product launch process as the channel partner stakeholder lead, including collaboration in launch plans and content", "Create campaign strategies promoting CYPHER Learning solutions and partner integrations with and through our channel partners", "Sales enablement \u2013 communicate the value proposition of CYPHER Learning solutions and integrations to the channel partner sales team and develop the sales tools that support the selling process", "Discover and drive opportunities to collaborate with partner marketing counterparts to deliver mutually successful programs", "Work cross-functionally to develop the strategy, focus, growth marketing strategies to drive revenue to, though, and with our Channel Partners", "Establish channel-specific Key Performance Indicators (KPIs), evaluate and report on the impact of campaigns, plans and programs in achieving their stated objectives", "Ensure that value-add content is up-to-date and relevant for audiences in the assigned channel and generate ideas for new content as industry dynamics and the needs of the channel change", "Partner with internal/eternal design team to assure that required presentations and print collateral materials are available for use in marketing campaigns and programs", "Write creative briefs and work with the content and design teams to develop ideas for, draft and create new sales support pieces for the channel to use with existing / prospective clients", "Facilitate with existing or prospective clients, as requested by channel leadership", "Own joint go-to-market marketing strategy with partners", "This includes marketing to the partner and with the partner to end users", "Monitor, assess, and report on partner marketing program's performance metrics and provide strategic direction and guidance based on analysis of results"]}, "job_job_title": "Marketing manager", "job_posting_language": "en", "job_onet_soc": "11202100", "job_onet_job_zone": "4"}