{"job_id": "JoNrlx3WDvGl8rzDAAAAAA==", "employer_name": "CONDUENT", "employer_logo": "https://www.conduentassets.com/conduent-logo.png", "employer_website": "http://www.conduent.com", "employer_company_type": null, "job_publisher": "Conduent", "job_employment_type": "FULLTIME", "job_title": "Commercial Sales Executive", "job_apply_link": "https://careers.conduent.com/us/en/job/90161/Commercial-Sales-Executive", "job_apply_is_direct": false, "job_apply_quality_score": 0.9157, "apply_options": [{"publisher": "Conduent", "apply_link": "https://careers.conduent.com/us/en/job/90161/Commercial-Sales-Executive", "is_direct": false}, {"publisher": "LocalJobs.com", "apply_link": "https://www.localjobs.com/job/united-states-commercial-sales-executive", "is_direct": false}, {"publisher": "Conduent Jobs", "apply_link": "https://conduent.dejobs.org/virtual-usa/commercial-sales-executive/F5665F672BAB44089BA83B6C8622B451/job/?utm_campaign=USNLx.com&utm_medium=NLX&utm_source=USNLx.com-DE", "is_direct": false}, {"publisher": "Jobright AI", "apply_link": "https://jobright.ai/jobs/info/65dded6c6eff62fcc4023dc9", "is_direct": false}], "job_description": "About Conduent:\n\nThrough our dedicated associates, Conduent delivers mission-critical services and solutions on behalf of Fortune 100 companies and over 500 governments \u2013 creating exceptional outcomes for our clients and the millions of people who count on them. You have an opportunity to personally thrive, make a difference and be part of a culture where individuality is noticed and valued every day.\n\nJob Description:\n\nCommercial Sales Executive\n\nAre you a dynamic sales executive ready to take on a challenging and rewarding role?\n\nDo you excel at building trusted relationships with C-suite executives and delivering innovative solutions to Fortune 500 companies?\n\nAbout the Role:\n\nAs a Sales Executive at Conduent, you will play a crucial role in driving our growth by utilizing your consultative sales expertise to secure new contracts and foster existing client relationships. You will be at the forefront of our sales efforts, collaborating with internal partners to provide innovative solutions to our clients' business challenges. Here's your chance to be a part of a dynamic team, make a meaningful impact, and shape the future of Conduent's success.\n\nResponsibilities:\n\u2022 Initiating relationships and securing contracts with new customers that meet assigned sales quotas and targets.\n\u2022 Nurturing and expanding relationships with current clients through cross-selling new services and collaborating with Account Management to promote new services within existing accounts.\n\u2022 Managing the entire sales cycle, from initial customer engagement to closing deals.\n\u2022 Evaluating prospects against company criteria for ideal customers and sales opportunities.\n\u2022 Engaging with prospects about their business challenges and requirements, as well as presenting the range of options and cost benefits of each.\n\u2022 Effectively presenting to senior managers and decision-makers.\n\u2022 Crafting and delivering compelling proposals.\n\u2022 Collaborating with technical staff and product specialists as needed to address customer requirements.\n\u2022 Developing and maintaining territory plans outlining how sales targets will be consistently met.\n\u2022 Partnering with Account Management to create key account plans, identifying opportunities and strategic motivators.\n\u2022 Collaborating with solutions leaders to enhance service delivery focus and align with Conduent's offerings.\n\u2022 Recommending and initiating improvements to sales and marketing operations.\n\u2022 Ensuring accurate and timely use of a robust CRM to track pursuit activities and solution details.\n\u2022 Providing timely submission of progress reports, forecasts, quotations, and pipeline development efforts.\n\u2022 Supporting the development of marketing plans to appeal to a global customer base, aiding in sales and profit objectives.\n\u2022 Participating in both product and pipeline development strategy sessions.\n\nRequirements:\n\u2022 Demonstrated ability to consistently exceed sales targets, develop new business, and grow existing accounts.\n\u2022 Proven experience in BPO sales and a background in selling solutions to Fortune 500 companies.\n\u2022 Proficiency in building and nurturing trusted relationships with C-suite executives.\n\u2022 Possess an established network of contacts and relationships within the market.\n\u2022 Advanced knowledge of BPO Sales and relationship management processes.\n\u2022 10+ years of proven experience in large-scale, enterprise-wide sales and account management.\n\u2022 Staying informed about macroeconomic factors, media coverage, market trends, and changes to create successful customer engagements.\n\u2022 Ability to collaborate with delivery organizations to provide added value.\n\u2022 Skill in uncovering new opportunities within large accounts.\n\u2022 Strong oral and written communication skills, including the ability to effectively present information to top management and executives, both internally and externally.\n\u2022 Demonstrated self-motivation and a strong desire for success.\n\u2022 Bachelor's degree in a related field or equivalent work experience.\n\nFlexible Working\n\nAt Conduent, we want you to be yourself. We recognize that everyone is different and that how people want to work and deliver at their best is different for everyone too.\nIn this role, you can expect the following working conditions:\n\u2022 Remote work: Enjoy the convenience of working from home and maximize your time.\n\u2022 Flexible Working Hours: Flex the times you work during the day, allowing you to balance your home life and work.\n\nWorking For You\n\nPerks and rewards designed for you:\n\u2022 Health and Welfare Benefits: Our health and welfare benefits can be tailored to fit your needs and start on the first day of employment.\n\u2022 Retirement Savings: We support you as you invest in your future.\n\u2022 Employee Discounts: We offer you access to a vast selection of global, national, and local discounts on merchandise, services, travel, and more.\n\u2022 Career Growth Opportunities: We help you thrive, so together, we can grow. We provide opportunities to advance your career with a vast portfolio of businesses and a global footprint.\n\u2022 Training: Earn while you learn and continue to grow with access to award-winning learning platforms throughout your Conduent career.\n\u2022 Great Work Environment: We are proud of our award-winning culture and the recognition we\u2019ve received for our diversity efforts.\n\nJoin Us\n\nAt Conduent, we are one team, one mission. We understand that our success is directly related to the success of our associates. We strive to create a culture where you can:\n\u2022 Bring your authentic self to work\n\u2022 Grow and thrive, both personally and professionally\n\u2022 Make a difference with our clients, in our communities, and with the millions of people we support\n\nWhen you join Conduent, you are engaged in creating the future - both our company\u2019s and your own. With more than 60,000 associates across 24 countries, we will provide you the opportunity to grow with a team of people who will challenge and inspire you to be the best.\n\nPay Transparency Laws in some locations require disclosure of compensation and/or benefits-related information. For this position, actual salaries will vary and may be above or below the range based on various factors including but not limited to location, experience, and performance. In addition to base pay, this position, based on business need, may be eligible for a bonus or incentive. In addition, Conduent provides a variety of benefits to employees including health insurance coverage, voluntary dental and vision programs, life and disability insurance, a retirement savings plan, paid holidays, and paid time off (PTO) or vacation and/or sick time. The estimated base salary range for this role is $135,000 - $180,000.\nClosing:\n\nConduent is an Equal Opportunity Employer and considers applicants for all positions without regard to race, color, creed, religion, ancestry, national origin, age, gender identity, gender expression, sex/gender, marital status, sexual orientation, physical or mental disability, medical condition, use of a guide dog or service animal, military/veteran status, citizenship status, basis of genetic information, or any other group protected by law.\n\nPeople with disabilities who need a reasonable accommodation to apply for or compete for employment with Conduent may request such accommodation(s) by clicking on the following link, completing the accommodation request form, and submitting the request by using the \"Submit\" button at the bottom of the form. For those using Google Chrome or Mozilla Firefox please download the form first: click here to access or download the form. You may also click here to access Conduent\u2019s ADAAA Accommodation Policy.\n\nAt Conduent, we value the health and safety of our associates, their families and our community. Under our current protocols, we do not require vaccination against COVID for most of our US jobs, but may require you to provide your COVID vaccination status, where legally permissible.", "job_is_remote": false, "job_posted_at_timestamp": 1710201600, "job_posted_at_datetime_utc": "2024-03-12T00:00:00.000Z", "job_city": null, "job_state": null, "job_country": "US", "job_latitude": 37.09024, "job_longitude": -95.71289, "job_benefits": ["retirement_savings", "health_insurance", "paid_time_off", "dental_coverage"], "job_google_link": "https://www.google.com/search?gl=us&hl=en&rciv=jb&q=sales+director&start=50&ibp=htl;jobs#fpstate=tldetail&htivrt=jobs&htiq=sales+director&htidocid=JoNrlx3WDvGl8rzDAAAAAA%3D%3D", "job_offer_expiration_datetime_utc": null, "job_offer_expiration_timestamp": null, "job_required_experience": {"no_experience_required": false, "required_experience_in_months": 120, "experience_mentioned": true, "experience_preferred": false}, "job_required_skills": null, "job_required_education": {"postgraduate_degree": false, "professional_certification": false, "high_school": false, "associates_degree": false, "bachelors_degree": false, "degree_mentioned": true, "degree_preferred": true, "professional_certification_mentioned": false}, "job_experience_in_place_of_education": false, "job_min_salary": null, "job_max_salary": null, "job_salary_currency": null, "job_salary_period": null, "job_highlights": {"Qualifications": ["Demonstrated ability to consistently exceed sales targets, develop new business, and grow existing accounts", "Proven experience in BPO sales and a background in selling solutions to Fortune 500 companies", "Proficiency in building and nurturing trusted relationships with C-suite executives", "Possess an established network of contacts and relationships within the market", "Advanced knowledge of BPO Sales and relationship management processes", "10+ years of proven experience in large-scale, enterprise-wide sales and account management", "Staying informed about macroeconomic factors, media coverage, market trends, and changes to create successful customer engagements", "Ability to collaborate with delivery organizations to provide added value", "Skill in uncovering new opportunities within large accounts", "Strong oral and written communication skills, including the ability to effectively present information to top management and executives, both internally and externally", "Demonstrated self-motivation and a strong desire for success", "Bachelor's degree in a related field or equivalent work experience"], "Responsibilities": ["As a Sales Executive at Conduent, you will play a crucial role in driving our growth by utilizing your consultative sales expertise to secure new contracts and foster existing client relationships", "You will be at the forefront of our sales efforts, collaborating with internal partners to provide innovative solutions to our clients' business challenges", "Initiating relationships and securing contracts with new customers that meet assigned sales quotas and targets", "Nurturing and expanding relationships with current clients through cross-selling new services and collaborating with Account Management to promote new services within existing accounts", "Managing the entire sales cycle, from initial customer engagement to closing deals", "Evaluating prospects against company criteria for ideal customers and sales opportunities", "Engaging with prospects about their business challenges and requirements, as well as presenting the range of options and cost benefits of each", "Effectively presenting to senior managers and decision-makers", "Crafting and delivering compelling proposals", "Collaborating with technical staff and product specialists as needed to address customer requirements", "Developing and maintaining territory plans outlining how sales targets will be consistently met", "Partnering with Account Management to create key account plans, identifying opportunities and strategic motivators", "Collaborating with solutions leaders to enhance service delivery focus and align with Conduent's offerings", "Recommending and initiating improvements to sales and marketing operations", "Ensuring accurate and timely use of a robust CRM to track pursuit activities and solution details", "Providing timely submission of progress reports, forecasts, quotations, and pipeline development efforts", "Supporting the development of marketing plans to appeal to a global customer base, aiding in sales and profit objectives", "Participating in both product and pipeline development strategy sessions"], "Benefits": ["Flexible Working Hours: Flex the times you work during the day, allowing you to balance your home life and work", "Health and Welfare Benefits: Our health and welfare benefits can be tailored to fit your needs and start on the first day of employment", "Retirement Savings: We support you as you invest in your future", "Employee Discounts: We offer you access to a vast selection of global, national, and local discounts on merchandise, services, travel, and more", "Career Growth Opportunities: We help you thrive, so together, we can grow", "We provide opportunities to advance your career with a vast portfolio of businesses and a global footprint", "Training: Earn while you learn and continue to grow with access to award-winning learning platforms throughout your Conduent career", "Bring your authentic self to work", "Grow and thrive, both personally and professionally", "For this position, actual salaries will vary and may be above or below the range based on various factors including but not limited to location, experience, and performance", "In addition to base pay, this position, based on business need, may be eligible for a bonus or incentive", "In addition, Conduent provides a variety of benefits to employees including health insurance coverage, voluntary dental and vision programs, life and disability insurance, a retirement savings plan, paid holidays, and paid time off (PTO) or vacation and/or sick time", "The estimated base salary range for this role is $135,000 - $180,000"]}, "job_job_title": "Sales executive", "job_posting_language": "en", "job_onet_soc": "41401200", "job_onet_job_zone": "4", "job_occupational_categories": ["Sales"]}