{"job_id": "T79J3pwYUmQoDZaHAAAAAA==", "employer_name": "Angi", "employer_logo": "https://encrypted-tbn0.gstatic.com/images?q=tbn:ANd9GcQsn6p-N_Sxn928NIUwnDvNiChys3-SHDJpqHYl&s=0", "employer_website": "http://www.angi.com", "employer_company_type": "Information", "job_publisher": "LinkedIn", "job_employment_type": "FULLTIME", "job_title": "Manager, 3rd Party Marketing Partnerships", "job_apply_link": "https://www.linkedin.com/jobs/view/manager-3rd-party-marketing-partnerships-at-angi-3848975409", "job_apply_is_direct": false, "job_apply_quality_score": 0.639, "apply_options": [{"publisher": "LinkedIn", "apply_link": "https://www.linkedin.com/jobs/view/manager-3rd-party-marketing-partnerships-at-angi-3848975409", "is_direct": false}, {"publisher": "ZipRecruiter", "apply_link": "https://www.ziprecruiter.com/c/Angi/Job/Manager,-Partnerships-&-Strategy/-in-Indianapolis,IN?jid=af725a8d44114ce2", "is_direct": false}], "job_description": "Angi\u00ae is transforming the home services industry, creating an environment for homeowners, service professionals and employees to feel right at \u201chome.\u201d For most home maintenance needs, our platform makes it easier than ever to find a qualified service professional for indoor and outdoor jobs, home renovations (or anything in between!). We are on a mission to become the home for everything home by helping small businesses thrive and providing solutions to financing and booking home jobs with just a few clicks.\n\nOver the last 25 years we have opened our doors to a network of over 200K service professionals and helped over 150 million homeowners love where they live. We believe home is the most important place on earth and are embarking on a journey to redefine how people care for their homes. Angi is an amazing place to build your dream career, join us\u2014we cannot wait to welcome you home!\n\nAbout The Team\n\nThe 3rd Party Marketing Partnerships team at Angi is a key part of the Marketing organization, propelling growth through external channels. The team\u2019s main objective is to drive EBITDA growth for Angi while maintaining high quality partnerships. We do this through consistent day-to-day management of the channels, and implementing new strategies to improve how we work with external partners. Within Angi, we work closely with product, data, corporate strategy and marketplace stakeholder teams (representing the Homeowners and Service Providers who use Angi each day).\n\nWhat You\u2019ll Do\n\nThe Manager, 3rd Party Marketing Partnerships at Angi is responsible for relationships with lead generation partners. The role\u2019s main objective is to maintain active relationships with these external partners, ensuring performance in line with Angi\u2019s KPIs. This role has a high impact at Angi, as the team is small and this position manages a significant scope of partners. This role involves monitoring KPIs, managing external relationships, and contributing to cross-functional initiatives which impact Angi\u2019s business. In 2024 the team will contribute to major strategic initiatives across Angi, and the Manager role will own tasks within broader projects.\n\nThe typical day of a Manager will include data monitoring and reporting, meeting with external partners, and executing tasks within larger strategic projects.\n\u2022 Manage relationships with 3rd party affiliate and referral lead generation partners\n\u2022 Monitor demand quality of partnerships and identify opportunities to improve\n\u2022 Optimize and monitor additional KPIs and program performance\n\u2022 Work alongside partners and team to ensure positive business performance and adoption of new tools on the Angi platform\n\u2022 Hold partners accountable to meet quality metrics and standards\n\u2022 Anticipate change & risk in external partnerships\n\u2022 Work internally and externally to support Angi's goals and objectives\n\u2022 Develop an understanding of how partnerships function, including the end-to-end experience and monetization streams\n\u2022 Support initiatives to improve user experience, Angi's profitability, and how we work with 3rd party partners\n\u2022 Collaborate with internal stakeholders to execute tasks within a workstream, contributing to larger Angi strategic initiatives\n\u2022 Proactively communicate information upwards\n\nWho You Are\n\u2022 3 - 5 years of experience, with experience managing external partnerships or clients\n\u2022 Excellent communication skills (both verbal and written)\n\u2022 Experience with KPI monitoring and reporting\n\u2022 High organizational ability and attention to detail\n\u2022 Desire to roll up sleeves and own account management tasks, spanning daily operational tasks to participating in broad company-wide projects\n\u2022 Ability to own day-to-day routines of external partners without direct involvement of your manager\n\u2022 Experience working with 3rd party marketing partners or affiliates is a plus\n\nWe value diversity\n\nWe know that the best ideas come from teams where diverse points of view uncover new solutions to hard problems. We welcome and value individuals who bring diverse life experiences, educational backgrounds, cultures, and work experiences.\n\nCompensation & Benefits\n\u2022 The salary band for this position ranges from $80,000 - $112,000 commensurate with experience and performance. Compensation may vary based on factors such as cost of living.\n\u2022 This position will be eligible for a competitive year end performance bonus & equity package.\n\u2022 Full medical, dental, vision package to fit your needs\n\u2022 Flexible vacation policy; work hard and take time when you need it\n\u2022 Pet discount plans & retirement plan with company match (401K)\n\u2022 The rare opportunity to work with sharp, motivated teammates solving some of the most unique challenges and changing the world", "job_is_remote": false, "job_posted_at_timestamp": 1710191973, "job_posted_at_datetime_utc": "2024-03-11T21:19:33.000Z", "job_city": null, "job_state": null, "job_country": "US", "job_latitude": 37.09024, "job_longitude": -95.71289, "job_benefits": ["dental_coverage", "retirement_savings", "paid_time_off", "health_insurance"], "job_google_link": "https://www.google.com/search?gl=us&hl=en&rciv=jb&q=manager+of+brand+partnerships&start=70&ibp=htl;jobs#fpstate=tldetail&htivrt=jobs&htiq=manager+of+brand+partnerships&htidocid=T79J3pwYUmQoDZaHAAAAAA%3D%3D", "job_offer_expiration_datetime_utc": "2024-04-10T21:19:33.000Z", "job_offer_expiration_timestamp": 1712783973, "job_required_experience": {"no_experience_required": false, "required_experience_in_months": 36, "experience_mentioned": true, "experience_preferred": true}, "job_required_skills": null, "job_required_education": {"postgraduate_degree": false, "professional_certification": false, "high_school": false, "associates_degree": false, "bachelors_degree": true, "degree_mentioned": false, "degree_preferred": false, "professional_certification_mentioned": false}, "job_experience_in_place_of_education": false, "job_min_salary": null, "job_max_salary": null, "job_salary_currency": null, "job_salary_period": null, "job_highlights": {"Qualifications": ["3 - 5 years of experience, with experience managing external partnerships or clients", "Excellent communication skills (both verbal and written)", "Experience with KPI monitoring and reporting", "High organizational ability and attention to detail", "Desire to roll up sleeves and own account management tasks, spanning daily operational tasks to participating in broad company-wide projects"], "Responsibilities": ["The Manager, 3rd Party Marketing Partnerships at Angi is responsible for relationships with lead generation partners", "The role\u2019s main objective is to maintain active relationships with these external partners, ensuring performance in line with Angi\u2019s KPIs", "This role has a high impact at Angi, as the team is small and this position manages a significant scope of partners", "This role involves monitoring KPIs, managing external relationships, and contributing to cross-functional initiatives which impact Angi\u2019s business", "In 2024 the team will contribute to major strategic initiatives across Angi, and the Manager role will own tasks within broader projects", "The typical day of a Manager will include data monitoring and reporting, meeting with external partners, and executing tasks within larger strategic projects", "Manage relationships with 3rd party affiliate and referral lead generation partners", "Monitor demand quality of partnerships and identify opportunities to improve", "Optimize and monitor additional KPIs and program performance", "Work alongside partners and team to ensure positive business performance and adoption of new tools on the Angi platform", "Hold partners accountable to meet quality metrics and standards", "Anticipate change & risk in external partnerships", "Work internally and externally to support Angi's goals and objectives", "Develop an understanding of how partnerships function, including the end-to-end experience and monetization streams", "Support initiatives to improve user experience, Angi's profitability, and how we work with 3rd party partners", "Collaborate with internal stakeholders to execute tasks within a workstream, contributing to larger Angi strategic initiatives", "Proactively communicate information upwards"], "Benefits": ["The salary band for this position ranges from $80,000 - $112,000 commensurate with experience and performance", "Compensation may vary based on factors such as cost of living", "This position will be eligible for a competitive year end performance bonus & equity package", "Full medical, dental, vision package to fit your needs", "Flexible vacation policy; work hard and take time when you need it", "Pet discount plans & retirement plan with company match (401K)", "The rare opportunity to work with sharp, motivated teammates solving some of the most unique challenges and changing the world"]}, "job_job_title": "Manager", "job_posting_language": "en", "job_onet_soc": "11202100", "job_onet_job_zone": "4", "job_naics_code": "519130", "job_naics_name": "Internet Publishing and Broadcasting and Web Search Portals"}