{"job_id": "OW2r4zd7edVe9DqyAAAAAA==", "employer_name": "Everlight Solar", "employer_logo": null, "employer_website": null, "employer_company_type": null, "job_publisher": "ZipRecruiter", "job_employment_type": "FULLTIME", "job_title": "Data Analyst (REMOTE)", "job_apply_link": "https://www.ziprecruiter.com/c/Everlight-Solar/Job/Data-Analyst-(REMOTE)/-in-Oklahoma-City,OK?jid=3ba76d420144fc5f", "job_apply_is_direct": true, "job_apply_quality_score": 0.7257, "apply_options": [{"publisher": "ZipRecruiter", "apply_link": "https://www.ziprecruiter.com/c/Everlight-Solar/Job/Data-Analyst-(REMOTE)/-in-Oklahoma-City,OK?jid=3ba76d420144fc5f", "is_direct": true}, {"publisher": "Talentify", "apply_link": "https://www.talentify.io/job/data-analyst-remote-louisville-kentucky-everlight-solar-0000fb215327", "is_direct": false}], "job_description": "Everlight Solar is seeking a skilled Data Analyst who will design and maintain functional programs and applications, producing fully functional software applications according to requirements. As a Data Analyst, you play a key role in serving our clients and team members. This will be a full-time, work-from-home \"remote\" position.\n\nThis is a role for Apple power-users, must know iWork and be skilled with iOS and macOS.\n\nEverlight Solar is a rapidly growing company and the leader of solar energy in the Midwest. We offer a unique experience that fosters individual growth and rewards performance. Our culture at Everlight is extremely important to us. The work environment is fast-paced and dynamic. We value teamwork, quality, innovation, and customer success. Our ideal candidate is self-motivated, detail-oriented, has excellent problem-solving abilities, is passionate about delivering results on-time, exceeding expectations, and ensuring success for our teams.\n\nResponsibilities:\n\u2022 Work with large amounts of data to draw meaningful conclusions\n\u2022 Develop and implement data collection systems and other strategies that optimize statistical efficiency and data quality\n\u2022 Provide regular reporting and analysis to team\n\u2022 Develop and maintain dashboards and reports to track key metrics and performance indicators\n\u2022 Collaborate with cross-functional teams to identify areas for improvement and to develop solutions to enhance business operations\n\u2022 Provide training and support to team members on data analysis techniques and tools\n\nRequirements:\n\u2022 Minimum two years of experience with DOMO\n\u2022 MajorDOMO Certification Required\n\u2022 3+ years experience in data analysis, reporting, business intelligence or financial analysis and a Bachelor's Degree in Business, Statistics, Mathematics, Analytics, Computer Sciences or related field or equivalent experience\n\u2022 2 years experience in providing people analytics reporting to organizations\n\u2022 Demonstrated experience using SQL, and DOMO\n\u2022 Experience with sensitive and confidential people data in a global environment\n\u2022 Analyze, evaluate, improve, and document processes and workflows. Identify and take advantage of opportunities for process automation and simplification.\n\u2022 Proven ability to design and implement new processes and facilitate user adoption.\n\u2022 Strong understanding of Salesforce.com best practices and functionality\n\u2022 Strong data management abilities\n\u2022 A documented history of successfully driving projects to completion\n\u2022 A demonstrated ability to understand and articulate complex requirements\n\u2022 Excellent project management skills and a positive attitude\n\u2022 Must demonstrate exceptional verbal and written communication skills\n\u2022 Must demonstrate ability to communicate effectively at all levels of the organization\n\u2022 Must own a Mac computer and be fluent with the Apple ecosystem of software (iOS, macOS, iWork, etc.)\n\nBenefits:\n\u2022 Health Insurance\n\u2022 Dental Insurance\n\u2022 Vision Insurance\n\u2022 Life Insurance\n\u2022 PTO\n\u2022 Sick and Safe Time\n\u2022 Paid Holidays Off\n\nSalary: $65,000-$100,000/year\n\nEverlight Solar is proudly an Equal Opportunity Employer. We value diversity of all types and are excited to work with talented individuals from a wide range of backgrounds. Everlight is committed to inclusion and we invite people of any race, creed, color, national origin, ancestry, marital status, sexual orientation, gender identity or expression, disability, nationality or sex, age groups (18+), and levels of education to apply. Authorized to work in the US and background check required.", "job_is_remote": true, "job_posted_at_timestamp": 1710830859, "job_posted_at_datetime_utc": "2024-03-19T06:47:39.000Z", "job_city": "Oklahoma City", "job_state": "OK", "job_country": "US", "job_latitude": 35.46756, "job_longitude": -97.516426, "job_benefits": ["paid_time_off", "dental_coverage", "health_insurance"], "job_google_link": "https://www.google.com/search?gl=us&hl=en&rciv=jb&q=data+analyst&start=60&ibp=htl;jobs#fpstate=tldetail&htivrt=jobs&htiq=data+analyst&htidocid=OW2r4zd7edVe9DqyAAAAAA%3D%3D", "job_offer_expiration_datetime_utc": "2024-04-17T00:00:00.000Z", "job_offer_expiration_timestamp": 1713312000, "job_required_experience": {"no_experience_required": false, "required_experience_in_months": 24, "experience_mentioned": true, "experience_preferred": false}, "job_required_skills": null, "job_required_education": {"postgraduate_degree": false, "professional_certification": false, "high_school": false, "associates_degree": false, "bachelors_degree": false, "degree_mentioned": true, "degree_preferred": true, "professional_certification_mentioned": true}, "job_experience_in_place_of_education": false, "job_min_salary": 65000, "job_max_salary": 100000, "job_salary_currency": "USD", "job_salary_period": "YEAR", "job_highlights": {"Qualifications": ["Minimum two years of experience with DOMO", "MajorDOMO Certification Required", "3+ years experience in data analysis, reporting, business intelligence or financial analysis and a Bachelor's Degree in Business, Statistics, Mathematics, Analytics, Computer Sciences or related field or equivalent experience", "2 years experience in providing people analytics reporting to organizations", "Demonstrated experience using SQL, and DOMO", "Experience with sensitive and confidential people data in a global environment", "Proven ability to design and implement new processes and facilitate user adoption", "Strong understanding of Salesforce.com best practices and functionality", "Strong data management abilities", "A documented history of successfully driving projects to completion", "A demonstrated ability to understand and articulate complex requirements", "Excellent project management skills and a positive attitude", "Must demonstrate exceptional verbal and written communication skills", "Must demonstrate ability to communicate effectively at all levels of the organization", "Must own a Mac computer and be fluent with the Apple ecosystem of software (iOS, macOS, iWork, etc.)", "Authorized to work in the US and background check required"], "Responsibilities": ["As a Data Analyst, you play a key role in serving our clients and team members", "This will be a full-time, work-from-home \"remote\" position", "Work with large amounts of data to draw meaningful conclusions", "Develop and implement data collection systems and other strategies that optimize statistical efficiency and data quality", "Provide regular reporting and analysis to team", "Develop and maintain dashboards and reports to track key metrics and performance indicators", "Collaborate with cross-functional teams to identify areas for improvement and to develop solutions to enhance business operations", "Provide training and support to team members on data analysis techniques and tools", "Analyze, evaluate, improve, and document processes and workflows", "Identify and take advantage of opportunities for process automation and simplification"], "Benefits": ["Health Insurance", "Dental Insurance", "Vision Insurance", "Life Insurance", "PTO", "Sick and Safe Time", "Paid Holidays Off", "Salary: $65,000-$100,000/year"]}, "job_job_title": "Data analyst", "job_posting_language": "en", "job_onet_soc": "43911100", "job_onet_job_zone": "4", "job_occupational_categories": ["15-1199.08: Business Intelligence Analysts"]}