{"job_id": "ZW5rYhLiXVgTmQ9qAAAAAA==", "employer_name": "Walmart", "employer_logo": "https://animationvisarts.com/wp-content/uploads/2020/08/Walmart-logo-2008-Now.jpg", "employer_website": "https://www.walmart.com", "employer_company_type": "Retail", "job_publisher": "ZipRecruiter", "job_employment_type": "FULLTIME", "job_title": "Senior Manager, Marketing Planning and Strategy - Grocery", "job_apply_link": "https://www.ziprecruiter.com/c/Walmart/Job/Senior-Manager,-Marketing-Planning-and-Strategy-Grocery/-in-Anderson,MO?jid=007f5abf36e1aece", "job_apply_is_direct": false, "job_apply_quality_score": 0.6552, "apply_options": [{"publisher": "ZipRecruiter", "apply_link": "https://www.ziprecruiter.com/c/Walmart/Job/Senior-Manager,-Marketing-Planning-and-Strategy-Grocery/-in-Anderson,MO?jid=007f5abf36e1aece", "is_direct": false}], "job_description": "Position Summary...\n\nWhat you'll do...\n\nSenior Manager, Marketing Planning and Strategy - Grocery\n\nThe Senior Manager, Marketing Planning and Strategy - Grocery is one of the essential leaders in the marketing organization that will help create & support the vision for how Walmart brings quality groceries to customers to lives - through strategic thinking, creative actions & never been done before campaign opportunities- with a keen eye to driving the businesses that allow it to come to life.\n\nAbout Walmart Marketing\n\nNamed Ad Age's Marketer of the Year in 2022, you'll join an internationally recognized team of thinkers, creators, and problem solvers passionate about helping people save money and live better.\n\nWalmart Marketing is a dynamic, multidimensional organization dedicated to redefining how the world shops through impactful creative and fast-paced innovation - all grounded in customer insights and brand strategy. We live out our company values each day while striving to exceed customer expectations and drive growth for the company.\n\nWe orchestrate marketing campaigns and experiences that reach millions of daily shoppers. Our work spans the digital and physical spaces and combines the work of numerous internal teams and external advertising and media agencies. Our teams work together to show our customers how they can save money and live better. If you are motivated by complex challenges and want to build the future of commerce and consumer services, a Marketing role at Walmart could be what you've been looking for.\n\nOur Marketing team has flexibility- We're currently operating 3 days in the office per week.\n\nYou will make an impact by:\n\u2022 Strategy and Execution: Drives the strategy and execution of lower funnel food marketing plan. Responsible for understanding business needs and translating those into marketing strategies that help us achieve our goals within grocery\n\u2022 Partnership and Collaboration: Partner with merchandising/buyers, customer science & marketing leads to develop and execute actionable customer propositions that lead the market and drive business growth\n\u2022 End-to-end journey: Work collaboratively with site and product teams to ensure that marketing activities are landing on destinations that deliver on the work and create sticky experiences\n\u2022 Training and development: provides development opportunities for associates through training, mentoring, assigning duties and building a team-based work environment\n\u2022 Integrated Marketing Planning & Implementation: Partner to provide holistic customer messaging plans with peers, agencies, media and creative partners to integrate stories into content plans- bringing them to life across a full funnel marketing approach- ensuring continuity between content and customer experience\n\u2022 Measurement: Supports weekly analytics reviews (in collaboration with analytics partners) and actions on optimizations to improve campaign and business performance.\n\u2022 The above information has been designed to indicate the general nature and level of work performed in the role. It is not designed to contain or be interpreted as a comprehensive inventory of all duties, responsibilities and qualifications required of employees assigned to this job. The full Job Description can be made available as part of the hiring process.\n\nYou'll sweep us off our feet if:\n\u2022 You have a background that includes food, grocery and/or grocery delivery marketing\n\u2022 You are customer and data obsessed. You think it's fun to translate complex data and research into insights that speak to customers' lives.\n\u2022 You enjoy crafting incredible creative brief and content plans to power creative and media strategies that are inspiring and motivating for a customer.\n\u2022 Working cross-functionally and being part of a team makes you feel energized and fuels your best ideas.\n\u2022 You're organized, disciplined, and know how to guide a strategy all the way through to meaningful results for the customer and our business.\n\u2022 You have high standards and help encourage excellence across your peers and partners\n\u2022 You have a passion for the customer journey. You are constantly thinking about ways to improve their shopping experience online and off.\n\nMinimum qualifications:\n\u2022 7+ years of experience in Strategic development or in a strategic capacity\n\u2022 5+ years of experience leading cross functional teams and influencing Cross functional partners like Merchandising, Creative, Media, Insights\n\u2022 2+ years of experience in Retail Analytics, Digital Analytics, or eCommerce Analytics\n\u2022 Strong organizational skills, a strong sense of ownership and accountability, and the ability to lead projects, communicate effectively, and be a self-starter\n\u2022 Leading cross-functional projects, Marketing or related field, Supervisory experience\n\nHow you'll thrive at Walmart:\n\u2022 Performance-based incentive awards\n\u2022 401k with company match\n\u2022 Discounted employee stock purchase plan\n\u2022 Paid parental leave,\n\u2022 New surrogacy & adoption benefits\n\u2022 Unlimited Flex Time Off\n\u2022 Working alongside a diverse group of collaborative and innovative team members\n\u2022 Opportunity for growth and development across several areas of the Fortune 1 organization\n\u2022 And much more\n\nEqual Opportunity Employer\n\nWalmart, Inc. is an Equal Opportunity Employer - By Choice. We believe we are best equipped to help our associates, customers and the communities we serve live better when we really know them. That means understanding, respecting and valuing diversity- unique styles, experiences, identities, ideas and opinions - while being inclusive of all people.\n\nWho We Are\n\nJoin Walmart and your work could help over 275 million global customers live better every week. Yes, we are the Fortune #1 company. But you'll quickly find we're a company who wants you to feel comfortable bringing your whole self to work. A career at Walmart is where the world's most complex challenges meet a kinder way of life. Our mission spreads far beyond the walls of our stores. Join us and you'll discover why we are a world leader in diversity and inclusion, sustainability, and community involvement. From day one, you'll be empowered and equipped to do the best work of your life. careers.walmart.com\n\nMinimum Qualifications...\n\nOutlined below are the required minimum qualifications for this position. If none are listed, there are no minimum qualifications.\n\nBachelor's degree in Business, Marketing, Communications, or related field and 3 years' experience in marketing or related field OR 7 years'\nexperience in marketing or related field.\n\nPreferred Qualifications...\n\nOutlined below are the optional preferred qualifications for this position. If none are listed, there are no preferred qualifications.\n\nLeading cross-functional projects, Marketing or related field, Supervisory experience\n\nMasters: Business Administration\n\nPrimary Location...\n702 SW 8TH ST, BENTONVILLE, AR 72716, United States of America", "job_is_remote": false, "job_posted_at_timestamp": 1710151200, "job_posted_at_datetime_utc": "2024-03-11T10:00:00.000Z", "job_city": "Anderson", "job_state": "MO", "job_country": "US", "job_latitude": 36.650627, "job_longitude": -94.44355, "job_benefits": ["retirement_savings"], "job_google_link": "https://www.google.com/search?gl=us&hl=en&rciv=jb&q=senior+manager+of+brand+partnerships&start=40&ibp=htl;jobs#fpstate=tldetail&htivrt=jobs&htiq=senior+manager+of+brand+partnerships&htidocid=ZW5rYhLiXVgTmQ9qAAAAAA%3D%3D", "job_offer_expiration_datetime_utc": "2024-04-12T00:00:00.000Z", "job_offer_expiration_timestamp": 1712880000, "job_required_experience": {"no_experience_required": false, "required_experience_in_months": 84, "experience_mentioned": true, "experience_preferred": false}, "job_required_skills": null, "job_required_education": {"postgraduate_degree": false, "professional_certification": false, "high_school": false, "associates_degree": false, "bachelors_degree": false, "degree_mentioned": true, "degree_preferred": true, "professional_certification_mentioned": false}, "job_experience_in_place_of_education": false, "job_min_salary": null, "job_max_salary": null, "job_salary_currency": null, "job_salary_period": null, "job_highlights": {"Qualifications": ["You have a background that includes food, grocery and/or grocery delivery marketing", "You are customer and data obsessed", "You think it's fun to translate complex data and research into insights that speak to customers' lives", "You enjoy crafting incredible creative brief and content plans to power creative and media strategies that are inspiring and motivating for a customer", "7+ years of experience in Strategic development or in a strategic capacity", "5+ years of experience leading cross functional teams and influencing Cross functional partners like Merchandising, Creative, Media, Insights", "2+ years of experience in Retail Analytics, Digital Analytics, or eCommerce Analytics", "Strong organizational skills, a strong sense of ownership and accountability, and the ability to lead projects, communicate effectively, and be a self-starter", "Leading cross-functional projects, Marketing or related field, Supervisory experience", "Bachelor's degree in Business, Marketing, Communications, or related field and 3 years' experience in marketing or related field OR 7 years'", "Masters: Business Administration"], "Responsibilities": ["Strategy and Execution: Drives the strategy and execution of lower funnel food marketing plan", "Responsible for understanding business needs and translating those into marketing strategies that help us achieve our goals within grocery", "Partnership and Collaboration: Partner with merchandising/buyers, customer science & marketing leads to develop and execute actionable customer propositions that lead the market and drive business growth", "End-to-end journey: Work collaboratively with site and product teams to ensure that marketing activities are landing on destinations that deliver on the work and create sticky experiences", "Training and development: provides development opportunities for associates through training, mentoring, assigning duties and building a team-based work environment", "Integrated Marketing Planning & Implementation: Partner to provide holistic customer messaging plans with peers, agencies, media and creative partners to integrate stories into content plans- bringing them to life across a full funnel marketing approach- ensuring continuity between content and customer experience", "Measurement: Supports weekly analytics reviews (in collaboration with analytics partners) and actions on optimizations to improve campaign and business performance", "The above information has been designed to indicate the general nature and level of work performed in the role", "You're organized, disciplined, and know how to guide a strategy all the way through to meaningful results for the customer and our business"], "Benefits": ["Performance-based incentive awards", "401k with company match", "Discounted employee stock purchase plan", "Paid parental leave,", "New surrogacy & adoption benefits", "Unlimited Flex Time Off", "Working alongside a diverse group of collaborative and innovative team members", "Opportunity for growth and development across several areas of the Fortune 1 organization"]}, "job_job_title": "Senior manager", "job_posting_language": "en", "job_onet_soc": "11202100", "job_onet_job_zone": "4", "job_occupational_categories": ["11-2021.00: Marketing Managers"], "job_naics_code": "452990", "job_naics_name": "All Other General Merchandise Stores"}