{"job_id": "_nTcMwHuuqkYPpVzAAAAAA==", "employer_name": "Southern Glazer's Wine & Spirits", "employer_logo": "https://upload.wikimedia.org/wikipedia/en/thumb/d/dc/Southern_Glazer%27s_Wine_%26_Spirits_Logo.svg/1200px-Southern_Glazer%27s_Wine_%26_Spirits_Logo.svg.png", "employer_website": null, "employer_company_type": "Wholesale", "job_publisher": "Salary.com", "job_employment_type": "FULLTIME", "job_title": "Sales Consultant", "job_apply_link": "https://www.salary.com/job/southern-glazer-s-wine-spirits/sales-consultant/j202309141135297493039", "job_apply_is_direct": false, "job_apply_quality_score": 0.6405, "apply_options": [{"publisher": "Salary.com", "apply_link": "https://www.salary.com/job/southern-glazer-s-wine-spirits/sales-consultant/j202309141135297493039", "is_direct": false}, {"publisher": "Pierre - AmericanListed.com", "apply_link": "https://pierre.americanlisted.com/jobs/sales-consultant-sgws-sd_8945229650.html", "is_direct": false}], "job_description": "Overview:\nThe Sales Consultant represents Southern Glazer\u2019s in the market as a member of the Southern Glazer\u2019s family. This individual is passionate, innovative, and self-motivated with a business-oriented and customer-focused mindset. The Sales Consultant\u2019s primary responsibilities are to visit the customer, have the right consultative sales conversations, and increase sales revenue. Face-to-face consultative selling built on trusting relationships drives maximum value to our customer and supplier partners as well as to the SGWS organization.\n\nCompensation:\n\u2022 $55,000 - $60,000/yr. Incentives\n\u2022 Mileage Reimbursement\n\u2022 Great Benefits (Medical, Dental, Vision)\n\u2022 Paid Time Off\n\u2022 401K\n\nPrimary Responsibilities:\n\u2022 Build positive, credible, lasting customer relationships based on trust\n\u2022 Discover and identify customer business growth needs\n\u2022 Develop a customer business growth plan for each account and build a pipeline of selling opportunities to drive incremental sales above base business\n\u2022 Analyze data and insights to increase sales, grow customer business, and better achieve objectives\n\u2022 Regularly and consistently pre-plan account visits with an agenda, service purpose, and selling opportunities documented in CRM (Proof)\n\u2022 Prioritize sales activities to achieve objectives based on each customer business growth plan\n\u2022 Visit accounts regularly, capture visit notes, and build visit plans considering previous visit outcomes and document in CRM (Proof)\n\u2022 Maintain deep knowledge of SGWS products and correctly present and position them in each account\n\u2022 Propose selling solutions to each customer and win the sale using consultative selling skills\n\u2022 Achieve internal SGWS and supplier objectives as prioritized by management\n\u2022 Manage customer issue resolution, seek additional opportunities to support the customer\u2019s needs, and support business growth by providing customers with useful information and guidance\n\u2022 Adapt the selling approach based on each customer\u2019s buying styles and individual business needs\n\u2022 Be knowledgeable and experienced in all accounts staying current with what competitors are offering and how SGWS products are positioned relative to the competition\n\u2022 Document and maintain account- and customer-specific information in CRM (Proof)\n\u2022 Participate in sales meetings, on-site training, and supplier events as required\n\u2022 Perform other duties as assigned\n\nMinimum Qualifications:\n\u2022 21 years or older\n\u2022 Able to analyze and understand data and information\n\u2022 Able to leverage SGWS technology to perform duties and responsibilities\n\u2022 Able to build and structure customer presentations and product proposals\n\u2022 Proficient in using mobile devices (e.g., iPad\u00ae, smartphone) and online communication techniques (email, posting, texting, etc.) in a professional manner\n\u2022 Able to consistently achieve results, even under tough circumstances\n\u2022 Able to take responsibility for own actions and results; commits to providing a consistently high level of service to customers, suppliers, colleagues, and management\n\u2022 Able to communicate effectively through various methods and express self clearly and concisely while appropriately tailoring the message to the audience\n\u2022 Able to be nimble in ambiguity; be open to change; embrace innovative ideas\n\u2022 Team player; works collaboratively with others\n\u2022 Able to work in a fast-paced, results-driven environment\n\u2022 Must possess a reliable vehicle, a valid driver\u2019s license, and the ability to obtain and maintain auto liability insurance on their vehicle in compliance with SGWS company requirements.\n\u2022 High School Diploma or GED required\n\u2022 Able to travel as needed\n\nEEO Statement:\nSouthern Glazer's Wine and Spirits, an Affirmative Action/EEO employer, prohibits discrimination and harassment of any type and provides equal employment opportunities to all employees and applicants for employment without regard to race, color, religion, age, sex, national origin, disability status, genetics, protected veteran status, sexual orientation, gender identity or expression, or any other characteristic protected by federal, state or local laws. This policy applies to all terms and conditions of employment, including recruiting, hiring, placement, promotion, termination, layoff, recall, transfer, leaves of absence, compensation and training. Southern Glazer's Wine and Spirits provides competitive compensation based on estimated performance level consistent with the past relevant experience, knowledge, skills, abilities and education of employees. Unless otherwise expressly stated, any pay ranges posted here are estimates from outside of Southern Glazer's Wine and Spirits and do not reflect Southern Glazer's pay bands or ranges.", "job_is_remote": false, "job_posted_at_timestamp": 1709596800, "job_posted_at_datetime_utc": "2024-03-05T00:00:00.000Z", "job_city": "Pierre", "job_state": "SD", "job_country": "US", "job_latitude": 44.366787, "job_longitude": -100.35375, "job_benefits": ["health_insurance", "paid_time_off", "dental_coverage", "retirement_savings"], "job_google_link": "https://www.google.com/search?gl=us&hl=en&rciv=jb&q=sales+consultant&start=10&ibp=htl;jobs#fpstate=tldetail&htivrt=jobs&htiq=sales+consultant&htidocid=_nTcMwHuuqkYPpVzAAAAAA%3D%3D", "job_offer_expiration_datetime_utc": "2024-03-26T00:00:00.000Z", "job_offer_expiration_timestamp": 1711411200, "job_required_experience": {"no_experience_required": false, "required_experience_in_months": null, "experience_mentioned": true, "experience_preferred": false}, "job_required_skills": null, "job_required_education": {"postgraduate_degree": false, "professional_certification": false, "high_school": false, "associates_degree": false, "bachelors_degree": false, "degree_mentioned": false, "degree_preferred": false, "professional_certification_mentioned": false}, "job_experience_in_place_of_education": false, "job_min_salary": null, "job_max_salary": null, "job_salary_currency": null, "job_salary_period": null, "job_highlights": {"Qualifications": ["21 years or older", "Able to analyze and understand data and information", "Able to leverage SGWS technology to perform duties and responsibilities", "Able to build and structure customer presentations and product proposals", "Proficient in using mobile devices (e.g., iPad\u00ae, smartphone) and online communication techniques (email, posting, texting, etc.) in a professional manner", "Able to consistently achieve results, even under tough circumstances", "Able to take responsibility for own actions and results; commits to providing a consistently high level of service to customers, suppliers, colleagues, and management", "Able to communicate effectively through various methods and express self clearly and concisely while appropriately tailoring the message to the audience", "Able to be nimble in ambiguity; be open to change; embrace innovative ideas", "Team player; works collaboratively with others", "Able to work in a fast-paced, results-driven environment", "Must possess a reliable vehicle, a valid driver\u2019s license, and the ability to obtain and maintain auto liability insurance on their vehicle in compliance with SGWS company requirements", "High School Diploma or GED required", "Able to travel as needed"], "Responsibilities": ["The Sales Consultant\u2019s primary responsibilities are to visit the customer, have the right consultative sales conversations, and increase sales revenue", "Face-to-face consultative selling built on trusting relationships drives maximum value to our customer and supplier partners as well as to the SGWS organization", "Build positive, credible, lasting customer relationships based on trust", "Discover and identify customer business growth needs", "Develop a customer business growth plan for each account and build a pipeline of selling opportunities to drive incremental sales above base business", "Analyze data and insights to increase sales, grow customer business, and better achieve objectives", "Regularly and consistently pre-plan account visits with an agenda, service purpose, and selling opportunities documented in CRM (Proof)", "Prioritize sales activities to achieve objectives based on each customer business growth plan", "Visit accounts regularly, capture visit notes, and build visit plans considering previous visit outcomes and document in CRM (Proof)", "Maintain deep knowledge of SGWS products and correctly present and position them in each account", "Propose selling solutions to each customer and win the sale using consultative selling skills", "Achieve internal SGWS and supplier objectives as prioritized by management", "Manage customer issue resolution, seek additional opportunities to support the customer\u2019s needs, and support business growth by providing customers with useful information and guidance", "Adapt the selling approach based on each customer\u2019s buying styles and individual business needs", "Be knowledgeable and experienced in all accounts staying current with what competitors are offering and how SGWS products are positioned relative to the competition", "Document and maintain account- and customer-specific information in CRM (Proof)", "Participate in sales meetings, on-site training, and supplier events as required", "Perform other duties as assigned"], "Benefits": ["$55,000 - $60,000/yr", "Incentives", "Mileage Reimbursement", "Great Benefits (Medical, Dental, Vision)", "Paid Time Off", "401K"]}, "job_job_title": "Sales consultant", "job_posting_language": "en", "job_onet_soc": "41401100", "job_onet_job_zone": "4", "job_naics_code": "424410", "job_naics_name": "General Line Grocery Merchant Wholesalers"}