{"job_id": "zM3a8eDdHcjx4TDuAAAAAA==", "employer_name": "El Paso Chamber", "employer_logo": null, "employer_website": null, "employer_company_type": null, "job_publisher": "Jooble", "job_employment_type": "FULLTIME", "job_title": "Event Sponsorship Manager", "job_apply_link": "https://jooble.org/jdp/-8201368917249670553", "job_apply_is_direct": false, "job_apply_quality_score": 0.6436, "apply_options": [{"publisher": "Jooble", "apply_link": "https://jooble.org/jdp/-8201368917249670553", "is_direct": false}, {"publisher": "Jobrapido.com", "apply_link": "https://us.jobrapido.com/jobpreview/3200693324", "is_direct": false}], "job_description": "Job Title: Event Sponsorship Manager\n\nJob Description: Under the supervision of the Executive Director of Marketing & Programs,\n\nthe full-time Sponsorship Sales Executive is responsible for the development, implementation, and fulfillment of all sponsorship sales at the El Paso Chamber. This key role is responsible for establishing the strategies and philosophies that will drive the sales team and plans to achieve targeted revenue objectives, ensuring that decisions drive the long-term success of the El Paso Chamber.\n\nPay range: $42,000.00 - $50,000.00 annually plus commission.\n\nPrimary Responsibilities:\n\n\u00b7 Create sponsorship opportunities (event marketing packages) for special events/programs, and cultivate, procure and manage sponsors, partners, and display vendors.\n\n\u00b7 Cultivate and manage strong business relationships with current and potential sponsors.\n\n\u00b7 Meet and exceed projections, schedules, and timelines provided by the Director of Membership.\n\n\u00b7 Identify and prioritize sponsorship opportunities.\n\n\u00b7 Manage Sponsor, Partner, and Vendor relationships via quality communication, gifts, and other incentives.\n\n\u00b7 Contact prospective companies and individuals to initiate the sales effort. Follow up on leads generated by outside sources.\n\n\u00b7 Schedule meetings and prepare, customize, and present sponsorship sales proposals to potential sponsors.\n\n\u00b7 Negotiate and compile sales contracts and agreements.\n\n\u00b7 Deliver requested information to potential sponsors in a timely manner.\n\n\u00b7 Assist in the preparation and design of sponsorship sales brochures, pamphlets, advertisements, or other sales materials.\n\n\u00b7 Support and participate in business and industry related events to include networking opportunities.\n\n\u00b7 Participate in and attend industry workshops and seminars.\n\n\u00b7 Work extended and/or irregular hours including nights, weekends, as needed.\n\n\u00b7 Other duties as assigned.\n\nAdditional Responsibilities:\n\n\u00b7 Attend staff meetings, including other meetings as requested.\n\n\u00b7 Network with staff in related industries such as hospitality, events, and tourism.\n\n\u00b7 Attend community events.\n\n\u00b7 Positively promote all El Paso Chamber programs and events.\n\n\u00b7 Effective communication skills and development of good working relationships with staff, prospective, existing clients, and strategic partners.\n\n\u00b7 Achievement of objectives as set in the Sales Plan, within the established timelines.\n\n\u00b7 Increase community engagement and brand awareness.\n\nKnowledge, Skills, and Abilities Preferred:\n\n\u00b7 Customer service mindset.\n\n\u00b7 Creative and decisive.\n\n\u00b7 Effective communication and relationship-building skills.\n\n\u00b7 Independent worker with limited supervision needed.\n\n\u00b7 Strong time management, organizational, and project management skills.\n\n\u00b7 Able to multitask on a regular basis.\n\n\u00b7 Comfortable and successful working with diverse groups of people.\n\nEl Paso Chamber Core Values:\n\n\u00b7 A commitment to excellence\n\n\u00b7 Dedication to service to our members\n\n\u00b7 Respect for everyone in the community\n\n\u00b7 Understanding that as a non-profit, we are held in the public\u2019s trust.\n\nQualifications:\n\n\u00b7 Bachelor\u2019s Degree from an accredited four-year university or college\n\n\u00b7 Bilingual preferred\n\n\u00b7 Strong verbal presentation and written skills with the proven ability to establish and maintain effective working relationships.\n\n\u00b7 Able to accurately solve problems, exceptional proficiency in data management, and effective, careful use of resources.\n\n\u00b7 Proficiency in the use and application of the following software: Required: Microsoft Office Suite (Excel, Word, and Outlook). Preferred: QuickBooks, PowerPoint, and Adobe.\n\n\u00b7 Must be willing to undergo a background screening.\n\nBenefits:\n\n\u00b7 401(k)\n\n\u00b7 401(k) matching\n\n\u00b7 Health insurance\n\n\u00b7 Paid time", "job_is_remote": false, "job_posted_at_timestamp": 1709769600, "job_posted_at_datetime_utc": "2024-03-07T00:00:00.000Z", "job_city": null, "job_state": null, "job_country": "US", "job_latitude": 37.09024, "job_longitude": -95.71289, "job_benefits": ["retirement_savings", "paid_time_off", "health_insurance"], "job_google_link": "https://www.google.com/search?gl=us&hl=en&rciv=jb&q=sponsorship+sales+director&start=10&ibp=htl;jobs#fpstate=tldetail&htivrt=jobs&htiq=sponsorship+sales+director&htidocid=zM3a8eDdHcjx4TDuAAAAAA%3D%3D", "job_offer_expiration_datetime_utc": "2024-04-10T10:47:05.000Z", "job_offer_expiration_timestamp": 1712746025, "job_required_experience": {"no_experience_required": false, "required_experience_in_months": null, "experience_mentioned": false, "experience_preferred": false}, "job_required_skills": null, "job_required_education": {"postgraduate_degree": false, "professional_certification": false, "high_school": false, "associates_degree": false, "bachelors_degree": false, "degree_mentioned": true, "degree_preferred": false, "professional_certification_mentioned": false}, "job_experience_in_place_of_education": false, "job_min_salary": null, "job_max_salary": null, "job_salary_currency": null, "job_salary_period": null, "job_highlights": {"Qualifications": ["Bachelor\u2019s Degree from an accredited four-year university or college", "Strong verbal presentation and written skills with the proven ability to establish and maintain effective working relationships", "Able to accurately solve problems, exceptional proficiency in data management, and effective, careful use of resources", "Must be willing to undergo a background screening"], "Responsibilities": ["the full-time Sponsorship Sales Executive is responsible for the development, implementation, and fulfillment of all sponsorship sales at the El Paso Chamber", "This key role is responsible for establishing the strategies and philosophies that will drive the sales team and plans to achieve targeted revenue objectives, ensuring that decisions drive the long-term success of the El Paso Chamber", "Create sponsorship opportunities (event marketing packages) for special events/programs, and cultivate, procure and manage sponsors, partners, and display vendors", "Cultivate and manage strong business relationships with current and potential sponsors", "Meet and exceed projections, schedules, and timelines provided by the Director of Membership", "Identify and prioritize sponsorship opportunities", "Manage Sponsor, Partner, and Vendor relationships via quality communication, gifts, and other incentives", "Contact prospective companies and individuals to initiate the sales effort", "Follow up on leads generated by outside sources", "Schedule meetings and prepare, customize, and present sponsorship sales proposals to potential sponsors", "Negotiate and compile sales contracts and agreements", "Deliver requested information to potential sponsors in a timely manner", "Assist in the preparation and design of sponsorship sales brochures, pamphlets, advertisements, or other sales materials", "Support and participate in business and industry related events to include networking opportunities", "Participate in and attend industry workshops and seminars", "Work extended and/or irregular hours including nights, weekends, as needed", "Other duties as assigned", "Attend staff meetings, including other meetings as requested", "Network with staff in related industries such as hospitality, events, and tourism", "Attend community events", "Positively promote all El Paso Chamber programs and events", "Effective communication skills and development of good working relationships with staff, prospective, existing clients, and strategic partners", "Achievement of objectives as set in the Sales Plan, within the established timelines", "Increase community engagement and brand awareness"], "Benefits": ["Pay range: $42,000.00 - $50,000.00 annually plus commission", "401(k) matching", "Health insurance", "Paid time"]}, "job_job_title": "Manager", "job_posting_language": "en", "job_onet_soc": "11202100", "job_onet_job_zone": "4"}