{"job_id": "7x3is9ANNRwMr3aIAAAAAA==", "employer_name": "Citi", "employer_logo": "https://upload.wikimedia.org/wikipedia/commons/thumb/1/1b/Citi.svg/200px-Citi.svg.png", "employer_website": "http://www.citigroup.com", "employer_company_type": "Finance", "job_publisher": "Jobs And Careers At Citi", "job_employment_type": "FULLTIME", "job_title": "AI/ML Engineer - Lead Analyst", "job_apply_link": "https://jobs.citi.com/job/jersey-city/ai-ml-engineer-lead-analyst/287/62060536832", "job_apply_is_direct": false, "job_apply_quality_score": 0.9001, "apply_options": [{"publisher": "Jobs And Careers At Citi", "apply_link": "https://jobs.citi.com/job/jersey-city/ai-ml-engineer-lead-analyst/287/62060536832", "is_direct": false}, {"publisher": "ZipRecruiter", "apply_link": "https://www.ziprecruiter.com/c/Citigroup,-Inc./Job/AI-ML-Engineer-Lead-Analyst/-in-Jersey-City,NJ?jid=6dd47138975ab5cd", "is_direct": false}, {"publisher": "CFA Institute Career Center", "apply_link": "https://careers.cfainstitute.org/job/9260675/aiml-engineer-lead-analyst", "is_direct": false}, {"publisher": "Glassdoor", "apply_link": "https://www.glassdoor.com/job-listing/ai-ml-engineer-lead-analyst-citi-JV_IC1126819_KO0,27_KE28,32.htm?jl=1009155007380", "is_direct": false}, {"publisher": "LinkedIn", "apply_link": "https://www.linkedin.com/jobs/view/ai-ml-engineer-lead-analyst-at-citi-3844559633", "is_direct": false}, {"publisher": "Dice", "apply_link": "https://www.dice.com/job-detail/e4a04223-0a83-4324-be70-bfe62a2d36cb", "is_direct": false}, {"publisher": "EFinancialCareers", "apply_link": "https://www.efinancialcareers.com/jobs-USA-NJ-Jersey_City-AIML_Engineer_-_Lead_Analyst.id20829869", "is_direct": true}, {"publisher": "JobServe", "apply_link": "https://www.jobserve.com/us/en/extjob/AI-ML-ENGINEER-LEAD-ANALYST-in-Jersey-City-New-Jersey-USA-91CE943A4AF456B2B2/", "is_direct": false}], "job_description": "Job Purpose:\n\nThe Digital Solutions and Innovation (DSI) function works with members of Internal Audit (IA) to identify automation opportunities and develop solutions and capabilities to support the development of audit analytics. A key aspect of DSI\u2019s strategy is to develop and deploy augmented intelligence (AI) and machine learning (ML) capabilities that are integrated with applications used by IA teams. The overarching objectives of these capabilities is to provide \u201cin the moment\u201d guidance to auditors, glean broader and deeper insights, enable efficiencies, and promote better quality and consistency.\n\nRole Overview:\n\nThe AI/ML Engineer - Lead Analyst is a critical role with the objective of exploring, developing, testing, deploying, enhancing, and maintaining machine learning and artificial intelligence capabilities integrated with Internal Audit\u2019s management systems.\n\nA broad understanding of AI/ML concepts and techniques, agile methodologies, cloud computing, intelligent chatbots, and related aspects is essential for the role. Additionally, a key aspect of this role involves the design and refinement of prompts to effectively communicate with generative AI models and to guide them, optimizing their output for a variety of technical applications and producing high-quality and contextually relevant content.\n\nThe role will entail collaborating with DSI, audit teams, external third parties and technology teams on ML use case ideation and prioritization, developing plans and timelines for implementation, thorough testing, deployment in a systemic way, maintenance to keep the capabilities up to date and relevant, and support in the onboarding of new technology for DSI.\n\nThe role will also involve collaborating with DSI team members and audit teams on new use case ideation, exploration, and eventual implementation.\n\nAnother success factor for the role will be documentation of model performance and other metrics and communication/presentation of results to pertinent audiences, including senior leadership. Along with a strong technical foundation, a creative, imaginative, forward-looking attitude and mindset is needed to continue to exert a positive impact on DSI and Internal Audit. Furthermore, a total quality assurance orientation is indispensable in all activities and outputs.\n\nKey Responsibilities:\n\u2022 Design, test, deploy and maintain machine learning use cases leveraging IBM Watson SaaS environment and toolset, and integrate with the audit management systems\n\u2022 Enhance existing AI/ML capabilities through ideation, exploration, testing, prioritization, and implementation\n\u2022 Design, test, and refine prompts to elicit the desired outputs from generative AI models, ensuring clarity, accuracy, effectiveness, and contextual relevance.\n\u2022 Perform analytics on AI/ML capabilities usage to understand trends, patterns, and pain points and implement a sustainable feedback loop to ensure positive, continually improving user experiences.\n\u2022 Explain the analysis of results in a methodical, analytical, visually-appealing manner\n\u2022 Collaborate with Innovation, technology, vendor, and information security teams on updates, enhancements, releases, and other procedural requirements\n\u2022 Assess current capabilities and chart a path for continuous improvement of the AI/ML capabilities value and impact\n\u2022 Prepare, manage, and maintain model risk management (MRM) documentation on model performance and accuracy\n\u2022 Engage with MRM team on adhering to and fulfilling requirements for MRM process\n\u2022 Engage with relevant stakeholders on use case ideation, planning, development, and deployment\n\u2022 Apply strong project management skills to develop project plans, timelines, milestones, and demonstrate progress toward objectives\n\u2022 Utilize excellent communication skills to ideate, educate, and present internally, often at senior levels (across functions); expected to communicate with external parties\n\u2022 Help shape the direction of machine learning and artificial intelligence capabilities in DSI\n\u2022 Apply a strong understanding of business processes, risks and controls to identify opportunities to enhance audit efficiencies and effectiveness through the development and delivery of automated processes\n\u2022 Drive tool innovations based on stakeholder needs, including adoption of new technologies and techniques\n\nQualifications:\n\u2022 5+ years\u2019 experience in AI, machine learning, and model development and deployment\n\u2022 Extensive experience in machine learning use case design, testing and deployment in IBM SaaS/Watson environment\n\u2022 Firm understanding of IBM cloud environment and its services\n\u2022 Demonstrable experience with IBM OpenPages platform, coupled with implementation and integration of machine learning algorithms using Watson capabilities\n\u2022 Demonstrable experience in working with Generative AI models, with a deep understanding of their capabilities, prompting strategies, model performance, and inherent limitations.\n\u2022 Extensive experience testing and using APIs\n\u2022 Strong statistical foundation, with in-depth knowledge of supervised, unsupervised, and semi-supervised machine learning models, with a particular focus on NLP/NLU\n\u2022 Solid understanding of data structures and data models\n\u2022 Understanding of conversational AI concepts, including intents, entities, dialogs trees, actions, journeys, and experiences\n\u2022 Experience in application development and UI and UX considerations\n\u2022 Experience in analytics, reporting, and visualization for the analysis and presentation of results. Cognos analytics experience is a plus\n\u2022 Possess an innovative, forward-looking, and imaginative mindset to continually reach for new horizons in audit innovation\n\u2022 Demonstrable experience working with stakeholders and exceeding their expectations\n\u2022 Take responsibility and accountability for planning, execution, and delivery\n\u2022 Positive attitude and a change-driven and change-oriented outlook\n\u2022 Adept at developing new ideas and improving current processes\n\u2022 Consider broad implications of decisions to different functions and units\n\u2022 Ability to thrive in a fast-paced, results-oriented environment\n\u2022 Excellent communication and interpersonal skills, with ability to develop strong working relationships and foster team collaboration\n\u2022 Possess excellent writing skills to deliver clear and concise messages, able to articulate complex concepts\n\u2022 Strong Presentation skills \u2013 comfortable with public speaking across various forums and be able to effectively and logically communicate when ideas are being challenged in an open forum\n\u2022 Familiarity with Financial Services industry and/or auditing a plus\n\nKnowledge and Skills:\n\u2022 Analytics, AI, machine learning, natural language processing (NLP), natural language understanding (NLU), large language models (LLMs)\n\u2022 Generative AI prompt engineering and tuning\n\u2022 Design of AI/ML model performance metrics and optimization\n\u2022 SaaS environments, cloud computing\n\u2022 IBM Watson, Watsonx.ai, Watson Assistant, OpenPages, Cognos\n\u2022 Agile and waterfall project management methodologies; JIRA a plus\n\u2022 Intermediate to Advanced level Python coding\n\u2022 Advanced SQL\n\u2022 MicroStrategy, Power BI, Tableau, or other visualization software\n\u2022 Intents, entities, dialogs, actions, and related chat bot concepts are a plus\n\nEducation:\n\u2022 Bachelor\u2019s degree in Data Science, Computer Science, MIS, or related discipline.\n\u2022 CISA, PMP, Agile/Scrum, Cloud Computing, or related certifications are a plus.\n\u2022 Master\u2019s degree is a plus.\n\n-------------------------------------------------\n\nJob Family Group:\nDecision Management\n\n-------------------------------------------------\n\nJob Family:\nSpecialized Analytics (Data Science/Computational Statistics)\n\n------------------------------------------------------\n\nTime Type:\nFull time\n\n------------------------------------------------------\n\nPrimary Location:\nJersey City New Jersey United States\n\n------------------------------------------------------\n\nPrimary Location Salary Range:\n$157,040.00 - $235,560.00\n\n------------------------------------------------------\n\nCiti is an equal opportunity and affirmative action employer.\n\nQualified applicants will receive consideration without regard to their race, color, religion, sex, sexual orientation, gender identity, national origin, disability, or status as a protected veteran.\n\nCitigroup Inc. and its subsidiaries (\"Citi\u201d) invite all qualified interested applicants to apply for career opportunities. If you are a person with a disability and need a reasonable accommodation to use our search tools and/or apply for a career opportunity review Accessibility at Citi.\n\nView the \"EEO is the Law\" poster. View the EEO is the Law Supplement.\n\nView the EEO Policy Statement.\n\nView the Pay Transparency Posting", "job_is_remote": false, "job_posted_at_timestamp": 1709251200, "job_posted_at_datetime_utc": "2024-03-01T00:00:00.000Z", "job_city": "Jersey City", "job_state": "NJ", "job_country": "US", "job_latitude": 40.717754, "job_longitude": -74.043144, "job_benefits": null, "job_google_link": "https://www.google.com/search?gl=us&hl=en&rciv=jb&q=ai+engineer&start=70&ibp=htl;jobs#fpstate=tldetail&htivrt=jobs&htiq=ai+engineer&htidocid=7x3is9ANNRwMr3aIAAAAAA%3D%3D", "job_offer_expiration_datetime_utc": null, "job_offer_expiration_timestamp": null, "job_required_experience": {"no_experience_required": false, "required_experience_in_months": 60, "experience_mentioned": true, "experience_preferred": true}, "job_required_skills": null, "job_required_education": {"postgraduate_degree": false, "professional_certification": false, "high_school": false, "associates_degree": false, "bachelors_degree": false, "degree_mentioned": true, "degree_preferred": true, "professional_certification_mentioned": true}, "job_experience_in_place_of_education": false, "job_min_salary": null, "job_max_salary": null, "job_salary_currency": null, "job_salary_period": null, "job_highlights": {"Qualifications": ["Along with a strong technical foundation, a creative, imaginative, forward-looking attitude and mindset is needed to continue to exert a positive impact on DSI and Internal Audit", "5+ years\u2019 experience in AI, machine learning, and model development and deployment", "Extensive experience in machine learning use case design, testing and deployment in IBM SaaS/Watson environment", "Firm understanding of IBM cloud environment and its services", "Demonstrable experience with IBM OpenPages platform, coupled with implementation and integration of machine learning algorithms using Watson capabilities", "Demonstrable experience in working with Generative AI models, with a deep understanding of their capabilities, prompting strategies, model performance, and inherent limitations", "Strong statistical foundation, with in-depth knowledge of supervised, unsupervised, and semi-supervised machine learning models, with a particular focus on NLP/NLU", "Solid understanding of data structures and data models", "Understanding of conversational AI concepts, including intents, entities, dialogs trees, actions, journeys, and experiences", "Experience in application development and UI and UX considerations", "Experience in analytics, reporting, and visualization for the analysis and presentation of results", "Possess an innovative, forward-looking, and imaginative mindset to continually reach for new horizons in audit innovation", "Demonstrable experience working with stakeholders and exceeding their expectations", "Take responsibility and accountability for planning, execution, and delivery", "Positive attitude and a change-driven and change-oriented outlook", "Adept at developing new ideas and improving current processes", "Consider broad implications of decisions to different functions and units", "Ability to thrive in a fast-paced, results-oriented environment", "Excellent communication and interpersonal skills, with ability to develop strong working relationships and foster team collaboration", "Possess excellent writing skills to deliver clear and concise messages, able to articulate complex concepts", "Strong Presentation skills \u2013 comfortable with public speaking across various forums and be able to effectively and logically communicate when ideas are being challenged in an open forum", "Analytics, AI, machine learning, natural language processing (NLP), natural language understanding (NLU), large language models (LLMs)", "Generative AI prompt engineering and tuning", "Design of AI/ML model performance metrics and optimization", "SaaS environments, cloud computing", "IBM Watson, Watsonx.ai, Watson Assistant, OpenPages, Cognos", "Intermediate to Advanced level Python coding", "Advanced SQL", "MicroStrategy, Power BI, Tableau, or other visualization software", "Bachelor\u2019s degree in Data Science, Computer Science, MIS, or related discipline"], "Responsibilities": ["A key aspect of DSI\u2019s strategy is to develop and deploy augmented intelligence (AI) and machine learning (ML) capabilities that are integrated with applications used by IA teams", "The overarching objectives of these capabilities is to provide \u201cin the moment\u201d guidance to auditors, glean broader and deeper insights, enable efficiencies, and promote better quality and consistency", "The AI/ML Engineer - Lead Analyst is a critical role with the objective of exploring, developing, testing, deploying, enhancing, and maintaining machine learning and artificial intelligence capabilities integrated with Internal Audit\u2019s management systems", "A broad understanding of AI/ML concepts and techniques, agile methodologies, cloud computing, intelligent chatbots, and related aspects is essential for the role", "Additionally, a key aspect of this role involves the design and refinement of prompts to effectively communicate with generative AI models and to guide them, optimizing their output for a variety of technical applications and producing high-quality and contextually relevant content", "The role will entail collaborating with DSI, audit teams, external third parties and technology teams on ML use case ideation and prioritization, developing plans and timelines for implementation, thorough testing, deployment in a systemic way, maintenance to keep the capabilities up to date and relevant, and support in the onboarding of new technology for DSI", "The role will also involve collaborating with DSI team members and audit teams on new use case ideation, exploration, and eventual implementation", "Another success factor for the role will be documentation of model performance and other metrics and communication/presentation of results to pertinent audiences, including senior leadership", "Design, test, deploy and maintain machine learning use cases leveraging IBM Watson SaaS environment and toolset, and integrate with the audit management systems", "Enhance existing AI/ML capabilities through ideation, exploration, testing, prioritization, and implementation", "Design, test, and refine prompts to elicit the desired outputs from generative AI models, ensuring clarity, accuracy, effectiveness, and contextual relevance", "Perform analytics on AI/ML capabilities usage to understand trends, patterns, and pain points and implement a sustainable feedback loop to ensure positive, continually improving user experiences", "Explain the analysis of results in a methodical, analytical, visually-appealing manner", "Collaborate with Innovation, technology, vendor, and information security teams on updates, enhancements, releases, and other procedural requirements", "Assess current capabilities and chart a path for continuous improvement of the AI/ML capabilities value and impact", "Prepare, manage, and maintain model risk management (MRM) documentation on model performance and accuracy", "Engage with MRM team on adhering to and fulfilling requirements for MRM process", "Engage with relevant stakeholders on use case ideation, planning, development, and deployment", "Apply strong project management skills to develop project plans, timelines, milestones, and demonstrate progress toward objectives", "Utilize excellent communication skills to ideate, educate, and present internally, often at senior levels (across functions); expected to communicate with external parties", "Help shape the direction of machine learning and artificial intelligence capabilities in DSI", "Apply a strong understanding of business processes, risks and controls to identify opportunities to enhance audit efficiencies and effectiveness through the development and delivery of automated processes", "Drive tool innovations based on stakeholder needs, including adoption of new technologies and techniques"], "Benefits": ["$157,040.00 - $235,560.00"]}, "job_job_title": "Engineer", "job_posting_language": "en", "job_onet_soc": "15111100", "job_onet_job_zone": "5", "job_naics_code": "522110", "job_naics_name": "Commercial Banking"}