{"job_id": "FzQC6YroGwfRrXMDAAAAAA==", "employer_name": "APEX Career Services", "employer_logo": "https://www.findmyprofession.com/wp-content/uploads/2018/12/APEX-Career-Services-800474.png", "employer_website": "https://apexcareerservices.com", "employer_company_type": "Staffing", "job_publisher": "Smart Recruiters Jobs", "job_employment_type": "FULLTIME", "job_title": "Travel Sales Consultant (TSC)", "job_apply_link": "https://jobs.smartrecruiters.com/APEXCareerServices/743999650756894-travel-sales-consultant-tsc-", "job_apply_is_direct": false, "job_apply_quality_score": 0.7481, "apply_options": [{"publisher": "Smart Recruiters Jobs", "apply_link": "https://jobs.smartrecruiters.com/APEXCareerServices/743999650756894-travel-sales-consultant-tsc-", "is_direct": false}], "job_description": "Company Description\n\nAPEX Career Services offers job seekers a full suite of services to assist in their job search and career exploration needs. In addition, we offer staffing services to reputable companies seeking to fill currently open positions. Our clients offer great pay and excellent benefits. All positions posted are full-time positions unless otherwise noted.\n\nJob Description\n\nJob Title: Travel Sales Consultant (TSC)\n\nPay: 100% Commission\n\nEmployment Type: 1099 Independent Contractor\n\nLocation: Virtual/ work from home\n\nHours: Set your own hours\n\nAbout Us\n\nElite Travel Team was founded by a husband and wife team who are devoted and seasoned travelers, with an undeniable and infectious passion for global travel. The company was created out of their shared passion for traveling, their favorite pastime. In spite of working long hours, they always make time to travel the world to enjoy amazing vacation experiences. They have traveled to all continents except Antarctica, and have plans to travel to Antarctica soon! Travel is truly their passion, and they continue to share many amazing experiences throughout the years, taking as many as 6 vacations annually, while running a busy travel business and other companies. You get the best when you book with Elite Travel Team, since the owners travel a lot and use their travel experiences and industry expertise to plan your vacations and advise you.\n\nThey are the consummate entrepreneurs who have built other successful businesses. Elite Travel Team was born out of their mutual passion and desire to help everyone they come in contact with see as much of the world as they have. They understand that people want to vacation more but don\u2019t always know where to start. Their goal is to help alleviate all the stress and worry that can sometimes accompany the vacation travel planning process. They use their knack for travel to make travel easier for their clients. They believe that everyone should experience the world, and are truly committed to ensuring that customer service remains a top priority. Elite Travel Team is built on always delivering top notch client service, as customer loyalty is important to them. They are a truly remarkable team and you will always have access to them.\n\nResponsibilities\n\nCurrently we have an outstanding opportunity for a confident, flexible individual to support our Travel Consultants. We are seeking motivated sales professionals to identify and send us leads for prospective travel clients and vacationers. Successful candidate must be confident and capable of promoting our travel agency services to as many people as possible. This is a superb opportunity to work for yourself and set your own hours. You get paid after travel has been completed when your referrals book with us, It\u2019s that simple.\n\nJob Summary\n\nElite Travel Team will consider remote candidates living in all 50 U.S. States. The Travel Sales Consultant (TSC) will identify potential customers for travel services through cold-calling and other means. As you are not a travel agent, we are relying on you to refer potential leads to us and we will handle all travel bookings using our global network of travel suppliers. As an independent contractor you are expected to market our full suite of travel services to your own pipeline of travelers and forward leads to us. This role will meet monthly and weekly sales goals set by personal and company objectives. The TSC will utilize their own phones, email, social media and other tools to identify leads. This role offers a fair commission structure. Commission can be generated based on meeting benchmarks and sales goals such as conversion rates, travel protection and other upgrades.\n\nObjectives of this Role\n\n\u00b7 Source and find potential clients\n\n\u00b7 Identify leads for prospective vacation and travel bookings\n\n\u00b7 Qualify leads to make sure they are serious about booking\n\n\u00b7 Secure upsells on deals closed\n\n\u00b7 Qualify leads for future sales\n\n\u00b7 Acquire new leads by being proactive in sourcing leads\n\n\u00b7 Provide excellent service at all stages of the sales and service cycles\n\nQualifications\n\nQualifications\n\n\u00b7 Ability to source and find potential\n\n\u00b7 Experience meeting and exceeding sales goals\n\n\u00b7 Experience working independently, in a call center or in customer service\n\n\u00b7 Experience working in a commission-base role preferred\n\n\u00b7 Travel/Travel Sales experience preferred\n\n\u00b7 General knowledge of world geography preferred\n\n\u00b7 High School diploma or equivalent required\n\nSkills That Will Make You Successful\n\n\u00b7 Ability to connect with people\n\n\u00b7 Strong networking Skills\n\n\u00b7 Ability to quickly learn systems and products\n\n\u00b7 Strong communication and negotiation skills\n\n\u00b7 Excellent problem-solving abilities\n\n\u00b7 Positive, persistent attitude\n\n\u00b7 Excellent typing, phone, and computer navigation skills required, including Windows based platform and basic Microsoft skills\n\nSoftware Requirements\n\n\u00b7 A working computer and telephone\n\n\u00b7 MS Word, Excel and Windows platform\n\n\u00b7 CRM system preferred\n\nAdditional Information\n\nAll information will be kept confidential according to EEO guidelines.\n\nHOW TO APPLY:\n\nPlease click the green \"I'm Interested\" button below\n\nHow to Apply:\n\nPlease submit your resume and cover letter to apply\n\nDO NOT CONTACT THE EMPLOYER DIRECTLY\n\nPlease click the green \"I'm Interested\" button below\n\u2022 ** NO PHONE CALLS PLEASE ***", "job_is_remote": false, "job_posted_at_timestamp": 1495315768, "job_posted_at_datetime_utc": "2017-05-20T21:29:28.000Z", "job_city": "Manhattan", "job_state": "KS", "job_country": "US", "job_latitude": 39.18361, "job_longitude": -96.57167, "job_benefits": ["health_insurance", "retirement_savings", "paid_time_off"], "job_google_link": "https://www.google.com/search?gl=us&hl=en&rciv=jb&q=sales+consultant&start=80&ibp=htl;jobs#fpstate=tldetail&htivrt=jobs&htiq=sales+consultant&htidocid=FzQC6YroGwfRrXMDAAAAAA%3D%3D", "job_offer_expiration_datetime_utc": null, "job_offer_expiration_timestamp": null, "job_required_experience": {"no_experience_required": false, "required_experience_in_months": null, "experience_mentioned": true, "experience_preferred": true}, "job_required_skills": null, "job_required_education": {"postgraduate_degree": false, "professional_certification": false, "high_school": false, "associates_degree": false, "bachelors_degree": false, "degree_mentioned": false, "degree_preferred": false, "professional_certification_mentioned": false}, "job_experience_in_place_of_education": false, "job_min_salary": null, "job_max_salary": null, "job_salary_currency": null, "job_salary_period": null, "job_highlights": {"Qualifications": ["Successful candidate must be confident and capable of promoting our travel agency services to as many people as possible", "Ability to source and find potential", "Experience meeting and exceeding sales goals", "Experience working independently, in a call center or in customer service", "High School diploma or equivalent required", "Skills That Will Make You Successful", "Ability to connect with people", "Strong networking Skills", "Ability to quickly learn systems and products", "Strong communication and negotiation skills", "Excellent problem-solving abilities", "Positive, persistent attitude", "Excellent typing, phone, and computer navigation skills required, including Windows based platform and basic Microsoft skills", "A working computer and telephone", "MS Word, Excel and Windows platform"], "Responsibilities": ["Their goal is to help alleviate all the stress and worry that can sometimes accompany the vacation travel planning process", "They use their knack for travel to make travel easier for their clients", "This role will meet monthly and weekly sales goals set by personal and company objectives", "The TSC will utilize their own phones, email, social media and other tools to identify leads", "Commission can be generated based on meeting benchmarks and sales goals such as conversion rates, travel protection and other upgrades", "Source and find potential clients", "Identify leads for prospective vacation and travel bookings", "Qualify leads to make sure they are serious about booking", "Secure upsells on deals closed", "Qualify leads for future sales", "Acquire new leads by being proactive in sourcing leads", "Provide excellent service at all stages of the sales and service cycles"], "Benefits": ["This is a superb opportunity to work for yourself and set your own hours", "You get paid after travel has been completed when your referrals book with us, It\u2019s that simple"]}, "job_job_title": "Sales consultant", "job_posting_language": "en", "job_onet_soc": "41304100", "job_onet_job_zone": "3", "job_naics_code": "5613", "job_naics_name": "Staffing"}