{"job_id": "tGYd0yeiJ6575rFtAAAAAA==", "employer_name": "CEDENT", "employer_logo": "https://encrypted-tbn0.gstatic.com/images?q=tbn:ANd9GcR9DdDHBA6BIkQLFX9ytQN4Fn3ZYPWltN8voBRg&s=0", "employer_website": null, "employer_company_type": null, "job_publisher": "Glassdoor", "job_employment_type": "FULLTIME", "job_title": "AI/ML Principal Solution Architect", "job_apply_link": "https://www.glassdoor.com/job-listing/ai-ml-principal-solution-architect-cedent-JV_IC1151614_KO0,34_KE35,41.htm?jl=1009179418944", "job_apply_is_direct": false, "job_apply_quality_score": 0.6474, "apply_options": [{"publisher": "Glassdoor", "apply_link": "https://www.glassdoor.com/job-listing/ai-ml-principal-solution-architect-cedent-JV_IC1151614_KO0,34_KE35,41.htm?jl=1009179418944", "is_direct": false}, {"publisher": "Monster", "apply_link": "https://www.monster.com/job-openings/ai-ml-principal-solution-architect-portland-or--4a28948c-341e-46b6-a24c-4bcc16646c07", "is_direct": false}, {"publisher": "Career Cactus", "apply_link": "https://careercactus.com/jobs/ai-ml-principal-solution-architect/04a60ce9-540e-4892-ba80-f4c14189d6df", "is_direct": false}], "job_description": "Title: AI/ML Principal Solution Architect@ Boston, MA\n\nTerms of Hire: Full Time.\n\nSalary: $ Open K/ YR + Benefits.\n\nJob description:\n\nIf you're ready to innovate and lead in the Solution Architecture space, join Client\u2019s Enterprise Architecture organization! You will be part of an organization that is revolutionizing Client technology platforms and architecting a technology landscape that is simplified, modern, flexible and will ultimately enable Client on its journey to 2020 and beyond.\n\nThe Principal Solution Architect will provide leadership in architectural planning and in driving solutions across multiple domains/ solution areas, contributing to the future success of the business through innovations in technology. A person in this role will be responsible for leading opportunity identification and analysis, problem definition, and overseeing the development and deployment of advanced analytic tools and methods within the Enterprise Architecture organization.\n\nThis role, along with engineering leaders within Analytics will lead and supply the definition of an overarching analytics strategy and architecture that will align analytics investments with the highest impact areas, while producing a suite of complementary models, tools, and technologies. The ideal candidate for this role will have a passion for all things data and analytics and an outstanding ability to provide strategic advantage for Client through innovative solutions.\n\nResponsibilities:\n\u2022 Evangelize break through AI/ML solutions, specifically passionate about consumer analytics, driving personalization for Client consumers across a broad spectrum of experiences\n\u2022 Architect and design advanced analytics solutions to power marketing communication and segmentation\n\u2022 Guide engineering teams to build AI/ML foundational services such as fraud detection, automated tagging, and A/B testing\n\u2022 Partner with Product and Engineering leadership to build standard framework and patterns for feature engineering, model building, training, and serving\n\u2022 Participate in design and engineering of data science applications solutions that have significant strategic impact and achieve long term competitive advantage for Client.\n\u2022 Accept and influence domain driven design and architecture principles of security, privacy, scale, uptime and reliability\n\u2022 Partner with business leaders to provide expert technical advice and influence strategic decision making\n\u2022 Guide and mentor engineering teams to raise collective technical expertise\n\u2022 Demonstrate a strong bias for architecture principles balanced with tactical timelines, cost and risks\n\u2022 Contribute to architecture guiding principles, development standards, training and hiring\n\nQualifications:::\n\nRequirements for the Position include:\n\u2022 Bachelor's degree in Computer Science or related subject area\n\u2022 3+ years in technology architect or engineering leadership roles\n\u2022 3+ years of experience in the field of Machine Learning, AI, Deep Learning\n\u2022 5+ years providing technical leadership to technical, business & multi-functional teams\n\u2022 7+ years in hands-on experience in software engineering with depth in data and analytics\n\u2022 Experience with model development, management, and deployment in production.\n\u2022 A solid understanding and experience managing high volume, variety and velocity data such as telemetry data from sensors, clickstream or unstructured data like images and speech.\n\u2022 Experience implementing AI/ML applications such as recommendations, forecasts, and sentiments\n\u2022 Solid experience in software development in languages like Java, Python etc. Experience working with RESTful API and streaming.\n\u2022 Strong understanding of data and analytics solution architecture, including experience with Big Data, Relational databases, real time and batch data processing.\n\u2022 Experience leading enterprise cloud/virtual architectures like AWS, Microsoft Azure, etc.\n\u2022 - Demonstrated track record of leading within sophisticated organizations requiring strong influence leadership skills - ability to work in coordination with all levels in matrix environment\n\u2022 Exceptional collaboration, listening, written and verbal communication skills with ability to facilitate technology strategy, requirements and architecture conversations with all partners (management, business users, and technology resources)\n\nYou Will Enjoy:\n\u2022 An opportunity to be a part of a great culture, an awesome team, a challenging work environment, and some fun along the way!\n\u2022 Apply today to learn more and be part of our Growth story.\n\nAll applications will be kept strictly confidential and once shortlisted, our team will be in touch with you for further discussions.", "job_is_remote": false, "job_posted_at_timestamp": 1710028800, "job_posted_at_datetime_utc": "2024-03-10T00:00:00.000Z", "job_city": "Boston", "job_state": "MA", "job_country": "US", "job_latitude": 42.36008, "job_longitude": -71.05888, "job_benefits": null, "job_google_link": "https://www.google.com/search?gl=us&hl=en&rciv=jb&q=principal+machine+learning+architect&start=20&ibp=htl;jobs#fpstate=tldetail&htivrt=jobs&htiq=principal+machine+learning+architect&htidocid=tGYd0yeiJ6575rFtAAAAAA%3D%3D", "job_offer_expiration_datetime_utc": "2024-07-13T00:00:00.000Z", "job_offer_expiration_timestamp": 1720828800, "job_required_experience": {"no_experience_required": false, "required_experience_in_months": 36, "experience_mentioned": true, "experience_preferred": false}, "job_required_skills": null, "job_required_education": {"postgraduate_degree": false, "professional_certification": false, "high_school": false, "associates_degree": false, "bachelors_degree": false, "degree_mentioned": true, "degree_preferred": true, "professional_certification_mentioned": false}, "job_experience_in_place_of_education": false, "job_min_salary": null, "job_max_salary": null, "job_salary_currency": null, "job_salary_period": null, "job_highlights": {"Qualifications": ["Bachelor's degree in Computer Science or related subject area", "3+ years in technology architect or engineering leadership roles", "3+ years of experience in the field of Machine Learning, AI, Deep Learning", "5+ years providing technical leadership to technical, business & multi-functional teams", "7+ years in hands-on experience in software engineering with depth in data and analytics", "Experience with model development, management, and deployment in production", "A solid understanding and experience managing high volume, variety and velocity data such as telemetry data from sensors, clickstream or unstructured data like images and speech", "Experience implementing AI/ML applications such as recommendations, forecasts, and sentiments", "Solid experience in software development in languages like Java, Python etc", "Experience working with RESTful API and streaming", "Strong understanding of data and analytics solution architecture, including experience with Big Data, Relational databases, real time and batch data processing", "Experience leading enterprise cloud/virtual architectures like AWS, Microsoft Azure, etc", "- Demonstrated track record of leading within sophisticated organizations requiring strong influence leadership skills - ability to work in coordination with all levels in matrix environment", "Exceptional collaboration, listening, written and verbal communication skills with ability to facilitate technology strategy, requirements and architecture conversations with all partners (management, business users, and technology resources)"], "Responsibilities": ["You will be part of an organization that is revolutionizing Client technology platforms and architecting a technology landscape that is simplified, modern, flexible and will ultimately enable Client on its journey to 2020 and beyond", "The Principal Solution Architect will provide leadership in architectural planning and in driving solutions across multiple domains/ solution areas, contributing to the future success of the business through innovations in technology", "A person in this role will be responsible for leading opportunity identification and analysis, problem definition, and overseeing the development and deployment of advanced analytic tools and methods within the Enterprise Architecture organization", "This role, along with engineering leaders within Analytics will lead and supply the definition of an overarching analytics strategy and architecture that will align analytics investments with the highest impact areas, while producing a suite of complementary models, tools, and technologies", "The ideal candidate for this role will have a passion for all things data and analytics and an outstanding ability to provide strategic advantage for Client through innovative solutions", "Evangelize break through AI/ML solutions, specifically passionate about consumer analytics, driving personalization for Client consumers across a broad spectrum of experiences", "Architect and design advanced analytics solutions to power marketing communication and segmentation", "Guide engineering teams to build AI/ML foundational services such as fraud detection, automated tagging, and A/B testing", "Partner with Product and Engineering leadership to build standard framework and patterns for feature engineering, model building, training, and serving", "Participate in design and engineering of data science applications solutions that have significant strategic impact and achieve long term competitive advantage for Client", "Accept and influence domain driven design and architecture principles of security, privacy, scale, uptime and reliability", "Partner with business leaders to provide expert technical advice and influence strategic decision making", "Guide and mentor engineering teams to raise collective technical expertise", "Demonstrate a strong bias for architecture principles balanced with tactical timelines, cost and risks", "Contribute to architecture guiding principles, development standards, training and hiring"], "Benefits": ["Salary: $ Open K/ YR + Benefits", "An opportunity to be a part of a great culture, an awesome team, a challenging work environment, and some fun along the way!"]}, "job_job_title": "Solution architect", "job_posting_language": "en", "job_onet_soc": "15111100", "job_onet_job_zone": "5"}