{"job_id": "d7ZzQrpsoQrGpWi9AAAAAA==", "employer_name": "1840 & Company", "employer_logo": null, "employer_website": null, "employer_company_type": null, "job_publisher": "1840 & Company - Career Page", "job_employment_type": "FULLTIME", "job_title": "AI Developer - AI Search Tool Specialist - Full-time - (India)", "job_apply_link": "http://jobs.1840andco.com/apply/gr75sgteR1/AI-Developer-AI-Search-Tool-Specialist-Fulltime-India", "job_apply_is_direct": false, "job_apply_quality_score": 0.6921, "apply_options": [{"publisher": "1840 & Company - Career Page", "apply_link": "http://jobs.1840andco.com/apply/gr75sgteR1/AI-Developer-AI-Search-Tool-Specialist-Fulltime-India", "is_direct": false}, {"publisher": "1840 & Company - Career Page - JazzHR", "apply_link": "https://1840company.applytojob.com/apply/aoGqzpJ6rs/AI-Developer-AI-Search-Tool-Specialist-Fulltime-Nigeria", "is_direct": false}], "job_description": "Job Summary:\nWe are seeking an experienced AI Developer specializing in the creation of advanced AI search tools. The ideal candidate will have a strong background in developing AI-driven search functionalities for a variety of purposes, with specific experience in vector databases, particularly Pinecone, and proficient in automating content crawling and scraping using Apify's web crawler. This role involves creating sophisticated AI search tools that provide seamless search experiences, integrating semantic and keyword search capabilities for our diverse range of clients.\n\nSalary - INR 79,374- 101,022 / Monthly\n\nKey Responsibilities:\n\u2022 Design and develop AI search tools using Pinecone for vector storage and OpenAI GPT-3 for enhanced keyword search generation.\n\u2022 Automate the process of crawling and scraping web content using Apify's web crawler, ensuring efficient and accurate data collection.\n\u2022 Pre-process scraped data to ensure its relevance and readiness for analysis and storage.\n\u2022 Vectorize content into embeddings using advanced models such as text-embedding-3-small or ADA v2, ensuring optimal search performance and accuracy.\n\u2022 Manage the upserting pipeline to store vectorized content into Pinecone, ensuring seamless data integration and retrieval.\n\u2022 Develop and maintain APIs using AWS services, including Lambda for scalability and API Gateway for API management.\n\u2022 Work closely with the development team (ReactJS/WordPress) to integrate the AI search functionality onto the front end of website.\n\u2022 Utilize FastAPI for developing robust search logic APIs and ensure smooth frontend integration.\n\u2022 Collaborate with cross-functional teams to define project scope, plan resources, and ensure timely delivery of projects.\n\u2022 Conduct thorough testing and gather feedback to refine and optimize the search tool.\n\u2022 Stay abreast of the latest AI and machine learning technologies and methodologies to drive continuous innovation.\nQualifications:\n\u2022 Bachelor\u2019s or Master\u2019s degree in Computer Science, Artificial Intelligence, Machine Learning, or related field.\n\u2022 Proven experience in developing AI-driven search tools, with at least 2+ years of experience working with vector databases, specifically Pinecone.\n\u2022 In-depth knowledge of OpenAI GPT-3, including experience with generating keywords and enhancing search functionalities.\n\u2022 Expertise in automating web crawling and scraping, with a solid understanding of content collection and management for search purposes.\n\u2022 Strong proficiency in AWS services (Lambda, API Gateway, DynamoDB) and experience with deploying Dockerized applications using AWS Lambda.\n\u2022 Experience with FastAPI or similar frameworks for API development.\n\u2022 Familiarity with front-end integration and ensuring seamless user experiences.\n\u2022 Excellent problem-solving abilities, with a keen attention to detail and a commitment to high-quality output.\n\u2022 Strong communication skills and the ability to work collaboratively in a fast-paced, dynamic environment.\nMandatory Requirements\n\u2022 Must have a laptop/desktop that meets the minimum qualifications:\n\u2022 Must have Dual Monitors (2 Monitors)\n\u2022 Processor:\n\u2022 Core i5 or higher/ MacBook\n\u2022 RAM - 8GB or higher\n\u2022 Bandwidth Requirements Minimum:\n\u2022 Download Speed: at least 6 Mbps\n\u2022 Upload Speed: at least 6 Mbps\n\u2022 A quiet, private place in your home where you can work without background\n\nBenefits\n\u2022 Work from home\n\u2022 Access to diverse projects\n\u2022 Opportunities for professional growth\n\u2022 Collaboration with diverse teams\n\u2022 No commute time\n\u2022 No dress code (unless there\u2019s a meeting!)\n\u2022 Eco-friendly work lifestyle\n\u2022 Exposure to a multicultural team\n\u2022 Potential for long-term engagement\n\u2022 Improved work-life balance\nAbout 1840 & Company\n\n1840 & Company is a global leader in Business Process Outsourcing (BPO) and remote talent solutions, dedicated to propelling businesses forward through our comprehensive suite of services. We specialize in connecting companies with world-class freelance professionals and delivering top-tier outsourcing services, across over 150 countries worldwide.\n\nOur mission is to empower growth for forward-thinking businesses, seamlessly bridging any skill or resource gaps with our expertly vetted talent pool. We firmly believe in fostering an environment where exceptional individuals can achieve an optimal work-life balance, working remotely from any location, while maximizing their professional growth and earning potential.\n\nWe are headquartered in Overland Park, KS, USA with service delivery facilities in the Philippines, India, Ukraine, South Africa and Argentina. We invite you to explore the opportunities we offer and consider joining our exclusive network of global freelance talent. Visit www.1840andco.com to learn more about us. To explore a wealth of career opportunities and find a role that suits your unique skills and aspirations, please visit our dedicated jobs portal at jobs.1840andco.com", "job_is_remote": true, "job_posted_at_timestamp": 1710806400, "job_posted_at_datetime_utc": "2024-03-19T00:00:00.000Z", "job_city": "Overland Park", "job_state": "KS", "job_country": "US", "job_latitude": 38.930252, "job_longitude": -94.64706, "job_benefits": null, "job_google_link": "https://www.google.com/search?gl=us&hl=en&rciv=jb&q=ai+specialist&start=10&ibp=htl;jobs#fpstate=tldetail&htivrt=jobs&htiq=ai+specialist&htidocid=d7ZzQrpsoQrGpWi9AAAAAA%3D%3D", "job_offer_expiration_datetime_utc": "2024-06-17T00:00:00.000Z", "job_offer_expiration_timestamp": 1718582400, "job_required_experience": {"no_experience_required": false, "required_experience_in_months": 24, "experience_mentioned": true, "experience_preferred": false}, "job_required_skills": null, "job_required_education": {"postgraduate_degree": false, "professional_certification": false, "high_school": false, "associates_degree": false, "bachelors_degree": false, "degree_mentioned": true, "degree_preferred": true, "professional_certification_mentioned": false}, "job_experience_in_place_of_education": false, "job_min_salary": null, "job_max_salary": null, "job_salary_currency": null, "job_salary_period": null, "job_highlights": {"Qualifications": ["The ideal candidate will have a strong background in developing AI-driven search functionalities for a variety of purposes, with specific experience in vector databases, particularly Pinecone, and proficient in automating content crawling and scraping using Apify's web crawler", "Bachelor\u2019s or Master\u2019s degree in Computer Science, Artificial Intelligence, Machine Learning, or related field", "Proven experience in developing AI-driven search tools, with at least 2+ years of experience working with vector databases, specifically Pinecone", "In-depth knowledge of OpenAI GPT-3, including experience with generating keywords and enhancing search functionalities", "Expertise in automating web crawling and scraping, with a solid understanding of content collection and management for search purposes", "Strong proficiency in AWS services (Lambda, API Gateway, DynamoDB) and experience with deploying Dockerized applications using AWS Lambda", "Experience with FastAPI or similar frameworks for API development", "Familiarity with front-end integration and ensuring seamless user experiences", "Excellent problem-solving abilities, with a keen attention to detail and a commitment to high-quality output", "Strong communication skills and the ability to work collaboratively in a fast-paced, dynamic environment", "Must have a laptop/desktop that meets the minimum qualifications:", "Must have Dual Monitors (2 Monitors)", "Core i5 or higher/ MacBook", "RAM - 8GB or higher", "Download Speed: at least 6 Mbps", "A quiet, private place in your home where you can work without background"], "Responsibilities": ["Design and develop AI search tools using Pinecone for vector storage and OpenAI GPT-3 for enhanced keyword search generation", "Automate the process of crawling and scraping web content using Apify's web crawler, ensuring efficient and accurate data collection", "Pre-process scraped data to ensure its relevance and readiness for analysis and storage", "Vectorize content into embeddings using advanced models such as text-embedding-3-small or ADA v2, ensuring optimal search performance and accuracy", "Manage the upserting pipeline to store vectorized content into Pinecone, ensuring seamless data integration and retrieval", "Develop and maintain APIs using AWS services, including Lambda for scalability and API Gateway for API management", "Work closely with the development team (ReactJS/WordPress) to integrate the AI search functionality onto the front end of website", "Utilize FastAPI for developing robust search logic APIs and ensure smooth frontend integration", "Collaborate with cross-functional teams to define project scope, plan resources, and ensure timely delivery of projects", "Conduct thorough testing and gather feedback to refine and optimize the search tool", "Stay abreast of the latest AI and machine learning technologies and methodologies to drive continuous innovation"], "Benefits": ["Salary - INR 79,374- 101,022 / Monthly", "Work from home", "Access to diverse projects", "Opportunities for professional growth", "Collaboration with diverse teams", "No commute time", "No dress code (unless there\u2019s a meeting!)", "Eco-friendly work lifestyle", "Exposure to a multicultural team", "Potential for long-term engagement", "Improved work-life balance"]}, "job_job_title": null, "job_posting_language": "en", "job_onet_soc": "15111100", "job_onet_job_zone": "5"}