{"job_id": "KzVnrI64omlsSeV6AAAAAA==", "employer_name": "FedEx", "employer_logo": "https://www.fedex.com/content/dam/fedex-com/logos/FedEx-Logo.png", "employer_website": "http://www.fedex.com", "employer_company_type": "Logistics", "job_publisher": "Salary.com", "job_employment_type": "FULLTIME", "job_title": "Data Engineer III", "job_apply_link": "https://www.salary.com/job/fedex/data-engineer-iii/j202310040333437511952", "job_apply_is_direct": false, "job_apply_quality_score": 0.5959, "apply_options": [{"publisher": "Salary.com", "apply_link": "https://www.salary.com/job/fedex/data-engineer-iii/j202310040333437511952", "is_direct": false}], "job_description": "The Data Engineer III plays a pivotal role within Dataworks, focused on driving engineering innovation within Dataworks, helping define and build the Dataworks organization and leading the delivery of key business initiatives. S/he acts as a \u201cuniversal translator\u201d between IT, business, software engineers and data scientists, collaborating with these multi-disciplinary teams. The Data Engineer III will contribute to the adherence of technical standards for data engineering, including the selection and refinements of foundational technical components. S/he will work on those aspects of the Dataworks platform that govern the ingestion, transformation, and pipelining of data assets, both to end users within FedEx and into data products and services that may be externally facing. Day-to-day, s/he will be deeply involved in code reviews and large-scale deployments. S/he will also provide mentorship and guidance to junior engineers to support the continued training and up-skilling of the Data Engineering team.\n\nEssential Job Duties & Responsibilities:\nUnderstanding in depth both the business and technical problems Dataworks aims to solve\nBuilding tools, platforms and pipelines to enable teams to clearly and cleanly analyze data, build models and drive decisions\nScaling up from \u201claptop-scale\u201d to \u201ccluster scale\u201d problems, in terms of both infrastructure and problem structure and technique\nDelivering tangible value very rapidly, collaborating with diverse teams of varying backgrounds and disciplines\nChampioning the adherence to best practices for future reuse in the form of accessible, reusable patterns, templates, and code bases\nInteracting with senior technologists from the broader enterprise and outside of FedEx (partner ecosystems and customers) to create synergies and ensure smooth deployments to downstream operational systems\n\nSkill/ Knowledge Considered a Plus:\nTechnical background in computer science, software engineering, database systems, distributed systems\nFluency with distributed and cloud environments and a strong understanding of how to balance computational considerations with theoretical properties\nDetailed knowledge of the Microsoft Azure tooling for large-scale data engineering efforts and deployments is highly preferred\nA track record of designing and deploying large scale technical solutions, which deliver tangible, ongoing value\nDirect experience having built and deployed robust, complex production systems that implement modern, data scientific methods at scale\nAbility to context-switch, to provide support to dispersed teams which may need an \u201cexpert hacker\u201d to unblock an especially challenging technical obstacle, and to work through problems as they are still being defined\nDemonstrated ability to deliver technical projects with a team, often working under tight time constraints to deliver value\nAn \u2018engineering\u2019 mindset, willing to make rapid, pragmatic decisions to improve performance, accelerate progress or magnify impact\nComfort with working with distributed teams on code-based deliverables, using version control systems and code reviews\nAbility to conduct data analysis, investigation, and lineage studies to document and enhance data quality and access\nUse of agile and devops practices for project and software management including continuous integration and continuous delivery\nDemonstrated expertise working with some of the following common languages and tools:\nSpark (Scala and PySpark), HDFS, Kafka and other high volume data tools\nSQL and NoSQL storage tools, such as MySQL, Postgres, Cassandra, MongoDB and ElasticSearch\nPandas, Scikit-Learn, Matplotlib, TensorFlow, Jupyter and other Python data tools\n\nMinimum Qualifications:\nBachelor\u2019s Degree in Information Systems, Computer Science or a quantitative discipline such as Mathematics or Engineering and/or equivalent formal training or work experience.\nFive (5) years equivalent work experience in measurement and analysis, quantitative business problem solving, simulation development and/or predictive analytics.\nExtensive knowledge in data engineering and machine learning frameworks including design, development and implementation of highly complex systems and data pipelines.\nExtensive knowledge in Information Systems including design, development and implementation of large batch or online transaction-based systems.\nStrong understanding of the transportation industry, competitors, and evolving technologies.\nExperience providing leadership in a general planning or consulting setting.\nExperience as a senior member of multi-functional project teams.\nStrong oral and written communication skills.\nA related advanced degree may offset the related experience requirements.\n\nAdditional Information\nMogilska 43 Street\nKrakow, 31-545\n\nPosting Start Date: 2023-06-28\nJob Family: FDW: Data Engineering\n\nWant a career where you are empowered to make a difference? Want to work for a company that is environmentally responsible? Want to grow and develop on the job? If so, FedEx is the place for you! Every day FedEx delivers for its customers with transportation and business solutions. FedEx serves more than 220 countries and territories around the globe. We can serve this global network due to our outstanding team of FedEx employees. FedEx has over 400,000 talented employees who are tasked with making every FedEx experience outstanding. FedEx has been recognized on many different lists both for business success and for being a great employer.\n\nHere are some of the recognitions FedEx has received from the past couple of years:\nFortune World\u2019s Most Admired Companies \u2013 2020.\nForbes Best Employers for Diversity - 2020.\nReputation Institute World\u2019s Most Reputable Companies - 2019.\nNational Business Inclusion Consortium Best-of-the-Best Corporations for Inclusion - 2019.\nWomen\u2019s Business Enterprise National Council America\u2019s Top Corporations for Women\u2019s Business Enterprises - 2019.\n\nWhen 400,000 employees around the globe are all working together it is amazing what we can achieve! FedEx connects people and ideas. If you would like to make a difference on a global scale while receiving top notch benefits, competitive pay, and plenty of opportunities to develop, click \u2018Apply\u2019 and tell us more about yourself.", "job_is_remote": false, "job_posted_at_timestamp": 1697932800, "job_posted_at_datetime_utc": "2023-10-22T00:00:00.000Z", "job_city": "Krakow", "job_state": "WI", "job_country": "US", "job_latitude": 44.76166, "job_longitude": -88.25149, "job_benefits": null, "job_google_link": "https://www.google.com/search?gl=us&hl=en&rciv=jb&q=data+engineer&start=50&ibp=htl;jobs#fpstate=tldetail&htivrt=jobs&htiq=data+engineer&htidocid=KzVnrI64omlsSeV6AAAAAA%3D%3D", "job_offer_expiration_datetime_utc": "2024-03-31T00:00:00.000Z", "job_offer_expiration_timestamp": 1711843200, "job_required_experience": {"no_experience_required": false, "required_experience_in_months": 60, "experience_mentioned": true, "experience_preferred": false}, "job_required_skills": null, "job_required_education": {"postgraduate_degree": false, "professional_certification": false, "high_school": false, "associates_degree": false, "bachelors_degree": false, "degree_mentioned": true, "degree_preferred": true, "professional_certification_mentioned": false}, "job_experience_in_place_of_education": false, "job_min_salary": null, "job_max_salary": null, "job_salary_currency": null, "job_salary_period": null, "job_highlights": {"Qualifications": ["Technical background in computer science, software engineering, database systems, distributed systems", "Fluency with distributed and cloud environments and a strong understanding of how to balance computational considerations with theoretical properties", "A track record of designing and deploying large scale technical solutions, which deliver tangible, ongoing value", "Ability to context-switch, to provide support to dispersed teams which may need an \u201cexpert hacker\u201d to unblock an especially challenging technical obstacle, and to work through problems as they are still being defined", "Demonstrated ability to deliver technical projects with a team, often working under tight time constraints to deliver value", "An \u2018engineering\u2019 mindset, willing to make rapid, pragmatic decisions to improve performance, accelerate progress or magnify impact", "Comfort with working with distributed teams on code-based deliverables, using version control systems and code reviews", "Demonstrated expertise working with some of the following common languages and tools:", "Spark (Scala and PySpark), HDFS, Kafka and other high volume data tools", "Bachelor\u2019s Degree in Information Systems, Computer Science or a quantitative discipline such as Mathematics or Engineering and/or equivalent formal training or work experience", "Five (5) years equivalent work experience in measurement and analysis, quantitative business problem solving, simulation development and/or predictive analytics", "Extensive knowledge in data engineering and machine learning frameworks including design, development and implementation of highly complex systems and data pipelines", "Extensive knowledge in Information Systems including design, development and implementation of large batch or online transaction-based systems", "Strong understanding of the transportation industry, competitors, and evolving technologies", "Experience providing leadership in a general planning or consulting setting", "Experience as a senior member of multi-functional project teams", "Strong oral and written communication skills", "A related advanced degree may offset the related experience requirements"], "Responsibilities": ["S/he acts as a \u201cuniversal translator\u201d between IT, business, software engineers and data scientists, collaborating with these multi-disciplinary teams", "The Data Engineer III will contribute to the adherence of technical standards for data engineering, including the selection and refinements of foundational technical components", "S/he will work on those aspects of the Dataworks platform that govern the ingestion, transformation, and pipelining of data assets, both to end users within FedEx and into data products and services that may be externally facing", "Day-to-day, s/he will be deeply involved in code reviews and large-scale deployments", "S/he will also provide mentorship and guidance to junior engineers to support the continued training and up-skilling of the Data Engineering team", "Understanding in depth both the business and technical problems Dataworks aims to solve", "Building tools, platforms and pipelines to enable teams to clearly and cleanly analyze data, build models and drive decisions", "Scaling up from \u201claptop-scale\u201d to \u201ccluster scale\u201d problems, in terms of both infrastructure and problem structure and technique", "Delivering tangible value very rapidly, collaborating with diverse teams of varying backgrounds and disciplines", "Championing the adherence to best practices for future reuse in the form of accessible, reusable patterns, templates, and code bases", "Interacting with senior technologists from the broader enterprise and outside of FedEx (partner ecosystems and customers) to create synergies and ensure smooth deployments to downstream operational systems", "Use of agile and devops practices for project and software management including continuous integration and continuous delivery"]}, "job_job_title": "Data engineer", "job_posting_language": "en", "job_onet_soc": "15113200", "job_onet_job_zone": "4", "job_naics_code": "484", "job_naics_name": "Truck Transportation"}