{"job_id": "7KWmjnq35TahYWBEAAAAAA==", "employer_name": "Institute of Inspection Cleaning and Restoration Certification", "employer_logo": "https://iicrc.org/wp-content/uploads/2020/12/cropped-cropped-colorlogo-01-scaled-2.jpg", "employer_website": "https://iicrc.org", "employer_company_type": "Education", "job_publisher": "ZipRecruiter", "job_employment_type": "FULLTIME", "job_title": "Business Development Manager (Marketing)", "job_apply_link": "https://www.ziprecruiter.com/c/Institute-of-Inspection-Cleaning-and-Restoration-Certification/Job/Business-Development-Manager-(Marketing)/-in-Holts-Summit,MO?jid=4b6c7293610243df", "job_apply_is_direct": false, "job_apply_quality_score": 0.7244, "apply_options": [{"publisher": "ZipRecruiter", "apply_link": "https://www.ziprecruiter.com/c/Institute-of-Inspection-Cleaning-and-Restoration-Certification/Job/Business-Development-Manager-(Marketing)/-in-Holts-Summit,MO?jid=4b6c7293610243df", "is_direct": false}], "job_description": "Paul Davis provides professional residential and commercial emergency restoration services for disasters of all sizes. From water and flood damage, to fire damage and mold remediation, Paul Davis franchise professionals are available 24/7 to clean up and repair damage to residential and commercial property. Founded in 1966, Paul Davis is a rapidly growing network of more than 370 independently owned and operated franchises in the United States and Canada. Paul Davis will grow to become over a $2 Billion business in the next 5 years.\n\nPosition: Business Development Manager\n\nHours/Week: Full-time, 40+ hours\n\nCompensation:\n\u2022 Strong base salary commensurate with experience plus commission\n\u2022 Bonus opportunities\n\u2022 Medical, dental and vision coverage offered\n\u2022 401(k) with company match\n\u2022 PTO and paid holidays\n\u2022 Cell phone, computer and company car\n\nReports To: GM\n\nTerritory: Columbia, MO and surrounding area\n\nSummary:\n\u2022 To increase awareness of the Paul Davis brand\n\u2022 To promote the services of Paul Davis\n\u2022 To build industry relationships\n\nResponsibilities:\n\u2022 Build strong relationships with current and potential clients through B2B, organized events, and cold calling\n\u2022 Organize and schedule a calendar of consistent Business-To-Business visits\n\u2022 Manage marketing programs found on the Marketing Activity Planner (MAP)\n\u2022 Ensure staff uses the Paul Davis brand correctly in accordance with Brand Standards\n\u2022 Utilize marketing technology software to upload contacts to the CRM, send email campaigns, customize and print marketing collateral, track sales calls, leads, referrals, and notes\n\u2022 Collaborate with the franchisor, read weekly communications, and schedule consistent meetings with the Regional Marketing Manager\n\u2022 Manage social media accounts, post relative content and graphics, monitor all reviews and feedback and reply/ follow-up accordingly\n\u2022 Attend business networking functions to promote the business\n\u2022 Coordinate and manage community and charitable events\n\u2022 Schedule, manage, and present Continuing Education courses\n\u2022 Research local trade shows and coordinate Paul Davis booth set-up\n\u2022 Attend training courses and annual conference seminars as requested\n\u2022 Any other duties and responsibilities may be assigned on a needed basis\n\nSkills and Knowledge:\n\u2022 Strong verbal and written communications\n\u2022 Strategic thinking and planning\n\u2022 Project management and multitasking capability\n\u2022 Strong organizational skills\n\u2022 Exemplary computer skills, i.e. Internet & Microsoft Office\n\nPersonal Characteristics:\n\u2022 Professional demeanor\n\u2022 Personable, presentable, articulate\n\u2022 Open, cooperative, enthusiastic\n\u2022 Self-directed with exceptional initiative\n\nQualifications:\n\u2022 Marketing, Public Relations or Communications degree\n\u2022 Two or more years' sales and marketing experience\n\u2022 Franchise, restoration, construction/home improvement, and/or insurance industry experience ideal\n\nPaul Davis is an equal opportunity employer.\n\nCompensation: $50,000.00 - $55,000.00 per year\n\nSince 1966, Paul Davis has been an industry leader in the areas of property damage mitigation, reconstruction and remodeling. With more than 370 offices in our franchise network, the company serves residential, institutional, and commercial customers and clients across the United States and Canada.\n\nWe have built our heritage one project at a time, establishing a reputation for performance, integrity and responsibility among customers and carriers alike. Whether property damage is caused by water, fire, smoke, storms or other disasters, we deliver on our promise to deliver excellence, expertise and a customer experience that is second to none. At Paul Davis, our passion for quality drives everything we do.\n\nOur Vision:\n\nTo Provide Extraordinary Care While Serving People In Their Time Of Need.\n\nOur Values:\n\nDeliver What You Promise\n\nRespect The Individual\n\nHave Pride In What You Do\n\nPractice Continuous Improvement\n\nOur Mission:\n\nTo provide opportunities for great people to deliver Best in Class results", "job_is_remote": false, "job_posted_at_timestamp": 1691971200, "job_posted_at_datetime_utc": "2023-08-14T00:00:00.000Z", "job_city": "Holts Summit", "job_state": "MO", "job_country": "US", "job_latitude": 38.640316, "job_longitude": -92.122406, "job_benefits": ["retirement_savings", "health_insurance", "dental_coverage", "paid_time_off"], "job_google_link": "https://www.google.com/search?gl=us&hl=en&rciv=jb&q=manager+of+business+development&start=50&ibp=htl;jobs#fpstate=tldetail&htivrt=jobs&htiq=manager+of+business+development&htidocid=7KWmjnq35TahYWBEAAAAAA%3D%3D", "job_offer_expiration_datetime_utc": "2024-04-07T00:00:00.000Z", "job_offer_expiration_timestamp": 1712448000, "job_required_experience": {"no_experience_required": false, "required_experience_in_months": null, "experience_mentioned": true, "experience_preferred": true}, "job_required_skills": null, "job_required_education": {"postgraduate_degree": false, "professional_certification": false, "high_school": false, "associates_degree": false, "bachelors_degree": false, "degree_mentioned": false, "degree_preferred": false, "professional_certification_mentioned": false}, "job_experience_in_place_of_education": false, "job_min_salary": null, "job_max_salary": null, "job_salary_currency": null, "job_salary_period": null, "job_highlights": {"Qualifications": ["Strong verbal and written communications", "Strategic thinking and planning", "Project management and multitasking capability", "Strong organizational skills", "Exemplary computer skills, i.e", "Internet & Microsoft Office", "Professional demeanor", "Personable, presentable, articulate", "Open, cooperative, enthusiastic", "Self-directed with exceptional initiative", "Marketing, Public Relations or Communications degree", "Two or more years' sales and marketing experience", "Franchise, restoration, construction/home improvement, and/or insurance industry experience ideal"], "Responsibilities": ["To increase awareness of the Paul Davis brand", "To promote the services of Paul Davis", "To build industry relationships", "Build strong relationships with current and potential clients through B2B, organized events, and cold calling", "Organize and schedule a calendar of consistent Business-To-Business visits", "Manage marketing programs found on the Marketing Activity Planner (MAP)", "Ensure staff uses the Paul Davis brand correctly in accordance with Brand Standards", "Utilize marketing technology software to upload contacts to the CRM, send email campaigns, customize and print marketing collateral, track sales calls, leads, referrals, and notes", "Collaborate with the franchisor, read weekly communications, and schedule consistent meetings with the Regional Marketing Manager", "Manage social media accounts, post relative content and graphics, monitor all reviews and feedback and reply/ follow-up accordingly", "Attend business networking functions to promote the business", "Coordinate and manage community and charitable events", "Schedule, manage, and present Continuing Education courses", "Research local trade shows and coordinate Paul Davis booth set-up", "Attend training courses and annual conference seminars as requested", "Any other duties and responsibilities may be assigned on a needed basis"], "Benefits": ["Strong base salary commensurate with experience plus commission", "Bonus opportunities", "Medical, dental and vision coverage offered", "401(k) with company match", "PTO and paid holidays", "Cell phone, computer and company car", "Compensation: $50,000.00 - $55,000.00 per year"]}, "job_job_title": "Development manager", "job_posting_language": "en", "job_onet_soc": "11202100", "job_onet_job_zone": "4", "job_occupational_categories": ["41-1012.00: First-Line Supervisors of Non-Retail Sales Workers"], "job_naics_code": "61", "job_naics_name": "Education"}