{"job_id": "rvThZmiB2tgnwGUiAAAAAA==", "employer_name": "Children's Health", "employer_logo": null, "employer_website": null, "employer_company_type": null, "job_publisher": "Children\u2019s Health Jobs", "job_employment_type": "FULLTIME", "job_title": "Sr Data Scientist", "job_apply_link": "https://jobsearch.childrens.com/job/14006/Sr-Data-Scientist", "job_apply_is_direct": false, "job_apply_quality_score": 0.9255, "apply_options": [{"publisher": "Children\u2019s Health Jobs", "apply_link": "https://jobsearch.childrens.com/job/14006/Sr-Data-Scientist", "is_direct": false}, {"publisher": "LinkedIn", "apply_link": "https://www.linkedin.com/jobs/view/sr-data-scientist-at-children-s-health-3704529503", "is_direct": false}, {"publisher": "Indeed", "apply_link": "https://www.indeed.com/viewjob?jk=b6e1dd98bd291ceb", "is_direct": false}, {"publisher": "Talent.com", "apply_link": "https://www.talent.com/view?id=ccacdd073069", "is_direct": false}, {"publisher": "SimplyHired", "apply_link": "https://www.simplyhired.com/job/4OqI4oHGHY_oQT1L6G20P4bEMGuCDUOvyS8-q5BQbB7bGz34wwxSgA", "is_direct": false}], "job_description": "Job Title & Specialty Area: Sr Data Scientist\n\nDepartment: Heart Center Admin\n\nLocation: Dallas\n\nShift: Monday - Friday 8am -4:30pm\n\nJob Type: Remote\n\nWhy Children\u2019s Health?\nAt Children's Health, our mission is to Make Life Better for Children, and we recognize that their health plays a crucial role in achieving this goal. Through our cutting-edge treatments and affiliation with UT Southwestern, we strive to deliver an extraordinary patient and family experience, ensuring that every moment, big or small, contributes to their overall well-being. Our dedication to promoting children's health extends beyond our organization and encompasses the broader community. Together, we can make a significant difference in the lives of children and contribute to a brighter and healthier future for all.\n\nSummary:\nThe Data Science team develops and deploys analytic solutions to equip stakeholders with data-based insights empowering them to effectively measure performance, establish improvement goals, comprehend relationships between variables, predict outcomes and make strategic decisions. The Sr. Data Scientist will be involved in all steps of the process including data gathering, cleaning, validation, analysis, modeling, visualization, and presentation for manuscripts and posters utilizing R or SAS to create tables and figures - and will often be responsible for directing the technical work of others on the team as well as in other functions in the department or division. The Sr. Data Scientist will be responsible for the translation of statistical findings for researchers utilizing tables, figures, etc. The Sr. Data Scientist acts as the primary expert for two or more technically advanced solutions as described in the responsibilities section below.\n\nResponsibilities:\n\u2022 Design workflow for and guide information systems experts to identify data sources, gather and validate necessary data. Work closely with senior operational and/or clinical experts to ensure that complex data content is complete, accurate and relevant. Intermediate knowledge related to database management is required. Intermediate proficiency in SQL or other data gathering technology and familiarity with Big Data concepts is strongly preferred. Working knowledge and experience with Microsoft Visual Studio and SQL Server Management Studio. Additional working knowledge in configuration and production environments of cloud computing platforms such as Azure and AWS.\n\u2022 Guide others and/or perform complex statistical analyses of data sets to identify performance status, trends over time and key drivers. Translate findings for researchers and creation of tables and figures for manuscripts and posters using R or SAS. Advanced knowledge of descriptive and inferential statistics with demonstrated proficiency in sampling theory, forecasting, regression, non-normal distributions and hypothesis testing is required. Advanced proficiency in a statistical software package (Minitab, JMP, Stata, QI Macros, Alteryx, SAS Enterprise Miner, Python, R, etc.) is required.\n\u2022 Create, present and publish elegant graphical representations of analyses and key findings and their impact to strategic business indicators to a wide variety of stakeholders. Advanced proficiency in PowerPoint and a data visualization software package (MicroStrategy, Power BI, SAS VA or Tableau) is required White paper or research paper publication experience strongly preferred. Public speaking experience required. Knowledge of basic color theory is preferred.\n\u2022 Participate in or lead quality/process improvement initiatives research initiatives and other strategic programs as the voice of the data ensuring that data limitations, interpretation and insights are accurately comprehended by stakeholders and decision makers. Topics may include clinical, operational and/or financial domains. Familiarity with Lean Six Sigma and healthcare operations is strongly preferred. Financial acumen including ability to read and interpret financial statements is preferred.\n\u2022 Act as the team's resident expert in two or more technically advanced analytic solutions such as GIS data mapping, complex visualization, process simulation, predictive modeling, machine learning, natural language processing, program evaluation and other specialties. Intermediate proficiency in programming languages such as R or Python (or similar) is required.\n\u2022 Guide the activities of junior team members. Mentor other peers in area of specialty to support their development. Teach statistical concepts and methods to various stakeholders as needed. Formal peer training experience required.\n\nHow You\u2019ll Be Successful:\n\nWORK EXPERIENCE\n\u2022 At least 10 years in data wrangling, analysis, visualization and advanced techniques. Req\n\nEDUCATION\n\u2022 Four-year bachelor's degree or equivalent experience Computer Science, Engineering (all types), Mathematics, Statistics, and Economics. Candidates with other STEM degrees such as core sciences (Physics, Chemistry, etc.) could be considered Req\n\u2022 Graduate or professional work or advanced degree; or equivalent experience PhD Preferred Req\n\nLICENSES AND CERTIFICATIONS\n\u2022 Udacity Nanodegree: Machine Learning and/or Artificial Intelligence (or equivalent) Pref\n\u2022 Lean Six Sigma Black Belt Pref\n\u2022 SAS Enterprise Guide, Enterprise Miner, Visual Analytics, Developer, Predictive Modeling Pref\n\nA Place Where You Belong\n\nWe put our people first. We welcome, value, and respect the beliefs, identities and experiences of our patients and colleagues. We are committed to delivering culturally effective care, creating meaningful partnerships in the communities we serve, and equipping and developing our team members to make Children\u2019s Health a place where everyone can contribute.\n\nHolistic Benefits \u2013 How We\u2019ll Care for You:\n\n\u00b7 Employee portion of medical plan premiums are covered after 3 years.\n\n\u00b7 4%-10% employee savings plan match based on tenure\n\n\u00b7 Paid Parental Leave (up to 12 weeks)\n\n\u00b7 Caregiver Leave\n\n\u00b7 Adoption and surrogacy reimbursement >", "job_is_remote": false, "job_posted_at_timestamp": 1710288000, "job_posted_at_datetime_utc": "2024-03-13T00:00:00.000Z", "job_city": "Dallas", "job_state": "TX", "job_country": "US", "job_latitude": 32.776665, "job_longitude": -96.79699, "job_benefits": ["health_insurance"], "job_google_link": "https://www.google.com/search?gl=us&hl=en&rciv=jb&q=senior+data+scientist&start=10&ibp=htl;jobs#fpstate=tldetail&htivrt=jobs&htiq=senior+data+scientist&htidocid=rvThZmiB2tgnwGUiAAAAAA%3D%3D", "job_offer_expiration_datetime_utc": null, "job_offer_expiration_timestamp": null, "job_required_experience": {"no_experience_required": false, "required_experience_in_months": 48, "experience_mentioned": true, "experience_preferred": true}, "job_required_skills": null, "job_required_education": {"postgraduate_degree": false, "professional_certification": false, "high_school": false, "associates_degree": false, "bachelors_degree": false, "degree_mentioned": true, "degree_preferred": true, "professional_certification_mentioned": true}, "job_experience_in_place_of_education": false, "job_min_salary": null, "job_max_salary": null, "job_salary_currency": null, "job_salary_period": null, "job_highlights": {"Qualifications": ["Intermediate knowledge related to database management is required", "Working knowledge and experience with Microsoft Visual Studio and SQL Server Management Studio", "Additional working knowledge in configuration and production environments of cloud computing platforms such as Azure and AWS", "Advanced knowledge of descriptive and inferential statistics with demonstrated proficiency in sampling theory, forecasting, regression, non-normal distributions and hypothesis testing is required", "Advanced proficiency in a statistical software package (Minitab, JMP, Stata, QI Macros, Alteryx, SAS Enterprise Miner, Python, R, etc.) is required", "Create, present and publish elegant graphical representations of analyses and key findings and their impact to strategic business indicators to a wide variety of stakeholders", "Public speaking experience required", "Intermediate proficiency in programming languages such as R or Python (or similar) is required", "Formal peer training experience required", "At least 10 years in data wrangling, analysis, visualization and advanced techniques", "Four-year bachelor's degree or equivalent experience Computer Science, Engineering (all types), Mathematics, Statistics, and Economics", "Candidates with other STEM degrees such as core sciences (Physics, Chemistry, etc.) could be considered Req", "LICENSES AND CERTIFICATIONS", "Udacity Nanodegree: Machine Learning and/or Artificial Intelligence (or equivalent) Pref", "Lean Six Sigma Black Belt Pref", "SAS Enterprise Guide, Enterprise Miner, Visual Analytics, Developer, Predictive Modeling Pref"], "Responsibilities": ["Shift: Monday - Friday 8am -4:30pm", "Data Scientist will be involved in all steps of the process including data gathering, cleaning, validation, analysis, modeling, visualization, and presentation for manuscripts and posters utilizing R or SAS to create tables and figures - and will often be responsible for directing the technical work of others on the team as well as in other functions in the department or division", "Data Scientist will be responsible for the translation of statistical findings for researchers utilizing tables, figures, etc", "Data Scientist acts as the primary expert for two or more technically advanced solutions as described in the responsibilities section below", "Design workflow for and guide information systems experts to identify data sources, gather and validate necessary data", "Work closely with senior operational and/or clinical experts to ensure that complex data content is complete, accurate and relevant", "Guide others and/or perform complex statistical analyses of data sets to identify performance status, trends over time and key drivers", "Translate findings for researchers and creation of tables and figures for manuscripts and posters using R or SAS", "Guide the activities of junior team members", "Mentor other peers in area of specialty to support their development", "Teach statistical concepts and methods to various stakeholders as needed"], "Benefits": ["Employee portion of medical plan premiums are covered after 3 years", "4%-10% employee savings plan match based on tenure", "Paid Parental Leave (up to 12 weeks)", "Caregiver Leave", "Adoption and surrogacy reimbursement >"]}, "job_job_title": "Data scientist", "job_posting_language": "en", "job_onet_soc": "15111100", "job_onet_job_zone": "5", "job_occupational_categories": ["Professional & Management"]}