{"job_id": "_DqzAueT-y6z6s-oAAAAAA==", "employer_name": "Choice Hotels International", "employer_logo": "https://www.choicehotels.com/assets/4e4b6b1367b8589e994436967857a102-choice-hotels.svg", "employer_website": "http://www.choicehotels.com", "employer_company_type": "Accommodation", "job_publisher": "Jobrapido.com", "job_employment_type": "FULLTIME", "job_title": "Senior Sales Manager", "job_apply_link": "https://us.jobrapido.com/jobpreview/3206325980", "job_apply_is_direct": false, "job_apply_quality_score": 0.444, "apply_options": [{"publisher": "Jobrapido.com", "apply_link": "https://us.jobrapido.com/jobpreview/3206325980", "is_direct": false}], "job_description": "The always beautiful Radisson Hotel Sunnyvale is looking for their next Sales Leader. As the Senior Sales Manager, you will drive the property\u2019s sales department and be responsible to drive all top line revenues with leadership, revenue management, marketing and sales acumen.\n\nWHAT WE OFFER\n\nDay 1, we are pleased to offer:\n\u2022 Hotel Discounts at over 7,000 Choice Hotels\n\n\u200b\n\n1st of the Month after 30 Days of Employment:\n\u2022 Full benefits package, including health, dental, vision, short & long-term disability, auto insurance, and so much more!\n\u2022 Employer paid short-term disability, accident insurance and HSA contribution\n\u2022 401(k) Retirement Plan with employer match\n\n90 Days:\n\u2022 Paid Vacation and Sick Time\n\u2022 8 Paid Holidays\n\u2022 Paid Bereavement\n\n1 Year:\n\u2022 Paid Floating Holidays\n\nStarting Salary: $80,000 Annual\n\nYOUR DAY-TO-DAY\n\nYou're the Hotel Sales Expert!\n\u2022 Serve as the authority on sales processes, contracts, sales platforms and liaison for hotel\u2019s ultimate success\n\u2022 deploy an \"Everybody Sells\" strategy for collaboration with all hotel departments\n\u2022 Achieve market share and revenue goals by partnering with the Director of Sales on individual and team goals within assigned market segments.\n\u2022 Exemplify excellent written and oral communication skills with all stakeholders, including ownership and operational partners\n\u2022 Collaborate with the General Manager in the development and implementation of business strategies for the hotel which are aligned\n\u2022 Manage sales team and their job duties, delegation, and training where applicable\n\u2022 Create 100% guest satisfaction by providing the Radisson experience through performance that demonstrates the standards of genuine hospitality\n\nResponsibility #1 (70%): Sales initiatives, managing RFPs, generating new leads, and providing clear, strong and creative negotiation and accommodation for current and potential client requests while also delegating appropriate tasks and responsibilities to direct reports to generate greatest efficiencies.\n\nResponsibility #2 (20%): Conduct market research and analysis to align with industry trends and opportunities for soliciting business and maintaining client loyalty for future bookings.\n\nResponsibility #3 (10%): Attend networking events, participate in community involvement opportunities, and serve as a strong presence for hotel service and brand advocacy.\n\nREQUIREMENTS\n\u2022 High School Diploma Required, bachelor's degree preferred\n\u2022 Minimum 4 years sales management experience within hotel industry\n\u2022 General Knowledge of contract laws\n\u2022 Experience managing a team\n\u2022 Ability to interpret and implement strategies based on reviews of STR, TravelClick/Kalibri Labs, GDS Audits, Online booking tools and other similar sales tools\n\u2022 Expert computer skills including Microsoft Office Suite\n\u2022 Ability to travel\n\u2022 Required to stand, sit and walk for extended periods of time\n\u2022 Lift, carry, or otherwise move and use of force up to 50 lbs.\n\u2022 Use of manual dexterity of common office equipment such as but not limited to, computers, printers, phones, etc.\n\nSKILLS\n\u2022 Experience managing owner relations\n\u2022 Able to resolve conflicts; guest, supervisor and employee\n\u2022 Able to collaborate effectively with other hotel employees and manager to ensure and environment of teamwork\n\u2022 Knowledge of hotel of hotel operations including; preparations of business plans, budget forecasting, quality assurance program, hospitality law, and long-range planning", "job_is_remote": false, "job_posted_at_timestamp": 1709942400, "job_posted_at_datetime_utc": "2024-03-09T00:00:00.000Z", "job_city": null, "job_state": null, "job_country": "US", "job_latitude": 37.09024, "job_longitude": -95.71289, "job_benefits": ["retirement_savings", "health_insurance", "dental_coverage", "paid_time_off"], "job_google_link": "https://www.google.com/search?gl=us&hl=en&rciv=jb&q=senior+sales+manager&start=10&ibp=htl;jobs#fpstate=tldetail&htivrt=jobs&htiq=senior+sales+manager&htidocid=_DqzAueT-y6z6s-oAAAAAA%3D%3D", "job_offer_expiration_datetime_utc": null, "job_offer_expiration_timestamp": null, "job_required_experience": {"no_experience_required": false, "required_experience_in_months": 48, "experience_mentioned": true, "experience_preferred": false}, "job_required_skills": null, "job_required_education": {"postgraduate_degree": false, "professional_certification": false, "high_school": false, "associates_degree": false, "bachelors_degree": false, "degree_mentioned": true, "degree_preferred": false, "professional_certification_mentioned": false}, "job_experience_in_place_of_education": false, "job_min_salary": null, "job_max_salary": null, "job_salary_currency": null, "job_salary_period": null, "job_highlights": {"Qualifications": ["Minimum 4 years sales management experience within hotel industry", "General Knowledge of contract laws", "Experience managing a team", "Ability to interpret and implement strategies based on reviews of STR, TravelClick/Kalibri Labs, GDS Audits, Online booking tools and other similar sales tools", "Expert computer skills including Microsoft Office Suite", "Ability to travel", "Required to stand, sit and walk for extended periods of time", "Lift, carry, or otherwise move and use of force up to 50 lbs", "Use of manual dexterity of common office equipment such as but not limited to, computers, printers, phones, etc", "Experience managing owner relations", "Able to resolve conflicts; guest, supervisor and employee", "Able to collaborate effectively with other hotel employees and manager to ensure and environment of teamwork", "Knowledge of hotel of hotel operations including; preparations of business plans, budget forecasting, quality assurance program, hospitality law, and long-range planning"], "Responsibilities": ["As the Senior Sales Manager, you will drive the property\u2019s sales department and be responsible to drive all top line revenues with leadership, revenue management, marketing and sales acumen", "Serve as the authority on sales processes, contracts, sales platforms and liaison for hotel\u2019s ultimate success", "deploy an \"Everybody Sells\" strategy for collaboration with all hotel departments", "Achieve market share and revenue goals by partnering with the Director of Sales on individual and team goals within assigned market segments", "Exemplify excellent written and oral communication skills with all stakeholders, including ownership and operational partners", "Collaborate with the General Manager in the development and implementation of business strategies for the hotel which are aligned", "Manage sales team and their job duties, delegation, and training where applicable", "Create 100% guest satisfaction by providing the Radisson experience through performance that demonstrates the standards of genuine hospitality", "Responsibility #1 (70%): Sales initiatives, managing RFPs, generating new leads, and providing clear, strong and creative negotiation and accommodation for current and potential client requests while also delegating appropriate tasks and responsibilities to direct reports to generate greatest efficiencies", "Responsibility #2 (20%): Conduct market research and analysis to align with industry trends and opportunities for soliciting business and maintaining client loyalty for future bookings", "Responsibility #3 (10%): Attend networking events, participate in community involvement opportunities, and serve as a strong presence for hotel service and brand advocacy"], "Benefits": ["Hotel Discounts at over 7,000 Choice Hotels", "Full benefits package, including health, dental, vision, short & long-term disability, auto insurance, and so much more!", "Employer paid short-term disability, accident insurance and HSA contribution", "401(k) Retirement Plan with employer match", "Paid Vacation and Sick Time", "8 Paid Holidays", "Paid Bereavement", "Paid Floating Holidays", "Starting Salary: $80,000 Annual"]}, "job_job_title": "Sales manager", "job_posting_language": "en", "job_onet_soc": "11202200", "job_onet_job_zone": "4", "job_naics_code": "7211", "job_naics_name": "Traveler Accommodation"}