{"job_id": "O9ykrkuGtcKiqiJdAAAAAA==", "employer_name": "RingCentral", "employer_logo": "https://www.ringcentral.com/content/dam/rc-www/en_us/images/content/whyringcentral/pressimages/dec-2023/logo-jpg-rendition.webp", "employer_website": "http://www.ringcentral.com", "employer_company_type": "Information", "job_publisher": "LinkedIn", "job_employment_type": "FULLTIME", "job_title": "Partner Alliance Manager", "job_apply_link": "https://www.linkedin.com/jobs/view/partner-alliance-manager-at-ringcentral-3830170091", "job_apply_is_direct": false, "job_apply_quality_score": 0.6437, "apply_options": [{"publisher": "LinkedIn", "apply_link": "https://www.linkedin.com/jobs/view/partner-alliance-manager-at-ringcentral-3830170091", "is_direct": false}], "job_description": "Say hello to possibilities.\n\nIt\u2019s not everyday that you consider starting a new career. We\u2019re RingCentral, and we\u2019re happy that someone as talented as you is considering this role. First, a little about us, we\u2019re the $2 billion global leader in cloud-based communications and collaboration software. We are fundamentally changing the nature of human interaction\u2014giving people the freedom to connect powerfully and personally from anywhere, at any time, on any device.\n\nThis is where you and your skills come in. We\u2019re currently looking for: The Partner Alliance Manager will have a demonstrated record of success in recruiting partners within the Event, Marketing and/or Video Communications Industry to grow our RingCentral Events partner network. The candidate must have a bias towards action, be self-motivated and must be able to work independently. This includes being hands-on and team oriented while possessing entrepreneurial business acumen. Utilizes communications skills, enthusiasm, commitment and creativity in order to achieve company goals and revenue in the specified territory. Candidates must possess integrity and confidence and have the ability to embrace the vibrant culture of RingCentral.\n\nJob Duties:\n\u2022 Develop and expand C-level relationships with event & marketing agencies and strategic profiled partners to increase sales and market share while maintaining profitability from a sales and overall business standpoint.\n\u2022 Results-oriented mindset, must be able to demonstrate a track record of success in Partner Management or in bringing in new Partners, exceeding quotas, and maximizing revenue\n\u2022 Engaging Presence. Use your interpersonal skills to effectively engage with partners, getting them excited to speak with you and learn more about how our solutions can help expand the partner revenue stream\n\u2022 Drive & Grit. Operate in a fast-paced environment with a focus and determination to achieve high-quality results\n\u2022 Build and maintain strong, long-lasting relationships with potential partners, fostering trust and collaboration.\n\u2022 Be able to work in a fast paced global organization across different business functions and stakeholders\n\u2022 Lead effective Cross Functional relationships between sales, customer success, enablement, marketing & product to drive Partner Recruitment Success\n\u2022 Effective decision making on all aspects of the business\n\u2022 Ensure compliance of to all RingCentral policies and procedures\n\u2022 Clear and effective communication skills, both verbal and written\n\u2022 Strong initiative and creativity applied through technology\n\nTo succeed in this role you must have experience in:\n\u2022 A minimum of 3-5+ years and strong experience with Partner Channels or Business Development, working with industry-leading partners\n\u2022 A minimum of 3-5+ years working in the event & marketing industry and SaaS, preferable.\n\u2022 Experience in reviewing and analyzing partner requirements with the ability to develop and convey effective business solutions through a consultative sales approach.\n\nDesired Qualifications:\n\u2022 A high level of creativity and marketplace awareness that will enable the successful assessment of a wide range of business opportunities internal and external to the channel.\n\u2022 Strong decision making skills with proficient project management skills.\n\u2022 Visionary and conceptual skills with the ability to anticipate change in a competitive market and react or adapt as required.\n\u2022 Understand partner\u2019s business and how RingCentral services can enhance their value proposition\n\u2022 Provide recommendations on marketing and enablement activities to align with company strategy and KPI objectives\n\u2022 Serve as internal channel advocate to ensure partner and customer satisfaction.\n\u2022 Participation in industry events such as trade shows and training.\n\u2022 Ability to travel up to 25%\n\u2022 Bachelor's degree or equivalent military and/or work experience\n\nWhat we offer:\n\u2022 Comprehensive medical, dental, vision, disability, life insurance\n\u2022 Health Savings Account (HSA), Flexible Spending Account (FSAs) and Commuter benefits\n\u2022 401K match and ESPP\n\u2022 Paid time off and paid sick leave\n\u2022 Wellness programs including 1:1 coaching and meditation guidance\n\u2022 Paid parental and pregnancy leave and new parent gift boxes\n\u2022 Family-forming benefits (IVF, Preservation, Adoption etc.)\n\u2022 Emergency backup care (Child/Adult/Pets)\n\u2022 Pet insurance and Pet Telehealth\n\u2022 Employee Assistance Program (EAP) with counseling sessions available 24/7\n\u2022 Free legal services that provide legal advice, document creation and estate planning\n\u2022 Employee bonus referral program\n\u2022 Student loan refinancing assistance\n\u2022 Employee perks and discounts program\n\nRingCentral\u2019s Partner team crafts, builds and collaborates with our partners to evolve our programs and deliver the best possible outcomes for our partners, teams and company. That\u2019s why RingCentral is the leading global cloud-based communications provider because we\u2019re not just selling solutions; we\u2019re changing the nature of communications. That\u2019s why we\u2019re the largest and fastest-growing pure-play provider in our space.\n\nRingCentral\u2019s work culture is the backbone of our success. And don\u2019t just take our word for it: we are recognized as a Best Place to Work by Glassdoor, the Top Work Culture by Comparably and hold local BPTW awards in every major location. Bottom line: We are committed to hiring and retaining great people because we know you power our success. RingCentral offers on-site, remote and hybrid work options optimized for the ways we work and live now.\n\nAbout RingCentral\n\nRingCentral, Inc. (NYSE: RNG) is a leading provider of business cloud communications and contact center solutions based on its powerful Message Video Phone\u2122\u200a\u200a(MVP\u2122) global platform. More flexible and cost effective than legacy on-premises PBX and video conferencing systems that it replaces, RingCentral\u00ae empowers modern mobile and distributed workforces to communicate, collaborate, and connect via any mode, any device, and any location. RingCentral is headquartered in Belmont, California, and has offices around the world.\n\nRingCentral is an equal opportunity employer that truly values diversity. We do not discriminate on the basis of race, religion, color, national origin, gender, sexual orientation, age, marital status, veteran status, or disability status. We are committed to providing reasonable accommodations for individuals with disabilities during our application and interview process. If you require such accommodations, please click on the following link to learn more about how we can assist you.\n\nIf you are hired in Colorado, the compensation range for this position is between $92,000 and $132,000 for full-time employees, in addition to eligibility for variable pay, equity, and benefits. Benefits may include, but are not limited to, health and wellness, 401k, ESPP, vacation, parental leave, and more! The salary may vary depending on your location, skills, and experience.\n\nWe hire for this role frequently. There is no application deadline for this role.", "job_is_remote": false, "job_posted_at_timestamp": 1710411391, "job_posted_at_datetime_utc": "2024-03-14T10:16:31.000Z", "job_city": null, "job_state": "TX", "job_country": "US", "job_latitude": 32.707874, "job_longitude": -96.92091, "job_benefits": ["health_insurance", "paid_time_off", "retirement_savings", "dental_coverage"], "job_google_link": "https://www.google.com/search?gl=us&hl=en&rciv=jb&q=manager+of+brand+partnerships&start=80&ibp=htl;jobs#fpstate=tldetail&htivrt=jobs&htiq=manager+of+brand+partnerships&htidocid=O9ykrkuGtcKiqiJdAAAAAA%3D%3D", "job_offer_expiration_datetime_utc": "2024-04-13T10:16:31.000Z", "job_offer_expiration_timestamp": 1713003391, "job_required_experience": {"no_experience_required": false, "required_experience_in_months": 36, "experience_mentioned": true, "experience_preferred": false}, "job_required_skills": null, "job_required_education": {"postgraduate_degree": false, "professional_certification": false, "high_school": false, "associates_degree": false, "bachelors_degree": true, "degree_mentioned": true, "degree_preferred": false, "professional_certification_mentioned": false}, "job_experience_in_place_of_education": false, "job_min_salary": null, "job_max_salary": null, "job_salary_currency": null, "job_salary_period": null, "job_highlights": {"Qualifications": ["The candidate must have a bias towards action, be self-motivated and must be able to work independently", "This includes being hands-on and team oriented while possessing entrepreneurial business acumen", "Candidates must possess integrity and confidence and have the ability to embrace the vibrant culture of RingCentral", "Clear and effective communication skills, both verbal and written", "Strong initiative and creativity applied through technology", "A minimum of 3-5+ years and strong experience with Partner Channels or Business Development, working with industry-leading partners", "A minimum of 3-5+ years working in the event & marketing industry and SaaS, preferable", "Experience in reviewing and analyzing partner requirements with the ability to develop and convey effective business solutions through a consultative sales approach"], "Responsibilities": ["Develop and expand C-level relationships with event & marketing agencies and strategic profiled partners to increase sales and market share while maintaining profitability from a sales and overall business standpoint", "Results-oriented mindset, must be able to demonstrate a track record of success in Partner Management or in bringing in new Partners, exceeding quotas, and maximizing revenue", "Engaging Presence", "Use your interpersonal skills to effectively engage with partners, getting them excited to speak with you and learn more about how our solutions can help expand the partner revenue stream", "Drive & Grit", "Operate in a fast-paced environment with a focus and determination to achieve high-quality results", "Build and maintain strong, long-lasting relationships with potential partners, fostering trust and collaboration", "Be able to work in a fast paced global organization across different business functions and stakeholders", "Effective decision making on all aspects of the business", "Ensure compliance of to all RingCentral policies and procedures", "Serve as internal channel advocate to ensure partner and customer satisfaction"], "Benefits": ["Comprehensive medical, dental, vision, disability, life insurance", "Health Savings Account (HSA), Flexible Spending Account (FSAs) and Commuter benefits", "401K match and ESPP", "Paid time off and paid sick leave", "Wellness programs including 1:1 coaching and meditation guidance", "Paid parental and pregnancy leave and new parent gift boxes", "Family-forming benefits (IVF, Preservation, Adoption etc.)", "Emergency backup care (Child/Adult/Pets)", "Pet insurance and Pet Telehealth", "Employee Assistance Program (EAP) with counseling sessions available 24/7", "Free legal services that provide legal advice, document creation and estate planning", "Employee bonus referral program", "Student loan refinancing assistance", "Employee perks and discounts program", "If you are hired in Colorado, the compensation range for this position is between $92,000 and $132,000 for full-time employees, in addition to eligibility for variable pay, equity, and benefits", "Benefits may include, but are not limited to, health and wellness, 401k, ESPP, vacation, parental leave, and more!", "The salary may vary depending on your location, skills, and experience"]}, "job_job_title": "Manager", "job_posting_language": "en", "job_onet_soc": "11202100", "job_onet_job_zone": "4", "job_naics_code": "511210", "job_naics_name": "Software Publishers"}