{"job_id": "2wSEPZDXnLX3094pAAAAAA==", "employer_name": "Jobot", "employer_logo": "https://encrypted-tbn0.gstatic.com/images?q=tbn:ANd9GcTt9YOWKRgO5tE2DGJgyoo7Znuk7BqMypGAtQn7&s=0", "employer_website": "http://www.jobot.com", "employer_company_type": null, "job_publisher": "Pangian", "job_employment_type": "FULLTIME", "job_title": "Sr Sales Manager Semiconductor Key Accounts (Remote)", "job_apply_link": "https://pangian.com/job/sr-sales-manager-semiconductor-key-accounts-remote-8/", "job_apply_is_direct": true, "job_apply_quality_score": 0.5207, "apply_options": [{"publisher": "Pangian", "apply_link": "https://pangian.com/job/sr-sales-manager-semiconductor-key-accounts-remote-8/", "is_direct": true}], "job_description": "100% remote job\n\nSr Sales Manager Semiconductor Key Accounts | Jobot | United States\n\nWant to learn more about this role and Jobot? Click our Jobot logo and follow our LinkedIn page!\n\nJob details\n\nUrgently Hiring Remote Sr Sales Manager for Global Semiconductor Market Leader\n\nThis Jobot Job is hosted by Alvin Truong\n\nAre you a fit? Easy Apply now by clicking the \u201cEasy Apply\u201d button and sending us your resume.\n\nSalary $75,000 \u2013 $350,000 per year\n\nA Bit About Us\n\nWe are a rapidly growing publicly-traded global semiconductor company that is looking for a Sr Sales Manager responsible for managing identified key accounts in the Eastern US and Canada territory and execute strategic business plans. You will use your technical knowledge of circuits and be able to discuss design issues and present the technical benefits of our products to solve customer challenges.\n\nIf you are a Sr Sales Manager with a strong background in strategic sales with enterprise accounts, business development, and driving partnerships, Please apply today!\n\nWhy join us?\n\u2022 Strong Compensation Package + RSU\u2019s\n\u2022 Extensive PTO\n\u2022 Huge Room for Growth\n\u2022 Weekly Lunches & Fun Company Culture!\n\u2022 Great 401k Match\n\u2022 Health, Vision, Dental Benefits\n\nJob Details\n\nResponsibilities\n\u2022 Aggressively drive new business by identifying opportunities and utilizing value-based selling.\n\u2022 Manage and grow business with customers in the Eastern region of U.S & Canada.\n\u2022 Co-work with Sales team members to manage business in other global regions (e.g. EMEA and Greater China), both transfer business w contract manufacturers, and well as design activity in multiple locations\n\u2022 Develop business cases for new products and participate in product and company strategy development\n\u2022 Present to purchasing staff, engineers, and management at accounts of interest in a professional setting as the front line representative of the company.\n\u2022 Manage identified key accounts in the territory and drive sales objectives.\n\u2022 Coordinate with Reps in the territory for success at named accounts using channel partners as needed.\n\u2022 Provide customer support as needed responding to customer technical and commercial questions.\n\u2022 Provide market feedback to the company on the competitive environment and new product ideas and features.\n\u2022 Maintain the CRM database with accurate customer and channel information regarding sales opportunities, design ins, design wins and production status.\n\u2022 Prepare accurate forecasts of business for use in capacity planning, longer range resource planning and sales prioritization.\n\u2022 Include company resources, engineers and management, in account calls as required.\n\u2022 Provide new product training and drive Disti sales, and lead them to generate increased Sales\n\u2022 Drive other projects as needed by management or as business needs change\n\nQualifications\n\u2022 Minimum of 7+ years of semiconductor sales experience\n\u2022 Bachelor\u2019s degree or higher in (Electrical engineering, Mechanical Engineering, Physics, or equivalent)\n\u2022 Good skill of customer relationship management, complex organization penetration\n\u2022 Deeply penetrate major accounts in assigned region.\n\u2022 Experience working with or strong understanding of circuits\n\u2022 Experience managing Distributor network\n\u2022 Understanding of semiconductor engineering terms that are relevant to the company\u2019s product\n\u2022 Strong verbal and written communication skills\n\u2022 Demonstrate a Positive, Collaborative, and Enthusiastic attitude\n\nBonus\n\u2022 MBA Degree\n\u2022 Sales Management experience\n\u2022 FAE experience\n\u2022 Inquisitive and a deep desire to learn new technologies\n\u2022 Self-starter that can work independently without proximity supervision\n\nInterested in hearing more? Easy Apply now by clicking the \u201cEasy Apply\u201d button.\n\nWant to learn more about this role and Jobot?\n\nClick our Jobot logo and follow our LinkedIn page!\n\nShow more\n\nShow less\n\nTagged as: remote, remote job, virtual, Virtual Job, virtual position, Work at Home, work from home", "job_is_remote": true, "job_posted_at_timestamp": 1708748371, "job_posted_at_datetime_utc": "2024-02-24T04:19:31.000Z", "job_city": null, "job_state": null, "job_country": "US", "job_latitude": 37.09024, "job_longitude": -95.71289, "job_benefits": ["dental_coverage", "paid_time_off", "retirement_savings", "health_insurance"], "job_google_link": "https://www.google.com/search?gl=us&hl=en&rciv=jb&q=senior+sales+manager&start=40&ibp=htl;jobs#fpstate=tldetail&htivrt=jobs&htiq=senior+sales+manager&htidocid=2wSEPZDXnLX3094pAAAAAA%3D%3D", "job_offer_expiration_datetime_utc": "2024-03-26T06:59:59.000Z", "job_offer_expiration_timestamp": 1711436399, "job_required_experience": {"no_experience_required": false, "required_experience_in_months": 84, "experience_mentioned": true, "experience_preferred": false}, "job_required_skills": null, "job_required_education": {"postgraduate_degree": false, "professional_certification": false, "high_school": false, "associates_degree": false, "bachelors_degree": false, "degree_mentioned": true, "degree_preferred": false, "professional_certification_mentioned": false}, "job_experience_in_place_of_education": false, "job_min_salary": null, "job_max_salary": null, "job_salary_currency": null, "job_salary_period": null, "job_highlights": {"Qualifications": ["Minimum of 7+ years of semiconductor sales experience", "Bachelor\u2019s degree or higher in (Electrical engineering, Mechanical Engineering, Physics, or equivalent)", "Good skill of customer relationship management, complex organization penetration", "Deeply penetrate major accounts in assigned region", "Experience working with or strong understanding of circuits", "Experience managing Distributor network", "Understanding of semiconductor engineering terms that are relevant to the company\u2019s product", "Strong verbal and written communication skills", "Demonstrate a Positive, Collaborative, and Enthusiastic attitude", "Sales Management experience", "FAE experience", "Inquisitive and a deep desire to learn new technologies", "Self-starter that can work independently without proximity supervision"], "Responsibilities": ["You will use your technical knowledge of circuits and be able to discuss design issues and present the technical benefits of our products to solve customer challenges", "Aggressively drive new business by identifying opportunities and utilizing value-based selling", "Manage and grow business with customers in the Eastern region of U.S & Canada", "Co-work with Sales team members to manage business in other global regions (e.g. EMEA and Greater China), both transfer business w contract manufacturers, and well as design activity in multiple locations", "Develop business cases for new products and participate in product and company strategy development", "Present to purchasing staff, engineers, and management at accounts of interest in a professional setting as the front line representative of the company", "Manage identified key accounts in the territory and drive sales objectives", "Coordinate with Reps in the territory for success at named accounts using channel partners as needed", "Provide customer support as needed responding to customer technical and commercial questions", "Provide market feedback to the company on the competitive environment and new product ideas and features", "Maintain the CRM database with accurate customer and channel information regarding sales opportunities, design ins, design wins and production status", "Prepare accurate forecasts of business for use in capacity planning, longer range resource planning and sales prioritization", "Include company resources, engineers and management, in account calls as required", "Provide new product training and drive Disti sales, and lead them to generate increased Sales", "Drive other projects as needed by management or as business needs change"], "Benefits": ["Salary $75,000 \u2013 $350,000 per year", "Strong Compensation Package + RSU\u2019s", "Extensive PTO", "Huge Room for Growth", "Weekly Lunches & Fun Company Culture!", "Great 401k Match", "Health, Vision, Dental Benefits"]}, "job_job_title": "Sales manager", "job_posting_language": "en", "job_onet_soc": "11202200", "job_onet_job_zone": "4"}