{"job_id": "nJyd6fQDDNCJIEZBAAAAAA==", "employer_name": "Designworks, a BMW Group Company", "employer_logo": null, "employer_website": null, "employer_company_type": null, "job_publisher": "Monster", "job_employment_type": "FULLTIME", "job_title": "AI Creative Consultant", "job_apply_link": "https://www.monster.com/job-openings/ai-creative-consultant-santa-monica-ca--bc5c2dc8-74c4-47fb-8a23-6593aaf8547a", "job_apply_is_direct": false, "job_apply_quality_score": 0.5739, "apply_options": [{"publisher": "Monster", "apply_link": "https://www.monster.com/job-openings/ai-creative-consultant-santa-monica-ca--bc5c2dc8-74c4-47fb-8a23-6593aaf8547a", "is_direct": false}], "job_description": "The AI Creative Consultant supports and focuses on the content development under the direction of the Associate Director and Lead Creative Consultant, having a discipline function in AI, Design, and Business. The specialist will craft with AI to empower creative thinking and design exploration and prototyping, to be at the forefront of transforming automotive experiences with AI-powered design, establishing Designworks as a leader and facilitator in this cutting-edge space.\n\nKey Responsibilities:\n\n\u2022 Real-time learning and experimenting with AI advancements: Continually apply and experiment new AI tools, finding innovative ways to leverage them in design, aesthetics, storytelling, moviemaking, fabrication, and innovation.\n\n\u2022 Infuse AI technologies into all programs: Apply AI thinking and insights into both AI and non-AI focused programs.\n\n\u2022 Provides AI-mentorship across the studio, developing new methods and processes that can be integrated into creative and business teams processes.\n\n\u2022 Employs system-thinking and a design mindset, coupled with AI expertise, to craft frameworks that guide the creation and validation of content, with a strong emphasis on AI Experience within the Automotive and Design sectors.\n\n\u2022 High-level blending of multiple-AI tools and processes, creating unique media outputs; actively uses advanced AI tools and techniques to enhance design solutions and validate potential concepts and experiences, ensuring cutting-edge outputs.\n\n\u2022 Collaborates under the mentorship of Creative Directors and Associate Directors, typically as a vital member of a core team of designers and AI specialists.\n\n\u2022 Merges multiple viewpoints - from AI-driven design best practices to customer insights and technical capabilities - to create actionable business opportunities from design and AI insights.\n\n\u2022 Engages both internal design teams and external clients, employing AI-driven narratives that are clear and emotionally compelling to ensure buy-in.\n\n\u2022 Delivers AI-enhanced strategic content across multiple projects, ensuring that they surpass client expectations as detailed in proposals or briefings from DW Strategic Management.\n\n\u2022 Provides AI-driven insights across the full design strategy spectrum, from defining strategic AI criteria to constructing AI-powered plans which the client/design team can execute and communicate with client backing.\n\n\u2022 Uses AI analytics to measure long-term business strategy success by observing shifts in client positioning or enhancements based on our AI-driven consultation. Direct client feedback is pivotal for this assessment.\n\n\u2022 Relying on standard business metrics tailored to project briefs, and utilizing AI tools to ensure insights such as quicker innovation, accurate consumer value predictions, or operational cost reductions.\n\n\u2022 Utilizes system-thinking, expertise in AI tools, and multi-dimensional perspectives to support and develop strategic questions, ideate AI-enhanced solutions, and seamlessly integrate these solutions.\n\n\u2022 Establish a local LA / US network of experts (the home of global AI development): Benchmark and concreate, using these tools to build Designwork's AI-Design community reach.\n\n\u2022 Ethical AI Considerations: Understand and apply ethical guidelines for AI - particularly around bias, privacy, transparency, and accountability.\n\nJoin the BMW North America team and enjoy a high-performance Total Rewards package that may include:\n\nMedical, Dental, and Vision insurance.\nAll with options for $0 Employee contribution.\n401(k) with Company match.\nRetirement Income Account (RIA).\nEmployee vehicle program.\nBonus eligibility.\nPaid Parental Leave of up to 6 weeks.\nPaid Time Off in addition to Company paid holidays where eligible.\nVoluntary Benefits to fit your needs.\n\nThe pay range for this role is $99,607.25- $128,903.50.\n\nThe selected candidate's education, skills, experience, and location will be used to determine the final salary offer. This statement is in accordance with state and local pay disclosure requirements.\n\nEven more so than the generous compensation and benefits, the culture and values of BMW North America make it the ultimate working environment. These values are Responsibility, Appreciation, Transparency, Trust, and Openness. We allow these values to guide the way we conduct ourselves and our business.\n\nAt BMW, we are driven by diversity, equity, and inclusion. We are proud to be an Equal Opportunity Employer and are welcoming of all individuals, regardless of race, color, religion, sex, sexual orientation, gender identity, national origin, disability, or protected veteran status.\n\u2022 Bachelor's Degree in Automotive Design, Design Strategy, Industrial Design or related field.\n\u2022 3 to 5 years of prior work experience within the field of Design, Strategy, or related field.\n\u2022 Minimum of 4 months of extensive-experience, using these in design processes and settings\n\u2022 Strong visual, verbal and written communication skills\n\u2022 Familiar with key AI tools such as LLMs, Image Gen and Gen AI.\n\nAbout the Company:\nDesignworks, a BMW Group Company", "job_is_remote": false, "job_posted_at_timestamp": 1701734400, "job_posted_at_datetime_utc": "2023-12-05T00:00:00.000Z", "job_city": "Santa Monica", "job_state": "CA", "job_country": "US", "job_latitude": 34.019455, "job_longitude": -118.49119, "job_benefits": ["health_insurance", "dental_coverage", "paid_time_off", "retirement_savings"], "job_google_link": "https://www.google.com/search?gl=us&hl=en&rciv=jb&q=ai+specialist&start=50&ibp=htl;jobs#fpstate=tldetail&htivrt=jobs&htiq=ai+specialist&htidocid=nJyd6fQDDNCJIEZBAAAAAA%3D%3D", "job_offer_expiration_datetime_utc": null, "job_offer_expiration_timestamp": null, "job_required_experience": {"no_experience_required": false, "required_experience_in_months": 4, "experience_mentioned": true, "experience_preferred": false}, "job_required_skills": null, "job_required_education": {"postgraduate_degree": false, "professional_certification": false, "high_school": false, "associates_degree": false, "bachelors_degree": false, "degree_mentioned": true, "degree_preferred": true, "professional_certification_mentioned": false}, "job_experience_in_place_of_education": false, "job_min_salary": null, "job_max_salary": null, "job_salary_currency": null, "job_salary_period": null, "job_highlights": {"Qualifications": ["Bachelor's Degree in Automotive Design, Design Strategy, Industrial Design or related field", "3 to 5 years of prior work experience within the field of Design, Strategy, or related field", "Minimum of 4 months of extensive-experience, using these in design processes and settings", "Strong visual, verbal and written communication skills", "Familiar with key AI tools such as LLMs, Image Gen and Gen AI"], "Responsibilities": ["The specialist will craft with AI to empower creative thinking and design exploration and prototyping, to be at the forefront of transforming automotive experiences with AI-powered design, establishing Designworks as a leader and facilitator in this cutting-edge space", "Real-time learning and experimenting with AI advancements: Continually apply and experiment new AI tools, finding innovative ways to leverage them in design, aesthetics, storytelling, moviemaking, fabrication, and innovation", "Infuse AI technologies into all programs: Apply AI thinking and insights into both AI and non-AI focused programs", "Provides AI-mentorship across the studio, developing new methods and processes that can be integrated into creative and business teams processes", "Employs system-thinking and a design mindset, coupled with AI expertise, to craft frameworks that guide the creation and validation of content, with a strong emphasis on AI Experience within the Automotive and Design sectors", "High-level blending of multiple-AI tools and processes, creating unique media outputs; actively uses advanced AI tools and techniques to enhance design solutions and validate potential concepts and experiences, ensuring cutting-edge outputs", "Collaborates under the mentorship of Creative Directors and Associate Directors, typically as a vital member of a core team of designers and AI specialists", "Merges multiple viewpoints - from AI-driven design best practices to customer insights and technical capabilities - to create actionable business opportunities from design and AI insights", "Engages both internal design teams and external clients, employing AI-driven narratives that are clear and emotionally compelling to ensure buy-in", "Delivers AI-enhanced strategic content across multiple projects, ensuring that they surpass client expectations as detailed in proposals or briefings from DW Strategic Management", "Provides AI-driven insights across the full design strategy spectrum, from defining strategic AI criteria to constructing AI-powered plans which the client/design team can execute and communicate with client backing", "Uses AI analytics to measure long-term business strategy success by observing shifts in client positioning or enhancements based on our AI-driven consultation", "Direct client feedback is pivotal for this assessment", "Relying on standard business metrics tailored to project briefs, and utilizing AI tools to ensure insights such as quicker innovation, accurate consumer value predictions, or operational cost reductions", "Utilizes system-thinking, expertise in AI tools, and multi-dimensional perspectives to support and develop strategic questions, ideate AI-enhanced solutions, and seamlessly integrate these solutions", "Establish a local LA / US network of experts (the home of global AI development): Benchmark and concreate, using these tools to build Designwork's AI-Design community reach", "Ethical AI Considerations: Understand and apply ethical guidelines for AI - particularly around bias, privacy, transparency, and accountability"], "Benefits": ["Medical, Dental, and Vision insurance", "All with options for $0 Employee contribution", "401(k) with Company match", "Retirement Income Account (RIA)", "Employee vehicle program", "Bonus eligibility", "Paid Parental Leave of up to 6 weeks", "Paid Time Off in addition to Company paid holidays where eligible", "Voluntary Benefits to fit your needs", "The pay range for this role is $99,607.25- $128,903.50", "The selected candidate's education, skills, experience, and location will be used to determine the final salary offer"]}, "job_job_title": "Consultant", "job_posting_language": "en", "job_onet_soc": "15111100", "job_onet_job_zone": "5"}