{"job_id": "TBw_sfoRkFFhpicDAAAAAA==", "employer_name": "Trace3", "employer_logo": "https://encrypted-tbn0.gstatic.com/images?q=tbn:ANd9GcT7lNyAyH4eMX2gxv02_OttN4TgwjLALsTR_7FE&s=0", "employer_website": "http://www.trace3.com", "employer_company_type": null, "job_publisher": "Built In", "job_employment_type": "FULLTIME", "job_title": "Director, Data Strategy (Remote)", "job_apply_link": "https://builtin.com/job/director-data-strategy-remote/2183843", "job_apply_is_direct": false, "job_apply_quality_score": 0.7984, "apply_options": [{"publisher": "Built In", "apply_link": "https://builtin.com/job/director-data-strategy-remote/2183843", "is_direct": false}], "job_description": "Who is Trace3?\n\nTrace3 is a leading Transformative IT Authority, providing unique technology solutions and consulting services to our clients. Equipped with elite engineering and dynamic innovation, we empower IT executives and their organizations to achieve competitive advantage through a process of Integrate, Automate, Innovate.\n\nOur culture at Trace3 embodies the spirit of a startup with the advantage of a scalable business. Employees can grow their career and have fun while doing it!\n\nTrace3 is headquartered in Irvine, California. We employ more than 1,200 people all over the United States. Our major field office locations include Denver, Indianapolis, Grand Rapids, Lexington, Los Angeles, Louisville, Texas, San Francisco.\n\nReady to discover the possibilities that live in technology?\n\nCome Join Us!\n\nStreet-Smart - Thriving in Dynamic Times\n\nWe are flexible and resilient in a fast-changing environment. We continuously innovate and drive constructive change while keeping a focus on the \u201cbig picture.\u201d We exercise sound business judgment in making high-quality decisions in a timely and cost-effective manner. We are highly creative and can dig deep within ourselves to find positive solutions to different problems.\n\nJuice - The \u201cStuff\u201d it takes to be a Needle Mover\n\nWe get things done and drive results. We lead without a title, empowering others through a can-do attitude. We look forward to the goal, mentally mapping out every checkpoint on the pathway to success, and visualizing what the final destination looks and feels like.\n\nTeamwork - Humble, Hungry and Smart\n\nWe are humble individuals who understand how our job impacts the company's mission. We treat others with respect, admit mistakes, give credit where it\u2019s due and demonstrate transparency. We \u201cbring the weather\u201d by exhibiting positive leadership and solution-focused thinking. We hug people in their trials, struggles, and failures \u2013 not just their success. We appreciate the individuality of the people around us.\n\nAbout the Role:\n\nWe are seeking a strategic and visionary Director of Data Strategy to lead and expand our Data Strategy consulting practice. This role is pivotal in developing data-driven strategies, guiding our clients through their data transformation journey, and ensuring the alignment of these strategies with execution capabilities. The Director of Data Strategy will report to the Vice President, Data and Analytics.\n\nWhat You\u2019ll Do:\n\u2022 Strategic Leadership: Develop comprehensive data strategies in alignment with client objectives and business goals.\n\u2022 Team Development: Build, mentor, and manage a team of data strategy experts to foster innovation and expertise.\n\u2022 Client Engagement: Provide expert data governance, quality management, and analytics consultation.\n\u2022 Focus on Key Data Strategy Areas:\n\u2022 Data Governance and Compliance: Develop policies and procedures for data management in compliance with legal and regulatory requirements.\n\u2022 Data Quality Management: Implement processes for data quality improvement and monitoring.\n\u2022 Data Architecture and Integration: Design data architectures that support diverse data sources and types, emphasizing scalability and flexibility.\n\u2022 Advanced Analytics and Business Intelligence: Leverage data analytics, machine learning, and AI for actionable insights.\n\u2022 Data Literacy and Culture: Promote a data-driven culture and enhance data literacy across the organization.\n\u2022 Innovation in Data Technologies: Stay updated on emerging data technologies and trends.\n\u2022 Data Democratization: Ensure accessibility of data and insights for informed decision-making.\n\u2022 Ethical AI and Responsible Data Use: Implement ethical AI guidelines and practices.\n\u2022 Sustainable Data Practices: Incorporate eco-friendly data storage and processing methods.\n\u2022 Data Monetization: Identify opportunities for data asset monetization and value creation.\n\u2022 Collaborative Execution: Work closely with other Trace3 business units to ensure seamless execution of strategies.\n\nQualifications & Interests:\n\u2022 Experience: A minimum of 10 years of leadership experience in data strategy at a major consulting firm or Fortune 500 company.\n\u2022 Education: Bachelor\u2019s or Master\u2019s degree in Data Science, Computer Science, Business, or a related field.\n\u2022 Skills: Exceptional leadership, strategic thinking, and communication skills. Proficient in the latest data technologies and trends.\n\u2022 Technical Expertise: In-depth understanding of data governance, quality management, architecture, analytics, literacy, emerging technologies, democratization, ethical AI, sustainability, and monetization.\n\nDesirable Qualities:\n\u2022 Innovative Thinking: Ability to envision and implement novel data solutions\n\u2022 Adaptability: Comfortable in a rapidly changing environment\n\u2022 Client-Centric Approach: Strong focus on understanding and meeting client needs\n\u2022 Ethical Responsibility: Commitment to ethical data practices and sustainable solutions\n\nThe Perks:\n\u2022 Comprehensive medical, dental and vision plans for you and your dependents\n\u2022 401(k) Retirement Plan with Employer Match, 529 College Savings Plan, Health Savings Account, Life Insurance, and Long-Term Disability\n\u2022 Competitive Compensation\n\u2022 Training and development programs\n\u2022 Stocked kitchen with snacks and beverages\n\u2022 Collaborative and cool culture\n\u2022 Work-life balance and generous paid time off\n\u2022 **To all recruitment agencies: Trace3 does not accept unsolicited agency resumes/CVs. Please do not forward resumes/CVs to our careers email addresses, Trace3 employees or any other company location. Trace3 is not responsible for any fees related to unsolicited resumes/CVs.\n\nActual salary will be based on a variety of factors, including location, experience, skill set, performance, licensure and certification, and business needs. The range for this position in other geographic locations may differ. Certain positions may also be eligible for variable incentive compensation, such as bonuses or commissions, that is not included in the base salary.\n\nEstimated Pay Range\n\n$163,200\u2014$220,800 USD", "job_is_remote": false, "job_posted_at_timestamp": 1709471940, "job_posted_at_datetime_utc": "2024-03-03T13:19:00.000Z", "job_city": null, "job_state": "TX", "job_country": "US", "job_latitude": 32.707874, "job_longitude": -96.92091, "job_benefits": ["retirement_savings", "dental_coverage", "health_insurance", "paid_time_off"], "job_google_link": "https://www.google.com/search?gl=us&hl=en&rciv=jb&q=director+of+advanced+analytics&start=40&ibp=htl;jobs#fpstate=tldetail&htivrt=jobs&htiq=director+of+advanced+analytics&htidocid=TBw_sfoRkFFhpicDAAAAAA%3D%3D", "job_offer_expiration_datetime_utc": "2024-04-02T00:00:00.000Z", "job_offer_expiration_timestamp": 1712016000, "job_required_experience": {"no_experience_required": false, "required_experience_in_months": 120, "experience_mentioned": true, "experience_preferred": false}, "job_required_skills": null, "job_required_education": {"postgraduate_degree": false, "professional_certification": false, "high_school": false, "associates_degree": false, "bachelors_degree": true, "degree_mentioned": true, "degree_preferred": true, "professional_certification_mentioned": true}, "job_experience_in_place_of_education": false, "job_min_salary": 163200, "job_max_salary": 220800, "job_salary_currency": "USD", "job_salary_period": "YEAR", "job_highlights": {"Qualifications": ["Experience: A minimum of 10 years of leadership experience in data strategy at a major consulting firm or Fortune 500 company", "Education: Bachelor\u2019s or Master\u2019s degree in Data Science, Computer Science, Business, or a related field", "Skills: Exceptional leadership, strategic thinking, and communication skills", "Proficient in the latest data technologies and trends", "Technical Expertise: In-depth understanding of data governance, quality management, architecture, analytics, literacy, emerging technologies, democratization, ethical AI, sustainability, and monetization", "Innovative Thinking: Ability to envision and implement novel data solutions", "Adaptability: Comfortable in a rapidly changing environment", "Client-Centric Approach: Strong focus on understanding and meeting client needs", "Ethical Responsibility: Commitment to ethical data practices and sustainable solutions"], "Responsibilities": ["We are seeking a strategic and visionary Director of Data Strategy to lead and expand our Data Strategy consulting practice", "This role is pivotal in developing data-driven strategies, guiding our clients through their data transformation journey, and ensuring the alignment of these strategies with execution capabilities", "The Director of Data Strategy will report to the Vice President, Data and Analytics", "Strategic Leadership: Develop comprehensive data strategies in alignment with client objectives and business goals", "Team Development: Build, mentor, and manage a team of data strategy experts to foster innovation and expertise", "Client Engagement: Provide expert data governance, quality management, and analytics consultation", "Focus on Key Data Strategy Areas:", "Data Governance and Compliance: Develop policies and procedures for data management in compliance with legal and regulatory requirements", "Data Quality Management: Implement processes for data quality improvement and monitoring", "Data Architecture and Integration: Design data architectures that support diverse data sources and types, emphasizing scalability and flexibility", "Advanced Analytics and Business Intelligence: Leverage data analytics, machine learning, and AI for actionable insights", "Data Literacy and Culture: Promote a data-driven culture and enhance data literacy across the organization", "Innovation in Data Technologies: Stay updated on emerging data technologies and trends", "Data Democratization: Ensure accessibility of data and insights for informed decision-making", "Ethical AI and Responsible Data Use: Implement ethical AI guidelines and practices", "Sustainable Data Practices: Incorporate eco-friendly data storage and processing methods", "Data Monetization: Identify opportunities for data asset monetization and value creation", "Collaborative Execution: Work closely with other Trace3 business units to ensure seamless execution of strategies"], "Benefits": ["Comprehensive medical, dental and vision plans for you and your dependents", "401(k) Retirement Plan with Employer Match, 529 College Savings Plan, Health Savings Account, Life Insurance, and Long-Term Disability", "Competitive Compensation", "Training and development programs", "Stocked kitchen with snacks and beverages", "Collaborative and cool culture", "Work-life balance and generous paid time off", "**To all recruitment agencies: Trace3 does not accept unsolicited agency resumes/CVs", "Certain positions may also be eligible for variable incentive compensation, such as bonuses or commissions, that is not included in the base salary", "$163,200\u2014$220,800 USD"]}, "job_job_title": "Director", "job_posting_language": "en", "job_onet_soc": "43911100", "job_onet_job_zone": "4"}