{"job_id": "WY-yulHa9svIwRmUAAAAAA==", "employer_name": "StackCommerce", "employer_logo": "https://cdnp0.stackassets.com/a3c277997d108b87ef125bea3ae70e8b48766ff1/store/e85890a11ca444bed8792c60bd9ddef9aa34dc9b26f9fabb4714c6a41a0b/StackSocial_2023_Logomark_Black_Knockout.svg", "employer_website": "http://www.stackcommerce.com", "employer_company_type": null, "job_publisher": "Salary.com", "job_employment_type": "FULLTIME", "job_title": "Manager, Brand Partnerships", "job_apply_link": "https://www.salary.com/job/stackcommerce/manager-brand-partnerships/j202310182342564152079", "job_apply_is_direct": false, "job_apply_quality_score": 0.6301, "apply_options": [{"publisher": "Salary.com", "apply_link": "https://www.salary.com/job/stackcommerce/manager-brand-partnerships/j202310182342564152079", "is_direct": false}], "job_description": "Who We Are:\n\nBrandCycle Inc. is a premium publisher network that represents more than 5,000 bloggers, content creators and social media influencers who use short-form content and strategic deals to convert today\u2019s shoppers. Our proprietary technology delivers exclusive affiliate and paid campaigns to publishers in a streamlined, easy-to-use way. BrandCycle is integrated with 600 of the top brand affiliate programs, including Coach, Kate Spade, Nordstrom, Target, Converse, Crocs and Michael Kors. In December 2021, BrandCycle was acquired by StackCommerce, the leader in commerce content for publishers.\n\nThe Role:\n\nBrandCycle is looking to hire a Manager of Brand Partnerships for a 100% remote position. This role works closely with the Brand team to foster and grow retailer opportunities for our affiliate community. This individual will be a key point person in all brand-related business decisions. This is a great opportunity to get in with a fast-growing team at a pivotal time in the company\u2019s growth.\n\nWhat You'll Do:\n\u2022 Brand Management: Actively manage large-scale affiliate brand relationships. Act as day-to-day point person as well as strategic lead on growing brands\u2019 sales revenue with BrandCycle\u2019s affiliate and influencer network.\n\u2022 Brand Investments: Work with brand team members to secure commission increases, paid placement fees and influencer campaigns from brands, aligned with company-wide and individual growth goals. Provide end-to-end management of secured investments.\n\u2022 Brand Campaigns: Liaison with internal influencer and marketing teams to schedule and execute brand campaigns. Overseeing timing, message and quality of all brand merchandising. Merchandising channels include email, social media, on-site, network and mobile notifications.\n\u2022 Brand Reporting: Work with data team to package and communicate campaign deliverables and results back to brands, securing recurring investments when appropriate.\n\u2022 Thought Leadership: Opportunities to engage in strategic planning, including rate changes, merchandising expansions, editorial calendar building and new revenue channel drivers.\n\nThe Ideal Candidate Is:\n\u2022 A Proven Leader\n\u2022 Highly entrepreneurial and has experience leading a sales and account team.\n\u2022 Highly effective at communicating with team members in a remote environment and is comfortable working independently with minimal supervision.\n\u2022 Thrives in a fast-paced company environment and enjoys wearing many hats.\n\u2022 Possesses mature and measured judgment, and the ability to proactively solve problems on their own.\n\u2022 A Go-Getter\n\u2022 Has a naturally competitive mindset and is motivated by securing new business.\n\u2022 Thrives on being able to create win/win scenarios for our brand and influencer communities.\n\u2022 An excellent communicator who is energetic and can easily deal with new or difficult situations.\n\u2022 Has a proven track record of developing and managing relationships with key stakeholders.\n\u2022 A self-starter who can independently manage relationships end-to-end with very little oversight.\n\u2022 Goals Driven\n\u2022 Deadline driven and operates well under pressure.\n\u2022 Highly analytical and enjoys the challenge of reaching and exceeding revenue goals.\n\u2022 Understands KPIs and other key business metrics to measure success.\n\u2022 Has the ability to continually identify new opportunities and connect with new brands.\n\u2022 A Fast-Learner\n\u2022 Interested in the digital marketing space e-commerce space and up-to-speed on the latest trends.\n\u2022 Comfortable with and thrives using new and emerging technology and media channels.\n\nWhat You'll Bring:\n\u2022 Minimum of 3 years of experience in affiliate marketing\n\u2022 Knowledge of affiliate networks and SaaS platforms (Impact, Commission Junction, ShareASale, Awin, Rakuten, Tune, etc.)\n\u2022 Minimum of 1 year of sales experience\n\u2022 Strong track record of building and cultivating relationships with affiliate brand managers. Has an existing rolodex of relationships, a big plus\n\u2022 Is comfortable with new and emerging digital platforms and tools\n\u2022 Highly proficient at Microsoft Excel and PowerPoint\n\u2022 Proven excellence in exceeding revenue goals\n\u2022 Strong written and verbal communication and presentation skills\n\u2022 Experience with Mailchimp, a plus\n\u2022 Bachelor\u2019s degree required\n\nWhat to Expect:\n\u2022 Intro Call: You\u2019ll hop on a quick call with the hiring manager so we can get to know you better \u2014 and you can learn a little more about the role.\n\u2022 Remote-Team Interview: You\u2019ll be meeting with 2-3 team members on a video call. This is your chance to ask questions and see who this role interacts with on a daily basis.\n\u2022 Final Video Call: This is a great opportunity to get to know one of our senior executives over video.\n\u2022 Offer: We send over an offer and you (hopefully) accept! Welcome to Stack!\n\nCompensation:\n\nOur overall compensation and rewards package includes base pay, bonus or commission, and a variety of benefits. Base pay is determined within a range that allows you the opportunity to progress as you grow and develop within a role. The anticipated annualized salary range for this role is $70,300 - $95,100 (this range may be modified in the future based on changing market conditions). Your initial base pay will be determined based on several factors, including demonstrated skills, relevant education or training, experience, qualifications, travel requirements, and job location.\n\nBenefits Perks:\n\nAs a company, we have a lot to offer for the right candidate:\n\u2022 Health Benefits: We offer medical, dental, vision, life, and short-term and long-term disability insurance.\n\u2022 401K: Eligible on your first day of employment.\n\u2022 Super Flex Time: Run errands as needed, just get your stuff done.\n\u2022 Unlimited Vacation: Take time to unwind with unlimited PTO, plus an office closure between Christmas and New Year\u2019s.\n\u2022 Generous Parental Leave Program: 12 weeks of paid pregnancy disability and baby bonding leave, as well as 4 weeks of paid paternity leave that must be taken within the first six months of the birth.\n\u2022 Learning Budget: Dollars towards eLearning courses, eBooks, and more.\n\u2022 WFH Office: Home office stipend and internet dollars to set you up for success.\n\u2022 Events: Happy hours, team bonding budgets and culture events (even while remote!) and an annual company offsite.\n\nStack Highlights:\n\nBy the numbers...\n\u2022 We\u2019ve paid our publisher and merchant partners $150 million and counting!\n\u2022 We\u2019ve been a profitable business from day 1.\n\u2022 We work with 1k media publishers including Mashable, TMZ, CNN, NY Post, & others.\n\u2022 We\u2019ve been a \u2018BuiltinLA Best Place to Work in LA\u2019 for 2 years straight.\n\u2022 We\u2019re currently a fully-remote team with 110 teammates. Are you next?\n\nStackCommerce values a diverse workplace and strongly encourages people of color, LGBTQIA , GNC, and NB individuals, people with disabilities, members of ethnic minorities, foreign-born residents, and veterans to apply. We respect and seek to empower each individual and support diverse cultures, perspectives, skills, and experiences within our workforce.\n\nStackCommerce is an equal opportunity employer. Applicants will not be discriminated against because of race, color, creed, sex, sexual orientation, gender identity or expression, age, religion, national origin, citizenship status, disability, ancestry, marital status, veteran status, medical condition, or any protected category prohibited by local, state or federal laws.", "job_is_remote": true, "job_posted_at_timestamp": 1709510400, "job_posted_at_datetime_utc": "2024-03-04T00:00:00.000Z", "job_city": "Ventura", "job_state": "CA", "job_country": "US", "job_latitude": 34.28049, "job_longitude": -119.29452, "job_benefits": ["retirement_savings", "health_insurance", "paid_time_off", "dental_coverage"], "job_google_link": "https://www.google.com/search?gl=us&hl=en&rciv=jb&q=director+of+brand+partnerships&start=50&ibp=htl;jobs#fpstate=tldetail&htivrt=jobs&htiq=director+of+brand+partnerships&htidocid=WY-yulHa9svIwRmUAAAAAA%3D%3D", "job_offer_expiration_datetime_utc": "2024-04-18T00:00:00.000Z", "job_offer_expiration_timestamp": 1713398400, "job_required_experience": {"no_experience_required": false, "required_experience_in_months": 36, "experience_mentioned": true, "experience_preferred": true}, "job_required_skills": null, "job_required_education": {"postgraduate_degree": false, "professional_certification": false, "high_school": false, "associates_degree": false, "bachelors_degree": false, "degree_mentioned": true, "degree_preferred": false, "professional_certification_mentioned": false}, "job_experience_in_place_of_education": false, "job_min_salary": null, "job_max_salary": null, "job_salary_currency": null, "job_salary_period": null, "job_highlights": {"Qualifications": ["A Proven Leader", "Highly entrepreneurial and has experience leading a sales and account team", "Highly effective at communicating with team members in a remote environment and is comfortable working independently with minimal supervision", "Thrives in a fast-paced company environment and enjoys wearing many hats", "Possesses mature and measured judgment, and the ability to proactively solve problems on their own", "A Go-Getter", "Has a naturally competitive mindset and is motivated by securing new business", "An excellent communicator who is energetic and can easily deal with new or difficult situations", "Has a proven track record of developing and managing relationships with key stakeholders", "A self-starter who can independently manage relationships end-to-end with very little oversight", "Deadline driven and operates well under pressure", "Highly analytical and enjoys the challenge of reaching and exceeding revenue goals", "Understands KPIs and other key business metrics to measure success", "A Fast-Learner", "Interested in the digital marketing space e-commerce space and up-to-speed on the latest trends", "Minimum of 3 years of experience in affiliate marketing", "Knowledge of affiliate networks and SaaS platforms (Impact, Commission Junction, ShareASale, Awin, Rakuten, Tune, etc.)", "Minimum of 1 year of sales experience", "Strong track record of building and cultivating relationships with affiliate brand managers", "Has an existing rolodex of relationships, a big plus", "Is comfortable with new and emerging digital platforms and tools", "Highly proficient at Microsoft Excel and PowerPoint", "Proven excellence in exceeding revenue goals", "Strong written and verbal communication and presentation skills", "Bachelor\u2019s degree required"], "Responsibilities": ["Brand Management: Actively manage large-scale affiliate brand relationships", "Act as day-to-day point person as well as strategic lead on growing brands\u2019 sales revenue with BrandCycle\u2019s affiliate and influencer network", "Brand Investments: Work with brand team members to secure commission increases, paid placement fees and influencer campaigns from brands, aligned with company-wide and individual growth goals", "Provide end-to-end management of secured investments", "Brand Campaigns: Liaison with internal influencer and marketing teams to schedule and execute brand campaigns", "Overseeing timing, message and quality of all brand merchandising", "Merchandising channels include email, social media, on-site, network and mobile notifications", "Brand Reporting: Work with data team to package and communicate campaign deliverables and results back to brands, securing recurring investments when appropriate", "Thought Leadership: Opportunities to engage in strategic planning, including rate changes, merchandising expansions, editorial calendar building and new revenue channel drivers", "This is your chance to ask questions and see who this role interacts with on a daily basis"], "Benefits": ["Our overall compensation and rewards package includes base pay, bonus or commission, and a variety of benefits", "Base pay is determined within a range that allows you the opportunity to progress as you grow and develop within a role", "The anticipated annualized salary range for this role is $70,300 - $95,100 (this range may be modified in the future based on changing market conditions)", "Your initial base pay will be determined based on several factors, including demonstrated skills, relevant education or training, experience, qualifications, travel requirements, and job location", "Health Benefits: We offer medical, dental, vision, life, and short-term and long-term disability insurance", "401K: Eligible on your first day of employment", "Super Flex Time: Run errands as needed, just get your stuff done", "Unlimited Vacation: Take time to unwind with unlimited PTO, plus an office closure between Christmas and New Year\u2019s", "Generous Parental Leave Program: 12 weeks of paid pregnancy disability and baby bonding leave, as well as 4 weeks of paid paternity leave that must be taken within the first six months of the birth", "Learning Budget: Dollars towards eLearning courses, eBooks, and more", "WFH Office: Home office stipend and internet dollars to set you up for success", "Events: Happy hours, team bonding budgets and culture events (even while remote!) and an annual company offsite"]}, "job_job_title": "Manager", "job_posting_language": "en", "job_onet_soc": "11202100", "job_onet_job_zone": "4"}