{"job_id": "PjRV0c8bTgnVpKXwAAAAAA==", "employer_name": "VolunteerMatch", "employer_logo": "https://upload.wikimedia.org/wikipedia/commons/e/ea/VolunteerMatch_official.png", "employer_website": "http://www.volunteermatch.org", "employer_company_type": "Information", "job_publisher": "LinkedIn", "job_employment_type": "VOLUNTEER", "job_title": "Volunteer: Sponsorship and Exhibit Sales Coordinator (paid position)", "job_apply_link": "https://www.linkedin.com/jobs/view/volunteer-sponsorship-and-exhibit-sales-coordinator-paid-position-at-volunteermatch-3803990546", "job_apply_is_direct": false, "job_apply_quality_score": 0.6487, "apply_options": [{"publisher": "LinkedIn", "apply_link": "https://www.linkedin.com/jobs/view/volunteer-sponsorship-and-exhibit-sales-coordinator-paid-position-at-volunteermatch-3803990546", "is_direct": false}], "job_description": "Your Hearing Dog is a Colorado-based nonprofit organization that is dedicated to providing support and assistance to the deaf and hard-of-hearing community.\n\nOur five (5) year plan includes the following\n\u2022 Identifying Hearing Dogs - YHD collaborates with a local shelter in Colorado to screen dogs for suitability to be trained as service dogs for the deaf and hard of hearing community.\n\u2022 Matching Program - YHD matches suitable dogs with eligible owners through an application process and needs assessment.\n\u2022 Training - The standard training for YHD service dogs involves two parts - the first part is to teach the service dogs a set of tasks to assist people who are deaf and hard-of-hearing while the second part involves a personalized bootcamp between the dog and the matched owner.\n\u2022 Help desk - YHD provides ongoing support through a phoneline and email, with potential for a virtual assistant on their website.\n\u2022 Meetups - YHD creates both in-person and online communities for support and annual events for successful matches to gather and provide feedback for improvement.\n\u2022 Museum - As part of our five-year plan, we intend to establish a museum showcasing the historical journey of prominent individuals who are deaf and hard-of-hearing.\n\nJOB TITLE Sponsorship and Exhibit Sales Coordinator\n\nSHIFT Fx (s )\n\nLOCATION V O\n\nREPORTS TO B Ds\n\nSTART DATE As s s ss\n\nTO APPLY Ps s V M\n\nSummary\n\nThe Sponsorship and Exhibit Sales Coordinator is responsible for raising money through the\n\nsale of sponsorship and exhibit packages for our nonprofit by targeting various companies, organizations\n\nand associations. The Coordinator creates sponsorship and exhibitor packages according to client\n\nspecification. The Coordinator attends weekly company meetings, sales update meetings and conference\n\nplanning meetings as required.\n\nESSENTIAL DUTIES AND RESPONSIBILITIES (other Duties May Be Assigned)\n\u2022 Utilize telephone solicitation, electronic and written correspondence and face-to-face meetings as tools in order to reach and exceed the budgeted sponsorship target;\n\u2022 Research and develop a list of potential sponsors for our nonprofit;\n\u2022 Research and develop a list of potential exhibitors for events when required;\n\u2022 Develop and maintain relationships with existing and potential sponsorship clients and\n\nexhibitors;\n\u2022 Keep precise records of conversations with all clients, sponsors and exhibitors;\n\u2022 Update the organization's database as required;\n\u2022 Assist in preparing promotional material to advertise sales/sponsorship opportunities;\n\u2022 Maintain knowledge of conference timelines and sponsorship deadlines;\n\u2022 Meet with trade and professional organizations and other groups to organize, promote and\n\ndiscuss YHD services, events and programs; and\n\u2022 Professionally represent YHD at all times.\n\nQualification Requirements\n\nTo perform this job successfully, an individual must be able to perform each essential duty\n\nsatisfactorily. Reasonable accommodations may be made to enable individuals with disabilities to perform the essential functions. General qualification requirements include having the ability to\n\u2022 communicate customer needs and resolve issues independently.\n\u2022 establish and master goals.\n\u2022 identify and develop accounts.\n\u2022 act independently with minimal or no supervision.\n\nEducation And/Or Experience\n\nAssociates degree and/or prior experience in sales. A reasonable combination of education and experience will also be considered. We will also train the right candidate.\n\nOther Skills And Abilities\n\nThis position is suited to a self-motivated, professional person who can confidently work with a variety\n\nof people from different cultures and backgrounds. Diplomacy, tact and a sense of humor are\n\nimportant to the success of this person.\n\nCompensation\n\nThis position is commission based. The Coordinator will receive up to 25% of total sponsorship/sales that he/she is responsible for closing. As our organization grows, other sales people will be hired and the Coordinator will receive compensation on their sales.\n\nThis is a volunteer opportunity provided by VolunteerMatch, in partnership with LinkedIn for Good.", "job_is_remote": false, "job_posted_at_timestamp": 1708992831, "job_posted_at_datetime_utc": "2024-02-27T00:13:51.000Z", "job_city": "Pueblo West", "job_state": "CO", "job_country": "US", "job_latitude": 38.350002, "job_longitude": -104.722755, "job_benefits": null, "job_google_link": "https://www.google.com/search?gl=us&hl=en&rciv=jb&q=sponsorship+senior+sales+manager&start=40&ibp=htl;jobs#fpstate=tldetail&htivrt=jobs&htiq=sponsorship+senior+sales+manager&htidocid=PjRV0c8bTgnVpKXwAAAAAA%3D%3D", "job_offer_expiration_datetime_utc": "2024-04-08T14:30:44.000Z", "job_offer_expiration_timestamp": 1712586644, "job_required_experience": {"no_experience_required": false, "required_experience_in_months": null, "experience_mentioned": true, "experience_preferred": false}, "job_required_skills": null, "job_required_education": {"postgraduate_degree": false, "professional_certification": false, "high_school": false, "associates_degree": true, "bachelors_degree": false, "degree_mentioned": true, "degree_preferred": false, "professional_certification_mentioned": false}, "job_experience_in_place_of_education": false, "job_min_salary": null, "job_max_salary": null, "job_salary_currency": null, "job_salary_period": null, "job_highlights": {"Qualifications": ["To perform this job successfully, an individual must be able to perform each essential duty", "communicate customer needs and resolve issues independently", "identify and develop accounts", "act independently with minimal or no supervision", "Associates degree and/or prior experience in sales", "A reasonable combination of education and experience will also be considered", "This position is suited to a self-motivated, professional person who can confidently work with a variety", "Diplomacy, tact and a sense of humor are", "important to the success of this person"], "Responsibilities": ["The Sponsorship and Exhibit Sales Coordinator is responsible for raising money through the", "sale of sponsorship and exhibit packages for our nonprofit by targeting various companies, organizations", "The Coordinator creates sponsorship and exhibitor packages according to client", "The Coordinator attends weekly company meetings, sales update meetings and conference", "planning meetings as required", "ESSENTIAL DUTIES AND RESPONSIBILITIES (other Duties May Be Assigned)", "Utilize telephone solicitation, electronic and written correspondence and face-to-face meetings as tools in order to reach and exceed the budgeted sponsorship target;", "Research and develop a list of potential sponsors for our nonprofit;", "Research and develop a list of potential exhibitors for events when required;", "Develop and maintain relationships with existing and potential sponsorship clients and", "Keep precise records of conversations with all clients, sponsors and exhibitors;", "Update the organization's database as required;", "Assist in preparing promotional material to advertise sales/sponsorship opportunities;", "Maintain knowledge of conference timelines and sponsorship deadlines;", "Meet with trade and professional organizations and other groups to organize, promote and", "discuss YHD services, events and programs; and", "Professionally represent YHD at all times"], "Benefits": ["This position is commission based"]}, "job_job_title": "Volunteer", "job_posting_language": "en", "job_onet_soc": "25401300", "job_onet_job_zone": "4", "job_naics_code": "519130", "job_naics_name": "Internet Publishing and Broadcasting and Web Search Portals"}