{"job_id": "Ff9V-4leZdatEaZdAAAAAA==", "employer_name": "BIC Recruiting", "employer_logo": null, "employer_website": null, "employer_company_type": null, "job_publisher": "Jooble", "job_employment_type": "FULLTIME", "job_title": "Director of Business Development", "job_apply_link": "https://jooble.org/jdp/-7616166922657388326", "job_apply_is_direct": false, "job_apply_quality_score": 0.6504, "apply_options": [{"publisher": "Jooble", "apply_link": "https://jooble.org/jdp/-7616166922657388326", "is_direct": false}, {"publisher": "CareerBuilder", "apply_link": "https://www.careerbuilder.com/job/J3Q34C6K75WFGRPCZ1Y", "is_direct": false}, {"publisher": "Learn4Good", "apply_link": "https://www.learn4good.com/jobs/houston/texas/business/2970456759/e/", "is_direct": false}, {"publisher": "Jobrapido.com", "apply_link": "https://us.jobrapido.com/jobpreview/3154801200", "is_direct": false}, {"publisher": "Hughkayers.com", "apply_link": "https://hughkayers.com/job-listing/job/director-of-business-development-at-bic-recruiting-houston-tx-bUFlVnJ5YUxYSXhheXpOZU9IQzNTSC9namc9PQ==", "is_direct": false}], "job_description": "COMPANY OVERVIEW: A Leader in industrial construction and mechanical services.\n\nPOSITION TITLE: Director of Business Development\n\nCOMPENSATION: Competitive Salary + DOE + Bonus\n\nBENEFITS: Standard package\n\nLOCATION: Houston, Texas\n\nSUMMARY: Plans, organizes, coordinates, and directs the operations and programs of all business development of the company divisions.\n\nDUTIES OR RESPONSIBILITIES:\n\nMake presentations to clients regarding the company\u2019s capabilities and differentiators.\nManage and grow key client relationships through routine business meetings and approved entertainment events.\nDevelop and implement written strategic account plans and advanced sales strategies\nIdentify contacts in client accounts that can help the company develop a picture of a 3-5 year look- ahead for turnarounds and projects for that client\nCoordinate other company resources (marketing, operations administrative) in pursuit of new client\u2019s business.\nSecure strategic agreements with priority target clients\nAnalyzing market pricing and determining a fair and reasonable service selling price that is competitive.\nCoordinate bid and proposal activity in assigned accounts, including pre-qualification forms,\nRequests for Information and Requests for Proposals (RFIs and RFPs)\nParticipate in industry trade shows and technical conferences as required.\nMaintain familiarity and knowledge of key company service and technology, strategic initiatives, safety and operations programs and business development practices and procedures\nParticipate in the constant branding of company through the proper use of logo, tag line and other marketing tools.\nCall on other prospects (engineering firms, other owners) to identify collaborative work opportunities.\nWhen visiting jobs/projects, be seen at the safety meetings to make the company\u2019s commitment to safety clearly known.\nConduct post-project safety, quality, performance and client satisfaction reviews\nMeet or exceed budgeted revenue in assigned or target client accounts including P&L Management\nDevelop scopes of work with schedule & budget\nCoordinate efforts with VP of Construction, VP of Turnarounds and Specialty Services and President\nMake presentations to company Board of Directors and Sr. Management\nComply with and abide by all the company\u2019s regulations, policies, work procedures, and instructions.\nAssist in hiring, developing, mentoring, and establishing office guidelines and procedures.\nWorking knowledge of maintenance projects, capital projects, and turnarounds.\n\nEXPERIENCE AND QUALIFICATIONS:\n\n10+ years of experience in sales team management, corporate account management and budgeting\nContacts in industrial construction are a must.\nBS degree strongly preferred.\nWorking knowledge of maintenance projects and turnarounds, and pipe fabrication.\nMust have a successful track record of exceeding sales goals and meeting quotas and setting qualified appointments with C-level executives.\nMust have strong book of contacts in Refining and Petrochem industries and must possess solid understanding of the market to educate company operations and marketing personnel.\nDemonstrate leadership qualities and possess strong organizational skills.\nAbility to think strategically based on knowledge of client\u2019s business.\nExcellent verbal and written communication skills\nProven experience in selling and generating business at executive level.\nProven success in acquiring new accounts (including cold calling) and expanding existing accounts.\nDemonstrated ability to build trusting relationships with all levels of client organizations from executive to field level.\nStrong personal initiative and drive for results, with proven program execution skills\nCreative problem-solving skills.\nPersonal qualities required that include the company\u2019s core values, self-confidence and ability to work in a team environment\n\u2022 **PLEASE NOTE: We try to respond to everyone who applies for our jobs, but in periods of high activity it may not be possible. We hope we can personally help you find your new job and wish you success in your job search. For more information, please email Toni Rosario at View email address on career.staffingsoft.com.", "job_is_remote": false, "job_posted_at_timestamp": 1705881600, "job_posted_at_datetime_utc": "2024-01-22T00:00:00.000Z", "job_city": "Houston", "job_state": "TX", "job_country": "US", "job_latitude": 29.760427, "job_longitude": -95.369804, "job_benefits": null, "job_google_link": "https://www.google.com/search?gl=us&hl=en&rciv=jb&q=director+of+business+development&start=40&ibp=htl;jobs#fpstate=tldetail&htivrt=jobs&htiq=director+of+business+development&htidocid=Ff9V-4leZdatEaZdAAAAAA%3D%3D", "job_offer_expiration_datetime_utc": "2024-04-11T03:31:56.000Z", "job_offer_expiration_timestamp": 1712806316, "job_required_experience": {"no_experience_required": false, "required_experience_in_months": null, "experience_mentioned": true, "experience_preferred": false}, "job_required_skills": null, "job_required_education": {"postgraduate_degree": false, "professional_certification": false, "high_school": false, "associates_degree": false, "bachelors_degree": false, "degree_mentioned": true, "degree_preferred": true, "professional_certification_mentioned": false}, "job_experience_in_place_of_education": false, "job_min_salary": null, "job_max_salary": null, "job_salary_currency": null, "job_salary_period": null, "job_highlights": {"Qualifications": ["10+ years of experience in sales team management, corporate account management and budgeting", "Contacts in industrial construction are a must", "Working knowledge of maintenance projects and turnarounds, and pipe fabrication", "Must have a successful track record of exceeding sales goals and meeting quotas and setting qualified appointments with C-level executives", "Must have strong book of contacts in Refining and Petrochem industries and must possess solid understanding of the market to educate company operations and marketing personnel", "Demonstrate leadership qualities and possess strong organizational skills", "Ability to think strategically based on knowledge of client\u2019s business", "Excellent verbal and written communication skills", "Proven experience in selling and generating business at executive level", "Proven success in acquiring new accounts (including cold calling) and expanding existing accounts", "Demonstrated ability to build trusting relationships with all levels of client organizations from executive to field level", "Strong personal initiative and drive for results, with proven program execution skills", "Creative problem-solving skills", "Personal qualities required that include the company\u2019s core values, self-confidence and ability to work in a team environment"], "Responsibilities": ["SUMMARY: Plans, organizes, coordinates, and directs the operations and programs of all business development of the company divisions", "Make presentations to clients regarding the company\u2019s capabilities and differentiators", "Manage and grow key client relationships through routine business meetings and approved entertainment events", "Develop and implement written strategic account plans and advanced sales strategies", "Identify contacts in client accounts that can help the company develop a picture of a 3-5 year look- ahead for turnarounds and projects for that client", "Coordinate other company resources (marketing, operations administrative) in pursuit of new client\u2019s business", "Secure strategic agreements with priority target clients", "Analyzing market pricing and determining a fair and reasonable service selling price that is competitive", "Coordinate bid and proposal activity in assigned accounts, including pre-qualification forms,", "Requests for Information and Requests for Proposals (RFIs and RFPs)", "Participate in industry trade shows and technical conferences as required", "Maintain familiarity and knowledge of key company service and technology, strategic initiatives, safety and operations programs and business development practices and procedures", "Participate in the constant branding of company through the proper use of logo, tag line and other marketing tools", "Call on other prospects (engineering firms, other owners) to identify collaborative work opportunities", "When visiting jobs/projects, be seen at the safety meetings to make the company\u2019s commitment to safety clearly known", "Conduct post-project safety, quality, performance and client satisfaction reviews", "Meet or exceed budgeted revenue in assigned or target client accounts including P&L Management", "Develop scopes of work with schedule & budget", "Coordinate efforts with VP of Construction, VP of Turnarounds and Specialty Services and President", "Make presentations to company Board of Directors and Sr", "Comply with and abide by all the company\u2019s regulations, policies, work procedures, and instructions", "Assist in hiring, developing, mentoring, and establishing office guidelines and procedures", "Working knowledge of maintenance projects, capital projects, and turnarounds"], "Benefits": ["COMPENSATION: Competitive Salary + DOE + Bonus", "BENEFITS: Standard package"]}, "job_job_title": "Director_of business", "job_posting_language": "en", "job_onet_soc": "11202100", "job_onet_job_zone": "4"}