{"job_id": "ul5DKCKnbWBnIQpcAAAAAA==", "employer_name": "World Wide Technology", "employer_logo": "https://dn9tckvz2rpxv.cloudfront.net/wwt/img/logo.svg", "employer_website": "http://www2.wwt.com", "employer_company_type": "Computer Services", "job_publisher": "Dice", "job_employment_type": "FULLTIME", "job_title": "Lead Data Scientist", "job_apply_link": "https://www.dice.com/job-detail/8441008f-6b93-4d7d-a43f-5b283c69a186", "job_apply_is_direct": false, "job_apply_quality_score": 0.7114, "apply_options": [{"publisher": "Dice", "apply_link": "https://www.dice.com/job-detail/8441008f-6b93-4d7d-a43f-5b283c69a186", "is_direct": false}, {"publisher": "IT Diversity Careers", "apply_link": "https://www.itdiversitycareers.com/job/data-scientist-saint-louis-12600247", "is_direct": false}, {"publisher": "Karkidi", "apply_link": "https://www.karkidi.com/job-details/72938-data-scientist-job", "is_direct": false}, {"publisher": "ArmedServicesJobs", "apply_link": "https://www.armedservicesjobs.com/jobs/data-scientist-united-states-2669030373-job.html", "is_direct": false}], "job_description": "Lead Data Scientist\n\nWhy WWT?\n\nAt World Wide Technology, we work together to make a new world happen. Our important work benefits our clients and partners as much as it does our people and communities across the globe. WWT is dedicated to achieving its mission of creating a profitable growth company that is also a Great Place to Work for All. We achieve this through our world-class culture, generous benefits and by delivering cutting-edge technology solutions for our clients.\n\nWWT was founded in 1990 in St. Louis, Missouri. We employ more than 10,000 people globally and closed nearly $20 billion in revenue in 2023. We have an inclusive culture and believe our core values are the key to company and employee success. WWT is proud to have been included on the FORTUNE \"100 Best Places to Work For \" list 12 years in a row!\n\nWant to work with highly motivated individuals on high-performance teams? Join WWT today!\n\nWhat is the Solutions Consulting & Engineering (SC&E) Team and why join?\n\nSolutions Consulting & Engineering is an organization that is Customer Focused and Solutions Led. We deliver end-to-end (E2E) and emerging solutions to drive customer satisfaction, increase profitability and growth. Our success is enabled by our world-class management consulting, delivery excellence and engineering brilliance. We embody the OneWWT mindset by bringing the right talent at the right time from anywhere within WWT to solve our customer's problems. Our goal is to bring together business acumen with full-stack technical know-how to develop innovative solutions for our clients' most complex challenges.\n\nRole Overview\n\nAs a Lead DataScientist, you will collaborate with a multi-disciplinary team of solution architects, engineers, and data scientists on a wide range of business problems.You willnot only work on large scale projects to provide value to our customers but will also routinely contribute to building our internal R&D capability to keep our edge in today's data science. We work on providing analytic solutions to a wide range of clients coming from the domains of mining, healthcare, financial services, retail industry, etc.\n\nWe are looking for candidates who not just apply algorithms and packages but also understand the working behind them and can develop their own algorithms/IP. Candidates who are passionate about real world business problems tend to also be good data scientists and think creatively.\n\nResponsibilities:\n\u2022 Work closely with customers and WWT business, engineering, and technology teams\n\u2022 Work with large, complex data sets. Solve difficult, non-routine analysis problems, applying advanced analytical methods as needed. Conduct end-to-end analysis that includes data gathering and requirements specification, processing, analysis, ongoing deliverables, and presentations.\n\u2022 Work on advanced analytics areas like deep learning and complex statistical data analysis\n\u2022 Interaction with clients including in-person meetings, towards making business recommendations with effective presentations of findings, including visual displays of quantitative information\n\u2022 Develop analysis, forecasting and optimization methods/models to provide the business solution to the clients\n\u2022 Research and develop internal capabilities to enhance the skill sets on latest data science developments, work towards producing innovative solutions to the existing challenges\n\u2022 Perform quality control of deliverables\n\u2022 Provide thought leadership in algorithmic and process innovations, and contribute to creativity in solving unconventional problems\n\u2022 Be a mentor to junior members of the team\n\nQualifications:\n\nEducation\n\u2022 Preferably a Ph.D. but also open to master's or bachelor's degree in a quantitative discipline (e.g., statistics, computer science, economics, mathematics, physics, electrical engineering, industrial engineering, or other STEM fields)\n\nWork Experience\n\u2022 6-10 years of relevant work experience in data analysis or related field. (e.g., as a statistician / data scientist/ data engineer).Ph.D. Research and post-doctoral experience also counts.\n\nSpecialized Knowledge, Skills, and Abilities\n\nWe don't need an exceptional IQ of 160. All we need is curiosity, humility, and openness to learn. In other words, we just need a Beginner's Mind, even if you have decades of professional experience.\n\nAnalysis\n\u2022 Experience with writing SQL queries, performing basic conversion and transformations (e.g., formatting date string), and obtaining statistical summaries by using windowing functions.\n\u2022 Experience with usage of R/RStudio, Python, Jupyter Notebook\n\u2022 Experience with version control tool like Git\n\u2022 Strong experience with Excel and PowerPoint to present results\n\u2022 Ability to write scripts to automate ETL tasks\n\u2022 Experience in AI / Deep Learning for text/image/video analytics preferred\n\u2022 Experience in Cloud Computing and data streaming preferred\n\nProblem Solving\n\u2022 Ability to run standard model algorithms in R and Python, to perform: classification/regression, clustering, basic text analytics, image recognition, etc. E.g., run a classification problem using random forest, and obtain the variable importance, produce performance metrics/KPIs; run a k-means clustering problem, produce a KPI to quantify the goodness of clusters\n\u2022 Demonstrated skills in selecting the right statistical tools given a data analysis problem\n\u2022 Experience with charting tools & knowledge of the proper charting tool to use, whether Excel or Tableau. For instance, when to use box-and-whiskers plot, when to use waterfall. Ability to zoom-in to smaller data sets in Tableau or display subcategories.\n\u2022 Capable of running multiple scenarios and pick up the optimal solution.\n\u2022 Capable of understanding advanced mathematical or physical explanations, to implement or execute the requested tasks. E.g., Fourier Transform, Power Spectral Density, Monte Carlo simulation, etc.\n\u2022 Actively participates and contributes in brain-storming session. Can work seamlessly with people from other disciplines: IT engineers, client SMEs, business consultants.\n\u2022 Experience articulating business questions and using mathematical techniques to arrive at an answer using available data. Experience translating analysis results into business recommendations.\n\nTeam & Business Skills\n\u2022 Consistently improves communication skills, both verbally and in written materials\n\u2022 Demonstrated creativity in problem solving.\n\u2022 Demonstrated leadership and self-direction. Demonstrated willingness to both teach others and learn new techniques.\n\u2022 Flexibility in task switching. For instance, when there are urgent requests or change of projects, can accommodate the changes without protesting.\n\u2022 Mindful of iterations and quality check in a smaller team, before presenting results to larger audience\n\u2022 Raises critical issues when detected.\n\u2022 This position will have direct reports.\n\nThe well-being of WWT employees is essential. So, when it comes to our benefits package, WWT has one of the best. We offer the following benefits to all full-time employees:\n\u2022 Health and Wellbeing: Heath, Dental, and Vision Care, Onsite Health Centers, Employee Assistance Program, Wellness program\n\u2022 Financial Benefits: Competitive pay, Profit Sharing, 401k Plan with Company Matching, Life and Disability Insurance, Tuition Reimbursement\n\u2022 Paid Time Off: PTO & Holidays, Parental Leave, Sick Leave, Military Leave, Bereavement\n\u2022 Additional Perks: Nursing Mothers Benefits, Voluntary Legal, Pet Insurance, Employee Discount Program\n\nDiversity, Equity, and Inclusion is more than a commitment at WWT -- it is the foundation of what we do. Through diverse networks and pipelines, we have a clear vision: to create a Great Place to Work for All. We believe inclusion includes U. Be who U are at WWT!\n\nEqual Opportunity Employer Minorities/Women/Veterans/Individuals with Disabilities\n\nLocations Include: MO, IL, GA, TX, FL, SC, KY, TN, KS and potentially others\n\nSome WWT customers have a COVID-19 vaccine requirement. In order to work on projects for these customers, employees must be fully vaccinated or have an appropriate religious or medical accommodation.", "job_is_remote": true, "job_posted_at_timestamp": 1710288155, "job_posted_at_datetime_utc": "2024-03-13T00:02:35.000Z", "job_city": "Remote", "job_state": "OR", "job_country": "US", "job_latitude": 43.005947, "job_longitude": -123.89259, "job_benefits": ["health_insurance", "paid_time_off", "retirement_savings"], "job_google_link": "https://www.google.com/search?gl=us&hl=en&rciv=jb&q=lead+data+scientist&start=0&ibp=htl;jobs#fpstate=tldetail&htivrt=jobs&htiq=lead+data+scientist&htidocid=ul5DKCKnbWBnIQpcAAAAAA%3D%3D", "job_offer_expiration_datetime_utc": "2024-04-15T12:02:49.000Z", "job_offer_expiration_timestamp": 1713182569, "job_required_experience": {"no_experience_required": false, "required_experience_in_months": 72, "experience_mentioned": true, "experience_preferred": true}, "job_required_skills": ["Research and development", "k-means clustering", "Monte Carlo method", "Collaboration", "Customer satisfaction", "Management consulting", "Business acumen", "Data Science", "Financial services", "Business requirements", "Advanced analytics", "Deep learning", "Data Analysis", "Quality control", "Thought leadership", "Computer science", "Electrical engineering", "Industrial engineering", "SQL", "Version control", "Cloud computing", "Problem solving", "Text mining", "Brainstorming", "Leadership", "Data", "Analytical skill", "Health care", "Retail", "Algorithms", "Intellectual property", "Presentations", "Forecasting", "Optimization", "Research", "Creativity", "Mentorship", "Statistics", "Economics", "Mathematics", "Physics", "IQ", "Writing", "R", "RStudio", "Python", "Jupyter", "Git", "Microsoft Excel", "Scripting", "Extract", "transform", "load", "Artificial intelligence", "Video", "Analytics", "Streaming", "Regression analysis", "Clustering", "Metrics", "KPI", "Tableau", "Waterfall", "Pick", "Communication", "Switches", "Management", "Finance", "Insurance", "Military", "Nursing", "Legal", "Marketing operations"], "job_required_education": {"postgraduate_degree": false, "professional_certification": false, "high_school": false, "associates_degree": false, "bachelors_degree": false, "degree_mentioned": true, "degree_preferred": true, "professional_certification_mentioned": false}, "job_experience_in_place_of_education": false, "job_min_salary": null, "job_max_salary": null, "job_salary_currency": null, "job_salary_period": null, "job_highlights": {"Qualifications": ["Preferably a Ph.D. but also open to master's or bachelor's degree in a quantitative discipline (e.g., statistics, computer science, economics, mathematics, physics, electrical engineering, industrial engineering, or other STEM fields)", "6-10 years of relevant work experience in data analysis or related field", "(e.g., as a statistician / data scientist/ data engineer).Ph.D", "Research and post-doctoral experience also counts", "Specialized Knowledge, Skills, and Abilities", "We don't need an exceptional IQ of 160", "All we need is curiosity, humility, and openness to learn", "In other words, we just need a Beginner's Mind, even if you have decades of professional experience", "Experience with usage of R/RStudio, Python, Jupyter Notebook", "Experience with version control tool like Git", "Strong experience with Excel and PowerPoint to present results", "Ability to write scripts to automate ETL tasks", "Experience with charting tools & knowledge of the proper charting tool to use, whether Excel or Tableau", "For instance, when to use box-and-whiskers plot, when to use waterfall", "Ability to zoom-in to smaller data sets in Tableau or display subcategories", "Capable of running multiple scenarios and pick up the optimal solution", "Capable of understanding advanced mathematical or physical explanations, to implement or execute the requested tasks. E.g., Fourier Transform, Power Spectral Density, Monte Carlo simulation, etc", "Experience articulating business questions and using mathematical techniques to arrive at an answer using available data", "Experience translating analysis results into business recommendations", "Team & Business Skills", "Consistently improves communication skills, both verbally and in written materials", "Demonstrated creativity in problem solving", "Demonstrated leadership and self-direction", "Demonstrated willingness to both teach others and learn new techniques", "Flexibility in task switching"], "Responsibilities": ["As a Lead DataScientist, you will collaborate with a multi-disciplinary team of solution architects, engineers, and data scientists on a wide range of business problems", "Work closely with customers and WWT business, engineering, and technology teams", "Work with large, complex data sets", "Solve difficult, non-routine analysis problems, applying advanced analytical methods as needed", "Conduct end-to-end analysis that includes data gathering and requirements specification, processing, analysis, ongoing deliverables, and presentations", "Work on advanced analytics areas like deep learning and complex statistical data analysis", "Interaction with clients including in-person meetings, towards making business recommendations with effective presentations of findings, including visual displays of quantitative information", "Develop analysis, forecasting and optimization methods/models to provide the business solution to the clients", "Research and develop internal capabilities to enhance the skill sets on latest data science developments, work towards producing innovative solutions to the existing challenges", "Perform quality control of deliverables", "Provide thought leadership in algorithmic and process innovations, and contribute to creativity in solving unconventional problems", "Be a mentor to junior members of the team", "Experience with writing SQL queries, performing basic conversion and transformations (e.g., formatting date string), and obtaining statistical summaries by using windowing functions", "Demonstrated skills in selecting the right statistical tools given a data analysis problem", "Actively participates and contributes in brain-storming session", "Can work seamlessly with people from other disciplines: IT engineers, client SMEs, business consultants", "Mindful of iterations and quality check in a smaller team, before presenting results to larger audience", "Raises critical issues when detected", "This position will have direct reports"], "Benefits": ["Health and Wellbeing: Heath, Dental, and Vision Care, Onsite Health Centers, Employee Assistance Program, Wellness program", "Financial Benefits: Competitive pay, Profit Sharing, 401k Plan with Company Matching, Life and Disability Insurance, Tuition Reimbursement", "Paid Time Off: PTO & Holidays, Parental Leave, Sick Leave, Military Leave, Bereavement", "Additional Perks: Nursing Mothers Benefits, Voluntary Legal, Pet Insurance, Employee Discount Program"]}, "job_job_title": "Data scientist", "job_posting_language": "en", "job_onet_soc": "15111100", "job_onet_job_zone": "5", "job_naics_code": "541511", "job_naics_name": "Custom Computer Programming Services"}