{"job_id": "-jBOSnOwbkeVpzMjAAAAAA==", "employer_name": "CVS Health", "employer_logo": null, "employer_website": null, "employer_company_type": null, "job_publisher": "CVS Health", "job_employment_type": "FULLTIME", "job_title": "Licensed Beauty Sales Consultant", "job_apply_link": "https://jobs.cvshealth.com/job/20047310/licensed-beauty-sales-consultant-wayne-nj/", "job_apply_is_direct": false, "job_apply_quality_score": 0.8045, "apply_options": [{"publisher": "CVS Health", "apply_link": "https://jobs.cvshealth.com/job/20047310/licensed-beauty-sales-consultant-wayne-nj/", "is_direct": false}, {"publisher": "LinkedIn", "apply_link": "https://www.linkedin.com/jobs/view/licensed-beauty-sales-consultant-at-cvs-health-3846444357", "is_direct": false}, {"publisher": "ZipRecruiter", "apply_link": "https://www.ziprecruiter.com/c/CVS-Health/Job/Licensed-Beauty-Sales-Consultant/-in-Wayne,NJ?jid=373864b0a2ccbbbf", "is_direct": false}, {"publisher": "The Muse", "apply_link": "https://www.themuse.com/jobs/cvshealth/licensed-beauty-sales-consultant-b04175", "is_direct": false}, {"publisher": "Indeed", "apply_link": "https://www.indeed.com/viewjob?jk=26751d9bc97027b5", "is_direct": false}, {"publisher": "SimplyHired", "apply_link": "https://www.simplyhired.com/job/QunXGNOT6JrFPl6cMeuDSWiUhkzAxSrhFL_FfksDXJD_tIf6wXDYQA", "is_direct": false}, {"publisher": "Adzuna", "apply_link": "https://www.adzuna.com/details/4600751925", "is_direct": false}, {"publisher": "EduCativ", "apply_link": "https://educativ.net/jobs/job/1183403-licensed-beauty-sales-consultant-nj-wayne/", "is_direct": false}], "job_description": "Bring your heart to CVS Health. Every one of us at CVS Health shares a single, clear purpose: Bringing our heart to every moment of your health. This purpose guides our commitment to deliver enhanced human-centric health care for a rapidly changing world. Anchored in our brand \u2014 with heart at its center \u2014 our purpose sends a personal message that how we deliver our services is just as important as what we deliver.\n\nOur Heart At Work Behaviors\u2122 support this purpose. We want everyone who works at CVS Health to feel empowered by the role they play in transforming our culture and accelerating our ability to innovate and deliver solutions to make health care more personal, convenient and affordable.\n\nPosition Summary\n\nIt is a great time to join the beauty retail division of CVS Health, as America\u2019s leading retail pharmacy with more than 8,000 stores and continuing to grow. We are seeking a talented, sales oriented, Licensed Beauty Sales Consultant who is passionate about the beauty industry and believes the customer experience should be topnotch. We have partnered with service industry leaders to bring top-notch beauty services to our customers in-store.\n\nCVS customers will experience your passion for beauty as you share the latest beauty trends and techniques through beauty services and sales. You will be responsible for the end-to-end customer experience in Beauty & Personal Care and will provide various paid beauty services and personalized product advice.\n\nCustomer Sales Experience\n\u2022 Seek out customers to ensure they have a world class beauty advisor experience.\n\u2022 Provide personalized sales service based on customer needs, productive upselling and suggestive selling.\n\u2022 Maneuver in a conversation to stimulate a different thought process. This means you are confident and comfortable using your verbal skills to generate sales.\n\u2022 Be the brand expert by answering customer questions in detail with product knowledge to produce the largest sales basket possible.\n\u2022 Engage all customers with CVS services, Beauty Club programs and invite customers to in-store events and/or explain current promotions to close the sale of products and services.\n\nPerforming Services\n\u2022 Represent both the CVS and partner brands when interacting with customers and uphold the highest standards of service.\n\u2022 CVS Licensed Beauty Sales Consultants are required to provide ear-piercing services in all stores. Licensed Beauty Sales Consultants are also required to perform all other applicable services offered in any location in which they work.\n\u2022 CVS Licensed Beauty Sales Consultants must successfully pass assessments of proficiency before performing services in store.\n\u2022 Educate beauty customers by demonstrating proper product usage and highlighting product features and benefits to help drive purchase conversion.\n\u2022 Manage time effectively between consultations, scheduled services and walk-in clients.\n\u2022 Display current and active Cosmetology/Esthetician license during all working hours in all locations in which they work as mandated by the state.\n\nOperational\n\u2022 Create and maintain product displays and display special promotional materials in support of key brand, corporate and local advertising efforts.\n\u2022 Participate in and represent CVS at sales programs and/or events.\n\u2022 Maintain a beautiful and clean zone by keeping your assigned area well-stocked, well-merchandised and compliant with hygiene standards for a positive shopping and service experience.\n\u2022 Ensure that all CVS sanitation and hazardous waste disposal policies are executed in a timely and compliant manner.\n\u2022 Complete ongoing sales, brand, and paid service execution training in a timely manner with CVS and service partners to ensure knowledge and skills are modern and current.\n\u2022 Maintain a professional colleague appearance in compliance with company policies and guidelines at all times.\n\u2022 Be our customer\u2019s Beauty Expert by being plugged-in to all of the latest beauty trends and techniques. Be a beauty enthusiast!\n\nWhy You\u2019ll Love Working Here!\n\u2022 Exposure to the latest and greatest product in the industry through brand interaction, training and more.\n\u2022 Gratis. Everyone loves free samples!\n\u2022 Aspire to be one of the top Beauty Sales Consultants to earn an invitation to the annual tradeshow. The day is full of learning, demonstrations and surprises!\n\u2022 You will be helping people on their path to better health. When people feel good about themselves and take care of their beauty needs, that translates to a positive impact on the rest of their lives, and you will contribute to this impact!\n\u2022 * Required Qualifications\n\u2022 Must possess a current and valid Cosmetology/Esthetician License in the state in which you will be working.\n\u2022 Must maintain an active Cosmetology/Esthetician license at all times in the state you are employed and ensure it is present and displayed during working hours at your work site(s) as mandated by that state.\n\u2022 CVS Licensed Beauty Sales Consultants must demonstrate the ability and willingness to perform ear-piercing services in all stores. Licensed Beauty Sales Consultants are also required to perform all other services offered in any location in which they work.\n\u2022 Must pass all required skills assessments and training courses to fully execute paid service options offered in the store locations in which you work.\n\u2022 Ability to use sales data with product/brand knowledge to meet sales and beauty service goals\n\u2022 Strong interpersonal, organizational and communication skills.\n\u2022 Goal-driven, with an ability to multi-task.\n\u2022 Ability to work independently and as an integral part of a team in a fast-paced environment, handling multiple priorities and quickly learning new procedures.\n\u2022 Available to work at a CVS store and travel to sales programs and events as needed.\n\u2022 Available to work a flexible retail schedule, which may include mornings, evenings, weekends, extended hours and \u201cPeak\u201d Hours\n\u2022 Nevada Licensed Beauty Sales Consultant applicants must provide confirmation of a MAKEUP ARTIST REGISTRATION/ THREADER REGISTRATION issued from the state of Nevada.\n\u2022 In specific CVS stores, we require bi-lingual beauty advisors that can speak to customers in both English and Spanish.\n\u2022 Must be at least 18 years old.\n\u2022 High school diploma or equivalent.\n\nPreferred Qualifications\n\u2022 Prior beauty sales experience with a strong passion for beauty.\n\nPhysical Requirements\n\u2022 Stand for extended periods of time and move throughout the store in order to provide excellent customer service, including providing services and beauty consulting, and perform other task work such as stocking and facing product displays and updating advertising promotions.\n\u2022 Able to stoop, kneel or crouch, and able to reach or grasp objects, including objects on lower shelves.\n\u2022 Able to perform duties requiring manual dexterity (e.g., hair styling, makeup applications, ear piercing).\n\u2022 Physical abilities to support the Required Qualifications listed above.\n\nEducation\n\nHigh School diploma or equivalent preferred but not required.\n\nPay Range\n\nThe typical pay range for this role is:\n\n$16.00 - $22.00\n\nThis pay range represents the base hourly rate or base annual full-time salary for all positions in the job grade within which this position falls. The actual base salary offer will depend on a variety of factors including experience, education, geography and other relevant factors.\n\nIn addition to your compensation, enjoy the rewards of an organization that puts our heart into caring for our colleagues and our communities. The Company offers a full range of medical, dental, and vision benefits. Eligible employees may enroll in the Company\u2019s 401(k) retirement savings plan, and an Employee Stock Purchase Plan is also available for eligible employees. The Company provides a fully-paid term life insurance plan to eligible employees, and short-term and long term disability benefits. CVS Health also offers numerous well-being programs, education assistance, free development courses, a CVS store discount, and discount programs with participating partners. As for time off, Company employees enjoy Paid Time Off (\u201cPTO\u201d) or vacation pay, as well as paid holidays throughout the calendar year. Number of paid holidays, sick time and other time off are provided consistent with relevant state law and Company policies.\n\nFor more detailed information on available benefits, please visit jobs.CVSHealth.com/benefits\n\nWe anticipate the application window for this opening will close on: 06/08/2024\n\nCVS Health requires certain colleagues to be fully vaccinated against COVID-19 (including any booster shots if required), where allowable under the law, unless they are approved for a reasonable accommodation based on disability, medical condition, religious belief, or other legally recognized reasons that prevents them from being vaccinated.\n\nYou are required to have received at least one COVID-19 shot prior to your first day of employment and to provide proof of your vaccination status or apply for a reasonable accommodation within the first 10 days of your employment. Please note that in some states and roles, you may be required to provide proof of full vaccination or an approved reasonable accommodation before you can begin to actively work.\n\nCVS Health is committed to recruiting, hiring, developing, advancing, and retaining individuals with disabilities. As such, we strive to provide equal access to the benefits and privileges of employment, including the provision of a reasonable accommodation to perform essential job functions. CVS Health can provide a request for a reasonable accommodation, including a qualified interpreter, written information in other formats, translation or other services through ColleagueRelations@CVSHealth.com If you have a speech or hearing disability, please call 7-1-1 to utilize Telecommunications Relay Services (TRS). We will make every effort to respond to your request within 48 business hours and do everything we can to work towards a solution.", "job_is_remote": false, "job_posted_at_timestamp": 1709769600, "job_posted_at_datetime_utc": "2024-03-07T00:00:00.000Z", "job_city": "Wayne", "job_state": "NJ", "job_country": "US", "job_latitude": 40.925373, "job_longitude": -74.27654, "job_benefits": ["dental_coverage", "paid_time_off", "health_insurance", "retirement_savings"], "job_google_link": "https://www.google.com/search?gl=us&hl=en&rciv=jb&q=sales+consultant&start=10&ibp=htl;jobs#fpstate=tldetail&htivrt=jobs&htiq=sales+consultant&htidocid=-jBOSnOwbkeVpzMjAAAAAA%3D%3D", "job_offer_expiration_datetime_utc": null, "job_offer_expiration_timestamp": null, "job_required_experience": {"no_experience_required": false, "required_experience_in_months": null, "experience_mentioned": true, "experience_preferred": false}, "job_required_skills": null, "job_required_education": {"postgraduate_degree": false, "professional_certification": false, "high_school": false, "associates_degree": false, "bachelors_degree": false, "degree_mentioned": false, "degree_preferred": false, "professional_certification_mentioned": false}, "job_experience_in_place_of_education": false, "job_min_salary": null, "job_max_salary": null, "job_salary_currency": null, "job_salary_period": null, "job_highlights": {"Qualifications": ["This means you are confident and comfortable using your verbal skills to generate sales", "Must possess a current and valid Cosmetology/Esthetician License in the state in which you will be working", "Must maintain an active Cosmetology/Esthetician license at all times in the state you are employed and ensure it is present and displayed during working hours at your work site(s) as mandated by that state", "CVS Licensed Beauty Sales Consultants must demonstrate the ability and willingness to perform ear-piercing services in all stores", "Ability to use sales data with product/brand knowledge to meet sales and beauty service goals", "Strong interpersonal, organizational and communication skills", "Goal-driven, with an ability to multi-task", "Ability to work independently and as an integral part of a team in a fast-paced environment, handling multiple priorities and quickly learning new procedures", "Available to work at a CVS store and travel to sales programs and events as needed", "Nevada Licensed Beauty Sales Consultant applicants must provide confirmation of a MAKEUP ARTIST REGISTRATION/ THREADER REGISTRATION issued from the state of Nevada", "In specific CVS stores, we require bi-lingual beauty advisors that can speak to customers in both English and Spanish", "Must be at least 18 years old", "High school diploma or equivalent", "Able to perform duties requiring manual dexterity (e.g., hair styling, makeup applications, ear piercing)", "Physical abilities to support the Required Qualifications listed above"], "Responsibilities": ["You will be responsible for the end-to-end customer experience in Beauty & Personal Care and will provide various paid beauty services and personalized product advice", "Seek out customers to ensure they have a world class beauty advisor experience", "Provide personalized sales service based on customer needs, productive upselling and suggestive selling", "Maneuver in a conversation to stimulate a different thought process", "Be the brand expert by answering customer questions in detail with product knowledge to produce the largest sales basket possible", "Engage all customers with CVS services, Beauty Club programs and invite customers to in-store events and/or explain current promotions to close the sale of products and services", "Represent both the CVS and partner brands when interacting with customers and uphold the highest standards of service", "CVS Licensed Beauty Sales Consultants are required to provide ear-piercing services in all stores", "Educate beauty customers by demonstrating proper product usage and highlighting product features and benefits to help drive purchase conversion", "Manage time effectively between consultations, scheduled services and walk-in clients", "Display current and active Cosmetology/Esthetician license during all working hours in all locations in which they work as mandated by the state", "Create and maintain product displays and display special promotional materials in support of key brand, corporate and local advertising efforts", "Participate in and represent CVS at sales programs and/or events", "Maintain a beautiful and clean zone by keeping your assigned area well-stocked, well-merchandised and compliant with hygiene standards for a positive shopping and service experience", "Ensure that all CVS sanitation and hazardous waste disposal policies are executed in a timely and compliant manner", "Complete ongoing sales, brand, and paid service execution training in a timely manner with CVS and service partners to ensure knowledge and skills are modern and current", "Maintain a professional colleague appearance in compliance with company policies and guidelines at all times", "Be our customer\u2019s Beauty Expert by being plugged-in to all of the latest beauty trends and techniques", "You will be helping people on their path to better health", "Available to work a flexible retail schedule, which may include mornings, evenings, weekends, extended hours and \u201cPeak\u201d Hours"], "Benefits": ["Exposure to the latest and greatest product in the industry through brand interaction, training and more", "Gratis", "Aspire to be one of the top Beauty Sales Consultants to earn an invitation to the annual tradeshow", "$16.00 - $22.00", "This pay range represents the base hourly rate or base annual full-time salary for all positions in the job grade within which this position falls", "The actual base salary offer will depend on a variety of factors including experience, education, geography and other relevant factors", "In addition to your compensation, enjoy the rewards of an organization that puts our heart into caring for our colleagues and our communities", "The Company offers a full range of medical, dental, and vision benefits", "Eligible employees may enroll in the Company\u2019s 401(k) retirement savings plan, and an Employee Stock Purchase Plan is also available for eligible employees", "The Company provides a fully-paid term life insurance plan to eligible employees, and short-term and long term disability benefits", "CVS Health also offers numerous well-being programs, education assistance, free development courses, a CVS store discount, and discount programs with participating partners", "As for time off, Company employees enjoy Paid Time Off (\u201cPTO\u201d) or vacation pay, as well as paid holidays throughout the calendar year", "Number of paid holidays, sick time and other time off are provided consistent with relevant state law and Company policies"]}, "job_job_title": "Sales consultant", "job_posting_language": "en", "job_onet_soc": "39501200", "job_onet_job_zone": "3"}