{"job_id": "jZCUZmo47n2LiRgyAAAAAA==", "employer_name": "Buster + Punch", "employer_logo": "https://pbs.twimg.com/profile_images/741204188261011457/No0mCas4_400x400.jpg", "employer_website": "http://www.busterandpunch.com", "employer_company_type": null, "job_publisher": "Glassdoor", "job_employment_type": "FULLTIME", "job_title": "National Sales Director", "job_apply_link": "https://www.glassdoor.com/job-listing/national-sales-director-buster-punch-JV_KO0,23_KE24,36.htm?jl=1009135412008", "job_apply_is_direct": true, "job_apply_quality_score": 0.6515, "apply_options": [{"publisher": "Glassdoor", "apply_link": "https://www.glassdoor.com/job-listing/national-sales-director-buster-punch-JV_KO0,23_KE24,36.htm?jl=1009135412008", "is_direct": true}, {"publisher": "Indeed", "apply_link": "https://www.indeed.com/viewjob?jk=cd3f39fa9fb4af2c", "is_direct": true}], "job_description": "The role:\n\nThe National Sales Director oversees B2B sales for the United States, Canada (maybe Mexico) and is responsible for management, business development and sales growth, of the B2B (business, distributor, retailer and trade professionals) channels of Buster + Punch. In addition, the National Sales Director is responsible for managing the B+P regional sales managers, the independent rep network, client relationships, B2B sales staff/team \u2013 and will implement the proper reporting and analyzing tools \u2013 with matrixes to properly manage the sales teams and the aggressive (yet strategic) sale initiatives required. This position reports to the President of Buster and Punch, Inc.\n\nResponsibility:\n\nThe director is responsible overseeing the B2B sales channels for Buster + Punch North America. The main initial focus is the United States, however this position supports the requirements of President handling Mexico and Canada (and any other territories/markets brought on). The director also is responsible for integration with the parent company related to global sales, branding strategies and initiatives \u2013 when and as required. The director must be fully entrenched in the brand and have a deep understanding of the technical and functional aspects of all products and categories brought to market. This is a hand\u2019s-on position where direct training, presenting, pitching and selling of the Buster + Punch brand is required.\n\nAdditional responsibilities include:\n\u2022 Buster + Punch (North America) strategic sales growth planning, and metrics management\n\u2022 Energize, coach and nurture an outside and inside B2B sales team to build an enthusiastic and engaged group/culture that is highly driven to generate profitable sales and exceptional customer service\n\u2022 Build and nurture productive industry relationships, and effectively work with A+D industry individuals and groups \u2013 to build and increase direct-sales opportunities and relationships\n\u2022 Build and develop project based opportunities within hospitality and boutique multi-residential projects Produce sales budgeting and forecasting \u2013 for internal team and as required for COO, CFO and President\n\u2022 Direct and collaborate with President for new business and market opportunities \u2013 stay on top of the initiatives required of President when out in field\n\u2022 Lead outside sales teams in tactical and strategic efforts to serve clients/dealers and secure renewal of programs \u2013 leading to client retention and organic growth\n\u2022 Collaborate and support marketing and sales initiatives of Buster + Punch \u2013 global and local basis - related to product launches/releases, procedures, and brand exposure\n\u2022 Develop and direct the creation of dealer and rep sales collateral/marketing materials, and communication tools \u2013 to deliver efficient, nimble and \u201creal-time\u201d implementation of any requirement or initiative\n\u2022 Support and promote the Buster + Punch brand merchandising programs and disciplines required to properly represent the brand \u2013 required for the North American market\n\u2022 Provide strategic advice to the board and president so that they will have accurate view of the sales, product requirements and status of Buster + Punch in the marketplace\n\u2022 Provide monthly reporting to the Board on sales performance and status of high-profile opportunities\n\u2022 Delegate responsibilities and supervise the work of regional and territory sales managers/team, providing guidance and motivation to drive maximum performance\n\u2022 Analyze problematic situations and occurrences and provide solutions to ensure company wellbeing and growth\n\u2022 Be available and have attitude to jump in as needed to fix things \u2013 including having to travel, be in the trenches \u2013 and be able to work with all senior team members \u2013 to get things done.\n\nRequirements and skills:\n\u2022 Proven experience as a national sales director or manager\n\u2022 Demonstrable experience in developing strategic sales plans \u2013 including working with retailers, distributors \u2013 from single boutique partners to multi-national businesses\n\u2022 Strong understanding of corporate finance and measures of performance\n\u2022 Excellent organizational and leadership skills\n\u2022 Excellent communication, interpersonal and presentation skills\n\u2022 Outstanding analytical and problem-solving abilities\n\u2022 Personable, available, and accessible attitude and demeanor\n\u2022 Looking for opportunities to increase efficiencies and processes across the business\n\u2022 Develop reporting tools to monitor ongoing performance of sales managers related teams\n\u2022 Setting KPI\u2019s to gauge team, departments, retail partners and total sales team\u2019s performance\n\nJob Type: Full-time\n\nBenefits:\n\u2022 401(k)\n\u2022 Dental insurance\n\u2022 Health insurance\n\u2022 Paid time off\n\nSchedule:\n\u2022 Monday to Friday\n\nApplication Question(s):\n\u2022 Have you been involved in a sales or managerial role in the following industries? (Please state all that apply)\n\na. Fashion \u2013 apparel\nb. Fashion - jewelry\nc. Wellness and Fitness Products\nd. Lifestyle accessories and soft goods\ne. Sports ware (apparel, foot ware, and accessories)\n\u2022 Have you managed a national network of independent sales rep agencies? Please detail\n\u2022 Have you managed and directed regional or territory sales managers? Please detail\n\u2022 Have you been involved in a sales or managerial role in the following industries? (Please state all that apply)\n\na. Interior Design\nb. Decorative hardware or plumbing\nc. Decorative lighting\nd. Furniture\ne. Architectural, Interior or Exterior Products\nf. Home D\u00e9cor \u2013 Products for residential, hospitality, commercial, workspaces\ng. Kitchen and/or Bath Products\nh. Major Appliances for residential\ni. Home automation Products\n\nExperience:\n\u2022 Sales management: 3 years (Required)\n\nWork Location: Remote", "job_is_remote": true, "job_posted_at_timestamp": 1708387200, "job_posted_at_datetime_utc": "2024-02-20T00:00:00.000Z", "job_city": null, "job_state": null, "job_country": "US", "job_latitude": 37.09024, "job_longitude": -95.71289, "job_benefits": ["retirement_savings", "dental_coverage", "paid_time_off", "health_insurance"], "job_google_link": "https://www.google.com/search?gl=us&hl=en&rciv=jb&q=sales+director&start=30&ibp=htl;jobs#fpstate=tldetail&htivrt=jobs&htiq=sales+director&htidocid=jZCUZmo47n2LiRgyAAAAAA%3D%3D", "job_offer_expiration_datetime_utc": "2024-07-09T00:00:00.000Z", "job_offer_expiration_timestamp": 1720483200, "job_required_experience": {"no_experience_required": false, "required_experience_in_months": null, "experience_mentioned": true, "experience_preferred": false}, "job_required_skills": null, "job_required_education": {"postgraduate_degree": false, "professional_certification": false, "high_school": false, "associates_degree": false, "bachelors_degree": false, "degree_mentioned": false, "degree_preferred": false, "professional_certification_mentioned": false}, "job_experience_in_place_of_education": false, "job_min_salary": null, "job_max_salary": null, "job_salary_currency": null, "job_salary_period": null, "job_highlights": {"Qualifications": ["Proven experience as a national sales director or manager", "Demonstrable experience in developing strategic sales plans \u2013 including working with retailers, distributors \u2013 from single boutique partners to multi-national businesses", "Strong understanding of corporate finance and measures of performance", "Excellent organizational and leadership skills", "Excellent communication, interpersonal and presentation skills", "Outstanding analytical and problem-solving abilities", "Personable, available, and accessible attitude and demeanor", "Looking for opportunities to increase efficiencies and processes across the business", "Sales management: 3 years (Required)"], "Responsibilities": ["The National Sales Director oversees B2B sales for the United States, Canada (maybe Mexico) and is responsible for management, business development and sales growth, of the B2B (business, distributor, retailer and trade professionals) channels of Buster + Punch", "In addition, the National Sales Director is responsible for managing the B+P regional sales managers, the independent rep network, client relationships, B2B sales staff/team \u2013 and will implement the proper reporting and analyzing tools \u2013 with matrixes to properly manage the sales teams and the aggressive (yet strategic) sale initiatives required", "The main initial focus is the United States, however this position supports the requirements of President handling Mexico and Canada (and any other territories/markets brought on)", "The director also is responsible for integration with the parent company related to global sales, branding strategies and initiatives \u2013 when and as required", "The director must be fully entrenched in the brand and have a deep understanding of the technical and functional aspects of all products and categories brought to market", "Buster + Punch (North America) strategic sales growth planning, and metrics management", "Energize, coach and nurture an outside and inside B2B sales team to build an enthusiastic and engaged group/culture that is highly driven to generate profitable sales and exceptional customer service", "Build and nurture productive industry relationships, and effectively work with A+D industry individuals and groups \u2013 to build and increase direct-sales opportunities and relationships", "Build and develop project based opportunities within hospitality and boutique multi-residential projects Produce sales budgeting and forecasting \u2013 for internal team and as required for COO, CFO and President", "Direct and collaborate with President for new business and market opportunities \u2013 stay on top of the initiatives required of President when out in field", "Lead outside sales teams in tactical and strategic efforts to serve clients/dealers and secure renewal of programs \u2013 leading to client retention and organic growth", "Collaborate and support marketing and sales initiatives of Buster + Punch \u2013 global and local basis - related to product launches/releases, procedures, and brand exposure", "Develop and direct the creation of dealer and rep sales collateral/marketing materials, and communication tools \u2013 to deliver efficient, nimble and \u201creal-time\u201d implementation of any requirement or initiative", "Support and promote the Buster + Punch brand merchandising programs and disciplines required to properly represent the brand \u2013 required for the North American market", "Provide strategic advice to the board and president so that they will have accurate view of the sales, product requirements and status of Buster + Punch in the marketplace", "Provide monthly reporting to the Board on sales performance and status of high-profile opportunities", "Delegate responsibilities and supervise the work of regional and territory sales managers/team, providing guidance and motivation to drive maximum performance", "Analyze problematic situations and occurrences and provide solutions to ensure company wellbeing and growth", "Be available and have attitude to jump in as needed to fix things \u2013 including having to travel, be in the trenches \u2013 and be able to work with all senior team members \u2013 to get things done", "Develop reporting tools to monitor ongoing performance of sales managers related teams", "Setting KPI\u2019s to gauge team, departments, retail partners and total sales team\u2019s performance"], "Benefits": ["401(k)", "Dental insurance", "Health insurance", "Paid time off"]}, "job_job_title": "Sales director", "job_posting_language": "en", "job_onet_soc": "11202200", "job_onet_job_zone": "4"}