{"job_id": "iQg57cH1Rkg-u0JUAAAAAA==", "employer_name": "Save the Children", "employer_logo": "https://www.savethechildren.net/sites/www.savethechildren.net/themes/stcui/img/logo.png", "employer_website": "https://www.savethechildren.net", "employer_company_type": "Consulting", "job_publisher": "Salary.com", "job_employment_type": "FULLTIME", "job_title": "Senior Director, Proposal Recruitment - New Business Development (M2)", "job_apply_link": "https://www.salary.com/job/save-the-children/senior-director-proposal-recruitment-new-business-development-m2/j202312092256143320528", "job_apply_is_direct": false, "job_apply_quality_score": 0.6218, "apply_options": [{"publisher": "Salary.com", "apply_link": "https://www.salary.com/job/save-the-children/senior-director-proposal-recruitment-new-business-development-m2/j202312092256143320528", "is_direct": false}, {"publisher": "Milwaukee Jobs", "apply_link": "https://www.milwaukeejobs.com/job/detail/77496388/Senior-Director-Proposal-Recruitment-New-Business-Development-M2", "is_direct": false}], "job_description": "Description\n\nAll Save the Children employees are required to be fully vaccinated against Covid-19 unless otherwise required by law. All new employees hired to Save the Children will be required to submit proof of vaccination as part of their onboarding process. Failure to provide proof of vaccination may result in disciplinary action, up to and including termination of employment. Save the Children complies with federal, state and local laws with regard to accommodations related to this policy.\n\nSummary\n\nNew Business Development provides leadership in Save the Children's efforts to achieve greater program results at scale through the successful pursuit of large and strategic US government development funding opportunities for Save the Children's International Programs division. The Senior Director, Proposal Recruitment is responsible for full lifecycle management of the recruitment process including identifying, selecting, and securing dedicated senior leadership staff for US government programs (funding from United States Agency for International Development (USAID), United States Department of Agriculture (USDA), and Department of State (DOS), among others). As the head of a team of proposal recruiters, you will be responsible for standardizing and improving the recruitment process to ensure high levels of offer acceptance and strong performance against evaluation criteria for key personnel in proposal submissions. You will be a critical position to advance the agency's strategic growth; their actions will substantially contribute to Save the Children's ability to competitively and successfully pursue and acquire funding, thereby increasing the agency's resource base for children.\n\nWhat You'll Be Doing (Essential Duties)\n\nProposal and Program Recruitment (70%)\n\u2022 Serve as the Personnel Lead working to identify, select and secure key and non-key personnel who will direct and support donor-funded programs. This will be done in close partnership with Human Resources (HR) staff in international country offices to prioritize hiring local talent to the greatest extent feasible.\n\u2022 Work and collaborate with all members of the proposal team to prioritize staffing needs, managing several dozen recruitments at varying stages across the team.\n\u2022 Write job descriptions and advertisements to accurately reflect proposed roles.\n\u2022 Publish and provide guidance on how to interview and select candidates, with formatted questionnaires to lead discussions and capture quality responses during the interview stage.\n\u2022 Source, screen, interview and select strong candidates to present to hiring managers and interview panels for consideration.\n\u2022 Understand current People & Culture (P & C) policies and compensation structures while working closely and collaboratively with P & C to ensure consistency and competitiveness among other non-governmental organizations (NGOs). Support market analysis and benchmarking efforts to ensure compensation plans are competitive in the marketplace for international staff and within the Save the Children United States (SCUS) and Save the Children International (SCI) structures.\n\u2022 Regularly participate in negotiations with SC country- and regional-level stakeholders to ensure that exceptional candidates proposed as Key Personnel on priority bids may be presented competitive compensation offers.\n\u2022 Perform reference and background checks to ensure only candidates who meet or exceed SCUS and donor policies are proposed and hired.\n\u2022 Once candidates are selected, revise Curriculum vitae (CV) to highlight strengths and craft compelling statements and biographical summaries for personnel and staffing needs. Review, inform and contribute to compelling staffing plans as part of Save the Children's proposals.\n\u2022 Stay current on existing United States Government (USG) trends and HR practices; maintain current information on candidate pipelines; and maintain relationships with top-tier talent in the marketplace to attract and retain well-qualified, professional candidates who are leaders in their field.\n\nTeam Management (15%)\n\u2022 Develop, manage, and mentor proposal recruiters (two), ensuring recruitment team provides high-caliber recruitment support and deliverables.\n\u2022 Monitor proposal pipeline and oversee assignments and workload for team.\n\u2022 Train, develop, coach, lead, and supervise staff, clearly communicating organization, division and department priorities, and how their work contributes to our mission, ensuring that the working environment continually fosters diversity, inclusion, and belonging - supporting Save the Children values\n\nStrategic Leadership and Representation (10%)\n\u2022 Help to support New Business Development (NBD) new raise targets and grow programs and funding in priority countries for SCUS.\n\u2022 Contribute actively to agency-wide initiatives including task force teams and strategic projects.\n\u2022 Interact regularly with SCUS senior management team members, regional and country directors, and others as applicable to ensure commitment from all key stakeholders and agreement on staffing plans.\n\nKnowledge Management and Learning (5%)\n\u2022 Collaborate with counterparts in P & C/HR in the US, international offices and other SC members to standardize and improve processes. These collaboration activities are focused on building capacity and enhancing knowledge around this core function to improve win rates, secure and manage these key programs and help fund business.\n\u2022 Build capacity of SC country office staff to understand and recruit for local talent for current and upcoming USG-funded opportunities.\n\nRequired Qualifications\n\u2022 Minimum of a Bachelor Degree or equivalent experience, plus at least 7 years of relevant experience.\n\u2022 Knowledge of USAID and understanding of USG regulations related to hiring of personnel\n\u2022 Ability to prioritize workload and manage senior-level staff expectations and deliverables.\n\u2022 Excellent communication skills in English - verbal and written.\n\u2022 Strong writing skills.\n\u2022 Experience strengthening the capacity of peers/colleagues through training techniques, tools/materials development and up-to-date templates.\n\u2022 Able to multi-task, meet tight deadlines and deliver results consistently.\n\u2022 Knowledgeable with applicant tracking systems, sourcing tools and web-based resources.\n\u2022 Solid knowledge of how to use Boolean search strings and logic-based techniques to identify talent and create more precision in identifying candidates for hard-to-fill positions.\n\u2022 Takes the initiative to work with diverse groups across multiple sectors, regions and functional areas to build cohesive, compelling and successful leadership teams to operate complex programs.\n\u2022 Professional proficiency in MS Office suite\n\u2022 Demonstrated ability to communicate and collaborate effectively with individuals and teams at all levels, both internally and externally\n\u2022 Demonstrated commitment to fostering and maintaining and environment of diversity, inclusion, and belonging.\n\nPreferred Qualifications\n\u2022 Proven experience writing compelling documents and crafting strong staffing plans\n\u2022 Foreign language skills (French, Spanish, Portuguese)\n\u2022 Background in Human Resources\n\u2022 Experience with USAID contracts\n\u2022 Experience managing staff, especially remote staff\n\u2022 Willingness and ability to travel internationally for proposal recruitment as required, i.e. up to 10%\n\nCompensation\n\nSave the Children is offering the following salary ranges for this position, dependent on candidate location:\n\u2022 Geo 1 - NY Metro, DC, and other locations with labor costs significantly above national average: Target Salary for this position is $108,800 - $121,600 base salary\n\u2022 Geo 2 - Locations around the US National Labor Cost Average: Target Salary for this position is $98,600 - $110,200 base salary\n\u2022 Geo 3 - Locations significantly below the US National Labor Cost Average: Target Salary for this position is $88,400 - $98,800 base salary\n\nActual base salary may vary based upon, but not limited to, relevant experience, base salary of internal peers, business sector, and geographic location (more information on job structure is available ). Employee may be eligible for an incentive program. Save the Children also offers paid vacation, accrued at least 12 days a year, depending on paygrade and length of service, paid safety and wellness leave of at least 1 day per month worked for a full time employee which is pro rata reduced for employees working less than a full time schedule, and at least 10 paid holidays a year. Employees may be eligible for additional bonus compensation. Save the Children US also offers outstanding benefits that include health, dental, vision and life insurances, short-term and long-term disability coverage, an Employee Assistance Program, a retirement savings plan with employer contribution, family leave, paid parental/adoption leave of 60 days, commuter benefits, paid caregiver leave days, 1 paid volunteer day a year, paid critical child illness leave days, dress for your day, and much more.\n\nWhy you should join the Save the Children Team...\n\nSave the Children US offers outstanding benefits that include health, dental, vision and life insurances, short-term and long-term disability coverage, an Employee Assistance Program, 403(b), generous vacation, personal sick leave, family leave, parental/adoption leave, commuter benefits, dress for your day, and much more.\n\nClick to learn more about how Save the Children US will invest in YOU!\n\nAbout Save the Children\n\nNo matter your role when you join Save the Children, each and every day you will challenge yourself to devote your skills, talent and expertise to changing the world for kids. It's an ambitious goal, and a meaningful one no matter how you see yourself professionally: an accountant, a writer, a data analyst, a teacher, a driver, a designer, or any one of the hundreds of dozens of roles we're looking to fill every day.\n\nYou see, Save the Children believes every child deserves a future. In the United States and around the world, we give children a healthy start in life, the opportunity to learn and protection from harm. We do whatever it takes for children - every day and in times of crisis - transforming their lives and the future we share.\n\nOur work for children and their families requires that we commit-at every opportunity-to work together to identify and dismantle persistent systemic and structural racism, inequality, and any other forms of discrimination in this country and beyond. As an anti-racist organization, Save the Children will not tolerate discrimination in any form-in our employment practices, amongst our staff, in our leadership or toward the people we serve. We stand in solidarity with all people to fight for equal rights, justice, inclusion, and belonging.\n\nWe provide equal employment opportunities (EEO) to all employees and qualified applicants for employment without regard to race, color, religion, gender, gender identity or expression, ancestry, sexual orientation, national origin, age, handicap, disability, marital status, or status as a veteran. Save the Children complies with all applicable laws.\n\nSave the Children is committed to conducting its programs and operations in a manner that is safe for the children it serves and helping protect the children with whom we are in contact. All Save the Children representatives are explicitly prohibited from engaging in any activity that may result in any kind of child abuse. In addition, it is Save the Children's policy to create and proactively maintain an environment that aims to prevent and deter any actions and omissions, whether deliberate or inadvertent, that place children at the risk of any kind of child abuse. All our representatives are expected to conduct themselves in a manner consistent with this commitment and obligation.\n\nSave the Children is committed to minimizing safety and security risks for our valued employees, ensuring all are given training, support and information to reduce their risk exposure while maximizing the impact of our programs for children and families. Our shared duty, both agency and individual, is to seek and maintain safe working conditions for all.\n\nEqual Opportunity Employer/Protected Veterans/Individuals with Disabilities\n\nThe contractor will not discharge or in any other manner discriminate against employees or applicants because they have inquired about, discussed, or disclosed their own pay or the pay of another employee or applicant. However, employees who have access to the compensation information of other employees or applicants as a part of their essential job functions cannot disclose the pay of other employees or applicants to individuals who do not otherwise have access to compensation information, unless the disclosure is (a) in response to a formal complaint or charge, (b) in furtherance of an investigation, proceeding, hearing, or action, including an investigation conducted by the employer, or (c) consistent with the contractor's legal duty to furnish information. 41 CFR 60-1.35(c)", "job_is_remote": false, "job_posted_at_timestamp": 1707696000, "job_posted_at_datetime_utc": "2024-02-12T00:00:00.000Z", "job_city": "Washington", "job_state": "DC", "job_country": "US", "job_latitude": 38.907192, "job_longitude": -77.03687, "job_benefits": ["dental_coverage", "health_insurance", "paid_time_off", "retirement_savings"], "job_google_link": "https://www.google.com/search?gl=us&hl=en&rciv=jb&q=senior+director+of+business+development&start=10&ibp=htl;jobs#fpstate=tldetail&htivrt=jobs&htiq=senior+director+of+business+development&htidocid=iQg57cH1Rkg-u0JUAAAAAA%3D%3D", "job_offer_expiration_datetime_utc": "2024-04-10T00:00:00.000Z", "job_offer_expiration_timestamp": 1712707200, "job_required_experience": {"no_experience_required": false, "required_experience_in_months": 84, "experience_mentioned": true, "experience_preferred": true}, "job_required_skills": null, "job_required_education": {"postgraduate_degree": false, "professional_certification": false, "high_school": false, "associates_degree": false, "bachelors_degree": false, "degree_mentioned": true, "degree_preferred": false, "professional_certification_mentioned": false}, "job_experience_in_place_of_education": false, "job_min_salary": null, "job_max_salary": null, "job_salary_currency": null, "job_salary_period": null, "job_highlights": {"Qualifications": ["Minimum of a Bachelor Degree or equivalent experience, plus at least 7 years of relevant experience", "Knowledge of USAID and understanding of USG regulations related to hiring of personnel", "Ability to prioritize workload and manage senior-level staff expectations and deliverables", "Excellent communication skills in English - verbal and written", "Strong writing skills", "Experience strengthening the capacity of peers/colleagues through training techniques, tools/materials development and up-to-date templates", "Able to multi-task, meet tight deadlines and deliver results consistently", "Knowledgeable with applicant tracking systems, sourcing tools and web-based resources", "Solid knowledge of how to use Boolean search strings and logic-based techniques to identify talent and create more precision in identifying candidates for hard-to-fill positions", "Takes the initiative to work with diverse groups across multiple sectors, regions and functional areas to build cohesive, compelling and successful leadership teams to operate complex programs", "Professional proficiency in MS Office suite", "Demonstrated ability to communicate and collaborate effectively with individuals and teams at all levels, both internally and externally", "Demonstrated commitment to fostering and maintaining and environment of diversity, inclusion, and belonging"], "Responsibilities": ["As the head of a team of proposal recruiters, you will be responsible for standardizing and improving the recruitment process to ensure high levels of offer acceptance and strong performance against evaluation criteria for key personnel in proposal submissions", "You will be a critical position to advance the agency's strategic growth; their actions will substantially contribute to Save the Children's ability to competitively and successfully pursue and acquire funding, thereby increasing the agency's resource base for children", "Serve as the Personnel Lead working to identify, select and secure key and non-key personnel who will direct and support donor-funded programs", "This will be done in close partnership with Human Resources (HR) staff in international country offices to prioritize hiring local talent to the greatest extent feasible", "Work and collaborate with all members of the proposal team to prioritize staffing needs, managing several dozen recruitments at varying stages across the team", "Write job descriptions and advertisements to accurately reflect proposed roles", "Publish and provide guidance on how to interview and select candidates, with formatted questionnaires to lead discussions and capture quality responses during the interview stage", "Source, screen, interview and select strong candidates to present to hiring managers and interview panels for consideration", "Understand current People & Culture (P & C) policies and compensation structures while working closely and collaboratively with P & C to ensure consistency and competitiveness among other non-governmental organizations (NGOs)", "Support market analysis and benchmarking efforts to ensure compensation plans are competitive in the marketplace for international staff and within the Save the Children United States (SCUS) and Save the Children International (SCI) structures", "Regularly participate in negotiations with SC country- and regional-level stakeholders to ensure that exceptional candidates proposed as Key Personnel on priority bids may be presented competitive compensation offers", "Perform reference and background checks to ensure only candidates who meet or exceed SCUS and donor policies are proposed and hired", "Once candidates are selected, revise Curriculum vitae (CV) to highlight strengths and craft compelling statements and biographical summaries for personnel and staffing needs", "Review, inform and contribute to compelling staffing plans as part of Save the Children's proposals", "Stay current on existing United States Government (USG) trends and HR practices; maintain current information on candidate pipelines; and maintain relationships with top-tier talent in the marketplace to attract and retain well-qualified, professional candidates who are leaders in their field", "Team Management (15%)", "Develop, manage, and mentor proposal recruiters (two), ensuring recruitment team provides high-caliber recruitment support and deliverables", "Monitor proposal pipeline and oversee assignments and workload for team", "Train, develop, coach, lead, and supervise staff, clearly communicating organization, division and department priorities, and how their work contributes to our mission, ensuring that the working environment continually fosters diversity, inclusion, and belonging - supporting Save the Children values", "Help to support New Business Development (NBD) new raise targets and grow programs and funding in priority countries for SCUS", "Contribute actively to agency-wide initiatives including task force teams and strategic projects", "Interact regularly with SCUS senior management team members, regional and country directors, and others as applicable to ensure commitment from all key stakeholders and agreement on staffing plans", "Knowledge Management and Learning (5%)", "Collaborate with counterparts in P & C/HR in the US, international offices and other SC members to standardize and improve processes", "These collaboration activities are focused on building capacity and enhancing knowledge around this core function to improve win rates, secure and manage these key programs and help fund business", "Build capacity of SC country office staff to understand and recruit for local talent for current and upcoming USG-funded opportunities"], "Benefits": ["Geo 1 - NY Metro, DC, and other locations with labor costs significantly above national average: Target Salary for this position is $108,800 - $121,600 base salary", "Geo 2 - Locations around the US National Labor Cost Average: Target Salary for this position is $98,600 - $110,200 base salary", "Geo 3 - Locations significantly below the US National Labor Cost Average: Target Salary for this position is $88,400 - $98,800 base salary", "Actual base salary may vary based upon, but not limited to, relevant experience, base salary of internal peers, business sector, and geographic location (more information on job structure is available )", "Employee may be eligible for an incentive program", "Save the Children also offers paid vacation, accrued at least 12 days a year, depending on paygrade and length of service, paid safety and wellness leave of at least 1 day per month worked for a full time employee which is pro rata reduced for employees working less than a full time schedule, and at least 10 paid holidays a year", "Employees may be eligible for additional bonus compensation", "Save the Children US also offers outstanding benefits that include health, dental, vision and life insurances, short-term and long-term disability coverage, an Employee Assistance Program, a retirement savings plan with employer contribution, family leave, paid parental/adoption leave of 60 days, commuter benefits, paid caregiver leave days, 1 paid volunteer day a year, paid critical child illness leave days, dress for your day, and much more"]}, "job_job_title": "Senior director", "job_posting_language": "en", "job_onet_soc": "13107100", "job_onet_job_zone": "4", "job_naics_code": "541613", "job_naics_name": "Marketing Consulting Services"}