{"job_id": "p9JB4Tv0tvOLbNAgAAAAAA==", "employer_name": "Patra Corporation", "employer_logo": "https://lookaside.fbsbx.com/lookaside/crawler/media/?media_id=100057051800545", "employer_website": "http://www.patracorp.com", "employer_company_type": null, "job_publisher": "Glassdoor", "job_employment_type": "FULLTIME", "job_title": "Vice President Business Development", "job_apply_link": "https://www.glassdoor.com/job-listing/vice-president-business-development-patra-corporation-JV_KO0,35_KE36,53.htm?jl=1009136051873", "job_apply_is_direct": false, "job_apply_quality_score": 0.6696, "apply_options": [{"publisher": "Glassdoor", "apply_link": "https://www.glassdoor.com/job-listing/vice-president-business-development-patra-corporation-JV_KO0,35_KE36,53.htm?jl=1009136051873", "is_direct": false}, {"publisher": "Indeed", "apply_link": "https://www.indeed.com/viewjob?jk=7a012f6051d4634f", "is_direct": true}, {"publisher": "Monster", "apply_link": "https://www.monster.com/job-openings/vice-president-business-development-remote-or--fda6d01a-b26a-4321-9a1d-c21cf2c0d1e7", "is_direct": false}, {"publisher": "Jobright AI", "apply_link": "https://jobright.ai/jobs/info/65d60fa89be99df0732110b6", "is_direct": false}], "job_description": "Overview:\n\nPatra is a leading provider of Technology-Enabled Services to the insurance industry. Patra\u2019s team of global experts allow brokers, MGAs, wholesalers, and carriers to capture the Patra Advantage \u2013 profitable growth and organizational value.\n\nPatra powers insurance processes by optimizing the application of people and technology; supporting insurance organizations as they sell, deliver, and manage policies for their customers.\n\nThe Patra sales team is organized into two divisions, Retail and Specialty. The Retail team works with retail insurance brokers/agencies and the Specialty team works with MGA's, Wholesalers, Insurance Carriers, and Insurtech's. The VP of Business Development, Specialty role is within the Specialty sales team.\n\nAbout this job\n\nThe VP of Business Development role is highly process-oriented and well connected in selling services and technology, or BPO to the insurance brokerage industry along with BPO experience. Role will work in results versus quota driven environment, focused on the large and very large insurance broker segment. Candidate will possess knowledge and understanding of business dynamics, vernacular used by MGA's, Wholesalers, and Insurance Carriers, and will have a record of exceptional sales achievement. The ability to undergo a detailed discovery process into the pain points and workflows of our client's business will be essential. A strategic mindset that understands buying personas and the decision-making criteria of our customers will be critical. Individuals will need to be a motivated self-starter with strong communication skills and must have the ability to present to a variety of audiences, and work in a decentralized organization.\n\nResponsibilities:\n\nCore Requirements by Competency:\n\nModern Sales Acuity and Strategic Thinker\n\u2022 Prior experience with the development, documentation, and execution of strategic Account Plans\n\u2022 Strong relationship-building and relationship-management skills\n\u2022 Deal planning and revenue forecasting - frequency and accuracy\n\u2022 Understanding of modern sales methodologies such as MEDDPICC\n\u2022 Enterprise sales experience and clear strategic thinking ability\n\u2022 Defend pricing structure and value in a competitive marketplace where competition could be third party, internal, and/or multiple decision-makers\n\u2022 Experience in contracts and SOWs\n\nInsurance Industry Experience\n\u2022 Enterprise insurance experience and understanding of MGA, Wholesale, and Carrier sectors including the challenges they face engaging with their trading partners\n\u2022 Discuss, present, and fully understand services and technology offered to enterprise clients/prospects\n\u2022 Ability to identify opportunities for growth - that align with Patra Services\n\u2022 Stays abreast and maintain detailed knowledge of current market conditions and technical knowledge in the insurance industry and MGA, Wholesale, and Carrier segments\n\nAccountable\n\u2022 A command and use of a CRM for Account and Deal visibility and forecasting\n\u2022 Closure of New Logo's and Cross Selling (land and expand)\n\u2022 Identify, develop, and structure enterprise proposals as well as enterprise contracts and statements of work (SOWs)\n\u2022 Engage subject matter experts and include them in discussions with clients/prospects throughout the sales process\n\nTeam Player\n\u2022 Actively participate in sales meetings, sales cycles, understand the stages and pipeline, and basic metrics\n\u2022 Coordination & Communication with Operations, Legal, and Executive functions to ensure overall continuity and coordination\n\u2022 Establish and maintain strong and positive relationships with the sales team and throughout the organization as well as with the C-suite clients/prospects\n\u2022 Interpersonal Skills:\n\u2022 Demonstrates the ability to work well with Patra colleagues and clients and with external organizations\n\u2022 Promotes Culture of Respect & Safety:\n\u2022 Demonstrates commitment to personal responsibility and value for safety and respect\n\u2022 Communicates concerns\n\u2022 Uses and promotes safe respectful behaviors based on training and lessons learned\n\nQualifications:\n\nMinimum Requirements - Education and Experience\n\u2022 5 to 10+ years minimum of Sales Experience in the Insurance sector, preferably Wholesale/MGA/Carrier Vertical\n\u2022 Prior B2B Sales Experience with a consistent track record of success\n\u2022 BPO Experience preferred but not required\n\u2022 Bachelor\u2019s degree\n\nAdditional Knowledge, Skills, and Abilities\n\u2022 Ability to travel to customer sites and industry events\n\u2022 High integrity and ability to establish trust\n\u2022 Strong negotiation skills and excellent use of business judgment\n\u2022 Excellent listening, verbal, and written communication skills\n\u2022 Good computer, internet skills, and Microsoft Outlook, Excel, Word, PowerPoint\n\u2022 Professional approach and demeanor\n\nWorking Conditions\n\u2022 Frequent travel by all forms of transportation including: flying, driving, car services, trains, buses\n\u2022 Occasionally stand/walk, writing by hand, lift/carry/push/pull objects that weigh 11-20 pounds\n\u2022 Sort/file paperwork, rarely twist/bend/stoop/squat\n\u2022 Consistent with its obligations under the law, the Patra Corp will provide reasonable accommodation to any employee with a disability who requires accommodation to perform the essential functions of his or her job.\n\nWorking Conditions\n\u2022 Work from home - Ability to work in a decentralized organization\n\u2022 Travel within the Eastern United States and occasionally outside that geographical area\n\u2022 Minimum internet speed of 6 mbps download and 3 mbps upload; no satellite\n\nCompensation\n\u2022 Competitive Salary / Benefits / PTO\n\nPhysical Requirements*\n\u2022 Constantly perform desk-based computer tasks\n\u2022 Frequent sitting\n\u2022 Occasionally stand/walk, writing by hand, use of telephone, lift/carry/push/pull objects that weigh 11-20 pounds\n\u2022 Sort/file paperwork, rarely twist/bend/stoop/squat\n\u2022 Consistent with its obligations under the law, the Patra Corp will provide reasonable accommodation to any employee with a disability who requires accommodation to perform the essential functions of his or her job.\n\u2022 Subject to and expected to comply with all applicable Patra Corp policies and procedures\n\nPatra Corporation is an equal opportunity employer committed to celebrating diversity and creating a safe and inclusive environment for all employees.", "job_is_remote": true, "job_posted_at_timestamp": 1708387200, "job_posted_at_datetime_utc": "2024-02-20T00:00:00.000Z", "job_city": null, "job_state": null, "job_country": "US", "job_latitude": 37.09024, "job_longitude": -95.71289, "job_benefits": ["paid_time_off"], "job_google_link": "https://www.google.com/search?gl=us&hl=en&rciv=jb&q=vice+president+of+business+development&start=30&ibp=htl;jobs#fpstate=tldetail&htivrt=jobs&htiq=vice+president+of+business+development&htidocid=p9JB4Tv0tvOLbNAgAAAAAA%3D%3D", "job_offer_expiration_datetime_utc": "2024-07-12T00:00:00.000Z", "job_offer_expiration_timestamp": 1720742400, "job_required_experience": {"no_experience_required": false, "required_experience_in_months": 60, "experience_mentioned": true, "experience_preferred": true}, "job_required_skills": null, "job_required_education": {"postgraduate_degree": false, "professional_certification": false, "high_school": false, "associates_degree": false, "bachelors_degree": false, "degree_mentioned": true, "degree_preferred": false, "professional_certification_mentioned": false}, "job_experience_in_place_of_education": false, "job_min_salary": null, "job_max_salary": null, "job_salary_currency": null, "job_salary_period": null, "job_highlights": {"Qualifications": ["Individuals will need to be a motivated self-starter with strong communication skills and must have the ability to present to a variety of audiences, and work in a decentralized organization", "Modern Sales Acuity and Strategic Thinker", "Prior experience with the development, documentation, and execution of strategic Account Plans", "Strong relationship-building and relationship-management skills", "Deal planning and revenue forecasting - frequency and accuracy", "Enterprise sales experience and clear strategic thinking ability", "Insurance Industry Experience", "Enterprise insurance experience and understanding of MGA, Wholesale, and Carrier sectors including the challenges they face engaging with their trading partners", "Discuss, present, and fully understand services and technology offered to enterprise clients/prospects", "Stays abreast and maintain detailed knowledge of current market conditions and technical knowledge in the insurance industry and MGA, Wholesale, and Carrier segments", "5 to 10+ years minimum of Sales Experience in the Insurance sector, preferably Wholesale/MGA/Carrier Vertical", "Prior B2B Sales Experience with a consistent track record of success", "Bachelor\u2019s degree", "Ability to travel to customer sites and industry events", "High integrity and ability to establish trust", "Strong negotiation skills and excellent use of business judgment", "Excellent listening, verbal, and written communication skills", "Good computer, internet skills, and Microsoft Outlook, Excel, Word, PowerPoint", "Professional approach and demeanor", "Work from home - Ability to work in a decentralized organization", "Constantly perform desk-based computer tasks", "Occasionally stand/walk, writing by hand, use of telephone, lift/carry/push/pull objects that weigh 11-20 pounds"], "Responsibilities": ["Role will work in results versus quota driven environment, focused on the large and very large insurance broker segment", "A command and use of a CRM for Account and Deal visibility and forecasting", "Closure of New Logo's and Cross Selling (land and expand)", "Identify, develop, and structure enterprise proposals as well as enterprise contracts and statements of work (SOWs)", "Engage subject matter experts and include them in discussions with clients/prospects throughout the sales process", "Team Player", "Actively participate in sales meetings, sales cycles, understand the stages and pipeline, and basic metrics", "Coordination & Communication with Operations, Legal, and Executive functions to ensure overall continuity and coordination", "Establish and maintain strong and positive relationships with the sales team and throughout the organization as well as with the C-suite clients/prospects", "Promotes Culture of Respect & Safety:", "Demonstrates commitment to personal responsibility and value for safety and respect", "Communicates concerns", "Uses and promotes safe respectful behaviors based on training and lessons learned", "Frequent travel by all forms of transportation including: flying, driving, car services, trains, buses", "Occasionally stand/walk, writing by hand, lift/carry/push/pull objects that weigh 11-20 pounds", "Consistent with its obligations under the law, the Patra Corp will provide reasonable accommodation to any employee with a disability who requires accommodation to perform the essential functions of his or her job", "Travel within the Eastern United States and occasionally outside that geographical area", "Minimum internet speed of 6 mbps download and 3 mbps upload; no satellite", "Frequent sitting"], "Benefits": ["Competitive Salary / Benefits / PTO"]}, "job_job_title": "Business", "job_posting_language": "en", "job_onet_soc": "11101100", "job_onet_job_zone": "5"}