{"job_id": "hqbXkeYTg2FXuDmtAAAAAA==", "employer_name": "Semrush", "employer_logo": "https://cdn.semrush.com/__static__/semrush-logo-700.jpg", "employer_website": "http://www.semrush.com", "employer_company_type": null, "job_publisher": "LinkedIn", "job_employment_type": "FULLTIME", "job_title": "Mid-Market Senior Sales Manager (US&Canada Markets)", "job_apply_link": "https://www.linkedin.com/jobs/view/mid-market-senior-sales-manager-us-canada-markets-at-semrush-3792830532", "job_apply_is_direct": false, "job_apply_quality_score": 0.6311, "apply_options": [{"publisher": "LinkedIn", "apply_link": "https://www.linkedin.com/jobs/view/mid-market-senior-sales-manager-us-canada-markets-at-semrush-3792830532", "is_direct": false}, {"publisher": "Jobright AI", "apply_link": "https://jobright.ai/jobs/info/65a28da8327606734c2ffc6d", "is_direct": false}], "job_description": "Hi there!\n\nWe are Semrush, a global IT company developing our own product \u2013 a platform for digital marketers. New stars are born here, so don\u2019t miss your chance. This is our Sales Manager (US and Canada Markets) role for those who can find a common language with anyone in the world.\n\nTasks in the role\n\u2022 Start with a team of eight Mid-Market Account Executives and continue to hire and develop the team to meet the needs of the territory growth you deliver.\n\u2022 Create situational playbooks and sales plays to expand business within an existing customer base.\u202f\n\u2022 Identify new market opportunities, customer segments, and sales channels to drive revenue.\n\u2022 Be the Executive contact in key customer deals to help your team close business.\n\u2022 Build a tight partnership with the GTM Enablement team to uplevel critical\u202fAE skills/competencies.\u202f\n\u2022 Develop and execute a comprehensive sales strategy for the enterprise segment, aligning it to business objectives.\u202f\n\u2022 Cultivate and maintain strong relationships with key enterprise customers.\n\u2022 Create a winning\u202fculture\u202fof high performance and an engaged team by achieving below-average regrettable attrition and high AE attainment (100%+).\u202f\n\nWho we are looking for\n\u2022 At least eight years of relevant sales experience, with 3+ years of people management with a majority of time spent in the MM & Enterprise.\n\u2022 A builder mindset and the ability to see and execute the opportunity ahead. A track record in doing so.\n\u2022 Proven track record of\u202frecruiting, hiring,\u202fand onboarding A-players.\u202f\n\u2022 Experience coaching and enabling with a track record\u202fof developing top-tier sellers.\u202f\n\u2022 Advanced with building and executing a customer-expansion strategy.\n\u2022 Domain expertise\u202fspecifically within SEO, digital marketing, and martech (preferred, but not needed).\n\u2022 Strong collaboration with cross-functional teams, including marketing and product development, to develop effective sales plans & strategies.\n\u2022 Diversity evangelism and sponsorship.\n\u2022 Excellent Judgment: Demonstrates sound decision-making skills and the ability to assess complex situations to make informed choices.\n\u2022 Ability to Build and Develop a Team: Excels in hiring top talent, developing team members' skills, and fostering a high-performing culture within the organization.\n\u2022 High-Performance Culture: Sets and maintains exceptionally high standards for themselves and their team, constantly coaching for excellence in all aspects of work.\n\u2022 Strategic Thinking with Tactical Execution: Balances strategic thinking with a hands-on approach to ensure effective execution of plans and initiatives.\n\u2022 Innovation Mindset: Encourages and expects innovation from their team, fostering a culture of creativity and continuous improvement in a psychologically safe place.\n\u2022 Ambitious and Conviction-Driven: Sets ambitious goals and possesses the confidence and determination to pursue them with conviction.\n\u2022 Results-Oriented: Focuses on achieving measurable results, meeting targets, and driving impactful outcomes.\n\u2022 Inspirational Leadership: As a key part of the leadership team. Inspires and motivates others, fostering passion and commitment within the team to achieve shared goals.\n\nThey say there are no perfect candidates, but that might well be you, if\n\u2022 You thrive in a fast-paced, team environment with a high drive for experimentation.\n\u2022 You will use your strategic skills to deal with ambiguity, manage timely decisions, drive vision and purpose, and manage innovation.\n\u2022 Martech and/or domain experience is strongly preferred.\n\u2022 Your people skills will build effective teams and resolve conflicts while developing, inspiring, and motivating others.\n\u2022 Your foundational skills include managerial courage, a drive for results, planning, and organizing. The ability to problem solve, drive change, manage and measure others\u2019 work, manage time, and communicate.\n\nA Bit About The Team\n\nThe Snr Sales Manager for Mid-Market is a key leadership position responsible for driving sales growth and managing a high-performing international Sales Org. Partnering with and reporting to the Director of Sales for MM & Enterprise, this leader will build and lead a high-performing sales team through recruiting, coaching, developing, and motivating the organization to overachieve revenue targets.\n\nYour passion for investing in and developing high-potential enterprise sellers, along with the ability to develop and deploy a repeatable enterprise strategy, will make you a frontrunner for this role. This is a unique opportunity to help shape and accelerate our success at Semrush.\n\nWe will try to create all the right conditions for you to work and rest comfortably\n\u2022 This offer stands for the \u201chybrid\u201d work format: some days, you work from the office, and some #wfh. Trust us, it\u2019s an efficient way of work. Proven!\n\u2022 Low-cost medical, dental, and vision plans.\n\u2022 Dependent Care Savings Accounts and Flexible Spending Accounts.\n\u2022 Employee Assistance Program.\n\u2022 401(k) plan with flexible ways to save and fully vested employer match up to 4%\n\u2022 Unlimited PTO.\n\u2022 Paid parental leave.\n\u2022 Short-term and Long-term Disability.\n\u2022 Accidental death and dismemberment (AD&D) insurance, Life Insurance.\n\u2022 Travel Insurance.\n\u2022 Corporate Events.\n\u2022 Snacks, coffee, tea.\n\u2022 Free Parking for employees (Prudential Center)\n\nFinally, a Little More About Our Company\n\nWe\u2019ve been developing our product for 15 years and have been awarded G2's Top 100 Software Products, Global and US Search Awards 2021, Great Place to Work Certification, Deloitte Technology Fast 500 and many more. In March 2021 Semrush went public and started trading on the NYSE with the SEMR ticker.\n\n10,000,000+ users in America, Europe, Asia, and Australia have already tried Semrush, and over 1,000 people around the world are working on its development. The Semrush team is constantly growing.\n\nSemrush is an equal opportunity employer. We celebrate diversity and are committed to creating an inclusive environment for all employees. We do not discriminate based upon race, religion, creed, color, national origin, sex, pregnancy, sexual orientation, gender identity, gender expression, age, ancestry, physical or mental disability, or medical condition including medical characteristics, genetic identity, marital status, military service, or any other classification protected by applicable local, state or federal laws. All employment decisions are based on business needs, job requirements, merit, and individual qualifications.\n\nAnna\n\nTalent Acquisition Specialist\n\u2022 herrera@semrush.com", "job_is_remote": true, "job_posted_at_timestamp": 1709300444, "job_posted_at_datetime_utc": "2024-03-01T13:40:44.000Z", "job_city": null, "job_state": null, "job_country": "US", "job_latitude": 37.09024, "job_longitude": -95.71289, "job_benefits": ["dental_coverage", "retirement_savings", "paid_time_off", "health_insurance"], "job_google_link": "https://www.google.com/search?gl=us&hl=en&rciv=jb&q=senior+sales+director&start=50&ibp=htl;jobs#fpstate=tldetail&htivrt=jobs&htiq=senior+sales+director&htidocid=hqbXkeYTg2FXuDmtAAAAAA%3D%3D", "job_offer_expiration_datetime_utc": "2024-04-26T05:03:54.000Z", "job_offer_expiration_timestamp": 1714107834, "job_required_experience": {"no_experience_required": false, "required_experience_in_months": 96, "experience_mentioned": true, "experience_preferred": true}, "job_required_skills": null, "job_required_education": {"postgraduate_degree": false, "professional_certification": false, "high_school": false, "associates_degree": false, "bachelors_degree": true, "degree_mentioned": false, "degree_preferred": false, "professional_certification_mentioned": true}, "job_experience_in_place_of_education": false, "job_min_salary": null, "job_max_salary": null, "job_salary_currency": null, "job_salary_period": null, "job_highlights": {"Qualifications": ["At least eight years of relevant sales experience, with 3+ years of people management with a majority of time spent in the MM & Enterprise", "A builder mindset and the ability to see and execute the opportunity ahead", "A track record in doing so", "Proven track record of\u202frecruiting, hiring,\u202fand onboarding A-players.\u202f", "Experience coaching and enabling with a track record\u202fof developing top-tier sellers.\u202f", "Advanced with building and executing a customer-expansion strategy", "Strong collaboration with cross-functional teams, including marketing and product development, to develop effective sales plans & strategies", "Diversity evangelism and sponsorship", "Excellent Judgment: Demonstrates sound decision-making skills and the ability to assess complex situations to make informed choices", "Ability to Build and Develop a Team: Excels in hiring top talent, developing team members' skills, and fostering a high-performing culture within the organization", "High-Performance Culture: Sets and maintains exceptionally high standards for themselves and their team, constantly coaching for excellence in all aspects of work", "Strategic Thinking with Tactical Execution: Balances strategic thinking with a hands-on approach to ensure effective execution of plans and initiatives", "Innovation Mindset: Encourages and expects innovation from their team, fostering a culture of creativity and continuous improvement in a psychologically safe place", "Ambitious and Conviction-Driven: Sets ambitious goals and possesses the confidence and determination to pursue them with conviction", "Results-Oriented: Focuses on achieving measurable results, meeting targets, and driving impactful outcomes", "Inspirational Leadership: As a key part of the leadership team", "You thrive in a fast-paced, team environment with a high drive for experimentation", "You will use your strategic skills to deal with ambiguity, manage timely decisions, drive vision and purpose, and manage innovation", "Your people skills will build effective teams and resolve conflicts while developing, inspiring, and motivating others", "Your foundational skills include managerial courage, a drive for results, planning, and organizing", "The ability to problem solve, drive change, manage and measure others\u2019 work, manage time, and communicate"], "Responsibilities": ["Start with a team of eight Mid-Market Account Executives and continue to hire and develop the team to meet the needs of the territory growth you deliver", "Create situational playbooks and sales plays to expand business within an existing customer base.\u202f", "Identify new market opportunities, customer segments, and sales channels to drive revenue", "Be the Executive contact in key customer deals to help your team close business", "Build a tight partnership with the GTM Enablement team to uplevel critical\u202fAE skills/competencies.\u202f", "Develop and execute a comprehensive sales strategy for the enterprise segment, aligning it to business objectives.\u202f", "Cultivate and maintain strong relationships with key enterprise customers", "Create a winning\u202fculture\u202fof high performance and an engaged team by achieving below-average regrettable attrition and high AE attainment (100%+).\u202f", "Inspires and motivates others, fostering passion and commitment within the team to achieve shared goals", "The Snr Sales Manager for Mid-Market is a key leadership position responsible for driving sales growth and managing a high-performing international Sales Org", "Partnering with and reporting to the Director of Sales for MM & Enterprise, this leader will build and lead a high-performing sales team through recruiting, coaching, developing, and motivating the organization to overachieve revenue targets", "Your passion for investing in and developing high-potential enterprise sellers, along with the ability to develop and deploy a repeatable enterprise strategy, will make you a frontrunner for this role", "This offer stands for the \u201chybrid\u201d work format: some days, you work from the office, and some #wfh"], "Benefits": ["Low-cost medical, dental, and vision plans", "Dependent Care Savings Accounts and Flexible Spending Accounts", "Employee Assistance Program", "401(k) plan with flexible ways to save and fully vested employer match up to 4%", "Unlimited PTO", "Paid parental leave", "Short-term and Long-term Disability", "Accidental death and dismemberment (AD&D) insurance, Life Insurance", "Travel Insurance"]}, "job_job_title": "Sales manager", "job_posting_language": "en", "job_onet_soc": "11202200", "job_onet_job_zone": "4"}