{"job_id": "L1uZIcaAVBImR7V6AAAAAA==", "employer_name": "Microsoft", "employer_logo": "https://c.s-microsoft.com/en-us/CMSImages/ImgOne.jpg?version=D418E733-821C-244F-37F9-DC865BDEFEC0", "employer_website": "http://www.microsoft.com", "employer_company_type": "Information", "job_publisher": "LinkedIn", "job_employment_type": "FULLTIME", "job_title": "Sr. Data Scientist", "job_apply_link": "https://www.linkedin.com/jobs/view/sr-data-scientist-at-microsoft-3848971604", "job_apply_is_direct": false, "job_apply_quality_score": 0.6349, "apply_options": [{"publisher": "LinkedIn", "apply_link": "https://www.linkedin.com/jobs/view/sr-data-scientist-at-microsoft-3848971604", "is_direct": false}, {"publisher": "Indeed", "apply_link": "https://www.indeed.com/viewjob?jk=60493dea2d4860e5", "is_direct": false}, {"publisher": "Glassdoor", "apply_link": "https://www.glassdoor.com/job-listing/sr-data-scientist-microsoft-JV_KO0,17_KE18,27.htm?jl=1009182350212", "is_direct": false}, {"publisher": "Adzuna", "apply_link": "https://www.adzuna.com/details/4607082186", "is_direct": false}], "job_description": "Do you enjoy solving problems, looking at problems through a different lens, and working closely with customers to innovate new solutions to complex problems? Do you jump with excitement at the opportunity to identify trends and provide unique business solutions? Do you want to join a team where learning about a new technology or solution is part of our work every day?\n\nThe Industry Solutions Delivery (ISD) Engineering & Architecture Group (EAG) is a global consulting and engineering organization that supports our most complex and leading-edge customer engagements. Driving early-stage deliveries, enhances ISD\u2019s technical capabilities, and partnering with others to develop approaches, innovative solutions, and engineering standards in order to set our sales and delivery teams up for success. Leveraging the principles of model, care, and coach, we provide consistent high-quality customer experience through technical and AI leadership and IP capture centered on delivery truth.\n\nWe are hiring a Sr. Data Scientist with deep expertise in machine learning, AI and a track record of developing production ML/AI solutions that are business impactful. As part of our team, you will be working side-by-side with high-impact engineers and strategic customers to solve complex problems. You will communicate trends and innovative solutions to stakeholders. You will work cross-functionally with several teams including engineering crews, product teams, and program management to deploy business solutions.\n\nOur team prides itself on embracing a growth mindset, inspiring excellence, and encouraging everyone to share their unique viewpoints and be their authentic selves. Join us and help create life-changing innovations that impact billions around the world!\n\nMicrosoft\u2019s mission is to empower every person and every organization on the planet to achieve more. As employees we come together with a growth mindset, innovate to empower others and collaborate to realize our shared goals. Each day we build on our values of respect, integrity, and accountability to create a culture of inclusion where everyone can thrive at work and beyond.\n\nResponsibilities\n\nBusiness Understanding and Impact\n\u2022 Learns and understands project objectives and requirements from a business perspective. Assists senior leads with the assessment of a project, including risks, contingencies, requirements, assumptions, and constraints. Contributes to the development of a project plan. Shares insights with stakeholders based on direct work.\n\nData Preparation and Understanding\n\u2022 Assists with initial data collection and familiarizes self with data in order to identify quality problems, discover insights into the data, and/or detect subsets to form hypotheses.\n\u2022 Understands which analysis techniques are appropriate for data and which key technologies and tools are necessary for data exploration (e.g., structured query language [SQL], Python).\n\u2022 Leverages data analysis knowledge to clean, transform, analyze, integrate, and organize data to the level required by the analysis techniques selected. Contributes to the description and exploration of data.\n\u2022 Develops foundational understanding of methodology and standard statistical options and when they should be used. Understands and follows ethics and privacy policies when collecting and preparing data.\n\u2022 Adheres to Microsoft's privacy policy related to collecting and preparing data. Identifies data integrity problems.\n\nModeling and Statistical Analysis\n\u2022 Learns and understands various modeling techniques used within the team (e.g., linear regression, multiple regression, decision-tree building, neural network generation, support machines, derivatives).\n\u2022 Runs model tools on prepared dataset to create one or more models, seeking guidance as needed.\n\u2022 Contributes to the research, identification, prototyping, and productizing of machine learning (ML)/artificial intelligence (AI) techniques and algorithms.\n\u2022 Collaborates with project managers and development engineers to design machine learning and artificial intelligence-driven features in the product.\n\nEvaluation\n\u2022 Understands linkage between achieved model and business objectives. Assists with testing models on test applications and on real data or production data.\n\u2022 Analyzes model performance. Incorporates implicit and explicit customer feedback into model evaluation.\n\u2022 Conducts review of data analysis and modeling techniques to determine factors that may have been overlooked or need to be reexamined. Contributes to the summary of the review process.\n\nIndustry and Research Knowledge/Opportunity Identification\n\u2022 Learns and understands the current state of the industry, including knowledge of tools, techniques, strategies, and processes that can be utilized to improve process efficiency and performance.\n\u2022 Maintains knowledge of current trends within the discipline. Attends internal research conferences and participates in on-hands training, when appropriate. Actively contributes to the body of thought leadership and intellectual property (IP) best practices.\n\nCoding and Debugging\n\u2022 Writes readable code for a specific feature, enhancement and/or model, seeking guidance when needed. Contributes to the development, testing, and implementation of changes to optimize code and improve the reliability of systems/solutions.\n\u2022 Develops an understanding of proper debugging techniques such as locating, isolating, and resolving errors and/or defects.\n\u2022 Understands known issues and learns from senior developers/team members. Develops foundational understanding of Agile methodology and when they should be used. Contributes to documentation for productionalisation.\n\nBusiness Management\n\u2022 Develops understanding of data structures and their relationship to Microsoft's customer business. Observes senior engineers and learns best practices in identifying growth opportunities, understanding strategy goals, customer- and product-strategy goals, and exploring opportunities for machine learning (ML) application, seeking guidance when needed. Understands business goals of the customer, per engagement basis.\n\nCustomer/Partner Orientation\n\u2022 Leverages understanding of data science and business to examine projects through a customer-oriented focus. Manages customer expectations regarding project/product progress and timeline. Takes responsibility to enhance customer excellence. Assists and learns from senior team members to interpret results, develop insights, and communicate results to customers. Possesses basic understanding about model accuracies dependency on data quality and able to articulate it in customer discussions.\n\nOther: Embody our culture and values\n\nQualifications\n\nRequired/Minimum Qualifications\n\u2022 Doctorate in Data Science, Mathematics, Statistics, Econometrics, Economics, Operations Research, Computer Science, or related field AND 1+ year(s) data-science experience (e.g., managing structured and unstructured data, applying statistical techniques and reporting results)\n\u2022 OR Master's Degree in Data Science, Mathematics, Statistics, Econometrics, Economics, Operations Research, Computer Science, or related field AND 3+ years data-science experience (e.g., managing structured and unstructured data, applying statistical techniques and reporting results.\n\u2022 OR Bachelor's Degree in Data Science, Mathematics, Statistics, Econometrics, Economics, Operations Research, Computer Science, or related field AND 5+ years data-science experience (e.g., managing structured and unstructured data, applying statistical techniques and reporting results.\n\u2022 OR equivalent experience.\n\u2022 2+ years customer-facing, project-delivery experience, professional services, and/or consulting experience.\n\nAdditional Or Preferred Qualifications\n\u2022 Doctorate in Data Science, Mathematics, Statistics, Econometrics, Economics, Operations Research, Computer Science, OR related field AND 3+ years data-science experience (e.g., managing structured and unstructured data, applying statistical techniques and reporting results)\n\u2022 OR Master's Degree in Data Science, Mathematics, Statistics, Econometrics, Economics, Operations Research, Computer Science, OR related field AND 5+ years data-science experience (e.g., managing structured and unstructured data, applying statistical techniques and reporting results)\n\u2022 OR Bachelor's Degree in Data Science, Mathematics, Statistics, Econometrics, Economics, Operations Research, Computer Science, OR related field AND 7+ years data-science experience (e.g., managing structured and unstructured data, applying statistical techniques and reporting results)\n\u2022 OR equivalent experience.\n\nData Science IC4 - The typical base pay range for this role across the U.S. is USD $112,000 - $218,400 per year. There is a different range applicable to specific work locations, within the San Francisco Bay area and New York City metropolitan area, and the base pay range for this role in those locations is USD $145,800 - $238,600 per year. Certain roles may be eligible for benefits and other compensation.\n\nFind additional benefits and pay information here: https://careers.microsoft.com/us/en/us-corporate-pay\n\n#ISEngineering\n\nMicrosoft is an equal opportunity employer. Consistent with applicable law, all qualified applicants will receive consideration for employment without regard to age, ancestry, citizenship, color, family or medical care leave, gender identity or expression, genetic information, immigration status, marital status, medical condition, national origin, physical or mental disability, political affiliation, protected veteran or military status, race, ethnicity, religion, sex (including pregnancy), sexual orientation, or any other characteristic protected by applicable local laws, regulations and ordinances. If you need assistance and/or a reasonable accommodation due to a disability during the application process, read more about requesting accommodations.", "job_is_remote": true, "job_posted_at_timestamp": 1710191863, "job_posted_at_datetime_utc": "2024-03-11T21:17:43.000Z", "job_city": null, "job_state": null, "job_country": "US", "job_latitude": 37.09024, "job_longitude": -95.71289, "job_benefits": ["health_insurance"], "job_google_link": "https://www.google.com/search?gl=us&hl=en&rciv=jb&q=senior+data+scientist&start=70&ibp=htl;jobs#fpstate=tldetail&htivrt=jobs&htiq=senior+data+scientist&htidocid=L1uZIcaAVBImR7V6AAAAAA%3D%3D", "job_offer_expiration_datetime_utc": "2024-04-10T21:17:43.000Z", "job_offer_expiration_timestamp": 1712783863, "job_required_experience": {"no_experience_required": false, "required_experience_in_months": 36, "experience_mentioned": true, "experience_preferred": false}, "job_required_skills": null, "job_required_education": {"postgraduate_degree": false, "professional_certification": false, "high_school": false, "associates_degree": false, "bachelors_degree": true, "degree_mentioned": true, "degree_preferred": true, "professional_certification_mentioned": false}, "job_experience_in_place_of_education": false, "job_min_salary": null, "job_max_salary": null, "job_salary_currency": null, "job_salary_period": null, "job_highlights": {"Qualifications": ["Learns and understands the current state of the industry, including knowledge of tools, techniques, strategies, and processes that can be utilized to improve process efficiency and performance", "OR Master's Degree in Data Science, Mathematics, Statistics, Econometrics, Economics, Operations Research, Computer Science, or related field AND 3+ years data-science experience (e.g., managing structured and unstructured data, applying statistical techniques and reporting results", "OR equivalent experience", "2+ years customer-facing, project-delivery experience, professional services, and/or consulting experience"], "Responsibilities": ["As part of our team, you will be working side-by-side with high-impact engineers and strategic customers to solve complex problems", "You will communicate trends and innovative solutions to stakeholders", "You will work cross-functionally with several teams including engineering crews, product teams, and program management to deploy business solutions", "Learns and understands project objectives and requirements from a business perspective", "Assists senior leads with the assessment of a project, including risks, contingencies, requirements, assumptions, and constraints", "Contributes to the development of a project plan", "Shares insights with stakeholders based on direct work", "Assists with initial data collection and familiarizes self with data in order to identify quality problems, discover insights into the data, and/or detect subsets to form hypotheses", "Understands which analysis techniques are appropriate for data and which key technologies and tools are necessary for data exploration (e.g., structured query language [SQL], Python)", "Leverages data analysis knowledge to clean, transform, analyze, integrate, and organize data to the level required by the analysis techniques selected", "Contributes to the description and exploration of data", "Develops foundational understanding of methodology and standard statistical options and when they should be used", "Understands and follows ethics and privacy policies when collecting and preparing data", "Adheres to Microsoft's privacy policy related to collecting and preparing data", "Identifies data integrity problems", "Modeling and Statistical Analysis", "Learns and understands various modeling techniques used within the team (e.g., linear regression, multiple regression, decision-tree building, neural network generation, support machines, derivatives)", "Runs model tools on prepared dataset to create one or more models, seeking guidance as needed", "Contributes to the research, identification, prototyping, and productizing of machine learning (ML)/artificial intelligence (AI) techniques and algorithms", "Collaborates with project managers and development engineers to design machine learning and artificial intelligence-driven features in the product", "Understands linkage between achieved model and business objectives", "Assists with testing models on test applications and on real data or production data", "Analyzes model performance", "Incorporates implicit and explicit customer feedback into model evaluation", "Conducts review of data analysis and modeling techniques to determine factors that may have been overlooked or need to be reexamined", "Contributes to the summary of the review process", "Maintains knowledge of current trends within the discipline", "Attends internal research conferences and participates in on-hands training, when appropriate", "Actively contributes to the body of thought leadership and intellectual property (IP) best practices", "Coding and Debugging", "Writes readable code for a specific feature, enhancement and/or model, seeking guidance when needed", "Contributes to the development, testing, and implementation of changes to optimize code and improve the reliability of systems/solutions", "Develops an understanding of proper debugging techniques such as locating, isolating, and resolving errors and/or defects", "Understands known issues and learns from senior developers/team members", "Contributes to documentation for productionalisation", "Develops understanding of data structures and their relationship to Microsoft's customer business", "Observes senior engineers and learns best practices in identifying growth opportunities, understanding strategy goals, customer- and product-strategy goals, and exploring opportunities for machine learning (ML) application, seeking guidance when needed", "Understands business goals of the customer, per engagement basis", "Leverages understanding of data science and business to examine projects through a customer-oriented focus", "Manages customer expectations regarding project/product progress and timeline", "Takes responsibility to enhance customer excellence", "Assists and learns from senior team members to interpret results, develop insights, and communicate results to customers", "Possesses basic understanding about model accuracies dependency on data quality and able to articulate it in customer discussions"], "Benefits": ["There is a different range applicable to specific work locations, within the San Francisco Bay area and New York City metropolitan area, and the base pay range for this role in those locations is USD $145,800 - $238,600 per year", "Certain roles may be eligible for benefits and other compensation"]}, "job_job_title": "Data scientist", "job_posting_language": "en", "job_onet_soc": "15111100", "job_onet_job_zone": "5", "job_naics_code": "511210", "job_naics_name": "Software Publishers"}