{"job_id": "DwJbLBCBDyMh5PBgAAAAAA==", "employer_name": "Persefoni AI", "employer_logo": "https://s6-recruiting.cdn.greenhouse.io/external_greenhouse_job_boards/logos/400/078/100/original/Persefoni_Logo_Emblem_Yellow.png?1668807686", "employer_website": "http://persefoni.com", "employer_company_type": null, "job_publisher": "Untapped", "job_employment_type": "FULLTIME", "job_title": "Senior Sales Director", "job_apply_link": "https://www.untapped.io/app/discover/jobs/persefoni-ai/senior-sales-director/6ad6170c-5f36-425f-96d7-bc6ae725ed48", "job_apply_is_direct": false, "job_apply_quality_score": 0.5614, "apply_options": [{"publisher": "Untapped", "apply_link": "https://www.untapped.io/app/discover/jobs/persefoni-ai/senior-sales-director/6ad6170c-5f36-425f-96d7-bc6ae725ed48", "is_direct": false}], "job_description": "Company Introduction & Mission\n\nPersefoni\u2019s mission is to enable every organization and person with the technology to positively impact the health of planet Earth. Persefoni has created an all-in-one platform that allows organizations to measure, analyze, and reduce their Enterprise Carbon Footprint. Our goal is to provide our customers unprecedented visibility and insights into the impact their organization has on the environment. Leveraging the latest breakthroughs in data science and software, our technology will empower teams and leaders to mobilize their organizations to disclose their organization's climate posture with the same confidence as their financial disclosure, continuously improve, and set and track science-based climate targets. One of Persefoni\u2019s target customer segments is the Private Markets, which includes Private Equity, Private Credit, Venture Capital, Real Assets, Fund of Funds, Co-investors, and Secondaries.\n\nOur Core Values\n\u2022 Sustainability - We are committed to sustainable business practices across our entire operation and culture. We go beyond achieving balance. We are a net-positive contributor to the environment, our employee\u2019s lives, and the global community.\n\u2022 Impact - We are focused on and passionate about tackling the biggest and hardest problems that will have the greatest impact. We create significant, not incremental, solutions.\n\u2022 Collaboration - We are always aligned in our goals and efforts to create the most impactful technologies possible. Constant cooperation across our company, customers, and partners is our standard mode of operating.\n\u2022 Equality - We value and respect people and organizations of all backgrounds. Ours is a culture of innovation, creativity, diversity of thought, and inclusion.\n\nAbout the Department\n\nThe Solutions team at Persefoni encompasses all customer-facing employees engaging with organizations to enable them to calculate, manage, and report on their carbon footprint utilizing the Persefoni SaaS platform, including the Sales organization. The objective of the Solutions group as a whole is to provide technical and business expertise to customers and internal teams both pre and post-sale to ensure customers are realizing a return on their Persefoni investment. The mission of the Sales team is to provide a solution-oriented buying experience for every customer that engenders trust and confidence in Persefoni and enables significant and sustainable growth for the company.\n\nAbout The Role\n\nThe Senior Sales Director role focused on the Private Markets requires solution selling, Private Markets fundraising/business development, or enterprise software sales experience. This is a commercially-focused role that will suit a customer facing field sales leader in the US and involve collaboration with Persefoni\u2019s Climate Solution Directors, Customer Success, Product, Marketing and engineering organizations. You will have a successful track record in the development of sales, business development, or capital-raising strategy and execution, building brand awareness and sales across a broad portfolio of clients, and a demonstrable passion for global sustainability/carbon/climate related developments.\n\nAs a key member of the Persefoni Solutions Sales team, the Senior Sales Director will be responsible for growing and retaining annual recurring revenue (ARR). This will involve building relationships with prospective customers; selling and closing new platform subscriptions; and successfully preparing customers for platform onboarding. The ability to lead through influence across direct and indirect reporting relationships is critical, and experience in building and leading a team would be advantageous.\n\nResponsibilities (What we expect)\n\u2022 Lead customer facing activities including inbound lead triage, first contact, discovery calls, platform demos, follow-up communication, presenting Persefoni solutions, coordinating internal resources, strategizing on proposals, and negotiating and closing sales\n\u2022 Grow annual recurring revenue (ARR), helping the Persefoni team meet quarterly and annual goals\n\u2022 Steward the sales process to support end-to-end customer acquisition, including winning new business, account management, revenue retention, revenue expansion, and an ongoing positive experience of successful impact for our customers\n\u2022 Collaborate with various Persefoni teams such as marketing, legal, product, solution directors, and customer success to deliver a unified customer experience\n\u2022 Maintain an accurate CRM with information across the sales lifecycle to include past events and planned tasks, relevant customer details, and sales revenue forecasts\n\u2022 Ensure that all required paperwork and documentation is properly organized, executed, and stored to successfully book subscriptions and manage customer accounts\n\u2022 Identify opportunities for participation in relevant industry events, engagements & potential partnerships\n\nRole Expectations\n\u2022 Within your first 2 weeks, you will be able to:\n\u2022 Articulate how Persefoni incorporates carbon accounting standards and sustainability reporting frameworks in its solutions\n\u2022 Demonstrate the Persefoni platform and bring together the appropriate Persefoni resources in customer facing meetings\n\u2022 Be proficient in using Persefoni systems and processes to appropriately track and report on relevant sales activities and customer information\n\u2022 Within your first 2 months:\n\u2022 Demonstrated expertise in managing a conversation with a prospective Persefoni customer\n\u2022 Ability to lead discovery, platform demo, and follow-up conversations with prospective customers\n\u2022 Ability to answer customers\u2019 frequently asked questions on carbon accounting, climate change, and the Persefoni platform\n\u2022 Within your first year, you will have:\n\u2022 Helped the Persefoni team achieve strategic market share and revenue goals\n\u2022 Identified areas for strategic company revenue growth within your defined territory assignment & contributed to internal systems, processes, product and sales material development to support proactively tackling new opportunities\n\nSkills & Experience\n\u2022 At least seven (7) years of total experience across: solutions sales, Private Markets business development or fundraising, and/or enterprise software sales experience\n\u2022 Expertise in selling software solutions into Private Markets customers is a plus\n\u2022 Ability to manage relationships internally and externally with individuals ranging from individual contributors to the C-suite, in addition to working/negotiating with C-suite\n\u2022 An engaging phone & video presence in addition to exemplary written and verbal skills\n\u2022 Experience influencing change in complex, global organizations & comfortable operating within a fast-paced, global team\n\u2022 Expertise in understanding value creation based on customer needs with full sales cycle experience to include qualifying opportunities, strategic outreach, pitching solutions, RFP response management, developing and presenting proposals, running / coordinating technical workshops, negotiating contracts and closing sales\n\u2022 A bachelor\u2019s degree from an accredited university\n\nInterview Process\n\u2022 Step 1: Interview with Talent Acquisition\n\u2022 Step 2: Interview with Global Head of Sales\n\u2022 Step 3: Interview with VP of Private Markets\n\u2022 Step 4: Final interview with President of Solutions Group\n\u2022 Step 5: Offer extended\n\u2022 Step 6: Background check and onboarding\n\nBenefit Offerings\n\u2022 Generous PTO policy\n\u2022 401k with company match\n\u2022 Medical, dental, and vision insurance\n\u2022 Disability, life insurance\n\u2022 Equity incentive plan\n\nPersefoni is an Equal Opportunity employer\n\nOne of our company Core Values is 'Equality' which emphasizes our commitment to value and respect people and organizations of all backgrounds. We proudly bring this to life by fostering a culture of innovation, creativity, diversity of thought, and inclusion.\n\nWe strive for each of our team members to be able to show up for work every day as their genuine selves. Similar to the reverence given to Earth\u2019s biodiversity, we recognize the vast potential that exists when all of the facets of diversity within our team are appreciated and illuminated. This policy extends to all aspects of our employment practices.\n\nAs you are considering us as a potential employer, it's important to ensure you are aware we currently have a COVID-19 vaccination policy in place for all U.S. employees.\n\nThe key tenets of our policy are:\n\u2022 Fully remote employees, those who are not doing any travel and do not have any in-person interactions related to their work, are not required to be vaccinated.\n\u2022 Employees who travel on behalf of Persefoni and/or have in-person interactions related to their work, are required to be fully vaccinated and boosted.\n\u2022 All employees, regardless of vaccination status, are required to inform us of whether they are fully vaccinated or not.\n\u2022 We provide the opportunity for employees to request special exceptions to the policy for medical, religious, and other reasons", "job_is_remote": false, "job_posted_at_timestamp": 1653067829, "job_posted_at_datetime_utc": "2022-05-20T17:30:29.000Z", "job_city": null, "job_state": null, "job_country": "US", "job_latitude": 37.09024, "job_longitude": -95.71289, "job_benefits": ["retirement_savings", "health_insurance", "dental_coverage", "paid_time_off"], "job_google_link": "https://www.google.com/search?gl=us&hl=en&rciv=jb&q=senior+sales+director&start=10&ibp=htl;jobs#fpstate=tldetail&htivrt=jobs&htiq=senior+sales+director&htidocid=DwJbLBCBDyMh5PBgAAAAAA%3D%3D", "job_offer_expiration_datetime_utc": null, "job_offer_expiration_timestamp": null, "job_required_experience": {"no_experience_required": false, "required_experience_in_months": 84, "experience_mentioned": true, "experience_preferred": false}, "job_required_skills": null, "job_required_education": {"postgraduate_degree": false, "professional_certification": false, "high_school": false, "associates_degree": false, "bachelors_degree": false, "degree_mentioned": true, "degree_preferred": false, "professional_certification_mentioned": false}, "job_experience_in_place_of_education": false, "job_min_salary": null, "job_max_salary": null, "job_salary_currency": null, "job_salary_period": null, "job_highlights": {"Qualifications": ["At least seven (7) years of total experience across: solutions sales, Private Markets business development or fundraising, and/or enterprise software sales experience", "Ability to manage relationships internally and externally with individuals ranging from individual contributors to the C-suite, in addition to working/negotiating with C-suite", "An engaging phone & video presence in addition to exemplary written and verbal skills", "Experience influencing change in complex, global organizations & comfortable operating within a fast-paced, global team", "Expertise in understanding value creation based on customer needs with full sales cycle experience to include qualifying opportunities, strategic outreach, pitching solutions, RFP response management, developing and presenting proposals, running / coordinating technical workshops, negotiating contracts and closing sales", "A bachelor\u2019s degree from an accredited university"], "Responsibilities": ["The Senior Sales Director role focused on the Private Markets requires solution selling, Private Markets fundraising/business development, or enterprise software sales experience", "This is a commercially-focused role that will suit a customer facing field sales leader in the US and involve collaboration with Persefoni\u2019s Climate Solution Directors, Customer Success, Product, Marketing and engineering organizations", "You will have a successful track record in the development of sales, business development, or capital-raising strategy and execution, building brand awareness and sales across a broad portfolio of clients, and a demonstrable passion for global sustainability/carbon/climate related developments", "As a key member of the Persefoni Solutions Sales team, the Senior Sales Director will be responsible for growing and retaining annual recurring revenue (ARR)", "This will involve building relationships with prospective customers; selling and closing new platform subscriptions; and successfully preparing customers for platform onboarding", "The ability to lead through influence across direct and indirect reporting relationships is critical, and experience in building and leading a team would be advantageous", "Lead customer facing activities including inbound lead triage, first contact, discovery calls, platform demos, follow-up communication, presenting Persefoni solutions, coordinating internal resources, strategizing on proposals, and negotiating and closing sales", "Grow annual recurring revenue (ARR), helping the Persefoni team meet quarterly and annual goals", "Steward the sales process to support end-to-end customer acquisition, including winning new business, account management, revenue retention, revenue expansion, and an ongoing positive experience of successful impact for our customers", "Collaborate with various Persefoni teams such as marketing, legal, product, solution directors, and customer success to deliver a unified customer experience", "Maintain an accurate CRM with information across the sales lifecycle to include past events and planned tasks, relevant customer details, and sales revenue forecasts", "Ensure that all required paperwork and documentation is properly organized, executed, and stored to successfully book subscriptions and manage customer accounts", "Identify opportunities for participation in relevant industry events, engagements & potential partnerships", "Within your first 2 weeks, you will be able to:", "Articulate how Persefoni incorporates carbon accounting standards and sustainability reporting frameworks in its solutions", "Demonstrate the Persefoni platform and bring together the appropriate Persefoni resources in customer facing meetings", "Be proficient in using Persefoni systems and processes to appropriately track and report on relevant sales activities and customer information", "Ability to answer customers\u2019 frequently asked questions on carbon accounting, climate change, and the Persefoni platform", "Helped the Persefoni team achieve strategic market share and revenue goals", "Identified areas for strategic company revenue growth within your defined territory assignment & contributed to internal systems, processes, product and sales material development to support proactively tackling new opportunities"], "Benefits": ["Generous PTO policy", "401k with company match", "Medical, dental, and vision insurance", "Disability, life insurance", "Equity incentive plan"]}, "job_job_title": "Sales director", "job_posting_language": "en", "job_onet_soc": "11202200", "job_onet_job_zone": "4"}