{"job_id": "H3kbqKIivIW9NXfcAAAAAA==", "employer_name": "Brex", "employer_logo": "https://upload.wikimedia.org/wikipedia/commons/4/49/Brex_Inc._Corporate_Logo.png", "employer_website": "http://brex.com", "employer_company_type": null, "job_publisher": "Wellfound", "job_employment_type": "FULLTIME", "job_title": "Senior Manager, Sales Development", "job_apply_link": "https://wellfound.com/jobs/2949344-senior-manager-sales-development", "job_apply_is_direct": true, "job_apply_quality_score": 0.5979, "apply_options": [{"publisher": "Wellfound", "apply_link": "https://wellfound.com/jobs/2949344-senior-manager-sales-development", "is_direct": true}, {"publisher": "Simplify", "apply_link": "https://simplify.jobs/p/c4be51b4-d0ba-40f4-a1cd-dd0c6cd79308/Senior-Manager", "is_direct": false}], "job_description": "Sales at Brex\n\nThe Sales team is the driving factor behind revenue for Brex. Every member of our team directly affects our bottom line. We focus on generating new opportunities, acquiring new customers, and building even stronger relationships with our current customers. We have a unified culture recognizing big wins daily and celebrating individual accomplishments weekly and monthly. We make sure that top performers are recognized and have built a competitive environment to keep the team motivated and unified.\n\nWhat you\u2019ll do\n\nAs a Senior Manager, Sales Development, you will lead and mentor a high-performing team of Outbound Sales Development Representatives. Hiring, coaching and training reps to ensure the business needs are met will be a heavy focus. Our organization is the top driving lead source for revenue, so you will continuously look for ways to optimize our process with new strategies. We value promotion from within so developing your team into top performing sales reps should also be your goal!\n\nResponsibilities\n\u2022 Lead and support the SDR team to goals, objectives and quota achievement\n\u2022 Effectively manage your team to achieve a monthly quota\n\u2022 Meet with your team on a regular cadence; including weekly 1:1 with reps\n\u2022 Partake in building the team and being a part of interview panels and feedback\n\u2022 Work cross functionally with GTM leaders to ensure SDR onboarding program and ongoing training is up-to-date on our current product offering\n\u2022 Partner with Marketing counterparts to improve lead scoring and SDR/demand generation processes to improve SDR effectiveness\n\u2022 Partner closely with Sales and other members of the SDR Management team to improve opportunity management and qualification processes\n\u2022 Report on individual, segment, team impact; maintain daily activity goals and weekly, monthly, quarterly reporting for various business stakeholders.\n\nRequirements\n\u2022 3+ years management experience in B2B SaaS Sales Development\n\u2022 Strong expertise in outbound sales, primarily through email, phone, and social selling\n\u2022 A proven track record of delivering sales pipeline at a fast growing company with multiple sales segments with an inbound and outbound model\n\u2022 Attract, retain, and motivate exceptional team members\n\u2022 Management experience in a high growth environment, preferably in sales development or a similar field\n\u2022 The desire to listen and creatively solve problems\n\u2022 You are an expert at partnering with marketing to plan and execute multi-touch, multi-channel campaigns\n\u2022 You are an expert at prospecting via Linkedin, using Outreach, SalesNav, Zoominfo\n\u2022 You are comfortable making cold calls\n\nBonus points\n\u2022 Experience in complex SaaS sales\n\u2022 Experience selling into the finance, HR and procurement personas\n\u2022 Closing experience in sales\n\nCompensation\n\nThe expected OTE range for this role is $156,000-$195,000. The starting wage will depend on a number of factors including the candidate\u2019s location, skills, experience, market demands, and internal pay parity. The OTE figure listed here includes base salary and commissions, which may or may not be earned depending on performance. Depending on the position offered, equity and other forms of compensation may be provided as part of a total compensation package.\n\nBrex focuses on Fin Tech and Financial Technology. Their company has offices in Brazil, Canada, and United States. They have a large team that's between 501-1000 employees. To date, Brex has raised $607.5M of funding; their latest round was closed on January 2022 at a valuation of $12.3B.\n\nYou can view their website at https://brex.com/ or find them on Twitter, Facebook, and LinkedIn.", "job_is_remote": false, "job_posted_at_timestamp": 1709935264, "job_posted_at_datetime_utc": "2024-03-08T22:01:04.000Z", "job_city": null, "job_state": null, "job_country": "US", "job_latitude": 37.09024, "job_longitude": -95.71289, "job_benefits": ["retirement_savings"], "job_google_link": "https://www.google.com/search?gl=us&hl=en&rciv=jb&q=senior+manager+of+business+development&start=80&ibp=htl;jobs#fpstate=tldetail&htivrt=jobs&htiq=senior+manager+of+business+development&htidocid=H3kbqKIivIW9NXfcAAAAAA%3D%3D", "job_offer_expiration_datetime_utc": "2024-06-11T11:46:33.000Z", "job_offer_expiration_timestamp": 1718106393, "job_required_experience": {"no_experience_required": false, "required_experience_in_months": 36, "experience_mentioned": true, "experience_preferred": false}, "job_required_skills": null, "job_required_education": {"postgraduate_degree": false, "professional_certification": false, "high_school": false, "associates_degree": false, "bachelors_degree": false, "degree_mentioned": false, "degree_preferred": false, "professional_certification_mentioned": false}, "job_experience_in_place_of_education": false, "job_min_salary": null, "job_max_salary": null, "job_salary_currency": null, "job_salary_period": null, "job_highlights": {"Qualifications": ["3+ years management experience in B2B SaaS Sales Development", "Strong expertise in outbound sales, primarily through email, phone, and social selling", "A proven track record of delivering sales pipeline at a fast growing company with multiple sales segments with an inbound and outbound model", "Attract, retain, and motivate exceptional team members", "Management experience in a high growth environment, preferably in sales development or a similar field", "The desire to listen and creatively solve problems", "You are an expert at partnering with marketing to plan and execute multi-touch, multi-channel campaigns", "You are an expert at prospecting via Linkedin, using Outreach, SalesNav, Zoominfo", "You are comfortable making cold calls", "Experience in complex SaaS sales", "Experience selling into the finance, HR and procurement personas", "Closing experience in sales"], "Responsibilities": ["As a Senior Manager, Sales Development, you will lead and mentor a high-performing team of Outbound Sales Development Representatives", "Hiring, coaching and training reps to ensure the business needs are met will be a heavy focus", "Lead and support the SDR team to goals, objectives and quota achievement", "Effectively manage your team to achieve a monthly quota", "Meet with your team on a regular cadence; including weekly 1:1 with reps", "Partake in building the team and being a part of interview panels and feedback", "Work cross functionally with GTM leaders to ensure SDR onboarding program and ongoing training is up-to-date on our current product offering", "Partner with Marketing counterparts to improve lead scoring and SDR/demand generation processes to improve SDR effectiveness", "Partner closely with Sales and other members of the SDR Management team to improve opportunity management and qualification processes", "Report on individual, segment, team impact; maintain daily activity goals and weekly, monthly, quarterly reporting for various business stakeholders"], "Benefits": ["The expected OTE range for this role is $156,000-$195,000", "The OTE figure listed here includes base salary and commissions, which may or may not be earned depending on performance", "Depending on the position offered, equity and other forms of compensation may be provided as part of a total compensation package"]}, "job_job_title": "Senior manager", "job_posting_language": "en", "job_onet_soc": "11202200", "job_onet_job_zone": "4"}