{"job_id": "YgPjtPzP8uo3tYGUAAAAAA==", "employer_name": "GrayMatters, Inc.", "employer_logo": null, "employer_website": null, "employer_company_type": null, "job_publisher": "Gray Matters Inc.", "job_employment_type": "FULLTIME", "job_title": "Machine Learning Engineer", "job_apply_link": "https://graymatters-inc.com/careers/machine-learning-engineer/", "job_apply_is_direct": false, "job_apply_quality_score": 0.7342, "apply_options": [{"publisher": "Gray Matters Inc.", "apply_link": "https://graymatters-inc.com/careers/machine-learning-engineer/", "is_direct": false}], "job_description": "Overview\nGray Matters Inc. is a disruptive technology company that is looking for talented, motivated individuals to help us grow. Our purpose-built, enterprise-grade blockchain platform is changing how companies view, manage, and protect their assets in very complex and challenging supply chains.\nWe are seeking a Machine Learning Engineer to join our team and help design and develop advanced machine learning models and algorithms tailored to specific business problems. The ideal candidate will be a self-driven individual with experience who can work across a cross-functional team to implement machine learning solutions into production systems.\nResponsibilities\nDesign, develop, and deploy advanced machine learning models and algorithms tailored to specific business problems.\nCollaborate with cross-functional teams to integrate machine learning solutions into production systems.\nAnalyze and preprocess large-scale IoT data, ensuring data quality and relevance for model training and evaluation.\nUtilize AWS services for efficient model deployment, scaling, and monitoring.\nContinuously research and stay up to date with the latest machine learning techniques and best practices to improve existing solutions and develop new ones.\nContribute to the overall architecture and design of machine learning systems.\nParticipate in code reviews and ensure high-quality code through adherence to best practices and industry standards.\nProvide technical leadership and mentorship to junior team members.\nKey Qualifications\nMust be a full U.S. citizen.\nBachelor\u2019s or master\u2019s degree in computer science, Engineering, or a related field.\n5+ years of experience in machine learning, with a strong foundation in algorithms, statistics, and probability.\nProficiency in Python and experience with machine learning frameworks such as TensorFlow, PyTorch, or Keras.\nDemonstrated experience working with IoT data, including data collection, preprocessing, and feature engineering.\nHands-on experience with AWS services, such as SageMaker, EC2, S3, and Lambda, and familiarity with the AWS ecosystem.\nStrong knowledge of various machine learning techniques, including supervised, unsupervised, and reinforcement learning.\nExperience with data visualization tools, such as Matplotlib, Seaborn, or Plotly.\nExcellent problem-solving, critical thinking, and communication skills.\nAbility to work independently and as part of a team in a fast-paced environment.\nPreferred Qualifications\nExperience with IoT platforms.\nKnowledge of big data technologies, such as Apache Spark, Hadoop, or Kafka.\nFamiliarity with containerization technologies, such as Docker and Kubernetes.\nExperience with version control systems, such as Git.\nTrack record of contributions to open-source projects or publications in relevant conferences and journals.\nOther Key Details\nWe are a bunch of self-starters who thrive in an environment where the path has not yet been paved. We love to innovate and collaborate and are never content until we get it right. We don\u2019t take ourselves too seriously, but we are very serious about the work we do. Integrity is very important to us, and we will never abandon a promise or commitment. We want to be the best in the marketplace and are always looking for talented, driven individuals to help us achieve this goal. Our benefits include:\nFull medical and dental benefits\n401k\nUnlimited PTO\nHybrid work location possible\nLittle hierarchy and the ability to work with colleagues at all levels and across disciplines\nAn opportunity to get into a growing company on the ground floor", "job_is_remote": false, "job_posted_at_timestamp": 1688947200, "job_posted_at_datetime_utc": "2023-07-10T00:00:00.000Z", "job_city": "Annapolis", "job_state": "MD", "job_country": "US", "job_latitude": 38.978447, "job_longitude": -76.49218, "job_benefits": ["retirement_savings", "dental_coverage", "paid_time_off", "health_insurance"], "job_google_link": "https://www.google.com/search?gl=us&hl=en&rciv=jb&q=machine+learning&start=20&ibp=htl;jobs#fpstate=tldetail&htivrt=jobs&htiq=machine+learning&htidocid=YgPjtPzP8uo3tYGUAAAAAA%3D%3D", "job_offer_expiration_datetime_utc": null, "job_offer_expiration_timestamp": null, "job_required_experience": {"no_experience_required": false, "required_experience_in_months": 60, "experience_mentioned": true, "experience_preferred": false}, "job_required_skills": null, "job_required_education": {"postgraduate_degree": false, "professional_certification": false, "high_school": false, "associates_degree": false, "bachelors_degree": false, "degree_mentioned": true, "degree_preferred": true, "professional_certification_mentioned": false}, "job_experience_in_place_of_education": false, "job_min_salary": null, "job_max_salary": null, "job_salary_currency": null, "job_salary_period": null, "job_highlights": {"Qualifications": ["The ideal candidate will be a self-driven individual with experience who can work across a cross-functional team to implement machine learning solutions into production systems", "Must be a full U.S. citizen", "Bachelor\u2019s or master\u2019s degree in computer science, Engineering, or a related field", "5+ years of experience in machine learning, with a strong foundation in algorithms, statistics, and probability", "Proficiency in Python and experience with machine learning frameworks such as TensorFlow, PyTorch, or Keras", "Demonstrated experience working with IoT data, including data collection, preprocessing, and feature engineering", "Hands-on experience with AWS services, such as SageMaker, EC2, S3, and Lambda, and familiarity with the AWS ecosystem", "Strong knowledge of various machine learning techniques, including supervised, unsupervised, and reinforcement learning", "Experience with data visualization tools, such as Matplotlib, Seaborn, or Plotly", "Excellent problem-solving, critical thinking, and communication skills", "Ability to work independently and as part of a team in a fast-paced environment", "Experience with IoT platforms", "Knowledge of big data technologies, such as Apache Spark, Hadoop, or Kafka", "Familiarity with containerization technologies, such as Docker and Kubernetes", "Experience with version control systems, such as Git", "Track record of contributions to open-source projects or publications in relevant conferences and journals"], "Responsibilities": ["Design, develop, and deploy advanced machine learning models and algorithms tailored to specific business problems", "Collaborate with cross-functional teams to integrate machine learning solutions into production systems", "Analyze and preprocess large-scale IoT data, ensuring data quality and relevance for model training and evaluation", "Utilize AWS services for efficient model deployment, scaling, and monitoring", "Continuously research and stay up to date with the latest machine learning techniques and best practices to improve existing solutions and develop new ones", "Contribute to the overall architecture and design of machine learning systems", "Participate in code reviews and ensure high-quality code through adherence to best practices and industry standards", "Provide technical leadership and mentorship to junior team members"], "Benefits": ["Full medical and dental benefits", "401k", "Unlimited PTO"]}, "job_job_title": "Learning engineer", "job_posting_language": "en", "job_onet_soc": "15111100", "job_onet_job_zone": "5"}