{"job_id": "4t3nOl0PCyzr4mAdAAAAAA==", "employer_name": "Sway AI", "employer_logo": null, "employer_website": "http://www.sway-ai.com", "employer_company_type": null, "job_publisher": "Sway AI", "job_employment_type": "FULLTIME", "job_title": "Principal Machine Learning Back End Engineer", "job_apply_link": "https://sway-ai.com/jobs/principal-machine-learning-back-end-engineer/", "job_apply_is_direct": false, "job_apply_quality_score": 0.8266, "apply_options": [{"publisher": "Sway AI", "apply_link": "https://sway-ai.com/jobs/principal-machine-learning-back-end-engineer/", "is_direct": false}], "job_description": "Who we are\n\nAt Sway AI, we believe there\u2019s a better way to do AI. No more expensive investments in AI tools and skillsets. No more months-long projects with uncertain results. We put compelling AI solutions in your hands using our \u201cno code\u201d platform. We save you time and money so that you can focus on actual decision-making.\n\nOur team is an experienced and talented group of entrepreneurs, scientists, and engineers who share a single-minded focus to re-architect how AI/ML applications are built and deployed. A venture-backed startup, we were founded and are led by proven entrepreneurs who have built several successful companies.\n\nAre you an ML engineer that knows the ins and outs of designing and deploying real-world cloud-based AI solutions? Do you have the skills and experience to make deploying AI models fast, secure and scalable? Do you want to work on exciting projects that help change the way people use AI? If so, we want you to join our awesome team of engineers and data scientists to help us build a new generation of no-code AI applications.\nWhat you\u2019ll do\n\u2022 Design, develop and deploy robust, reliable and scalable ML solutions using cloud platforms such as AWS, Azure, GCP or other cloud providers\n\u2022 Implement and automate ML best practices\n\u2022 Collaborate with other ML engineers, data scientists, front end engineers, and product managers to ensure the quality and delivery of machine learning products\n\u2022 Research and evaluate new ML technologies and trends\n\u2022 Mentor and coach other ML engineers\n\u2022 Design, develop and deploy machine learning models using frameworks such as TensorFlow, PyTorch, Scikit-Learn, etc.\n\u2022 Implement and maintain model deployment tools such as Kubernetes, Kubeflow, MLflow, Seldon Core, etc.\n\u2022 Conduct model testing and validation using tools such as Jest, Enzyme, Cypress, etc.\n\u2022 Monitor and improve model performance and accuracy using tools such as TensorBoard, MLflow Tracking, etc.\n\nWhat you\u2019ll need\n\u2022 PhD or MS, or equivalent, in mathematics or CS with a focus on machine learning\n\u2022 8+ years of professional experience as an ML engineer or similar role\n\u2022 Experience with machine learning frameworks such as TensorFlow, PyTorch, Scikit-Learn, etc.\n\u2022 Experience with model deployment tools such as Kubernetes, Kubeflow, MLflow, Seldon Core, etc.\n\u2022 Experience with model testing and validation tools such as Jest, Enzyme, Cypress, etc.\n\u2022 Experience with cloud platforms such as AWS, Azure, GCP or other cloud providers\n\u2022 Experience with model performance and accuracy tools such as TensorBoard, MLflow Tracking\n\u2022 Experience writing code in Python and writing documentation in easily understandable language\n\u2022 Strong communication, collaboration and problem-solving skills\n\nWhat you\u2019ll get\n\u2022 A chance to help define the company, our culture, and the industry\n\u2022 A competitive compensation package\n\u2022 A chance to work on exciting projects that make a positive impact\n\u2022 An opportunity to learn and grow with some of the best engineers and data scientists in the industry\n\nWhat\u2019s next?\n\nIf you\u2019re as excited about this opportunity as we are, don\u2019t hesitate to apply. We can\u2019t wait to hear from you!", "job_is_remote": false, "job_posted_at_timestamp": 1687811737, "job_posted_at_datetime_utc": "2023-06-26T20:35:37.000Z", "job_city": "Burlington", "job_state": "MA", "job_country": "US", "job_latitude": 42.493706, "job_longitude": -71.18963, "job_benefits": null, "job_google_link": "https://www.google.com/search?gl=us&hl=en&rciv=jb&q=principal+machine+learning+architect&start=20&ibp=htl;jobs#fpstate=tldetail&htivrt=jobs&htiq=principal+machine+learning+architect&htidocid=4t3nOl0PCyzr4mAdAAAAAA%3D%3D", "job_offer_expiration_datetime_utc": null, "job_offer_expiration_timestamp": null, "job_required_experience": {"no_experience_required": false, "required_experience_in_months": 96, "experience_mentioned": true, "experience_preferred": false}, "job_required_skills": null, "job_required_education": {"postgraduate_degree": false, "professional_certification": false, "high_school": false, "associates_degree": false, "bachelors_degree": false, "degree_mentioned": true, "degree_preferred": false, "professional_certification_mentioned": false}, "job_experience_in_place_of_education": false, "job_min_salary": null, "job_max_salary": null, "job_salary_currency": null, "job_salary_period": null, "job_highlights": {"Qualifications": ["PhD or MS, or equivalent, in mathematics or CS with a focus on machine learning", "8+ years of professional experience as an ML engineer or similar role", "Experience with machine learning frameworks such as TensorFlow, PyTorch, Scikit-Learn, etc", "Experience with model deployment tools such as Kubernetes, Kubeflow, MLflow, Seldon Core, etc", "Experience with model testing and validation tools such as Jest, Enzyme, Cypress, etc", "Experience with cloud platforms such as AWS, Azure, GCP or other cloud providers", "Experience with model performance and accuracy tools such as TensorBoard, MLflow Tracking", "Experience writing code in Python and writing documentation in easily understandable language", "Strong communication, collaboration and problem-solving skills"], "Responsibilities": ["Design, develop and deploy robust, reliable and scalable ML solutions using cloud platforms such as AWS, Azure, GCP or other cloud providers", "Implement and automate ML best practices", "Collaborate with other ML engineers, data scientists, front end engineers, and product managers to ensure the quality and delivery of machine learning products", "Research and evaluate new ML technologies and trends", "Mentor and coach other ML engineers", "Design, develop and deploy machine learning models using frameworks such as TensorFlow, PyTorch, Scikit-Learn, etc", "Implement and maintain model deployment tools such as Kubernetes, Kubeflow, MLflow, Seldon Core, etc", "Conduct model testing and validation using tools such as Jest, Enzyme, Cypress, etc", "Monitor and improve model performance and accuracy using tools such as TensorBoard, MLflow Tracking, etc"], "Benefits": ["A chance to help define the company, our culture, and the industry", "A competitive compensation package", "A chance to work on exciting projects that make a positive impact", "An opportunity to learn and grow with some of the best engineers and data scientists in the industry"]}, "job_job_title": "End engineer", "job_posting_language": "en", "job_onet_soc": "15111100", "job_onet_job_zone": "5"}