{"job_id": "9jnwE7fpByQG5O7gAAAAAA==", "employer_name": "Sysco", "employer_logo": "https://upload.wikimedia.org/wikipedia/commons/thumb/b/bf/Sysco-Logo.svg/2560px-Sysco-Logo.svg.png", "employer_website": "http://www.sysco.com", "employer_company_type": "Wholesale", "job_publisher": "Sysco Careers", "job_employment_type": "FULLTIME", "job_title": "Sales Consultant - Wichita, Kansas", "job_apply_link": "https://careers.sysco.com/jobs/R141935?lang=en-us", "job_apply_is_direct": true, "job_apply_quality_score": 0.7968, "apply_options": [{"publisher": "Sysco Careers", "apply_link": "https://careers.sysco.com/jobs/R141935?lang=en-us", "is_direct": true}, {"publisher": "Jora", "apply_link": "https://us.jora.com/job/Sales-Consultant-a9d57d1324e6118207ce722b75ac2e39", "is_direct": false}, {"publisher": "Kansas Jobs - Tarta.ai", "apply_link": "https://kansas.tarta.ai/j/H_jkSI0BcRajQcTjctzr0124-sales-consultant-in-wichita-kansas-at-sysco", "is_direct": false}], "job_description": "Company:\nUS0057 Sysco Kansas City, Inc.\n\nZip Code:\n67209\n\nMinimum Years of Experience:\n0-1 Years\n\nEmployment Type:\nFull Time\n\nTravel Percentage:\nUp to 25%\n\nCOMPENSATION INFORMATION:\n\nThe pay range provided is not indicative of Sysco\u2019s actual pay range but is merely algorithmic and provided for generalized comparison. Factors that may be used to determine rate of pay include specific skills, work location, work experience and other individualized factors\n\nThe work territory for this position is Wichita, Kansas, and surrounding areas.\n\nYou must live no further than 1 hour away from the territory (including traffic) or be willing to relocate on your own. (relocation is not approved for this position).\n\nAre you an experienced Sales Professional, Restaurant Manager, Culinary Manager or Chef looking for career development opportunities? Join Sysco\u2019s World Class Sales Team and explore all the benefits and perks.\n\nWhy you should join our Sales Team:\n\u2022 Competitive base salary, bonus, plus promotional incentive opportunities\n\u2022 Car allowance (mileage reimbursement for candidates in CA) and cell phone provided\n\u2022 Career pathing opportunities for both entry level, and experienced individuals\n\u2022 Opportunity to be part of a purpose driven organization that supports communities and associates\n\u2022 Specialized sales training\n\u2022 Individual as well as team-based selling\n\u2022 Opportunity to learn different ethnic segments\n\u2022 Monthly and annual sales rewards and recognition\n\u2022 Robust benefits package including an Employee Stock Purchase Plan, & 401(k) with automatic matching\n\nJOB SUMMARY\nThis is an outside sales position responsible for promoting the company's products and services and for building relationships with new and existing accounts. The main focus is to help Sysco customers succeed while achieving sales and profit goals established by the company. This position may require working some non-traditional hours (evening, weekends, and holidays) to successfully meet customers' needs.\n\nRESPONSIBILITIES\n\u2022 Develop new business, penetrate existing accounts, and minimize lost business to achieve profitable sales growth and special objectives within assigned territory.\n\u2022 Seek and qualify prospects following company account stratification goals.\n\u2022 Research customer business needs and develops a mix of products and service to meet needs.\n\u2022 Evaluate market trends and recommend products to customers, based on business needs and goals.\n\u2022 Be informed of market conditions, product innovations, and competitors' products, prices, and sales; share information with customers as part of value-added services provided.\n\u2022 Answer customers' questions about products, prices, availability, and product use.\n\u2022 Provide product information and practical training to customer personnel.\n\u2022 Drive personal vehicle to customer accounts, conventions, company meetings, etc.\n\u2022 Communicate and collect accounts receivable as necessary, working with the credit department and client; collect all balances due based on approved credit terms.\n\u2022 Manage deliveries to the routing schedule published by the transportation department; troubleshoot any problems that occur during the order process (for example, out of stock items, special order items, low inventory, etc.).\n\u2022 Participate in company functions, promotions, customer visits, and customer events.\n\u2022 Attend and participate in general sales and district meetings.\n\u2022 Engage in ongoing training sessions.\n\u2022 Assist with the training of new employees as requested.\n\u2022 Review and analyze daily and weekly reports such as special-order requests, customer bid files, and sales/gross profit margin data.\n\u2022 Perform administrative duties, such as preparing sales budgets and reports, maintaining sales records, processing credits, and pick-up requests, preparing sales quotes and menu suggestions, and filing reports.\n\u2022 Other duties may be assigned.\n\nQUALIFICATIONS\n\nRequired Education/Experience\n\u2022 Bachelor's degree in Business, Sales, Marketing, Hospitality, Culinary Arts or related discipline OR HSD/GED and 3 years Restaurant Management, B2B or outside sales experience, or equivalent relatable experience.\n\nPreferred Qualifications\n\u2022 Bi-Lingual\n\u2022 Restaurant Management, Foodservice Outside Sales, Chef Experience preferred\n\nCertificates, Licenses, and Registrations\n\u2022 Valid driver's license with a \"clean\" driving record (including no multiple DUIs within the last 2 years)\n\u2022 Current automobile insurance with the following limits of liability: Bodily injury - $100,000 each person and $300,000 each accident; property damage - $100,000 is required\n\nRequirement\n\u2022 Submit to pre-employment testing (Drug Screen, Background Check).\n\u2022 Must sign Sysco Protective Covenants Agreement.\n\u2022 Reside or willing to relocate to the geographical vicinity of territory.\n\nProfessional Skills\n\u2022 Basic PC skills and proficiency with MS Office.\n\u2022 Ability to read, write, speak English.\n\nCompetencies\n\u2022 Building Trust\n\u2022 Building Customer Loyalty\n\u2022 Follow-up\n\u2022 Sales Ability / Persuasiveness\n\u2022 Managing Work\n\u2022 Adaptability\n\u2022 Communication\n\n#LI-DM1\n\nBENEFITS INFORMATION:\nFor information on Sysco\u2019s Benefits, please visit https://SyscoBenefits.com\n\nOVERVIEW:\n\nSysco is the global leader in foodservice distribution. With over 71,000 colleagues and a fleet of over 13,000 vehicles, Sysco operates approximately 333 distribution facilities worldwide and serves more than 700,000 customer locations.\n\nWe offer our colleagues the opportunity to grow personally and professionally, to contribute to the success of a dynamic organization, and to serve others in a manner that exceeds their expectations. We\u2019re looking for talented, hard-working individuals to join our team. Come grow with us and let us show you why Sysco is at the heart of food and service.\n\nAFFIRMATIVE ACTION STATEMENT:\n\nApplicants must be currently authorized to work in the United States.\n\nWe are proud to be an Equal Opportunity and Affirmative Action employer, and consider qualified applicants without regard to race, color, creed, religion, ancestry, national origin, sex, sexual orientation, gender identity, age, disability, veteran status or any other protected factor under federal, state or local law.\n\nThis opportunity is available through Sysco Corporation, its subsidiaries and affiliates.", "job_is_remote": false, "job_posted_at_timestamp": 1710374400, "job_posted_at_datetime_utc": "2024-03-14T00:00:00.000Z", "job_city": "Wichita", "job_state": "KS", "job_country": "US", "job_latitude": 37.687176, "job_longitude": -97.330055, "job_benefits": ["health_insurance", "retirement_savings"], "job_google_link": "https://www.google.com/search?gl=us&hl=en&rciv=jb&q=sales+consultant&start=0&ibp=htl;jobs#fpstate=tldetail&htivrt=jobs&htiq=sales+consultant&htidocid=9jnwE7fpByQG5O7gAAAAAA%3D%3D", "job_offer_expiration_datetime_utc": "2025-03-14T14:36:39.000Z", "job_offer_expiration_timestamp": 1741962999, "job_required_experience": {"no_experience_required": false, "required_experience_in_months": null, "experience_mentioned": true, "experience_preferred": true}, "job_required_skills": ["UNAVAILABLE"], "job_required_education": {"postgraduate_degree": false, "professional_certification": false, "high_school": false, "associates_degree": false, "bachelors_degree": false, "degree_mentioned": true, "degree_preferred": true, "professional_certification_mentioned": false}, "job_experience_in_place_of_education": false, "job_min_salary": null, "job_max_salary": null, "job_salary_currency": null, "job_salary_period": null, "job_highlights": {"Qualifications": ["You must live no further than 1 hour away from the territory (including traffic) or be willing to relocate on your own", "Bachelor's degree in Business, Sales, Marketing, Hospitality, Culinary Arts or related discipline OR HSD/GED and 3 years Restaurant Management, B2B or outside sales experience, or equivalent relatable experience", "Certificates, Licenses, and Registrations", "Valid driver's license with a \"clean\" driving record (including no multiple DUIs within the last 2 years)", "Current automobile insurance with the following limits of liability: Bodily injury - $100,000 each person and $300,000 each accident; property damage - $100,000 is required", "Submit to pre-employment testing (Drug Screen, Background Check)", "Must sign Sysco Protective Covenants Agreement", "Reside or willing to relocate to the geographical vicinity of territory", "Basic PC skills and proficiency with MS Office", "Ability to read, write, speak English", "Building Trust", "Building Customer Loyalty", "Sales Ability / Persuasiveness", "Managing Work", "Adaptability", "Communication", "Applicants must be currently authorized to work in the United States"], "Responsibilities": ["This is an outside sales position responsible for promoting the company's products and services and for building relationships with new and existing accounts", "The main focus is to help Sysco customers succeed while achieving sales and profit goals established by the company", "This position may require working some non-traditional hours (evening, weekends, and holidays) to successfully meet customers' needs", "Develop new business, penetrate existing accounts, and minimize lost business to achieve profitable sales growth and special objectives within assigned territory", "Seek and qualify prospects following company account stratification goals", "Research customer business needs and develops a mix of products and service to meet needs", "Evaluate market trends and recommend products to customers, based on business needs and goals", "Be informed of market conditions, product innovations, and competitors' products, prices, and sales; share information with customers as part of value-added services provided", "Answer customers' questions about products, prices, availability, and product use", "Provide product information and practical training to customer personnel", "Drive personal vehicle to customer accounts, conventions, company meetings, etc", "Communicate and collect accounts receivable as necessary, working with the credit department and client; collect all balances due based on approved credit terms", "Manage deliveries to the routing schedule published by the transportation department; troubleshoot any problems that occur during the order process (for example, out of stock items, special order items, low inventory, etc.)", "Participate in company functions, promotions, customer visits, and customer events", "Attend and participate in general sales and district meetings", "Engage in ongoing training sessions", "Assist with the training of new employees as requested", "Review and analyze daily and weekly reports such as special-order requests, customer bid files, and sales/gross profit margin data", "Perform administrative duties, such as preparing sales budgets and reports, maintaining sales records, processing credits, and pick-up requests, preparing sales quotes and menu suggestions, and filing reports", "Other duties may be assigned"], "Benefits": ["The pay range provided is not indicative of Sysco\u2019s actual pay range but is merely algorithmic and provided for generalized comparison", "Competitive base salary, bonus, plus promotional incentive opportunities", "Car allowance (mileage reimbursement for candidates in CA) and cell phone provided", "Career pathing opportunities for both entry level, and experienced individuals", "Opportunity to learn different ethnic segments", "Monthly and annual sales rewards and recognition", "Robust benefits package including an Employee Stock Purchase Plan, & 401(k) with automatic matching"]}, "job_job_title": "Sales consultant", "job_posting_language": "en", "job_onet_soc": "41401100", "job_onet_job_zone": "4", "job_naics_code": "424410", "job_naics_name": "General Line Grocery Merchant Wholesalers"}