{"job_id": "Zszf_PCDSpepJ8dnAAAAAA==", "employer_name": "CrowdStrike", "employer_logo": "https://d15shllkswkct0.cloudfront.net/wp-content/blogs.dir/1/files/2022/03/CrowdStrike-Logo.png", "employer_website": "http://www.crowdstrike.com", "employer_company_type": "Information", "job_publisher": "SimplyHired", "job_employment_type": "FULLTIME", "job_title": "Regional Sales Director, North Central - Majors (Remote)", "job_apply_link": "https://www.simplyhired.com/job/sTtiUvhnbt4_HWZutqkWkOisa_ZSpMO04HnGmzs0IK1OmmpBZUwHCg", "job_apply_is_direct": false, "job_apply_quality_score": 0.5164, "apply_options": [{"publisher": "SimplyHired", "apply_link": "https://www.simplyhired.com/job/sTtiUvhnbt4_HWZutqkWkOisa_ZSpMO04HnGmzs0IK1OmmpBZUwHCg", "is_direct": false}], "job_description": "#WeAreCrowdStrike and our mission is to stop breaches. As a global leader in cybersecurity, our team changed the game. Since our inception, our market leading cloud-native platform has offered unparalleled protection against the most sophisticated cyberattacks. We\u2019re looking for people with limitless passion, a relentless focus on innovation and a fanatical commitment to the customer to join us in shaping the future of cybersecurity. Consistently recognized as a top workplace, CrowdStrike is committed to cultivating an inclusive, remote-first culture that offers people the autonomy and flexibility to balance the needs of work and life while taking their career to the next level. Interested in working for a company that sets the standard and leads with integrity? Join us on a mission that matters - one team, one fight.\n\nAbout the Role:\n\nCrowdStrike is currently looking for a Regional Sales Director to help us build, grow and sustain Success in this position will require someone who possess excellent energy and drive and a real desire to build business across the region. A problem-solving attitude with an ability to motivate the team to achieve specific goals are essential skills to perform well in this position.\n\nWhat You\u2019ll Do:\n\u2022 Provide management oversight to Regional Sales Managers within the Region to drive all pertinent issues related to sales strategy and goal attainment.\n\u2022 Participate in strategic planning sessions with the sales management team on a quarterly and annual basis.\n\u2022 Communicate corporate strategy to employees within your Region.\n\u2022 Plan and direct activities including planning and implementing forecasts, relationship development and customer satisfaction.\n\u2022 Establish short-term and long-term goals and quotas in line with corporate objectives.\n\u2022 Identify needed resources for supporting sales strategy and develop a proposed budget for Senior Management review.\n\u2022 Identify and qualify important Enterprise sales opportunities at the management level.\n\u2022 Act as coach, mentor and educator to all Regional Sales Managers within your Region.\n\u2022 Select, develop, and evaluate personnel to ensure sales goals are met.\n\u2022 Keep senior leadership informed of key issues and changes which may impact expected business results\n\nWhat You\u2019ll Need:\n\u2022 A minimum of 10 years of experience as an individual contributor and 5 years as a people manager is required\n\u2022 Passionate relationship building and executive level negotiating skills.\n\u2022 Ability to work collaboratively with functional peers across functions including the Channel, Marketing, Sales Operations, System Engineering, Services Customer Support, and Product Development.\n\u2022 Strong understanding of Cybersecurity technologies and competitive offerings in the marketplace.\n\u2022 Experience with target account selling, solution selling, and/or consultative sales techniques.\n\u2022 An aptitude for understanding how technology products and solutions solve business problems.\n\u2022 Experience as a successful Regional Sales Director with a track record of exceeding assigned sales quotas in contiguous, multiple years.\n\u2022 Demonstrated experience working with Sales organizations and technical teams.\n\u2022 Experience with developing budgets and predicting project costs.\n\u2022 A demonstrated ability to manage professional level employees.\n\u2022 Ability to foster a positive work environment and attitude.\n\u2022 Ability to work remotely and able and willing to travel on short notice, up to 50% of the time\n\u2022 Excellent communications and presentation skills\n\n#LI-CB1\n\n#LI-Remote\n\nBenefits of Working at CrowdStrike:\n\u2022 Remote-first culture\n\u2022 Market leader in compensation and equity awards\n\u2022 Competitive vacation and flexible working arrangements\n\u2022 Comprehensive and inclusive health benefits\n\u2022 Physical and mental wellness programs\n\u2022 Paid parental leave, including adoption\n\u2022 A variety of professional development and mentorship opportunities\n\u2022 Offices with stocked kitchens when you need to fuel innovation and collaboration\n\nWe are committed to fostering a culture of belonging where everyone feels seen, heard, valued for who they are and empowered to succeed. Our approach to cultivating a diverse, equitable, and inclusive culture is rooted in listening, learning and collective action. By embracing the diversity of our people, we achieve our best work and fuel innovation - generating the best possible outcomes for our customers and the communities they serve.\n\nCrowdStrike is committed to maintaining an environment of Equal Opportunity and Affirmative Action. If you need reasonable accommodation to access the information provided on this website, please contact Recruiting@crowdstrike.com\n, for further assistance.\n\nCrowdStrike participates in the E-Verify program.\n\nNotice of E-Verify Participation\n\nRight to Work", "job_is_remote": false, "job_posted_at_timestamp": 1709186400, "job_posted_at_datetime_utc": "2024-02-29T06:00:00.000Z", "job_city": "Springfield", "job_state": "IL", "job_country": "US", "job_latitude": 39.781723, "job_longitude": -89.65015, "job_benefits": ["paid_time_off", "health_insurance"], "job_google_link": "https://www.google.com/search?gl=us&hl=en&rciv=jb&q=sales+director&start=50&ibp=htl;jobs#fpstate=tldetail&htivrt=jobs&htiq=sales+director&htidocid=Zszf_PCDSpepJ8dnAAAAAA%3D%3D", "job_offer_expiration_datetime_utc": null, "job_offer_expiration_timestamp": null, "job_required_experience": {"no_experience_required": false, "required_experience_in_months": 120, "experience_mentioned": true, "experience_preferred": false}, "job_required_skills": null, "job_required_education": {"postgraduate_degree": false, "professional_certification": false, "high_school": false, "associates_degree": false, "bachelors_degree": false, "degree_mentioned": false, "degree_preferred": false, "professional_certification_mentioned": false}, "job_experience_in_place_of_education": false, "job_min_salary": null, "job_max_salary": null, "job_salary_currency": null, "job_salary_period": null, "job_highlights": {"Qualifications": ["A problem-solving attitude with an ability to motivate the team to achieve specific goals are essential skills to perform well in this position", "A minimum of 10 years of experience as an individual contributor and 5 years as a people manager is required", "Passionate relationship building and executive level negotiating skills", "Ability to work collaboratively with functional peers across functions including the Channel, Marketing, Sales Operations, System Engineering, Services Customer Support, and Product Development", "Strong understanding of Cybersecurity technologies and competitive offerings in the marketplace", "Experience with target account selling, solution selling, and/or consultative sales techniques", "An aptitude for understanding how technology products and solutions solve business problems", "Experience as a successful Regional Sales Director with a track record of exceeding assigned sales quotas in contiguous, multiple years", "Demonstrated experience working with Sales organizations and technical teams", "Experience with developing budgets and predicting project costs", "A demonstrated ability to manage professional level employees", "Ability to foster a positive work environment and attitude", "Ability to work remotely and able and willing to travel on short notice, up to 50% of the time", "Excellent communications and presentation skills"], "Responsibilities": ["Provide management oversight to Regional Sales Managers within the Region to drive all pertinent issues related to sales strategy and goal attainment", "Participate in strategic planning sessions with the sales management team on a quarterly and annual basis", "Communicate corporate strategy to employees within your Region", "Plan and direct activities including planning and implementing forecasts, relationship development and customer satisfaction", "Establish short-term and long-term goals and quotas in line with corporate objectives", "Identify needed resources for supporting sales strategy and develop a proposed budget for Senior Management review", "Identify and qualify important Enterprise sales opportunities at the management level", "Act as coach, mentor and educator to all Regional Sales Managers within your Region", "Select, develop, and evaluate personnel to ensure sales goals are met", "Keep senior leadership informed of key issues and changes which may impact expected business results"], "Benefits": ["Market leader in compensation and equity awards", "Competitive vacation and flexible working arrangements", "Comprehensive and inclusive health benefits", "Physical and mental wellness programs", "Paid parental leave, including adoption", "A variety of professional development and mentorship opportunities"]}, "job_job_title": "Sales director", "job_posting_language": "en", "job_onet_soc": "11202200", "job_onet_job_zone": "4", "job_naics_code": "511210", "job_naics_name": "Software Publishers"}