{"job_id": "nH7--1x-SBvZr-rCAAAAAA==", "employer_name": "New Schools for New Orleans", "employer_logo": null, "employer_website": null, "employer_company_type": null, "job_publisher": "WorkNOLA", "job_employment_type": "FULLTIME", "job_title": "Director of Data Analytics", "job_apply_link": "https://worknola.com/job/340126/director-of-data-analytics", "job_apply_is_direct": false, "job_apply_quality_score": 0.6055, "apply_options": [{"publisher": "WorkNOLA", "apply_link": "https://worknola.com/job/340126/director-of-data-analytics", "is_direct": false}], "job_description": "Context\n\nNew Schools for New Orleans\u2019 (NSNO) mission \u2014 delivering on the promise of excellent public schools for every child in New Orleans \u2014 drives everything we do. To achieve this mission, NSNO is investing in internal and external systems to share, analyze, and explain important data related to our city\u2019s public schools. This data will be used to inform NSNO\u2019s strategy, provide helpful information to policy- and decision-makers, support charter school leaders in planning for the future, and communicate to the public.\n\nThis is a full-time position with an immediate start date, with an annual salary of $70,000 \u2013 $88,000, commensurate with experience. NSNO has a hybrid work environment which involves primarily remote work with required attendance at New Orleans-based events throughout the year.\n\nRole and Responsibilities\n\nThe Director of Data Analytics will be part of the Policy & Portfolio team, but the Director\u2019s work will often cross over to support other NSNO teams. This role is an excellent fit for someone who believes in the power of data and is eager to develop systems and strategies to communicate data insights and data-informed strategies. Specific responsibilities will include:\n\u2022 Managing and connecting different pieces of information about our schools and system, including large and often complex data systems to help understand and communicate outcomes\n\u2022 Developing systems to regularly update and share important school- and system-level data across the NSNO organization (enrollment, academic performance, etc.)\n\u2022 Developing materials and visualizations to communicate data trends and insights\n\u2022 Designing and executing analyses and communicating insights to inform NSNO\u2019s policy, system planning, and school investment strategies\n\u2022 Coordinating the development of a public-facing online data dashboard and data library\n\u2022 Managing relationships with external data partners and collaborators including paid consultants, government agencies, and other nonprofit organizations\n\u2022 Leading regular convenings of local education data experts and integrating insights from beyond the education world that may impact our schools and education community\n\nQualifications\n\u2022 Bachelor\u2019s degree required; Master\u2019s degree in Education Policy or Administration, Computer Science, Statistics, Mathematics, Data Analytics, Information Management or other related field of study preferred\n\u2022 Three years of experience with data analysis and communicating insights strongly preferred\n\u2022 Work or volunteer experience demonstrating a commitment to education, students, or families preferred\n\u2022 Proficiency in connecting and working with large and complex data sets\n\u2022 Extreme attention to detail and commitment to accuracy\n\u2022 Expertise or experience in data visualization software (Google Charts, Tableau, etc.), data analytics (Python, R, SQL, Excel, STATA), and other Microsoft and google software and applications\n\nBenefits\n\nNSNO believes in protecting the health of the whole person through comprehensive mental and physical health benefits.\n\u2022 Medical, dental, and vision insurance\n\u2022 100% employer paid disability and life insurance\n\u2022 Access to Dependent Care Assistance, Health Savings, or Flexible Savings Account options\n\u2022 Annual wellness subsidy of $500\n\u2022 Up to $100 monthly stipend for phone and internet expenses\n\u2022 Open Paid Time Off (PTO) Policy- Your manager will work with you to take the time off you need to achieve a work-life balance.\n\u2022 Employer paid Maternity and Parental Leave\n\u2022 401K, 4% match\n\u2022 Role related professional development funds and specific Diversity, Equity, and Inclusion related professional development funds\u202favailable\n\nBefore you apply\u2026\n\nWe will be removing all identifying information from your resume before our hiring team reviews your resume. This is to ensure our hiring process is equitable and to remove any unconscious bias from our resume review process. New Schools for New Orleans is committed to cultivating an inclusive environment where a diverse group of people can and want to do their best work and that starts with our hiring practices. Identifying information includes your name, photos, LinkedIn URL, email address, and more. If you have any questions about this approach, feel free to email us at hr@nsno.org.\n\nHow to Apply\n\nPlease send a tailored cover letter and resume to hr@nsno.org. Candidates will be required to complete a performance task as part of the multi-stage interview process.\n\nNew Schools for New Orleans (NSNO) is an Equal Employment Opportunity employer and has a strong commitment to building a diverse and inclusive team. As such, it is the continuing policy of NSNO to consider all applicants without regard to race, color, religion, national origin, age, gender, sexual orientation, genetic information, veteran status, physical or mental disability, or any other categories protected by applicable federal, state, or local law, provided they are otherwise able to perform the essential functions of the job.", "job_is_remote": false, "job_posted_at_timestamp": 1654300800, "job_posted_at_datetime_utc": "2022-06-04T00:00:00.000Z", "job_city": "New Orleans", "job_state": "LA", "job_country": "US", "job_latitude": 29.951065, "job_longitude": -90.07153, "job_benefits": ["health_insurance", "dental_coverage", "paid_time_off", "retirement_savings"], "job_google_link": "https://www.google.com/search?gl=us&hl=en&rciv=jb&q=director+of+advanced+analytics&start=10&ibp=htl;jobs#fpstate=tldetail&htivrt=jobs&htiq=director+of+advanced+analytics&htidocid=nH7--1x-SBvZr-rCAAAAAA%3D%3D", "job_offer_expiration_datetime_utc": null, "job_offer_expiration_timestamp": null, "job_required_experience": {"no_experience_required": false, "required_experience_in_months": 36, "experience_mentioned": true, "experience_preferred": true}, "job_required_skills": null, "job_required_education": {"postgraduate_degree": false, "professional_certification": false, "high_school": false, "associates_degree": false, "bachelors_degree": false, "degree_mentioned": true, "degree_preferred": true, "professional_certification_mentioned": false}, "job_experience_in_place_of_education": false, "job_min_salary": null, "job_max_salary": null, "job_salary_currency": null, "job_salary_period": null, "job_highlights": {"Qualifications": ["Proficiency in connecting and working with large and complex data sets", "Extreme attention to detail and commitment to accuracy", "Expertise or experience in data visualization software (Google Charts, Tableau, etc.), data analytics (Python, R, SQL, Excel, STATA), and other Microsoft and google software and applications"], "Responsibilities": ["To achieve this mission, NSNO is investing in internal and external systems to share, analyze, and explain important data related to our city\u2019s public schools", "This data will be used to inform NSNO\u2019s strategy, provide helpful information to policy- and decision-makers, support charter school leaders in planning for the future, and communicate to the public", "The Director of Data Analytics will be part of the Policy & Portfolio team, but the Director\u2019s work will often cross over to support other NSNO teams", "This role is an excellent fit for someone who believes in the power of data and is eager to develop systems and strategies to communicate data insights and data-informed strategies", "Managing and connecting different pieces of information about our schools and system, including large and often complex data systems to help understand and communicate outcomes", "Developing systems to regularly update and share important school- and system-level data across the NSNO organization (enrollment, academic performance, etc.)", "Developing materials and visualizations to communicate data trends and insights", "Designing and executing analyses and communicating insights to inform NSNO\u2019s policy, system planning, and school investment strategies", "Coordinating the development of a public-facing online data dashboard and data library", "Managing relationships with external data partners and collaborators including paid consultants, government agencies, and other nonprofit organizations", "Leading regular convenings of local education data experts and integrating insights from beyond the education world that may impact our schools and education community"], "Benefits": ["This is a full-time position with an immediate start date, with an annual salary of $70,000 \u2013 $88,000, commensurate with experience", "NSNO believes in protecting the health of the whole person through comprehensive mental and physical health benefits", "Medical, dental, and vision insurance", "100% employer paid disability and life insurance", "Access to Dependent Care Assistance, Health Savings, or Flexible Savings Account options", "Annual wellness subsidy of $500", "Up to $100 monthly stipend for phone and internet expenses", "Open Paid Time Off (PTO) Policy- Your manager will work with you to take the time off you need to achieve a work-life balance", "Employer paid Maternity and Parental Leave", "401K, 4% match", "Role related professional development funds and specific Diversity, Equity, and Inclusion related professional development funds\u202favailable"]}, "job_job_title": null, "job_posting_language": "en", "job_onet_soc": "11302100", "job_onet_job_zone": "4"}