{"job_id": "fO2FAdf0KLcJ5cYbAAAAAA==", "employer_name": "Truckstop", "employer_logo": "https://img.truckpartsandservice.com/files/base/randallreilly/all/image/2023/06/Truckstop.64947d8984607.png?auto=format%2Ccompress&q=70&w=400", "employer_website": "http://www.truckstop.com", "employer_company_type": null, "job_publisher": "LinkedIn", "job_employment_type": "FULLTIME", "job_title": "Lead Data Scientist", "job_apply_link": "https://www.linkedin.com/jobs/view/lead-data-scientist-at-truckstop-3846447938", "job_apply_is_direct": false, "job_apply_quality_score": 0.6311, "apply_options": [{"publisher": "LinkedIn", "apply_link": "https://www.linkedin.com/jobs/view/lead-data-scientist-at-truckstop-3846447938", "is_direct": false}, {"publisher": "Jobgether", "apply_link": "https://jobgether.com/offer/65ecb8f2f235ccdf790b397f-lead-data-scientist", "is_direct": false}, {"publisher": "Offered.AI", "apply_link": "https://www.offered.ai/jobs/clpjbf6oa01pxlpkwp9ja8fsx", "is_direct": false}, {"publisher": "Www.infirmsin.net", "apply_link": "https://www.infirmsin.net/?_=%2Fjobs%2Fview%2Fprincipal-data-scientist-at-truckstop-3813137221%23KJWqMdlUlBn8PPpbXBTujI7xcY8uGFCs", "is_direct": false}], "job_description": "At Truckstop, we have transformed the entire freight-moving lifecycle with our SaaS solutions. \u202fFrom freight matching to payments and everything in between, we are the trusted partner for carriers, brokers, and shippers alike. We lead this industry forward with our One Team mindset committing to principles such as assume positive intent, have each other\u2019s back, and be your authentic self.\u202f Our drive for greatness produces high expectations, yet our regard for humans is even higher. Join a team of brilliant minds and generous hearts who care deeply about other's success. \u202f\n\nPosition Summary\n\nThe Lead Data Scientist is a subject matter expert that will provide advice on technical issues, business issues, and team operations. This position will report directly to the Sr. Director of Data Science, will actively lead projects, write production quality code, deploy models, mentor individuals on the Data Science Team, and regularly find ways to improve team dynamics. The Lead Data Scientist is a key contributor to data science strategy and can solve unique problems. This role will help recruit top talent.\n\nEssential Job Functions\n\u2022 Ownership and leadership in two major verticals within the data science team such as Product Data Science, Personalization, or Fraud Detection.\n\u2022 Provide technical and thought leadership for the data science team\n\u2022 Can present to a wide audience\n\u2022 Accountable for the quality and design of the systems built while providing guidance\n\u2022 Partner with department head on technical direction and strategy\n\u2022 Bring business context to decisions made across teams\n\u2022 Provide exemplary architectures in terms of robustness, stability, scalability and cost-effectiveness\n\u2022 Continuously decompose complex problems into simple, straight-forward solutions\n\u2022 Suggest appropriate algorithms for specific technical challenges at hand, and lead team members to implement and tune the algorithms\n\u2022 Consultant and technical expert in high-stakes projects\n\u2022 Flexibly apply ETL best practices, identify and resolve challenges long-term in key stages\n\u2022 Actively mentor individuals on advanced data science techniques\n\u2022 Regularly examine team culture looking for ways to improve team dynamics\n\u2022 Contribute to Truckstop\u2019s intellectual property\n\u2022 Key contributor to engineering strategy and large projects\n\u2022 Participate with the external technical community\n\u2022 Write production quality code, APIs, and data pipelines\n\u2022 Train and deploy statistical and machine learning models\n\u2022 Design and measure experiments\n\u2022 Bring actionable and thoughtful solutions / recommendations to roadblocks\n\u2022 Participate in hiring process by interviewing and making recommendations\n\u2022 Use causal reasoning to triage problems\n\u2022 Document postmortem\n\nPosition Requirements\n\u2022 MS or PhD in Computer Science, Math, Physics or related field, and 5-9+ years of data science experience. PhD strongly preferred, but will evaluate relevant experience + MS in lieu of a PhD\n\u2022 Strong experience in building practical, efficient, accurate, reliable, and scalable data science models\n\u2022 Strong understanding of data architecture fundamentals\n\u2022 Fluency in machine learning algorithms for supervised and unsupervised scenario\n\u2022 Understanding of the business value of data problems\n\u2022 Deeply understand the construction of user centric tracking and segmentation systems or similar experiences\n\u2022 Deep understanding of the limitations of various algorithms and suggesting appropriate algorithms for specific technical challenges at hand, and leading team members to implement and tune the algorithms\n\u2022 Considering the time and space complexity of algorithms and implementation of complete algorithms\n\u2022 Applying multi-source attribution models to analyze importance of product features\n\u2022 Understand ETL best practices, identifying and resolving challenges long-term in key stages\n\u2022 Expert in Linux, familiar with command line operations\n\u2022 Expert in Python\n\u2022 Architect API based modules and lead team to develop these implementations in parallel with collaborating teams\n\nAt Truckstop we are dedicated to creating a workplace that is equitable, inclusive, and inspiring for every employee. In an effort to provide greater transparency, we are sharing the base salary range for this position. The position is also eligible for a yearly bonus. Final salary is based on a number of factors including market location, job-related knowledge, education/training, certifications, key skills, experience, internal peer equity as well as business considerations.\n\nThe anticipated base pay range for this position is :\n\n$150,000\u2014$165,000 USD\n\nThe above description covers the most significant duties performed but does not include other related occasional work that may be assigned or is completed by the employee.\u202f\n\nTruckstop provides equal employment opportunities to all employees and applicants for employment and prohibits discrimination and harassment of any type without regard to race, color, religion, age, sex, national origin, disability status, genetics, protected veteran status, sexual orientation, gender identity or expression, or any other characteristic protected by federal, state, or local laws.\u202f\n\nTruckstop Privacy Policy", "job_is_remote": true, "job_posted_at_timestamp": 1709956618, "job_posted_at_datetime_utc": "2024-03-09T03:56:58.000Z", "job_city": null, "job_state": null, "job_country": "US", "job_latitude": 37.09024, "job_longitude": -95.71289, "job_benefits": null, "job_google_link": "https://www.google.com/search?gl=us&hl=en&rciv=jb&q=lead+data+scientist&start=40&ibp=htl;jobs#fpstate=tldetail&htivrt=jobs&htiq=lead+data+scientist&htidocid=fO2FAdf0KLcJ5cYbAAAAAA%3D%3D", "job_offer_expiration_datetime_utc": "2024-04-08T03:56:58.000Z", "job_offer_expiration_timestamp": 1712548618, "job_required_experience": {"no_experience_required": false, "required_experience_in_months": 60, "experience_mentioned": true, "experience_preferred": true}, "job_required_skills": null, "job_required_education": {"postgraduate_degree": false, "professional_certification": false, "high_school": false, "associates_degree": false, "bachelors_degree": true, "degree_mentioned": true, "degree_preferred": false, "professional_certification_mentioned": true}, "job_experience_in_place_of_education": false, "job_min_salary": null, "job_max_salary": null, "job_salary_currency": null, "job_salary_period": null, "job_highlights": {"Qualifications": ["MS or PhD in Computer Science, Math, Physics or related field, and 5-9+ years of data science experience"], "Responsibilities": ["The Lead Data Scientist is a subject matter expert that will provide advice on technical issues, business issues, and team operations", "This position will report directly to the Sr", "Director of Data Science, will actively lead projects, write production quality code, deploy models, mentor individuals on the Data Science Team, and regularly find ways to improve team dynamics", "The Lead Data Scientist is a key contributor to data science strategy and can solve unique problems", "This role will help recruit top talent", "Ownership and leadership in two major verticals within the data science team such as Product Data Science, Personalization, or Fraud Detection", "Provide technical and thought leadership for the data science team", "Can present to a wide audience", "Accountable for the quality and design of the systems built while providing guidance", "Partner with department head on technical direction and strategy", "Bring business context to decisions made across teams", "Provide exemplary architectures in terms of robustness, stability, scalability and cost-effectiveness", "Continuously decompose complex problems into simple, straight-forward solutions", "Suggest appropriate algorithms for specific technical challenges at hand, and lead team members to implement and tune the algorithms", "Consultant and technical expert in high-stakes projects", "Flexibly apply ETL best practices, identify and resolve challenges long-term in key stages", "Actively mentor individuals on advanced data science techniques", "Regularly examine team culture looking for ways to improve team dynamics", "Contribute to Truckstop\u2019s intellectual property", "Key contributor to engineering strategy and large projects", "Participate with the external technical community", "Write production quality code, APIs, and data pipelines", "Train and deploy statistical and machine learning models", "Design and measure experiments", "Bring actionable and thoughtful solutions / recommendations to roadblocks", "Participate in hiring process by interviewing and making recommendations", "Use causal reasoning to triage problems", "Document postmortem"], "Benefits": ["The position is also eligible for a yearly bonus", "Final salary is based on a number of factors including market location, job-related knowledge, education/training, certifications, key skills, experience, internal peer equity as well as business considerations", "$150,000\u2014$165,000 USD"]}, "job_job_title": "Data scientist", "job_posting_language": "en", "job_onet_soc": "15111100", "job_onet_job_zone": "5"}