{"job_id": "6f-tQw9X3VArUThJAAAAAA==", "employer_name": "Tipico - North America", "employer_logo": null, "employer_website": null, "employer_company_type": null, "job_publisher": "Smart Recruiters Jobs", "job_employment_type": "FULLTIME", "job_title": "Senior Data Engineer", "job_apply_link": "https://jobs.smartrecruiters.com/Tipico-NorthAmerica/743999974226993-senior-data-engineer", "job_apply_is_direct": false, "job_apply_quality_score": 0.6404, "apply_options": [{"publisher": "Smart Recruiters Jobs", "apply_link": "https://jobs.smartrecruiters.com/Tipico-NorthAmerica/743999974226993-senior-data-engineer", "is_direct": false}, {"publisher": "LinkedIn", "apply_link": "https://www.linkedin.com/jobs/view/senior-data-engineer-at-tipico-north-america-3857272363", "is_direct": false}, {"publisher": "ZipRecruiter", "apply_link": "https://www.ziprecruiter.com/c/Tipico-North-America/Job/Senior-Data-Engineer/-in-Denver,CO?jid=70687014781cc5bc", "is_direct": false}, {"publisher": "Indeed", "apply_link": "https://www.indeed.com/viewjob?jk=f07b93de0e9eefc7", "is_direct": false}, {"publisher": "Monster", "apply_link": "https://www.monster.com/job-openings/senior-data-engineer-denver-co--507f7046-a6be-467c-ba00-ed2a6bca9d97", "is_direct": false}, {"publisher": "Built In Colorado", "apply_link": "https://www.builtincolorado.com/job/senior-data-engineer/173269", "is_direct": false}, {"publisher": "Glassdoor", "apply_link": "https://www.glassdoor.com/job-listing/senior-data-engineer-tipico-north-america-JV_IC1148170_KO0,20_KE21,41.htm?jl=1009188958254", "is_direct": false}, {"publisher": "Jooble", "apply_link": "https://jooble.org/jdp/3757607463079652047", "is_direct": false}], "job_description": "Company Description\n\nFounded in Europe in 2004, Tipico is now a licensed U.S. Sportsbook operating in New Jersey, Iowa, Ohio, and Colorado. Renowned in Germany and globally, Tipico offers online betting across 30 sports. Guided by values such as innovation and inclusion, Tipico focuses on creating top-notch mobile sports betting and casino products. Recently recognized as the No. 1 rated casino app in the U.S., Tipico is dedicated to enhancing gaming excitement for millions daily. Join us in redefining excellence in online entertainment!\n\nPlease note: this role is located in our Denver, CO office; we work off a hybrid model and come into the office 2 days per week.\n\nJob Description\n\nThe Data Engineer is responsible for developing, constructing, testing and maintaining Tipico\u2019s data platform and pipelines. This is achieved by ensuring the infrastructure is reliable and a high level of data quality is maintained.\n\nThe Data Engineer will report directly to the VP of data or team lead and work together with rest of the data engineers, BI analysts, and product teams. This person will:\n\u2022 Create and maintain both batch (ETL) and real-time data pipelines and architecture\u202f\u202f\n\u2022 Ensure all data provided by Data Platform is of the highest quality and is delivered in a timely manner and in line with agreed SLAs\u202f\u202f\n\u2022 Assemble large and complex data sets that meet functional and non-functional business requirements\u202f\u202f\n\u2022 Identify, design, and implement internal process improvements: automating manual processes, optimizing data delivery, re-designing infrastructure for greater scalability, etc.\u202f\u202f\n\u2022 Build the infrastructure required for optimal extraction, transformation and loading of data from a wide variety of data sources using SQL and AWS \u2018big data\u2019 technologies\u202f\u202f\n\u2022 Collaborate with stakeholders including data architects, Executive, Product, Data, and IT team members from the beginning to the delivery of a project\u202f\u202f\n\u2022 Build a scalable, modern, and trusted data eco system, making sure it is responsive, available and in line with business requirements\u202f\u202f\n\u2022 Design, build, and scale data pipelines across a variety of source systems and streams (internal, third-party, as well as cloud-based), distributed/elastic environments, and downstream applications and/or self-service solutions\u202f\u202f\n\u2022 Think of new ways to help make our data platform more scalable, resilient, and reliable and then work across our team to put your ideas into action\u202f\u202f\n\u2022 Take part in sprints, workloads, and deliverables through agile methodologies.\u202f\u202f\u202f\n\u2022 Manage quality assurance, verification of accuracy and consistency of data \u2013 specifically KPI measures sent to the business\u202f\u202f\n\u2022 Provide expert level advice to data engineers to deliver high quality data pipelines and ETL flows. Review design and code produced by other engineers\u202f\u202f\n\nQualifications\n\nEducation\n\u2022 Bachelor's degree in Computer Science, Computer Engineering, relevant technical field, or equivalent practical experience\n\nExperience\n\u2022 Experience working in an online, gaming, or fast-moving industry required\n\u2022 7+ years of work experience in data engineers and data platforms\n\u2022 Must have experience in successfully implementing data-centric applications, such as data warehouses, operational data stores, and data integration projects\u202f\u202f\n\u2022 Experience with SQL, ETL, data modeling, and Python\n\u2022 Experience working with terabyte to petabyte scale data\n\u2022 Designing technical solutions and teaching team members.\n\nSkills\n\u2022 Excellent Verbal and written Communication skills\n\u2022 Strong analytical and problem-solving skills that balance with creative approaches\u202f\u202f\u202f\n\u2022 Ability to take ownership of projects with diligence and consistency in carrying out tasks with a high level of attention to detail and priority\n\u2022 Collaborative, able to engage in interactive discussions with the rest of the team and able to communicate technical concepts clearly and concisely\n\nLanguage\n\u2022 Fluent in English, Oral and written \u2013 essential\n\nFunctional/Technical Competence\n\u2022 Strong experience with large-scale production databases and SQL\u202f\u202f\n\u2022 Solid understanding of cloud data services: AWS services such as S3, Athena, EC2, RedShift, EMR, EKS, RDS and Lambda\u202f\u202f\n\u2022 Proficient with one or more big data & new data technologies such as DBT, NIFI, Airflow, Kafka\u202f\u202f\n\u2022 Knowledge in working with time-series/analytics databases such as Elasticsearch\u202f\u202f\n\u2022 Understanding of containerization and orchestration technologies like Docker/Kubernetes\u202f\u202f\n\u2022 Familiarity with Marketing tooling and/or CRM systems is preferred\u202f\u202f\n\u2022 Familiarity with using business intelligence tools such as Domo, Superset or other similar tooling\u202f\u202f\n\nPersonal Characteristics\n\u2022 Exemplifies our values \u2013 Trust, Passion and Progress\n\u2022 Proactive, agile, innovative and solution orientated work approach with strong sense of ownership and accountability for his\u2019s/her\u2019s work and impact on business\n\u2022 Thrives working in a fast-paced and challenging environment\n\u2022 Ability to think outside of the box, be innovative, adaptable, identify continuous improvement areas and come up with creative solutions to challenges\n\u2022 Detail-oriented and organized.\u202f\n\u2022 Strong work ethic and ability to work in a collaborative environment.\u202f\n\u2022 Ability to multitask and prioritize.\u202f\n\u2022 Adaptability and flexibility\u202f\n\u2022 Constructively challenges with positive arguments\n\u2022 Comfortable with being challenged / seeking challenge\n\nAdditional Information\n\nWhat's in it for you:\n\u2022 Work in a new and thriving industry with high growth potential.\n\u2022 Competitive salary and performance bonus.\n\u2022 Medical, Dental, and Vision Insurance.\n\u2022 401k employer matching.\n\u2022 Unlimited PTO with 15 paid holidays.\n\u2022 100% paid parental leave.\n\u2022 Professional training and development opportunities.\n\u2022 Gym reimbursement.\n\u2022 Free workout classes at Prime Cycle in Hoboken, NJ.\n\u2022 1-year free Apple Fitness+ subscription.\n\u2022 Work in an environment with a start-up feeling, backed-up by a leading European sports betting house. We are a high-volume business and are taking off in the US!\n\nSalary range for this role is $140-150k", "job_is_remote": false, "job_posted_at_timestamp": 1710531022, "job_posted_at_datetime_utc": "2024-03-15T19:30:22.000Z", "job_city": "Denver", "job_state": "CO", "job_country": "US", "job_latitude": 39.739235, "job_longitude": -104.99025, "job_benefits": ["dental_coverage", "paid_time_off", "retirement_savings", "health_insurance"], "job_google_link": "https://www.google.com/search?gl=us&hl=en&rciv=jb&q=data+engineer&start=30&ibp=htl;jobs#fpstate=tldetail&htivrt=jobs&htiq=data+engineer&htidocid=6f-tQw9X3VArUThJAAAAAA%3D%3D", "job_offer_expiration_datetime_utc": null, "job_offer_expiration_timestamp": null, "job_required_experience": {"no_experience_required": false, "required_experience_in_months": 84, "experience_mentioned": true, "experience_preferred": false}, "job_required_skills": null, "job_required_education": {"postgraduate_degree": false, "professional_certification": false, "high_school": false, "associates_degree": false, "bachelors_degree": false, "degree_mentioned": true, "degree_preferred": true, "professional_certification_mentioned": false}, "job_experience_in_place_of_education": false, "job_min_salary": null, "job_max_salary": null, "job_salary_currency": null, "job_salary_period": null, "job_highlights": {"Qualifications": ["Bachelor's degree in Computer Science, Computer Engineering, relevant technical field, or equivalent practical experience", "Experience working in an online, gaming, or fast-moving industry required", "7+ years of work experience in data engineers and data platforms", "Must have experience in successfully implementing data-centric applications, such as data warehouses, operational data stores, and data integration projects\u202f\u202f", "Experience with SQL, ETL, data modeling, and Python", "Experience working with terabyte to petabyte scale data", "Designing technical solutions and teaching team members", "Excellent Verbal and written Communication skills", "Strong analytical and problem-solving skills that balance with creative approaches\u202f\u202f\u202f", "Ability to take ownership of projects with diligence and consistency in carrying out tasks with a high level of attention to detail and priority", "Collaborative, able to engage in interactive discussions with the rest of the team and able to communicate technical concepts clearly and concisely", "Fluent in English, Oral and written \u2013 essential", "Functional/Technical Competence", "Strong experience with large-scale production databases and SQL\u202f\u202f", "Solid understanding of cloud data services: AWS services such as S3, Athena, EC2, RedShift, EMR, EKS, RDS and Lambda\u202f\u202f", "Proficient with one or more big data & new data technologies such as DBT, NIFI, Airflow, Kafka\u202f\u202f", "Knowledge in working with time-series/analytics databases such as Elasticsearch\u202f\u202f", "Understanding of containerization and orchestration technologies like Docker/Kubernetes\u202f\u202f", "Familiarity with using business intelligence tools such as Domo, Superset or other similar tooling\u202f\u202f", "Exemplifies our values \u2013 Trust, Passion and Progress", "Proactive, agile, innovative and solution orientated work approach with strong sense of ownership and accountability for his\u2019s/her\u2019s work and impact on business", "Thrives working in a fast-paced and challenging environment", "Ability to think outside of the box, be innovative, adaptable, identify continuous improvement areas and come up with creative solutions to challenges", "Detail-oriented and organized.\u202f", "Strong work ethic and ability to work in a collaborative environment.\u202f", "Ability to multitask and prioritize.\u202f", "Adaptability and flexibility\u202f", "Constructively challenges with positive arguments", "Comfortable with being challenged / seeking challenge"], "Responsibilities": ["The Data Engineer is responsible for developing, constructing, testing and maintaining Tipico\u2019s data platform and pipelines", "This is achieved by ensuring the infrastructure is reliable and a high level of data quality is maintained", "The Data Engineer will report directly to the VP of data or team lead and work together with rest of the data engineers, BI analysts, and product teams", "Create and maintain both batch (ETL) and real-time data pipelines and architecture\u202f\u202f", "Ensure all data provided by Data Platform is of the highest quality and is delivered in a timely manner and in line with agreed SLAs\u202f\u202f", "Assemble large and complex data sets that meet functional and non-functional business requirements\u202f\u202f", "Identify, design, and implement internal process improvements: automating manual processes, optimizing data delivery, re-designing infrastructure for greater scalability, etc.\u202f\u202f", "Build the infrastructure required for optimal extraction, transformation and loading of data from a wide variety of data sources using SQL and AWS \u2018big data\u2019 technologies\u202f\u202f", "Collaborate with stakeholders including data architects, Executive, Product, Data, and IT team members from the beginning to the delivery of a project\u202f\u202f", "Build a scalable, modern, and trusted data eco system, making sure it is responsive, available and in line with business requirements\u202f\u202f", "Design, build, and scale data pipelines across a variety of source systems and streams (internal, third-party, as well as cloud-based), distributed/elastic environments, and downstream applications and/or self-service solutions\u202f\u202f", "Think of new ways to help make our data platform more scalable, resilient, and reliable and then work across our team to put your ideas into action\u202f\u202f", "Take part in sprints, workloads, and deliverables through agile methodologies.\u202f\u202f\u202f", "Manage quality assurance, verification of accuracy and consistency of data \u2013 specifically KPI measures sent to the business\u202f\u202f", "Provide expert level advice to data engineers to deliver high quality data pipelines and ETL flows", "Review design and code produced by other engineers\u202f\u202f"], "Benefits": ["Work in a new and thriving industry with high growth potential", "Competitive salary and performance bonus", "Medical, Dental, and Vision Insurance", "401k employer matching", "Unlimited PTO with 15 paid holidays", "100% paid parental leave", "Professional training and development opportunities", "Gym reimbursement", "Free workout classes at Prime Cycle in Hoboken, NJ", "1-year free Apple Fitness+ subscription", "Work in an environment with a start-up feeling, backed-up by a leading European sports betting house", "Salary range for this role is $140-150k"]}, "job_job_title": "Data engineer", "job_posting_language": "en", "job_onet_soc": "15113200", "job_onet_job_zone": "4"}