{"job_id": "UfsOfNVurNAjlSOCAAAAAA==", "employer_name": "United States Fund for UNICEF", "employer_logo": "https://lookaside.fbsbx.com/lookaside/crawler/media/?media_id=100064501041951", "employer_website": "http://www.unicefusa.org", "employer_company_type": null, "job_publisher": "SimplyHired", "job_employment_type": "FULLTIME", "job_title": "Senior Director, Foundation Partnerships", "job_apply_link": "https://www.simplyhired.com/job/13eia8NWgnlonBftPIW6bGelmpChyWWVmGFr094dYPOvE_jytzxBrA", "job_apply_is_direct": false, "job_apply_quality_score": 0.5404, "apply_options": [{"publisher": "SimplyHired", "apply_link": "https://www.simplyhired.com/job/13eia8NWgnlonBftPIW6bGelmpChyWWVmGFr094dYPOvE_jytzxBrA", "is_direct": false}], "job_description": "Organization Overview\n\nUNICEF USA (\u201cUUSA\u201d or \u201cWe\u201d) relentlessly pursues a more equitable world for every child, upholding the rights of all children and empowering every child, everywhere. We also support the fundamental belief that children should have a voice and role in shaping their futures and the futures of their communities.\n\nOver eight decades, the United Nations Children\u2019s Fund (UNICEF) has built an unprecedented global support system for the world\u2019s children, and has boldly taken on the biggest, seemingly impossible challenges facing children. UNICEF relentlessly works day in and day out to deliver the essentials that give every child an equitable chance in life: health care and immunizations, safe water and sanitation, nutrition, education, emergency relief and more. UNICEF USA advances the global mission of UNICEF by rallying the American public to support the world\u2019s most vulnerable children.\n\nWe know that sustainable change is attainable, but it can\u2019t be achieved alone. It takes a committed team \u2013 individuals, governments, corporations, volunteers and staff \u2013 who demonstrate a relentless commitment to working tirelessly, day in and day out in some of the toughest, hardest to reach places. Big problems need big solutions, and we harness our collective, global voice and energy to do better, in more places for children. We will never stop supporting UNICEF to develop smarter, more cost-effective solutions; scaling up proven, data-driven programs; and harnessing new technologies to create measurable change for children.\n\nUUSA is organized under the laws of New York State as a not-for-profit corporation. As such, UUSA is a tax-exempt organization as defined under Section 501(c)3 of the Internal Revenue Code and is governed by an independent, non-salaried Board of Directors.\n\nPosition: Senior Director, Foundation Partnerships\n\nLocation: Nationwide / Remote\n\nFLSA Status: Exempt\n\nSalary: The estimated salary range for this position is $125,500 - $144,100. This midpoint for the salary grade is $163,200. Actual pay will vary based on various factors, including but not limited to relevant experience.\n\nPosition Description\n\nThe Senior Director is a senior leader on the Foundation Partnerships team, responsible for leading the development of thematic strategies for a portfolio focused on Education, Child and Social Protection, Advocacy, Data, Social Behavior Change, Innovation and Gender. The role will serve to cultivate partnership development, proactively growing and securing new partnerships with leading U.S. private foundations and institutions, and directly overseeing the workstream a The Senior Director reports to the Vice President.\n\nPosition Responsibilities\n\nStrategy & Operations (40 percent)\n\u2022 Lead the development of Education, Child and Social Protection, Advocacy, Data, Social Behavior Change, Innovation and Gender vertical-wide partnership strategy, including conducting or overseeing landscape mapping, research and analysis, and build stewardship strategies.\n\u2022 Oversee the development of specific Education, Child and Social Protection, Advocacy, Data, Social Behavior Change, Innovation and Gender focused thematic outreach and engagement strategies.\n\u2022 Manage and oversee four program thematic vertical staff. Mentor, and coach direct reports to manage increasingly complex funding relationships and grants, and foster professional development.\n\u2022 Initiate innovative ideas to generate new revenue and add value to partnerships and develop compelling presentations and proposals. This includes potential challenges, competitions, innovative financing, and new ways of working together to achieve intended outcomes.\n\u2022 Support the skills development and training of staff on partnership development.\n\u2022 Forecast and develop budget projections for foundation partnerships.\n\u2022 Monitor vertical revenue and provide updates on revenue projections; identify and address any anticipated issues in meeting budget expectations.\n\u2022 Liaise with UNICEF USA finance and compliance personnel to resolve any legal, procedural or financial issues regarding grants, sub-grants and contracts.\n\u2022 Maximize outcomes by partnering with internal UUSA teams (Finance, Individual and Institutional Philanthropy, Marketing & Communications, Philanthropy Insight, Philanthropy Advancement and the Impact Fund for Children) to leverage resources.\n\u2022 Partner with Philanthropy Advancement and Philanthropy Insight to understand latest trends and research and support performance measurement.\n\u2022 Work closely with UUSA senior leadership and UNICEF technical experts and program leads to identify needs, opportunities, and alignment with programmatic priorities.\n\u2022 Contribute to thought-leadership objectives to grow the UNICEF brand within the foundation landscape.\n\nPartnership Development (50 percent)\n\u2022 Leads relationships with key donors investing in Education, Child and Social Protection, Advocacy, Data, Social Behavior Change, Innovation and Gender.\n\u2022 Advises in development and implementation of new partnership engagement and strategies.\n\u2022 Seeks and promotes new partnerships in alignment with the programmatic thematic pillar to support of the larger UNICEF agenda, working with UNICEF colleagues to identify partnership needs, objectives, and funding gaps.\n\u2022 Identifies, stewards, and manages a portfolio of diverse prospects and partners to expand UNICEF\u2019s reach and involvement with the goal of mobilizing resources. Supports the team to facilitate successful partnerships.\n\u2022 Receives and screens inquiries from potential collaborators and facilitates communication with appropriate UNICEF USA and UNICEF colleagues.\n\u2022 Expands UNICEF and UNICEF USA\u2019s network of key interlocutors to build stronger relationships and thought leadership engagements to advance partnerships.\n\u2022 Develops and maintains deep knowledge and familiarity with current and prospective partners and relevant stakeholders, contributing to a database of key contacts and to UNICEF USA\u2019s base of knowledge on partnership and overall larger objectives.\n\u2022 Cultivate, manage and grow relationships with foundation prospects and secure annual revenue of at least $2.5 Million.\n\nGrants Management (10 percent)\n\u2022 Provides oversight on overall grants management activities of the vertical workstream, focused on Education, Child and Social Protection, Advocacy, Data, Social Behavior Change, Innovation and Gender programming.\n\u2022 Troubleshoot and provide guidance on grants management activities.\n\u2022 Identify opportunities to communicate grants impact and outcomes across UNICEF USA and UNICEF.\n\u2022 Negotiate partnership terms and contracts.\n\nQualifications:\n\u2022 Bachelor\u2019s degree with a minimum 10-12 years\u2019 experience in a partnership management or strategic partnerships role; a mix of foundation and non-profit experience preferred.\n\u2022 Advanced degree in international development, international relations, global/public health, or a related field welcome.\n\u2022 Experience managing a team and supporting their growth.\n\u2022 Significant relationship-building skills including with a network of institutional foundations, ability to generate revenue, and partnership management experience\n\u2022 Preferred experience with Education, Child and Social Protection, Advocacy, Data, Social Behavior Change, Innovation and Gender focused development programming.\n\u2022 Proven ability to generate revenue growth; ability to identify and pursue new opportunities\n\u2022 Ability to build relationships with individuals with diverse personalities and styles and at different levels of seniority, from assistants to C-level leadership\n\u2022 Ability to develop and execute a business or account plan including goals, metrics, strategy, and tactics\n\u2022 Ability to navigate complex relationships, thrive in a fast-paced environment, and to prioritize multiple deadlines\n\u2022 Excellent problem solving and negotiation skills; ability to effectively collect, analyze, organize distill and present information\n\u2022 Excellent written and oral communication skills\n\u2022 Self-motivated; ability to lead projects independently from concept to completion\n\u2022 Some travel required, within the U.S. and internationally\n\nMust possess current and valid US Work Authorization and be eligible to work for any US employer without sponsorship.\n\nDue to the high volume of applications received, only those selected for an interview will be contacted.\n\nUNICEF USA is proud to be an Equal Opportunity Employer\n\nWe do not discriminate based upon race, religion, color, national origin, sex (including pregnancy, childbirth, reproductive health decisions, or related medical conditions), sexual orientation, gender identity, gender expression, age, status as a protected veteran, status as an individual with a disability, genetic information, or other applicable legally protected characteristics. We also consider qualified applicants with criminal histories, consistent with applicable federal, state, and local law. UUSA is committed to providing reasonable accommodations for qualified individuals with disabilities and disabled veterans in our job application procedures. If you need assistance or accommodation due to a disability, you may contact us at peopleandculture@unicefusa.org.", "job_is_remote": false, "job_posted_at_timestamp": 1698296400, "job_posted_at_datetime_utc": "2023-10-26T05:00:00.000Z", "job_city": "New York", "job_state": "NY", "job_country": "US", "job_latitude": 40.712776, "job_longitude": -74.005974, "job_benefits": null, "job_google_link": "https://www.google.com/search?gl=us&hl=en&rciv=jb&q=senior+director+of+brand+partnerships&start=0&ibp=htl;jobs#fpstate=tldetail&htivrt=jobs&htiq=senior+director+of+brand+partnerships&htidocid=UfsOfNVurNAjlSOCAAAAAA%3D%3D", "job_offer_expiration_datetime_utc": null, "job_offer_expiration_timestamp": null, "job_required_experience": {"no_experience_required": false, "required_experience_in_months": 120, "experience_mentioned": true, "experience_preferred": true}, "job_required_skills": null, "job_required_education": {"postgraduate_degree": false, "professional_certification": false, "high_school": false, "associates_degree": false, "bachelors_degree": false, "degree_mentioned": true, "degree_preferred": true, "professional_certification_mentioned": false}, "job_experience_in_place_of_education": false, "job_min_salary": null, "job_max_salary": null, "job_salary_currency": null, "job_salary_period": null, "job_highlights": {"Qualifications": ["Expands UNICEF and UNICEF USA\u2019s network of key interlocutors to build stronger relationships and thought leadership engagements to advance partnerships", "Develops and maintains deep knowledge and familiarity with current and prospective partners and relevant stakeholders, contributing to a database of key contacts and to UNICEF USA\u2019s base of knowledge on partnership and overall larger objectives", "Advanced degree in international development, international relations, global/public health, or a related field welcome", "Experience managing a team and supporting their growth", "Significant relationship-building skills including with a network of institutional foundations, ability to generate revenue, and partnership management experience", "Proven ability to generate revenue growth; ability to identify and pursue new opportunities", "Ability to build relationships with individuals with diverse personalities and styles and at different levels of seniority, from assistants to C-level leadership", "Ability to develop and execute a business or account plan including goals, metrics, strategy, and tactics", "Ability to navigate complex relationships, thrive in a fast-paced environment, and to prioritize multiple deadlines", "Excellent problem solving and negotiation skills; ability to effectively collect, analyze, organize distill and present information", "Excellent written and oral communication skills", "Self-motivated; ability to lead projects independently from concept to completion", "Some travel required, within the U.S. and internationally", "Must possess current and valid US Work Authorization and be eligible to work for any US employer without sponsorship"], "Responsibilities": ["The role will serve to cultivate partnership development, proactively growing and securing new partnerships with leading U.S. private foundations and institutions, and directly overseeing the workstream a The Senior Director reports to the Vice President", "Strategy & Operations (40 percent)", "Lead the development of Education, Child and Social Protection, Advocacy, Data, Social Behavior Change, Innovation and Gender vertical-wide partnership strategy, including conducting or overseeing landscape mapping, research and analysis, and build stewardship strategies", "Oversee the development of specific Education, Child and Social Protection, Advocacy, Data, Social Behavior Change, Innovation and Gender focused thematic outreach and engagement strategies", "Manage and oversee four program thematic vertical staff", "Mentor, and coach direct reports to manage increasingly complex funding relationships and grants, and foster professional development", "Initiate innovative ideas to generate new revenue and add value to partnerships and develop compelling presentations and proposals", "Support the skills development and training of staff on partnership development", "Forecast and develop budget projections for foundation partnerships", "Monitor vertical revenue and provide updates on revenue projections; identify and address any anticipated issues in meeting budget expectations", "Liaise with UNICEF USA finance and compliance personnel to resolve any legal, procedural or financial issues regarding grants, sub-grants and contracts", "Maximize outcomes by partnering with internal UUSA teams (Finance, Individual and Institutional Philanthropy, Marketing & Communications, Philanthropy Insight, Philanthropy Advancement and the Impact Fund for Children) to leverage resources", "Partner with Philanthropy Advancement and Philanthropy Insight to understand latest trends and research and support performance measurement", "Work closely with UUSA senior leadership and UNICEF technical experts and program leads to identify needs, opportunities, and alignment with programmatic priorities", "Contribute to thought-leadership objectives to grow the UNICEF brand within the foundation landscape", "Advises in development and implementation of new partnership engagement and strategies", "Seeks and promotes new partnerships in alignment with the programmatic thematic pillar to support of the larger UNICEF agenda, working with UNICEF colleagues to identify partnership needs, objectives, and funding gaps", "Identifies, stewards, and manages a portfolio of diverse prospects and partners to expand UNICEF\u2019s reach and involvement with the goal of mobilizing resources", "Supports the team to facilitate successful partnerships", "Provides oversight on overall grants management activities of the vertical workstream, focused on Education, Child and Social Protection, Advocacy, Data, Social Behavior Change, Innovation and Gender programming", "Troubleshoot and provide guidance on grants management activities", "Identify opportunities to communicate grants impact and outcomes across UNICEF USA and UNICEF"], "Benefits": ["Salary: The estimated salary range for this position is $125,500 - $144,100", "This midpoint for the salary grade is $163,200", "Cultivate, manage and grow relationships with foundation prospects and secure annual revenue of at least $2.5 Million", "Negotiate partnership terms and contracts"]}, "job_job_title": "Senior director", "job_posting_language": "en", "job_onet_soc": "11203100", "job_onet_job_zone": "4"}