{"job_id": "KQvAKYHsKEixV2hFAAAAAA==", "employer_name": "CareerPlug", "employer_logo": null, "employer_website": null, "employer_company_type": null, "job_publisher": "Jooble", "job_employment_type": "FULLTIME", "job_title": "Senior Marketing Manager, Partners", "job_apply_link": "https://jooble.org/jdp/-2916253606923102217", "job_apply_is_direct": false, "job_apply_quality_score": 0.6474, "apply_options": [{"publisher": "Jooble", "apply_link": "https://jooble.org/jdp/-2916253606923102217", "is_direct": false}, {"publisher": "Media Bistro", "apply_link": "https://www.mediabistro.com/jobs/210943444-senior-marketing-manager-upgrades", "is_direct": false}, {"publisher": "Learn4Good", "apply_link": "https://www.learn4good.com/jobs/online_remote/marketing_and_pr/2975425938/e/", "is_direct": false}], "job_description": "Be a key contributor to an exciting software company!\n\nCareerPlug provides innovative recruiting and HR software for over 17,000 growing companies. Our applicant tracking and paperless onboarding platforms help companies make better hires to have the right people in place to build a successful business.\n\nWe believe that people are the heart of our business and are committed to building one of the best places to work --anywhere. To us, that means putting care and purpose into our hiring process, providing meaningful development and training opportunities for our team members, and living our core values every day.\n\nCareerPlug is proud to be an equal opportunity employer committed to fostering a diverse team. Our leadership takes responsibility for creating a safe and welcoming environment built on inclusion and respect for all.\n\nWho are we looking for?\n\nWe are looking for a Senior Marketing Manager, Partners to work across the company to play a crucial role in driving the growth of our partner ecosystem of franchisors and membership-based organizations. This is an individual contributor role reporting directly to the VP of Marketing who will focus on creating compelling content to attract and engage potential partners, ultimately leading to scheduled demos.\n\nKey Responsibilities:\n\u2022 Outbound Campaigns for Prospecting:\n\u2022 Develop and execute outbound campaigns targeting prospective partners to generate new leads\n\u2022 Craft compelling, personalized messaging for targeted prospects\n\u2022 Create content to effectively communicate the value proposition of partnering with CareerPlug\n\u2022 Collaborate with cross-functional teams to ensure alignment with overall marketing and business objectives\n\u2022 Campaigns for Prospecting Units within Partners:\n\u2022 Design targeted campaigns to reach specific franchisees or members within existing partners for prospecting purposes to gain access to the decision-makers within the brand/organization\n\u2022 Tailor messaging to address the unique needs and challenges of different partner segments\n\u2022 Work closely with sales teams to align campaigns with partner-specific goals\n\u2022 Leverage content calendar for up-to-date content\n\u2022 Personalized Marketing for Partner Prospects:\n\u2022 Collaborate with the rest of the marketing team to create or leverage marketing materials to engage and nurture potential partners.\n\u2022 Utilize data-driven insights to tailor content for specific industries, regions, and partner profiles\n\u2022 Implement strategies to enhance the partner to increase conversion rates of franchisees and association members by working with key contacts within the partner's organization\n\u2022 Demo Script and Sales Enablement:\n\u2022 Develop impactful demo scripts and sales material to showcase the key features and benefits of our offerings to potential partners.\n\u2022 Create comprehensive sales enablement materials that empower the sales team to effectively communicate with partners during demos.\n\u2022 Collaborate with product teams to stay updated on new features and ensure accurate representation in sales materials.\n\nKey Qualifications:\n\u2022 5+ years working in a SaaS company preferred\n\u2022 Familiarity with the franchise business model and experience with working with brands and or membership organizations\n\u2022 Familiarity with Human Capital Management, HR, and Applicant Tracking Systems\n\u2022 Demonstrated success in creating and implementing innovative, result-oriented, full-funnel marketing programs with proven results\n\u2022 Persuasive and able to relate/empathize with entrepreneurs and small business owners\n\u2022 Experience with Canva to use templates and a brand library is a plus!\n\u2022 Experience with HubSpot is a plus!\n\nBenefits:\n\u2022 100% Remote Company!\n\u2022 Employer Paid Health Insurance\n\u2022 Dental & Vision Insurance\n\u2022 401(K) Employer Match\n\u2022 Pet Insurance\n\u2022 LTD\n\u2022 Unlimited PTO (with minimums!)\n\u2022 One-week paid PTO (prestart date)\n\u2022 100% Employer Matched Donations\n\u2022 Life Insurance\n\nRemote: As of March 2020, our formerly Austin-based team has been working fully remotely. We have transitioned to a Remote First company forever. This role may be filled by any U.S.-based candidate.\n\nCompensation: This is a salaried exempt role with a base salary of $116,000 with an additional $10,000 in bonus potential annually.\n\nCareerPlug believes in equitable and transparent compensation practices. All our employees have access to what every role pays at the company. We post compensation on all our job postings. In order to ensure equitability and fairness for candidates and current employees, we always lead at our best and don\u2019t negotiate offers.\n\nCareerPlug is an affirmative action and equal opportunity employer. All qualified applicants will receive consideration for employment without regard to race, color, religion, sex, disability, age, sexual orientation, gender identity, national origin, veteran status, or genetic information. CareerPlug is committed to providing access, equal opportunity, and reasonable accommodation for individuals with disabilities in employment, its services, programs, and activities.\n\nTo request a reasonable accommodation, applicants should communicate a request when contacted for an interview. All requests should be sent to View email address on cplugjobs.careerplug.com.", "job_is_remote": false, "job_posted_at_timestamp": 1709715954, "job_posted_at_datetime_utc": "2024-03-06T09:05:54.000Z", "job_city": null, "job_state": null, "job_country": "US", "job_latitude": 37.09024, "job_longitude": -95.71289, "job_benefits": ["dental_coverage", "paid_time_off", "health_insurance", "retirement_savings"], "job_google_link": "https://www.google.com/search?gl=us&hl=en&rciv=jb&q=senior+manager+of+brand+partnerships&start=20&ibp=htl;jobs#fpstate=tldetail&htivrt=jobs&htiq=senior+manager+of+brand+partnerships&htidocid=KQvAKYHsKEixV2hFAAAAAA%3D%3D", "job_offer_expiration_datetime_utc": "2024-04-13T05:51:29.000Z", "job_offer_expiration_timestamp": 1712987489, "job_required_experience": {"no_experience_required": false, "required_experience_in_months": 60, "experience_mentioned": true, "experience_preferred": true}, "job_required_skills": null, "job_required_education": {"postgraduate_degree": false, "professional_certification": false, "high_school": false, "associates_degree": false, "bachelors_degree": false, "degree_mentioned": false, "degree_preferred": false, "professional_certification_mentioned": false}, "job_experience_in_place_of_education": false, "job_min_salary": null, "job_max_salary": null, "job_salary_currency": null, "job_salary_period": null, "job_highlights": {"Qualifications": ["Familiarity with the franchise business model and experience with working with brands and or membership organizations", "Familiarity with Human Capital Management, HR, and Applicant Tracking Systems", "Demonstrated success in creating and implementing innovative, result-oriented, full-funnel marketing programs with proven results", "Persuasive and able to relate/empathize with entrepreneurs and small business owners"], "Responsibilities": ["This is an individual contributor role reporting directly to the VP of Marketing who will focus on creating compelling content to attract and engage potential partners, ultimately leading to scheduled demos", "Develop and execute outbound campaigns targeting prospective partners to generate new leads", "Craft compelling, personalized messaging for targeted prospects", "Create content to effectively communicate the value proposition of partnering with CareerPlug", "Collaborate with cross-functional teams to ensure alignment with overall marketing and business objectives", "Design targeted campaigns to reach specific franchisees or members within existing partners for prospecting purposes to gain access to the decision-makers within the brand/organization", "Tailor messaging to address the unique needs and challenges of different partner segments", "Work closely with sales teams to align campaigns with partner-specific goals", "Leverage content calendar for up-to-date content", "Personalized Marketing for Partner Prospects:", "Collaborate with the rest of the marketing team to create or leverage marketing materials to engage and nurture potential partners", "Utilize data-driven insights to tailor content for specific industries, regions, and partner profiles", "Implement strategies to enhance the partner to increase conversion rates of franchisees and association members by working with key contacts within the partner's organization", "Demo Script and Sales Enablement:", "Develop impactful demo scripts and sales material to showcase the key features and benefits of our offerings to potential partners", "Create comprehensive sales enablement materials that empower the sales team to effectively communicate with partners during demos", "Collaborate with product teams to stay updated on new features and ensure accurate representation in sales materials"], "Benefits": ["100% Remote Company!", "Employer Paid Health Insurance", "Dental & Vision Insurance", "401(K) Employer Match", "Pet Insurance", "LTD", "Unlimited PTO (with minimums!)", "One-week paid PTO (prestart date)", "100% Employer Matched Donations", "Life Insurance", "Compensation: This is a salaried exempt role with a base salary of $116,000 with an additional $10,000 in bonus potential annually", "CareerPlug believes in equitable and transparent compensation practices", "All our employees have access to what every role pays at the company"]}, "job_job_title": "Marketing manager", "job_posting_language": "en", "job_onet_soc": "11202100", "job_onet_job_zone": "4"}