{"job_id": "pa2TwSqn4dD_SYa7AAAAAA==", "employer_name": "The Ockers Company", "employer_logo": null, "employer_website": "http://www.ockers.com", "employer_company_type": null, "job_publisher": "Glassdoor", "job_employment_type": "FULLTIME", "job_title": "Senior Sales Executive - Maine/New Hampshire (state residency req'd)", "job_apply_link": "https://www.glassdoor.com/job-listing/senior-sales-executive-maine-new-hampshire-state-residency-req-d-the-ockers-company-JV_KO0,64_KE65,83.htm?jl=1009160076312", "job_apply_is_direct": true, "job_apply_quality_score": 0.674, "apply_options": [{"publisher": "Glassdoor", "apply_link": "https://www.glassdoor.com/job-listing/senior-sales-executive-maine-new-hampshire-state-residency-req-d-the-ockers-company-JV_KO0,64_KE65,83.htm?jl=1009160076312", "is_direct": true}], "job_description": "Senior Sales Executive \u2013 Maine/New Hampshire (state residency required)\n\nAt Ockers, our mission is to continue expanding the array of services we provide to help our national client base to help them keep pace with the latest advances in technology. Ockers proudly serves a diverse customer base that includes educational and government markets, major corporations, municipalities, and small to medium-sized businesses within a wide spectrum of industries.\n\nOckers has been in business for 102 years, with seven different client-based divisions. While our core client base is K through 12 schools, we also provide next generation technology solutions for police, fire, and emergency response groups, cities and towns, and a variety of private and public private businesses. We currently employ over 110 people and are looking to exceed $50M in revenue in 2024.\n\nThe Senior Sales Executive assigned to this region is responsible for driving profitable revenue growth. The right candidate must have remote sales experience, be proficient with reseller programs, promotions, forecasting, pricing, and P&L. The company is seeking someone who has a very strong track record of achieving targets and objectives. An individual who is highly effective and successful in sales lead generation, negotiations, and closing who also has a passion for education technology adoption would be ideal.\n\nResponsibilities\n\n\u00b7 Identify and establish contact with potential customers\n\n\u00b7 Drive profitable revenue growth\n\n\u00b7 Build and maintain a network of sources from which to identify new sales leads\n\n\u00b7 Meet or exceed quarterly jointly agreed revenue and gross margin targets\n\n\u00b7 Develop and execute regional sales initiatives to support growth goals\n\n\u00b7 Ensure customer satisfaction through ongoing communication and relationship management; resolves any issues that may arise post-sale\n\n\u00b7 Schedule and perform product demonstrations with prospective customers\n\n\u00b7 Routinely communicate with customers and leads to identify and understand their product or service needs; identifies and suggests products and services to meet those requirements\n\n\u00b7 Monthly/Quarterly progress reporting to management\n\n\u00b7 Follow industry trends to identify new opportunities for potential sales\n\n\u00b7 Must be willing to make cold calls, search for sales leads, and identify possible clients\n\n\u00b7 Maintain communication with existing and previous customers, alerting them of new products, services, and enhancements that may be of interest\n\n\u00b7 Deliver on-site and remote training to clients\n\n\u00b7 Attend industry trade shows to identify potential sales leads and make meaningful contact with existing customers\n\n\u00b7 Actively participate in regional industry associations and related activities\n\no Planning for, managing and staffing all sales promotion activities, including trade shows, seminars, training classes, and customer-driven activities. Attendance and participation in local, regional, and national meetings.\n\n\u00b7 Recommend marketing strategies to target a specific region or demographic\n\n\u00b7 Assist clients with technical support issues until a resolution is achieved\n\n\u00b7 Create and deliver detailed reports of sales activities including calls, orders, sales, lost business, and any customer or vendor relationship problems\n\n\u00b7 Provide territory sales forecasts and pipelines\n\n\u00b7 Willing to travel to client locations and also travel to internal quarterly sales meetings\n\n\u00b7 SELL!\n\n\u00b7 Perform other duties as requested\n\nRequired Skills and Experience\n\n\u00b7 Must reside within a 15-minute commute of either I-91 or I-95 in Maine or New Hampshire\n\n\u00b7 BS/BA degree preferred, preferably in Business Administration, Management, Sales, or other related field\n\n\u00b7 Aggressive, determined, and successful salesperson who will call on, and pursue, new prospects\n\n\u00b7 5+ years of experience in channel management, account management, sales management key account management or similar experience\n\n\u00b7 Must be a self-starter\n\n\u00b7 Required to be a Maine or New Hampshire resident\n\n\u00b7 Ability to routinely travel throughout the states of Maine and New Hampshire\n\n\u00b7 Proficient with Microsoft Office Suite and related software\n\n\u00b7 Excellent oral and written communication skills\n\n\u00b7 Able to excel without daily oversight and supervision\n\n\u00b7 Phenomenal listening, negotiation, and presentation abilities\n\n\u00b7 Attend quarterly Sales meetings at corporate headquarters in Middleboro, MA\n\n\u00b7 Strong analytical and problem-solving abilities\n\n\u00b7 Outstanding organizational skills and superior attention to detail\n\n\u00b7 Persistent, tenacious, and tremendous negotiating qualifications\n\n\u00b7 Technically savvy\n\n\u00b7 Fantastic interpersonal and customer service capabilities\n\nOckers is committed to creating a diverse environment and is proud to be an equal opportunity employer. All qualified applicants will receive consideration for employment without regard to race, color, religion, gender, gender identity or expression, sexual orientation, national origin, genetics, pregnancy, disability, age, veteran status, or any other characteristics. Ockers is also committed to compliance with all fair employment practices regarding citizenship and immigration status.\n\nJob Type: Full-time\n\nPay: $75,000.00 - $90,000.00 per year\n\nBenefits:\n\u2022 401(k)\n\u2022 401(k) matching\n\u2022 Dental insurance\n\u2022 Employee assistance program\n\u2022 Flexible spending account\n\u2022 Health insurance\n\u2022 Health savings account\n\u2022 Paid time off\n\u2022 Travel reimbursement\n\u2022 Vision insurance\n\u2022 Work from home\n\nCompensation package:\n\u2022 Bonus opportunities\n\u2022 Commission pay\n\u2022 Quarterly bonus\n\nSchedule:\n\u2022 Monday to Friday\n\u2022 Weekends as needed\n\nTravel requirement:\n\u2022 Travel\n\u2022 Up to 75% travel\n\nPeople with a criminal record are encouraged to apply\n\nApplication Question(s):\n\u2022 Do you live in New Hampshire ?\n\u2022 Do you live in Maine\n\nEducation:\n\u2022 Bachelor's (Preferred)\n\nExperience:\n\u2022 Channel management: 5 years (Required)\n\u2022 Account management: 5 years (Required)\n\u2022 Cold calling: 3 years (Required)\n\u2022 Product demos: 3 years (Required)\n\u2022 Sales management: 5 years (Required)\n\u2022 Customer relationship management: 4 years (Required)\n\u2022 IT Sales: 3 years (Required)\n\nAbility to Commute:\n\u2022 New Hampshire (Required)\n\nWillingness to travel:\n\u2022 75% (Required)\n\nWork Location: On the road", "job_is_remote": false, "job_posted_at_timestamp": 1709596800, "job_posted_at_datetime_utc": "2024-03-05T00:00:00.000Z", "job_city": null, "job_state": null, "job_country": "US", "job_latitude": 37.09024, "job_longitude": -95.71289, "job_benefits": ["retirement_savings", "health_insurance", "dental_coverage", "paid_time_off"], "job_google_link": "https://www.google.com/search?gl=us&hl=en&rciv=jb&q=senior+sales+manager&start=60&ibp=htl;jobs#fpstate=tldetail&htivrt=jobs&htiq=senior+sales+manager&htidocid=pa2TwSqn4dD_SYa7AAAAAA%3D%3D", "job_offer_expiration_datetime_utc": "2024-07-08T00:00:00.000Z", "job_offer_expiration_timestamp": 1720396800, "job_required_experience": {"no_experience_required": false, "required_experience_in_months": 60, "experience_mentioned": true, "experience_preferred": false}, "job_required_skills": null, "job_required_education": {"postgraduate_degree": false, "professional_certification": false, "high_school": false, "associates_degree": false, "bachelors_degree": false, "degree_mentioned": true, "degree_preferred": true, "professional_certification_mentioned": false}, "job_experience_in_place_of_education": false, "job_min_salary": 75000, "job_max_salary": 90000, "job_salary_currency": "USD", "job_salary_period": "YEAR", "job_highlights": {"Qualifications": ["The right candidate must have remote sales experience, be proficient with reseller programs, promotions, forecasting, pricing, and P&L", "The company is seeking someone who has a very strong track record of achieving targets and objectives", "An individual who is highly effective and successful in sales lead generation, negotiations, and closing who also has a passion for education technology adoption would be ideal", "Must reside within a 15-minute commute of either I-91 or I-95 in Maine or New Hampshire", "Aggressive, determined, and successful salesperson who will call on, and pursue, new prospects", "5+ years of experience in channel management, account management, sales management key account management or similar experience", "Must be a self-starter", "Ability to routinely travel throughout the states of Maine and New Hampshire", "Proficient with Microsoft Office Suite and related software", "Excellent oral and written communication skills", "Able to excel without daily oversight and supervision", "Phenomenal listening, negotiation, and presentation abilities", "Attend quarterly Sales meetings at corporate headquarters in Middleboro, MA", "Strong analytical and problem-solving abilities", "Outstanding organizational skills and superior attention to detail", "Persistent, tenacious, and tremendous negotiating qualifications", "Technically savvy", "Fantastic interpersonal and customer service capabilities", "Up to 75% travel", "People with a criminal record are encouraged to apply", "Cold calling: 3 years (Required)", "Product demos: 3 years (Required)", "Customer relationship management: 4 years (Required)", "IT Sales: 3 years (Required)", "New Hampshire (Required)", "75% (Required)"], "Responsibilities": ["Drive profitable revenue growth", "Build and maintain a network of sources from which to identify new sales leads", "Meet or exceed quarterly jointly agreed revenue and gross margin targets", "Develop and execute regional sales initiatives to support growth goals", "Ensure customer satisfaction through ongoing communication and relationship management; resolves any issues that may arise post-sale", "Schedule and perform product demonstrations with prospective customers", "Routinely communicate with customers and leads to identify and understand their product or service needs; identifies and suggests products and services to meet those requirements", "Monthly/Quarterly progress reporting to management", "Follow industry trends to identify new opportunities for potential sales", "Must be willing to make cold calls, search for sales leads, and identify possible clients", "Maintain communication with existing and previous customers, alerting them of new products, services, and enhancements that may be of interest", "Deliver on-site and remote training to clients", "Attend industry trade shows to identify potential sales leads and make meaningful contact with existing customers", "Actively participate in regional industry associations and related activities", "Planning for, managing and staffing all sales promotion activities, including trade shows, seminars, training classes, and customer-driven activities", "Attendance and participation in local, regional, and national meetings", "Recommend marketing strategies to target a specific region or demographic", "Assist clients with technical support issues until a resolution is achieved", "Create and deliver detailed reports of sales activities including calls, orders, sales, lost business, and any customer or vendor relationship problems", "Provide territory sales forecasts and pipelines", "Willing to travel to client locations and also travel to internal quarterly sales meetings", "SELL!", "Perform other duties as requested"], "Benefits": ["Pay: $75,000.00 - $90,000.00 per year", "401(k) matching", "Dental insurance", "Employee assistance program", "Flexible spending account", "Health insurance", "Health savings account", "Paid time off", "Travel reimbursement", "Vision insurance", "Work from home", "Compensation package:", "Bonus opportunities", "Commission pay", "Quarterly bonus", "Monday to Friday"]}, "job_job_title": "Sales executive", "job_posting_language": "en", "job_onet_soc": "39904100", "job_onet_job_zone": "3"}