{"job_id": "c0W0iTYVSQ7ZfQiUAAAAAA==", "employer_name": "Northpoint Recovery", "employer_logo": null, "employer_website": null, "employer_company_type": null, "job_publisher": "CareerBuilder", "job_employment_type": "FULLTIME", "job_title": "Corporate Director, Business Development (Adult Services)", "job_apply_link": "https://www.careerbuilder.com/job/J3S70J67CCP89YB29XC", "job_apply_is_direct": false, "job_apply_quality_score": 0.5486, "apply_options": [{"publisher": "CareerBuilder", "apply_link": "https://www.careerbuilder.com/job/J3S70J67CCP89YB29XC", "is_direct": false}, {"publisher": "BeBee", "apply_link": "https://us.bebee.com/job/20240311-13159537f7bee9f7807db2961bc6d303", "is_direct": false}], "job_description": "Career Opportunities with Northpoint Recovery Holdings, LLC\n\nCareers at Northpoint Recovery Holdings, LLC\n\nCorporate Director, Business Development (Adult Services)\n\nJob Title: Corporate Director, Business Development (Adult Services)\n\nReports To: Vice President of Business Development\n\nNorthpoint Recovery Holdings, LLC , established in 2009, is a growing, behavioral healthcare treatment platform treating adults with substance use disorder and co-occurring conditions under the Northpoint Recovery brand and adolescents with mental healthcare conditions under the Imagine by Northpoint brand. The Company serves patients with commercial health insurance and is an in-network model. Northpoint has grown from two facilities to fifteen today entirely on a de novo basis with plans to expand rapidly in both existing and new markets. Organizational values include humility, heart, inspiration and conviction. Our commitment to excellence means doing good for others and engaging in innovative empirical based treatment. In short, our mission is to help people get their lives back and show them respect and empathy in the process.\n\nPOSITION SUMMARY: T he Corporate Director, Business Development (Adult Services) is both a key member of the Northpoint team and ambassador to the community. This person will lead the business development team for the adult service line. This person meets extensively with clinical and healthcare professionals in the communities we operate in to form new relationships and maintain existing ones, so that Northpoint is part of an extended network of resources and support. This role is also a vital contributor to onsite events and culture. To excel in these dual missions, the ideal incumbent must be able to find multiple balances: between productivity and relationships, confidence and vulnerability, connection and autonomy, passion and compassion. This person is driven, creative and poised and communicates with great clarity and empathy. This person knows their audience and tends to impress \u2013 hit targets and touch hearts. As an ambassador of our company, becoming a trusted face to our constituents while also adhering to our Core Values is paramount.\n\nESSENTIAL RESPONSIBILITIES AND DUTIES INCLUDE BUT ARE NOT LIMITED TO THE FOLLOWING:\n\u2022 Develop and execute a business plan that is designed to meet and exceed financial, market, and operational goals; execute to established KPIs at all adult locations\n\u2022 Lead business development efforts nationally and in the communities, we operate in\n\u2022 Attend relevant local and national conferences\n\u2022 Provide go to market strategy for referral generation at each adult location\n\u2022 Identify strategy for growth and execute plans to achieve growth goals\n\u2022 Lead business development training for adult focused Business Development Representatives\n\u2022 Work closely, cooperatively, and amicably with a multidisciplinary treatment team and maintain professional boundaries with all staff members\n\u2022 Promote programs to meet Northpoint wide admissions goals. Coach the business development team ativities to include cold calling, prospecting, public speaking, presenting services to potential referral sources, exhibiting at conferences, developing and following call cycle, and planning and executing events\n\u2022 Service existing referral sources, and establish new referral sources by planning and organizing daily work schedule to increase awareness and drive revenue in market\n\u2022 Adjust content of presentations by studying the type of referral source\n\u2022 Effective territory planning to ensure retention and penetration of existing referral sources, cultivation of new community partners, and the conversion of high-quality revenue\n\u2022 Work cross functionally with team members including other Business Development employees, Admissions, Billing, Marketing, and other internal support functions to ensure successful client/patient outcome\n\u2022 Utilize CRM (Salesforce/Kipu) and other methods for planning, forecasting and business intelligence in order to support strategic and tactical decisions\n\u2022 Keep leadership informed of territory progress on a regular basis\n\u2022 Provide high quality resource support to staff and treatment team\n\u2022 Identify market research and adjust marketing strategy to meet changing market and competitive conditions\n\u2022 In partnership with the Admissions Team, provide leadership planning, development, and continual process improvement of leads and referral sources\n\u2022 Participate in program design initiatives, ensuring that each is supported by a base of current information on evidence-based practices and a thorough understanding of needs\n\u2022 Hire the best people and ensure their ongoing development to maintain a robust referral network, and to provide a world class outreach program\n\u2022 Maintain confidentiality in accordance with established policies and procedures and standards of care\n\u2022 Adhere to all Company policies and procedures\n\u2022 Perform other job-related duties as assigned\n\nQUALIFICATIONS/REQUIREMENTS FOR POSITION:\n\u2022 Minimum of three (3) years of business development experience within the behavioral health field with a proven track record of growing programs and census\n\u2022 Minimum of two (2) years of experience working in a substance abuse treatment facility\n\u2022 Experience working with adolescent and young adult populations is highly desirable\n\u2022 A four (4) year degree in science, business, or related discipline preferred\n\u2022 Valid driver\u2019s license and a safe driving record\n\u2022 Self-motivated, organized and a passion to help are a must. A hunter with a proven history of top ranking in past positions with a highly energetic and focused sales personality\n\u2022 Demonstrated ability to develop both internal and external long-term business relationships\n\u2022 Proven skills in working independently on several projects and presentations simultaneously\n\u2022 Prior experience using Salesforce.com or other CRM system\n\nPREFERRED KNOWLEDGE AND SKILLS:\n\u2022 Excellent critical thinking skills and organizational abilities\n\u2022 Excellent communication skills; ability to communicate clearly and concisely, verbally and in writing\n\u2022 Quickly and effectively identify and resolve problematic situations\n\u2022 Comfortable analyzing information and dealing with complexity\n\u2022 Attention to detail and accuracy\n\u2022 Able to handle confidential material in a reliable manner\n\u2022 Ability to interact and communicate with individuals at all levels of organization\n\u2022 Ability to perform several tasks concurrently with ease and professionalism\n\u2022 Ability to effectively prioritize workload in a fast-paced environment\n\u2022 Proficiency with Microsoft Office Suite\n\nREQUIRED CERTIFICATES/LICENSES/REGISTRATIONS:\n\u2022 Must be at least twenty-one (21) years of age\n\u2022 Must have a valid driver\u2019s license and safe driving record\n\nSUPERVISORY RESPONSIBILITIES:\n\u2022 Supervise adult service line focused Business Development employees; provide guidance regarding work priorities and oversight of adult service line business development projects companywide\n\nPHYSICAL DEMANDS:\n\nThe physical demands described here are representative of those that must be met by an employee to successfully perform the essential functions of this job. Reasonable accommodations may be made to enable individuals with disabilities to perform the essential functions.\n\u2022 Job performed at a desk in front of a computer\n\u2022 Requires heavy use of mouse and keyboard\n\u2022 Indoor office environment\n\u2022 Though this position is not permanently located in a treatment facility setting, exposure to emotionally impaired patients is possible, and may be frequent. Stress ranges from low to high, depending on the situation\n\u2022 Frequent travel required, inclusive of overnight stays and weekends\n\u2022 Ability to work out of a home office. This will include maintaining an inventory and storage of literature and merchandise\n\nCONDITIONS OF EMPLOYMENT:\n\u2022 Completion of a tuberculin screening during first week of employment\n\u2022 Completion of a pre-employment drug screening, post-accident and upon reasonable suspicion of use\n\u2022 Completion of orientation and required paperwork prior to reporting to work\n\u2022 Demonstrated computer literacy\n\u2022 Attendance at all mandatory staff development and training\n\u2022 Completion of background and professional reference checks\n\u2022 Completion of a Motor Vehicle Record check\n\nJob Type: Full-Time\n\nCompensation:\n\u2022 $105,000 - 140,000 annual salary\n\nProfessional Development:\n\u2022 Northpoint provides reimbursement for clinical licensure fees\n\u2022 Northpoint provides clinical supervision for licensure at no cost to the employee\n\u2022 Professional development, and the opportunity for continuing education credits to maintain licensure is provided at no cost to the employee\n\nFull-Time Benefits Include:\n\u2022 85% Employer Paid Medical premium for employee level coverage \u2013 spouse and dependent premiums are subsidized at 50%\n\u2022 100% Employer Paid Basic Life Insurance equal to 1x annual salary, up to $100,000\n\u2022 100% Employer Paid Employee Assistance Program\n\u2022 Voluntary Dental, Vision, Short-Term Disability, and Supplemental Life & AD&D Insurance\n\u2022 Pre-tax Savings Accounts for all IRS-allowable medical and dependent care expenses\n\u2022 Generous Paid Time Off plan and 10 paid holidays annually\n\u2022 Free counseling services and resources for emotional, physical and financial wellbeing\n\u2022 Consumer discounts through LifeMart\n\u2022 Free parking!\n\nThis job description is not intended, and should not be construed, to be exhaustive lists of all responsibilities, skills, efforts or working conditions associated with this job. It is meant to be an accurate reflection of the principal job elements essential for making fair pay decisions about jobs.\n\nEmployees with potential access to protected health information must comply with all procedures and guidelines governed by HIPAA.\n\nNorthpoint is an Equal Opportunity Employer. Northpoint is an at-will employer. Employment may be terminated at any time by employee, or employer with or without notice.\n\n#J-18808-Ljbffr", "job_is_remote": false, "job_posted_at_timestamp": 1709164800, "job_posted_at_datetime_utc": "2024-02-29T00:00:00.000Z", "job_city": "Iowa", "job_state": "LA", "job_country": "US", "job_latitude": 30.23683, "job_longitude": -93.01364, "job_benefits": ["dental_coverage", "health_insurance", "paid_time_off"], "job_google_link": "https://www.google.com/search?gl=us&hl=en&rciv=jb&q=director+of+business+development&start=50&ibp=htl;jobs#fpstate=tldetail&htivrt=jobs&htiq=director+of+business+development&htidocid=c0W0iTYVSQ7ZfQiUAAAAAA%3D%3D", "job_offer_expiration_datetime_utc": "2024-03-28T00:00:00.000Z", "job_offer_expiration_timestamp": 1711584000, "job_required_experience": {"no_experience_required": false, "required_experience_in_months": 36, "experience_mentioned": true, "experience_preferred": false}, "job_required_skills": null, "job_required_education": {"postgraduate_degree": false, "professional_certification": false, "high_school": false, "associates_degree": false, "bachelors_degree": false, "degree_mentioned": false, "degree_preferred": true, "professional_certification_mentioned": false}, "job_experience_in_place_of_education": false, "job_min_salary": null, "job_max_salary": null, "job_salary_currency": null, "job_salary_period": null, "job_highlights": {"Qualifications": ["To excel in these dual missions, the ideal incumbent must be able to find multiple balances: between productivity and relationships, confidence and vulnerability, connection and autonomy, passion and compassion", "This person is driven, creative and poised and communicates with great clarity and empathy", "This person knows their audience and tends to impress \u2013 hit targets and touch hearts", "Minimum of three (3) years of business development experience within the behavioral health field with a proven track record of growing programs and census", "Minimum of two (2) years of experience working in a substance abuse treatment facility", "Self-motivated, organized and a passion to help are a must", "A hunter with a proven history of top ranking in past positions with a highly energetic and focused sales personality", "Demonstrated ability to develop both internal and external long-term business relationships", "Proven skills in working independently on several projects and presentations simultaneously", "Prior experience using Salesforce.com or other CRM system", "Must be at least twenty-one (21) years of age", "Must have a valid driver\u2019s license and safe driving record", "Job performed at a desk in front of a computer", "Requires heavy use of mouse and keyboard", "Ability to work out of a home office", "Completion of a pre-employment drug screening, post-accident and upon reasonable suspicion of use", "Completion of orientation and required paperwork prior to reporting to work", "Demonstrated computer literacy", "Attendance at all mandatory staff development and training", "Completion of a Motor Vehicle Record check"], "Responsibilities": ["This person will lead the business development team for the adult service line", "Develop and execute a business plan that is designed to meet and exceed financial, market, and operational goals; execute to established KPIs at all adult locations", "Lead business development efforts nationally and in the communities, we operate in", "Attend relevant local and national conferences", "Provide go to market strategy for referral generation at each adult location", "Identify strategy for growth and execute plans to achieve growth goals", "Lead business development training for adult focused Business Development Representatives", "Work closely, cooperatively, and amicably with a multidisciplinary treatment team and maintain professional boundaries with all staff members", "Promote programs to meet Northpoint wide admissions goals", "Coach the business development team ativities to include cold calling, prospecting, public speaking, presenting services to potential referral sources, exhibiting at conferences, developing and following call cycle, and planning and executing events", "Service existing referral sources, and establish new referral sources by planning and organizing daily work schedule to increase awareness and drive revenue in market", "Adjust content of presentations by studying the type of referral source", "Effective territory planning to ensure retention and penetration of existing referral sources, cultivation of new community partners, and the conversion of high-quality revenue", "Work cross functionally with team members including other Business Development employees, Admissions, Billing, Marketing, and other internal support functions to ensure successful client/patient outcome", "Utilize CRM (Salesforce/Kipu) and other methods for planning, forecasting and business intelligence in order to support strategic and tactical decisions", "Keep leadership informed of territory progress on a regular basis", "Provide high quality resource support to staff and treatment team", "Identify market research and adjust marketing strategy to meet changing market and competitive conditions", "In partnership with the Admissions Team, provide leadership planning, development, and continual process improvement of leads and referral sources", "Participate in program design initiatives, ensuring that each is supported by a base of current information on evidence-based practices and a thorough understanding of needs", "Hire the best people and ensure their ongoing development to maintain a robust referral network, and to provide a world class outreach program", "Maintain confidentiality in accordance with established policies and procedures and standards of care", "Adhere to all Company policies and procedures", "Perform other job-related duties as assigned", "Supervise adult service line focused Business Development employees; provide guidance regarding work priorities and oversight of adult service line business development projects companywide"], "Benefits": ["$105,000 - 140,000 annual salary", "Northpoint provides reimbursement for clinical licensure fees", "Northpoint provides clinical supervision for licensure at no cost to the employee", "Professional development, and the opportunity for continuing education credits to maintain licensure is provided at no cost to the employee", "85% Employer Paid Medical premium for employee level coverage \u2013 spouse and dependent premiums are subsidized at 50%", "100% Employer Paid Basic Life Insurance equal to 1x annual salary, up to $100,000", "100% Employer Paid Employee Assistance Program", "Voluntary Dental, Vision, Short-Term Disability, and Supplemental Life & AD&D Insurance", "Pre-tax Savings Accounts for all IRS-allowable medical and dependent care expenses", "Generous Paid Time Off plan and 10 paid holidays annually", "Free counseling services and resources for emotional, physical and financial wellbeing", "Consumer discounts through LifeMart", "Free parking!"]}, "job_job_title": "Director", "job_posting_language": "en", "job_onet_soc": "11202100", "job_onet_job_zone": "4"}