{"job_id": "RAuuNG3rVW2FDyUiAAAAAA==", "employer_name": "World Wide Technology", "employer_logo": "https://dn9tckvz2rpxv.cloudfront.net/wwt/img/logo.svg", "employer_website": "http://www2.wwt.com", "employer_company_type": "Computer Services", "job_publisher": "Dice.com", "job_employment_type": "FULLTIME", "job_title": "Software Engineer - Machine Learning", "job_apply_link": "https://www.dice.com/job-detail/a02f79d6-01d6-47d4-ae17-6299f11100f6", "job_apply_is_direct": false, "job_apply_quality_score": 0.7098, "apply_options": [{"publisher": "Dice.com", "apply_link": "https://www.dice.com/job-detail/a02f79d6-01d6-47d4-ae17-6299f11100f6", "is_direct": false}, {"publisher": "Talentify", "apply_link": "https://www.talentify.io/job/software-engineer-machine-learning---world-wide-technology-5001028330406", "is_direct": false}], "job_description": "Machine Learning Engineer\n\nWhy WWT?\n\nAt World Wide Technology, we work together to make a new world happen. Our important work benefits our clients and partners as much as it does our people and communities across the globe. WWT is dedicated to achieving its mission of creating a profitable growth company that is also a Great Place to Work for All. We achieve this through our world-class culture, generous benefits and by delivering cutting-edge technology solutions for our clients.\n\nWWT was founded in 1990 in St. Louis, Missouri. We employ more than 10,000 people globally and closed nearly $20 billion in revenue in 2023. We have an inclusive culture and believe our core values are the key to company and employee success. WWT is proud to have been included on the FORTUNE \"100 Best Places to Work For \" list 12 years in a row!\n\nWant to work with highly motivated individuals on high-performance teams? Join WWT today!\n\nWhat is the Solutions Consulting & Engineering (SC&E) Team and why join?\n\nSolutions Consulting & Engineering is an organization that is Customer Focused and Solutions Led. We deliver end-to-end (E2E) and emerging solutions to drive customer satisfaction, increase profitability and growth. Our success is enabled by our world-class management consulting, delivery excellence and engineering brilliance. We embody the OneWWT mindset by bringing the right talent at the right time from anywhere within WWT to solve our customer's problems. Our goal is to bring together business acumen with full-stack technical know-how to develop innovative solutions for our clients' most complex challenges.\n\nRESPONSIBILITIES:\n\u2022 Develop, productionize, and deploy scalable, resilient software solutions for operationalizing AI & ML\n\u2022 Adhere to software architecture and software design best practices to write scalable, maintainable, well-designed code.\n\u2022 Full ML pipelines. In collaboration with Data Engineering design and build feature engineering pipelines for extraction, transformation, and loading of data from a variety of data sources for ML models.\n\u2022 Stay current on new developments in ML frameworks, data structures, data modelling, software architecture and libraries available for solution development.\n\u2022 Coach data scientists and data engineers on software development best practices\n\nAgile Project Work\n\u2022 Work in cross-functional agile teams of highly skilled software/machine learning engineers, data scientists, DevOps engineers, designers, product managers, technical delivery teams, and others to continuously innovate AI and MLOps solutions.\n\u2022 Act as a positive champion for broader organization to develop stronger understanding of software design patterns that deliver scalable, maintainable, well-designed analytics solutions.\n\u2022 Acts as an expert on complex technical topics that require cross-functional consultation.\n\u2022 Perform other duties as required.\n\nQUALIFICATIONS:\n\u2022 Experience in object-oriented programming and software architecture\n\u2022 Experience applying continuous delivery best practices, including CI/CD, Version Control, Trunk Based Development, Release Management, and Test-Driven Development using Python and SQL\n\u2022 Knowledge of Machine Learning lifecycle (wrangling data, model selection, model training, modeling validation and deployment at scale) and experience working with data scientists\n\u2022 Familiar with at least one major cloud solutions, preferably Azure\n\u2022 Familiar with Snowflake or similar cloud data warehousing solutions\n\u2022 Experience with deep learning platforms (eg: Databricks, Nvidia DGX) and frameworks (e.g.: TensorFlow, Keras, Theano, PyTorch, Caffe, etc.)\n\u2022 Experience with Agile and DevOps software development principles/methodologies and working on teams focused on delivering business value.\n\nPreferred:\n\u2022 Experience with Edge Analytics, embedded systems, or computer vision\n\u2022 Experience working in Data Architecture, engineering and ETL teams, managing implementation of projects that utilize big data, advanced analytics, and machine learning technologies.\n\u2022 Experience with popular MLOps tools (e.g., Kubeflow, mlflow, AzureML)\n\u2022 Experience influencing and building mindshare convincingly with any audience. Confident and experienced in public speaking to large audiences.\n\u2022 Demonstrated experience in teaching and/or mentoring professionals.\n\nWant to learn more about SC&E Check us out on our platform:\n\nThe well-being of WWT employees is essential. So, when it comes to our benefits package, WWT has one of the best. We offer the following benefits to all full-time employees:\n\u2022 Health and Wellbeing: Health, Dental, and Vision Care, Onsite Health Centers, Employee Assistance Program, Wellness Program\n\u2022 Financial Benefits: Competitive Pay, Profit Sharing, 401k Plan with Company Matching, Life and Disability Insurance, Tuition Reimbursement\n\u2022 Paid Time Off: PTO & Holidays, Parental Leave, Sick Leave, Military Leave, Bereavement\n\u2022 Additional Perks: Nursing Mothers Benefits, Voluntary Legal, Pet Insurance, Employee Discount Program\n\nEqual Opportunity Employer Minorities/Women/Veterans/Individuals with Disabilities\n\n#LI-WWTACRIDER", "job_is_remote": true, "job_posted_at_timestamp": 1710460971, "job_posted_at_datetime_utc": "2024-03-15T00:02:51.000Z", "job_city": "Remote", "job_state": "OR", "job_country": "US", "job_latitude": 43.005947, "job_longitude": -123.89259, "job_benefits": ["paid_time_off", "retirement_savings", "health_insurance", "dental_coverage"], "job_google_link": "https://www.google.com/search?gl=us&hl=en&rciv=jb&q=machine+learning&start=80&ibp=htl;jobs#fpstate=tldetail&htivrt=jobs&htiq=machine+learning&htidocid=RAuuNG3rVW2FDyUiAAAAAA%3D%3D", "job_offer_expiration_datetime_utc": "2024-04-17T12:02:46.000Z", "job_offer_expiration_timestamp": 1713355366, "job_required_experience": {"no_experience_required": false, "required_experience_in_months": null, "experience_mentioned": true, "experience_preferred": false}, "job_required_skills": ["Object-Oriented Programming", "Test-driven development", "Machine Learning (ML)", "Collaboration", "Customer satisfaction", "Management consulting", "Business acumen", "Software architecture", "Software design", "Data engineering", "Data structure", "Data modeling", "Software development", "Continuous delivery", "Version control", "Release management", "Cloud computing", "Data warehouse", "Deep learning", "Embedded systems", "Computer vision", "Data architecture", "Big data", "Advanced analytics", "Public speaking", "Artificial intelligence", "Design", "Extraction", "Transformation", "Data", "Agile", "DevOps", "Machine Learning Operations (ML Ops)", "ACT", "Analytics", "Continuous integration", "Python", "SQL", "Training", "Modeling", "Software deployment", "Microsoft Azure", "Snow flake schema", "Databricks", "TensorFlow", "Keras", "Theano", "PyTorch", "Caffe", "Extract", "transform", "load", "Management", "Teaching", "Mentorship", "Finance", "Insurance", "Military", "Nursing", "Legal"], "job_required_education": {"postgraduate_degree": false, "professional_certification": false, "high_school": false, "associates_degree": false, "bachelors_degree": false, "degree_mentioned": false, "degree_preferred": false, "professional_certification_mentioned": false}, "job_experience_in_place_of_education": false, "job_min_salary": null, "job_max_salary": null, "job_salary_currency": null, "job_salary_period": null, "job_highlights": {"Qualifications": ["Experience in object-oriented programming and software architecture", "Experience applying continuous delivery best practices, including CI/CD, Version Control, Trunk Based Development, Release Management, and Test-Driven Development using Python and SQL", "Knowledge of Machine Learning lifecycle (wrangling data, model selection, model training, modeling validation and deployment at scale) and experience working with data scientists", "Familiar with at least one major cloud solutions, preferably Azure", "Familiar with Snowflake or similar cloud data warehousing solutions", "Experience with deep learning platforms (eg: Databricks, Nvidia DGX) and frameworks (e.g.: TensorFlow, Keras, Theano, PyTorch, Caffe, etc.)", "Experience with Agile and DevOps software development principles/methodologies and working on teams focused on delivering business value", "Confident and experienced in public speaking to large audiences", "Demonstrated experience in teaching and/or mentoring professionals"], "Responsibilities": ["Develop, productionize, and deploy scalable, resilient software solutions for operationalizing AI & ML", "Adhere to software architecture and software design best practices to write scalable, maintainable, well-designed code", "Full ML pipelines", "In collaboration with Data Engineering design and build feature engineering pipelines for extraction, transformation, and loading of data from a variety of data sources for ML models", "Stay current on new developments in ML frameworks, data structures, data modelling, software architecture and libraries available for solution development", "Coach data scientists and data engineers on software development best practices", "Work in cross-functional agile teams of highly skilled software/machine learning engineers, data scientists, DevOps engineers, designers, product managers, technical delivery teams, and others to continuously innovate AI and MLOps solutions", "Act as a positive champion for broader organization to develop stronger understanding of software design patterns that deliver scalable, maintainable, well-designed analytics solutions", "Acts as an expert on complex technical topics that require cross-functional consultation", "Perform other duties as required"], "Benefits": ["Health and Wellbeing: Health, Dental, and Vision Care, Onsite Health Centers, Employee Assistance Program, Wellness Program", "Financial Benefits: Competitive Pay, Profit Sharing, 401k Plan with Company Matching, Life and Disability Insurance, Tuition Reimbursement", "Paid Time Off: PTO & Holidays, Parental Leave, Sick Leave, Military Leave, Bereavement", "Additional Perks: Nursing Mothers Benefits, Voluntary Legal, Pet Insurance, Employee Discount Program"]}, "job_job_title": "Software engineer", "job_posting_language": "en", "job_onet_soc": "15111100", "job_onet_job_zone": "5", "job_naics_code": "541511", "job_naics_name": "Custom Computer Programming Services"}