{"job_id": "D9dPmMyP7paDWFyeAAAAAA==", "employer_name": "Driving Academy", "employer_logo": null, "employer_website": null, "employer_company_type": null, "job_publisher": "ZipRecruiter", "job_employment_type": "FULLTIME", "job_title": "Franchise Training Manager", "job_apply_link": "https://www.ziprecruiter.com/c/Driving-Academy/Job/Franchise-Training-Manager/-in-Linden,AL?jid=6fe82cbcb7f38456", "job_apply_is_direct": true, "job_apply_quality_score": 0.7186, "apply_options": [{"publisher": "ZipRecruiter", "apply_link": "https://www.ziprecruiter.com/c/Driving-Academy/Job/Franchise-Training-Manager/-in-Linden,AL?jid=6fe82cbcb7f38456", "is_direct": true}], "job_description": "POSITION SUMMARY\n\nThe Regional Sales Trainer is primarily responsible for overseeing the training of sales teams for franchise locations. They will also monitor the overall performance of franchise locations for their designated region, and offer guidance to franchises to maximize performance. Lastly, they ensure compliance with Driving Academy policy and procedure in franchise locations.\n\nABOUT OUR COMPANY\n\nWe are the Driving Academy, we provide affordable, state-approved classroom and behind-the-wheel lessons for aspiring truck (aka commercial driver's license [CDL]) drivers, and we are growing by the day. Our mission is to help our students get on the Road to Freedom by earning their CDL! We are Accountable and Results Oriented in our pursuit to see every team member reach their personal, professional, and financial goals through the work we do together. Our core value of having Integrity is the backbone of our business and guides our hiring process.\n\nPERFORMANCE OBJECTIVES\n\u2022 Oversees the initial training of new franchise locations.\n\u2022 Conducts and leads in sales training of new Driving Academy locations.\n\u2022 Provides individual coaching to franchise management to ensure leadership success.\n\u2022 Coordinates with franchise leadership to ensure compliance with Driving Academy policy and practices.\n\u2022 Establishes and tracks Key Performance Indicators (KPI's) as metrics for organizational success.\n\u2022 Assesses franchise location performance via standardized rubric to identify key methods of increasing success.\n\u2022 Coordinates with franchise owners in developing strategies and implementation to address location deficiencies.\n\u2022 Travels between a local base and franchise locations.\n\u2022 Delivers reports to key stakeholders regarding performance of the designated region.\n\u2022 Other related duties as assigned\n\nKEY COMPETENCIES\n\nThe requirements listed below are representative of the knowledge, skill, and/or ability required to be successful in this role, but are not necessarily all inclusive.\n\u2022 Excellent written and oral communication skills.\n\u2022 Ability to work with small and large groups\n\u2022 Strong interpersonal skills to tailor training needs\n\u2022 Knowledge of adult training principle\n\u2022 Excellent analytical, decision-making, and problem-solving skills\n\nEDUCATION AND EXPERIENCE\n\u2022 5 Years in Direct Sales Experience (required)\n\u2022 3 Years in Management or Supervisory experience (required)\n\u2022 3 Years Sales Training Experience (required)\n\u2022 Bachelor's Degree in business or related field (optional)\n\u2022 Proficient in Microsoft Office and Google Suite\n\u2022 Must possess or be able and willing to earn a Commercial Driver's License (CDL)\n\nPHYSICAL REQUIREMENTS\n\u2022 Ability to spend prolonged periods of time standing, speaking, walking, driving, writing, and/or sitting at a desk and working on a computer\n\u2022 Must be able to lift at least 15 pounds at a time\n\u2022 Perform work with OSHA required PPE; Including COVID19 PPE\n\u2022 Reasonable accommodations may be made to enable individuals with disabilities to perform the essential requirements\n\nBENEFITS\n\u2022 Paid Vacation Days\n\u2022 Paid Holidays\n\u2022 Paid Sick Days\n\u2022 Health Insurance Stipend\n\u2022 401K with 4% Matching\n\u2022 Employee Discount\n\u2022 Professional Training & Development Opportunities\n\nCOMMITMENT TO DIVERSITY\n\nAs an equal opportunity employer committed to meeting the needs of a multigenerational and multicultural workforce, Driving Academy recognizes that a diverse staff, reflective of our community, is an integral and welcome part of a successful and ethical business. We hire local talent at all levels regardless of race, color, religion, age, national origin, gender, gender identity, sexual orientation, or disability and actively foster inclusion in all forms both within our company and across interactions with clients, candidates, and partners.\n\nIf this position caught your eye, send us your resume! For best consideration, include the job title and source where you found this position in the subject line of your email to hr@cdldrivingacademy .org. Already a Driving Academy candidate? Please connect directly with your recruiter to discuss this opportunity.", "job_is_remote": false, "job_posted_at_timestamp": 1705139217, "job_posted_at_datetime_utc": "2024-01-13T09:46:57.000Z", "job_city": "Linden", "job_state": "AL", "job_country": "US", "job_latitude": 32.30625, "job_longitude": -87.798065, "job_benefits": ["health_insurance", "retirement_savings", "paid_time_off"], "job_google_link": "https://www.google.com/search?gl=us&hl=en&rciv=jb&q=manager+of+sales+training&start=30&ibp=htl;jobs#fpstate=tldetail&htivrt=jobs&htiq=manager+of+sales+training&htidocid=D9dPmMyP7paDWFyeAAAAAA%3D%3D", "job_offer_expiration_datetime_utc": "2024-04-08T00:00:00.000Z", "job_offer_expiration_timestamp": 1712534400, "job_required_experience": {"no_experience_required": false, "required_experience_in_months": 60, "experience_mentioned": true, "experience_preferred": false}, "job_required_skills": null, "job_required_education": {"postgraduate_degree": false, "professional_certification": false, "high_school": false, "associates_degree": false, "bachelors_degree": false, "degree_mentioned": true, "degree_preferred": true, "professional_certification_mentioned": true}, "job_experience_in_place_of_education": false, "job_min_salary": 55000, "job_max_salary": 75000, "job_salary_currency": "USD", "job_salary_period": "YEAR", "job_highlights": {"Qualifications": ["The requirements listed below are representative of the knowledge, skill, and/or ability required to be successful in this role, but are not necessarily all inclusive", "Excellent written and oral communication skills", "Ability to work with small and large groups", "Strong interpersonal skills to tailor training needs", "Knowledge of adult training principle", "Excellent analytical, decision-making, and problem-solving skills", "5 Years in Direct Sales Experience (required)", "3 Years in Management or Supervisory experience (required)", "3 Years Sales Training Experience (required)", "Bachelor's Degree in business or related field (optional)", "Proficient in Microsoft Office and Google Suite", "Must possess or be able and willing to earn a Commercial Driver's License (CDL)", "Ability to spend prolonged periods of time standing, speaking, walking, driving, writing, and/or sitting at a desk and working on a computer", "Must be able to lift at least 15 pounds at a time", "Perform work with OSHA required PPE; Including COVID19 PPE", "Reasonable accommodations may be made to enable individuals with disabilities to perform the essential requirements"], "Responsibilities": ["The Regional Sales Trainer is primarily responsible for overseeing the training of sales teams for franchise locations", "They will also monitor the overall performance of franchise locations for their designated region, and offer guidance to franchises to maximize performance", "Oversees the initial training of new franchise locations", "Conducts and leads in sales training of new Driving Academy locations", "Provides individual coaching to franchise management to ensure leadership success", "Coordinates with franchise leadership to ensure compliance with Driving Academy policy and practices", "Establishes and tracks Key Performance Indicators (KPI's) as metrics for organizational success", "Assesses franchise location performance via standardized rubric to identify key methods of increasing success", "Coordinates with franchise owners in developing strategies and implementation to address location deficiencies", "Travels between a local base and franchise locations", "Delivers reports to key stakeholders regarding performance of the designated region", "Other related duties as assigned"], "Benefits": ["Paid Vacation Days", "Paid Holidays", "Paid Sick Days", "Health Insurance Stipend", "401K with 4% Matching", "Employee Discount", "Professional Training & Development Opportunities"]}, "job_job_title": "Training manager", "job_posting_language": "en", "job_onet_soc": "11313100", "job_onet_job_zone": "4", "job_occupational_categories": ["11-3131.00: Training and Development Managers"]}