{"job_id": "m7NNFbaOVoLKzmCiAAAAAA==", "employer_name": "Joyce University of Nursing and Health Sciences", "employer_logo": "https://www.joyce.edu/wp-content/uploads/2022/11/joyce-logo-google.jpg", "employer_website": "https://www.joyce.edu", "employer_company_type": "Education", "job_publisher": "Ladders", "job_employment_type": "FULLTIME", "job_title": "SENIOR DIRECTOR OF DATA ANALYTICS", "job_apply_link": "https://www.theladders.com/job/senior-director-of-data-analytics-joyce-university-of-nursing-and-health-sciences-draper-ut_67561058", "job_apply_is_direct": false, "job_apply_quality_score": 0.536, "apply_options": [{"publisher": "Ladders", "apply_link": "https://www.theladders.com/job/senior-director-of-data-analytics-joyce-university-of-nursing-and-health-sciences-draper-ut_67561058", "is_direct": false}], "job_description": "Job Type\n\nFull-time\n\nDescription\n\nWe are currently looking for an experienced and proven Senior Director of Data Analytics. As the Senior Director of Data Analytics, you will lead Joyce University's data strategy, ensuring alignment with institutional goals. Responsible for overseeing data collection, integration, and validation processes, you will uphold data accuracy and compliance. Your role involves driving advanced analytics initiatives, guiding the development of models, algorithms, and dashboards, and translating complex insights into actionable recommendations. Spearheading business intelligence efforts, you will implement and manage analytics tools, collaborate with cross-functional teams, and provide performance analysis reports to senior leadership. Your leadership extends to mentoring data professionals, fostering innovation, and acting as a strategic advisor to influence decision-making processes. Additionally, you will engage with internal and external stakeholders, building strong relationships and staying abreast of emerging trends and technologies in data and analytics. The ideal candidate brings a strong background in data management, 10+ years of proven experience, proficiency in programming languages, and excellent communication skills. This is a hybrid work position on our Draper, UT campus, but fully remote could be considered for the right candidate.\n\nWHAT'S IN IT FOR YOU:\n\u2022 Self-Directed PTO policy\n\u2022 Paid holidays\n\u2022 401k with employer match\n\u2022 Medical, dental, and vision insurance\n\u2022 Fully paid short term disability\n\u2022 Long term disability\n\u2022 Life Insurance\n\u2022 Professional Development\n\u2022 Education assistance\n\nWHAT YOU DO EVERYDAY:\n\nData Strategy and Management:\n\u2022 Develop and execute a comprehensive data strategy aligned with the company's goals and objectives.\n\u2022 Oversee data collection, integration, and validation processes to ensure data accuracy and consistency.\n\u2022 Create institutional data definitions and ensure adherence to definitions through Q/A protocols.\n\u2022 Implement best practices in data governance, compliance, and security to safeguard sensitive information.\n\nAdvanced Analytics and Insights:\n\u2022 Lead the company's data team to develop analytical models, algorithms, and dashboards\n\u2022 Translate complex data insights into understandable and actionable recommendations for key stakeholders.\n\u2022 Utilize statistical techniques and machine learning algorithms to identify trends, patterns, and opportunities within large datasets.\n\nBusiness Intelligence:\n\u2022 Implement and manage business intelligence tools and platforms to enable self-service analytics for various departments.\n\u2022 Work closely with cross-functional teams to identify reporting requirements and deliver intuitive dashboards and reports.\n\u2022 Monitor key performance indicators (KPIs) and provide regular performance analysis reports to senior leadership.\n\nCollaboration and Leadership:\n\u2022 Collaborate with executive leadership to align data and analytics initiatives with overall business strategies.\n\u2022 Mentor and guide data professionals (direct reports and cross-departmental), fostering a culture of innovation, collaboration, and continuous learning.\n\u2022 Act as a strategic advisor, influencing decision-making processes across departments by leveraging data insights.\n\nStakeholder Engagement:\n\u2022 Engage with internal stakeholders to understand their data needs and provide tailored solutions.\n\u2022 Communicate complex technical concepts and insights to non-technical stakeholders in a clear and concise manner.\n\u2022 Build strong relationships with external partners, vendors, and industry experts to stay abreast of emerging trends and technologies in data and analytics.\n\u2022 Other duties as assigned\n\nRequirements\n\nWHAT YOU BRING TO THE TABLE:\n\nTechnical and Professional Knowledge, Skills, and Abilities\n\nAchievement of technical and professional knowledge, skills, and abilities is high in position-related areas; demonstrates curiosity and keeps current with trends in areas of expertise.\n\nAnalytical Proficiency\n\nLeverages extensive knowledge of qualitative and quantitative methods to identify, organize, interpret and report data needed by organizational decision makers to achieve favorable organizational outcomes; establishes ongoing procedures to collect and monitor information.\n\nCommunication Skills\n\nEffectively listens, speaks, observes, and empathizes while showing appropriate assertiveness, confidence, and respect. Communicates concepts, ideas, needs, and feelings with appropriate tone, clarity, volume and non-verbal cues for each situation. Demonstrates understanding of differences communicating through face-to-face interactions, phone conversations, and written / digital communications. Adjusts communication styles to suit different audiences, including students, peers, managers, executives, and vendors/partners. Utilize more advanced communication skills, such as persuasive communication, conflict resolution, and negotiation skills. Communicate effectively with own / other teams. Demonstrates strong presentation skills and the ability to communicate complex ideas clearly and concisely.\n\nWork Standards\n\nSets high standards of performance for self, assumes responsibility and accountability for successfully completing assignments or tasks on time; work demonstrates a high degree of excellence and accuracy.\n\nTeamwork and Engagement\n\nParticipates as an active member of the team and works towards common goals; builds positive relationships in the workplace and participates in learning and social functions.\n\nOrganizational Alignment\n\nModels the behaviors expected of all employees including an adherence to the mission, vision, values, and core themes of the organization; high levels of mutual respect, emotional maturity, professionalism, communication, and a drive for results.\n\nManagement and Empowerment\n\nEffectively manages time and resources at a business level. Conducts regular one on ones and team meetings including team building activities. Identifies opportunities to empower others to improve existing conditions and processes; uses appropriate methods to drive accountability in the organization.\n\nBuild Strategic Working Relationships\n\nDevelop collaborative relationships with other senior leaders throughout the organization to build internally and externally one's functional reputation in pursuit of improved business results. Demonstrate advanced leadership skills in a manner that inspires, unites, and motivates others.\n\nPerformance Development\n\nGuides others in accomplishing work and professional objectives by providing regular coaching and feedback, tracking and evaluating performance, and supporting the development of individuals' skills and abilities so that they can fulfill current or future responsibilities effectively.\n\nEmotional Intelligence\n\nEstablish and sustain trusting relationships by accurately perceiving and interpreting one's own and others' emotions and behaviors in the context of the organization's political and cultural environment; leverage insights to effectively manage one's own responses and reactions.\n\nDecision Making\n\nIdentify and understand issues, problems, and opportunities by comparing data from different sources to draw conclusions and determine effective courses of action consistent with available facts, constraints and probable consequences.\n\nStrategy Execution\n\nTranslate strategy into operational reality by aligning communication, accountability, resources, processes, and ongoing measurements to ensure that strategic priorities yield measurable and sustainable results; be an agent of change.\n\nExperience and Education:\n\u2022 Bachelor's or Master's degree in data science, Statistics, Computer Science, Business Analytics, or related field.\n\u2022 Proven experience (10 years preferred) in data and analytics roles, with a focus on strategy development, advanced analytics, and business intelligence.\n\u2022 Strong background in data management, data governance, and data architecture.\n\u2022 Proficiency in programming languages (such as Python, R, or SQL) and familiarity with data visualization tools (such as DOMO and PowerBI).\n\u2022 Experience with Salesforce CRM, DOMO, and Snowflake data warehouse a plus.\n\u2022 Excellent leadership and people management skills, with a track record of building and leading high-performing teams.\n\u2022 Exceptional communication skills, both verbal and written, with the ability to convey complex data concepts to diverse audiences.\n\u2022 Demonstrated experience in collaborating with cross-functional teams and senior executives to drive data-driven decision-making processes.\n\u2022 Knowledge of industry best practices, emerging trends, and advancements in data science and analytics.\n\nTERMS OF EMPLOYMENT:\n\nLocation: Hybrid or Fully Remote for highly qualified candidate\n\nEmployment Status: Full time\n\nHours of Employment: Minimum 40 hrs./week, Mon-Fri, occasional evenings, and Saturdays\n\nTravel: 10%\n\nEQUAL EMPLOYMENT OPPORUTNITY POLICY:\n\nJoyce University provides equal employment opportunities to all employees and applicants for employment and prohibits discrimination and harassment of any type without regard to race, color, religion, age, sex, national origin, disability status, genetics, protected veteran status, sexual orientation, gender identity or expression, or any other characteristic protected by federal, state, or local laws. This policy applies to all terms and conditions of employment, including recruiting, hiring, placement, promotion, termination, layoff, recall, transfer, leaves of absence, compensation, and training.", "job_is_remote": false, "job_posted_at_timestamp": 1707207590, "job_posted_at_datetime_utc": "2024-02-06T08:19:50.000Z", "job_city": "Draper", "job_state": "UT", "job_country": "US", "job_latitude": 40.52467, "job_longitude": -111.86382, "job_benefits": ["paid_time_off", "health_insurance", "dental_coverage", "retirement_savings"], "job_google_link": "https://www.google.com/search?gl=us&hl=en&rciv=jb&q=director+of+advanced+analytics&start=40&ibp=htl;jobs#fpstate=tldetail&htivrt=jobs&htiq=director+of+advanced+analytics&htidocid=m7NNFbaOVoLKzmCiAAAAAA%3D%3D", "job_offer_expiration_datetime_utc": null, "job_offer_expiration_timestamp": null, "job_required_experience": {"no_experience_required": false, "required_experience_in_months": 120, "experience_mentioned": true, "experience_preferred": true}, "job_required_skills": null, "job_required_education": {"postgraduate_degree": false, "professional_certification": false, "high_school": false, "associates_degree": false, "bachelors_degree": false, "degree_mentioned": true, "degree_preferred": true, "professional_certification_mentioned": false}, "job_experience_in_place_of_education": false, "job_min_salary": 141420, "job_max_salary": 181826, "job_salary_currency": "USD", "job_salary_period": "YEAR", "job_highlights": {"Qualifications": ["We are currently looking for an experienced and proven Senior Director of Data Analytics", "The ideal candidate brings a strong background in data management, 10+ years of proven experience, proficiency in programming languages, and excellent communication skills", "Achievement of technical and professional knowledge, skills, and abilities is high in position-related areas; demonstrates curiosity and keeps current with trends in areas of expertise", "Leverages extensive knowledge of qualitative and quantitative methods to identify, organize, interpret and report data needed by organizational decision makers to achieve favorable organizational outcomes; establishes ongoing procedures to collect and monitor information", "Effectively listens, speaks, observes, and empathizes while showing appropriate assertiveness, confidence, and respect", "Communicate effectively with own / other teams", "Demonstrates strong presentation skills and the ability to communicate complex ideas clearly and concisely", "Sets high standards of performance for self, assumes responsibility and accountability for successfully completing assignments or tasks on time; work demonstrates a high degree of excellence and accuracy", "Models the behaviors expected of all employees including an adherence to the mission, vision, values, and core themes of the organization; high levels of mutual respect, emotional maturity, professionalism, communication, and a drive for results", "Establish and sustain trusting relationships by accurately perceiving and interpreting one's own and others' emotions and behaviors in the context of the organization's political and cultural environment; leverage insights to effectively manage one's own responses and reactions", "Bachelor's or Master's degree in data science, Statistics, Computer Science, Business Analytics, or related field", "Strong background in data management, data governance, and data architecture", "Proficiency in programming languages (such as Python, R, or SQL) and familiarity with data visualization tools (such as DOMO and PowerBI)", "Excellent leadership and people management skills, with a track record of building and leading high-performing teams", "Exceptional communication skills, both verbal and written, with the ability to convey complex data concepts to diverse audiences", "Demonstrated experience in collaborating with cross-functional teams and senior executives to drive data-driven decision-making processes", "Knowledge of industry best practices, emerging trends, and advancements in data science and analytics"], "Responsibilities": ["As the Senior Director of Data Analytics, you will lead Joyce University's data strategy, ensuring alignment with institutional goals", "Responsible for overseeing data collection, integration, and validation processes, you will uphold data accuracy and compliance", "Your role involves driving advanced analytics initiatives, guiding the development of models, algorithms, and dashboards, and translating complex insights into actionable recommendations", "Spearheading business intelligence efforts, you will implement and manage analytics tools, collaborate with cross-functional teams, and provide performance analysis reports to senior leadership", "Your leadership extends to mentoring data professionals, fostering innovation, and acting as a strategic advisor to influence decision-making processes", "Additionally, you will engage with internal and external stakeholders, building strong relationships and staying abreast of emerging trends and technologies in data and analytics", "Develop and execute a comprehensive data strategy aligned with the company's goals and objectives", "Create institutional data definitions and ensure adherence to definitions through Q/A protocols", "Implement best practices in data governance, compliance, and security to safeguard sensitive information", "Lead the company's data team to develop analytical models, algorithms, and dashboards", "Translate complex data insights into understandable and actionable recommendations for key stakeholders", "Utilize statistical techniques and machine learning algorithms to identify trends, patterns, and opportunities within large datasets", "Implement and manage business intelligence tools and platforms to enable self-service analytics for various departments", "Work closely with cross-functional teams to identify reporting requirements and deliver intuitive dashboards and reports", "Monitor key performance indicators (KPIs) and provide regular performance analysis reports to senior leadership", "Collaborate with executive leadership to align data and analytics initiatives with overall business strategies", "Mentor and guide data professionals (direct reports and cross-departmental), fostering a culture of innovation, collaboration, and continuous learning", "Act as a strategic advisor, influencing decision-making processes across departments by leveraging data insights", "Engage with internal stakeholders to understand their data needs and provide tailored solutions", "Communicate complex technical concepts and insights to non-technical stakeholders in a clear and concise manner", "Build strong relationships with external partners, vendors, and industry experts to stay abreast of emerging trends and technologies in data and analytics", "Other duties as assigned", "Demonstrates understanding of differences communicating through face-to-face interactions, phone conversations, and written / digital communications", "Adjusts communication styles to suit different audiences, including students, peers, managers, executives, and vendors/partners", "Utilize more advanced communication skills, such as persuasive communication, conflict resolution, and negotiation skills", "Participates as an active member of the team and works towards common goals; builds positive relationships in the workplace and participates in learning and social functions", "Effectively manages time and resources at a business level", "Conducts regular one on ones and team meetings including team building activities", "Identifies opportunities to empower others to improve existing conditions and processes; uses appropriate methods to drive accountability in the organization", "Build Strategic Working Relationships", "Develop collaborative relationships with other senior leaders throughout the organization to build internally and externally one's functional reputation in pursuit of improved business results", "Translate strategy into operational reality by aligning communication, accountability, resources, processes, and ongoing measurements to ensure that strategic priorities yield measurable and sustainable results; be an agent of change"], "Benefits": ["Self-Directed PTO policy", "Paid holidays", "401k with employer match", "Medical, dental, and vision insurance", "Fully paid short term disability", "Long term disability", "Life Insurance", "Professional Development", "Education assistance"]}, "job_job_title": "Senior", "job_posting_language": "en", "job_onet_soc": "11302100", "job_onet_job_zone": "4", "job_naics_code": "61", "job_naics_name": "Education"}