{"job_id": "BgqvZLZijA4_60rAAAAAAA==", "employer_name": "Katapult", "employer_logo": "https://encrypted-tbn0.gstatic.com/images?q=tbn:ANd9GcQu1sd6c-NYc05_ncuw8sgZHNIkY-1JLn66sJQy&s=0", "employer_website": null, "employer_company_type": null, "job_publisher": "LinkedIn", "job_employment_type": "FULLTIME", "job_title": "Director Partnership Development", "job_apply_link": "https://www.linkedin.com/jobs/view/director-partnership-development-at-katapult-3854524509", "job_apply_is_direct": false, "job_apply_quality_score": 0.6311, "apply_options": [{"publisher": "LinkedIn", "apply_link": "https://www.linkedin.com/jobs/view/director-partnership-development-at-katapult-3854524509", "is_direct": false}, {"publisher": "Indeed", "apply_link": "https://www.indeed.com/viewjob?jk=bd55bb6b34fc1107", "is_direct": false}, {"publisher": "Levels.fyi", "apply_link": "https://www.levels.fyi/jobs?jobId=121388988578570950", "is_direct": false}], "job_description": "The Director Partnership Development will drive growth with new and existing Katapult partners. This role reports to the Chief Revenue Officer and falls within the Revenue Team. Katapult\u2019s partnerships create value through acquiring merchants and consumers, as well as growing revenue.\n\nThis individual will oversee three partner categories. The first is platform partners, including ecommerce platforms such as Shopify, Magento, etc, and waterfall platforms such as ChargeAfter, Synchrony, and others. The second is referral partners: those third parties that drive new consumers to Katapult. These cross a broad range of companies, including lenders, marketplaces, service providers, and retailers. The last category is outbound affiliate partners, companies where Katapult receives a commission for driving Katapult consumers to a third party. The Director Partnership Development is responsible for creating and executing the growth strategy across all of these partnership types.\n\nOur teams are hyper-collaborative, so this role will work closely with other teams, including the Executive Team, Sales, Client Success, Marketing, and Product. To be successful in this role, you must have in-depth knowledge of business operations, expertise in the financing & commerce landscape, an analytical mindset, and the ability to think outside the box, as well as superb leadership and management skills.\n\nWhat You\u2019ll Do\n\u2022 Develops and executes the strategic plan to enhance partner acquisition, engagement & growth, and retention\n\u2022 Acts as senior leader and partnership advisor\n\u2022 Owns and implements B2B and B2C partnerships and platforms\n\u2022 Accountable for assigned OKRs\n\u2022 Analyzes business performance and create monthly/quarterly reviews.\n\u2022 Provides regular updates to Katapult\u2019s executive leadership team\n\u2022 Drives new strategic connections and fosters growth with existing partners\n\u2022 Works closely with senior leaders to develop and implement partnership structures/programs to maximize revenue and growth\n\u2022 Develops and manages key metrics/KPIs to develop deep partnership insights, assess partnership effectiveness, and drive strategy\n\u2022 Provides direction, guidance, development, and manages performance of Partner Development Manager\n\u2022 Collaborates across all Katapult teams on implementation of partner program initiatives\n\u2022 Educates and informs cross-functionally to ensure alignment\n\u2022 This list is not all inclusive and subject to change without prior notice\n\nRequirements\n\u2022 10 years direct experience (Required)\n\u2022 Management: 3-5 years (Required)\n\u2022 Bachelor's degree (Preferred)\n\u2022 Proven success in developing and evaluating enterprise partnerships\n\u2022 Experience interacting with C-level executives in traditional corporate settings and start-ups\n\u2022 Excellent project management skills with some experience in tech industries\n\u2022 Strong presentation and communication skills?\n\u2022 Highly goal driven and work well in fast-paced environments\n\u2022 Possess strong analytical skills\n\u2022 Entrepreneurial, creative mindset and highly self-motivated\n\u2022 Adept at building relationships and liaising with multiple stakeholders\n\u2022 Experience within the listed platforms\n\u2022 This position is primarily remote. Occasional travel is outside the local area and overnight.\n\nBenefits and Perks: At Katapult, there's a lot more to consider than just base pay! We pride ourselves in offering an above-market total compensation package along with other benefits:\n\u2022 Medical coverage starting at $0.00 cost to you!\n\u2022 Dental & Vision\n\u2022 Flexible Spending Accounts\n\u2022 New Parent Leave\n\u2022 401K (100% company match up to 5% - immediate vesting)\n\u2022 Flexible Paid Vacation & Personal Time Policy - \"Unlimited PTO\"\n\u2022 Company-paid life & disability insurance\n\u2022 Pet Insurance\n\u2022 Employee Assistance Program for personal counseling\n\u2022 Legal Services & more!\n\nAbout Katapult\n\nKatapult\u2019s mission is simple: Our technology inspires financial possibility. Our vision is to create a world where financial barriers no longer exist by providing disruptive technology that empowers and simplifies the shopping experience. Our values speak volumes about how we operate. We enhance the lives of our employees, customers, and retail partners by providing transparent, innovative and empowering financial products. We achieve extraordinary results through commitment, integrity and teamwork. We create opportunities for success and growth everyday. Inclusion is in our DNA, together we are stronger. We persevere, we work hard, we play hard, we win big.\n\nKatapult is transforming the world of lease-to-own with transparent lease-purchase plans that flex to meet the needs of consumers who are overlooked by traditional credit. With proprietary artificial intelligence (AI) and machine learning (ML) risk-modeling technology, Katapult predicts consumer behavior more accurately than traditional credit scores - providing new paths to ownership for people and new customers for omnichannel retailers. Katapult ensures exceptional experiences with seamless integration, both directly with merchants and through ecommerce platforms, and award-winning customer service.\n\nInclusion is in our DNA. Katapult hires the best candidates without regard to race, color, religion, sex, national origin, age, sexual orientation, gender identity, disability status, protected veteran status, or any other characteristic protected by federal, state and local law.", "job_is_remote": true, "job_posted_at_timestamp": 1710345301, "job_posted_at_datetime_utc": "2024-03-13T15:55:01.000Z", "job_city": null, "job_state": null, "job_country": "US", "job_latitude": 37.09024, "job_longitude": -95.71289, "job_benefits": ["dental_coverage", "paid_time_off", "retirement_savings", "health_insurance"], "job_google_link": "https://www.google.com/search?gl=us&hl=en&rciv=jb&q=vice+president+of+brand+partnerships&start=40&ibp=htl;jobs#fpstate=tldetail&htivrt=jobs&htiq=vice+president+of+brand+partnerships&htidocid=BgqvZLZijA4_60rAAAAAAA%3D%3D", "job_offer_expiration_datetime_utc": "2024-04-12T15:55:01.000Z", "job_offer_expiration_timestamp": 1712937301, "job_required_experience": {"no_experience_required": false, "required_experience_in_months": 120, "experience_mentioned": true, "experience_preferred": false}, "job_required_skills": null, "job_required_education": {"postgraduate_degree": false, "professional_certification": false, "high_school": false, "associates_degree": false, "bachelors_degree": true, "degree_mentioned": true, "degree_preferred": false, "professional_certification_mentioned": false}, "job_experience_in_place_of_education": false, "job_min_salary": null, "job_max_salary": null, "job_salary_currency": null, "job_salary_period": null, "job_highlights": {"Qualifications": ["To be successful in this role, you must have in-depth knowledge of business operations, expertise in the financing & commerce landscape, an analytical mindset, and the ability to think outside the box, as well as superb leadership and management skills", "10 years direct experience (Required)", "Management: 3-5 years (Required)", "Proven success in developing and evaluating enterprise partnerships", "Experience interacting with C-level executives in traditional corporate settings and start-ups", "Excellent project management skills with some experience in tech industries", "Strong presentation and communication skills?", "Highly goal driven and work well in fast-paced environments", "Possess strong analytical skills", "Entrepreneurial, creative mindset and highly self-motivated", "Adept at building relationships and liaising with multiple stakeholders", "Experience within the listed platforms"], "Responsibilities": ["The Director Partnership Development will drive growth with new and existing Katapult partners", "This role reports to the Chief Revenue Officer and falls within the Revenue Team", "Katapult\u2019s partnerships create value through acquiring merchants and consumers, as well as growing revenue", "This individual will oversee three partner categories", "The first is platform partners, including ecommerce platforms such as Shopify, Magento, etc, and waterfall platforms such as ChargeAfter, Synchrony, and others", "The Director Partnership Development is responsible for creating and executing the growth strategy across all of these partnership types", "Our teams are hyper-collaborative, so this role will work closely with other teams, including the Executive Team, Sales, Client Success, Marketing, and Product", "Develops and executes the strategic plan to enhance partner acquisition, engagement & growth, and retention", "Acts as senior leader and partnership advisor", "Owns and implements B2B and B2C partnerships and platforms", "Accountable for assigned OKRs", "Analyzes business performance and create monthly/quarterly reviews", "Provides regular updates to Katapult\u2019s executive leadership team", "Drives new strategic connections and fosters growth with existing partners", "Works closely with senior leaders to develop and implement partnership structures/programs to maximize revenue and growth", "Develops and manages key metrics/KPIs to develop deep partnership insights, assess partnership effectiveness, and drive strategy", "Provides direction, guidance, development, and manages performance of Partner Development Manager", "Collaborates across all Katapult teams on implementation of partner program initiatives", "Educates and informs cross-functionally to ensure alignment", "This list is not all inclusive and subject to change without prior notice", "Occasional travel is outside the local area and overnight"], "Benefits": ["Benefits and Perks: At Katapult, there's a lot more to consider than just base pay!", "We pride ourselves in offering an above-market total compensation package along with other benefits:", "Medical coverage starting at $0.00 cost to you!", "Dental & Vision", "Flexible Spending Accounts", "New Parent Leave", "401K (100% company match up to 5% - immediate vesting)", "Flexible Paid Vacation & Personal Time Policy - \"Unlimited PTO\"", "Company-paid life & disability insurance", "Pet Insurance", "Employee Assistance Program for personal counseling"]}, "job_job_title": "Director", "job_posting_language": "en", "job_onet_soc": "11202100", "job_onet_job_zone": "4"}