{"job_id": "EoJ85YeWsF5OBI1IAAAAAA==", "employer_name": "Empire Candle Co., LLC - 3.4", "employer_logo": null, "employer_website": null, "employer_company_type": null, "job_publisher": "Kansas City KS Geebo.com Free Classifieds Ads - Geebo", "job_employment_type": "FULLTIME", "job_title": "Director of Business Development", "job_apply_link": "https://kansascity-ks.geebo.com/jobs-online/view/id/1286209376-director-of-business-development-/", "job_apply_is_direct": true, "job_apply_quality_score": 0.4746, "apply_options": [{"publisher": "Kansas City KS Geebo.com Free Classifieds Ads - Geebo", "apply_link": "https://kansascity-ks.geebo.com/jobs-online/view/id/1286209376-director-of-business-development-/", "is_direct": true}], "job_description": "3.\n4 Quick Apply Full-time 7 hours ago Full Job Description Empire Candle Co.\n, LLC 2925 Fairfax Trafficway Kansas City, KS 66115 Job Title:\nDirector of Business Development Position Overview The Director of Business Development is responsible for expanding the company's core business, identifying new and diverse channels, as well as building our company's physical brand presence.\nThe Director of Business Development will work for the EVP of Sales and will constantly work on developing new opportunities to develop plans and ideas to create new sales, business, distribution and customer opportunities.\nEssential Job Functions Develop and execute new strategic channel and business plans with EVP of Sales (and CEO), including:\nIdentify and land new non-grocery customers and channels for existing Tuscany Candle Collections.\nIdentify and land new customer opportunities and segments we do not currently serve (e.\ng.\ndepartment stores, other retailers, multi-unit gift stores, e-commerce) Where appropriate, identify contract manufacturing or private label customers that fit our business and distribution model.\nSell in new Tier 1/higher end collections (to be developed) into appropriate non-grocery channels.\nResearch, plan, and implement new target market, channel and customer initiatives.\nIdentify leads and develop and move them along the sales cycle toward closing.\nCollaborate with Sales and Marketing to identify new customers, channels and product development opportunities.\nTrack emerging candle markets, trends, gaps, development opportunities and win new business.\nEstablish productive, professional relationships with key personnel in assigned customer accounts.\nWith guidance from EVP of Sales, recommend and negotiate price and service agreements Meet assigned targets for profitable sales volume and strategic objectives in assigned accounts.\nPerform data analysis to track business performance and identify opportunities to grow revenue and profit.\nPropose and develop strategic partnerships, and prepare business development documents and plans to support them.\nHelp to execute the company's long-term objectives of diversification with the right new channels and business.\nRequirements, Skills & Experience To perform this job successfully, an individual must be able to perform each essential duty satisfactorily.\nThe requirements listed below are representative of the knowledge, skill, and/or ability required.\nReasonable accommodations may be made to enable individuals with disabilities to perform the essential functions.\nBachelor's Degree in Marketing, business or related degree.\n5 -7 years of candle or home d cor industry or similar retail channels (such as, gift, home goods or department stores, etc.\n) Experience selling home d cor, candles, home goods products, gift or similar products AND retailers.\nExperience developing strategic manufacturing partnerships.\nMust be able to demonstrate a successful track record in a past Business Development role.\nMust be able to travel up to 50% - 75% of time with overnight stays.\nStrong drive to acquire new business.\nExhibit strong initiative, proactiveness and follow through.\nCollaboration and negotiation skills Lead Generation and management.\nExceptional attention to detail.\nAbility to understand customer analytics and performance management.\nUnderstand the core consumer and the buying experience.\nCustomer Relationship Management (CRM) software experience Excellent relationship building, presentation and communication skills.\nThis is not necessarily an exhaustive list of responsibilities, skills, duties, requirements, efforts, or working conditions associate with the job.\nWhile this list is intended to be an accurate reflection of the current job, the Company reserves the right to revise the functions and duties of the job or to require that additional or different tasks be performed when circumstances change (i.\ne.\n, emergencies, changes in personnel, work load, rush jobs, or technological developments).\nJob Type:\nFull-time Pay:\nFrom $90,000.\n00 per year\nBenefits:\n401(k) 401(k) matching Dental insurance Employee discount Health insurance Life insurance Paid time off Referral program Tuition reimbursement Vision insurance Schedule:\nDay shift Overtime\nExperience:\nBusiness development:\n2 years (Preferred) Consumer goods Sales:\n5 years (Preferred) Work Location:\nOne location Quick Apply.\nEstimated Salary: $20 to $28 per hour based on qualifications.", "job_is_remote": false, "job_posted_at_timestamp": 1710028800, "job_posted_at_datetime_utc": "2024-03-10T00:00:00.000Z", "job_city": "Kansas City", "job_state": "KS", "job_country": "US", "job_latitude": 39.115532, "job_longitude": -94.626785, "job_benefits": ["paid_time_off", "retirement_savings", "health_insurance", "dental_coverage"], "job_google_link": "https://www.google.com/search?gl=us&hl=en&rciv=jb&q=director+of+business+development&start=10&ibp=htl;jobs#fpstate=tldetail&htivrt=jobs&htiq=director+of+business+development&htidocid=EoJ85YeWsF5OBI1IAAAAAA%3D%3D", "job_offer_expiration_datetime_utc": "2024-03-17T00:00:00.000Z", "job_offer_expiration_timestamp": 1710633600, "job_required_experience": {"no_experience_required": false, "required_experience_in_months": null, "experience_mentioned": true, "experience_preferred": false}, "job_required_skills": null, "job_required_education": {"postgraduate_degree": false, "professional_certification": false, "high_school": false, "associates_degree": false, "bachelors_degree": false, "degree_mentioned": true, "degree_preferred": true, "professional_certification_mentioned": false}, "job_experience_in_place_of_education": false, "job_min_salary": 20, "job_max_salary": 28, "job_salary_currency": "USD", "job_salary_period": "HOUR", "job_highlights": {"Qualifications": ["Requirements, Skills & Experience To perform this job successfully, an individual must be able to perform each essential duty satisfactorily", "Reasonable accommodations may be made to enable individuals with disabilities to perform the essential functions", "Bachelor's Degree in Marketing, business or related degree", "5 -7 years of candle or home d cor industry or similar retail channels (such as, gift, home goods or department stores, etc", ") Experience selling home d cor, candles, home goods products, gift or similar products AND retailers", "Experience developing strategic manufacturing partnerships", "Must be able to demonstrate a successful track record in a past Business Development role", "Must be able to travel up to 50% - 75% of time with overnight stays", "Strong drive to acquire new business", "Exhibit strong initiative, proactiveness and follow through", "Exceptional attention to detail", "Ability to understand customer analytics and performance management", "Understand the core consumer and the buying experience", "Customer Relationship Management (CRM) software experience Excellent relationship building, presentation and communication skills"], "Responsibilities": ["The Director of Business Development will work for the EVP of Sales and will constantly work on developing new opportunities to develop plans and ideas to create new sales, business, distribution and customer opportunities", "Essential Job Functions Develop and execute new strategic channel and business plans with EVP of Sales (and CEO), including:", "Identify and land new non-grocery customers and channels for existing Tuscany Candle Collections", "Sell in new Tier 1/higher end collections (to be developed) into appropriate non-grocery channels", "Research, plan, and implement new target market, channel and customer initiatives", "Identify leads and develop and move them along the sales cycle toward closing", "Collaborate with Sales and Marketing to identify new customers, channels and product development opportunities", "Track emerging candle markets, trends, gaps, development opportunities and win new business", "Establish productive, professional relationships with key personnel in assigned customer accounts", "With guidance from EVP of Sales, recommend and negotiate price and service agreements Meet assigned targets for profitable sales volume and strategic objectives in assigned accounts", "Perform data analysis to track business performance and identify opportunities to grow revenue and profit", "Propose and develop strategic partnerships, and prepare business development documents and plans to support them", "Help to execute the company's long-term objectives of diversification with the right new channels and business"], "Benefits": ["From $90,000", "00 per year", "401(k) 401(k) matching Dental insurance Employee discount Health insurance Life insurance Paid time off Referral program Tuition reimbursement Vision insurance Schedule:", "Day shift Overtime", "Estimated Salary: $20 to $28 per hour based on qualifications"]}, "job_job_title": "Director_of business", "job_posting_language": "en", "job_onet_soc": "11202100", "job_onet_job_zone": "4"}