{"job_id": "Vh4PUyousoZoZi0OAAAAAA==", "employer_name": "My Talent Planner", "employer_logo": null, "employer_website": "https://mytalentplanner.com", "employer_company_type": null, "job_publisher": "Indeed", "job_employment_type": "FULLTIME", "job_title": "Director of Business Development & Growth", "job_apply_link": "https://www.indeed.com/viewjob?jk=756a074397e7e992", "job_apply_is_direct": true, "job_apply_quality_score": 0.613, "apply_options": [{"publisher": "Indeed", "apply_link": "https://www.indeed.com/viewjob?jk=756a074397e7e992", "is_direct": true}], "job_description": "Job Title: Director of Business Development & Growth\n\nReports to: CEO/Founder\n\nDirect Reports: None at this time\n\nLocation: Remote/Large Midwest City\n\nCompany Profile\n\nMyTalentPlanner is a Platform as a Service (PaaS) company that provides organizations the ability to dominate their industry with the right people and strategy. We have all these plans in place in our business (marketing plan) and life (health insurance plan) but how come we don\u2019t put a talent plan in place in our organization. MyTalentPlanner provides our unique talent planning process and software to Small to Medium-Sized Businesses (SMBs), as well as other consultants to use with their clients. MyTalentPlanner is the only platform for SMBs that integrates their strategy, talent and execution plans all in one place accessible from any place.\n\nMyTalentPlanner is staged for significant growth and wants to add a Business Development Manager to our team that is focused on increasing revenue. The Business Development Manager will be rewarded for increasing users on the software through salary, aggressive commission plan and company stock.\n\nThis is a one-of-a-kind opportunity for an individual who is wants to be part of a cohesive team, change the industry, increasing responsibility control your own destiny\n\nWhat You Can Expect from Us\n\n\u25cf Salary with commissions based on new sales\n\n\u25cf Company ownership/Employee stock ownership\n\n\u25cf 401k with 3% match\n\n\u25cf Vacation\n\n\u25cf Total person development plan\n\n\u25cf Advancement and leadership opportunities\n\nKey Accountabilities for Business Development Manager\n\n\u00b7 These key accountabilities are ranked in order of importance and include the % of time in a week/month that the Business Development Manager will spend on each key accountability.\n\n1. New Business Development/Increase Revenue (60% of time) \u2013 Add new consultants (TPAs) and SMB companies to MyTalentPlanner through a consultative sales approach.\n\n2. Sales Strategy (20% of time) \u2013 Develop a proactive sales strategy that achieves budgeted sales with our target markets\n\n3. CRM/Database Management (5% of time) -Consistently use CRM software to fill the sales pipeline by tracking, monitoring, communicating with and close active leads.\n\n4. Team Member (10% of time) \u2013 Be a contributing Revenue Team Member by providing insight and ideas to achieve monthly reoccurring revenue (MRR) goals.\n\n5. Market Intelligence (5% of time) \u2013Collect and distribute market and competitive intelligence/be the eyes and ears of the organization in the field.\n\n\u00b7 Lead the sales strategy and execution of the company to achieve revenue goals\n\n\u00b7 Proactive in bringing forward creative and unique sales ideas\n\n\u00b7 Optimistic/Inspires others to the vision of MyTalentPlanner\n\n\u00b7 Is passionate about helping companies grow their people and organization.\n\n\u00b7 Self-starter \u2013 Works independently with a sense of urgency\n\n\u00b7 Interpersonal skills\n\n\u00b7 Personal accountability\n\n\u00b7 Self-management\n\n\u00b7 Teamwork\n\nRequirements\n\n\u00b7 Education\n\no 4-year degree in business related field\n\n\u00b7 Experience\n\no 3+ years of successful business-to business sales experience required\n\no Experience selling SMB or HR leaders\n\no CRM system experience a plus\n\no SaaS sales experience a plus\n\nMeasures of Performance (vs. Budget)\n\n\u00b7 MRR = Monthly Reoccurring Revenue vs. budget\n\n\u00b7 ARR \u2013 Annual Reoccurring Revenue vs. budget\n\n\u00b7 Sales Pipeline\n\n\u00b7 # of Talent Planning Advisors\n\n\u00b7 # of Companies/Users\n\nNOTE: This job description is not intended to be all-inclusive. Employee may perform other related duties as assigned to meet the ongoing needs of the organization.\n\nJob Type: Full-time\n\nBenefits:\n\u2022 401(k)\n\u2022 Dental insurance\n\u2022 Health insurance\n\u2022 Paid time off\n\u2022 Vision insurance\n\nSchedule:\n\u2022 8 hour shift\n\u2022 Monday to Friday\n\nWork Location: Remote", "job_is_remote": true, "job_posted_at_timestamp": 1710268347, "job_posted_at_datetime_utc": "2024-03-12T18:32:27.000Z", "job_city": "Remote", "job_state": "OR", "job_country": "US", "job_latitude": 43.005947, "job_longitude": -123.89259, "job_benefits": ["dental_coverage", "retirement_savings", "health_insurance", "paid_time_off"], "job_google_link": "https://www.google.com/search?gl=us&hl=en&rciv=jb&q=director+of+business+development&start=0&ibp=htl;jobs#fpstate=tldetail&htivrt=jobs&htiq=director+of+business+development&htidocid=Vh4PUyousoZoZi0OAAAAAA%3D%3D", "job_offer_expiration_datetime_utc": "2024-07-12T02:27:09.000Z", "job_offer_expiration_timestamp": 1720751229, "job_required_experience": {"no_experience_required": false, "required_experience_in_months": 48, "experience_mentioned": true, "experience_preferred": true}, "job_required_skills": null, "job_required_education": {"postgraduate_degree": false, "professional_certification": false, "high_school": false, "associates_degree": false, "bachelors_degree": false, "degree_mentioned": false, "degree_preferred": true, "professional_certification_mentioned": false}, "job_experience_in_place_of_education": false, "job_min_salary": null, "job_max_salary": null, "job_salary_currency": null, "job_salary_period": null, "job_highlights": {"Qualifications": ["Interpersonal skills", "4-year degree in business related field", "3+ years of successful business-to business sales experience required", "Experience selling SMB or HR leaders"], "Responsibilities": ["These key accountabilities are ranked in order of importance and include the % of time in a week/month that the Business Development Manager will spend on each key accountability", "New Business Development/Increase Revenue (60% of time) \u2013 Add new consultants (TPAs) and SMB companies to MyTalentPlanner through a consultative sales approach", "Sales Strategy (20% of time) \u2013 Develop a proactive sales strategy that achieves budgeted sales with our target markets", "CRM/Database Management (5% of time) -Consistently use CRM software to fill the sales pipeline by tracking, monitoring, communicating with and close active leads", "Team Member (10% of time) \u2013 Be a contributing Revenue Team Member by providing insight and ideas to achieve monthly reoccurring revenue (MRR) goals", "Market Intelligence (5% of time) \u2013Collect and distribute market and competitive intelligence/be the eyes and ears of the organization in the field", "Lead the sales strategy and execution of the company to achieve revenue goals", "Proactive in bringing forward creative and unique sales ideas", "Optimistic/Inspires others to the vision of MyTalentPlanner", "Is passionate about helping companies grow their people and organization", "Self-starter \u2013 Works independently with a sense of urgency", "Teamwork"], "Benefits": ["Salary with commissions based on new sales", "Company ownership/Employee stock ownership", "401k with 3% match", "Vacation", "Total person development plan", "Advancement and leadership opportunities", "MRR = Monthly Reoccurring Revenue vs", "ARR \u2013 Annual Reoccurring Revenue vs", "401(k)", "Dental insurance", "Health insurance", "Paid time off", "Vision insurance", "8 hour shift", "Monday to Friday"]}, "job_job_title": "Director_of business", "job_posting_language": "en", "job_onet_soc": "11202100", "job_onet_job_zone": "4"}