{"job_id": "HmnWzkVDUAqLHqogAAAAAA==", "employer_name": "Muscular Dystrophy Association", "employer_logo": "https://www.mda.org/sites/all/themes/mda_bootstrap_subtheme/img/mda-logo-horizontal-2.svg", "employer_website": "http://www.mda.org", "employer_company_type": "Health Care", "job_publisher": "LinkedIn", "job_employment_type": "FULLTIME", "job_title": "Project Director, Community Partnerships", "job_apply_link": "https://www.linkedin.com/jobs/view/project-director-community-partnerships-at-muscular-dystrophy-association-3814327080", "job_apply_is_direct": false, "job_apply_quality_score": 0.7389, "apply_options": [{"publisher": "LinkedIn", "apply_link": "https://www.linkedin.com/jobs/view/project-director-community-partnerships-at-muscular-dystrophy-association-3814327080", "is_direct": false}, {"publisher": "Glassdoor", "apply_link": "https://www.glassdoor.com/job-listing/project-director-community-partnerships-muscular-dystrophy-assoc-inc-JV_KO0,39_KE40,68.htm?jl=1009090612607", "is_direct": true}, {"publisher": "Indeed", "apply_link": "https://www.indeed.com/viewjob?jk=2729bfe308f5ab21", "is_direct": true}, {"publisher": "Jobgether", "apply_link": "https://jobgether.com/offer/65d53e67af69414782a76d3b-project-director-community-partnerships", "is_direct": false}, {"publisher": "Jobright AI", "apply_link": "https://jobright.ai/jobs/info/65b2056e616cac5efa365c11", "is_direct": false}, {"publisher": "Anvlogisticspty.com", "apply_link": "http://anvlogisticspty.com/?refId=b8JkVbpiYRy3gP9vK9qQSg%3D%3D&trackingId=kDdQwgVFT9GBO%2FePDp7%2BJg%3D%3D&position=15&pageNum=0&trk=public_jobs_jserp-result_search-card&_=%2Fjobs%2Fview%2Fproject-director-community-partnerships-at-muscular-dystrophy-association-3814327080%23PhiIOzy5Bo%2FBBtZjkNwzrNlLocA6HjN%2B", "is_direct": false}], "job_description": "MDA Overview:\n\nAt MDA, we believe our biggest asset is our combination of different backgrounds, cultures, and disciplines united to form one high-performing team. By bringing together people from different backgrounds, perspectives, and generations, we ensure that we all have access to the opportunities, relationships, and resources necessary to learn, grow and thrive. What we do starts with our people and the neuromuscular disease community we serve. As America\u2019s largest voluntary health organization covering research, healthcare, and advocacy for people with neuromuscular diseases, MDA is leading the way in improving the quality of life for those living with muscular dystrophy, ALS, spinal muscular atrophy, and dozens of related disorders \u2013 many first discovered and diagnosed by MDA supported scientists and clinicians.\n\nDepartment Overview:\n\nT he Community Partnerships Department is responsible for planning and executing fundraising events throughout the United States and Puerto Rico. Through community and corporate-led events such as golf tournaments, galas, walks, DIY, and MDA-supported events, the team\u2019s overarching goal is to raise critical funds in a cost-effective manner. This is done by adhering to event best practices, operational efficiencies, and creative integration of volunteers into every aspect of fundraising. The Community Partnerships department is part of t he Development Partnerships structure that is responsible for relationship management to retain donors and fiscal management to ensure best practices are employed to keep margins (net revenue after expenses) for all summative fundraising activities above 85%.\n\nPosition Description:\n\nThe Project Director, Community Partnerships is accountable for implementing complex and diverse projects and cross-division programs working with key internal and external stakeholders to ensure each assigned event, project and programs are delivered with excellence to meet or exceed client expectation.\n\nThis role manages workstreams and develop comprehensive project plans to ensure initiatives are delivered on time, in scope, and on budget and responsible for the day-to-day execution of their clients' campaigns. This individual partners with leadership to deliver high-quality solutions, evaluate business needs, develop functional and any related requirements, and implement project plans to achieve results from conception through completion of the full life cycle.\n\nThe Project Director, Community Partnerships works and manages signature event(s) that fall within the business unit. This includes events logistics, marketing strategies, committee communication & development, budget management, and sponsorship solicitation and management. This position develops new relationships with key industry partners to further the success of the business unit. The Project Director, Community Partnerships reports directly to the Vice President, Community Partnerships.\n\nWhat you\u2019ll do:\n\u2022 Collaborate with Signature Events and P2P teams in expanding committees through various events. Responsibilities to include, but not limited to, researching individuals who have the profile to make a successful committee member, building a pipeline for events (2 to 3 per year) where committee growth is needed and setting up meetings to introduce the opportunity.\n\u2022 Recruit, steward and manage auction committees for events where applicable. Responsibilities to include, but not limited to, individual and group meetings with those committee members who solely support the auction by providing support, resources, and overall management of the auction.\n\u2022 Partner with the departments within the Community Partnerships business unit to help create efficiencies that drive productivity and results.\n\u2022 Foster a positive, ongoing, and enduring relationship with new and current partners and program supporters by, in part, maintaining contact and proactively educating partners/supporters on MDA\u2019s mission outcomes.\n\u2022 Maintain and refine as needed as comprehensive partners relations plan to support MDA\u2019s community-based fundraising programs by responding in a timely fashion to partners concerns and/or requests, gift/donation acknowledgments, program information, and stewardship.\n\u2022 Accountable for the successful delivery of complex projects through the effective management of solution design/development, project plans, resources, and stakeholder engagement.\n\u2022 Convert business objectives into achievable project plans, milestones, and deliverables.\n\u2022 Implements effective frameworks and processes to maintain appropriate operational and organizational support throughout solution lifecycle.\n\u2022 Provide effective/timely communication of project planning, status, issues, risks, and financials to key internal and external stakeholders.\n\u2022 Provide leadership that fosters participant equity and inclusiveness in project development and implementation.\n\u2022 Interact with senior and executive level management (as needed) regarding project, expected business outcome, contract/engagement administration.\n\u2022 Enforce delivery excellence and compliance while managing the quality and timeliness to deliver on time, within budget, meet revenue/margin targets and meet contractual obligations.\n\nSalary Range:\n\nThis position's salary range is $70,000 - $75,000. Final offer amounts and levels are determined by multiple factors, including your experience, and may vary from the amounts listed above.\n\nTravel Percentage: 15%\n\nWhat we are looking for:\n\u2022 Bachelor\u2019s Degree required.\n\u2022 5+ years of experience in project management or similar roles required.\n\u2022 Ability to work across a wide variety of platforms including, Salesforce, digital, social platforms, and client specific applications.\n\u2022 Demonstrated ability to effectively manage competing priorities and multiple tasks simultaneously.\n\u2022 Extensive experience managing external vendors and working with finance on contract management.\n\u2022 Strong written/verbal communication, presentation, and listening skills, with the ability to present complex information in a clear and concise manner to a variety of audience.\n\u2022 Strong collaborator with demonstrated success leading diverse, cross-functional teams and fostering a results-focused culture.\n\u2022 Comprehensive understanding of project risk, financials, and functional/non-functional requirements.\n\nMDA is an Equal Opportunity/Affirmative Action employer. All qualified applicants will receive consideration for employment without regard to race, color, religion, sex, national origin, disability, or protected veteran status.\n\nMDA Benefits:\n\u2022 For fulltime employees\n\u2022 Medical, Dental and Vision insurance with prescription coverage\n\u2022 Health Savings Account with contribution matching and Flexible Spending Accounts for medical and/or dependent care\n\u2022 Paid sick leave\n\u2022 Employee Assistance Program (EAP)\n\u2022 100% contribution towards basic life insurance, short-term and long-term disability\n\u2022 Optional additional life insurance and dependent life insurance available\n\u2022 403(b) Retirement Savings Plan with company match\n\u2022 Generous paid time off policy, with increasing accrual rate schedule\n\u2022 16 paid holidays\n\u2022 Standard 35-hour work week with flexible hours\n\u2022 Remote, work from home opportunities\n\u2022 Professional Learning and Development training opportunities, including Leadership Skills\n\u2022 Company sponsored Wellness Program", "job_is_remote": true, "job_posted_at_timestamp": 1708542485, "job_posted_at_datetime_utc": "2024-02-21T19:08:05.000Z", "job_city": null, "job_state": null, "job_country": "US", "job_latitude": 37.09024, "job_longitude": -95.71289, "job_benefits": ["health_insurance", "dental_coverage", "paid_time_off", "retirement_savings"], "job_google_link": "https://www.google.com/search?gl=us&hl=en&rciv=jb&q=director+of+brand+partnerships&start=70&ibp=htl;jobs#fpstate=tldetail&htivrt=jobs&htiq=director+of+brand+partnerships&htidocid=HmnWzkVDUAqLHqogAAAAAA%3D%3D", "job_offer_expiration_datetime_utc": "2024-03-22T19:08:05.000Z", "job_offer_expiration_timestamp": 1711134485, "job_required_experience": {"no_experience_required": false, "required_experience_in_months": null, "experience_mentioned": true, "experience_preferred": false}, "job_required_skills": null, "job_required_education": {"postgraduate_degree": false, "professional_certification": false, "high_school": false, "associates_degree": false, "bachelors_degree": true, "degree_mentioned": true, "degree_preferred": false, "professional_certification_mentioned": false}, "job_experience_in_place_of_education": false, "job_min_salary": null, "job_max_salary": null, "job_salary_currency": null, "job_salary_period": null, "job_highlights": {"Qualifications": ["Bachelor\u2019s Degree required", "5+ years of experience in project management or similar roles required", "Ability to work across a wide variety of platforms including, Salesforce, digital, social platforms, and client specific applications", "Demonstrated ability to effectively manage competing priorities and multiple tasks simultaneously", "Extensive experience managing external vendors and working with finance on contract management", "Strong written/verbal communication, presentation, and listening skills, with the ability to present complex information in a clear and concise manner to a variety of audience", "Strong collaborator with demonstrated success leading diverse, cross-functional teams and fostering a results-focused culture", "Comprehensive understanding of project risk, financials, and functional/non-functional requirements"], "Responsibilities": ["T he Community Partnerships Department is responsible for planning and executing fundraising events throughout the United States and Puerto Rico", "Through community and corporate-led events such as golf tournaments, galas, walks, DIY, and MDA-supported events, the team\u2019s overarching goal is to raise critical funds in a cost-effective manner", "This is done by adhering to event best practices, operational efficiencies, and creative integration of volunteers into every aspect of fundraising", "The Project Director, Community Partnerships is accountable for implementing complex and diverse projects and cross-division programs working with key internal and external stakeholders to ensure each assigned event, project and programs are delivered with excellence to meet or exceed client expectation", "This role manages workstreams and develop comprehensive project plans to ensure initiatives are delivered on time, in scope, and on budget and responsible for the day-to-day execution of their clients' campaigns", "This individual partners with leadership to deliver high-quality solutions, evaluate business needs, develop functional and any related requirements, and implement project plans to achieve results from conception through completion of the full life cycle", "The Project Director, Community Partnerships works and manages signature event(s) that fall within the business unit", "This includes events logistics, marketing strategies, committee communication & development, budget management, and sponsorship solicitation and management", "This position develops new relationships with key industry partners to further the success of the business unit", "Collaborate with Signature Events and P2P teams in expanding committees through various events", "Responsibilities to include, but not limited to, researching individuals who have the profile to make a successful committee member, building a pipeline for events (2 to 3 per year) where committee growth is needed and setting up meetings to introduce the opportunity", "Recruit, steward and manage auction committees for events where applicable", "Responsibilities to include, but not limited to, individual and group meetings with those committee members who solely support the auction by providing support, resources, and overall management of the auction", "Partner with the departments within the Community Partnerships business unit to help create efficiencies that drive productivity and results", "Foster a positive, ongoing, and enduring relationship with new and current partners and program supporters by, in part, maintaining contact and proactively educating partners/supporters on MDA\u2019s mission outcomes", "Maintain and refine as needed as comprehensive partners relations plan to support MDA\u2019s community-based fundraising programs by responding in a timely fashion to partners concerns and/or requests, gift/donation acknowledgments, program information, and stewardship", "Accountable for the successful delivery of complex projects through the effective management of solution design/development, project plans, resources, and stakeholder engagement", "Convert business objectives into achievable project plans, milestones, and deliverables", "Implements effective frameworks and processes to maintain appropriate operational and organizational support throughout solution lifecycle", "Provide effective/timely communication of project planning, status, issues, risks, and financials to key internal and external stakeholders", "Provide leadership that fosters participant equity and inclusiveness in project development and implementation", "Interact with senior and executive level management (as needed) regarding project, expected business outcome, contract/engagement administration", "Enforce delivery excellence and compliance while managing the quality and timeliness to deliver on time, within budget, meet revenue/margin targets and meet contractual obligations"], "Benefits": ["This position's salary range is $70,000 - $75,000", "Final offer amounts and levels are determined by multiple factors, including your experience, and may vary from the amounts listed above", "Travel Percentage: 15%", "For fulltime employees", "Medical, Dental and Vision insurance with prescription coverage", "Health Savings Account with contribution matching and Flexible Spending Accounts for medical and/or dependent care", "Paid sick leave", "Employee Assistance Program (EAP)", "100% contribution towards basic life insurance, short-term and long-term disability", "Optional additional life insurance and dependent life insurance available", "403(b) Retirement Savings Plan with company match", "Generous paid time off policy, with increasing accrual rate schedule", "16 paid holidays", "Standard 35-hour work week with flexible hours", "Remote, work from home opportunities", "Professional Learning and Development training opportunities, including Leadership Skills", "Company sponsored Wellness Program"]}, "job_job_title": "Project director", "job_posting_language": "en", "job_onet_soc": "11919900", "job_onet_job_zone": "4", "job_naics_code": "62", "job_naics_name": "Health Care"}