{"job_id": "awOu6fRUV5z4l6LuAAAAAA==", "employer_name": "PlayVS", "employer_logo": null, "employer_website": "http://www.playvs.com", "employer_company_type": null, "job_publisher": "Lever", "job_employment_type": "FULLTIME", "job_title": "Senior Director of Sponsorship Sales", "job_apply_link": "https://jobs.lever.co/playvs/afd77adc-e5a5-45c7-9c05-452d583c72e0", "job_apply_is_direct": false, "job_apply_quality_score": 0.7455, "apply_options": [{"publisher": "Lever", "apply_link": "https://jobs.lever.co/playvs/afd77adc-e5a5-45c7-9c05-452d583c72e0", "is_direct": false}, {"publisher": "SportsTech Jobs", "apply_link": "https://sportstechjobs.com/senior-director-of-sponsorship-sales-playvs/658829bdb67f590d3d493d99", "is_direct": false}], "job_description": "PlayVS is the leading amateur esports platform in North America. We are the single community where players come together to compete, fans gather to spectate, and coaches manage their programs. We offer an incredible, full-stack esport platform\u2014game integrations, team-building tools, leagues, tournaments, and schedules\u2014and our software products tie everything together into a cohesive experience.\n\nAs the Senior Director of Sponsorship Sales, you'll be a driving force behind our revenue generation through strategic partnerships with leading brands. You'll work directly with the VP of Sponsorships to help set the vision, develop winning strategies, and secure deals that propel PlayVS to the forefront of the amateur esports landscape.\n\nHere's What You'll Get To Do:\n\u2022 Sponsorship Strategy: Partner with the VP of Sponsorships and C-level executives to help develop and execute a comprehensive sponsorship strategy aligned with our PlayVS\u2019 OKRs and vision. Identify new market opportunities and build relationships with key decision-makers at target companies.\n\u2022 Prospect Identification and Qualification: Proactively research and identify potential corporate sponsors who align with our brand, values, and target audience. Develop a deep understanding of their marketing objectives and tailor partnership proposals accordingly.\n\u2022 Proposal Development and Negotiation: Craft compelling and data-driven sponsorship proposals that showcase the unique value proposition of partnering with PlayVS. Negotiate win-win agreements that secure optimal revenue and mutual benefit.\n\u2022 Financial Performance and Reporting: Track key performance indicators (KPIs) related to sponsorship activity, analyze data to measure campaign effectiveness, and generate insightful reports for internal stakeholders, including the PlayVS Leadership team.\n\u2022 Industry Expertise: Stay ahead of the curve in the evolving esports landscape and emerging trends in corporate sponsorship. Continuously identify new and innovative ways to leverage our platform for sponsor benefit.\n\u2022 Cross-functional Alignment: Work cross-functionally with leaders across Scholastic, Customer Experience, Product, Live Operations, and Marketing teams to foster internal alignment and provide a robust experience for sponsors.\n\nHere's What We're Looking For:\n\u2022 BA/BS degree or equivalent.\n\u2022 10+ years of experience in B2B sales or sponsorship, with a proven track record of success in a fast-paced environment.\n\u2022 Excellent communication, presentation, and negotiation skills, with the ability to tailor messaging to different audiences.\n\u2022 Data-driven decision-making skills and experience with analyzing complex data sets.\n\u2022 Excellent ability to identify, cultivate, and close sponsorship deals.\n\u2022 Expert ability to manage complex projects with input from cross-functional teams and company leaders.\n\nBonus points for:\n\u2022 Passion for esports and a genuine interest in supporting the growth of amateur players.\n\u2022 Esports and gaming industry experience.\n\n$175,000 - $195,000 a year\nPlayVS is proud to be a remote-first company where employees can work almost anywhere within the United States. We have a simple and transparent remote-first level-based compensation structure. The salary range for this full-time remote position is $175,000 - $195,000, plus a very competitive variable compensation, equity, and comprehensive benefits. Compensation details listed in this posting reflect the base salary only and do not include bonus, equity, or sales incentives, if applicable. Our salary ranges are determined by role and level. The range displayed on each job posting reflects the minimum and maximum target for new hire base salaries for the position across all US locations. Within the range, individual pay is determined by several factors, including job-related skills, experience, and relevant education or training.\n\nPlayVS cares about you and your overall well-being, and that\u2019s why we offer a comprehensive benefits package for full-time employees that includes but is not limited to the following:\n\u2022 healthcare benefits (medical, dental, vision),\n\u2022 401(k) plan,\n\u2022 wellbeing benefits (including Headspace, Omada, and Gympass),\n\u2022 flexible paid time off,\n\u2022 volunteer time off,\n\u2022 paid parental leave,\n\u2022 several paid holidays,\n\u2022 learning and development programs (including Liinkedin Learning and Mineral memberships),\n\u2022 monthly mobile, wellness, and internet stipends!\n\nPlayVS is an equal opportunity employer and is proud to be a majority minority company. We provide equal employment opportunities and are committed to maintaining an inclusive environment for our customers, employees, and applicants. We prohibit discrimination and harassment of any type regardless of race, color, religion, age, sex (including pregnancy and gender identity), national origin, disability status, genetics, protected veteran status, sexual orientation, gender identity or expression, parental status, or any other characteristic protected by federal, state or local laws.\n\nIf you have a disability or special need that requires an accommodation, please contact us at accommodations@playvs.com", "job_is_remote": false, "job_posted_at_timestamp": 1703203200, "job_posted_at_datetime_utc": "2023-12-22T00:00:00.000Z", "job_city": "Los Angeles", "job_state": "CA", "job_country": "US", "job_latitude": 34.03352, "job_longitude": -118.44687, "job_benefits": ["dental_coverage", "paid_time_off", "health_insurance", "retirement_savings"], "job_google_link": "https://www.google.com/search?gl=us&hl=en&rciv=jb&q=sponsorship+sales+director&start=0&ibp=htl;jobs#fpstate=tldetail&htivrt=jobs&htiq=sponsorship+sales+director&htidocid=awOu6fRUV5z4l6LuAAAAAA%3D%3D", "job_offer_expiration_datetime_utc": null, "job_offer_expiration_timestamp": null, "job_required_experience": {"no_experience_required": false, "required_experience_in_months": 120, "experience_mentioned": true, "experience_preferred": false}, "job_required_skills": null, "job_required_education": {"postgraduate_degree": false, "professional_certification": false, "high_school": false, "associates_degree": false, "bachelors_degree": false, "degree_mentioned": true, "degree_preferred": true, "professional_certification_mentioned": false}, "job_experience_in_place_of_education": false, "job_min_salary": null, "job_max_salary": null, "job_salary_currency": null, "job_salary_period": null, "job_highlights": {"Qualifications": ["BA/BS degree or equivalent", "10+ years of experience in B2B sales or sponsorship, with a proven track record of success in a fast-paced environment", "Excellent communication, presentation, and negotiation skills, with the ability to tailor messaging to different audiences", "Data-driven decision-making skills and experience with analyzing complex data sets", "Excellent ability to identify, cultivate, and close sponsorship deals", "Expert ability to manage complex projects with input from cross-functional teams and company leaders", "Esports and gaming industry experience"], "Responsibilities": ["You'll work directly with the VP of Sponsorships to help set the vision, develop winning strategies, and secure deals that propel PlayVS to the forefront of the amateur esports landscape", "Sponsorship Strategy: Partner with the VP of Sponsorships and C-level executives to help develop and execute a comprehensive sponsorship strategy aligned with our PlayVS\u2019 OKRs and vision", "Prospect Identification and Qualification: Proactively research and identify potential corporate sponsors who align with our brand, values, and target audience", "Develop a deep understanding of their marketing objectives and tailor partnership proposals accordingly", "Proposal Development and Negotiation: Craft compelling and data-driven sponsorship proposals that showcase the unique value proposition of partnering with PlayVS"], "Benefits": ["$175,000 - $195,000 a year", "The salary range for this full-time remote position is $175,000 - $195,000, plus a very competitive variable compensation, equity, and comprehensive benefits", "Compensation details listed in this posting reflect the base salary only and do not include bonus, equity, or sales incentives, if applicable", "Our salary ranges are determined by role and level", "PlayVS cares about you and your overall well-being, and that\u2019s why we offer a comprehensive benefits package for full-time employees that includes but is not limited to the following:", "healthcare benefits (medical, dental, vision),", "401(k) plan,", "wellbeing benefits (including Headspace, Omada, and Gympass),", "flexible paid time off,", "volunteer time off,", "paid parental leave,", "several paid holidays,", "learning and development programs (including Liinkedin Learning and Mineral memberships),", "monthly mobile, wellness, and internet stipends!"]}, "job_job_title": "Senior", "job_posting_language": "en", "job_onet_soc": "11202200", "job_onet_job_zone": "4"}