{"job_id": "59NSyOzYpJHG1kr-AAAAAA==", "employer_name": "Multiplier", "employer_logo": "https://encrypted-tbn0.gstatic.com/images?q=tbn:ANd9GcTZ3-96_WCpmN7vQzGWB3SHuoqGBclolfhGISby&s=0", "employer_website": null, "employer_company_type": null, "job_publisher": "Talent.com", "job_employment_type": "FULLTIME", "job_title": "Sr sales manager", "job_apply_link": "https://www.talent.com/view?id=ef14fc8b68d9", "job_apply_is_direct": false, "job_apply_quality_score": 0.5004, "apply_options": [{"publisher": "Talent.com", "apply_link": "https://www.talent.com/view?id=ef14fc8b68d9", "is_direct": false}], "job_description": "Sr Sales Manager / Director, NAMER\n\nNew York\n\nA BIT ABOUT US\n\nWe're at the forefront of one of the most exciting evolutions of our generation - remote staffing. No longer do employers have to hire according to geography, and no longer do employees have to worry about proximity to work and daily commutes.\n\nToday, companies can hire the best talent they can find, anywhere in the world. But they need digital solutions to help them streamline the process...\n\nWe are Multiplier! Our global employment platform empowers companies to hire people all across the world by managing the complexities of local compliance, labor contracts, payroll, benefits and taxes - all from one software system. It's a game changer!\n\nWe're on a mission to impact economies of scale by enabling companies to hire the best candidate for the job, regardless of location.\n\nWe're backed by some of the best in the game (Sequoia and Tiger Global), led by domain level experts, growing, and seeking brilliant like minded enthusiasts to join our team.\n\nA BIT ABOUT THE OPPORTUNITY\n\nWe're building a world class sales org to help us get there. Our Regional Sales leaders are responsible for helping us build world class sales teams, processes, and to deliver on ambitious revenue targets.\n\nWe're seeking a proven commercial leader, who knows how to build a culture of over-achievers predicted on discipline and execution.\n\nThis role will report directly into our CRO, and work closely with peers and cross functional stakeholders. Process, efficiency, and tenacity will be critical to your success in this role.\n\nWhat you'll do :\n\u2022 Meet / exceed the revenue targets for your region.\n\u2022 Build and execute effective GTM plans and sales motions to sell up-market and maximize ROI on our salesforce.\n\u2022 Forecast accurately, and build a highly disciplined data culture within your team.\n\u2022 Consistently deliver on staffing and budgeting needs to build a successful, over-achieving sales team.\n\u2022 Coach AEs on hard and soft skills as they relate to prospecting, engagement, nurturing, closing, and scaling.\n\u2022 Maximize key sales metrics, like lead-MQL-SQL-close rates, ACV, and time to value.\n\u2022 Help build career plans for your staff, and maximize retention of top talent.\n\u2022 Help us build a predictable, repeatable, and scalable sales engine.\n\u2022 Provide access to a rolodex of high value prospects through your personal and professional network.\n\u2022 Deliver on quarterly OKRs, with a laser focus on data.\n\nWhat you'll bring :\n\u2022 Min 5 years in sales management (at least 3 in b2b SaaS / HR Tech), with a track record of achieving quota at least 2 of the past 3 years.\n\u2022 Obsession over data and analytics, and the expressed ability to convert to actionable insights.\n\u2022 Change management experience, a steady hand and resilience in the face of organizational change.\n\u2022 The ability to work independently, problem solve proactively, and collaborate effectively.\n\u2022 Excellent leadership, communication and presentation skills.\n\u2022 A process oriented approach to sales.\n\u2022 Work ethic beyond the norm, and a commitment to excellence as a leader.\n\nWhat we'll provide for you :\n\u2022 Ability to contribute to this business at a high level.\n\u2022 Autonomy within your role.\n\u2022 Ability to work fully-remotely.\n\u2022 Working with a compassionate, energetic, inspired, ambitious, global, and diverse team.\n\u2022 Opportunity to grow within a fast-growth business.\n\u2022 Competitive benefits, compensation, and culture of recognition.\n\u2022 Generous holiday policy.\n\u2022 A commitment to positively impact your career.\n\nA BIT ABOUT YOU\n\nYou're a company builder, not just a sales leader. You absolutely love working with a unique and inspired workforce, and being part of a dispersed team.\n\nStartups excite you because you covet the opportunity to contribute to building something special, early on. You understand the art and science of sales, have been successful as an outbound sales rep yourself, and use systems and mathematics to succeed.\n\nYou've been successful in management, and relish the opportunity to grow. You're progressively minded, creative, accountable, and quirky in your own way.\n\nIf this sounds like you, we'd love to hear from you.\n\nTHANK YOU!\n\nLast updated : 2024-03-07", "job_is_remote": false, "job_posted_at_timestamp": 1709769600, "job_posted_at_datetime_utc": "2024-03-07T00:00:00.000Z", "job_city": "Philadelphia", "job_state": "PA", "job_country": "US", "job_latitude": 39.952583, "job_longitude": -75.16522, "job_benefits": null, "job_google_link": "https://www.google.com/search?gl=us&hl=en&rciv=jb&q=senior+sales+director&start=40&ibp=htl;jobs#fpstate=tldetail&htivrt=jobs&htiq=senior+sales+director&htidocid=59NSyOzYpJHG1kr-AAAAAA%3D%3D", "job_offer_expiration_datetime_utc": "2024-06-30T00:00:00.000Z", "job_offer_expiration_timestamp": 1719705600, "job_required_experience": {"no_experience_required": false, "required_experience_in_months": null, "experience_mentioned": true, "experience_preferred": false}, "job_required_skills": null, "job_required_education": {"postgraduate_degree": false, "professional_certification": false, "high_school": false, "associates_degree": false, "bachelors_degree": false, "degree_mentioned": false, "degree_preferred": false, "professional_certification_mentioned": false}, "job_experience_in_place_of_education": false, "job_min_salary": null, "job_max_salary": null, "job_salary_currency": null, "job_salary_period": null, "job_highlights": {"Qualifications": ["Min 5 years in sales management (at least 3 in b2b SaaS / HR Tech), with a track record of achieving quota at least 2 of the past 3 years", "Obsession over data and analytics, and the expressed ability to convert to actionable insights", "Change management experience, a steady hand and resilience in the face of organizational change", "The ability to work independently, problem solve proactively, and collaborate effectively", "Excellent leadership, communication and presentation skills", "A process oriented approach to sales", "Work ethic beyond the norm, and a commitment to excellence as a leader", "Ability to work fully-remotely", "Working with a compassionate, energetic, inspired, ambitious, global, and diverse team", "You understand the art and science of sales, have been successful as an outbound sales rep yourself, and use systems and mathematics to succeed", "You've been successful in management, and relish the opportunity to grow", "You're progressively minded, creative, accountable, and quirky in your own way"], "Responsibilities": ["This role will report directly into our CRO, and work closely with peers and cross functional stakeholders", "Process, efficiency, and tenacity will be critical to your success in this role", "Meet / exceed the revenue targets for your region", "Build and execute effective GTM plans and sales motions to sell up-market and maximize ROI on our salesforce", "Forecast accurately, and build a highly disciplined data culture within your team", "Consistently deliver on staffing and budgeting needs to build a successful, over-achieving sales team", "Coach AEs on hard and soft skills as they relate to prospecting, engagement, nurturing, closing, and scaling", "Maximize key sales metrics, like lead-MQL-SQL-close rates, ACV, and time to value", "Help build career plans for your staff, and maximize retention of top talent", "Help us build a predictable, repeatable, and scalable sales engine", "Provide access to a rolodex of high value prospects through your personal and professional network", "Deliver on quarterly OKRs, with a laser focus on data"], "Benefits": ["Ability to contribute to this business at a high level", "Competitive benefits, compensation, and culture of recognition", "Generous holiday policy", "A commitment to positively impact your career"]}, "job_job_title": "Sales manager", "job_posting_language": "en", "job_onet_soc": "11202200", "job_onet_job_zone": "4", "job_occupational_categories": ["11-2022.00"]}