{"job_id": "xOyWwTVmWQsFG3iCAAAAAA==", "employer_name": "Pinnacle Search Partners", "employer_logo": "https://encrypted-tbn0.gstatic.com/images?q=tbn:ANd9GcR2zCvnowlw3RSEzFNW6WP-7Kz9bIJgfhdKYyZN&s=0", "employer_website": null, "employer_company_type": null, "job_publisher": "LinkedIn", "job_employment_type": "FULLTIME", "job_title": "Business Development Manager", "job_apply_link": "https://www.linkedin.com/jobs/view/business-development-manager-at-pinnacle-search-partners-3831109013", "job_apply_is_direct": false, "job_apply_quality_score": 0.7414, "apply_options": [{"publisher": "LinkedIn", "apply_link": "https://www.linkedin.com/jobs/view/business-development-manager-at-pinnacle-search-partners-3831109013", "is_direct": false}, {"publisher": "Jobright AI", "apply_link": "https://jobright.ai/jobs/info/65d4e0f9145e01b03a154e6e", "is_direct": false}], "job_description": "Our client, a leading Commercial and Residential Remediation provider is seeking a Houston-based Business Development Manager. The ideal candidate will lead initiatives to generate and engage with business partners to build new business for the company. This candidate will be focused and have strong communication skills. They should be able to think critically when making plans and have a demonstrated ability to execute a particular strategy.\n\nThe ideal candidate will have experience calling into the Commercial Real Estate industry: Property Owners, Property Managers, Building Maintenance Engineers, and Commercial Property Adjustors.\n\nResponsibilities\n\u2022 Identify partnership opportunities within the Commercial Real Estate industry: Property Owners, Property Managers, Building Maintenance Engineers, and Commercial Property Adjustors.\n\u2022 Develop new relationships to grow business and help the company expand\n\u2022 Maintain existing business\n\u2022 Think critically when planning to ensure project success\n\nMarket Research and Analysis\n\n\u2022 Conduct thorough market research to identify potential clients, industry trends, and emerging\n\nopportunities.\n\n\u2022 Analyze competitors and market conditions to develop informed business development\n\nstrategies.\n\n\u2022 Activity to generate new business accounts including making sales calls and cold calls.\n\nClient Relationship Management\n\n\u2022 Identifying prospective customers, following up on sales leads, branding at trade shows and\n\nindustry conventions, annual sales plan, and weekly reporting of all determined KPI\u2019s/Metrics.\n\n\u2022 Build and maintain strong relationships with existing clients, understanding their needs, and\n\nensuring satisfaction.\n\n\u2022 Identify opportunities for upselling or expanding services to existing clients.\n\nNetworking\n\n\u2022 Attend industry events, conferences, and networking functions to build a strong professional\n\nnetwork.\n\n\u2022 Represent the company and actively engage with potential clients, partners, and industry\n\nparticipants.\n\n\u2022 Proactively identify and pursue new business opportunities through lead generation and\n\nprospecting activities.\n\n\u2022 Collaborate with marketing and other professionals to coordinate brand awareness and\n\nmarketing efforts.\n\nQualifications\n\u2022 Bachelor's degree or equivalent experience\n\u2022 3 + years' prior industry-related business development experience preferably in the Construction or Commercial Real Estate industry\n\u2022 Strong communication and interpersonal skills\n\u2022 Proven knowledge and execution of successful development strategies\n\u2022 Focused and goal-oriented", "job_is_remote": false, "job_posted_at_timestamp": 1710169516, "job_posted_at_datetime_utc": "2024-03-11T15:05:16.000Z", "job_city": "Houston", "job_state": "TX", "job_country": "US", "job_latitude": 29.760427, "job_longitude": -95.369804, "job_benefits": null, "job_google_link": "https://www.google.com/search?gl=us&hl=en&rciv=jb&q=manager+of+brand+partnerships&start=80&ibp=htl;jobs#fpstate=tldetail&htivrt=jobs&htiq=manager+of+brand+partnerships&htidocid=xOyWwTVmWQsFG3iCAAAAAA%3D%3D", "job_offer_expiration_datetime_utc": "2024-04-20T15:10:06.000Z", "job_offer_expiration_timestamp": 1713625806, "job_required_experience": {"no_experience_required": false, "required_experience_in_months": 36, "experience_mentioned": true, "experience_preferred": false}, "job_required_skills": null, "job_required_education": {"postgraduate_degree": false, "professional_certification": false, "high_school": false, "associates_degree": false, "bachelors_degree": true, "degree_mentioned": true, "degree_preferred": false, "professional_certification_mentioned": false}, "job_experience_in_place_of_education": false, "job_min_salary": null, "job_max_salary": null, "job_salary_currency": null, "job_salary_period": null, "job_highlights": {"Qualifications": ["They should be able to think critically when making plans and have a demonstrated ability to execute a particular strategy", "The ideal candidate will have experience calling into the Commercial Real Estate industry: Property Owners, Property Managers, Building Maintenance Engineers, and Commercial Property Adjustors", "Bachelor's degree or equivalent experience", "3 + years' prior industry-related business development experience preferably in the Construction or Commercial Real Estate industry", "Strong communication and interpersonal skills", "Proven knowledge and execution of successful development strategies", "Focused and goal-oriented"], "Responsibilities": ["The ideal candidate will lead initiatives to generate and engage with business partners to build new business for the company", "This candidate will be focused and have strong communication skills", "Identify partnership opportunities within the Commercial Real Estate industry: Property Owners, Property Managers, Building Maintenance Engineers, and Commercial Property Adjustors", "Develop new relationships to grow business and help the company expand", "Maintain existing business", "Think critically when planning to ensure project success", "Conduct thorough market research to identify potential clients, industry trends, and emerging", "Analyze competitors and market conditions to develop informed business development", "Activity to generate new business accounts including making sales calls and cold calls", "Client Relationship Management", "Identifying prospective customers, following up on sales leads, branding at trade shows and", "industry conventions, annual sales plan, and weekly reporting of all determined KPI\u2019s/Metrics", "Build and maintain strong relationships with existing clients, understanding their needs, and", "ensuring satisfaction", "Identify opportunities for upselling or expanding services to existing clients", "Attend industry events, conferences, and networking functions to build a strong professional", "Represent the company and actively engage with potential clients, partners, and industry", "Proactively identify and pursue new business opportunities through lead generation and", "Collaborate with marketing and other professionals to coordinate brand awareness and"]}, "job_job_title": "Development manager", "job_posting_language": "en", "job_onet_soc": "11202100", "job_onet_job_zone": "4"}