{"job_id": "PlDjFEqzh2o_kqF4AAAAAA==", "employer_name": "Global Lending Services", "employer_logo": null, "employer_website": "http://www.glsauto.com", "employer_company_type": null, "job_publisher": "Lever", "job_employment_type": "FULLTIME", "job_title": "Regional Sales Director (Midwest)", "job_apply_link": "https://jobs.lever.co/glsllc/9bae1c25-f279-4cb5-88c6-e8f70ed08341", "job_apply_is_direct": false, "job_apply_quality_score": 0.7577, "apply_options": [{"publisher": "Lever", "apply_link": "https://jobs.lever.co/glsllc/9bae1c25-f279-4cb5-88c6-e8f70ed08341", "is_direct": false}], "job_description": "Why GLS?\n\nPurpose: Access to affordable, reliable transportation is essential to leading productive work and personal lives, caring well for oneself, one\u2019s family, and the needs of others. Through advanced analytics and technology, we can more accurately predict credit risk and provide more people with an affordable auto financing option for their next vehicle. That\u2019s what GLS has done for over 10 years, helping more than half a million families meet and improve their transportation needs.\n\nPeople: Join a culture of over 1,000 employees who Care Deeply and Think Boldly, driving innovation in an adaptive and positive culture that celebrates successes. We empower and reward individuals and teams who make direct, positive impacts to the business and each other, who take pride in their work and are ever-raising the bar.\n\nGrowth: Recognized by Inc 5000 as one of the fastest-growing private companies in America. Join GLS to grow with us!\n\nBenefits: GLS offers the below great benefits for your amazing work!\n\no Competitive base pay and performance bonuses, dependent on role\n\no Medical, dental, vision, telemedicine, supplemental insurance benefits, long-term and short-term disability\n\no 401K with employer match and 100% immediate vesting\n\no Paid Time Off (PTO) and paid company holidays to help you balance work and personal life\n\no Paid Volunteer Time Off (VTO) Annually\n\no Tuition Reimbursement\n\no Parental Leave\n\no Business casual work environment\n\nWhat does it mean to be a Regional Sales Director with GLS?\n\nAs a Regional Sales Director in the Midwest region with Global Lending Services, you are responsible for increasing sales in the designated region (includes CO, IA, KS, MN, MO, MT, ND, NE, SD, UT, WY) through the development, support, and coaching of our Area Sales Managers and Independent Sales Agents to position the organization as a leading supplier of high-quality auto financing.\n\nHow will you drive value within the organization as a Regional Sales Director?\n\u2022 Establish key business initiatives with measurable goals and milestones that support the overall region and company strategy\n\u2022 Make new dealer visits or cold calls and take inbound calls from dealerships to build relationships and capture business\n\u2022 Recruit and train new Area Sales Managers\n\u2022 Introduce new and acquired businesses to company procedures and appropriate personnel for related services\n\u2022 Establish goals for Area Sales Managers; provide coaching and support towards goal obtainment and hold him/her accountable for results\n\u2022 Communicate expectations and hold Area Sales Managers accountable for meeting financial goals and performance metrics \u2013 all while maintaining a high level of morale\n\u2022 Perform these same functions with GLS Agency partners in terms of coaching, servicing and support\n\u2022 Maintain electronic records and files\n\u2022 Foster a collaborative culture that facilitates the achievement of business plan objectives by working closely with other associates and members of management\n\u2022 Participate in special projects as needed\n\u2022 Perform additional assignments as required by the needs of the company or as directed by management\n\nWhat should you already know to be successful as a Regional Sales Director?\n\u2022 Minimum of bachelor\u2019s degree required\n\u2022 Three (3) years\u2019 experience in auto finance, preferably in sub-prime auto financing preferred\n\u2022 Five (5) years\u2019 sales experience within the auto industry preferred\n\u2022 Knowledge of the assigned territory market with existing customer relationships preferred\n\u2022 Intrinsically motivated with demonstrated ability to take initiative\n\u2022 Exceptional interpersonal skills\n\u2022 Exceptional oral and written communication skills\n\u2022 Proficient computer skills with working knowledge of internet and standard business applications such as Microsoft Office; ability to quickly learn new computer applications as required\n\u2022 Demonstrated ability to motivate and lead a team\n\u2022 Excellent organizational skills with high attention to detail and demonstrated ability to effectively set and manage multiple conflicting priorities\n\nEmployment Requirements:\n\u2022 Must be able to pass a criminal background check\n\u2022 Must possess a valid driver\u2019s license with an acceptable driving record\n\u2022 Talk and hear to exchange accurate information\n\u2022 Have close visual acuity to perform activities such as: preparing and analyzing data and figures; viewing a computer terminal; extensive reading\n\u2022 This is an exempt level position whereby business need will dictate the exact work schedule which should be expected to vary at times\n\u2022 Must have the ability to operate from a home office\n\u2022 This position does require extensive travel both in a vehicle and by air; travel is to be expected 75% of the time, with overnight travel and extended hours\n\n$95,000 - $125,000 a year\nPay structure includes base pay rate plus monthly commission\n\n2023 California Applicant Privacy Notice\n\nGLS participates in the E-Verify program to confirm the employment eligibility of all newly hired employees\n\nPlease visit www.glsauto.com for information about our great company and other amazing opportunities\n\nApplicants have rights under Federal Employment Laws\n\nFamily and Medical Leave Act (FMLA)\n\nEqual Employment Opportunity (EEO)\n\nEmployee Polygraph Protection Act (EPPA)", "job_is_remote": false, "job_posted_at_timestamp": 1703030400, "job_posted_at_datetime_utc": "2023-12-20T00:00:00.000Z", "job_city": "Salt Lake City", "job_state": "UT", "job_country": "US", "job_latitude": 40.76078, "job_longitude": -111.891045, "job_benefits": ["paid_time_off", "dental_coverage", "retirement_savings", "health_insurance"], "job_google_link": "https://www.google.com/search?gl=us&hl=en&rciv=jb&q=sales+director&start=30&ibp=htl;jobs#fpstate=tldetail&htivrt=jobs&htiq=sales+director&htidocid=PlDjFEqzh2o_kqF4AAAAAA%3D%3D", "job_offer_expiration_datetime_utc": null, "job_offer_expiration_timestamp": null, "job_required_experience": {"no_experience_required": false, "required_experience_in_months": 36, "experience_mentioned": true, "experience_preferred": true}, "job_required_skills": null, "job_required_education": {"postgraduate_degree": false, "professional_certification": false, "high_school": false, "associates_degree": false, "bachelors_degree": false, "degree_mentioned": true, "degree_preferred": false, "professional_certification_mentioned": false}, "job_experience_in_place_of_education": false, "job_min_salary": null, "job_max_salary": null, "job_salary_currency": null, "job_salary_period": null, "job_highlights": {"Qualifications": ["Minimum of bachelor\u2019s degree required", "Intrinsically motivated with demonstrated ability to take initiative", "Exceptional interpersonal skills", "Exceptional oral and written communication skills", "Proficient computer skills with working knowledge of internet and standard business applications such as Microsoft Office; ability to quickly learn new computer applications as required", "Demonstrated ability to motivate and lead a team", "Excellent organizational skills with high attention to detail and demonstrated ability to effectively set and manage multiple conflicting priorities", "Must be able to pass a criminal background check", "Must possess a valid driver\u2019s license with an acceptable driving record", "Talk and hear to exchange accurate information", "Have close visual acuity to perform activities such as: preparing and analyzing data and figures; viewing a computer terminal; extensive reading", "This is an exempt level position whereby business need will dictate the exact work schedule which should be expected to vary at times", "Must have the ability to operate from a home office", "This position does require extensive travel both in a vehicle and by air; travel is to be expected 75% of the time, with overnight travel and extended hours"], "Responsibilities": ["As a Regional Sales Director in the Midwest region with Global Lending Services, you are responsible for increasing sales in the designated region (includes CO, IA, KS, MN, MO, MT, ND, NE, SD, UT, WY) through the development, support, and coaching of our Area Sales Managers and Independent Sales Agents to position the organization as a leading supplier of high-quality auto financing", "Establish key business initiatives with measurable goals and milestones that support the overall region and company strategy", "Make new dealer visits or cold calls and take inbound calls from dealerships to build relationships and capture business", "Recruit and train new Area Sales Managers", "Introduce new and acquired businesses to company procedures and appropriate personnel for related services", "Establish goals for Area Sales Managers; provide coaching and support towards goal obtainment and hold him/her accountable for results", "Communicate expectations and hold Area Sales Managers accountable for meeting financial goals and performance metrics \u2013 all while maintaining a high level of morale", "Perform these same functions with GLS Agency partners in terms of coaching, servicing and support", "Maintain electronic records and files", "Foster a collaborative culture that facilitates the achievement of business plan objectives by working closely with other associates and members of management", "Participate in special projects as needed", "Perform additional assignments as required by the needs of the company or as directed by management"], "Benefits": ["Benefits: GLS offers the below great benefits for your amazing work!", "Competitive base pay and performance bonuses, dependent on role", "Medical, dental, vision, telemedicine, supplemental insurance benefits, long-term and short-term disability", "401K with employer match and 100% immediate vesting", "Paid Time Off (PTO) and paid company holidays to help you balance work and personal life", "Paid Volunteer Time Off (VTO) Annually", "Tuition Reimbursement", "Parental Leave", "Business casual work environment", "$95,000 - $125,000 a year", "Pay structure includes base pay rate plus monthly commission"]}, "job_job_title": "Sales director", "job_posting_language": "en", "job_onet_soc": "11202200", "job_onet_job_zone": "4"}