{"job_id": "yOejWpYSmttdFw1nAAAAAA==", "employer_name": "Cloudflare", "employer_logo": "https://images.folloze.com/image/fetch/https://www.cloudflare.com/static/b30a57477bde900ba55c0b5f98c4e524/Cloudflare_default_OG_.png", "employer_website": "http://www.cloudflare.com", "employer_company_type": "Information", "job_publisher": "LinkedIn", "job_employment_type": "FULLTIME", "job_title": "Director of Technology Partner Ecosystems", "job_apply_link": "https://www.linkedin.com/jobs/view/director-of-technology-partner-ecosystems-at-cloudflare-3850888765", "job_apply_is_direct": false, "job_apply_quality_score": 0.6259, "apply_options": [{"publisher": "LinkedIn", "apply_link": "https://www.linkedin.com/jobs/view/director-of-technology-partner-ecosystems-at-cloudflare-3850888765", "is_direct": false}, {"publisher": "Www.oe24-Info.net", "apply_link": "https://www.oe24-info.net/?refId=Kfe1dYB5Yp6M0Z5VNiVt0A%3D%3D&trackingId=T0FAFPpJvFDV0aDY6IFnYw%3D%3D&position=21&pageNum=0&trk=public_jobs_jserp-result_search-card&_=%2Fjobs%2Fview%2Fdirector-of-technology-partner-ecosystems-at-cloudflare-3850888765%23KJWqMdlUlBn8PPpbXBTujI7xcY8uGFCs", "is_direct": false}], "job_description": "About Us\n\nAt Cloudflare, we have our eyes set on an ambitious goal: to help build a better Internet. Today the company runs one of the world\u2019s largest networks that powers approximately 25 million Internet properties, for customers ranging from individual bloggers to SMBs to Fortune 500 companies. Cloudflare protects and accelerates any Internet application online without adding hardware, installing software, or changing a line of code. Internet properties powered by Cloudflare all have web traffic routed through its intelligent global network, which gets smarter with every request. As a result, they see significant improvement in performance and a decrease in spam and other attacks. Cloudflare was named to Entrepreneur Magazine\u2019s Top Company Cultures list and ranked among the World\u2019s Most Innovative Companies by Fast Company.\n\nWe realize people do not fit into neat boxes. We are looking for curious and empathetic individuals who are committed to developing themselves and learning new skills, and we are ready to help you do that. We cannot complete our mission without building a diverse and inclusive team. We hire the best people based on an evaluation of their potential and support them throughout their time at Cloudflare. Come join us!\n\nAvailable Locations: US Remote\n\nAbout The Department\n\nCloudflare\u2019s Special Projects team oversees a wide range of strategic and technical partnership projects that are critical to the operations and long-term development of Cloudflare. The Special Projects team works closely with Product and Engineering to bring new and innovative ideas to life. These range from launching cutting edge consumer privacy protection services, innovative channel partnerships, unique distribution deals, and developing new products and technologies. Overall, we look for a technically minded, big-picture thinker who can build strong relationships, grow strategic partner opportunities, and drive Cloudflare\u2019s business strategy and development globally.\n\nWhat You'll Do\n\nFor this role, we are seeking an experienced technology partner manager/director to lead our partner ecosystems and product integrations at Cloudflare. We are building a thriving ecosystem of partners that improve the value of our products and help partners grow their business with Cloudflare. This role offers an incredible opportunity to make a significant contribution to a high growth company in a rapidly changing space. You will lead all efforts to qualify and build meaningful product integrations, build better together stories to co-market and take those winning solutions into the channel to co-sell with industry leading companies. You will work hand in hand with product, marketing, sales and channel alliances to continue building out our technology partner ecosystems at Cloudflare. This will include managing the technical relationships with existing partners and marketplaces as well as all new partnership evaluations and go to market strategies across Cloudflare\u2019s expanding product portfolio.\n\u2022 Working with Product teams and sales to prioritize partner integrations and channel opportunities.\n\u2022 Managing existing technology partners and coming up with new partnership ideas, defining joint integrations/solutions, and driving GTM activities across the org.\n\u2022 Developing, negotiating, and closing agreements with new partners and systematically scaling the go-to market motion with technology partners.\n\u2022 Increasing awareness about tech partnerships with customers and prospects, and soliciting feedback from to improve and solve any issues with the integrations.\n\u2022 Enabling GTM functions at Cloudflare, such as direct sales, channel, marketing etc., about how these integrations operate and how they can leverage tech partners to drive more leads and joint sales.\n\u2022 Managing partner relationships throughout the lifecycle \u2014 from maintaining existing relationships with partners and adding new initiatives with established partners.\n\nRequirements\n\u2022 10+ years of experience, in a combination of technology partner management, partnerships, or go-to-market roles.\n\u2022 Ideal candidate has been managing technology partnerships for or with leading cyber security companies for the last 5+ years.\n\u2022 Track record of successful commercial execution of partner or GTM programs through joint go-to-market activities & cross-functional work across various internal teams.\n\u2022 Director level candidates must be very technical minded. Bachelor\u2019s degree in a technical/engineering field, or specific technical experience required.\n\u2022 Experience in the Cloud (SaaS/PaaS/IaaS) and Security (DDoS, firewalls) ecosystems preferred.\n\u2022 Ability to lead a cross functional team as well as direct reports in a fast paced environment.\n\u2022 Strong interpersonal skills and experience in working cross-functionally with a variety of teams, including product, sales, and marketing teams, to establish effective partnerships.\n\u2022 The role can be remote based in the United States\n\u2022 A natural curiosity and eagerness to do whatever it takes, no task is beneath you, is a must. We are a scrappy team that works hard to accomplish ideas that others say can\u2019t be done.\n\nCompensation\n\nCompensation may be adjusted depending on work location.\n\u2022 For Colorado-based hires: Estimated annual salary of $186,000 - $228,000\n\u2022 For New York City, Washington, and California (excluding Bay Area) based hires: Estimated annual salary of $209,000 - $255,000\n\u2022 For Bay Area-based hires: Estimated annual salary of $220,000 - $268,000\n\nEquity\n\nThis role is eligible to participate in Cloudflare\u2019s equity plan.\n\nBenefits\n\nCloudflare offers a complete package of benefits and programs to support you and your family. Our benefits programs can help you pay health care expenses, support caregiving, build capital for the future and make life a little easier and fun! The below is a description of our benefits for employees in the United States, and benefits may vary for employees based outside the U.S.\n\nHealth & Welfare Benefits\n\u2022 Medical/Rx Insurance\n\u2022 Dental Insurance\n\u2022 Vision Insurance\n\u2022 Flexible Spending Accounts\n\u2022 Commuter Spending Accounts\n\u2022 Fertility & Family Forming Benefits\n\u2022 On-demand mental health support and Employee Assistance Program\n\u2022 Global Travel Medical Insurance\n\nFinancial Benefits\n\u2022 Short and Long Term Disability Insurance\n\u2022 Life & Accident Insurance\n\u2022 401(k) Retirement Savings Plan\n\u2022 Employee Stock Participation Plan\n\nTime Off\n\u2022 Flexible paid time off covering vacation and sick leave\n\u2022 Leave programs, including parental, pregnancy health, medical, and bereavement leave\n\nWhat Makes Cloudflare Special?\n\nWe\u2019re not just a highly ambitious, large-scale technology company. We\u2019re a highly ambitious, large-scale technology company with a soul. Fundamental to our mission to help build a better Internet is protecting the free and open Internet.\n\nProject Galileo : We equip politically and artistically important organizations and journalists with powerful tools to defend themselves against attacks that would otherwise censor their work, technology already used by Cloudflare\u2019s enterprise customers--at no cost.\n\nAthenian Project : We created Athenian Project to ensure that state and local governments have the highest level of protection and reliability for free, so that their constituents have access to election information and voter registration.\n\nPath Forward Partnership : Since 2016, we have partnered with Path Forward, a nonprofit organization, to create 16-week positions for mid-career professionals who want to get back to the workplace after taking time off to care for a child, parent, or loved one.\n\n1.1.1.1 : We released 1.1.1.1 to help fix the foundation of the Internet by building a faster, more secure and privacy-centric public DNS resolver. This is available publicly for everyone to use - it is the first consumer-focused service Cloudflare has ever released. Here\u2019s the deal - we don\u2019t store client IP addresses never, ever. We will continue to abide by our privacy commitment and ensure that no user data is sold to advertisers or used to target consumers.\n\nSound like something you\u2019d like to be a part of? We\u2019d love to hear from you!\n\nThis position may require access to information protected under U.S. export control laws, including the U.S. Export Administration Regulations. Please note that any offer of employment may be conditioned on your authorization to receive software or technology controlled under these U.S. export laws without sponsorship for an export license.\n\nCloudflare is proud to be an equal opportunity employer. We are committed to providing equal employment opportunity for all people and place great value in both diversity and inclusiveness. All qualified applicants will be considered for employment without regard to their, or any other person's, perceived or actual race, color, religion, sex, gender, gender identity, gender expression, sexual orientation, national origin, ancestry, citizenship, age, physical or mental disability, medical condition, family care status, or any other basis protected by law. We are an AA/Veterans/Disabled Employer.\n\nCloudflare provides reasonable accommodations to qualified individuals with disabilities. Please tell us if you require a reasonable accommodation to apply for a job. Examples of reasonable accommodations include, but are not limited to, changing the application process, providing documents in an alternate format, using a sign language interpreter, or using specialized equipment. If you require a reasonable accommodation to apply for a job, please contact us via e-mail at hr@cloudflare.com or via mail at 101 Townsend St. San Francisco, CA 94107.", "job_is_remote": false, "job_posted_at_timestamp": 1709938973, "job_posted_at_datetime_utc": "2024-03-08T23:02:53.000Z", "job_city": "Kansas City", "job_state": "MO", "job_country": "US", "job_latitude": 39.099728, "job_longitude": -94.57857, "job_benefits": ["paid_time_off", "dental_coverage", "health_insurance", "retirement_savings"], "job_google_link": "https://www.google.com/search?gl=us&hl=en&rciv=jb&q=director+of+brand+partnerships&start=80&ibp=htl;jobs#fpstate=tldetail&htivrt=jobs&htiq=director+of+brand+partnerships&htidocid=yOejWpYSmttdFw1nAAAAAA%3D%3D", "job_offer_expiration_datetime_utc": "2024-04-07T23:02:53.000Z", "job_offer_expiration_timestamp": 1712530973, "job_required_experience": {"no_experience_required": false, "required_experience_in_months": 120, "experience_mentioned": true, "experience_preferred": true}, "job_required_skills": null, "job_required_education": {"postgraduate_degree": false, "professional_certification": false, "high_school": false, "associates_degree": false, "bachelors_degree": true, "degree_mentioned": true, "degree_preferred": true, "professional_certification_mentioned": false}, "job_experience_in_place_of_education": false, "job_min_salary": null, "job_max_salary": null, "job_salary_currency": null, "job_salary_period": null, "job_highlights": {"Qualifications": ["10+ years of experience, in a combination of technology partner management, partnerships, or go-to-market roles", "Ideal candidate has been managing technology partnerships for or with leading cyber security companies for the last 5+ years", "Track record of successful commercial execution of partner or GTM programs through joint go-to-market activities & cross-functional work across various internal teams", "Director level candidates must be very technical minded", "Bachelor\u2019s degree in a technical/engineering field, or specific technical experience required", "Ability to lead a cross functional team as well as direct reports in a fast paced environment", "Strong interpersonal skills and experience in working cross-functionally with a variety of teams, including product, sales, and marketing teams, to establish effective partnerships", "The role can be remote based in the United States", "A natural curiosity and eagerness to do whatever it takes, no task is beneath you, is a must"], "Responsibilities": ["You will lead all efforts to qualify and build meaningful product integrations, build better together stories to co-market and take those winning solutions into the channel to co-sell with industry leading companies", "You will work hand in hand with product, marketing, sales and channel alliances to continue building out our technology partner ecosystems at Cloudflare", "This will include managing the technical relationships with existing partners and marketplaces as well as all new partnership evaluations and go to market strategies across Cloudflare\u2019s expanding product portfolio", "Working with Product teams and sales to prioritize partner integrations and channel opportunities", "Managing existing technology partners and coming up with new partnership ideas, defining joint integrations/solutions, and driving GTM activities across the org", "Developing, negotiating, and closing agreements with new partners and systematically scaling the go-to market motion with technology partners", "Increasing awareness about tech partnerships with customers and prospects, and soliciting feedback from to improve and solve any issues with the integrations", "Enabling GTM functions at Cloudflare, such as direct sales, channel, marketing etc., about how these integrations operate and how they can leverage tech partners to drive more leads and joint sales", "Managing partner relationships throughout the lifecycle \u2014 from maintaining existing relationships with partners and adding new initiatives with established partners"], "Benefits": ["Compensation may be adjusted depending on work location", "For Colorado-based hires: Estimated annual salary of $186,000 - $228,000", "For New York City, Washington, and California (excluding Bay Area) based hires: Estimated annual salary of $209,000 - $255,000", "For Bay Area-based hires: Estimated annual salary of $220,000 - $268,000", "This role is eligible to participate in Cloudflare\u2019s equity plan", "Cloudflare offers a complete package of benefits and programs to support you and your family", "Our benefits programs can help you pay health care expenses, support caregiving, build capital for the future and make life a little easier and fun!", "The below is a description of our benefits for employees in the United States, and benefits may vary for employees based outside the U.S", "Health & Welfare Benefits", "Medical/Rx Insurance", "Dental Insurance", "Vision Insurance", "Flexible Spending Accounts", "Commuter Spending Accounts", "Fertility & Family Forming Benefits", "On-demand mental health support and Employee Assistance Program", "Global Travel Medical Insurance", "Financial Benefits", "Short and Long Term Disability Insurance", "Life & Accident Insurance", "401(k) Retirement Savings Plan", "Employee Stock Participation Plan", "Flexible paid time off covering vacation and sick leave", "Leave programs, including parental, pregnancy health, medical, and bereavement leave"]}, "job_job_title": "Partner", "job_posting_language": "en", "job_onet_soc": "11202100", "job_onet_job_zone": "4", "job_naics_code": "51121", "job_naics_name": "Software Publishers"}