{"job_id": "nZdLhuKCWjteIcKBAAAAAA==", "employer_name": "LPL Financial", "employer_logo": "https://www.lpl.com/content/dam/lpl-www/images/Logo/logo.png", "employer_website": "http://www.lpl.com", "employer_company_type": "Finance", "job_publisher": "LPL Financial", "job_employment_type": "FULLTIME", "job_title": "VP Insurance Business Development (remote)", "job_apply_link": "https://career.lpl.com/job/R-035061/VP-Insurance-Business-Development-remote", "job_apply_is_direct": false, "job_apply_quality_score": 0.8192, "apply_options": [{"publisher": "LPL Financial", "apply_link": "https://career.lpl.com/job/R-035061/VP-Insurance-Business-Development-remote", "is_direct": false}], "job_description": "Are you a team player? Are you curious to learn? Are you interested in working in meaningful projects? Do you want to work with cutting-edge technology? Are you interested in being part of a team that is working to transform and do things differently? If so, LPL Financial is the place for you!\n\nLPL Financial (Nasdaq: LPLA) was founded on the principle that the firm should work for the advisor, and not the other way around. Today, LPL is a leader* in the markets we serve, supporting more than 18,000 financial advisors, 800 institution-based investment programs and 450 independent RIA firms nationwide. We are steadfast in our commitment to the advisor-centered model and the belief that Americans deserve access to personalized guidance from a financial advisor. At LPL, independence means that advisors have the freedom they deserve to choose the business model, services, and technology resources that allow them to run their perfect practice. And they have the freedom to manage their client relationships, because they know their clients best. Simply put, we take care of our advisors, so they can take care of their clients.\n\nJob Overview:\n\nOur VP Insurance Business Development will be responsible for proactively driving life, LTC and DI insurance sales within the Western US Territory serving both LPL institutional clients and independent advisors with a particular focus on larger permanent life cases. As the VP of Insurance Business Development, you will engage with LPL advisors to uncover insurance opportunities through book and policy reviews as well as provide point of sales support.\n\nThis position will also function as an informal leader within our Insurance sales team. Responsibilities include regular contact with other LPL insurance team professionals (including internal sales consultants and case managers) as well as building relationships with LPL stakeholders across other disciplines (e.g., Financial Planning, Private Client, Sales Channel leaders). Assistance will be needed periodically for onboarding larger producing groups or advisors and working with LPL\u2019s recruiting efforts to educate new recruits on the LPL Insurance offering.\n\nSome of the activities and strategies that will be used to successfully grow insurance include:\n\u2022 Proactive outreach: 1:1 meetings, small to mid- size group meetings, prospecting phone calls, targeted sales campaigns, webinars and client events.\n\u2022 Point of sale support: Help advisors close business with end clients on phone calls and in person meetings\n\u2022 The role will be approximately 75% field-based and 25% phone/video work. The phone work will consist primarily of proactively reaching out to advisors across the LPL advisor population in order to build relationships, help advisors identify opportunities and drive LPL Insurance sales.\n\u2022 The field work will primarily consist of face to face advisor meetings, small group meetings, LPL workshops/conferences and some larger group settings.\n\nResponsibilities:\n\u2022 The position requires extensive phone and video call work that will include making daily outbound sales calls to help advisors increase their insurance business. This includes methodical profiling, book reviews, policy reviews and consistent outreach and follow-up, and targeted marketing campaigns.\n\u2022 This position will require hosting and presenting on conference calls and webinars in order to drive sales results. This role requires the ability to match style, tone and pace with many different types of advisors across various experience levels.\n\u2022 The position will offer point of sales support to advisors with their clients to help close business\n\u2022 This position involves tracking large cases and proactively working with the team and the advisor to move cases to closing.\n\u2022 The position requires extensive travel to LPL advisor office, branches, seminars and conferences and to advisor and institutional meetings.\n\u2022 This position will partner with management, the sales organization, LPL departments and our insurance carriers to drive forward the business plan to achieve sales goals.\n\u2022 This position will assist other business units with insurance-related questions and requests, as needed. Serve as a Subject Matter Expert (SME) on life insurance.\n\u2022 The position will participate in various departmental projects, when assigned.\n\nWhat are we looking for?\n\nWe want strong collaborators who can deliver a world-class client experience. We are looking for people who thrive in a fast-paced environment, are client-focused, team oriented, and are able to execute in a way that encourages creativity and continuous improvement.\n\nRequirements:\n\u2022 Bachelor's degree\n\u2022 Series 6 (or 7) and 63, Life Insurance license required\n\u2022 5+ years life insurance sales or brokerage experience (BGA experience preferred)\n\nPreferences:\n\u2022 CLU, ChFC, or CFP, or willingness to obtain\n\u2022 Proven track record of sales success\n\u2022 Excellent phone communication and interpersonal skills required\n\u2022 Self-starter, detail oriented and process focused\n\u2022 Self-disciplined, with the ability to be proactive with strong follow-up mentality\n\u2022 Winflex, Ensight or other multiple insurance carrier illustration systems\n\u2022 Ability to Interact well with all departments inside of LPL Financial\n\u2022 Presentation and business planning experience required\n\u2022 Ability to handle high volume and fast paced environment\n\u2022 Pay listed does not reflect total compensation*\n\nPay Range:\n80,000-120,000/year\n\nActual base salary varies based on factors, including but not limited to, relevant skill, prior experience, education, base salary of internal peers, demonstrated performance, and geographic location. This position is also eligible to earn sales incentive compensation. Additionally, LPL Total Rewards package is highly competitive, designed to support your success at work, at home, and at play \u2013 such as 401K matching, health benefits, employee stock options, paid time off, volunteer time off, and more. This position is also eligible to earn sales incentive compensation. Your recruiter will be happy to discuss all that LPL has to offer!\n\nWhy LPL?\n\nAt LPL, we believe that objective financial guidance is a fundamental need for everyone. As the nation\u2019s leading independent broker-dealer, we offer an integrated platform of proprietary technology, brokerage, and investment advisor services. We provide you with a work environment that encourages your creativity and growth, a leadership team that is supportive and responsive, and the opportunity to create a career that has no limits, only amazing potential.\n\nWe are one team on one mission. We take care of our advisors, so they can take care of their clients.\n\nBecause our company is not too big and not too small, you can seize the opportunity to make a real impact. We are committed to supporting workplace equality, and we embrace the different perspectives and backgrounds of our employees. We also care for our communities, and we encourage our employees to do the same. This creates an environment in which you can do your best work.\n\nWant to hear from our employees on what it\u2019s like to work at LPL? Watch this!\n\nWe take social responsibility seriously. Learn more here\n\nWant to see info on our benefits? Learn more here\n\nJoin the LPL team and help us make a difference by turning life\u2019s aspirations into financial realities. Please log in or create an account to apply to this position. Principals only. EOE.\n\nInformation on Interviews:\n\nLPL will only communicate with a job applicant directly from an @lplfinancial.com email address and will never conduct an interview online or in a chatroom forum. During an interview, LPL will not request any form of payment from the applicant, or information regarding an applicant\u2019s bank or credit card. Should you have any questions regarding the application process, please contact LPL\u2019s Human Resources Solutions Center at (855) 575-6947.", "job_is_remote": false, "job_posted_at_timestamp": 1710288000, "job_posted_at_datetime_utc": "2024-03-13T00:00:00.000Z", "job_city": "San Diego", "job_state": "CA", "job_country": "US", "job_latitude": 32.898113, "job_longitude": -117.202934, "job_benefits": ["paid_time_off", "health_insurance", "retirement_savings", "dental_coverage"], "job_google_link": "https://www.google.com/search?gl=us&hl=en&rciv=jb&q=vice+president+of+business+development&start=10&ibp=htl;jobs#fpstate=tldetail&htivrt=jobs&htiq=vice+president+of+business+development&htidocid=nZdLhuKCWjteIcKBAAAAAA%3D%3D", "job_offer_expiration_datetime_utc": null, "job_offer_expiration_timestamp": null, "job_required_experience": {"no_experience_required": false, "required_experience_in_months": 60, "experience_mentioned": true, "experience_preferred": true}, "job_required_skills": null, "job_required_education": {"postgraduate_degree": false, "professional_certification": false, "high_school": false, "associates_degree": false, "bachelors_degree": false, "degree_mentioned": true, "degree_preferred": false, "professional_certification_mentioned": false}, "job_experience_in_place_of_education": false, "job_min_salary": null, "job_max_salary": null, "job_salary_currency": null, "job_salary_period": null, "job_highlights": {"Qualifications": ["We want strong collaborators who can deliver a world-class client experience", "We are looking for people who thrive in a fast-paced environment, are client-focused, team oriented, and are able to execute in a way that encourages creativity and continuous improvement", "Bachelor's degree", "Series 6 (or 7) and 63, Life Insurance license required", "CLU, ChFC, or CFP, or willingness to obtain", "Proven track record of sales success", "Excellent phone communication and interpersonal skills required", "Self-starter, detail oriented and process focused", "Self-disciplined, with the ability to be proactive with strong follow-up mentality", "Winflex, Ensight or other multiple insurance carrier illustration systems", "Ability to Interact well with all departments inside of LPL Financial", "Presentation and business planning experience required", "Ability to handle high volume and fast paced environment"], "Responsibilities": ["Our VP Insurance Business Development will be responsible for proactively driving life, LTC and DI insurance sales within the Western US Territory serving both LPL institutional clients and independent advisors with a particular focus on larger permanent life cases", "As the VP of Insurance Business Development, you will engage with LPL advisors to uncover insurance opportunities through book and policy reviews as well as provide point of sales support", "This position will also function as an informal leader within our Insurance sales team", "Responsibilities include regular contact with other LPL insurance team professionals (including internal sales consultants and case managers) as well as building relationships with LPL stakeholders across other disciplines (e.g., Financial Planning, Private Client, Sales Channel leaders)", "Assistance will be needed periodically for onboarding larger producing groups or advisors and working with LPL\u2019s recruiting efforts to educate new recruits on the LPL Insurance offering", "Some of the activities and strategies that will be used to successfully grow insurance include:", "Proactive outreach: 1:1 meetings, small to mid- size group meetings, prospecting phone calls, targeted sales campaigns, webinars and client events", "Point of sale support: Help advisors close business with end clients on phone calls and in person meetings", "The role will be approximately 75% field-based and 25% phone/video work", "The phone work will consist primarily of proactively reaching out to advisors across the LPL advisor population in order to build relationships, help advisors identify opportunities and drive LPL Insurance sales", "The field work will primarily consist of face to face advisor meetings, small group meetings, LPL workshops/conferences and some larger group settings", "The position requires extensive phone and video call work that will include making daily outbound sales calls to help advisors increase their insurance business", "This includes methodical profiling, book reviews, policy reviews and consistent outreach and follow-up, and targeted marketing campaigns", "This position will require hosting and presenting on conference calls and webinars in order to drive sales results", "This role requires the ability to match style, tone and pace with many different types of advisors across various experience levels", "The position will offer point of sales support to advisors with their clients to help close business", "This position involves tracking large cases and proactively working with the team and the advisor to move cases to closing", "The position requires extensive travel to LPL advisor office, branches, seminars and conferences and to advisor and institutional meetings", "This position will partner with management, the sales organization, LPL departments and our insurance carriers to drive forward the business plan to achieve sales goals", "This position will assist other business units with insurance-related questions and requests, as needed", "Serve as a Subject Matter Expert (SME) on life insurance", "The position will participate in various departmental projects, when assigned"], "Benefits": ["Pay listed does not reflect total compensation*", "Actual base salary varies based on factors, including but not limited to, relevant skill, prior experience, education, base salary of internal peers, demonstrated performance, and geographic location", "This position is also eligible to earn sales incentive compensation", "Additionally, LPL Total Rewards package is highly competitive, designed to support your success at work, at home, and at play \u2013 such as 401K matching, health benefits, employee stock options, paid time off, volunteer time off, and more"]}, "job_job_title": "Business", "job_posting_language": "en", "job_onet_soc": "11202100", "job_onet_job_zone": "4", "job_occupational_categories": ["Sales"], "job_naics_code": "523920", "job_naics_name": "Portfolio Management"}