{"job_id": "KZmuv8PozmU-qfJ9AAAAAA==", "employer_name": "Orion Solutions Group", "employer_logo": null, "employer_website": "http://www.orionsolutionsgroup.net", "employer_company_type": null, "job_publisher": "Jooble", "job_employment_type": "CONTRACTOR", "job_title": "Business Development Manager", "job_apply_link": "https://jooble.org/jdp/-651474676902774291", "job_apply_is_direct": false, "job_apply_quality_score": 0.6544, "apply_options": [{"publisher": "Jooble", "apply_link": "https://jooble.org/jdp/-651474676902774291", "is_direct": false}, {"publisher": "LinkedIn", "apply_link": "https://www.linkedin.com/jobs/view/business-development-manager-at-orion-solutions-group-3849917798", "is_direct": false}], "job_description": "Orion Solutions Group is working with a world-class International Freight Forwarding company, which has been offering supply chain solutions to multinational companies of various sizes for more than 35 years. Their comprehensive Contract Logistics and Freight Management service form a seamlessly integrated global network, with offices strategically located in key sourcing countries. This enables them to provide exceptional operational services to clients across the globe.\nOrion's client is currently seeking a skilled and enthusiastic Business Development Manager to join their North American team, specializing in the promotion of Ocean and Air freight solutions. The selected candidate will play a key role in formulating and implementing effective sales strategies, cultivating customer relationships, and fostering revenue growth.\nThe ideal candidate should possess a documented history of successful sales, exceptional communication abilities, and the capacity to think strategically while making decisive actions. This presents a fantastic opportunity for a driven individual aiming to elevate their career to new heights. The Business Development Manager will be tasked with pinpointing, pursuing, and finalizing new business prospects. Prospective customers will be engaged through diverse methods such as direct calls, face-to-face meetings, and networking across various industry events. A prosperous candidate will exhibit self-motivation and a proactive \"hunter\" mindset.\nWhat is great about this opportunity:\n\u2022 Competitive Base Salary\n\u2022 Uncapped Commissions\n\u2022 Excellent Benefits\n\u2022 Exceptional Culture\n\u2022 Privately Held Company\n\nResponsibilities:\n\u2022 Cultivates relationships with new clients and secures new contracts throughout the year.\n\u2022 Guides the complete sales cycle from the \"Initial Opportunity\" phase to a \"Closed Won\" status.\n\u2022 Utilizes various direct methods such as cold-calling, face-to-face meetings, and industry networking to prospect potential customers.\n\u2022 Offers sales volume forecasts for relevant time periods, presenting best-case and most likely scenarios.\n\u2022 Conducts customer presentations, submits opportunities, manages activity reports, and actively contributes to the overall growth strategy of the company.\n\u2022 Establishes and nurtures a robust sales pipeline to either meet or surpass sales targets.\n\u2022 Develops and retains a functional understanding of the company's products, services, and operations.\n\u2022 Collaborates closely with operations managers to foster cooperative relationships and ensure the fulfillment of all customer requirements.\n\u2022 Records sales data in the CRM system or other designated sales call software provided by the company.\n\u2022 Achieves or surpasses the sales threshold/quota as defined by the company.\n\u2022 Engages collaboratively with other sales and operational staff to foster a team-selling environment.\n\nQualifications:\n\u2022 Bachelor\u2019s Degree preferred, or equivalent combination of education and work experience.\n\u2022 Position level commensurate with experience, will consider candidates with:\n\u2022 Degree or Military experience with demonstrated aptitude and desire to sell.\n\u2022 Candidate with strong understanding of Freight Forwarding/Logistics with demonstrated aptitude and desire to sell.\n\u2022 Candidate with operations or operations management experience interested in outside sales.\n\u2022 Proficiency in Microsoft Office (including PowerPoint, Word and Excel), internet, web-based and job specific software applications required.\n\u2022 Ability to work effectively in a team environment to achieve required results.\n\u2022 Must have strong persuasive and negotiating skills.\n\u2022 Must have strong problem-solving skills and the ability to think and respond quickly to sales and service issues.\n\u2022 Effective planning and organization skills required to schedule appointments appropriately and to meet reporting deadlines.\n\u2022 A valid state issued driver\u2019s license required, acceptable driving record required, and proof of automobile insurance required.\nTravel: Up to 50% local market/region", "job_is_remote": false, "job_posted_at_timestamp": 1710028800, "job_posted_at_datetime_utc": "2024-03-10T00:00:00.000Z", "job_city": null, "job_state": null, "job_country": "US", "job_latitude": 37.09024, "job_longitude": -95.71289, "job_benefits": null, "job_google_link": "https://www.google.com/search?gl=us&hl=en&rciv=jb&q=manager+of+business+development&start=50&ibp=htl;jobs#fpstate=tldetail&htivrt=jobs&htiq=manager+of+business+development&htidocid=KZmuv8PozmU-qfJ9AAAAAA%3D%3D", "job_offer_expiration_datetime_utc": "2024-04-11T11:53:20.000Z", "job_offer_expiration_timestamp": 1712836400, "job_required_experience": {"no_experience_required": false, "required_experience_in_months": null, "experience_mentioned": true, "experience_preferred": false}, "job_required_skills": null, "job_required_education": {"postgraduate_degree": false, "professional_certification": false, "high_school": false, "associates_degree": false, "bachelors_degree": false, "degree_mentioned": true, "degree_preferred": false, "professional_certification_mentioned": false}, "job_experience_in_place_of_education": false, "job_min_salary": null, "job_max_salary": null, "job_salary_currency": null, "job_salary_period": null, "job_highlights": {"Qualifications": ["The ideal candidate should possess a documented history of successful sales, exceptional communication abilities, and the capacity to think strategically while making decisive actions", "Position level commensurate with experience, will consider candidates with:", "Degree or Military experience with demonstrated aptitude and desire to sell", "Candidate with strong understanding of Freight Forwarding/Logistics with demonstrated aptitude and desire to sell", "Candidate with operations or operations management experience interested in outside sales", "Proficiency in Microsoft Office (including PowerPoint, Word and Excel), internet, web-based and job specific software applications required", "Ability to work effectively in a team environment to achieve required results", "Must have strong persuasive and negotiating skills", "Must have strong problem-solving skills and the ability to think and respond quickly to sales and service issues", "Effective planning and organization skills required to schedule appointments appropriately and to meet reporting deadlines", "A valid state issued driver\u2019s license required, acceptable driving record required, and proof of automobile insurance required"], "Responsibilities": ["This enables them to provide exceptional operational services to clients across the globe", "Orion's client is currently seeking a skilled and enthusiastic Business Development Manager to join their North American team, specializing in the promotion of Ocean and Air freight solutions", "The selected candidate will play a key role in formulating and implementing effective sales strategies, cultivating customer relationships, and fostering revenue growth", "The Business Development Manager will be tasked with pinpointing, pursuing, and finalizing new business prospects", "Prospective customers will be engaged through diverse methods such as direct calls, face-to-face meetings, and networking across various industry events", "Cultivates relationships with new clients and secures new contracts throughout the year", "Guides the complete sales cycle from the \"Initial Opportunity\" phase to a \"Closed Won\" status", "Utilizes various direct methods such as cold-calling, face-to-face meetings, and industry networking to prospect potential customers", "Offers sales volume forecasts for relevant time periods, presenting best-case and most likely scenarios", "Conducts customer presentations, submits opportunities, manages activity reports, and actively contributes to the overall growth strategy of the company", "Establishes and nurtures a robust sales pipeline to either meet or surpass sales targets", "Develops and retains a functional understanding of the company's products, services, and operations", "Collaborates closely with operations managers to foster cooperative relationships and ensure the fulfillment of all customer requirements", "Records sales data in the CRM system or other designated sales call software provided by the company", "Achieves or surpasses the sales threshold/quota as defined by the company", "Engages collaboratively with other sales and operational staff to foster a team-selling environment"], "Benefits": ["Competitive Base Salary", "Uncapped Commissions", "Excellent Benefits", "Exceptional Culture", "Privately Held Company"]}, "job_job_title": "Development manager", "job_posting_language": "en", "job_onet_soc": "11202100", "job_onet_job_zone": "4"}