{"job_id": "O3tDutEPOiErSZTCAAAAAA==", "employer_name": "Jackson Lewis P.C.", "employer_logo": "https://upload.wikimedia.org/wikipedia/commons/thumb/8/8a/Jackson_Lewis_logo.svg/1200px-Jackson_Lewis_logo.svg.png", "employer_website": "http://www.jacksonlewis.com", "employer_company_type": "Legal", "job_publisher": "LinkedIn", "job_employment_type": "FULLTIME", "job_title": "AI Engineer", "job_apply_link": "https://www.linkedin.com/jobs/view/ai-engineer-at-jackson-lewis-p-c-3859503719", "job_apply_is_direct": false, "job_apply_quality_score": 0.6503, "apply_options": [{"publisher": "LinkedIn", "apply_link": "https://www.linkedin.com/jobs/view/ai-engineer-at-jackson-lewis-p-c-3859503719", "is_direct": false}], "job_description": "Focused on labor and employment law since 1958, Jackson Lewis P.C.\u2019s 950+ attorneys located in major cities nationwide consistently identify and respond to new ways workplace law intersects business. We help employers develop proactive strategies, strong policies and business-oriented solutions to cultivate high-functioning workforces that are engaged, stable and diverse, and share our clients' goals to emphasize inclusivity and respect for the contribution of every employee.\n\nThe Firm is ranked in the First Tier nationally in the category of Labor and Employment Litigation, as well as in both Employment Law and Labor Law on behalf of Management, in the U.S. News - Best Lawyers\u00ae \u201cBest Law Firms\u201d.\n\nThe AI Engineer is an important role within the Innovation team, elevating our commitment to exceptional client service and internal operational excellence. The ideal candidate will work closely with the firm\u2019s AI Working Group and other stakeholders across the firm, playing a pivotal role in designing, developing, and implementing AI solutions. This position focuses on both Generative AI and non-Generative AI technologies, using Microsoft Azure OpenAI Service and other advanced tools. This position reports to the Director of Innovation and Knowledge Management Firm Solutions.\n\nPrimary Responsibilities:\n\nIdentify and Develop AI Use Cases: Work closely with stakeholders to identify and develop AI use cases relevant to the firm\u2019s practice.\n\nEvaluate AI Applications: Evaluate potential AI applications for feasibility and impact on both legal and business services processes and outcomes and make appropriate recommendations.\n\nAssist with Infrastructure and Data Strategy Alignment: Work with the firm\u2019s IT and Data Services teams to help ensure the appropriate technical infrastructure is in place to support a wide variety of AI projects and initiatives (both generative and non-generative) and that the firm\u2019s data strategy aligns with its AI goals.\n\nDesign, Develop, and Implement AI Solutions: Following an agile approach and leveraging Microsoft Azure OpenAI Service and a variety of other AI technologies, design, develop, and implement custom AI systems and applications to enhance service delivery, and assist with the implementation of \u201coff-the-shelf\u201d AI solutions.\n\nAdhere to Responsible and Ethical AI Principles: Ensure all AI applications comply with ethical standards and regulations.\n\nServe as an AI Subject Matter Expert and Advocate: Stay abreast of emerging trends and technologies, particularly those applicable to the legal industry, and provide technical insights and recommendations to improve AI adoption and integration within the firm.\n\nProject Management: Oversee AI project activities, employing effective project management techniques and tools. Ensure timely and successful execution of initiatives.\n\nMetrics and Reporting: Develop and track key metrics. Provide regular reports on the effectiveness of AI initiatives and propose data-driven recommendations for continuous improvement.\n\nRequirements:\n\nExperience: Minimum of 3 years of experience in AI technology development and implementation with demonstrated experience in Generative AI.\n\nEducation: Bachelor\u2019s degree in Computer Science, AI, Machine Learning, Data Science, or related field.\n\nSkills:\n\u2022 Strong analytical and problem-solving abilities.\n\u2022 Excellent communication and collaboration skills.\n\u2022 Ability to translate complex technical concepts for non-technical audiences.\n\nTechnical Proficiency:\n\u2022 Proficiency in AI frameworks and programming languages, including Python, R, Java, and C++.\n\u2022 Understanding of key mathematical concepts such as statistics, probability, and linear algebra.\n\u2022 Experience with developing AI solutions, preferably in a professional services environment.\n\u2022 Experience with common AI/ML algorithms and models, neural networks, deep learning, natural language processing, and prompt engineering.\n\u2022 Knowledge of REST API development.\n\u2022 Knowledge of Microsoft technologies such as Azure OpenAI Service, Azure Machine Learning, Azure AI Studio/prompt flow, Power Automate, and AI/Cognitive Search, along with their application in real-world scenarios.\n\nThe expected salary range for this position in New York City and Westchester County is $125,000 - $150,000. The actual compensation will be determined based on experience and other factors permitted by law.\n\nJackson Lewis understands that embracing our differences makes us a stronger, better firm. We appreciate the importance of having a workforce that reflects the various communities in which we work, and we strive to create an inclusive environment where diverse employees want to work and where they can flourish professionally. In furtherance of our culture, all qualified applicants will receive consideration for employment without regard to race, national origin, gender, age, religion, disability, sexual orientation, veteran status, marital status or any other characteristics protected by law.", "job_is_remote": false, "job_posted_at_timestamp": 1710800530, "job_posted_at_datetime_utc": "2024-03-18T22:22:10.000Z", "job_city": "New York", "job_state": "NY", "job_country": "US", "job_latitude": 40.712776, "job_longitude": -74.005974, "job_benefits": null, "job_google_link": "https://www.google.com/search?gl=us&hl=en&rciv=jb&q=ai+engineer&start=0&ibp=htl;jobs#fpstate=tldetail&htivrt=jobs&htiq=ai+engineer&htidocid=O3tDutEPOiErSZTCAAAAAA%3D%3D", "job_offer_expiration_datetime_utc": "2024-04-17T22:22:09.000Z", "job_offer_expiration_timestamp": 1713392529, "job_required_experience": {"no_experience_required": false, "required_experience_in_months": 36, "experience_mentioned": true, "experience_preferred": false}, "job_required_skills": null, "job_required_education": {"postgraduate_degree": false, "professional_certification": false, "high_school": false, "associates_degree": false, "bachelors_degree": true, "degree_mentioned": true, "degree_preferred": true, "professional_certification_mentioned": false}, "job_experience_in_place_of_education": false, "job_min_salary": null, "job_max_salary": null, "job_salary_currency": null, "job_salary_period": null, "job_highlights": {"Qualifications": ["Experience: Minimum of 3 years of experience in AI technology development and implementation with demonstrated experience in Generative AI", "Education: Bachelor\u2019s degree in Computer Science, AI, Machine Learning, Data Science, or related field", "Strong analytical and problem-solving abilities", "Excellent communication and collaboration skills", "Ability to translate complex technical concepts for non-technical audiences", "Proficiency in AI frameworks and programming languages, including Python, R, Java, and C++", "Understanding of key mathematical concepts such as statistics, probability, and linear algebra", "Experience with developing AI solutions, preferably in a professional services environment", "Experience with common AI/ML algorithms and models, neural networks, deep learning, natural language processing, and prompt engineering", "Knowledge of REST API development", "Knowledge of Microsoft technologies such as Azure OpenAI Service, Azure Machine Learning, Azure AI Studio/prompt flow, Power Automate, and AI/Cognitive Search, along with their application in real-world scenarios"], "Responsibilities": ["The ideal candidate will work closely with the firm\u2019s AI Working Group and other stakeholders across the firm, playing a pivotal role in designing, developing, and implementing AI solutions", "Identify and Develop AI Use Cases: Work closely with stakeholders to identify and develop AI use cases relevant to the firm\u2019s practice", "Evaluate AI Applications: Evaluate potential AI applications for feasibility and impact on both legal and business services processes and outcomes and make appropriate recommendations", "Assist with Infrastructure and Data Strategy Alignment: Work with the firm\u2019s IT and Data Services teams to help ensure the appropriate technical infrastructure is in place to support a wide variety of AI projects and initiatives (both generative and non-generative) and that the firm\u2019s data strategy aligns with its AI goals", "Design, Develop, and Implement AI Solutions: Following an agile approach and leveraging Microsoft Azure OpenAI Service and a variety of other AI technologies, design, develop, and implement custom AI systems and applications to enhance service delivery, and assist with the implementation of \u201coff-the-shelf\u201d AI solutions", "Adhere to Responsible and Ethical AI Principles: Ensure all AI applications comply with ethical standards and regulations", "Serve as an AI Subject Matter Expert and Advocate: Stay abreast of emerging trends and technologies, particularly those applicable to the legal industry, and provide technical insights and recommendations to improve AI adoption and integration within the firm", "Project Management: Oversee AI project activities, employing effective project management techniques and tools", "Ensure timely and successful execution of initiatives", "Metrics and Reporting: Develop and track key metrics", "Provide regular reports on the effectiveness of AI initiatives and propose data-driven recommendations for continuous improvement"], "Benefits": ["The expected salary range for this position in New York City and Westchester County is $125,000 - $150,000"]}, "job_job_title": "Engineer", "job_posting_language": "en", "job_onet_soc": "15111100", "job_onet_job_zone": "5", "job_naics_code": "5411", "job_naics_name": "Legal"}