{"job_id": "NN3sFv7mokS_UTaXAAAAAA==", "employer_name": "Artisan Partners", "employer_logo": "https://www.moneycontroller.fr/upload/aziende/artisan-partners-asset-managem_20210210153445.png", "employer_website": "https://www.apam.com", "employer_company_type": null, "job_publisher": "Jooble", "job_employment_type": "FULLTIME", "job_title": "Data Science Developer", "job_apply_link": "https://jooble.org/jdp/-4121538060276121813", "job_apply_is_direct": false, "job_apply_quality_score": 0.5413, "apply_options": [{"publisher": "Jooble", "apply_link": "https://jooble.org/jdp/-4121538060276121813", "is_direct": false}, {"publisher": "Adzuna", "apply_link": "https://www.adzuna.com/details/4614000110", "is_direct": false}], "job_description": "The Information Technology department at Artisan Partners is responsible for providing technology solutions that are reliable, adaptable, integrated, scalable and maintainable. The key clients of the Information Technology group span the entire investment process, from portfolio management to operations.\n\nThe Data Science Developer role for the Data Services team is primarily responsible for the architecture, development and support of systems related to data science and machine learning. This individual may at times be responsible for the design, coding, testing, deployment and documentation of various data science tools, models and processes. Exceptional interpersonal skills, strong written and oral communication skills are critical to successful performance in this role.\n\nLocation: Milwaukee, WI | Boston, MA | Chicago, IL\nResponsibilities\n\nThe candidate can expect to:\n\u2022 Act as a data science expert, collaborating with data scientists and other stakeholders to understand their needs and develop solutions that meet those needs\n\u2022 Evaluate, select, implement, administer, and support an enterprise data science toolkit, ensuring that systems are reliable, scalable, and maintainable\n\u2022 Build consensus around standards and best practices while ensuring alignment with enterprise principles\n\u2022 Use statistical and machine learning techniques to analyze data and develop predictive models\n\u2022 Communicate insights and findings to both technical and non-technical audiences\n\u2022 Develop and deploy processes to automate data ingestion and preparation, model training and predictions, and data delivery\n\u2022 Monitor the performance of machine learning models and make improvements as needed\n\u2022 Research and pilot tools to enhance Artisan\u2019s ability to deliver data science solutions\n\u2022 Provide ongoing support and assistance with existing platforms and projects\n\u2022 Complete special assignments as needed\nQualifications\n\nThe successful candidate will possess strong analytical skills and attention to detail. Additionally, the ideal candidate will possess:\n\u2022 Bachelor\u2019s Degree in Computer Science or related field\n\u2022 5-7 years of experience in a Data Scientist or Machine Learning Engineer role within the financial industry required\n\u2022 Proven track record of supporting high quality data science processes or applications\n\u2022 Keen interest in gaining business knowledge and driven to solve challenges through technology\n\u2022 Highly developed problem-solving and troubleshooting skills\n\u2022 Ability to multi-task and manage several projects at once\n\u2022 Ability to clearly present technical concepts to a non-technical business audience\n\u2022 Ability to interact effectively with peers in a fast-paced environment and under aggressive deadlines\n\u2022 Ability to perform various data sourcing, transformation, and storage tasks\n\u2022 Knowledge of statistical based data analysis and developing machine learning models\n\u2022 Extensive Python and SQL experience\n\u2022 Experience with deploying and monitoring machine learning models\n\u2022 Experience with enterprise data science tools is strongly preferred (Amazon SageMaker, Snowflake\u2019s Snowpark, HuggingFace)\n\nArtisan Partners Limited Partnership is an equal opportunity employer. Artisan Partners does not discriminate on the basis of race, religion, color, national origin, gender, age, disability, marital status, sexual orientation or any other characteristic protected under applicable law. All employment decisions are made on the basis of qualifications, merit and business need.\n\n#LI-Hybrid/span>", "job_is_remote": false, "job_posted_at_timestamp": 1710578992, "job_posted_at_datetime_utc": "2024-03-16T08:49:52.000Z", "job_city": "Boston", "job_state": "MA", "job_country": "US", "job_latitude": 42.36008, "job_longitude": -71.05888, "job_benefits": null, "job_google_link": "https://www.google.com/search?gl=us&hl=en&rciv=jb&q=data+science+leader&start=60&ibp=htl;jobs#fpstate=tldetail&htivrt=jobs&htiq=data+science+leader&htidocid=NN3sFv7mokS_UTaXAAAAAA%3D%3D", "job_offer_expiration_datetime_utc": "2024-04-16T07:03:56.000Z", "job_offer_expiration_timestamp": 1713251036, "job_required_experience": {"no_experience_required": false, "required_experience_in_months": 60, "experience_mentioned": true, "experience_preferred": true}, "job_required_skills": null, "job_required_education": {"postgraduate_degree": false, "professional_certification": false, "high_school": false, "associates_degree": false, "bachelors_degree": false, "degree_mentioned": true, "degree_preferred": true, "professional_certification_mentioned": false}, "job_experience_in_place_of_education": false, "job_min_salary": null, "job_max_salary": null, "job_salary_currency": null, "job_salary_period": null, "job_highlights": {"Qualifications": ["Exceptional interpersonal skills, strong written and oral communication skills are critical to successful performance in this role", "The successful candidate will possess strong analytical skills and attention to detail", "Bachelor\u2019s Degree in Computer Science or related field", "5-7 years of experience in a Data Scientist or Machine Learning Engineer role within the financial industry required", "Proven track record of supporting high quality data science processes or applications", "Keen interest in gaining business knowledge and driven to solve challenges through technology", "Highly developed problem-solving and troubleshooting skills", "Ability to multi-task and manage several projects at once", "Ability to clearly present technical concepts to a non-technical business audience", "Ability to interact effectively with peers in a fast-paced environment and under aggressive deadlines", "Ability to perform various data sourcing, transformation, and storage tasks", "Knowledge of statistical based data analysis and developing machine learning models", "Extensive Python and SQL experience", "Experience with deploying and monitoring machine learning models"], "Responsibilities": ["The Data Science Developer role for the Data Services team is primarily responsible for the architecture, development and support of systems related to data science and machine learning", "This individual may at times be responsible for the design, coding, testing, deployment and documentation of various data science tools, models and processes", "Act as a data science expert, collaborating with data scientists and other stakeholders to understand their needs and develop solutions that meet those needs", "Evaluate, select, implement, administer, and support an enterprise data science toolkit, ensuring that systems are reliable, scalable, and maintainable", "Build consensus around standards and best practices while ensuring alignment with enterprise principles", "Use statistical and machine learning techniques to analyze data and develop predictive models", "Communicate insights and findings to both technical and non-technical audiences", "Develop and deploy processes to automate data ingestion and preparation, model training and predictions, and data delivery", "Monitor the performance of machine learning models and make improvements as needed", "Research and pilot tools to enhance Artisan\u2019s ability to deliver data science solutions", "Provide ongoing support and assistance with existing platforms and projects", "Complete special assignments as needed"]}, "job_job_title": "Data science", "job_posting_language": "en", "job_onet_soc": "15111100", "job_onet_job_zone": "5"}