{"job_id": "se0yFwjEF1z-x0-2AAAAAA==", "employer_name": "Path Company", "employer_logo": null, "employer_website": null, "employer_company_type": null, "job_publisher": "Indeed", "job_employment_type": "FULLTIME", "job_title": "Vice President of Business Development (Baton Rouge, LA)", "job_apply_link": "https://www.indeed.com/viewjob?jk=171e81806e66d482", "job_apply_is_direct": true, "job_apply_quality_score": 0.6153, "apply_options": [{"publisher": "Indeed", "apply_link": "https://www.indeed.com/viewjob?jk=171e81806e66d482", "is_direct": true}], "job_description": "PATH Company is seeking to hire a Vice President of Business Development in Baton Rouge, LA to lead the efforts of expanding PATH\u2019s market. PATH\u2019s continued growth trajectory and expansion throughout the region have identified the need for additional team members who can help deliver the customer- centric approach PATH was founded on. Reporting to Path\u2019s Executive Vice President, the Vice President of Business Development will sell high-level infrastructure solutions in key vertical markets including municipalities, K-12 Schools, Colleges and Universities, State and local Government, Industrial and Commercial. These are large, sophisticated construction projects that require a complex selling process and focused customer management. Therefore, we are looking for a seasoned account executive with a consistent track record of success leading and driving high-level solutions. To be successful, the Vice President of Business Development must be a seasoned sales professional who can drive the process, think creatively, and work collaboratively with a multi- disciplined team of professionals.\n\nResponsibilities\n\nReporting to Path\u2019s Executive Vice President, this professional will be responsible for the sale and account management of infrastructure solutions including but not limited to building retrofits, controls and automation technology, central plant construction and renovation, streetlighting, sports lighting, new building construction, and renewable energy solutions. Key tasks for this professional include the following:\n\u2022 Promote the Path value proposition to executive level decision makers by providing comprehensive infrastructure solutions for the customer\u2019s business and operational needs\n\u2022 Build and maintain long term customer relationships and business partnerships within the industry\n\u2022 Track and coordinate the delivery of both internal and external project deliverables\n\u2022 Lead the sales process, including but not limited to the following:\n\u2022 Identify prospective customers through market research and the development of business strategies\n\u2022 Implement Path\u2019s sales process to cultivate relationships while qualifying and closing new opportunities\n\u2022 Recommend solutions and link customer needs and objectives\n\u2022 Positively influence design and construction with owners\n\u2022 Collaborate and partner with Path\u2019s internal Project Design Engineers. Communicate the vision of the project and work closely on specifications throughout the design phase with support of team, credibly present cost/benefit analysis, financial evaluation, technology and infrastructure options, and Path differentiators\n\u2022 Prepare customer-facing presentations and written responses to RFQs/RFPs\n\u2022 Track customer interaction through the use of PATH\u2019s CRM platform (Salesforce)\n\u2022 Coordinate events centered around customer appreciation\n\nPATH Company is seeking to hire for this position as soon as possible. The salary range will be commensurate with experience and includes health, retirement benefits, and vacation time.\nNormal weekly work hours are expected. There will be travel throughout the state and region that will sometimes include overnight stays. No weekend work is anticipated.\n\nSkills and Qualifications:\n\u2022 Strong Written and Verbal Communication Skills\n\u2022 Proven success in complex sales and customer management\n\u2022 Ability to credibly communicate with executive level decision makers including college presidents, K-12 school boards and superintendents, city managers and mayors, C-suite leadership, etc.\n\u2022 Demonstrated ability to analyze complex data and communicate findings\n\u2022 Problem Solver and Self-Starter with a passion for serving customers\n\u2022 Emotional intelligence and intuition\n\nEducation and Experience Requirements:\n\u2022 Bachelor\u2019s or Associate\u2019s Degree required\n\u2022 Seven years of sales experience in the MUSH market or correlating experience\n\u2022 Three years of experience working in the building technology market\n\u2022 Construction Industry knowledge\n\u2022 Familiarity with accounting and finance principles\n\nPATH is an infrastructure solutions company focused on helping government entities identify, develop, and implement solutions that leverage today\u2019s technology to create better efficiencies in the areas of energy, water, and operations.", "job_is_remote": false, "job_posted_at_timestamp": 1694481712, "job_posted_at_datetime_utc": "2023-09-12T01:21:52.000Z", "job_city": "Baton Rouge", "job_state": "LA", "job_country": "US", "job_latitude": 30.451468, "job_longitude": -91.18715, "job_benefits": ["paid_time_off", "health_insurance", "retirement_savings"], "job_google_link": "https://www.google.com/search?gl=us&hl=en&rciv=jb&q=vice+president+of+business+development&start=50&ibp=htl;jobs#fpstate=tldetail&htivrt=jobs&htiq=vice+president+of+business+development&htidocid=se0yFwjEF1z-x0-2AAAAAA%3D%3D", "job_offer_expiration_datetime_utc": "2024-07-07T18:56:54.000Z", "job_offer_expiration_timestamp": 1720378614, "job_required_experience": {"no_experience_required": false, "required_experience_in_months": 84, "experience_mentioned": true, "experience_preferred": false}, "job_required_skills": null, "job_required_education": {"postgraduate_degree": false, "professional_certification": false, "high_school": false, "associates_degree": false, "bachelors_degree": false, "degree_mentioned": true, "degree_preferred": false, "professional_certification_mentioned": false}, "job_experience_in_place_of_education": false, "job_min_salary": null, "job_max_salary": null, "job_salary_currency": null, "job_salary_period": null, "job_highlights": {"Qualifications": ["Therefore, we are looking for a seasoned account executive with a consistent track record of success leading and driving high-level solutions", "To be successful, the Vice President of Business Development must be a seasoned sales professional who can drive the process, think creatively, and work collaboratively with a multi- disciplined team of professionals", "Strong Written and Verbal Communication Skills", "Proven success in complex sales and customer management", "Ability to credibly communicate with executive level decision makers including college presidents, K-12 school boards and superintendents, city managers and mayors, C-suite leadership, etc", "Demonstrated ability to analyze complex data and communicate findings", "Problem Solver and Self-Starter with a passion for serving customers", "Emotional intelligence and intuition", "Bachelor\u2019s or Associate\u2019s Degree required", "Seven years of sales experience in the MUSH market or correlating experience", "Three years of experience working in the building technology market", "Construction Industry knowledge", "Familiarity with accounting and finance principles"], "Responsibilities": ["Reporting to Path\u2019s Executive Vice President, the Vice President of Business Development will sell high-level infrastructure solutions in key vertical markets including municipalities, K-12 Schools, Colleges and Universities, State and local Government, Industrial and Commercial", "Reporting to Path\u2019s Executive Vice President, this professional will be responsible for the sale and account management of infrastructure solutions including but not limited to building retrofits, controls and automation technology, central plant construction and renovation, streetlighting, sports lighting, new building construction, and renewable energy solutions", "Promote the Path value proposition to executive level decision makers by providing comprehensive infrastructure solutions for the customer\u2019s business and operational needs", "Build and maintain long term customer relationships and business partnerships within the industry", "Track and coordinate the delivery of both internal and external project deliverables", "Lead the sales process, including but not limited to the following:", "Identify prospective customers through market research and the development of business strategies", "Implement Path\u2019s sales process to cultivate relationships while qualifying and closing new opportunities", "Recommend solutions and link customer needs and objectives", "Positively influence design and construction with owners", "Collaborate and partner with Path\u2019s internal Project Design Engineers", "Communicate the vision of the project and work closely on specifications throughout the design phase with support of team, credibly present cost/benefit analysis, financial evaluation, technology and infrastructure options, and Path differentiators", "Prepare customer-facing presentations and written responses to RFQs/RFPs", "Track customer interaction through the use of PATH\u2019s CRM platform (Salesforce)", "Coordinate events centered around customer appreciation", "There will be travel throughout the state and region that will sometimes include overnight stays"], "Benefits": ["The salary range will be commensurate with experience and includes health, retirement benefits, and vacation time", "Normal weekly work hours are expected"]}, "job_job_title": "Business", "job_posting_language": "en", "job_onet_soc": "11101100", "job_onet_job_zone": "5"}