{"job_id": "WvwwjtIMiWFZRB3OAAAAAA==", "employer_name": "BizDev Experts", "employer_logo": null, "employer_website": null, "employer_company_type": null, "job_publisher": "LazyApply", "job_employment_type": "FULLTIME", "job_title": "Business Development Consultant & Proposal Writter", "job_apply_link": "https://lazyapply.com/jobpreview/job_a08cb3819140182d", "job_apply_is_direct": true, "job_apply_quality_score": 0.5093, "apply_options": [{"publisher": "LazyApply", "apply_link": "https://lazyapply.com/jobpreview/job_a08cb3819140182d", "is_direct": true}], "job_description": "Job Title: Business Development Consultant and Proposal Writer\nLocation: 100% Remote Work\nCompany: BizDev Experts\nAbout Us:BizDev Experts is a leading consulting firm specializing in helping small businesses secure federal, state, and local government contracts. We are committed to delivering exceptional value to our clients and driving growth through strategic business development and proposal writing. Our team is dedicated to helping small businesses achieve success in the highly competitive government contracting arena, and we are seeking an experienced Business Development Consultant and Proposal Writer to join our dynamic team.\nPosition Overview:We are looking for a talented and results-driven Business Development Consultant and Proposal Writer with a minimum of 5 years of proven experience in government contracting. The ideal candidate is a self-starter, well-versed in federal, state, and local procurement processes, and capable of developing winning proposals that meet or exceed client expectations. While Shipley certification is considered ideal, it is not mandatory.\nResponsibilities:\n\nConduct market research to identify government contracting opportunities at the federal, state, and local levels.\nDevelop and maintain relationships with government agencies, prime contractors, and potential teaming partners.\nCollaborate with clients to understand their needs and goals, providing strategic advice on government contracting strategies.\nWrite, review, and edit comprehensive and compelling proposals, ensuring compliance with all RFP/RFQ requirements.\nManage the entire proposal development process, including proposal schedule, content, and coordination with subject matter experts.\nEnsure proposals are submitted accurately and on time.\nMonitor and analyze government procurement trends, regulations, and changes in the competitive landscape.\nContinuously improve proposal development processes and templates.\nStay updated on industry best practices and innovations in government contracting.\n\nQualifications:\n\nMinimum of 5 years of experience in government contracting, with a proven track record of winning contracts.\nStrong knowledge of federal, state, and local procurement processes and regulations.\nExceptional writing, editing, and proofreading skills.\nAbility to work independently and as part of a team.\nExcellent communication and interpersonal skills.\nProficiency in Microsoft Office Suite and proposal development tools.\nShipley certification (ideal, but not required).\n\nJob Types: Full-time, Part-time, Contract, Temporary\nPay: $25.00 - $35.00 per hour\nExpected hours: 10 \u2013 30 per week\nBenefits:\n\nFlexible schedule\n\nSchedule:\n\n4 hour shift\n8 hour shift\nMonday to Friday\n\nTravel requirement:\n\nNo travel\n\nApplication Question(s):\n\nAre you open to part-time or freelance work?\nWhat is your HOURLY pay requirement?\nIf hired, when is the soonest you can start working?\n\nWork Location: Remote", "job_is_remote": true, "job_posted_at_timestamp": 1706815160, "job_posted_at_datetime_utc": "2024-02-01T19:19:20.000Z", "job_city": "Remote", "job_state": "OR", "job_country": "US", "job_latitude": 43.005947, "job_longitude": -123.89259, "job_benefits": null, "job_google_link": "https://www.google.com/search?gl=us&hl=en&rciv=jb&q=business+development+consultant&start=10&ibp=htl;jobs#fpstate=tldetail&htivrt=jobs&htiq=business+development+consultant&htidocid=WvwwjtIMiWFZRB3OAAAAAA%3D%3D", "job_offer_expiration_datetime_utc": "2024-05-31T19:52:56.000Z", "job_offer_expiration_timestamp": 1717185176, "job_required_experience": {"no_experience_required": false, "required_experience_in_months": 60, "experience_mentioned": true, "experience_preferred": false}, "job_required_skills": null, "job_required_education": {"postgraduate_degree": false, "professional_certification": false, "high_school": false, "associates_degree": false, "bachelors_degree": false, "degree_mentioned": false, "degree_preferred": false, "professional_certification_mentioned": true}, "job_experience_in_place_of_education": false, "job_min_salary": 25, "job_max_salary": 35, "job_salary_currency": "USD", "job_salary_period": "HOUR", "job_highlights": {"Qualifications": ["Position Overview:We are looking for a talented and results-driven Business Development Consultant and Proposal Writer with a minimum of 5 years of proven experience in government contracting", "The ideal candidate is a self-starter, well-versed in federal, state, and local procurement processes, and capable of developing winning proposals that meet or exceed client expectations", "Minimum of 5 years of experience in government contracting, with a proven track record of winning contracts", "Strong knowledge of federal, state, and local procurement processes and regulations", "Exceptional writing, editing, and proofreading skills", "Ability to work independently and as part of a team", "Excellent communication and interpersonal skills", "Proficiency in Microsoft Office Suite and proposal development tools", "Shipley certification (ideal, but not required)"], "Responsibilities": ["Conduct market research to identify government contracting opportunities at the federal, state, and local levels", "Develop and maintain relationships with government agencies, prime contractors, and potential teaming partners", "Collaborate with clients to understand their needs and goals, providing strategic advice on government contracting strategies", "Write, review, and edit comprehensive and compelling proposals, ensuring compliance with all RFP/RFQ requirements", "Manage the entire proposal development process, including proposal schedule, content, and coordination with subject matter experts", "Ensure proposals are submitted accurately and on time", "Monitor and analyze government procurement trends, regulations, and changes in the competitive landscape", "Continuously improve proposal development processes and templates", "Stay updated on industry best practices and innovations in government contracting"], "Benefits": ["Pay: $25.00 - $35.00 per hour", "Expected hours: 10 \u2013 30 per week", "Flexible schedule"]}, "job_job_title": "Business", "job_posting_language": "en", "job_onet_soc": "41401400", "job_onet_job_zone": null}