{"job_id": "hMTyp_uKMxlbJf0VAAAAAA==", "employer_name": "FINN Partners", "employer_logo": "https://media.licdn.com/dms/image/C561BAQFAadprBuydMA/company-background_10000/0/1584474258832/zpr_a_finn_partners_company_cover?e=2147483647&v=beta&t=u5rgopXUoSYkjbUg3WmGxy5N_J75NKM4Y6FwXRxmOog", "employer_website": "http://www.finnpartners.com", "employer_company_type": null, "job_publisher": "LinkedIn", "job_employment_type": "FULLTIME", "job_title": "B2B Media Director", "job_apply_link": "https://www.linkedin.com/jobs/view/b2b-media-director-at-finn-partners-3853849169", "job_apply_is_direct": false, "job_apply_quality_score": 0.6376, "apply_options": [{"publisher": "LinkedIn", "apply_link": "https://www.linkedin.com/jobs/view/b2b-media-director-at-finn-partners-3853849169", "is_direct": false}, {"publisher": "ZipRecruiter", "apply_link": "https://www.ziprecruiter.com/c/Finn-Partners/Job/B2B-Media-Director/-in-Washington,DC?jid=eabd4cc24c4efaa8", "is_direct": true}, {"publisher": "Indeed", "apply_link": "https://www.indeed.com/viewjob?jk=00d30ee8c502f815", "is_direct": true}, {"publisher": "Media Bistro", "apply_link": "https://www.mediabistro.com/jobs/214222514-b2b-media-director", "is_direct": false}, {"publisher": "ShowbizJobs", "apply_link": "https://www.showbizjobs.com/jobs/finn-partners-b2b-media-director-in-new-york/jid-d8e9x9", "is_direct": false}, {"publisher": "Finn Partners - JazzHR", "apply_link": "https://joinus.applytojob.com/apply/RrWoxaOrjZ/B2B-Media-Director", "is_direct": false}, {"publisher": "Jobright AI", "apply_link": "https://jobright.ai/jobs/info/65effdad8ae2a7521df198f4", "is_direct": false}], "job_description": "Come Join FINN Partners, a leading firm in the digital marketing space, dedicated to leveraging innovative technologies and strategies to drive growth for our clients. We are seeking an experienced B2B Media Director to join our Global Intelligence team. Our team is composed of passionate, skilled professionals who thrive in a fast-paced environment and are committed to staying at the forefront of the digital marketing industry.\n\nPosition Summary\n\nAs Media Director at Finn Partners, you will oversee multiple planning groups, provide strategic leadership, and understand all aspects of their client\u2019s business and efforts to market their products and services to other companies - with a B2B background and expertise at the helm.\n\nThe successful candidate will oversee a team responsible for developing multi-channel media plans in accordance with the objectives, strategies, and goals communicated by Account Management teams and Clients.\n\nResponsibilities\n\u2022 Take charge of the planning output for multiple clients, maintaining consistency to deliver unparalleled work\n\u2022 Assist in new business development and pitches, acting as the primary media SME on respective needs\n\u2022 Interpret research and provide insight that effectively translates brand marketing objectives into succinct media strategies\n\u2022 Actively provide and discuss industry information on media, markets, and related dynamics\n\u2022 Accurately represent the client's point of view when reviewing work, leveraging this perspective when providing feedback to the team and presenting to client\n\u2022 Direct/own the development of client presentations and other important communication, making sure that it is clear, compelling, and persuasive\n\u2022 Build and maintain client trust at all levels, including senior clients\n\u2022 Oversee more junior team members to ensure consistent and high-quality deliverables\n\u2022 Ensure all deliverables are aligned with media strategy\n\u2022 Manage performance reviews, coaching to maximize success, setting goals for career development\n\u2022 Foster a performance-first culture that rallies around delivering client results\n\u2022 Assist in new business idea creations, scoping, presentation development, etc.\n\u2022 Be a leader that clients look to for strategy and the team looks to for guidance\n\nEducation and Experience:\n\u2022 Bachelor\u2019s degree\n\u2022 7-10 years advertising or media agency experience, with high level clients (both digital and offline)\n\u2022 Expertise in B2B marketing strategies: you understand the complexities of B2B sales cycles, lead and demand generation, and the development of targeted communication strategies that address the unique needs of business clients\n\u2022 Skills in complex sale navigations: Emphasize the ability to craft media campaigns tailored to decision-makers within businesses, understanding the multiple touchpoints and stakeholders involved in B2B decisions\n\u2022 Proficiency in analytics and data-driven decision-making: Proficiency in using analytics to inform strategies, understand customer behavior in a B2B context, and measure the effectiveness of campaigns in generating leads and driving sales\n\u2022 Experience with account-based marketing (ABM): Proven experience in implementing ABM strategies, focusing on targeting key accounts with personalized marketing campaigns. You should have expertise in identifying high-value accounts, engaging with stakeholders through customized communications, and leveraging data analytics to refine and optimize ABM efforts. B2C, B2G and other sectors experience a plus\n\nKnowledge & Skill Requirements\n\u2022 G Suite (sheets, docs, slides), Microsoft Office (Word, PowerPoint, Excel)\n\u2022 Self-serve social media platforms (Facebook, Twitter, LinkedIn, Pinterest, Snapchat)\n\u2022 Knowledge of media tools and research providers (comScore, Nielsen, MNI, MRI, Mintel, etc.)\n\u2022 Google Marketing platform (Campaign Manager, Google Analytics, Google Data Studio)\n\u2022 Believer in the importance of the role of data & analytics in decision making\n\u2022 Ability to rally team members around a new solution\n\u2022 Ability to conduct critical analysis and identify key insights\n\u2022 Strong written, verbal, and visual communication skills\n\u2022 Proactive and self-motivated\n\u2022 Excellent problem solving skills\n\u2022 Solid project management and organizational skills\n\u2022 High level of accuracy and attention to detail\n\u2022 Ability to deliver sound strategy that aligns directly to client business goals\n\u2022 Experience overseeing the full suite of media channels into a single mix\n\u2022 Excellent presentation skills\n\u2022 Resourceful, with proven problem-solving skills\n\nWhy Join FINN Partners?\n\u2022 Opportunity to work in a dynamic environment at the intersection of digital marketing and data science.\n\u2022 Access to state-of-the-art tools and technologies for advanced analytics and data science projects.\n\u2022 Competitive salary, benefits package, and a commitment to work-life balance.\n\u2022 A culture that values innovation, continuous learning, and collaboration.\n\u2022 Career advancement opportunities in a fast-growing company.\n\nAnticipated Salary: Compensation is up to $135,000 depending on work experience.\n\nHow To Apply\n\nPlease send your resume, a cover letter highlighting your relevant experience in media, and any examples of plans you\u2019re able/willing to share to [insert application email or link]. Please include \" Media Director Application\" in the subject line.\n\nFINN Partners is an equal opportunity employer that values diversity and inclusion. We encourage applications from all qualified individuals, regardless of race, color, religion, gender, sexual orientation, gender identity or expression, age, national origin, marital status, citizenship, disability, veteran status, or any other characteristic protected by law.\n\nAbout FINN Partners:\u202f\n\nFINN Partners was launched in 2011 to realize Peter Finn's vision to create a leading communications agency dedicated to shaping a bold new future in which innovation and partnership are strong drivers of the brand. FINN Partners specializes in the full spectrum of communications services, including digital and social media. Practice areas include arts, consumer lifestyle & sports, corporate social responsibility, education, health, manufacturing, technology, travel, and public affairs.\u202f\n\nWe are entrepreneurial-minded, global, and focused on\u202fintegrated programs that bring to life the world-changing technologies, products, and services of our client partners.\u202f\u202fOur company culture celebrates delighting our clients with innovative and creative campaigns and programs, and we provide opportunities for our employees to conduct career-meaningful work in a creative, fast-paced, collaborative, and fun environment. We work hard and play nice.", "job_is_remote": true, "job_posted_at_timestamp": 1710216845, "job_posted_at_datetime_utc": "2024-03-12T04:14:05.000Z", "job_city": null, "job_state": null, "job_country": "US", "job_latitude": 37.09024, "job_longitude": -95.71289, "job_benefits": ["health_insurance"], "job_google_link": "https://www.google.com/search?gl=us&hl=en&rciv=jb&q=director+of+brand+partnerships&start=60&ibp=htl;jobs#fpstate=tldetail&htivrt=jobs&htiq=director+of+brand+partnerships&htidocid=hMTyp_uKMxlbJf0VAAAAAA%3D%3D", "job_offer_expiration_datetime_utc": "2024-04-11T04:14:05.000Z", "job_offer_expiration_timestamp": 1712808845, "job_required_experience": {"no_experience_required": false, "required_experience_in_months": 84, "experience_mentioned": true, "experience_preferred": true}, "job_required_skills": null, "job_required_education": {"postgraduate_degree": false, "professional_certification": false, "high_school": false, "associates_degree": false, "bachelors_degree": true, "degree_mentioned": true, "degree_preferred": false, "professional_certification_mentioned": false}, "job_experience_in_place_of_education": false, "job_min_salary": null, "job_max_salary": null, "job_salary_currency": null, "job_salary_period": null, "job_highlights": {"Qualifications": ["Bachelor\u2019s degree", "7-10 years advertising or media agency experience, with high level clients (both digital and offline)", "Expertise in B2B marketing strategies: you understand the complexities of B2B sales cycles, lead and demand generation, and the development of targeted communication strategies that address the unique needs of business clients", "Skills in complex sale navigations: Emphasize the ability to craft media campaigns tailored to decision-makers within businesses, understanding the multiple touchpoints and stakeholders involved in B2B decisions", "Proficiency in analytics and data-driven decision-making: Proficiency in using analytics to inform strategies, understand customer behavior in a B2B context, and measure the effectiveness of campaigns in generating leads and driving sales", "Experience with account-based marketing (ABM): Proven experience in implementing ABM strategies, focusing on targeting key accounts with personalized marketing campaigns", "You should have expertise in identifying high-value accounts, engaging with stakeholders through customized communications, and leveraging data analytics to refine and optimize ABM efforts", "G Suite (sheets, docs, slides), Microsoft Office (Word, PowerPoint, Excel)", "Self-serve social media platforms (Facebook, Twitter, LinkedIn, Pinterest, Snapchat)", "Knowledge of media tools and research providers (comScore, Nielsen, MNI, MRI, Mintel, etc.)", "Google Marketing platform (Campaign Manager, Google Analytics, Google Data Studio)", "Believer in the importance of the role of data & analytics in decision making", "Ability to rally team members around a new solution", "Ability to conduct critical analysis and identify key insights", "Strong written, verbal, and visual communication skills", "Proactive and self-motivated", "Excellent problem solving skills", "Solid project management and organizational skills", "High level of accuracy and attention to detail", "Ability to deliver sound strategy that aligns directly to client business goals", "Experience overseeing the full suite of media channels into a single mix", "Excellent presentation skills", "Resourceful, with proven problem-solving skills"], "Responsibilities": ["As Media Director at Finn Partners, you will oversee multiple planning groups, provide strategic leadership, and understand all aspects of their client\u2019s business and efforts to market their products and services to other companies - with a B2B background and expertise at the helm", "The successful candidate will oversee a team responsible for developing multi-channel media plans in accordance with the objectives, strategies, and goals communicated by Account Management teams and Clients", "Take charge of the planning output for multiple clients, maintaining consistency to deliver unparalleled work", "Assist in new business development and pitches, acting as the primary media SME on respective needs", "Interpret research and provide insight that effectively translates brand marketing objectives into succinct media strategies", "Actively provide and discuss industry information on media, markets, and related dynamics", "Accurately represent the client's point of view when reviewing work, leveraging this perspective when providing feedback to the team and presenting to client", "Direct/own the development of client presentations and other important communication, making sure that it is clear, compelling, and persuasive", "Build and maintain client trust at all levels, including senior clients", "Oversee more junior team members to ensure consistent and high-quality deliverables", "Ensure all deliverables are aligned with media strategy", "Manage performance reviews, coaching to maximize success, setting goals for career development", "Foster a performance-first culture that rallies around delivering client results", "Assist in new business idea creations, scoping, presentation development, etc", "Be a leader that clients look to for strategy and the team looks to for guidance"], "Benefits": ["Competitive salary, benefits package, and a commitment to work-life balance", "A culture that values innovation, continuous learning, and collaboration", "Career advancement opportunities in a fast-growing company", "Anticipated Salary: Compensation is up to $135,000 depending on work experience"]}, "job_job_title": "Director", "job_posting_language": "en", "job_onet_soc": "41301100", "job_onet_job_zone": "4"}