{"job_id": "kdbI682R65AspNIOAAAAAA==", "employer_name": "Devo", "employer_logo": null, "employer_website": null, "employer_company_type": null, "job_publisher": "Jobvite", "job_employment_type": "FULLTIME", "job_title": "Senior Manager, Cloud Alliances", "job_apply_link": "https://jobs.jobvite.com/devo/job/oMRqpfwc", "job_apply_is_direct": false, "job_apply_quality_score": 0.816, "apply_options": [{"publisher": "Jobvite", "apply_link": "https://jobs.jobvite.com/devo/job/oMRqpfwc", "is_direct": false}, {"publisher": "VentureFizz", "apply_link": "https://venturefizz.com/jobs/senior-manager-cloud-alliances-at-devo", "is_direct": false}, {"publisher": "LinkedIn", "apply_link": "https://www.linkedin.com/jobs/view/senior-manager-cloud-alliances-at-devo-3766132298", "is_direct": false}], "job_description": "Senior Manager, Cloud Partnerships\n\nDevo is the only cloud-native logging and security analytics platform that releases the full potential of your data to empower bold, confident action. With unrivaled scale to collect all of your data without compromise, speed to give you immediate access and answers, and clarity to focus on the signals that matter most, Devo is your ally in protecting your organization today and tomorrow. Headquartered in Cambridge, Mass., Devo is backed by Insight Partners, Georgian, TCV, General Atlantic, Bessemer Venture Partners, Kibo Ventures and Eurazeo. Learn more at www.devo.com.\n\nDevo is proud to be recognized as a Great Place to Work\u00ae.\n\nJOB DESCRIPTION\n\nAs the Senior Manager, Cloud Partnerships, you will have worldwide responsibility to manage Cloud Partnerships for Devo. You will manage strategy, sales, go-to-market, enablement, operations, and executive relationships to drive adoption of Devo within customers leveraging these partners cloud platforms. This role will be responsible to drive revenue for Devo by leveraging these cloud partnerships and their respective marketplace offerings.\n\nResponsibilities\n\nYou will be responsible to drive the success of Devo\u2019s cloud partnerships to ensure Devo is listed and promoted on the cloud providers store/marketplace, is promoted and discussed as the key log management and security analytics platform and also aligned to the providers future roadmap.\n\nSpecifically:\n\u2022 Develop and implement the partnership strategy, including strategic sales and go-to market plans\n\u2022 Develop and manage partner marketing programs, and collaborate with Sales and Marketing to execute partner marketing campaigns\n\u2022 Manage programs to maximize sales revenue, touch, and influence for the cloud partner\n\u2022 Represent Devo by driving business development initiatives\n\u2022 Engage in business development and ongoing partner success\n\u2022 Be accountable for partner sales quotas and partnership P&L\n\u2022 Develop and actively maintain partner sales forecasts across assigned accounts and lines of business\n\u2022 Measure and report results of partner plan execution\n\u2022 Identify areas for improvement and act to implement positive change\n\u2022 Manage development and execution of external and internal partner communications plans\n\u2022 Collaborate with Sales, Products, and Marketing to develop new product offerings\n\nIn this role, you will build a critical mass of interest and enthusiasm for Devo\u2019s technology and product offerings, and help to establish Devo as the enterprise wide log management and security analytics platform within the strategic cloud partners and other cloud partnerships worldwide. You will work with your partners to help target, identify, recruit and sell-to customers that are seeking an enterprise wide solution.\n\nWho are we looking for?\n\nThe ideal person will have an existing network of partner contacts at the key providers like AWS, that they can call upon to help grow and expand Devo\u2019s presence. This person will have excellent communication & negotiation skills to drive this channel. This person can multi-task, is self-motivated, while still interacting well with a team; is highly organized with high energy level and can-do attitude.\n\nRequirements:\n\u2022 8+ years of experience in an alliance management role working with technology & cloud providers\n\u2022 Experience as a business development leader, sales strategy, partner management, working with enterprise software products or services\n\u2022 Ability to recruit, enable and drive business with cloud providers\n\u2022 Recent familiarity or hands-on experience with:\n\u2022 Security Software\n\u2022 Cloud computing environments (AWS, Azure, and Google Compute)\n\u2022 Log Management and SIEM basics\n\u2022 Knowledge of general security practices, regulatory compliance requirements, organizational structures and corporate cultures.\n\u2022 Certifications such as CISSP, SSSP are preferred\n\nCompensation\n\nThis role will have a general pay range of $125,000.00 to $140,000.00. The provided base salary range is what we expect to pay a substantially qualified candidate, with final offer being based on the candidate\u2019s relevant experience and skills, as well as location and other factors. Total compensation for the role will include base salary, as well as a bonus or commission target and an equity grant applicable to the level of the role.\n\nWhy work at Devo?\n\u2022 You\u2019ll join a Great Place to Work\u00ae certified company where we value our people and provide the tremendous opportunities that come with a hyper-growth organization.\n\u2022 Be part of an international company with a strong team culture that celebrates success. Share our core values: Be bold - Be Inventive - Be humble - Be an ally.\n\u2022 A flexible work environment that lets you work in the way that works best for you \u2014 in office, fully remote, or hybrid.\n\u2022 Work in an environment that will challenge you and enable you to grow as a professional with training and professional development to help you reach your goals.\n\u2022 Comprehensive Benefits including Healthcare 401K, Employee Stock Option plan, Employee referral program, and so much more!\n\n\"Devo is committed to creating a welcoming culture that is not only grounded in teamwork and customer success but is fair and equitable for everyone.\" Marc van Zadelhoff, CEO.\n\nAt Devo, diversity and inclusion means more than treating employees well and making them feel welcome. It is a commitment to hiring people who bring different insights because of their unique perspectives, ways of thinking, and prior experiences.\n\nDevo does not discriminate on the basis of race, color, national origin, religion, gender, age, veteran status, sexual orientation, marital status or disability (in compliance with the Americans with Disabilities Act) with respect to employment opportunities.", "job_is_remote": false, "job_posted_at_timestamp": 1699401600, "job_posted_at_datetime_utc": "2023-11-08T00:00:00.000Z", "job_city": null, "job_state": null, "job_country": "US", "job_latitude": 37.09024, "job_longitude": -95.71289, "job_benefits": ["health_insurance", "retirement_savings"], "job_google_link": "https://www.google.com/search?gl=us&hl=en&rciv=jb&q=senior+manager+of+brand+partnerships&start=10&ibp=htl;jobs#fpstate=tldetail&htivrt=jobs&htiq=senior+manager+of+brand+partnerships&htidocid=kdbI682R65AspNIOAAAAAA%3D%3D", "job_offer_expiration_datetime_utc": null, "job_offer_expiration_timestamp": null, "job_required_experience": {"no_experience_required": false, "required_experience_in_months": 96, "experience_mentioned": true, "experience_preferred": false}, "job_required_skills": null, "job_required_education": {"postgraduate_degree": false, "professional_certification": false, "high_school": false, "associates_degree": false, "bachelors_degree": false, "degree_mentioned": false, "degree_preferred": false, "professional_certification_mentioned": true}, "job_experience_in_place_of_education": false, "job_min_salary": null, "job_max_salary": null, "job_salary_currency": null, "job_salary_period": null, "job_highlights": {"Qualifications": ["This person will have excellent communication & negotiation skills to drive this channel", "This person can multi-task, is self-motivated, while still interacting well with a team; is highly organized with high energy level and can-do attitude", "8+ years of experience in an alliance management role working with technology & cloud providers", "Experience as a business development leader, sales strategy, partner management, working with enterprise software products or services", "Ability to recruit, enable and drive business with cloud providers", "Recent familiarity or hands-on experience with:", "Security Software", "Cloud computing environments (AWS, Azure, and Google Compute)", "Log Management and SIEM basics", "Knowledge of general security practices, regulatory compliance requirements, organizational structures and corporate cultures"], "Responsibilities": ["As the Senior Manager, Cloud Partnerships, you will have worldwide responsibility to manage Cloud Partnerships for Devo", "You will manage strategy, sales, go-to-market, enablement, operations, and executive relationships to drive adoption of Devo within customers leveraging these partners cloud platforms", "This role will be responsible to drive revenue for Devo by leveraging these cloud partnerships and their respective marketplace offerings", "You will be responsible to drive the success of Devo\u2019s cloud partnerships to ensure Devo is listed and promoted on the cloud providers store/marketplace, is promoted and discussed as the key log management and security analytics platform and also aligned to the providers future roadmap", "Develop and implement the partnership strategy, including strategic sales and go-to market plans", "Develop and manage partner marketing programs, and collaborate with Sales and Marketing to execute partner marketing campaigns", "Manage programs to maximize sales revenue, touch, and influence for the cloud partner", "Represent Devo by driving business development initiatives", "Engage in business development and ongoing partner success", "Be accountable for partner sales quotas and partnership P&L", "Develop and actively maintain partner sales forecasts across assigned accounts and lines of business", "Measure and report results of partner plan execution", "Identify areas for improvement and act to implement positive change", "Manage development and execution of external and internal partner communications plans", "Collaborate with Sales, Products, and Marketing to develop new product offerings", "In this role, you will build a critical mass of interest and enthusiasm for Devo\u2019s technology and product offerings, and help to establish Devo as the enterprise wide log management and security analytics platform within the strategic cloud partners and other cloud partnerships worldwide", "You will work with your partners to help target, identify, recruit and sell-to customers that are seeking an enterprise wide solution"], "Benefits": ["This role will have a general pay range of $125,000.00 to $140,000.00", "The provided base salary range is what we expect to pay a substantially qualified candidate, with final offer being based on the candidate\u2019s relevant experience and skills, as well as location and other factors", "Total compensation for the role will include base salary, as well as a bonus or commission target and an equity grant applicable to the level of the role", "Work in an environment that will challenge you and enable you to grow as a professional with training and professional development to help you reach your goals", "Comprehensive Benefits including Healthcare 401K, Employee Stock Option plan, Employee referral program, and so much more!"]}, "job_job_title": "Senior manager", "job_posting_language": "en", "job_onet_soc": "11302100", "job_onet_job_zone": "4"}