{"job_id": "2U3aQK0N9pNHij2WAAAAAA==", "employer_name": "Mosaic Consulting Group", "employer_logo": "https://encrypted-tbn0.gstatic.com/images?q=tbn:ANd9GcQPi404JOM5zElc4NuRzvFjA4niotQVNDJjla2k&s=0", "employer_website": "http://www.mosaic-cg.com", "employer_company_type": null, "job_publisher": "LinkedIn", "job_employment_type": "FULLTIME", "job_title": "VP of Business Development\u202f& Marketing", "job_apply_link": "https://www.linkedin.com/jobs/view/vp-of-business-development%E2%80%AF-marketing-at-mosaic-consulting-group-3851869226", "job_apply_is_direct": false, "job_apply_quality_score": 0.6434, "apply_options": [{"publisher": "LinkedIn", "apply_link": "https://www.linkedin.com/jobs/view/vp-of-business-development%E2%80%AF-marketing-at-mosaic-consulting-group-3851869226", "is_direct": false}], "job_description": "Based in Nashville, Tennessee, Mosaic Consulting Group helps businesses of all sizes and across all industries leverage their investment in UKG HCM & WFM Technologies. We are more than a consulting company; we are a highly skilled team delivering value and exceptional service to our clients. Every day we strive to live up to our promise: Make a difference and inspire confidence. Because of our dedication to client and team experience, we have been recognized on the Inc. 5000 list for 4 consecutive years and are certified as a Great Place to Work.\n\nWe are looking for a remote VP of Business Development & Marketing to serve as a leader for Mosaic on the Executive team, and lead the Client Engagement and Marketing teams. In this role, you would oversee our net-new sales team and processes to help us achieve our sales and revenue goals.\n\nWhat you\u2019ll do:\n\u2022 Create and execute on Client Engagement team strategy, including revenue targets, pricing strategies, and alignment to our sales methodology\n\u2022 Focus on building a consultative sales approach and fostering this approach within the team\n\u2022 Leverage your industry expertise to partner with our prospective clients and recommend solutions that are in line with industry trends and market conditions\n\u2022 Build relationships with various channels to expand Mosaic\u2019s footprint and drive long term, mutually beneficial partnerships. This includes building relationships with the Global Alliance team and Sales team within UKG\n\u2022 Lead, engage, and mentor your team to accomplish developmental and company goals, most notably team revenue goals\n\u2022 Partner with team members throughout the company to hone our sales to service processes\n\u2022 Own sales data and provide weekly updates to executive team on revenue projections, sales pipeline, and other data as needed\n\nWhat makes you successful:\n\nNeed to haves:\n\u2022 Bachelor\u2019s degree or equivalent work experience\n\u2022 8-10+ years of Professional Services sales experience\n\u2022 5+ years of experience in the HCM industry\n\u2022 Experience building, leading and motivating a high growth, fast-paced sales team\n\u2022 Ability to travel as needed\n\u2022 Effective leadership and team building skills\n\u2022 Strong relationships within UKG implementation partner ecosystem\n\u2022 UKG product experience (UltiPro & Kronos)\n\nHow you\u2019ll be measured:\n\u2022 Achievement of revenue goals\n\u2022 Achievement of EBITDA goals\n\u2022 Building a team of 80% stars through hiring, skill development, and removing under performers\n\u2022 Increasing average closed/won deal size\n\u2022 Building strategic partnerships in the ecosystem and beyond\n\nWhat we offer you:\n\u2022 The ability to put your sales philosophies to the test and lead a high-growth sales practice\n\u2022 An opportunity to learn the ins and outs of a small and rapidly growing business\n\u2022 A competitive salary with 25% bonus potential, and comprehensive benefits and PTO package\n\u2022 Deferred profit sharing, stipend for reading books, wellness program, and other unique perks like unlimited time off", "job_is_remote": true, "job_posted_at_timestamp": 1710174197, "job_posted_at_datetime_utc": "2024-03-11T16:23:17.000Z", "job_city": null, "job_state": null, "job_country": "US", "job_latitude": 37.09024, "job_longitude": -95.71289, "job_benefits": ["health_insurance", "paid_time_off"], "job_google_link": "https://www.google.com/search?gl=us&hl=en&rciv=jb&q=vice+president+of+business+development&start=80&ibp=htl;jobs#fpstate=tldetail&htivrt=jobs&htiq=vice+president+of+business+development&htidocid=2U3aQK0N9pNHij2WAAAAAA%3D%3D", "job_offer_expiration_datetime_utc": "2024-09-07T16:23:17.000Z", "job_offer_expiration_timestamp": 1725726197, "job_required_experience": {"no_experience_required": false, "required_experience_in_months": 96, "experience_mentioned": true, "experience_preferred": false}, "job_required_skills": null, "job_required_education": {"postgraduate_degree": false, "professional_certification": false, "high_school": false, "associates_degree": false, "bachelors_degree": true, "degree_mentioned": true, "degree_preferred": false, "professional_certification_mentioned": false}, "job_experience_in_place_of_education": false, "job_min_salary": null, "job_max_salary": null, "job_salary_currency": null, "job_salary_period": null, "job_highlights": {"Qualifications": ["Bachelor\u2019s degree or equivalent work experience", "8-10+ years of Professional Services sales experience", "5+ years of experience in the HCM industry", "Experience building, leading and motivating a high growth, fast-paced sales team", "Ability to travel as needed", "Effective leadership and team building skills", "Strong relationships within UKG implementation partner ecosystem", "UKG product experience (UltiPro & Kronos)"], "Responsibilities": ["In this role, you would oversee our net-new sales team and processes to help us achieve our sales and revenue goals", "Create and execute on Client Engagement team strategy, including revenue targets, pricing strategies, and alignment to our sales methodology", "Focus on building a consultative sales approach and fostering this approach within the team", "Leverage your industry expertise to partner with our prospective clients and recommend solutions that are in line with industry trends and market conditions", "Build relationships with various channels to expand Mosaic\u2019s footprint and drive long term, mutually beneficial partnerships", "This includes building relationships with the Global Alliance team and Sales team within UKG", "Lead, engage, and mentor your team to accomplish developmental and company goals, most notably team revenue goals", "Partner with team members throughout the company to hone our sales to service processes", "Own sales data and provide weekly updates to executive team on revenue projections, sales pipeline, and other data as needed", "Building a team of 80% stars through hiring, skill development, and removing under performers", "Increasing average closed/won deal size", "Building strategic partnerships in the ecosystem and beyond"], "Benefits": ["A competitive salary with 25% bonus potential, and comprehensive benefits and PTO package", "Deferred profit sharing, stipend for reading books, wellness program, and other unique perks like unlimited time off"]}, "job_job_title": "Marketing", "job_posting_language": "en", "job_onet_soc": "11202100", "job_onet_job_zone": "4"}