{"job_id": "ZjeB0nH8tJiycHvdAAAAAA==", "employer_name": "WAC Lighting", "employer_logo": "https://encrypted-tbn0.gstatic.com/images?q=tbn:ANd9GcQR15RVBmSepff9-nIwkGkiMKOvJGVwkA-s8xko&s=0", "employer_website": "http://www.waclighting.com", "employer_company_type": null, "job_publisher": "Glassdoor", "job_employment_type": "FULLTIME", "job_title": "Executive Vice President Business Development - Lighting", "job_apply_link": "https://www.glassdoor.com/job-listing/executive-vice-president-business-development-lighting-wac-lighting-JV_IC1132379_KO0,54_KE55,67.htm?jl=1009122511469", "job_apply_is_direct": true, "job_apply_quality_score": 0.6454, "apply_options": [{"publisher": "Glassdoor", "apply_link": "https://www.glassdoor.com/job-listing/executive-vice-president-business-development-lighting-wac-lighting-JV_IC1132379_KO0,54_KE55,67.htm?jl=1009122511469", "is_direct": true}, {"publisher": "Indeed", "apply_link": "https://www.indeed.com/viewjob?jk=22088203e888198a", "is_direct": true}, {"publisher": "SimplyHired", "apply_link": "https://www.simplyhired.com/job/nhz7NcoM55V-mXlfTlT2ARrIYOpe0BOy1wNZy2gBbeFi3742blRbvw", "is_direct": false}, {"publisher": "Jobright AI", "apply_link": "https://jobright.ai/jobs/info/65d9fbaacdea5fc140eed8c7", "is_direct": false}], "job_description": "Born with a global vision and rapid-paced culture in New York, WAC Lighting has disrupted and elevated the lighting industry by challenging conventions and building sustainable products responsibly. With six thriving brands and more on the horizon, this unparalleled, vertically integrated world-class organization includes WAC Lighting, Modern Forms Luminaires + Smart Fans, Schonbek, dweLED, WAC Landscape, and Limited brands with $500 million+ in annual revenue. The group has made significant investments in breakthrough technologies, electronics research and development, rigorous testing, advanced engineering, and eco-friendly manufacturing while giving back to the local and global communities, providing thought-leadership, and solving challenges with creativity and innovation.\n\nOverview:\n\nThe incumbent will be a highly polished corporate C-Suite Level Executive to serve as a committed and driven agent of change. Reporting directly to the CEO, the EVP of Business Development will have direct oversight of Sales, Research and Development, and Marketing. Major accountabilities involve the formulation and implementation of strategic recommendations and delivery of innovative solutions, delivering fast, scalable, cumulative, and continuous growth across all brands.\n\nThe EVP of Business Development will lead by modeling the entrepreneurial, ambitious, and humble culture of our organization which defines our uniquely innovative, rich history and tradition. They are a leader who has significant experience in the development and management of complex sales, and an understanding of the channel and distributed sales ecosystem.\n\nThe EVP of Business Development is expected to help provide vision and strategic direction for the company. They will have responsibility and accountability for meeting the goals and objectives of the company and will develop growth strategies and identify business opportunities that lead to future financial growth. This leader will have a history of exceeding sales quotas, building sales teams, and developing and delivering growth for multiple company brands.\n\nKey responsibilities & essential job functions include, but are not limited to:\n\u2022 Foster a positive working environment, which allows employees the opportunity for professional growth, and accountability. This person must have \u201cLeadership Agility\u201d in order to maintain business success in our increasingly complex, fast-paced and changing business environment.\n\u2022 Own and drive full accountability for development and implementation of product marketing and product development strategy and initiatives, client communication, process improvement, industry research, and ROI from daily activities.\n\u2022 Ownership for sales. Drive achievement of annual sales targets and profitability targets. Develop and manage division sales and expense budgets. Drive the resolution to amicably overcome channel conflicts.\n\u2022 Identify, develop and drive innovative new product lines and company brands. Be a strong leader focused on growth, rallying a team comprised of internal and external business development representatives and other stakeholders to deliver revenue goals.\n\u2022 Facilitate annual strategic review and goal setting processes by identifying gaps and obstacles in reaching the monthly, quarterly, and annual sales goals.\n\u2022 Deliver regular reporting to CEO on market analysis with a focus upon competition, pricing, market conditions, as well as new and existing product lines.\n\u2022 Provide recommendations on new products and technologies to meet market demands.\n\u2022 Collaborate with executive leadership team to develop and execute the company\u2019s strategic plan.\n\u2022 Continually evaluates the effectiveness of the business development performance against market constraints and changes and revises the business development plan as appropriate.\n\u2022 Work with Marketing to develop new ways to attract and engage leads to track and adjust marketing spend to drive sales ROI.\n\u2022 Continuously develop fresh and creative initiatives to drive sales team success.\n\u2022 Develop and deploy cross functional tools, policies, and practices to drive sales, increase profitability and streamline process. Analyze data and synthesize it into areas of sales and marketing focus, sales tools needed, technology solutions required, etc.\n\u2022 Drive strategic cross functional team leadership in areas of R&D, Sales, Specification Sales, Product Marketing, Sales Support, and Integration Business Development.\n\u2022 Provide subject matter expertise and direction in accordance with entrepreneurial culture, policies, and core values.\n\u2022 Cultivate and maintain strong, effective relationships with all internal and external stakeholders.\n\u2022 Maintain and leverage strong customer network at influential levels \u2013 personal involvement securing outcomes with key deals and customers.\n\u2022 Work closely with business unit managers on pricing, volume and market strategies to maximize profitability and value to the company\n\u2022 Lead and improve the ability to provide an accurate sales forecast.\n\u2022 Successfully develop and manage expense budgets to meet profitability goals.\n\u2022 Human capital development, mentoring, and succession planning.\n\nRequirements For Consideration:\n\u2022 Master of Business Administration preferred.\n\u2022 15 years + of innovative lighting industry experience including managing multiple channels of distribution with the ability to amicably overcome channel conflicts.\n\u2022 A proven record of analyzing market research, competitor analysis, and industry trends and making creative recommendations based on opportunities and threats to the business.\n\u2022 P&L responsibility with a proven track record of successful sales and profitability.\n\u2022 Experience with Integrated Lean Six Sigma methodology and a track record of implementing scalable procedures that drive fast growth in an entrepreneurial environment.\n\u2022 Significant leadership experience working with multiple business channels including and not limited to large scale Showrooms, electrical distributors, Hospitality, Integration, Irrigation, specification sales and internet channels within architectural and decorative product markets.\n\u2022 Proven track record overseeing multiple product lines and brands.\n\u2022 Solid history of strategic, swift decision-making ability.\n\u2022 Documented high level verbal and written presentation skills with a strong ability to gain buy in at all levels.\n\u2022 Reputation for executing a hands-on, leadership by example management style.\n\u2022 Evidenced commitment to professional development and continuing education.\n\u2022 Experience sourcing in Asia.\n\u2022 Travel will be required, including regular presence in the NY Corporate Headquarters.", "job_is_remote": false, "job_posted_at_timestamp": 1707696000, "job_posted_at_datetime_utc": "2024-02-12T00:00:00.000Z", "job_city": "Port Washington", "job_state": "NY", "job_country": "US", "job_latitude": 40.825657, "job_longitude": -73.69819, "job_benefits": null, "job_google_link": "https://www.google.com/search?gl=us&hl=en&rciv=jb&q=vice+president+of+business+development&start=60&ibp=htl;jobs#fpstate=tldetail&htivrt=jobs&htiq=vice+president+of+business+development&htidocid=ZjeB0nH8tJiycHvdAAAAAA%3D%3D", "job_offer_expiration_datetime_utc": "2024-07-07T00:00:00.000Z", "job_offer_expiration_timestamp": 1720310400, "job_required_experience": {"no_experience_required": false, "required_experience_in_months": 180, "experience_mentioned": true, "experience_preferred": false}, "job_required_skills": null, "job_required_education": {"postgraduate_degree": false, "professional_certification": false, "high_school": false, "associates_degree": false, "bachelors_degree": false, "degree_mentioned": true, "degree_preferred": false, "professional_certification_mentioned": false}, "job_experience_in_place_of_education": false, "job_min_salary": 350000, "job_max_salary": 500000, "job_salary_currency": "USD", "job_salary_period": "YEAR", "job_highlights": {"Qualifications": ["15 years + of innovative lighting industry experience including managing multiple channels of distribution with the ability to amicably overcome channel conflicts", "A proven record of analyzing market research, competitor analysis, and industry trends and making creative recommendations based on opportunities and threats to the business", "P&L responsibility with a proven track record of successful sales and profitability", "Experience with Integrated Lean Six Sigma methodology and a track record of implementing scalable procedures that drive fast growth in an entrepreneurial environment", "Significant leadership experience working with multiple business channels including and not limited to large scale Showrooms, electrical distributors, Hospitality, Integration, Irrigation, specification sales and internet channels within architectural and decorative product markets", "Proven track record overseeing multiple product lines and brands", "Solid history of strategic, swift decision-making ability", "Documented high level verbal and written presentation skills with a strong ability to gain buy in at all levels", "Reputation for executing a hands-on, leadership by example management style", "Evidenced commitment to professional development and continuing education", "Experience sourcing in Asia", "Travel will be required, including regular presence in the NY Corporate Headquarters"], "Responsibilities": ["The incumbent will be a highly polished corporate C-Suite Level Executive to serve as a committed and driven agent of change", "Reporting directly to the CEO, the EVP of Business Development will have direct oversight of Sales, Research and Development, and Marketing", "The EVP of Business Development is expected to help provide vision and strategic direction for the company", "They will have responsibility and accountability for meeting the goals and objectives of the company and will develop growth strategies and identify business opportunities that lead to future financial growth", "This leader will have a history of exceeding sales quotas, building sales teams, and developing and delivering growth for multiple company brands", "Foster a positive working environment, which allows employees the opportunity for professional growth, and accountability", "This person must have \u201cLeadership Agility\u201d in order to maintain business success in our increasingly complex, fast-paced and changing business environment", "Own and drive full accountability for development and implementation of product marketing and product development strategy and initiatives, client communication, process improvement, industry research, and ROI from daily activities", "Ownership for sales", "Drive achievement of annual sales targets and profitability targets", "Develop and manage division sales and expense budgets", "Drive the resolution to amicably overcome channel conflicts", "Identify, develop and drive innovative new product lines and company brands", "Be a strong leader focused on growth, rallying a team comprised of internal and external business development representatives and other stakeholders to deliver revenue goals", "Facilitate annual strategic review and goal setting processes by identifying gaps and obstacles in reaching the monthly, quarterly, and annual sales goals", "Deliver regular reporting to CEO on market analysis with a focus upon competition, pricing, market conditions, as well as new and existing product lines", "Provide recommendations on new products and technologies to meet market demands", "Collaborate with executive leadership team to develop and execute the company\u2019s strategic plan", "Continually evaluates the effectiveness of the business development performance against market constraints and changes and revises the business development plan as appropriate", "Work with Marketing to develop new ways to attract and engage leads to track and adjust marketing spend to drive sales ROI", "Continuously develop fresh and creative initiatives to drive sales team success", "Develop and deploy cross functional tools, policies, and practices to drive sales, increase profitability and streamline process", "Analyze data and synthesize it into areas of sales and marketing focus, sales tools needed, technology solutions required, etc", "Drive strategic cross functional team leadership in areas of R&D, Sales, Specification Sales, Product Marketing, Sales Support, and Integration Business Development", "Provide subject matter expertise and direction in accordance with entrepreneurial culture, policies, and core values", "Cultivate and maintain strong, effective relationships with all internal and external stakeholders", "Maintain and leverage strong customer network at influential levels \u2013 personal involvement securing outcomes with key deals and customers", "Work closely with business unit managers on pricing, volume and market strategies to maximize profitability and value to the company", "Lead and improve the ability to provide an accurate sales forecast", "Successfully develop and manage expense budgets to meet profitability goals", "Human capital development, mentoring, and succession planning"]}, "job_job_title": "Business", "job_posting_language": "en", "job_onet_soc": "11202100", "job_onet_job_zone": "4"}