{"job_id": "gSBhkZCBxMVRIAkzAAAAAA==", "employer_name": "Dent Wizard", "employer_logo": null, "employer_website": null, "employer_company_type": null, "job_publisher": "Jooble", "job_employment_type": "FULLTIME", "job_title": "Business Development Manager", "job_apply_link": "https://jooble.org/jdp/-6153715047353100776", "job_apply_is_direct": false, "job_apply_quality_score": 0.6439, "apply_options": [{"publisher": "Jooble", "apply_link": "https://jooble.org/jdp/-6153715047353100776", "is_direct": false}], "job_description": "As a Business Development Manager, your essential job functions include:\n\nConquesting (55%)\n\u2022 Conquest new business through focused selling activities\n\u2022 Manage the full sales cycle with the customer\n\u2022 Engage front line managers to secure business or add additional services\n\u2022 Lead the identification of new customer prospects and sales process to land new business (focusing on the Division\u2019s mid-sized growth opportunities)\n\u2022 Own and lead origination of DW strategic sales initiatives, WTD/FLF+, etc.\n\u2022 Contribute to and drive the Division\u2019s sales strategy, plan and critical priorities\n\u2022 Deliver professional sales presentations\n\u2022 Lead the coordination of cross-functional teams throughout the sales process\n\u2022 Leverage industry intelligence/information to grow Dent Wizard\u2019s footprint in all channels of business\n\u2022 Represent Dent Wizard at professional trade association meetings, client seminars, conventions, etc.\n\nAccount Management (25%)\n\u2022 Conduct Quarterly Business Reviews with current customers (QBR)\n\u2022 Develop and manage strong relationships with mid-sized customers within the Division in partnership with Operations\n\u2022 Collaborate with Dealer Tire sales partners\n\u2022 Lead and execute price increases\n\u2022 Drive existing customer growth and retention\n\u2022 Proactively identify opportunities and provide solutions that address customer needs\n\u2022 Identify competitive opportunities, threats, trends and issues; elevate awareness and proactively implement value-added solutions\n\nOperations Coordination/Integration (10%)\n\u2022 Partner with District Operations Managers and Area Operations Managers to ensure customers have five-star experience based on a Team Sell approach\n\u2022 Provide counsel and support in resolving existing customer issues\n\u2022 Maintain a positive and productive working environment consistent with Dent Wizard\u2019s core values\n\u2022 Participate in operations huddles and management routines to ensure strong alignment, integration and collaboration across teams\n\u2022 Fuel M&A pipeline for future growth opportunities\n\nSales Administration (10%)\n\u2022 Participate in the Goal Setting & Review (GS&R) process providing regular updates\n\u2022 Enter and update sales related data in a timely manner\n\u2022 Actively lead and participate in a cadence of sales calls\n\nCompetencies Required\n\u2022 Results Orientation\n\u2022 Value-based Selling Skills\n\u2022 Strong Presentation Skills\n\u2022 Customer Focus\n\u2022 Critical Thinking\n\u2022 Influence\n\u2022 Industry/Product Knowledge\n\u2022 Portfolio Management\n\u2022 Trusted Advisor\n\nPosition Requirements\n\u2022 5+ years proven sales experience in a similar type of sales environment\n\u2022 Auto and reconditioning industry experience preferred.\n\nPhysical Job Requirements\n\u2022 Continuous viewing from and inputting data to a computer screen.\n\u2022 Travel as necessary (up to 75%).\n\nDrug Policy\n\u2022 All applicants being considered for employment must pass a pre-employment drug screening and background check.\n\nThe compensation offered for this position will depend on qualifications, experience, and geographic location. The starting base salary is expected to be between $75,000 and $80,000 annually. The total compensation package may also include commission or bonus. We offer a competitive & comprehensive benefit package including: paid time off, medical, dental, vision, and 401k match (50% on the dollar up to 7% of employee contribution).", "job_is_remote": false, "job_posted_at_timestamp": 1700092800, "job_posted_at_datetime_utc": "2023-11-16T00:00:00.000Z", "job_city": "Salt Lake City", "job_state": "UT", "job_country": "US", "job_latitude": 40.76078, "job_longitude": -111.891045, "job_benefits": ["dental_coverage", "paid_time_off", "health_insurance", "retirement_savings"], "job_google_link": "https://www.google.com/search?gl=us&hl=en&rciv=jb&q=manager+of+business+development&start=60&ibp=htl;jobs#fpstate=tldetail&htivrt=jobs&htiq=manager+of+business+development&htidocid=gSBhkZCBxMVRIAkzAAAAAA%3D%3D", "job_offer_expiration_datetime_utc": "2024-04-08T22:03:15.000Z", "job_offer_expiration_timestamp": 1712613795, "job_required_experience": {"no_experience_required": false, "required_experience_in_months": 60, "experience_mentioned": true, "experience_preferred": true}, "job_required_skills": null, "job_required_education": {"postgraduate_degree": false, "professional_certification": false, "high_school": false, "associates_degree": false, "bachelors_degree": false, "degree_mentioned": false, "degree_preferred": false, "professional_certification_mentioned": false}, "job_experience_in_place_of_education": false, "job_min_salary": null, "job_max_salary": null, "job_salary_currency": null, "job_salary_period": null, "job_highlights": {"Qualifications": ["Results Orientation", "Value-based Selling Skills", "Strong Presentation Skills", "Customer Focus", "Critical Thinking", "Influence", "Industry/Product Knowledge", "Portfolio Management", "Trusted Advisor", "5+ years proven sales experience in a similar type of sales environment", "Continuous viewing from and inputting data to a computer screen", "Travel as necessary (up to 75%)", "All applicants being considered for employment must pass a pre-employment drug screening and background check"], "Responsibilities": ["Conquest new business through focused selling activities", "Manage the full sales cycle with the customer", "Engage front line managers to secure business or add additional services", "Lead the identification of new customer prospects and sales process to land new business (focusing on the Division\u2019s mid-sized growth opportunities)", "Own and lead origination of DW strategic sales initiatives, WTD/FLF+, etc", "Contribute to and drive the Division\u2019s sales strategy, plan and critical priorities", "Deliver professional sales presentations", "Lead the coordination of cross-functional teams throughout the sales process", "Leverage industry intelligence/information to grow Dent Wizard\u2019s footprint in all channels of business", "Represent Dent Wizard at professional trade association meetings, client seminars, conventions, etc", "Account Management (25%)", "Conduct Quarterly Business Reviews with current customers (QBR)", "Develop and manage strong relationships with mid-sized customers within the Division in partnership with Operations", "Collaborate with Dealer Tire sales partners", "Lead and execute price increases", "Drive existing customer growth and retention", "Proactively identify opportunities and provide solutions that address customer needs", "Identify competitive opportunities, threats, trends and issues; elevate awareness and proactively implement value-added solutions", "Operations Coordination/Integration (10%)", "Partner with District Operations Managers and Area Operations Managers to ensure customers have five-star experience based on a Team Sell approach", "Provide counsel and support in resolving existing customer issues", "Maintain a positive and productive working environment consistent with Dent Wizard\u2019s core values", "Participate in operations huddles and management routines to ensure strong alignment, integration and collaboration across teams", "Fuel M&A pipeline for future growth opportunities", "Participate in the Goal Setting & Review (GS&R) process providing regular updates", "Enter and update sales related data in a timely manner", "Actively lead and participate in a cadence of sales calls"], "Benefits": ["The starting base salary is expected to be between $75,000 and $80,000 annually", "The total compensation package may also include commission or bonus", "We offer a competitive & comprehensive benefit package including: paid time off, medical, dental, vision, and 401k match (50% on the dollar up to 7% of employee contribution)"]}, "job_job_title": "Development manager", "job_posting_language": "en", "job_onet_soc": "11202100", "job_onet_job_zone": "4"}