{"job_id": "54n9I0iujs_B32faAAAAAA==", "employer_name": "Society of Exploration Geophysicists", "employer_logo": "https://upload.wikimedia.org/wikipedia/en/4/4d/SEG_2016_logo.svg", "employer_website": "http://www.seg.org", "employer_company_type": "Information", "job_publisher": "Media Bistro", "job_employment_type": "FULLTIME", "job_title": "Lead Data Scientist, Marketing Analytics", "job_apply_link": "https://www.mediabistro.com/jobs/178862325-lead-data-scientist-marketing-analytics", "job_apply_is_direct": false, "job_apply_quality_score": 0.6697, "apply_options": [{"publisher": "Media Bistro", "apply_link": "https://www.mediabistro.com/jobs/178862325-lead-data-scientist-marketing-analytics", "is_direct": false}, {"publisher": "Trabajo.org", "apply_link": "https://us.trabajo.org/job-835-20240307-5fc77356c89f2917b4836376eaf27913", "is_direct": false}], "job_description": "Universal Orlando Resort believes in-person collaboration is key to our success. Many of our Team Members work in a hybrid capacity, contributing from the workplace a minimum of three days per week. Some remote opportunities are available within specific departments. There are also roles that require being on-site full time. You\u2019ll learn more about this during the application process.JOB SUMMARY:Leads a team of data scientists who design, develop, and evaluate advanced predictive and causal models to measure and influence strategic decisions for investments relating to marketing tactics including audience, promotion, creative, media channel and offer. Drives analysis and development of statistical models to optimize marketing tactics. Helps define and optimize audience and market segmentation strategy. Delivers clear and compelling findings with visualizations and presentations that inform and inspire internal stakeholders to make better business decisions. Collaborates with colleagues in Marketing Operations and IT to infuse predictive analytics and machine learning into customer touchpoints to drive increased relevance and resulting business performance.This is a working role where the majority of the lead\u2019s time is spent creating data pipelines, extracting and analyzing relevant information from both structured and unstructured data using a variety of techniques, ranging from the statistical analysis to complex data mining and modeling.MAJOR RESPONSIBILITIES:AnalyticsCollaborates with business stakeholders translating hypotheses and scenarios into predictive modelling frameworks.Offer technical guidance on modeling methodologies and best practices and build predictive and causal models as needed.Lead team members in the application of advanced methodologies and effectively utilize them to deliver insights.Use advanced analytics approaches such as:Attribution to support the marketing optimization of paid, owned and earned media to drive actionable media insights across key business areas for point of origin, campaigns, destinations, attractions, and events.Leverage top-down marketing mix modeling results, bottom-up attribution and consumer and marketing insights in order to provide strategic recommendations.Develops segmentation, propensity to purchase and look-a-like modeling of individuals across known, identified and anonymous audiences.Create a comprehensive understanding of consumer behaviors that drives audience strategy, improves the customer experience, and generates revenue.Visualize media performance and attribution results in an interactive dashboard.Mentor team members with technical and professional development opportunities.Data EngineeringLead implementation of best practices for development of model pipelines and analytics workflows.Manage and optimize computational resources to minimize cost and increase efficiency.Understanding of enterprise architecture, how to best integrate projects within existing framework and identify opportunities for platform enhancements.Provide strategic guidance in working alongside the technology department in defining business requirements and enabling the data processing system for modeling.Develop business requirements for IT support in enabling technologies and platforms for advanced analytics use.Leadership & ProcessProvide input into strategic leadership and guidance in prioritizing technical projects and developing roadmap.Multi-project management and oversight within function.Able to inform and influence projects or complex solutions in an innovative manner.Conduct monthly/quarterly/annual planning with team to ensure team objectives align and support broader business objectives.Mentor direct reports on a weekly basis to guide them on performance, and personal and career growth.Business IntegrationEngage with internal partners to translate business problems into a framework for advanced analytics and collaborate to establish project goals and deliverables.Translate complex technical subjects for internal partners and team leadership through clear visual, written, and verbal communication.Explain methodology, results, and recommendations using business actions and impacts.Helps business stakeholders and leadership understand data science capabilities and aligns the teams support capabilities with business needs.Understands and actively participates in Environmental, Health & Safety responsibilities by following established UO policy, procedures, training and team member involvement activities.Performs other duties as assigned.EDUCATION:Advanced degree (M.S., or M.A., or Ph.D.) in relevant quantitative field (e.g., computer science, mathematics, engineering, statistics, data science, business analytics) required.EXPERIENCE:8+ years\u2019 prior hands-on experience in data science.Strong experience in programming with statistical modeling tools to fuel and deliver marketing personalization and business insights.Strong experience in manipulating and mining data to transform business decisions that impact the bottom line.Experience leveraging visual analytics to create a seamless and inspirational story that will inspire and inform business leaders with the necessary knowledge to drive revenue and customer loyalty.5+ years using R, Python, and SQL to apply modeling methodologies and deliver insights ingesting, cleaning and leveraging data from disparate data sources.5+ years designing and implementing experiments and conducting analysis including exploratory analysis to assess the need for modeling, correlation analysis, assessing model performance, and value of predictive attributes.5+ years developing code and leveraging data in accordance with company policy and team standards. Ability to monitor data usage for privacy and compliance concerns and adhere to customer data usage standards.5+ years experience in applying advanced analytical solutions to complex industry/business problems.1+ years demonstrable experience with team member and/or project level leadership.or equivalent combination of education and experience.Your talent, skills and experience will be rewarded with a competitive compensation package.Universal is not accepting unsolicited assistance from search firms for this employment opportunity. All resumes submitted by search firms to any employee at Universal Orlando via-email, the Internet or in any form and/or method without a valid written Statement of Work in place for this position from Universal Orlando HR/Recruitment will be deemed the sole property of Universal Orlando. No fee will be paid in the event the candidate is hired by Universal Orlando as a result of the referral or through other means.Universal Orlando Resort.Here you can.Universal Orlando is an equal opportunity employer. Universal elements and all related indicia TM &2024 Universal Studios. All rights reserved. EOE#J-18808-Ljbffr", "job_is_remote": false, "job_posted_at_timestamp": 1709560800, "job_posted_at_datetime_utc": "2024-03-04T14:00:00.000Z", "job_city": null, "job_state": null, "job_country": "US", "job_latitude": 37.09024, "job_longitude": -95.71289, "job_benefits": null, "job_google_link": "https://www.google.com/search?gl=us&hl=en&rciv=jb&q=data+science+leader&start=50&ibp=htl;jobs#fpstate=tldetail&htivrt=jobs&htiq=data+science+leader&htidocid=54n9I0iujs_B32faAAAAAA%3D%3D", "job_offer_expiration_datetime_utc": null, "job_offer_expiration_timestamp": null, "job_required_experience": {"no_experience_required": false, "required_experience_in_months": 96, "experience_mentioned": true, "experience_preferred": false}, "job_required_skills": null, "job_required_education": {"postgraduate_degree": false, "professional_certification": false, "high_school": false, "associates_degree": false, "bachelors_degree": false, "degree_mentioned": true, "degree_preferred": true, "professional_certification_mentioned": false}, "job_experience_in_place_of_education": false, "job_min_salary": null, "job_max_salary": null, "job_salary_currency": null, "job_salary_period": null, "job_highlights": {"Qualifications": ["Performs other duties as assigned.EDUCATION:Advanced degree (M.S., or M.A., or Ph.D.) in relevant quantitative field (e.g., computer science, mathematics, engineering, statistics, data science, business analytics) required.EXPERIENCE:8+ years\u2019 prior hands-on experience in data science", "Strong experience in programming with statistical modeling tools to fuel and deliver marketing personalization and business insights", "Strong experience in manipulating and mining data to transform business decisions that impact the bottom line", "Experience leveraging visual analytics to create a seamless and inspirational story that will inspire and inform business leaders with the necessary knowledge to drive revenue and customer loyalty.5+ years using R, Python, and SQL to apply modeling methodologies and deliver insights ingesting, cleaning and leveraging data from disparate data sources.5+ years designing and implementing experiments and conducting analysis including exploratory analysis to assess the need for modeling, correlation analysis, assessing model performance, and value of predictive attributes.5+ years developing code and leveraging data in accordance with company policy and team standards", "Ability to monitor data usage for privacy and compliance concerns and adhere to customer data usage standards.5+ years experience in applying advanced analytical solutions to complex industry/business problems.1+ years demonstrable experience with team member and/or project level leadership.or equivalent combination of education and experience"], "Responsibilities": ["JOB SUMMARY:Leads a team of data scientists who design, develop, and evaluate advanced predictive and causal models to measure and influence strategic decisions for investments relating to marketing tactics including audience, promotion, creative, media channel and offer", "Drives analysis and development of statistical models to optimize marketing tactics", "Helps define and optimize audience and market segmentation strategy", "Delivers clear and compelling findings with visualizations and presentations that inform and inspire internal stakeholders to make better business decisions", "Collaborates with colleagues in Marketing Operations and IT to infuse predictive analytics and machine learning into customer touchpoints to drive increased relevance and resulting business performance", "This is a working role where the majority of the lead\u2019s time is spent creating data pipelines, extracting and analyzing relevant information from both structured and unstructured data using a variety of techniques, ranging from the statistical analysis to complex data mining and modeling", "MAJOR RESPONSIBILITIES:AnalyticsCollaborates with business stakeholders translating hypotheses and scenarios into predictive modelling frameworks", "Offer technical guidance on modeling methodologies and best practices and build predictive and causal models as needed", "Lead team members in the application of advanced methodologies and effectively utilize them to deliver insights", "Use advanced analytics approaches such as:Attribution to support the marketing optimization of paid, owned and earned media to drive actionable media insights across key business areas for point of origin, campaigns, destinations, attractions, and events", "Leverage top-down marketing mix modeling results, bottom-up attribution and consumer and marketing insights in order to provide strategic recommendations", "Develops segmentation, propensity to purchase and look-a-like modeling of individuals across known, identified and anonymous audiences", "Create a comprehensive understanding of consumer behaviors that drives audience strategy, improves the customer experience, and generates revenue", "Visualize media performance and attribution results in an interactive dashboard", "Mentor team members with technical and professional development opportunities", "Data EngineeringLead implementation of best practices for development of model pipelines and analytics workflows", "Manage and optimize computational resources to minimize cost and increase efficiency", "Understanding of enterprise architecture, how to best integrate projects within existing framework and identify opportunities for platform enhancements", "Provide strategic guidance in working alongside the technology department in defining business requirements and enabling the data processing system for modeling", "Develop business requirements for IT support in enabling technologies and platforms for advanced analytics use", "Leadership & ProcessProvide input into strategic leadership and guidance in prioritizing technical projects and developing roadmap.Multi-project management and oversight within function", "Able to inform and influence projects or complex solutions in an innovative manner", "Conduct monthly/quarterly/annual planning with team to ensure team objectives align and support broader business objectives", "Mentor direct reports on a weekly basis to guide them on performance, and personal and career growth", "Business IntegrationEngage with internal partners to translate business problems into a framework for advanced analytics and collaborate to establish project goals and deliverables", "Translate complex technical subjects for internal partners and team leadership through clear visual, written, and verbal communication", "Explain methodology, results, and recommendations using business actions and impacts", "Helps business stakeholders and leadership understand data science capabilities and aligns the teams support capabilities with business needs", "Understands and actively participates in Environmental, Health & Safety responsibilities by following established UO policy, procedures, training and team member involvement activities"], "Benefits": ["Your talent, skills and experience will be rewarded with a competitive compensation package"]}, "job_job_title": "Data scientist", "job_posting_language": "en", "job_onet_soc": "15111100", "job_onet_job_zone": "5", "job_naics_code": "51113", "job_naics_name": "Book Publishers"}