{"job_id": "9tSNEHaglf7x7dc_AAAAAA==", "employer_name": "Databricks", "employer_logo": "https://upload.wikimedia.org/wikipedia/commons/6/63/Databricks_Logo.png", "employer_website": "http://databricks.com", "employer_company_type": "Information", "job_publisher": "Databricks", "job_employment_type": "FULLTIME", "job_title": "Specialist Solutions Architect - HLS", "job_apply_link": "https://www.databricks.com/company/careers/field-engineering/specialist-solutions-architect---hls-7287296002", "job_apply_is_direct": false, "job_apply_quality_score": 0.8239, "apply_options": [{"publisher": "Databricks", "apply_link": "https://www.databricks.com/company/careers/field-engineering/specialist-solutions-architect---hls-7287296002", "is_direct": false}], "job_description": "FEQ325R86\n\nWe are open to hiring in any remote location in the USA.\n\nAs a Specialist Solutions Architect (SSA) - Machine Learning on the Healthcare & Life Sciences team, you will guide customers in building big data solutions on Databricks that span a large variety of machine learning use cases. You will be in a customer-facing role, working with and supporting Solution Architects, that requires hands-on production experience with MLFlow\u2122 and expertise in other MLOps technologies. SSAs help customers through design and successful implementation of essential workloads while aligning their technical roadmap for expanding the usage of the Databricks Lakehouse Platform. As a deep go-to-expert reporting to the Specialist Field Engineering Manager, you will continue to strengthen your technical skills through mentorship, learning, and internal training programs and establish yourself in an area of specialty - whether that be machine learning, MLOps, industry expertise, or more.\n\nThe impact you will have:\n\u2022 Provide technical leadership to guide strategic customers to successful implementations on big data projects, ranging from feature engineering, training, tracking, registry, serving to model monitoring all within a single platform\n\u2022 Architect production level workloads, including end-to-end ML pipelines load performance testing and optimization\n\u2022 Become a technical expert in Databricks Machine Learning and MLOps technologies\n\u2022 Assist Solution Architects with more advanced aspects of the technical sale including custom proof of concept content, estimating workload sizing, and custom architectures\n\u2022 Provide tutorials and training to improve community adoption (including hackathons and conference presentations)\n\u2022 Contribute to adoption of a variety of the ML offerings Databricks with customers as well as the larger Databricks Community\n\nWhat we look for:\n\u2022 5+ years hands on experience in a technical role with expertise in at least one of the following:\n\u2022 Data Scientist/ML Engineer: model selection, model lifecycle, model scaling, AutoML, hyperparameter tuning, model serving, model monitoring, deep learning\n\u2022 MLOps Engineer: Build and maintain cloud infrastructure that supports the deployment of ML models and algorithms, monitors data drift, integration with production systems\n\u2022 Extensive experience in applying Data Science / ML in production to build data-driven products for solving business problems\n\u2022 Experience maintaining and extending production data systems to evolve with complex needs\n\u2022 Deep Specialty Expertise regarding ML concepts including Model Tracking, Model Serving and other aspects of productionizing ML pipelines in distributed data processing environments like Apache Spark, using tools like MLflow\n\u2022 Production programming experience in SQL and Python, Scala, or Java\n\u2022 2 years hands-on professional experience with Big Data technologies (e.g. Spark, Hadoop, Kafka) and architectures\n\u2022 2 years customer-facing experience in a pre-sales or post-sales role\n\u2022 Can meet expectations for technical training and role-specific outcomes within 6 months of hire\n\u2022 Bachelor's degree in Computer Science, Information Systems, Engineering, or equivalent experience through work experience\n\u2022 Ability to travel up to 30% when needed\n\nBenefits\n\u2022 Medical, Dental, and Vision\n\u2022 401(k) Plan\n\u2022 FSA, HSA and Commuter Benefit Plans\n\u2022 Equity Awards\n\u2022 Flexible Time Off\n\u2022 Paid Parental Leave\n\u2022 Family Planning\n\u2022 Fitness Reimbursement\n\u2022 Annual Career Development Fund\n\u2022 Home Office/Work Headphones Reimbursement\n\u2022 Employee Assistance Program (EAP)\n\u2022 Business Travel Accident Insurance\n\u2022 Mental Wellness Resources", "job_is_remote": false, "job_posted_at_timestamp": 1710374400, "job_posted_at_datetime_utc": "2024-03-14T00:00:00.000Z", "job_city": "San Francisco", "job_state": "CA", "job_country": "US", "job_latitude": 37.77493, "job_longitude": -122.41942, "job_benefits": ["dental_coverage", "health_insurance", "retirement_savings"], "job_google_link": "https://www.google.com/search?gl=us&hl=en&rciv=jb&q=machine+learning+specialist&start=50&ibp=htl;jobs#fpstate=tldetail&htivrt=jobs&htiq=machine+learning+specialist&htidocid=9tSNEHaglf7x7dc_AAAAAA%3D%3D", "job_offer_expiration_datetime_utc": null, "job_offer_expiration_timestamp": null, "job_required_experience": {"no_experience_required": false, "required_experience_in_months": 60, "experience_mentioned": true, "experience_preferred": false}, "job_required_skills": null, "job_required_education": {"postgraduate_degree": false, "professional_certification": false, "high_school": false, "associates_degree": false, "bachelors_degree": false, "degree_mentioned": true, "degree_preferred": true, "professional_certification_mentioned": false}, "job_experience_in_place_of_education": false, "job_min_salary": null, "job_max_salary": null, "job_salary_currency": null, "job_salary_period": null, "job_highlights": {"Qualifications": ["5+ years hands on experience in a technical role with expertise in at least one of the following:", "Data Scientist/ML Engineer: model selection, model lifecycle, model scaling, AutoML, hyperparameter tuning, model serving, model monitoring, deep learning", "Extensive experience in applying Data Science / ML in production to build data-driven products for solving business problems", "Experience maintaining and extending production data systems to evolve with complex needs", "Deep Specialty Expertise regarding ML concepts including Model Tracking, Model Serving and other aspects of productionizing ML pipelines in distributed data processing environments like Apache Spark, using tools like MLflow", "Production programming experience in SQL and Python, Scala, or Java", "2 years hands-on professional experience with Big Data technologies (e.g", "Spark, Hadoop, Kafka) and architectures", "2 years customer-facing experience in a pre-sales or post-sales role", "Can meet expectations for technical training and role-specific outcomes within 6 months of hire", "Bachelor's degree in Computer Science, Information Systems, Engineering, or equivalent experience through work experience", "Ability to travel up to 30% when needed"], "Responsibilities": ["You will be in a customer-facing role, working with and supporting Solution Architects, that requires hands-on production experience with MLFlow\u2122 and expertise in other MLOps technologies", "SSAs help customers through design and successful implementation of essential workloads while aligning their technical roadmap for expanding the usage of the Databricks Lakehouse Platform", "As a deep go-to-expert reporting to the Specialist Field Engineering Manager, you will continue to strengthen your technical skills through mentorship, learning, and internal training programs and establish yourself in an area of specialty - whether that be machine learning, MLOps, industry expertise, or more", "Provide technical leadership to guide strategic customers to successful implementations on big data projects, ranging from feature engineering, training, tracking, registry, serving to model monitoring all within a single platform", "Architect production level workloads, including end-to-end ML pipelines load performance testing and optimization", "Become a technical expert in Databricks Machine Learning and MLOps technologies", "Assist Solution Architects with more advanced aspects of the technical sale including custom proof of concept content, estimating workload sizing, and custom architectures", "Provide tutorials and training to improve community adoption (including hackathons and conference presentations)", "Contribute to adoption of a variety of the ML offerings Databricks with customers as well as the larger Databricks Community"], "Benefits": ["Medical, Dental, and Vision", "401(k) Plan", "FSA, HSA and Commuter Benefit Plans", "Equity Awards", "Flexible Time Off", "Paid Parental Leave", "Family Planning", "Fitness Reimbursement", "Annual Career Development Fund", "Home Office/Work Headphones Reimbursement", "Employee Assistance Program (EAP)", "Business Travel Accident Insurance", "Mental Wellness Resources"]}, "job_job_title": "Solutions architect", "job_posting_language": "en", "job_onet_soc": "15119900", "job_onet_job_zone": "4", "job_naics_code": "511210", "job_naics_name": "Software Publishers"}