{"job_id": "wZ06j4hNrlo_0VanAAAAAA==", "employer_name": "ManTech", "employer_logo": "https://www.govconwire.com/wp-content/uploads/2022/05/00P4y000017tw1REAQ.png", "employer_website": "http://www.mantech.com", "employer_company_type": "Computer Services", "job_publisher": "LinkedIn", "job_employment_type": "FULLTIME", "job_title": "Solutions Machine Learning Architect", "job_apply_link": "https://www.linkedin.com/jobs/view/solutions-machine-learning-architect-at-mantech-3852751292", "job_apply_is_direct": false, "job_apply_quality_score": 0.645, "apply_options": [{"publisher": "LinkedIn", "apply_link": "https://www.linkedin.com/jobs/view/solutions-machine-learning-architect-at-mantech-3852751292", "is_direct": false}, {"publisher": "Jobgether", "apply_link": "https://jobgether.com/offer/65f1f113f235ccdf7906e748-solutions-machine-learning-architect", "is_direct": false}, {"publisher": "ClearedJobs.Net", "apply_link": "https://clearedjobs.net/job/solutions-machine-learning-architect-remt-worker-1546760", "is_direct": false}, {"publisher": "Indeed", "apply_link": "https://www.indeed.com/viewjob?jk=48f93325c80bcad2", "is_direct": false}], "job_description": "Secure our Nation, Ignite your Future\n\nManTech is seeking a motivated, career, and customer-oriented Senior ML Architect - Cyber to join our team to provide unparalleled support to multiple federal agencies through the Continuous Diagnostics & Mitigation (CDM) Program. The CDM Program is a high-profile, high-visibility, cybersecurity modernization and risk management program where you can contribute innovative solutions and consult with multiple federal agencies to enhance their Information Assurance (IA) programs and continuous monitoring capabilities.\n\nThe Senior ML Architect \u2013 Cyber\u2019s responsibilities include conducting full lifecycle analysis of data that includes requirements from DHS, other OMB initiatives, and provide support for the whole program. This position also requires building a new AI/ML practice on the program to address our client\u2019s most pressing needs with Cyber Security Threats and Data. The successful candidate will bring a consultative approach to data and use ML/NLP discipline to improve the value of the data that\u2019s being collected by our customers. This position is also a thought leader in the practice of ML/NL/AI in solving our clients\u2019 cyber security problems, coupled with demonstrated experience designing and developing enterprise data solutions for large clients by providing a new approach to the team, presenting white papers and other solutions.\n\nResponsibilities\n\nThe Solutions Architect \u2013 Machine Learning and AI will:\n\u2022 Architect, position, design, develop and deploy enterprise solutions which include components across the Artificial Intelligence spectrum such as, Machine Learning, and Natural language Process.\n\u2022 Develops solutions to implement Defense in Depth principles and practices. Identifies potential conflicts with implementation of any cyber security tools within the enterprise and develops recommendations to remediate these conflicts.\n\u2022 Analyzes life-cycle configuration management of applications, rules, filters, and configurations of managed cyber security systems.\n\u2022 Provides solutions to a variety of technical problems of moderate scope and complexity.\n\u2022 Advises customers and colleagues on a wide variety of topics including cyber security risk management.\n\u2022 Work with Data and Architect team to understand Data that is generated by multiple tools such as Asset Management, Identity Management, Vulnerability management.\n\u2022 Develop rules and algorithms for ML/AI use cases for Data processing, transformation, and correlations.\n\u2022 Lead ML workshops for Client.\n\u2022 Architect the Next Generation Data integration discipline in transforming Business Logic rules into adaptable Data rules using ML/NL.\n\u2022 Review, Identify, Analyze data from multiple source Cyber Security tools at multiple agencies.\n\u2022 Interpret data, analyze results using statistical techniques and support data trends based on the customer needs.\n\u2022 Develop and implement databases, data collection systems, data analytics and other strategies that optimize statistical efficiency and quality.\n\u2022 Acquire data from primary and other data sources and maintain databases/data systems\n\u2022 Identify, analyze, and interpret trends or patterns in complex data sets\n\u2022 Analyze source data and types, identify data requirements for destination systems.\n\u2022 Analyze, interpret, and develop data models on data based on Data Dictionary & Logical Data Models guidance.\n\u2022 Locate and define new process improvement opportunities.\n\u2022 Ensure that mapping of data elements provided by COTS products to our standard data model\n\u2022 Other duties as assigned.\n\nPosition Requirements\n\u2022 Proven working experience with large Data set from multiple systems including machine data, cyber security tool data and other relevant data that is used within an enterprise for security posture.\n\u2022 Experience architecting, designing, developing and deploying enterprise solutions, based on client or business requirements, which include components across the Artificial Intelligence spectrum such as Advanced Analytics, Machine Learning and Data Science\n\u2022 Proficient at queries, report writing and presenting findings.\n\u2022 Technical expertise regarding data models, database design development, data mining and segmentation techniques\n\u2022 Experience in Hadoop, Spark, Storm or related paradigms and associated languages such as Pig, Hive, Mahout, plus advanced skills in Java/C++, R, Python, etc\n\u2022 Experience in programming knowledge in SQL, NoSQL. Operating system experience with Linux and relational database knowledge such as SQL.\n\u2022 Experience in Cloud Data tools such as Azure Data Factory, AWS Glue, AWS Stitch\n\u2022 Experience in Cloud Data Lakes / Warehouses in Azure / AWS\n\u2022 Experience in working with Cryptography and Hashing models.\n\u2022 Experience with quantitative modeling (design, development & implementation) using 3+ types of algorithms (e.g., Decision Trees, Naive Bayes Classification, Ordinary Least Squares Regression, Logistic Regression, Support Vector Machines, Ensemble Methods, Clustering Algorithms, Principal Component Analysis, Singular Value Decomposition, Independent Component Analysis)\n\u2022 Demonstrated expertise in at least one of the following: machine learning, deep learning, time-series modeling, propensity and prediction, behavioral nudges, recommenders, anomaly detection, segmentation, AI architecture, AI interface design\n\u2022 Strong knowledge of and experience with reporting packages (Business Objects etc), databases (SQL, MySql etc.), programming (XML, Javascript, or ETL frameworks)\n\u2022 Knowledge of statistics and experience using statistical packages for analyzing datasets (Excel, SPSS, SAS etc)\n\u2022 Strong analytical skills with the ability to collect, organize, analyze, and disseminate significant amounts of information with attention to detail and accuracy\n\u2022 Experience with collaborating with other roles, such as solution architects, data engineers, data scientists, Automation engineers, database administrators, and developers.\n\u2022 Experience understanding organizational needs, proposing solutions, and managing project execution efforts designed to deliver overall program benefits for Government Agencies\n\u2022 Experience collaborating with US Government Agencies, state or local governments, or commercial entities to develop IT service program maturity in accordance with Federal IT mandates and best practices\n\u2022 Experience in conducting assessments of an Enterprise by reviewing technical documentation, conducting interviews and workshops to identify gaps and develop a tailored solution is highly desired\n\u2022 Demonstrated experience in security solution design using existing as well as emerging technologies to deliver enterprise solutions\n\nAdditional Skills\n\u2022 Demonstrated ability to present to senior leadership and client audiences\n\u2022 JIRA experience\n\u2022 MS SQL\n\nEducation\n\u2022 Bachelor's Degree preferably in applied mathematics, statistics, computer science, data science, electrical engineering, physics, or closely related field (required)\n\nCertification\n\u2022 CISSP or Security + Certification (preferred)\n\nSecurity/Clearance Requirements\n\u2022 Must be a US citizen and pass a background investigation\n\u2022 Able to obtain and maintain a DHS Suitability/Entry on Duty (EOD)\n\u2022 Active Secret or Top-Secret clearance desired\n\nPhysical Requirements\n\u2022 Office work, typically sedentary with some movement around the office\n\nThe projected compensation range for this position is $141,100-$234,400. There are differentiating factors that can impact a final salary/hourly rate, including, but not limited to, Contract Wage Determination, relevant work experience, skills and competencies that align to the specified role, geographic location (For Remote Opportunities), education and certifications as well as Federal Government Contract Labor categories. In addition, ManTech invests in it\u2019s employees beyond just compensation. ManTech\u2019s benefits offerings include, dependent upon position, Health Insurance, Life Insurance, Paid Time Off, Holiday Pay, Short Term and Long Term Disability, Retirement and Savings, Learning and Development opportunities, wellness programs as well as other optional benefit elections.\n\nFor all positions requiring access to technology/software source code that is subject to export control laws, employment with the company is contingent on either verifying U.S.-person status or obtaining any necessary license. The applicant will be required to answer certain questions for export control purposes, and that information will be reviewed by compliance personnel to ensure compliance with federal law. ManTech may choose not to apply for a license for such individuals whose access to export-controlled technology or software source code may require authorization and may decline to proceed with an applicant on that basis alone.\n\nManTech International Corporation, as well as its subsidiaries proactively fulfills its role as an equal opportunity employer. We do not discriminate against any employee or applicant for employment because of race, color, sex, religion, age, sexual orientation, gender identity and expression, national origin, marital status, physical or mental disability, status as a Disabled Veteran, Recently Separated Veteran, Active Duty Wartime or Campaign Badge Veteran, Armed Forces Services Medal, or any other characteristic protected by law.\n\nIf you require a reasonable accommodation to apply for a position with ManTech through its online applicant system, please contact ManTech's Corporate EEO Department at (703) 218-6000. ManTech is an affirmative action/equal opportunity employer - minorities, females, disabled and protected veterans are urged to apply. ManTech's utilization of any external recruitment or job placement agency is predicated upon its full compliance with our equal opportunity/affirmative action policies. ManTech does not accept resumes from unsolicited recruiting firms. We pay no fees for unsolicited services.\n\nIf you are a qualified individual with a disability or a disabled veteran, you have the right to request an accommodation if you are unable or limited in your ability to use or access http://www.mantech.com/careers/Pages/careers.aspx as a result of your disability. To request an accommodation please click careers@mantech.com and provide your name and contact information.", "job_is_remote": true, "job_posted_at_timestamp": 1710367777, "job_posted_at_datetime_utc": "2024-03-13T22:09:37.000Z", "job_city": null, "job_state": null, "job_country": "US", "job_latitude": 37.09024, "job_longitude": -95.71289, "job_benefits": ["paid_time_off", "retirement_savings", "dental_coverage", "health_insurance"], "job_google_link": "https://www.google.com/search?gl=us&hl=en&rciv=jb&q=principal+machine+learning+architect&start=60&ibp=htl;jobs#fpstate=tldetail&htivrt=jobs&htiq=principal+machine+learning+architect&htidocid=wZ06j4hNrlo_0VanAAAAAA%3D%3D", "job_offer_expiration_datetime_utc": "2024-04-12T22:09:37.000Z", "job_offer_expiration_timestamp": 1712959777, "job_required_experience": {"no_experience_required": false, "required_experience_in_months": null, "experience_mentioned": true, "experience_preferred": true}, "job_required_skills": null, "job_required_education": {"postgraduate_degree": false, "professional_certification": false, "high_school": false, "associates_degree": false, "bachelors_degree": true, "degree_mentioned": true, "degree_preferred": false, "professional_certification_mentioned": true}, "job_experience_in_place_of_education": false, "job_min_salary": null, "job_max_salary": null, "job_salary_currency": null, "job_salary_period": null, "job_highlights": {"Qualifications": ["Proven working experience with large Data set from multiple systems including machine data, cyber security tool data and other relevant data that is used within an enterprise for security posture", "Experience architecting, designing, developing and deploying enterprise solutions, based on client or business requirements, which include components across the Artificial Intelligence spectrum such as Advanced Analytics, Machine Learning and Data Science", "Proficient at queries, report writing and presenting findings", "Technical expertise regarding data models, database design development, data mining and segmentation techniques", "Experience in Hadoop, Spark, Storm or related paradigms and associated languages such as Pig, Hive, Mahout, plus advanced skills in Java/C++, R, Python, etc", "Operating system experience with Linux and relational database knowledge such as SQL", "Experience in Cloud Data tools such as Azure Data Factory, AWS Glue, AWS Stitch", "Experience in Cloud Data Lakes / Warehouses in Azure / AWS", "Experience in working with Cryptography and Hashing models", "Experience with quantitative modeling (design, development & implementation) using 3+ types of algorithms (e.g., Decision Trees, Naive Bayes Classification, Ordinary Least Squares Regression, Logistic Regression, Support Vector Machines, Ensemble Methods, Clustering Algorithms, Principal Component Analysis, Singular Value Decomposition, Independent Component Analysis)", "Demonstrated expertise in at least one of the following: machine learning, deep learning, time-series modeling, propensity and prediction, behavioral nudges, recommenders, anomaly detection, segmentation, AI architecture, AI interface design", "Strong knowledge of and experience with reporting packages (Business Objects etc), databases (SQL, MySql etc.), programming (XML, Javascript, or ETL frameworks)", "Knowledge of statistics and experience using statistical packages for analyzing datasets (Excel, SPSS, SAS etc)", "Strong analytical skills with the ability to collect, organize, analyze, and disseminate significant amounts of information with attention to detail and accuracy", "Experience with collaborating with other roles, such as solution architects, data engineers, data scientists, Automation engineers, database administrators, and developers", "Experience understanding organizational needs, proposing solutions, and managing project execution efforts designed to deliver overall program benefits for Government Agencies", "Experience collaborating with US Government Agencies, state or local governments, or commercial entities to develop IT service program maturity in accordance with Federal IT mandates and best practices", "Demonstrated ability to present to senior leadership and client audiences", "JIRA experience", "MS SQL", "Bachelor's Degree preferably in applied mathematics, statistics, computer science, data science, electrical engineering, physics, or closely related field (required)", "Certification", "Must be a US citizen and pass a background investigation", "Able to obtain and maintain a DHS Suitability/Entry on Duty (EOD)", "Office work, typically sedentary with some movement around the office"], "Responsibilities": ["The Senior ML Architect \u2013 Cyber\u2019s responsibilities include conducting full lifecycle analysis of data that includes requirements from DHS, other OMB initiatives, and provide support for the whole program", "This position also requires building a new AI/ML practice on the program to address our client\u2019s most pressing needs with Cyber Security Threats and Data", "The successful candidate will bring a consultative approach to data and use ML/NLP discipline to improve the value of the data that\u2019s being collected by our customers", "This position is also a thought leader in the practice of ML/NL/AI in solving our clients\u2019 cyber security problems, coupled with demonstrated experience designing and developing enterprise data solutions for large clients by providing a new approach to the team, presenting white papers and other solutions", "Architect, position, design, develop and deploy enterprise solutions which include components across the Artificial Intelligence spectrum such as, Machine Learning, and Natural language Process", "Develops solutions to implement Defense in Depth principles and practices", "Identifies potential conflicts with implementation of any cyber security tools within the enterprise and develops recommendations to remediate these conflicts", "Analyzes life-cycle configuration management of applications, rules, filters, and configurations of managed cyber security systems", "Provides solutions to a variety of technical problems of moderate scope and complexity", "Advises customers and colleagues on a wide variety of topics including cyber security risk management", "Work with Data and Architect team to understand Data that is generated by multiple tools such as Asset Management, Identity Management, Vulnerability management", "Develop rules and algorithms for ML/AI use cases for Data processing, transformation, and correlations", "Lead ML workshops for Client", "Architect the Next Generation Data integration discipline in transforming Business Logic rules into adaptable Data rules using ML/NL", "Review, Identify, Analyze data from multiple source Cyber Security tools at multiple agencies", "Interpret data, analyze results using statistical techniques and support data trends based on the customer needs", "Develop and implement databases, data collection systems, data analytics and other strategies that optimize statistical efficiency and quality", "Acquire data from primary and other data sources and maintain databases/data systems", "Identify, analyze, and interpret trends or patterns in complex data sets", "Analyze source data and types, identify data requirements for destination systems", "Analyze, interpret, and develop data models on data based on Data Dictionary & Logical Data Models guidance", "Locate and define new process improvement opportunities", "Ensure that mapping of data elements provided by COTS products to our standard data model", "Other duties as assigned"], "Benefits": ["The projected compensation range for this position is $141,100-$234,400", "There are differentiating factors that can impact a final salary/hourly rate, including, but not limited to, Contract Wage Determination, relevant work experience, skills and competencies that align to the specified role, geographic location (For Remote Opportunities), education and certifications as well as Federal Government Contract Labor categories", "In addition, ManTech invests in it\u2019s employees beyond just compensation", "ManTech\u2019s benefits offerings include, dependent upon position, Health Insurance, Life Insurance, Paid Time Off, Holiday Pay, Short Term and Long Term Disability, Retirement and Savings, Learning and Development opportunities, wellness programs as well as other optional benefit elections"]}, "job_job_title": "Architect", "job_posting_language": "en", "job_onet_soc": "15111100", "job_onet_job_zone": "5", "job_naics_code": "541512", "job_naics_name": "Computer Systems Design Services"}