{"job_id": "wwbk06QWuk19TnCQAAAAAA==", "employer_name": "Rokt", "employer_logo": null, "employer_website": null, "employer_company_type": null, "job_publisher": "Jobs By Workable", "job_employment_type": "FULLTIME", "job_title": "Principal Applied Scientist/Machine Learning Engineer", "job_apply_link": "https://apply.workable.com/rokt/j/BA5D068410/", "job_apply_is_direct": true, "job_apply_quality_score": 0.7682, "apply_options": [{"publisher": "Jobs By Workable", "apply_link": "https://apply.workable.com/rokt/j/BA5D068410/", "is_direct": true}], "job_description": "Unlock your inner voice. The one that knows you can do it. The one to listen to more. Unlock that desire you\u2019ve always had to achieve something bigger. Take the leap. Join a team of diverse individuals who thrive by conquering new frontiers and working in different ways. Learn, grow, and then learn some more in a hyper-growth environment. Develop your voice, your ideas, your ability to help others. People at Rokt aren't inspired by job titles, they are inspired by other people. Unleash all the possibilities. At Rokt, you\u2019ll unlock your full potential.\nAbout Rokt\n\nRokt is the global leader in ecommerce technology. We unlock revenue for companies by using AI and machine learning to present highly relevant offers to each shopper, personalizing the online shopping experience and maximizing the value of each transaction moment. Uber, Live Nation, AMC Theatres, PayPal, Hulu, Staples, Lands\u2019 End, GoPuff, HelloFresh are among the more than 2,500 leading global businesses and advertisers relying on Rokt\u2019s technology to increase engagement, revenue and customer acquisition.\n\nWith our December 2022 secondary transaction, Rokt\u2019s valuation increased to $2.4 billion. We are expanding rapidly and operating in 15 countries across North America, Europe and Asia-Pacific with the largest office in NYC and a major R&D hub in Sydney. With consistent hyper growth ahead of the market and a vibrant company culture, Rokt has been listed in \u2018Great Places to Work\u2019 in the US and Australia.\nAbout Rokt\u2019stars\n\nAs a mission-driven, hyper-growth community of curious explorers, our ambition is to unlock the full potential in ecommerce and beyond. Our bias for action means we are not afraid to quickly venture into uncharted territories, take risks or challenge the status quo; in doing so we either win or learn. We work together as one aligned team never letting egos get in the way of brilliant ideas. We value diversity, transparency and smart humble people who enjoy building a disruptive business together. We pride ourselves on being a force for good as we make the world better.\n\nThe Rokt engineering team builds best-in-class ecommerce technology that provides personalized and relevant experiences for customers globally and empowers marketers with sophisticated, AI-driven tooling to better understand consumers. Our bespoke platform handles millions of transactions per day and considers billions of data points which give engineers the opportunity to build technology at scale, collaborate across teams and gain exposure to a wide range of technology. We are expanding rapidly in our major R&D centers in NYC and Sydney. We are passionate about using intelligent systems to improve the transaction moment for retailers everywhere. Come join us and build the future!\n\nAbout the role\n\nAs a Principal Scientist/Machine Learning Engineer you will be able to drive the future direction of new initiatives and push the boundaries on what the world thinks is possible by leveraging the latest advancements in ML. You will join a team of top-tier Machine Learning Engineers and be an inherent part of the Relevancy org and will be responsible for driving machine learning solutions from research to production.\n\nYour expertise will be critical in designing, implementing and scaling innovative machine learning solutions that drive impact across the business. Reporting to the VP of Engineering (AI/Data) you will work closely with product managers, machine learning engineers and software engineers to understand business priorities, frame ML problems and architect solutions that deliver real-world value specifically in CTR modelling, Conversion modelling, UX optimisation, price optimisation and NLP.\n\nIn this role you will be encouraged to keep up with emerging trends in machine learning, research state of the art deep learning architectures, prototype new modelling ideas and conduct offline and online experiments and deploy your solutions to production.\n\nResponsibilities\n\u2022 Develop and implement machine learning algorithms to solve business problems\n\u2022 Design and implement scalable data processing and machine learning pipelines\n\u2022 Collaborate with product, engineering, and data teams to identify machine learning opportunities\n\u2022 Evaluate and improve the performance of machine learning models\n\u2022 Stay up-to-date with the latest developments in machine learning research and apply them to real-world problems\n\u2022 Write clean, scalable, and maintainable code\n\u2022 Communicate technical concepts and ideas to both technical and non-technical stakeholders\n\u2022 Sharing your knowledge by giving brown bag sessions, tech talks, and evangelising appropriate tech and engineering best practices.\n\u2022 Mentoring other team members, facilitating within/across team workshops, and leading agile development.\n\u2022 PhD or Masters's Degree in Computer Science, Mathematics, or Statistics a similar technical field of study with a specialisation in Machine Learning, Data mining, Information Retrieval or Data science.\n\u2022 10+ years of industry experience in building production-grade machine learning systems with all aspects of research, model training, tuning, deploying, serving and monitoring. Industry experience in ecommerce, recommender systems, digital marketing or two-sided marketplaces is a plus.\n\u2022 Experience in the following areas - Bayesian methods, Reinforcement learning, Deep learning Architectures and Recommendation systems and if you have experience in ML for Ads or ecommerce it is a big plus.\n\u2022 Be motivated, and self-driven in a fast (we truly mean fast) paced environment with a proven track record demonstrating impact across several teams and/or organisations.\n\u2022 Ability to communicate and collaborate effectively with business stakeholders and manage tasks in a timely manner.\n\u2022 At Rokt we encourage autonomy; teams have complete ownership of their systems including building, running and monitoring. As such, you may be required to be on-call and respond to system alerts should they arise.\n\u2022 Ideas, opinions, and the ability to share them through respectful proposals, presentations, and team-wide discussions, An eagerness to work and learn in the open and share your learnings with your teammates.\n\u2022 Experience with Kubernetes, Kubeflow, TFX and Feature Store in a production environment is a massive plus\n\u2022 Work with the greatest talent in tech. Our recruitment process is tough but diligent. We\u2019re constantly aiming to implement our value of \u201craise the bar\u201d and set high standards for our Rokt\u2019stars. This is essential in our high-performing, high-grow culture where we strive to bring in the brightest and best talent. Our teams thrive by challenging the status quo and we encourage all of our teams to unlock their desire to achieve something bigger.\n\u2022 Join a community. At Rokt we\u2019re a community of curious explorers. We\u2019re not afraid of venturing into uncharted territories. We work together as one single, aligned team. We value diversity and transparency which is why we support a number of internal employee resource groups including an EDI steering committee, Rainbow Rokts that empowers our LGBTQIA+ Rokt\u2019stars, and Womxn who Rokt that promotes gender equality in tech.\n\u2022 Accelerate your career. We want you to unlock your full potential. This is why we have an annual \u2018Level Up\u2019 allowance of $5,000 that gives Rokt\u2019stars the ability to take courses, attend events, go to training, and more to help our great employees become even better.\n\u2022 Take a break. When you work hard, we know you also need to rest. We offer generous time off and parental leave policies, as well as mental health and wellness days for all employees. We even incentivize individuals to utilize their PTO with \u201cHigh 5\u201d days, an additional 5 days of PTO when you\u2019ve used 75% of your allotted annual paid leave. We also offer a paid Rokt\u2019star Sabbatical for employees who have been with us for 5 years or more.\n\u2022 Become a shareholder. All Rokt\u2019stars have stock options. If we succeed, everyone is rewarded.\n\u2022 See the world! We want our Rokt\u2019stars to enjoy the ride. As we aim to bring meaning and fun to our everyday work, we host global all-staff events in amazing locations (Phuket, Thailand in January 2020, Hawaii in May 2022, and Whistler in 2023). As we strive to build a community of curious explorers, we also offer generous relocation packages for those interested in moving to another Rokt office. We have bustling offices in great cities including: New York,Seattle, Sydney, London, and Tokyo.\n\u2022 We believe we\u2019re better together. We love spending time together and are in the office most days (all teams are in the office 4 days per week). We also get that you need to balance your life and your commitments so you have flexibility to manage your own hours and can spend up to a week of every quarter working from anywhere.\n\u2022 Stay happy and healthy. In order to unleash our potential, we want to ensure you\u2019re able to keep your wellbeing a priority. This means you can enjoy a well-balanced, catered lunch 5x a week in the office along with healthy snacks. We also want you to feel at home when coming into work which is why we\u2019re a dog-friendly office so you can bring your furry friend to work with you. As part of your wellbeing benefits, we offer a wellness stipend so you can enjoy the gym on us. In the US, access generous retirement plans like a 4% dollar-for-dollar 401K matching plan and get fully funded premium health insurance for your entire family! [ NY OFFICE ONLY]\n\u2022 We believe in equality. Rokt is an Equal Opportunity Employer and we know our collective strength comes from how different we all are. We encourage you to apply for one of our open roles\u2014irrespective of socio-economic status or background, age, gender identity, race, religion, sexual orientation, color, pregnancy, carer/family responsibilities, national and social origin, political opinion, marital, veteran, or disability status.\n\nSalary Range - $260,000 - $300,000 per year plus equity\n\n#LI-Hybrid", "job_is_remote": true, "job_posted_at_timestamp": 1699488000, "job_posted_at_datetime_utc": "2023-11-09T00:00:00.000Z", "job_city": "Seattle", "job_state": "WA", "job_country": "US", "job_latitude": 47.60614, "job_longitude": -122.33285, "job_benefits": ["health_insurance", "paid_time_off", "retirement_savings"], "job_google_link": "https://www.google.com/search?gl=us&hl=en&rciv=jb&q=principal+machine+learning+architect&start=20&ibp=htl;jobs#fpstate=tldetail&htivrt=jobs&htiq=principal+machine+learning+architect&htidocid=wwbk06QWuk19TnCQAAAAAA%3D%3D", "job_offer_expiration_datetime_utc": null, "job_offer_expiration_timestamp": null, "job_required_experience": {"no_experience_required": false, "required_experience_in_months": 120, "experience_mentioned": true, "experience_preferred": true}, "job_required_skills": null, "job_required_education": {"postgraduate_degree": false, "professional_certification": false, "high_school": false, "associates_degree": false, "bachelors_degree": false, "degree_mentioned": true, "degree_preferred": true, "professional_certification_mentioned": false}, "job_experience_in_place_of_education": false, "job_min_salary": null, "job_max_salary": null, "job_salary_currency": null, "job_salary_period": null, "job_highlights": {"Qualifications": ["10+ years of industry experience in building production-grade machine learning systems with all aspects of research, model training, tuning, deploying, serving and monitoring", "Experience in the following areas - Bayesian methods, Reinforcement learning, Deep learning Architectures and Recommendation systems and if you have experience in ML for Ads or ecommerce it is a big plus", "Be motivated, and self-driven in a fast (we truly mean fast) paced environment with a proven track record demonstrating impact across several teams and/or organisations", "Ability to communicate and collaborate effectively with business stakeholders and manage tasks in a timely manner", "Ideas, opinions, and the ability to share them through respectful proposals, presentations, and team-wide discussions, An eagerness to work and learn in the open and share your learnings with your teammates", "Experience with Kubernetes, Kubeflow, TFX and Feature Store in a production environment is a massive plus"], "Responsibilities": ["You will join a team of top-tier Machine Learning Engineers and be an inherent part of the Relevancy org and will be responsible for driving machine learning solutions from research to production", "Your expertise will be critical in designing, implementing and scaling innovative machine learning solutions that drive impact across the business", "Reporting to the VP of Engineering (AI/Data) you will work closely with product managers, machine learning engineers and software engineers to understand business priorities, frame ML problems and architect solutions that deliver real-world value specifically in CTR modelling, Conversion modelling, UX optimisation, price optimisation and NLP", "In this role you will be encouraged to keep up with emerging trends in machine learning, research state of the art deep learning architectures, prototype new modelling ideas and conduct offline and online experiments and deploy your solutions to production", "Develop and implement machine learning algorithms to solve business problems", "Design and implement scalable data processing and machine learning pipelines", "Collaborate with product, engineering, and data teams to identify machine learning opportunities", "Evaluate and improve the performance of machine learning models", "Stay up-to-date with the latest developments in machine learning research and apply them to real-world problems", "Write clean, scalable, and maintainable code", "Communicate technical concepts and ideas to both technical and non-technical stakeholders", "Sharing your knowledge by giving brown bag sessions, tech talks, and evangelising appropriate tech and engineering best practices", "Mentoring other team members, facilitating within/across team workshops, and leading agile development", "PhD or Masters's Degree in Computer Science, Mathematics, or Statistics a similar technical field of study with a specialisation in Machine Learning, Data mining, Information Retrieval or Data science", "At Rokt we encourage autonomy; teams have complete ownership of their systems including building, running and monitoring"], "Benefits": ["Accelerate your career", "This is why we have an annual \u2018Level Up\u2019 allowance of $5,000 that gives Rokt\u2019stars the ability to take courses, attend events, go to training, and more to help our great employees become even better", "We offer generous time off and parental leave policies, as well as mental health and wellness days for all employees", "We even incentivize individuals to utilize their PTO with \u201cHigh 5\u201d days, an additional 5 days of PTO when you\u2019ve used 75% of your allotted annual paid leave", "We also offer a paid Rokt\u2019star Sabbatical for employees who have been with us for 5 years or more", "We also get that you need to balance your life and your commitments so you have flexibility to manage your own hours and can spend up to a week of every quarter working from anywhere", "This means you can enjoy a well-balanced, catered lunch 5x a week in the office along with healthy snacks", "As part of your wellbeing benefits, we offer a wellness stipend so you can enjoy the gym on us", "In the US, access generous retirement plans like a 4% dollar-for-dollar 401K matching plan and get fully funded premium health insurance for your entire family!", "Salary Range - $260,000 - $300,000 per year plus equity"]}, "job_job_title": "Learning engineer", "job_posting_language": "en", "job_onet_soc": "15111100", "job_onet_job_zone": "5"}