{"job_id": "YnAj3jWVtxe-LkXKAAAAAA==", "employer_name": "Detroit Lions", "employer_logo": "https://s3.amazonaws.com/cms.ipressroom.com/67/files/20237/64dbf1c73d6332067eb56cdb_Detroit+Lions+Logo/Detroit+Lions+Logo_88161154-59c3-4040-940c-04ca6cd7a3ea-prv.png", "employer_website": "https://www.detroitlions.com", "employer_company_type": "Entertainment", "job_publisher": "ZipRecruiter", "job_employment_type": "FULLTIME", "job_title": "Corporate Partnerships Sales Director", "job_apply_link": "https://www.ziprecruiter.com/c/Detroit-Lions/Job/Corporate-Partnerships-Sales-Director/-in-Detroit,MI?jid=eac6f5e240788a33", "job_apply_is_direct": false, "job_apply_quality_score": 0.7284, "apply_options": [{"publisher": "ZipRecruiter", "apply_link": "https://www.ziprecruiter.com/c/Detroit-Lions/Job/Corporate-Partnerships-Sales-Director/-in-Detroit,MI?jid=eac6f5e240788a33", "is_direct": false}, {"publisher": "TeamWork Online", "apply_link": "https://www.teamworkonline.com/football-jobs/detroit-lions/lions/corporate-partnerships-sales-director-2070258", "is_direct": false}, {"publisher": "Startup Jobs", "apply_link": "https://startup.jobs/corporate-partnerships-sales-director-detroit-lions-5040444", "is_direct": false}, {"publisher": "JobServe", "apply_link": "https://www.jobserve.com/us/en/extjob/CORPORATE-PARTNERSHIPS-SALES-DIRECTOR-in-Detroit-Michigan-USA-A6C90311598977791D/", "is_direct": false}, {"publisher": "Ladders", "apply_link": "https://www.theladders.com/job/corporate-partnerships-sales-director-aeg-detroit-mi_68105912", "is_direct": false}, {"publisher": "LifeworQ", "apply_link": "https://lifeworq.com/job/de15d329-73fd-48b1-b3b4-8c08bddae77f", "is_direct": false}, {"publisher": "Detroit, MI - Geebo", "apply_link": "https://detroit-mi.geebo.com/jobs-online/view/id/1348621132-corporate-partnerships-sales-director-/", "is_direct": false}, {"publisher": "Learn4Good", "apply_link": "https://www.learn4good.com/jobs/detroit/michigan/sales/2924134535/e/", "is_direct": false}], "job_description": "The Corporate Partnerships Sales Director will be responsible for sales interactions and strategies to acquire, develop, and retain corporate sponsors, advertisers, and partners to generate new and sustain existing revenue streams that support the Detroit Lions' business objectives. The candidate will work with various departments to build assets and programs with an analytical approach to demonstrate the value proposition of a partnership. This role will implement sales presentations to prospects to foster new business acquisition, and revenue optimization objectives. The position will identify new opportunities to strengthen and ensure sustainable growth opportunities. The position will work with the Sr. Director of Corporate Partnerships.\n\nESSENTIAL FUNCTIONS (including, but not limited to):\nThe Corporate Partnerships Sales Director position will have daily responsibilities including, without limitation, the following:\n\u2022 Responsible for creating, developing and selling fully integrated partnerships with local, regional and national clients/markets and establish effective pursuit strategies to secure partnerships.\n\u2022 Identify and collaboratively assess partnership opportunities while establishing new client relationships utilizing various sales strategies, including but not limited to, research, cold calls, site visits, and outside sales calls.\n\u2022 Initiate contracts develop and nurture strategic/mutually beneficial relationships with partners to drive additional revenue generation.\n\u2022 Manage the sustained development and management of partner relationships with a focus on the creation of plans which accomplish strategic objectives and a measurable return on investment.\n\u2022 Work with internal departments to develop and execute programs that support partnership programs and elements.\n\u2022 Execute meetings, calls, and presentations with high-level corporate executives.\n\nNONESSENTIAL FUNCTIONS:\n\u2022 Work in conjunction with Business Strategy & Analytics, Marketing, and all critical departments to develop presentations that include measurable elements.\n\u2022 Research prospect brands and their competitors to identify opportunities and solution-based programs.\n\u2022 Create and manage high-value, fully-integrated advertising and sponsorship packages that are in line with the partner's marketing objectives.\n\u2022 Participate in the development, ideation, evolution, implementation, and fulfillment of service and activation platform.\n\u2022 Sell NFL Corporate Sponsors and work with NFL Business Development colleagues to maximize partner investment levels.\n\u2022 Fiscal responsibility with departmental budget expenses.\n\u2022 Develop, write and present corporate sponsorship sales proposals to key clients.\n\u2022 In coordination with the Sr. Director of Corporate Partnership, create new sales collateral or modify existing collateral as required for both the Detroit Lions and Ford Field.\n\u2022 Work cross-departmentally to develop new sellable marketing, community, NFL initiatives and digital platforms our sales team can use to monetize business opportunities.\n\u2022 Manage client programs as they relate to billing/accounting, promotions/marketing, ticket office, broadcasting, community outreach, etc.\n\u2022 Collaboration with Sr. Director of Corporate Partnership with the identification of prospect opportunities.\n\u2022 Maintain weekly reports for personal sales pipeline, revenue achievements, and prospecting.\n\u2022 Incorporate appropriate market research into sponsorship proposals and sales presentations.\n\u2022 Utilize NFL SABR data to maximize category opportunities for the Detroit Lions.\n\u2022 Effectively communicate client expectations and contractual obligations to appropriate internal departments.\n\u2022 Work as a team with Activation Account Managers to provide excellent customer service and to ensure fulfillment of client deliverables with account base.\n\u2022 Work in partnership with assigned Activation Account Manager team to form 1:1 team responsible for revenue generation consistent with expectations for new business, renewals and contracted accounts.\n\u2022 Ability to develop strong, long-term relationships with both clients and co-workers.\n\u2022 Business aptitude to understand and manage client needs and organizational goals to create unique and innovative revenue generating programs.\n\u2022 Gameday responsibilities include activation setup, entertaining clients and fulfilling sponsorship contract obligations.\n\u2022 Conducts business during non-traditional hours, taking advantage of opportunities to interact with clients and prospects during games, events and away game trips.\n\u2022 Event planning and execution for partner-sponsored events or meetings.\n\u2022 Work with NFL sponsorship colleagues to grow and develop partnerships.\n\u2022 Will accept other responsibilities and duties required by the supervisor consistent with the objectives and essential functions of this position. Such responsibilities shall be incorporated into the position description if they are ongoing.\n\nQUALIFICATIONS / REQUIREMENTS:\n\u2022 Bachelor's degree with an emphasis in Business, Communications, Marketing or Management required.\n\u2022 Minimum five years of sponsorship sales experience with a major league professional sports team or high-profile entertainment entity, while working in a competitive sales environment.\n\u2022 Exceptional organizational skills with an ability to handle multiple assignments in a fast-paced environment with tight deadlines.\n\u2022 Strong verbal and written communication skills with proven interpersonal skills.\n\u2022 Ability to exercise sound business judgment generating effective solutions quickly and raising issues to management as necessary.\n\u2022 Team player spirit with an exceptional customer service attitude.\n\u2022 Strong working knowledge of MS Office (Word, Excel, Outlook, PowerPoint)\n\u2022 Must be able to work flexible hours including some weekends and evenings.\n\u2022 May require work out of both the Ford Field Management Office and the Allen Park Training Facility.\n\u2022 A valid Driver's License and a good driving record.\n\u2022 Willingness to travel, including weekends.", "job_is_remote": false, "job_posted_at_timestamp": 1707811200, "job_posted_at_datetime_utc": "2024-02-13T08:00:00.000Z", "job_city": "Detroit", "job_state": "MI", "job_country": "US", "job_latitude": 42.33143, "job_longitude": -83.04575, "job_benefits": null, "job_google_link": "https://www.google.com/search?gl=us&hl=en&rciv=jb&q=sponsorship+sales+director&start=10&ibp=htl;jobs#fpstate=tldetail&htivrt=jobs&htiq=sponsorship+sales+director&htidocid=YnAj3jWVtxe-LkXKAAAAAA%3D%3D", "job_offer_expiration_datetime_utc": "2024-04-12T00:00:00.000Z", "job_offer_expiration_timestamp": 1712880000, "job_required_experience": {"no_experience_required": false, "required_experience_in_months": 60, "experience_mentioned": true, "experience_preferred": false}, "job_required_skills": null, "job_required_education": {"postgraduate_degree": false, "professional_certification": false, "high_school": false, "associates_degree": false, "bachelors_degree": false, "degree_mentioned": true, "degree_preferred": false, "professional_certification_mentioned": false}, "job_experience_in_place_of_education": false, "job_min_salary": null, "job_max_salary": null, "job_salary_currency": null, "job_salary_period": null, "job_highlights": {"Qualifications": ["Ability to develop strong, long-term relationships with both clients and co-workers", "Business aptitude to understand and manage client needs and organizational goals to create unique and innovative revenue generating programs", "Bachelor's degree with an emphasis in Business, Communications, Marketing or Management required", "Minimum five years of sponsorship sales experience with a major league professional sports team or high-profile entertainment entity, while working in a competitive sales environment", "Exceptional organizational skills with an ability to handle multiple assignments in a fast-paced environment with tight deadlines", "Strong verbal and written communication skills with proven interpersonal skills", "Ability to exercise sound business judgment generating effective solutions quickly and raising issues to management as necessary", "Team player spirit with an exceptional customer service attitude", "Strong working knowledge of MS Office (Word, Excel, Outlook, PowerPoint)", "Must be able to work flexible hours including some weekends and evenings", "May require work out of both the Ford Field Management Office and the Allen Park Training Facility", "A valid Driver's License and a good driving record", "Willingness to travel, including weekends"], "Responsibilities": ["The Corporate Partnerships Sales Director will be responsible for sales interactions and strategies to acquire, develop, and retain corporate sponsors, advertisers, and partners to generate new and sustain existing revenue streams that support the Detroit Lions' business objectives", "The candidate will work with various departments to build assets and programs with an analytical approach to demonstrate the value proposition of a partnership", "This role will implement sales presentations to prospects to foster new business acquisition, and revenue optimization objectives", "The position will identify new opportunities to strengthen and ensure sustainable growth opportunities", "The Corporate Partnerships Sales Director position will have daily responsibilities including, without limitation, the following:", "Responsible for creating, developing and selling fully integrated partnerships with local, regional and national clients/markets and establish effective pursuit strategies to secure partnerships", "Identify and collaboratively assess partnership opportunities while establishing new client relationships utilizing various sales strategies, including but not limited to, research, cold calls, site visits, and outside sales calls", "Initiate contracts develop and nurture strategic/mutually beneficial relationships with partners to drive additional revenue generation", "Manage the sustained development and management of partner relationships with a focus on the creation of plans which accomplish strategic objectives and a measurable return on investment", "Work with internal departments to develop and execute programs that support partnership programs and elements", "Execute meetings, calls, and presentations with high-level corporate executives", "Work in conjunction with Business Strategy & Analytics, Marketing, and all critical departments to develop presentations that include measurable elements", "Research prospect brands and their competitors to identify opportunities and solution-based programs", "Create and manage high-value, fully-integrated advertising and sponsorship packages that are in line with the partner's marketing objectives", "Participate in the development, ideation, evolution, implementation, and fulfillment of service and activation platform", "Sell NFL Corporate Sponsors and work with NFL Business Development colleagues to maximize partner investment levels", "Fiscal responsibility with departmental budget expenses", "Develop, write and present corporate sponsorship sales proposals to key clients", "In coordination with the Sr", "Director of Corporate Partnership, create new sales collateral or modify existing collateral as required for both the Detroit Lions and Ford Field", "Work cross-departmentally to develop new sellable marketing, community, NFL initiatives and digital platforms our sales team can use to monetize business opportunities", "Manage client programs as they relate to billing/accounting, promotions/marketing, ticket office, broadcasting, community outreach, etc", "Collaboration with Sr", "Director of Corporate Partnership with the identification of prospect opportunities", "Maintain weekly reports for personal sales pipeline, revenue achievements, and prospecting", "Incorporate appropriate market research into sponsorship proposals and sales presentations", "Utilize NFL SABR data to maximize category opportunities for the Detroit Lions", "Effectively communicate client expectations and contractual obligations to appropriate internal departments", "Work as a team with Activation Account Managers to provide excellent customer service and to ensure fulfillment of client deliverables with account base", "Gameday responsibilities include activation setup, entertaining clients and fulfilling sponsorship contract obligations", "Conducts business during non-traditional hours, taking advantage of opportunities to interact with clients and prospects during games, events and away game trips", "Event planning and execution for partner-sponsored events or meetings", "Work with NFL sponsorship colleagues to grow and develop partnerships", "Will accept other responsibilities and duties required by the supervisor consistent with the objectives and essential functions of this position", "Such responsibilities shall be incorporated into the position description if they are ongoing"]}, "job_job_title": "Sales director", "job_posting_language": "en", "job_onet_soc": "11202200", "job_onet_job_zone": "4", "job_occupational_categories": ["11-2022.00: Sales Managers"], "job_naics_code": "711", "job_naics_name": "Performing Arts, Spectator Sports, and Related Industries"}