{"job_id": "cMclR7ustuGy6CUzAAAAAA==", "employer_name": "Cardinal Health", "employer_logo": "https://www.cardinalhealth.com/content/dam/corp/web/logos/logo-main.png", "employer_website": "http://www.cardinal.com", "employer_company_type": "Wholesale", "job_publisher": "Cardinal Health", "job_employment_type": "FULLTIME", "job_title": "Senior Data Scientist", "job_apply_link": "https://jobs.cardinalhealth.com/search/jobdetails/senior-data-scientist/eb5dcd91-8765-401e-85cc-6e58ae6c9034", "job_apply_is_direct": false, "job_apply_quality_score": 0.898, "apply_options": [{"publisher": "Cardinal Health", "apply_link": "https://jobs.cardinalhealth.com/search/jobdetails/senior-data-scientist/eb5dcd91-8765-401e-85cc-6e58ae6c9034", "is_direct": false}, {"publisher": "Workday", "apply_link": "https://cardinalhealth.wd1.myworkdayjobs.com/EXT/job/OH-Ohio-Work-from-Home/Senior-Data-Scientist_20138807", "is_direct": false}, {"publisher": "Glassdoor", "apply_link": "https://www.glassdoor.com/job-listing/senior-data-scientist-cardinal-health-JV_KO0,21_KE22,37.htm?jl=1009136112991", "is_direct": false}, {"publisher": "Jooble", "apply_link": "https://jooble.org/jdp/8390816121233564880", "is_direct": false}, {"publisher": "Health Industry Distributors Association", "apply_link": "https://jobs.hida.org/job/senior-data-scientist-253962", "is_direct": false}, {"publisher": "LinkedIn", "apply_link": "https://www.linkedin.com/jobs/view/senior-data-scientist-at-cardinal-health-3835013794", "is_direct": false}, {"publisher": "Adzuna", "apply_link": "https://www.adzuna.com/details/4577592031", "is_direct": false}, {"publisher": "Alumni Career Center", "apply_link": "https://alumnijobs.cofc.edu/jobs/19783596/senior-data-scientist", "is_direct": false}], "job_description": "Fuse is on a mission to disrupt healthcare. Our focus on technology, design and a product mindset will help drive that disruption and establish Cardinal Health as a leader in healthcare technology. Fuse\u2019s innovation culture and modern product development teams power the evolution of our commercial products and spark the creation of new businesses and products. We leverage technology and insights across the enterprise to solve customer problems and forge new models. Design thinking drives our teams to imagine and invent the next horizon. It\u2019s more than technology innovation \u2013 it\u2019s creating new business models beyond our wildest dreams. With a strong leadership team setting the bar high, Fusers are challenged to bring their creativity, technical expertise and diverse perspectives to do the best work of their lives.\n\nThe Data Scientist is a key role in the transformation of business. They will work closely with business stakeholders to understand their goals and determine how data science can be used to achieve those goals. They will use relevant statistical techniques, machine learning models and artificial intelligence algorithms to analyze data, design data models and derive insights to influence actions that maximize business value and effectiveness for the commercial technology segments.\n\nWhat Data Science contributes to Cardinal Health\n\nThe Data & Analytics Function oversees the analytics life-cycle in order to identify, analyze and present relevant insights that drive business decisions and anticipate opportunities to achieve a competitive advantage. This function manages analytic data platforms, the access, design and implementation of reporting/business intelligence solutions, and the application of advanced quantitative modeling.\n\nData Science applies base, scientific methodologies from various disciplines, techniques and tools that extracts knowledge and insight from data to solve complex business problems on large data sets, integrating multiple systems.\n\nResponsibilities\n\u2022 Designing and developing machine learning and deep learning solutions and systems.\n\u2022 Using statistical analysis determine which\u202fdata modeling\u202fapproach to use and running / training machine learning tests and experiments. Implementing appropriate ML algorithms.\n\u2022 Mine and analyze large structured and unstructured datasets. Identify the data attributes that influence the outcome, define, and monitor metrics, create data narratives, and builds tools to drive decisions.\n\u2022 Lead data science projects and partner with cross functional teams to deliver end-to-end advanced analytics/machine learning solution.\n\u2022 Propose, own initiatives and demonstrate though leadership that improve the efficiency and productivity of the data science Center of Excellence\n\u2022 Work across diverse teams, perspectives and opinions and quickly build consensus.\n\u2022 Encourages informed risk-taking and acts as a catalyst for innovation at Fuse; generates practical, sustainable and creative options to solve problems and create business opportunities, while maximizing existing resources.\n\u2022 Communicate results and statistical concepts to key business leaders.\n\u2022 Create visualizations of data that make distributions, trends, and results easy to understand for business leaders.\n\u2022 Diagnose business need, analyze business process, data flows, IT / technical artifacts and extract understanding of how the system or business process works as input into projects / solutions.\n\u2022 Proactively develops, maintains and evangelizes technical knowledge in Machine Learning and adjacent technologies.\u202f Keeps up-to-date on current trends and best practices.\n\u2022 Performs assessments and listens to internal/external customers to understand and anticipate their needs and determine their priorities in the context of the overall enterprise.\n\u2022 Possess deep functional and technical understanding of the Machine Learning technologies (Google\u2019s Cloud Platform, custom and COTS-embedded) and provide prescriptive guidance on how these are leveraged across the Fuse landscape.\n\u2022 Identify high-value ML business opportunities and work with Business and IT stakeholders to realize business benefit.\n\u2022 Assist in implementation of ML related efforts to ensure their operational viability.\n\u2022 Assist skill uplift across the Fuse and the business.\n\u2022 Understand and enable Commercial Technology\u2019s business via an efficient and effective ML practice that provides ML solutions and outcomes at the most efficient cost.\u202f\n\u2022 Ensure effective designs and quality deliverables in the ML space by designing and developing machine learning and deep learning systems, running machine learning tests and experiments, implementing appropriate ML algorithms\n\u2022 Aide adoption of ML solutions within the business by conducting training, coordinating demos.\n\u2022 Support and influence delivery operations within platforms by continually looking for opportunities to streamline delivery, increase business value and measure platform value via metrics and measures.\n\u2022 Weigh Risk & ROI against schedule & budget considerations and provides solution recommendations.\n\u2022 Ensure projects are delivered in-line with ML Reference Architecture, road map and to the defined standards and best practices.\n\u2022 Effectively communicate and influence others towards future state solutions and architectures.\u202f Evangelize the purpose and value of Machine Learning solutions.\n\nQualifications\n\u2022 Deep knowledge of clinical domain and datasets\n\u2022 Experience in Natural language processing (NLP), Prompt engineering, Embedding, Vector DB\n\u2022 Implement, train, and fine-tune LLM and GPT-like models on large-scale datasets to ensure optimal performance and accuracy\n\u2022 Proven Machine Learning experience and involvement in data science projects and product delivery.\n\u2022 Experience in the Design and implementation of AI/ML models and solutions using Google Cloud Platform technologies, including but not limited to Vertex AI , BigQuery, AI Platform, TensorFlow Extended (TFX), Dataflow, and Compute Engine.\n\u2022 Experience with Machine Learning and related technologies such as Python, other relevant libraries and frameworks like PyTorch and tools like Jupiter Notebooks, git.\n\u2022 Strong understanding of machine learning principles, including supervised and unsupervised learning, deep learning, and reinforcement learning. Knowledge of generative models and autoregressive models.\n\u2022 Understanding of cloud data engineering and integration concepts.\n\u2022 Strong mathematical and statistical skills.\n\u2022 Understanding of exploratory data analysis, descriptive analytics, prescriptive analytics, predictive analytics and so on.\n\u2022 10+ years in the Healthcare industry and knowledge of clinical data preferred.\n\u2022 MD, PharmD by training and Healthcare informatics experience preferred\n\u2022 Delivery experience in Data Engineering with Google Cloud Platform including Big Query, Dataflow, Cloud Data Fusion, Cloud Composer, Dataproc, Cloud Pubsub, Cloud Function etc.\n\u2022 Delivery of related information software solutions such as data warehouses and integration platforms.\n\u2022 Agile development skills and experience.\n\u2022 Bachelor\u2019s degree in Mathematics, Statistics, Engineering, Computer Science, other related field, or equivalent years of relevant work experience is preferred. Advanced technical degree is a plus.\n\nWhat is expected of you and others at this level\n\u2022 Applies advanced knowledge and understanding of concepts, principles, and technical capabilities to manage a wide variety of projects\n\u2022 Participates in the development of policies and procedures to achieve specific goals\n\u2022 Recommends new practices, processes, metrics, or models\n\u2022 Works on or may lead complex projects of large scope\n\u2022 Projects may have significant and long-term impact\n\u2022 Provides solutions which may set precedent\n\u2022 Independently determines method for completion of new projects\n\u2022 Receives guidance on overall project objectives\n\u2022 Acts as a mentor to less experienced colleagues\n\n\u200b\n\nAnticipated salary range: $119,800-$171,100\n\nBonus eligible: Yes\n\nBenefits: Cardinal Health offers a wide variety of benefits and programs to support health and well-being.\n\u2022 Medical, dental and vision coverage\n\u2022 Paid time off plan\n\u2022 Health savings account (HSA)\n\u2022 401k savings plan\n\u2022 Access to wages before pay day with myFlexPay\n\u2022 Flexible spending accounts (FSAs)\n\u2022 Short- and long-term disability coverage\n\u2022 Work-Life resources\n\u2022 Paid parental leave\n\u2022 Healthy lifestyle programs\n\nApplication window anticipated to close: 04/20/2024 *if interested in opportunity, please submit application as soon as possible.\n\n#LI-Remote\n\nCandidates who are back-to-work, people with disabilities, without a college degree, and Veterans are encouraged to apply.\n\nCardinal Health supports an inclusive workplace that values diversity of thought, experience and background. We celebrate the power of our differences to create better solutions for our customers by ensuring employees can be their authentic selves each day. Cardinal Health is an Equal Opportunity/Affirmative Action employer. All qualified applicants will receive consideration for employment without regard to race, religion, color, national origin, ancestry, age, physical or mental disability, sex, sexual orientation, gender identity/expression, pregnancy, veteran status, marital status, creed, status with regard to public assistance, genetic status or any other status protected by federal, state or local law.", "job_is_remote": false, "job_posted_at_timestamp": 1708387200, "job_posted_at_datetime_utc": "2024-02-20T00:00:00.000Z", "job_city": null, "job_state": null, "job_country": "US", "job_latitude": 37.09024, "job_longitude": -95.71289, "job_benefits": ["retirement_savings", "dental_coverage", "health_insurance", "paid_time_off"], "job_google_link": "https://www.google.com/search?gl=us&hl=en&rciv=jb&q=lead+data+scientist&start=40&ibp=htl;jobs#fpstate=tldetail&htivrt=jobs&htiq=lead+data+scientist&htidocid=cMclR7ustuGy6CUzAAAAAA%3D%3D", "job_offer_expiration_datetime_utc": "2024-04-20T00:00:00.000Z", "job_offer_expiration_timestamp": 1713571200, "job_required_experience": {"no_experience_required": false, "required_experience_in_months": null, "experience_mentioned": true, "experience_preferred": true}, "job_required_skills": null, "job_required_education": {"postgraduate_degree": false, "professional_certification": false, "high_school": false, "associates_degree": false, "bachelors_degree": false, "degree_mentioned": true, "degree_preferred": true, "professional_certification_mentioned": false}, "job_experience_in_place_of_education": false, "job_min_salary": null, "job_max_salary": null, "job_salary_currency": null, "job_salary_period": null, "job_highlights": {"Qualifications": ["Deep knowledge of clinical domain and datasets", "Experience in Natural language processing (NLP), Prompt engineering, Embedding, Vector DB", "Implement, train, and fine-tune LLM and GPT-like models on large-scale datasets to ensure optimal performance and accuracy", "Proven Machine Learning experience and involvement in data science projects and product delivery", "Experience in the Design and implementation of AI/ML models and solutions using Google Cloud Platform technologies, including but not limited to Vertex AI , BigQuery, AI Platform, TensorFlow Extended (TFX), Dataflow, and Compute Engine", "Experience with Machine Learning and related technologies such as Python, other relevant libraries and frameworks like PyTorch and tools like Jupiter Notebooks, git", "Strong understanding of machine learning principles, including supervised and unsupervised learning, deep learning, and reinforcement learning", "Knowledge of generative models and autoregressive models", "Understanding of cloud data engineering and integration concepts", "Strong mathematical and statistical skills", "Understanding of exploratory data analysis, descriptive analytics, prescriptive analytics, predictive analytics and so on", "Delivery experience in Data Engineering with Google Cloud Platform including Big Query, Dataflow, Cloud Data Fusion, Cloud Composer, Dataproc, Cloud Pubsub, Cloud Function etc", "Delivery of related information software solutions such as data warehouses and integration platforms", "Agile development skills and experience"], "Responsibilities": ["They will work closely with business stakeholders to understand their goals and determine how data science can be used to achieve those goals", "They will use relevant statistical techniques, machine learning models and artificial intelligence algorithms to analyze data, design data models and derive insights to influence actions that maximize business value and effectiveness for the commercial technology segments", "The Data & Analytics Function oversees the analytics life-cycle in order to identify, analyze and present relevant insights that drive business decisions and anticipate opportunities to achieve a competitive advantage", "This function manages analytic data platforms, the access, design and implementation of reporting/business intelligence solutions, and the application of advanced quantitative modeling", "Data Science applies base, scientific methodologies from various disciplines, techniques and tools that extracts knowledge and insight from data to solve complex business problems on large data sets, integrating multiple systems", "Using statistical analysis determine which\u202fdata modeling\u202fapproach to use and running / training machine learning tests and experiments", "Mine and analyze large structured and unstructured datasets", "Identify the data attributes that influence the outcome, define, and monitor metrics, create data narratives, and builds tools to drive decisions", "Lead data science projects and partner with cross functional teams to deliver end-to-end advanced analytics/machine learning solution", "Propose, own initiatives and demonstrate though leadership that improve the efficiency and productivity of the data science Center of Excellence", "Work across diverse teams, perspectives and opinions and quickly build consensus", "Encourages informed risk-taking and acts as a catalyst for innovation at Fuse; generates practical, sustainable and creative options to solve problems and create business opportunities, while maximizing existing resources", "Communicate results and statistical concepts to key business leaders", "Create visualizations of data that make distributions, trends, and results easy to understand for business leaders", "Diagnose business need, analyze business process, data flows, IT / technical artifacts and extract understanding of how the system or business process works as input into projects / solutions", "Proactively develops, maintains and evangelizes technical knowledge in Machine Learning and adjacent technologies.\u202f Keeps up-to-date on current trends and best practices", "Performs assessments and listens to internal/external customers to understand and anticipate their needs and determine their priorities in the context of the overall enterprise", "Possess deep functional and technical understanding of the Machine Learning technologies (Google\u2019s Cloud Platform, custom and COTS-embedded) and provide prescriptive guidance on how these are leveraged across the Fuse landscape", "Identify high-value ML business opportunities and work with Business and IT stakeholders to realize business benefit", "Assist in implementation of ML related efforts to ensure their operational viability", "Assist skill uplift across the Fuse and the business", "Understand and enable Commercial Technology\u2019s business via an efficient and effective ML practice that provides ML solutions and outcomes at the most efficient cost.\u202f", "Ensure effective designs and quality deliverables in the ML space by designing and developing machine learning and deep learning systems, running machine learning tests and experiments, implementing appropriate ML algorithms", "Aide adoption of ML solutions within the business by conducting training, coordinating demos", "Support and influence delivery operations within platforms by continually looking for opportunities to streamline delivery, increase business value and measure platform value via metrics and measures", "Weigh Risk & ROI against schedule & budget considerations and provides solution recommendations", "Ensure projects are delivered in-line with ML Reference Architecture, road map and to the defined standards and best practices", "Effectively communicate and influence others towards future state solutions and architectures.\u202f Evangelize the purpose and value of Machine Learning solutions", "Applies advanced knowledge and understanding of concepts, principles, and technical capabilities to manage a wide variety of projects", "Participates in the development of policies and procedures to achieve specific goals", "Recommends new practices, processes, metrics, or models", "Projects may have significant and long-term impact", "Provides solutions which may set precedent", "Independently determines method for completion of new projects", "Receives guidance on overall project objectives", "Acts as a mentor to less experienced colleagues"], "Benefits": ["Anticipated salary range: $119,800-$171,100", "Bonus eligible: Yes", "Benefits: Cardinal Health offers a wide variety of benefits and programs to support health and well-being", "Medical, dental and vision coverage", "Paid time off plan", "Health savings account (HSA)", "401k savings plan", "Access to wages before pay day with myFlexPay", "Flexible spending accounts (FSAs)", "Short- and long-term disability coverage", "Work-Life resources", "Paid parental leave", "Healthy lifestyle programs"]}, "job_job_title": "Data scientist", "job_posting_language": "en", "job_onet_soc": "15111100", "job_onet_job_zone": "5", "job_naics_code": "424210", "job_naics_name": "Drugs and Druggists' Sundries Merchant Wholesalers"}