{"job_id": "uWjfN_Nl9EimK-M8AAAAAA==", "employer_name": "NetImpact Strategies", "employer_logo": null, "employer_website": "http://netimpactstrategies.com", "employer_company_type": null, "job_publisher": "Monster", "job_employment_type": "FULLTIME", "job_title": "Senior MLOps Engineer", "job_apply_link": "https://www.monster.com/job-openings/senior-mlops-engineer-remote-or--14b485ef-d260-49bf-9ac4-2da23e8827ab", "job_apply_is_direct": false, "job_apply_quality_score": 0.5704, "apply_options": [{"publisher": "Monster", "apply_link": "https://www.monster.com/job-openings/senior-mlops-engineer-remote-or--14b485ef-d260-49bf-9ac4-2da23e8827ab", "is_direct": false}], "job_description": "Job Description\n\nNetImpact Strategies has an opportunity for a Senior MLOps Engineer to join our talented Professional Services team. The Senior MLOps Engineer will support ongoing Information Technology (IT) Operations services for our Federal Civilian client. The Senior MLOps Engineer is a platform team developer who develops and manages Continuous Integration/Continuous Delivery (CI/CD) pipelines for machine learning models. The ideal candidate will bring forward solution ideas that support collaboration with IT Operations leadership and acts as an expert in Machine Learning Operations. Ultimately, a top-notch MLOps Engineer should have exceptional communication skills, be knowledgeable about the latest industry trends, and be highly innovative.\n\nTypical responsibilities include\n\u2022 Develops and maintains CI/CD pipelines to support machine learning workflows.\n\u2022 Develops and maintains Infrastructure as Code.\n\u2022 Works closely with development teams to debug and add new functionality to CI/CD pipelines.\n\u2022 Participates in plans to migrate and modernize workflows in Amazon Web Services.\n\u2022 Performs root cause analysis.\n\u2022 Designs procedures for system troubleshooting and maintenance.\n\u2022 Recommends cost-effective, technically feasible IT operations solutions that provide long term scalability, and anticipate future growth and performance needs.\n\u2022 Recommends data science best practices for ETL, EDA, and data wrangling.\n\u2022 Recommends MLOps tools and best practices.\n\u2022 Works with machine learning platforms like: AWS SageMaker, MLFlow.\n\u2022 Works with machine learning frameworks like: PyTorch, TensorFlow, Scikit-learn\n\u2022 Works with Infrastructure as Code tools like Terraform.\n\u2022 Works with container tools like; Kubernetes, Docker\n\u2022 Works with programming languages like: Python, R.\n\u2022 Works with database engines like: MS SQL, PostgreSQL, MySQL.\n\u2022 Works with DevOps tools like Jenkins.\nQualifications\n\nRequired Skills:\n\u2022 M.S. or B.S. in a degree such as Computer Science, Information Systems, or Information Technology.\n\u2022 5 years of experience in this role or a similar role.\n\u2022 Experience providing technical leadership in creation and maintenance of CI/CD pipelines.\n\u2022 Demonstrates a leadership mindset, solid operational experience, and the ability to problem-solve.\n\u2022 Must have a problem-solving attitude and a collaborative team spirit.\n\u2022 Capable of organizing, tracking, and managing multiple projects and deadlines.\n\u2022 Expertise with machine learning platforms such as: AWS SageMaker, MLFlow.\n\u2022 Expertise with machine learning frameworks such as: PyTorch, Tensforflow.\n\u2022 Expertise with Python and Jupyter Notebooks.\n\u2022 Expertise in data science; ETL, EDA, and data wrangling.\n\u2022 Strong experience with Cloud providers such as AWS.\n\u2022 Strong experience with database engines such as: MS SQL, PostgreSQL, MySQL.\n\u2022 Strong experience with IaaS, PaaS, and SaaS based systems.\n\u2022 Working knowledge of Infrastructure as Code tools like Terraform.\n\u2022 Working knowledge of DevOps tools like Jenkins.\n\u2022 Working knowledge of geospatial data.\nAbout Us\n\nPerks of working at NetImpact Strategies\n\u2022 Your health comes first \u2013 we offer comprehensive medical, dental, & vision insurance that starts the first of the month after you join the team\n\u2022 Invest in your future \u2013 401(k) Plan \u2013 Immediately vested employer contributions; no matching required\n\u2022 Work hard, play hard \u2013 we offer a generous Paid Time Off (PTO) policy and observe ALL ten (10) federal holidays\n\u2022 Pawsitively pawesome \u2013 Pet Insurance (because our little critters are part of our families, too!)\n\u2022 Invest in your education \u2013 Tuition reimbursement, internal training programs, & company-sponsored industry certifications\n\u2022 Be part of a dynamic and collaborative work environment recently ranked by The Washington Post as a Top Work Place in 2019, 2020, & 2022!\n\u2022 Have fun and celebrate and give back \u2013 Team building activities, community volunteering, quarterly HQ days, & an offsite annual awards banquet\n\nABOUT US\n\nNetImpact Strategies Inc. (NetImpact) has been a Trusted Advisor driving impact through digital transformation for the Federal Government for over a decade. We solve complex problems with innovation and agility to create meaningful, transformative, and enduring change. As Trusted Advisors, NetImpact professionals partner with customer agencies to deliver solutions that empower them to not only meet their missions but also realize their strategic vision through agile, outcome-focused solutions addressing both strategic and tactical requirements. We design and implement comprehensive, tailored solutions that are both mindful of the client's culture and organizational dynamics. NetImpact\u2019s core values and commitment to a customer and results-oriented delivery approach has propelled our growth and enabled us to deliver impactful value across Strategic Consulting, Process Automation, Cloud, DevSecOps, Data and Analytics, and Cyber Security for the Federal Government.\n\nACCESSIBILITY NOTE\n\nNetImpact Strategies is committed to complying with all applicable provisions of the Americans with Disabilities Act, as amended (\u201cADA\u201d), and applicable state and local laws. It is NetImpact\u2019s policy not to discriminate against any qualified person or applicant with regard to any terms or conditions of employment on the basis of such individual\u2019s disability. Consistent with this policy of non-discrimination, NetImpact will provide reasonable accommodations to an individual with a disability, as defined in the ADA or applicable law, who has made NetImpact aware of his/her disability, unless doing so would cause undue hardship to NetImpact. If you are an applicant and need reasonable accommodation when applying for job opportunities within NetImpact, or request reasonable accommodation to utilize NetImpact\u2019s online employment application, please contact careers@netimpactstrategies.com.\n\nEQUAL OPPORTUNITY EMPLOYER\n\nNetImpact is committed to the development of a creative, diverse, and inclusive work environment. In order to provide equal employment and advancement opportunities to all individuals, employment decisions at NetImpact will be based on merit, qualifications, and abilities. NetImpact does not discriminate against any person because of race, color, creed, religion, sex (including gender identity, sexual orientation, and pregnancy), marital status, national origin, disability, age, veteran status, genetic information or any other characteristic protected by federal, state, and local laws (referred to as \"protected status\").\n\nAbout the Company:\nNetImpact Strategies", "job_is_remote": false, "job_posted_at_timestamp": 1709942400, "job_posted_at_datetime_utc": "2024-03-09T00:00:00.000Z", "job_city": "Remote", "job_state": "OR", "job_country": "US", "job_latitude": 43.005947, "job_longitude": -123.89259, "job_benefits": ["paid_time_off", "health_insurance", "retirement_savings", "dental_coverage"], "job_google_link": "https://www.google.com/search?gl=us&hl=en&rciv=jb&q=mlops+expert&start=10&ibp=htl;jobs#fpstate=tldetail&htivrt=jobs&htiq=mlops+expert&htidocid=uWjfN_Nl9EimK-M8AAAAAA%3D%3D", "job_offer_expiration_datetime_utc": null, "job_offer_expiration_timestamp": null, "job_required_experience": {"no_experience_required": false, "required_experience_in_months": 60, "experience_mentioned": true, "experience_preferred": false}, "job_required_skills": null, "job_required_education": {"postgraduate_degree": false, "professional_certification": false, "high_school": false, "associates_degree": false, "bachelors_degree": false, "degree_mentioned": true, "degree_preferred": true, "professional_certification_mentioned": true}, "job_experience_in_place_of_education": false, "job_min_salary": null, "job_max_salary": null, "job_salary_currency": null, "job_salary_period": null, "job_highlights": {"Qualifications": ["M.S. or B.S. in a degree such as Computer Science, Information Systems, or Information Technology", "5 years of experience in this role or a similar role", "Experience providing technical leadership in creation and maintenance of CI/CD pipelines", "Demonstrates a leadership mindset, solid operational experience, and the ability to problem-solve", "Must have a problem-solving attitude and a collaborative team spirit", "Capable of organizing, tracking, and managing multiple projects and deadlines", "Expertise with machine learning platforms such as: AWS SageMaker, MLFlow", "Expertise with machine learning frameworks such as: PyTorch, Tensforflow", "Expertise with Python and Jupyter Notebooks", "Expertise in data science; ETL, EDA, and data wrangling", "Strong experience with Cloud providers such as AWS", "Strong experience with database engines such as: MS SQL, PostgreSQL, MySQL", "Strong experience with IaaS, PaaS, and SaaS based systems", "Working knowledge of Infrastructure as Code tools like Terraform", "Working knowledge of DevOps tools like Jenkins", "Working knowledge of geospatial data"], "Responsibilities": ["Develops and maintains CI/CD pipelines to support machine learning workflows", "Develops and maintains Infrastructure as Code", "Works closely with development teams to debug and add new functionality to CI/CD pipelines", "Participates in plans to migrate and modernize workflows in Amazon Web Services", "Performs root cause analysis", "Designs procedures for system troubleshooting and maintenance", "Recommends cost-effective, technically feasible IT operations solutions that provide long term scalability, and anticipate future growth and performance needs", "Recommends data science best practices for ETL, EDA, and data wrangling", "Recommends MLOps tools and best practices", "Works with machine learning platforms like: AWS SageMaker, MLFlow", "Works with machine learning frameworks like: PyTorch, TensorFlow, Scikit-learn", "Works with Infrastructure as Code tools like Terraform", "Works with container tools like; Kubernetes, Docker", "Works with database engines like: MS SQL, PostgreSQL, MySQL"], "Benefits": ["Your health comes first \u2013 we offer comprehensive medical, dental, & vision insurance that starts the first of the month after you join the team", "Invest in your future \u2013 401(k) Plan \u2013 Immediately vested employer contributions; no matching required", "Work hard, play hard \u2013 we offer a generous Paid Time Off (PTO) policy and observe ALL ten (10) federal holidays", "Pawsitively pawesome \u2013 Pet Insurance (because our little critters are part of our families, too!)", "Invest in your education \u2013 Tuition reimbursement, internal training programs, & company-sponsored industry certifications", "Be part of a dynamic and collaborative work environment recently ranked by The Washington Post as a Top Work Place in 2019, 2020, & 2022!", "Have fun and celebrate and give back \u2013 Team building activities, community volunteering, quarterly HQ days, & an offsite annual awards banquet"]}, "job_job_title": "Engineer", "job_posting_language": "en", "job_onet_soc": "15111100", "job_onet_job_zone": "5"}