{"job_id": "cSSwEdDMxhnEEkFhAAAAAA==", "employer_name": "Thrive Scholars", "employer_logo": "https://encrypted-tbn0.gstatic.com/images?q=tbn:ANd9GcTWoOP-Tifuc5PnPMXlmwRNP18XuOQCnTESo_lW&s=0", "employer_website": null, "employer_company_type": null, "job_publisher": "LinkedIn", "job_employment_type": "FULLTIME", "job_title": "Senior Director of Corporate Partnerships, Technology", "job_apply_link": "https://www.linkedin.com/jobs/view/senior-director-of-corporate-partnerships-technology-at-thrive-scholars-3786595429", "job_apply_is_direct": false, "job_apply_quality_score": 0.7324, "apply_options": [{"publisher": "LinkedIn", "apply_link": "https://www.linkedin.com/jobs/view/senior-director-of-corporate-partnerships-technology-at-thrive-scholars-3786595429", "is_direct": false}], "job_description": "The Opportunity:\n\nAs our Director of Corporate Partnerships, you will play a critical role in helping us grow our partnerships with Technology-focused corporations in Los Angeles, Boston and across the country, effectively meeting the needs of our Scholars as well as those of our partners through mutually-beneficial relationships. At Thrive Scholars, we see these partners as key to our ability to deliver on our mission and ensure that our Scholars are able to successfully enter and grow within competitive Technology careers. Simultaneously, partners value their relationship with Thrive Scholars, as they recognize the role our organization plays in preparing highly-talented, underrepresented students to succeed within their companies and industry. In this role, you will have the opportunity to build and leverage Technology-focused corporate partnerships, unlocking key career opportunities for our Scholars and supporting partners in investing in a diverse pipeline of future industry leaders.\n\nThrive Scholars currently benefits from a wide range of corporate partnerships across industries, including an emerging base of Technology-focused partnerships. In this role, you will leverage your dynamic fundraising and partnership-development skills to steward and build on existing relationships, to market Thrive Scholars to the Technology sector and engage new partners, and to develop the most comprehensive philanthropic and corporate partnerships possible with leading Technology-focused companies across the country.\n\nIn addition to setting and implementing our Technology corporate partnership strategy in collaboration with members of our senior staff, fundraising, career development, and mentorship teams, you will work to ensure that we track and exceed our current partner satisfaction goals and our revenue and new corporate partnerships growth goals. As a team player who contributes to our broader development goals, your collaborative nature, attention to detail, and experience managing complex relationships will help us retain and secure sustainable revenue and corporate partnership opportunities within the Technology field.\n\nReporting to the Managing Director of Corporate Partnerships, this role is ideal for someone who enjoys exceeding partner expectations, is entrepreneurial, seeks to build a model corporate partnership program within the Technology industry, and is passionate about unlocking opportunities for highly talented, underrepresented young people. The position also provides a significant opportunity to collaborate with senior leaders, with whom you will partner to manage and upsell existing partners and close new deals.\n\nThis position is location flexible, with a preference for Los Angeles, Boston, or another major market and may require up to 20-25% national travel.\n\nKey Responsibilities:\n\nBusiness Development\n\nGOAL: Successfully establish new corporate partnerships with top-tier Technology-focused corporations in Los Angeles, Boston and across the country\n\u2022 Drive a consultative sales process by:\n\u2022 Identifying mission-aligned prospect corporations and developing and leveraging tailored cultivation strategies\n\u2022 Building a strong business case for partnering with us and leveraging interest in a stronger, more diverse talent pool to forge new corporate partnerships and attract philanthropic support\n\u2022 Identifying key decision-makers and supporters within prospective partner organizations\n\u2022 Manage sales pipeline & accelerate sales process\n\u2022 Managing relationships through strong communication and project management\n\u2022 Develop and leverage tailored cultivation strategies and solutions for each prospect\n\nPartner Engagement\n\nGOAL: Manage the onboarding of new partners and the seamless transition to account management team\n\u2022 Serve as the main point of contact with partners through partnership launch\n\u2022 Ensure that the partners are set up for a successful transition by capturing all required information and completing of the onboarding checklist\n\u2022 Build a program at a glance to ensure efficient execution for our account managers and partners\n\u2022 Work cross-functionally with our Career Development Team and Career Coaches to support recruitment for partner job opportunities\n\nAdministration\n\nGOAL: Ensure strong data and communications infrastructure to support a national technology-focused corporate partnership program\n\u2022 Manage all data records for corporate partners in Salesforce, including revenue pipeline and forecast\n\u2022 Manage/track sales process /activity for high-priority prospects\n\u2022 Create customized marketing materials and pitch presentations, as well as proposals for partner prospects\n\u2022 Contribute to the development team and overall organizational team efforts\n\u2022 Assist in development operations initiatives, including Salesforce data review and analysis, gift processing, and donor acknowledgments\n\u2022 Collaborate on the development annual planning\n\u2022 Support local fundraising events and cultivation/stewardship of key decision-makers\n\nQualifications And Experience\n\nThere are innumerable ways to learn, grow and excel professionally. We respect this when we review applications and take a broad look at the experience of each applicant. The qualifications and experiences listed below are intended as a guide; we do not expect candidates to check every box. If you believe you can meet the expectations and responsibilities of this position, we want to get to know you and the unique strengths you will bring to the work.\n\u2022 Minimum of 7 years in business development and strategic partnership management or transferrable skills and experiences in human resources, corporate recruitment and revenue generation\n\u2022 Minimum of 4 years in a technology-related setting, or managing Technology, Engineering, or LifeScience focused partnerships\n\u2022 Ability to navigate complex organizations and to understand key access points, identify prospects, develop strategic relationships and influence stakeholder decision-making\n\u2022 Deep knowledge of science, technology, engineering, and math (STEM) disciplines and related industry landscape (top hiring companies, career paths)\n\u2022 Expertise in and passion for issues related to diversity, equity, and inclusion in the corporate settings\n\u2022 Track record of success meeting and exceeding fundraising/sales goals and closing new deals\n\u2022 Ability to work independently while being an integral and collaborative member of a larger team\n\u2022 High level of professionalism and excellent judgment in communication and in handling sensitive information\n\u2022 Strong written and oral communication skills, with the ability to synthesize complex information into a simple and understandable form; Strong ability to develop effective written pitch documents, including presentation decks that frame data in a compelling, audience-centered narrative\n\u2022 A highly organized individual who can take initiative and prioritize short-term and long-term needs in a fast-paced environment involving multiple projects and stakeholders\n\u2022 Excellent research skills and entrepreneurial nature\n\u2022 Experience using Salesforce\n\u2022 Commitment to Thrive Scholars mission and a commitment to diversity, equity and inclusion in all aspects of the work\n\u2022 Willingness to travel and attend conferences and pitch meetings as needed\n\nCompetencies:\n\nAlong with the specific qualifications and experiences noted above, the ideal candidate for this position will be expected to demonstrate the following competencies:\n\u2022 Influencing: Communicates persuasively across the organization to build stakeholder and team alignment and support.\n\u2022 Strategic Collaboration: Understand how and when to work with others to drive strong results. Able to balance attention to both results and relationships.\n\u2022 Problem Solving: Able to analyze situations and apply critical thinking in order to identify issues and solutions.\n\u2022 Commitment to Results: Takes action to produce high-quality work with measurable results in service of Thrive\u2019s mission and Scholars.\n\u2022 Fostering Thrive Community: Contributes to a work environment that embraces organizational values and works effectively across identities.\n\nCompensation & Benefits\n\nThrive Scholars offers a robust compensation and benefits package including high-quality health and dental insurance, three weeks of paid vacation, generous professional development funding, and access to an employer-matched retirement plan. This is a full-time exempt position.\n\nStarting salary Range: $135,000 - $165,000\n\nCOVID-19 Vaccine Requirement:\n\nThrive has instituted a COVID-19 vaccine mandate for all employees, including remote staff. Individuals selected for job opportunities must be fully vaccinated and up to date, per CDC guidelines, and will be required to provide proof of vaccination status in advance of your hire date. If you are unable to be vaccinated for medical reasons or sincerely-held religious beliefs, Thrive will consider requests for reasonable accommodations consistent with our policy.\n\nAccommodation requests cannot be guaranteed, Thrive will consider requests where we are able to provide such accommodations without undue hardship to the organization pursuant to applicable law. Any such accommodation must be approved in advance of signing an offer letter.\n\nThrive Scholars provides equal employment opportunities (EEO) to all employees and applicants for employment and prohibits discrimination and harassment based on race, color, religion, gender, gender identity, national origin, sexual orientation, age, disability, or veteran status. Knowing its importance to the success of our work, Thrive Scholars is committed to diversity, equity, and inclusion, and we aspire to build a diverse staff team and community. We strongly encourage people of all backgrounds to apply.\n\nFor more information, please visit thrivescholars.org", "job_is_remote": true, "job_posted_at_timestamp": 1709580113, "job_posted_at_datetime_utc": "2024-03-04T19:21:53.000Z", "job_city": null, "job_state": null, "job_country": "US", "job_latitude": 37.09024, "job_longitude": -95.71289, "job_benefits": ["dental_coverage", "paid_time_off", "health_insurance", "retirement_savings"], "job_google_link": "https://www.google.com/search?gl=us&hl=en&rciv=jb&q=senior+manager+of+brand+partnerships&start=10&ibp=htl;jobs#fpstate=tldetail&htivrt=jobs&htiq=senior+manager+of+brand+partnerships&htidocid=cSSwEdDMxhnEEkFhAAAAAA%3D%3D", "job_offer_expiration_datetime_utc": "2024-04-04T14:07:47.000Z", "job_offer_expiration_timestamp": 1712239667, "job_required_experience": {"no_experience_required": false, "required_experience_in_months": null, "experience_mentioned": true, "experience_preferred": false}, "job_required_skills": null, "job_required_education": {"postgraduate_degree": false, "professional_certification": false, "high_school": false, "associates_degree": false, "bachelors_degree": true, "degree_mentioned": false, "degree_preferred": false, "professional_certification_mentioned": false}, "job_experience_in_place_of_education": false, "job_min_salary": null, "job_max_salary": null, "job_salary_currency": null, "job_salary_period": null, "job_highlights": {"Qualifications": ["There are innumerable ways to learn, grow and excel professionally", "Minimum of 7 years in business development and strategic partnership management or transferrable skills and experiences in human resources, corporate recruitment and revenue generation", "Minimum of 4 years in a technology-related setting, or managing Technology, Engineering, or LifeScience focused partnerships", "Ability to navigate complex organizations and to understand key access points, identify prospects, develop strategic relationships and influence stakeholder decision-making", "Deep knowledge of science, technology, engineering, and math (STEM) disciplines and related industry landscape (top hiring companies, career paths)", "Expertise in and passion for issues related to diversity, equity, and inclusion in the corporate settings", "High level of professionalism and excellent judgment in communication and in handling sensitive information", "Strong written and oral communication skills, with the ability to synthesize complex information into a simple and understandable form; Strong ability to develop effective written pitch documents, including presentation decks that frame data in a compelling, audience-centered narrative", "A highly organized individual who can take initiative and prioritize short-term and long-term needs in a fast-paced environment involving multiple projects and stakeholders", "Excellent research skills and entrepreneurial nature", "Experience using Salesforce", "Along with the specific qualifications and experiences noted above, the ideal candidate for this position will be expected to demonstrate the following competencies:", "Influencing: Communicates persuasively across the organization to build stakeholder and team alignment and support", "Strategic Collaboration: Understand how and when to work with others to drive strong results", "Able to balance attention to both results and relationships", "Problem Solving: Able to analyze situations and apply critical thinking in order to identify issues and solutions"], "Responsibilities": ["This position is location flexible, with a preference for Los Angeles, Boston, or another major market and may require up to 20-25% national travel", "Drive a consultative sales process by:", "Identifying mission-aligned prospect corporations and developing and leveraging tailored cultivation strategies", "Building a strong business case for partnering with us and leveraging interest in a stronger, more diverse talent pool to forge new corporate partnerships and attract philanthropic support", "Identifying key decision-makers and supporters within prospective partner organizations", "Manage sales pipeline & accelerate sales process", "Managing relationships through strong communication and project management", "Develop and leverage tailored cultivation strategies and solutions for each prospect", "Partner Engagement", "GOAL: Manage the onboarding of new partners and the seamless transition to account management team", "Serve as the main point of contact with partners through partnership launch", "Ensure that the partners are set up for a successful transition by capturing all required information and completing of the onboarding checklist", "Build a program at a glance to ensure efficient execution for our account managers and partners", "Work cross-functionally with our Career Development Team and Career Coaches to support recruitment for partner job opportunities", "GOAL: Ensure strong data and communications infrastructure to support a national technology-focused corporate partnership program", "Manage all data records for corporate partners in Salesforce, including revenue pipeline and forecast", "Manage/track sales process /activity for high-priority prospects", "Create customized marketing materials and pitch presentations, as well as proposals for partner prospects", "Contribute to the development team and overall organizational team efforts", "Assist in development operations initiatives, including Salesforce data review and analysis, gift processing, and donor acknowledgments", "Collaborate on the development annual planning", "Willingness to travel and attend conferences and pitch meetings as needed", "Commitment to Results: Takes action to produce high-quality work with measurable results in service of Thrive\u2019s mission and Scholars"], "Benefits": ["Thrive Scholars offers a robust compensation and benefits package including high-quality health and dental insurance, three weeks of paid vacation, generous professional development funding, and access to an employer-matched retirement plan", "This is a full-time exempt position", "Starting salary Range: $135,000 - $165,000"]}, "job_job_title": "Senior", "job_posting_language": "en", "job_onet_soc": "11202100", "job_onet_job_zone": "4"}