{"job_id": "SIROc79S6KNvlJKsAAAAAA==", "employer_name": "Bitmovin", "employer_logo": "https://upload.wikimedia.org/wikipedia/commons/thumb/7/74/Bitmovin_logo_2016.svg/1280px-Bitmovin_logo_2016.svg.png", "employer_website": "http://bitmovin.com", "employer_company_type": null, "job_publisher": "Y Combinator", "job_employment_type": "FULLTIME", "job_title": "Sales Director", "job_apply_link": "https://www.ycombinator.com/companies/bitmovin/jobs/SPlTI7FBv-sales-director", "job_apply_is_direct": false, "job_apply_quality_score": 0.6799, "apply_options": [{"publisher": "Y Combinator", "apply_link": "https://www.ycombinator.com/companies/bitmovin/jobs/SPlTI7FBv-sales-director", "is_direct": false}, {"publisher": "Work At A Startup", "apply_link": "https://www.workatastartup.com/jobs/17025", "is_direct": false}, {"publisher": "Blythe-Masters.org", "apply_link": "http://blythe-masters.org/splti7fbv-sales-director.html", "is_direct": false}], "job_description": "Use this link to apply directly: https://grnh.se/99d740c42\n\nBitmovin provides API based Software that helps developers around the world to solve the most complex video problems with a video player library that plays everywhere. Come join the team building innovative online video software for developers and content owners worldwide!\n\nWe\u2019re looking for talented, passionate and inspired people who believe in the possibilities of video to tell compelling stories and want to enable video creation as well as consumption. Join us to innovate and lead the market for video encoding, playback on mobile and other devices, and analytics around user experiences.\n\nBitmovin is looking for a motivated sales executive with a background in B2B/B2D technology and/or SaaS with a strong track record of overachievement. As the Sales Director at Bitmovin, you will build relationships and close business with existing as well as new enterprise customers. The successful candidate is a results-oriented and self-motivated individual with an outgoing personality and comfortable with both technical and business concepts. In addition, we are searching for an energetic and organized self-starter who understands sales processes and can build relationships with the right decision-makers. You will be a key driver of revenue growth for the company and on the front lines for evangelizing our product to prospective users.\n\nIn this position, you will be working closely with the Sales and Business Development team to develop targeted strategies and messaging in order to drive opportunities for new business and get new leads. Outstanding communication skills are required, a willingness to go above and beyond both for Bitmovin as well as our customers.\n\nAs a Sales Director you will\n\u2022 Identify high-potential prospective customers and grow new revenue from businesses of all sizes\n\u2022 Build and maintain relationships with executives, operational teams and developers\n\u2022 Present the value of our solutions to the customers\u2019 individual needs\n\u2022 Manage the full sales cycle from prospecting to close\n\u2022 Manage legal/procurement process to create scalable global agreements\n\u2022 Work with internal departments to coordinate resources to make accounts successful\n\u2022 Travel occasionally for conferences and customer meetings\n\nIt would be great if you have\n\u2022 5+ years of B2B/B2D and/or SaaS sales experience in a revenue closing sales executive role\n\u2022 Experience of selling streaming media solutions and/or video infrastructure to the major broadcasters\n\u2022 Ability to understand the Bitmovin Platform and not only build great relationships with Technical and Business buyers, but transform the platform into Business Value for the customers\n\u2022 Results driven while able to try new processes and iterate to scale a global sales engine - including lead generation, presentation, negotiation, and more\n\u2022 Strong analytical, critical thinking and problem solving skills.\n\u2022 Exceptional communication skills \u2013 written and verbal\n\u2022 Passion for technology and aptitude to learn new technologies\n\u2022 Knowledge of technologies and applications such as Salesforce, Github, etc\n\u2022 Bachelor\u2019s degree\n\nBitmovin\u2019s Benefits\n\u2022 Working with an innovative, fast-growing and international team with low hierarchy\n\u2022 Opportunity to make an impact on the multimedia industry, with target markets EU, US and APAC\n\u2022 Competitive salary\n\u2022 Flexible work hours\n\u2022 Investment in growth and education\n\u2022 No routines, but new challenging projects with global impact\n\u2022 Regular and fun team activities (hackathons, skiing days, \u2026)\n\u2022 Choose your own hardware\n\u2022 The opportunity to work for an exciting start-up, building innovative video solutions\n\u2022 401k plan (US only)\n\nAbout Bitmovin\n\nBitmovin, a YCombinator company, is a fast growing privately owned technology leader, located in San Francisco, CA and Klagenfurt, Austria.\nThe company was founded by the co-creators of international media standards like MPEG-DASH, that is used today by Netflix, Youtube, and others. Bitmovin is the technology leader in online video technologies such as cloud-based encoding, adaptive streaming players, 360\u00b0/VR streaming and performance analytics. Bitmovin is backed by top investors such as Atomico as well as industry leaders like the former VP Engineering of Netflix, former CTO of Cisco, founder of Unity3D, and many others. Bitmovin\u2019s customers include the top media and technology companies worldwide, including Ooyala, RTL, Pro7Sat1, Bouygues Telecom, Cloudflare, Technicolor, Televisa, Zattoo and many others.\n\nWorking at Bitmovin is fast-paced, fun and challenging with colleagues and customers worldwide.\n\nBitmovin is an equal opportunity employer. We value diversity at our company and do not discriminate on the basis of race, religion, color, national origin, gender, sexual orientation, age, marital status, veteran status, or disability status.\n\nSTARTING TIME: Immediately\n\nEmpower your future and join us now!\n\nBitmovin does not accept unsolicited referrals or resumes from any source other than directly from candidates. The submission of referrals or resumes by anyone other than a candidate directly to Bitmovin will be deemed gratuitous, and the company will not be obligated or bound in any way to pay any fee if the candidate is hired.", "job_is_remote": true, "job_posted_at_timestamp": 1569923542, "job_posted_at_datetime_utc": "2019-10-01T09:52:22.000Z", "job_city": null, "job_state": null, "job_country": "US", "job_latitude": 37.09024, "job_longitude": -95.71289, "job_benefits": ["retirement_savings"], "job_google_link": "https://www.google.com/search?gl=us&hl=en&rciv=jb&q=sales+director&start=30&ibp=htl;jobs#fpstate=tldetail&htivrt=jobs&htiq=sales+director&htidocid=SIROc79S6KNvlJKsAAAAAA%3D%3D", "job_offer_expiration_datetime_utc": null, "job_offer_expiration_timestamp": null, "job_required_experience": {"no_experience_required": false, "required_experience_in_months": 60, "experience_mentioned": true, "experience_preferred": false}, "job_required_skills": null, "job_required_education": {"postgraduate_degree": false, "professional_certification": false, "high_school": false, "associates_degree": false, "bachelors_degree": false, "degree_mentioned": true, "degree_preferred": false, "professional_certification_mentioned": false}, "job_experience_in_place_of_education": false, "job_min_salary": null, "job_max_salary": null, "job_salary_currency": null, "job_salary_period": null, "job_highlights": {"Qualifications": ["The successful candidate is a results-oriented and self-motivated individual with an outgoing personality and comfortable with both technical and business concepts", "5+ years of B2B/B2D and/or SaaS sales experience in a revenue closing sales executive role", "Experience of selling streaming media solutions and/or video infrastructure to the major broadcasters", "Ability to understand the Bitmovin Platform and not only build great relationships with Technical and Business buyers, but transform the platform into Business Value for the customers", "Results driven while able to try new processes and iterate to scale a global sales engine - including lead generation, presentation, negotiation, and more", "Strong analytical, critical thinking and problem solving skills", "Exceptional communication skills \u2013 written and verbal", "Passion for technology and aptitude to learn new technologies", "Knowledge of technologies and applications such as Salesforce, Github, etc", "Bachelor\u2019s degree"], "Responsibilities": ["You will be a key driver of revenue growth for the company and on the front lines for evangelizing our product to prospective users", "In this position, you will be working closely with the Sales and Business Development team to develop targeted strategies and messaging in order to drive opportunities for new business and get new leads", "Identify high-potential prospective customers and grow new revenue from businesses of all sizes", "Build and maintain relationships with executives, operational teams and developers", "Present the value of our solutions to the customers\u2019 individual needs", "Manage the full sales cycle from prospecting to close", "Manage legal/procurement process to create scalable global agreements", "Work with internal departments to coordinate resources to make accounts successful", "Travel occasionally for conferences and customer meetings"], "Benefits": ["Working with an innovative, fast-growing and international team with low hierarchy", "Competitive salary", "Flexible work hours", "Investment in growth and education", "No routines, but new challenging projects with global impact", "Regular and fun team activities (hackathons, skiing days, \u2026)", "Choose your own hardware", "The opportunity to work for an exciting start-up, building innovative video solutions", "401k plan (US only)"]}, "job_job_title": "Sales director", "job_posting_language": "en", "job_onet_soc": "11202200", "job_onet_job_zone": "4"}