{"job_id": "B72a4pR0D0JjWvZhAAAAAA==", "employer_name": "1000 Abbott Laboratories Inc(ALI)", "employer_logo": null, "employer_website": null, "employer_company_type": null, "job_publisher": "Workday", "job_employment_type": "FULLTIME", "job_title": "Manager Sales Training", "job_apply_link": "https://abbott.wd5.myworkdayjobs.com/en-US/abbottcareers/job/United-States---Illinois---Des-Plaines/Manager-Sales-Training_31077796-2", "job_apply_is_direct": false, "job_apply_quality_score": 0.7755, "apply_options": [{"publisher": "Workday", "apply_link": "https://abbott.wd5.myworkdayjobs.com/en-US/abbottcareers/job/United-States---Illinois---Des-Plaines/Manager-Sales-Training_31077796-2", "is_direct": false}], "job_description": "Abbott is a global healthcare leader that helps people live more fully at all stages of life. Our portfolio of life-changing technologies spans the spectrum of healthcare, with leading businesses and products in diagnostics, medical devices, nutritionals and branded generic medicines. Our 114,000 colleagues serve people in more than 160 countries. JOB DESCRIPTION: Working at Abbott At Abbott, you can do work that matters, grow, and learn, care for yourself and family, be your true self and live a full life. You\u2019ll also have access to: Career development with an international company where you can grow the career you dream of. Free medical coverage for employees* via the Health Investment Plan (HIP) PPO An excellent retirement savings plan with high employer contribution Tuition reimbursement, the Freedom 2 Save student debt program and FreeU education benefit - an affordable and convenient path to getting a bachelor\u2019s degree. A company recognized as a great place to work in dozens of countries around the world and named one of the most admired companies in the world by Fortune. A company that is recognized as one of the best big companies to work for as well as a best place to work for diversity, working mothers, female executives, and scientists. The Opportunity This position works out of our Lake Forest location in the Molecular Division. Manager, Sales Training will organize, plan and execute all aspects of training for our Global field-based employees. The successful candidate will be responsible for ensuring the education and preparation of our teams, including but not limited to Sales representatives and Sales Managers. You will work in coordination with the Training Team to to create consistency of content in training sessions and field co-travel. We are looking for an ambitious, organized and highly efficient expert with medical devices and/or successful diagnostic sales and training experience. Familiarity with molecular sales is also helpful for candidates considered for this position. We offer a generous compensation structure and a team-oriented environment. What You\u2019ll Work On Responsible for managing and making recommendations for all programs within New Hire Training, Strategic selling and Training & Development Programs budgets. Assess employee skills, talents, performance and productivity and prepare written evaluations with advice for improvement. Responsible for the success of administration and executing training programs. Develop content for Molecular learning platform(s). Oversight for maintaining training material on Molecular learning platform. Oversee the training in all key areas of product understanding, sales strategies/tactics, internal processes; including but not limited to Salesforce, Power BI (DOMO) and Definitive Health. Research new training materials and programs that enhance our training procedures and provide value to the organization. Oversee the onboarding of new hires, assignment to training sessions. Review and assess new hire selling skills and knowledge; provide input on any recommended corrective measures. Identify/anticipate future training needs and create curriculum to facilitate the necessary training. High level of communication with Training Director, Area Sales Director(s) and to ensure all training and development needs are identified and met. Oversee maintenance of repository of competency measures, including quiz questions, role plays, projects, videos, etc Maintain repository of certification results and report to management. Assess and make recommendations for skill development, performance improvement and career path development as individuals gain more tenure. Search for/identify gaps in training materials or content to ensure continuous development and elevation of the skill for the field teams. Collaborate with Product Managers, Contracts and Pricing, Area Sales Director\u2019s, and Regional Sales Trainers to deliver training, content and development, new product information and product launches. Ensure field sales teams are certified on training programs, Required Qualifications Bachelor\u2019s Degree (Business or Organizational Development preferred, but not required) 5+ years of experience in Medical or Diagnostics Sales Previous people management experience strongly desired. Demonstrated excellence in leadership, organization, communication and team building skills. Experience designing and administrating learning management systems (Seismic Learning preferred) Preferred Qualifications Minimum 4 years field coaching experience preferred 2+ years training experience preferred. Previous people management experience strongly desired. Experience designing and implementing training curricula preferred. Delivering effective virtual and in-person training experience preferred. Apply Now * Participants who complete a short wellness assessment qualify for FREE coverage in our HIP PPO medical plan. Free coverage applies in the next calendar year. Learn more about our health and wellness benefits, which provide the security to help you and your family live full lives: www.abbottbenefits.com Follow your career aspirations to Abbott for diverse opportunities with a company that can help you build your future and live your best life. Abbott is an Equal Opportunity Employer, committed to employee diversity. Connect with us at www.abbott.com, on Facebook at www.facebook.com/Abbott and on Twitter @AbbottNews. Divisional Information Diagnostics We\u2019re empowering smarter medical and economic decision making to help transform the way people manage their health at all stages of life. Every day, more than 10 million tests are run on Abbott\u2019s diagnostics instruments, providing lab results for millions of people. Abbott Molecular is a leader in molecular diagnostics and the analysis of DNA, RNA, and proteins at the molecular level. Our Point of Care diagnostic portfolio spans key heath and therapeutic areas, including infections disease, cardiometabolic, informatics and toxicology. Our diagnostic solutions are used in hospitals, laboratories and clinics around the globe. The crucial information derived from our tests, instruments and informatics systems are often the first step in patient care decision making for hundreds of health conditions from heart attacks to blood disorders to infectious diseases and cancers. Our rapid diagnostics solutions are helping address some of the world\u2019s greatest healthcare challenges. The base pay for this position is $109,300.00 \u2013 $218,700.00 In specific locations, the pay range may vary from the range posted. JOB FAMILY: Sales Support & Administration DIVISION: AMD Molecular LOCATION: United States > Des Plaines : 1350 East Touhy Avenue ADDITIONAL LOCATIONS: WORK SHIFT: Standard TRAVEL: Yes, 10 % of the Time MEDICAL SURVEILLANCE: Not Applicable SIGNIFICANT WORK ACTIVITIES: Continuous sitting for prolonged periods (more than 2 consecutive hours in an 8 hour day), Keyboard use (greater or equal to 50% of the workday) Abbott is an Equal Opportunity Employer of Minorities/Women/Individuals with Disabilities/Protected Veterans. EEO is the Law link - English: http://webstorage.abbott.com/common/External/EEO_English.pdf EEO is the Law link - Espanol: http://webstorage.abbott.com/common/External/EEO_Spanish.pdf Abbott is about the power of health. For more than 135 years, Abbott has been helping people reach their potential \u2014 because better health allows people and communities to achieve more. With a diverse, global network serving customers in more than 160 countries, we create new solutions \u2014 across the spectrum of health, around the world, for all stages of life. Whether it\u2019s next-generation diagnostics, life-changing devices, science-based nutrition, or novel reformulations, we are advancing some of the most innovative and revolutionary technologies in healthcare, helping people live their best lives through better health. The people of Abbott come to work each day with relentless energy, enthusiasm and a promise to enhance the health and well-being of millions of people. They push the boundaries to help manage and treat some of life\u2019s greatest health challenges. We invite you to explore opportunities at Abbott, to see if your talents and career aspirations may fit with our openings. An equal opportunity employer, Abbott welcomes and encourages diversity in our workforce. Follow Us: Facebook LinkedIn YouTube Twitter", "job_is_remote": true, "job_posted_at_timestamp": 1709251200, "job_posted_at_datetime_utc": "2024-03-01T00:00:00.000Z", "job_city": null, "job_state": null, "job_country": "US", "job_latitude": 37.09024, "job_longitude": -95.71289, "job_benefits": ["retirement_savings", "health_insurance"], "job_google_link": "https://www.google.com/search?gl=us&hl=en&rciv=jb&q=director+of+sales+training&start=10&ibp=htl;jobs#fpstate=tldetail&htivrt=jobs&htiq=director+of+sales+training&htidocid=B72a4pR0D0JjWvZhAAAAAA%3D%3D", "job_offer_expiration_datetime_utc": null, "job_offer_expiration_timestamp": null, "job_required_experience": {"no_experience_required": false, "required_experience_in_months": 60, "experience_mentioned": true, "experience_preferred": true}, "job_required_skills": null, "job_required_education": {"postgraduate_degree": false, "professional_certification": false, "high_school": false, "associates_degree": false, "bachelors_degree": false, "degree_mentioned": true, "degree_preferred": false, "professional_certification_mentioned": true}, "job_experience_in_place_of_education": false, "job_min_salary": null, "job_max_salary": null, "job_salary_currency": null, "job_salary_period": null, "job_highlights": {"Qualifications": ["We are looking for an ambitious, organized and highly efficient expert with medical devices and/or successful diagnostic sales and training experience", "Demonstrated excellence in leadership, organization, communication and team building skills"], "Responsibilities": ["Manager, Sales Training will organize, plan and execute all aspects of training for our Global field-based employees", "The successful candidate will be responsible for ensuring the education and preparation of our teams, including but not limited to Sales representatives and Sales Managers", "You will work in coordination with the Training Team to to create consistency of content in training sessions and field co-travel", "What You\u2019ll Work On Responsible for managing and making recommendations for all programs within New Hire Training, Strategic selling and Training & Development Programs budgets", "Assess employee skills, talents, performance and productivity and prepare written evaluations with advice for improvement", "Responsible for the success of administration and executing training programs", "Develop content for Molecular learning platform(s)", "Oversight for maintaining training material on Molecular learning platform", "Oversee the training in all key areas of product understanding, sales strategies/tactics, internal processes; including but not limited to Salesforce, Power BI (DOMO) and Definitive Health", "Research new training materials and programs that enhance our training procedures and provide value to the organization", "Oversee the onboarding of new hires, assignment to training sessions", "Review and assess new hire selling skills and knowledge; provide input on any recommended corrective measures", "Identify/anticipate future training needs and create curriculum to facilitate the necessary training", "High level of communication with Training Director, Area Sales Director(s) and to ensure all training and development needs are identified and met", "Oversee maintenance of repository of competency measures, including quiz questions, role plays, projects, videos, etc Maintain repository of certification results and report to management", "Assess and make recommendations for skill development, performance improvement and career path development as individuals gain more tenure", "Search for/identify gaps in training materials or content to ensure continuous development and elevation of the skill for the field teams", "Collaborate with Product Managers, Contracts and Pricing, Area Sales Director\u2019s, and Regional Sales Trainers to deliver training, content and development, new product information and product launches"], "Benefits": ["You\u2019ll also have access to: Career development with an international company where you can grow the career you dream of", "Free medical coverage for employees* via the Health Investment Plan (HIP) PPO An excellent retirement savings plan with high employer contribution Tuition reimbursement, the Freedom 2 Save student debt program and FreeU education benefit - an affordable and convenient path to getting a bachelor\u2019s degree", "Participants who complete a short wellness assessment qualify for FREE coverage in our HIP PPO medical plan", "Free coverage applies in the next calendar year", "The base pay for this position is $109,300.00 \u2013 $218,700.00 In specific locations, the pay range may vary from the range posted"]}, "job_job_title": "Sales training", "job_posting_language": "en", "job_onet_soc": "11313100", "job_onet_job_zone": "4"}