{"job_id": "gP68BLZ1DLr4V7r4AAAAAA==", "employer_name": "Alight", "employer_logo": "https://upload.wikimedia.org/wikipedia/commons/2/21/Alight_Solutions_Logo.png", "employer_website": "http://alight.com", "employer_company_type": null, "job_publisher": "Careers At Alight", "job_employment_type": "FULLTIME", "job_title": "Lead Development Representative - Virtual", "job_apply_link": "https://careers.alight.com/it/it/job/R-27871/Lead-Development-Representative-Virtual", "job_apply_is_direct": false, "job_apply_quality_score": 0.8528, "apply_options": [{"publisher": "Careers At Alight", "apply_link": "https://careers.alight.com/it/it/job/R-27871/Lead-Development-Representative-Virtual", "is_direct": false}, {"publisher": "Adzuna", "apply_link": "https://www.adzuna.com/details/4588842217", "is_direct": false}], "job_description": "Our story\n\nAt Alight, we believe a company\u2019s success starts with its people. At our core, we Champion People, help our colleagues Grow with Purpose and true to our name we encourage colleagues to \u201cBe Alight.\u201d\n\nOur Values:\n\nChampion People \u2013 be empathetic and help create a place where everyone belongs.\n\nGrow with purpose \u2013 Be inspired by our higher calling of improving lives.\n\nBe Alight \u2013 act with integrity, be real and empower others.\n\nIt\u2019s why we\u2019re so driven to connect passion with purpose. Our team\u2019s expertise in human insights and cloud technology gives companies and employees around the world the ability to power confident decisions, for life.\n\nWith a comprehensive total rewards package, continuing education and training, and tremendous potential with a growing global organization, Alight is the perfect place to put your passion to work.\n\nJoin our team if you Champion People, want to Grow with Purpose through acting with integrity and if you embody the meaning of Be Alight.\n\nLearn more at careers.alight.com.\n\u2022 ******Please Note: Work From Home Opportunity | Virtual/Remote*********\n\nThe Lead Development Representative conducts outbound calling to generate opportunities for new logos in an assigned region, focused on employer group sales of 1,000+ employees.\n\nThe Lead Development Representative is responsible for a specific geographical area and within that territory is accountable for identifying business opportunities via direct group outreach. Once group outreach is made, the goal is to secure meetings, qualify sales leads, and hand-off leads process with the regional Enterprise Sales Executive to close the opportunity to exceed an annual sales goal. Generating the leads will come from this individual\u2019s direct discovery, utilizing multiple angles to reach out and identify new opportunities. Once meetings are secured, the regional Enterprise Sales Executive will drive account selling functions. The Lead Development Representative will need to partner closely with the Sales Executive and Sales Ops team throughout the sales process, along with the regional Sales Executives in order to achieve growth initiatives and exceed sales goals.\n\nResponsibilities:\n\nSales process\n\u2022 Generates leads by developing contacts with target accounts via referrals, daily calling, online resources, and other outreach activities in conjunction with field marketing campaigns.\n\u2022 Daily calls and other outreach activities to follow up on inbound leads\u2013 (targeted goal of 100+ outreach calls and follow-ups a day)\n\u2022 Conducts initial qualification of opportunity to confirm viability and gather high-level understanding of customer needs\n\u2022 Accountable for identifying contacts at prospect accounts for Sales Executives to leverage for landing new accounts\n\u2022 Successfully transitions leads to the Sales teams\n\u2022 Facilitates appointment scheduling in prospect accounts\n\u2022 Attains company Key Performance Indicators (KPIs) of 10 scheduled appointments per month and 3 opportunities\n\nOther\n\u2022 Regularly engages with Marketing and the Alight Sales Executive to execute on strategy for region for net new lands\n\u2022 Effectively work with marketing to identify creative campaigns and ways to generate sales ready opportunities\n\u2022 Utilizes SalesForce.com and identify continuous improvement opportunities\n\nQualifications\nNot every candidate will possess all the below qualifications. You are encouraged to apply regardless of the completeness of qualifications.\n\nFormal education and certification\n\u2022 Bachelor's degree or equivalent experience\n\nKnowledge and Experience\n\u2022 1-3 years of inside sales or business development lead generation experience\n\u2022 Experience working in wealth and retirement business\n\u2022 Documented achievement of plan performance\n\u2022 Experience with lead generation, customer service, and/or phone based selling techniques\n\u2022 Experience of daily dials, appointment setting, and opportunity generation accountability\n\u2022 Experience running lead generation campaigns and multi-touch cadences\n\u2022 Experience using front-end cadence tools (Groove, Outreach, etc)\n\u2022 Have worked and collaborated with a field sales team with lead handoff\n\u2022 Knowledge of the benefits industry and ability to quickly learn and understand Alight products and services to accurately relate to targets\n\u2022 Ability to partner and collaborate with cross functional teams\n\u2022 Proficient with Microsoft Office, Salesforce, LinkedIn Navigator\n\nOther\n\u2022 Strong communicator focused on achieving results\n\u2022 Great work ethic, coachable, organized team player\n\u2022 Able to work well under pressure\n\u2022 Open to receiving direct feedback\n\nFlexible Working\n\nSo that you can be your best at work and home, we consider flexible working arrangements wherever possible. Alight has been a leader in the flexible workspace and \u201cTop 100 Company for Remote Jobs\u201d 5 years in a row.\n\nBenefits\n\nWe offer programs and plans for a healthy mind, body, wallet and life because it\u2019s important our benefits care for the whole person. Options include a variety of health coverage options, wellbeing and support programs, retirement, vacation and sick leave, maternity, paternity & adoption leave, continuing education and training as well as a number of voluntary benefit options.\n\nBy applying for a position with Alight, you understand that, should you be made an offer, it will be contingent on your undergoing and successfully completing a background check consistent with Alight\u2019s employment policies. Background checks may include some or all the following based on the nature of the position: SSN/SIN validation, education verification, employment verification, and criminal check, search against global sanctions and government watch lists, credit check, and/or drug test. You will be notified during the hiring process which checks are required by the position.\n\nOur commitment to Diversity and Inclusion\n\nAlight is committed to diversity, equity, and inclusion. We celebrate differences and believe in fostering an environment where everyone feels valued, respected, and supported. We know that diverse teams are stronger, more innovative, and more successful.\n\nAt Alight, we welcome and embrace all individuals, regardless of their background, and are dedicated to creating a culture that enables every employee to thrive. Join us in building a brighter, more inclusive future.\n\nDiversity Policy Statement\n\nAlight is an Equal Employment Opportunity employer and does not discriminate against anyone based on sex, race, color, religion, creed, national origin, ancestry, age, physical or mental disability, medical condition, pregnancy, marital or domestic partner status, citizenship, military or veteran status, sexual orientation, gender, gender identity or expression, genetic information, or any other legally protected characteristics or conduct covered by federal, state or local law. In addition, we take affirmative action to employ and advance in the employment of qualified minorities, women, disabled persons, disabled veterans and other covered veterans.\n\nAlight provides reasonable accommodations to the known limitations of otherwise qualified employees and applicants for employment with disabilities and sincerely held religious beliefs, practices and observances, unless doing so would result in undue hardship. Applicants for employment may request a reasonable accommodation/modification by contacting his/her recruiter.\n\nAuthorization to work in the Employing Country\n\nApplicants for employment in the country in which they are applying (Employing Country) must have work authorization that does not now or in the future require sponsorship of a visa for employment authorization in the Employing Country and with Alight.\n\nNote, this job description does not restrict management's right to assign or reassign duties and responsibilities of this job to other entities; including but not limited to subsidiaries, partners, or purchasers of Alight business units.\n\nWe offer you a competitive total rewards package, continuing education & training, and tremendous potential with a growing worldwide organization.\n\nSalary Pay Range\n\nMinimum :\n35,000 USD\n\nMaximum :\n55,500 USD\n\nPay Transparency Statement: Alight considers a variety of factors in determining whether to extend an offer of employment and in setting the appropriate compensation level, including, but not limited to, a candidate\u2019s experience, education, certification/credentials, market data, internal equity, and geography. Alight makes these decisions on an individualized, non-discriminatory basis. Bonus and/or incentive eligibility are determined by role and level. Alight also offers a comprehensive benefits package; for specific details on our benefits package, please visit: https://bit.ly/Alight_Benefits\n\nDISCLAIMER:\n\nNothing in this job description restricts management's right to assign or reassign duties and responsibilities of this job to other entities; including but not limited to subsidiaries, partners, or purchasers of Alight business units.\n\nAlight Solutions provides equal employment opportunities (EEO) to all employees and applicants for employment without regard to race, color, religion, creed, sex, sexual orientation, gender identity, national origin, age, disability, genetic information, pregnancy, childbirth or related medical condition, veteran, marital, parental, citizenship, or domestic partner status, or any other status protected by applicable national, federal, state or local law. Alight Solutions is committed to a diverse workforce and is an affirmative action employer.", "job_is_remote": false, "job_posted_at_timestamp": 1710201600, "job_posted_at_datetime_utc": "2024-03-12T00:00:00.000Z", "job_city": null, "job_state": "FL", "job_country": "US", "job_latitude": 27.664827, "job_longitude": -81.515755, "job_benefits": ["paid_time_off", "retirement_savings", "health_insurance"], "job_google_link": "https://www.google.com/search?gl=us&hl=en&rciv=jb&q=sales+director&start=30&ibp=htl;jobs#fpstate=tldetail&htivrt=jobs&htiq=sales+director&htidocid=gP68BLZ1DLr4V7r4AAAAAA%3D%3D", "job_offer_expiration_datetime_utc": null, "job_offer_expiration_timestamp": null, "job_required_experience": {"no_experience_required": false, "required_experience_in_months": 12, "experience_mentioned": true, "experience_preferred": false}, "job_required_skills": null, "job_required_education": {"postgraduate_degree": false, "professional_certification": false, "high_school": false, "associates_degree": false, "bachelors_degree": false, "degree_mentioned": true, "degree_preferred": false, "professional_certification_mentioned": true}, "job_experience_in_place_of_education": false, "job_min_salary": null, "job_max_salary": null, "job_salary_currency": null, "job_salary_period": null, "job_highlights": {"Qualifications": ["Not every candidate will possess all the below qualifications", "You are encouraged to apply regardless of the completeness of qualifications", "Bachelor's degree or equivalent experience", "1-3 years of inside sales or business development lead generation experience", "Experience working in wealth and retirement business", "Documented achievement of plan performance", "Experience with lead generation, customer service, and/or phone based selling techniques", "Experience of daily dials, appointment setting, and opportunity generation accountability", "Experience running lead generation campaigns and multi-touch cadences", "Experience using front-end cadence tools (Groove, Outreach, etc)", "Have worked and collaborated with a field sales team with lead handoff", "Knowledge of the benefits industry and ability to quickly learn and understand Alight products and services to accurately relate to targets", "Ability to partner and collaborate with cross functional teams", "Proficient with Microsoft Office, Salesforce, LinkedIn Navigator", "Strong communicator focused on achieving results", "Great work ethic, coachable, organized team player", "Able to work well under pressure", "Open to receiving direct feedback", "Applicants for employment in the country in which they are applying (Employing Country) must have work authorization that does not now or in the future require sponsorship of a visa for employment authorization in the Employing Country and with Alight"], "Responsibilities": ["The Lead Development Representative is responsible for a specific geographical area and within that territory is accountable for identifying business opportunities via direct group outreach", "Once group outreach is made, the goal is to secure meetings, qualify sales leads, and hand-off leads process with the regional Enterprise Sales Executive to close the opportunity to exceed an annual sales goal", "Generating the leads will come from this individual\u2019s direct discovery, utilizing multiple angles to reach out and identify new opportunities", "Once meetings are secured, the regional Enterprise Sales Executive will drive account selling functions", "The Lead Development Representative will need to partner closely with the Sales Executive and Sales Ops team throughout the sales process, along with the regional Sales Executives in order to achieve growth initiatives and exceed sales goals", "Generates leads by developing contacts with target accounts via referrals, daily calling, online resources, and other outreach activities in conjunction with field marketing campaigns", "Daily calls and other outreach activities to follow up on inbound leads\u2013 (targeted goal of 100+ outreach calls and follow-ups a day)", "Conducts initial qualification of opportunity to confirm viability and gather high-level understanding of customer needs", "Accountable for identifying contacts at prospect accounts for Sales Executives to leverage for landing new accounts", "Successfully transitions leads to the Sales teams", "Facilitates appointment scheduling in prospect accounts", "Attains company Key Performance Indicators (KPIs) of 10 scheduled appointments per month and 3 opportunities", "Regularly engages with Marketing and the Alight Sales Executive to execute on strategy for region for net new lands", "Effectively work with marketing to identify creative campaigns and ways to generate sales ready opportunities", "Utilizes SalesForce.com and identify continuous improvement opportunities"], "Benefits": ["So that you can be your best at work and home, we consider flexible working arrangements wherever possible", "We offer programs and plans for a healthy mind, body, wallet and life because it\u2019s important our benefits care for the whole person", "Options include a variety of health coverage options, wellbeing and support programs, retirement, vacation and sick leave, maternity, paternity & adoption leave, continuing education and training as well as a number of voluntary benefit options", "We offer you a competitive total rewards package, continuing education & training, and tremendous potential with a growing worldwide organization", "Salary Pay Range", "Alight also offers a comprehensive benefits package; for specific details on our benefits package, please visit: https://bit.ly/Alight_Benefits"]}, "job_job_title": "Development representative", "job_posting_language": "en", "job_onet_soc": "41401400", "job_onet_job_zone": null, "job_occupational_categories": ["Other"]}