{"job_id": "36m8itJj_2bBC4HXAAAAAA==", "employer_name": "Dianthus Therapeutics", "employer_logo": "https://dianthustx.com/wp-content/uploads/2021/09/logo.png", "employer_website": "https://www.magentatx.com", "employer_company_type": null, "job_publisher": "Greenhouse", "job_employment_type": "FULLTIME", "job_title": "Senior Director, Business Development and Alliance Management", "job_apply_link": "https://boards.greenhouse.io/dianthustherapeutics/jobs/4388408005", "job_apply_is_direct": false, "job_apply_quality_score": 0.6578, "apply_options": [{"publisher": "Greenhouse", "apply_link": "https://boards.greenhouse.io/dianthustherapeutics/jobs/4388408005", "is_direct": false}], "job_description": "About Us\n\nDianthus Therapeutics is a publicly traded, clinical-stage biotechnology company dedicated to designing and delivering novel, best-in-class monoclonal antibodies with improved selectivity and potency. Based in New York City and Waltham, Mass., Dianthus is comprised of an experienced team of biotech and pharma executives who are leading the development of next-generation antibody complement therapeutics, aiming to deliver transformative medicines for people living with severe autoimmune and inflammatory diseases. To learn more, please visit www.dianthustx.com and follow us on LinkedIn.\n\nAbout the Role\n\nThe Senior Director of Business Development and Alliance Management will have a significant impact by driving the strategic growth and development opportunities of Dianthus Therapeutics.\n\nReporting to the CFO / CBO, you will be responsible for evaluating, structuring, and negotiating new business opportunities, cultivating partnerships, and managing key alliances to enhance the company's market position and adding strategic value to help build a long-term successful Biotech company. You must have experience bringing new assets or products into the pipeline, maintaining a commercial mindset, and an understanding of full lifecycle product development.\n\nThis is a unique opportunity to join a fast-growing biotech company who aims to deliver transformative medicines for people living with severe autoimmune and inflammatory diseases. We are building a culture of individuals who hold our core principles at the center of our operations, with the goal to elevate the care of our patients\u2019 lives. We are open to you working remotely.\n\nRESPONSIBILITIES\n\nBusiness Development:\n\u2022 Identify and evaluate new business opportunities that align with the company's strategic objectives and growth targets.\n\u2022 Develop and execute comprehensive business development strategies to expand market share.\n\u2022 Lead the negotiation and structuring of complex partnership agreements (including geographic partnering), licensing deals, and strategic alliances.\n\u2022 Build and maintain a robust pipeline of potential opportunities and effectively prioritize initiatives based on their potential impact and alignment with company goals.\n\u2022 Collaborate closely with cross-functional teams (Discovery, Clinical, Regulatory CMC, Legal/IP, Finance, etc.) to assess market trends, patient needs, and competitive dynamics to inform business development strategies.\n\u2022 Lead the evaluation of potential deals including scientific/portfolio rationale, market opportunity assessment, NPV modeling, comparative deals, and evaluation of business fit, in collaboration with cross-functional teams\n\nAlliance Management:\n\u2022 Serve as the primary point of contact for key partners and alliances, fostering strong relationships and driving mutual value creation.\n\u2022 Develop and execute alliance management plans to ensure the successful implementation and execution of partnership agreements.\n\u2022 Facilitate regular communication and collaboration between internal and external stakeholders to drive alignment and achieve shared objectives.\n\u2022 Monitor and track the performance of strategic alliances, identifying opportunities for optimization and improvement.\n\u2022 Resolve conflicts and mitigate risks that may arise in the course of managing complex partnerships and alliances.\n\nStrategic Planning:\n\u2022 Contribute to the development of long-term strategic plans and initiatives to support the company's growth objectives.\n\u2022 Provide strategic insights and recommendations based on market analysis, industry trends, and competitive intelligence.\n\u2022 Collaborate with senior leadership to define and prioritize strategic initiatives and allocate resources effectively.\n\nEXPERIENCE\n\u2022 Bachelor\u2019s degree in sciences required, advance degrees (MS, PhD, MBA, MD) preferred\n\u2022 Experience in business development, alliance management, or related roles within the biopharma industry.\n\u2022 Proven track record of successfully identifying and executing business opportunities that drive revenue growth and enhance market position; robust deal sheet.\n\u2022 Robust business acumen and strong negotiation skills, with the ability to structure complex agreements and drive mutually beneficial outcomes.\n\u2022 Excellent interpersonal and communication skills, with the ability to build and maintain relationships with internal and external stakeholders at all levels.\n\u2022 Ability to present results to senior management and the Board\n\u2022 Strategic thinker with a demonstrated ability to analyze market trends, assess competitive dynamics, and develop actionable insights and recommendations.\n\u2022 Highly organized and detail-oriented, with the ability to manage multiple projects simultaneously and thrive in a fast-paced, dynamic environment.\n\u2022 Strong leadership capabilities, with experience leading cross-functional teams and driving results through collaboration and influence.", "job_is_remote": false, "job_posted_at_timestamp": 1710201600, "job_posted_at_datetime_utc": "2024-03-12T00:00:00.000Z", "job_city": "Waltham", "job_state": "MA", "job_country": "US", "job_latitude": 42.376484, "job_longitude": -71.23561, "job_benefits": null, "job_google_link": "https://www.google.com/search?gl=us&hl=en&rciv=jb&q=senior+director+of+business+development&start=0&ibp=htl;jobs#fpstate=tldetail&htivrt=jobs&htiq=senior+director+of+business+development&htidocid=36m8itJj_2bBC4HXAAAAAA%3D%3D", "job_offer_expiration_datetime_utc": null, "job_offer_expiration_timestamp": null, "job_required_experience": {"no_experience_required": false, "required_experience_in_months": null, "experience_mentioned": true, "experience_preferred": false}, "job_required_skills": null, "job_required_education": {"postgraduate_degree": false, "professional_certification": false, "high_school": false, "associates_degree": false, "bachelors_degree": false, "degree_mentioned": true, "degree_preferred": true, "professional_certification_mentioned": false}, "job_experience_in_place_of_education": false, "job_min_salary": null, "job_max_salary": null, "job_salary_currency": null, "job_salary_period": null, "job_highlights": {"Qualifications": ["Experience in business development, alliance management, or related roles within the biopharma industry", "Proven track record of successfully identifying and executing business opportunities that drive revenue growth and enhance market position; robust deal sheet", "Robust business acumen and strong negotiation skills, with the ability to structure complex agreements and drive mutually beneficial outcomes", "Excellent interpersonal and communication skills, with the ability to build and maintain relationships with internal and external stakeholders at all levels", "Ability to present results to senior management and the Board", "Strategic thinker with a demonstrated ability to analyze market trends, assess competitive dynamics, and develop actionable insights and recommendations", "Highly organized and detail-oriented, with the ability to manage multiple projects simultaneously and thrive in a fast-paced, dynamic environment", "Strong leadership capabilities, with experience leading cross-functional teams and driving results through collaboration and influence"], "Responsibilities": ["The Senior Director of Business Development and Alliance Management will have a significant impact by driving the strategic growth and development opportunities of Dianthus Therapeutics", "Reporting to the CFO / CBO, you will be responsible for evaluating, structuring, and negotiating new business opportunities, cultivating partnerships, and managing key alliances to enhance the company's market position and adding strategic value to help build a long-term successful Biotech company", "You must have experience bringing new assets or products into the pipeline, maintaining a commercial mindset, and an understanding of full lifecycle product development", "Identify and evaluate new business opportunities that align with the company's strategic objectives and growth targets", "Develop and execute comprehensive business development strategies to expand market share", "Lead the negotiation and structuring of complex partnership agreements (including geographic partnering), licensing deals, and strategic alliances", "Build and maintain a robust pipeline of potential opportunities and effectively prioritize initiatives based on their potential impact and alignment with company goals", "Collaborate closely with cross-functional teams (Discovery, Clinical, Regulatory CMC, Legal/IP, Finance, etc.)", "to assess market trends, patient needs, and competitive dynamics to inform business development strategies", "Lead the evaluation of potential deals including scientific/portfolio rationale, market opportunity assessment, NPV modeling, comparative deals, and evaluation of business fit, in collaboration with cross-functional teams", "Serve as the primary point of contact for key partners and alliances, fostering strong relationships and driving mutual value creation", "Develop and execute alliance management plans to ensure the successful implementation and execution of partnership agreements", "Facilitate regular communication and collaboration between internal and external stakeholders to drive alignment and achieve shared objectives", "Monitor and track the performance of strategic alliances, identifying opportunities for optimization and improvement", "Resolve conflicts and mitigate risks that may arise in the course of managing complex partnerships and alliances", "Contribute to the development of long-term strategic plans and initiatives to support the company's growth objectives", "Provide strategic insights and recommendations based on market analysis, industry trends, and competitive intelligence", "Collaborate with senior leadership to define and prioritize strategic initiatives and allocate resources effectively"]}, "job_job_title": "Senior director", "job_posting_language": "en", "job_onet_soc": "11202100", "job_onet_job_zone": "4"}