{"job_id": "6aZFIUU2bNr_0lwnAAAAAA==", "employer_name": "Pivotal Recruitment Ltd", "employer_logo": "https://encrypted-tbn0.gstatic.com/images?q=tbn:ANd9GcSh4o_z5HhAoyhKHoNoQZUvjTzCfZ2ms7wpME4X&s=0", "employer_website": null, "employer_company_type": null, "job_publisher": "LinkedIn", "job_employment_type": "FULLTIME", "job_title": "Senior Sales Executive", "job_apply_link": "https://www.linkedin.com/jobs/view/senior-sales-executive-at-pivotal-recruitment-ltd-3857176679", "job_apply_is_direct": false, "job_apply_quality_score": 0.6394, "apply_options": [{"publisher": "LinkedIn", "apply_link": "https://www.linkedin.com/jobs/view/senior-sales-executive-at-pivotal-recruitment-ltd-3857176679", "is_direct": false}], "job_description": "Position Title: Senior Sales Executive\n\nCompany: Corrugated Manufacturer (Must have Corrugated experience)\n\nLocation: Georgia, United States (Remote)\n\nSalary: $120-160K\n\nOverview:\n\nWe are seeking a dynamic and experienced Senior Sales Executive to join a market leading Corrugated Manufacturer. As a Senior Sales Executive, you will play a crucial role in driving sales growth and expanding our market presence across the East Coast. You will be responsible for cultivating relationships with existing clients, identifying new business opportunities, and effectively communicating the value of our products and services.\n\nResponsibilities:\n\n-Develop and implement strategic sales plans to achieve company sales targets and objectives.\n\n-Identify and pursue new business opportunities within markets such as FMCG, Distributors, Manufacturing and more.\n\n-Build and maintain strong relationships with existing clients to ensure customer satisfaction and retention.\n\n-Conduct market research to identify emerging trends, competitive activities, and customer needs.\n\n-Ability to collaborate with the multiple teams (Production, Technical, Customer Service and Management) to provide the best possible service to our customers.\n\n-Attend industry trade shows, conferences, and networking events to promote company products and services.\n\n-Prepare and deliver sales proposals, quotations, and contracts to prospective clients.\n\n-Negotiate pricing, terms, and agreements with customers to maximize profitability.\n\n-Provide regular sales forecasts, reports, and updates to management.\n\n-Stay informed about industry developments, technological advancements, and regulatory changes affecting the corrugated packaging market.\n\n-Maintain a high level of professionalism, integrity, and ethical standards in all interactions with customers, colleagues, and stakeholders.\n\nQualifications:\n\n-Proven track record of success in B2B sales within the corrugated packaging industry.\n\n-Minimum of 3 years of experience in a senior sales role, preferably with a focus on Paper, Packaging and Manufacturing.\n\n-Strong business acumen and understanding of sales principles, techniques, and strategies.\n\n-Excellent communication, negotiation, and presentation skills.\n\n-Ability to build and maintain long-term relationships with clients and internal stakeholders.\n\n-Results-driven mindset with a passion for exceeding sales targets and achieving goals.\n\n-Proficiency in Microsoft Office suite and CRM software.\n\n-Willingness to travel as needed to meet with clients and attend industry events.\n\n-Valid driver's license and clean driving record.\n\nApply now with your resume and cover letter outlining your qualifications and why you are the ideal candidate for this position.", "job_is_remote": true, "job_posted_at_timestamp": 1710415138, "job_posted_at_datetime_utc": "2024-03-14T11:18:58.000Z", "job_city": null, "job_state": null, "job_country": "US", "job_latitude": 37.09024, "job_longitude": -95.71289, "job_benefits": null, "job_google_link": "https://www.google.com/search?gl=us&hl=en&rciv=jb&q=senior+sales+director&start=0&ibp=htl;jobs#fpstate=tldetail&htivrt=jobs&htiq=senior+sales+director&htidocid=6aZFIUU2bNr_0lwnAAAAAA%3D%3D", "job_offer_expiration_datetime_utc": "2024-04-13T11:18:58.000Z", "job_offer_expiration_timestamp": 1713007138, "job_required_experience": {"no_experience_required": false, "required_experience_in_months": null, "experience_mentioned": true, "experience_preferred": false}, "job_required_skills": null, "job_required_education": {"postgraduate_degree": false, "professional_certification": false, "high_school": false, "associates_degree": false, "bachelors_degree": false, "degree_mentioned": false, "degree_preferred": false, "professional_certification_mentioned": false}, "job_experience_in_place_of_education": false, "job_min_salary": 120000, "job_max_salary": 160000, "job_salary_currency": "USD", "job_salary_period": "YEAR", "job_highlights": {"Qualifications": ["Company: Corrugated Manufacturer (Must have Corrugated experience)", "Proven track record of success in B2B sales within the corrugated packaging industry", "Minimum of 3 years of experience in a senior sales role, preferably with a focus on Paper, Packaging and Manufacturing", "Strong business acumen and understanding of sales principles, techniques, and strategies", "Excellent communication, negotiation, and presentation skills", "Ability to build and maintain long-term relationships with clients and internal stakeholders", "Results-driven mindset with a passion for exceeding sales targets and achieving goals", "Proficiency in Microsoft Office suite and CRM software", "Willingness to travel as needed to meet with clients and attend industry events", "Valid driver's license and clean driving record"], "Responsibilities": ["As a Senior Sales Executive, you will play a crucial role in driving sales growth and expanding our market presence across the East Coast", "You will be responsible for cultivating relationships with existing clients, identifying new business opportunities, and effectively communicating the value of our products and services", "Develop and implement strategic sales plans to achieve company sales targets and objectives", "Identify and pursue new business opportunities within markets such as FMCG, Distributors, Manufacturing and more", "Build and maintain strong relationships with existing clients to ensure customer satisfaction and retention", "Conduct market research to identify emerging trends, competitive activities, and customer needs", "Ability to collaborate with the multiple teams (Production, Technical, Customer Service and Management) to provide the best possible service to our customers", "Attend industry trade shows, conferences, and networking events to promote company products and services", "Prepare and deliver sales proposals, quotations, and contracts to prospective clients", "Negotiate pricing, terms, and agreements with customers to maximize profitability", "Provide regular sales forecasts, reports, and updates to management", "Stay informed about industry developments, technological advancements, and regulatory changes affecting the corrugated packaging market", "Maintain a high level of professionalism, integrity, and ethical standards in all interactions with customers, colleagues, and stakeholders"], "Benefits": ["Salary: $120-160K"]}, "job_job_title": "Sales executive", "job_posting_language": "en", "job_onet_soc": "41401200", "job_onet_job_zone": "4"}