{"job_id": "AOsDWzRA1gWouTf2AAAAAA==", "employer_name": "Abbott Laboratories", "employer_logo": "https://images.forbes.com/media/lists/companies/abbott-laboratories_416x416.jpg", "employer_website": "http://www.abbott.com", "employer_company_type": "Manufacturing", "job_publisher": "Abbott Jobs", "job_employment_type": "FULLTIME", "job_title": "Staff Data Scientist", "job_apply_link": "https://www.jobs.abbott/us/en/job/31077115/Staff-Data-Scientist", "job_apply_is_direct": false, "job_apply_quality_score": 0.8061, "apply_options": [{"publisher": "Abbott Jobs", "apply_link": "https://www.jobs.abbott/us/en/job/31077115/Staff-Data-Scientist", "is_direct": false}, {"publisher": "ZipRecruiter", "apply_link": "https://www.ziprecruiter.com/c/Abbott/Job/Staff-Data-Scientist/-in-Burlington,MA?jid=77955ec773901478", "is_direct": false}, {"publisher": "LinkedIn", "apply_link": "https://www.linkedin.com/jobs/view/staff-data-scientist-at-abbott-3813929342", "is_direct": false}, {"publisher": "Glassdoor", "apply_link": "https://www.glassdoor.com/job-listing/staff-data-scientist-abbott-laboratories-JV_IC1154543_KO0,20_KE21,40.htm?jl=1009089512709", "is_direct": false}, {"publisher": "LocalJobs.com", "apply_link": "https://www.localjobs.com/job/burlington-ma-staff-data-scientist", "is_direct": false}, {"publisher": "SaluteMyJob", "apply_link": "https://salutemyjob.com/jobs/staff-data-scientist-burlington-massachusetts/1257183468-2/", "is_direct": false}, {"publisher": "Indeed", "apply_link": "https://www.indeed.com/viewjob?jk=c592de656bf784f7", "is_direct": false}, {"publisher": "National Labor Exchange Veterans Jobs", "apply_link": "https://veterans.usnlx.com/burlington-ma/staff-data-scientist/E2E135CF6B284859BBB1F54EA3620BB7/job/?vs=28", "is_direct": false}], "job_description": "Working at Abbott\n\nAt Abbott, you can do work that matters, grow, and learn, care for yourself and family, be your true self and live a full life. You\u2019ll also have access to:\n\u2022 Career development with an international company where you can grow the career you dream of.\n\u2022 Free medical coverage for employees* via the Health Investment Plan (HIP) PPO\n\u2022 An excellent retirement savings plan with high employer contribution\n\u2022 Tuition reimbursement, the Freedom 2 Save student debt program and FreeU education benefit - an affordable and convenient path to getting a bachelor\u2019s degree.\n\u2022 A company recognized as a great place to work in dozens of countries around the world and named one of the most admired companies in the world by Fortune.\n\u2022 A company that is recognized as one of the best big companies to work for as well as a best place to work for diversity, working mothers, female executives, and scientists.\n\nThe Opportunity\n\nThis position works out of our Pleasanton, California location in the Heart Failure Division. In Abbott\u2019s Heart Failure (HF) business, we\u2019re developing solutions to diagnose, monitor and manage heart failure, allowing people to restore their health and get on with their lives.\n\nAs a Staff Data Scientist, you will play a crucial role in shaping our data-driven strategies and contributing to the success of our Heart Failure initiatives. You will be responsible for designing, developing, and deploying advanced data science solutions to extract valuable insights from large and complex datasets. As a key member of our team, you must be capable of exhibiting a sense of inquisitiveness and a creative mind to uncover opportunities that will directly contribute to enhancing the quality of patient care and the development of innovative medical devices and therapy solutions.\n\nWhat You\u2019ll Work On\n\nData Analysis and Modeling:\n\u2022 Conduct exploratory data analysis to understand trends and patterns.\n\u2022 Collaborate with cross-functional teams to define project objectives.\n\u2022 Utilize large datasets from various sources, including medical devices and phenotype data.\n\nMachine Learning and Statistical Analysis:\n\u2022 Develop and refine features for predictive modeling, ensuring that relevant clinical variables are incorporated effectively.\n\u2022 Build and validate predictive models for clinical outcomes, patient risk assessments, and other relevant applications, using appropriate machine learning algorithms.\n\u2022 Evaluate and optimize models for accuracy and performance.\n\nClinical Insights:\n\u2022 Collaborate closely with cross-functional teams, including medical experts, clinical research scientists, and engineers to identify clinically significant insights and patterns within the data.\n\u2022 Understanding of physiological systems and therapies in the cardiovascular space is a plus\n\nData Visualization:\n\u2022 Create informative data visualizations and dashboards to communicate findings and insights to non-technical stakeholders.\n\nData Governance:\n\u2022 Implement data governance best practices to ensure data quality, integrity, and compliance with relevant regulations, such as HIPAA.\n\nResearch and Innovation:\n\u2022 Stay updated with the latest developments in data science and machine learning to continually improve data analysis methodologies and techniques.\n\u2022 Identify opportunities for innovation and propose data-driven solutions.\n\nCollaboration:\n\u2022 Collaborate with external partners, academic institutions, and healthcare providers to access additional data sources and research opportunities.\n\nDocumentation:\n\nMaintain comprehensive documentation of data analysis processes, methodologies, and findings.\n\nRequired Qualifications\n\u2022 Bachelor\u2019s Degree in Data Science, Computer Science, Statistics, or a related field plus 8 years of experience.\n\u2022 Master\u2019s Degree in Data Science, Computer Science, Statistics, or a related field plus 6 years of experience.\n\u2022 Proven experience in data analysis and modeling, preferably in the medical device or healthcare industry.\n\u2022 Proficiency in programming languages such as Python or R.\n\u2022 Strong knowledge of machine learning algorithms, statistical techniques, and data visualization.\n\u2022 Experience with healthcare data, including Electronic Health Records (EHR), is a plus.\n\u2022 Excellent communication skills and the ability to translate technical findings into actionable insights for non-technical stakeholders.\n\u2022 Strong problem-solving skills and attention to detail.\n\u2022 Familiarity with data privacy and security regulations, such as HIPAA.\n\u2022 Experience with data visualization tools (e.g., Tableau, Power BI) is a plus.\n\u2022 Ability to work collaboratively in a fast-paced, cross-functional team environment.\n\nPreferred Qualifications\n\u2022 Master\u2019s Degree or Ph.D. in Data Science, Computer Science, Statistics, or a related field.\n\nWorking at Abbott\n\nAt Abbott, you can do work that matters, grow, and learn, care for yourself and family, be your true self and live a full life. You\u2019ll also have access to:\n\u2022 Career development with an international company where you can grow the career you dream of.\n\u2022 Free medical coverage for employees* via the Health Investment Plan (HIP) PPO\n\u2022 An excellent retirement savings plan with high employer contribution\n\u2022 Tuition reimbursement, the Freedom 2 Save student debt program and FreeU education benefit - an affordable and convenient path to getting a bachelor\u2019s degree.\n\u2022 A company recognized as a great place to work in dozens of countries around the world and named one of the most admired companies in the world by Fortune.\n\u2022 A company that is recognized as one of the best big companies to work for, as well as a best place to work for diversity, working mothers, female executives, and scientists.\n\nThe Opportunity\nThe Senior Staff Systems Engineer will be accountable for delivering system verification across the full CardioMEMS system in support of multiple ongoing projects. This role ensures the logical and systematic verification of system level design input and performance requirements accounting for technical, schedule, and cost constraints. You will be applying an expert understanding of applications, customer needs and use, verification best practices, test tools, and sub-system verification to streamline design verification.\n\nPrimary Responsibilities:\n\u2022 Lead verification projects with significant novelty and integration across various disciplines and team members. Apply a portfolio-centric approach to developing programs and verification solutions.\n\u2022 Build and improve system verification processes and methods for the CardioMEMS system of devices, which includes implanted MEMS devices, external medical electrical equipment devices, database and software-based products, and mobile application products.\n\u2022 Identify and implement tools, fixturing, testing automation methods, and other resources necessary for system verification.\n\u2022 Plan, develop, and execute system verification based on established system requirements, as an individual contributor and as a leader directing other test engineers.\n\u2022 Drive review and optimization of project-wide and cross-project verification efforts to ensure adequate coverage, minimize duplication, and increase transparency and understanding of system verification versus sub-system verification versus other types of testing.\n\u2022 Contribute to and support gathering, analyzing, and reviewing system level and sub-system requirements.\n\u2022 Develop, write, and review test plans, procedures, methods, and reports with excellent writing skills.\n\u2022 Foster collaboration with cross-functional teams and other leaders to drive work to completion and resolve issues. Successfully influence stakeholders. Communicate effectively with cross-functional teams and senior management. Keeps leadership informed of progress and issues.\n\u2022 Organize and manage work to deliver programs, leads in the execution of assigned work. Prioritize tasks by distinguishing urgent from important tasks and assess cost/benefit trade-offs.\n\u2022 Develop and apply an expert understanding of designated systems as well as serve as a subject matter expert for the development team regarding behaviors, implementation, system and sub-system verification methodologies, and the applicable technologies required to solve problems and deliver upon business objectives. Participate in broad cross-functional reviews of work output.\n\u2022 Apply industry best practices and applicable regulations to work area.\n\u2022 Comply with U.S. Food and Drug Administration (FDA) regulations, other regulatory requirements, Company policies, operating procedures, processes, and task assignments.\n\nRequired Qualifications:\n\u2022 Bachler\u2019s Degree in Engineering (Computer, Electrical, Software, or Biomedical), Computer Science, or related discipline\n\u2022 9+ years of experience in a similar position, including system verification and validation, systems integration experience, and/or end-to-end (ideation to commercialization) technical product development experience\n\u2022 Experience leading and managing other engineers to complete project work\n\u2022 Experience working in new product development of medical device industry\n\u2022 Excellent verbal and written communication skills, with ability to communicate to all levels of the organization\n\u2022 Ability to work within a team and as an individual contributor in a fast-paced, changing environment\n\u2022 Ability to collect, organize, and analyze data using statistical methods\n\nPreferred Qualifications:\n\u2022 Advanced degree in Engineering (Computer, Electrical, Software, or Biomedical), Computer Science, or related discipline with 10 years of work experience\n\u2022 Experience and expertise with systems consisting of hardware, software, mobile app, and cloud components\n\u2022 Experience and expertise with systems with RF, electromagnetics, ASICs, Bluetooth, and NFC technologies\n\u2022 Class III implantable medical device experience\n\u2022 Demonstrated ability to effectively integrate information from varied disciplines including Clinical Medicine, Engineering, Marketing and Regulatory Affairs\n\nWHAT WE OFFER\n\nAt Abbott, you can have a good job that can grow into a great career. We offer:\n\u2022 Training and career development, with onboarding programs for new employees and tuition assistance\n\u2022 Financial security through competitive compensation, incentives and retirement plans\n\u2022 Health care and well-being programs including medical, dental, vision, wellness and occupational health programs\n\u2022 Paid time off\n\u2022 401(k) retirement savings with a generous company match\n\u2022 The stability of a company with a record of strong financial performance and history of being actively involved in local communities\n\nLearn more about our benefits that add real value to your life to help you live fully: http://www.abbottbenefits.com/pages/candidate.aspx\n\nFollow your career aspirations to Abbott for diverse opportunities with a company that provides the growth and strength to build your future. Abbott is an Equal Opportunity Employer, committed to employee diversity. Connect with us at www.abbott.com, on Facebook at www.facebook.com/Abbott and on Twitter @AbbottNews and @AbbottGlobal.\n\nThe base pay for this position is $95,000.00 \u2013 $190,000.00. In specific locations, the pay range may vary from the range posted.", "job_is_remote": false, "job_posted_at_timestamp": 1709424000, "job_posted_at_datetime_utc": "2024-03-03T00:00:00.000Z", "job_city": "Burlington", "job_state": "MA", "job_country": "US", "job_latitude": 42.504715, "job_longitude": -71.19562, "job_benefits": ["paid_time_off", "health_insurance", "dental_coverage", "retirement_savings"], "job_google_link": "https://www.google.com/search?gl=us&hl=en&rciv=jb&q=senior+data+scientist&start=50&ibp=htl;jobs#fpstate=tldetail&htivrt=jobs&htiq=senior+data+scientist&htidocid=AOsDWzRA1gWouTf2AAAAAA%3D%3D", "job_offer_expiration_datetime_utc": null, "job_offer_expiration_timestamp": null, "job_required_experience": {"no_experience_required": false, "required_experience_in_months": 120, "experience_mentioned": true, "experience_preferred": true}, "job_required_skills": null, "job_required_education": {"postgraduate_degree": false, "professional_certification": false, "high_school": false, "associates_degree": false, "bachelors_degree": false, "degree_mentioned": true, "degree_preferred": true, "professional_certification_mentioned": false}, "job_experience_in_place_of_education": false, "job_min_salary": null, "job_max_salary": null, "job_salary_currency": null, "job_salary_period": null, "job_highlights": {"Qualifications": ["Bachelor\u2019s Degree in Data Science, Computer Science, Statistics, or a related field plus 8 years of experience", "Proven experience in data analysis and modeling, preferably in the medical device or healthcare industry", "Proficiency in programming languages such as Python or R", "Strong knowledge of machine learning algorithms, statistical techniques, and data visualization", "Excellent communication skills and the ability to translate technical findings into actionable insights for non-technical stakeholders", "Strong problem-solving skills and attention to detail", "Familiarity with data privacy and security regulations, such as HIPAA", "Ability to work collaboratively in a fast-paced, cross-functional team environment", "Bachler\u2019s Degree in Engineering (Computer, Electrical, Software, or Biomedical), Computer Science, or related discipline", "9+ years of experience in a similar position, including system verification and validation, systems integration experience, and/or end-to-end (ideation to commercialization) technical product development experience", "Experience leading and managing other engineers to complete project work", "Experience working in new product development of medical device industry", "Excellent verbal and written communication skills, with ability to communicate to all levels of the organization", "Ability to work within a team and as an individual contributor in a fast-paced, changing environment", "Ability to collect, organize, and analyze data using statistical methods"], "Responsibilities": ["You will be responsible for designing, developing, and deploying advanced data science solutions to extract valuable insights from large and complex datasets", "As a key member of our team, you must be capable of exhibiting a sense of inquisitiveness and a creative mind to uncover opportunities that will directly contribute to enhancing the quality of patient care and the development of innovative medical devices and therapy solutions", "Conduct exploratory data analysis to understand trends and patterns", "Collaborate with cross-functional teams to define project objectives", "Utilize large datasets from various sources, including medical devices and phenotype data", "Machine Learning and Statistical Analysis:", "Develop and refine features for predictive modeling, ensuring that relevant clinical variables are incorporated effectively", "Build and validate predictive models for clinical outcomes, patient risk assessments, and other relevant applications, using appropriate machine learning algorithms", "Evaluate and optimize models for accuracy and performance", "Collaborate closely with cross-functional teams, including medical experts, clinical research scientists, and engineers to identify clinically significant insights and patterns within the data", "Create informative data visualizations and dashboards to communicate findings and insights to non-technical stakeholders", "Implement data governance best practices to ensure data quality, integrity, and compliance with relevant regulations, such as HIPAA", "Stay updated with the latest developments in data science and machine learning to continually improve data analysis methodologies and techniques", "Identify opportunities for innovation and propose data-driven solutions", "Collaborate with external partners, academic institutions, and healthcare providers to access additional data sources and research opportunities", "Maintain comprehensive documentation of data analysis processes, methodologies, and findings", "The Senior Staff Systems Engineer will be accountable for delivering system verification across the full CardioMEMS system in support of multiple ongoing projects", "This role ensures the logical and systematic verification of system level design input and performance requirements accounting for technical, schedule, and cost constraints", "Lead verification projects with significant novelty and integration across various disciplines and team members", "Apply a portfolio-centric approach to developing programs and verification solutions", "Build and improve system verification processes and methods for the CardioMEMS system of devices, which includes implanted MEMS devices, external medical electrical equipment devices, database and software-based products, and mobile application products", "Identify and implement tools, fixturing, testing automation methods, and other resources necessary for system verification", "Plan, develop, and execute system verification based on established system requirements, as an individual contributor and as a leader directing other test engineers", "Drive review and optimization of project-wide and cross-project verification efforts to ensure adequate coverage, minimize duplication, and increase transparency and understanding of system verification versus sub-system verification versus other types of testing", "Contribute to and support gathering, analyzing, and reviewing system level and sub-system requirements", "Develop, write, and review test plans, procedures, methods, and reports with excellent writing skills", "Foster collaboration with cross-functional teams and other leaders to drive work to completion and resolve issues", "Successfully influence stakeholders", "Communicate effectively with cross-functional teams and senior management", "Keeps leadership informed of progress and issues", "Organize and manage work to deliver programs, leads in the execution of assigned work", "Prioritize tasks by distinguishing urgent from important tasks and assess cost/benefit trade-offs", "Develop and apply an expert understanding of designated systems as well as serve as a subject matter expert for the development team regarding behaviors, implementation, system and sub-system verification methodologies, and the applicable technologies required to solve problems and deliver upon business objectives", "Participate in broad cross-functional reviews of work output", "Apply industry best practices and applicable regulations to work area", "Comply with U.S. Food and Drug Administration (FDA) regulations, other regulatory requirements, Company policies, operating procedures, processes, and task assignments"], "Benefits": ["Career development with an international company where you can grow the career you dream of", "Free medical coverage for employees* via the Health Investment Plan (HIP) PPO", "An excellent retirement savings plan with high employer contribution", "Tuition reimbursement, the Freedom 2 Save student debt program and FreeU education benefit - an affordable and convenient path to getting a bachelor\u2019s degree", "Training and career development, with onboarding programs for new employees and tuition assistance", "Financial security through competitive compensation, incentives and retirement plans", "Health care and well-being programs including medical, dental, vision, wellness and occupational health programs", "Paid time off", "401(k) retirement savings with a generous company match", "The stability of a company with a record of strong financial performance and history of being actively involved in local communities", "The base pay for this position is $95,000.00 \u2013 $190,000.00", "In specific locations, the pay range may vary from the range posted"]}, "job_job_title": "Data scientist", "job_posting_language": "en", "job_onet_soc": "15111100", "job_onet_job_zone": "5", "job_occupational_categories": ["Research & Development"], "job_naics_code": "325412", "job_naics_name": "Pharmaceutical Preparation Manufacturing"}