{"job_id": "8sFG6v2Hc4kcTC6EAAAAAA==", "employer_name": "PlayersTV", "employer_logo": null, "employer_website": "http://playerstv.com", "employer_company_type": null, "job_publisher": "Jooble", "job_employment_type": "FULLTIME", "job_title": "Media Sales and Partnerships Manager", "job_apply_link": "https://jooble.org/jdp/4052155252135463382", "job_apply_is_direct": false, "job_apply_quality_score": 0.5447, "apply_options": [{"publisher": "Jooble", "apply_link": "https://jooble.org/jdp/4052155252135463382", "is_direct": false}, {"publisher": "LazyApply", "apply_link": "https://lazyapply.com/jobpreview/job_ef430e2a0df218ac", "is_direct": false}], "job_description": "Media Sales and Partnerships Manager Location Remote : Job Title: Media Sales and Partnerships Manager Department: Sports Media & Entertainment Location: Remote PlayersTV is an athlete-owned company that houses an ecosystem of media and entertainment verticals dedicated to athlete lifestyle content creation and distribution. Our mission is to build a media platform for athletes dedicated to athlete lifestyle content that connects athletes directly with fans and brands. Each day the PlayersTV will deliver with boldness and excellence, the most authentic sports lifestyle and culture entertainment experiences to its audiences while always remaining respectful to each other in our practice and in our pursuit to be unifying and extraordinary citizens. Position Summary: Manager, Media Sales and Partnerships Position Summary We are seeking a dynamic and results-oriented Media Sales and Partnerships Manager to join our team. As the Media Sales and Partnerships Manager, you will play a crucial role in driving revenue growth through strategic media sales and establishing and nurturing partnerships. The ideal candidate should have a proven track record in media sales, a deep understanding of the media landscape, and the ability to cultivate and maintain strong relationships with partners. Responsibilities 1. Media Sales: a. Develop and execute a comprehensive media sales strategy to achieve revenue targets. b. Identify and pursue new business opportunities, including potential clients and advertising partners. c. Build and maintain a robust sales pipeline, ensuring consistent revenue growth. d. Collaborate with the marketing team to create compelling sales collateral and presentations. 2. Partnerships Development: a. Identify, negotiate, and establish partnerships with key players in the media industry. b. Foster and maintain strong relationships with existing partners, ensuring satisfaction and repeat business. c. Evaluate potential partnership opportunities based on strategic fit and mutual benefits. d. Collaborate with cross-functional teams to ensure successful implementation and execution of partnership initiatives. 3. Market Research and Analysis: a. Stay informed about industry trends, competitor activities, and market dynamics. b. Conduct regular market research to identify new opportunities and stay ahead of industry developments. c. Analyze sales data and performance metrics to refine strategies and optimize results. 4. Collaboration and Communication: a. Work closely with internal teams, including marketing, product development, and operations, to align strategies and achieve common goals. b. Communicate effectively with clients and partners, providing regular updates and ensuring a high level of customer satisfaction. 5. Contract Negotiation: a. Lead negotiations for media sales and partnership agreements, ensuring favorable terms for all parties involved. b. Collaborate with legal teams to review and finalize contracts in accordance with company policies. Qualifications\n\u2022 Proven experience in media sales and partnerships development, preferably in a related\nindustry.\n\u2022 Strong understanding of the media landscape, advertising trends, and digital marketing.\n\u2022 Excellent negotiation and communication skills.\n\u2022 Ability to analyze data and market trends to inform strategic decision-making.\n\u2022 Demonstrated ability to meet and exceed sales targets.\n\u2022 Bachelor's degree in Business, Marketing, Communications, or a related field.\nKnowledge, Skills & Abilities\n\u2022 Demonstrated ability to work in a highly collaborative environment;\n\u2022 High attention to detail;\n\u2022 Excellent presentation, written and verbal communication skills;\n\u2022 Proficient in Microsoft Office Suite including Microsoft Excel, PowerPoint, Word and\nrelated Google Office Suite comparable platforms;\n\u2022 Ability to manage multiple projects while being responsive to the needs of the division\nand peers, be able to prioritize effectively and exercise flexibility as needed;\n\u2022 Self-confidence in creative idea generation and ability to communicate a narrative;\n\u2022 Excellent project management and organization skills;\n\u2022 Knowledge and understanding of sports business, sports media and athlete\nrepresentation industry;\n\u2022 Strong research and analytical skills;\n\u2022 Ability to identify and solve problems creatively;\n\u2022 Ability to work well with others in a team environment;\n\u2022 Self-motivated and self-directed; and\n\u2022 Highly responsive and accessible.\nSalary\n\u2022 $60,000 annual salary with competitive commission structure\n\u2022 40 hours per week minimum\nPlayersTV provides equal employment opportunities (EEO) to all employees and applicants for employment without regard to age, color, national origin, citizenship status, physical or mental disability, race, religion, creed, gender, sex, sexual orientation, gender identity and/or expression, genetic information, marital status, status with regard to public assistance, veteran status, or any other characteristic protected by federal, state or local law. This policy applies to all terms and conditions of employment, including recruiting, hiring, placement, promotion, termination, leaves of absence, compensation and training.", "job_is_remote": false, "job_posted_at_timestamp": 1710028800, "job_posted_at_datetime_utc": "2024-03-10T00:00:00.000Z", "job_city": null, "job_state": null, "job_country": "US", "job_latitude": 37.09024, "job_longitude": -95.71289, "job_benefits": null, "job_google_link": "https://www.google.com/search?gl=us&hl=en&rciv=jb&q=manager+of+brand+partnerships&start=50&ibp=htl;jobs#fpstate=tldetail&htivrt=jobs&htiq=manager+of+brand+partnerships&htidocid=8sFG6v2Hc4kcTC6EAAAAAA%3D%3D", "job_offer_expiration_datetime_utc": "2024-04-04T00:00:00.000Z", "job_offer_expiration_timestamp": 1712188800, "job_required_experience": {"no_experience_required": false, "required_experience_in_months": null, "experience_mentioned": true, "experience_preferred": false}, "job_required_skills": null, "job_required_education": {"postgraduate_degree": false, "professional_certification": false, "high_school": false, "associates_degree": false, "bachelors_degree": false, "degree_mentioned": true, "degree_preferred": true, "professional_certification_mentioned": false}, "job_experience_in_place_of_education": false, "job_min_salary": 60000, "job_salary_currency": "USD", "job_salary_period": "YEAR", "job_highlights": {"Qualifications": ["Proven experience in media sales and partnerships development, preferably in a related", "Strong understanding of the media landscape, advertising trends, and digital marketing", "Excellent negotiation and communication skills", "Ability to analyze data and market trends to inform strategic decision-making", "Demonstrated ability to meet and exceed sales targets", "Bachelor's degree in Business, Marketing, Communications, or a related field", "Demonstrated ability to work in a highly collaborative environment;", "High attention to detail;", "Excellent presentation, written and verbal communication skills;", "Proficient in Microsoft Office Suite including Microsoft Excel, PowerPoint, Word and", "related Google Office Suite comparable platforms;", "Ability to manage multiple projects while being responsive to the needs of the division", "and peers, be able to prioritize effectively and exercise flexibility as needed;", "Self-confidence in creative idea generation and ability to communicate a narrative;", "Excellent project management and organization skills;", "Knowledge and understanding of sports business, sports media and athlete", "Strong research and analytical skills;", "Ability to identify and solve problems creatively;", "Ability to work well with others in a team environment;", "Self-motivated and self-directed; and", "Highly responsive and accessible"], "Responsibilities": ["As the Media Sales and Partnerships Manager, you will play a crucial role in driving revenue growth through strategic media sales and establishing and nurturing partnerships", "Develop and execute a comprehensive media sales strategy to achieve revenue targets", "Identify and pursue new business opportunities, including potential clients and advertising partners. c. Build and maintain a robust sales pipeline, ensuring consistent revenue growth", "d. Collaborate with the marketing team to create compelling sales collateral and presentations", "Partnerships Development: a", "Identify, negotiate, and establish partnerships with key players in the media industry", "Foster and maintain strong relationships with existing partners, ensuring satisfaction and repeat business", "Evaluate potential partnership opportunities based on strategic fit and mutual benefits. d. Collaborate with cross-functional teams to ensure successful implementation and execution of partnership initiatives", "Stay informed about industry trends, competitor activities, and market dynamics", "Conduct regular market research to identify new opportunities and stay ahead of industry developments", "Analyze sales data and performance metrics to refine strategies and optimize results", "Collaboration and Communication: a", "Work closely with internal teams, including marketing, product development, and operations, to align strategies and achieve common goals", "Communicate effectively with clients and partners, providing regular updates and ensuring a high level of customer satisfaction", "Contract Negotiation: a", "Lead negotiations for media sales and partnership agreements, ensuring favorable terms for all parties involved", "Collaborate with legal teams to review and finalize contracts in accordance with company policies"], "Benefits": ["$60,000 annual salary with competitive commission structure", "40 hours per week minimum"]}, "job_job_title": "Manager", "job_posting_language": "en", "job_onet_soc": "11202200", "job_onet_job_zone": "4"}