{"job_id": "bkJpRsxKp7uougP5AAAAAA==", "employer_name": "Walmart", "employer_logo": "https://animationvisarts.com/wp-content/uploads/2020/08/Walmart-logo-2008-Now.jpg", "employer_website": "https://www.walmart.com", "employer_company_type": "Retail", "job_publisher": "JOFDAV", "job_employment_type": "FULLTIME", "job_title": "Staff, Data Scientist (MLOps)", "job_apply_link": "https://www.jofdav.com/jobs/48956207-staff-data-scientist-mlops", "job_apply_is_direct": false, "job_apply_quality_score": 0.4948, "apply_options": [{"publisher": "JOFDAV", "apply_link": "https://www.jofdav.com/jobs/48956207-staff-data-scientist-mlops", "is_direct": false}], "job_description": "What you'll do at\n\nPosition Summary...\n\nWhat you'll do...\n\nIt's an exciting time to join our Walmart journey, we are seeking a Staff MLOps Data\nScientist. At Walmart, technology empowers us and people to lead. We believe new\ntechnologies will enhance the associate and customer experience in our stores. You will be\nworking on future-looking initiatives that are targeted at improving in-store customer\nexperience for the 240+ million Walmart customers that shop at our stores. The mission is\nto create step change in-store experiences, leveraging emerging technology to help define\nand deliver evolving customer expectations. Its success requires a cross-functional, mission-\nbased team that is highly entrepreneurial, collaborative, and passionate about solving\nunsolved problems.\n\nAs an MLOps Data Scientist, you will be a key player in developing and maintaining our\nmachine learning infrastructure and data platform ensuring the smooth integration of\nmodels into our production environment. Your role involves collaborating closely with\nComputer Vision data scientists, software engineers, and DevOps teams to optimize the end-\nto-end machine learning lifecycle. From implementing model performance improvement\nstrategies to troubleshooting issues in machine learning pipelines, your contributions will be\ncrucial to the efficiency and reliability of our ML operations\n\nYou'll make an impact by...\n\n\u2022Deploying and monitoring machine learning models for production environments.\n\u2022Building CV data pipelines, ensuring that data is easily accessible, updatable,\nreusable.\n\u2022Develop strategies to optimize the annotation process, minimizing the need for\nlabeling large amounts of data.\n\u2022Enhance model performance by selecting the most informative data for annotation\nand training.\n\u2022Providing expertise and guidance on all technical aspects of development, including\nrequirements, design, and implementation.\n\u2022Ensuring engineering and computer vision best practices, so that the team follows a\nstructured and efficient approach to their projects.\n\nWhat you'll do...\n\n\u2022Build a scalable and extensive ML data platform that can support multiple forms of\ndata and support the scalability of computer vision models.\n\u2022Pioneer novel software systems for the rapidly growing field of data-centric AI. The\nplatform has several tools that automatically find & fix issues in datasets.\n\u2022Build curated data sets with auto ML and active learning capabilities.\n\u2022Innovate with feedback loops and human-in-the-loop processes to continuously refine\nour systems to better meet product needs.\n\u2022Develop and implement robust model drift monitoring capabilities to ensure the\ncontinued accuracy of deployed models.\n\u2022Collaborate with data scientists and data engineers to address drift-related\nchallenges.\n\u2022Implement and manage ML Ops practices to streamline the machine learning\ndevelopment lifecycle.\n\u2022Provide mentorship to more junior members of the team.\n\u2022Stay ahead of the curve by keeping abreast of the latest technological\nadvancements, ensuring our solutions stay ahead of the curve.\n\nYou'll sweep us off our feet if...\n\n7+ years machine learning experience, PhD or MA/MS in related Computer Science,\nComputer Engineering or equivalent, OR 5+ years industry experience\n\u2022Experience leading projects with industry-wide impact.\n\u2022Significant experience in one or more of the following areas: machine learning, deep\nlearning, computer vision.\n\u2022Significant experience with advanced data pipeline, preferable with video or images\n\u2022Significant experience in programming languages with a technical background\n\u2022You are a team player - that is, you're a nice person - see no ego.\n\u2022Highly motivated and independent; good at prioritization and results oriented.\n\u2022A self-learner: ability to effectively adapt to rapidly changing technology and apply it\nto business needs, integrate multiple tools together to solve business problems.\n\u2022Proficient in scripting and automation with an emphasis on integration.\n\u2022Experience in shipping computer vision products to thousands of customers or have\nstarted a new line of products.\n\u2022Experience with complex image or video analytic pipelines.\n\u2022Expertise in machine learning development life cycle.\n\u2022Experience in some of the following fields: computer vision (object detection,\ntracking, scene understanding), machine learning.\n\nAbout Walmart Global Tech\n\nImagine working in an environment where one line of code can make life easier for hundreds of millions of people. That's what we do at Walmart Global Tech. We're a team of software engineers, data scientists, cybersecurity expert's and service professionals within the world's leading retailer who make an epic impact and are at the forefront of the next retail disruption. People are why we innovate, and people power our innovations. We are people-led and tech-empowered. We train our team in the skillsets of the future and bring in experts like you to help us grow. We have roles for those chasing their first opportunity as well as those looking for the opportunity that will define their career. Here, you can kickstart a great career in tech, gain new skills and experience for virtually every industry, or leverage your expertise to innovate at scale, impact millions and reimagine the future of retail.\n\nFlexible, hybrid work:\nWe use a hybrid way of working that is primarily in office coupled with virtual when not onsite. Our campuses serve as a hub to enhance collaboration, bring us together for purpose and deliver on business needs. This approach helps us make quicker decisions, remove location barriers across our global team and be more flexible in our personal lives.\n\nBenefits:\n\nBenefits: Beyond our great compensation package, you can receive incentive awards for your performance. Other great perks include 401(k) match, stock purchase plan, paid maternity and parental leave, PTO, multiple health plans, and much more.\n\nEqual Opportunity Employer:\n\nWalmart, Inc. is an Equal Opportunity Employer - By Choice. We believe we are best equipped to help our associates, customers and the communities we serve live better when we really know them. That means understanding, respecting and valuing diversity- unique styles, experiences, identities, ideas and opinions - while being inclusive of all people.\n\nThe above information has been designed to indicate the general nature and level of work performed in the role. It is not designed to contain or be interpreted as a comprehensive inventory of all responsibilities and qualifications required of employees assigned to this job. The full Job Description can be made available as part of the hiring process.\n\nAt Walmart, we offer competitive pay as well as performance-based incentive awards and other great benefits for a happier mind, body, and wallet. Health benefits include medical, vision and dental coverage. Financial benefits include 401(k), stock purchase and company-paid life insurance. Paid time off benefits include PTO (including sick leave), parental leave, family care leave, bereavement, jury duty, and voting. Other benefits include short-term and long-term disability, company discounts, Military Leave Pay, adoption and surrogacy expense reimbursement, and more.\n\nYou will also receive PTO and/or PPTO that can be used for vacation, sick leave, holidays, or other purposes. The amount you receive depends on your job classification and length of employment. It will meet or exceed the requirements of paid sick leave laws, where applicable. For information about PTO, see https://one.walmart.com/notices .\n\nLive Better U is a Walmart-paid education benefit program for full-time and part-time associates in Walmart and Sam's Club facilities. Programs range from high school completion to bachelor's degrees, including English Language Learning and short-form certificates. Tuition, books, and fees are completely paid for by Walmart.\n\nEligibility requirements apply to some benefits and may depend on your job classification and length of employment. Benefits are subject to change and may be subject to a specific plan or program terms. For information about benefits and eligibility, see One.Walmart at https://bit.ly/3iOOb1J .\n\nThe annual salary range for this position is $143,000.00-$286,000.00\n\nAdditional compensation includes annual or quarterly performance incentives.\n\nAdditional compensation for certain positions may also include:\n\n- Regional Pay Zone (RPZ) (based on location)\n\n- Stock equity incentives\n\nMinimum Qualifications...\n\nOutlined below are the required minimum qualifications for this position. If none are listed, there are no minimum qualifications.\n\nOption 1: Bachelors degree in Statistics, Economics, Analytics, Mathematics, Computer Science, Information Technology or related field and 4 years' experience in an analytics related field. Option 2: Masters degree in Statistics, Economics, Analytics, Mathematics, Computer Science, Information Technology or related field and 2 years' experience in an analytics related field. Option 3: 6 years' experience in an analytics or related field\n\nPreferred Qualifications...\n\nOutlined below are the optional preferred qualifications for this position. If none are listed, there are no preferred qualifications.\n\nData science, machine learning, optimization models, PhD in Machine Learning, Computer Science, Information Technology, Operations Research, Statistics, Applied Mathematics, Econometrics, Successful completion of one or more assessments in Python, Spark, Scala, or R, Using open source frameworks (for example, scikit learn, tensorflow, torch)\n\nPrimary Location...\n\n640 W California Avenue, Sunnyvale, CA 94086-4828, United States of America\n\nAbout Walmart\n\nAt Walmart, we help people save money so they can live better. This mission serves as the foundation for every decision we make, from responsible sourcing to sustainability-and everything in between. As a Walmart associate, you will play an integral role in shaping the future of retail, tech, merchandising, finance and hundreds of other industries-all while affecting the lives of millions of customers all over the world. Here, your work makes an impact every day. What are you waiting for?\n\nWalmart, Inc. is an Equal Opportunity Employer- By Choice. We believe we are best equipped to help our associates, customers, and the communities we serve live better when we really know them. That means understanding, respecting, and valuing diversity- unique styles, experiences, identities, abilities, ideas and opinions- while being inclusive of all people.\n\n\"At Walmart, we get the opportunity to grow professionally and personally-all while improving how we work and what we deliver to consumers.\" - Lola, Project Analyst\n\nHello, Silicon Valley\n\nYou don't have to choose between your career and your lifestyle in Silicon Valley. Here, you can have both.", "job_is_remote": false, "job_posted_at_timestamp": 1709878779, "job_posted_at_datetime_utc": "2024-03-08T06:19:39.000Z", "job_city": "Sunnyvale", "job_state": "CA", "job_country": "US", "job_latitude": 37.36883, "job_longitude": -122.03635, "job_benefits": ["dental_coverage", "retirement_savings", "paid_time_off", "health_insurance"], "job_google_link": "https://www.google.com/search?gl=us&hl=en&rciv=jb&q=mlops+expert&start=40&ibp=htl;jobs#fpstate=tldetail&htivrt=jobs&htiq=mlops+expert&htidocid=bkJpRsxKp7uougP5AAAAAA%3D%3D", "job_offer_expiration_datetime_utc": "2024-04-07T23:59:59.000Z", "job_offer_expiration_timestamp": 1712534399, "job_required_experience": {"no_experience_required": false, "required_experience_in_months": 84, "experience_mentioned": true, "experience_preferred": false}, "job_required_skills": null, "job_required_education": {"postgraduate_degree": false, "professional_certification": false, "high_school": false, "associates_degree": false, "bachelors_degree": false, "degree_mentioned": true, "degree_preferred": true, "professional_certification_mentioned": false}, "job_experience_in_place_of_education": false, "job_min_salary": null, "job_max_salary": null, "job_salary_currency": null, "job_salary_period": null, "job_highlights": {"Qualifications": ["7+ years machine learning experience, PhD or MA/MS in related Computer Science,", "Computer Engineering or equivalent, OR 5+ years industry experience", "Experience leading projects with industry-wide impact", "Significant experience in one or more of the following areas: machine learning, deep", "learning, computer vision", "Significant experience with advanced data pipeline, preferable with video or images", "Significant experience in programming languages with a technical background", "You are a team player - that is, you're a nice person - see no ego", "Highly motivated and independent; good at prioritization and results oriented", "A self-learner: ability to effectively adapt to rapidly changing technology and apply it", "to business needs, integrate multiple tools together to solve business problems", "Proficient in scripting and automation with an emphasis on integration", "Experience in shipping computer vision products to thousands of customers or have", "Experience with complex image or video analytic pipelines", "Expertise in machine learning development life cycle", "Experience in some of the following fields: computer vision (object detection,", "tracking, scene understanding), machine learning", "Option 1: Bachelors degree in Statistics, Economics, Analytics, Mathematics, Computer Science, Information Technology or related field and 4 years' experience in an analytics related field", "Option 3: 6 years' experience in an analytics or related field", "Data science, machine learning, optimization models, PhD in Machine Learning, Computer Science, Information Technology, Operations Research, Statistics, Applied Mathematics, Econometrics, Successful completion of one or more assessments in Python, Spark, Scala, or R, Using open source frameworks (for example, scikit learn, tensorflow, torch)"], "Responsibilities": ["working on future-looking initiatives that are targeted at improving in-store customer", "to create step change in-store experiences, leveraging emerging technology to help define", "and deliver evolving customer expectations", "As an MLOps Data Scientist, you will be a key player in developing and maintaining our", "machine learning infrastructure and data platform ensuring the smooth integration of", "Computer Vision data scientists, software engineers, and DevOps teams to optimize the end-", "to-end machine learning lifecycle", "From implementing model performance improvement", "strategies to troubleshooting issues in machine learning pipelines, your contributions will be", "crucial to the efficiency and reliability of our ML operations", "You'll make an impact by..", "Deploying and monitoring machine learning models for production environments", "Building CV data pipelines, ensuring that data is easily accessible, updatable,", "reusable", "Develop strategies to optimize the annotation process, minimizing the need for", "labeling large amounts of data", "Enhance model performance by selecting the most informative data for annotation", "Providing expertise and guidance on all technical aspects of development, including", "requirements, design, and implementation", "Ensuring engineering and computer vision best practices, so that the team follows a", "structured and efficient approach to their projects", "Build a scalable and extensive ML data platform that can support multiple forms of", "data and support the scalability of computer vision models", "Build curated data sets with auto ML and active learning capabilities", "Innovate with feedback loops and human-in-the-loop processes to continuously refine", "our systems to better meet product needs", "Develop and implement robust model drift monitoring capabilities to ensure the", "continued accuracy of deployed models", "Collaborate with data scientists and data engineers to address drift-related", "Implement and manage ML Ops practices to streamline the machine learning", "development lifecycle", "Provide mentorship to more junior members of the team", "Stay ahead of the curve by keeping abreast of the latest technological"], "Benefits": ["Benefits: Beyond our great compensation package, you can receive incentive awards for your performance", "Other great perks include 401(k) match, stock purchase plan, paid maternity and parental leave, PTO, multiple health plans, and much more", "At Walmart, we offer competitive pay as well as performance-based incentive awards and other great benefits for a happier mind, body, and wallet", "Health benefits include medical, vision and dental coverage", "Financial benefits include 401(k), stock purchase and company-paid life insurance", "Paid time off benefits include PTO (including sick leave), parental leave, family care leave, bereavement, jury duty, and voting", "Other benefits include short-term and long-term disability, company discounts, Military Leave Pay, adoption and surrogacy expense reimbursement, and more", "You will also receive PTO and/or PPTO that can be used for vacation, sick leave, holidays, or other purposes", "It will meet or exceed the requirements of paid sick leave laws, where applicable", "Tuition, books, and fees are completely paid for by Walmart", "The annual salary range for this position is $143,000.00-$286,000.00", "Additional compensation includes annual or quarterly performance incentives", "Additional compensation for certain positions may also include:", "Regional Pay Zone (RPZ) (based on location)", "Stock equity incentives"]}, "job_job_title": "Staff", "job_posting_language": "en", "job_onet_soc": "15111100", "job_onet_job_zone": "5", "job_naics_code": "452990", "job_naics_name": "All Other General Merchandise Stores"}