{"job_id": "kxHw0IuXUGxUnNerAAAAAA==", "employer_name": "WorkSpark", "employer_logo": null, "employer_website": null, "employer_company_type": null, "job_publisher": "Glassdoor", "job_employment_type": "FULLTIME", "job_title": "Senior Sales Executive - Enterprise Solutions", "job_apply_link": "https://www.glassdoor.com/job-listing/senior-sales-executive-enterprise-solutions-workspark-JV_KO0,43_KE44,53.htm?jl=1009100650267", "job_apply_is_direct": true, "job_apply_quality_score": 0.6586, "apply_options": [{"publisher": "Glassdoor", "apply_link": "https://www.glassdoor.com/job-listing/senior-sales-executive-enterprise-solutions-workspark-JV_KO0,43_KE44,53.htm?jl=1009100650267", "is_direct": true}, {"publisher": "Indeed", "apply_link": "https://www.indeed.com/viewjob?jk=5979d1430c13fb7d", "is_direct": true}, {"publisher": "LazyApply", "apply_link": "https://lazyapply.com/jobpreview/job_eeb2ecd6135027bc", "is_direct": true}], "job_description": "Company: Workspark (www.myworkspark.com)\n\nWorkSpark provides tailored remote administrative and sales assistant services to businesses across various industries. Our dedicated team members handle tasks such as scheduling, customer support, data management, social media, and more \u2014 allowing our clients to focus on growth and core business activities. With a commitment to efficiency and flexibility, we empower businesses to achieve their goals while reducing operational burdens and day-to-day tasks.\n\nAbout WorkSpark:\n\nWorkSpark\u2019s culture is rooted in our core values, which promote an collaborative and inclusive environment where varied perspectives and new ideas are encouraged and celebrated. We are committed to innovation, trustworthiness, working hard, giving back, and being authentic. At WorkSpark, we believe in doing good in the world. Ask us about our non-profit support!\n\nJob Description:\n\nWorkspark is seeking a seasoned Senior Sales Executive with a strong background in B2B sales and a proven track record of success. The ideal candidate possesses an existing network of contacts within companies having 50 or more employees and has experience dealing directly with key decision-makers. This role demands a strategic thinker with excellent communication skills, capable of nurturing meaningful relationships with business leaders to drive sales and foster growth. This is a remote, work from home position.\n\nResponsibilities:\n\u2022 Business Development: Leverage your existing network to introduce Workspark\u2019s solutions to new prospects in the enterprise sector. Develop and implement strategic sales plans to achieve corporate objectives.\n\u2022 Client Management: Build and maintain strong, long-lasting customer relationships. Understand client needs and offer solutions and support that meet their individual business requirements.\n\u2022 Market Analysis: Conduct research to identify emerging market trends, customer needs, and the competitive landscape. Use insights to tailor and innovate sales strategies.\n\u2022 Sales Targets: Achieve growth and hit sales targets by successfully managing your sales pipeline. Prepare sales reports and forecasts for the management team, providing insights into your sales strategies and their effectiveness.\n\u2022 Collaboration: Work closely with the marketing, product, and customer service teams to ensure a cohesive and integrated approach to sales and customer satisfaction.\n\u2022 Lead Source Management: Take charge of managing and analyzing lead sources in our CRM system. Your expertise will ensure that every lead is accurately tracked and categorized, providing a clear view of our sales funnel.\n\nRequirements:\n\u2022 Proven B2B Experience: At least 5 years of experience in B2B sales, particularly in selling to medium to large-sized businesses (50+ employees). A solid track record of meeting or exceeding sales quotas.\n\u2022 Software: Prior experience with CRMs and the existing ability to network via Linkedin\n\u2022 Strong Network: Access to a substantial network of professionals within medium to large-sized organizations. Demonstrated ability to communicate, present, and influence credibly and effectively at all levels of the organization.\n\u2022 Strategic Thinking: Strong business sense and industry expertise. Ability to think strategically and to lead strong sales processes.\n\u2022 Communication Skills: Excellent mentoring, coaching, and people management skills. Outstanding communication and interpersonal abilities.\n\u2022 Educational Background: Bachelor\u2019s degree in Business Administration, Sales, or a relevant field.\n\nCompensation:\n\u2022 A competitive base salary of $70,000 plus a performance-based commission structure.\n\nHow to Apply:\n\nPlease submit your resume, cover letter, and any relevant sales performance records. We look forward to exploring how your expertise aligns with the needs of our team at Workspark.\n\nWorkspark is an equal opportunity employer. We celebrate diversity and are committed to creating an inclusive environment for all employees.\n\nJob Type: Full-time\n\nPay: $70,000.00 - $110,000.00 per year\n\nBenefits:\n\u2022 Dental insurance\n\u2022 Flexible schedule\n\u2022 Health insurance\n\u2022 Paid time off\n\u2022 Work from home\n\nCompensation package:\n\u2022 Uncapped commission\n\nSchedule:\n\u2022 8 hour shift\n\u2022 Monday to Friday\n\nTravel requirement:\n\u2022 No travel\n\nApplication Question(s):\n\u2022 Do you have an existing B2B Network?\n\u2022 Describe what industries your B2B network consists of.\n\nExperience:\n\u2022 B2B sales: 3 years (Required)\n\nWork Location: Remote", "job_is_remote": true, "job_posted_at_timestamp": 1709164800, "job_posted_at_datetime_utc": "2024-02-29T00:00:00.000Z", "job_city": null, "job_state": null, "job_country": "US", "job_latitude": 37.09024, "job_longitude": -95.71289, "job_benefits": ["paid_time_off", "dental_coverage", "health_insurance"], "job_google_link": "https://www.google.com/search?gl=us&hl=en&rciv=jb&q=senior+sales+manager&start=60&ibp=htl;jobs#fpstate=tldetail&htivrt=jobs&htiq=senior+sales+manager&htidocid=kxHw0IuXUGxUnNerAAAAAA%3D%3D", "job_offer_expiration_datetime_utc": "2024-07-05T00:00:00.000Z", "job_offer_expiration_timestamp": 1720137600, "job_required_experience": {"no_experience_required": false, "required_experience_in_months": 60, "experience_mentioned": true, "experience_preferred": false}, "job_required_skills": null, "job_required_education": {"postgraduate_degree": false, "professional_certification": false, "high_school": false, "associates_degree": false, "bachelors_degree": false, "degree_mentioned": true, "degree_preferred": true, "professional_certification_mentioned": false}, "job_experience_in_place_of_education": false, "job_min_salary": 70000, "job_max_salary": 110000, "job_salary_currency": "USD", "job_salary_period": "YEAR", "job_highlights": {"Qualifications": ["Proven B2B Experience: At least 5 years of experience in B2B sales, particularly in selling to medium to large-sized businesses (50+ employees)", "A solid track record of meeting or exceeding sales quotas", "Software: Prior experience with CRMs and the existing ability to network via Linkedin", "Strong Network: Access to a substantial network of professionals within medium to large-sized organizations", "Demonstrated ability to communicate, present, and influence credibly and effectively at all levels of the organization", "Strategic Thinking: Strong business sense and industry expertise", "Ability to think strategically and to lead strong sales processes", "Communication Skills: Excellent mentoring, coaching, and people management skills", "Outstanding communication and interpersonal abilities", "Educational Background: Bachelor\u2019s degree in Business Administration, Sales, or a relevant field", "No travel", "B2B sales: 3 years (Required)"], "Responsibilities": ["Our dedicated team members handle tasks such as scheduling, customer support, data management, social media, and more \u2014 allowing our clients to focus on growth and core business activities", "Business Development: Leverage your existing network to introduce Workspark\u2019s solutions to new prospects in the enterprise sector", "Develop and implement strategic sales plans to achieve corporate objectives", "Client Management: Build and maintain strong, long-lasting customer relationships", "Understand client needs and offer solutions and support that meet their individual business requirements", "Market Analysis: Conduct research to identify emerging market trends, customer needs, and the competitive landscape", "Use insights to tailor and innovate sales strategies", "Sales Targets: Achieve growth and hit sales targets by successfully managing your sales pipeline", "Prepare sales reports and forecasts for the management team, providing insights into your sales strategies and their effectiveness", "Collaboration: Work closely with the marketing, product, and customer service teams to ensure a cohesive and integrated approach to sales and customer satisfaction", "Lead Source Management: Take charge of managing and analyzing lead sources in our CRM system", "Your expertise will ensure that every lead is accurately tracked and categorized, providing a clear view of our sales funnel"], "Benefits": ["A competitive base salary of $70,000 plus a performance-based commission structure", "Pay: $70,000.00 - $110,000.00 per year", "Dental insurance", "Flexible schedule", "Health insurance", "Paid time off", "Work from home", "Compensation package:", "Uncapped commission", "8 hour shift", "Monday to Friday"]}, "job_job_title": "Sales executive", "job_posting_language": "en", "job_onet_soc": "41401200", "job_onet_job_zone": "4"}