{"job_id": "jVMjwN1FCKZnhBjfAAAAAA==", "employer_name": "Simpson Housing LP", "employer_logo": "https://media.licdn.com/dms/image/C560BAQEKSaV439ZNRw/company-logo_200_200/0/1630672438803/simpson_housing_logo?e=2147483647&v=beta&t=S72RcheK4d-wylr1TwnlV2Ch1vlqnu5WASiUChC5SkM", "employer_website": "http://www.simpsonhousing.com", "employer_company_type": "Real Estate", "job_publisher": "Adzuna", "job_employment_type": "FULLTIME", "job_title": "Marketing Analytics Manager", "job_apply_link": "https://www.adzuna.com/details/4580948165", "job_apply_is_direct": false, "job_apply_quality_score": 0.5206, "apply_options": [{"publisher": "Adzuna", "apply_link": "https://www.adzuna.com/details/4580948165", "is_direct": false}], "job_description": "Overview\n\nSimpson Housing is a large, fully-integrated real estate company with an enthusiastic entrepreneurial spirit. For 75 years, we have acquired, developed, built, and managed luxury apartment communities in highly desirable locations throughout the United States. We are driven by our Mission and Core Values and believe that our most valuable asset is our team.\n\nSimpson Housing is committed to be a trusted leader in the multifamily industry. Our mission is to provide an exceptional employee experience, award-winning customer service, long-term value to our investors, and enhance our local communities.\n\nResponsibilities\n\nMarketing Analytics Manager - Simpson Housing Regional Office located in the Dunwoody neighborhood near Perimeter Mall - Atlanta, GA\n\nAs a key member of our marketing team, you will be responsible for:\n\u2022 Conducting comprehensive market research to identify strategies and support underwriting for all of Simpson Housing's new development, acquisition, and redevelopment activity.\n\u2022 Analyzing market, pipeline, demographics, locations, and consumer behavior to identify market strategies.\n\u2022 Maintaining and distributing a comprehensive database of relevant market news and data.\n\u2022 Managing and using a variety of research techniques to identify target markets/ strategies from traveling and touring competitors, phone and in-person conversation, Internet research, use of Power BI tools and various industry data and analytic resources.\n\u2022 Ability to suggest product and programming for target properties.\n\u2022 Preparing and analyzing rent roll and operating statements for subject property and its competitors.\n\u2022 Underwriting rents, operational and capital expenses.\n\u2022 Researching and document new products to enhance Simpson communities and improve marketing effectiveness.\n\u2022 Reporting and recommending products to various Simpson Stakeholders.\n\u2022 Developing and tracking product testing and roll-outs.\n\u2022 Evaluating the performance of marketing campaigns across various channels to assess effectiveness and ROI.\n\u2022 Providing insights into campaign optimization and recommending adjustments as needed.\n\u2022 Unit and floor plan set-up coloration for all new properties added to portfolio.\n\nQualifications\n\u2022 Bachelor's degree in Marketing, Analytics, Business or related fields.\n\u2022 Requires 5-7 years of marketing and/or analytics. Proven experience as a Marketing Analyst.\n\u2022 Strong analytical mindset.\n\u2022 Proficient in data analytical tools.\n\u2022 Advanced Excel skills required.\n\u2022 Knowledge of marketing principles, trends, and best practices.\n\u2022 Excellent communication and presentation skills.\n\u2022 Very strong attention to detail specifically spelling and grammar.\n\u2022 Ability to interact and collaborate with all levels of the organization including on-site team members.\n\nWhat Simpson Can Offer You:\n\nAs an industry leader, we understand what it takes to be successful in today's competitive marketplace. Just as you're unique in your skills, experience, and personality, each of our jobs has a curated set of benefits specific to the position.\n\nSimpson is proud to offer you:\n\u2022 Substantial discount on rent (certain restrictions apply)\n\u2022 Highly competitive compensation\n\u2022 Discretionary bonus potential\n\u2022 Health, dental, and vision insurance\n\u2022 Flexible spending accounts\n\u2022 Life and AD&D insurance\n\u2022 Disability insurance\n\u2022 401(k) plan with company match\n\u2022 Generous paid time off (PTO) program (FT and PT employees)\n\u2022 Additional paid days off: 8 holidays, 2 floating holidays, and 2 designated wellness days\n\u2022 Education reimbursement\n\nWhy work for Simpson? You might want to ask one of our employees that question. Our business is focused on community and improving the lives of those around us. We aim to deliver happiness while managing our communities and residents, engaging in our local communities, and creating a rewarding experience for our employees. Our supportive community of team members are welcoming and celebrate each other's differences. Their commitment to service continues to strengthen the Simpson name.\n\nIf this sounds like the type of company that you would like to work for, we would like to hear from you. Find out where your talents can take you by applying today!\n\nPay Range: $85,000 - $95,000 per year\n\nThis pay range is approximate and the actual pay received may vary dependent upon certain factors such as related job experience, education, training, professional/industry certifications, etc. Please note this pay range does not include any additional compensation this position may be eligible for as listed above, such as commissions or bonuses.\n\nTo perform this job successfully, an individual must be able to perform each essential duty satisfactorily. The requirements listed are representative of the knowledge, skills and abilities required. Reasonable accommodations may be made to enable individuals with disabilities to perform the essential functions.\n\nApplications are accepted on an ongoing basis.\n\nSimpson Housing is an Equal Opportunity Employer\n\nJob type: Full-time\n\nSchedule: Monday to Friday, Day shift\n\nKeyword Search:\n\nReal Estate, Multifamily, Apartments, Marketing, Analytics\n\nLocation : City\n\nAtlanta\n\nLocation : State/Province\n\nGA", "job_is_remote": false, "job_posted_at_timestamp": 1708542000, "job_posted_at_datetime_utc": "2024-02-21T19:00:00.000Z", "job_city": "Hapeville", "job_state": "GA", "job_country": "US", "job_latitude": 33.66011, "job_longitude": -84.4102, "job_benefits": ["health_insurance", "dental_coverage", "retirement_savings", "paid_time_off"], "job_google_link": "https://www.google.com/search?gl=us&hl=en&rciv=jb&q=marketing+analytics+manager&start=0&ibp=htl;jobs#fpstate=tldetail&htivrt=jobs&htiq=marketing+analytics+manager&htidocid=jVMjwN1FCKZnhBjfAAAAAA%3D%3D", "job_offer_expiration_datetime_utc": "2024-03-26T17:02:17.000Z", "job_offer_expiration_timestamp": 1711472537, "job_required_experience": {"no_experience_required": false, "required_experience_in_months": 60, "experience_mentioned": true, "experience_preferred": false}, "job_required_skills": null, "job_required_education": {"postgraduate_degree": false, "professional_certification": false, "high_school": false, "associates_degree": false, "bachelors_degree": false, "degree_mentioned": true, "degree_preferred": true, "professional_certification_mentioned": true}, "job_experience_in_place_of_education": false, "job_min_salary": null, "job_max_salary": null, "job_salary_currency": null, "job_salary_period": null, "job_highlights": {"Qualifications": ["Bachelor's degree in Marketing, Analytics, Business or related fields", "Requires 5-7 years of marketing and/or analytics", "Proven experience as a Marketing Analyst", "Strong analytical mindset", "Proficient in data analytical tools", "Advanced Excel skills required", "Knowledge of marketing principles, trends, and best practices", "Excellent communication and presentation skills", "Very strong attention to detail specifically spelling and grammar", "Ability to interact and collaborate with all levels of the organization including on-site team members", "As an industry leader, we understand what it takes to be successful in today's competitive marketplace"], "Responsibilities": ["Conducting comprehensive market research to identify strategies and support underwriting for all of Simpson Housing's new development, acquisition, and redevelopment activity", "Analyzing market, pipeline, demographics, locations, and consumer behavior to identify market strategies", "Maintaining and distributing a comprehensive database of relevant market news and data", "Managing and using a variety of research techniques to identify target markets/ strategies from traveling and touring competitors, phone and in-person conversation, Internet research, use of Power BI tools and various industry data and analytic resources", "Ability to suggest product and programming for target properties", "Preparing and analyzing rent roll and operating statements for subject property and its competitors", "Underwriting rents, operational and capital expenses", "Researching and document new products to enhance Simpson communities and improve marketing effectiveness", "Reporting and recommending products to various Simpson Stakeholders", "Developing and tracking product testing and roll-outs", "Evaluating the performance of marketing campaigns across various channels to assess effectiveness and ROI", "Providing insights into campaign optimization and recommending adjustments as needed", "Unit and floor plan set-up coloration for all new properties added to portfolio"], "Benefits": ["Substantial discount on rent (certain restrictions apply)", "Highly competitive compensation", "Discretionary bonus potential", "Health, dental, and vision insurance", "Flexible spending accounts", "Life and AD&D insurance", "Disability insurance", "401(k) plan with company match", "Generous paid time off (PTO) program (FT and PT employees)", "Additional paid days off: 8 holidays, 2 floating holidays, and 2 designated wellness days", "Education reimbursement", "Pay Range: $85,000 - $95,000 per year", "This pay range is approximate and the actual pay received may vary dependent upon certain factors such as related job experience, education, training, professional/industry certifications, etc"]}, "job_job_title": "Analytics manager", "job_posting_language": "en", "job_onet_soc": "11202100", "job_onet_job_zone": "4", "job_naics_code": "5311", "job_naics_name": "Lessors of Real Estate"}