{"job_id": "QHoHQcYtdOKHDOmnAAAAAA==", "employer_name": "LivePerson", "employer_logo": "https://d1hryyr5hiabsc.cloudfront.net/web2020/img/header/logo.svg", "employer_website": "http://www.liveperson.com", "employer_company_type": "Information", "job_publisher": "Built In", "job_employment_type": "FULLTIME", "job_title": "Senior Sales Incentive Compensation Manager", "job_apply_link": "https://builtin.com/job/senior-sales-incentive-compensation-manager/2379827", "job_apply_is_direct": false, "job_apply_quality_score": 0.6831, "apply_options": [{"publisher": "Built In", "apply_link": "https://builtin.com/job/senior-sales-incentive-compensation-manager/2379827", "is_direct": false}, {"publisher": "LinkedIn", "apply_link": "https://www.linkedin.com/jobs/view/senior-sales-incentive-compensation-manager-at-liveperson-3856719386", "is_direct": false}], "job_description": "LivePerson (NASDAQ: LPSN) is a global leader in trustworthy and equal AI for business. Hundreds of the world's leading brands \u2014 including HSBC, Chipotle, and Virgin Media \u2014 use our Conversational Cloud platform to engage with millions of consumers safely and responsibly. We power a billion conversational interactions every month, providing a uniquely rich data set and safety tools to unlock the power of Generative AI and Large Language Models for better business outcomes.\n\nAt LivePerson, we foster an inclusive workplace culture that encourages meaningful connection, collaboration, and innovation. Every mind is invited to ask questions and actively seek new ways to achieve success and reach their full potential. We operate as one with a growth mindset. This means spotting opportunities, solving ambiguities, and seeking effective solutions to challenges that make things better.\n\nOverview:\n\nThe Sales Incentive Compensation Manager is responsible for the delivery and administration of LivePerson\u2019 global sales incentive compensation program. This role reports into the Director, Global Financial Planning and Analysis and will partner closely with the Revenue Operations team to ensure effective and scalable compensation plan designs across the LivePerson\u2019 commercial organization. This role is also accountable for reporting plan effectiveness and forecasting of incentive compensation expenses globally and managing the SPIFF application.\n\nResponsibilities include:\n\u2022 Lead the creation and articulation of a compensation philosophy that aligns with LivePerson\u2019 values and mission.\n\u2022 Manage all incentive compensation calculations and payouts globally.\n\u2022 Act as the liaison across different functional groups including Corporate Compensation, HR, Legal, Field Operations, Sales, Customer Success and Finance leadership.\n\u2022 Ownership of all business processes related to plan delivery and administration to include ownership of the SPIFF application. Manage the SPIFF relationship.\n\u2022 Configure Incentive compensation plans in SPIFF. Rollout plans to plan participants. Monitor plan performance and coordinate payments with Commercial Leadership, Finance and HR.\n\u2022 Work closely with Field Operations, IT and the CRM Application Manager to upgrade to SPIFF.\n\u2022 Create plan documents and communicate plan details to employees via SPIFF.\n\u2022 Implement and maintain rigorous audit process to ensure data integrity.\n\u2022 Create & manage sales contests and SPIF\u2019s with the assistance of the Field Operations team and CRM Application manager.\n\u2022 Maintain policies, procedures and controls for incentive compensation plans.\n\u2022 Build incentive compensation dashboards and reports in SPIFF, providing Sales leadership real-time visibility into plan performance and effectiveness. Partner with regional Vice Presidents, establish monthly meeting rhythm with Sales Leadership to review plan performance.\n\u2022 Work with Revenue Operations and Finance leadership to develop quarterly forecasts and annual budgets on incentive compensation expenses.\n\u2022 Mid-term (12-24 months): Build/Develop a team of highly efficient incentive analysts responsible for supporting LivePerson\u2019 growing commercial organization.\n\nRequirements\n\u2022 5+ years of incentive compensation experience.\n\u2022 Experience managing SPIFF\u2019 s sales incentive platform a plus.\n\u2022 Xactly Configuration and Reporting Certification Levels 1-3 preferred. This will translate into management of the SPIFF application.\n\u2022 Demonstrated knowledge of best practices in incentive compensation \u2013 plan delivery, process management, and administration.\n\u2022 Knowledge of industry benchmarks in plan creation and compensation benchmarks.\n\u2022 Ability to build relationships and to influence and collaborate across departments in order to achieve objectives.\n\u2022 Possess a high level of integrity. Be widely trusted, direct and truthful, with the ability to establish and maintain effective relationships and gain confidence.\n\u2022 Solutions and client service-oriented, with an emphasis on problem solving.\n\u2022 Proven organizational skills with attention to detail and the ability to prioritize and work well in an environment with competing demands.\n\u2022 A data-driven mindset and strong demonstrated analytical and problem-solving skills \u2013 ability to influence, drive decisions and lead discussions utilizing data.\n\u2022 Willingness to travel quarterly to Portugal (or other locations) to meet with the Field Operations team and key stakeholders. Attend the Global Sales Kick-off.\n\nEducation:\n\u2022 Bachelor\u2019s degree required or the equivalent in experience. Business administration, finance, economics, or other quantitative focus preferred.\n\u2022 MBA a plus.\n\nBenefits:\n\nThe salary range for this role will be between $120,000 to $150,000 USD. Final compensation will be determined by a variety of factors, including, but not limited to your location, skills, experience, education, and/or professional certifications. During the phone screening, your recruiter will provide the location-specific salary range for this role. Regardless of your personal situation or where you are in the world, LivePerson offers comprehensive and great benefits programs to meet your needs:\n\u2022 Health: Health: medical, dental, and vision insurance and wellbeing resources and programs\n\u2022 Time away: generous time away programs that cover vacation, dependent care, holidays, wellness days, and more.\n\u2022 Financial: 401K, ESPP, Basic life and AD&D insurance, long-term and short-term disability\n\u2022 Family: parental leave, maternity support, fertility services\n\u2022 Development: Generous tuition reimbursement and access to internal professional development resources.\n\u2022 Additional: 24/7 access to professional counselors, voluntary insurance coverage, exclusive perks and discounts\n\nWhy you\u2019ll love working here:\n\nYour entrepreneurial spirit will be supported. We love team members who chase down their big ideas, become experts, help colleagues, and own their work. These four company values guide our continued, holistic growth as individuals, as teams, and as a global organization. And to further make our point, let's just say we're very proud to be on Fast Company's list of Most Innovative Companies and Newsweek's list of most-loved workplaces.\n\nBelonging at LivePerson\n\nAt LivePerson, people from diverse backgrounds come together to make an impact and be their authentic selves. One way we share and connect is through our employee resource groups such as: Live In Color, LP Proud, and Women In Tech. We are proud to be an equal opportunity employer. All qualified applicants will receive consideration for employment without regard to age, ancestry, color, family or medical care leave, gender identity or expression, genetic information, marital status, medical condition, national origin, physical or mental disability, protected veteran status, race, religion, sex (including pregnancy), sexual orientation, or any other characteristic protected by applicable laws, regulations and ordinances. We also consider qualified applicants with criminal histories, consistent with applicable federal, state, and local law.\n\nWe are committed to the accessibility needs of applicants and employees. We provide reasonable accommodations to job applicants with physical or mental disabilities. Applicants with a disability who require a reasonable accommodation for any part of the application or hiring process should inform their recruiting contact upon initial connection.\n\n#LI-Remote", "job_is_remote": true, "job_posted_at_timestamp": 1710358080, "job_posted_at_datetime_utc": "2024-03-13T19:28:00.000Z", "job_city": null, "job_state": null, "job_country": "US", "job_latitude": 37.09024, "job_longitude": -95.71289, "job_benefits": ["dental_coverage", "paid_time_off", "health_insurance", "retirement_savings"], "job_google_link": "https://www.google.com/search?gl=us&hl=en&rciv=jb&q=senior+sales+manager&start=60&ibp=htl;jobs#fpstate=tldetail&htivrt=jobs&htiq=senior+sales+manager&htidocid=QHoHQcYtdOKHDOmnAAAAAA%3D%3D", "job_offer_expiration_datetime_utc": "2024-04-12T00:00:00.000Z", "job_offer_expiration_timestamp": 1712880000, "job_required_experience": {"no_experience_required": false, "required_experience_in_months": 60, "experience_mentioned": true, "experience_preferred": true}, "job_required_skills": null, "job_required_education": {"postgraduate_degree": false, "professional_certification": false, "high_school": false, "associates_degree": false, "bachelors_degree": true, "degree_mentioned": true, "degree_preferred": false, "professional_certification_mentioned": true}, "job_experience_in_place_of_education": false, "job_min_salary": 120000, "job_max_salary": 150000, "job_salary_currency": "USD", "job_salary_period": "YEAR", "job_highlights": {"Qualifications": ["5+ years of incentive compensation experience", "Knowledge of industry benchmarks in plan creation and compensation benchmarks", "Possess a high level of integrity", "Be widely trusted, direct and truthful, with the ability to establish and maintain effective relationships and gain confidence", "Solutions and client service-oriented, with an emphasis on problem solving", "Proven organizational skills with attention to detail and the ability to prioritize and work well in an environment with competing demands", "A data-driven mindset and strong demonstrated analytical and problem-solving skills \u2013 ability to influence, drive decisions and lead discussions utilizing data", "Bachelor\u2019s degree required or the equivalent in experience"], "Responsibilities": ["The Sales Incentive Compensation Manager is responsible for the delivery and administration of LivePerson\u2019 global sales incentive compensation program", "This role reports into the Director, Global Financial Planning and Analysis and will partner closely with the Revenue Operations team to ensure effective and scalable compensation plan designs across the LivePerson\u2019 commercial organization", "This role is also accountable for reporting plan effectiveness and forecasting of incentive compensation expenses globally and managing the SPIFF application", "Lead the creation and articulation of a compensation philosophy that aligns with LivePerson\u2019 values and mission", "Manage all incentive compensation calculations and payouts globally", "Act as the liaison across different functional groups including Corporate Compensation, HR, Legal, Field Operations, Sales, Customer Success and Finance leadership", "Ownership of all business processes related to plan delivery and administration to include ownership of the SPIFF application", "Manage the SPIFF relationship", "Rollout plans to plan participants", "Monitor plan performance and coordinate payments with Commercial Leadership, Finance and HR", "Work closely with Field Operations, IT and the CRM Application Manager to upgrade to SPIFF", "Create plan documents and communicate plan details to employees via SPIFF", "Implement and maintain rigorous audit process to ensure data integrity", "Create & manage sales contests and SPIF\u2019s with the assistance of the Field Operations team and CRM Application manager", "Maintain policies, procedures and controls for incentive compensation plans", "Build incentive compensation dashboards and reports in SPIFF, providing Sales leadership real-time visibility into plan performance and effectiveness", "Partner with regional Vice Presidents, establish monthly meeting rhythm with Sales Leadership to review plan performance", "Work with Revenue Operations and Finance leadership to develop quarterly forecasts and annual budgets on incentive compensation expenses", "Mid-term (12-24 months): Build/Develop a team of highly efficient incentive analysts responsible for supporting LivePerson\u2019 growing commercial organization", "This will translate into management of the SPIFF application", "Willingness to travel quarterly to Portugal (or other locations) to meet with the Field Operations team and key stakeholders"], "Benefits": ["The salary range for this role will be between $120,000 to $150,000 USD", "Final compensation will be determined by a variety of factors, including, but not limited to your location, skills, experience, education, and/or professional certifications", "During the phone screening, your recruiter will provide the location-specific salary range for this role", "Regardless of your personal situation or where you are in the world, LivePerson offers comprehensive and great benefits programs to meet your needs:", "Health: Health: medical, dental, and vision insurance and wellbeing resources and programs", "Time away: generous time away programs that cover vacation, dependent care, holidays, wellness days, and more", "Financial: 401K, ESPP, Basic life and AD&D insurance, long-term and short-term disability", "Family: parental leave, maternity support, fertility services", "Development: Generous tuition reimbursement and access to internal professional development resources", "Additional: 24/7 access to professional counselors, voluntary insurance coverage, exclusive perks and discounts"]}, "job_job_title": "Manager", "job_posting_language": "en", "job_onet_soc": "11311100", "job_onet_job_zone": "4", "job_naics_code": "511210", "job_naics_name": "Software Publishers"}