{"job_id": "dYjX6JIdrcAXOZCNAAAAAA==", "job_title": "Sr. Machine Learning Engineer (Full Stack Developer)", "employer_name": "Newscape Consulting LLP", "employer_logo": null, "employer_website": "http://www.newscapeconsulting.com/", "job_publisher": "Indeed", "job_employment_type": "Full-time and Contractor", "job_employment_types": ["FULLTIME", "CONTRACTOR", "CONTRACTOR"], "job_apply_link": "https://www.indeed.com/viewjob?jk=dcb3455d140b2e64&utm_campaign=google_jobs_apply&utm_source=google_jobs_apply&utm_medium=organic", "job_apply_is_direct": true, "apply_options": [{"publisher": "Indeed", "apply_link": "https://www.indeed.com/viewjob?jk=dcb3455d140b2e64&utm_campaign=google_jobs_apply&utm_source=google_jobs_apply&utm_medium=organic", "is_direct": true}], "job_description": "Sr. Machine Learning Engineer (Full Stack Developer)\n\nAbout the Role\n\nWe are seeking a Machine Learning Engineer with strong Python expertise and full-stack development capabilities to join our team. In this role, you will design, develop, and deploy scalable machine learning solutions while also contributing to the end-to-end application stack\u2014ranging from backend services to frontend interfaces. You will work cross-functionally with data scientists, software engineers, and product teams to build AI-driven applications that drive real business impact.\n\nKey Responsibilities\n\nMachine Learning & AI Development\n\u2022 Design, develop, and optimize machine learning models for predictive analytics, recommendation systems, NLP, or computer vision.\n\u2022 Implement, train, and fine-tune models using frameworks like TensorFlow, PyTorch, Scikit-learn, or Hugging Face.\n\u2022 Perform data preprocessing, feature engineering, and model evaluation to ensure high-performance ML systems.\n\u2022 Deploy and monitor ML models in production environments, ensuring scalability and reliability.\n\nFull-Stack Development\n\u2022 Develop and maintain backend services (APIs, microservices) using Python (FastAPI, Flask, Django).\n\u2022 Build scalable, responsive front-end interfaces using React, Vue.js, or Angular.\n\u2022 Integrate ML models into web and cloud-based applications with seamless user interactions.\n\u2022 Ensure security, performance, and maintainability of the full-stack architecture.\n\nDevOps & MLOps\n\u2022 Automate deployment pipelines with CI/CD tools (Docker, Kubernetes, GitHub Actions, Jenkins).\n\u2022 Implement MLOps best practices for model versioning, retraining, and monitoring.\n\u2022 Solid understanding for how to optimize cloud infrastructure on AWS, Azure, or GCP for ML workloads.\n\nCollaboration & Leadership\n\u2022 Work closely with data scientists, product managers, and software engineers to align ML solutions with business objectives.\n\u2022 Advocate for best practices in software engineering, ML model lifecycle management, and scalable architectures.\n\u2022 Contribute to code reviews, technical documentation, and knowledge-sharing initiatives.\n\nKey Qualifications\n\u2022 5+ years of hands-on experience in machine learning and full-stack development.\n\u2022 Strong Python programming skills with experience in data structures, algorithms, and object-oriented programming.\n\u2022 Proficiency in ML frameworks (TensorFlow, PyTorch, Scikit-learn) and data science libraries (Pandas, NumPy).\n\u2022 Experience building RESTful APIs, GraphQL services, or gRPC-based microservices.\n\u2022 Frontend experience with Angular, and state management (Redux, Vuex).\n\u2022 Strong knowledge of SQL & NoSQL databases (PostgreSQL, MongoDB, Redis).\n\u2022 Experience with Docker, Kubernetes, CI/CD pipelines, and cloud platforms (AWS/GCP/Azure).\n\u2022 Solid understanding of data pipelines, ETL workflows, and distributed computing.\n\u2022 Strong problem-solving skills and ability to optimize code for efficiency and scalability.\n\u2022 Experience with LLMs (Large Language Models), Generative AI, and NLP.\n\u2022 Familiarity with vector databases and embeddings (e.g., Pinecone, FAISS, Weaviate).\n\nBackground in computer vision, reinforcement learning, or time-series forecasting.\n\nJob Types: Full-time, Contract\n\nPay: $65,000.00 - $75,000.00 per year\n\nSchedule:\n\u2022 Monday to Friday\n\nWork Location: Remote", "job_is_remote": true, "job_posted_at": "11 days ago", "job_posted_at_timestamp": 1742774400, "job_posted_at_datetime_utc": "2025-03-24T00:00:00.000Z", "job_location": "United States", "job_city": null, "job_state": null, "job_country": "US", "job_latitude": 38.794595199999996, "job_longitude": -106.5348379, "job_benefits": null, "job_google_link": "https://www.google.com/search?q=jobs&gl=us&hl=en&udm=8#vhid=vt%3D20/docid%3DdYjX6JIdrcAXOZCNAAAAAA%3D%3D&vssid=jobs-detail-viewer", "job_min_salary": 65000, "job_max_salary": 75000, "job_salary_period": "YEAR", "job_highlights": {"Qualifications": ["DevOps & MLOps", "5+ years of hands-on experience in machine learning and full-stack development", "Strong Python programming skills with experience in data structures, algorithms, and object-oriented programming", "Proficiency in ML frameworks (TensorFlow, PyTorch, Scikit-learn) and data science libraries (Pandas, NumPy)", "Experience building RESTful APIs, GraphQL services, or gRPC-based microservices", "Frontend experience with Angular, and state management (Redux, Vuex)", "Strong knowledge of SQL & NoSQL databases (PostgreSQL, MongoDB, Redis)", "Experience with Docker, Kubernetes, CI/CD pipelines, and cloud platforms (AWS/GCP/Azure)", "Solid understanding of data pipelines, ETL workflows, and distributed computing", "Strong problem-solving skills and ability to optimize code for efficiency and scalability", "Experience with LLMs (Large Language Models), Generative AI, and NLP", "Familiarity with vector databases and embeddings (e.g., Pinecone, FAISS, Weaviate)", "Background in computer vision, reinforcement learning, or time-series forecasting"], "Benefits": ["Pay: $65,000.00 - $75,000.00 per year", "Monday to Friday"], "Responsibilities": ["We are seeking a Machine Learning Engineer with strong Python expertise and full-stack development capabilities to join our team", "In this role, you will design, develop, and deploy scalable machine learning solutions while also contributing to the end-to-end application stack\u2014ranging from backend services to frontend interfaces", "You will work cross-functionally with data scientists, software engineers, and product teams to build AI-driven applications that drive real business impact", "Machine Learning & AI Development", "Design, develop, and optimize machine learning models for predictive analytics, recommendation systems, NLP, or computer vision", "Implement, train, and fine-tune models using frameworks like TensorFlow, PyTorch, Scikit-learn, or Hugging Face", "Perform data preprocessing, feature engineering, and model evaluation to ensure high-performance ML systems", "Deploy and monitor ML models in production environments, ensuring scalability and reliability", "Full-Stack Development", "Develop and maintain backend services (APIs, microservices) using Python (FastAPI, Flask, Django)", "Build scalable, responsive front-end interfaces using React, Vue.js, or Angular", "Integrate ML models into web and cloud-based applications with seamless user interactions", "Ensure security, performance, and maintainability of the full-stack architecture", "Automate deployment pipelines with CI/CD tools (Docker, Kubernetes, GitHub Actions, Jenkins)", "Implement MLOps best practices for model versioning, retraining, and monitoring", "Solid understanding for how to optimize cloud infrastructure on AWS, Azure, or GCP for ML workloads", "Collaboration & Leadership", "Work closely with data scientists, product managers, and software engineers to align ML solutions with business objectives", "Advocate for best practices in software engineering, ML model lifecycle management, and scalable architectures", "Contribute to code reviews, technical documentation, and knowledge-sharing initiatives"]}, "job_onet_soc": "15111100", "job_onet_job_zone": "5"}