{"job_id": "65P0YySQwXvz-nBqAAAAAA==", "employer_name": "CVS Health", "employer_logo": "https://akidagain.org/wp-content/uploads/2022/08/cvs-health-logo-stacked.png", "employer_website": "http://www.cvshealth.com", "employer_company_type": "Retail", "job_publisher": "LazyApply", "job_employment_type": "FULLTIME", "job_title": "Senior Manager, Data Science - Retail Supply Chain Analytics", "job_apply_link": "https://lazyapply.com/jobpreview/job_5be9c6e6e7b4a95b", "job_apply_is_direct": false, "job_apply_quality_score": 0.4963, "apply_options": [{"publisher": "LazyApply", "apply_link": "https://lazyapply.com/jobpreview/job_5be9c6e6e7b4a95b", "is_direct": false}], "job_description": "Bring your heart to CVS Health. Every one of us at CVS Health shares a single, clear purpose: Bringing our heart to every moment of your health. This purpose guides our commitment to deliver enhanced human-centric health care for a rapidly changing world. Anchored in our brand \u2014 with heart at its center \u2014 our purpose sends a personal message that how we deliver our services is just as important as what we deliver. Our Heart At Work Behaviors\u2122 support this purpose. We want everyone who works at CVS Health to feel empowered by the role they play in transforming our culture and accelerating our ability to innovate and deliver solutions to make health care more personal, convenient and affordable.\n\nThe Retail Supply Chain Analytics team is looking for an exceptional Senior Manager, Data Science to drive our Data Science Strategy and roadmap. This role is an opportunity to join the team building the Data and Machine Learning products that power CVS Health to make healthier happen across America. You will have the opportunity to ideate and drive new strategic initiatives which will unlock the immense power of our data to produce value for our customers.\nThis position will report to the Director of Data Science, Retail Supply Chain Analytics with consistent exposure to senior leadership within Supply Chain\n\nAs a Senior Manager, Data Science, your role will entail:\n\nDefine analytics strategy, capabilities, and roadmaps for our modern data and analytics platform.\nAbility to identify opportunities to enhance and build data assets to enable new analytics and modeling solutions. Performs analyses of structured and unstructured data to solve multiple complex business problems utilizing advanced statistical techniques and mathematical analyses and broad knowledge of the organization and/or industry.\nUnderstand key drivers of business value and being able to translate into business opportunities and frame them as analytical problems e.g., how to advance analytics strategy to enable business initiatives\nMentor more junior team member, share insights across teams, and Review work of more junior team members\nAutonomously lead the client relationship. Lead development of solutions with high complexity and risk. Developing, prototyping, and refining robust and scalable analytic solutions to business problems in support of the CVS Health Supply Chain.\nConsult on the creation of analytics solutions and any data enhancements needed to drive those solutions, that effectively weigh business and technical tradeoffs using an advanced understanding of business strategy as well as relevant big data environment topics\nWork closely with the business team to understand business needs, develop requirements, and implement data strategy solutions\nDefine objectives and key milestones to meet short- and long-term needs of business stakeholders and oversee project management activities including team communication, leadership updates, stakeholder management and timelines\nDevelop and maintain relationships with wide range of stakeholders including business partners, IT, other analytic teams, Legal, etc.\nDefine methodology and approach to launch new capabilities and features, test their performance, and iterate quality.\nProduce journey maps, solution context diagrams and other strategic artifacts to help guide the team and stakeholders towards the product\u2019s vision.\nDevelop and present meaningful and insights-driven materials on analytical results with recommendations and go forward planning to guide a variety of audiences including internal stakeholders and senior leadership\n\nRequired Qualifications\n\n5+ years of experience as Solution Architect/Business Architect or similar technical role\n5+ years of experience programming in SQL/ Python/R\n5+ years of people management experience\n5+ years' experience strategy consulting or on strategy teams in large companies\n5+ years of business experience leading analyses and initiatives with a track record of business impact\nMinimum 7 years total business experience\nExpertise with data visualization platforms (e.g., Tableau/ThoughtSpot)\nStrong knowledge of the underlying mathematical and statistical principles that are foundational to data science\nExperience building and utilizing a robust experimentation framework (e.g., A/B testing) to measure performance of deployed models\nExperience with cloud distributed-computing platforms (e.g., AWS, Snowflake, etc.), including querying/mining large datasets and deploying projects on cloud systems.\nExperience with working in an Agile framework and Project management tools\n\nPreferred Qualifications\n\nRetail Industry experience would be desired\nAbility to communicate technical concepts and implications effectively to non-technical business partners\nHigh energy and a sense of urgency to deliver results, attention to detail and ability to manage multiple projects simultaneously & meet deadlines.\nCapability to anticipate and prevent project roadblocks before they occur\nKnowledge of Git for version control.\n\nEducation\n\nBachelor\u2019s degree in Mathematics, Statistics, Computer Science, Business Analytics, Economics, Physics, Engineering, or related discipline. Master\u2019s degree or MBA strongly preferred.\n\nPay Range\nThe typical pay range for this role is:\n$120,750.00 - $240,000.00\nThis pay range represents the base hourly rate or base annual full-time salary for all positions in the job grade within which this position falls. The actual base salary offer will depend on a variety of factors including experience, education, geography and other relevant factors. This position is eligible for a CVS Health bonus, commission or short-term incentive program in addition to the base pay range listed above. This position also includes an award target in the company\u2019s equity award program. In addition to your compensation, enjoy the rewards of an organization that puts our heart into caring for our colleagues and our communities. The Company offers a full range of medical, dental, and vision benefits. Eligible employees may enroll in the Company\u2019s 401(k) retirement savings plan, and an Employee Stock Purchase Plan is also available for eligible employees. The Company provides a fully-paid term life insurance plan to eligible employees, and short-term and long term disability benefits. CVS Health also offers numerous well-being programs, education assistance, free development courses, a CVS store discount, and discount programs with participating partners. As for time off, Company employees enjoy Paid Time Off (\u201cPTO\u201d) or vacation pay, as well as paid holidays throughout the calendar year. Number of paid holidays, sick time and other time off are provided consistent with relevant state law and Company policies. For more detailed information on available benefits, please visit jobs.CVSHealth.com/benefits\n\nCVS Health requires certain colleagues to be fully vaccinated against COVID-19 (including any booster shots if required), where allowable under the law, unless they are approved for a reasonable accommodation based on disability, medical condition, religious belief, or other legally recognized reasons that prevents them from being vaccinated.\n\nYou are required to have received at least one COVID-19 shot prior to your first day of employment and to provide proof of your vaccination status or apply for a reasonable accommodation within the first 10 days of your employment. Please note that in some states and roles, you may be required to provide proof of full vaccination or an approved reasonable accommodation before you can begin to actively work.\n\nCVS Health is committed to recruiting, hiring, developing, advancing, and retaining individuals with disabilities. As such, we strive to provide equal access to the benefits and privileges of employment, including the provision of a reasonable accommodation to perform essential job functions. CVS Health can provide a request for a reasonable accommodation, including a qualified interpreter, written information in other formats, translation or other services through ColleagueRelations@CVSHealth.com If you have a speech or hearing disability, please call 7-1-1 to utilize Telecommunications Relay Services (TRS). We will make every effort to respond to your request within 48 business hours and do everything we can to work towards a solution.", "job_is_remote": false, "job_posted_at_timestamp": 1699654245, "job_posted_at_datetime_utc": "2023-11-10T22:10:45.000Z", "job_city": "Wellesley", "job_state": "MA", "job_country": "US", "job_latitude": 42.2968, "job_longitude": -71.29239, "job_benefits": ["paid_time_off", "health_insurance", "dental_coverage", "retirement_savings"], "job_google_link": "https://www.google.com/search?gl=us&hl=en&rciv=jb&q=director+of+advanced+analytics&start=70&ibp=htl;jobs#fpstate=tldetail&htivrt=jobs&htiq=director+of+advanced+analytics&htidocid=65P0YySQwXvz-nBqAAAAAA%3D%3D", "job_offer_expiration_datetime_utc": "2024-03-22T21:12:31.000Z", "job_offer_expiration_timestamp": 1711141951, "job_required_experience": {"no_experience_required": false, "required_experience_in_months": 60, "experience_mentioned": true, "experience_preferred": false}, "job_required_skills": null, "job_required_education": {"postgraduate_degree": false, "professional_certification": false, "high_school": false, "associates_degree": false, "bachelors_degree": false, "degree_mentioned": true, "degree_preferred": true, "professional_certification_mentioned": false}, "job_experience_in_place_of_education": false, "job_min_salary": 120750, "job_max_salary": 240000, "job_salary_currency": "USD", "job_salary_period": "YEAR", "job_highlights": {"Qualifications": ["5+ years of experience as Solution Architect/Business Architect or similar technical role", "5+ years of experience programming in SQL/ Python/R", "5+ years of people management experience", "5+ years' experience strategy consulting or on strategy teams in large companies", "5+ years of business experience leading analyses and initiatives with a track record of business impact", "Minimum 7 years total business experience", "Expertise with data visualization platforms (e.g., Tableau/ThoughtSpot)", "Strong knowledge of the underlying mathematical and statistical principles that are foundational to data science", "Experience building and utilizing a robust experimentation framework (e.g., A/B testing) to measure performance of deployed models", "Experience with cloud distributed-computing platforms (e.g., AWS, Snowflake, etc.), including querying/mining large datasets and deploying projects on cloud systems", "Experience with working in an Agile framework and Project management tools", "Ability to communicate technical concepts and implications effectively to non-technical business partners", "High energy and a sense of urgency to deliver results, attention to detail and ability to manage multiple projects simultaneously & meet deadlines", "Capability to anticipate and prevent project roadblocks before they occur", "Knowledge of Git for version control", "Bachelor\u2019s degree in Mathematics, Statistics, Computer Science, Business Analytics, Economics, Physics, Engineering, or related discipline"], "Responsibilities": ["You will have the opportunity to ideate and drive new strategic initiatives which will unlock the immense power of our data to produce value for our customers", "This position will report to the Director of Data Science, Retail Supply Chain Analytics with consistent exposure to senior leadership within Supply Chain", "Define analytics strategy, capabilities, and roadmaps for our modern data and analytics platform", "Ability to identify opportunities to enhance and build data assets to enable new analytics and modeling solutions", "Performs analyses of structured and unstructured data to solve multiple complex business problems utilizing advanced statistical techniques and mathematical analyses and broad knowledge of the organization and/or industry", "Understand key drivers of business value and being able to translate into business opportunities and frame them as analytical problems e.g., how to advance analytics strategy to enable business initiatives", "Mentor more junior team member, share insights across teams, and Review work of more junior team members", "Autonomously lead the client relationship", "Lead development of solutions with high complexity and risk", "Developing, prototyping, and refining robust and scalable analytic solutions to business problems in support of the CVS Health Supply Chain", "Consult on the creation of analytics solutions and any data enhancements needed to drive those solutions, that effectively weigh business and technical tradeoffs using an advanced understanding of business strategy as well as relevant big data environment topics", "Work closely with the business team to understand business needs, develop requirements, and implement data strategy solutions", "Define objectives and key milestones to meet short- and long-term needs of business stakeholders and oversee project management activities including team communication, leadership updates, stakeholder management and timelines", "Develop and maintain relationships with wide range of stakeholders including business partners, IT, other analytic teams, Legal, etc", "Define methodology and approach to launch new capabilities and features, test their performance, and iterate quality", "Produce journey maps, solution context diagrams and other strategic artifacts to help guide the team and stakeholders towards the product\u2019s vision", "Develop and present meaningful and insights-driven materials on analytical results with recommendations and go forward planning to guide a variety of audiences including internal stakeholders and senior leadership"], "Benefits": ["$120,750.00 - $240,000.00", "This pay range represents the base hourly rate or base annual full-time salary for all positions in the job grade within which this position falls", "The actual base salary offer will depend on a variety of factors including experience, education, geography and other relevant factors", "This position is eligible for a CVS Health bonus, commission or short-term incentive program in addition to the base pay range listed above", "This position also includes an award target in the company\u2019s equity award program", "In addition to your compensation, enjoy the rewards of an organization that puts our heart into caring for our colleagues and our communities", "The Company offers a full range of medical, dental, and vision benefits", "Eligible employees may enroll in the Company\u2019s 401(k) retirement savings plan, and an Employee Stock Purchase Plan is also available for eligible employees", "The Company provides a fully-paid term life insurance plan to eligible employees, and short-term and long term disability benefits", "CVS Health also offers numerous well-being programs, education assistance, free development courses, a CVS store discount, and discount programs with participating partners", "As for time off, Company employees enjoy Paid Time Off (\u201cPTO\u201d) or vacation pay, as well as paid holidays throughout the calendar year", "Number of paid holidays, sick time and other time off are provided consistent with relevant state law and Company policies"]}, "job_job_title": "Senior manager", "job_posting_language": "en", "job_onet_soc": "15204100", "job_onet_job_zone": "5", "job_naics_code": "44611", "job_naics_name": "Pharmacies and Drug Stores"}