{"job_id": "GAGpL6IKaleO347jAAAAAA==", "employer_name": "Berthel Fisher Companies", "employer_logo": null, "employer_website": "http://www.berthel.com", "employer_company_type": null, "job_publisher": "Salary.com", "job_employment_type": "FULLTIME", "job_title": "Vice President of Business Development", "job_apply_link": "https://www.salary.com/job/berthel-fisher-companies/vice-president-of-business-development/j202305040537502542958", "job_apply_is_direct": false, "job_apply_quality_score": 0.6233, "apply_options": [{"publisher": "Salary.com", "apply_link": "https://www.salary.com/job/berthel-fisher-companies/vice-president-of-business-development/j202305040537502542958", "is_direct": false}], "job_description": "Berthel Fisher offers comprehensive benefits including:\nHealth, dental and vision insurance\n401(k) program\nEmployer paid life insurance\nPaid vacation, paid sick leave, paid holidays, and paid birthday leave\nEmployer paid short term and long-term disability coverage\nOpportunity for career growth\nOn site exercise facility\nWe offer a great working environment in a beautiful and professional office location. This is your opportunity to play a key role in the continued success of our company. Our culture is fast-paced, motivational and focused on improving our client\u2019s lives.\nPlease check back often for new opportunities to join the Berthel Fisher Family. Or send a cover letter and resume to humanresources@berthel.com\n\nJoin Our Team!\n\nWe have the opportunity for a self-motivated, professional individual to assume the role of\n\nVice President of Business Development. The primary responsibility of the Vice President of\n\nBusiness Development is to facilitate the growth of Berthel Fisher Companies by engaging with\n\nand attracting Financial Professionals. The Vice President of Business Development plays an\n\nimportant role in setting the impression of our organization. Duties include, but are not limited\n\nto:\n\nCollaborate with management and internal marketing department to establish and execute\n\nrecruiting campaigns, retention plans, and acquisition strategies\n\nRecruit and acquire new Financial Professionals via phone, email and in person\n\nconversations\n\nCoordinate with Business Development department to communicate across the organization\n\nthroughout the recruiting and transition process\n\nDevelop relationships with third party recruiting firms\n\nOrganize and track data using various systems\n\nBuild and maintain relationships with previously recruited Financial Professionals\n\nQualified candidates will have previous experience in the Financial Services industry. FINRA\n\nSecurities Licenses 7 and/or 65 are required. Willingness to obtain additional FINRA or Sate\n\nLicenses as required.\n\nDesired candidates will present themselves professionally and have excellent written and oral\n\ncommunication skills. Candidate must have excellent attention to detail and organizational skills\n\nand must be self-motivated.\n\nThis position requires up to 50% travel.\n\nRemote work is an option for candidates outside of the local area. Travel to the Cedar Rapids,\n\nIowa office would be required periodically.\n\nCompensation: $80,000-100,000 base salary with recruiting incentive. This range is a good\n\nfaith estimate of the compensation to be offered for this position based on the ideal candidate\u2019s\n\nqualifications, the Company\u2019s operational needs, and other considerations permitted by law.\n\nThe actual pay offered to a specific candidate may vary above or below the stated range.", "job_is_remote": false, "job_posted_at_timestamp": 1708646400, "job_posted_at_datetime_utc": "2024-02-23T00:00:00.000Z", "job_city": "Cedar Rapids", "job_state": "IA", "job_country": "US", "job_latitude": 42.016636, "job_longitude": -91.66635, "job_benefits": ["retirement_savings", "paid_time_off", "health_insurance", "dental_coverage"], "job_google_link": "https://www.google.com/search?gl=us&hl=en&rciv=jb&q=vice+president+of+business+development&start=30&ibp=htl;jobs#fpstate=tldetail&htivrt=jobs&htiq=vice+president+of+business+development&htidocid=GAGpL6IKaleO347jAAAAAA%3D%3D", "job_offer_expiration_datetime_utc": "2024-03-21T00:00:00.000Z", "job_offer_expiration_timestamp": 1710979200, "job_required_experience": {"no_experience_required": false, "required_experience_in_months": null, "experience_mentioned": true, "experience_preferred": false}, "job_required_skills": null, "job_required_education": {"postgraduate_degree": false, "professional_certification": false, "high_school": false, "associates_degree": false, "bachelors_degree": false, "degree_mentioned": false, "degree_preferred": false, "professional_certification_mentioned": false}, "job_experience_in_place_of_education": false, "job_min_salary": null, "job_max_salary": null, "job_salary_currency": null, "job_salary_period": null, "job_highlights": {"Qualifications": ["Qualified candidates will have previous experience in the Financial Services industry", "Securities Licenses 7 and/or 65 are required", "Willingness to obtain additional FINRA or Sate", "Candidate must have excellent attention to detail and organizational skills", "and must be self-motivated", "This position requires up to 50% travel", "qualifications, the Company\u2019s operational needs, and other considerations permitted by law"], "Responsibilities": ["The primary responsibility of the Vice President of", "Business Development is to facilitate the growth of Berthel Fisher Companies by engaging with", "Collaborate with management and internal marketing department to establish and execute", "recruiting campaigns, retention plans, and acquisition strategies", "Recruit and acquire new Financial Professionals via phone, email and in person", "Coordinate with Business Development department to communicate across the organization", "Develop relationships with third party recruiting firms", "Organize and track data using various systems"], "Benefits": ["Health, dental and vision insurance", "401(k) program", "Employer paid life insurance", "Paid vacation, paid sick leave, paid holidays, and paid birthday leave", "Employer paid short term and long-term disability coverage", "Opportunity for career growth", "Compensation: $80,000-100,000 base salary with recruiting incentive"]}, "job_job_title": "Business", "job_posting_language": "en", "job_onet_soc": "11101100", "job_onet_job_zone": "5"}