{"job_id": "fmZNbpceb4WJbCjmAAAAAA==", "employer_name": "The Knot Worldwide", "employer_logo": "https://upload.wikimedia.org/wikipedia/en/thumb/e/e8/The_Knot_Worldwide_Logo.jpg/800px-The_Knot_Worldwide_Logo.jpg", "employer_website": "http://theknotww.com", "employer_company_type": null, "job_publisher": "ZipRecruiter", "job_employment_type": "FULLTIME", "job_title": "Senior Data Scientist", "job_apply_link": "https://www.ziprecruiter.com/c/The-Knot-Worldwide/Job/Senior-Data-Scientist/-in-Beverly,NJ?jid=8dcb03e8f7024806", "job_apply_is_direct": false, "job_apply_quality_score": 0.6156, "apply_options": [{"publisher": "ZipRecruiter", "apply_link": "https://www.ziprecruiter.com/c/The-Knot-Worldwide/Job/Senior-Data-Scientist/-in-Beverly,NJ?jid=8dcb03e8f7024806", "is_direct": false}], "job_description": "ABOUT THE ROLE AND OUR TEAM:\n\nThe Knot Worldwide is actively seeking a skilled Senior Data Scientist to become an integral part of our Data Science team. This role is centered around utilizing advanced analytics and statistical methods to empower our non-wedding brands with insights that optimize performance. As a Senior Data Scientist, you will develop analytical tools, conduct ad-hoc analyses, and assist in correlating user activity with marketing and product initiatives. Your involvement will extend to statistical modeling, investigations, and visualizations, collaborating with various teams to drive measurable outcomes. As a member of the wider Data organization within TKWW, your primary focus will be on constructing analytic models and designing as well as analyzing experiments to quantify the impact of your contributions. In this capacity, you will serve as both a valued partner and trusted advisor, playing a pivotal role in our data-driven decision-making process across the Data and Marketing departments.\n\nRESPONSIBILITIES:\n\u2022 Taking a proactive leadership role in shaping the strategy and direction of teams dedicated to transforming and innovating our non-wedding brands, The Bash and The Bump, leveraging collaborative approaches and innovative thinking to drive successful outcomes\n\u2022 Conducting in-depth analysis of TKWW user behavior to identify growth opportunities that enhance our product experiences\n\u2022 Using descriptive statistical and modeling techniques like hypothesis testing, regression, classification, and clustering to augment data analyses and insights\n\u2022 Designing & analyzing A/B testing experiments\n\u2022 Forecasting and simulating hypotheticals to deliver early potential signals before large initiatives start\n\u2022 Building out self-serve reports, capabilities, and applications for partners within the organization\n\u2022 Maintaining a deep understanding of the product, relevant data products, and past experiments and analyses\n\u2022 Recognizing opportunities for new data products and integrations and work with business partners to implement them\n\u2022 Working with Product Managers and engineers to ensure appropriate tracking is in place\n\u2022 Communicating, collaborating, and presenting results to partners within TKWW\n\nSUCCESSFUL SENIOR DATA SCIENTISTS HAVE:\n\u2022 Fluency in English\n\u2022 A minimum of 3-5 years of experience in data science and analytics roles within technology brands, with a preference for experience in a two-sided marketplace or e-commerce domain.\n\u2022 Advanced knowledge of statistics including hypothesis testing, regression analysis, and forecasting, and hands-on experience with A/B testing design and analysis.\n\u2022 Advanced knowledge of SQL and ability to write efficient SQL code\n\u2022 Ability to code in Python for data manipulation, visualization, and analysis using Jupyter notebooks\n\u2022 Excellent communication skills, both written and verbal, with the ability to explain complex concepts to audiences of varying technical proficiency.\n\u2022 Experience in using and building self-service analytics tools.\n\u2022 A strategic mindset capable of translating business problems into analytics opportunities and solutions.\n\u2022 A collaborative attitude that fosters a culture of data-driven decision making across the organization.\n\u2022 An innovative spirit that thrives on exploring new ideas and approaches to solve challenging problems.\n\nBENEFITS & PERKS:\n\u2022 Private Health Insurance paid by the Company\n\u2022 Subsidies and grants in training and English courses\n\u2022 Working 100% from home\n\u2022 Flexible working hours\n\u2022 Tax relief options for Ticket Restaurant, Ticket Transportation, and Daycare\n\u2022 Tickets restaurant\n\u2022 Udemy courses\n\u2022 Life insurance\n\u2022 Gym discounts\n\u2022 TYPS: easy APP to ask for salary advance payments in 48h\n\u2022 Free paid hours: use your paid holidays as hours\n\u2022 Referral bonus\n\u2022 Getting married or having a baby? We have a gift for you!\n\nWHAT WE DO MATTERS:\n\nHere at The Knot Worldwide, we believe in doing work that matters. In more than 16 countries around the world, The Knot Worldwide's leading family of brands-including The Knot, WeddingWire, Bodas, The Bash, The Bump, and more-help people take celebration planning from inspiration to action. When you join our global team, you'll be a part of a diverse group of individuals passionate about serving and enabling our communities to celebrate the moments that make us.\n\nAt The Knot Worldwide, we believe you are more than a resume and invite you to go for it, take the leap of faith, and apply for this job if it sparks your passion to join TKWW and make a difference!\n\nWHAT WE LOVE ABOUT YOU:\n\u2022 You Dream Big. You iterate and experiment to drive innovation.\n\u2022 You Love Our Users. You keep our global community at the center of everything you do.\n\u2022 You Do the Right Thing. You strengthen your team through respect, fairness, and inclusion.\n\u2022 You Hustle Every Day. You favor urgency and own your outcomes.\n\u2022 You Win Together. People are at the heart of our success and you play as a team.\n\nWHAT YOU LOVE ABOUT US:\n\nWe believe in a wide range of holistic offerings to support our employees so that they can live our values day in and day out. From mental wellbeing, physical health and financial planning, to engaging perks and discounts, we are in the business of celebrating and supporting the Moments that Matter both in and out of the \"office\". We offer flexible vacation, generous parental leave and prioritize initiatives that support the growth, development, and happiness of our people.\n\nTKWW's approach to the future of work: We embrace a remote culture and empower our employees to work wherever they feel most productive. To facilitate in-person collaboration, we have office spaces in Austin, TX; Barcelona, Spain; Delhi, India; Galway, Ireland; London, England; New York, NY; Norwalk, CT; Omaha, NE; Portland, OR; and Washington, D.C.\n\n--\n\nUS Notice: The Knot Worldwide provides equal employment opportunities (EEO) to all employees and applicants for employment without regard to race, color, religion, sex, national origin, age, or disability. In addition to federal law requirements, The Knot Worldwide complies with applicable state and local laws governing nondiscrimination in employment in every location in which the company has facilities. The Knot Worldwide expressly prohibits any form of workplace harassment based on race, color, religion, gender, sexual orientation, gender identity or expression, national origin, age, genetic information, disability, or veteran status.\n\nU.S. Applicants: If you are a resident of California, Colorado, Washington State or New York City, please email statejobdescriptions@theknotww.com to request your state-specific job description. In the subject line, please add the specific job title of the role you are applying to. Please also be sure to specify your state of residence.", "job_is_remote": true, "job_posted_at_timestamp": 1709280000, "job_posted_at_datetime_utc": "2024-03-01T08:00:00.000Z", "job_city": "Beverly", "job_state": "NJ", "job_country": "US", "job_latitude": 40.065388, "job_longitude": -74.91905, "job_benefits": ["paid_time_off", "health_insurance"], "job_google_link": "https://www.google.com/search?gl=us&hl=en&rciv=jb&q=senior+data+scientist&start=60&ibp=htl;jobs#fpstate=tldetail&htivrt=jobs&htiq=senior+data+scientist&htidocid=fmZNbpceb4WJbCjmAAAAAA%3D%3D", "job_offer_expiration_datetime_utc": "2024-04-01T00:00:00.000Z", "job_offer_expiration_timestamp": 1711929600, "job_required_experience": {"no_experience_required": false, "required_experience_in_months": 36, "experience_mentioned": true, "experience_preferred": false}, "job_required_skills": null, "job_required_education": {"postgraduate_degree": false, "professional_certification": false, "high_school": false, "associates_degree": false, "bachelors_degree": false, "degree_mentioned": false, "degree_preferred": false, "professional_certification_mentioned": false}, "job_experience_in_place_of_education": false, "job_min_salary": null, "job_max_salary": null, "job_salary_currency": null, "job_salary_period": null, "job_highlights": {"Qualifications": ["Fluency in English", "A minimum of 3-5 years of experience in data science and analytics roles within technology brands, with a preference for experience in a two-sided marketplace or e-commerce domain", "Advanced knowledge of statistics including hypothesis testing, regression analysis, and forecasting, and hands-on experience with A/B testing design and analysis", "Advanced knowledge of SQL and ability to write efficient SQL code", "Ability to code in Python for data manipulation, visualization, and analysis using Jupyter notebooks", "Excellent communication skills, both written and verbal, with the ability to explain complex concepts to audiences of varying technical proficiency", "Experience in using and building self-service analytics tools", "A strategic mindset capable of translating business problems into analytics opportunities and solutions", "A collaborative attitude that fosters a culture of data-driven decision making across the organization", "An innovative spirit that thrives on exploring new ideas and approaches to solve challenging problems"], "Responsibilities": ["As a Senior Data Scientist, you will develop analytical tools, conduct ad-hoc analyses, and assist in correlating user activity with marketing and product initiatives", "Your involvement will extend to statistical modeling, investigations, and visualizations, collaborating with various teams to drive measurable outcomes", "As a member of the wider Data organization within TKWW, your primary focus will be on constructing analytic models and designing as well as analyzing experiments to quantify the impact of your contributions", "In this capacity, you will serve as both a valued partner and trusted advisor, playing a pivotal role in our data-driven decision-making process across the Data and Marketing departments", "Taking a proactive leadership role in shaping the strategy and direction of teams dedicated to transforming and innovating our non-wedding brands, The Bash and The Bump, leveraging collaborative approaches and innovative thinking to drive successful outcomes", "Conducting in-depth analysis of TKWW user behavior to identify growth opportunities that enhance our product experiences", "Using descriptive statistical and modeling techniques like hypothesis testing, regression, classification, and clustering to augment data analyses and insights", "Designing & analyzing A/B testing experiments", "Forecasting and simulating hypotheticals to deliver early potential signals before large initiatives start", "Building out self-serve reports, capabilities, and applications for partners within the organization", "Maintaining a deep understanding of the product, relevant data products, and past experiments and analyses", "Recognizing opportunities for new data products and integrations and work with business partners to implement them", "Working with Product Managers and engineers to ensure appropriate tracking is in place", "Communicating, collaborating, and presenting results to partners within TKWW"], "Benefits": ["Private Health Insurance paid by the Company", "Subsidies and grants in training and English courses", "Working 100% from home", "Flexible working hours", "Tax relief options for Ticket Restaurant, Ticket Transportation, and Daycare", "Udemy courses", "Life insurance", "Gym discounts", "TYPS: easy APP to ask for salary advance payments in 48h", "Free paid hours: use your paid holidays as hours", "Referral bonus", "You Hustle Every Day", "From mental wellbeing, physical health and financial planning, to engaging perks and discounts, we are in the business of celebrating and supporting the Moments that Matter both in and out of the \"office\"", "We offer flexible vacation, generous parental leave and prioritize initiatives that support the growth, development, and happiness of our people"]}, "job_job_title": "Data scientist", "job_posting_language": "en", "job_onet_soc": "15111100", "job_onet_job_zone": "5", "job_occupational_categories": ["15-2041.00: Statisticians"]}