{"job_id": "T6qHsP9QhK4fkn-VAAAAAA==", "employer_name": "Ekimetrics", "employer_logo": null, "employer_website": null, "employer_company_type": null, "job_publisher": "Lever", "job_employment_type": "FULLTIME", "job_title": "Senior Manager in Marketing Analytics & Data Science - New York | Los Angeles", "job_apply_link": "https://jobs.lever.co/ekimetrics/54519bbd-238f-4063-88ae-0ad261242e51", "job_apply_is_direct": false, "job_apply_quality_score": 0.7789, "apply_options": [{"publisher": "Lever", "apply_link": "https://jobs.lever.co/ekimetrics/54519bbd-238f-4063-88ae-0ad261242e51", "is_direct": false}, {"publisher": "Startup Jobs", "apply_link": "https://startup.jobs/manager-in-marketing-analytics-data-science-new-york-los-angeles-ekimetrics-1850950", "is_direct": false}, {"publisher": "Karkidi", "apply_link": "https://www.karkidi.com/job-details/61473-senior-manager-in-marketing-analytics-data-science-new-york-los-angeles-job", "is_direct": false}], "job_description": "Ekimetrics is a leader in data science and AI-powered solutions. For over 16 years, we\u2019ve pioneered the use of AI and advanced data science applied to unified marketing measurement, holistic business optimization and broad-ranging sustainability goals.\n\nOur goal: combine high impact with long-term business purpose.\n\nEkimetrics is one of the world\u2019s largest independent analytics firms with offices on 3 continents, and with more than 400 data experts. Since 2006, we have led more than a thousand data science projects in over 50 countries, generating more than $1bn in profit for our customers.\n\nWe help companies rethink the way they operate, so they can reconcile financial KPIs with non-financial goals. We are uniquely specialized in creating scalable data and analytics solutions that drive high-impact optimizations in alignment with overarching brand strategy and sustainability goals.\n\nOur New York office is one of our newer branches focused on managing our rapid growth trajectory working with Fortune 500 companies on a wide range of projects. We are a tight-knit group that works closely together, expanding as we take on new clients and building upon the Ekimetrics culture.\n\nAbout the job:\n\nWe are looking for a Senior Manager to join our New York team of Data Science Consultants.\n\nYou will be a member of our New York Executive team, with cross-functional responsibilities in a growing and dynamic environment.\n\nThe Senior Manager will focus on steering some of our largest and most complex accounts, and on delivering analytics projects that will lead to significant, value-led transformation for our clients. This requires building strong client relationships by understanding their needs and offering the right solutions.\n\nAs a Senior Manager at Eki, you will work with the Global Management, to contribute to the growth and health of the company by providing thought leadership and supporting the company\u2019s strategic goals.\n\nYou will also be leading prospection activities and leveraging your expertise to create and identify new business opportunities for Ekimetrics.\n\nThe Senior Manager also acts as a leader of operations, taking the lead on strategic topics such as, HR, Innovation, Thought Leadership, or Industrialization.\n\nFinally, you will have people management responsibilities which require you to develop and coach a small team of Data Science consultants, ensuring they are motivated and have clear pathways for growth. You will manage their performance evaluations and provide constant and impactful feedback, paving the way for the immense talent coming through our doors.\n\nJob Responsibilities\n\n1. Strategic Contributions & Ekimetrics Growth\n\n\u00b7 Member of New York leadership team, involved in the entity\u2019s development initiatives and strategic decisions;\n\n\u00b7 Heavily involved in entity operations, P&L decisions, short- and long-term investment strategy, and staffing/development plans;\n\n\u00b7 Be a strong representative of Ekimetrics\u2019 culture, leading internal initiatives to enhance consultant skills/experience and promoting Ekimetrics culture in external settings;\n\n\u00b7 Lead path of innovation as Ekimetrics\u2019 expands its offer and capabilities in the market;\n\n\u00b7 Identify innovation opportunities to increase company efficiency and profitability;\n\n\u00b7 Bring prior expertise to Ekimetrics to assist in driving the right solutions for our clients.\n\n2. Account Steering & Delivery\n\n\u00b7 Ownership of the client relationship of managed accounts;\n\n\u00b7 Promote confidence and develop close relationships with senior execs on the client-side;\n\n\u00b7 Lead Ekimetrics\u2019 most complex projects: multi-million accounts, critical and strategic projects, or innovation projects to expand our offer or increase efficiency;\n\n\u00b7 Oversee multiple accounts simultaneously, ensuring account growth and profitability, in partnership with the established project teams;\n\n\u00b7 Drive high levels of client satisfaction;\n\n\u00b7 Cultivate your external network with a client centric approach, driving new business and enhancing Ekimetrics\u2019 standing on the market\n\n3. People Management & Development\n\n\u00b7 Driving the HR plan and giving team members opportunities to succeed;\n\n\u00b7 Recruit and align resources to hire, develop staff, manage performance, and create/enhance data scientists at all levels;\n\n\u00b7 Actively work with the team to improve engagement, retain top performers and support the development of future Eki leaders;\n\n\u00b7 Lead trainings for Consultants on topics, from data science techniques through to business strategy;\n\n\u00b7 Work with international counterparts on global people management topics, such as annual review processes, mentorship training, and culture initiatives.\n\n4. Business Development\n\n\u00b7 Drive velocity and accelerate Ekimetrics\u2019 footprint on the market\n\n\u00b7 Identify and close up-sell/cross-sell opportunities with existing clients;\n\n\u00b7 Position Ekimetrics as an enabler of Data Science Transformation with key decision makers;\n\n\u00b7 Act as an SME for sales efforts, including RFPs, new business pitches, and other commercial opportunities;\n\n\u00b7 Act as a company ambassador \u2013 including thought-leadership, speaking at events, networking with brand executives and industry partners.\n\n5. Eki Life\n\n\u00b7 Helping support our team and business growth by contributing to local and global initiatives, such as, Thought-Leadership, Knowledge Management, Recruitment, Culture, and Diversity teams, and building Data Engineering/Architecture capabilities in the office.\n\n\u00b7 Adopting and living by Ekimetrics\u2019 values: Curiosity, Creativity, Excellence, Transmission and Pleasure.\n\nAbout you\n\nWe are looking for someone who can wear 2 hats: steering marketing analytics & data science projects but also a the strategic partner for our growth\n\nYou will need significant prior experience in advanced analytics, be used to working with senior stakeholders at reputable brands and be able to confidently drive our strategy in the analytics and data transformation space.\n\nIdeally, you will have:\n\n- 7+ years experience in advanced analytics and marketing science\n\n\u00b7 An ability to conduct business & strategy assignments in order to create value and innovative customer engagements;\n\n\u00b7 Experience with software such as Python\n\n\u00b7 The capacity to develop high impact thought leadership that articulates a forward-thinking view of the market.\n\nTransversal Skills\n\nPeople are at the center of who we are at Ekimetrics, so as well as excellent technical skills, it\u2019s important that you also have the following:\n\n\u00b7 Excellent communication skills \u2013 especially translating complex technical findings into insights and stories for stakeholders (internal and external);\n\n\u00b7 A demonstrated ability to develop new and long-lasting client relationships at senior levels across multiple industries and sectors;\n\n\u00b7 An ability to work autonomously and be self-motivated;\n\n\u00b7 A team-oriented and collaborative working style, both with clients and within Ekimetrics;\n\n\u00b7 People management experience and demonstrated ability to develop younger talent and build a high performing team, (this doesn\u2019t necessarily mean you have directly managed a team; this could relate to mentorship, project team management, etc.);\n\n\u00b7 Project management and delivery expertise;\n\n\u00b7 A passion for joining a small team and desire to help the business grow quickly.\n\nWhat we offer:\n\nAt Ekimetrics, final base salary is determined by a multitude of factors and vary from candidate to candidate. Determining factors for base compensation include, but are not limited to, professional background, years of experience, and skillset. A reasonable estimate of the base salary for our NYC office would a range between $130,000 and $175,000. In addition to this base salary, we have a comprehensive benefits package, generous bonus package, and a dynamic promotions and salary raise structure.\n\n- An emphasis on work-life-balance and 20 PTO days per year and holidays\n\n- Dynamic environment with a strong culture and great offices\n\n- Close-knit team with friendly environment, bi-monthly team events and more\n\n- Creative and entrepreneurial start-up environment with vertical and lateral mobility\n\n- Best-in-class methodologies and cutting-edge technologies\n\n- Unique internal training package with 70+ sessions in our Eki.Academy digital platform\n\n- Growth to develop a double profile in data science and strategic consulting\n\n- Client exposure up to the executive level\n\n- Opportunities for international mobility across our three other offices in Paris, London, and Hong Kong\n\nOur values are our 5 cardinal points; our employees have these 5 great strengths in common which serve as pillars in their work and attitude.\n\nCuriosity\u2013 Our primary value, the spark that makes you want to get involved, to discover, to share, to grow with a pinch of aplomb.\n\nCreativity \u2013 Offices and teams that allow everyone to unleash their creative potential, have a breakthrough, and get out of one\u2019s comfort zone with colleagues and clients alike.\n\nExcellence \u2013 Our central value; a continuous appetite for the perfect finishing touch, the extra mile, with the aim of satisfying our customers and our teams.\n\nTransmission \u2013 Desire to share our know-how and assets, working together with generosity, bringing together corporate forces\n\nPleasure \u2013 Essential to the well-being of our teams and our projects, the pleasure of innovating, growing, helping others grow, and of course the pleasure of sharing our rituals!\n\nEkimetrics is an equal opportunity employer committed to making all employment decisions without regard to race/ethnicity, gender, pregnancy, gender identity or expression, color, creed, religion, national origin, age, disability, marital status (including domestic partnerships and civil unions), sexual orientation, military veteran status, unemployment status, or other legally protected categories, subject to applicable law.", "job_is_remote": false, "job_posted_at_timestamp": 1642118400, "job_posted_at_datetime_utc": "2022-01-14T00:00:00.000Z", "job_city": null, "job_state": null, "job_country": "US", "job_latitude": 37.09024, "job_longitude": -95.71289, "job_benefits": ["health_insurance", "paid_time_off"], "job_google_link": "https://www.google.com/search?gl=us&hl=en&rciv=jb&q=manager+of+marketing+analytics&start=20&ibp=htl;jobs#fpstate=tldetail&htivrt=jobs&htiq=manager+of+marketing+analytics&htidocid=T6qHsP9QhK4fkn-VAAAAAA%3D%3D", "job_offer_expiration_datetime_utc": null, "job_offer_expiration_timestamp": null, "job_required_experience": {"no_experience_required": false, "required_experience_in_months": 84, "experience_mentioned": true, "experience_preferred": false}, "job_required_skills": null, "job_required_education": {"postgraduate_degree": false, "professional_certification": false, "high_school": false, "associates_degree": false, "bachelors_degree": false, "degree_mentioned": false, "degree_preferred": false, "professional_certification_mentioned": false}, "job_experience_in_place_of_education": false, "job_min_salary": null, "job_max_salary": null, "job_salary_currency": null, "job_salary_period": null, "job_highlights": {"Qualifications": ["You will need significant prior experience in advanced analytics, be used to working with senior stakeholders at reputable brands and be able to confidently drive our strategy in the analytics and data transformation space", "7+ years experience in advanced analytics and marketing science", "An ability to conduct business & strategy assignments in order to create value and innovative customer engagements;", "Experience with software such as Python", "The capacity to develop high impact thought leadership that articulates a forward-thinking view of the market", "Excellent communication skills \u2013 especially translating complex technical findings into insights and stories for stakeholders (internal and external);", "A demonstrated ability to develop new and long-lasting client relationships at senior levels across multiple industries and sectors;", "An ability to work autonomously and be self-motivated;", "A team-oriented and collaborative working style, both with clients and within Ekimetrics;", "People management experience and demonstrated ability to develop younger talent and build a high performing team, (this doesn\u2019t necessarily mean you have directly managed a team; this could relate to mentorship, project team management, etc.);", "Project management and delivery expertise;", "A passion for joining a small team and desire to help the business grow quickly"], "Responsibilities": ["The Senior Manager will focus on steering some of our largest and most complex accounts, and on delivering analytics projects that will lead to significant, value-led transformation for our clients", "This requires building strong client relationships by understanding their needs and offering the right solutions", "As a Senior Manager at Eki, you will work with the Global Management, to contribute to the growth and health of the company by providing thought leadership and supporting the company\u2019s strategic goals", "You will also be leading prospection activities and leveraging your expertise to create and identify new business opportunities for Ekimetrics", "The Senior Manager also acts as a leader of operations, taking the lead on strategic topics such as, HR, Innovation, Thought Leadership, or Industrialization", "Finally, you will have people management responsibilities which require you to develop and coach a small team of Data Science consultants, ensuring they are motivated and have clear pathways for growth", "You will manage their performance evaluations and provide constant and impactful feedback, paving the way for the immense talent coming through our doors", "Strategic Contributions & Ekimetrics Growth", "Member of New York leadership team, involved in the entity\u2019s development initiatives and strategic decisions;", "Heavily involved in entity operations, P&L decisions, short- and long-term investment strategy, and staffing/development plans;", "Be a strong representative of Ekimetrics\u2019 culture, leading internal initiatives to enhance consultant skills/experience and promoting Ekimetrics culture in external settings;", "Lead path of innovation as Ekimetrics\u2019 expands its offer and capabilities in the market;", "Identify innovation opportunities to increase company efficiency and profitability;", "Bring prior expertise to Ekimetrics to assist in driving the right solutions for our clients", "Account Steering & Delivery", "Ownership of the client relationship of managed accounts;", "Promote confidence and develop close relationships with senior execs on the client-side;", "Lead Ekimetrics\u2019 most complex projects: multi-million accounts, critical and strategic projects, or innovation projects to expand our offer or increase efficiency;", "Oversee multiple accounts simultaneously, ensuring account growth and profitability, in partnership with the established project teams;", "Drive high levels of client satisfaction;", "Cultivate your external network with a client centric approach, driving new business and enhancing Ekimetrics\u2019 standing on the market", "Driving the HR plan and giving team members opportunities to succeed;", "Recruit and align resources to hire, develop staff, manage performance, and create/enhance data scientists at all levels;", "Actively work with the team to improve engagement, retain top performers and support the development of future Eki leaders;", "Lead trainings for Consultants on topics, from data science techniques through to business strategy;", "Work with international counterparts on global people management topics, such as annual review processes, mentorship training, and culture initiatives", "Business Development", "Drive velocity and accelerate Ekimetrics\u2019 footprint on the market", "Identify and close up-sell/cross-sell opportunities with existing clients;", "Position Ekimetrics as an enabler of Data Science Transformation with key decision makers;", "Act as an SME for sales efforts, including RFPs, new business pitches, and other commercial opportunities;", "Act as a company ambassador \u2013 including thought-leadership, speaking at events, networking with brand executives and industry partners", "Eki Life", "Helping support our team and business growth by contributing to local and global initiatives, such as, Thought-Leadership, Knowledge Management, Recruitment, Culture, and Diversity teams, and building Data Engineering/Architecture capabilities in the office", "Adopting and living by Ekimetrics\u2019 values: Curiosity, Creativity, Excellence, Transmission and Pleasure"], "Benefits": ["At Ekimetrics, final base salary is determined by a multitude of factors and vary from candidate to candidate", "A reasonable estimate of the base salary for our NYC office would a range between $130,000 and $175,000", "In addition to this base salary, we have a comprehensive benefits package, generous bonus package, and a dynamic promotions and salary raise structure", "An emphasis on work-life-balance and 20 PTO days per year and holidays", "Dynamic environment with a strong culture and great offices", "Unique internal training package with 70+ sessions in our Eki"]}, "job_job_title": "Senior manager", "job_posting_language": "en", "job_onet_soc": "15204100", "job_onet_job_zone": "5"}