{"job_id": "jkqCmd7PSUrS8CtsAAAAAA==", "employer_name": "Leanin' Tree Inc.", "employer_logo": "https://leanintree.com/cdn/shop/files/leanintree-logo-checkout.jpg?v=1698680215&width=300", "employer_website": "http://www.leanintree.com", "employer_company_type": null, "job_publisher": "ZipRecruiter", "job_employment_type": "FULLTIME", "job_title": "Vice President of Sales", "job_apply_link": "https://www.ziprecruiter.com/c/Leanin-Tree-Inc./Job/Vice-President-of-Sales/-in-Boulder,CO?jid=36b23bc59d8aa916", "job_apply_is_direct": false, "job_apply_quality_score": 0.7194, "apply_options": [{"publisher": "ZipRecruiter", "apply_link": "https://www.ziprecruiter.com/c/Leanin-Tree-Inc./Job/Vice-President-of-Sales/-in-Boulder,CO?jid=36b23bc59d8aa916", "is_direct": false}, {"publisher": "Indeed", "apply_link": "https://www.indeed.com/m/viewjob?jk=2d1017f3ec411679&from=serp&tk=1hirpnh2ji6jt801&xkcb=SoCS67M3Gb7R8iQYhB0PbzkdCdPP", "is_direct": true}, {"publisher": "SimplyHired", "apply_link": "https://www.simplyhired.com/job/C9eEuu6i17qgiwgiYZ7tIfSsXbPU1e3KTyO767kULIVirH81nlvdlA", "is_direct": false}, {"publisher": "Talent.com", "apply_link": "https://www.talent.com/view?id=a5f5ec49c388", "is_direct": false}, {"publisher": "Learn4Good", "apply_link": "https://www.learn4good.com/jobs/boulder/colorado/sales/2731168466/e/", "is_direct": false}, {"publisher": "FactoryFix", "apply_link": "https://jobs.factoryfix.com/jobs/vice-president-of-sales--boulder--co--2566265132--V2", "is_direct": false}, {"publisher": "Jobilize", "apply_link": "https://www.jobilize.com/job/us-co-boulder-vice-president-sales-leanin-tree-hiring-now-job-immediately", "is_direct": false}, {"publisher": "Jobs Cast", "apply_link": "https://www.jobs-cast.com/job/hdi0n6a0/vice-president-of-sales", "is_direct": false}], "job_description": "Vice President of Sales\nBoulder, CO, USA Req #134\nThursday, November 16, 2023\n\nThank you for your interest in employment with Leanin' Tree!Leanin' Tree is the nation's leading fine art greeting card publisher and #1 rated alternative greeting card manufacturer. Our facility is located in beautiful Boulder, Colorado. For over 70 years, we have been bringing the best of words and art together. Leanin' Tree is employee owned and offers a warm and friendly working environment. Come join our team!\n\nAvailable Position: Vice President of Sales\n\nReporting to the Chief Executive Officer, the Vice President of Sales will lead our group of Sales Leaders in developing and executing Sales strategy and deliverables for the Company. This person will provide strategic, tactical, and executional leadership in utilizing category, customer, and consumer insight information to support development and execution of effective sales initiatives at Leanin' Tree.\n\nThe Vice President of Sales position is accountable for developing a high-performance sales team and deliver company volume, net revenue and gross margin objectives.\n\nWe are looking for a top-notch VP of Sales with an in-depth knowledge of the market and competitive products and who has excellent customer service, interpersonal, and communication skills.\n\nDuties and Responsibilities:\n\u2022 Responsible for managing the sales organization and using experience and networks to prospect, manage, and close large key accounts.\n\u2022 Strong focus on AOP achievement, both sales and margin.\n\u2022 Work with the Product Development and Marketing departments to design print and online /digital promotional materials for the company's products and services.\n\u2022 Identify where improvements can be made while developing sales plans and strategies to achieve sales goals.\n\u2022 Develop and manage sales budgets.\n\u2022 Oversee long-term sales processes and strategy; identify market opportunities, create effective positioning with customers, and translate big ideas, company objectives, and goals into clear and actionable plans.\n\u2022 Develop and execute a comprehensive sales strategy to drive revenue growth and ensure successful execution. Set quarterly and annual sales goals and lead the sales teams to achieve their goals.\n\u2022 Create a proactive sales culture, sharing and testing new ideas to drive leads and customer meetings.\n\u2022 Review and make appropriate adjustments to the existing sales incentive structures.\n\u2022 Monitor market trends to understand customer opportunities and needs; recommend and implement new strategies to drive revenue goals and stay competitive in the market.\n\u2022 Monitor revenue pipeline and leads, including forecasting, and adjusting as necessary to create sustainable growth.\n\u2022 Build and grow relationships and lead conversations with key clients, ensuring an exceptional client experience and long-term retention.\n\u2022 Effectively manage promotion strategies to maximize results by retailer.\n\u2022 Oversee analytics across the revenue funnels and maintain a consistent reporting process.\n\u2022 Other duties as assigned.\n\nSupervision\n\u2022 Provide effective executive-level leadership to the Sales organization.\n\u2022 Manage and coach the Sales team and support their professional development; understand what motivates sellers, what their obstacles are, what they need to be successful.\n\u2022 Promote communication and cooperation among departments to create a spirit of unity in the organization.\n\u2022 Lead and motivate the Sales Team; coaching staff and fostering teamwork to ensure staff optimization and organizational competency.\n\u2022 Uphold an environment that promotes great performance and positive morale.\n\nQualifications and Experience:\n\u2022 Bachelor's degree in a business-related field\n\u2022 Minimum of 7 years' experience in a sales leadership position in the CPG sector.\n\u2022 Preferred 5 + years' experience in a senior sales role in the Greeting Card Industry.\n\u2022 Experience reviewing and implementing incentive structures.\n\u2022 Experience prospecting and closing large key accounts.\n\u2022 Preferred experience selling to brick-and-mortar retail chains.\n\u2022 In-depth knowledge of selling strategies and methods.\n\u2022 Seasoning knowledge of Ecommerce.\n\u2022 Strong working knowledge of the company's products, competitive products, and the market.\n\u2022 Excellent leadership, communication, interpersonal, and customer service skills.\n\u2022 Great strategic planning, organizational, and creative thinking skills.\n\u2022 Strong relationships and knowledge of top 10 retailers for this industry.\n\u2022 Superlative communication skills with the ability to communicate as a leader, listen attentively, and excel at public speaking.\n\u2022 Proven record of accomplishment for effective team management and results driven leadership.\n\u2022 Ability to inspire confidence and create trust.\n\u2022 A positive and tenacious attitude and an unyielding passion for success\n\u2022 An outside the box, pro-active approach to self-generate new business through activity, referrals and networks.\n\u2022 Ability to travel approximately 60%.\n\nWork Location: Boulder, Colorado\n\nCompensation: Competitive salary and bonus, commensurate with experience. Salary range: $150,000-$225,000\n\nBenefits include health plan, life insurance, disability, 401 plan, and entitlements.\n\nNote: This job description is not intended to be an exhaustive list of all duties, responsibilities or qualifications for the job.\n\u2022 Prospective candidates for the VP Sales role will possess relevant experience in the consumer goods sector.\n\u2022 They will have a demonstrated track record to drive organizations to higher growth and profitability through strategy, innovation, and crisp and consistent execution of strategic sales plans.\n\u2022 The ideal candidate will have worked with smaller companies and / or start-ups to bring an appreciation for building / scaling businesses from earlier stages. Experience building sales process, systems, and rigor will be important. Deep experience and knowledge of retail sales is critical.\n\nOur company is an Equal Opportunity employer. All qualified applicants will receive consideration for employment without regard to race, national origin, age, sex, religion, disability, sexual orientation, marital status, veteran status, gender identity or expression, or any other basis protected by local, state or federal law.\n\nThis policy applies regarding all aspects of one's employment, including hiring, transfer, promotion, compensation, eligibility for benefits and termination.\n\nWe offer excellent benefits- 3 weeks Paid Time Off your first year of employment, 10 paid holidays, plus Floating Holiday and Volunteer time! Health, dental, and vision eligible after 30 days, Life Assistance Program, FSA, life/disability insurance, 401(k), and free product! We are an EEO Employer\n\nOther details\n\u2022 Pay Type Salary\n\u2022 Min Hiring Rate $150,000.00\n\u2022 Max Hiring Rate $225,000.00\n\u2022 Travel Required Yes\n\u2022 Travel % 60\nApply Now", "job_is_remote": false, "job_posted_at_timestamp": 1710116820, "job_posted_at_datetime_utc": "2024-03-11T00:27:00.000Z", "job_city": "Boulder", "job_state": "CO", "job_country": "US", "job_latitude": 40.014984, "job_longitude": -105.270546, "job_benefits": ["retirement_savings", "paid_time_off", "dental_coverage", "health_insurance"], "job_google_link": "https://www.google.com/search?gl=us&hl=en&rciv=jb&q=vice+president+of+sales&start=30&ibp=htl;jobs#fpstate=tldetail&htivrt=jobs&htiq=vice+president+of+sales&htidocid=jkqCmd7PSUrS8CtsAAAAAA%3D%3D", "job_offer_expiration_datetime_utc": "2024-04-09T00:00:00.000Z", "job_offer_expiration_timestamp": 1712620800, "job_required_experience": {"no_experience_required": false, "required_experience_in_months": 84, "experience_mentioned": true, "experience_preferred": false}, "job_required_skills": null, "job_required_education": {"postgraduate_degree": false, "professional_certification": false, "high_school": false, "associates_degree": false, "bachelors_degree": false, "degree_mentioned": true, "degree_preferred": true, "professional_certification_mentioned": false}, "job_experience_in_place_of_education": false, "job_min_salary": null, "job_max_salary": null, "job_salary_currency": null, "job_salary_period": null, "job_highlights": {"Qualifications": ["Bachelor's degree in a business-related field", "Minimum of 7 years' experience in a sales leadership position in the CPG sector", "Experience reviewing and implementing incentive structures", "Experience prospecting and closing large key accounts", "In-depth knowledge of selling strategies and methods", "Seasoning knowledge of Ecommerce", "Strong working knowledge of the company's products, competitive products, and the market", "Excellent leadership, communication, interpersonal, and customer service skills", "Great strategic planning, organizational, and creative thinking skills", "Strong relationships and knowledge of top 10 retailers for this industry", "Superlative communication skills with the ability to communicate as a leader, listen attentively, and excel at public speaking", "Proven record of accomplishment for effective team management and results driven leadership", "Ability to inspire confidence and create trust", "A positive and tenacious attitude and an unyielding passion for success", "An outside the box, pro-active approach to self-generate new business through activity, referrals and networks", "Ability to travel approximately 60%", "Experience building sales process, systems, and rigor will be important", "Deep experience and knowledge of retail sales is critical"], "Responsibilities": ["Reporting to the Chief Executive Officer, the Vice President of Sales will lead our group of Sales Leaders in developing and executing Sales strategy and deliverables for the Company", "This person will provide strategic, tactical, and executional leadership in utilizing category, customer, and consumer insight information to support development and execution of effective sales initiatives at Leanin' Tree", "The Vice President of Sales position is accountable for developing a high-performance sales team and deliver company volume, net revenue and gross margin objectives", "Responsible for managing the sales organization and using experience and networks to prospect, manage, and close large key accounts", "Strong focus on AOP achievement, both sales and margin", "Work with the Product Development and Marketing departments to design print and online /digital promotional materials for the company's products and services", "Identify where improvements can be made while developing sales plans and strategies to achieve sales goals", "Develop and manage sales budgets", "Oversee long-term sales processes and strategy; identify market opportunities, create effective positioning with customers, and translate big ideas, company objectives, and goals into clear and actionable plans", "Develop and execute a comprehensive sales strategy to drive revenue growth and ensure successful execution", "Set quarterly and annual sales goals and lead the sales teams to achieve their goals", "Create a proactive sales culture, sharing and testing new ideas to drive leads and customer meetings", "Review and make appropriate adjustments to the existing sales incentive structures", "Monitor market trends to understand customer opportunities and needs; recommend and implement new strategies to drive revenue goals and stay competitive in the market", "Monitor revenue pipeline and leads, including forecasting, and adjusting as necessary to create sustainable growth", "Build and grow relationships and lead conversations with key clients, ensuring an exceptional client experience and long-term retention", "Effectively manage promotion strategies to maximize results by retailer", "Oversee analytics across the revenue funnels and maintain a consistent reporting process", "Other duties as assigned", "Supervision", "Provide effective executive-level leadership to the Sales organization", "Manage and coach the Sales team and support their professional development; understand what motivates sellers, what their obstacles are, what they need to be successful", "Promote communication and cooperation among departments to create a spirit of unity in the organization", "Lead and motivate the Sales Team; coaching staff and fostering teamwork to ensure staff optimization and organizational competency", "Uphold an environment that promotes great performance and positive morale", "Prospective candidates for the VP Sales role will possess relevant experience in the consumer goods sector", "They will have a demonstrated track record to drive organizations to higher growth and profitability through strategy, innovation, and crisp and consistent execution of strategic sales plans", "The ideal candidate will have worked with smaller companies and / or start-ups to bring an appreciation for building / scaling businesses from earlier stages"], "Benefits": ["Compensation: Competitive salary and bonus, commensurate with experience", "Salary range: $150,000-$225,000", "Benefits include health plan, life insurance, disability, 401 plan, and entitlements", "We offer excellent benefits- 3 weeks Paid Time Off your first year of employment, 10 paid holidays, plus Floating Holiday and Volunteer time!", "Health, dental, and vision eligible after 30 days, Life Assistance Program, FSA, life/disability insurance, 401(k), and free product!", "Max Hiring Rate $225,000.00"]}, "job_job_title": "Vice", "job_posting_language": "en", "job_onet_soc": "11101100", "job_onet_job_zone": "5", "job_occupational_categories": ["11-2022.00: Sales Managers"]}