{"job_id": "WwTNr5L6_bAzShFLAAAAAA==", "employer_name": "Gopuff", "employer_logo": "https://logowik.com/content/uploads/images/gopuff2126.jpg", "employer_website": "http://gopuff.com", "employer_company_type": null, "job_publisher": "Salary.com", "job_employment_type": "INTERN", "job_title": "Partnerships Manager Intern", "job_apply_link": "https://www.salary.com/job/gopuff/partnerships-manager-intern/j202309230331464592807", "job_apply_is_direct": false, "job_apply_quality_score": 0.5968, "apply_options": [{"publisher": "Salary.com", "apply_link": "https://www.salary.com/job/gopuff/partnerships-manager-intern/j202309230331464592807", "is_direct": false}], "job_description": "We are seeking a proactive Partnerships Manager Intern to join our team and build on our growth in Bristol. In this role, you will be pivotal in nurturing partnerships with local brands, suppliers, and businesses, ultimately developing Gopuff\u2019s brand perception in the city. We recognize that people come from diverse backgrounds and skills and welcome all to apply.\n\nYou will:\n\u2022 Research, identify, and assess potential partners, from brands to businesses to universities\n\u2022 Initiate contact and cultivate relationships with selected partners\n\u2022 Seek and execute opportunities that lead to new customers and brand enhancement\n\u2022 Quantify the impact you\u2019ve had on the business by tracking the new customers you bring in\n\nYou are:\n\u2022 Must be 18 years or older\n\u2022 Extremely self-motivated and results-oriented\n\u2022 Enthused about building relationships\n\u2022 A strong communicator, both written and verbal\n\u2022 Eager to learn and take on new challenges\n\u2022 Entrepreneurial and commercially minded\n\u2022 Passionate about your city!\n\nBenefits:\n\u2022 Weekly pay cycle (Get paid weekly!)\n\u2022 A performance bonus\n\u2022 Hands-on experience in partnership management\n\u2022 Quantifiable impact: be able to say you directly contributed to X partnerships and Y new customers\n\u2022 Potential for future career opportunities with Gopuff\n\nAt Gopuff, we know that life can be unpredictable. Sometimes you forget the milk at the store, run out of pet food for Fido, or just really need ice cream at 11 pm. We get it\u2014stuff happens. But that\u2019s where we come in, delivering all your wants and needs in just minutes.\n\nAnd now, we\u2019re assembling a team of motivated people to help us drive forward that vision to bring a new age of convenience and predictability to an unpredictable world.\n\nLike what you\u2019re hearing? Then join us on Team Blue.\n\nGopuff is an equal employment opportunity employer, committed to an inclusive workplace where we do not discriminate on the basis of race, sex, gender, national origin, religion, sexual orientation, gender identity, marital or familial status, age, ancestry, disability, genetic information, or any other characteristic protected by applicable laws. We believe in diversity and encourage any qualified individual to apply.", "job_is_remote": false, "job_posted_at_timestamp": 1695513600, "job_posted_at_datetime_utc": "2023-09-24T00:00:00.000Z", "job_city": null, "job_state": null, "job_country": "US", "job_latitude": 37.09024, "job_longitude": -95.71289, "job_benefits": null, "job_google_link": "https://www.google.com/search?gl=us&hl=en&rciv=jb&q=manager+of+brand+partnerships&start=60&ibp=htl;jobs#fpstate=tldetail&htivrt=jobs&htiq=manager+of+brand+partnerships&htidocid=WwTNr5L6_bAzShFLAAAAAA%3D%3D", "job_offer_expiration_datetime_utc": "2024-03-23T00:00:00.000Z", "job_offer_expiration_timestamp": 1711152000, "job_required_experience": {"no_experience_required": false, "required_experience_in_months": null, "experience_mentioned": true, "experience_preferred": false}, "job_required_skills": null, "job_required_education": {"postgraduate_degree": false, "professional_certification": false, "high_school": false, "associates_degree": false, "bachelors_degree": false, "degree_mentioned": true, "degree_preferred": false, "professional_certification_mentioned": false}, "job_experience_in_place_of_education": false, "job_min_salary": null, "job_max_salary": null, "job_salary_currency": null, "job_salary_period": null, "job_highlights": {"Qualifications": ["Must be 18 years or older", "Extremely self-motivated and results-oriented", "Enthused about building relationships", "A strong communicator, both written and verbal", "Eager to learn and take on new challenges", "Entrepreneurial and commercially minded", "Passionate about your city!"], "Responsibilities": ["In this role, you will be pivotal in nurturing partnerships with local brands, suppliers, and businesses, ultimately developing Gopuff\u2019s brand perception in the city", "Research, identify, and assess potential partners, from brands to businesses to universities", "Initiate contact and cultivate relationships with selected partners", "Seek and execute opportunities that lead to new customers and brand enhancement", "Quantify the impact you\u2019ve had on the business by tracking the new customers you bring in"], "Benefits": ["Weekly pay cycle (Get paid weekly!)", "A performance bonus", "Hands-on experience in partnership management", "Quantifiable impact: be able to say you directly contributed to X partnerships and Y new customers", "Potential for future career opportunities with Gopuff"]}, "job_job_title": "Partnerships manager", "job_posting_language": "en", "job_onet_soc": "11202100", "job_onet_job_zone": "4"}