{"job_id": "Ywc4TgSUsNYgF3kOAAAAAA==", "employer_name": "The Opus Group", "employer_logo": "https://www.dgedc.com/wp-content/uploads/2021/11/Opus-Group-Logo-.jpg", "employer_website": null, "employer_company_type": null, "job_publisher": "Salary.com", "job_employment_type": "FULLTIME", "job_title": "Sr. Director, Business Development", "job_apply_link": "https://www.salary.com/job/the-opus-group/sr-director-business-development/j202310170529037777259", "job_apply_is_direct": false, "job_apply_quality_score": 0.5156, "apply_options": [{"publisher": "Salary.com", "apply_link": "https://www.salary.com/job/the-opus-group/sr-director-business-development/j202310170529037777259", "is_direct": false}], "job_description": "Job Title: Sr. Director, Business Development\nGroup / Team: Growth/ Accounts & Sales\nReports to: VP, Business Development\nLocation: Remote\nEmployment Type: FT, Salaried, Exempt\nTravel Requirement: 30%\n\nOPUS AGENCY\n\nOpus Agency partners with world-shaping brands like Amazon, Google, Microsoft, and Salesforce to catalyze movements through shared experiences. Crafted through our end-to-end capabilities and propelled from the epicenter of events, content, and community, these experiences are renowned for accelerating momentum\u2014and success\u2014for everyone involved.\n\nBuilt across four decades, we scale excellence at the forefront of focused strategy, fearless creativity, emerging technology, and agile delivery. Today, as the flagship of The Opus Group, our team members are outperforming from hubs throughout the United States, in the heart of London, and around the world.\n\nIf you embody our cultural pillars\u2014if you can bring versatility, embody optimism, elevate integrity, catalyze curiosity, and own excellence\u2014then join us in fueling the future of brand movements.\n\nWHAT WE ARE LOOKING FOR\n\nAt Opus, we place high importance on building strong client relations. Business Development plays a key role in receiving, vetting, and managing the process of the Agency response on opportunities both known and new. The Sr. Director, Business Development is responsible to find opportunities within accounts that drive growth for both clients and revenue for the agency. Revenue targets, established at the beginning of the calendar year, will identify a mix of current account and net new business desired to achieve and exceed the goal. The Sr. Director, Business Development is a highly collaborative, influential, and experienced senior leader responsible for managing and overseeing a team that initiates and closes sales opportunities, that significantly accelerates the Agency\u2019s growth and profitability and helps fulfill the company\u2019s vision. This position achieves these goals by developing and implementing the company\u2019s business development strategy and tactics.\n\nThe Sr. Director, Business Development understands the client\u2019s business needs and strategy and finds opportunities for Opus to meet those needs (sales). The Sr. Director, Business Development will develop positive, trusting, value-add relationships with clients, provides leadership necessary to increasingly align Opus offerings with client objectives, and own overall responsibility for account revenue targets and profitability goals.\n\nThe Sr. Director, Business Development works closely with the agency to create opportunities and growth for the agency.\n\nKey Responsibilities:\n\u2022 Develops and maintains strong client relationships and creates client success by providing unique and effective solutions to our clients\n\u2022 Maintains leading-edge knowledge of clients\u2019 culture, processes, structure, business, and industry to service them effectively and is responsible for the overall satisfaction and retention of client(s)\n\u2022 Possesses and learns complete knowledge of Opus Agency as a company, our service offerings and the competitive landscape of our industry\n\u2022 Shows value across all agency service lines and effectively communicates client needs to direct teams to successful delivery\n\u2022 Guides the development, writing, and presentation of incremental project proposals, scopes of work, schedules and staffing plans\n\u2022 Drives and leads new business pitches and grows account portfolio via service line growth and new events\n\u2022 Maintains a passion for the brand strategy and can have the complex conversations at a broader business level and sell in the strategic story\n\u2022 Reports on accountability for all aspects of the clients\u2019 business\n\u2022 Maintains a dashboard to track all key client metrics and plans deliverables and creates action plans to achieve key metrics\n\u2022 Owns the overall responsibility for account revenue targets and profitability goals\n\u2022 Manages budget process form a profit generation perspective including expense management, client quoting, and profit modeling\n\u2022 Is responsible for managing and overseeing the Business Development Team\n\u2022 Stays abreast of client billing escalation issues and ensures they are being resolved\n\u2022 Forecasts budget estimates and percent to close rations for pipeline reports and manages scope creep and client\u2019s budgets to maintain profitability\n\u2022 Provides leadership necessary to direct and motivate Opus team members across disciplines (strategy, creative, production, and finance) to contribute and deliver absolute best work while exceeding client expectations\n\u2022 Conceptualizes strategic client programs, understanding the in-depth view of the account as a whole along with industry insight\n\u2022 Responsible for keeping an eye on the client accounts as a whole and how we are being measured on all projects produced within an account\n\u2022 Manages for account success and client relationship, understands event cycles and customer needs and creates customer/partner relationship\n\u2022 Provides fresh strategic ideas to grow and expand the account and adds vision and creativity to client programs\n\u2022 Participates in development of new product lines, modification of existing product lines, & termination of ineffective product lines in an effective and professional manner\n\u2022 Grows Account business and meet revenue goals through a solid understanding of all Opus product lines and ability to upsell/cross-sell services\n\u2022 Drives revenue through recognition and realization of opportunity with existing accounts\n\u2022 Keeps abreast of latest industry trends in order to keep program fresh and on the cutting edge within the client\u2019s industry\n\nCore Requirements:\n\u2022 Bachelor\u2019s degree in related field or equivalent, 5 plus years of related experience, or equivalent combination of education and experience\n\u2022 Strong ability to manage and build relationships and trust with multiple stakeholders internal and external to the organization\n\u2022 3-5 years\u2019 experience selling multiple event service solutions; focus on creative and experiential sales beneficial\n\u2022 Excellent people and management skills to interact with staff, colleagues, cross- functional teams and third parties\n\u2022 Experience with enterprise high tech clients (Intel, Microsoft, Oracle, etc.) a plus\n\u2022 Experience with budget management, financial tracking and contract negotiations\n\u2022 Knowledge of accounting, marketing and sales tactics/strategies\n\u2022 Strong organizational, problem-solving, and analytical skills\n\u2022 Ability to make sound business decisions based upon researched and known data\n\u2022 Ability to work independently and collaborate with others to identify issues and develop solutions\n\u2022 Strong influence-management, negotiation, leadership and assertiveness capabilities\n\u2022 Strong communication skills, both written and verbal\n\u2022 Strong ability to prioritize deadlines and manage multiple workstreams as an individual contributor\n\u2022 Versatility, flexibility, and a willingness to work within constantly changing priorities with enthusiasm\n\u2022 Proven ability to work in a fast-paced environment, manage multiple projects and deliver quick results\n\nWHAT YOU CAN EXPECT IN RETURN\n\u2022 Full time position\n\u2022 Opportunities for growth and development\n\u2022 Health & Dental Insurance (choice of plans)\n\u2022 100% Employer paid short-term disability and life insurance\n\u2022 Opportunity to elect additional life insurance and LTD insurance at employee expense\n\u2022 Paid parental leave\n\u2022 Opportunity to contribute pre-tax dollars to flexible spending accounts\n\u2022 401(K) with employer match\n\u2022 Flexibility in work schedules\n\u2022 Generous time off\n\nHOW WE\u2019LL TAKE CARE OF YOU\n\nOur job titles may span more than one career level. The starting salary for this role is between $120,000 and $150,000. Our salary ranges are based on third-party national average market compensation analysis. The actual salary is dependent upon many factors, such as: training, transferable skills, work experience, business needs, and market demands. The salary range is subject to change and may be modified in the future.\n\nNOT SURE IF YOU SHOULD APPLY?\n\nStudies show that those identifying as under-represented individuals might have talked themselves out of applying at this point. Don\u2019t worry about checking every single box. At Opus Agency, we are dedicated to building a diverse, inclusive, and authentic team \u2013 so if you\u2019re excited about this role, but your past experience doesn\u2019t align perfectly with every single qualification in this job description, we encourage you to apply anyway. You may just be the right candidate for this role or we may have other roles that better align with your skillset.\n\nPhysical Requirements:\n\nIndividuals will be required to sit for the majority of the day and will be required to stand as needed. May require walking primarily on a level surface for periodic periods throughout the day. Reaching above shoulder heights, below the waist or lifting as required to file documents or store materials throughout the workday. Proper lifting techniques required. Individuals will be required to travel via airplane, train, taxi, car and/or other means of transportation as needed.\n\nThe job description is not designed to cover or contain a comprehensive listing of activities, duties or responsibilities that are required of the employee. Duties, responsibilities and activities may change, or new ones may be assigned at any time with or without notice.\u201d\n\nOTHER DUTIES AND ACKNOWLEDGEMENT\n\nThe above noted job description is not intended to describe, in detail, the multitude of tasks that may be assigned but rather to give the employee/ candidate a general sense of the responsibilities and expectations of the position. Duties, responsibilities, and activities may change at any time with or without notice. This does not create an employment contract, implied or otherwise, other than an \"at will\" relationship. This employer participates in E-Verify and will provide the federal government with your Form I-9 information to confirm that you are authorized to work in the U.S.\n\nOpus Agency does not discriminate based upon race, religion, color, national origin, gender (including pregnancy, childbirth, or related medical conditions), sexual orientation, gender identity, gender expression, age, status as a protected veteran, status as an individual with a disability, or other applicable legally protected characteristics. All employment is decided based on qualifications, merit, and business need. Reasonable accommodations may be made to enable individuals with disabilities to perform the essential functions.\n\n#LI-Remote", "job_is_remote": false, "job_posted_at_timestamp": 1697587200, "job_posted_at_datetime_utc": "2023-10-18T00:00:00.000Z", "job_city": null, "job_state": null, "job_country": "US", "job_latitude": 37.09024, "job_longitude": -95.71289, "job_benefits": ["retirement_savings", "health_insurance", "paid_time_off", "dental_coverage"], "job_google_link": "https://www.google.com/search?gl=us&hl=en&rciv=jb&q=senior+manager+of+business+development&start=40&ibp=htl;jobs#fpstate=tldetail&htivrt=jobs&htiq=senior+manager+of+business+development&htidocid=Ywc4TgSUsNYgF3kOAAAAAA%3D%3D", "job_offer_expiration_datetime_utc": "2024-04-17T00:00:00.000Z", "job_offer_expiration_timestamp": 1713312000, "job_required_experience": {"no_experience_required": false, "required_experience_in_months": 60, "experience_mentioned": true, "experience_preferred": true}, "job_required_skills": null, "job_required_education": {"postgraduate_degree": false, "professional_certification": false, "high_school": false, "associates_degree": false, "bachelors_degree": false, "degree_mentioned": true, "degree_preferred": true, "professional_certification_mentioned": false}, "job_experience_in_place_of_education": false, "job_min_salary": null, "job_max_salary": null, "job_salary_currency": null, "job_salary_period": null, "job_highlights": {"Qualifications": ["Bachelor\u2019s degree in related field or equivalent, 5 plus years of related experience, or equivalent combination of education and experience", "Strong ability to manage and build relationships and trust with multiple stakeholders internal and external to the organization", "3-5 years\u2019 experience selling multiple event service solutions; focus on creative and experiential sales beneficial", "Excellent people and management skills to interact with staff, colleagues, cross- functional teams and third parties", "Experience with budget management, financial tracking and contract negotiations", "Knowledge of accounting, marketing and sales tactics/strategies", "Strong organizational, problem-solving, and analytical skills", "Ability to make sound business decisions based upon researched and known data", "Ability to work independently and collaborate with others to identify issues and develop solutions", "Strong influence-management, negotiation, leadership and assertiveness capabilities", "Strong communication skills, both written and verbal", "Strong ability to prioritize deadlines and manage multiple workstreams as an individual contributor", "Versatility, flexibility, and a willingness to work within constantly changing priorities with enthusiasm", "Proven ability to work in a fast-paced environment, manage multiple projects and deliver quick results", "Reaching above shoulder heights, below the waist or lifting as required to file documents or store materials throughout the workday"], "Responsibilities": ["Director, Business Development is responsible to find opportunities within accounts that drive growth for both clients and revenue for the agency", "Director, Business Development is a highly collaborative, influential, and experienced senior leader responsible for managing and overseeing a team that initiates and closes sales opportunities, that significantly accelerates the Agency\u2019s growth and profitability and helps fulfill the company\u2019s vision", "Director, Business Development understands the client\u2019s business needs and strategy and finds opportunities for Opus to meet those needs (sales)", "Director, Business Development will develop positive, trusting, value-add relationships with clients, provides leadership necessary to increasingly align Opus offerings with client objectives, and own overall responsibility for account revenue targets and profitability goals", "Director, Business Development works closely with the agency to create opportunities and growth for the agency", "Develops and maintains strong client relationships and creates client success by providing unique and effective solutions to our clients", "Maintains leading-edge knowledge of clients\u2019 culture, processes, structure, business, and industry to service them effectively and is responsible for the overall satisfaction and retention of client(s)", "Possesses and learns complete knowledge of Opus Agency as a company, our service offerings and the competitive landscape of our industry", "Shows value across all agency service lines and effectively communicates client needs to direct teams to successful delivery", "Guides the development, writing, and presentation of incremental project proposals, scopes of work, schedules and staffing plans", "Drives and leads new business pitches and grows account portfolio via service line growth and new events", "Maintains a passion for the brand strategy and can have the complex conversations at a broader business level and sell in the strategic story", "Reports on accountability for all aspects of the clients\u2019 business", "Maintains a dashboard to track all key client metrics and plans deliverables and creates action plans to achieve key metrics", "Manages budget process form a profit generation perspective including expense management, client quoting, and profit modeling", "Stays abreast of client billing escalation issues and ensures they are being resolved", "Forecasts budget estimates and percent to close rations for pipeline reports and manages scope creep and client\u2019s budgets to maintain profitability", "Provides leadership necessary to direct and motivate Opus team members across disciplines (strategy, creative, production, and finance) to contribute and deliver absolute best work while exceeding client expectations", "Conceptualizes strategic client programs, understanding the in-depth view of the account as a whole along with industry insight", "Responsible for keeping an eye on the client accounts as a whole and how we are being measured on all projects produced within an account", "Manages for account success and client relationship, understands event cycles and customer needs and creates customer/partner relationship", "Provides fresh strategic ideas to grow and expand the account and adds vision and creativity to client programs", "Participates in development of new product lines, modification of existing product lines, & termination of ineffective product lines in an effective and professional manner", "Grows Account business and meet revenue goals through a solid understanding of all Opus product lines and ability to upsell/cross-sell services", "Drives revenue through recognition and realization of opportunity with existing accounts", "Keeps abreast of latest industry trends in order to keep program fresh and on the cutting edge within the client\u2019s industry"], "Benefits": ["Full time position", "Opportunities for growth and development", "Health & Dental Insurance (choice of plans)", "100% Employer paid short-term disability and life insurance", "Opportunity to elect additional life insurance and LTD insurance at employee expense", "Paid parental leave", "Opportunity to contribute pre-tax dollars to flexible spending accounts", "401(K) with employer match", "Flexibility in work schedules", "Generous time off", "The starting salary for this role is between $120,000 and $150,000", "Our salary ranges are based on third-party national average market compensation analysis"]}, "job_job_title": "Sr. director", "job_posting_language": "en", "job_onet_soc": "11202100", "job_onet_job_zone": "4"}