{"job_id": "TrS4eoxfv3yDZcq4AAAAAA==", "employer_name": "Sweety High Media", "employer_logo": "https://encrypted-tbn0.gstatic.com/images?q=tbn:ANd9GcRh_3Mftwsql189MdAJ6ICbxtwMlR0TicVRf0p7&s=0", "employer_website": null, "employer_company_type": null, "job_publisher": "LinkedIn", "job_employment_type": "FULLTIME", "job_title": "VP/Director of Brand Partnership Marketing", "job_apply_link": "https://www.linkedin.com/jobs/view/vp-director-of-brand-partnership-marketing-at-sweety-high-media-3849966374", "job_apply_is_direct": false, "job_apply_quality_score": 0.6288, "apply_options": [{"publisher": "LinkedIn", "apply_link": "https://www.linkedin.com/jobs/view/vp-director-of-brand-partnership-marketing-at-sweety-high-media-3849966374", "is_direct": false}], "job_description": "DIGITAL FUTURES / SWEETY HIGH MEDIA VP/DIRECTOR OF BRAND PARTNERSHIP\n\nJob Title: VP/Director of Brand Partnership Marketing (DOE)\n\nAgency Name: Digital Futures and Sweety High Media\n\nReports To: CEO + CCO\n\nDirect Reports: Frank Simonetti and Veronica Zelle\n\nEngagement Type: Full-Time\n\nLocation + Work Policy: Hybrid, Los Angeles\n\nCompany Overview\n\nSweety High Media is the culture-leading vertical media business serving the Gen Z audience. As a platform,\n\nstudio, growth agency and music business, we\u2019re highly creative and differentiated in serving this critical niche.\n\nWe work with the top studios, labels, artists and brands to deliver authenticity and value to our end consumers in\n\nan inclusive environment.\n\nRole Overview\n\nSweety High Media is seeking an experienced marketing professional to join our Brand Marketing team. This Sr.\n\nDirector of Brand Marketing serves as the primary lead on all custom, cross-platform solutions and client\n\nmaterials to support our growing media portfolio. This role is for a thought leader who can move between ideation,\n\ncollateral development, packaging, and pitching to onboarding clients and helping manage those high profile\n\nrelationships.\n\nThis is a position for an experienced and creative marketer. You will be responsible for supporting sales efforts\n\nwith a thorough understanding of Sweety High Media\u2019s network portfolio. You will work closely with the CEO,\n\nCCO, Production and Fulfillment teams to drive commercial success by balancing pricing, performance and brand\n\nequity.\n\nYou will be a dynamic and thoughtful innovator who solves brand challenges by utilizing Sweety High Media\u2019s\n\nrobust client solutions. We are looking for someone capable of developing in-house brand materials as well as\n\ntailored campaigns for both agencies and brand-direct clients with thought-leading executions in entertainment,\n\nCPG and adjacent market sectors.\n\nGrowth Path Roles\n\n\u25cf VP, Brand Partnership Marketing\n\n\u25cf SVP, Brand Marketing\n\nResponsibilities\n\n\u25cf Thorough understanding of Sweety High Media value proposition and market positioning\n\n\u25cf Concept and craft custom brand campaigns through best-in-class proposals and presentations\n\n\u25cf Collaborate with Editorial, and Production teams to identify, create and package new proactive programs\n\nand sales opportunities\n\n\u25cf Develop integrated advertising packages (content, creators, experiential) from ideation to formal or\n\ninformal response to proactive or reactive (RFP/RFI) needs\n\n\u25cf Create research, media and marketing plans alongside proposal materials and socialize with clients\n\n\u25cf Create and manage brand marketing materials, including case studies and sell sheets across Sweety High\n\nMedia and Digital Futures products\n\n\u25cf Build Sweety High Media/Digital Futures capabilities presentations that showcase the Sweety High Media\n\nstory, audience insights, and creative solutions\n\n\u25cf Oversee in-house data studies and project management\n\n\u25cf Act as a key client liaison to help ensure campaigns are successful and oversee reporting\n\nRequirements (Skills & Experience)\n\n\u25cf 8+ years of digital marketing experience in Integrated Marketing, Client Solutions, and/or Creative\n\nServices role for a B2C Publisher, media agency or brand\n\n\u25cf Core Google Suite, Keynote, MS Excel, MS Word\n\n\u25cf Experience executing strategy, content, talent and social media focused campaigns\n\n\u25cf Knowledge of analytics reporting across Social Media platforms and Ad Manager\n\n\u25cf Experience working across multiple stakeholders with the ability to articulate, aggregate and deliver on\n\nkey milestones\n\n\u25cf Demonstrable track record of creating culture leading marketing and content programs, working with\n\ndesigners, producers and clients that track to yield and margin.\n\n\u25cf Strong creative and tactical mindset. Ability to think both in and out of the box as needed\n\n\u25cf for clients with a knack for writing marketing copy\n\n\u25cf Detail-oriented, thrive on multitasking and high performance\n\n\u25cf Excellent verbal and written communication skills, with a taste for design and creative storytelling\n\n\u25cf The ability to work independently and as a leader across multifunctional teams\n\n\u25cf Experience with custom content, the creative economy and social growth\n\n\u25cf Positive attitude, energetic and passionate about pop culture and the Gen Z media landscape\n\n\u25cf Exceptional organizational and time-management skills", "job_is_remote": false, "job_posted_at_timestamp": 1710338874, "job_posted_at_datetime_utc": "2024-03-13T14:07:54.000Z", "job_city": "Los Angeles", "job_state": "CA", "job_country": "US", "job_latitude": 34.05491, "job_longitude": -118.242645, "job_benefits": null, "job_google_link": "https://www.google.com/search?gl=us&hl=en&rciv=jb&q=director+of+brand+partnerships&start=0&ibp=htl;jobs#fpstate=tldetail&htivrt=jobs&htiq=director+of+brand+partnerships&htidocid=TrS4eoxfv3yDZcq4AAAAAA%3D%3D", "job_offer_expiration_datetime_utc": "2024-04-12T14:07:54.000Z", "job_offer_expiration_timestamp": 1712930874, "job_required_experience": {"no_experience_required": false, "required_experience_in_months": 96, "experience_mentioned": true, "experience_preferred": false}, "job_required_skills": ["Attitude Change", "Sell Sheets", "Job Skills", "Integrated Marketing", "Milestones", "VBA Excel", "Positioning (Marketing)", "Defining Requirements", "Pop Culture", "Client Liaison"], "job_required_education": {"postgraduate_degree": false, "professional_certification": false, "high_school": false, "associates_degree": false, "bachelors_degree": true, "degree_mentioned": false, "degree_preferred": false, "professional_certification_mentioned": false}, "job_experience_in_place_of_education": false, "job_min_salary": null, "job_max_salary": null, "job_salary_currency": null, "job_salary_period": null, "job_highlights": {"Qualifications": ["This is a position for an experienced and creative marketer", "8+ years of digital marketing experience in Integrated Marketing, Client Solutions, and/or Creative", "Core Google Suite, Keynote, MS Excel, MS Word", "Experience executing strategy, content, talent and social media focused campaigns", "Knowledge of analytics reporting across Social Media platforms and Ad Manager", "Experience working across multiple stakeholders with the ability to articulate, aggregate and deliver on", "Strong creative and tactical mindset", "Ability to think both in and out of the box as needed", "for clients with a knack for writing marketing copy", "Detail-oriented, thrive on multitasking and high performance", "Excellent verbal and written communication skills, with a taste for design and creative storytelling", "The ability to work independently and as a leader across multifunctional teams", "Experience with custom content, the creative economy and social growth", "Positive attitude, energetic and passionate about pop culture and the Gen Z media landscape", "Exceptional organizational and time-management skills"], "Responsibilities": ["Director of Brand Marketing serves as the primary lead on all custom, cross-platform solutions and client", "This role is for a thought leader who can move between ideation,", "collateral development, packaging, and pitching to onboarding clients and helping manage those high profile", "You will be responsible for supporting sales efforts", "You will work closely with the CEO,", "CCO, Production and Fulfillment teams to drive commercial success by balancing pricing, performance and brand", "You will be a dynamic and thoughtful innovator who solves brand challenges by utilizing Sweety High Media\u2019s", "tailored campaigns for both agencies and brand-direct clients with thought-leading executions in entertainment,", "Thorough understanding of Sweety High Media value proposition and market positioning", "Concept and craft custom brand campaigns through best-in-class proposals and presentations", "Collaborate with Editorial, and Production teams to identify, create and package new proactive programs", "Develop integrated advertising packages (content, creators, experiential) from ideation to formal or", "informal response to proactive or reactive (RFP/RFI) needs", "Create research, media and marketing plans alongside proposal materials and socialize with clients", "Create and manage brand marketing materials, including case studies and sell sheets across Sweety High", "Oversee in-house data studies and project management", "Act as a key client liaison to help ensure campaigns are successful and oversee reporting", "Demonstrable track record of creating culture leading marketing and content programs, working with", "designers, producers and clients that track to yield and margin"]}, "job_job_title": "Marketing", "job_posting_language": "en", "job_onet_soc": "11202100", "job_onet_job_zone": "4"}