{"job_id": "zt2Z60K_iLuWPguVAAAAAA==", "employer_name": "Ekimetrics", "employer_logo": null, "employer_website": null, "employer_company_type": null, "job_publisher": "Lever", "job_employment_type": "FULLTIME", "job_title": "Manager in Marketing Analytics & Data Science - New York & Los Angeles", "job_apply_link": "https://jobs.lever.co/ekimetrics/759f620b-88d7-458c-8ab3-4f93a164b72e", "job_apply_is_direct": false, "job_apply_quality_score": 0.7792, "apply_options": [{"publisher": "Lever", "apply_link": "https://jobs.lever.co/ekimetrics/759f620b-88d7-458c-8ab3-4f93a164b72e", "is_direct": false}, {"publisher": "Built In", "apply_link": "https://builtin.com/job/senior-manager-marketing-analytics-data-science-new-york-los-angeles/1500304", "is_direct": false}, {"publisher": "Glassdoor", "apply_link": "https://www.glassdoor.com/job-listing/manager-in-marketing-analytics-data-science-new-york-los-angeles-ekimetrics-JV_KO0,64_KE65,75.htm?jl=1008767277589", "is_direct": false}, {"publisher": "Startup Jobs", "apply_link": "https://startup.jobs/senior-manager-in-marketing-analytics-data-science-new-york-los-angeles-ekimetrics-2774678", "is_direct": false}, {"publisher": "Indeed", "apply_link": "https://www.indeed.com/viewjob?jk=f079c15874c5cafa", "is_direct": false}, {"publisher": "Simplify", "apply_link": "https://simplify.jobs/p/980cf3a4-eb9d-4e3e-9abf-c7e888cfecad/Manager-in-Marketing-Analytics--Data-Science", "is_direct": false}], "job_description": "Ekimetrics is a leader in data science and AI-powered solutions. For over 16 years, we\u2019ve pioneered the use of AI and advanced data science applied to unified marketing measurement, holistic business optimization and broad-ranging sustainability goals.\n\nOur goal: combine high impact with long-term business purpose.\n\nEkimetrics is one of the world\u2019s largest independent analytics firms with offices on 3 continents, and with more than 400 data experts. Since 2006, we have led more than a thousand data science projects in over 50 countries, generating more than $1bn in profit for our customers.\n\nWe help companies rethink the way they operate, so they can reconcile financial KPIs with non-financial goals. We are uniquely specialized in creating scalable data and analytics solutions that drive high-impact optimizations in alignment with overarching brand strategy and sustainability goals.\n\nAt Ekimetrics, we believe our best assets are our people. They are what set us apart and drive our success with entrepreneurial spirit and innovation. We encourage entrepreneurial spirit and innovation. We share what we know with others, and, above all, we love what we do. These sentiments are supported by our company values which serve as pillars in our work and attitude: curiosity, creativity, excellence, transmission, and pleasure.\n\nContext:\n\nTo sustain our quick growth, we are seeking a Manager to join our team in New York.\n\nThe successful candidate will show both analytic skills and strong interest for marketing & business strategy.\n\nThe Manager plays a key role in Ekimetrics organization. They will be contributing to the growth and health of the company, including providing thorough leadership by closely working with the Ekimetrics Management team.\n\nThe ideal candidate will focus on delivering analytics projects that will lead to significant, value-led transformation for our clients. This requires building strong client relationships by understanding their needs and offering the right solutions.\n\nJob Responsibilities:\n\u2022 Client facing\n\nOwnership on the client relationship of the managed accounts. Promote a confidence and proximity relationship with blue chip clients at EXEC Level\n\nEnsure the day-to-day operational management of key accounts and coordinate several projects simultaneously.\n\nCultivating your external network with a client centric approach\n\u2022 Data Science and Modeling\n\nResponsible for the production of statistics and econometrics modeling\n\nEnsure the respect of Ekimetrics standards of Excellence on the strategic recommendations delivered\n\nAbility to manage data scientists\n\u2022 Business Acumen\n\nLead strategic consulting missions for key clients around the company portfolio. The ideal candidate will bring real value into our projects by helping top management to define marketing & business strategic direction and implement changes needed to achieve sustainable performance improvement.\n\nBroad client relationships at VP level in order to achieve new business opportunities.\n\u2022 Team management/People developer\n\nRecruit and align resources to hire, develop staff, manage performance, and create/enhance data scientists at all levels.\n\nActively work with the team to improve team\u2019s engagement, retain top performers and support the development of future leaders at Ekimetrics\n\u2022 Company development\n\nManagers at Ekimetrics are strongly involved in the company\u2019s development initiatives. The successful candidate will be involved in strategic decisions and be a strong representative of Ekimetric\u2019s Culture.\n\nBring leadership insight specific to Industry or functional analytics and continue to build Ekimetrics\u2019 reputation and brand.\n\nCandidate profile\n\u2022 The successful candidate will possess both, a strong track record in analytics & modelling and capacity to conduct business & strategy assignments in order to create value and innovative customer engagements.\n\u2022 The key management consulting skills and experiences will include:\n\u2022 Experience at a consulting firm or other relevant service provider or providing leadership within a highly regarded global corporation with a strong reputation for analytics.\n\u2022 Strong ability to develop new and long lasting client relationships at senior levels (including business leaders) within the sector and a focus on complex analytic issues\n\u2022 Team oriented and collaborative working style, both with clients and those within the organization.\n\u2022 Capacity to develop high impact thought leadership that articulates a forward thinking view of the market.\n\u2022 Demonstrated ability to develop younger talent and build a high performing team.\n\nWhat we offer:\n\nAt Ekimetrics, final base salary is determined by a multitude of factors and vary from candidate to candidate. Determining factors for base compensation include, but are not limited to, professional background, years of experience, and skillset. A reasonable estimate of the base salary for our NYC office is $140,000. In addition to this base salary range, we have a comprehensive benefits package, generous bonus package, and a dynamic promotions and salary raise structure.\n\n- Medical insurance, dental and vision\n\n- An emphasis on work-life-balance and generous PTO\n\n- Dynamic environment with a strong culture and great offices\n\n- Close-knit team with friendly environment, bi-monthly team events and more\n\n- Creative and entrepreneurial start-up environment with vertical mobility\n\n- Best-in-class methodologies and cutting edge technologies\n\n- Unique training package with 70+ sessions\n\n- Growth to develop a double profile in data science and strategic consulting\n\n- Client exposure up to the executive level\n\n- Opportunities for international mobility\n\nEkimetrics is an equal opportunity employer committed to making all employment decisions without regard to race/ethnicity, gender, pregnancy, gender identity or expression, color, creed, religion, national origin, age, disability, marital status (including domestic partnerships and civil unions), sexual orientation, military veteran status, unemployment status, or other legally protected categories, subject to applicable law.\n\nPlease note that we do not offer visa sponsorship or transfer for this position.\n\n$140,000 - $140,000 a year", "job_is_remote": false, "job_posted_at_timestamp": 1568764800, "job_posted_at_datetime_utc": "2019-09-18T00:00:00.000Z", "job_city": null, "job_state": null, "job_country": "US", "job_latitude": 37.09024, "job_longitude": -95.71289, "job_benefits": ["paid_time_off", "dental_coverage", "health_insurance"], "job_google_link": "https://www.google.com/search?gl=us&hl=en&rciv=jb&q=data+science+leader&start=70&ibp=htl;jobs#fpstate=tldetail&htivrt=jobs&htiq=data+science+leader&htidocid=zt2Z60K_iLuWPguVAAAAAA%3D%3D", "job_offer_expiration_datetime_utc": null, "job_offer_expiration_timestamp": null, "job_required_experience": {"no_experience_required": false, "required_experience_in_months": null, "experience_mentioned": true, "experience_preferred": false}, "job_required_skills": null, "job_required_education": {"postgraduate_degree": false, "professional_certification": false, "high_school": false, "associates_degree": false, "bachelors_degree": false, "degree_mentioned": false, "degree_preferred": false, "professional_certification_mentioned": false}, "job_experience_in_place_of_education": false, "job_min_salary": null, "job_max_salary": null, "job_salary_currency": null, "job_salary_period": null, "job_highlights": {"Qualifications": ["Ability to manage data scientists", "Business Acumen", "The successful candidate will possess both, a strong track record in analytics & modelling and capacity to conduct business & strategy assignments in order to create value and innovative customer engagements", "Experience at a consulting firm or other relevant service provider or providing leadership within a highly regarded global corporation with a strong reputation for analytics", "Strong ability to develop new and long lasting client relationships at senior levels (including business leaders) within the sector and a focus on complex analytic issues", "Team oriented and collaborative working style, both with clients and those within the organization", "Capacity to develop high impact thought leadership that articulates a forward thinking view of the market", "Demonstrated ability to develop younger talent and build a high performing team"], "Responsibilities": ["The Manager plays a key role in Ekimetrics organization", "They will be contributing to the growth and health of the company, including providing thorough leadership by closely working with the Ekimetrics Management team", "The ideal candidate will focus on delivering analytics projects that will lead to significant, value-led transformation for our clients", "This requires building strong client relationships by understanding their needs and offering the right solutions", "Client facing", "Ownership on the client relationship of the managed accounts", "Promote a confidence and proximity relationship with blue chip clients at EXEC Level", "Ensure the day-to-day operational management of key accounts and coordinate several projects simultaneously", "Cultivating your external network with a client centric approach", "Data Science and Modeling", "Responsible for the production of statistics and econometrics modeling", "Ensure the respect of Ekimetrics standards of Excellence on the strategic recommendations delivered", "Lead strategic consulting missions for key clients around the company portfolio", "The ideal candidate will bring real value into our projects by helping top management to define marketing & business strategic direction and implement changes needed to achieve sustainable performance improvement", "Broad client relationships at VP level in order to achieve new business opportunities", "Team management/People developer", "Recruit and align resources to hire, develop staff, manage performance, and create/enhance data scientists at all levels", "Actively work with the team to improve team\u2019s engagement, retain top performers and support the development of future leaders at Ekimetrics", "The successful candidate will be involved in strategic decisions and be a strong representative of Ekimetric\u2019s Culture", "Bring leadership insight specific to Industry or functional analytics and continue to build Ekimetrics\u2019 reputation and brand"], "Benefits": ["At Ekimetrics, final base salary is determined by a multitude of factors and vary from candidate to candidate", "Determining factors for base compensation include, but are not limited to, professional background, years of experience, and skillset", "A reasonable estimate of the base salary for our NYC office is $140,000", "In addition to this base salary range, we have a comprehensive benefits package, generous bonus package, and a dynamic promotions and salary raise structure", "Medical insurance, dental and vision", "An emphasis on work-life-balance and generous PTO", "Dynamic environment with a strong culture and great offices", "Close-knit team with friendly environment, bi-monthly team events and more", "Unique training package with 70+ sessions", "Client exposure up to the executive level", "Opportunities for international mobility", "$140,000 - $140,000 a year"]}, "job_job_title": "Manager", "job_posting_language": "en", "job_onet_soc": "15204100", "job_onet_job_zone": "5"}