{"job_id": "R5qj8JVxVQo1cMwRAAAAAA==", "employer_name": "Oracle", "employer_logo": "https://upload.wikimedia.org/wikipedia/commons/thumb/5/50/Oracle_logo.svg/2560px-Oracle_logo.svg.png", "employer_website": "http://www.oracle.com", "employer_company_type": "Information", "job_publisher": "Adzuna", "job_employment_type": "FULLTIME", "job_title": "Director of Machine Learning Engineering", "job_apply_link": "https://www.adzuna.com/details/4606063114", "job_apply_is_direct": false, "job_apply_quality_score": 0.5193, "apply_options": [{"publisher": "Adzuna", "apply_link": "https://www.adzuna.com/details/4606063114", "is_direct": false}], "job_description": "Job Description\nAt Oracle Cloud Infrastructure (OCI), we build the future of the cloud for Enterprises as a diverse team of fellow creators and inventors. We act with the speed and attitude of a start-up, with the scale and customer-focus of the leading enterprise software company in the world.\nOracle Generative AI Services is an exciting team in Oracle Cloud Infrastructure. We are delivering innovative services at the intersection of artificial intelligence and cloud infrastructure. In Generative AI Services team, you will build and operate massive-scale cloud services leveraging state of art machine learning technologies. We are committed to providing the best in cloud products to meet the needs of our customers who are tackling some of the world's most challenging problems.\nWe're looking for a Director of Machine Learning Engineering with expertise and passion in building teams, coaching individuals, and solving difficult problems in LLM (Large Language Model) training and serving infrastructure.\nAs a Director of Machine Learning Engineering, you will build and lead Machine Learning Engineering teams to define, design, develop service and infrastructure with cutting edge technology. You would be responsible to provide leadership, direction, and strategy to the team, establish and develop the team to meet and execute the strategy, working with geographically distributed teams, and contributing to the success of your team and other related teams. We expect you to deliver large-scale projects on time with high quality.\nRequired Qualifications\n- MS or BS in Computer Science, or equivalent experience\n- 5+ years of experience managing Machine Learning Engineering teams.\n- 12+ years of software engineering experience\n- Strong communication skills, analytical skills, and project management skills\n- Experience in AI model performance optimization and pushing model to production.\n- Experience in AI model training infrastructure.\n- Strong knowledge of data structures, algorithms, operating systems, networking and distributed systems fundamentals\nPreferred Qualifications\n- Production experience with cloud computing.\n- Experience with Large Language Model (LLM) serving technologies like DeepSpeed, FasterTransformer, vLLM etc.\n- Experience with popular model training and serving frameworks like KServe, KubeFlow, Triton etc.\n- Experience with LLM fine-tuning, especially the latest parameter efficient fine-tuning technologies and multi-task serving technologies\n- Experience with deep learning frameworks (such as PyTorch, JAX, or TensorFlow) and deep learning architectures (especially Transformers).\n- Experience in diagnosing, fixing and resolving issues in AI model training and serving\nResponsibilities\nAs a Director of Machine Learning Engineering, you will build and lead Machine Learning Engineering teams to define, design, develop service and infrastructure with cutting edge technology. You would be responsible to provide leadership, direction, and strategy to the team, establish and develop the team to meet and execute the strategy, working with geographically distributed teams, and contributing to the success of your team and other related teams. We expect you to deliver large-scale projects on time with high quality.\nAssists in the development of short, medium, and long term plans to achieve strategic objectives. Regularly interacts across functional areas with senior management or executives to ensure unit objectives are met. Ability to influence thinking or gain acceptance of others in sensitive situations. Demonstrated leadership and people management skills. Strong communication skills, analytical skills, thorough understanding of product development.\nDisclaimer:\nCertain US customer or client-facing roles may be required to comply with applicable requirements, such as immunization and occupational health mandates.\nRange and benefit information provided in this posting are specific to the stated locations only\nUS: Hiring Range: from $120,300 to $291,900 per annum. May be eligible for bonus, equity, and compensation deferral.\nOracle maintains broad salary ranges for its roles in order to account for variations in knowledge, skills, experience, market conditions and locations, as well as reflect Oracle's differing products, industries and lines of business.\nCandidates are typically placed into the range based on the preceding factors as well as internal peer equity.\nOracle US offers a comprehensive benefits package which includes the following:\n- Medical, dental, and vision insurance, including expert medical opinion\n- Short term disability and long term disability\n- Life insurance and AD&D\n- Supplemental life insurance (Employee/Spouse/Child)\n- Health care and dependent care Flexible Spending Accounts\n- Pre-tax commuter and parking benefits\n- 401(k) Savings and Investment Plan with company match\n- Paid time off: Flexible Vacation is provided to all eligible employees assigned to a salaried (non-overtime eligible) position. Accrued Vacation is provided to all other employees eligible for vacation benefits. For employees working at least 35 hours per week, the vacation accrual rate is 13 days annually for the first three years of employment and 18 days annually for subsequent years of employment. Vacation accrual is prorated for employees working between 20 and 34 hours per week. Employees working fewer than 20 hours per week are not eligible for vacation.\n- 11 paid holidays\n- Paid sick leave: 72 hours of paid sick leave upon date of hire. Refreshes each calendar year. Unused balance will carry over each year up to a maximum cap of 112 hours.\n- Paid parental leave\n- Adoption assistance\n- Employee Stock Purchase Plan\n- Financial planning and group legal\n- Voluntary benefits including auto, homeowner and pet insurance\nAbout Us\nAs a world leader in cloud solutions, Oracle uses tomorrow's technology to tackle today's problems. True innovation starts with diverse perspectives and various abilities and backgrounds.\nWhen everyone's voice is heard, we're inspired to go beyond what's been done before. It's why we're committed to expanding our inclusive workforce that promotes diverse insights and perspectives.\nWe've partnered with industry-leaders in almost every sector-and continue to thrive after 40+ years of change by operating with integrity.\nOracle careers open the door to global opportunities where work-life balance flourishes. We offer a highly competitive suite of employee benefits designed on the principles of parity and consistency. We put our people first with flexible medical, life insurance and retirement options. We also encourage employees to give back to their communities through our volunteer programs.\nWe're committed to including people with disabilities at all stages of the employment process. If you require accessibility assistance or accommodation for a disability at any point, let us know by calling +1 888 404 2494, option one.\nDisclaimer:\nOracle is an Equal Employment Opportunity Employer*. All qualified applicants will receive consideration for employment without regard to race, color, religion, sex, national origin, sexual orientation, gender identity, disability and protected veterans' status, or any other characteristic protected by law. Oracle will consider for employment qualified applicants with arrest and conviction records pursuant to applicable law.\n- Which includes being a United States Affirmative Action Employer", "job_is_remote": false, "job_posted_at_timestamp": 1710321350, "job_posted_at_datetime_utc": "2024-03-13T09:15:50.000Z", "job_city": "Lansing", "job_state": "MI", "job_country": "US", "job_latitude": 42.732536, "job_longitude": -84.555534, "job_benefits": ["dental_coverage", "paid_time_off", "health_insurance", "retirement_savings"], "job_google_link": "https://www.google.com/search?gl=us&hl=en&rciv=jb&q=machine+learning&start=50&ibp=htl;jobs#fpstate=tldetail&htivrt=jobs&htiq=machine+learning&htidocid=R5qj8JVxVQo1cMwRAAAAAA%3D%3D", "job_offer_expiration_datetime_utc": "2024-03-27T20:25:57.000Z", "job_offer_expiration_timestamp": 1711571157, "job_required_experience": {"no_experience_required": false, "required_experience_in_months": 60, "experience_mentioned": true, "experience_preferred": false}, "job_required_skills": null, "job_required_education": {"postgraduate_degree": false, "professional_certification": false, "high_school": false, "associates_degree": false, "bachelors_degree": false, "degree_mentioned": true, "degree_preferred": true, "professional_certification_mentioned": false}, "job_experience_in_place_of_education": false, "job_min_salary": null, "job_max_salary": null, "job_salary_currency": null, "job_salary_period": null, "job_highlights": {"Qualifications": ["MS or BS in Computer Science, or equivalent experience", "5+ years of experience managing Machine Learning Engineering teams", "12+ years of software engineering experience", "Strong communication skills, analytical skills, and project management skills", "Experience in AI model performance optimization and pushing model to production", "Experience in AI model training infrastructure", "Strong knowledge of data structures, algorithms, operating systems, networking and distributed systems fundamentals", "Ability to influence thinking or gain acceptance of others in sensitive situations", "Demonstrated leadership and people management skills", "Strong communication skills, analytical skills, thorough understanding of product development", "Which includes being a United States Affirmative Action Employer"], "Responsibilities": ["As a Director of Machine Learning Engineering, you will build and lead Machine Learning Engineering teams to define, design, develop service and infrastructure with cutting edge technology", "You would be responsible to provide leadership, direction, and strategy to the team, establish and develop the team to meet and execute the strategy, working with geographically distributed teams, and contributing to the success of your team and other related teams", "We expect you to deliver large-scale projects on time with high quality", "Assists in the development of short, medium, and long term plans to achieve strategic objectives", "Regularly interacts across functional areas with senior management or executives to ensure unit objectives are met"], "Benefits": ["US: Hiring Range: from $120,300 to $291,900 per annum", "May be eligible for bonus, equity, and compensation deferral", "Oracle maintains broad salary ranges for its roles in order to account for variations in knowledge, skills, experience, market conditions and locations, as well as reflect Oracle's differing products, industries and lines of business", "Medical, dental, and vision insurance, including expert medical opinion", "Short term disability and long term disability", "Life insurance and AD&D", "Supplemental life insurance (Employee/Spouse/Child)", "Health care and dependent care Flexible Spending Accounts", "Pre-tax commuter and parking benefits", "401(k) Savings and Investment Plan with company match", "Paid time off: Flexible Vacation is provided to all eligible employees assigned to a salaried (non-overtime eligible) position", "Accrued Vacation is provided to all other employees eligible for vacation benefits", "For employees working at least 35 hours per week, the vacation accrual rate is 13 days annually for the first three years of employment and 18 days annually for subsequent years of employment", "Vacation accrual is prorated for employees working between 20 and 34 hours per week", "Employees working fewer than 20 hours per week are not eligible for vacation", "11 paid holidays", "Paid sick leave: 72 hours of paid sick leave upon date of hire", "Unused balance will carry over each year up to a maximum cap of 112 hours", "Paid parental leave", "Adoption assistance", "Employee Stock Purchase Plan", "Financial planning and group legal", "Voluntary benefits including auto, homeowner and pet insurance", "We offer a highly competitive suite of employee benefits designed on the principles of parity and consistency"]}, "job_job_title": "Engineering", "job_posting_language": "en", "job_onet_soc": "15111100", "job_onet_job_zone": "5", "job_naics_code": "511210", "job_naics_name": "Software Publishers"}