{"job_id": "X-HSgOPEMT6S-OchAAAAAA==", "employer_name": "spglobal", "employer_logo": "http://vignette2.wikia.nocookie.net/logopedia/images/3/3d/S%26P_Global_Logo.png/revision/latest/scale-to-width-down/640?cb=20161128193916", "employer_website": "http://www.spglobal.com", "employer_company_type": "Finance", "job_publisher": "AdWeek Jobs", "job_employment_type": "FULLTIME", "job_title": "Senior Sales Manager (Conference Sponsorship and Advertising)", "job_apply_link": "https://jobs.adweek.com/job/senior-sales-manager-conference-sponsorship-and-advertising-houston-tx-fb1a8645c70d2c62724471b1f5835a5fb", "job_apply_is_direct": false, "job_apply_quality_score": 0.6556, "apply_options": [{"publisher": "AdWeek Jobs", "apply_link": "https://jobs.adweek.com/job/senior-sales-manager-conference-sponsorship-and-advertising-houston-tx-fb1a8645c70d2c62724471b1f5835a5fb", "is_direct": false}], "job_description": "The Role: Senior Sales Manager (Conference Sponsorship and Advertising)\n\nThe Location: New York, Houston, Denver\n\nThe Team: The Conferences, Training & Strategic Media team manages a portfolio of cross-commodity industry-leading events and media solutions. We engage, and connect clients, business leaders and industry experts in an environment of knowledge excellence to extend insights capture the moment and take critical conversations forward on key topics in the Energy and related arenas.\n\nThe team delivers approximately twenty global events per year, engaging industry at C-Suite and executive levels, showcasing our own Energy, Oil, Gas, Chemicals and Commodities experts across a wide range of markets and pricing dynamics. Our focus Energy Transition where we offer a unique sector- leading capability. Our industry Training enables companies to maintain strong human resource capabilities in a competitive and complex marketplace of technical and business expertise. Our Strategic Media solutions support marketing initiatives of leading corporations worldwide.\n\nThe Impact: The Senior Sales Manager is a critical part of our growth trajectory in generating new revenue and engaging new clients, by building and executing a dynamic sales strategy to achieve ambitious revenue growth for our events and strategic media. Our Sales activity intersects with the S&P Global sales team for wider effect and offers clients a platform to access our extensive global reach.\n\nResponsibilities:\n\u2022 Generate conference sponsorship, digital advertising, and printed advertising revenue by opening new opportunities through face-to-face and telephone selling.\n\u2022 Actively seek out and follow through on new prospects from all relevant sources. Actively source and develop new business areas relevant to the events and to the strategic media plan.\n\u2022 Build strong and long-term relationships to maximize client engagement.\n\u2022 Improve growth and retention of the existing business through strategic account management.\n\u2022 Joint responsibility for all sectors of the event including sales planning, campaign management, forecasting, and achieving the sales target.\n\u2022 Preparation of event specific sales plans and use market knowledge to input into the overall strategic direction of the conference.\n\u2022 Maintain effective relationships with:\n\u2022 Internal sales team ensuring that they are fully briefed on conference details. Regularly monitor their revenue generation for your event and escalate any issues as appropriate.\n\u2022 Trade associations, either as a strategic partner and/or as a S&P Global customer.\n\u2022 Fully understand the event model and the strategic media model.\n\u2022 Communicate across all disciplines (production, marketing, operations, finance) to ensure market intelligence is shared in order to maximize on potential opportunities.\n\u2022 Accurately and efficiently manage the sales dashboard and the sales pipeline.\n\u2022 Maintain and update the sales pipeline with relevant contacts, notes and market intelligence.\n\u2022 Monitor and plan own [and team] sales activity and regularly monitor the sales pipeline accordingly.\n\u2022 Work with marketing to manage the entire sales promotion campaign ensuring targeted, timely and appropriate communications are sent out to the prospect base. Full management of campaigns and tracking of sales plan effectiveness.\n\u2022 Work closely with the event team to develop targeted partners promotional campaigns according to the sales plan.\n\u2022 Have a creative approach with a keen eye on revenue generation from event related and non-event related activities and participate in ad hoc business projects as required.\n\u2022 Attend S&P Global events and competitor, industry and trade association events (both domestically and internationally) thereby obtaining industry and market intelligence, maintaining and creating new relationships, expanding the database and prospecting for new business.\n\u2022 Write sales reports as required.\n\u2022 Work with finance on debt collection pre and post show.\n\nWhat We\u2019re Looking For: A target driven and enthusiastic sales professional who can demonstrate the following:\n\u2022 10 years strong sales experience in a relevant environment (conferences sponsorship, digital advertising, publishing, etc.) with a track record in generating new business.\n\u2022 Knowledge of Energy, Oil, Gas, Chemicals and Commodities sectors preferred.\n\u2022 Proven experience in consultative and value led selling, negotiating and objection handling, maximizing revenue from new and existing customers by demonstrating innovation and creativity in ideas.\n\u2022 Proven experience in international sales and tailoring the selling style to reflect cultural etiquette.\n\u2022 An ability to assimilate and practice key account management principles.\n\u2022 An ability to build long-term, sustainable and profitable relationships with customers.\n\u2022 Excellent interpersonal skills at all levels.\n\u2022 Strong written and oral communication skills, including presentations and report writing.\n\u2022 Empathy and understanding of other cultures within a commercial context.\n\u2022 Experience in developing and implementing successful Sales Strategies.\n\u2022 Ability to assess and explain the long-term impact of new practices by undertaking a high level of analysis to assess risk.\n\u2022 Keen eye for development of additional revenue opportunities outside of personal area of responsibility.\n\nReturn to Work\n\nHave you taken time out for caring responsibilities and are now looking to return to work? As part of our Return to Work initiative (link to career site page when available), we are encouraging enthusiastic and talented returners to apply, and will actively support your return to the workplace.\n\nGrade/Level (relevant for internal applicants only): Grade 11\n\nAbout Company Statement:\n\nS&P Global delivers essential intelligence that powers decision making. We provide the world\u2019s leading organizations with the right data, connected technologies and expertise they need to move ahead. As part of our team, you\u2019ll help solve complex challenges that equip businesses, governments and individuals with the knowledge to adapt to a changing economic landscape.\n\nS&P Global Commodity Insights enables organizations to create long-term, sustainable value with data and insights for a complete view on the global energy and commodities markets.\n\n-----------------------------------------------------------\n\nEqual Opportunity Employer\n\nS&P Global is an equal opportunity employer and all qualified candidates will receive consideration for employment without regard to race/ethnicity, color, religion, sex, sexual orientation, gender identity, national origin, age, disability, marital status, military veteran status, unemployment status, or any other status protected by law. Only electronic job submissions will be considered for employment.\n\nIf you need an accommodation during the application process due to a disability, please send an email to: EEO.Compliance@spglobal.com and your request will be forwarded to the appropriate person.\n\nUS Candidates Only: The EEO is the Law Poster http://www.dol.gov/ofccp/regs/compliance/posters/pdf/eeopost.pdf describes discrimination protections under federal law.\n\n-----------------------------------------------------------\n40 - Sales (EEO-2 Job Categories-United States of America), SLSOUS402.2 - Middle Professional Tier II-Ou Sales (EEO Job Group)\n\nJob ID: 294212\nPosted On: 2023-11-27\nLocation: New York, New York, United States", "job_is_remote": false, "job_posted_at_timestamp": 1701838800, "job_posted_at_datetime_utc": "2023-12-06T05:00:00.000Z", "job_city": "Houston", "job_state": "TX", "job_country": "US", "job_latitude": 29.760427, "job_longitude": -95.369804, "job_benefits": null, "job_google_link": "https://www.google.com/search?gl=us&hl=en&rciv=jb&q=sponsorship+sales+manager&start=0&ibp=htl;jobs#fpstate=tldetail&htivrt=jobs&htiq=sponsorship+sales+manager&htidocid=X-HSgOPEMT6S-OchAAAAAA%3D%3D", "job_offer_expiration_datetime_utc": null, "job_offer_expiration_timestamp": null, "job_required_experience": {"no_experience_required": false, "required_experience_in_months": 120, "experience_mentioned": true, "experience_preferred": false}, "job_required_skills": null, "job_required_education": {"postgraduate_degree": false, "professional_certification": false, "high_school": false, "associates_degree": false, "bachelors_degree": false, "degree_mentioned": true, "degree_preferred": false, "professional_certification_mentioned": false}, "job_experience_in_place_of_education": false, "job_min_salary": null, "job_max_salary": null, "job_salary_currency": null, "job_salary_period": null, "job_highlights": {"Qualifications": ["10 years strong sales experience in a relevant environment (conferences sponsorship, digital advertising, publishing, etc.) with a track record in generating new business", "Proven experience in consultative and value led selling, negotiating and objection handling, maximizing revenue from new and existing customers by demonstrating innovation and creativity in ideas", "Proven experience in international sales and tailoring the selling style to reflect cultural etiquette", "An ability to assimilate and practice key account management principles", "An ability to build long-term, sustainable and profitable relationships with customers", "Excellent interpersonal skills at all levels", "Strong written and oral communication skills, including presentations and report writing", "Empathy and understanding of other cultures within a commercial context", "Experience in developing and implementing successful Sales Strategies", "Ability to assess and explain the long-term impact of new practices by undertaking a high level of analysis to assess risk"], "Responsibilities": ["Generate conference sponsorship, digital advertising, and printed advertising revenue by opening new opportunities through face-to-face and telephone selling", "Actively seek out and follow through on new prospects from all relevant sources", "Actively source and develop new business areas relevant to the events and to the strategic media plan", "Build strong and long-term relationships to maximize client engagement", "Improve growth and retention of the existing business through strategic account management", "Joint responsibility for all sectors of the event including sales planning, campaign management, forecasting, and achieving the sales target", "Preparation of event specific sales plans and use market knowledge to input into the overall strategic direction of the conference", "Maintain effective relationships with:", "Internal sales team ensuring that they are fully briefed on conference details", "Regularly monitor their revenue generation for your event and escalate any issues as appropriate", "Trade associations, either as a strategic partner and/or as a S&P Global customer", "Fully understand the event model and the strategic media model", "Communicate across all disciplines (production, marketing, operations, finance) to ensure market intelligence is shared in order to maximize on potential opportunities", "Accurately and efficiently manage the sales dashboard and the sales pipeline", "Maintain and update the sales pipeline with relevant contacts, notes and market intelligence", "Monitor and plan own [and team] sales activity and regularly monitor the sales pipeline accordingly", "Work with marketing to manage the entire sales promotion campaign ensuring targeted, timely and appropriate communications are sent out to the prospect base", "Full management of campaigns and tracking of sales plan effectiveness", "Work closely with the event team to develop targeted partners promotional campaigns according to the sales plan", "Have a creative approach with a keen eye on revenue generation from event related and non-event related activities and participate in ad hoc business projects as required", "Attend S&P Global events and competitor, industry and trade association events (both domestically and internationally) thereby obtaining industry and market intelligence, maintaining and creating new relationships, expanding the database and prospecting for new business", "Write sales reports as required", "Work with finance on debt collection pre and post show"], "Benefits": ["Keen eye for development of additional revenue opportunities outside of personal area of responsibility"]}, "job_job_title": "Sales manager", "job_posting_language": "en", "job_onet_soc": "13112100", "job_onet_job_zone": "4", "job_naics_code": "523920", "job_naics_name": "Portfolio Management"}