{"job_id": "-8hoGtPAqGKzUgOnAAAAAA==", "employer_name": "Zayo", "employer_logo": "https://upload.wikimedia.org/wikipedia/commons/1/17/Zayo_Logo_2019.png", "employer_website": "http://www.zayo.com", "employer_company_type": "Information", "job_publisher": "Ladders", "job_employment_type": "FULLTIME", "job_title": "Principal, Senior Sales Manager", "job_apply_link": "https://www.theladders.com/job/principal-senior-sales-manager-zayo-dearing-ks_68405649", "job_apply_is_direct": false, "job_apply_quality_score": 0.5374, "apply_options": [{"publisher": "Ladders", "apply_link": "https://www.theladders.com/job/principal-senior-sales-manager-zayo-dearing-ks_68405649", "is_direct": false}], "job_description": "Company Description\n\nZayo provides mission-critical bandwidth to the world's most impactful companies, fueling the innovations that are transforming our society. Zayo's 141,000-mile network in North America and Europe includes extensive metro connectivity to thousands of buildings and data centers. Zayo's communications infrastructure solutions include dark fiber, private data networks, wavelengths, Ethernet, and dedicated Internet access. Zayo serves wireless and wireline carriers, media, tech, content, finance, healthcare and other large enterprises.\n\nThe Principal, Sr. Sales Manager will lead a team supporting Zayo's largest Cloud, Technology and Infrastructure (Including Satellite, Cableco, FTTH & WISP) Accounts . The successful candidate will execute and drive team selling initiatives to develop customer relationships and drive sales of Connectivity, Data Center Colocation and Cloud Infrastructure services. The Principal is responsible for providing coaching, leadership, and development to a team of Sales professionals, as well as providing sales leadership within Zayo. This role will drive the team to meet and exceed monthly, quarterly, and annual sales goals and provide guidance and counsel throughout the sales process to drive the sales cycle to closure. The ideal candidate has a strong understanding of telecommunications, network connectivity such as Dark Fiber, Wavelengths and Internet Transit services along with the ability to work on large, complex deals applying a consultative and trusted advisor approach.\n\nQualifications\n\u2022 Bachelor's degree or equivalent from four-year College; or equivalent combination of education and experience. 15-20 years' experience solution selling into large accounts primarily headquartered in Texas, Central and Southeast US.\n\u2022 12-15 years' demonstrated experience leading successful sales teams.\n\u2022 Strong financial acumen.\n\u2022 Demonstrated success and consistency in achieving targeted sales goals.\n\u2022 Excellent communication skills, both verbal and written.\n\u2022 Exceptional customer service and relationship building and maintaining skills.\n\u2022 Thorough understanding of account management and the strategic selling process.\n\u2022 Effective problem solving, leadership, and interpersonal skills.\n\u2022 Excellent time management and organizational skills.\n\u2022 A sense of urgency and desire to rapidly accelerate results and career with Zayo Group Sales Possesses excellent interpersonal skills and can work effectively with a diverse group of personalities; must be approachable, show respect for others and be able to present data with effective communication and presentation skills.\n\u2022 Knowledge of Microsoft Word, Excel, and PowerPoint; Salesforce a plus.\n\u2022 Complete understanding of Zayo Networks value proposition, products and services such as Ethernet, OCN, IP Transport, Dark Fiber, Custom Access, and Colocation.\n\u2022 Consistent focus on results and goal achievement. Strong teamwork skills.\n\u2022 Ability to handle ambiguity and anticipate and quickly react to changes in a fast-paced environment.\n\u2022 Ability to travel approximately 30-50% of the time\n\nResponsibilities\n\u2022 Lead a team to generate sales revenue by actively promoting Zayo Network products and services to targeted account base.\n\u2022 Provide coaching to team of Sales representatives in the sale of Zayo products and services to regional account patch\n\u2022 Oversee the teams' recruiting, hiring, and training program; including participation in training new hires as they are onboarded Working closely with Direct Sales and Product Groups Through coaching and technical sales, drive sale closure to shorten sales cycle and ensure sales goals and objectives are achieved\n\u2022 Present proposals and manage customers though the sales process\n\u2022 Maintain current business relationships with customers, securing existing revenue on long-term commitments\n\u2022 Apply knowledge of customers, industry, and services to achieve revenue targets Identify, initiate contact with, and qualify potential customers\n\u2022 Track, analyze and report on sales performance and activities in Zayo's CRM tool and other reporting tools\n\u2022 Develop accurate and timely forecasts of sales opportunities\n\u2022 Develop and maintain records of customer activity for reporting of sales and forecasts\n\u2022 Provide accurate and timely information to management\n\u2022 Coordinate closely with other departments to ensure customer satisfaction is maintained and revenue objectives met\n\u2022 Participate in the creation and delivery of high-level face-to-face sales presentations that demonstrate the latest Zayo products and services\n\u2022 Analyze customer requirements to understand how Zayo products and services can be applied to meet their needs and solve their problems\n\u2022 Keep abreast of the competitive landscape and emerging technologies in order to best position Zayo in the marketplace\n\u2022 Collaboratively work as a part of a team while concurrently performing as an individual with minimal supervision\n\nBase pay range: $89,100 - $130,000, commensurate with experience\n\nBenefits, Rewards & Wellness\n\u2022 Excellent Health, Dental & Vision Insurance\n\u2022 Retirement 401(k) Savings Plan\n\u2022 Fitness membership discounts\n\u2022 Generous paid time off policy including paid parental leave\n\nZayo provides equal employment opportunities to all employees and applicants for employment and prohibits discrimination and harassment of any type without regard to race, color, religion, age, sex, national origin, disability status, genetics, protected veteran status, sexual orientation, gender identity or expression, or any other characteristic protected by federal, state, provincial or local laws.\n\nThis policy applies to all terms and conditions of employment, including recruiting, hiring, placement, promotion, termination, layoff, recall, transfer, leaves of absence, compensation and training.", "job_is_remote": false, "job_posted_at_timestamp": 1709178228, "job_posted_at_datetime_utc": "2024-02-29T03:43:48.000Z", "job_city": "Dearing", "job_state": "KS", "job_country": "US", "job_latitude": 37.057518, "job_longitude": -95.7105, "job_benefits": ["health_insurance", "retirement_savings", "paid_time_off", "dental_coverage"], "job_google_link": "https://www.google.com/search?gl=us&hl=en&rciv=jb&q=senior+sales+manager&start=30&ibp=htl;jobs#fpstate=tldetail&htivrt=jobs&htiq=senior+sales+manager&htidocid=-8hoGtPAqGKzUgOnAAAAAA%3D%3D", "job_offer_expiration_datetime_utc": null, "job_offer_expiration_timestamp": null, "job_required_experience": {"no_experience_required": false, "required_experience_in_months": 180, "experience_mentioned": true, "experience_preferred": false}, "job_required_skills": null, "job_required_education": {"postgraduate_degree": false, "professional_certification": false, "high_school": false, "associates_degree": false, "bachelors_degree": false, "degree_mentioned": true, "degree_preferred": false, "professional_certification_mentioned": false}, "job_experience_in_place_of_education": false, "job_min_salary": 89100, "job_max_salary": 130000, "job_salary_currency": "USD", "job_salary_period": "YEAR", "job_highlights": {"Qualifications": ["Bachelor's degree or equivalent from four-year College; or equivalent combination of education and experience", "15-20 years' experience solution selling into large accounts primarily headquartered in Texas, Central and Southeast US", "12-15 years' demonstrated experience leading successful sales teams", "Strong financial acumen", "Demonstrated success and consistency in achieving targeted sales goals", "Excellent communication skills, both verbal and written", "Exceptional customer service and relationship building and maintaining skills", "Thorough understanding of account management and the strategic selling process", "Effective problem solving, leadership, and interpersonal skills", "Excellent time management and organizational skills", "A sense of urgency and desire to rapidly accelerate results and career with Zayo Group Sales Possesses excellent interpersonal skills and can work effectively with a diverse group of personalities; must be approachable, show respect for others and be able to present data with effective communication and presentation skills", "Complete understanding of Zayo Networks value proposition, products and services such as Ethernet, OCN, IP Transport, Dark Fiber, Custom Access, and Colocation", "Strong teamwork skills", "Ability to handle ambiguity and anticipate and quickly react to changes in a fast-paced environment", "Ability to travel approximately 30-50% of the time"], "Responsibilities": ["The successful candidate will execute and drive team selling initiatives to develop customer relationships and drive sales of Connectivity, Data Center Colocation and Cloud Infrastructure services", "The Principal is responsible for providing coaching, leadership, and development to a team of Sales professionals, as well as providing sales leadership within Zayo", "This role will drive the team to meet and exceed monthly, quarterly, and annual sales goals and provide guidance and counsel throughout the sales process to drive the sales cycle to closure", "Lead a team to generate sales revenue by actively promoting Zayo Network products and services to targeted account base", "Provide coaching to team of Sales representatives in the sale of Zayo products and services to regional account patch", "Oversee the teams' recruiting, hiring, and training program; including participation in training new hires as they are onboarded Working closely with Direct Sales and Product Groups Through coaching and technical sales, drive sale closure to shorten sales cycle and ensure sales goals and objectives are achieved", "Present proposals and manage customers though the sales process", "Maintain current business relationships with customers, securing existing revenue on long-term commitments", "Apply knowledge of customers, industry, and services to achieve revenue targets Identify, initiate contact with, and qualify potential customers", "Track, analyze and report on sales performance and activities in Zayo's CRM tool and other reporting tools", "Develop accurate and timely forecasts of sales opportunities", "Develop and maintain records of customer activity for reporting of sales and forecasts", "Provide accurate and timely information to management", "Coordinate closely with other departments to ensure customer satisfaction is maintained and revenue objectives met", "Participate in the creation and delivery of high-level face-to-face sales presentations that demonstrate the latest Zayo products and services", "Analyze customer requirements to understand how Zayo products and services can be applied to meet their needs and solve their problems", "Keep abreast of the competitive landscape and emerging technologies in order to best position Zayo in the marketplace", "Collaboratively work as a part of a team while concurrently performing as an individual with minimal supervision"], "Benefits": ["Base pay range: $89,100 - $130,000, commensurate with experience", "Benefits, Rewards & Wellness", "Excellent Health, Dental & Vision Insurance", "Retirement 401(k) Savings Plan", "Fitness membership discounts", "Generous paid time off policy including paid parental leave"]}, "job_job_title": "Principal", "job_posting_language": "en", "job_onet_soc": "11202200", "job_onet_job_zone": "4", "job_naics_code": "517110", "job_naics_name": "Wired Telecommunications Carriers"}