{"job_id": "kQ1YhqlKK_q0-9HgAAAAAA==", "employer_name": "JORNY", "employer_logo": null, "employer_website": "https://www.farmersworld.nl", "employer_company_type": null, "job_publisher": "Ladders", "job_employment_type": "PARTTIME", "job_title": "Strategic Partnership Consultant", "job_apply_link": "https://www.theladders.com/job-listing/strategic-partnership-consultant-jorny-city-of-da-ak-ny-_v2_-7-3587201566.html", "job_apply_is_direct": false, "job_apply_quality_score": 0.5418, "apply_options": [{"publisher": "Ladders", "apply_link": "https://www.theladders.com/job-listing/strategic-partnership-consultant-jorny-city-of-da-ak-ny-_v2_-7-3587201566.html", "is_direct": false}], "job_description": "Company DescriptionJRNY is a pioneering hybrid hospitality brand headquartered in the heart of New York City (NYC) with a global footprint. Our mission is to provide mid-lifers and beyond with an unparalleled opportunity to embark on a transformative journey of connection, exploration, and personal growth. We foster a community where members can connect with like-minded individuals, discover new perspectives, and embrace their unique stage of life.Position SummaryAs a part-time Strategic Partnership Consultant (1099) you will be in charge of creating linkages with various community-based originations, relationship building, and fostering meaningful and mutually beneficial connections. This is a pivotal role at JORNY, as you will be a key player by building and nurturing strategic business relationships. Your responsibilities will include identifying and engaging potential partners, negotiating agreements, and ensuring mutually beneficial terms with strategic alliances. Additionally, you'll be tasked with researching industry trends, managing leads and prospects, and driving negotiations forward. This role offers flexibility to work either at our NYC offices or remotely, with occasional travel required.Responsibilities1. Relationship Management:- Build and maintain strong relationships with partner organizations, vendors, influencers, social media presence, thought leaders, etc including regular communication, meetings, and updates on progress.2. Strategic Planning: Collaborate with internal teams to develop strategic plans for partnerships that align with the organization's goals and objectives.3. Negotiation:- Negotiate partnership agreements, contracts, and terms to ensure mutual benefit for both parties. Note, any partnership that is high value will be given to the management team to execute negotiations.4. Project Management-: Oversee the implementation of partnership initiatives, ensuring they are executed effectively and efficiently, and provide timely updates or progress reports. Must be able to be autonomous and own the project with little oversight.5. Performance Tracking: While we are developing this portion of responsibilities, please find solutions to monitor and track the performance of partnerships against predefined metrics and KPIs, and make adjustments as needed to optimize outcomes.6. Problem Solving: Address any issues or challenges that arise during the partnership, working closely with internal and external stakeholders to find solutions.7. Cross-Functional Collaboration:: Work closely with various internal teams such as sales, marketing, product development, and legal to support partnership initiatives and ensure alignment across the organization.8. Market Analysis: Conduct research and analysis to identify potential partnership opportunities and assess market trends and competitive landscape.9. Communication: Act as a liaison between partner organizations and internal stakeholders, ensuring clear and effective communication throughout the partnership lifecycle.10. Reporting and Analysis: Prepare regular reports and presentations on partnership activities, outcomes, and ROI for internal stakeholders and senior management.11. Continuous Improvement:: Continuously evaluate and refine partnership strategies and processes to drive growth and maximize value for the organization.12. Compliance and Risk Management: Ensure that all partnership activities comply with relevant regulations and mitigate any potential risks to the organization.Hourly rate: $45.00 to $55.00 DOE Qualifications:Proven experience in partnership development, partnership management, and creating collaborative connections.Strong analytical and problem-solving skillsExcellent communication, negotiation, and presentation abilitiesAbility to cultivate and maintain strong relationships with external stakeholders, vendors, influencers,, and any other partnership that may be beneficial to the company\u2019s overall mission.Previous experience in the hospitality industry is a plusFamiliarity with the mid-lifers and beyond market segment is advantageous.Bachelor's degree in Business Administration, Marketing, or related fieldHourly rate: $45.00 to $55.00 DOEJoin us at JORNY and be part of a dynamic team that is redefining the hospitality experience for a new generation of mid-life!To apply, please submit your resume and cover letter outlining your relevant experience and why you're excited about joining JORNY.-\n#J-18808-Ljbffr", "job_is_remote": false, "job_posted_at_timestamp": 1708387200, "job_posted_at_datetime_utc": "2024-02-20T00:00:00.000Z", "job_city": "New York", "job_state": "NY", "job_country": "US", "job_latitude": 40.712776, "job_longitude": -74.005974, "job_benefits": null, "job_google_link": "https://www.google.com/search?gl=us&hl=en&rciv=jb&q=brand+partnerships+consultant&start=0&ibp=htl;jobs#fpstate=tldetail&htivrt=jobs&htiq=brand+partnerships+consultant&htidocid=kQ1YhqlKK_q0-9HgAAAAAA%3D%3D", "job_offer_expiration_datetime_utc": null, "job_offer_expiration_timestamp": null, "job_required_experience": {"no_experience_required": false, "required_experience_in_months": null, "experience_mentioned": true, "experience_preferred": false}, "job_required_skills": null, "job_required_education": {"postgraduate_degree": false, "professional_certification": false, "high_school": false, "associates_degree": false, "bachelors_degree": false, "degree_mentioned": true, "degree_preferred": true, "professional_certification_mentioned": false}, "job_experience_in_place_of_education": false, "job_min_salary": null, "job_max_salary": null, "job_salary_currency": null, "job_salary_period": null, "job_highlights": {"Qualifications": ["Strong analytical and problem-solving skills", "Excellent communication, negotiation, and presentation abilities", "Ability to cultivate and maintain strong relationships with external stakeholders, vendors, influencers,, and any other partnership that may be beneficial to the company\u2019s overall mission", "Familiarity with the mid-lifers and beyond market segment is advantageous", "Bachelor's degree in Business Administration, Marketing, or related field"], "Responsibilities": ["This is a pivotal role at JORNY, as you will be a key player by building and nurturing strategic business relationships", "Your responsibilities will include identifying and engaging potential partners, negotiating agreements, and ensuring mutually beneficial terms with strategic alliances", "Additionally, you'll be tasked with researching industry trends, managing leads and prospects, and driving negotiations forward", "This role offers flexibility to work either at our NYC offices or remotely, with occasional travel required.Responsibilities1", "Relationship Management:- Build and maintain strong relationships with partner organizations, vendors, influencers, social media presence, thought leaders, etc including regular communication, meetings, and updates on progress.2. Strategic Planning: Collaborate with internal teams to develop strategic plans for partnerships that align with the organization's goals and objectives", "Negotiation:- Negotiate partnership agreements, contracts, and terms to ensure mutual benefit for both parties", "Note, any partnership that is high value will be given to the management team to execute negotiations.4. Project Management-: Oversee the implementation of partnership initiatives, ensuring they are executed effectively and efficiently, and provide timely updates or progress reports", "Cross-Functional Collaboration:: Work closely with various internal teams such as sales, marketing, product development, and legal to support partnership initiatives and ensure alignment across the organization", "Market Analysis: Conduct research and analysis to identify potential partnership opportunities and assess market trends and competitive landscape.9. Communication: Act as a liaison between partner organizations and internal stakeholders, ensuring clear and effective communication throughout the partnership lifecycle.10", "Reporting and Analysis: Prepare regular reports and presentations on partnership activities, outcomes, and ROI for internal stakeholders and senior management.11", "Continuous Improvement:: Continuously evaluate and refine partnership strategies and processes to drive growth and maximize value for the organization.12", "Compliance and Risk Management: Ensure that all partnership activities comply with relevant regulations and mitigate any potential risks to the organization"]}, "job_job_title": "Consultant", "job_posting_language": "en", "job_onet_soc": "13111100", "job_onet_job_zone": "5"}