{"job_id": "9-4rI_4CJPho9_cPAAAAAA==", "employer_name": "Livanta", "employer_logo": null, "employer_website": null, "employer_company_type": null, "job_publisher": "Snagajob", "job_employment_type": "FULLTIME", "job_title": "Senior Director, Business Development and Capture", "job_apply_link": "https://www.snagajob.com/jobs/889102770", "job_apply_is_direct": false, "job_apply_quality_score": 0.621, "apply_options": [{"publisher": "Snagajob", "apply_link": "https://www.snagajob.com/jobs/889102770", "is_direct": false}], "job_description": "Summary\nThe Senior Director, Business Development and Capture, is responsible for formulating, leading, and implementing strategy and activities for business pursuits with the federal government, state and local governments, and commercial opportunities. The Senior Director, Business Development and Capture is responsible for leading and winning service and solutions-based business opportunities identified and qualified by Company's business development organization and the executive team, as well as directing business development and capture activities for services and products to federal, state, and local government agencies. The Senior Director, Business Development and Capture works closely with company directors, c-suite members, and company staff toward achieving business growth goals.\n\nAt Livanta, we serve our customers by advancing population health, improving patient care and safety, engaging caregivers and other stakeholders, and effectively managing healthcare costs through quality improvement, strategic communication, and innovation.\n\nResponsibilities\nWhat will you be doing\n\u2022 Leads end-to-end capture and supports other capture-related activities to include proposal management, proposal writing, pricing strategy, and proposal review. * Develops and implements business strategy and the development of a sales pipeline through the identification, qualification, and pursuit of business opportunities.\n\u2022 Manages the opportunity assessment process. This includes communicating with government and partner contacts to provide information for the company to make well-informed bid/no bid decisions, assisting in building relationships with those key partners, and designing and executing a winning proposal strategy.\n\u2022 Collects market trends and data for capture management.\n\u2022 Conducts analysis of business development data to measure effectiveness and efficiency of the capture process.\n\u2022 Contributes to the development of the marketing budget, as requested.\n\u2022 Builds meaningful relationships internally and externally.\n\u2022 Identifies \"suspect\" business needs and qualifies client fit for Company products/services.\n\u2022 Contributes to the review of Request for Proposals (RFPs) and prepares technical responses, as applicable.\n\u2022 Executes follow-up with clients once products or services are delivered to assure complete customer satisfaction.\n\u2022 Maintains confidentiality of client information and reports each interaction.\n\u2022 Updates the sales pipeline on a weekly basis.\n\u2022 Reports key performance metrics and measures results.\n\u2022 Prepares business development, capture, sales, and marketing reports.\n\u2022 Collaborates with the sales and marketing team.\n\u2022 Develops reseller networks, as needed.\n\u2022 Serves as the reseller liaison for the resolution of client questions and complex service issues.\n\u2022 Protects the confidentiality of patient information through compliance with the Health Insurance Portability and Accountability Act (HIPAA) and the Health Information Technology for Economic and Clinical Health Act (HITECH).\n\nQualifications and requirements\nWhat we're looking for\n\u2022 Company's customer base, industry market, operations, contracts, systems, and technologies.\n\u2022 Health care and the current health care environment.\n\u2022 The Centers for Medicare & Medicaid Services (CMS) and other federal, state, and local government agencies.\n\u2022 Medicare, Medicaid, and CMS contractors.\n\u2022 The RFP process and proposal preparation.\n\u2022 Expertise to manage a product/service transition, implementation, and operation.\n\nDesired Characteristics\nSkills that will help you in the role\n\u2022 Business or marketing-related degree or equivalent.\n\u2022 Professional and leadership experience.\n\u2022 Experience in developing operational, marketing, and sales strategies.\n\u2022 Contract management experience.\n\u2022 Proven experience in developing successful customer relationships.\n\nAll qualified applicants will receive consideration for employment without regard to race, color, religion, sex, sexual orientation, gender identity, national origin, disability, or status as a protected veteran.\n\nPosted:12/8/2023 2:20:13 PMLocations:Maryland\nAnnapolis Junction, MD 20701\nCareer Level:DirectorDepartment:Business DevelopmentClearance Requirement:Clearable, but no clearanceTelecommuting options:Full-time telecommuting is okay\n\nAll qualified applicants will receive consideration for employment without regard to race, color, religion, sex, sexual orientation, gender identity, national origin, disability, or status as a protected veteran.", "job_is_remote": true, "job_posted_at_timestamp": 1710402684, "job_posted_at_datetime_utc": "2024-03-14T07:51:24.000Z", "job_city": "Annapolis Junction", "job_state": "MD", "job_country": "US", "job_latitude": 39.130325, "job_longitude": -76.79673, "job_benefits": null, "job_google_link": "https://www.google.com/search?gl=us&hl=en&rciv=jb&q=senior+manager+of+business+development&start=20&ibp=htl;jobs#fpstate=tldetail&htivrt=jobs&htiq=senior+manager+of+business+development&htidocid=9-4rI_4CJPho9_cPAAAAAA%3D%3D", "job_offer_expiration_datetime_utc": "2024-04-07T07:13:26.000Z", "job_offer_expiration_timestamp": 1712474006, "job_required_experience": {"no_experience_required": false, "required_experience_in_months": null, "experience_mentioned": true, "experience_preferred": false}, "job_required_skills": null, "job_required_education": {"postgraduate_degree": false, "professional_certification": false, "high_school": false, "associates_degree": false, "bachelors_degree": false, "degree_mentioned": false, "degree_preferred": false, "professional_certification_mentioned": false}, "job_experience_in_place_of_education": false, "job_min_salary": 35.73, "job_max_salary": 72.25, "job_salary_currency": "USD", "job_salary_period": "HOUR", "job_highlights": {"Qualifications": ["The RFP process and proposal preparation", "Expertise to manage a product/service transition, implementation, and operation", "Business or marketing-related degree or equivalent", "Professional and leadership experience", "Experience in developing operational, marketing, and sales strategies", "Contract management experience", "Proven experience in developing successful customer relationships"], "Responsibilities": ["The Senior Director, Business Development and Capture, is responsible for formulating, leading, and implementing strategy and activities for business pursuits with the federal government, state and local governments, and commercial opportunities", "The Senior Director, Business Development and Capture is responsible for leading and winning service and solutions-based business opportunities identified and qualified by Company's business development organization and the executive team, as well as directing business development and capture activities for services and products to federal, state, and local government agencies", "Leads end-to-end capture and supports other capture-related activities to include proposal management, proposal writing, pricing strategy, and proposal review", "Develops and implements business strategy and the development of a sales pipeline through the identification, qualification, and pursuit of business opportunities", "Manages the opportunity assessment process", "This includes communicating with government and partner contacts to provide information for the company to make well-informed bid/no bid decisions, assisting in building relationships with those key partners, and designing and executing a winning proposal strategy", "Collects market trends and data for capture management", "Conducts analysis of business development data to measure effectiveness and efficiency of the capture process", "Contributes to the development of the marketing budget, as requested", "Builds meaningful relationships internally and externally", "Identifies \"suspect\" business needs and qualifies client fit for Company products/services", "Contributes to the review of Request for Proposals (RFPs) and prepares technical responses, as applicable", "Executes follow-up with clients once products or services are delivered to assure complete customer satisfaction", "Maintains confidentiality of client information and reports each interaction", "Updates the sales pipeline on a weekly basis", "Reports key performance metrics and measures results", "Prepares business development, capture, sales, and marketing reports", "Collaborates with the sales and marketing team", "Develops reseller networks, as needed", "Serves as the reseller liaison for the resolution of client questions and complex service issues", "Protects the confidentiality of patient information through compliance with the Health Insurance Portability and Accountability Act (HIPAA) and the Health Information Technology for Economic and Clinical Health Act (HITECH)"]}, "job_job_title": "Senior director", "job_posting_language": "en", "job_onet_soc": "11202100", "job_onet_job_zone": "4"}