{"job_id": "AaaCPC_ACoQlTwkFAAAAAA==", "employer_name": "Swiss American CDMO", "employer_logo": "https://encrypted-tbn0.gstatic.com/images?q=tbn:ANd9GcRDump271H_7J4uig5eVjwe2zVwfZSwX30rrfZ-&s=0", "employer_website": "http://www.swissamericancdmo.com", "employer_company_type": null, "job_publisher": "LinkedIn", "job_employment_type": "FULLTIME", "job_title": "Vice President of Sales", "job_apply_link": "https://www.linkedin.com/jobs/view/vice-president-of-sales-at-swiss-american-cdmo-3855238763", "job_apply_is_direct": false, "job_apply_quality_score": 0.6665, "apply_options": [{"publisher": "LinkedIn", "apply_link": "https://www.linkedin.com/jobs/view/vice-president-of-sales-at-swiss-american-cdmo-3855238763", "is_direct": false}, {"publisher": "Indeed", "apply_link": "https://www.indeed.com/viewjob?jk=25f5871a0133fa0b", "is_direct": true}, {"publisher": "SimplyHired", "apply_link": "https://www.simplyhired.com/job/_-LjuRemVat65RUaiRmnh-lXvuC9ERgnNxXAdy4qtBIPDCM9y9Qllw", "is_direct": false}, {"publisher": "FactoryFix", "apply_link": "https://jobs.factoryfix.com/jobs/vice-president-of-sales--carrollton--tx--1020492874--V2", "is_direct": true}], "job_description": "Job Details\n\nJob Location\n\nCorporate - CARROLLTON, TX\n\nPosition Type\n\nFull Time\n\nJob Shift\n\nDay\n\nDescription\n\nPosition Summary: As the Vice President of Sales, you will be a pivotal member of our leadership team and will be responsible for overseeing the sales function of the company. You will develop and execute strategic sales initiatives, manage a team of high-performing sales professionals, and collaborate with cross-functional departments to ensure the achievement of sales targets and the overall success of bringing new business into Swiss. This role is full-time on-site office position with some travel.\n\nResponsibilities\n\nEssential Duties and Responsibilities Other duties may be assigned.\n\u2022 Identify, develop, and capitalize on new, expansion, and renewal business opportunities.\n\u2022 Evaluate and enhance existing partnerships and sales strategies for optimal performance.\n\u2022 Cultivate and maintain strong relationships with internal and external stakeholders.\n\u2022 Manage key client relationships (especially through onboarding transition to client services) while actively seeking opportunities to establish new ones.\n\u2022 Expand the company\u2019s profile and brand reach through sales initiatives.\n\u2022 Lead sales team. In concert, with VP of Marketing & Client Engagement, provide a full suite of service that distinguishes the SA brand of customer service and client relationship.\n\u2022 Participate with cross-functional New Business Development teams to foster sustainable, long-term growth. Manage the sales funnel.\n\u2022 Strengthen internal and external relationships to increase lead generation and market share.\n\u2022 Track emerging markets and trends to inform business decisions and identify new markets for potential expansion.\n\u2022 Foster and maintain an entrepreneurial growth culture across the organization.\n\u2022 Propose and develop strategic partnerships to enhance the company\u2019s position.\n\u2022 Contribute to shaping the company\u2019s long-term Strategic objectives and plans.\n\u2022 Provide insights on product development, distribution, and promotion strategies.\n\u2022 Leverage experience in the CDMO industry, preferably in topical applications, to balance risk appropriately.\n\u2022 Aggressively pursue new business opportunities for the organization.\n\u2022 Create and execute manufacturing sales strategies with existing resources, both human and digital.\n\u2022 Manage and develop human and digital resources efficiently.\n\u2022 Execute programs to promote the business\u2019s needs, to fill production capacity.\n\u2022 Implement and manage compensation plans, liaising with finance for effective tracking and accurate and precise commission payments.\n\u2022 Ensure successful execution of quotes through proactive intervention and support.\n\u2022 Ensure successful execution of Manufacturing, Quality and other agreements, and contract related items, to streamline the process for new business.\n\u2022 Utilize tools/resources to identify and capitalize on opportunities, such as the potential to produce large quantity runs, or complex pack-outs or new formulations in advance of moving leads through sales funnel\n\u2022 Develop programs, with input from Operations re: short term capacity gaps, flexibility in filling and packaging configuration, marshaling resources effectively.\n\u2022 Block and tackle challenges for BD Managers to ensure the successful realization of strategic and tactical goals.\n\nQualifications\n\nQualifications:\n\u2022 Bachelor's degree (BA/BS) preferred, or equivalent experience in sales within the Contract Manufacturing Organization (CMO) or Contract Development and Manufacturing Organization (CDMO) industry.\n\u2022 Minimum four years of demonstrably successful sales experience.\n\u2022 Extensive knowledge of the CMO/CDMO industry and its dynamics.\n\u2022 Ability to analyze complex data (technical journals, financial reports, market intelligence) and translate insights into actionable sales strategies.\n\u2022 Proficiency in building sales plans, setting targets, and developing compelling presentations to win business for internal and external stakeholders.\n\u2022 Strong analytical skills to build pricing models and quotes that support successful deal negotiations.\n\u2022 Excellent written and verbal communication skills to present complex information clearly and concisely to diverse audiences (customers, prospects, internal stakeholders).\n\u2022 Ability to build strong relationships and navigate complex conversations.\n\u2022 Strong social selling skills and a solid understanding of digital marketing tools.\n\u2022 Proven ability to lead, motivate, and develop a high-performing sales team\n\u2022 Proficiency in presentation software, communication tools, and collaboration platforms.", "job_is_remote": false, "job_posted_at_timestamp": 1710388277, "job_posted_at_datetime_utc": "2024-03-14T03:51:17.000Z", "job_city": "Carrollton", "job_state": "TX", "job_country": "US", "job_latitude": 32.975643, "job_longitude": -96.88996, "job_benefits": null, "job_google_link": "https://www.google.com/search?gl=us&hl=en&rciv=jb&q=vice+president+of+sales&start=0&ibp=htl;jobs#fpstate=tldetail&htivrt=jobs&htiq=vice+president+of+sales&htidocid=AaaCPC_ACoQlTwkFAAAAAA%3D%3D", "job_offer_expiration_datetime_utc": "2024-04-13T03:51:02.000Z", "job_offer_expiration_timestamp": 1712980262, "job_required_experience": {"no_experience_required": false, "required_experience_in_months": 48, "experience_mentioned": true, "experience_preferred": false}, "job_required_skills": null, "job_required_education": {"postgraduate_degree": false, "professional_certification": false, "high_school": false, "associates_degree": false, "bachelors_degree": true, "degree_mentioned": true, "degree_preferred": true, "professional_certification_mentioned": false}, "job_experience_in_place_of_education": false, "job_min_salary": null, "job_max_salary": null, "job_salary_currency": null, "job_salary_period": null, "job_highlights": {"Qualifications": ["Minimum four years of demonstrably successful sales experience", "Extensive knowledge of the CMO/CDMO industry and its dynamics", "Ability to analyze complex data (technical journals, financial reports, market intelligence) and translate insights into actionable sales strategies", "Proficiency in building sales plans, setting targets, and developing compelling presentations to win business for internal and external stakeholders", "Strong analytical skills to build pricing models and quotes that support successful deal negotiations", "Excellent written and verbal communication skills to present complex information clearly and concisely to diverse audiences (customers, prospects, internal stakeholders)", "Ability to build strong relationships and navigate complex conversations", "Strong social selling skills and a solid understanding of digital marketing tools", "Proven ability to lead, motivate, and develop a high-performing sales team", "Proficiency in presentation software, communication tools, and collaboration platforms"], "Responsibilities": ["Position Summary: As the Vice President of Sales, you will be a pivotal member of our leadership team and will be responsible for overseeing the sales function of the company", "You will develop and execute strategic sales initiatives, manage a team of high-performing sales professionals, and collaborate with cross-functional departments to ensure the achievement of sales targets and the overall success of bringing new business into Swiss", "This role is full-time on-site office position with some travel", "Essential Duties and Responsibilities Other duties may be assigned", "Identify, develop, and capitalize on new, expansion, and renewal business opportunities", "Evaluate and enhance existing partnerships and sales strategies for optimal performance", "Cultivate and maintain strong relationships with internal and external stakeholders", "Manage key client relationships (especially through onboarding transition to client services) while actively seeking opportunities to establish new ones", "Expand the company\u2019s profile and brand reach through sales initiatives", "Lead sales team", "In concert, with VP of Marketing & Client Engagement, provide a full suite of service that distinguishes the SA brand of customer service and client relationship", "Participate with cross-functional New Business Development teams to foster sustainable, long-term growth", "Manage the sales funnel", "Strengthen internal and external relationships to increase lead generation and market share", "Track emerging markets and trends to inform business decisions and identify new markets for potential expansion", "Foster and maintain an entrepreneurial growth culture across the organization", "Propose and develop strategic partnerships to enhance the company\u2019s position", "Contribute to shaping the company\u2019s long-term Strategic objectives and plans", "Provide insights on product development, distribution, and promotion strategies", "Leverage experience in the CDMO industry, preferably in topical applications, to balance risk appropriately", "Aggressively pursue new business opportunities for the organization", "Create and execute manufacturing sales strategies with existing resources, both human and digital", "Manage and develop human and digital resources efficiently", "Execute programs to promote the business\u2019s needs, to fill production capacity", "Implement and manage compensation plans, liaising with finance for effective tracking and accurate and precise commission payments", "Ensure successful execution of quotes through proactive intervention and support", "Ensure successful execution of Manufacturing, Quality and other agreements, and contract related items, to streamline the process for new business", "Utilize tools/resources to identify and capitalize on opportunities, such as the potential to produce large quantity runs, or complex pack-outs or new formulations in advance of moving leads through sales funnel", "Develop programs, with input from Operations re: short term capacity gaps, flexibility in filling and packaging configuration, marshaling resources effectively", "Block and tackle challenges for BD Managers to ensure the successful realization of strategic and tactical goals"]}, "job_job_title": "Vice", "job_posting_language": "en", "job_onet_soc": "11101100", "job_onet_job_zone": "5"}