{"job_id": "w-RN5_rLiyAfJlihAAAAAA==", "employer_name": "Paul Hastings", "employer_logo": "https://images.ctfassets.net/t0ydv1wnf2mi/3tBWFAfsj5J0DaAYCIZ9og/4b1b97b221423c90403a15a3a810286f/share-logo.jpg", "employer_website": "http://www.paulhastings.com", "employer_company_type": "Legal", "job_publisher": "Glassdoor", "job_employment_type": "FULLTIME", "job_title": "Cloud Architect", "job_apply_link": "https://www.glassdoor.com/job-listing/cloud-architect-paul-hastings-JV_KO0,15_KE16,29.htm?jl=1009115263653", "job_apply_is_direct": false, "job_apply_quality_score": 0.6472, "apply_options": [{"publisher": "Glassdoor", "apply_link": "https://www.glassdoor.com/job-listing/cloud-architect-paul-hastings-JV_KO0,15_KE16,29.htm?jl=1009115263653", "is_direct": false}, {"publisher": "Indeed", "apply_link": "https://www.indeed.com/viewjob?jk=8217e88a720a5302", "is_direct": false}, {"publisher": "Talent.com", "apply_link": "https://www.talent.com/view?id=9a3b09af7335", "is_direct": false}, {"publisher": "Ladders", "apply_link": "https://www.theladders.com/job-listing/cloud-architect-franklin-fitch-_v2_-7-3567986232.html", "is_direct": false}, {"publisher": "LazyApply", "apply_link": "https://lazyapply.com/jobpreview/job_8217e88a720a5302", "is_direct": false}], "job_description": "Paul Hastings is a leading international law firm that provides innovative legal solutions to many of the world's top financial institutions and Fortune Global 500 companies. With a strong presence throughout Asia, Europe, Latin America, and the U.S., we have the global reach and extensive capabilities to provide personalized service wherever our clients\u2019 needs take us. As one of the world\u2019s leading law firms, we seek dynamic individuals who share our commitment to service, innovation, and professional growth.\n\nWe have an opening for a Cloud Architect, Microsoft 365.\n\nThe Cloud Architect for Microsoft 365 position will be responsible for the design, planning, assessment and strategies around the firm\u2019s migrations and operation within the Microsoft cloud. This position requires expert level understanding and experience in the migration and configuration of Microsoft enterprise cloud solutions including related technologies such as Active Directory, Exchange, OneDrive, Sharepoint, Teams, Entra ID and Entra Connect. The position also requires a deep understanding of the governance needs and security options around these services.\n\nIn this capacity, the Cloud Architect, Microsoft 365 will:\n\u2022 Serve as the go-to technical expert in the Microsoft 365 space;\n\u2022 Design, configure and maintain the firms Microsoft 365 environment;\n\u2022 Translate requirements into architectural design and present to C level management;\n\u2022 Plan and execute end-to-end implementations of Microsoft 365 workloads;\n\u2022 Provide guidance to the firm\u2019s IT management of existing and emerging Microsoft 365 and related core technologies;\n\u2022 Create high and low level detailed documentation on existing and future cloud solutions;\n\u2022 Review and identify Microsoft 365 platform governance needs and security configurations options;\n\u2022 Provide expertise and be a key resource with major service migrations into the Microsoft 365 services;\n\u2022 Work directly with Infosec teams to validate designs account for all aspects of information security best practices and firm requirements;\n\u2022 Regularly analyze 365 and cloud environments to detect critical deficiencies and recommend solutions for improvement;\n\u2022 At an expert level, create, review and distribute technical documentation for cloud solutions and projects including, processes, procedures, troubleshooting, training and change management;\n\u2022 Mentor/Coach other IT teams members; and\n\u2022 Provide solution ownership and subject matter expertise through the firms SDLC process.\n\nProficiencies:\n\u2022 Excellent verbal and written communication skills;\n\u2022 The ability to lead internal IT groups and present on new technologies;\n\u2022 The ability to identify, scope, and present detailed technical solutions to C Suite personnel;\n\u2022 Ability to implement Microsoft cloud technologies and understand interdependencies in large on-premise enterprise environments;\n\u2022 Ability to proactively collaborate across internal, and third party vendor teams;\n\u2022 Ability to provide strategic vision to large technical teams on complex projects;\n\u2022 Provide leadership across cloud services to the firm and it\u2019s IT department;\n\u2022 Proactively provide process improvement, security configuration and standardization across the firm\u2019s cloud solutions;\n\u2022 In-depth technical problem-solving capability; and\n\u2022 Effectively articulate escalations and communicate progress to stakeholders.\n\nQualifications:\n\u2022 Bachelor's degree (or equivalent work experience) required in Computer Science, Information Systems, Technology, System Analysis, Engineering or a related study;\n\u2022 10+ years of progressive global enterprise level experience with IT solutions and engineering;\n\u2022 Microsoft Certifications: Advanced Microsoft M365 certifications;\n\u2022 Office 365 subject matter expertise for Microsoft Entra ID, Exchange Online, Defender for Office 365, Teams and Teams voice services and other O365 workloads;\n\u2022 Microsoft Security components: Defender for Identity, Defender for Cloud Apps, Microsoft Entra ID Premium;\n\u2022 Experience in Microsoft cloud security controls, Data Loss Prevention, Purview, and understanding of Litigation Hold, Retention, and eDiscovery;\n\u2022 Exchange: Must have real-world, hands-on experience delivering messaging and collaboration solutions utilizing Microsoft Exchange and Office 365 within large, complex environments;\n\u2022 Active Directory: Must have real-world experience helping to manage and maintain on-premises Active Directory, GPO's, and on-premises Active Directory migrations to M365;\n\u2022 Azure: Experience with Azure is a plus;\n\u2022 Intune: Experience with Microsoft Intune a plus; and\n\u2022 Experience with email protection and security leveraging Proofpoint is a plus.\n\nEmployees will be provided with an excellent career opportunity in a collaborative environment, in addition to a generous total compensation package with the opportunity to earn bonuses based on individual contribution and firm profitability.\n\nThe salary wage range that we expect to pay for this position is a minimum of $150,700 and a maximum of $219,000 annually. The actual pay wage may vary based on experience or other relevant factors.\n\nEligible employees can participate in the Firm\u2019s comprehensive benefits program, which include the following:\n\u2022 Medical, Dental, Vision, Life/AD&D, Long Term Care, and Short and Long Term Disability\n\u2022 Flexible Spending Account and Health Savings Account\n\u2022 Healthcare Concierge and Advocacy\n\u2022 Voluntary 401k Plan and Profit Sharing\n\u2022 10 Paid Holidays per year and a generous PTO program\n\u2022 Family Support including Pediatric Mental Health and Parental Support, Paid Parental Leave, Fertility Benefits, and Breast Milk Shipping\n\u2022 Back-up Child Care, Elder Care, and Tutoring\n\u2022 Wellness Programs (Employee Assistance Program, Mental Health, and Well-Being Events)\n\u2022 Retirement Plan Consulting\n\u2022 Anniversary Bonus Program\n\u2022 Professional Development Programs\n\u2022 Transportation Allowance and Commuter Benefits\n\u2022 International Travel Insurance\n\u2022 Auto/Home/Legal Insurance\n\u2022 Pet Insurance\n\u2022 Employee discounts\n\u2022 And more!\n\nThe Firm has a range of diversity initiatives including our Paul Hastings Affinity Networks (PHANs), Women\u2019s Initiative, and PH Balanced. These initiatives provide a firmwide forum to share experiences, as well as an opportunity to participate in a supportive network with common interests to help make life at the firm more inclusive. Learn more about our Global Diversity, Inclusion and Wellness Initiatives here.\n\nPaul Hastings LLP is an equal employment and affirmative action employer F/M/Disability/Vet/Sexual Orientation/Gender Identity.", "job_is_remote": false, "job_posted_at_timestamp": 1709769600, "job_posted_at_datetime_utc": "2024-03-07T00:00:00.000Z", "job_city": "New York", "job_state": "NY", "job_country": "US", "job_latitude": 40.712776, "job_longitude": -74.005974, "job_benefits": ["paid_time_off", "health_insurance", "dental_coverage", "retirement_savings"], "job_google_link": "https://www.google.com/search?gl=us&hl=en&rciv=jb&q=cloud+architect&start=50&ibp=htl;jobs#fpstate=tldetail&htivrt=jobs&htiq=cloud+architect&htidocid=w-RN5_rLiyAfJlihAAAAAA%3D%3D", "job_offer_expiration_datetime_utc": "2024-07-11T00:00:00.000Z", "job_offer_expiration_timestamp": 1720656000, "job_required_experience": {"no_experience_required": false, "required_experience_in_months": 120, "experience_mentioned": true, "experience_preferred": true}, "job_required_skills": null, "job_required_education": {"postgraduate_degree": false, "professional_certification": false, "high_school": false, "associates_degree": false, "bachelors_degree": false, "degree_mentioned": true, "degree_preferred": false, "professional_certification_mentioned": true}, "job_experience_in_place_of_education": false, "job_min_salary": 219000, "job_max_salary": 219000, "job_salary_currency": "USD", "job_salary_period": "YEAR", "job_highlights": {"Qualifications": ["The position also requires a deep understanding of the governance needs and security options around these services", "Excellent verbal and written communication skills;", "The ability to lead internal IT groups and present on new technologies;", "The ability to identify, scope, and present detailed technical solutions to C Suite personnel;", "Ability to implement Microsoft cloud technologies and understand interdependencies in large on-premise enterprise environments;", "Bachelor's degree (or equivalent work experience) required in Computer Science, Information Systems, Technology, System Analysis, Engineering or a related study;", "10+ years of progressive global enterprise level experience with IT solutions and engineering;", "Microsoft Certifications: Advanced Microsoft M365 certifications;", "Office 365 subject matter expertise for Microsoft Entra ID, Exchange Online, Defender for Office 365, Teams and Teams voice services and other O365 workloads;", "Microsoft Security components: Defender for Identity, Defender for Cloud Apps, Microsoft Entra ID Premium;", "Experience in Microsoft cloud security controls, Data Loss Prevention, Purview, and understanding of Litigation Hold, Retention, and eDiscovery;", "Exchange: Must have real-world, hands-on experience delivering messaging and collaboration solutions utilizing Microsoft Exchange and Office 365 within large, complex environments;", "Active Directory: Must have real-world experience helping to manage and maintain on-premises Active Directory, GPO's, and on-premises Active Directory migrations to M365;"], "Responsibilities": ["Serve as the go-to technical expert in the Microsoft 365 space;", "Design, configure and maintain the firms Microsoft 365 environment;", "Plan and execute end-to-end implementations of Microsoft 365 workloads;", "Provide guidance to the firm\u2019s IT management of existing and emerging Microsoft 365 and related core technologies;", "Create high and low level detailed documentation on existing and future cloud solutions;", "Review and identify Microsoft 365 platform governance needs and security configurations options;", "Provide expertise and be a key resource with major service migrations into the Microsoft 365 services;", "Work directly with Infosec teams to validate designs account for all aspects of information security best practices and firm requirements;", "Regularly analyze 365 and cloud environments to detect critical deficiencies and recommend solutions for improvement;", "At an expert level, create, review and distribute technical documentation for cloud solutions and projects including, processes, procedures, troubleshooting, training and change management;", "Mentor/Coach other IT teams members; and", "Provide solution ownership and subject matter expertise through the firms SDLC process", "Provide leadership across cloud services to the firm and it\u2019s IT department;", "Proactively provide process improvement, security configuration and standardization across the firm\u2019s cloud solutions;", "In-depth technical problem-solving capability; and", "Effectively articulate escalations and communicate progress to stakeholders"], "Benefits": ["Employees will be provided with an excellent career opportunity in a collaborative environment, in addition to a generous total compensation package with the opportunity to earn bonuses based on individual contribution and firm profitability", "The salary wage range that we expect to pay for this position is a minimum of $150,700 and a maximum of $219,000 annually", "The actual pay wage may vary based on experience or other relevant factors", "Medical, Dental, Vision, Life/AD&D, Long Term Care, and Short and Long Term Disability", "Flexible Spending Account and Health Savings Account", "Healthcare Concierge and Advocacy", "Voluntary 401k Plan and Profit Sharing", "10 Paid Holidays per year and a generous PTO program", "Family Support including Pediatric Mental Health and Parental Support, Paid Parental Leave, Fertility Benefits, and Breast Milk Shipping", "Back-up Child Care, Elder Care, and Tutoring", "Wellness Programs (Employee Assistance Program, Mental Health, and Well-Being Events)", "Retirement Plan Consulting", "Anniversary Bonus Program", "Professional Development Programs", "Transportation Allowance and Commuter Benefits", "International Travel Insurance", "Auto/Home/Legal Insurance", "Pet Insurance", "Employee discounts"]}, "job_job_title": "Cloud architect", "job_posting_language": "en", "job_onet_soc": "15119900", "job_onet_job_zone": "4", "job_naics_code": "5411", "job_naics_name": "Legal"}