{"job_id": "M6fBJ8LO29uBM4goAAAAAA==", "employer_name": "HydroJug", "employer_logo": "http://t3.gstatic.com/images?q=tbn:ANd9GcSJYbmv_a3ZuK8CCQoMCrDLWoFyXjdGJXfMxt3GQ9_L-6UD8XxV", "employer_website": "http://www.thehydrojug.com", "employer_company_type": null, "job_publisher": "Jooble", "job_employment_type": "CONTRACTOR", "job_title": "Senior Key Account Sales Manager", "job_apply_link": "https://jooble.org/jdp/2404158447634897676", "job_apply_is_direct": false, "job_apply_quality_score": 0.6468, "apply_options": [{"publisher": "Jooble", "apply_link": "https://jooble.org/jdp/2404158447634897676", "is_direct": false}, {"publisher": "Jobrapido.com", "apply_link": "https://us.jobrapido.com/jobpreview/3192744250", "is_direct": false}], "job_description": "About HydroJug:\n\nHydroJug is on a mission to innovate in the drinkware sector, offering products that promote\n\nhealthy hydration habits with a blend of style, functionality, and sustainability. As a rapidly\n\ngrowing brand in the consumer packaged goods (CPG) industry, we're seeking talented\n\nindividuals to help expand our footprint and make a lasting impact on our customers' lives.\n\nPosition Overview:\n\nWe're looking for an experienced Senior Key Account Sales Manager to spearhead our sales\n\nefforts, particularly focusing on managing and expanding relationships with big box retailers.\n\nThe ideal candidate will bring a strong background in CPG sales, with demonstrated success in\n\nmanaging large accounts, forecasting, and profit and loss (P&L) management. This role is\n\npivotal in driving HydroJug's growth by leveraging strategic partnerships, optimizing sales\n\nstrategies, and delivering on financial objectives.\n\nLocation:\n\nOgden UT, In-Office\n\nKey Responsibilities:\n\n\u25cf Develop strategic plans to manage and grow key accounts, particularly with big box\n\nretailers, to achieve sales targets and expand market presence.\n\n\u25cf Leverage extensive experience in the CPG sector to understand client needs, tailor\n\nofferings, and ensure HydroJug's products stand out in a competitive marketplace.\n\n\u25cf Conduct sophisticated contract negotiations, aiming to secure profitable deals while\n\nmaintaining strong, long-lasting customer relationships.\n\n\u25cf Collaborate with cross-functional teams to align sales strategies with marketing initiatives\n\nand product development goals, ensuring a cohesive approach to account growth.\n\n\u25cf Utilize forecasting tools and techniques to accurately predict sales trends, manage\n\ninventory levels, and ensure product availability aligns with consumer demand.\n\n\u25cf Take full responsibility for managing account-specific P&Ls, implementing strategies to\n\noptimize profitability while controlling costs.\n\n\u25cf Provide insightful market analysis, identifying emerging trends and potential threats, and\n\nadjust account strategies accordingly.\n\n\u25cf Offer mentorship and guidance to junior sales team members, fostering a culture of\n\nexcellence and continuous improvement within the sales department.\n\n\u25cf Represent HydroJug at industry events, trade shows, and in key meetings, enhancing\n\nthe brand's visibility and reputation.\n\nQualifications:\n\n\u25cf Bachelor\u2019s degree in Business Administration, Sales, Marketing, or related field, with an\n\nMBA preferred.\n\n\u25cf At least 7 years of experience in key account management within the consumer\n\npackaged goods industry, with a proven track record of success with big box retailers.\n\n\u25cf Strong expertise in forecasting, sales analysis, and P&L management, with the ability to\n\nmake data-driven decisions to drive growth.\n\n\u25cf Exceptional negotiation, communication, and presentation skills, capable of influencing\n\nkey stakeholders and decision-makers.\n\n\u25cf Strategic thinker with a problem-solving mindset, able to identify opportunities for growth\n\nand efficiency improvements.\n\n\u25cf Proficiency in CRM software, MS Office/G Suite, and forecasting tools.\n\n\u25cf Willingness to travel as needed to meet with clients and attend industry events.\n\nWhat We Offer:\n\n\u25cf A competitive compensation package, including a base salary, performance bonuses,\n\nand comprehensive benefits.\n\n\u25cf A dynamic work environment at a forward-thinking company poised for significant\n\ngrowth.\n\n\u25cf Professional development opportunities and the chance to make a meaningful impact in\n\nthe CPG and drinkware sectors.\n\n\u25cf Application Process:\n\n\u25cf Qualified candidates are invited to submit their resume and a cover letter explaining why\n\nthey are the ideal fit for the Senior Key Account Sales Manager position at HydroJug to\n\nView email address on click.appcast.io.\n\nJoin us at HydroJug, where your work directly contributes to our mission of promoting hydration\n\nin style. We're excited to welcome a strategic, results-driven sales leader to our team!\n\nHydroJug is an equal opportunity employer committed to diversity and inclusion.", "job_is_remote": false, "job_posted_at_timestamp": 1710028800, "job_posted_at_datetime_utc": "2024-03-10T00:00:00.000Z", "job_city": null, "job_state": null, "job_country": "US", "job_latitude": 37.09024, "job_longitude": -95.71289, "job_benefits": ["health_insurance"], "job_google_link": "https://www.google.com/search?gl=us&hl=en&rciv=jb&q=senior+sales+manager&start=60&ibp=htl;jobs#fpstate=tldetail&htivrt=jobs&htiq=senior+sales+manager&htidocid=M6fBJ8LO29uBM4goAAAAAA%3D%3D", "job_offer_expiration_datetime_utc": "2024-04-11T11:52:48.000Z", "job_offer_expiration_timestamp": 1712836368, "job_required_experience": {"no_experience_required": false, "required_experience_in_months": null, "experience_mentioned": true, "experience_preferred": false}, "job_required_skills": null, "job_required_education": {"postgraduate_degree": false, "professional_certification": false, "high_school": false, "associates_degree": false, "bachelors_degree": false, "degree_mentioned": true, "degree_preferred": true, "professional_certification_mentioned": false}, "job_experience_in_place_of_education": false, "job_min_salary": null, "job_max_salary": null, "job_salary_currency": null, "job_salary_period": null, "job_highlights": {"Qualifications": ["Bachelor\u2019s degree in Business Administration, Sales, Marketing, or related field, with an", "packaged goods industry, with a proven track record of success with big box retailers", "Strong expertise in forecasting, sales analysis, and P&L management, with the ability to"], "Responsibilities": ["healthy hydration habits with a blend of style, functionality, and sustainability", "efforts, particularly focusing on managing and expanding relationships with big box retailers", "managing large accounts, forecasting, and profit and loss (P&L) management", "pivotal in driving HydroJug's growth by leveraging strategic partnerships, optimizing sales", "Develop strategic plans to manage and grow key accounts, particularly with big box", "retailers, to achieve sales targets and expand market presence", "Leverage extensive experience in the CPG sector to understand client needs, tailor", "offerings, and ensure HydroJug's products stand out in a competitive marketplace", "Conduct sophisticated contract negotiations, aiming to secure profitable deals while", "maintaining strong, long-lasting customer relationships", "Collaborate with cross-functional teams to align sales strategies with marketing initiatives", "and product development goals, ensuring a cohesive approach to account growth", "Utilize forecasting tools and techniques to accurately predict sales trends, manage", "inventory levels, and ensure product availability aligns with consumer demand", "Take full responsibility for managing account-specific P&Ls, implementing strategies to", "optimize profitability while controlling costs", "Provide insightful market analysis, identifying emerging trends and potential threats, and", "adjust account strategies accordingly", "Offer mentorship and guidance to junior sales team members, fostering a culture of", "excellence and continuous improvement within the sales department", "Represent HydroJug at industry events, trade shows, and in key meetings, enhancing", "Strategic thinker with a problem-solving mindset, able to identify opportunities for growth", "Proficiency in CRM software, MS Office/G Suite, and forecasting tools", "Willingness to travel as needed to meet with clients and attend industry events"], "Benefits": ["A competitive compensation package, including a base salary, performance bonuses,", "A dynamic work environment at a forward-thinking company poised for significant", "Professional development opportunities and the chance to make a meaningful impact in"]}, "job_job_title": "Sales manager", "job_posting_language": "en", "job_onet_soc": "41401300", "job_onet_job_zone": null}