{"job_id": "OzFstm68YtaKEiDXAAAAAA==", "employer_name": "Hoteltonight", "employer_logo": "https://upload.wikimedia.org/wikipedia/commons/thumb/1/19/Hotel_Tonight_logo.svg/1280px-Hotel_Tonight_logo.svg.png", "employer_website": "http://www.hoteltonight.com", "employer_company_type": "Travel", "job_publisher": "Meritocracy", "job_employment_type": "FULLTIME", "job_title": "Strategic Partnerships Manager Brand Partnerships", "job_apply_link": "https://meritocracy.is/de/hoteltonight/strategic-partnerships-manager-brand-partnerships-19735", "job_apply_is_direct": false, "job_apply_quality_score": 0.5554, "apply_options": [{"publisher": "Meritocracy", "apply_link": "https://meritocracy.is/de/hoteltonight/strategic-partnerships-manager-brand-partnerships-19735", "is_direct": false}], "job_description": "HotelTonight makes it remarkably easy to book great hotels at amazing last-minute rates on your mobile device, for tonight, tomorrow and beyond. Our mission is to make people feel more alive by delivering the unexpected and we\u2019re looking for a Strategic Partnerships Manager to help do just that.\n\nWITHIN 1 MONTH YOU WILL:\n\u2022 Develop strong understanding of HT\u2019s value proposition, available solutions and data sets to have meaningful conversations with prospective partners\n\u2022 Understand supplier needs and competitive landscape in order to position HT effectively in marketplace\n\u2022 Become familiar with prospect list of top management companies and hotel chains\n\u2022 Seek and establish warm introductions with potential partners\nWITHIN 3 MONTHS YOU WILL:\n\u2022 Manage overall pipeline and update internal stakeholders\n\u2022 Develop marketing materials to effectively showcase our product offering\n\u2022 Conduct conference calls and in-person meetings with potential partners to understand their needs\n\u2022 Conduct analysis to determine revenue potential and desired business terms\n\u2022 Implement creative strategies to overcome objections to achieve desired results\n\u2022 Negotiate win-win business terms and sign contracts with new partners\n\u2022 Work with our operations team to develop implementation plan and timelines\nWITHIN 12 MONTHS YOU WILL:\n\u2022 Work cross-functionally with Data & Strategy, Product, Legal, and Finance to resolve issues and identify new solutions\n\u2022 Work with stakeholders across the company on short and long term strategic projects with the goal of strengthening our hotel marketplace\n\u2022 Represent HT and meet new partners at industry events\nWHAT WE'RE LOOKING FOR IN YOU:\n\u2022 2-4 years of relevant work experience, preferably in a fast growing startup, and/or consulting, finance\n\u2022 Experience managing sophisticated, multi-faceted partnerships & negotiations\n\u2022 Proven track record in navigating complex deals, terms, and contracting processes\n\u2022 Strong ability to collaborate, but also to prioritize and manage yourself autonomously\n\u2022 Excellent communication, organizational and analytical skills\n\u2022 A love of networking & fostering new connections\n\u2022 Ability to travel 25% of the time", "job_is_remote": false, "job_posted_at_timestamp": 1544724600, "job_posted_at_datetime_utc": "2018-12-13T18:10:00.000Z", "job_city": "San Francisco", "job_state": "CA", "job_country": "US", "job_latitude": 37.77493, "job_longitude": -122.41942, "job_benefits": null, "job_google_link": "https://www.google.com/search?gl=us&hl=en&rciv=jb&q=manager+of+brand+partnerships&start=20&ibp=htl;jobs#fpstate=tldetail&htivrt=jobs&htiq=manager+of+brand+partnerships&htidocid=OzFstm68YtaKEiDXAAAAAA%3D%3D", "job_offer_expiration_datetime_utc": null, "job_offer_expiration_timestamp": null, "job_required_experience": {"no_experience_required": false, "required_experience_in_months": 24, "experience_mentioned": true, "experience_preferred": false}, "job_required_skills": ["Marketing", "Networking"], "job_required_education": {"postgraduate_degree": false, "professional_certification": false, "high_school": false, "associates_degree": false, "bachelors_degree": false, "degree_mentioned": false, "degree_preferred": false, "professional_certification_mentioned": false}, "job_experience_in_place_of_education": false, "job_min_salary": null, "job_max_salary": null, "job_salary_currency": null, "job_salary_period": null, "job_highlights": {"Qualifications": ["2-4 years of relevant work experience, preferably in a fast growing startup, and/or consulting, finance", "Experience managing sophisticated, multi-faceted partnerships & negotiations", "Proven track record in navigating complex deals, terms, and contracting processes", "Strong ability to collaborate, but also to prioritize and manage yourself autonomously", "Excellent communication, organizational and analytical skills", "A love of networking & fostering new connections", "Ability to travel 25% of the time"], "Responsibilities": ["Develop strong understanding of HT\u2019s value proposition, available solutions and data sets to have meaningful conversations with prospective partners", "Understand supplier needs and competitive landscape in order to position HT effectively in marketplace", "Become familiar with prospect list of top management companies and hotel chains", "Seek and establish warm introductions with potential partners", "Manage overall pipeline and update internal stakeholders", "Develop marketing materials to effectively showcase our product offering", "Conduct conference calls and in-person meetings with potential partners to understand their needs", "Conduct analysis to determine revenue potential and desired business terms", "Implement creative strategies to overcome objections to achieve desired results", "Negotiate win-win business terms and sign contracts with new partners", "Work with our operations team to develop implementation plan and timelines", "Work cross-functionally with Data & Strategy, Product, Legal, and Finance to resolve issues and identify new solutions", "Work with stakeholders across the company on short and long term strategic projects with the goal of strengthening our hotel marketplace", "Represent HT and meet new partners at industry events"]}, "job_job_title": "Partnerships manager", "job_posting_language": "en", "job_onet_soc": "11202100", "job_onet_job_zone": "4", "job_naics_code": "561510", "job_naics_name": "Travel Agencies"}