{"job_id": "7oyGwpqxEz2njOndAAAAAA==", "employer_name": "PingWind", "employer_logo": null, "employer_website": "http://www.pingwind.com", "employer_company_type": null, "job_publisher": "Lever", "job_employment_type": "FULLTIME", "job_title": "Cloud Architect", "job_apply_link": "https://jobs.lever.co/pingwind/9ef65c7a-4b6b-404d-bb2e-403e6d798976", "job_apply_is_direct": false, "job_apply_quality_score": 0.7407, "apply_options": [{"publisher": "Lever", "apply_link": "https://jobs.lever.co/pingwind/9ef65c7a-4b6b-404d-bb2e-403e6d798976", "is_direct": false}], "job_description": "Description:\n\nPingWind is seeking a highly skilled and experienced Cloud Architect to join our dynamic team. As a Cloud Architect, you will take a leadership role in overseeing a team responsible for planning, configuring, migrating, and enhancing the MEDCHART system within the Government-selected Cloud hosting facility.\n\nOpen Positions: 1\n\nRequired Clearance: Secret w/ability to obtain TS.\n\nRequired Education: Bachelor\u2019 s Degree in relevant field.\n\nRequired Experience: Eight+ (8+) years of relevant experience.\n\nResponsibilities:\n\n\u00b7 Develop and execute comprehensive cloud strategies for the MEDCHART system, aligned with Government objectives.\n\n\u00b7 Collaborate with stakeholders to understand business requirements and translate them into scalable cloud solutions.\n\n\u00b7 Design and architect cloud infrastructure solutions based on best practices and industry standards.\n\n\u00b7 Ensure scalability, reliability, and performance of cloud applications.\n\n\u00b7 Evaluate and select appropriate cloud services and technologies to meet project and organizational requirements.\n\n\u00b7 Develop and execute migration plans for the MEDCHART system to the Government-selected Cloud hosting facility.\n\n\u00b7 Implement robust security measures and compliance controls in cloud architectures.\n\n\u00b7 Collaborate with software developers to ensure applications are optimized for cloud environments.\n\nRequirements:\n\n\u00b7 Develop cost models and optimize cloud resource usage to ensure cost-effectiveness.\n\n\u00b7 Implement strategies for monitoring and managing cloud expenses.\n\n\u00b7 Create and maintain comprehensive documentation for cloud architectures, configurations, and processes.\n\n\u00b7 Ensure documentation is accessible to relevant stakeholders.\n\n\u00b7 Proven experience as a Cloud Architect or in a similar role.\n\n\u00b7 Strong knowledge of cloud platforms such as AWS, Azure, or Google Cloud.\n\n\u00b7 Expertise in cloud architecture design, including networking, security, and scalability.\n\n\u00b7 Familiarity with DevOps practices and principles.\n\nPreferred Qualifications:\n\nAWS Certified Solutions Architect, Microsoft Certified: Azure Solutions Architect Expert, or Google Cloud Professional Cloud Architect\n\nCertifications:\n\n\u00b7 Security+\n\n\u00b7 HIPPA\n\nAbout PingWind\n\nPingWind is focused on delivering outstanding services to the federal government. We have extensive experience in the fields of cybersecurity, development, IT infrastructure, supply chain management and other professional services such as system design and continuous improvement. PingWind is a VA CVE certified Service-Disabled Veteran-Owned Small Business (SDVOSB) and SBA Certified with offices in Washington DC and Northern Virginia. www.PingWind.com\n\nOur benefits include:\n\nPaid Federal Holidays\n\nRobust Health & Dental Insurance Options\n\n401k with matching\n\nPaid vacation and sick leave\n\nContinuing education assistance\n\nShort Term / Long Term Disability & Life Insurance\n\nEmployee Assistance Program through Sun Life Financial EAP Guidance Resources\n\nVeterans are encouraged to apply\n\nPingWind, Inc. does not discriminate in employment opportunities, terms, and conditions of employment, or practices on the basis of race, age, gender, religious or political beliefs, national origin or heritage, disability, sexual orientation, or any characteristic protected by law.", "job_is_remote": false, "job_posted_at_timestamp": 1707782400, "job_posted_at_datetime_utc": "2024-02-13T00:00:00.000Z", "job_city": "Annandale", "job_state": "VA", "job_country": "US", "job_latitude": 38.833805, "job_longitude": -77.20836, "job_benefits": ["paid_time_off", "retirement_savings", "dental_coverage", "health_insurance"], "job_google_link": "https://www.google.com/search?gl=us&hl=en&rciv=jb&q=cloud+architect&start=50&ibp=htl;jobs#fpstate=tldetail&htivrt=jobs&htiq=cloud+architect&htidocid=7oyGwpqxEz2njOndAAAAAA%3D%3D", "job_offer_expiration_datetime_utc": null, "job_offer_expiration_timestamp": null, "job_required_experience": {"no_experience_required": false, "required_experience_in_months": 96, "experience_mentioned": true, "experience_preferred": false}, "job_required_skills": null, "job_required_education": {"postgraduate_degree": false, "professional_certification": false, "high_school": false, "associates_degree": false, "bachelors_degree": false, "degree_mentioned": true, "degree_preferred": true, "professional_certification_mentioned": true}, "job_experience_in_place_of_education": false, "job_min_salary": null, "job_max_salary": null, "job_salary_currency": null, "job_salary_period": null, "job_highlights": {"Qualifications": ["Required Education: Bachelor\u2019 s Degree in relevant field", "Required Experience: Eight+ (8+) years of relevant experience", "Proven experience as a Cloud Architect or in a similar role", "Strong knowledge of cloud platforms such as AWS, Azure, or Google Cloud", "Expertise in cloud architecture design, including networking, security, and scalability", "Familiarity with DevOps practices and principles", "AWS Certified Solutions Architect, Microsoft Certified: Azure Solutions Architect Expert, or Google Cloud Professional Cloud Architect", "HIPPA"], "Responsibilities": ["As a Cloud Architect, you will take a leadership role in overseeing a team responsible for planning, configuring, migrating, and enhancing the MEDCHART system within the Government-selected Cloud hosting facility", "Required Clearance: Secret w/ability to obtain TS", "Develop and execute comprehensive cloud strategies for the MEDCHART system, aligned with Government objectives", "Collaborate with stakeholders to understand business requirements and translate them into scalable cloud solutions", "Design and architect cloud infrastructure solutions based on best practices and industry standards", "Ensure scalability, reliability, and performance of cloud applications", "Evaluate and select appropriate cloud services and technologies to meet project and organizational requirements", "Implement robust security measures and compliance controls in cloud architectures", "Collaborate with software developers to ensure applications are optimized for cloud environments", "Develop cost models and optimize cloud resource usage to ensure cost-effectiveness", "Implement strategies for monitoring and managing cloud expenses", "Create and maintain comprehensive documentation for cloud architectures, configurations, and processes", "Ensure documentation is accessible to relevant stakeholders"], "Benefits": ["Paid Federal Holidays", "Robust Health & Dental Insurance Options", "401k with matching", "Paid vacation and sick leave", "Continuing education assistance", "Short Term / Long Term Disability & Life Insurance", "Employee Assistance Program through Sun Life Financial EAP Guidance Resources"]}, "job_job_title": "Cloud architect", "job_posting_language": "en", "job_onet_soc": "15119900", "job_onet_job_zone": "4"}