{"job_id": "wTkTj01eWJPH0-LYAAAAAA==", "employer_name": "Rocket Software", "employer_logo": "https://www.rocketsoftware.com/themes/rocketon/Stacked_color_black.png", "employer_website": "http://www.rocketsoftware.com", "employer_company_type": "Information", "job_publisher": "Adzuna", "job_employment_type": "FULLTIME", "job_title": "Senior Manager, Business Applications", "job_apply_link": "https://www.adzuna.com/details/4556665604?title=Senior_Manager%2C_Business_Applications", "job_apply_is_direct": false, "job_apply_quality_score": 0.6092, "apply_options": [{"publisher": "Adzuna", "apply_link": "https://www.adzuna.com/details/4556665604?title=Senior_Manager%2C_Business_Applications", "is_direct": false}, {"publisher": "Monster", "apply_link": "https://www.monster.com/job-openings/senior-manager-business-applications-augusta-me--7a1a3fd3-f6ad-49b7-bdfd-24df265749ff", "is_direct": false}, {"publisher": "Hispanic Today", "apply_link": "https://hispanic-today.com/augusta-me/senior-manager-business-applications/61C0C1749B1E430BA69DDD222E3871B0/job/", "is_direct": false}], "job_description": "It's fun to work in a company where people truly BELIEVE in what they're doing!\nJob Description Summary:\nThe Senior Manager, Business Applications - Salesforce on the Global Business Applications team is responsible for managing a geographically distributed team of remote technical resources based across the United States and India, leading development of new features and functionality, enhancing application capabilities on Rocket's critical back office systems and platforms, and day-to-day administration. Coordinates with the Director, Business Applications - Salesforce to determine goals for the technical team, and provides business and technical leadership for engineering, enhancing, and testing on the Salesforce platform.\nEssential Duties and Responsibilities :\n- Leadership and Team Management:\n- Lead, mentor, and grow a team of Salesforce developers, administrators, and analysts.\n- Conduct regular one-on-ones and performance reviews and provide career development guidance.\n- Foster a collaborative team environment that encourages innovation and continuous learning.\n- Strategic Planning and Execution:\n- Develop and execute a strategic roadmap for Salesforce within the organization.\n- Collaborate with cross-functional teams to ensure Salesforce solutions meet business needs and align with company goals.\n- Stay updated with the latest Salesforce features and trends to inform strategic decisions.\n- Project Management:\n- Oversee multiple Salesforce projects, ensuring timely delivery and quality.\n- Manage resource allocation, budgeting, and scheduling for Salesforce projects.\n- Ensure adherence to best practices in project management and software development lifecycle.\n- Technical Oversight:\n- Provide technical leadership in Salesforce architecture, design, and development.\n- Ensure the team adheres to the best coding, testing, and deployment practices.\n- Oversee the integration of Salesforce with other systems and third-party services.\n- Quality Assurance and Risk Management:\n- Implement and oversee robust QA processes for all Salesforce deployments.\n- Monitor system performance and security, ensuring high availability and compliance.\n- Manage risks and issue resolution in a timely and effective manner.\n- Stakeholder engagement\n- Act as a key liaison between the IT department and business units.\n- Analyze business requirements and translate them into technical solutions.\n- Communicate project status and escalate issues to stakeholders as needed.\nQualifications:\n- 6+ years of experience providing leadership for Salesforce development teams.\n- 5+ years of software engineering / application development experience.\n- Minimum 2 years' experience developing in Salesforce in Apex / Visualforce / Lightning.\n- Proven expertise in Salesforce CRM, including Sales Cloud, Service Cloud, and Experience Cloud, Einstein Analytics, etc.\n- Strong understanding of Salesforce best practices, design patterns, and limits\n- Salesforce certifications in the development, administrator, and/or architect tracks preferred.\n- Strong leadership, decision-making, relationship management, conflict resolution, and problem-solving skills\n- Demonstrated success in establishing, managing, and maintaining effective working relationships with all levels of employees.\n- Good understanding of agile methodologies, such as Scrum or Kanban.\n- Critical thinking, strong analytical skills, and problem-solving ability\n- Strong verbal and written communication skills.\n- Team oriented, collaborative, accountable and dependable.\nInformation Security:\nInformation security is everyone's responsibility. A fundamental principle of information security at Rocket Software is that all individuals in the organization have a responsibility for the security and protection of company information and IT Resources over which they have control, according to their role.\nDiversity, Inclusion & Equity:\nAt Rocket we are committed to an inclusive workplace environment, where every Rocketeer can thrive by bringing their full selves to work. Being a Rocketeer means you are part of our movement to continually drive inclusivity, diversity and equity in our workforce.\n#LI-JC1\nThe base salary range for this role is $139,799.00 - $174,749.00 /year. Exact compensation may vary based on skills, experience, and location.\n.\nWhat Rocket Software can offer you in USA:\nExtensive paid time off programs (paid holidays, sick, and unlimited vacation time)\nHealthcare coverage options to fit you (and your family's) needs\nRetirement savings, with matching contributions by Rocket Software\nLife and disability coverage\nLeadership and skills training opportunities\nTwo paid work days for off-site training\nRocket Software Inc. is committed to creating a diverse environment and is proud to be an equal opportunity employer. All qualified applicants will receive consideration for employment without regard to race, color, religion, gender, gender identity or expression, sexual orientation, national origin, genetics, disability, age, or veteran status. Rocket Software Inc. is also committed to compliance with all fair employment practices regarding citizenship and immigration status.\nRocket is committed to working with and providing reasonable accommodation to individuals with physical and mental disabilities. If you need special assistance or an accommodation while seeking employment, please call: 781-577-4321 or send an email to people@rocketsoftware.com. We will make a determination on your request for reasonable accommodation on a case-by-case basis.\n#LI-Remote\nIf you like wild growth and working with happy, enthusiastic over-achievers, you'll enjoy your career with us!\nThousands of companies around the world depend on Rocket to solve their most challenging business problems by helping them run their critical infrastructure, business processes, and data, as well as extending the value of these assets to take advantage of cloud and mobile computing, advanced analytics, and other future innovations. From the clothes we wear to the cars we drive, Rocket solutions power the back-end systems that thousands of brands interact with every day. At Rocket, software has always been about people-not just ones and zeroes. We're people solving problems for other people, and we strive to treat our customers, partners, and fellow Rocketeers with humanity. Founded in 1990, Rocket Software is headquartered in Waltham, Massachusetts with 31 offices around the world.", "job_is_remote": false, "job_posted_at_timestamp": 1706945729, "job_posted_at_datetime_utc": "2024-02-03T07:35:29.000Z", "job_city": "Augusta", "job_state": "ME", "job_country": "US", "job_latitude": 44.310623, "job_longitude": -69.77949, "job_benefits": ["retirement_savings", "paid_time_off", "health_insurance"], "job_google_link": "https://www.google.com/search?gl=us&hl=en&rciv=jb&q=senior+director+of+business+development&start=70&ibp=htl;jobs#fpstate=tldetail&htivrt=jobs&htiq=senior+director+of+business+development&htidocid=wTkTj01eWJPH0-LYAAAAAA%3D%3D", "job_offer_expiration_datetime_utc": "2024-03-26T20:06:00.000Z", "job_offer_expiration_timestamp": 1711483560, "job_required_experience": {"no_experience_required": false, "required_experience_in_months": 72, "experience_mentioned": true, "experience_preferred": false}, "job_required_skills": null, "job_required_education": {"postgraduate_degree": false, "professional_certification": false, "high_school": false, "associates_degree": false, "bachelors_degree": false, "degree_mentioned": false, "degree_preferred": false, "professional_certification_mentioned": true}, "job_experience_in_place_of_education": false, "job_min_salary": null, "job_max_salary": null, "job_salary_currency": null, "job_salary_period": null, "job_highlights": {"Qualifications": ["6+ years of experience providing leadership for Salesforce development teams", "5+ years of software engineering / application development experience", "Minimum 2 years' experience developing in Salesforce in Apex / Visualforce / Lightning", "Proven expertise in Salesforce CRM, including Sales Cloud, Service Cloud, and Experience Cloud, Einstein Analytics, etc", "Strong understanding of Salesforce best practices, design patterns, and limits", "Strong leadership, decision-making, relationship management, conflict resolution, and problem-solving skills", "Demonstrated success in establishing, managing, and maintaining effective working relationships with all levels of employees", "Good understanding of agile methodologies, such as Scrum or Kanban", "Critical thinking, strong analytical skills, and problem-solving ability", "Strong verbal and written communication skills", "Team oriented, collaborative, accountable and dependable"], "Responsibilities": ["Coordinates with the Director, Business Applications - Salesforce to determine goals for the technical team, and provides business and technical leadership for engineering, enhancing, and testing on the Salesforce platform", "Leadership and Team Management:", "Lead, mentor, and grow a team of Salesforce developers, administrators, and analysts", "Conduct regular one-on-ones and performance reviews and provide career development guidance", "Foster a collaborative team environment that encourages innovation and continuous learning", "Strategic Planning and Execution:", "Develop and execute a strategic roadmap for Salesforce within the organization", "Collaborate with cross-functional teams to ensure Salesforce solutions meet business needs and align with company goals", "Stay updated with the latest Salesforce features and trends to inform strategic decisions", "Oversee multiple Salesforce projects, ensuring timely delivery and quality", "Manage resource allocation, budgeting, and scheduling for Salesforce projects", "Ensure adherence to best practices in project management and software development lifecycle", "Technical Oversight:", "Provide technical leadership in Salesforce architecture, design, and development", "Ensure the team adheres to the best coding, testing, and deployment practices", "Oversee the integration of Salesforce with other systems and third-party services", "Quality Assurance and Risk Management:", "Implement and oversee robust QA processes for all Salesforce deployments", "Monitor system performance and security, ensuring high availability and compliance", "Manage risks and issue resolution in a timely and effective manner", "Stakeholder engagement", "Act as a key liaison between the IT department and business units", "Analyze business requirements and translate them into technical solutions", "Communicate project status and escalate issues to stakeholders as needed"], "Benefits": ["The base salary range for this role is $139,799.00 - $174,749.00 /year", "Exact compensation may vary based on skills, experience, and location", "Extensive paid time off programs (paid holidays, sick, and unlimited vacation time)", "Healthcare coverage options to fit you (and your family's) needs", "Retirement savings, with matching contributions by Rocket Software", "Life and disability coverage", "Leadership and skills training opportunities", "Two paid work days for off-site training"]}, "job_job_title": "Senior manager", "job_posting_language": "en", "job_onet_soc": "11302100", "job_onet_job_zone": "4", "job_naics_code": "511210", "job_naics_name": "Software Publishers"}