{"job_id": "f4HFe4NDkRZGzholAAAAAA==", "employer_name": "Exact Sciences Corp", "employer_logo": "https://www.exactsciences.com/-/media/Project/ExactCore/Images/Logos/ExactSciences-logo.svg?h=44&iar=0&w=127&rev=d2b730af71d1428ba8262eece64ec5c3&hash=559BFC74B2B7AC5A83D8753E460A4B7F", "employer_website": "https://patient.exactsciences.com", "employer_company_type": "Research", "job_publisher": "Media Bistro", "job_employment_type": "FULLTIME", "job_title": "Director, Health Systems Partnerships and Portfolio Marketing", "job_apply_link": "https://www.mediabistro.com/jobs/198557502-director-health-systems-partnerships-and-portfolio-marketing", "job_apply_is_direct": false, "job_apply_quality_score": 0.6732, "apply_options": [{"publisher": "Media Bistro", "apply_link": "https://www.mediabistro.com/jobs/198557502-director-health-systems-partnerships-and-portfolio-marketing", "is_direct": false}], "job_description": "Director, Health Systems Partnerships and Portfolio Marketing page is loadedDirector, Health Systems Partnerships and Portfolio MarketingApplylocationsUS - WI - MadisonUS - MA - CambridgeUS - CA - San FranciscoUS - AZ - PhoenixUS - CA - San Diegotime typeFull timeposted onPosted 2 Days Agojob requisition idR24-4482Help us change livesAt Exact Sciences, we\u2019re helping change how the world prevents, detects and guides treatment for cancer. We give patients and clinicians the clarity needed to make confident decisions when they matter most. Join our team to find a purpose-driven career, an inclusive culture, and robust benefits to supportyourlife while you\u2019re working to help others.Position OverviewThe Director, Partnerships and Portfolio Marketing will oversee and lead the development and implementation of the Health System marketing strategy across the portfolio of Exact Sciences on-market offerings and surrounding value-add services in accordance with the brand plans. This individual will be responsible for effective execution and development of portfolio assets, resources, partnerships, and marketing campaigns and initiatives to meet business goals and objectives. This individual develops operational objectives, oversees third party partnerships, manages and leads the team in developing national and regional based campaigns leveraging our existing product-brand awareness at health systems. This role will be critical in the development and management of a Key Option Leader panel to aid inVoice-of-the-Customerresearch and to lead key speaking engagements and provide insight into brand communications.The Director, Partnerships and Portfolio Marketing will be recognized as a marketing expert and brand strategy champion for the entire Exact Sciences portfolio of products and offerings. This role will provide leadership and guidance to cross functional teams in addition to direct engagement with field team leadership while facilitating seamless collaboration across all teams.Essential DutiesInclude, but are not limited to, the following:Serve as a subject matter expert in the health system market (customers, business models, priorities, capabilities, etc.).Collaborate cross-functionally with key internal stakeholders to develop the Exact Sciences portfolio story and key data-driven messages aligned to identified market segments.Identify and understand the impact of influencer entities/partners on the health system leader.Source, develop relationships with, develop a strategy for and execute tactics with key opinion leaders and entities that impact the health system landscape.Identify, partner with and execute on third party digital and SaMD solutions to drive business results across the portfolio.Collaborate across multiple internal and external teams to sponsor/serve as a change agent internally around health systems and the elevation and activation of our portfolio narrative for health systems. Collaboration will also be important to ensure development and execution of customer needs and resources.Coordinate the work of multiple external vendors and internal departments including agency partners, marketing, market research, legal, regulatory, medical affairs, corporate compliance and the relevant field teams.Translate market trends into relevant resources, think outside-the-box, and create disruptive solutions which enable us to meet our mission of early cancer detection.Translate knowledge including payment reform topics, care redesign, the move towards value-based care, healthcare information technology, population health management and other trends impacting the healthcare environment into strategy and actionable tactics that could enhance the relationship with our health systems.Collaborate with field leadership to execute upon engagement strategy both internal and external to the organization.Demonstrated ability to manage budget and resources.Demonstrated people management, leadership, and project management skills.Demonstrated ability to achieve results in a highly matrixed organization.Organize work effectively, prioritize work, and align the work to organizational initiatives.Work in a self-directed and organized manner using excellent planning and organizational skills.Possess strong interpersonal and leadership qualities.Consistent demonstration of exceptional leadership qualities, including but not limited to the ability to attract and retain the best team, foster a culture of high performance, lead with integrity, humility, accountability, and courage, and set a clear vision to energize teams towards thefuture.Effectively manage, support, and guide your team, including, but not limited to delegating tasks and responsibilities, assess employee performance and provide helpful feedback and training opportunities.Uphold company mission and values through accountability, innovation, integrity, quality, andteamwork.Support and comply with the company\u2019s Quality Management System policies andprocedures.Maintain regular and reliableattendance.Ability to act with an inclusion mindset and model these behaviors for theorganization.Ability to work on a mobile device, tablet, or in front of a computer screen and/or perform typing for approximately 90% of a typical working day.Ability to travel 40% of working time away from work location. May include overnight/weekend travel.Minimum QualificationsBachelor\u2019s degree in healthcare field, marketing, business administration or related field.Ability to develop a customized, compelling story to communicate our Exact Science message.Proficient in metrics and analytics to document value and ROI of associated partnerships and engagements.Experience working with healthcare influencers such as societies and trade associations.10+ years of experience in marketing, or commercial field.Basic computer skills include Internet navigation, Email usage, and word processing. Microsoft Word, Excel and PowerPoint skills are essential.Authorization to work in the United States without sponsorship.Demonstrated ability to perform the Essential Duties of the position with or without accommodation.Preferred QualificationsMaster\u2019s degree in healthcare, business administration or related field.Experience working with health systems and health systems leaders.Project management experience.#LI-KP1 Salary Range:$174,000.00 - $277,000.00The annual base salary shown is for this position located in US - WI - Madison on a full-time basis and may differ by hiring location. In addition, this position is bonus eligible, and is eligible to receive company stock upon hire as well as annually. Exact Sciences is proud to offer an employee experience that includes paid time off (including days for vacation, holidays, volunteering, and personal time), paid leave for parents and caregivers, a retirement savings plan, wellness support, and health benefits including medical, prescription drug, dental, and vision coverage. Learn more about our benefits .Our success relies on the experiences and perspectives of a diverse team, and Exact Sciences fosters a culture where all employees can develop personally and professionally with a sense of respect and belonging. If you require an accommodation, emailhr@exactsciences.com.We\u2019ll work with you to meet your accessibility needs.Not ready to apply? Join our talent communityand stay up to date on what\u2019s new at Exact Sciences.We are an equal employment opportunity employer. All qualified applicants will receive consideration for employment without regard to age, color, creed, disability, gender identity, national origin, protected veteran status, race, religion, sex, sexual orientation, and any other status protected by applicable local, state, or federal law. Any applicant or employee may request to view applicable portions of the company\u2019s affirmative action program.To view the Right to Work, E-Verify Employer, and Pay Transparency notices and Federal, Federal Contractor, and State employment law posters, visit our compliance hub . The documents summarize important details of the law and provide key points that you have a right to know.About Exact SciencesWe are Exact Sciences, and we're changing lives together through earlier detection and smarter answers.#J-18808-Ljbffr", "job_is_remote": false, "job_posted_at_timestamp": 1709258400, "job_posted_at_datetime_utc": "2024-03-01T02:00:00.000Z", "job_city": null, "job_state": null, "job_country": "US", "job_latitude": 37.09024, "job_longitude": -95.71289, "job_benefits": ["health_insurance", "paid_time_off", "dental_coverage", "retirement_savings"], "job_google_link": "https://www.google.com/search?gl=us&hl=en&rciv=jb&q=director+of+brand+partnerships&start=50&ibp=htl;jobs#fpstate=tldetail&htivrt=jobs&htiq=director+of+brand+partnerships&htidocid=f4HFe4NDkRZGzholAAAAAA%3D%3D", "job_offer_expiration_datetime_utc": null, "job_offer_expiration_timestamp": null, "job_required_experience": {"no_experience_required": false, "required_experience_in_months": 120, "experience_mentioned": true, "experience_preferred": true}, "job_required_skills": null, "job_required_education": {"postgraduate_degree": false, "professional_certification": false, "high_school": false, "associates_degree": false, "bachelors_degree": false, "degree_mentioned": false, "degree_preferred": true, "professional_certification_mentioned": false}, "job_experience_in_place_of_education": false, "job_min_salary": null, "job_max_salary": null, "job_salary_currency": null, "job_salary_period": null, "job_highlights": {"Qualifications": ["Demonstrated people management, leadership, and project management skills", "Demonstrated ability to achieve results in a highly matrixed organization", "Work in a self-directed and organized manner using excellent planning and organizational skills", "Possess strong interpersonal and leadership qualities", "Consistent demonstration of exceptional leadership qualities, including but not limited to the ability to attract and retain the best team, foster a culture of high performance, lead with integrity, humility, accountability, and courage, and set a clear vision to energize teams towards thefuture", "Ability to act with an inclusion mindset and model these behaviors for theorganization", "Ability to work on a mobile device, tablet, or in front of a computer screen and/or perform typing for approximately 90% of a typical working day", "Minimum QualificationsBachelor\u2019s degree in healthcare field, marketing, business administration or related field", "Ability to develop a customized, compelling story to communicate our Exact Science message", "Proficient in metrics and analytics to document value and ROI of associated partnerships and engagements", "Experience working with healthcare influencers such as societies and trade associations.10+ years of experience in marketing, or commercial field", "Basic computer skills include Internet navigation, Email usage, and word processing", "Microsoft Word, Excel and PowerPoint skills are essential", "Authorization to work in the United States without sponsorship", "Demonstrated ability to perform the Essential Duties of the position with or without accommodation", "Experience working with health systems and health systems leaders"], "Responsibilities": ["Position OverviewThe Director, Partnerships and Portfolio Marketing will oversee and lead the development and implementation of the Health System marketing strategy across the portfolio of Exact Sciences on-market offerings and surrounding value-add services in accordance with the brand plans", "This individual will be responsible for effective execution and development of portfolio assets, resources, partnerships, and marketing campaigns and initiatives to meet business goals and objectives", "This individual develops operational objectives, oversees third party partnerships, manages and leads the team in developing national and regional based campaigns leveraging our existing product-brand awareness at health systems", "This role will be critical in the development and management of a Key Option Leader panel to aid inVoice-of-the-Customerresearch and to lead key speaking engagements and provide insight into brand communications", "The Director, Partnerships and Portfolio Marketing will be recognized as a marketing expert and brand strategy champion for the entire Exact Sciences portfolio of products and offerings", "This role will provide leadership and guidance to cross functional teams in addition to direct engagement with field team leadership while facilitating seamless collaboration across all teams", "Essential DutiesInclude, but are not limited to, the following:Serve as a subject matter expert in the health system market (customers, business models, priorities, capabilities, etc.).Collaborate cross-functionally with key internal stakeholders to develop the Exact Sciences portfolio story and key data-driven messages aligned to identified market segments", "Identify and understand the impact of influencer entities/partners on the health system leader.Source, develop relationships with, develop a strategy for and execute tactics with key opinion leaders and entities that impact the health system landscape.Identify, partner with and execute on third party digital and SaMD solutions to drive business results across the portfolio", "Collaborate across multiple internal and external teams to sponsor/serve as a change agent internally around health systems and the elevation and activation of our portfolio narrative for health systems", "Collaboration will also be important to ensure development and execution of customer needs and resources", "Coordinate the work of multiple external vendors and internal departments including agency partners, marketing, market research, legal, regulatory, medical affairs, corporate compliance and the relevant field teams", "Translate market trends into relevant resources, think outside-the-box, and create disruptive solutions which enable us to meet our mission of early cancer detection", "Translate knowledge including payment reform topics, care redesign, the move towards value-based care, healthcare information technology, population health management and other trends impacting the healthcare environment into strategy and actionable tactics that could enhance the relationship with our health systems", "Collaborate with field leadership to execute upon engagement strategy both internal and external to the organization", "Effectively manage, support, and guide your team, including, but not limited to delegating tasks and responsibilities, assess employee performance and provide helpful feedback and training opportunities", "Uphold company mission and values through accountability, innovation, integrity, quality, andteamwork", "Support and comply with the company\u2019s Quality Management System policies andprocedures", "Maintain regular and reliableattendance"], "Benefits": ["Project management experience.#LI-KP1 Salary Range:$", "174,000.00 - $277,000.00The annual base salary shown is for this position located in US - WI - Madison on a full-time basis and may differ by hiring location", "In addition, this position is bonus eligible, and is eligible to receive company stock upon hire as well as annually", "Exact Sciences is proud to offer an employee experience that includes paid time off (including days for vacation, holidays, volunteering, and personal time), paid leave for parents and caregivers, a retirement savings plan, wellness support, and health benefits including medical, prescription drug, dental, and vision coverage"]}, "job_job_title": "Director", "job_posting_language": "en", "job_onet_soc": "11202100", "job_onet_job_zone": "4", "job_naics_code": "541711", "job_naics_name": "Research and Development in Biotechnology"}