{"job_id": "NpjgecmJDJ4nSYfpAAAAAA==", "employer_name": "Windsor Communities", "employer_logo": null, "employer_website": null, "employer_company_type": null, "job_publisher": "ZipRecruiter", "job_employment_type": "FULLTIME", "job_title": "Vice President of Sales", "job_apply_link": "https://www.ziprecruiter.com/c/Windsor-Communities/Job/Vice-President-of-Sales/-in-Atlanta,GA?jid=376e732a5b09714d", "job_apply_is_direct": false, "job_apply_quality_score": 0.7279, "apply_options": [{"publisher": "ZipRecruiter", "apply_link": "https://www.ziprecruiter.com/c/Windsor-Communities/Job/Vice-President-of-Sales/-in-Atlanta,GA?jid=376e732a5b09714d", "is_direct": false}, {"publisher": "LinkedIn", "apply_link": "https://www.linkedin.com/jobs/view/vice-president-of-sales-at-windsor-communities-3785246253", "is_direct": false}, {"publisher": "The Muse", "apply_link": "https://www.themuse.com/jobs/windsorcommunities/vice-president-of-sales-c79d7a", "is_direct": false}, {"publisher": "Indeed", "apply_link": "https://www.indeed.com/viewjob?jk=dbbbe2e0a505ab08", "is_direct": false}, {"publisher": "Talent.com", "apply_link": "https://www.talent.com/view?id=08e27d617847", "is_direct": false}, {"publisher": "SimplyHired", "apply_link": "https://www.simplyhired.com/job/WgwuXAK0v0lThuoO_Mll6ajT4wmLWuoYlkmAJ7Wf1t13GgbkPlHSyQ", "is_direct": false}, {"publisher": "Jooble", "apply_link": "https://jooble.org/jdp/-1265033197600972704", "is_direct": false}, {"publisher": "Lensa", "apply_link": "https://lensa.com/vice-president-of-sales-jobs/atlanta/jd/059dc87cff23ebebbff6ebfa033620fb", "is_direct": false}], "job_description": "Description\n\nPosition at Windsor Communities\n\nVice President, Sales GID - Atlanta, GA\n\nGID is a leading real estate investment and management firm that operates a diverse portfolio of multifamily, industrial, and mixed-use developments across the United States. With over 60 years of experience across multiple asset classes, GID is an established real estate private equity investor and fiduciary supported by an integrated operating platform with approximately 54,000 multifamily units and over 25M square feet of industrial and commercial space of assets under management. The company also operates a credit platform that aims to provide commercial real estate debt solutions for institutional borrowers.\n\nWith corporate offices in Atlanta, Boston, Dallas, New York City, and San Francisco, GID employs over 1,200 real estate professionals and operates an expansive portfolio of existing and under-development properties valued at over $30.11 billion as of June 2023.\n\nDESCRIPTION:\nAt Windsor, a leading national property management firm committed to providing homes where people are truly cared for, we are revolutionizing the Multifamily industry. Windsor is transforming sales through implementation of next-generation technology solutions including AI (Artificial Intelligence) and sales strategies to transform the customer experience and maximize operating results. The Vice President of Sales plays a crucial role in driving sales strategy, implementing innovative sales techniques, and leveraging technology to enhance sales performance. They lead the sales efforts by developing and executing sales plans to increase the company's profit and motivating associates to consistently hit their sales goals.\n\nTo excel as a Vice President of Sales they must develop a deep understanding of the operational intricacies within the sales vertical to formulate effective sales strategies, and aggressive but achievable, sales goals. This individual must embody Windsor's values of being accountable, inclusive, energizing, and courageous.\n\nRESPONSIBILITIES:\n\nSales Strategy and Performance:\n\u2022 Develops and executes a comprehensive strategy to achieve sales, revenue, and leasing targets.\n\u2022 Continuously analyzes leasing and sales performance indicators, recommending necessary adjustments to maintain exceptional sales performance.\n\u2022 Collaborates closely with the revenue team on market assessments, customer landscape changes, competitive intelligence, and market trend forecasting.\n\u2022 Collaborates closely with the marketing department to ensure seamless alignment between sales strategies and marketing practices.\n\u2022 Monitors and reports on key performance indicators, sales metrics, and sales effectiveness.\n\u2022 Analyzes industry trends, competitor strategies, and customer needs to identify opportunities and refine our sales strategy as necessary.\n\nSales Technology and Innovation:\n\u2022 Leverages the seamless integration of AI, human touch, and innovative sales technology, processes, and techniques to drive revenue growth and customer satisfaction.\n\u2022 Oversees the adoption and management of sales technologies, such as CRM, with a focus on ongoing improvement and process efficiency.\n\u2022 Owns the development and documentation of sales processes, including sales-related policies, standard operating procedures, technology integrations, and product workflows, providing clear guidelines for the sales team to follow.\n\u2022 Nurtures and maintains strong relationships with prop-tech (property technology) partners who focus on sales, fostering close collaboration to evolve their products.\n\u2022 Collaborates with cross-functional teams to improve communication, handoffs, and efficiency within the sales process and technologies.\n\u2022 Stays up to date on emerging sales technologies and techniques and recommends relevant tools and resources for the sales team.\n\nSales Execution & Enhancement:\n\u2022 Implements national sales programs by developing regional and site-level action plans, evaluating their effectiveness, and making improvements as needed.\n\u2022 Ensures sales associates efficiently and effectively promote and execute various programs, including video touring through Realync, self-guided touring, Bilt Rewards, Funnel CRM, Engrain mapping, EliseAI customer communications, and other technologies.\n\u2022 Maintains sales volume by tracking changing trends, customer preferences, economic indicators, competitors, and supply and demand.\n\u2022 Takes responsibility for the secret shop program, including review processes, setting expectations for successful tours, and providing guidance to improve sales strategies.\n\u2022 Manages the sales leader programs, incentives, competitions, validation, and associated rewards to drive performance excellence.\n\u2022 Leads, mentors, and inspires sales teams to meet and exceed individual and team sales targets.\n\u2022 Continuously monitors and appraises sales results, such as conversion ratios, occupancy, and revenue.\n\u2022 Provides resources, tools, and collateral to support the sales team in their efforts, ensuring they have the necessary materials to succeed.\n\u2022 Collaborates closely with the Learning & Development (L&D) team to develop tools and training programs aimed at enhancing sales performance.\n\u2022 Partners with the Analytics Department to develop and leverage new sales-related Power BI Dashboards.\n\nRole Expectations:\n\u2022 Collaborates with VP of Strategic Operations and other Windsor leaders to identify and implement innovative prop-tech partnerships that enhance the sales experience.\n\u2022 Provides expert guidance on sales-related matters to Operational Leadership, leveraging insights and offering support as needed.\n\u2022 Works closely with Marketing to ensure brand consistency, reinforce sales-related initiatives, and uphold policies and procedures.\n\u2022 Collaborates with Pricing and Revenue Management to create sales initiatives and action plans for improving asset performance.\n\u2022 Guides the creation of sales-focused learning programs in collaboration with the Learning & Development team.\n\u2022 Partners with Talent Acquisitions to attract top sales talent.\n\u2022 Builds and nurtures industry relationships, recommending valuable opportunities and staying informed about trends.\n\u2022 Demonstrates effective communication and attentive listening with diverse stakeholders.\n\u2022 Seeks continuous improvement in professional and technical expertise by staying current with sales trends and tools.\n\nREQUIREMENTS:\n\u2022 Bachelor's degree in business, marketing, or a related field (MBA preferred); or 7-10 years related experience and/or training; or equivalent combination of education and experience.\n\u2022 Proven experience in a senior sales leadership role in the Hospitality, Real Estate, Property Management or Multifamily industry, preferred.\n\u2022 Demonstrated success in consistently leading large sales teams to meet and exceed sales targets and driving revenue growth.\n\u2022 Deep knowledge of sales strategies, techniques, and best practices.\n\u2022 Proficiency in using sales technologies and CRMs.\n\u2022 Exceptional leadership and team-building skills.\n\u2022 Outstanding communication, presentation, and negotiation abilities.\n\u2022 Analytical mindset with the ability to use data to inform decisions.\n\nCompensation range: $150K - $182K plus bonuses.\n\nDrug testing and background checks are an employment requirement. These are required steps in the hiring process.\n\nE-Verify\n\nOur company considers a range of factors including education and experience when determining base compensation.\n\nThis position is also eligible for bonus and benefits. For more information, visit: Benefits!\n\nGID is an Equal Opportunity Employer", "job_is_remote": false, "job_posted_at_timestamp": 1699488000, "job_posted_at_datetime_utc": "2023-11-09T00:00:00.000Z", "job_city": "Atlanta", "job_state": "GA", "job_country": "US", "job_latitude": 33.748753, "job_longitude": -84.38769, "job_benefits": ["health_insurance"], "job_google_link": "https://www.google.com/search?gl=us&hl=en&rciv=jb&q=vice+president+of+sales&start=50&ibp=htl;jobs#fpstate=tldetail&htivrt=jobs&htiq=vice+president+of+sales&htidocid=NpjgecmJDJ4nSYfpAAAAAA%3D%3D", "job_offer_expiration_datetime_utc": "2024-04-09T00:00:00.000Z", "job_offer_expiration_timestamp": 1712620800, "job_required_experience": {"no_experience_required": false, "required_experience_in_months": 84, "experience_mentioned": true, "experience_preferred": true}, "job_required_skills": null, "job_required_education": {"postgraduate_degree": false, "professional_certification": false, "high_school": false, "associates_degree": false, "bachelors_degree": false, "degree_mentioned": true, "degree_preferred": true, "professional_certification_mentioned": false}, "job_experience_in_place_of_education": false, "job_min_salary": null, "job_max_salary": null, "job_salary_currency": null, "job_salary_period": null, "job_highlights": {"Qualifications": ["Demonstrated success in consistently leading large sales teams to meet and exceed sales targets and driving revenue growth", "Deep knowledge of sales strategies, techniques, and best practices", "Proficiency in using sales technologies and CRMs", "Exceptional leadership and team-building skills", "Outstanding communication, presentation, and negotiation abilities", "Analytical mindset with the ability to use data to inform decisions", "Drug testing and background checks are an employment requirement"], "Responsibilities": ["The Vice President of Sales plays a crucial role in driving sales strategy, implementing innovative sales techniques, and leveraging technology to enhance sales performance", "They lead the sales efforts by developing and executing sales plans to increase the company's profit and motivating associates to consistently hit their sales goals", "To excel as a Vice President of Sales they must develop a deep understanding of the operational intricacies within the sales vertical to formulate effective sales strategies, and aggressive but achievable, sales goals", "This individual must embody Windsor's values of being accountable, inclusive, energizing, and courageous", "Develops and executes a comprehensive strategy to achieve sales, revenue, and leasing targets", "Continuously analyzes leasing and sales performance indicators, recommending necessary adjustments to maintain exceptional sales performance", "Collaborates closely with the revenue team on market assessments, customer landscape changes, competitive intelligence, and market trend forecasting", "Collaborates closely with the marketing department to ensure seamless alignment between sales strategies and marketing practices", "Monitors and reports on key performance indicators, sales metrics, and sales effectiveness", "Analyzes industry trends, competitor strategies, and customer needs to identify opportunities and refine our sales strategy as necessary", "Leverages the seamless integration of AI, human touch, and innovative sales technology, processes, and techniques to drive revenue growth and customer satisfaction", "Oversees the adoption and management of sales technologies, such as CRM, with a focus on ongoing improvement and process efficiency", "Owns the development and documentation of sales processes, including sales-related policies, standard operating procedures, technology integrations, and product workflows, providing clear guidelines for the sales team to follow", "Nurtures and maintains strong relationships with prop-tech (property technology) partners who focus on sales, fostering close collaboration to evolve their products", "Collaborates with cross-functional teams to improve communication, handoffs, and efficiency within the sales process and technologies", "Stays up to date on emerging sales technologies and techniques and recommends relevant tools and resources for the sales team", "Implements national sales programs by developing regional and site-level action plans, evaluating their effectiveness, and making improvements as needed", "Ensures sales associates efficiently and effectively promote and execute various programs, including video touring through Realync, self-guided touring, Bilt Rewards, Funnel CRM, Engrain mapping, EliseAI customer communications, and other technologies", "Maintains sales volume by tracking changing trends, customer preferences, economic indicators, competitors, and supply and demand", "Takes responsibility for the secret shop program, including review processes, setting expectations for successful tours, and providing guidance to improve sales strategies", "Manages the sales leader programs, incentives, competitions, validation, and associated rewards to drive performance excellence", "Leads, mentors, and inspires sales teams to meet and exceed individual and team sales targets", "Continuously monitors and appraises sales results, such as conversion ratios, occupancy, and revenue", "Provides resources, tools, and collateral to support the sales team in their efforts, ensuring they have the necessary materials to succeed", "Collaborates closely with the Learning & Development (L&D) team to develop tools and training programs aimed at enhancing sales performance", "Partners with the Analytics Department to develop and leverage new sales-related Power BI Dashboards", "Collaborates with VP of Strategic Operations and other Windsor leaders to identify and implement innovative prop-tech partnerships that enhance the sales experience", "Provides expert guidance on sales-related matters to Operational Leadership, leveraging insights and offering support as needed", "Works closely with Marketing to ensure brand consistency, reinforce sales-related initiatives, and uphold policies and procedures", "Collaborates with Pricing and Revenue Management to create sales initiatives and action plans for improving asset performance", "Guides the creation of sales-focused learning programs in collaboration with the Learning & Development team", "Partners with Talent Acquisitions to attract top sales talent", "Builds and nurtures industry relationships, recommending valuable opportunities and staying informed about trends", "Demonstrates effective communication and attentive listening with diverse stakeholders", "Seeks continuous improvement in professional and technical expertise by staying current with sales trends and tools"], "Benefits": ["Compensation range: $150K - $182K plus bonuses", "Our company considers a range of factors including education and experience when determining base compensation", "This position is also eligible for bonus and benefits"]}, "job_job_title": "Vice", "job_posting_language": "en", "job_onet_soc": "11101100", "job_onet_job_zone": "5", "job_occupational_categories": ["11-2022.00: Sales Managers"]}