{"job_id": "gIp6thLwp5f90t8dAAAAAA==", "employer_name": "Flexential Corp", "employer_logo": "https://www.flexential.com/themes/custom/themekit/images/logo-blue.png", "employer_website": "http://www.flexential.com", "employer_company_type": null, "job_publisher": "Dice", "job_employment_type": "FULLTIME", "job_title": "Sr. Marketing Operations and Analytics Manager", "job_apply_link": "https://www.dice.com/apply-redirect?eyJjb25maWd1cmVkVXJsIjoiaHR0cHM6Ly90bmwyLmpvbWV0ZXIuY29tL3YyL2pvYj9qeD01dXdsYmI4ODAwOGJjYWJiYjc2YWE4NzgxOGU1MTA4OTU5NWRiQzRBRkNCRzRBVUJBQUFBQUFET0FLJmp6PTVnc2VsODUyNjQ0Y2ZhZjc1OGY2MjllMmE3Zjk5ODQ5YWRhNjFEQUFPTUNERUFBQVFBQUFBQUJTQSZzb3VyY2U9Sm92ZW85PSIsImpvYklkIjoiMzM0NWQ1MGItMGU4MC00NDQ5LWFhZTctMzUwOTZmZTg1MmJiIiwiam9iVGl0bGUiOiJTci4gTWFya2V0aW5nIE9wZXJhdGlvbnMgYW5kIEFuYWx5dGljcyBNYW5hZ2VyIiwiam9iVHlwZSI6InByb2dyYW1tYXRpYyJ9", "job_apply_is_direct": false, "job_apply_quality_score": 0.7048, "apply_options": [{"publisher": "Dice", "apply_link": "https://www.dice.com/apply-redirect?eyJjb25maWd1cmVkVXJsIjoiaHR0cHM6Ly90bmwyLmpvbWV0ZXIuY29tL3YyL2pvYj9qeD01dXdsYmI4ODAwOGJjYWJiYjc2YWE4NzgxOGU1MTA4OTU5NWRiQzRBRkNCRzRBVUJBQUFBQUFET0FLJmp6PTVnc2VsODUyNjQ0Y2ZhZjc1OGY2MjllMmE3Zjk5ODQ5YWRhNjFEQUFPTUNERUFBQVFBQUFBQUJTQSZzb3VyY2U9Sm92ZW85PSIsImpvYklkIjoiMzM0NWQ1MGItMGU4MC00NDQ5LWFhZTctMzUwOTZmZTg1MmJiIiwiam9iVGl0bGUiOiJTci4gTWFya2V0aW5nIE9wZXJhdGlvbnMgYW5kIEFuYWx5dGljcyBNYW5hZ2VyIiwiam9iVHlwZSI6InByb2dyYW1tYXRpYyJ9", "is_direct": false}, {"publisher": "BeBee", "apply_link": "https://us.bebee.com/job/20240319-5392747bb441bfb9794febfadb46bc4f", "is_direct": false}], "job_description": "Pay Rate Type Job Description: As Flexential continues to build an agile and fast paced modern marketing organization, we're looking for a resourceful, collaborative, and highly analytical individual to join our Marketing Operations team. In this strategic role as a Senior Marketing Operations and Analytics Manager, you will analyze marketing programs\u2019 performance data to help the marketing teams understand the effectiveness of overall and individual campaigns and deliver actionable insights for increased investment or corrective improvements. You will focus on systems, standards, and processes used to analyze program performance and business KPIs. As a collaborator with proven ability to work effectively and earn trust in a fast-paced, high-pressure entrepreneurial environment, you\u2019ll work with marketing channel owners, IT, and BI teams to manage and maintain the reporting infrastructure and ecosystem. Key Responsibilities and Essential Job Functions Drive the end-to-end marketing analytics functions including regular campaign performance measurement, program optimization insights, lead quality analysis, and funnel conversion KPIs. Partner with revenue marketing team to strategize and build the attribution models, establish relevant OKRs, KPIs, and other analytics reporting to optimize cost, maximize revenue and improve efficiencies. Provide a high value consultative layer on top of analytics deliverables; tell relevant and actionable data stories. Ensure optimal MarTech integration for data flow and attributions, actively monitor, analyze, and report on the health of the marketing funnel, including investigating and troubleshooting any issues. Provide marketing channel owners the segmentation and insights to help develop prospecting strategy and targeting tactics for new business growth and upsell/cross-sell to current customers. Drive the management of executive dashboards, and monthly/quarterly/annual marketing KPI reporting package. Interpret the data and results and present to the stakeholders to help them drive informed business decisions. Proactively engage and collaborate with marketing leadership, digital marketing, demand gen, field marketing, product marketing, and content marketing teams, on a weekly, monthly, and quarterly basis to communicate progress, take feedback and adjust plans to continue to improve performance and business objectives. Be an expert in customer data to identify and bridge the gaps using internal resources and outside data sources and maintain a healthy blend of buying committee contacts. Own and improve overall data quality and hygiene through regular audit, cleansing and enrichment. Create efficiencies within Marketing Operations functional group by implementing industry best practices, best in class automation, and process improvements Technical Skills: Campaign Analysis: Expertise in campaign architecture, performance score cards and diagnostics, behavioral analytics, and make strategic recommendations. BI and Visualization: Strong in data visualization, reporting, interactive dashboards, and data modeling. Technology Platforms: Hands on experience in Marketo, SFDC, GA4, 6sense, Zoominfo, Tableau, Excel etc. Ecosystem: Experience with MarTech ecosystem, digital analytics, content optimization, and personalization. Database: Competently and independently navigate through disparate data sources to extract, process, transform, analyze, and present the analysis to stakeholders. AI and ML: Strong interest in artificial intelligence and machine learning principles including statistical analysis, model creation and application of custom analytical models. Qualifications: 6+ years of marketing operations or marketing analyst/consultant experience with at least 5 years of hands-on experience in advanced campaign analysis and data management within the B2B enterprise technology space. Bachelor\u2019s degree in marketing analytics, data science, or a related field of study In-depth knowledge of marketing automation ecosystem and various marketing channels used for demand generation, digital marketing, ABM, content marketing, email nurture, etc. Strong communication and interpersonal skills to establish trust and develop relationships with cross-functional stakeholders. Highly analytical with advanced Excel skills, digital marketing KPI measurement, and exposure to Tableau or similar BI tools. Exceptional project management skills, and complex problem-solving ability. Data-driven, well organized, detail-oriented, and self-starter. Willingness to learn, collaborate, and receive feedback. If you enjoy a collaborative work environment, are eager to roll up your sleeves to tinker and tune processes, celebrate successes, and bring passion and enthusiasm to enhance team culture, then we encourage you to APPLY NOW! Physical Requirements Primarily sitting with some walking, standing, and bending. Able to hear and speak into a telephone. Close visual work on a computer terminal. Dexterity of hands and fingers to operate any required computer keyboard, mouse, and other technical instruments. Able to lift and carry up to 20 lbs. Able to set up and take down tradeshow space. Work Conditions Standard office environment. Extensive daily usage of workstation or computer. Occasional overnight travel, up to 10%. Must possess a current, valid state-issued driver\u2019s license. Benefits of working at Flexential: Medical, Telehealth, Dental and Vision 401(k) Health Savings Accounts (HAS) and Flexible Spending Accounts (FSA) Life and AD&D Short Term and Long-Term disability Flex Time Off (PTO) Leave of Absence Employee Assistance Program Wellness Program Rewards and Recognition Program Benefits are subject to change at the Company\u2019s discretion. Base Pay Range: Annualized salary range offered for this position is estimated to be $116,900 - $134,000. However, the actual pay range depends on each candidate\u2019s experience, location, and qualifications. Variable Pay: Discretionary annual bonus, based on personal and company performance. EEO Statement: Flexential is an equal opportunity employer, and all qualified applicants will receive consideration for employment without regard to race, color, religion, sex, sexual orientation, gender identity or expression, pregnancy, age, national origin, disability status, genetic information, protected veteran status, or any other characteristic protected by law. #LI-PS1 Flexential offers flexible and essential services that help organizations optimize their journey of IT transformation while simultaneously balancing cost, scalability, compliance and security. The company, co-headquartered in Charlotte and Denver, is committed to building trusted relationships and delivering tailored solutions that suit the individual needs of its customers. Flexential is deeply invested in the success of its customers, who trust it to deliver core data center solutions of colocation and connectivity, as well as, cloud, managed solutions and professional services. Flexential\u2019s robust suite of assets spans 21 markets and comprises 38 highly redundant and connectivity-rich data centers. For more information on Flexential, please visit www.flexential.com. Flexential is a registered trademark of the Flexential Corp. Follow Flexential on LinkedIn, Twitter, Facebook and YouTube.", "job_is_remote": true, "job_posted_at_timestamp": 1707177600, "job_posted_at_datetime_utc": "2024-02-06T00:00:00.000Z", "job_city": null, "job_state": null, "job_country": "US", "job_latitude": 37.09024, "job_longitude": -95.71289, "job_benefits": ["dental_coverage", "retirement_savings", "health_insurance", "paid_time_off"], "job_google_link": "https://www.google.com/search?gl=us&hl=en&rciv=jb&q=manager+of+marketing+analytics&start=20&ibp=htl;jobs#fpstate=tldetail&htivrt=jobs&htiq=manager+of+marketing+analytics&htidocid=gIp6thLwp5f90t8dAAAAAA%3D%3D", "job_offer_expiration_datetime_utc": null, "job_offer_expiration_timestamp": null, "job_required_experience": {"no_experience_required": false, "required_experience_in_months": 72, "experience_mentioned": true, "experience_preferred": false}, "job_required_skills": null, "job_required_education": {"postgraduate_degree": false, "professional_certification": false, "high_school": false, "associates_degree": false, "bachelors_degree": false, "degree_mentioned": true, "degree_preferred": true, "professional_certification_mentioned": false}, "job_experience_in_place_of_education": false, "job_min_salary": null, "job_max_salary": null, "job_salary_currency": null, "job_salary_period": null, "job_highlights": {"Qualifications": ["Ecosystem: Experience with MarTech ecosystem, digital analytics, content optimization, and personalization", "Qualifications: 6+ years of marketing operations or marketing analyst/consultant experience with at least 5 years of hands-on experience in advanced campaign analysis and data management within the B2B enterprise technology space", "Bachelor\u2019s degree in marketing analytics, data science, or a related field of study In-depth knowledge of marketing automation ecosystem and various marketing channels used for demand generation, digital marketing, ABM, content marketing, email nurture, etc", "Strong communication and interpersonal skills to establish trust and develop relationships with cross-functional stakeholders", "Highly analytical with advanced Excel skills, digital marketing KPI measurement, and exposure to Tableau or similar BI tools", "Exceptional project management skills, and complex problem-solving ability", "Data-driven, well organized, detail-oriented, and self-starter", "Willingness to learn, collaborate, and receive feedback", "If you enjoy a collaborative work environment, are eager to roll up your sleeves to tinker and tune processes, celebrate successes, and bring passion and enthusiasm to enhance team culture, then we encourage you to APPLY NOW!", "Physical Requirements Primarily sitting with some walking, standing, and bending", "Able to hear and speak into a telephone", "Close visual work on a computer terminal", "Dexterity of hands and fingers to operate any required computer keyboard, mouse, and other technical instruments", "Able to lift and carry up to 20 lbs", "Able to set up and take down tradeshow space", "Must possess a current, valid state-issued driver\u2019s license"], "Responsibilities": ["In this strategic role as a Senior Marketing Operations and Analytics Manager, you will analyze marketing programs\u2019 performance data to help the marketing teams understand the effectiveness of overall and individual campaigns and deliver actionable insights for increased investment or corrective improvements", "You will focus on systems, standards, and processes used to analyze program performance and business KPIs", "As a collaborator with proven ability to work effectively and earn trust in a fast-paced, high-pressure entrepreneurial environment, you\u2019ll work with marketing channel owners, IT, and BI teams to manage and maintain the reporting infrastructure and ecosystem", "Key Responsibilities and Essential Job Functions Drive the end-to-end marketing analytics functions including regular campaign performance measurement, program optimization insights, lead quality analysis, and funnel conversion KPIs", "Partner with revenue marketing team to strategize and build the attribution models, establish relevant OKRs, KPIs, and other analytics reporting to optimize cost, maximize revenue and improve efficiencies", "Provide a high value consultative layer on top of analytics deliverables; tell relevant and actionable data stories", "Ensure optimal MarTech integration for data flow and attributions, actively monitor, analyze, and report on the health of the marketing funnel, including investigating and troubleshooting any issues", "Provide marketing channel owners the segmentation and insights to help develop prospecting strategy and targeting tactics for new business growth and upsell/cross-sell to current customers", "Drive the management of executive dashboards, and monthly/quarterly/annual marketing KPI reporting package", "Interpret the data and results and present to the stakeholders to help them drive informed business decisions", "Proactively engage and collaborate with marketing leadership, digital marketing, demand gen, field marketing, product marketing, and content marketing teams, on a weekly, monthly, and quarterly basis to communicate progress, take feedback and adjust plans to continue to improve performance and business objectives", "Be an expert in customer data to identify and bridge the gaps using internal resources and outside data sources and maintain a healthy blend of buying committee contacts", "Own and improve overall data quality and hygiene through regular audit, cleansing and enrichment", "Create efficiencies within Marketing Operations functional group by implementing industry best practices, best in class automation, and process improvements Technical Skills: Campaign Analysis: Expertise in campaign architecture, performance score cards and diagnostics, behavioral analytics, and make strategic recommendations", "BI and Visualization: Strong in data visualization, reporting, interactive dashboards, and data modeling", "Occasional overnight travel, up to 10%"], "Benefits": ["Benefits of working at Flexential: Medical, Telehealth, Dental and Vision 401(k) Health Savings Accounts (HAS) and Flexible Spending Accounts (FSA) Life and AD&D Short Term and Long-Term disability Flex Time Off (PTO) Leave of Absence Employee Assistance Program Wellness Program Rewards and Recognition Program Benefits are subject to change at the Company\u2019s discretion", "Base Pay Range: Annualized salary range offered for this position is estimated to be $116,900 - $134,000", "Variable Pay: Discretionary annual bonus, based on personal and company performance"]}, "job_job_title": "Manager", "job_posting_language": "en", "job_onet_soc": "11202100", "job_onet_job_zone": "4"}