{"job_id": "lYKXZns03HH4oN69AAAAAA==", "employer_name": "CONDUENT", "employer_logo": "https://www.conduentassets.com/conduent-logo.png", "employer_website": "http://www.conduent.com", "employer_company_type": null, "job_publisher": "Conduent", "job_employment_type": "FULLTIME", "job_title": "Senior Director, Client Partner Executive", "job_apply_link": "https://careers.conduent.com/us/en/job/90395/Senior-Director-Client-Partner-Executive", "job_apply_is_direct": false, "job_apply_quality_score": 0.9157, "apply_options": [{"publisher": "Conduent", "apply_link": "https://careers.conduent.com/us/en/job/90395/Senior-Director-Client-Partner-Executive", "is_direct": false}, {"publisher": "LinkedIn", "apply_link": "https://www.linkedin.com/jobs/view/senior-director-client-partner-executive-at-conduent-3854544201", "is_direct": false}, {"publisher": "LocalJobs.com", "apply_link": "https://www.localjobs.com/job/united-states-senior-director-client-partner-executive", "is_direct": false}, {"publisher": "Levels.fyi", "apply_link": "https://www.levels.fyi/jobs?jobId=92358990018552518", "is_direct": false}], "job_description": "About Conduent:\n\nThrough our dedicated associates, Conduent delivers mission-critical services and solutions on behalf of Fortune 100 companies and over 500 governments \u2013 creating exceptional outcomes for our clients and the millions of people who count on them. You have an opportunity to personally thrive, make a difference and be part of a culture where individuality is noticed and valued every day.\n\nJob Description:\n\nSenior Director, Client Partner Executive\n\nAre you an experienced Client Partner and seller with a strong track record of building and maintaining long-term relationships with enterprise clients?\n\nDo you possess advanced knowledge of BPO sales and the ability to add value to clients' businesses over time?\n\nAbout this Role:\n\nAs a Client Partner at Conduent, you will play a pivotal role in maintaining the health and satisfaction of our current enterprise accounts while driving revenue growth and overall sales. Your responsibilities will encompass building trusting relationships, growing client satisfaction, and delivering revenue growth.\n\nResponsibilities:\n\u2022 Building Trusting Relationships: Growing relationships with Conduent's largest clients by establishing long-term, deep, and meaningful connections across the C-Suite and other senior executives with the authority to make buying decisions. Becoming the trusted partner clients can rely on for advice and insights regarding their businesses.\n\u2022 Consultative Cross-Selling: Utilizing consultative selling expertise to cross-sell new services to existing clients.\n\u2022 Value Proposition Development: Collaborating with solutions leaders to develop new value propositions across a range of commercial services and solutions.\n\u2022 Financial Management: Managing account-level P&L to meet business unit financial targets.\n\u2022 Alignment with Strategy: Developing and supporting value propositions for focus areas and ensuring alignment with Conduent and the business unit's strategy.\n\u2022 Sales Expansion: Partnering with solutions leaders and Base Sales executives to promote sales of new services into existing accounts.\n\u2022 Operational Enhancement: Recommending and initiating enhancements to the sales and marketing operations, including the establishment of sales goals, growth analysis, and the timely submission of required progress reports, forecasts, quotations, budgets, and rates.\n\u2022 Solution Expertise: Developing a basic understanding of Conduent services, solutions, and offerings to guide clients in driving business outcomes. Solution areas include customer experience, financial services, claims, F&A, legal services, and more.\n\u2022 Global Marketing Support: Supporting the development of marketing plans that appeal to a diverse global customer base to achieve sales and profit objectives.\n\u2022 Ad Hoc Duties: Performing all other duties as assigned.\n\nRequirements:\n\u2022 Consultative Account Manager: Developing deep relationships and adding value to clients' businesses over the long term.\n\u2022 Proven Sales Experience: Demonstrating 15+ years of experience with large-scale, enterprise-wide sales and account management.\n\u2022 BPO Knowledge: Demonstrating advanced knowledge of BPO sales and relationship management processes.\n\u2022 Leadership: Possessing strong leadership experience, pursuit, self-motivation, and excellent presentation skills.\n\u2022 Solution Selling: Having a strong understanding of BPO solution selling and account leadership.\n\u2022 Collaborative Team Player: Demonstrating the ability to partner with delivery organizations to add value.\n\u2022 Aggressive Seller: Forging relationships with CEOs and other C-suite executives, as well as key line of business contacts.\n\u2022 New Logo Business Development: Bringing experience in new logo business development and sales.\n\u2022 Strategic Skills: Being skilled in account strategy, account planning, and relationship strategy.\n\u2022 P&L Leadership: Having experience leading a P&L.\n\u2022 Service Delivery Collaboration: Having experience working closely with service delivery counterparts.\n\u2022 Account Growth: Demonstrating a proven track record of significantly growing existing accounts.\n\u2022 Sales Achievement: Proving a track record of attaining and exceeding quotas.\n\u2022 Communication Skills: Possessing strong communication and presentation skills.\n\u2022 Opportunity Identification: Being able to delve deep into large accounts to uncover new opportunities.\n\u2022 Strong Communication: Possessing excellent oral and written communication skills, including the ability to effectively present information to top management and executives (internally and externally) as required.\n\u2022 Self-Motivated: Demonstrating strong self-motivation and a desire for success.\n\u2022 Educational Qualification: Holding a bachelor's degree in a related field or equivalent work experience.\n\nFlexible Working\n\nAt Conduent, we want you to be yourself. We recognize that everyone is different and that how people want to work and deliver at their best is different for everyone too.\nIn this role, you can expect the following working conditions:\n\u2022 Remote work: Enjoy the convenience of working from home and maximize your time.\n\u2022 Flexible Working Hours: Flex the times you work during the day, allowing you to balance your home life and work.\n\nWorking For You\n\nPerks and rewards designed for you:\n\u2022 Health and Welfare Benefits: Our health and welfare benefits can be tailored to fit your needs and start on the first day of employment.\n\u2022 Retirement Savings: We support you as you invest in your future.\n\u2022 Employee Discounts: We offer you access to a vast selection of global, national, and local discounts on merchandise, services, travel, and more.\n\u2022 Career Growth Opportunities: We help you thrive, so together, we can grow. We provide opportunities to advance your career with a vast portfolio of businesses and a global footprint.\n\u2022 Training: Earn while you learn and continue to grow with access to award-winning learning platforms throughout your Conduent career.\n\u2022 Great Work Environment: We are proud of our award-winning culture and the recognition we\u2019ve received for our diversity efforts.\n\nJoin Us\n\nAt Conduent, we are one team, one mission. We understand that our success is directly related to the success of our associates. We strive to create a culture where you can:\n\u2022 Bring your authentic self to work.\n\u2022 Grow and thrive, both personally and professionally\n\u2022 Make a difference with our clients, in our communities, and with the millions of people we support.\n\nWhen you join Conduent, you are engaged in creating the future - both our company\u2019s and your own. With more than 60,000 associates across 24 countries, we will provide you the opportunity to grow with a team of people who will challenge and inspire you to be the best.\n\nPay Transparency Laws in some locations require disclosure of compensation and/or benefits-related information. For this position, actual salaries will vary and may be above or below the range based on various factors including but not limited to location, experience, and performance. In addition to base pay, this position, based on business need, may be eligible for a bonus or incentive. In addition, Conduent provides a variety of benefits to employees including health insurance coverage, voluntary dental and vision programs, life and disability insurance, a retirement savings plan, paid holidays, and paid time off (PTO) or vacation and/or sick time. The estimated base salary range for this role is $152,250 - $203,000.\nClosing:\n\nConduent is an Equal Opportunity Employer and considers applicants for all positions without regard to race, color, creed, religion, ancestry, national origin, age, gender identity, gender expression, sex/gender, marital status, sexual orientation, physical or mental disability, medical condition, use of a guide dog or service animal, military/veteran status, citizenship status, basis of genetic information, or any other group protected by law.\n\nPeople with disabilities who need a reasonable accommodation to apply for or compete for employment with Conduent may request such accommodation(s) by clicking on the following link, completing the accommodation request form, and submitting the request by using the \"Submit\" button at the bottom of the form. For those using Google Chrome or Mozilla Firefox please download the form first: click here to access or download the form. You may also click here to access Conduent\u2019s ADAAA Accommodation Policy.\n\nAt Conduent, we value the health and safety of our associates, their families and our community. Under our current protocols, we do not require vaccination against COVID for most of our US jobs, but may require you to provide your COVID vaccination status, where legally permissible.", "job_is_remote": false, "job_posted_at_timestamp": 1710288000, "job_posted_at_datetime_utc": "2024-03-13T00:00:00.000Z", "job_city": null, "job_state": null, "job_country": "US", "job_latitude": 37.09024, "job_longitude": -95.71289, "job_benefits": ["paid_time_off", "dental_coverage", "health_insurance", "retirement_savings"], "job_google_link": "https://www.google.com/search?gl=us&hl=en&rciv=jb&q=senior+manager+of+business+development&start=10&ibp=htl;jobs#fpstate=tldetail&htivrt=jobs&htiq=senior+manager+of+business+development&htidocid=lYKXZns03HH4oN69AAAAAA%3D%3D", "job_offer_expiration_datetime_utc": null, "job_offer_expiration_timestamp": null, "job_required_experience": {"no_experience_required": false, "required_experience_in_months": 180, "experience_mentioned": true, "experience_preferred": false}, "job_required_skills": null, "job_required_education": {"postgraduate_degree": false, "professional_certification": false, "high_school": false, "associates_degree": false, "bachelors_degree": false, "degree_mentioned": true, "degree_preferred": true, "professional_certification_mentioned": false}, "job_experience_in_place_of_education": false, "job_min_salary": null, "job_max_salary": null, "job_salary_currency": null, "job_salary_period": null, "job_highlights": {"Qualifications": ["Do you possess advanced knowledge of BPO sales and the ability to add value to clients' businesses over time?", "Consultative Account Manager: Developing deep relationships and adding value to clients' businesses over the long term", "Proven Sales Experience: Demonstrating 15+ years of experience with large-scale, enterprise-wide sales and account management", "BPO Knowledge: Demonstrating advanced knowledge of BPO sales and relationship management processes", "Leadership: Possessing strong leadership experience, pursuit, self-motivation, and excellent presentation skills", "Solution Selling: Having a strong understanding of BPO solution selling and account leadership", "New Logo Business Development: Bringing experience in new logo business development and sales", "Strategic Skills: Being skilled in account strategy, account planning, and relationship strategy", "P&L Leadership: Having experience leading a P&L", "Service Delivery Collaboration: Having experience working closely with service delivery counterparts", "Account Growth: Demonstrating a proven track record of significantly growing existing accounts", "Sales Achievement: Proving a track record of attaining and exceeding quotas", "Opportunity Identification: Being able to delve deep into large accounts to uncover new opportunities", "Strong Communication: Possessing excellent oral and written communication skills, including the ability to effectively present information to top management and executives (internally and externally) as required", "Self-Motivated: Demonstrating strong self-motivation and a desire for success", "Educational Qualification: Holding a bachelor's degree in a related field or equivalent work experience"], "Responsibilities": ["As a Client Partner at Conduent, you will play a pivotal role in maintaining the health and satisfaction of our current enterprise accounts while driving revenue growth and overall sales", "Your responsibilities will encompass building trusting relationships, growing client satisfaction, and delivering revenue growth", "Building Trusting Relationships: Growing relationships with Conduent's largest clients by establishing long-term, deep, and meaningful connections across the C-Suite and other senior executives with the authority to make buying decisions", "Becoming the trusted partner clients can rely on for advice and insights regarding their businesses", "Consultative Cross-Selling: Utilizing consultative selling expertise to cross-sell new services to existing clients", "Value Proposition Development: Collaborating with solutions leaders to develop new value propositions across a range of commercial services and solutions", "Financial Management: Managing account-level P&L to meet business unit financial targets", "Alignment with Strategy: Developing and supporting value propositions for focus areas and ensuring alignment with Conduent and the business unit's strategy", "Sales Expansion: Partnering with solutions leaders and Base Sales executives to promote sales of new services into existing accounts", "Operational Enhancement: Recommending and initiating enhancements to the sales and marketing operations, including the establishment of sales goals, growth analysis, and the timely submission of required progress reports, forecasts, quotations, budgets, and rates", "Solution Expertise: Developing a basic understanding of Conduent services, solutions, and offerings to guide clients in driving business outcomes", "Global Marketing Support: Supporting the development of marketing plans that appeal to a diverse global customer base to achieve sales and profit objectives", "Ad Hoc Duties: Performing all other duties as assigned"], "Benefits": ["Flexible Working Hours: Flex the times you work during the day, allowing you to balance your home life and work", "Health and Welfare Benefits: Our health and welfare benefits can be tailored to fit your needs and start on the first day of employment", "Retirement Savings: We support you as you invest in your future", "Employee Discounts: We offer you access to a vast selection of global, national, and local discounts on merchandise, services, travel, and more", "Career Growth Opportunities: We help you thrive, so together, we can grow", "We provide opportunities to advance your career with a vast portfolio of businesses and a global footprint", "Training: Earn while you learn and continue to grow with access to award-winning learning platforms throughout your Conduent career", "Bring your authentic self to work", "Grow and thrive, both personally and professionally", "For this position, actual salaries will vary and may be above or below the range based on various factors including but not limited to location, experience, and performance", "In addition to base pay, this position, based on business need, may be eligible for a bonus or incentive", "In addition, Conduent provides a variety of benefits to employees including health insurance coverage, voluntary dental and vision programs, life and disability insurance, a retirement savings plan, paid holidays, and paid time off (PTO) or vacation and/or sick time", "The estimated base salary range for this role is $152,250 - $203,000"]}, "job_job_title": "Senior director", "job_posting_language": "en", "job_onet_soc": "11202200", "job_onet_job_zone": "4", "job_occupational_categories": ["Sales"]}