{"job_id": "VZp1BrPnMg8xsH00AAAAAA==", "employer_name": "ZoomInfo", "employer_logo": "https://mms.businesswire.com/media/20230201005300/en/1353560/5/ZoomInfo_Primary_Logo.jpg", "employer_website": "http://www.zoominfo.com", "employer_company_type": "Information", "job_publisher": "VentureFizz", "job_employment_type": "FULLTIME", "job_title": "Senior Director, Applications", "job_apply_link": "https://venturefizz.com/jobs/senior-director-applications-at-zoominfo", "job_apply_is_direct": false, "job_apply_quality_score": 0.7338, "apply_options": [{"publisher": "VentureFizz", "apply_link": "https://venturefizz.com/jobs/senior-director-applications-at-zoominfo", "is_direct": false}, {"publisher": "Built In", "apply_link": "https://builtin.com/job/senior-director-applications/2365322", "is_direct": false}, {"publisher": "Jobright AI", "apply_link": "https://jobright.ai/jobs/info/65eae7574c7c8532d7c824b8", "is_direct": false}], "job_description": "At ZoomInfo, we encourage creativity, value innovation, demand teamwork, expect accountability and cherish results. We value your take charge, take initiative, get stuff done attitude and will help you unlock your growth potential. One great choice can change everything. Thrive with us at ZoomInfo.\n\nIn this role, you will serve as a strategic consultative partner to Executive and C-Suite stakeholders to translate business strategy into products that deliver high-quality experiences. This position requires an ability to think strategically and scale for future growth, as well as execute tactically to meet short-term goals.\n\nYou will be responsible for building and managing scalable and sustainable architecture, organizational strategy, solution designs and serve as a technical and thought leader for SAP platform in the Finance domain including order-to-cash, Record-to-Report and Procure-to-Pay functions.\n\nAs Senior Director you will be responsible for the overall design and maintenance of our SAP platform, including data architecture, feature roadmap, and integrations. You will collaborate with cross-functional teams and lead the development efforts to deliver solutions based on a deep understanding of business requirements. You will play a critical role in defining the application strategy and shaping the future of our Finance applications.\n\nYou will lead a dynamic and geographically distributed team responsible for constantly evolving the systems and processes that support our Finance and Accounting functions. Youll work closely with business leaders, partners, and our governance working group to prioritize, and align resource plans and schedules.\n\nWhat You'll do:\n\u2022 Establish and create the Technology and Systems roadmap (immediate and long term) for Finance Tech\n\u2022 Partner with senior business leaders on their strategic roadmap, understand their operational issues and opportunities(business processes) and create technical solutions to grow business operations and ensure compliance.\n\u2022 Identify and recommend creative solutions to improve business operations, business engagement and project delivery.\n\u2022 Oversee the portfolio of projects, and lead projects to achieve desired goals and benefits in consideration of planned timelines and budgets.\n\u2022 Manage the above applications and the product vendor relationships.\n\u2022 Analyze current state needs and challenges, identify improvement and automation opportunities, portfolio planning and tool rationalization.\n\u2022 Provide leadership and establish a culture that strives towards best practice and solutions excellence. Lead and develop a team with end-to-end responsibilities: engagement, analysis, design, develop, QA, support\n\u2022 Represent Finance processes in technology assessments, solution design, and implementations.\n\u2022 Assist IT/Engineering Org in defining and communicating organizational plans for implementing and operating financial systems.\n\u2022 Work with business stakeholders to prioritize activities based on our needs, focusing on order management, billing, revenue recognition, procurement and general accounting processes.\n\u2022 Develop knowledge of related business and technology capabilities to promote value.\n\u2022 Oversee technical system availability, including managing patching and upgrades, security and DR scenario readiness.\n\u2022 Work with business partners on prioritization and proactively anticipate gaps and overlaps within the Finance portfolio.\n\u2022 Provide optimized solutions based on business needs and technology capabilities\n\u2022 Serve as a solution architect for the projects and provide best practices and strategic platform direction.\n\u2022 Manage Design & Delivery of products/solutions in SAP S4 HANA Finance (RAR, FICA, AP, GL & FA, RAR, BRIM)\n\u2022 Stay abreast of technology trends and industry best practices and influence others to seek best-in-class solutions/technology to resolve business challenges.\n\nWhat you bring:\n\u2022 Bachelor's or Masters degree in Computer Science, Software Engineering, Business Administration or in a related field\n\u2022 15 + years of experience in architecting and designing solutions using SAP Platform\n\u2022 7+ years in a leadership position within an IT organization, with demonstrated experience driving change and improving operations\n\u2022 Proven experience with designing, implementing and supporting critical business processes in Finance and HR Systems, such as Workday, Salesforce/CPQ, Netsuite, Anaplan, Coupa, Xactly; Deep understanding of Robotics Process Automation (RPA) is a plus\n\u2022 Experience with audit/SOX requirements and workflows for a publicly-traded company\n\u2022 Have SAP implementation experiences; Have led multiple Finance transformation initiatives.\n\u2022 Deep understanding of the SAP Finance modules and business process areas Revenue Recognition, FICA, AP, FP&A, General Ledger, Fixed Assets.\n\u2022 Experience partnering and communicating with teams and partners in diverse roles at all levels.\n\u2022 Experience training and developing teams and being an effective coach\n\u2022 Experience managing vendor relationships and ability to partner with them to conduct business and technical discovery\n\u2022 Experience working and presenting proposals to executives in a clear and compelling was\n\nThe US base salary range for this position is $244,000.00 - $366,000.00 + variable compensation + benefits.\n\nActual compensation offered will be based on factors such as the candidates work location, qualifications, skills, experience and/or training. Your recruiter can share more information about the specific salary range for your desired work location during the hiring process.\n\nWe want our employees and their families to thrive. In addition to comprehensive benefits we offer holistic mind, body and lifestyle programs designed for overall well-being. Learn more about ZoomInfo benefits here.\n\n#LI- VC\n\n#LI-Hybrid\n\nAbout us:\n\nZoomInfo (NASDAQ: ZI) is the trusted go-to-market platform for businesses to find, acquire, and grow their customers. It delivers accurate, real-time data, insights, and technology to more than 35,000 companies worldwide. Businesses use ZoomInfo to increase efficiency, consolidate technology stacks, and align their sales and marketing teams all in one platform.\n\nZoomInfo may use a software-based assessment as part of the recruitment process. More information about this tool, including the results of the most recent bias audit, is available here.\n\nZoomInfo is proud to be an Equal Opportunity employer. We are committed to equal employment opportunities for applicants and employees regardless of sex, race, age, color, national origin, sexual orientation, gender identity, marital status, disability status, religion, protected military or veteran status, medical condition, or any other characteristic or status protected by applicable law. At ZoomInfo, we also consider qualified candidates with criminal histories, consistent with legal requirements.", "job_is_remote": false, "job_posted_at_timestamp": 1709871600, "job_posted_at_datetime_utc": "2024-03-08T04:20:00.000Z", "job_city": null, "job_state": null, "job_country": "US", "job_latitude": 37.09024, "job_longitude": -95.71289, "job_benefits": ["health_insurance"], "job_google_link": "https://www.google.com/search?gl=us&hl=en&rciv=jb&q=senior+manager+of+business+development&start=80&ibp=htl;jobs#fpstate=tldetail&htivrt=jobs&htiq=senior+manager+of+business+development&htidocid=VZp1BrPnMg8xsH00AAAAAA%3D%3D", "job_offer_expiration_datetime_utc": null, "job_offer_expiration_timestamp": null, "job_required_experience": {"no_experience_required": false, "required_experience_in_months": 180, "experience_mentioned": true, "experience_preferred": true}, "job_required_skills": null, "job_required_education": {"postgraduate_degree": false, "professional_certification": false, "high_school": false, "associates_degree": false, "bachelors_degree": false, "degree_mentioned": true, "degree_preferred": true, "professional_certification_mentioned": false}, "job_experience_in_place_of_education": false, "job_min_salary": null, "job_max_salary": null, "job_salary_currency": null, "job_salary_period": null, "job_highlights": {"Qualifications": ["Bachelor's or Masters degree in Computer Science, Software Engineering, Business Administration or in a related field", "15 + years of experience in architecting and designing solutions using SAP Platform", "7+ years in a leadership position within an IT organization, with demonstrated experience driving change and improving operations", "Experience with audit/SOX requirements and workflows for a publicly-traded company", "Have SAP implementation experiences; Have led multiple Finance transformation initiatives", "Deep understanding of the SAP Finance modules and business process areas Revenue Recognition, FICA, AP, FP&A, General Ledger, Fixed Assets", "Experience partnering and communicating with teams and partners in diverse roles at all levels", "Experience training and developing teams and being an effective coach", "Experience managing vendor relationships and ability to partner with them to conduct business and technical discovery", "Experience working and presenting proposals to executives in a clear and compelling was"], "Responsibilities": ["In this role, you will serve as a strategic consultative partner to Executive and C-Suite stakeholders to translate business strategy into products that deliver high-quality experiences", "This position requires an ability to think strategically and scale for future growth, as well as execute tactically to meet short-term goals", "You will be responsible for building and managing scalable and sustainable architecture, organizational strategy, solution designs and serve as a technical and thought leader for SAP platform in the Finance domain including order-to-cash, Record-to-Report and Procure-to-Pay functions", "As Senior Director you will be responsible for the overall design and maintenance of our SAP platform, including data architecture, feature roadmap, and integrations", "You will collaborate with cross-functional teams and lead the development efforts to deliver solutions based on a deep understanding of business requirements", "You will play a critical role in defining the application strategy and shaping the future of our Finance applications", "You will lead a dynamic and geographically distributed team responsible for constantly evolving the systems and processes that support our Finance and Accounting functions", "Youll work closely with business leaders, partners, and our governance working group to prioritize, and align resource plans and schedules", "Establish and create the Technology and Systems roadmap (immediate and long term) for Finance Tech", "Partner with senior business leaders on their strategic roadmap, understand their operational issues and opportunities(business processes) and create technical solutions to grow business operations and ensure compliance", "Identify and recommend creative solutions to improve business operations, business engagement and project delivery", "Oversee the portfolio of projects, and lead projects to achieve desired goals and benefits in consideration of planned timelines and budgets", "Manage the above applications and the product vendor relationships", "Analyze current state needs and challenges, identify improvement and automation opportunities, portfolio planning and tool rationalization", "Provide leadership and establish a culture that strives towards best practice and solutions excellence", "Lead and develop a team with end-to-end responsibilities: engagement, analysis, design, develop, QA, support", "Represent Finance processes in technology assessments, solution design, and implementations", "Assist IT/Engineering Org in defining and communicating organizational plans for implementing and operating financial systems", "Work with business stakeholders to prioritize activities based on our needs, focusing on order management, billing, revenue recognition, procurement and general accounting processes", "Develop knowledge of related business and technology capabilities to promote value", "Oversee technical system availability, including managing patching and upgrades, security and DR scenario readiness", "Work with business partners on prioritization and proactively anticipate gaps and overlaps within the Finance portfolio", "Provide optimized solutions based on business needs and technology capabilities", "Serve as a solution architect for the projects and provide best practices and strategic platform direction", "Manage Design & Delivery of products/solutions in SAP S4 HANA Finance (RAR, FICA, AP, GL & FA, RAR, BRIM)", "Stay abreast of technology trends and industry best practices and influence others to seek best-in-class solutions/technology to resolve business challenges"], "Benefits": ["The US base salary range for this position is $244,000.00 - $366,000.00 + variable compensation + benefits", "Actual compensation offered will be based on factors such as the candidates work location, qualifications, skills, experience and/or training", "In addition to comprehensive benefits we offer holistic mind, body and lifestyle programs designed for overall well-being"]}, "job_job_title": "Senior director", "job_posting_language": "en", "job_onet_soc": "11302100", "job_onet_job_zone": "4", "job_naics_code": "511210", "job_naics_name": "Software Publishers"}