{"job_id": "bnyfIiTKDuYmTKsTAAAAAA==", "employer_name": "Milo's Tea Company", "employer_logo": "https://media.licdn.com/dms/image/C4E0BAQHVU2Mxnd84ow/company-logo_200_200/0/1649970867337/milos_tea_company_inc__logo?e=2147483647&v=beta&t=gs6ko_VsRHfHIhpSM6oN6_NM1OzuBI441NxVC6WjXdo", "employer_website": "http://drinkmilos.com", "employer_company_type": null, "job_publisher": "Milo's Tea Company - ICIMS", "job_employment_type": "FULLTIME", "job_title": "Field Sales Manager - Houston", "job_apply_link": "https://careers-drinkmilos.icims.com/jobs/1900/field-sales-manager---houston/job", "job_apply_is_direct": true, "job_apply_quality_score": 0.7598, "apply_options": [{"publisher": "Milo's Tea Company - ICIMS", "apply_link": "https://careers-drinkmilos.icims.com/jobs/1900/field-sales-manager---houston/job", "is_direct": true}, {"publisher": "Adzuna", "apply_link": "https://www.adzuna.com/details/4600616409", "is_direct": false}], "job_description": "Overview\n\nCompany Overview\n\nMilo\u2019s Tea Company is one of the fastest growing beverage companies in the US. Our culture and operations are built on the belief that we can make a difference in the world. That\u2019s why we put People First and strive to continually reduce our environmental impact on the planet. We leverage our world class operations and decades-long distribution partnerships to grow the footprint of our core products and create new, innovative beverage products.\n\u2022 We are the #1 and fastest growing brand in the Refrigerated Tea Category in the nation.\n\u2022 Our core mission is that we put people and the planet first and by doing this, it will be good for our business.\n\u2022 We are committed to unlocking the personal genius of every associate and have a strong focus on growth and learning.\n\u2022 Our Company is women-led and strongly committed to Diversity, Inclusion and Belonging.\n\u2022 We are committed to annual charitable giving by delivering upon our 1% profit pledge.\n\u2022 We are Platinum Certified in Zero Waste Manufacturing; recycling, reducing, and reusing 95% of waste at all facilities.\n\nBeing a part of the Milo\u2019s TEAm, you\u2019ll get to collaborate with a group of passionate and high-performing people, where everyone feels empowered to do their best work and feels good about the work they\u2019re doing.\n\nAnd as a \"People First\" company, Milo\u2019s is committed to the success and well-being of our associates, customers, and fans, no matter their gender, race or creed. Some of the great things offered that reflect our commitment include:\n\u2022 Competitive salary with bonus opportunities for various roles\n\u2022 100% employer paid medical premium for our associates and their families\n\u2022 Free Mental Health, Financial Wellness, and Legal Counseling benefits\n\u2022 401K with a company match\n\u2022 Company paid Life Insurance\n\u2022 Tuition reimbursement assistance\n\u2022 Continuous learning opportunities through various platforms and resources\n\u2022 A robust parental leave program\n\u2022 Care Relief Fund to help Associates in need\n\u2022 Associate Assistance Program\n\u2022 Paid volunteer time\n\nPosition Summary\n\nThe Field Sales Manager builds the Milo\u2019s brand throughout the assigned territory through daily engagement with retailers, Key Decision Makers, and consumers. Improving the retail placement and treatment of our products within current retailers, as well as expanding the brand to new ones. They develop business plans specific to their territories and build internal and external alignment. They implement their strategy with cross-functional teamwork and communication. They partner with retailers to profitably grow sales within the assigned territory.\n\nOwnership\n\u2022 Travel as needed (approximately 50% - 75% overnight) throughout assigned territory to visit existing and prospective customers to grow sales in all channels.\n\u2022 Work closely with immediate supervisor for direction and planning of efforts to drive sales through consumer events and retail sales opportunities. Utilize any opportunity to inform and educate consumers about our products and the Milo\u2019s Difference.\n\u2022 Effectively work with store managers and KDMs to maximize sales opportunities.\n\u2022 Drive sales by assisting customers with proper product rotation, ordering, delivery, and creative merchandising ideas.\n\u2022 Organize in-store sampling of product, confirming sufficient product is in stores before, during and after demo.\n\u2022 Execute events to grow brand awareness and sales as requested or needed; may require overnight stay and weekend work.\n\u2022 Review and analyze key sales and market reports weekly to uncover specific opportunities and develop an action plan to be implemented.\n\u2022 Know and communicate detailed information about products, company, and category to be a category expert.\n\u2022 Uphold and participate in all Corporate Responsibility programming including recycling, social advocacy and MMAD volunteering opportunities.\n\u2022 Invest in and is an example of Milo\u2019s Responsibility commitment which includes environmental, social, and corporate governance components.\n\u2022 Other duties as assigned.\n\nQualifications\n\u2022 All applicants must have either an Associate\u2019s (A.A.) or Bachelor\u2019s (B.A.) degree in Sales/Marketing or equivalent, or minimum of one to three years\u2019 experience in sales and marketing. Equivalent combination of education and experience acceptable.\n\u2022 Experience in Food and Beverage Industry preferred.\n\u2022 Proficiency in Microsoft Office (Outlook, Word, Excel, and Power Point) and a working knowledge of Social media web platforms is required.\n\u2022 Valid Driver's license. Must provide certificates of insurance indicating personal auto liability limits of $50,000 per accident. Must have sufficient driving record to be covered under our company automobile insurance and to comply with Milo\u2019s Vehicle Safety program.\n\nResponsibilities\nDeliver on SMART goals in support of regional objectives by implementing strategic territory plans with focus on consumer and customer Brand awareness while creating Milo\u2019s Moments that drive trial and repeat purchase\u200b", "job_is_remote": false, "job_posted_at_timestamp": 1707465600, "job_posted_at_datetime_utc": "2024-02-09T08:00:00.000Z", "job_city": null, "job_state": null, "job_country": "US", "job_latitude": 37.09024, "job_longitude": -95.71289, "job_benefits": ["health_insurance", "retirement_savings"], "job_google_link": "https://www.google.com/search?gl=us&hl=en&rciv=jb&q=sales+manager&start=20&ibp=htl;jobs#fpstate=tldetail&htivrt=jobs&htiq=sales+manager&htidocid=bnyfIiTKDuYmTKsTAAAAAA%3D%3D", "job_offer_expiration_datetime_utc": "2025-02-09T08:00:00.000Z", "job_offer_expiration_timestamp": 1739088000, "job_required_experience": {"no_experience_required": false, "required_experience_in_months": 36, "experience_mentioned": true, "experience_preferred": true}, "job_required_skills": null, "job_required_education": {"postgraduate_degree": false, "professional_certification": false, "high_school": false, "associates_degree": false, "bachelors_degree": false, "degree_mentioned": true, "degree_preferred": true, "professional_certification_mentioned": true}, "job_experience_in_place_of_education": false, "job_min_salary": null, "job_max_salary": null, "job_salary_currency": null, "job_salary_period": null, "job_highlights": {"Qualifications": ["All applicants must have either an Associate\u2019s (A.A.) or Bachelor\u2019s (B.A.) degree in Sales/Marketing or equivalent, or minimum of one to three years\u2019 experience in sales and marketing", "Equivalent combination of education and experience acceptable", "Proficiency in Microsoft Office (Outlook, Word, Excel, and Power Point) and a working knowledge of Social media web platforms is required", "Valid Driver's license", "Must provide certificates of insurance indicating personal auto liability limits of $50,000 per accident", "Must have sufficient driving record to be covered under our company automobile insurance and to comply with Milo\u2019s Vehicle Safety program"], "Responsibilities": ["The Field Sales Manager builds the Milo\u2019s brand throughout the assigned territory through daily engagement with retailers, Key Decision Makers, and consumers", "Improving the retail placement and treatment of our products within current retailers, as well as expanding the brand to new ones", "They develop business plans specific to their territories and build internal and external alignment", "They implement their strategy with cross-functional teamwork and communication", "They partner with retailers to profitably grow sales within the assigned territory", "Travel as needed (approximately 50% - 75% overnight) throughout assigned territory to visit existing and prospective customers to grow sales in all channels", "Work closely with immediate supervisor for direction and planning of efforts to drive sales through consumer events and retail sales opportunities", "Utilize any opportunity to inform and educate consumers about our products and the Milo\u2019s Difference", "Effectively work with store managers and KDMs to maximize sales opportunities", "Drive sales by assisting customers with proper product rotation, ordering, delivery, and creative merchandising ideas", "Organize in-store sampling of product, confirming sufficient product is in stores before, during and after demo", "Execute events to grow brand awareness and sales as requested or needed; may require overnight stay and weekend work", "Review and analyze key sales and market reports weekly to uncover specific opportunities and develop an action plan to be implemented", "Know and communicate detailed information about products, company, and category to be a category expert", "Uphold and participate in all Corporate Responsibility programming including recycling, social advocacy and MMAD volunteering opportunities", "Invest in and is an example of Milo\u2019s Responsibility commitment which includes environmental, social, and corporate governance components", "Other duties as assigned", "Deliver on SMART goals in support of regional objectives by implementing strategic territory plans with focus on consumer and customer Brand awareness while creating Milo\u2019s Moments that drive trial and repeat purchase\u200b"], "Benefits": ["Competitive salary with bonus opportunities for various roles", "100% employer paid medical premium for our associates and their families", "Free Mental Health, Financial Wellness, and Legal Counseling benefits", "401K with a company match", "Company paid Life Insurance", "Tuition reimbursement assistance", "Continuous learning opportunities through various platforms and resources", "A robust parental leave program", "Care Relief Fund to help Associates in need", "Associate Assistance Program", "Paid volunteer time"]}, "job_job_title": "Sales manager", "job_posting_language": "en", "job_onet_soc": "11202200", "job_onet_job_zone": "4", "job_occupational_categories": ["Sales"]}