{"job_id": "aCZZiyztvdMsYUT-AAAAAA==", "employer_name": "Metals Treatment Technologies, MT2 LLC", "employer_logo": "https://mt2.com/wp-content/uploads/2017/05/newlogo_mt2_95px.jpg", "employer_website": "http://mt2.com", "employer_company_type": null, "job_publisher": "Glassdoor", "job_employment_type": "FULLTIME", "job_title": "Business Development Manager", "job_apply_link": "https://www.glassdoor.com/job-listing/business-development-manager-metals-treatment-technologies-mt2-llc-JV_KO0,28_KE29,66.htm?jl=1009118854512", "job_apply_is_direct": true, "job_apply_quality_score": 0.6664, "apply_options": [{"publisher": "Glassdoor", "apply_link": "https://www.glassdoor.com/job-listing/business-development-manager-metals-treatment-technologies-mt2-llc-JV_KO0,28_KE29,66.htm?jl=1009118854512", "is_direct": true}, {"publisher": "Indeed", "apply_link": "https://www.indeed.com/viewjob?jk=7f9db1abb2c05956", "is_direct": true}, {"publisher": "LazyApply", "apply_link": "https://lazyapply.com/jobpreview/job_7f9db1abb2c05956", "is_direct": true}], "job_description": "POSITION SUMMARY\n\nThe Business Development Manager (BDM) deepens and broadens existing customer and partner relationships, builds new relationships with project gate-keepers, generates new opportunities that fit the company\u2019s capabilities, and identifies opportunities to expand the company\u2019s capabilities and revenue. The role will require development of strategic relationships and opportunities for large-project prospects leading to high-value closed-won deals.\n\nThe role requires prospecting, developing relationships with the principals in those opportunities, and selling the appropriate MT2 services that meet their needs utilizing strategic solutions. Further, this individual is to adhere to the MT2 values and culture while working to achieve this objective.\n\nThe BDM will identify key engineering and consulting firms, as well as state and federal EPA/DEP entities, and introduce them to MT2\u2019s capabilities, leading to strategic opportunities through those organizations for MT2 to pursue. Those relationships will be nurtured and managed to generate future sales leads.\n\nESSENTIAL DUTIES AND RESPONSIBILITIES\n\n\u00b7 Develop strong relationships with leadership, decision makers, and influencers within existing and new customer accounts and within the industry engineers/consultants and regulators.\n\n\u00b7 Ability to communicate Company qualifications and unique capabilities to new customer and project influencer base.\n\n\u00b7 Engage in the entire sales cycle utilizing customer fiscal year opportunities, matching customer needs, and providing strategic solutions by overcoming sales challenges.\n\n\u00b7 Proficiently negotiate and manage complex sales and purchase agreements, from initial prospecting through job/project close.\n\n\u00b7 Lead a team of sales professionals to meet company sales goals.\n\n\u00b7 Maintain all activities and related sales opportunity funnels in the CRM and develop/distribute internal reports.\n\n\u00b7 Effectively partner and cooperate with the Estimating/Proposal team, and Sales team, as well as the Operations team in the completion of proposals and the job/project.\n\n\u00b7 Develop and implement effective plans to achieve order, revenue, and margin projections.\n\n\u00b7 Penetrate target accounts across the United States.\n\n\u00b7 Build customer plans including sales potential, opportunities, contacts, and other information as needed.\n\n\u00b7 Identify MT2 business potential and new business opportunities.\n\n\u00b7 Collaborate with industry contacts to discover customer leads.\n\n\u00b7 Understand customer needs, expectations, wants and demands to provide customer solutions.\n\n\u00b7 Monitor competitive activity and develop plans to countermeasure.\n\n\u00b7 Create and implement strategies to identify and develop target accounts.\n\n\u00b7 Mentor and coach Regional Sales Manager and Inside Sales Manager positions.\n\n\u00b7 Serve as an industry expert on panels, at conferences and in various other content.\n\n\u00b7 Participate in strategic planning sessions and sales forecast development and profit forecasts.\n\n\u00b7 Gather, interpret, and disseminate market data. Implement strategies to recognize new revenue and margin opportunities.\n\n\u00b7 Assist with strategic marketing planning and execution.\n\nQUALIFICATIONS\n\n\u00b7 Bachelor\u2019s degree with focus in Environmental sciences, engineering, or business, or equivalent experience in professional sales.\n\n\u00b7 5 yrs minimum of professional experience in sales or technical consulting of customers.\n\n\u00b7 Work independently with little supervision, but also strong sense of teamwork. Self-starter and a quick learner.\n\n\u00b7 Demonstrated communication and presentation skills and the ability to communicate at a level with customers with decision-making authority.\n\n\u00b7 Experience leading and coaching other sales professionals, including setting goals, developing their skillsets, and managing their work effort.\n\n\u00b7 Experience in environmental sciences field a plus.\n\n\u00b7 Must be able to fluently read, write and speak English. Bilingual is a plus.\n\n\u00b7 Customer focus; results driven; well-organized and able to handle several multi-tasks simultaneously; team building / relationship building; analytical thinking / decision making.\n\n\u00b7 Desired knowledge: Microsoft Office Package (Excel, Word, PowerPoint), Outlook, Teams, CRM.\n\n\u00b7 Extensive travel may be required.\n\nJob Type: Full-time\n\nBenefits:\n\u2022 401(k) matching\n\u2022 Dental insurance\n\u2022 Health insurance\n\u2022 Life insurance\n\u2022 Paid time off\n\u2022 Professional development assistance\n\u2022 Vision insurance\n\nSchedule:\n\u2022 Monday to Friday\n\nSupplemental pay types:\n\u2022 Bonus opportunities\n\nExperience:\n\u2022 Business development: 5 years (Required)\n\u2022 Environmental Services / EPA: 4 years (Required)\n\nWillingness to travel:\n\u2022 50% (Required)\n\nWork Location: Remote", "job_is_remote": true, "job_posted_at_timestamp": 1709942400, "job_posted_at_datetime_utc": "2024-03-09T00:00:00.000Z", "job_city": null, "job_state": null, "job_country": "US", "job_latitude": 37.09024, "job_longitude": -95.71289, "job_benefits": ["paid_time_off", "health_insurance", "retirement_savings", "dental_coverage"], "job_google_link": "https://www.google.com/search?gl=us&hl=en&rciv=jb&q=manager+of+business+development&start=0&ibp=htl;jobs#fpstate=tldetail&htivrt=jobs&htiq=manager+of+business+development&htidocid=aCZZiyztvdMsYUT-AAAAAA%3D%3D", "job_offer_expiration_datetime_utc": "2024-07-10T00:00:00.000Z", "job_offer_expiration_timestamp": 1720569600, "job_required_experience": {"no_experience_required": false, "required_experience_in_months": 60, "experience_mentioned": true, "experience_preferred": true}, "job_required_skills": null, "job_required_education": {"postgraduate_degree": false, "professional_certification": false, "high_school": false, "associates_degree": false, "bachelors_degree": false, "degree_mentioned": true, "degree_preferred": false, "professional_certification_mentioned": false}, "job_experience_in_place_of_education": false, "job_min_salary": null, "job_max_salary": null, "job_salary_currency": null, "job_salary_period": null, "job_highlights": {"Qualifications": ["Bachelor\u2019s degree with focus in Environmental sciences, engineering, or business, or equivalent experience in professional sales", "5 yrs minimum of professional experience in sales or technical consulting of customers", "Work independently with little supervision, but also strong sense of teamwork", "Self-starter and a quick learner", "Demonstrated communication and presentation skills and the ability to communicate at a level with customers with decision-making authority", "Experience leading and coaching other sales professionals, including setting goals, developing their skillsets, and managing their work effort", "Must be able to fluently read, write and speak English", "Customer focus; results driven; well-organized and able to handle several multi-tasks simultaneously; team building / relationship building; analytical thinking / decision making", "Extensive travel may be required", "Business development: 5 years (Required)", "Environmental Services / EPA: 4 years (Required)", "50% (Required)"], "Responsibilities": ["The Business Development Manager (BDM) deepens and broadens existing customer and partner relationships, builds new relationships with project gate-keepers, generates new opportunities that fit the company\u2019s capabilities, and identifies opportunities to expand the company\u2019s capabilities and revenue", "The role will require development of strategic relationships and opportunities for large-project prospects leading to high-value closed-won deals", "The role requires prospecting, developing relationships with the principals in those opportunities, and selling the appropriate MT2 services that meet their needs utilizing strategic solutions", "Further, this individual is to adhere to the MT2 values and culture while working to achieve this objective", "The BDM will identify key engineering and consulting firms, as well as state and federal EPA/DEP entities, and introduce them to MT2\u2019s capabilities, leading to strategic opportunities through those organizations for MT2 to pursue", "Those relationships will be nurtured and managed to generate future sales leads", "Develop strong relationships with leadership, decision makers, and influencers within existing and new customer accounts and within the industry engineers/consultants and regulators", "Ability to communicate Company qualifications and unique capabilities to new customer and project influencer base", "Engage in the entire sales cycle utilizing customer fiscal year opportunities, matching customer needs, and providing strategic solutions by overcoming sales challenges", "Proficiently negotiate and manage complex sales and purchase agreements, from initial prospecting through job/project close", "Lead a team of sales professionals to meet company sales goals", "Maintain all activities and related sales opportunity funnels in the CRM and develop/distribute internal reports", "Effectively partner and cooperate with the Estimating/Proposal team, and Sales team, as well as the Operations team in the completion of proposals and the job/project", "Develop and implement effective plans to achieve order, revenue, and margin projections", "Penetrate target accounts across the United States", "Build customer plans including sales potential, opportunities, contacts, and other information as needed", "Identify MT2 business potential and new business opportunities", "Collaborate with industry contacts to discover customer leads", "Understand customer needs, expectations, wants and demands to provide customer solutions", "Monitor competitive activity and develop plans to countermeasure", "Create and implement strategies to identify and develop target accounts", "Mentor and coach Regional Sales Manager and Inside Sales Manager positions", "Serve as an industry expert on panels, at conferences and in various other content", "Participate in strategic planning sessions and sales forecast development and profit forecasts", "Gather, interpret, and disseminate market data", "Implement strategies to recognize new revenue and margin opportunities", "Assist with strategic marketing planning and execution"], "Benefits": ["401(k) matching", "Dental insurance", "Health insurance", "Life insurance", "Paid time off", "Professional development assistance", "Vision insurance", "Monday to Friday", "Bonus opportunities"]}, "job_job_title": "Development manager", "job_posting_language": "en", "job_onet_soc": "11202100", "job_onet_job_zone": "4"}