{"job_id": "20JKT8y6SdeQ9kU_AAAAAA==", "employer_name": "aiacareers", "employer_logo": null, "employer_website": null, "employer_company_type": null, "job_publisher": "Salary.com", "job_employment_type": "FULLTIME", "job_title": "Director, Event & Sponsorship Marketing", "job_apply_link": "https://www.salary.com/job/aiacareers/director-event-sponsorship-marketing/j202311200048500565819", "job_apply_is_direct": false, "job_apply_quality_score": 0.6257, "apply_options": [{"publisher": "Salary.com", "apply_link": "https://www.salary.com/job/aiacareers/director-event-sponsorship-marketing/j202311200048500565819", "is_direct": false}, {"publisher": "LifeworQ", "apply_link": "https://lifeworq.com/job/82d7836f-8586-4643-bac9-c02ed2ec82be", "is_direct": false}, {"publisher": "Tarta.ai", "apply_link": "https://jobs.tarta.ai/j/S6dZLo0BcRajQcTjPY1N0124-director-event-sponsorship-marketing-in-washington-dc-at-the-american-institute-of-architects", "is_direct": false}], "job_description": "Shift Type\n\nDate Needed By\n\nSalary Grade\n\nCategory\n\nMarketing & Digital Strategy\n\nCareer Level\n\nDirector\n\nLocation\n\nAmerican Institute of Architects - Washington, DC 20006 US (Primary)\n\nEducation\n\nBachelor's Degree\n\nJob Title\n\nDirector, Event & Sponsorship Marketing\n\nJob Type\n\nFull-time\n\nTravel\n\nJob Requirements\n\nQualifications\n\u2022 Experience developing campaigns that drive sponsorships.\n\u2022 Experience with MarTech tools and platforms, including but not limited to, Google Analytics, CRM (Salesforce), CMS (Wordpress/Drupal), Marketing Automation (Marketing Cloud), Social Media and SEO tools.\n\u2022 Strong persuasive copywriting experience with command of grammar and style.\n\u2022 Understanding of Marketing best practices including value proposition creation, calls to action, pricing and promotion strategies, and conversion rate optimization.\n\u2022 Strong judgment and proven ability to assimilate complex organizational, political, and cultural issues into high-quality, multimedia marketing strategies, storytelling, and tactics.\n\u2022 Ability to navigate and successfully develop relationships in a matrixed organization.\n\u2022 Must have a proven track record in developing successful, multifaceted strategic event and sponsorship marketing campaigns that have increased attendance, revenue and customer engagement.\n\u2022 Experience in strategic planning and budgeting to meet revenue and expense targets.\n\u2022 Strong aptitude for staying abreast of external trends and new developments in event and sponsorship marketing, customer experience, and the digital landscape.\n\u2022 Demonstrated project management skills and be a highly motivated self-starter able to work in an extremely fast-paced team environment, manage multiple projects simultaneously, and meet deadlines.\n\u2022 Demonstrated effectiveness through interpersonal, presentation, written, and oral communications.\n\u2022 Effective time management skills and the ability to multitask.\n\u2022 Strong attention to detail while understanding the bigger picture.\n\u2022 Ability to effectively communicate and present to senior colleagues.\n\u2022 Ability to take constructive feedback and consistently improve.\n\nCollege degree in Marketing, Business, or a related discipline with 8 or more years of experience in an Event Marketing role with progressive responsibilities.\n\nSupervisory Requirements\n\nIndividual contributor.\n\nWhat we offer\n\nWe offer a comprehensive benefits package that reflects our company values and workplace culture, including:\n\u2022 Medical and dental\n\u2022 401(k)\n\u2022 Flexibility\n\u2022 Paid time off\n\u2022 Flexible spending accounts\n\u2022 Income protection- (Life Insurance Coverage up to 2x salary) & disability plans at no cost.\n\u2022 Tuition and membership reimbursements\n\u2022 AIA employees have access to a variety of other programs, including:\n\u2022 Employee Assistance Program (EAP) for employees and their family members\n\u2022 Computer purchase program\n\u2022 Fitness club discounts\n\u2022 Prepaid legal services program\n\u2022 Identity theft protection\n\nTravel Requirements: N/A\n\nWork Location: Washington, DC. All AIA employees in the DC metro area are currently working remotely during our office renovation. Employees in the DC Metro area will have the option to return to the newly renovated office at the completion of the renovation in Spring 2025.\n\nAn Equal Opportunity Employer. All qualified applicants will receive consideration for employment without regard to race, color, religion, age sex, sexual orientation, gender identity, national origin, or protected veteran status and will not be discriminated against on the basis of disability, in accordance with the applicable law.\n\nHiring Manager\n\nExemption Type\n\nExempt\n\n# of Hires Needed\n\n1\n\nJob Description\n\nThe American Institute of Architects (AIA)\n\nAIA will provide you with the opportunity to advocate for the value of architecture and give architects and design professionals the resources they need to do their best work. The collective voice of architects is essential and our work drives positive change through the power of design.\n\nEach one of us at AIA is a leader committed to demonstrating our mission and values and designing a better future for our country and planet. Even in times of change, AIA\u2019s values remain constant:\n\u2022 We stand for equity and human rights\n\u2022 We stand for architecture that strengthens our communities\n\u2022 We stand for a sustainable future\n\u2022 We stand for protecting communities from the impacts of climate change\n\u2022 We stand for economic opportunity\n\u2022 We stand for investing in the future\n\u2022 We speak up, and policymakers listen\n\nThe American Institute of Architects, as part of the global community, is building a culture of equity, diversity, and inclusion within the profession of architecture to create a better built environment for all. Achieving this vision has a direct impact on the relevance of the profession of architecture and the world's prosperity, health, and future.\n\nJob Summary\n\nReporting to the Managing Director, Marketing & Digital Strategy. The Director, Event & Sponsorship Marketing will be responsible for the creation and execution of marketing plans, strategies, and tactics that drive revenue, attendance, and audience engagement for large-scale signature events and tradeshows, and compelling marketing packages that grow sponsorships, collaborating closely with Events, Sales and other teams across the organization.\n\nThe Director, Event & Sponsorship Marketing will collaborate with their broader MarCom team members (Brand, Digital, Media and Communications), including the Director of Marketing and Director of Digital Marketing, to create compelling value propositions that support high-profile, professional events within the architecture, design, and allied AEC industries. This role will collaborate directly with Sales to close and fulfill high-value sponsorship packages for top brands that provide products and services that support the industries within the built environment. The Director, Event & Sponsorship Marketing will work closely with the Managing Director, Brand & Operations to ensure strong project management, goal setting, and performance management for Events portfolios.\n\nResponsibilities Include:\n\u2022 Lead the ideation, development, planning, and execution of marketing campaigns through execution from start to finish that grow event attendance, achieve revenue targets, and strengthen audience engagement across multiple channels and platforms for an omnichannel customer experience.\n\u2022 Expand the annual Conference on Architecture and Expo, which attracts 15,000 attendees and hundreds of exhibitors per year, to attract new attendees and exhibitors in the broader AEC industries.\n\u2022 Grow registrations for the Women\u2019s Leadership Summit, the largest gathering of women in the architecture & design and broader AEC industries.\n\u2022 Serve as primary point of contact on events marketing, constantly assessing the events landscape, bringing fresh ideas and best practices, and applying them to building innovative and achievable event marketing campaigns aligned with target audiences.\n\u2022 Provide guidance and recommendations on themes, content, keynotes, panels, and experiences that will attract target audience segments, working in collaboration with the Communications and Events teams.\n\u2022 Develop event personas and expand our audience scope to align messaging, value propositions, CTAs, and customer journeys to attract new audience segments and convert them to event loyalists.\n\u2022 Design pricing and promotional packages for different audience segments that achieve revenue goals while engaging and expanding target audiences.\n\u2022 Customer-obsessed and data-informed, continuously analyze event marketing campaign performance and consistently set benchmarks and strengthen ROI. Communicate findings and recommendations to Event and MarCom colleagues and cross-departmental stakeholders.\n\u2022 In collaboration with Event team, ensure on-point brand experiences at in-person and virtual events that heighten the profile of the organization and support its mission.\n\u2022 Collaborate with Digital and Media and Communication teams to develop compelling marketing funnels with a focus on lead generation and conversions.\n\u2022 Conduct customer and competitor analysis, ensuring events are positioned competitively in the marketplace\u2015including brand, messaging, and pricing\u2015and aligned with target audiences.\n\u2022 Perform strong project management, setting clear timelines with Events, MarCom Operations, Marketing colleagues, and cross-departmental teams to ensure on-time delivery of campaigns and launches.\n\u2022 Collaborate directly with Sales teams to identify prospective sponsorship opportunities and create marketing packages that attract and convert target brands into paid sponsors.\n\u2022 Work directly with Marketing and Communications leadership to support the annual MarCom plan and provide recommendations for strategies and tactics that will achieve organizational goals.\n\u2022 Work directly with Events, Membership, and Knowledge teams to build an annual events calendar that supports the organizational goals and marketing and sales cycles.\n\u2022 Own event marketing agency relationships and vendors engaged in support of event marketing goals and activities.\n\u2022 Model and foster behavior that establishes a culture of belonging consistent with the values, goals, and objectives of the organization to create an atmosphere of trust, cooperation, accountability, empowerment, and dedication to the mission.\n\u2022 Ensure that event and sponsorship marketing strategies reflect the diversity of the communities served by the organization within a strategic lens of equity, diversity & inclusion, and sustainability.\n\nFrequent Contacts:\n\u2022 AIA Marketing & Communications Department\n\u2022 Sales, Events & Exhibitions Department\n\u2022 Knowledge & Practice Department\n\nWage Amount\n\n$94,400.00-$121,800.00", "job_is_remote": false, "job_posted_at_timestamp": 1709251200, "job_posted_at_datetime_utc": "2024-03-01T00:00:00.000Z", "job_city": "Washington", "job_state": "DC", "job_country": "US", "job_latitude": 38.907192, "job_longitude": -77.03687, "job_benefits": ["dental_coverage", "paid_time_off", "health_insurance", "retirement_savings"], "job_google_link": "https://www.google.com/search?gl=us&hl=en&rciv=jb&q=sponsorship+sales+director&start=20&ibp=htl;jobs#fpstate=tldetail&htivrt=jobs&htiq=sponsorship+sales+director&htidocid=20JKT8y6SdeQ9kU_AAAAAA%3D%3D", "job_offer_expiration_datetime_utc": "2024-03-27T00:00:00.000Z", "job_offer_expiration_timestamp": 1711497600, "job_required_experience": {"no_experience_required": false, "required_experience_in_months": 96, "experience_mentioned": true, "experience_preferred": false}, "job_required_skills": null, "job_required_education": {"postgraduate_degree": false, "professional_certification": false, "high_school": false, "associates_degree": false, "bachelors_degree": false, "degree_mentioned": true, "degree_preferred": true, "professional_certification_mentioned": false}, "job_experience_in_place_of_education": false, "job_min_salary": null, "job_max_salary": null, "job_salary_currency": null, "job_salary_period": null, "job_highlights": {"Qualifications": ["Experience developing campaigns that drive sponsorships", "Experience with MarTech tools and platforms, including but not limited to, Google Analytics, CRM (Salesforce), CMS (Wordpress/Drupal), Marketing Automation (Marketing Cloud), Social Media and SEO tools", "Strong persuasive copywriting experience with command of grammar and style", "Understanding of Marketing best practices including value proposition creation, calls to action, pricing and promotion strategies, and conversion rate optimization", "Strong judgment and proven ability to assimilate complex organizational, political, and cultural issues into high-quality, multimedia marketing strategies, storytelling, and tactics", "Ability to navigate and successfully develop relationships in a matrixed organization", "Must have a proven track record in developing successful, multifaceted strategic event and sponsorship marketing campaigns that have increased attendance, revenue and customer engagement", "Experience in strategic planning and budgeting to meet revenue and expense targets", "Strong aptitude for staying abreast of external trends and new developments in event and sponsorship marketing, customer experience, and the digital landscape", "Demonstrated project management skills and be a highly motivated self-starter able to work in an extremely fast-paced team environment, manage multiple projects simultaneously, and meet deadlines", "Demonstrated effectiveness through interpersonal, presentation, written, and oral communications", "Effective time management skills and the ability to multitask", "Strong attention to detail while understanding the bigger picture", "Ability to effectively communicate and present to senior colleagues", "Ability to take constructive feedback and consistently improve", "College degree in Marketing, Business, or a related discipline with 8 or more years of experience in an Event Marketing role with progressive responsibilities"], "Responsibilities": ["Reporting to the Managing Director, Marketing & Digital Strategy", "The Director, Event & Sponsorship Marketing will be responsible for the creation and execution of marketing plans, strategies, and tactics that drive revenue, attendance, and audience engagement for large-scale signature events and tradeshows, and compelling marketing packages that grow sponsorships, collaborating closely with Events, Sales and other teams across the organization", "The Director, Event & Sponsorship Marketing will collaborate with their broader MarCom team members (Brand, Digital, Media and Communications), including the Director of Marketing and Director of Digital Marketing, to create compelling value propositions that support high-profile, professional events within the architecture, design, and allied AEC industries", "This role will collaborate directly with Sales to close and fulfill high-value sponsorship packages for top brands that provide products and services that support the industries within the built environment", "The Director, Event & Sponsorship Marketing will work closely with the Managing Director, Brand & Operations to ensure strong project management, goal setting, and performance management for Events portfolios", "Lead the ideation, development, planning, and execution of marketing campaigns through execution from start to finish that grow event attendance, achieve revenue targets, and strengthen audience engagement across multiple channels and platforms for an omnichannel customer experience", "Expand the annual Conference on Architecture and Expo, which attracts 15,000 attendees and hundreds of exhibitors per year, to attract new attendees and exhibitors in the broader AEC industries", "Grow registrations for the Women\u2019s Leadership Summit, the largest gathering of women in the architecture & design and broader AEC industries", "Serve as primary point of contact on events marketing, constantly assessing the events landscape, bringing fresh ideas and best practices, and applying them to building innovative and achievable event marketing campaigns aligned with target audiences", "Provide guidance and recommendations on themes, content, keynotes, panels, and experiences that will attract target audience segments, working in collaboration with the Communications and Events teams", "Develop event personas and expand our audience scope to align messaging, value propositions, CTAs, and customer journeys to attract new audience segments and convert them to event loyalists", "Design pricing and promotional packages for different audience segments that achieve revenue goals while engaging and expanding target audiences", "Customer-obsessed and data-informed, continuously analyze event marketing campaign performance and consistently set benchmarks and strengthen ROI", "Communicate findings and recommendations to Event and MarCom colleagues and cross-departmental stakeholders", "In collaboration with Event team, ensure on-point brand experiences at in-person and virtual events that heighten the profile of the organization and support its mission", "Collaborate with Digital and Media and Communication teams to develop compelling marketing funnels with a focus on lead generation and conversions", "Conduct customer and competitor analysis, ensuring events are positioned competitively in the marketplace\u2015including brand, messaging, and pricing\u2015and aligned with target audiences", "Perform strong project management, setting clear timelines with Events, MarCom Operations, Marketing colleagues, and cross-departmental teams to ensure on-time delivery of campaigns and launches", "Collaborate directly with Sales teams to identify prospective sponsorship opportunities and create marketing packages that attract and convert target brands into paid sponsors", "Work directly with Marketing and Communications leadership to support the annual MarCom plan and provide recommendations for strategies and tactics that will achieve organizational goals", "Work directly with Events, Membership, and Knowledge teams to build an annual events calendar that supports the organizational goals and marketing and sales cycles", "Own event marketing agency relationships and vendors engaged in support of event marketing goals and activities", "Model and foster behavior that establishes a culture of belonging consistent with the values, goals, and objectives of the organization to create an atmosphere of trust, cooperation, accountability, empowerment, and dedication to the mission", "Ensure that event and sponsorship marketing strategies reflect the diversity of the communities served by the organization within a strategic lens of equity, diversity & inclusion, and sustainability"], "Benefits": ["We offer a comprehensive benefits package that reflects our company values and workplace culture, including:", "Medical and dental", "401(k)", "Paid time off", "Flexible spending accounts", "Income protection- (Life Insurance Coverage up to 2x salary) & disability plans at no cost", "Tuition and membership reimbursements", "AIA employees have access to a variety of other programs, including:", "Employee Assistance Program (EAP) for employees and their family members", "Computer purchase program", "Fitness club discounts", "Prepaid legal services program", "Identity theft protection", "$94,400.00-$121,800.00"]}, "job_job_title": "Director", "job_posting_language": "en", "job_onet_soc": "13112100", "job_onet_job_zone": "4"}