{"job_id": "m8KPjyQYcftZ5dOzAAAAAA==", "employer_name": "Stanford Health Care", "employer_logo": null, "employer_website": null, "employer_company_type": null, "job_publisher": "JobServe", "job_employment_type": "FULLTIME", "job_title": "MLOps Engineer", "job_apply_link": "https://www.jobserve.com/us/en/extjob/MLOPS-ENGINEER-in-Palo-Alto-California-USA-BB139932C461E93F8C/", "job_apply_is_direct": false, "job_apply_quality_score": 0.5586, "apply_options": [{"publisher": "JobServe", "apply_link": "https://www.jobserve.com/us/en/extjob/MLOPS-ENGINEER-in-Palo-Alto-California-USA-BB139932C461E93F8C/", "is_direct": false}, {"publisher": "LifeworQ", "apply_link": "https://lifeworq.com/job/bdcf6b60-86cd-490d-b36d-a223d10d1349", "is_direct": false}, {"publisher": "Lensa", "apply_link": "https://lensa.com/mlops-engineer-jobs/palo-alto/jd/30d3ac7f8398523d651347db0beb2292", "is_direct": false}], "job_description": "If you're ready to be part of our legacy of hope and innovation, we encourage you to take the first step and explore our current job openings. Your best is waiting to be discovered.\n\nDay - 08 Hour (United States of America)\n\nWe are seeking a versatile DevOps Engineer with a strong foundation in full stack development to join our dynamic team. In addition to your expert-level DevOps skills, we are excited to see candidates who have hands-on experience in full stack development. As a DevOps Engineer at Stanford Healthcare, you'll play a crucial role in bridging the gap between development and operations, ensuring seamless integration, deployment, and automation of our systems. Your proficiency in both areas will empower you to architect solutions that not only optimize our infrastructure but also enhance the end-to-end development lifecycle. If you possess a deep understanding of coding, architecture, and deployment processes, coupled with your proven DevOps expertise, we encourage you to bring your unique perspective and skill set to our team. Your ability to collaborate, adapt, and innovate will contribute to the growth and success of both our DevOps practices and our broader development initiatives.\n\nThis is a Stanford Health Care job.\n\nA Brief Overview\n\nThe MLOPs Engineer will play an integral role incorporating Artificial Intelligence (AI) within Stanford Health Care. The solutions will impact patient care, medical research, and operational services. This group is tasked to innovate, build, deploy and monitor production grade AI, machine learning (ML) and predictive algorithms into healthcare. The role will partner closely with lead researchers within the AI field and leaders across various clinical specialties and operations.\n\nThis role will report to the Infrastructure group and have a dotted line relationship to the Data Science team. The role will be responsible for maintaining cloud-based infrastructure as code repositories, maintaining infrastructure, deployment pipelines and designing the security landscape for the team and objects. The role will set the standards for the full SDLC of projects for the Data Science team.\n\nLocations\n\nStanford Health Care\n\nWhat you will do\n\u2022 Design, build and maintain scalable and robust infrastructure for AI/ML systems, including cloud-based environments, containerization and orchestration platforms.\n\u2022 Develop and implement CI/CD pipelines to automate the deployment, testing and monitoring of AI/ML models and applications.\n\u2022 Collaborate with data scientists, data engineers and software engineers to optimize model training, deployment and inference pipelines.\n\u2022 Monitor and troubleshoot AI/ML systems to ensure high availability, performance and reliability.\n\u2022 Maintain and monitor model training and inference pipelines across multi-cloud tenants especially around Large Language Models (LLMs).\n\u2022 Maintain Kubernetes pods, container registry and virtual machine image library and model registry\n\u2022 Monitor infrastructure utilization and costs pertaining to model training, inference and GPU utilization\n\u2022 Implement best practices for security, data privacy and compliance in AI/ML workflows and infrastructure.\n\u2022 Evaluate and integrate new tools, technologies and frameworks to improve the efficiency and effectiveness of our MLOps processes.\n\u2022 Mentor and provide technical guidance to junior members of the organization.\n\u2022 Stay up-to-date with the latest advancements and trends in MLOps, DevOps and cloud technologies and share them with the team.\n\nEducation Qualifications\n\u2022 Bachelor's or higher degree in Computer Science, Engineering or a related field\n\nExperience Qualifications\n\u2022 Three (3) or more years of directly related experience\n\nRequired Knowledge, Skills and Abilities\n\u2022 Proven experience as an MLOps Engineer.\n\u2022 Strong knowledge of cloud platforms such as AWS, Azure or Google Cloud and experience with infrastructure-as-code tools like Terraform or CloudFormation.\n\u2022 Proficiency in containerization technologies such as Docker and container orchestration platforms like Kubernetes.\n\u2022 Experience with CI/CD tools such as GitLab CI/CD, Github Actions or CiricleCI.\n\u2022 Solid programming skills in languages such as Python, Rust or Go and experience in scripting and automation.\n\u2022 Familiarity with machine learning frameworks and libraries such as PyTorch, Tensorflow and scikit-learn.\n\u2022 Deep understanding of DevOps principles, agile methodologies and software development lifecycle.\n\u2022 Strong problem-solving and trouble shooting skills, with the ability to analyze and resolve complex technical issues.\n\u2022 Excellent communication and collaboration skills with the ability to work effectively in cross-functional teams.\n\nPhysical Demands and Work Conditions\n\nBlood Borne Pathogens\n\u2022 Category III - Tasks that involve NO exposure to blood, body fluids or tissues, and Category I tasks that are not a condition of employment\n\nThese principles apply to ALL employees:\n\nSHC Commitment to Providing an Exceptional Patient & Family Experience\n\nStanford Health Care sets a high standard for delivering value and an exceptional experience for our patients and families. Candidates for employment and existing employees must adopt and execute C-I-CARE standards for all of patients, families and towards each other. C-I-CARE is the foundation of Stanford's patient-experience and represents a framework for patient-centered interactions. Simply put, we do what it takes to enable and empower patients and families to focus on health, healing and recovery.\n\nYou will do this by executing against our three experience pillars, from the patient and family's perspective:\n\u2022 Know Me: Anticipate my needs and status to deliver effective care\n\u2022 Show Me the Way: Guide and prompt my actions to arrive at better outcomes and better health\n\u2022 Coordinate for Me: Own the complexity of my care through coordination\n\nEqual Opportunity Employer Stanford Health Care (SHC) strongly values diversity and is committed to equal opportunity and non-discrimination in all of its policies and practices, including the area of employment. Accordingly, SHC does not discriminate against any person on the basis of race, color, sex, sexual orientation or gender identity and/or expression, religion, age, national or ethnic origin, political beliefs, marital status, medical condition, genetic information, veteran status, or disability, or the perception of any of the above. People of all genders, members of all racial and ethnic groups, people with disabilities, and veterans are encouraged to apply. Qualified applicants with criminal convictions will be considered after an individualized assessment of the conviction and the job requirements.\n\nBase Pay Scale: Generally starting at $74.66 - $98.94 per hour\n\nThe salary of the finalist selected for this role will be set based on a variety of factors, including but not limited to, internal equity, experience, education, specialty and training. This pay scale is not a promise of a particular wage.\n\nAt Stanford Health Care, we seek to provide patients with the very best in diagnosis and treatment, with outstanding quality, compassion and coordination. With an unmatched track record of scientific discovery, technological innovation and translational medicine, Stanford Medicine physicians are pioneering leading edge therapies today that will change the way health care is delivered tomorrow.\n\nAs part of our spirit of discovery, we also leverage our deep relationships with luminary Silicon Valley companies to develop new ways to deliver preeminent patient care.\n\nLearn about our awards (https://stanfordhealthcare.org/about-us/awards.html) and significant events (https://stanfordhealthcare.org/about-us/our-history.html) .", "job_is_remote": false, "job_posted_at_timestamp": 1710040380, "job_posted_at_datetime_utc": "2024-03-10T03:13:00.000Z", "job_city": "Palo Alto", "job_state": "CA", "job_country": "US", "job_latitude": 37.441883, "job_longitude": -122.14302, "job_benefits": null, "job_google_link": "https://www.google.com/search?gl=us&hl=en&rciv=jb&q=mlops+expert&start=10&ibp=htl;jobs#fpstate=tldetail&htivrt=jobs&htiq=mlops+expert&htidocid=m8KPjyQYcftZ5dOzAAAAAA%3D%3D", "job_offer_expiration_datetime_utc": "2024-04-09T03:13:00.000Z", "job_offer_expiration_timestamp": 1712632380, "job_required_experience": {"no_experience_required": false, "required_experience_in_months": 36, "experience_mentioned": true, "experience_preferred": false}, "job_required_skills": null, "job_required_education": {"postgraduate_degree": false, "professional_certification": false, "high_school": false, "associates_degree": false, "bachelors_degree": false, "degree_mentioned": true, "degree_preferred": true, "professional_certification_mentioned": false}, "job_experience_in_place_of_education": false, "job_min_salary": 74, "job_max_salary": 98, "job_salary_currency": "USD", "job_salary_period": "HOUR", "job_highlights": {"Qualifications": ["Bachelor's or higher degree in Computer Science, Engineering or a related field", "Three (3) or more years of directly related experience", "Required Knowledge, Skills and Abilities", "Proven experience as an MLOps Engineer", "Strong knowledge of cloud platforms such as AWS, Azure or Google Cloud and experience with infrastructure-as-code tools like Terraform or CloudFormation", "Proficiency in containerization technologies such as Docker and container orchestration platforms like Kubernetes", "Experience with CI/CD tools such as GitLab CI/CD, Github Actions or CiricleCI", "Solid programming skills in languages such as Python, Rust or Go and experience in scripting and automation", "Familiarity with machine learning frameworks and libraries such as PyTorch, Tensorflow and scikit-learn", "Deep understanding of DevOps principles, agile methodologies and software development lifecycle", "Strong problem-solving and trouble shooting skills, with the ability to analyze and resolve complex technical issues", "Excellent communication and collaboration skills with the ability to work effectively in cross-functional teams"], "Responsibilities": ["The solutions will impact patient care, medical research, and operational services", "This group is tasked to innovate, build, deploy and monitor production grade AI, machine learning (ML) and predictive algorithms into healthcare", "The role will partner closely with lead researchers within the AI field and leaders across various clinical specialties and operations", "This role will report to the Infrastructure group and have a dotted line relationship to the Data Science team", "The role will be responsible for maintaining cloud-based infrastructure as code repositories, maintaining infrastructure, deployment pipelines and designing the security landscape for the team and objects", "The role will set the standards for the full SDLC of projects for the Data Science team", "Design, build and maintain scalable and robust infrastructure for AI/ML systems, including cloud-based environments, containerization and orchestration platforms", "Develop and implement CI/CD pipelines to automate the deployment, testing and monitoring of AI/ML models and applications", "Collaborate with data scientists, data engineers and software engineers to optimize model training, deployment and inference pipelines", "Monitor and troubleshoot AI/ML systems to ensure high availability, performance and reliability", "Maintain and monitor model training and inference pipelines across multi-cloud tenants especially around Large Language Models (LLMs)", "Maintain Kubernetes pods, container registry and virtual machine image library and model registry", "Monitor infrastructure utilization and costs pertaining to model training, inference and GPU utilization", "Implement best practices for security, data privacy and compliance in AI/ML workflows and infrastructure", "Evaluate and integrate new tools, technologies and frameworks to improve the efficiency and effectiveness of our MLOps processes", "Mentor and provide technical guidance to junior members of the organization", "Stay up-to-date with the latest advancements and trends in MLOps, DevOps and cloud technologies and share them with the team", "Category III - Tasks that involve NO exposure to blood, body fluids or tissues, and Category I tasks that are not a condition of employment", "You will do this by executing against our three experience pillars, from the patient and family's perspective:", "Know Me: Anticipate my needs and status to deliver effective care", "Show Me the Way: Guide and prompt my actions to arrive at better outcomes and better health", "Coordinate for Me: Own the complexity of my care through coordination"], "Benefits": ["Base Pay Scale: Generally starting at $74.66 - $98.94 per hour", "The salary of the finalist selected for this role will be set based on a variety of factors, including but not limited to, internal equity, experience, education, specialty and training"]}, "job_job_title": "Engineer", "job_posting_language": "en", "job_onet_soc": "15111100", "job_onet_job_zone": "5"}