{"job_id": "Ku3bcDB2xfXzakW2AAAAAA==", "employer_name": "Kraken", "employer_logo": "https://assets.kraken.com/marketing/static/kraken-logo.jpg", "employer_website": null, "employer_company_type": "Finance", "job_publisher": "LazyApply", "job_employment_type": "FULLTIME", "job_title": "Brand Partnerships Manager", "job_apply_link": "https://lazyapply.com/jobpreview/job_6d213af787081b0e", "job_apply_is_direct": false, "job_apply_quality_score": 0.5098, "apply_options": [{"publisher": "LazyApply", "apply_link": "https://lazyapply.com/jobpreview/job_6d213af787081b0e", "is_direct": false}, {"publisher": "Recruit.net", "apply_link": "https://www.recruit.net/job/manager-jobs/91076BD084E08BC3", "is_direct": false}], "job_description": "Location\n\nUnited States\n\nType\n\nFull time\n\nDepartment\n\nMarketing\n\nCompensation\n\n$117K \u2013 $176K \u2022 Offers Equity \u2022 Offers Bonus\n\nThis is the target annual salary range for this role. This range is not inclusive of other additional compensation elements, such as our Bonus program, Equity program, Wellness allowance, and other benefits [US Only] (including medical, dental, vision and 401(k)).\n\nThe compensation range provided is influenced by various factors and represents the initial target range. Our salary offerings are dynamic and we strive to ensure that our base salary and total compensation package aligns and recognizes the top talent we aim to attract and retain. The compensation package of the successful candidate is based on various factors such as their skillset, experience, and job scope.\n\nBuilding the Future of Crypto\n\nOur Krakenites are a world-class team with crypto conviction, united by our desire to discover and unlock the potential of crypto and blockchain technology.\n\nWhat makes us different?\nKraken is a mission-focused company rooted in crypto values. As a Krakenite, you\u2019ll join us on our mission to accelerate the global adoption of crypto, so that everyone can achieve financial freedom and inclusion. For over a decade, Kraken\u2019s focus on our mission and crypto ethos has attracted many of the most talented crypto experts in the world.\n\nBefore you apply, please read the Kraken Culture page to learn more about our internal culture, values, and mission.\n\nAs a fully remote company, we have Krakenites in 60+ countries who speak over 50 languages. Krakenites are industry pioneers who develop premium crypto products for experienced traders, institutions, and newcomers to the space. Kraken is committed to industry-leading security, crypto education, and world-class client support through our products like Kraken Pro, Kraken NFT, and Kraken Futures.\n\nBecome a Krakenite and build the future of crypto!\nThe Team\nKraken is looking for a Brand Partnerships Manager to join the Marketing team. Reporting to the Head of Brand Partnerships, you will manage the relationships with our global brand partners, including producing and participating in partnership strategy development, leading partnership activations, campaigns, experiences and more. You will work closely with all Marketing functions including Brand, Social, Events, Growth and Creative teams, as well as Managed Accounts, Product and other departments, to build and execute partnership activations, and capture and convey impact. This is a key role contributing to the long-term growth plan for the Kraken brand and product suite.\n\nThe ideal candidate for this position is someone who is tapped into culture \u2013 from music to sports, to fashion, to art and beyond \u2013 and has experience leading partnerships across a number of these cultural verticals. You are creative, organized, versatile, a strong communicator and collaborator internally and externally, and able to ideate and produce creative, efficient and engaging partnership initiatives content on tight deadlines. You are also a self-starter that has experience wearing multiple hats in a fast-paced environment, switching effortlessly between planning and execution. Building and strengthening relationships is at the core the role, along with unlocking value and furthering Kraken\u2019s Mission through creative brand partnerships. Additionally, you will help to lead and support brand-partnership related IRL activations throughout the year.\n\nThis position is a full-time remote position reporting to the Head of Brand Partnerships.\n\nThe Opportunity\n\nHelp execute the brand partnerships that will support and further Kraken\u2019s Mission and drive brand awareness\n\nLead the day-to-day partnership management across some of our key brand partnerships, like Williams Racing\n\nWork independently to lead cross-functional partnership initiatives, while building, maintaining and growing strong relationships with internal and external teams\n\nIn collaboration with our Head of Brand Partnerships, support all elements of the partner management life cycle: evaluating potential opportunities, ideating and executing valuable initiatives with current partners, framing and assessment of value and impact, negotiating agreements, and implementation and optimization\n\nConnect Kraken business priorities, brand marketing, objectives and key messages across our brand partnerships\n\nCoordinatie and manage pre-activation promotion, on-the-day management and post-activation follow up activities\n\nCollaborate cross-functionally on event execution logistics, asset development, and event communication and execution\n\nHelp lead the development of promotional activation content for various distribution channels\n\nNegotiate and manage external partners/vendors\n\nManage event budgets efficiently through forecasting and tracking\n\nDemonstrate effectiveness of partnership efforts through data collection and reporting\n\nAdditional duties and responsibilities as assigned\n\nSkills you should HODL\n\n6+ years of brand partnerships management, planning and execution experience, preferably including brand partnerships experience within the digital assets industry\n\nStrong time management, communication, organizational and multitasking skills, flexibility and professional confidence\n\nDemonstrated ability to efficiently work on multiple project requests simultaneously in a fast-paced environment\n\nExperience working cross-functionally and communicating to a wide range of stakeholders\n\nExperience in a fast paced and high growth environment, ability to pivot to the needs of the market.\n\nExperience across verticals including gaming, sports, art, music, and/or fashion partnerships a plus\n\nAbility to learn and manage a number of different organizational tools\n\nEnjoy and excel at working cross functionally to deliver results through partnerships\n\nAbility to build and manage relationships with product and business leaders, internally and externally\n\nStrong knowledge and passion for the Crypto industry\n\nGreat strategic instincts, and can exercise good judgment in ambiguous situations\n\nAbility to travel 15%+ of the time, both domestically and internationally\n\nNice to haves:\n\nExperience in business development, product or growth a plus\n\nSuccess negotiating and executing a broad range of partnerships\n\n#LI-Remote\nKraken is powered by people from around the world and we celebrate all Krakenites for their diverse talents, backgrounds, contributions and unique perspectives. We hire strictly based on merit, meaning we seek out the candidates with the right abilities, knowledge, and skills considered the most suitable for the job. We encourage you to apply for roles where you don't fully meet the listed requirements, especially if you're passionate or knowledgable about crypto!\n\nAs an equal opportunity employer, we don\u2019t tolerate discrimination or harassment of any kind. Whether that\u2019s based on race, ethnicity, age, gender identity, citizenship, religion, sexual orientation, disability, pregnancy, veteran status or any other protected characteristic as outlined by federal, state or local laws.", "job_is_remote": true, "job_posted_at_timestamp": 1706723764, "job_posted_at_datetime_utc": "2024-01-31T17:56:04.000Z", "job_city": null, "job_state": null, "job_country": "US", "job_latitude": 37.09024, "job_longitude": -95.71289, "job_benefits": ["dental_coverage", "health_insurance", "retirement_savings"], "job_google_link": "https://www.google.com/search?gl=us&hl=en&rciv=jb&q=manager+of+brand+partnerships&start=10&ibp=htl;jobs#fpstate=tldetail&htivrt=jobs&htiq=manager+of+brand+partnerships&htidocid=Ku3bcDB2xfXzakW2AAAAAA%3D%3D", "job_offer_expiration_datetime_utc": "2024-05-30T20:47:19.000Z", "job_offer_expiration_timestamp": 1717102039, "job_required_experience": {"no_experience_required": false, "required_experience_in_months": null, "experience_mentioned": true, "experience_preferred": true}, "job_required_skills": null, "job_required_education": {"postgraduate_degree": false, "professional_certification": false, "high_school": false, "associates_degree": false, "bachelors_degree": false, "degree_mentioned": false, "degree_preferred": false, "professional_certification_mentioned": false}, "job_experience_in_place_of_education": false, "job_min_salary": 117000, "job_max_salary": 176000, "job_salary_currency": "USD", "job_salary_period": "YEAR", "job_highlights": {"Qualifications": ["The ideal candidate for this position is someone who is tapped into culture \u2013 from music to sports, to fashion, to art and beyond \u2013 and has experience leading partnerships across a number of these cultural verticals", "You are creative, organized, versatile, a strong communicator and collaborator internally and externally, and able to ideate and produce creative, efficient and engaging partnership initiatives content on tight deadlines", "You are also a self-starter that has experience wearing multiple hats in a fast-paced environment, switching effortlessly between planning and execution", "6+ years of brand partnerships management, planning and execution experience, preferably including brand partnerships experience within the digital assets industry", "Strong time management, communication, organizational and multitasking skills, flexibility and professional confidence", "Demonstrated ability to efficiently work on multiple project requests simultaneously in a fast-paced environment", "Experience working cross-functionally and communicating to a wide range of stakeholders", "Experience in a fast paced and high growth environment, ability to pivot to the needs of the market", "Ability to learn and manage a number of different organizational tools", "Ability to build and manage relationships with product and business leaders, internally and externally", "Strong knowledge and passion for the Crypto industry", "Great strategic instincts, and can exercise good judgment in ambiguous situations", "Ability to travel 15%+ of the time, both domestically and internationally", "Success negotiating and executing a broad range of partnerships"], "Responsibilities": ["Reporting to the Head of Brand Partnerships, you will manage the relationships with our global brand partners, including producing and participating in partnership strategy development, leading partnership activations, campaigns, experiences and more", "You will work closely with all Marketing functions including Brand, Social, Events, Growth and Creative teams, as well as Managed Accounts, Product and other departments, to build and execute partnership activations, and capture and convey impact", "This is a key role contributing to the long-term growth plan for the Kraken brand and product suite", "Additionally, you will help to lead and support brand-partnership related IRL activations throughout the year", "Help execute the brand partnerships that will support and further Kraken\u2019s Mission and drive brand awareness", "Lead the day-to-day partnership management across some of our key brand partnerships, like Williams Racing", "Work independently to lead cross-functional partnership initiatives, while building, maintaining and growing strong relationships with internal and external teams", "In collaboration with our Head of Brand Partnerships, support all elements of the partner management life cycle: evaluating potential opportunities, ideating and executing valuable initiatives with current partners, framing and assessment of value and impact, negotiating agreements, and implementation and optimization", "Connect Kraken business priorities, brand marketing, objectives and key messages across our brand partnerships", "Coordinatie and manage pre-activation promotion, on-the-day management and post-activation follow up activities", "Collaborate cross-functionally on event execution logistics, asset development, and event communication and execution", "Help lead the development of promotional activation content for various distribution channels", "Negotiate and manage external partners/vendors", "Manage event budgets efficiently through forecasting and tracking", "Demonstrate effectiveness of partnership efforts through data collection and reporting"], "Benefits": ["$117K \u2013 $176K", "Offers Equity", "Offers Bonus", "This is the target annual salary range for this role", "This range is not inclusive of other additional compensation elements, such as our Bonus program, Equity program, Wellness allowance, and other benefits [US Only] (including medical, dental, vision and 401(k))", "The compensation range provided is influenced by various factors and represents the initial target range", "Our salary offerings are dynamic and we strive to ensure that our base salary and total compensation package aligns and recognizes the top talent we aim to attract and retain"]}, "job_job_title": "Partnerships manager", "job_posting_language": "en", "job_onet_soc": "11202100", "job_onet_job_zone": "4", "job_naics_code": "52", "job_naics_name": "Finance"}