{"job_id": "xFqeHkQRIuSoyd1_AAAAAA==", "employer_name": "Hemster", "employer_logo": "https://media.licdn.com/dms/image/C4E0BAQFJiQtquqbWMw/company-logo_200_200/0/1674661611203/hemster_logo?e=2147483647&v=beta&t=kCbNUKsfvFRgEnvahTIIdEyI8MTrA1imsVmROtuyNxw", "employer_website": "http://www.hemster.co", "employer_company_type": null, "job_publisher": "LinkedIn", "job_employment_type": "FULLTIME", "job_title": "Business Data Analyst", "job_apply_link": "https://www.linkedin.com/jobs/view/business-data-analyst-at-hemster-3864039425?refId=Hnlwv3iOCw9Fb6qc1DvPBg%3D%3D&trackingId=QWtheE4r8RfFIV8kbPOJjw%3D%3D&position=24&pageNum=0&trk=public_jobs_jserp-result_search-card", "job_apply_is_direct": false, "job_apply_quality_score": 0.6311, "apply_options": [{"publisher": "LinkedIn", "apply_link": "https://www.linkedin.com/jobs/view/business-data-analyst-at-hemster-3864039425?refId=Hnlwv3iOCw9Fb6qc1DvPBg%3D%3D&trackingId=QWtheE4r8RfFIV8kbPOJjw%3D%3D&position=24&pageNum=0&trk=public_jobs_jserp-result_search-card", "is_direct": false}], "job_description": "Business Data Analyst\n\nDepartment: Product\n\nReports To: COO\n\nFull Time \u2013 Exempt (Salary)\n\nLocation: Remote\n\nSalary Range: $85,000 - $95,000\n\nCompany Description:\n\nHemster offers technology solutions to the fashion industry in order to optimize how clothes fit consumers, and helps brands maximize inventory productivity via data-driven refurbishment services. Hemster\u2019s focus on technology innovation and sustainability is changing how consumers and brands view the garments they buy and produce.\n\nOverview:\n\nThe Business Data Analyst supports the development of a data-driven culture, where analytical data is used to inform new strategies, develop operational improvements, and establish the evaluative framework for critical business initiatives. This role uses statistical methods, data modeling, analytical methodologies, and data analysis to develop and deploy tools including dashboards, infographics, reports, and models to inform and support decision-making. The individual will identify relevant data sets, analyze data, and support the development of KPIs to hold cross-functional teams accountable. Role will require developing a detailed understanding of the Company\u2019s business model, objectives, issues, and challenges by interacting and collaborating with external users and internal stakeholders.\n\nThis job description is intended to describe the general nature and level of work but is not inclusive of all duties, responsibilities or qualifications. Duties, responsibilities, and activities may change at any time based on business needs.\n\nResponsibilities:\n\nData Collection and Analysis:\n\u2022 Gather, clean, and analyze large volumes of data from various sources to extract meaningful insights.\n\u2022 Manipulate and adjust external data points to align with internal validation requirements.\n\u2022 Utilize statistical methods to identify trends, patterns, and correlations in the data.\n\u2022 Develop and execute \u201cred-flag\u201d data identification strategies to quickly identify concerns.\n\nReport Generation:\n\u2022 Create and generate regular reports for key stakeholders, highlighting relevant KPIs and performance metrics.\n\u2022 Develop dashboards and visualizations to effectively communicate complex data findings.\n\u2022 Provide context on dashboards and/or reports in external cross-functional meetings.\n\nBusiness Strategy Support:\n\u2022 Collaborate with cross-functional teams to understand business requirements and provide data-driven recommendations.\n\u2022 Assist in the development and evaluation of business strategies based on data analysis.\n\nData Quality Assurance and Access Controls:\n\u2022 Implement data quality checks and validation processes to ensure accuracy and reliability of data.\n\u2022 Proactively identify and resolve data discrepancies or anomalies.\n\u2022 Manage our Metabase platform to ensure proper user access.\n\nProduct Support\n\u2022 Collaborate with Product to ensure that essential data points are being tracked and monitored for new product launches.\n\nContinuous Improvement:\n\u2022 Recommend and implement improvements to data collection and analysis processes.\n\nGreat-to-haves:\n\u2022 Familiarity with multi-brand inventory catalog manipulations\n\u2022 Experience providing data guidance to product and engineering\n\u2022 Comfortable presenting data insights to company partners and external parties\n\u2022 Deep understanding of Metabase Cloud\n\u2022 B2B2C experience\n\nRequirements:\n\u2022 SQL fluency\n\u2022 2-3 years related work experience\n\u2022 Strong time management and organizational skills\n\u2022 Ability to read, write, and understand English\n\u2022 Self-motivated and team-oriented\n\u2022 Excellent written and verbal communication skills\n\u2022 Good problem-solving skills and the ability to troubleshoot problems.\n\u2022 Strong organization skills, attention to detail and follow through to resolve any outstanding issues.\n\nPosition Type / Expected Hours of Work:\n\nThis is a full-time, exempt position. This position is not eligible for overtime. Work hours are typically 40 hours a week, Monday thru Friday.\n\nCOVID VACCINATION REQUIRED", "job_is_remote": true, "job_posted_at_timestamp": 1710868436, "job_posted_at_datetime_utc": "2024-03-19T17:13:56.000Z", "job_city": null, "job_state": null, "job_country": "US", "job_latitude": 37.09024, "job_longitude": -95.71289, "job_benefits": null, "job_google_link": "https://www.google.com/search?gl=us&hl=en&rciv=jb&q=data+analyst&start=0&ibp=htl;jobs#fpstate=tldetail&htivrt=jobs&htiq=data+analyst&htidocid=xFqeHkQRIuSoyd1_AAAAAA%3D%3D", "job_offer_expiration_datetime_utc": "2024-09-15T17:13:22.000Z", "job_offer_expiration_timestamp": 1726420402, "job_required_experience": {"no_experience_required": false, "required_experience_in_months": 24, "experience_mentioned": true, "experience_preferred": false}, "job_required_skills": null, "job_required_education": {"postgraduate_degree": false, "professional_certification": false, "high_school": false, "associates_degree": false, "bachelors_degree": true, "degree_mentioned": false, "degree_preferred": false, "professional_certification_mentioned": false}, "job_experience_in_place_of_education": false, "job_min_salary": null, "job_max_salary": null, "job_salary_currency": null, "job_salary_period": null, "job_highlights": {"Qualifications": ["Familiarity with multi-brand inventory catalog manipulations", "Experience providing data guidance to product and engineering", "Comfortable presenting data insights to company partners and external parties", "Deep understanding of Metabase Cloud", "B2B2C experience", "SQL fluency", "2-3 years related work experience", "Strong time management and organizational skills", "Ability to read, write, and understand English", "Self-motivated and team-oriented", "Excellent written and verbal communication skills", "Good problem-solving skills and the ability to troubleshoot problems", "Strong organization skills, attention to detail and follow through to resolve any outstanding issues"], "Responsibilities": ["The Business Data Analyst supports the development of a data-driven culture, where analytical data is used to inform new strategies, develop operational improvements, and establish the evaluative framework for critical business initiatives", "This role uses statistical methods, data modeling, analytical methodologies, and data analysis to develop and deploy tools including dashboards, infographics, reports, and models to inform and support decision-making", "The individual will identify relevant data sets, analyze data, and support the development of KPIs to hold cross-functional teams accountable", "Role will require developing a detailed understanding of the Company\u2019s business model, objectives, issues, and challenges by interacting and collaborating with external users and internal stakeholders", "Duties, responsibilities, and activities may change at any time based on business needs", "Gather, clean, and analyze large volumes of data from various sources to extract meaningful insights", "Manipulate and adjust external data points to align with internal validation requirements", "Utilize statistical methods to identify trends, patterns, and correlations in the data", "Develop and execute \u201cred-flag\u201d data identification strategies to quickly identify concerns", "Create and generate regular reports for key stakeholders, highlighting relevant KPIs and performance metrics", "Develop dashboards and visualizations to effectively communicate complex data findings", "Provide context on dashboards and/or reports in external cross-functional meetings", "Collaborate with cross-functional teams to understand business requirements and provide data-driven recommendations", "Assist in the development and evaluation of business strategies based on data analysis", "Data Quality Assurance and Access Controls:", "Implement data quality checks and validation processes to ensure accuracy and reliability of data", "Proactively identify and resolve data discrepancies or anomalies", "Manage our Metabase platform to ensure proper user access", "Product Support", "Collaborate with Product to ensure that essential data points are being tracked and monitored for new product launches", "Continuous Improvement:", "Recommend and implement improvements to data collection and analysis processes"], "Benefits": ["Full Time \u2013 Exempt (Salary)", "Location: Remote", "Salary Range: $85,000 - $95,000"]}, "job_job_title": "Data analyst", "job_posting_language": "en", "job_onet_soc": "43911100", "job_onet_job_zone": "4"}