{"job_id": "JvlvkW6vRzzsHZ97AAAAAA==", "employer_name": "Mitchell Talent Solutions", "employer_logo": "https://encrypted-tbn0.gstatic.com/images?q=tbn:ANd9GcRD57pg53O_jmP8vdnCRvldn7ioA7n_c6I5XRWJ&s=0", "employer_website": null, "employer_company_type": null, "job_publisher": "LinkedIn", "job_employment_type": "FULLTIME", "job_title": "Vice President of Sales", "job_apply_link": "https://www.linkedin.com/jobs/view/vice-president-of-sales-at-mitchell-talent-solutions-3849944926", "job_apply_is_direct": false, "job_apply_quality_score": 0.6381, "apply_options": [{"publisher": "LinkedIn", "apply_link": "https://www.linkedin.com/jobs/view/vice-president-of-sales-at-mitchell-talent-solutions-3849944926", "is_direct": false}, {"publisher": "Cybersecurity Jobs", "apply_link": "https://www.cybersecurityhq.io/jobs/51783509-vice-president-of-sales", "is_direct": false}], "job_description": "Mitchell Talent Solutions has partnered with a leading ERP Preferred Partner specializing in providing comprehensive ERP solutions to small to mid-size businesses, primarily in the manufacturing industry, but a variety of industry opportunities for growth.\n\nPosition Overview:\n\nAs the Vice President of Sales, you will play a pivotal role in driving revenue growth and expanding our client base. You will lead a team of 3 sales professionals and will be responsible for hiring and onboarding an additional 3 salespeople who will report directly to you. Your strategic leadership will be instrumental in achieving sales targets (~2 million as an individual, ~7 million as a team) and establishing long-term relationships with clients. Ideal candidate is preferred to be on-site in Knoxville, TN. Relocation bonus is offered after completion of first year of employment. If a candidate would prefer to work in a hybrid capacity, travel to Knoxville would be required for at least 1 week out of the month.\n\nResponsibilities:\n\u2022 Develop and execute strategic sales plans to penetrate the manufacturing market and achieve revenue targets.\n\u2022 Lead, mentor, and manage a team of 3 sales professionals, fostering a high-performance culture and providing ongoing training and support.\n\u2022 Lead the hiring process for 3 additional salespeople, ensuring the recruitment of top talent that aligns with our company's values and goals.\n\u2022 Collaborate with marketing, product development, and implementation teams to ensure alignment of sales strategies with client needs and market trends.\n\u2022 Identify and prioritize target accounts and develop customized sales strategies to address their specific business challenges.\n\u2022 Build and maintain strong relationships with key decision-makers in the manufacturing industry, including C-level executives, IT directors, and operations managers.\n\u2022 Stay abreast of industry trends, competitor activities, and market developments to inform sales strategies and maintain a competitive edge.\n\u2022 Analyze sales data and performance metrics to evaluate the effectiveness of sales initiatives and identify areas for improvement.\n\u2022 Represent the company at industry events, trade shows, and conferences to promote our brand and establish thought leadership in the ERP space.\n\u2022 Total annual sales commission should be in the range of ~$100,000 in addition to annual salary.\n\u2022 THIS ROLE HAS A STRONG PATH TO OWNERSHIP EQUITY\n\nRequirements:\n\u2022 Bachelor's degree in Business Administration, Sales, Marketing, or related field; MBA or relevant advanced degree preferred.\n\u2022 At least 10 years of experience in sales leadership roles, preferably in the ERP or technology industry, with a proven track record of achieving sales targets and driving revenue growth.\n\u2022 Experience selling ERP solutions or related services to small to mid-size businesses.\n\u2022 Strong leadership and management skills, with the ability to inspire, motivate, and develop a sales team.\n\u2022 Excellent communication, negotiation, and interpersonal skills, with the ability to build and maintain strong client relationships.\n\u2022 Strategic thinker with the ability to develop and implement effective sales strategies that align with client needs and market trends.\n\u2022 Analytical mindset with the ability to analyze sales data and metrics to drive informed decision-making.\n\u2022 Proven ability to thrive in a fast-paced, dynamic environment and adapt to changing priorities.\n\u2022 Knowledge of ERP systems, manufacturing processes, and industry-specific challenges and opportunities.", "job_is_remote": false, "job_posted_at_timestamp": 1710261560, "job_posted_at_datetime_utc": "2024-03-12T16:39:20.000Z", "job_city": "Knoxville", "job_state": "TN", "job_country": "US", "job_latitude": 35.96064, "job_longitude": -83.92074, "job_benefits": null, "job_google_link": "https://www.google.com/search?gl=us&hl=en&rciv=jb&q=vice+president+of+sales&start=50&ibp=htl;jobs#fpstate=tldetail&htivrt=jobs&htiq=vice+president+of+sales&htidocid=JvlvkW6vRzzsHZ97AAAAAA%3D%3D", "job_offer_expiration_datetime_utc": "2024-04-11T16:39:17.000Z", "job_offer_expiration_timestamp": 1712853557, "job_required_experience": {"no_experience_required": false, "required_experience_in_months": 120, "experience_mentioned": true, "experience_preferred": false}, "job_required_skills": null, "job_required_education": {"postgraduate_degree": false, "professional_certification": false, "high_school": false, "associates_degree": false, "bachelors_degree": true, "degree_mentioned": true, "degree_preferred": true, "professional_certification_mentioned": false}, "job_experience_in_place_of_education": false, "job_min_salary": null, "job_max_salary": null, "job_salary_currency": null, "job_salary_period": null, "job_highlights": {"Qualifications": ["At least 10 years of experience in sales leadership roles, preferably in the ERP or technology industry, with a proven track record of achieving sales targets and driving revenue growth", "Experience selling ERP solutions or related services to small to mid-size businesses", "Strong leadership and management skills, with the ability to inspire, motivate, and develop a sales team", "Excellent communication, negotiation, and interpersonal skills, with the ability to build and maintain strong client relationships", "Strategic thinker with the ability to develop and implement effective sales strategies that align with client needs and market trends", "Analytical mindset with the ability to analyze sales data and metrics to drive informed decision-making", "Proven ability to thrive in a fast-paced, dynamic environment and adapt to changing priorities", "Knowledge of ERP systems, manufacturing processes, and industry-specific challenges and opportunities"], "Responsibilities": ["As the Vice President of Sales, you will play a pivotal role in driving revenue growth and expanding our client base", "You will lead a team of 3 sales professionals and will be responsible for hiring and onboarding an additional 3 salespeople who will report directly to you", "Your strategic leadership will be instrumental in achieving sales targets (~2 million as an individual, ~7 million as a team) and establishing long-term relationships with clients", "Develop and execute strategic sales plans to penetrate the manufacturing market and achieve revenue targets", "Lead, mentor, and manage a team of 3 sales professionals, fostering a high-performance culture and providing ongoing training and support", "Lead the hiring process for 3 additional salespeople, ensuring the recruitment of top talent that aligns with our company's values and goals", "Collaborate with marketing, product development, and implementation teams to ensure alignment of sales strategies with client needs and market trends", "Identify and prioritize target accounts and develop customized sales strategies to address their specific business challenges", "Build and maintain strong relationships with key decision-makers in the manufacturing industry, including C-level executives, IT directors, and operations managers", "Stay abreast of industry trends, competitor activities, and market developments to inform sales strategies and maintain a competitive edge", "Analyze sales data and performance metrics to evaluate the effectiveness of sales initiatives and identify areas for improvement", "Represent the company at industry events, trade shows, and conferences to promote our brand and establish thought leadership in the ERP space", "Total annual sales commission should be in the range of ~$100,000 in addition to annual salary", "THIS ROLE HAS A STRONG PATH TO OWNERSHIP EQUITY"], "Benefits": ["Relocation bonus is offered after completion of first year of employment"]}, "job_job_title": "Vice", "job_posting_language": "en", "job_onet_soc": "11101100", "job_onet_job_zone": "5"}