{"job_id": "IVC6_IFiRVhk-HN2AAAAAA==", "employer_name": "Datalogicrecruitment", "employer_logo": "https://encrypted-tbn0.gstatic.com/images?q=tbn:ANd9GcR6ql90NZDbKr9V3llMPXY76U51HWp9BPSEZeNs&s=0", "employer_website": null, "employer_company_type": null, "job_publisher": "DataLogic", "job_employment_type": "FULLTIME", "job_title": "Senior Data Scientist", "job_apply_link": "https://www.datalogicrecruitment.com/vacancy/senior-data-scientist", "job_apply_is_direct": false, "job_apply_quality_score": 0.7778, "apply_options": [{"publisher": "DataLogic", "apply_link": "https://www.datalogicrecruitment.com/vacancy/senior-data-scientist", "is_direct": false}], "job_description": "Senior Data Scientist\n\nAbout the job\n\nOur wonderful client is seeking an experienced Senior Data Scientist to join their engineering team in support of the development and improvement of their proprietary algorithms potheyring the mobile application. This is a critical role on their existing data science team to build a scalable and accurate solution to serve customers personalized notifications regarding upcoming, interesting live sports look-ins.\n\nThis person will be focused on developing and scaling personalized recommendation system. This system will be used to enhance notification system by utilizing explicit and implicit user preferences to notify fans of buzzworthy moments across a variety of sports and leagues. The goal of these models is to trigger high-value, personalized notifications to users based on their preferences and usage data. This role reports into their Director of Engineering and will build upon the existing infrastructure created to develop and refine existing and new models.\n\nThis person should be highly self-motivated, able to effectively manage one\u2019s own time, extremely collaborative, and highly communicative especially given their distributed team.\n\nThe Senior Data Scientist works directly with the Engineering and Product teams, and collaborates with the broader Operations and Partnerships teams.\n\nIn This Role, You Will\n\nResearch and Development: Research and develop a scalable, personalized recommendation system spanning each sport and league that they cover in order to trigger effective notifications. You will also conduct research and development related to league and sport specific modeling to better predict noteworthy sports moments.\nScoping Data Needs: Define key user data needed to build an effective recommendation and notification engine. In preparation for partnership discussions, identify league-specific data needs to effectively detect exciting moments that have some degree of predictability. Represent the team on league calls and articulate data requests and requirements for a successful customer experience.\nModel Enhancement: Contribute as a thought partner to the existing Data science team in further enhancing the model development process and existing league models. Evaluate existing models and processes to find possible improvements or potential bottlenecks.\nOnboarding and Personalization: Scope and identify what data Buzzer needs to best cluster/categorize its users for efficient recommendations and play an active role in discussions on how Buzzer should use onboarding data to send the best-personalized notifications.\nCoach and Mentor: As a technical competence leader, be responsible for coaching and mentoring data scientists across data modeling, machine learning, and other areas of their professional development in order to grow and level up the data science team.\n\nRequired Qualifications\n\n5+ years working with traditional data modeling and comfortable with leveraging multiple data stheirces\nStrong experience with Python and SQL\nExperience building and evaluating both supervised and unsupervised machine learning algorithms\nExperience working within a cloud environment like AWS\nExperience with statistics and or data modeling tools and analysis\nWorking knowledge of Unix/Linux\nWorking knowledge of stheirce control systems, including Git\n\nPreferred Qualifications\n\nExperience building a recommendation engine or implementing a collaborative filtering system\nExperience using cloud-based services and big data technologies to support data processing pipelines such as AWS Redshift, EMR, Sagemaker, and Spark.\nPrevious experience working in an agile environment with 2-theyek sprints\nExperience in working with clients or external partners to achieve mutually desired results\nExperience with sports media applications and or design\nAbility to self-motivate and manage up to report on progress and blockers\nEmpathetic, values-driven individual who is eager to contribute to a broader team culture\nMaster\u2019s Degree in Engineering, Data Science, Mathematics, Computational Statistics, Operations Research, Machine Learning or related technical fields.\n\nAbout the Company\n\nThis firm delivers the moments that matter to you most. They celebrate their community of fans who are fueled by their passion for sports. Founded in New York, their growing remote team respects tradition while valuing innovation. Their belief is that as a leading unifier of the sports ecosystem, they can foster togetherness through meaningful touch points & across generations.", "job_is_remote": false, "job_posted_at_timestamp": 1632096000, "job_posted_at_datetime_utc": "2021-09-20T00:00:00.000Z", "job_city": "New York", "job_state": "NY", "job_country": "US", "job_latitude": 40.712776, "job_longitude": -74.005974, "job_benefits": null, "job_google_link": "https://www.google.com/search?gl=us&hl=en&rciv=jb&q=senior+data+scientist&start=80&ibp=htl;jobs#fpstate=tldetail&htivrt=jobs&htiq=senior+data+scientist&htidocid=IVC6_IFiRVhk-HN2AAAAAA%3D%3D", "job_offer_expiration_datetime_utc": null, "job_offer_expiration_timestamp": null, "job_required_experience": {"no_experience_required": false, "required_experience_in_months": 60, "experience_mentioned": true, "experience_preferred": false}, "job_required_skills": null, "job_required_education": {"postgraduate_degree": false, "professional_certification": false, "high_school": false, "associates_degree": false, "bachelors_degree": false, "degree_mentioned": true, "degree_preferred": true, "professional_certification_mentioned": false}, "job_experience_in_place_of_education": false, "job_min_salary": null, "job_max_salary": null, "job_salary_currency": null, "job_salary_period": null, "job_highlights": {"Qualifications": ["5+ years working with traditional data modeling and comfortable with leveraging multiple data stheirces", "Strong experience with Python and SQL", "Experience building and evaluating both supervised and unsupervised machine learning algorithms", "Experience working within a cloud environment like AWS", "Experience with statistics and or data modeling tools and analysis", "Working knowledge of Unix/Linux", "Working knowledge of stheirce control systems, including Git", "Experience building a recommendation engine or implementing a collaborative filtering system", "Experience using cloud-based services and big data technologies to support data processing pipelines such as AWS Redshift, EMR, Sagemaker, and Spark", "Previous experience working in an agile environment with 2-theyek sprints", "Experience with sports media applications and or design", "Ability to self-motivate and manage up to report on progress and blockers", "Empathetic, values-driven individual who is eager to contribute to a broader team culture", "Master\u2019s Degree in Engineering, Data Science, Mathematics, Computational Statistics, Operations Research, Machine Learning or related technical fields"], "Responsibilities": ["This person will be focused on developing and scaling personalized recommendation system", "This system will be used to enhance notification system by utilizing explicit and implicit user preferences to notify fans of buzzworthy moments across a variety of sports and leagues", "This role reports into their Director of Engineering and will build upon the existing infrastructure created to develop and refine existing and new models", "This person should be highly self-motivated, able to effectively manage one\u2019s own time, extremely collaborative, and highly communicative especially given their distributed team", "Research and Development: Research and develop a scalable, personalized recommendation system spanning each sport and league that they cover in order to trigger effective notifications", "You will also conduct research and development related to league and sport specific modeling to better predict noteworthy sports moments", "In preparation for partnership discussions, identify league-specific data needs to effectively detect exciting moments that have some degree of predictability", "Represent the team on league calls and articulate data requests and requirements for a successful customer experience", "Model Enhancement: Contribute as a thought partner to the existing Data science team in further enhancing the model development process and existing league models", "Evaluate existing models and processes to find possible improvements or potential bottlenecks", "Onboarding and Personalization: Scope and identify what data Buzzer needs to best cluster/categorize its users for efficient recommendations and play an active role in discussions on how Buzzer should use onboarding data to send the best-personalized notifications", "Coach and Mentor: As a technical competence leader, be responsible for coaching and mentoring data scientists across data modeling, machine learning, and other areas of their professional development in order to grow and level up the data science team"]}, "job_job_title": "Data scientist", "job_posting_language": "en", "job_onet_soc": "15111100", "job_onet_job_zone": "5"}