{"job_id": "U-ydpl5T7L2huYaxAAAAAA==", "employer_name": "Harris County", "employer_logo": null, "employer_website": null, "employer_company_type": null, "job_publisher": "GovernmentJobs.com", "job_employment_type": "FULLTIME", "job_title": "Senior Data Engineer", "job_apply_link": "https://www.governmentjobs.com/jobs/4353042-0/senior-data-engineer", "job_apply_is_direct": false, "job_apply_quality_score": 0.8049, "apply_options": [{"publisher": "GovernmentJobs.com", "apply_link": "https://www.governmentjobs.com/jobs/4353042-0/senior-data-engineer", "is_direct": false}, {"publisher": "Glassdoor", "apply_link": "https://www.glassdoor.com/job-listing/senior-data-engineer-harris-county-JV_IC1140171_KO0,20_KE21,34.htm?jl=1009090146361", "is_direct": false}, {"publisher": "LinkedIn", "apply_link": "https://www.linkedin.com/jobs/view/senior-data-engineer-at-harris-county-3812533445", "is_direct": false}, {"publisher": "Salary.com", "apply_link": "https://www.salary.com/job/harris-county/senior-data-engineer/j202401252308207542222", "is_direct": false}, {"publisher": "LazyApply", "apply_link": "https://lazyapply.com/jobpreview/job_32f36edf19b65251", "is_direct": false}], "job_description": "Harris County Public Health has earned the 2023 Best Place for Working Parents Business Designation.\n\nAbout Harris County Public Health:\nHarris County Public Health (HCPH) includes a network of more than 700 public health professionals working together to improve health outcomes for the third most populous county in the United States. HCPH provides a multitude of services such as medical and dental services, community programming, and health education for the approximately 2.3 million people in unincorporated Harris County. Through its core values of innovation, engagement, and health equity, HCPH strives to bring meaningful solutions to public health issues while keeping Harris County healthy and vibrant.\n\nPosition Overview:\nThe Senior Data Engineer will play a crucial role within the Operations and Technology Services team at Harris County Public Health. Reporting directly to the DevOps Manager, this role will be responsible for designing, developing, and maintaining robust data pipelines, infrastructure, and tools to support data integration, transformation, and analysis. The Senior Data Engineer will collaborate closely with cross-functional teams to ensure efficient data management practices that enable informed decision-making and advance the organization's public health goals.\n\nDuties and Responsibilities:\n\u2022 Design, implement, and maintain scalable and efficient data pipelines for ingesting, processing, and transforming data from various sources. Implement automation scripts and workflows to streamline data processing, deployment, and monitoring tasks. Implement and maintain data security best practices to safeguard sensitive information to comply with relevant data privacy regulations.\n\u2022 Optimize data structures and schema designs to improve query performance and data retrieval. Monitor system performance, troubleshoot issues, and implement improvements to ensure optimal data processing and storage.\n\u2022 Collaborate with other teams including data scientists, analysts, software engineers, and stakeholders to understand data requirements and deliver effective solutions.\n\u2022 Communicate technical concepts and findings to non-technical audiences, ensuring clear understanding of data processes and outcomes. Maintain clear and thorough documentation of data pipelines, processes, and infrastructure configurations.\n\u2022 Other duties as assigned including special tasks involved in responding to an emergency event.\n\nHarris County is an Equal Opportunity Employer\nhttps://hrrm.harriscountytx.gov/Pages/EqualEmploymentOpportunityPlan.aspx\nIf you need special services or accommodations, please call (713) 274-5445 or email ADACoordinator@bmd.hctx.net.\n\nThis position is subject to a criminal history check. Only relevant convictions will be considered and, even when considered, may not automatically disqualify the candidate.\n\nEducation:\n\u2022 Bachelor's degree in computer science, information technology (IT), computer engineering or a closely related field.\n\nExperience:\n\u2022 Five (5) years of Data warehouse experience.\n\u2022 Two (2) years of Data warehouse implementations from start to finish.\n\nComputer Skills:\n\u2022 Proficient in Microsoft Office Suite software, including 365 programs\n\u2022 Proficient in Agile project methodology (Scrum, Agile, etc.)\n\u2022 Proficient in software development tools (DevOPS, Jira, etc.)\n\u2022 Proficient in ETL tools (SSIS, Azure data factory)\n\u2022 Proficient in database systems (MSSQL, CosmosDB)\n\u2022 Proficient in designing solutions on cloud platforms (Azure)\n\u2022 Proficient in data warehouse solutions (Snowflake)\n\u2022 Proficient in scripting languages (Python, NodeJS)\n\nCore Competencies:\nOrganizational Leadership\n\u2022 Understands the organizational mission\n\u2022 Understands ethics and public good; is concerned with public trust\n\u2022 Demonstrates respect for the opinions and beliefs of others\n\nCollaboration\n\u2022 Contributes to an inclusive workplace where equity, diversity, inclusion, and individual differences are valued and leveraged to achieve the vision and mission\n\u2022 Demonstrates a sense of responsibility for the success of the group\n\u2022 Collaborates with others to improve quality and address needs\n\nInnovation\n\u2022 Ability to adapt to change\n\nInterpersonal Abilities/Personal Characteristics\n\u2022 Treats others with courtesy, sensitivity, and respect\n\u2022 Behaves in an honest, fair, and ethical manner\n\u2022 Assesses and recognizes own strengths and weaknesses\n\u2022 Uses sound judgment\n\u2022 Self-motivated\n\u2022 Organizes and maintains work environment to allow for maximum productivity\n\nCommunication\n\u2022 Communicates clearly and effectively, both orally and in writing\n\nNOTE: Qualifying education, experience, knowledge and skills must be documented on your job application. You may attach a resume to the application as supporting documentation but ONLY information stated on the application will be used for consideration. \"See Resume\" will not be accepted for qualifications.\n\nPosition Type, and Typical Hours of Work:\n\u2022 Full-Time | Regular\n\u2022 Monday - Friday; 8 am - 5 pm (40hrs. per week)\n\u2022 Hours may vary based on the business needs of the department or tasks requirements.\n\u2022 May require periodic overnight travel and long hours/overtime during emergencies/disasters.\n\nWork Environment:\n\u2022 This job operates in a professional office environment.\n\u2022 This role routinely uses standard office equipment such as computers, phones, photocopiers, filing cabinets and fax machines.\n\nPhysical Demands:\n\u2022 This position is primarily a sedentary role.\n\u2022 May occasionally lift and move up to 25 pounds.\n\nWork Location:\n\u2022 Harris County Public Health (1111 Fannin, Houston, 77002)\n\nEmployment may be contingent on passing a drug screen and meeting other standards.\n\nDue to a high volume of applications positions may close prior to the advertised closing date or at the discretion of the Hiring Department.", "job_is_remote": false, "job_posted_at_timestamp": 1706047200, "job_posted_at_datetime_utc": "2024-01-23T22:00:00.000Z", "job_city": "Houston", "job_state": "TX", "job_country": "US", "job_latitude": 29.760427, "job_longitude": -95.369804, "job_benefits": null, "job_google_link": "https://www.google.com/search?gl=us&hl=en&rciv=jb&q=data+engineer&start=10&ibp=htl;jobs#fpstate=tldetail&htivrt=jobs&htiq=data+engineer&htidocid=U-ydpl5T7L2huYaxAAAAAA%3D%3D", "job_offer_expiration_datetime_utc": "2024-04-24T23:59:00.000Z", "job_offer_expiration_timestamp": 1714003140, "job_required_experience": {"no_experience_required": false, "required_experience_in_months": 60, "experience_mentioned": true, "experience_preferred": false}, "job_required_skills": null, "job_required_education": {"postgraduate_degree": false, "professional_certification": false, "high_school": false, "associates_degree": false, "bachelors_degree": false, "degree_mentioned": true, "degree_preferred": true, "professional_certification_mentioned": false}, "job_experience_in_place_of_education": false, "job_min_salary": null, "job_max_salary": null, "job_salary_currency": null, "job_salary_period": null, "job_highlights": {"Qualifications": ["Bachelor's degree in computer science, information technology (IT), computer engineering or a closely related field", "Five (5) years of Data warehouse experience", "Two (2) years of Data warehouse implementations from start to finish", "Proficient in Microsoft Office Suite software, including 365 programs", "Proficient in Agile project methodology (Scrum, Agile, etc.)", "Proficient in software development tools (DevOPS, Jira, etc.)", "Proficient in ETL tools (SSIS, Azure data factory)", "Proficient in database systems (MSSQL, CosmosDB)", "Proficient in designing solutions on cloud platforms (Azure)", "Proficient in data warehouse solutions (Snowflake)", "Proficient in scripting languages (Python, NodeJS)", "Ability to adapt to change", "May require periodic overnight travel and long hours/overtime during emergencies/disasters"], "Responsibilities": ["Reporting directly to the DevOps Manager, this role will be responsible for designing, developing, and maintaining robust data pipelines, infrastructure, and tools to support data integration, transformation, and analysis", "The Senior Data Engineer will collaborate closely with cross-functional teams to ensure efficient data management practices that enable informed decision-making and advance the organization's public health goals", "Design, implement, and maintain scalable and efficient data pipelines for ingesting, processing, and transforming data from various sources", "Implement automation scripts and workflows to streamline data processing, deployment, and monitoring tasks", "Implement and maintain data security best practices to safeguard sensitive information to comply with relevant data privacy regulations", "Optimize data structures and schema designs to improve query performance and data retrieval", "Monitor system performance, troubleshoot issues, and implement improvements to ensure optimal data processing and storage", "Collaborate with other teams including data scientists, analysts, software engineers, and stakeholders to understand data requirements and deliver effective solutions", "Communicate technical concepts and findings to non-technical audiences, ensuring clear understanding of data processes and outcomes", "Maintain clear and thorough documentation of data pipelines, processes, and infrastructure configurations", "Other duties as assigned including special tasks involved in responding to an emergency event", "Understands the organizational mission", "Understands ethics and public good; is concerned with public trust", "Demonstrates respect for the opinions and beliefs of others", "Contributes to an inclusive workplace where equity, diversity, inclusion, and individual differences are valued and leveraged to achieve the vision and mission", "Demonstrates a sense of responsibility for the success of the group", "Collaborates with others to improve quality and address needs", "Behaves in an honest, fair, and ethical manner", "Assesses and recognizes own strengths and weaknesses", "Organizes and maintains work environment to allow for maximum productivity", "This role routinely uses standard office equipment such as computers, phones, photocopiers, filing cabinets and fax machines", "This position is primarily a sedentary role", "May occasionally lift and move up to 25 pounds"], "Benefits": ["Full-Time | Regular", "Monday - Friday; 8 am - 5 pm (40hrs"]}, "job_job_title": "Data engineer", "job_posting_language": "en", "job_onet_soc": "15113200", "job_onet_job_zone": "4"}