{"job_id": "0y4sxU2ikjnaJ69wAAAAAA==", "employer_name": "The Video Consortium", "employer_logo": "https://encrypted-tbn0.gstatic.com/images?q=tbn:ANd9GcQHCw4IKx7HB3fZ-1qyUuh-7_olmLv2pXZDawtL&s=0", "employer_website": null, "employer_company_type": null, "job_publisher": "LinkedIn", "job_employment_type": "FULLTIME", "job_title": "Director, Strategic Partnerships", "job_apply_link": "https://www.linkedin.com/jobs/view/director-strategic-partnerships-at-the-video-consortium-3854180579", "job_apply_is_direct": false, "job_apply_quality_score": 0.6418, "apply_options": [{"publisher": "LinkedIn", "apply_link": "https://www.linkedin.com/jobs/view/director-strategic-partnerships-at-the-video-consortium-3854180579", "is_direct": false}], "job_description": "The opening for this position is rolling (until the right fit is found), or until March 25th.\n\nThe Video Consortium, a global media organization that supports and connects today\u2019s documentary filmmakers and visual journalists, is seeking its first Director of Strategic Partnerships to join the team. In this exciting new role, the Director of Strategic Partnerships will build and implement the organization\u2019s foundational strategies around corporate sponsorships, business partnerships, and individual donor campaigns.\n\nThis person must come to VC with feet already deep in business development: with existing corporate relationships in their back pockets and a passionate, charismatic knack for \u201cthe art of the sale.\u201d They will be joining a fully remote and small yet extremely spirited core staff that runs the organization; they must be ready and excited to be part of a fast-paced and collaborative start-up environment. The right candidate has the opportunity to build this essential role from the ground up, all the while working alongside an inspiring and talented global community of storytellers who are pushing to catalyze social change.\n\nResponsibilities:\n\nBusiness Development + Corporate Sponsorships:\n\u2022 Develop marketing materials and strategies for VC as a whole\n\u2022 Deepen relationships with VC\u2019s existing partners and nurture new ones\n\u2022 Outreach and incubate new partnerships and corporate sponsorships that align with VC\u2019s mission, vision, and values\n\u2022 Coordinate with VC staff to implement partnership deliverables\n\u2022 Work with the Executive Director to identify and execute new development opportunities that benefit VC\u2019s creative community\n\nIndividual Donor Cultivation\n\u2022 Help oversee VC\u2019s major donor strategy, from directing related marketing communications to cultivating relationships with existing and, especially, new major donors\n\u2022 Manage event-focused community and donor activations (one-offs, at industry events/festivals) and envision innovative pathways to build upon already existing events.\n\nQualifications:\n\u2022 Minimum of 4 years of experience in business development/sales\n\u2022 A robust or growing rolodex of existing relationships with media-driven companies, and beyond\n\u2022 A proven ability to tell the story of a brand with confidence and charisma\n\u2022 Meticulous and nuanced written and oral communication skills\n\u2022 Excellent project management skills and extreme organizational abilities\n\u2022 A gift for pleasant persistence\n\u2022 A track record of innovation and successful sales/business development growth in previous positions\n\u2022 A deep passion for serving a greater purpose and a drive to contribute to and build infrastructure that supports a noble mission for decades to come.\n\nRole Specifics:\n\u2022 Reports to the Executive Director\n\u2022 Full-time (W2)\n\u2022 Salary: $70,000 to $74,000, based on experience\n\u2022 Fully remote and flexible work hours\n\u2022 We offer healthcare and home office stipends, as well as generous PTO and holiday schedules.\n\nPlease apply with:\n\u2022 Your resume / Linkedin\n\u2022 A cover letter specifically addressing previous sales experience and where you\u2019re looking to go in your career\n\u2022 5+ examples of partnerships made, sales landed, etc from past roles\n\nWe look forward to learning about you and your work!", "job_is_remote": true, "job_posted_at_timestamp": 1710255359, "job_posted_at_datetime_utc": "2024-03-12T14:55:59.000Z", "job_city": null, "job_state": null, "job_country": "US", "job_latitude": 37.09024, "job_longitude": -95.71289, "job_benefits": ["paid_time_off"], "job_google_link": "https://www.google.com/search?gl=us&hl=en&rciv=jb&q=vice+president+of+brand+partnerships&start=80&ibp=htl;jobs#fpstate=tldetail&htivrt=jobs&htiq=vice+president+of+brand+partnerships&htidocid=0y4sxU2ikjnaJ69wAAAAAA%3D%3D", "job_offer_expiration_datetime_utc": "2024-04-11T14:55:59.000Z", "job_offer_expiration_timestamp": 1712847359, "job_required_experience": {"no_experience_required": false, "required_experience_in_months": 48, "experience_mentioned": true, "experience_preferred": false}, "job_required_skills": ["Business Development", "Corporate Sponsorships", "Skill Development", "Sales", "Major Donor Cultivation", "Job Skills", "Self-confidence", "Communication", "Oral Communication", "Face-to-face Communication"], "job_required_education": {"postgraduate_degree": false, "professional_certification": false, "high_school": false, "associates_degree": false, "bachelors_degree": true, "degree_mentioned": false, "degree_preferred": false, "professional_certification_mentioned": false}, "job_experience_in_place_of_education": false, "job_min_salary": null, "job_max_salary": null, "job_salary_currency": null, "job_salary_period": null, "job_highlights": {"Qualifications": ["Minimum of 4 years of experience in business development/sales", "A robust or growing rolodex of existing relationships with media-driven companies, and beyond", "A proven ability to tell the story of a brand with confidence and charisma", "Meticulous and nuanced written and oral communication skills", "Excellent project management skills and extreme organizational abilities", "A gift for pleasant persistence", "A track record of innovation and successful sales/business development growth in previous positions", "A deep passion for serving a greater purpose and a drive to contribute to and build infrastructure that supports a noble mission for decades to come", "A cover letter specifically addressing previous sales experience and where you\u2019re looking to go in your career", "5+ examples of partnerships made, sales landed, etc from past roles"], "Responsibilities": ["In this exciting new role, the Director of Strategic Partnerships will build and implement the organization\u2019s foundational strategies around corporate sponsorships, business partnerships, and individual donor campaigns", "Develop marketing materials and strategies for VC as a whole", "Deepen relationships with VC\u2019s existing partners and nurture new ones", "Outreach and incubate new partnerships and corporate sponsorships that align with VC\u2019s mission, vision, and values", "Coordinate with VC staff to implement partnership deliverables", "Work with the Executive Director to identify and execute new development opportunities that benefit VC\u2019s creative community", "Individual Donor Cultivation", "Help oversee VC\u2019s major donor strategy, from directing related marketing communications to cultivating relationships with existing and, especially, new major donors", "Manage event-focused community and donor activations (one-offs, at industry events/festivals) and envision innovative pathways to build upon already existing events", "Reports to the Executive Director"], "Benefits": ["Salary: $70,000 to $74,000, based on experience", "Fully remote and flexible work hours", "We offer healthcare and home office stipends, as well as generous PTO and holiday schedules"]}, "job_job_title": "Director", "job_posting_language": "en", "job_onet_soc": "11202100", "job_onet_job_zone": "4"}