{"job_id": "PT0V_w3CH2wEp22VAAAAAA==", "employer_name": "Enchant", "employer_logo": "https://encrypted-tbn0.gstatic.com/images?q=tbn:ANd9GcTN5Hmzpj1zTPlLrQp2cgl-PbNVdLqi8J5y_q4G&s=0", "employer_website": null, "employer_company_type": null, "job_publisher": "LinkedIn", "job_employment_type": "FULLTIME", "job_title": "Senior Partnership Manager", "job_apply_link": "https://www.linkedin.com/jobs/view/senior-partnership-manager-at-enchant-3838754501", "job_apply_is_direct": false, "job_apply_quality_score": 0.6388, "apply_options": [{"publisher": "LinkedIn", "apply_link": "https://www.linkedin.com/jobs/view/senior-partnership-manager-at-enchant-3838754501", "is_direct": false}], "job_description": "Join forces with the finest team of marketing magic makers to lead the development and implementation of key partnerships for Enchant. This role is pivotal in aligning each venue with strategic partners to enhance the overall experience and drive ticket sales. Enchant\u2019s partnership efforts should increase market reach and community access to the event. Your primary responsibility is to curate and execute partnerships that resonate with our audience, creating unforgettable moments, and maximizing revenue opportunities. As such, you enjoy networking and building meaningful relationships.\n\nWHO WE ARE:\n\nWe are creators of a magical holiday experience called Enchant Christmas featuring the World\u2019s Largest Christmas Light Maze. We have hosted over 7+ million guests over the past 7 years and have experienced significant growth.\n\nWHAT YOU WILL BE ACCOUNTABLE FOR:\n\nStrategic Partnership Development:\n\u2022 Identify, develop, and nurture relationships with key partners aligning with target audience and brand values\n\u2022 Craft and propose unique partnership concepts for each event night, ensuring alignment with company theme and values\n\u2022 Execute a relevant strategic partnership plan for every partnership owned, ensuring partnership launches, maintenance, project timelines, event impact, and business results are achieved\n\nRevenue Generation:\n\u2022 Collaborate with partners to create mutually beneficial revenue-sharing models\n\u2022 Develop and implement strategies to maximize ticket sales through strategic partnerships\n\u2022 Work closely with Business Development team members to identify additional revenue streams through sponsorships and group sales opportunities\n\nEvent Integration:\n\u2022 Lead and oversee the collaboration with the Event Production team to seamlessly on-board local event producers to each partner activation on-site\n\u2022 Ensure all partner branding and messaging align with overall aesthetic and narrative, collaboration with Creative Services, Guest Services, and other relevant internal stakeholders\n\nTeam Leadership:\n\u2022 Manage a team of Partnership & Promotion Managers nationally and on the ground in the event markets, providing guidance, support, and leadership\n\u2022 Foster a collaborative and innovative team culture focused on achieving revenue targets and partnership\n\u2022 Research, recommend, attend/participate in appropriate regional, professional organizations or events to represent Enchant and extend our reach\n\nPerformance Analysis:\n\u2022 Track and analyze the performance of each partnership, providing regular reports to the Vice President of Marketing\n\u2022 Implement data-driven insights to optimize future partnerships and enhance overall event success.\n\nWHAT YOU BRING TO THE TEAM:\n\u2022 7+ years of relevant post-secondary education and experience in: Marketing, Communications, Business Development, Account Management or Client Relationship Management with a focus in strategic brand partnerships\n\u2022 Proven track record of successfully developing and executing strategic partnerships that drive revenue\n\u2022 Strong leadership skills with experience managing a team and multiple projects\n\u2022 Exceptional negotiation and communication skills\n\u2022 Creative thinker with the ability to conceptualize and implement unique ideas\n\u2022 Familiarity with the events and entertainment industry is a plus\n\u2022 Software skills required: Google Suite\n\u2022 Strong organizational skills and attention to detail\n\u2022 Ability to effectively collaborate with stakeholders across the company\n\u2022 A sincere desire to help create magical memories\n\u2022 Your own personal values are aligned with those of Enchant; Driven, Courageous, Sincere, Magical\n\nWHAT\u2019S IN IT FOR YOU:\n\u2022 Competitive Benefits Package\n\u2022 Remote work environment with team members spread out across the world\n\u2022 Flexibility on hours worked\n\u2022 The tools you need to get the job done well - personalized equipment package\n\u2022 We\u2019re a small yet mighty team so you\u2019ll have impact almost immediately\n\u2022 We\u2019re scaling! So, there\u2019s an opportunity to grow with us in whatever professional area you\u2019re looking to grow\n\u2022 Last but certainly not least, you\u2019re an integral part of creating Holiday traditions and creating magical memories! Plus free tickets to our Enchant events ;)\n\nAre you ready to join our team of magic makers? Apply today. We\u2019re excited to meet you!\n\nEnchant is an equal opportunity employer. We welcome members of all backgrounds and perspectives to apply. We\u2019re committed to continually developing and upholding an inclusive and diverse environment where every voice, perspective, and idea is heard. We embrace differences and know that our diverse team is our strength and what drives our innovation. Federal law requires all employers to verify the identity and employment eligibility of all persons hired to work in the United States, Enchant is an E-Verify participant.", "job_is_remote": true, "job_posted_at_timestamp": 1708716508, "job_posted_at_datetime_utc": "2024-02-23T19:28:28.000Z", "job_city": null, "job_state": null, "job_country": "US", "job_latitude": 37.09024, "job_longitude": -95.71289, "job_benefits": null, "job_google_link": "https://www.google.com/search?gl=us&hl=en&rciv=jb&q=senior+manager+of+brand+partnerships&start=30&ibp=htl;jobs#fpstate=tldetail&htivrt=jobs&htiq=senior+manager+of+brand+partnerships&htidocid=PT0V_w3CH2wEp22VAAAAAA%3D%3D", "job_offer_expiration_datetime_utc": "2024-08-21T19:28:28.000Z", "job_offer_expiration_timestamp": 1724268508, "job_required_experience": {"no_experience_required": false, "required_experience_in_months": 84, "experience_mentioned": true, "experience_preferred": false}, "job_required_skills": null, "job_required_education": {"postgraduate_degree": false, "professional_certification": false, "high_school": false, "associates_degree": false, "bachelors_degree": false, "degree_mentioned": false, "degree_preferred": false, "professional_certification_mentioned": false}, "job_experience_in_place_of_education": false, "job_min_salary": null, "job_max_salary": null, "job_salary_currency": null, "job_salary_period": null, "job_highlights": {"Qualifications": ["7+ years of relevant post-secondary education and experience in: Marketing, Communications, Business Development, Account Management or Client Relationship Management with a focus in strategic brand partnerships", "Proven track record of successfully developing and executing strategic partnerships that drive revenue", "Strong leadership skills with experience managing a team and multiple projects", "Exceptional negotiation and communication skills", "Creative thinker with the ability to conceptualize and implement unique ideas", "Software skills required: Google Suite", "Strong organizational skills and attention to detail", "Ability to effectively collaborate with stakeholders across the company", "A sincere desire to help create magical memories", "Your own personal values are aligned with those of Enchant; Driven, Courageous, Sincere, Magical"], "Responsibilities": ["This role is pivotal in aligning each venue with strategic partners to enhance the overall experience and drive ticket sales", "Enchant\u2019s partnership efforts should increase market reach and community access to the event", "Your primary responsibility is to curate and execute partnerships that resonate with our audience, creating unforgettable moments, and maximizing revenue opportunities", "Identify, develop, and nurture relationships with key partners aligning with target audience and brand values", "Craft and propose unique partnership concepts for each event night, ensuring alignment with company theme and values", "Execute a relevant strategic partnership plan for every partnership owned, ensuring partnership launches, maintenance, project timelines, event impact, and business results are achieved", "Collaborate with partners to create mutually beneficial revenue-sharing models", "Develop and implement strategies to maximize ticket sales through strategic partnerships", "Work closely with Business Development team members to identify additional revenue streams through sponsorships and group sales opportunities", "Lead and oversee the collaboration with the Event Production team to seamlessly on-board local event producers to each partner activation on-site", "Ensure all partner branding and messaging align with overall aesthetic and narrative, collaboration with Creative Services, Guest Services, and other relevant internal stakeholders", "Manage a team of Partnership & Promotion Managers nationally and on the ground in the event markets, providing guidance, support, and leadership", "Foster a collaborative and innovative team culture focused on achieving revenue targets and partnership", "Research, recommend, attend/participate in appropriate regional, professional organizations or events to represent Enchant and extend our reach", "Track and analyze the performance of each partnership, providing regular reports to the Vice President of Marketing", "Implement data-driven insights to optimize future partnerships and enhance overall event success"], "Benefits": ["Competitive Benefits Package", "Remote work environment with team members spread out across the world", "Flexibility on hours worked", "The tools you need to get the job done well - personalized equipment package", "We\u2019re a small yet mighty team so you\u2019ll have impact almost immediately", "Last but certainly not least, you\u2019re an integral part of creating Holiday traditions and creating magical memories!"]}, "job_job_title": "Manager", "job_posting_language": "en", "job_onet_soc": "11202100", "job_onet_job_zone": "4"}