{"job_id": "R2Jy_oRcKAkVFmKiAAAAAA==", "employer_name": "Carmel Christkindlmarkt, Inc.", "employer_logo": "https://encrypted-tbn0.gstatic.com/images?q=tbn:ANd9GcTgUQngYTnhatq3jdK-xIsAcwur_GKFQmMOORfY&s=0", "employer_website": null, "employer_company_type": null, "job_publisher": "LinkedIn", "job_employment_type": "FULLTIME", "job_title": "Director of Corporate Sponsorship", "job_apply_link": "https://www.linkedin.com/jobs/view/director-of-corporate-sponsorship-at-carmel-christkindlmarkt-inc-3850343810", "job_apply_is_direct": false, "job_apply_quality_score": 0.6393, "apply_options": [{"publisher": "LinkedIn", "apply_link": "https://www.linkedin.com/jobs/view/director-of-corporate-sponsorship-at-carmel-christkindlmarkt-inc-3850343810", "is_direct": false}], "job_description": "Carmel Christkindlmarkt - Director of Corporate Sponsorships\n\nCarmel Christkindlmarkt, Inc. is a 501(c)3 nonprofit organization. The primary mission of the organization\n\nis to create and host an authentic, traditional German Christmas festival - the Carmel Christkindlmarkt.\n\nThe festival has taken place for six years (2017-2023, skipping 2020 due to Covid-19), drawing 400,000+\n\nvisitors annually from mid-November through Christmas Eve. In 2019, 2021, 2022, and 2023 the Carmel\n\nChristkindlmarkt was voted the #1 Holiday Market in North America according to USAToday\u2019s 10Best\n\nReaders\u2019 Choice poll.\n\nThe mission of the Carmel Christkindlmarkt is supported by a small team of year-round\n\nstaff and seasonal staff members. Our organization highly values the ability of our team members to\n\nwork together, to adapt to changing circumstances, and to cultivate an atmosphere of shared success\n\nwhen engaging with each other, contract vendors, and guests of the Carmel Christkindlmarkt.\n\nJob title:\n\nDirector of Sponsorships\n\nJob type:\n\nFull-Time, W-2\n\nJob description:\n\nThe Director of Sponsorships is responsible for identifying and recruiting sponsors for the Market,\n\nscheduling tours of the Market with prospective sponsors, and serves as the main point of contact for\n\nthe VIP Soft Open event. This Director shepherds the sponsor relationships throughout the duration of\n\nthe Market, including overseeing the delivery of all sponsor commitments. The Director is responsible for\n\nall sponsor follow up, including reporting, recognition and renewals. The Director of Sponsorships\n\nreports to the CEO of the Carmel Christkindlmarkt and works closely with them regarding all sponsor\n\nrelationships.\n\nKey responsibilities include creating sponsorship proposals, selling sponsorship opportunities to local\n\nbusinesses, planning and executing sponsorship activation components, facilitating internal and external\n\ncommunications, and effectively tracking/measuring sponsorship initiatives.\n\nJob duties:\n\u2022 Plan, direct, and/or coordinate activities to solicit and maintain funds for special projects and\n\u2022 Organization.\n\u2022 Ensure that Sponsors align with the mission and vision of the Organization\n\u2022 Work with Management Team to ensure alignment\n\u2022 Work with VP of Communications to ensure that Sponsor deliverables are appropriate\n\u2022 for scale of sponsorship\n\u2022 Work with VP of Cultural Programs to develop community partnerships\n\u2022 Work with the Market CEO to recruit sponsors for the Carmel Christkindlmarkt, beginning with\n\u2022 renewing and/or upgrading existing relationships established during prior Markets and\n\u2022 expanding to include new partnerships\n\u2022 Manage sponsor relationships from start to finish\n\u2022 This includes identifying new sponsors, bringing them to the Market, negotiating\n\u2022 sponsorship contracts, communicating required sponsorship agreements/deliverables to\n\u2022 relevant Market staff members, and ensuring all needed sponsorship reporting is\n\u2022 completed\n\u2022 Includes meeting with prospective sponsors, negotiating contract details through CEO\n\u2022 signature, invoicing, and following up on all commitments\n\u2022 Create and maintain all relevant records regarding the sales process through CRM\n\u2022 This includes prospect lists, contact records, details of all complete and incomplete sales\n\u2022 opportunities\n\u2022 Attend all key Market events and activities throughout the Market dates that are meaningful to\n\u2022 the sponsors\n\u2022 Work closely with the VP of Communications to ensure all sponsor needs are met in Market\n\u2022 marketing\n\u2022 This includes social media needs, inclusion in the Carmel Christkindlmarkt newsletter,\n\u2022 logo inclusion on signage, etc.\n\u2022 Execute all post-Market sponsor follow up, including reporting and renewals\n\u2022 Develop grant writing program\n\u2022 Develop appropriate and comprehensive Sponsorship Packets (Overall Market, Gl\u00fchwein Gallop,\n\u2022 and VIP Soft Open)\n\u2022 Determining range of sponsorship levels\n\u2022 Working with CEO & VP of Communications to develop consistent sponsor recruitment\n\u2022 strategies and marketing collateral\n\u2022 Serve as main point of contact for Event Planner with regard to VIP Soft Open event\n\u2022 Work closely with CEO to create invitation list and identify potential Sponsors\n\u2022 Work closely with VP of Communications for all marketing collateral\n\u2022 Keep CKM Team up-to-date with planning needs and day-of roles\n\u2022 Manages budget for event\n\u2022 This position is remote during the off season, with on-site requirements during the Market\u2019s\n\u2022 open season (November-December)\n\u2022 Oversees Private Rental Administrator and Volunteer/Guest Services Coordinator\n\u2022 Other duties as assigned\n\nQualifications:\n\u2022 2+ years of experience in selling and managing sponsorship relationships\n\u2022 Ability to work within Google Products and Microsoft Office Suite\n\u2022 Proven ability to take initiative and work independently\n\u2022 Desired skills include: Effective Communication; Leadership Experience; Team Management;\n\u2022 Research\n\u2022 Ability to coordinate through conflict and problem-solve issues to resolution\n\u2022 Ability to adapt to change, establish relationships, and work in a team environment\n\u2022 Willingness to work in cold temperatures, predominantly standing an\n\nHow to apply:\n\nTo apply, email your resume and cover letter to Staffing@CarmelChristkindlmarkt.com, and please\n\ninclude (3) professional references.", "job_is_remote": false, "job_posted_at_timestamp": 1709905934, "job_posted_at_datetime_utc": "2024-03-08T13:52:14.000Z", "job_city": "Carmel", "job_state": "IN", "job_country": "US", "job_latitude": 39.97837, "job_longitude": -86.11804, "job_benefits": null, "job_google_link": "https://www.google.com/search?gl=us&hl=en&rciv=jb&q=sponsorship+sales+director&start=10&ibp=htl;jobs#fpstate=tldetail&htivrt=jobs&htiq=sponsorship+sales+director&htidocid=R2Jy_oRcKAkVFmKiAAAAAA%3D%3D", "job_offer_expiration_datetime_utc": "2024-04-07T13:52:14.000Z", "job_offer_expiration_timestamp": 1712497934, "job_required_experience": {"no_experience_required": false, "required_experience_in_months": 24, "experience_mentioned": true, "experience_preferred": false}, "job_required_skills": ["Corporate Sponsorships", "Sponsorship Activation", "Relationship Development", "Service Work", "Initiation", "Grant Writing", "Contract Negotiation"], "job_required_education": {"postgraduate_degree": false, "professional_certification": false, "high_school": false, "associates_degree": false, "bachelors_degree": true, "degree_mentioned": false, "degree_preferred": false, "professional_certification_mentioned": false}, "job_experience_in_place_of_education": false, "job_min_salary": null, "job_max_salary": null, "job_salary_currency": null, "job_salary_period": null, "job_highlights": {"Qualifications": ["2+ years of experience in selling and managing sponsorship relationships", "Ability to work within Google Products and Microsoft Office Suite", "Proven ability to take initiative and work independently", "Ability to coordinate through conflict and problem-solve issues to resolution", "Ability to adapt to change, establish relationships, and work in a team environment", "Willingness to work in cold temperatures, predominantly standing an"], "Responsibilities": ["is to create and host an authentic, traditional German Christmas festival - the Carmel Christkindlmarkt", "when engaging with each other, contract vendors, and guests of the Carmel Christkindlmarkt", "The Director of Sponsorships is responsible for identifying and recruiting sponsors for the Market,", "scheduling tours of the Market with prospective sponsors, and serves as the main point of contact for", "the Market, including overseeing the delivery of all sponsor commitments", "reports to the CEO of the Carmel Christkindlmarkt and works closely with them regarding all sponsor", "Key responsibilities include creating sponsorship proposals, selling sponsorship opportunities to local", "businesses, planning and executing sponsorship activation components, facilitating internal and external", "communications, and effectively tracking/measuring sponsorship initiatives", "Plan, direct, and/or coordinate activities to solicit and maintain funds for special projects and", "Ensure that Sponsors align with the mission and vision of the Organization", "Work with Management Team to ensure alignment", "Work with VP of Communications to ensure that Sponsor deliverables are appropriate", "for scale of sponsorship", "Work with VP of Cultural Programs to develop community partnerships", "Work with the Market CEO to recruit sponsors for the Carmel Christkindlmarkt, beginning with", "renewing and/or upgrading existing relationships established during prior Markets and", "expanding to include new partnerships", "Manage sponsor relationships from start to finish", "This includes identifying new sponsors, bringing them to the Market, negotiating", "sponsorship contracts, communicating required sponsorship agreements/deliverables to", "relevant Market staff members, and ensuring all needed sponsorship reporting is", "Includes meeting with prospective sponsors, negotiating contract details through CEO", "signature, invoicing, and following up on all commitments", "Create and maintain all relevant records regarding the sales process through CRM", "This includes prospect lists, contact records, details of all complete and incomplete sales", "Attend all key Market events and activities throughout the Market dates that are meaningful to", "Work closely with the VP of Communications to ensure all sponsor needs are met in Market", "This includes social media needs, inclusion in the Carmel Christkindlmarkt newsletter,", "logo inclusion on signage, etc", "Execute all post-Market sponsor follow up, including reporting and renewals", "Develop grant writing program", "Develop appropriate and comprehensive Sponsorship Packets (Overall Market, Gl\u00fchwein Gallop,", "Determining range of sponsorship levels", "Working with CEO & VP of Communications to develop consistent sponsor recruitment", "strategies and marketing collateral", "Serve as main point of contact for Event Planner with regard to VIP Soft Open event", "Work closely with CEO to create invitation list and identify potential Sponsors", "Keep CKM Team up-to-date with planning needs and day-of roles", "Manages budget for event", "This position is remote during the off season, with on-site requirements during the Market\u2019s", "open season (November-December)", "Oversees Private Rental Administrator and Volunteer/Guest Services Coordinator", "Other duties as assigned"]}, "job_job_title": null, "job_posting_language": "en", "job_onet_soc": "11202100", "job_onet_job_zone": "4"}