{"job_id": "87K6lpzsjObl2W9wAAAAAA==", "employer_name": "FORWARD", "employer_logo": null, "employer_website": null, "employer_company_type": null, "job_publisher": "Smart Recruiters Jobs", "job_employment_type": "FULLTIME", "job_title": "Director, Business Development - Government", "job_apply_link": "https://jobs.smartrecruiters.com/FORWARD/743999914223926-director-business-development-government", "job_apply_is_direct": false, "job_apply_quality_score": 0.7325, "apply_options": [{"publisher": "Smart Recruiters Jobs", "apply_link": "https://jobs.smartrecruiters.com/FORWARD/743999914223926-director-business-development-government", "is_direct": false}, {"publisher": "Talent.com", "apply_link": "https://www.talent.com/view?id=d1a1aa8b0e36", "is_direct": false}], "job_description": "Company Description\n\nFORWARD is a venture-backed company on a mission to build comprehensive solutions allowing governments to assist their communities at scale.\n\nThe FORWARD Platform is an Integrated Program Administration solution that incorporates all essential components, people, and technology into a single streamlined workflow to effectively, securely, and equitably administer critical resources to help communities thrive.\n\nMunicipalities nationwide are utilizing FORWARD to streamline the design, implementation, operations, communications, reporting, and compliance functions of their economic and community development assistance programs.\n\nOur fully remote team works hard, but we fully embrace the advantages of this new paradigm. We work autonomously, collaborate asynchronously, and take ownership of our work.\n\nJob Description\n\nPosition Summary\n\nAs the Director of Business Development, you will be the head of our business development team and will be responsible for leading and driving their success. You will identify new market segments, develop comprehensive go-to-market strategies, and oversee the execution of these strategies. Additionally, you will hire, supervise, and mentor a high-performing team, setting aggressive sales goals and supporting team members in achieving them.\n\nResponsibilities\n\u2022 Lead the business development team by providing clear direction, guidance, and support to ensure the achievement of sales goals.\n\u2022 Identify new market segments and assess their potential for growth, working closely with the team to develop targeted strategies.\n\u2022 Develop and execute comprehensive go-to-market strategies for new products, ensuring alignment with company objectives.\n\u2022 Plan, execute, and manage GTM experiments to validate assumptions and optimize market entry strategies.\n\u2022 Build and nurture co-selling opportunities through the establishment of strategic partnerships and alliances.\n\u2022 Hire, train, and supervise a high-performing business development team, fostering a culture of collaboration, continuous improvement, and excellence.\n\u2022 Set aggressive sales goals for the team and track progress, providing coaching and support to team members to help them achieve targets.\n\u2022 Collaborate closely with the team, providing insights, strategies, and support for targeting specific customer segments.\n\u2022 Regularly interact with the team to foster collaboration, exchange feedback, and make adjustments based on market realities.\n\u2022 Leverage customer behavior data, market trends, and analytics to gain actionable insights that inform go-to-market strategies and experiments.\n\u2022 Monitor industry trends, competitive landscape, and regulatory changes to identify opportunities and risks.\n\nQualifications\n\u2022 Minimum of 10-15 years of proven experience in business development, strategic planning, or a related role, preferably within the B2G or Non-Profit industry.\n\u2022 Strong knowledge and understanding of the B2G market, including government procurement processes and regulations.\n\u2022 Demonstrated success in developing and executing go-to-market strategies that resulted in revenue growth.\n\u2022 Excellent analytical skills and the ability to leverage data and analytics to inform decision-making.\n\u2022 Exceptional communication and presentation skills, with the ability to effectively convey complex concepts to both internal and external stakeholders.\n\u2022 Strong leadership abilities, with a proven track record of building and managing high-performing teams.\n\u2022 Strategic mindset and the ability to think critically and make informed decisions.\n\u2022 Familiarity with emerging technologies and trends in the B2G space.\n\u2022 Eager to be part of a team that puts a premium on assuming best intentions and giving one another grace\n\nAdditional Information\n\nWe are an equal opportunity employer and value diversity at our company. We do not discriminate on the basis of race, religion, color, national origin, gender, sexual orientation, age, marital status, veteran status, or disability status.\n\nWe offer a full range of employee benefits for our regular full-time employees including:\n\u2022 Fully remote position\n\u2022 Unlimited PTO\n\u2022 100% Employee paid medical and dental insurance\n\u2022 Stock Options\n\u2022 401K Plan", "job_is_remote": false, "job_posted_at_timestamp": 1687366501, "job_posted_at_datetime_utc": "2023-06-21T16:55:01.000Z", "job_city": "Seattle", "job_state": "WA", "job_country": "US", "job_latitude": 47.60614, "job_longitude": -122.33285, "job_benefits": ["paid_time_off", "dental_coverage", "health_insurance", "retirement_savings"], "job_google_link": "https://www.google.com/search?gl=us&hl=en&rciv=jb&q=manager+of+business+development&start=60&ibp=htl;jobs#fpstate=tldetail&htivrt=jobs&htiq=manager+of+business+development&htidocid=87K6lpzsjObl2W9wAAAAAA%3D%3D", "job_offer_expiration_datetime_utc": null, "job_offer_expiration_timestamp": null, "job_required_experience": {"no_experience_required": false, "required_experience_in_months": 120, "experience_mentioned": true, "experience_preferred": false}, "job_required_skills": null, "job_required_education": {"postgraduate_degree": false, "professional_certification": false, "high_school": false, "associates_degree": false, "bachelors_degree": false, "degree_mentioned": false, "degree_preferred": false, "professional_certification_mentioned": false}, "job_experience_in_place_of_education": false, "job_min_salary": null, "job_max_salary": null, "job_salary_currency": null, "job_salary_period": null, "job_highlights": {"Qualifications": ["Minimum of 10-15 years of proven experience in business development, strategic planning, or a related role, preferably within the B2G or Non-Profit industry", "Strong knowledge and understanding of the B2G market, including government procurement processes and regulations", "Demonstrated success in developing and executing go-to-market strategies that resulted in revenue growth", "Excellent analytical skills and the ability to leverage data and analytics to inform decision-making", "Exceptional communication and presentation skills, with the ability to effectively convey complex concepts to both internal and external stakeholders", "Strong leadership abilities, with a proven track record of building and managing high-performing teams", "Strategic mindset and the ability to think critically and make informed decisions", "Familiarity with emerging technologies and trends in the B2G space", "Eager to be part of a team that puts a premium on assuming best intentions and giving one another grace"], "Responsibilities": ["As the Director of Business Development, you will be the head of our business development team and will be responsible for leading and driving their success", "You will identify new market segments, develop comprehensive go-to-market strategies, and oversee the execution of these strategies", "Additionally, you will hire, supervise, and mentor a high-performing team, setting aggressive sales goals and supporting team members in achieving them", "Lead the business development team by providing clear direction, guidance, and support to ensure the achievement of sales goals", "Identify new market segments and assess their potential for growth, working closely with the team to develop targeted strategies", "Develop and execute comprehensive go-to-market strategies for new products, ensuring alignment with company objectives", "Plan, execute, and manage GTM experiments to validate assumptions and optimize market entry strategies", "Build and nurture co-selling opportunities through the establishment of strategic partnerships and alliances", "Hire, train, and supervise a high-performing business development team, fostering a culture of collaboration, continuous improvement, and excellence", "Set aggressive sales goals for the team and track progress, providing coaching and support to team members to help them achieve targets", "Collaborate closely with the team, providing insights, strategies, and support for targeting specific customer segments", "Regularly interact with the team to foster collaboration, exchange feedback, and make adjustments based on market realities", "Leverage customer behavior data, market trends, and analytics to gain actionable insights that inform go-to-market strategies and experiments", "Monitor industry trends, competitive landscape, and regulatory changes to identify opportunities and risks"], "Benefits": ["Fully remote position", "Unlimited PTO", "100% Employee paid medical and dental insurance", "Stock Options", "401K Plan"]}, "job_job_title": "Director", "job_posting_language": "en", "job_onet_soc": "11202100", "job_onet_job_zone": "4"}