{"job_id": "HfRgh-r8O1RInDNPAAAAAA==", "employer_name": "TaxRise", "employer_logo": null, "employer_website": null, "employer_company_type": null, "job_publisher": "Jooble", "job_employment_type": "FULLTIME", "job_title": "Sales Training Specialist", "job_apply_link": "https://jooble.org/jdp/-6253847499909567891", "job_apply_is_direct": false, "job_apply_quality_score": 0.462, "apply_options": [{"publisher": "Jooble", "apply_link": "https://jooble.org/jdp/-6253847499909567891", "is_direct": false}], "job_description": "INTRO TO TAXRISE:\n\nAt TaxRise, our mission is simple yet impactful: to revolutionize the way taxpayers navigate their tax challenges. We believe in the power of lifting others up, and that's the driving force behind everything we do.\n\nWhen you join us, you're not just becoming part of a company; you're joining a movement. We're a team that thrives on celebrating successes and making a genuine impact on people's lives. We're proud to be the fastest-growing company in our industry, and we're on the lookout for exceptional individuals to help us continue our journey of transformation.\n\nIf you're ready to bring your unique talents and innovative spirit to a company where your work truly matters, TaxRise is the place to be. Join us and be part of a team that\u2019s reshaping the future of tax resolution.\n\nABOUT THE ROLE:\n\nThe Sales Training Specialist is responsible for developing and delivering an engaging sales training program educating new team members on the various tax resolution programs available under the IRS Fresh Start Program, familiarizing them with the consultation process, and how to enroll new clients. This position actively searches, creatively designs, and implements effective methods to educate and enhance sales performance. This role is for a strong team player who loves bringing ideas to the table, shares best practices, has a passion for developing others and possesses an engaging and energetic presence in the training room and sales floor.\n\nWHAT YOU\u2019LL DO:\n\u2022 Develop comprehensive training materials and resources on different types of tax resolution programs offered under the IRS Fresh Start Program.\n\u2022 Conduct engaging and interactive training sessions for new employees to ensure they have a thorough understanding of tax resolution strategies, processes, and compliance requirements.\n\u2022 Conduct training sessions utilizing a combination of learning methods such as in-classroom, hands-on system walkthroughs, job shadowing, and role playing.\n\u2022 Conduct engaging and interactive training sessions for new employees to ensure they have a thorough understanding of tax resolution strategies, processes, and compliance requirements.\n\u2022 Provide hands-on training to new employees utilizing Salesforce for interview intake procedures, including client data entry, properly entering consultation notes in Salesforce, uploading documentation and executing signed agreements.\n\u2022 Coach new employees on effectively utilizing sales techniques, ethical selling practices, and leveraging scripts to enroll new clients.\n\u2022 Collaborate with sales management to customize training programs based on evolving business needs and sales goals.\n\u2022 Monitor and evaluate the performance of trainees, providing constructive feedback and support to facilitate their professional development.\n\u2022 Provide regular updates to leadership regarding progress of newly hired employees receiving training.\n\u2022 Become a subject matter expert (SME) in all sales procedures to support the entire operations of the team, serving as a go-to resource for clarifications, guidance, and best practices for new team members.\n\u2022 Provide ongoing support and resources to employees, including refresher courses, skill development workshops, and access to learning materials.\n\u2022 Manage workload by setting priorities, allocating resources, and overcoming challenges to ensure delivery on time and on budget.\n\u2022 Other duties and responsibilities as assigned by management.\n\nWHAT YOU\u2019LL NEED TO HAVE:\n\nTo perform this job successfully, an individual must be able to perform each essential duty satisfactorily. The requirements listed below are representative of the knowledge, skill, and/or ability required.\n\u2022 Proficient experience in various CRM systems such as Salesforce.\n\u2022 Knowledge of adult learning principles and training methods.\n\u2022 Ability to motivate, engage and develop new team members into sales professionals.\n\u2022 Ability to build trusting relationships and influenced at senior levels.\n\u2022 Ability to balance competing priorities in a fast-paced working environment.\n\u2022 Ability to relate your work with business outcomes and how work aligns across business functions.\n\u2022 Excellent written and oral communication skills, including presentation and facilitation skills and the ability to effectively communicate with employees of all levels.\n\u2022 Detail orientated and commitment to a high degree of accuracy.\n\u2022 Comfortable working in a high-energy, quickly changing, and demanding environment.\n\u2022 Have a high level of interpersonal skills, emotional intelligence, and be trustworthy to a broad range of stakeholders.\n\u2022 Motivated self-starter with a passion for coaching and developing others.\n\u2022 Proficient Microsoft Office Suites, Google Gmail, Calendar and internal communication software.\n\u2022 Minimum 5 years\u2019 experience delivering sales training, preferably in financial services, consumer lending or tax industry.\n\nWe understand potential comes in many forms. Even if you don\u2019t check every box, we still encourage you to apply; we consider all qualified candidates.\n\nWHAT WE OFFER:\n\u2022 Medical, Dental, Vision and other auxiliary benefits after 60 days\n\u2022 401(k) retirement\n\u2022 Professional Development Program\n\u2022 Catered meals every Friday\n\u2022 Quarterly company outings\n\u2022 Fun, energetic and inclusive culture\n\u2022 On-site gym\n\u2022 Access to game room\n\nSALARY: $80,000 - $90,000 annual salary\n\nThe above-range represents TaxRise\u2019s current good-faith pay scale for this role. TaxRise reserves the right to modify or update this range at any time.\n\nAt TaxRise, we\u2019re proud to be an equal opportunity employer. We realize the key to creating a company with world-class culture and employee experience comes from who we hire and creating a workplace that celebrates everyone.\n\nWe provide equal employment opportunities (EEO) to all without regard to race, color, religion (including religious dress and grooming practices), sex (including pregnancy, childbirth and related medical conditions, breastfeeding, and conditions related to breastfeeding), gender, gender identity, gender expression, national origin, ancestry, age (40 or over), physical or medical disability, medical condition, marital status, registered domestic partner status, sexual orientation, genetic information, military and/or veteran status, or any other basis prohibited by applicable state or federal law.\n\nTaxRise is also committed to ensuring equal opportunity in employment for qualified persons with disabilities. If you require any reasonable accommodation throughout the recruiting process, please let your recruiter know.", "job_is_remote": false, "job_posted_at_timestamp": 1709342687, "job_posted_at_datetime_utc": "2024-03-02T01:24:47.000Z", "job_city": null, "job_state": null, "job_country": "US", "job_latitude": 62.41136, "job_longitude": -149.07297, "job_benefits": ["retirement_savings", "dental_coverage", "health_insurance"], "job_google_link": "https://www.google.com/search?gl=us&hl=en&rciv=jb&q=manager+of+sales+training&start=40&ibp=htl;jobs#fpstate=tldetail&htivrt=jobs&htiq=manager+of+sales+training&htidocid=HfRgh-r8O1RInDNPAAAAAA%3D%3D", "job_offer_expiration_datetime_utc": "2024-04-02T14:59:28.000Z", "job_offer_expiration_timestamp": 1712069968, "job_required_experience": {"no_experience_required": false, "required_experience_in_months": 60, "experience_mentioned": true, "experience_preferred": false}, "job_required_skills": null, "job_required_education": {"postgraduate_degree": false, "professional_certification": false, "high_school": false, "associates_degree": false, "bachelors_degree": false, "degree_mentioned": false, "degree_preferred": false, "professional_certification_mentioned": false}, "job_experience_in_place_of_education": false, "job_min_salary": null, "job_max_salary": null, "job_salary_currency": null, "job_salary_period": null, "job_highlights": {"Qualifications": ["To perform this job successfully, an individual must be able to perform each essential duty satisfactorily", "Proficient experience in various CRM systems such as Salesforce", "Knowledge of adult learning principles and training methods", "Ability to motivate, engage and develop new team members into sales professionals", "Ability to build trusting relationships and influenced at senior levels", "Ability to balance competing priorities in a fast-paced working environment", "Ability to relate your work with business outcomes and how work aligns across business functions", "Excellent written and oral communication skills, including presentation and facilitation skills and the ability to effectively communicate with employees of all levels", "Detail orientated and commitment to a high degree of accuracy", "Comfortable working in a high-energy, quickly changing, and demanding environment", "Have a high level of interpersonal skills, emotional intelligence, and be trustworthy to a broad range of stakeholders", "Motivated self-starter with a passion for coaching and developing others", "Proficient Microsoft Office Suites, Google Gmail, Calendar and internal communication software", "Minimum 5 years\u2019 experience delivering sales training, preferably in financial services, consumer lending or tax industry"], "Responsibilities": ["The Sales Training Specialist is responsible for developing and delivering an engaging sales training program educating new team members on the various tax resolution programs available under the IRS Fresh Start Program, familiarizing them with the consultation process, and how to enroll new clients", "This position actively searches, creatively designs, and implements effective methods to educate and enhance sales performance", "This role is for a strong team player who loves bringing ideas to the table, shares best practices, has a passion for developing others and possesses an engaging and energetic presence in the training room and sales floor", "Develop comprehensive training materials and resources on different types of tax resolution programs offered under the IRS Fresh Start Program", "Conduct engaging and interactive training sessions for new employees to ensure they have a thorough understanding of tax resolution strategies, processes, and compliance requirements", "Conduct training sessions utilizing a combination of learning methods such as in-classroom, hands-on system walkthroughs, job shadowing, and role playing", "Provide hands-on training to new employees utilizing Salesforce for interview intake procedures, including client data entry, properly entering consultation notes in Salesforce, uploading documentation and executing signed agreements", "Coach new employees on effectively utilizing sales techniques, ethical selling practices, and leveraging scripts to enroll new clients", "Collaborate with sales management to customize training programs based on evolving business needs and sales goals", "Monitor and evaluate the performance of trainees, providing constructive feedback and support to facilitate their professional development", "Provide regular updates to leadership regarding progress of newly hired employees receiving training", "Become a subject matter expert (SME) in all sales procedures to support the entire operations of the team, serving as a go-to resource for clarifications, guidance, and best practices for new team members", "Provide ongoing support and resources to employees, including refresher courses, skill development workshops, and access to learning materials", "Manage workload by setting priorities, allocating resources, and overcoming challenges to ensure delivery on time and on budget", "Other duties and responsibilities as assigned by management"], "Benefits": ["Medical, Dental, Vision and other auxiliary benefits after 60 days", "401(k) retirement", "Professional Development Program", "Catered meals every Friday", "Quarterly company outings", "Fun, energetic and inclusive culture", "On-site gym", "Access to game room", "SALARY: $80,000 - $90,000 annual salary", "The above-range represents TaxRise\u2019s current good-faith pay scale for this role"]}, "job_job_title": "Training specialist", "job_posting_language": "en", "job_onet_soc": "13115100", "job_onet_job_zone": "4"}