{"job_id": "vx9YVdOmVnhzVCCXAAAAAA==", "employer_name": "OCTANE", "employer_logo": null, "employer_website": null, "employer_company_type": null, "job_publisher": "Indeed", "job_employment_type": "FULLTIME", "job_title": "Events Sponsorship Sales Manager", "job_apply_link": "https://www.indeed.com/viewjob?jk=848c944b48e2e220", "job_apply_is_direct": true, "job_apply_quality_score": 0.6082, "apply_options": [{"publisher": "Indeed", "apply_link": "https://www.indeed.com/viewjob?jk=848c944b48e2e220", "is_direct": true}], "job_description": "Job Posting\nEvents Sponsorship Sales Manager\n\nPosition Title: Events Sponsorship Sales Manager\nTime Requirement: Full-Time\nLocation: Aliso Viejo, CA\n\nOctane convenes and enables the Southern California tech and medtech business ecosystem by connecting people, resources and capital. We will help create 55,000+ high- paying technology jobs in Southern California by 2030 through our five Annual Signature\nEvents, LaunchPad SBDC accelerator, as well as our Octane Enterprise Solutions (OES) business.\n\nThe Octane Events Sponsorship Sales Manager will be responsible for managing relationships and generating revenue within Octane\u2019s signature events, directly supporting the Director of Partner Relations and working closely with the Events and Marketing teams.\n\nEssential functions include:\n\u2022 Sell event sponsorships for Octane\u2019s Tech Innovation Forum and other Octane\n\nSignature Events\n\u2022 Responsible for achieving annual sales goals, including weekly reporting\n\u2022 Cultivate relationships with partners and sponsors\n\u2022 Research net new sales pipeline opportunities utilizing ZoomInfo\n\u2022 Create, develop and manage a sales pipeline through Salesforce\n\u2022 Responsible for on-site sponsorship management at Octane events\n\u2022 Collaborate with Marketing and the Event Manager to generate sponsorship, lead generation and to ensure sponsor commitments are executed\n\u2022 Provide sales support for the Director of Partner Relations, including Annual\n\nPartnerships\n\u2022 Demonstrate leadership in promoting Octane values and commitment to customer service\n\u2022 Other duties as assigned\n\nKnowledge, Skill and Experience:\n\nMinimum Education (or substitute experience) required:\n\u2022 Bachelor\u2019s degree\n\nMinimum Experience required:\n\u2022 Minimum 3-5 years of experience with corporate event sales with a proven track\n\nJob Posting\n\nEvents Sponsorship Sales Manager record of revenue generation and pipeline management\n\u2022 Experience working with key decision makers in a B2B environment\n\u2022 Experience working in a team environment, including cross-functional collaboration\n\nSkills Required:\n\u2022 Engaging presentation skills (oral and written) for communication to all levels in the sales cycle\n\u2022 Ability to rapidly ramp up and understand and articulate the organization\u2019s offerings\n\u2022 Management of a sales pipeline in a CRM, Salesforce preferred\n\u2022 Strong organization skills\n\u2022 Keen ability to prioritize, manage multiple projects, and maintain high productivity levels at all times\n\u2022 Apply critical thinking skills to solve problems and contribute to goals\n\u2022 Strong contributor in collaborative, team environments\n\u2022 Demonstrate acute attention to detail\n\u2022 Self-starter, ability to recognize gaps and opportunities, shows initiative\n\u2022 Deliver a high quality of work output\n\u2022 Demonstrate leadership skills, including personal and professional leadership in every role you assume\n\u2022 Strong capabilities with Microsoft Office, including Excel, Word and Pitch\n\nAbout Octane:\nMore information is available online at www.octaneoc.org.\n\nJob Type: Full-time\n\nPay: $30,000.00 - $98,000.00 per year\n\nBenefits:\n\u2022 401(k)\n\u2022 Dental insurance\n\u2022 Flexible schedule\n\u2022 Health insurance\n\u2022 Paid time off\n\u2022 Vision insurance\n\nSchedule:\n\u2022 Monday to Friday\n\nSupplemental pay types:\n\u2022 Bonus pay\n\nWork Location: In person", "job_is_remote": false, "job_posted_at_timestamp": 1638569766, "job_posted_at_datetime_utc": "2021-12-03T22:16:06.000Z", "job_city": "Aliso Viejo", "job_state": "CA", "job_country": "US", "job_latitude": 33.568462, "job_longitude": -117.726295, "job_benefits": ["dental_coverage", "health_insurance", "paid_time_off", "retirement_savings"], "job_google_link": "https://www.google.com/search?gl=us&hl=en&rciv=jb&q=sponsorship+sales+director&start=20&ibp=htl;jobs#fpstate=tldetail&htivrt=jobs&htiq=sponsorship+sales+director&htidocid=vx9YVdOmVnhzVCCXAAAAAA%3D%3D", "job_offer_expiration_datetime_utc": null, "job_offer_expiration_timestamp": null, "job_required_experience": {"no_experience_required": false, "required_experience_in_months": 36, "experience_mentioned": true, "experience_preferred": false}, "job_required_skills": null, "job_required_education": {"postgraduate_degree": false, "professional_certification": false, "high_school": false, "associates_degree": false, "bachelors_degree": false, "degree_mentioned": true, "degree_preferred": false, "professional_certification_mentioned": false}, "job_experience_in_place_of_education": false, "job_min_salary": 30000, "job_max_salary": 98000, "job_salary_currency": "USD", "job_salary_period": "YEAR", "job_highlights": {"Qualifications": ["Bachelor\u2019s degree", "Minimum 3-5 years of experience with corporate event sales with a proven track", "Experience working with key decision makers in a B2B environment", "Experience working in a team environment, including cross-functional collaboration", "Engaging presentation skills (oral and written) for communication to all levels in the sales cycle", "Ability to rapidly ramp up and understand and articulate the organization\u2019s offerings", "Strong organization skills", "Keen ability to prioritize, manage multiple projects, and maintain high productivity levels at all times", "Apply critical thinking skills to solve problems and contribute to goals", "Strong contributor in collaborative, team environments", "Demonstrate acute attention to detail", "Self-starter, ability to recognize gaps and opportunities, shows initiative", "Deliver a high quality of work output", "Demonstrate leadership skills, including personal and professional leadership in every role you assume", "Strong capabilities with Microsoft Office, including Excel, Word and Pitch"], "Responsibilities": ["The Octane Events Sponsorship Sales Manager will be responsible for managing relationships and generating revenue within Octane\u2019s signature events, directly supporting the Director of Partner Relations and working closely with the Events and Marketing teams", "Sell event sponsorships for Octane\u2019s Tech Innovation Forum and other Octane", "Responsible for achieving annual sales goals, including weekly reporting", "Cultivate relationships with partners and sponsors", "Research net new sales pipeline opportunities utilizing ZoomInfo", "Create, develop and manage a sales pipeline through Salesforce", "Collaborate with Marketing and the Event Manager to generate sponsorship, lead generation and to ensure sponsor commitments are executed", "Provide sales support for the Director of Partner Relations, including Annual", "Demonstrate leadership in promoting Octane values and commitment to customer service", "Events Sponsorship Sales Manager record of revenue generation and pipeline management"], "Benefits": ["Pay: $30,000.00 - $98,000.00 per year", "401(k)", "Dental insurance", "Flexible schedule", "Health insurance", "Paid time off", "Vision insurance", "Monday to Friday", "Bonus pay"]}, "job_job_title": "Sales manager", "job_posting_language": "en", "job_onet_soc": "13112100", "job_onet_job_zone": "4"}