{"job_id": "2gQ0cVx93zltIOKrAAAAAA==", "employer_name": "Connect Life Science", "employer_logo": null, "employer_website": null, "employer_company_type": null, "job_publisher": "Glassdoor", "job_employment_type": "FULLTIME", "job_title": "Sales Manager", "job_apply_link": "https://www.glassdoor.com/job-listing/sales-manager-connect-life-science-JV_IC1153447_KO0,13_KE14,34.htm?jl=1009127951702", "job_apply_is_direct": true, "job_apply_quality_score": 0.6399, "apply_options": [{"publisher": "Glassdoor", "apply_link": "https://www.glassdoor.com/job-listing/sales-manager-connect-life-science-JV_IC1153447_KO0,13_KE14,34.htm?jl=1009127951702", "is_direct": true}, {"publisher": "Indeed", "apply_link": "https://www.indeed.com/viewjob?jk=670ce4a1fcebed04", "is_direct": true}, {"publisher": "SimplyHired", "apply_link": "https://www.simplyhired.com/job/ZAB00gB5xeqbHKRkB5iAVbbGSV0zLswYYOKUrrjqykaANu6XgOhJ2g", "is_direct": false}], "job_description": "Sales Manager\nPharmaceutical Manufacturing\nYork, PA\nHybrid\nUp to $150,000\n\nJob Summary:\nDrive new business growth by expanding work plans with new and existing customers. Develop and implement sales strategies in an assigned territory, meeting financial sales goals and supporting the strategic plan. Responsibilities include prospecting, coordinating meetings, conducting due diligence, and contributing to strategic planning.\n\nEssential Functions:\n\u2022 Identify and engage prospects at various levels in pharmaceutical companies.\n\u2022 Develop a qualified lead database through multiple channels.\n\u2022 Coordinate initial meetings, deliver company presentations, and assess strategic fit.\n\u2022 Perform initial project due diligence, provide forecasts, and assist in negotiations.\n\u2022 Utilize comprehensive understanding of offerings and pharmaceutical development needs.\n\u2022 Maintain accurate records of sales and prospecting activities in the CRM database.\n\u2022 Execute a portion of the Strategic Plan for assigned territory to drive revenue growth.\n\u2022 Provide market feedback for the development of new drug delivery technologies.\n\nAdditional Responsibilities:\n\u2022 Contribute to the annual strategic planning process.\n\u2022 Maintain high levels of customer satisfaction and collaborate effectively with internal teams.\n\u2022 Demonstrate a commitment to company principles and compliance with cGMP requirements.\n\u2022 Uphold safety regulations and company policies.\n\nJob Specifications:\n\u2022 Over 5 years of consultative selling or customer-facing pharmaceutical experience.\n\u2022 Bachelor's degree required.\n\u2022 Willingness to travel and collaborate with a global team.\n\u2022 Strong communication, presentation, and project management skills.\n\u2022 Proven track record of entering and closing new projects and achieving sales goals.\n\u2022 Strategic thinking, organizational skills, and ability to work cross-functionally.\n\u2022 Maintain confidentiality and proficiency in standard office software.\n\u2022 Basic knowledge of negotiating confidentiality and supply agreements.\n\nJob Type: Full-time\n\nSalary: $100,000.00 - $150,000.00 per year\n\nBenefits:\n\u2022 401(k)\n\u2022 Dental insurance\n\u2022 Employee assistance program\n\u2022 Employee discount\n\u2022 Flexible schedule\n\u2022 Health insurance\n\u2022 Health savings account\n\u2022 Life insurance\n\u2022 Paid time off\n\u2022 Parental leave\n\u2022 Relocation assistance\n\u2022 Retirement plan\n\u2022 Vision insurance\n\nSchedule:\n\u2022 Monday to Friday\n\nTravel requirement:\n\u2022 Travel\n\nEducation:\n\u2022 Bachelor's (Required)\n\nExperience:\n\u2022 Pharmaceutical sales: 5 years (Preferred)\n\u2022 FDA regulations: 5 years (Preferred)\n\u2022 CGMP: 4 years (Preferred)\n\nAbility to Relocate:\n\u2022 Glen Rock, PA 17327: Relocate before starting work (Required)\n\nWillingness to travel:\n\u2022 50% (Preferred)\n\nWork Location: Hybrid remote in Glen Rock, PA 17327", "job_is_remote": false, "job_posted_at_timestamp": 1707955200, "job_posted_at_datetime_utc": "2024-02-15T00:00:00.000Z", "job_city": "Glen Rock", "job_state": "PA", "job_country": "US", "job_latitude": 39.79316, "job_longitude": -76.73025, "job_benefits": ["dental_coverage", "health_insurance", "retirement_savings", "paid_time_off"], "job_google_link": "https://www.google.com/search?gl=us&hl=en&rciv=jb&q=sales+manager&start=50&ibp=htl;jobs#fpstate=tldetail&htivrt=jobs&htiq=sales+manager&htidocid=2gQ0cVx93zltIOKrAAAAAA%3D%3D", "job_offer_expiration_datetime_utc": "2024-07-09T00:00:00.000Z", "job_offer_expiration_timestamp": 1720483200, "job_required_experience": {"no_experience_required": false, "required_experience_in_months": 60, "experience_mentioned": true, "experience_preferred": false}, "job_required_skills": null, "job_required_education": {"postgraduate_degree": false, "professional_certification": false, "high_school": false, "associates_degree": false, "bachelors_degree": false, "degree_mentioned": true, "degree_preferred": false, "professional_certification_mentioned": false}, "job_experience_in_place_of_education": false, "job_min_salary": 100000, "job_max_salary": 150000, "job_salary_currency": "USD", "job_salary_period": "YEAR", "job_highlights": {"Qualifications": ["Over 5 years of consultative selling or customer-facing pharmaceutical experience", "Bachelor's degree required", "Willingness to travel and collaborate with a global team", "Strong communication, presentation, and project management skills", "Proven track record of entering and closing new projects and achieving sales goals", "Strategic thinking, organizational skills, and ability to work cross-functionally", "Maintain confidentiality and proficiency in standard office software", "Glen Rock, PA 17327: Relocate before starting work (Required)"], "Responsibilities": ["Drive new business growth by expanding work plans with new and existing customers", "Develop and implement sales strategies in an assigned territory, meeting financial sales goals and supporting the strategic plan", "Responsibilities include prospecting, coordinating meetings, conducting due diligence, and contributing to strategic planning", "Identify and engage prospects at various levels in pharmaceutical companies", "Develop a qualified lead database through multiple channels", "Coordinate initial meetings, deliver company presentations, and assess strategic fit", "Perform initial project due diligence, provide forecasts, and assist in negotiations", "Utilize comprehensive understanding of offerings and pharmaceutical development needs", "Maintain accurate records of sales and prospecting activities in the CRM database", "Execute a portion of the Strategic Plan for assigned territory to drive revenue growth", "Provide market feedback for the development of new drug delivery technologies", "Contribute to the annual strategic planning process", "Maintain high levels of customer satisfaction and collaborate effectively with internal teams", "Demonstrate a commitment to company principles and compliance with cGMP requirements", "Uphold safety regulations and company policies"], "Benefits": ["Up to $150,000", "Salary: $100,000.00 - $150,000.00 per year", "401(k)", "Dental insurance", "Employee assistance program", "Employee discount", "Flexible schedule", "Health insurance", "Health savings account", "Life insurance", "Paid time off", "Parental leave", "Relocation assistance", "Retirement plan", "Vision insurance", "Monday to Friday"]}, "job_job_title": "Sales manager", "job_posting_language": "en", "job_onet_soc": "11202200", "job_onet_job_zone": "4"}