{"job_id": "_47wL0hKMCCK0usMAAAAAA==", "employer_name": "Boys & Girls Clubs of Tampa Bay, Inc.", "employer_logo": null, "employer_website": null, "employer_company_type": null, "job_publisher": "Jooble", "job_employment_type": "FULLTIME", "job_title": "Senior Director of Development", "job_apply_link": "https://jooble.org/jdp/2869489096331240705", "job_apply_is_direct": false, "job_apply_quality_score": 0.543, "apply_options": [{"publisher": "Jooble", "apply_link": "https://jooble.org/jdp/2869489096331240705", "is_direct": false}, {"publisher": "LifeworQ", "apply_link": "https://lifeworq.com/job/10d33454-f29b-4834-8836-0a9c18f3600e", "is_direct": false}, {"publisher": "Talentify", "apply_link": "https://www.talentify.io/job/senior-director-of-development-tampa-florida-bgc-tampa-bay-485688", "is_direct": false}, {"publisher": "Learn4Good", "apply_link": "https://www.learn4good.com/jobs/tampa/florida/non-profit/2956311148/e/", "is_direct": false}, {"publisher": "Jobs Trabajo.org", "apply_link": "https://us.trabajo.org/job-2467-20240309-815e50785b0490eda2ea348c2efb769a", "is_direct": false}, {"publisher": "Lensa", "apply_link": "https://lensa.com/job/boys-girls-clubs-of-tampa-bay-inc/tampa-fl/senior-director-of-development/d71203d43d585be531e602afe6239b8e", "is_direct": false}, {"publisher": "Jobilize", "apply_link": "https://www.jobilize.com/job/us-fl-tampa-senior-director-development-boys-girls-clubs-bay-hiring", "is_direct": false}, {"publisher": "WhatJobs", "apply_link": "https://www.whatjobs.com/job/Senior-Director-of/tampa/1529506368", "is_direct": false}], "job_description": "POSITION DESCRIPTION\n\nTITLE :\n\nSenior Director of Development\n\nREPORTS TO:\n\nChief Development Officer\n\nSTATUS:\n\nFull Time \u2013 Exempt*\n\nDEPARTMENT:\n\nDevelopment Department\n\nPOSITION SUMMARY:\n\nThe Senior Director of Development works closely with the Chief Development Officer to assist in growing support and market visibility through the development and execution of strategic fundraising and communications/marketing plans in alignment with the organization\u2019s overall goals. These would include positioning the organization advantageously in media, social media, with prospects and donors and by creating and maintaining fundraising campaigns and stewardships plans for all donors and constituents. The Senior Director of Development will manage the Director of Development and Community Engagement, the Events Manager, and the Digital Storyteller and Marketing coordinator.\n\nRESPONSIBILITIES:\nIdentify, cultivate and fundraise gifts at five and six figures for the organization.\nDevelop and execute development plans, including cultivation and stewardship plans for all levels of donors.\nAssist the Chief Development Officer in the execution of a comprehensive fundraising plan.\nManage strategies and activities for donor cultivation, solicitation, and relations.\nIn conjunction with Chief Development Officer, oversee event logistics, development, stewardship, donor relations and budgeting.\nAssist with preparing budgets and provide periodic progress reports.\nReach set fundraising goals, including but not limited to asking for monetary contributions, overseeing fundraising events, and soliciting funds and resources in collaboration with the Development Team.\nDesign, develop and execute program initiatives and activities to support Boys & Girls Clubs of Tampa Bay\u2019s Mission.\nLead the Development Team in creating and executing visibility campaigns to further the Mission, including strategy behind social media.\nIn conjunction with the Chief Development Officer, create and execute all aspects of the giving societies.\nManage the publishing of the following: the Impact Report, monthly e-blasts, Annual Report, end-of-year Appeals, mailings, and other annual projects as needed.\nImplement annual fund campaigns.\nSecure sponsors for events and annual fund campaigns.\nManage production design, layout, and distribution of sponsorship \u201cmenu\u201d packages to potential event sponsors and donors in the community.\nDevelop an annual marketing plan to promote Boys & Girls Clubs of Tampa Bay, generate funding, and create awareness.\nCreate stewardship engagement and marketing campaigns.\nGrow asset library (photos, video etc.)\nWork closely with Development Team to establish content and timelines for effective email, direct mail, and social media campaigns.\nAssist with all event logistics in support of Development Team.\nOversee management of Great Future Professional Council.\nPerform other related duties as requested by Chief Development Officer to assist in the success of the Development Team.\nSKILLS/KNOWLEDGE REQUIRED:\n\nKnowledge of the mission, objectives, policies, programs, and procedures of the Boys & Girls Clubs of Tampa Bay; and the principles and practices of non-profit organization.\nBe goal driven especially with respect to initiating and maintaining donor relationships.\nDisplay a positive attitude, show concern for people and community, demonstrate presence, self-confidence, common sense and good listening ability.\nDemonstrated organizational and project management abilities.\nExcellent writing and communication skills; strong interpersonal and organizational skills.\nAttention to detail and the ability to prioritize and execute multiple projects under demanding deadlines are essential.\nFamiliarity with web content management, communications, and social media.\nThe ability to lead multiple long and short-term projects simultaneously while meeting all related deadlines is critical.\nDemonstrated capability to conduct oneself in a calm, positive, professional demeanor when dealing with the public and/or with demanding situations.\nAbility to work as a team player.\nProficient in Microsoft Office software applications, MobileCause/Give Smart, and donor database, preferably Raiser\u2019s Edge and/or Salesforce.\nSelf-starter; ability to work independently as well as in a team environment with minimal supervision.\nWillingness to adjust hours to accommodate the needs of the job.\nAbility to effectively manage a wide array of tasks, projects, and responsibilities.\nEDUCATION/CERTIFICATIONS:\n\nBachelor\u2019s Degree required from accredited college or university required.\nSix to ten years of progressive experience in marketing, communications, and fundraising in the non-profit sector.\nPHYSICAL REQUIREMENTS/WORK ENVIRONMENT:\n\nOccasionally required to stand and walk and may occasionally lift and/or move up to 50 pounds.\nRequired to have a valid Driver\u2019s License.\nNormal office environment. Evenings & weekend work required at times.\n\nABOUT BOYS & GIRLS CLUBS OF TAMPA BAY:\n\nBoys & Girls Clubs of Tampa Bay, Inc. is a nonprofit organization based in Tampa, Florida whose mission is to enable all young people especially those who need us the most, to reach their full potential as productive, caring, and responsible citizens. Be part of an exciting organization that fosters diverse community relationships, and engages community partners, funders, and vendors in the Tampa Bay area. Boys & Girls Clubs of Tampa Bay is a fast paced, energetic, nonprofit organization with approximately 200 dedicated staff members.\n\nWe are excited that currently, we have entered into a shared services agreement by which the CEO of Boys & Girls Clubs of the Suncoast has now become the President & CEO of Boys & Girls Clubs of Tampa Bay. Through this agreement, we will be afforded the ability to reach more kids in need and combine our talent to gain better outcomes for those we serve.\n\nDISCLAIMER:\n\nThe information presented indicates the general nature and level of work expected of employees in this classification. It is not designed to contain, nor to be interpreted as, a comprehensive inventory of all duties, responsibilities, qualifications and objectives required of employees assigned to this job.", "job_is_remote": false, "job_posted_at_timestamp": 1710169694, "job_posted_at_datetime_utc": "2024-03-11T15:08:14.000Z", "job_city": "Tampa", "job_state": "FL", "job_country": "US", "job_latitude": 27.951689, "job_longitude": -82.458755, "job_benefits": ["retirement_savings"], "job_google_link": "https://www.google.com/search?gl=us&hl=en&rciv=jb&q=senior+director+of+business+development&start=50&ibp=htl;jobs#fpstate=tldetail&htivrt=jobs&htiq=senior+director+of+business+development&htidocid=_47wL0hKMCCK0usMAAAAAA%3D%3D", "job_offer_expiration_datetime_utc": "2024-04-11T07:56:43.000Z", "job_offer_expiration_timestamp": 1712822203, "job_required_experience": {"no_experience_required": false, "required_experience_in_months": 72, "experience_mentioned": true, "experience_preferred": false}, "job_required_skills": null, "job_required_education": {"postgraduate_degree": false, "professional_certification": false, "high_school": false, "associates_degree": false, "bachelors_degree": false, "degree_mentioned": true, "degree_preferred": false, "professional_certification_mentioned": true}, "job_experience_in_place_of_education": false, "job_min_salary": null, "job_max_salary": null, "job_salary_currency": null, "job_salary_period": null, "job_highlights": {"Qualifications": ["Knowledge of the mission, objectives, policies, programs, and procedures of the Boys & Girls Clubs of Tampa Bay; and the principles and practices of non-profit organization", "Display a positive attitude, show concern for people and community, demonstrate presence, self-confidence, common sense and good listening ability", "Demonstrated organizational and project management abilities", "Excellent writing and communication skills; strong interpersonal and organizational skills", "Attention to detail and the ability to prioritize and execute multiple projects under demanding deadlines are essential", "Familiarity with web content management, communications, and social media", "The ability to lead multiple long and short-term projects simultaneously while meeting all related deadlines is critical", "Demonstrated capability to conduct oneself in a calm, positive, professional demeanor when dealing with the public and/or with demanding situations", "Ability to work as a team player", "Proficient in Microsoft Office software applications, MobileCause/Give Smart, and donor database, preferably Raiser\u2019s Edge and/or Salesforce", "Self-starter; ability to work independently as well as in a team environment with minimal supervision", "Willingness to adjust hours to accommodate the needs of the job", "Ability to effectively manage a wide array of tasks, projects, and responsibilities", "Bachelor\u2019s Degree required from accredited college or university required", "Six to ten years of progressive experience in marketing, communications, and fundraising in the non-profit sector", "Occasionally required to stand and walk and may occasionally lift and/or move up to 50 pounds", "Required to have a valid Driver\u2019s License"], "Responsibilities": ["The Senior Director of Development works closely with the Chief Development Officer to assist in growing support and market visibility through the development and execution of strategic fundraising and communications/marketing plans in alignment with the organization\u2019s overall goals", "These would include positioning the organization advantageously in media, social media, with prospects and donors and by creating and maintaining fundraising campaigns and stewardships plans for all donors and constituents", "The Senior Director of Development will manage the Director of Development and Community Engagement, the Events Manager, and the Digital Storyteller and Marketing coordinator", "Identify, cultivate and fundraise gifts at five and six figures for the organization", "Develop and execute development plans, including cultivation and stewardship plans for all levels of donors", "Manage strategies and activities for donor cultivation, solicitation, and relations", "In conjunction with Chief Development Officer, oversee event logistics, development, stewardship, donor relations and budgeting", "Assist with preparing budgets and provide periodic progress reports", "Reach set fundraising goals, including but not limited to asking for monetary contributions, overseeing fundraising events, and soliciting funds and resources in collaboration with the Development Team", "Design, develop and execute program initiatives and activities to support Boys & Girls Clubs of Tampa Bay\u2019s Mission", "Lead the Development Team in creating and executing visibility campaigns to further the Mission, including strategy behind social media", "In conjunction with the Chief Development Officer, create and execute all aspects of the giving societies", "Manage the publishing of the following: the Impact Report, monthly e-blasts, Annual Report, end-of-year Appeals, mailings, and other annual projects as needed", "Implement annual fund campaigns", "Secure sponsors for events and annual fund campaigns", "Manage production design, layout, and distribution of sponsorship \u201cmenu\u201d packages to potential event sponsors and donors in the community", "Develop an annual marketing plan to promote Boys & Girls Clubs of Tampa Bay, generate funding, and create awareness", "Create stewardship engagement and marketing campaigns", "Grow asset library (photos, video etc.)", "Work closely with Development Team to establish content and timelines for effective email, direct mail, and social media campaigns", "Assist with all event logistics in support of Development Team", "Oversee management of Great Future Professional Council", "Perform other related duties as requested by Chief Development Officer to assist in the success of the Development Team"]}, "job_job_title": "Senior", "job_posting_language": "en", "job_onet_soc": "11203100", "job_onet_job_zone": "4"}