{"job_id": "U9GAGXWh9KNloFzMAAAAAA==", "employer_name": "Homewell Franchising Inc.", "employer_logo": null, "employer_website": "http://homewellfranchising.com", "employer_company_type": null, "job_publisher": "Paragoncapllc.com", "job_employment_type": "FULLTIME", "job_title": "Franchise Business Consultant at Homewell Franchising Inc. Burkburnett, TX", "job_apply_link": "https://paragoncapllc.com/gig/job/franchise-business-consultant-at-homewell-franchising-inc-burkburnett-tx-akg4dmdjMEJnNXpldEs0N0Fka3hib090c0E9PQ==", "job_apply_is_direct": false, "job_apply_quality_score": 0.4353, "apply_options": [{"publisher": "Paragoncapllc.com", "apply_link": "https://paragoncapllc.com/gig/job/franchise-business-consultant-at-homewell-franchising-inc-burkburnett-tx-akg4dmdjMEJnNXpldEs0N0Fka3hib090c0E9PQ==", "is_direct": false}, {"publisher": "Gobimarketing.com", "apply_link": "https://gobimarketing.com/career/job/franchise-business-consultant-at-homewell-franchising-inc-burkburnett-tx-SDNQekkvQTlxTGpxUjlncG8wSTl1R1NCb2c9PQ==", "is_direct": false}, {"publisher": "Planktons Beach", "apply_link": "https://planktonsbeach.com/gig/job/franchise-business-consultant-at-homewell-franchising-inc-burkburnett-tx-aERyNGwzSTBFc2V6dDZmNW5zR2t5bk1sT3c9PQ==", "is_direct": false}, {"publisher": "Rrrrrrrrrarrr", "apply_link": "https://rrrrrrrrrarrr.com/list/job/franchise-business-consultant-at-homewell-franchising-inc-burkburnett-tx-YlpMclJHM1hYaHE3QmUxT1RDRjdVNmlIUXc9PQ==", "is_direct": false}], "job_description": "Franchise Business Consultant job at Homewell Franchising Inc.. Burkburnett, TX. Job Description\n\nJob Description\n\nJOB RESPONSIBILITIES:\n\nThe Franchise Business Consultant position is responsible for working with HomeWell franchise partners on our brand standards and best practices to grow their business. This position is pivotal in helping our franchise partners succeed through performance management and continual coaching to organizational goals. The Franchise Business Consultant will work closely with each franchise partner through leadership, influence, and functional expertise to create meaningful, productive business relationships that allow for owners to meet or exceed corporate budgeted revenue and royalty initiatives. The Franchise Business Consultant will provide advice, counsel, coaching, and assistance to impact and improve the sales, profits, market share and operating standards of each franchise partner\u2019s business. The goal is to achieve the status of a trusted advisor to franchisor owners and agency teams and to facilitate continuous improvement action planning to help generate incremental top-line revenue and client and employee satisfaction. The Franchise Business Consultant is instrumental in serving as the \u201ceyes and ears\u201d of the franchise system and acting as an advisor and conduit of information between the franchise partners and corporate team.\n\nESSENTIAL FUNCTIONS:\n\nBe knowledgeable and able to evaluate and assist franchisees in the following key business areas:\n\u2022 Financial Analysis, including:\n\u2022 Operating guidelines\n\u2022 Profit and loss analysis\n\u2022 Sales & Operations Performance Management, including:\n\u2022 Coaching and promoting to franchise partners the resources and tools offered by corporate\n\u2022 Informing best practices in caregiver recruitment and retention\n\u2022 Overall operational excellence to lead to greater profitability\n\u2022 Franchise Partner Relationship Management, including:\n\u2022 Being the brand ambassador and brand champion to all franchise partners\n\u2022 Acting as the conduit of information between franchise partners and corporate\n\u2022 Sharing best practices through various communication channels, including support calls and on-site visits\n\nKey performance activities include, but are not limited to:\n\u2022 Ensuring franchise partners are compliant with brand standards.\n\u2022 Responding to franchisee requests and questions within a timely manner.\n\u2022 Helping each franchise partner develop, follow, and monitor an annual Business Plan including, sales & marketing, financial goals, and action plans.\n\u2022 Performing site visits with identified franchise partners to provide overall support and quality assurance, including ensuring effective utilization of the Clear Care platform, taking part in an intake/scheduler, sitting in on orientation and caregiver interviews, ensuring personnel files and client files are compliant, ensuring correct collateral and marketing is being utilized and offering feedback/opportunity to improve processes and practices.\n\u2022 Consulting with other departments to identify additional support, resources and training needs to improve gaps in agency operations.\n\u2022 Fully understand the purpose and benefits of consumer brand programs and education initiatives, general company strategic direction, vendor partnerships, training and education programs, tools and resources to effectively influence franchisees and obtain requisite adoption.\n\u2022 Maintain appropriate documentation of virtual and on-site consultation and support.\n\u2022 Assist with other projects as assigned.\n\nQUALIFICATIONS:\n\u2022 Bachelor\u2019s degree highly preferred; equivalent experience may be considered\n\u2022 Requires minimum of 3-5 years of relevant experience in home care or healthcare industry\n\u2022 Extensive operational and/or sales support\n\u2022 Understanding of P&L statements, budgeting and controllable costs\n\u2022 Strong consulting, training and persuasion skills\n\u2022 Strong interpersonal and communication skills with the ability, desire and enjoyment to work in a cooperative, professional and friendly manner.\n\u2022 Self-motivated, organized and able to balance multiple projects\n\u2022 Strong attention to detail and accuracy\n\u2022 Thrive on exceeding goals and meeting deadlines\n\u2022 Excellent interpersonal skills\n\u2022 Proficiency in Microsoft Office (Word, Excel, PowerPoint and Outlook)\n\nPHYSICAL AND ENVIROMENTAL DEMANDS: This is a primarily sedentary position.\n\nORGANIZATIONAL RELATIONSHIP: Reports directly to the Vice President of Operations\n\nCLASSIFICATION: Exempt\n\nPOSITION TYPE & EXPECTED HOURS OF WORK: Full-Time; 40-hours a week\n\nTRAVEL : 50% or more\n\nDISCLAIMER: This job description is not designed to cover or contain a comprehensive listing of activities, duties or responsibilities that are required of the employee. Duties, responsibilities and activities may change or be assigned at any time with or without notice.", "job_is_remote": false, "job_posted_at_timestamp": 1709596800, "job_posted_at_datetime_utc": "2024-03-05T00:00:00.000Z", "job_city": "Burkburnett", "job_state": "TX", "job_country": "US", "job_latitude": 34.09787, "job_longitude": -98.57061, "job_benefits": null, "job_google_link": "https://www.google.com/search?gl=us&hl=en&rciv=jb&q=brand+partnerships+consultant&start=30&ibp=htl;jobs#fpstate=tldetail&htivrt=jobs&htiq=brand+partnerships+consultant&htidocid=U9GAGXWh9KNloFzMAAAAAA%3D%3D", "job_offer_expiration_datetime_utc": "2024-04-04T00:00:00.000Z", "job_offer_expiration_timestamp": 1712188800, "job_required_experience": {"no_experience_required": false, "required_experience_in_months": 36, "experience_mentioned": true, "experience_preferred": false}, "job_required_skills": null, "job_required_education": {"postgraduate_degree": false, "professional_certification": false, "high_school": false, "associates_degree": false, "bachelors_degree": false, "degree_mentioned": true, "degree_preferred": false, "professional_certification_mentioned": false}, "job_experience_in_place_of_education": false, "job_min_salary": null, "job_max_salary": null, "job_salary_currency": null, "job_salary_period": null, "job_highlights": {"Qualifications": ["Requires minimum of 3-5 years of relevant experience in home care or healthcare industry", "Extensive operational and/or sales support", "Understanding of P&L statements, budgeting and controllable costs", "Strong consulting, training and persuasion skills", "Strong interpersonal and communication skills with the ability, desire and enjoyment to work in a cooperative, professional and friendly manner", "Self-motivated, organized and able to balance multiple projects", "Strong attention to detail and accuracy", "Thrive on exceeding goals and meeting deadlines", "Excellent interpersonal skills", "Proficiency in Microsoft Office (Word, Excel, PowerPoint and Outlook)", "PHYSICAL AND ENVIROMENTAL DEMANDS: This is a primarily sedentary position"], "Responsibilities": ["The Franchise Business Consultant position is responsible for working with HomeWell franchise partners on our brand standards and best practices to grow their business", "The Franchise Business Consultant will work closely with each franchise partner through leadership, influence, and functional expertise to create meaningful, productive business relationships that allow for owners to meet or exceed corporate budgeted revenue and royalty initiatives", "The Franchise Business Consultant will provide advice, counsel, coaching, and assistance to impact and improve the sales, profits, market share and operating standards of each franchise partner\u2019s business", "The goal is to achieve the status of a trusted advisor to franchisor owners and agency teams and to facilitate continuous improvement action planning to help generate incremental top-line revenue and client and employee satisfaction", "The Franchise Business Consultant is instrumental in serving as the \u201ceyes and ears\u201d of the franchise system and acting as an advisor and conduit of information between the franchise partners and corporate team", "Be knowledgeable and able to evaluate and assist franchisees in the following key business areas:", "Operating guidelines", "Profit and loss analysis", "Sales & Operations Performance Management, including:", "Coaching and promoting to franchise partners the resources and tools offered by corporate", "Informing best practices in caregiver recruitment and retention", "Overall operational excellence to lead to greater profitability", "Being the brand ambassador and brand champion to all franchise partners", "Sharing best practices through various communication channels, including support calls and on-site visits", "Ensuring franchise partners are compliant with brand standards", "Responding to franchisee requests and questions within a timely manner", "Helping each franchise partner develop, follow, and monitor an annual Business Plan including, sales & marketing, financial goals, and action plans", "Performing site visits with identified franchise partners to provide overall support and quality assurance, including ensuring effective utilization of the Clear Care platform, taking part in an intake/scheduler, sitting in on orientation and caregiver interviews, ensuring personnel files and client files are compliant, ensuring correct collateral and marketing is being utilized and offering feedback/opportunity to improve processes and practices", "Consulting with other departments to identify additional support, resources and training needs to improve gaps in agency operations", "Fully understand the purpose and benefits of consumer brand programs and education initiatives, general company strategic direction, vendor partnerships, training and education programs, tools and resources to effectively influence franchisees and obtain requisite adoption", "Maintain appropriate documentation of virtual and on-site consultation and support", "Assist with other projects as assigned", "ORGANIZATIONAL RELATIONSHIP: Reports directly to the Vice President of Operations"]}, "job_job_title": "Business consultant", "job_posting_language": "en", "job_onet_soc": "13111100", "job_onet_job_zone": "5"}