{"job_id": "iCrBDyMgU9708y-_AAAAAA==", "employer_name": "M & T Bank", "employer_logo": "https://filecache.mediaroom.com/mr5mr_mtbank/177606/UWIRGB.jpg", "employer_website": "http://www.mtb.com", "employer_company_type": "Finance", "job_publisher": "Jooble", "job_employment_type": "TEMPORARY", "job_title": "Enterprise Data Engineering Tech Manager", "job_apply_link": "https://jooble.org/jdp/2322542715109939285", "job_apply_is_direct": false, "job_apply_quality_score": 0.6368, "apply_options": [{"publisher": "Jooble", "apply_link": "https://jooble.org/jdp/2322542715109939285", "is_direct": false}], "job_description": "at M & T Bank in Wilmington, Delaware, United States\n\nThis role offers a hybrid work schedule; offering the flexibility to work from home two days a week, while providing the opportunity for in-person collaboration.\n\nThis position is available in Buffalo, NY or Wilmington, DE\n\nAbout the Team\n\nOur team is on a mission of unleashing the power of data to support decision making. Our team builds enduring data products, provides platforms to access & derive insights from data, enables confidence in decision making with appropriate data governance, delivers actionable insights through use of data science and activates value for the business by innovatively solving problems with data. We operate with a sense of urgency, have a startup mentality, build data analytic products at scale, and innovate solutions on behalf of our user communities . We work hard but value the need for downtime to unplug and recharge. We embrace our differences and view them as a key driver of innovation. We are View email address on joblink.delaware.gov&T\n\nRole Overview:\n\nLeads the activities of two or more scrum teams enabling enterprise wide data modernization in partnership with CDO , Product Owners , Business and Technology teams . Responsible for setting the long and short-term strategic direction for the M&T tech data ecosystems. Serves as primary contact to the Technology leadership team , Sr Product Owners , CDO and business partners when it comes to transformational initiatives . Owns the budget of concurrent development streams. Assists in the development and career planning for all team members. The team will be executing in Scrum/Kanban fashion, and this role will be responsible for the assistance in prioritization for the team; be a partner to the various tech team as to the work coming in for data; participate in the data modernization initiatives ; be a representative of the Data work when it needs to be discussed at an architecture level.\n\nPrimary Responsibilities:\n\nPeople Leadership\n\n\u00b7 Participating in our engineering culture, with an emphasis on contributing ideas, thoughts, and constructive feedback regarding the work of others on our team.\n\n\u00b7 Assisting with interviewing, onboarding, and training engineers as they join the team.\n\n\u00b7 Assisting leading a team of developers and engineers on their agile transformation journey including: performance management, Career planning, Technical implementation guidance on the stack that they develop on, Technical guidance around build/release automation & devops, Participate in code reviews\n\nTechnical Leadership\n\n\u00b7 Create high complexity detailed technical design, involved in detailed analysis, design, construction and testing thereby ensuring technical compatibility and integration.\n\n\u00b7 Recommend, design and code efficient and effective solutions for challenging problems for medium to large work efforts of medium to high complexity.\n\n\u00b7 Responsible for ensuring compliance with ELT / ETL standards and guidelines related to the design, construction, testing, and deployment activities within the Delivery Management environments.\n\n\u00b7 Act as the single point of contact and set clear expectations with Data Tech teams and hold them responsible for the planning, completion and coordination of work activity for projects involving more than one developer\n\n\u00b7 Perform the role of Application Owner including tasks like\n\no Disaster recovery planning\n\no Vulnerability management\n\no Audit / compliance management\n\nFunctional (Domain) Leadership\n\n\u00b7 Perform complex analysis, and summarize to senior leaders in simple language\n\n\u00b7 Work with various stakeholders in developing high level functional specifications, and use a combination of technical and domain knowledge to propose solutions and product features\n\n\u00b7 Participate/Contribute in requirements and analysis discussion with stakeholders\n\nProcess Leadership\n\n\u00b7 Build out and streamline agile teams responsible for M&T\u2019s data modernization initiatives .\n\n\u00b7 Enable self-service frameworks to ensure adoption of data products and features .\n\n\u00b7 Constantly look for opportunities to make the workflows and processes efficient \u2013 across business processes, software development processes, etc\n\nMinimum Qualifications Required:\n\n\u00b7 Minimum of an Associate degree and with 9 years\u2019 technology or systems management/leadership experience, or in lieu of a degree, a combined minimum of 11 years\u2019 higher education and/or work experience, including a minimum of 9 years\u2019 technology or systems management/leadership experience\n\nEducation\n\n\u00b7 Computer science, development and/or systems engineering background required\n\nRequired Technology skills\n\n\u00b7 In-Depth Knowledge of data architecture as well as modern data architecture as well as consumption solutions such as data mesh , data fabric , data lake or other Solutions\n\n\u00b7 Experience in cloud-data technologies, such as: Snowflake, Azure , Databricks etc.\n\n\u00b7 Experience in big-data technologies, such as: Hive, Impala, Kudu\n\n\u00b7 Experience or understanding of implementation patterns foir various ETL / ELT tools such as Informatica, Mattalion , Striim ,Databricks , DBT (or equivalent) tools.\n\n\u00b7 Experience or have an understanding of working with multiple file structures \u2013 Mainframe, Flat files, Json, XML\u2019s\n\n\u00b7 Experience or have an understanding Programming skillsets in at least one of these languages: Java, Scala, Python\n\nPreferred Technology skills\n\n\u00b7 Realtime processing like Spark streaming, Kafka\n\n\u00b7 Cloud computing (Azure, AWS )\n\n\u00b7 NOSQL Databases such as Mongo, Cassandra, HBase\n\n\u00b7 Cache software such as Gemfire, Ignite, Redis\n\n\u00b7 Reporting/Dashboard tools such as PowerBI, Tableau, Qlik\n\nPreferred Other skills:\n\n\u00b7 Agile (such as JIRA ), Source code repository (Git, Bitbucket, etc.) CI/CD tools (Jenkins, Teamcity, etc.),\n\n\u00b7 Data Modeling\n\n\u00b7 Data Quality management, and data governance\n\nPreferred Functional skills\n\n\u00b7 Financial regulatory reporting.\n\n\u00b7 Knowledge of Banking products lifecycle: Checking, Mortgages, Loans, Treasury, Cash Management, etc.\n\nCOMPANY :\n\nAt M&T Tech, we\u2019re a team of makers, doers, and builders, working to create the most advanced technology solutions in banking. We\u2019re not your stereotypical suit and tie bankers: We\u2019re an innovative team of leading tech experts, pushing boundaries, and taking risks. We\u2019re building an agile team of the most skilled and creative, workers to solve complex problems, architecting solutions, writing high-performance software, and charting our new path, all to make the lives of our customers, and the communities that we serve, better. Join us and be part of something new as we build tomorrow\u2019s bank, today.\n\nM&T Bank is a Top 20 US bank holding company and one of the best performing and financial stable regional banks in the country, we offer our technology employees a wide range of performance-based career development opportunities. We have a strong commitment to our customers and the communities we serve, and we continue to grow with a focus on the future. So, when looking to advance your career, look to M&T. Grow with us.\n\nHiring Immediately.\n\nWe support our team members with generous benefits.\n\n\u00b7 Competitive compensation\n\n\u00b7 Health, welfare, and retirement benefits\n\n\u00b7 401(k) match at 5%\n\n\u00b7 Work-life balance and flexible work arrangements\n\n\u00b7 Start with 25 days PTO plus 12 paid holidays\n\n\\#LI-KB1\n\nM&T Bank is committed to fair, competitive, and market-informed pay for our employees. The pay range for this position is $127,274.43 \u2013 $212,124.05 Annual ( USD ). The successful candidate\u2019s particular combination of knowledge, skills, and experience will inform their specific compensation.\n\nLocation:\n\nWilmington, Delaware, United States of America\n\nM&T Bank Corporation is an Equal Opportunity/Affirmative Action Employer, including disabilities and veterans.\nTo view full details and how to apply, please login or create a Job Seeker account", "job_is_remote": false, "job_posted_at_timestamp": 1710633600, "job_posted_at_datetime_utc": "2024-03-17T00:00:00.000Z", "job_city": "Delaware", "job_state": "OH", "job_country": "US", "job_latitude": 40.29867, "job_longitude": -83.06796, "job_benefits": ["retirement_savings", "paid_time_off", "health_insurance"], "job_google_link": "https://www.google.com/search?gl=us&hl=en&rciv=jb&q=data+engineering&start=30&ibp=htl;jobs#fpstate=tldetail&htivrt=jobs&htiq=data+engineering&htidocid=iCrBDyMgU9708y-_AAAAAA%3D%3D", "job_offer_expiration_datetime_utc": "2024-04-16T00:00:00.000Z", "job_offer_expiration_timestamp": 1713225600, "job_required_experience": {"no_experience_required": false, "required_experience_in_months": 132, "experience_mentioned": true, "experience_preferred": false}, "job_required_skills": null, "job_required_education": {"postgraduate_degree": false, "professional_certification": false, "high_school": false, "associates_degree": false, "bachelors_degree": false, "degree_mentioned": true, "degree_preferred": false, "professional_certification_mentioned": false}, "job_experience_in_place_of_education": false, "job_min_salary": null, "job_max_salary": null, "job_salary_currency": null, "job_salary_period": null, "job_highlights": {"Qualifications": ["Minimum of an Associate degree and with 9 years\u2019 technology or systems management/leadership experience, or in lieu of a degree, a combined minimum of 11 years\u2019 higher education and/or work experience, including a minimum of 9 years\u2019 technology or systems management/leadership experience", "Computer science, development and/or systems engineering background required", "Required Technology skills", "In-Depth Knowledge of data architecture as well as modern data architecture as well as consumption solutions such as data mesh , data fabric , data lake or other Solutions", "Experience in cloud-data technologies, such as: Snowflake, Azure , Databricks etc", "Experience in big-data technologies, such as: Hive, Impala, Kudu", "Experience or understanding of implementation patterns foir various ETL / ELT tools such as Informatica, Mattalion , Striim ,Databricks , DBT (or equivalent) tools", "Experience or have an understanding of working with multiple file structures \u2013 Mainframe, Flat files, Json, XML\u2019s", "Experience or have an understanding Programming skillsets in at least one of these languages: Java, Scala, Python", "CI/CD tools (Jenkins, Teamcity, etc.),", "Data Modeling", "Data Quality management, and data governance"], "Responsibilities": ["Leads the activities of two or more scrum teams enabling enterprise wide data modernization in partnership with CDO , Product Owners , Business and Technology teams ", "Responsible for setting the long and short-term strategic direction for the M&T tech data ecosystems", "Serves as primary contact to the Technology leadership team , Sr Product Owners , CDO and business partners when it comes to transformational initiatives ", "Owns the budget of concurrent development streams", "Assists in the development and career planning for all team members", "The team will be executing in Scrum/Kanban fashion, and this role will be responsible for the assistance in prioritization for the team; be a partner to the various tech team as to the work coming in for data; participate in the data modernization initiatives ; be a representative of the Data work when it needs to be discussed at an architecture level", "Participating in our engineering culture, with an emphasis on contributing ideas, thoughts, and constructive feedback regarding the work of others on our team", "Assisting with interviewing, onboarding, and training engineers as they join the team", "Assisting leading a team of developers and engineers on their agile transformation journey including: performance management, Career planning, Technical implementation guidance on the stack that they develop on, Technical guidance around build/release automation & devops, Participate in code reviews", "Create high complexity detailed technical design, involved in detailed analysis, design, construction and testing thereby ensuring technical compatibility and integration", "Recommend, design and code efficient and effective solutions for challenging problems for medium to large work efforts of medium to high complexity", "Responsible for ensuring compliance with ELT / ETL standards and guidelines related to the design, construction, testing, and deployment activities within the Delivery Management environments", "Act as the single point of contact and set clear expectations with Data Tech teams and hold them responsible for the planning, completion and coordination of work activity for projects involving more than one developer", "Perform the role of Application Owner including tasks like", "Disaster recovery planning", "Vulnerability management", "Audit / compliance management", "Perform complex analysis, and summarize to senior leaders in simple language", "Work with various stakeholders in developing high level functional specifications, and use a combination of technical and domain knowledge to propose solutions and product features", "Participate/Contribute in requirements and analysis discussion with stakeholders", "Process Leadership", "Build out and streamline agile teams responsible for M&T\u2019s data modernization initiatives ", "Enable self-service frameworks to ensure adoption of data products and features ", "Constantly look for opportunities to make the workflows and processes efficient \u2013 across business processes, software development processes, etc"], "Benefits": ["This role offers a hybrid work schedule; offering the flexibility to work from home two days a week, while providing the opportunity for in-person collaboration", "We support our team members with generous benefits", "Competitive compensation", "Health, welfare, and retirement benefits", "401(k) match at 5%", "Work-life balance and flexible work arrangements", "Start with 25 days PTO plus 12 paid holidays", "The pay range for this position is $127,274.43 \u2013 $212,124.05 Annual ( USD )"]}, "job_job_title": "Manager", "job_posting_language": "en", "job_onet_soc": "11302100", "job_onet_job_zone": "4", "job_naics_code": "522120", "job_naics_name": "Savings Institutions"}