{"job_id": "ZlFPqxNF5A0uDDrcAAAAAA==", "employer_name": "Opera Theatre of Saint Louis", "employer_logo": null, "employer_website": null, "employer_company_type": null, "job_publisher": "Nonprofit Staffing", "job_employment_type": "FULLTIME", "job_title": "Senior Manager, Events & Sponsorships", "job_apply_link": "https://nonprofitstaffing.org/job/273/senior-manager,-events-&-sponsorships-opera-theatre-of-saint-louis", "job_apply_is_direct": false, "job_apply_quality_score": 0.6521, "apply_options": [{"publisher": "Nonprofit Staffing", "apply_link": "https://nonprofitstaffing.org/job/273/senior-manager,-events-&-sponsorships-opera-theatre-of-saint-louis", "is_direct": false}], "job_description": "Position Description\n\nOpera Theatre of Saint Louis is hiring for the position of Senior Manager, Events & Sponsorships. This positions will be responsible for overseeing the planning and execution of OTSL fundraising and cultivation events (including the Spring Gala, Holiday Celebration, and season tent dinners), and institutional funding requests.\n\nDuties & Responsibilities:\n\nDevelop strategies for, plan, and execute OTSL\u2019s major fundraising events, including the Spring Gala, Holiday Celebration, and activities of the Intermezzo Society.\n\nIdentify volunteer event leaders with the ability to contribute significant resources and/or service to Opera Theatre. Manage ongoing communication with event leadership and committees;\n\nResearch event donor prospects and cultivate top prospects;\nDevelop and execute strategies and timelines to effectively solicit prospects and manage ongoing follow-up in collaboration with volunteer event leadership;\nDevelop and execute pre-event communications and promotion in collaboration with the marketing and development teams;\nManage event expenses and re-allocate resources as needed to achieve event goals;\nReport revenue projections regularly to measure progress toward goals;\nNegotiate and contract with vendors to ensure competitive pricing while maintaining quality;\nSupervise all onsite event logistics in coordination with OTSL\u2019s development team;\nResolve unexpected event challenges in real time, using discretion and judgement to adjust established policies or procedures as needed to ensure a positive experience for guests;\nManage strategy and activities for the Intermezzo Society.\n\nCollaborate with the Director of Development to develop and steward relationships with foundations, government agencies, and corporate donors, including:\n\nWork with grant writing staff or contract personnel to identify new prospects, submit compelling and timely grant proposals and reports, and cultivate corporate and foundation representatives.\nDirect corporate sponsorship efforts and serve as the liaison to the board\u2019s corporate sponsorship committee;\nWork with committee members to identify and evaluate new prospects and determine an appropriate strategy for each prospect;\nProvide materials needed for successful solicitation and monitor solicitation progress relative to corporate revenue goal;\nCoordinate corporate sponsorship requests for fundraising events.\n\nPlan and execute donor events and cultivation activities during the opera season (May/June) and off-season, including:\n\nIdentify and secure event hosts to advance OTSL\u2019s donor appreciation and cultivation efforts;\nCommunicate with hosts and guests to ensure a positive experience, and respond to any questions or concerns;\nManage event budgets and re-allocate resources as needed to achieve event goals;\nNegotiate and contract with vendors to ensure competitive pricing while maintaining quality;\nManage all logistical details, guest seating, and on-site personnel for each event;\nProvide oversight for all event logistics, manage event vendors, and respond to guest concerns or grievances in collaboration with OTSL development team.\n\nManage grant writing staff or contract personnel, and the seasonal Development Intern, including recruitment and supervision.\n\nExperience & Qualifications\n\n3-5 years of experience planning special events;\nFamiliarity with Tessitura or similar donor database;\nExcellent written and verbal communication skills;\nAn ability to build relationships with donors and prospective donors;\nExtraordinary attention to detail and a commitment to meeting deadlines;\nProficiency with word processing and spreadsheets;\nA knowledge of local and national arts funding sources, and interest in the performing arts and opera preferred.\n\nCompensation & Hours\n\nCompensation: $60,000-$69,999 annual salary plus benefits.\nThis is a full-time, exempt position.\nOpera Theatre has a flexible work policy which allows for individual remote and asynchronous work arrangements.\nPosition requires evening and weekend hours during key times of year.\n\nAbout Opera Theatre of Saint Louis\n\nOpera Theatre of Saint Louis (OTSL) is a nationally recognized nonprofit organization known for innovative productions featuring outstanding young artists. The company offers a festival opera season each spring which attracts ticket buyers from zip codes throughout the metropolitan area, as well as visitors from nearly 50 states and multiple countries. As of 2022, Opera Theatre of Saint Louis has presented 33 world premieres and 28 American premieres, which may be the highest percentage of new work in the repertory of any American company. In addition to the spring Festival Season, Opera Theatre operates year-round education and community programs serving nearly 17,000 local children and adults.\n\nOpera Theatre of Saint Louis has a year-round artistic and administrative staff of approximately 40, which grows to nearly 500 during the Festival Season. Several hundred volunteer members of the Opera Theatre Guild provide support for all aspects of Opera Theatre\u2019s work and advocate for the company throughout the greater St. Louis community. The company\u2019s annual budget size is approximately $12 million; contributed revenue represents more than 50% of budget.\n\nTO APPLY:\n\nApplicants for the position are asked to submit a resume along with a cover letter in which they describe their interest in Opera Theatre of Saint Louis and their experience and qualifications for the position.\n\nPlease email application information to:\n\nLinda Schulte, Director of Development\n\nEmail: lschulte@opera-stl.org\n\n(no calls, please)\n\nAt Opera Theatre of Saint Louis, we value equity, diversity, and mutual respect. We strongly encourage people of color, LGBTQ+ individuals, women, people with disabilities, and others who have been historically excluded to apply. Our goal is to be a diverse workforce that is representative of our community. We are committed to creating an inclusive environment for all employees.\n\nOTSL will not discriminate against employees or applicants on the basis of race, color, religion or belief; national, social, or ethnic origin; age; sex, sexual orientation, gender identity and/or expression; physical, mental, or sensory disability; family or parental status; genetic information or characteristics; protected veteran status; or any other protected class under federal, state, or local law. OTSL will not tolerate discrimination or harassment based on any of these characteristics.\n\nIf you need assistance or an accommodation in completing an application, interviewing, or otherwise participating in the employee selection process, please contact (314) 963-4226 or mmyers@opera-stl.org.", "job_is_remote": false, "job_posted_at_timestamp": null, "job_posted_at_datetime_utc": null, "job_city": null, "job_state": null, "job_country": "US", "job_latitude": 37.09024, "job_longitude": -95.71289, "job_benefits": ["health_insurance"], "job_google_link": "https://www.google.com/search?gl=us&hl=en&rciv=jb&q=senior+sponsorships+director&start=0&ibp=htl;jobs#fpstate=tldetail&htivrt=jobs&htiq=senior+sponsorships+director&htidocid=ZlFPqxNF5A0uDDrcAAAAAA%3D%3D", "job_offer_expiration_datetime_utc": null, "job_offer_expiration_timestamp": null, "job_required_experience": {"no_experience_required": false, "required_experience_in_months": 36, "experience_mentioned": true, "experience_preferred": false}, "job_required_skills": null, "job_required_education": {"postgraduate_degree": false, "professional_certification": false, "high_school": false, "associates_degree": false, "bachelors_degree": false, "degree_mentioned": true, "degree_preferred": false, "professional_certification_mentioned": false}, "job_experience_in_place_of_education": false, "job_min_salary": null, "job_max_salary": null, "job_salary_currency": null, "job_salary_period": null, "job_highlights": {"Qualifications": ["3-5 years of experience planning special events;", "Familiarity with Tessitura or similar donor database;", "Excellent written and verbal communication skills;", "An ability to build relationships with donors and prospective donors;", "Extraordinary attention to detail and a commitment to meeting deadlines;", "Proficiency with word processing and spreadsheets;", "Position requires evening and weekend hours during key times of year"], "Responsibilities": ["This positions will be responsible for overseeing the planning and execution of OTSL fundraising and cultivation events (including the Spring Gala, Holiday Celebration, and season tent dinners), and institutional funding requests", "Develop strategies for, plan, and execute OTSL\u2019s major fundraising events, including the Spring Gala, Holiday Celebration, and activities of the Intermezzo Society", "Identify volunteer event leaders with the ability to contribute significant resources and/or service to Opera Theatre", "Manage ongoing communication with event leadership and committees;", "Research event donor prospects and cultivate top prospects;", "Develop and execute strategies and timelines to effectively solicit prospects and manage ongoing follow-up in collaboration with volunteer event leadership;", "Develop and execute pre-event communications and promotion in collaboration with the marketing and development teams;", "Manage event expenses and re-allocate resources as needed to achieve event goals;", "Report revenue projections regularly to measure progress toward goals;", "Negotiate and contract with vendors to ensure competitive pricing while maintaining quality;", "Supervise all onsite event logistics in coordination with OTSL\u2019s development team;", "Resolve unexpected event challenges in real time, using discretion and judgement to adjust established policies or procedures as needed to ensure a positive experience for guests;", "Collaborate with the Director of Development to develop and steward relationships with foundations, government agencies, and corporate donors, including:", "Work with grant writing staff or contract personnel to identify new prospects, submit compelling and timely grant proposals and reports, and cultivate corporate and foundation representatives", "Direct corporate sponsorship efforts and serve as the liaison to the board\u2019s corporate sponsorship committee;", "Work with committee members to identify and evaluate new prospects and determine an appropriate strategy for each prospect;", "Provide materials needed for successful solicitation and monitor solicitation progress relative to corporate revenue goal;", "Coordinate corporate sponsorship requests for fundraising events", "Plan and execute donor events and cultivation activities during the opera season (May/June) and off-season, including:", "Identify and secure event hosts to advance OTSL\u2019s donor appreciation and cultivation efforts;", "Communicate with hosts and guests to ensure a positive experience, and respond to any questions or concerns;", "Manage all logistical details, guest seating, and on-site personnel for each event;", "Provide oversight for all event logistics, manage event vendors, and respond to guest concerns or grievances in collaboration with OTSL development team", "Manage grant writing staff or contract personnel, and the seasonal Development Intern, including recruitment and supervision"], "Benefits": ["Compensation & Hours", "Compensation: $60,000-$69,999 annual salary plus benefits"]}, "job_job_title": "Senior manager", "job_posting_language": "en", "job_onet_soc": "13112100", "job_onet_job_zone": "4"}