{"job_id": "nwlYstvqhvBBHIbxAAAAAA==", "employer_name": "Pindrop", "employer_logo": "https://encrypted-tbn0.gstatic.com/images?q=tbn:ANd9GcQks43Mo_HtAtmcY-N6v4St7OoE3rIRijFBf0Po&s=0", "employer_website": null, "employer_company_type": null, "job_publisher": "Built In", "job_employment_type": "FULLTIME", "job_title": "Strategic Account Executive and Partner Manager (UK)", "job_apply_link": "https://builtin.com/job/strategic-account-executive-and-partner-manager-uk/2376646", "job_apply_is_direct": false, "job_apply_quality_score": 0.7048, "apply_options": [{"publisher": "Built In", "apply_link": "https://builtin.com/job/strategic-account-executive-and-partner-manager-uk/2376646", "is_direct": false}, {"publisher": "VentureLoop", "apply_link": "https://www.ventureloop.com/ventureloop/jobdetail.php?jobid=2641250", "is_direct": false}, {"publisher": "LinkedIn", "apply_link": "https://www.linkedin.com/jobs/view/strategic-account-executive-and-partner-manager-uk-at-pindrop-3854814558", "is_direct": false}, {"publisher": "Wellfound", "apply_link": "https://wellfound.com/jobs/2952576-strategic-account-executive-and-partner-manager-uk", "is_direct": true}], "job_description": "Strategic Sales Executive and Partner Manager\n\nLocation: United Kingdom (UK)\n\nWho we are\n\nAre you passionate about innovating at the intersection of technology and personal security? At Pindrop, we recognize that the human voice is a unique personal identifier, increasingly susceptible to sophisticated fraud, including the threat of deepfakes. We're leading the way in developing cutting-edge authentication, fraud prevention, and deepfake detection. Our mission is to provide seamless and secure digital experiences, safeguarding the most personal aspect of our identity: our voice. Here, you'll be part of a team driven by values of Innovation, Customer Advocacy, Excellence, and Impact. We're not just creating a safer digital landscape by fortifying trust and integrity with those we serve, we\u2019re also building a dynamic, supportive workplace where your contributions make a real difference.\n\nHeadquartered in Atlanta, GA, Pindrop is backed by world-class investors such as Andreessen-Horowitz, IVP, and CapitalG\n\nWe are looking for a Sales Executive and Partner Manager to join our growing software company and help us expand our presence in the UK market. You will be responsible for developing and managing relationships with channel partners, as well as selling our products and services directly to customers.\n\nWhat you\u2019ll do\n\u2022 Conduct market research to identify selling opportunities and customer needs\n\u2022 Develop comprehensive Go To Market strategy for Pindrop Products leveraging direct and indirect channels.\n\u2022 Actively seek out new sales leads and prospects through cold calling, networking, and social media\n\u2022 Conduct meetings with potential clients and partners to identify potential opportunities\n\u2022 Prepare and deliver presentations and demos on our products and services\n\u2022 Negotiate and close deals with customers and partners, ensuring mutual satisfaction and long-term collaboration\n\u2022 Provide support and training to partners and customers, as well as feedback and insights to our internal teams\n\u2022 Monitor and report on sales performance, partner performance, and market trends\n\u2022 Participate in industry events and exhibitions to promote our brand and products\n\u2022 Acquire and integrate industry and market knowledge related to the competitive landscape, emerging fraud risk trends, and technologies in order to successfully sell\n\nWho you are\n\u2022 You are a self-driven and motivated individual with a goal setting frame of mind\n\u2022 You are an exceptional communicator\n\u2022 You are resilient in the face of challenges, change, and ambiguity\n\u2022 You are optimistic and believe that you can make a problem into a solution\n\u2022 You are resourceful, excited to uncover innovative solutions and teach yourself something new when needed\n\u2022 You take accountability, do the things you say you\u2019ll do, under-promise and over-deliver\n\u2022 You are nimble and adaptable when priorities change and continue to see the \u201cforest through the trees\u201d\n\nYour skill-set:\n\u2022 8+ years experience in strategic sales for enterprise software\n\nSuccess closing license sales deals of 7 figures or more and experience with Complex contract managementExperience selling a complex product to executive buyers\n\u2022 Experience setting up and running a new territory for an established software company\n\u2022 Ability to execute on different sales motions direct, co-sell as well as resell through partners\n\u2022 Proven record of successful selling, business development, executive level influence, negotiation, and exceptional communication and presence\n\u2022 Must be able to self-prospect to build qualified pipeline\n\u2022 Strong acumen in technology and ability to articulate solution value proposition\n\u2022 Ability to manage multiple opportunities to meet deadlines, setting direction for and ensuring the success of all sales and customer interactions\n\u2022 Ability to work closely and cross functionally with engineering, marketing and product management as well as experience working with partners and alliances, and other internal stakeholders\n\u2022 Must possess the appropriate level of math and analytical skill required to construct a financial business case\n\nWhat\u2019s in it for you:\n\nAs a Pindropper, you join a rapidly growing company making technology more human with the power of voice. You will work alongside some of the best and brightest. We\u2019re a passionate group committed to excellence - but that doesn\u2019t stop us from enjoying the journey as a team with chess and poker tournaments, catered lunches and happy hours, wellness programming, and more. Because we take our jobs seriously, we add time for rest with Unlimited PTO, Focus Thursday, and Company-wide Rest Days.\n\nFirst 30 Days:\n\u2022 Complete onboarding and attend New Employee Orientation sessions with other new Pindroppers\n\u2022 Review account list with your manager\n\u2022 Become familiar with Pindrop\u2019s key value propositions\n\u2022 Market Overview\n\u2022 Overview and familiarity with the Pindrop Sales Process\n\nFirst 60 Days:\n\u2022 Understand a Day in the Life of the Contact Center\n\u2022 Understand the high-level workings of Call Flows\n\u2022 Get to know your key contacts across multiple departments\n\u2022 Present the IVR pitch to your manager and team\n\u2022 Develop at least three new qualified leads\n\nFirst 90 Days:\n\u2022 Develop a forecast for 1H of 2024 and 2H of 2024.\n\u2022 Conduct solo intro meetings with Contact Center Week\n\u2022 Build a Business Plan for 2024\n\u2022 Identify new pipeline >= 3X your quota\n\u2022 Teach us something new\n\nWhat we offer (UK)\n\nAs a part of Pindrop, you\u2019ll have a direct impact on our growing list of products and thus the future of security in the voice-driven economy. We hire great people and take care of them. Here\u2019s a snapshot of the benefits we offer:\n\u2022 Competitive salary\n\u2022 Company holidays and company-wide rest days\n\u2022 Unlimited paid time off\n\u2022 Remote-first culture - including initial and monthly work from home allowance\n\u2022 Annual professional development and learning budget\n\u2022 Pick your own Apple MacBook Pro\n\u2022 Pension scheme & salary exchange option\n\u2022 Medical and Dental insurance/Private Health care\n\u2022 Life Insurance and Critical Illness Insurance\n\u2022 Flex schedules\n\u2022 Best in class tools and tech stack\n\u2022 Fun activities to celebrate our accomplishments as a team\n\nWhat we live by\n\nAt Pindrop, our Core Values are fundamental beliefs at the center of all we do. They are our guiding principles that dictate our actions and behaviors. Our Values are deeply embedded into our culture in big and small ways and even help us decide right from wrong when the path forward is unclear. At Pindrop, we believe in taking accountability to make decisions and act in a way that reflects who we are. We truly believe making decisions and acting with our Core Values in mind will help us to achieve our goals and keep Pindrop a great place to work:\n\u2022 Audaciously Innovate - We continue to change the world, and the way people safely engage and interact with technology. As first principle thinkers, we challenge standards, take risks and learn from our mistakes in order to make positive change and continuous improvement. We believe nothing is impossible.\n\u2022 Evangelical Customers for Life - We delight, inspire and empower customers from day one and for life. We create a partnership and experience that results in a shared passion. We are champions for our customers, and our customers become our champions, creating a universal commitment to one another.\n\u2022 Execution Excellence - We do what we say and say what we do. We are accountable for making the tough decisions and necessary tradeoffs to deliver quality and effective solutions on time.\n\u2022 Win as a Company - Every time we win, we win as a company. Every time we lose, we lose as a company. We break down silos, support one another, embrace diversity and celebrate our successes. We are better together.\n\u2022 Make a Difference - Every day we have the opportunity to make a positive impact. We operate with dedication, passion, and uncompromising integrity, creating a safer, more secure world.\n\nNot sure if this is you?\n\nWe want a diverse, global team, with a broad range of experience and perspectives. If this job sounds great, but you\u2019re not sure if you qualify, apply anyway! We carefully consider every application and will either move forward with you, find another team that might be a better fit, keep in touch for future opportunities, or thank you for your time.\n\nPindrop is an Equal Opportunity Employer\n\nHere at Pindrop, it is our mission to create and maintain a diverse and inclusive work environment. As an equal opportunity employer, all qualified applicants receive consideration for employment without regard to race, color, age, religion, sex, gender, gender identity or expression, sexual orientation, national origin, genetic information, disability, marital and/or veteran status.\n\n#LI-remote", "job_is_remote": true, "job_posted_at_timestamp": 1710270840, "job_posted_at_datetime_utc": "2024-03-12T19:14:00.000Z", "job_city": null, "job_state": null, "job_country": "US", "job_latitude": 37.09024, "job_longitude": -95.71289, "job_benefits": ["dental_coverage", "health_insurance", "paid_time_off"], "job_google_link": "https://www.google.com/search?gl=us&hl=en&rciv=jb&q=manager+of+brand+partnerships&start=40&ibp=htl;jobs#fpstate=tldetail&htivrt=jobs&htiq=manager+of+brand+partnerships&htidocid=nwlYstvqhvBBHIbxAAAAAA%3D%3D", "job_offer_expiration_datetime_utc": "2024-04-11T00:00:00.000Z", "job_offer_expiration_timestamp": 1712793600, "job_required_experience": {"no_experience_required": false, "required_experience_in_months": null, "experience_mentioned": true, "experience_preferred": false}, "job_required_skills": null, "job_required_education": {"postgraduate_degree": false, "professional_certification": false, "high_school": false, "associates_degree": false, "bachelors_degree": true, "degree_mentioned": false, "degree_preferred": false, "professional_certification_mentioned": false}, "job_experience_in_place_of_education": false, "job_min_salary": null, "job_max_salary": null, "job_salary_currency": null, "job_salary_period": null, "job_highlights": {"Qualifications": ["You are a self-driven and motivated individual with a goal setting frame of mind", "You are an exceptional communicator", "You are resilient in the face of challenges, change, and ambiguity", "You are optimistic and believe that you can make a problem into a solution", "You are resourceful, excited to uncover innovative solutions and teach yourself something new when needed", "You are nimble and adaptable when priorities change and continue to see the \u201cforest through the trees\u201d", "8+ years experience in strategic sales for enterprise software", "Success closing license sales deals of 7 figures or more and experience with Complex contract management", "Experience selling a complex product to executive buyers", "Experience setting up and running a new territory for an established software company", "Proven record of successful selling, business development, executive level influence, negotiation, and exceptional communication and presence", "Must be able to self-prospect to build qualified pipeline", "Strong acumen in technology and ability to articulate solution value proposition", "Ability to manage multiple opportunities to meet deadlines, setting direction for and ensuring the success of all sales and customer interactions", "Ability to work closely and cross functionally with engineering, marketing and product management as well as experience working with partners and alliances, and other internal stakeholders", "Must possess the appropriate level of math and analytical skill required to construct a financial business case"], "Responsibilities": ["You will be responsible for developing and managing relationships with channel partners, as well as selling our products and services directly to customers", "Conduct market research to identify selling opportunities and customer needs", "Develop comprehensive Go To Market strategy for Pindrop Products leveraging direct and indirect channels", "Actively seek out new sales leads and prospects through cold calling, networking, and social media", "Conduct meetings with potential clients and partners to identify potential opportunities", "Prepare and deliver presentations and demos on our products and services", "Negotiate and close deals with customers and partners, ensuring mutual satisfaction and long-term collaboration", "Provide support and training to partners and customers, as well as feedback and insights to our internal teams", "Monitor and report on sales performance, partner performance, and market trends", "Participate in industry events and exhibitions to promote our brand and products", "Acquire and integrate industry and market knowledge related to the competitive landscape, emerging fraud risk trends, and technologies in order to successfully sell", "Understand the high-level workings of Call Flows", "Present the IVR pitch to your manager and team", "Develop a forecast for 1H of 2024 and 2H of 2024", "Conduct solo intro meetings with Contact Center Week"], "Benefits": ["Competitive salary", "Company holidays and company-wide rest days", "Unlimited paid time off", "Remote-first culture - including initial and monthly work from home allowance", "Annual professional development and learning budget", "Pick your own Apple MacBook Pro", "Pension scheme & salary exchange option", "Medical and Dental insurance/Private Health care", "Life Insurance and Critical Illness Insurance", "Flex schedules", "Best in class tools and tech stack", "Fun activities to celebrate our accomplishments as a team"]}, "job_job_title": "Manager", "job_posting_language": "en", "job_onet_soc": "41401200", "job_onet_job_zone": "4"}