{"job_id": "fYs2AzWcjlhPatahAAAAAA==", "employer_name": "Kforce Technology Staffing", "employer_logo": "https://encrypted-tbn0.gstatic.com/images?q=tbn:ANd9GcTc3LFz-DHalAzi-EqqOIhRdXo4xyXOiqy43Ghu&s=0", "employer_website": null, "employer_company_type": null, "job_publisher": "Dice", "job_employment_type": "FULLTIME", "job_title": "Remote Senior Data Scientist", "job_apply_link": "https://www.dice.com/job-detail/07fb3ed3-debe-402c-ac20-3fcf0ab3f05a", "job_apply_is_direct": false, "job_apply_quality_score": 0.5615, "apply_options": [{"publisher": "Dice", "apply_link": "https://www.dice.com/job-detail/07fb3ed3-debe-402c-ac20-3fcf0ab3f05a", "is_direct": false}, {"publisher": "Talent.com", "apply_link": "https://www.talent.com/view?id=e4e851d0fed0", "is_direct": false}], "job_description": "RESPONSIBILITIES:\nKforce's client is looking for a Remote Senior Data Scientist.\n\nOverview:\nThe Senior Data Scientist is a key technical position and plays an important role in the organization by leading and performing number of activities related to the company's Information Technology functions. The candidate is responsible for leading the development and deployment of innovative and impactful data products and services that solve various business problems and create value for the company and its customers. The role requires a strong background in machine learning, statistics, programming, and data engineering, as well as excellent communication and collaboration skills. The Senior Data Scientist works closely with other data scientists, engineers, product managers, and stakeholders to understand the business needs, define the data requirements, design, and implement the data pipelines and workflows, apply and evaluate the machine learning models, and deliver and communicate the data analysis results and findings. The candidate also mentors and coaches' junior data scientists and engineers, and stays updated with the latest research and trends in data science and related fields.\n\nEssential Functions:\n\u2022 Lead the development and deployment of sophisticated analytics models to predict, quantify, and interpret complex data related to mortgage lending; Utilize machine learning, statistical analysis, and other advanced techniques to improve decision-making processes, risk assessment, and customer segmentation\n\u2022 Work closely with business units to identify opportunities for leveraging company data to drive business solutions; Innovate and implement new modeling techniques and algorithms for predictive analytics and data mining projects; Act as a thought leader, staying abreast of the latest industry trends and technologies in data science\n\nREQUIREMENTS:\n\u2022 Bachelor's degree, BS in Statistics, Computer Science, Data Science, or related quantitative field is required, along with a minimum of five years' experience in Data Science related role\n\u2022 Expertise in statistical software (e.g., R, SAS), programming languages (e.g., Python, SQL), and big data technologies (e.g., Hadoop, Spark). Strong experience with machine learning libraries (e.g., scikit-learn, TensorFlow). data visualization tools are a plus (e.g., Tableau, Power BI)\n\u2022 Proven experience with data lake and warehouse best practices and leading products in the marketplace\n\u2022 Experience collecting structured, semi-structured and unstructured data in various popular formats and sourced from internal core systems as well as 3rd partner providers such as Google Analytics, Facebook Insights, Zillow, and CoreLogic\n\u2022 Exceptional analytical and quantitative problem-solving skills; Ability to work with complex datasets and extract meaningful insights; Strong understanding of statistical analysis, predictive modeling, and machine learning algorithms\n\u2022 Demonstrated ability to lead and manage projects and teams; Strong mentoring and coaching skills to nurture talent within the team; Ability to inspire and drive innovation\n\u2022 Strong strategic thinking and planning abilities; Ability to align data science activities with business objectives; Proven capability to work under pressure and adapt to changing business environments\n\u2022 Ability to prioritize multiple tasks in a deadline-driven environment, strong sense of urgency and responsiveness\n\u2022 Strong detail orientation and highly organized with proven ability to lead effectively and drive results in a matrixed management environment\n\u2022 Ability to think critically, including the ability to evaluate facts and data to draw conclusions, determine the downstream impact of decisions and associated risks\n\u2022 Self-starter with the demonstrated ability to learn/adapt to new technologies and techniques\n\nThe pay range is the lowest to highest compensation we reasonably in good faith believe we would pay at posting for this role. We may ultimately pay more or less than this range. Employee pay is based on factors like relevant education, qualifications, certifications, experience, skills, seniority, location, performance, union contract and business needs. This range may be modified in the future.\n\nWe offer comprehensive benefits including medical/dental/vision insurance, HSA, FSA, 401(k), and life, disability & ADD insurance to eligible employees. Salaried personnel receive paid time off. Hourly employees are not eligible for paid time off unless required by law. Hourly employees on a Service Contract Act project are eligible for paid sick leave.\n\nNote: Pay is not considered compensation until it is earned, vested and determinable. The amount and availability of any compensation remains in Kforce's sole discretion unless and until paid and may be modified in its discretion consistent with the law.\n\nThis job is not eligible for bonuses, incentives or commissions.\n\nKforce is an Equal Opportunity/Affirmative Action Employer. All qualified applicants will receive consideration for employment without regard to race, color, religion, sex, pregnancy, sexual orientation, gender identity, national origin, age, protected veteran status, or disability status.", "job_is_remote": true, "job_posted_at_timestamp": 1709325199, "job_posted_at_datetime_utc": "2024-03-01T20:33:19.000Z", "job_city": "San Diego", "job_state": "CA", "job_country": "US", "job_latitude": 32.715736, "job_longitude": -117.16109, "job_benefits": ["retirement_savings", "paid_time_off", "health_insurance", "dental_coverage"], "job_google_link": "https://www.google.com/search?gl=us&hl=en&rciv=jb&q=senior+data+scientist&start=70&ibp=htl;jobs#fpstate=tldetail&htivrt=jobs&htiq=senior+data+scientist&htidocid=fYs2AzWcjlhPatahAAAAAA%3D%3D", "job_offer_expiration_datetime_utc": "2024-04-03T03:41:51.000Z", "job_offer_expiration_timestamp": 1712115711, "job_required_experience": {"no_experience_required": false, "required_experience_in_months": 60, "experience_mentioned": true, "experience_preferred": true}, "job_required_skills": ["Information Technology", "Machine Learning (ML)", "Data engineering", "Data Analysis", "Data Science", "Statistics", "Decision-making", "Risk assessment", "Predictive analytics", "Data mining", "Computer science", "SAS", "Big data", "scikit-learn", "Data Visualization", "A+", "Microsoft Power BI", "data lake", "Unstructured data", "AS3", "Google Analytics", "Problem solving", "Predictive modelling", "Strategic thinking", "Data", "Leadership", "Software deployment", "Software development", "Communication", "Collaboration", "Design", "Workflow", "Research", "Analytics", "Mortgage", "Modeling", "Algorithms", "ACT", "R", "Python", "SQL", "Apache Hadoop", "Apache Spark", "TensorFlow", "Tableau", "Warehouse", "Research and development", "Facebook", "Analytical skill", "Management", "Mentorship", "Coaching", "Innovation", "Planning", "Organized", "IMPACT", "Insurance", "FSA", "Law"], "job_required_education": {"postgraduate_degree": false, "professional_certification": false, "high_school": false, "associates_degree": false, "bachelors_degree": false, "degree_mentioned": true, "degree_preferred": true, "professional_certification_mentioned": true}, "job_experience_in_place_of_education": false, "job_min_salary": 140000, "job_max_salary": 160000, "job_salary_currency": "USD", "job_salary_period": "YEAR", "job_highlights": {"Qualifications": ["Bachelor's degree, BS in Statistics, Computer Science, Data Science, or related quantitative field is required, along with a minimum of five years' experience in Data Science related role", "Proven experience with data lake and warehouse best practices and leading products in the marketplace", "Experience collecting structured, semi-structured and unstructured data in various popular formats and sourced from internal core systems as well as 3rd partner providers such as Google Analytics, Facebook Insights, Zillow, and CoreLogic", "Exceptional analytical and quantitative problem-solving skills; Ability to work with complex datasets and extract meaningful insights; Strong understanding of statistical analysis, predictive modeling, and machine learning algorithms", "Demonstrated ability to lead and manage projects and teams; Strong mentoring and coaching skills to nurture talent within the team; Ability to inspire and drive innovation", "Strong strategic thinking and planning abilities; Ability to align data science activities with business objectives; Proven capability to work under pressure and adapt to changing business environments", "Ability to prioritize multiple tasks in a deadline-driven environment, strong sense of urgency and responsiveness", "Strong detail orientation and highly organized with proven ability to lead effectively and drive results in a matrixed management environment", "Ability to think critically, including the ability to evaluate facts and data to draw conclusions, determine the downstream impact of decisions and associated risks", "Self-starter with the demonstrated ability to learn/adapt to new technologies and techniques"], "Responsibilities": ["The candidate is responsible for leading the development and deployment of innovative and impactful data products and services that solve various business problems and create value for the company and its customers", "The Senior Data Scientist works closely with other data scientists, engineers, product managers, and stakeholders to understand the business needs, define the data requirements, design, and implement the data pipelines and workflows, apply and evaluate the machine learning models, and deliver and communicate the data analysis results and findings", "The candidate also mentors and coaches' junior data scientists and engineers, and stays updated with the latest research and trends in data science and related fields", "Lead the development and deployment of sophisticated analytics models to predict, quantify, and interpret complex data related to mortgage lending; Utilize machine learning, statistical analysis, and other advanced techniques to improve decision-making processes, risk assessment, and customer segmentation", "Work closely with business units to identify opportunities for leveraging company data to drive business solutions; Innovate and implement new modeling techniques and algorithms for predictive analytics and data mining projects; Act as a thought leader, staying abreast of the latest industry trends and technologies in data science"], "Benefits": ["We offer comprehensive benefits including medical/dental/vision insurance, HSA, FSA, 401(k), and life, disability & ADD insurance to eligible employees", "Salaried personnel receive paid time off", "Hourly employees are not eligible for paid time off unless required by law", "Hourly employees on a Service Contract Act project are eligible for paid sick leave", "The amount and availability of any compensation remains in Kforce's sole discretion unless and until paid and may be modified in its discretion consistent with the law", "This job is not eligible for bonuses, incentives or commissions"]}, "job_job_title": "Data scientist", "job_posting_language": "en", "job_onet_soc": "15111100", "job_onet_job_zone": "5"}