{"job_id": "uCGCb6fuzslOlioJAAAAAA==", "employer_name": "FactSet", "employer_logo": "https://go.factset.com/hubfs/Logos%20and%20Icons/FactSet%20Logos/factset-logo.svg", "employer_website": "http://www.factset.com", "employer_company_type": "Information", "job_publisher": "LinkedIn", "job_employment_type": "FULLTIME", "job_title": "Lead Cloud Architect", "job_apply_link": "https://www.linkedin.com/jobs/view/lead-cloud-architect-at-factset-3862934706", "job_apply_is_direct": false, "job_apply_quality_score": 0.6199, "apply_options": [{"publisher": "LinkedIn", "apply_link": "https://www.linkedin.com/jobs/view/lead-cloud-architect-at-factset-3862934706", "is_direct": false}, {"publisher": "Talentify", "apply_link": "https://www.talentify.io/job/lead-cloud-architect-chicago-illinois-factset-r23205", "is_direct": false}], "job_description": "Cloud has and remains a core enabler for several of our enterprise strategies: rounding the corner on Digital Transformation, executing on M&A, driving Investment Programs, and enabling GenAI. The Platform Infrastructure Engineering Team at FactSet is looking for an additional member for the Cloud Architecture team. The team is comprised of Cloud Architects and Engineers, focusing on overall Cloud Architecture strategy & execution, and enablement of the organization to create and run optimized Cloud Native solutions on AWS and Azure. The Lead Cloud Architect will help maximize the benefit FactSet receives from its usage of public cloud. The architect will directly contribute to the growth of the business by partnering with Strategic Business Units and Engineering teams to promote modernization, leveling up Cloud knowledge, increasing collaboration across the organization and helping to realize FactSet\u2019s Cloud Architecture strategy.\n\nResponsibilities:\n\u2022 Supports the planning and implementation of enterprise Cloud Programs\n\u2022 Make meaningful contributions to FactSets cloud platform and capabilities.\n\u2022 Fosters a culture of innovation and encourages colleagues to think differently in finding solutions.\n\u2022 Focuses on providing efficient business value; ensuring programs are delivered as efficiently as possible.\n\u2022 Work with other Platform Infrastructure Engineering teams to help drive adoption of cloud services.\n\u2022 Ensures core FactSet Infrastructure services are available in the cloud and easily consumable by FactSet engineering teams.\n\u2022 Increase velocity of cloud migration and digital transformation by helping engineering teams adopt DevOps, Infrastructure as Code, and automated release processes.\n\u2022 Work with FactSet security organization to ensure a strong security posture of services and data in the cloud.\n\u2022 Provide input and assistance on high availability (HA) and disaster recovery (DR) of services running in the cloud. Develop processes and tooling to help engineering teams implement these HA & DR strategies for critical services deployed in the cloud.\n\u2022 Identify and implement cost optimization strategies for cloud services.\n\nMinimum Requirements:\n\u2022 5 or more years of hands-on public cloud experience successfully making architecture contributions in a fast-paced, high growth business with demonstrable experience leading cross-functional technology teams, planning, capital expense budgeting, and process improvement.\n\nCritical Skills:\n\u2022 3+ years AWS experience working in a highly distributed fast paced environment.\n\u2022 Leadership experience\n\u2022 Proven track record of being an innovative and pragmatic technology expert.\n\u2022 Understanding of Cloud Computing technologies.\n\u2022 Strong Working knowledge of one or more of the following: Python, GoLang, Terraform, CloudFormation, or Ansible\n\u2022 Experience with Docker, EC2/ASG, Serverless (Lambda), ECS/EKS\n\u2022 Strong foundational knowledge on AWS Networking services: VPC, TGW, Direct Connect, ALB/NLB, PrivateLink\n\u2022 Knowledge of Generative AI and AI/ML tools & techniques\n\u2022 Strong desire for learning new tech and solving challenging engineering problems.\n\nAdditional Skills:\n\u2022 Excellent communication skills, with the ability to lead business and technology discussions at all levels.\n\u2022 Ability to review initiatives, understand detailed business processes and technology, and make timely decisive decisions.\n\u2022 Track record of being a change agent, one who can drive new and commercial thinking across the organization and the behaviors supporting such, while engaging in a collaborative, inclusive style\n\u2022 Strategic, analytical, and creative thinking style with a realistic, pragmatic approach\n\nEducation:\n\u2022 Bachelor\u2019s degree in information/computer science, engineering, or related discipline with IT focus required.\n\nThe budgeted salary range for this position in the states of California, Connecticut and New York is $140,800.00 - $186,000.00.\n\nAt FactSet, we celebrate diversity of thought, experience, and perspective. We are committed to disrupting bias and a transparent hiring process. All qualified applicants will be considered for employment regardless of race, color, ancestry, religion, sex, national origin, sexual orientation, age, citizenship, marital status, disability, gender identity or veteran status. FactSet participates in E-Verify.\n\nFactSet is an Equal Opportunity Employer \u2013 M/F/Veteran/Disability/Sexual Orientation/Gender Identity\n\nAt FactSet, we celebrate diversity of thought, experience, and perspective. We are committed to disrupting bias and a transparent hiring process. All qualified applicants will be considered for employment regardless of race, color, ancestry, religion, sex, national origin, sexual orientation, age, citizenship, marital status, disability, gender identity or veteran status. FactSet participates in E-Verify\n\nFactSet is an Equal Opportunity Employer \u2013 M/F/Veteran/Disability/Sexual Orientation/Gender Identity", "job_is_remote": false, "job_posted_at_timestamp": 1710797888, "job_posted_at_datetime_utc": "2024-03-18T21:38:08.000Z", "job_city": "Chicago", "job_state": "IL", "job_country": "US", "job_latitude": 41.878113, "job_longitude": -87.6298, "job_benefits": null, "job_google_link": "https://www.google.com/search?gl=us&hl=en&rciv=jb&q=cloud+architect&start=30&ibp=htl;jobs#fpstate=tldetail&htivrt=jobs&htiq=cloud+architect&htidocid=uCGCb6fuzslOlioJAAAAAA%3D%3D", "job_offer_expiration_datetime_utc": "2024-04-17T21:38:08.000Z", "job_offer_expiration_timestamp": 1713389888, "job_required_experience": {"no_experience_required": false, "required_experience_in_months": 60, "experience_mentioned": true, "experience_preferred": false}, "job_required_skills": null, "job_required_education": {"postgraduate_degree": false, "professional_certification": false, "high_school": false, "associates_degree": false, "bachelors_degree": true, "degree_mentioned": true, "degree_preferred": true, "professional_certification_mentioned": false}, "job_experience_in_place_of_education": false, "job_min_salary": null, "job_max_salary": null, "job_salary_currency": null, "job_salary_period": null, "job_highlights": {"Qualifications": ["5 or more years of hands-on public cloud experience successfully making architecture contributions in a fast-paced, high growth business with demonstrable experience leading cross-functional technology teams, planning, capital expense budgeting, and process improvement", "3+ years AWS experience working in a highly distributed fast paced environment", "Leadership experience", "Proven track record of being an innovative and pragmatic technology expert", "Understanding of Cloud Computing technologies", "Strong Working knowledge of one or more of the following: Python, GoLang, Terraform, CloudFormation, or Ansible", "Experience with Docker, EC2/ASG, Serverless (Lambda), ECS/EKS", "Strong foundational knowledge on AWS Networking services: VPC, TGW, Direct Connect, ALB/NLB, PrivateLink", "Knowledge of Generative AI and AI/ML tools & techniques", "Strong desire for learning new tech and solving challenging engineering problems", "Excellent communication skills, with the ability to lead business and technology discussions at all levels", "Ability to review initiatives, understand detailed business processes and technology, and make timely decisive decisions", "Track record of being a change agent, one who can drive new and commercial thinking across the organization and the behaviors supporting such, while engaging in a collaborative, inclusive style", "Strategic, analytical, and creative thinking style with a realistic, pragmatic approach", "Bachelor\u2019s degree in information/computer science, engineering, or related discipline with IT focus required"], "Responsibilities": ["The architect will directly contribute to the growth of the business by partnering with Strategic Business Units and Engineering teams to promote modernization, leveling up Cloud knowledge, increasing collaboration across the organization and helping to realize FactSet\u2019s Cloud Architecture strategy", "Supports the planning and implementation of enterprise Cloud Programs", "Make meaningful contributions to FactSets cloud platform and capabilities", "Fosters a culture of innovation and encourages colleagues to think differently in finding solutions", "Focuses on providing efficient business value; ensuring programs are delivered as efficiently as possible", "Work with other Platform Infrastructure Engineering teams to help drive adoption of cloud services", "Ensures core FactSet Infrastructure services are available in the cloud and easily consumable by FactSet engineering teams", "Increase velocity of cloud migration and digital transformation by helping engineering teams adopt DevOps, Infrastructure as Code, and automated release processes", "Work with FactSet security organization to ensure a strong security posture of services and data in the cloud", "Provide input and assistance on high availability (HA) and disaster recovery (DR) of services running in the cloud", "Develop processes and tooling to help engineering teams implement these HA & DR strategies for critical services deployed in the cloud", "Identify and implement cost optimization strategies for cloud services"], "Benefits": ["The budgeted salary range for this position in the states of California, Connecticut and New York is $140,800.00 - $186,000.00"]}, "job_job_title": "Cloud architect", "job_posting_language": "en", "job_onet_soc": "15119900", "job_onet_job_zone": "4", "job_naics_code": "518210", "job_naics_name": "Data Processing, Hosting, and Related Services"}