{"job_id": "XO0jZDkENImtxH-xAAAAAA==", "employer_name": "DePaul Community Resources", "employer_logo": null, "employer_website": null, "employer_company_type": null, "job_publisher": "The Chronicle Of Philanthropy Jobs", "job_employment_type": "FULLTIME", "job_title": "Vice President of Marketing and Development", "job_apply_link": "https://jobs.philanthropy.com/job/42657/vice-president-of-marketing-and-development/", "job_apply_is_direct": false, "job_apply_quality_score": 0.8246, "apply_options": [{"publisher": "The Chronicle Of Philanthropy Jobs", "apply_link": "https://jobs.philanthropy.com/job/42657/vice-president-of-marketing-and-development/", "is_direct": false}, {"publisher": "BeBee", "apply_link": "https://us.bebee.com/job/20240315-e8bd0cd878a89a7af97c052dbf16ee39", "is_direct": false}, {"publisher": "Trabajo.org", "apply_link": "https://us.trabajo.org/job-1842-20240315-742af40757128098eb2994909bb88f53", "is_direct": false}, {"publisher": "Learn4Good", "apply_link": "https://www.learn4good.com/jobs/virginia/marketing_and_pr/2996912432/e/", "is_direct": false}], "job_description": "DePaul Community Resources is seeking a Vice President\nof Marketing & Development.\n\nWe invite experienced marketing and development professionals to\njoin our dynamic team and contribute to our mission of making a\npositive impact in the community. If you possess the skills and\nvision to lead our marketing and development initiatives, we\nencourage you to apply and be a key part of our organization's\ngrowth and success. This position may work out of any DePaul\noffice location in Virginia.\n\nThe desired candidate should have:\n\nProven expertise in executing special events, board member\nstewardship, strategic plan development, donor cultivation, and\nexecutive team leadership. Demonstrated success in supervisory or\nmanagerial roles overseeing marketing and development teams, with a\ncomprehensive understanding of marketing budgets and their\napplication in the non-profit sector.\n\nAbout DePaul\nCommunity\nResources:\n\nFor 47 years, DePaul Community Resources has opened doors to\nhope and belonging for families and individuals across Central and\nSouthwest Virginia. As a social impact organization, DePaul strives\nevery day to change the world by improving the lives of children,\nfamilies, and individuals with developmental disabilities.\n\nDePaul exists to address the gaps where resources are lacking to\nimprove the quality of life of these individuals. Its Child and\nFamily Services (CFS) division provides foster care, independent\nliving, outpatient counseling, and adoption to prepare foster\nchildren and adoptive families with the services and support\nnecessary for each waiting child to find a permanent, forever\nhome.\n\nThe Developmental Disabilities Division is committed to\nincreasing self-sufficiency and promoting the growth of individuals\nthroughout their lives (not just when they were young) through\nsponsored residential programs and the new agency directed services\nprogram. Two daytime support centers not only provide relief and a\ncritical resource for families who have loved ones with\ndevelopmental disabilities but also allow the individuals to\nintegrate and engage with others, elevating the significance of\ntheir dignity and worth.\n\nThrough two service divisions and eleven service locations\nthroughout the state of Virginia \u2014 Child and Family Services and\nDevelopmental Disabilities, 150 staff, a network of nearly 400 care\nproviders, foster and adoptive parents, and a host of volunteers,\nadvocates, and partners, DePaul provides safe homes, permanent\nfamilies, integrated community support, and opportunities for deep\nhealing across Virginia.\n\nJOB SUMMARY:\n\nThe Vice President of Marketing and Development is a member of\nthe Executive Leadership team and leads the agency in marketing,\nexternal communications, public relations, community events, and\nlegislative advocacy and grows the organization's capacity through\ndevelopment strategies and home-finding efforts. The Vice President\nof Marketing and Development leads, guides, and directs all major\nexternal engagement areas as assigned by the Chief Executive\nOfficer (CEO/President). This person must effectively represent the\norganization in the community, build relationships, and work\ncollaboratively in all settings.\n\nSUPERVISION RECEIVED AND EXERCISED:\n\nThe Vice President of Marketing and Development supervises the\nDirector of Development, the Director of Marketing, and an\nAdministrative Assistant and reports directly to the\nCEO/President.\n\nESSENTIAL FUNCTIONS AND DUTIES:\n\nThis list is not an exhaustive & all-inclusive list of job\nresponsibilities. The distribution of time allotted for any\nfunction or duty is subject to change with or without notice.\nNothing in this job description restricts management's right to\nassign other responsibilities to this job or reassign them\nelsewhere at any time.\n\nPLANNING:\n\u2022 Lead, guide, delegate, and direct all major areas of marketing:\npublic and media relations, communication, branding, community\nevents, legislative advocacy, and recruitment of foster care and\nsponsored residential homes\n\u2022 Lead, guide, and direct all major areas of development:\nresearch and prospect identification, cultivation and communication\nstrategies, solicitation strategies, grant writing, donor\nstewardship, database management, communications and outreach\nactivities, and development-related volunteer relations\n\u2022 Ensure the organization is represented well, establish and\nmaintain good relationships with our media and communication\npartners\n\u2022 Work with division and organization leadership teams to\nidentify specific areas of advocacy, marketing, and development\nneeds\n\u2022 Provide leadership, supervision, and oversight for marketing\nand development staff and work collaboratively with all departments\non organizational projects\n\u2022 Develop and adhere to an annual marketing and development\nbudget to ensure proper use of the organization's funds in a\ncost-effective, sustainable manner\n\u2022 Serve as an exemplary advocate for DePaul in the community with\nlocal leaders, religious organizations, business and corporate\npartnerships, and other leaders, and build relationships that\nclosely link the community to the organization\n\u2022 Ensure open communication to create a community, inform and\nreinforce values and connections, and promote a greater\nunderstanding of DePaul's services, standing in the community, and\nfiscal sustainability\n\u2022 Ensure effective methods of communication with stakeholders,\ndesigning regular, meaningful interactions both in and outside the\norganization\n\u2022 Engage external stakeholders, coordinate marketing,\nfundraising, social media, and signature event projects that\nsupport the mission, build brand recognition or community awareness\nof DePaul, and increase alternate revenue streams while remaining\nattentive to an assigned budget\n\nTEAM DEVELOPMENT AND LEADERSHIP:\n\u2022 Hire, supervise, and ensure professional development (high\nperformance and continuous improvement for all marketing and\ndevelopment staff and develop a commitment to quality, customer\nservice, and teamwork within the marketing and development\ndepartments\n\nOPERATIONS:\n\u2022 Ensure alignment of strategic and tactical operations within\nthe department and serve as an active and contributing member of\nthe Executive Leadership team\n\u2022 Ensure accountability to results through regular monitoring and\nreporting of department data\n\u2022 Achieve financial objectives by preparing the annual budget,\nscheduling expenditures, analyzing variances, and estimating return\non investment or ROI\n\u2022 Coordinate media and legislative interests in the organization\nand ensure regular contact with target audiences\n\nMINIMUM REQUIREMENTS TO APPLY:\n\nA bachelor\u2019s degree with five years of demonstrated excellence\nin supervising and leading in marketing, public and media\nrelations, communications, strategic plan development, special\nevents, fundraising, grant writing, and donor cultivation is\nrequired. Experience with board stewardship and creating and\nmanaging budgets in the non-profit sector is desirable.\n\nNOTE:\n\nPlease visit DePaul\u2019s webpage and employment section to view\nmore of the job description. This description provides information\nregarding the essential functions of the designated job and the\ngeneral nature and level of work associated with the job. It should\nnot be interpreted to describe all the duties whose performance may\nbe required of such employees or be used to limit the nature and\nextent of assignments such an individual may be given.\n\nCompensation depends on qualifications and experience.\n\nDePaul is committed to diversity, equity, and inclusion\nand is an Equal Opportunity Employer.\n\nE-Verify Participant.", "job_is_remote": false, "job_posted_at_timestamp": 1710302400, "job_posted_at_datetime_utc": "2024-03-13T04:00:00.000Z", "job_city": "Hollins", "job_state": "VA", "job_country": "US", "job_latitude": 37.341248, "job_longitude": -79.94309, "job_benefits": null, "job_google_link": "https://www.google.com/search?gl=us&hl=en&rciv=jb&q=marketing&start=10&ibp=htl;jobs#fpstate=tldetail&htivrt=jobs&htiq=marketing&htidocid=XO0jZDkENImtxH-xAAAAAA%3D%3D", "job_offer_expiration_datetime_utc": "2024-04-12T03:59:00.000Z", "job_offer_expiration_timestamp": 1712894340, "job_required_experience": {"no_experience_required": false, "required_experience_in_months": null, "experience_mentioned": true, "experience_preferred": false}, "job_required_skills": null, "job_required_education": {"postgraduate_degree": false, "professional_certification": false, "high_school": false, "associates_degree": false, "bachelors_degree": false, "degree_mentioned": true, "degree_preferred": false, "professional_certification_mentioned": false}, "job_experience_in_place_of_education": false, "job_min_salary": null, "job_max_salary": null, "job_salary_currency": null, "job_salary_period": null, "job_highlights": {"Qualifications": ["A bachelor\u2019s degree with five years of demonstrated excellence", "in supervising and leading in marketing, public and media", "Experience with board stewardship and creating and"], "Responsibilities": ["stewardship, strategic plan development, donor cultivation, and", "Demonstrated success in supervisory or", "managerial roles overseeing marketing and development teams, with a", "comprehensive understanding of marketing budgets and their", "children and adoptive families with the services and support", "developmental disabilities but also allow the individuals to", "integrate and engage with others, elevating the significance of", "the Executive Leadership team and leads the agency in marketing,", "legislative advocacy and grows the organization's capacity through", "development strategies and home-finding efforts", "external engagement areas as assigned by the Chief Executive", "collaboratively in all settings", "SUPERVISION RECEIVED AND EXERCISED:", "Director of Development, the Director of Marketing, and an", "Administrative Assistant and reports directly to the", "Lead, guide, delegate, and direct all major areas of marketing:", "research and prospect identification, cultivation and communication", "strategies, solicitation strategies, grant writing, donor", "stewardship, database management, communications and outreach", "activities, and development-related volunteer relations", "Ensure the organization is represented well, establish and", "maintain good relationships with our media and communication", "Work with division and organization leadership teams to", "identify specific areas of advocacy, marketing, and development", "Provide leadership, supervision, and oversight for marketing", "and development staff and work collaboratively with all departments", "Develop and adhere to an annual marketing and development", "budget to ensure proper use of the organization's funds in a", "Serve as an exemplary advocate for DePaul in the community with", "local leaders, religious organizations, business and corporate", "Ensure open communication to create a community, inform and", "reinforce values and connections, and promote a greater", "Ensure effective methods of communication with stakeholders,", "designing regular, meaningful interactions both in and outside the", "Engage external stakeholders, coordinate marketing,", "fundraising, social media, and signature event projects that", "support the mission, build brand recognition or community awareness", "of DePaul, and increase alternate revenue streams while remaining", "Hire, supervise, and ensure professional development (high", "performance and continuous improvement for all marketing and", "development staff and develop a commitment to quality, customer", "service, and teamwork within the marketing and development", "Ensure alignment of strategic and tactical operations within", "the department and serve as an active and contributing member of", "Ensure accountability to results through regular monitoring and", "reporting of department data", "Achieve financial objectives by preparing the annual budget,", "Coordinate media and legislative interests in the organization", "and ensure regular contact with target audiences"], "Benefits": ["families, integrated community support, and opportunities for deep", "Lead, guide, and direct all major areas of development:"]}, "job_job_title": "Vice", "job_posting_language": "en", "job_onet_soc": "11202100", "job_onet_job_zone": "4"}