{"job_id": "dkrPqLLqHwj1RRonAAAAAA==", "employer_name": "Western & Southern Financial Group", "employer_logo": "https://www.westernsouthern.com/-/media/feature/westernsouthern/globals/logos/company-logo-135-years.svg", "employer_website": "http://www.westernsouthern.com", "employer_company_type": "Finance", "job_publisher": "Media Bistro", "job_employment_type": "FULLTIME", "job_title": "Marketing Analytics Manager- Onsite", "job_apply_link": "https://www.mediabistro.com/jobs/152555016-marketing-analytics-manager-onsite", "job_apply_is_direct": false, "job_apply_quality_score": 0.6742, "apply_options": [{"publisher": "Media Bistro", "apply_link": "https://www.mediabistro.com/jobs/152555016-marketing-analytics-manager-onsite", "is_direct": false}], "job_description": "Overview:We are seeking a highly skilled and experienced Marketing Analytics Manager with expertise in Lifetime Value (LTV) modeling, cross channel measurement across lifecycle of customers and their journeys, and audience measurement. As a key member of our marketing team, you will be responsible for driving data-driven insights and recommendations to optimize our marketing strategies and enhance customer acquisition and retention efforts. The ideal candidate will have a strong analytical mindset, a deep understanding of marketing analytics, and the ability to work collaboratively across teams.The position will collaborate with Leadership to develop strategies, tactics and initiatives to help Gerber Life successfully grow its premium stream in an economically viable manner. While promoting efficient growth, the person will oversee the allocation of the Marketing budget across a variety of products, campaigns and audiences. Key metrics include: top of the funnel marketing metrics such as display impressions, TV eyeballs, Direct Mail volumes; middle of the funnel metrics such as site traffic and calls; bottom of the funnel metrics such as Applications, Issues, Policies, Issue Rates, Conversion Rates, Retention Rates, Premium, Life Time Revenue, and Return on Ad spend.The person must love numbers.Responsibilities:Develop, implement, and maintain advanced Lifetime Value (LTV) models to assess customer profitability, customer segmentation, and customer lifetime behavior.Analyze marketing campaigns across multiple channels, including digital, traditional, social media, and offline, to evaluate their effectiveness and identify areas for improvement.Conduct in-depth audience analysis to understand customer behavior, preferences, and trends, and provide actionable insights to enhance targeting and segmentation strategies.Collaborate with cross-functional teams, including marketing, data science, and business intelligence, to ensure alignment on analytics objectives and strategies.Design and execute experiments and A/B tests to measure the impact of marketing initiatives on customer behavior and business performance.Develop and maintain key performance indicators (KPIs) and dashboards to monitor marketing effectiveness and communicate insights to stakeholders.Utilize statistical analysis techniques to uncover patterns, correlations, and trends in large datasets, translating findings into actionable recommendations.Stay up-to-date with industry trends and emerging analytics methodologies, bringing innovative ideas and best practices to the team.Qualifications:Proven experience (5 years) working in marketing analytics or a similar role, preferably in a fast-paced, data-driven environment.Strong expertise in developing and implementing Lifetime Value (LTV) models, customer segmentation, and customer lifetime behavior analysis.Proficiency in statistical analysis tools and programming languages such as Python, R, or SQL.Demonstrated experience working with marketing analytics platforms, web analytics tools, and data visualization tools (e.g., Google Analytics, Tableau, Power BI).Solid understanding of digital marketing channels, attribution models, and audience measurement methodologies.Strong analytical skills with the ability to work with large datasets and derive actionable insights.Excellent communication and presentation skills, with the ability to effectively convey complex analytical concepts to non-technical stakeholders.Strong problem-solving abilities and attention to detail.Ability to work both independently and collaboratively in a cross-functional team environment.A passion for staying ahead of industry trends and leveraging new technologies and methodologies to drive marketing success.Work Setting:This position works in an office setting and remains in a stationary position for long periods of time while working at a desk, on a computer or with other standard office equipment, or while in meetings.Position requires substantial movement of wrist, hands and fingers for continuous computer work.Educational Requirements:Advanced degree in Analytics, Finance or MBA preferred.5 years of experience within Insurance or Financial Services industry or within Marketing analyticsBachelor's degree in Marketing, Statistics, Mathematics, Economics, or a related field. A Master's degree is preferred.Computer Skills and Knowledge of Hardware & Software Required:Advanced Excel skillsIntermediate/advanced PowerPoint skillsStrong quantitative and communication skillsMust code in SQL and PythonProficient in new technology and/or data visualization platforms such as Power BI, Tableau, etc.Proficient in accessing data through Salesforce, DataMart, Google Cloud Platform(GCP), database, or Google Analytics (GA4)Familiarity with Cognos is a plusCertifications & Licenses (i.e., Series 6 & 63, CPA, etc.):NAPosition Demands:Extended hours required during the peak planning period (fall) or during special/ad hoc projectsMinimal travelHighly organized with an adherence to deadlines and commitmentsAbility to provide insight and direction to colleagues that do not possess similar skill setsThe salary ranges posted reflect our targeted base pay hiring range for the position. The final determination on base pay for any position will be determined based on multiple factors to ensure pay equity within the organization. Non-sales positions have the opportunity to participate in a bonus program. Sales positions are eligible for sales incentives whereby total compensation may exceed base salary depending on individual performance.Note: Posted Hiring Salary Range:$120,000-$150,000#J-18808-Ljbffr", "job_is_remote": false, "job_posted_at_timestamp": 1706749200, "job_posted_at_datetime_utc": "2024-02-01T01:00:00.000Z", "job_city": null, "job_state": null, "job_country": "US", "job_latitude": 37.09024, "job_longitude": -95.71289, "job_benefits": null, "job_google_link": "https://www.google.com/search?gl=us&hl=en&rciv=jb&q=marketing+analytics+manager&start=60&ibp=htl;jobs#fpstate=tldetail&htivrt=jobs&htiq=marketing+analytics+manager&htidocid=dkrPqLLqHwj1RRonAAAAAA%3D%3D", "job_offer_expiration_datetime_utc": null, "job_offer_expiration_timestamp": null, "job_required_experience": {"no_experience_required": false, "required_experience_in_months": 60, "experience_mentioned": true, "experience_preferred": true}, "job_required_skills": null, "job_required_education": {"postgraduate_degree": false, "professional_certification": false, "high_school": false, "associates_degree": false, "bachelors_degree": false, "degree_mentioned": true, "degree_preferred": true, "professional_certification_mentioned": true}, "job_experience_in_place_of_education": false, "job_min_salary": null, "job_max_salary": null, "job_salary_currency": null, "job_salary_period": null, "job_highlights": {"Qualifications": ["Strong expertise in developing and implementing Lifetime Value (LTV) models, customer segmentation, and customer lifetime behavior analysis", "Proficiency in statistical analysis tools and programming languages such as Python, R, or SQL", "Demonstrated experience working with marketing analytics platforms, web analytics tools, and data visualization tools (e.g., Google Analytics, Tableau, Power BI)", "Solid understanding of digital marketing channels, attribution models, and audience measurement methodologies", "Strong analytical skills with the ability to work with large datasets and derive actionable insights", "Excellent communication and presentation skills, with the ability to effectively convey complex analytical concepts to non-technical stakeholders", "Strong problem-solving abilities and attention to detail", "Ability to work both independently and collaboratively in a cross-functional team environment.A passion for staying ahead of industry trends and leveraging new technologies and methodologies to drive marketing success", "Work Setting:This position works in an office setting and remains in a stationary position for long periods of time while working at a desk, on a computer or with other standard office equipment, or while in meetings", "Position requires substantial movement of wrist, hands and fingers for continuous computer work", "Computer Skills and Knowledge of Hardware & Software Required:Advanced Excel skills", "Intermediate/advanced PowerPoint skills", "Strong quantitative and communication skills", "Must code in SQL and PythonProficient in new technology and/or data visualization platforms such as Power BI, Tableau, etc", "Certifications & Licenses (i.e., Series 6 & 63, CPA, etc.):NAPosition Demands:Extended hours required during the peak planning period (fall) or during special/ad hoc projects", "Minimal travel", "Highly organized with an adherence to deadlines and commitments", "Ability to provide insight and direction to colleagues that do not possess similar skill sets"], "Responsibilities": ["As a key member of our marketing team, you will be responsible for driving data-driven insights and recommendations to optimize our marketing strategies and enhance customer acquisition and retention efforts", "The position will collaborate with Leadership to develop strategies, tactics and initiatives to help Gerber Life successfully grow its premium stream in an economically viable manner", "While promoting efficient growth, the person will oversee the allocation of the Marketing budget across a variety of products, campaigns and audiences", "Key metrics include: top of the funnel marketing metrics such as display impressions, TV eyeballs, Direct Mail volumes; middle of the funnel metrics such as site traffic and calls; bottom of the funnel metrics such as Applications, Issues, Policies, Issue Rates, Conversion Rates, Retention Rates, Premium, Life Time Revenue, and Return on Ad spend", "The person must love numbers.Responsibilities:Develop, implement, and maintain advanced Lifetime Value (LTV) models to assess customer profitability, customer segmentation, and customer lifetime behavior", "Analyze marketing campaigns across multiple channels, including digital, traditional, social media, and offline, to evaluate their effectiveness and identify areas for improvement", "Conduct in-depth audience analysis to understand customer behavior, preferences, and trends, and provide actionable insights to enhance targeting and segmentation strategies", "Collaborate with cross-functional teams, including marketing, data science, and business intelligence, to ensure alignment on analytics objectives and strategies", "Design and execute experiments and A/B tests to measure the impact of marketing initiatives on customer behavior and business performance", "Develop and maintain key performance indicators (KPIs) and dashboards to monitor marketing effectiveness and communicate insights to stakeholders", "Utilize statistical analysis techniques to uncover patterns, correlations, and trends in large datasets, translating findings into actionable recommendations"], "Benefits": ["The final determination on base pay for any position will be determined based on multiple factors to ensure pay equity within the organization", "Non-sales positions have the opportunity to participate in a bonus program", "Sales positions are eligible for sales incentives whereby total compensation may exceed base salary depending on individual performance.Note: Posted Hiring Salary Range:$120,000-$150,000#J-18808-Ljbffr"]}, "job_job_title": "Analytics manager", "job_posting_language": "en", "job_onet_soc": "11202100", "job_onet_job_zone": "4", "job_naics_code": "524113", "job_naics_name": "Direct Life Insurance Carriers"}