{"job_id": "rzVhPrDJr459aLhfAAAAAA==", "employer_name": "Xebia", "employer_logo": "https://lookaside.fbsbx.com/lookaside/crawler/media/?media_id=100038170517387", "employer_website": "http://www.xebia.com", "employer_company_type": null, "job_publisher": "LinkedIn", "job_employment_type": "FULLTIME", "job_title": "Senior Sales Manager", "job_apply_link": "https://www.linkedin.com/jobs/view/senior-sales-manager-at-xebia-3846598468", "job_apply_is_direct": false, "job_apply_quality_score": 0.6388, "apply_options": [{"publisher": "LinkedIn", "apply_link": "https://www.linkedin.com/jobs/view/senior-sales-manager-at-xebia-3846598468", "is_direct": false}], "job_description": "Who are we?\n\nWith over 20 years of experience, our global network of passionate technologists and pioneering craftsmen deliver cutting-edge technology and game-changing consulting to companies on the brink of transformation. Since 2001, we have grown from a Java company into a full-service digital consulting company with 4500+ professionals working on a worldwide ambition.\n\nWe are organized in complementary chapters \u2013 teams with a tremendous amount of knowledge and experience within a particular field, such as Agile, DevOps, Data and AI, Cloud, Software Technology, Functional Programming, Low Code, and Microsoft.\n\nJob Title: Sr. Sales Manager (Data/AI)\n\nLocation: Remote, USA\n\nAbout the role\n\nWe are seeking a highly motivated Senior Sales Manager with a proven track record in Data/AI solution selling in the services industry to join our team. As the Senior Sales Executive, you will be responsible for developing new business opportunities and driving revenue growth within Xebia\u2019s Data/AI service line.\n\nXebia is actively looking for Data/AI sellers who have 12+ years of experience with ambitions to develop a 3x to 5x sales funnel in the North American region and convert that into revenue by opening net new, greenfield logos as well as mining the existing install base of Xebia for cross-sell opportunities.\n\nResponsibilities\n\nWe are looking for an exceptional Sales leader with strong knowledge in the Data/AI space delivering data/AI solutions to enterprise customers:\n\u2022 Acquire new customers in the Data/AI space across North America\n\u2022 Experience in working with partner ecosystem driving business together via co-sell and sourced revenue\n\u2022 Working on partner activities such as lunch and learns to sales organizations on both the partner side and Xebia side, co-marketing activities such as blogs, webinars, conferences, customer round tables, joint pipeline review, new pipeline creation\n\u2022 Use knowledge of the Data/AI industry, technology, processes, and consultative sales skills to assess and educate clients on the value of our business and implementation expertise\n\u2022 Build long-term relationships with key contacts at target customers\n\u2022 Maximize existing relationships by engaging clients as their primary touchpoint\n\u2022 Utilize strategic client hunting practices, industry/market analysis, internal communication, external promotions, and constant in-depth client analysis to uncover revenue opportunities.\n\u2022 Develop and perform strategic prospecting activities to generate pipeline and grow territory\n\u2022 Build, Manage, and accurately forecast a strong sales pipeline and revenue\n\u2022 Customer profiling, and account planning against set revenue/margin targets by services line at the account level.\n\u2022 Anchor client meetings and pursue opportunities generated with the help of pre-sales, delivery, and external partners.\n\u2022 Build in-depth knowledge of clients' business priorities, challenges, and initiatives that can be translated into opportunities.\n\u2022 Willingness to work with a geographically distributed team structure in an extremely fast-paced and challenging environment.\n\u2022 Understand and respond to clients\u2019 business issues by developing a go-forward roadmap\n\u2022 Has experience in driving and managing large deals.\n\u2022 Continuously learn about Xebia\u2019s offerings, successes, and business ecosystem to share and bring insights to clients.\n\u2022 Using CRM effectively to track opportunities and sales forecasts in a weekly, monthly, quarterly, and annual planning rhythm for your region with high levels of predictability, quality, and accuracy\n\nQualifications\n\u2022 12+ years of experience in software services selling to enterprise accounts, 6+ years experience in selling Data/AI solutions to business and technology stakeholders, understanding of BFSI and Retail verticals is a plus\n\u2022 Demonstrable experience in working with partners such as Snowflake and Databricks\n\u2022 Demonstrable experience in achieving annual revenue targets, primarily on net new logos\n\u2022 Highly referenceable previous/current customers\n\u2022 Experience with the global delivery model, particularly in outsourcing and transformation\n\u2022 Ability to manage in a complex matrix environment and should be strong and focused on Customer Service excellence\n\u2022 Excellent Relationship Building Skills\n\u2022 Excellent communication skills, both oral and written\n\u2022 Large deal sales experience with the global delivery model, particularly in outsourcing and transformation.\n\u2022 Technology background in IT consulting/services or Software Engineering services company understands details of the latest Data/AI technology stack including how the landscape has evolved\n\u2022 Proven ability to land and expand in the acquired customer base, with methodical\n\u2022 Account planning, and mapping with an approach to build and nurture client relationships.\n\u2022 Strong solution-selling background\n\u2022 Legitimate and proven self-starter. Highly motivated to jump in and get things done\n\u2022 Excellent leadership and communications skills required. High comfort level working with all levels of an organization, including C-suite\n\nBenefits\n\u2022 Medical, Dental and Vision Insurance (Subsidized)\n\u2022 Health Savings Account\n\u2022 Flexible Spending Accounts (Healthcare and Dependent Care)\n\u2022 Short-Term and Long-Term Disability\n\u2022 Life and AD&D Insurance\n\u2022 Assistance Program\n\u2022 Unlimited access to LinkedIn learning solutions\n\u2022 Matched 401(k) Retirement Savings Plan\n\u2022 Paid Time Off\n\nXebia is committed to creating an inclusive and diverse environment and is proud to be an equal opportunity employer. All qualified applicants will receive consideration for employment without regard to race, color, religion, gender, gender identity or expression, sexual orientation, national origin, genetics, disability, age, or veteran status.\n\nPlease feel free to share your preferred pronouns with us during the application process.\n\nXebia does not sponsor work visas, either at the time of hire or at any later time. All persons hired will be required to verify identity and eligibility to work in the United States, and to complete any required employment eligibility forms.", "job_is_remote": true, "job_posted_at_timestamp": 1709667092, "job_posted_at_datetime_utc": "2024-03-05T19:31:32.000Z", "job_city": null, "job_state": null, "job_country": "US", "job_latitude": 37.09024, "job_longitude": -95.71289, "job_benefits": ["paid_time_off", "dental_coverage", "retirement_savings", "health_insurance"], "job_google_link": "https://www.google.com/search?gl=us&hl=en&rciv=jb&q=senior+sales+director&start=50&ibp=htl;jobs#fpstate=tldetail&htivrt=jobs&htiq=senior+sales+director&htidocid=rzVhPrDJr459aLhfAAAAAA%3D%3D", "job_offer_expiration_datetime_utc": "2024-04-04T19:31:32.000Z", "job_offer_expiration_timestamp": 1712259092, "job_required_experience": {"no_experience_required": false, "required_experience_in_months": 240, "experience_mentioned": true, "experience_preferred": true}, "job_required_skills": null, "job_required_education": {"postgraduate_degree": false, "professional_certification": false, "high_school": false, "associates_degree": false, "bachelors_degree": true, "degree_mentioned": false, "degree_preferred": false, "professional_certification_mentioned": false}, "job_experience_in_place_of_education": false, "job_min_salary": null, "job_max_salary": null, "job_salary_currency": null, "job_salary_period": null, "job_highlights": {"Qualifications": ["Demonstrable experience in working with partners such as Snowflake and Databricks", "Demonstrable experience in achieving annual revenue targets, primarily on net new logos", "Highly referenceable previous/current customers", "Ability to manage in a complex matrix environment and should be strong and focused on Customer Service excellence", "Excellent Relationship Building Skills", "Excellent communication skills, both oral and written", "Large deal sales experience with the global delivery model, particularly in outsourcing and transformation", "Technology background in IT consulting/services or Software Engineering services company understands details of the latest Data/AI technology stack including how the landscape has evolved", "Proven ability to land and expand in the acquired customer base, with methodical", "Account planning, and mapping with an approach to build and nurture client relationships", "Strong solution-selling background", "Legitimate and proven self-starter", "Highly motivated to jump in and get things done", "Excellent leadership and communications skills required", "High comfort level working with all levels of an organization, including C-suite"], "Responsibilities": ["Acquire new customers in the Data/AI space across North America", "Experience in working with partner ecosystem driving business together via co-sell and sourced revenue", "Working on partner activities such as lunch and learns to sales organizations on both the partner side and Xebia side, co-marketing activities such as blogs, webinars, conferences, customer round tables, joint pipeline review, new pipeline creation", "Use knowledge of the Data/AI industry, technology, processes, and consultative sales skills to assess and educate clients on the value of our business and implementation expertise", "Build long-term relationships with key contacts at target customers", "Maximize existing relationships by engaging clients as their primary touchpoint", "Utilize strategic client hunting practices, industry/market analysis, internal communication, external promotions, and constant in-depth client analysis to uncover revenue opportunities", "Develop and perform strategic prospecting activities to generate pipeline and grow territory", "Build, Manage, and accurately forecast a strong sales pipeline and revenue", "Customer profiling, and account planning against set revenue/margin targets by services line at the account level", "Anchor client meetings and pursue opportunities generated with the help of pre-sales, delivery, and external partners", "Build in-depth knowledge of clients' business priorities, challenges, and initiatives that can be translated into opportunities", "Understand and respond to clients\u2019 business issues by developing a go-forward roadmap", "Continuously learn about Xebia\u2019s offerings, successes, and business ecosystem to share and bring insights to clients", "Using CRM effectively to track opportunities and sales forecasts in a weekly, monthly, quarterly, and annual planning rhythm for your region with high levels of predictability, quality, and accuracy"], "Benefits": ["Medical, Dental and Vision Insurance (Subsidized)", "Health Savings Account", "Flexible Spending Accounts (Healthcare and Dependent Care)", "Short-Term and Long-Term Disability", "Life and AD&D Insurance", "Assistance Program", "Unlimited access to LinkedIn learning solutions", "Matched 401(k) Retirement Savings Plan", "Paid Time Off"]}, "job_job_title": "Sales manager", "job_posting_language": "en", "job_onet_soc": "11202200", "job_onet_job_zone": "4"}