{"job_id": "ZwH41qS9kZC8Nw5WAAAAAA==", "employer_name": "Figment", "employer_logo": "https://encrypted-tbn0.gstatic.com/images?q=tbn:ANd9GcTW_gcsFFxECmJ-tIBb4n6r_RqMAi90hNNYxKH8&s=0", "employer_website": null, "employer_company_type": null, "job_publisher": "Built In", "job_employment_type": "FULLTIME", "job_title": "Lead Data Scientist, Protocol Research", "job_apply_link": "https://builtin.com/job/lead-data-scientist-protocol-research/2379703", "job_apply_is_direct": false, "job_apply_quality_score": 0.6912, "apply_options": [{"publisher": "Built In", "apply_link": "https://builtin.com/job/lead-data-scientist-protocol-research/2379703", "is_direct": false}, {"publisher": "Wellfound", "apply_link": "https://wellfound.com/jobs/2953544-lead-data-scientist-protocol-research", "is_direct": true}], "job_description": "Figment is the world\u2019s leading provider of blockchain infrastructure. We provide the most comprehensive staking solution for our over 200+ institutional clients including exchanges, wallets, foundations, custodians, and large token holders to earn rewards on their crypto assets. These clients rely on Figment\u2019s institutional staking service including rewards optimization, rapid API development, rewards reporting, partner integrations, governance, and slashing protection. Figment is backed by industry experts, financial institutions and our global team across twenty three countries. This all leads to our mission to support the adoption, growth and long term success of the Web3 ecosystem.\n\nWe are a growth stage technology company \u2013 looking for people who are builders and doers. People who are comfortable plotting their course through ambiguity and uncertainty to drive impact and who are excited to work in new ways and empower a generative company culture.\n\nAbout this Role\n\nWe are seeking a Lead Data Scientist with experience in proof of stake protocols to help grow the figment data team.\n\nWe're looking for someone who has strong technical data science skills and the ability to interact with multiple business units. The candidate should be able to identify issues, use data to propose solutions, and clearly convey how to leverage data driven results for effective decision making.\n\nIf you enjoy developing data driven solutions and providing real business impact, then this role may be a good fit for you. Ideal candidates are comfortable working in an unstructured environment, dealing with uncertainty, minimal direction, and working across a range of projects.\n\nResponsibilities\n\u2022 Scoping, planning, and delivering data driven solutions for the Figment Sales and DevOps teams\n\u2022 Using analytics, statistics and machine learning tools to produce solutions\n\u2022 Be the team interface with Sales and DevOps for supporting ad hoc EDA and various reports\n\u2022 Data extraction (python scripts, json files, etc) to building pipelines from various external sources such as; blockchain block explores, APIs and RPCs nodes\n\u2022 Establish new systems and processes and look for opportunities to improve the flow of data\n\u2022 Evaluate new and emerging technologies\n\u2022 Stay up to date with the latest technology, techniques and methods\n\nQualifications\n\u2022 Significant experience with Data Science and Data Solutions\n\u2022 Familiarity with a modern data stack (databases and pipelining, Vis tools, ML platforms )\n\u2022 Results oriented individual with a high EQ and attention to detail\n\u2022 Desire to try new ideas if the first one doesn't work\n\u2022 Team working skills and a collaborative approach to sharing ideas and finding solutions\n\u2022 Experience in one of the following - protocol data, research, writing reports\n\u2022 Familiarity of working with Blockchains or in the Web3 space\n\u2022 Experience with data engineering tasks\n\u2022 Background in cross-functional collaboration with internal teams\n\u2022 Working knowledge of:\n\u2022 Our stack (AWS, Snowflake, jupyterhub, Dagster, dbt, Fivetran, Monte Carlo)\n\u2022 Our tools (Python, Sigma, GitHub, Jira, Slack)\n\nOne of Figment\u2019s core principles is \u201cMaking the Invisible Visible\u201d - ensuring transparency and information sharing in all communication. Figment is committed to transparency regarding pay, benefits, and other compensation types for all internal roles as well as all roles being hired for.\n\nBase Salary: The CAD base salary range for this position is CAD $160,000 - $200,000. The US base salary range for this position is USD $160,000 - $x. This range reflects base salary only, and does not include additional compensation or benefits. For candidates in other countries, the pay range will be disclosed upon your first interview with Figment (being a globally remote company, the list of salary ranges would simply be too long to note here!). The range displayed reflects the minimum and maximum range for a new hire across all Canada or the US. A candidate\u2019s specific pay within the range will be determined by various factors including job-related skills, relevant education, and training.\n\nBenefits: All employees of Figment receive the following competitive benefits. For candidates beyond Canada and the US, benefits will be outlined during your first interview with Figment.\n\u2022 100% remote-first environment, with co-working spaces in our employee \u201chubs\u201d across the globe for those who enjoy a hybrid model\n\u2022 4 weeks of PTO that kick in day one, with an additional 1 week of flex days\n\u2022 Extended company-paid health benefits that kick in day one\n\u2022 Best in class parental leave and flexible arrangements\n\u2022 A home office stipend to create a space that you enjoy working in\n\u2022 Monthly Wifi reimbursement\n\u2022 A yearly Learning & Development budget\n\u2022 401K (US) or RRSP match (Canada)\n\u2022 Stock Options in the company\n\u2022 Competitive bonus (based on company performance) that is distributed bi-annually - we believe that the company\u2019s success should be shared with our employees often\n\u2022 For roles listed within the Sales Department, there is instead a competitive commissions structure which will be outlined during your first interview with Figment\n\u2022 Annual onsite company gatherings and retreats to inspire team bonding, collaboration, and fun!\n\u2022 A culture of honesty, professionalism and risk taking in a high-growth environment\n\nSee here for Figment's Privacy Policy and California Employee Privacy Policy.\n\nFigment is a remote-first company operating with a global footprint across 23 countries. Are you interested in helping us build the future of digital assets?", "job_is_remote": true, "job_posted_at_timestamp": 1710357360, "job_posted_at_datetime_utc": "2024-03-13T19:16:00.000Z", "job_city": null, "job_state": null, "job_country": "US", "job_latitude": 37.09024, "job_longitude": -95.71289, "job_benefits": ["paid_time_off", "retirement_savings", "health_insurance"], "job_google_link": "https://www.google.com/search?gl=us&hl=en&rciv=jb&q=lead+data+scientist&start=20&ibp=htl;jobs#fpstate=tldetail&htivrt=jobs&htiq=lead+data+scientist&htidocid=ZwH41qS9kZC8Nw5WAAAAAA%3D%3D", "job_offer_expiration_datetime_utc": "2024-04-12T00:00:00.000Z", "job_offer_expiration_timestamp": 1712880000, "job_required_experience": {"no_experience_required": false, "required_experience_in_months": null, "experience_mentioned": true, "experience_preferred": false}, "job_required_skills": null, "job_required_education": {"postgraduate_degree": false, "professional_certification": false, "high_school": false, "associates_degree": false, "bachelors_degree": true, "degree_mentioned": false, "degree_preferred": false, "professional_certification_mentioned": false}, "job_experience_in_place_of_education": false, "job_min_salary": 160000, "job_max_salary": 200000, "job_salary_currency": "USD", "job_salary_period": "YEAR", "job_highlights": {"Qualifications": ["We're looking for someone who has strong technical data science skills and the ability to interact with multiple business units", "The candidate should be able to identify issues, use data to propose solutions, and clearly convey how to leverage data driven results for effective decision making", "Significant experience with Data Science and Data Solutions", "Familiarity with a modern data stack (databases and pipelining, Vis tools, ML platforms )", "Results oriented individual with a high EQ and attention to detail", "Desire to try new ideas if the first one doesn't work", "Team working skills and a collaborative approach to sharing ideas and finding solutions", "Experience in one of the following - protocol data, research, writing reports", "Familiarity of working with Blockchains or in the Web3 space", "Experience with data engineering tasks", "Background in cross-functional collaboration with internal teams", "Working knowledge of:", "Our stack (AWS, Snowflake, jupyterhub, Dagster, dbt, Fivetran, Monte Carlo)"], "Responsibilities": ["Scoping, planning, and delivering data driven solutions for the Figment Sales and DevOps teams", "Using analytics, statistics and machine learning tools to produce solutions", "Be the team interface with Sales and DevOps for supporting ad hoc EDA and various reports", "Data extraction (python scripts, json files, etc) to building pipelines from various external sources such as; blockchain block explores, APIs and RPCs nodes", "Establish new systems and processes and look for opportunities to improve the flow of data", "Evaluate new and emerging technologies", "Stay up to date with the latest technology, techniques and methods"], "Benefits": ["Base Salary: The CAD base salary range for this position is CAD $160,000 - $200,000", "The US base salary range for this position is USD $160,000 - $x", "This range reflects base salary only, and does not include additional compensation or benefits", "For candidates in other countries, the pay range will be disclosed upon your first interview with Figment (being a globally remote company, the list of salary ranges would simply be too long to note here!). The range displayed reflects the minimum and maximum range for a new hire across all Canada or the US", "A candidate\u2019s specific pay within the range will be determined by various factors including job-related skills, relevant education, and training", "Benefits: All employees of Figment receive the following competitive benefits", "4 weeks of PTO that kick in day one, with an additional 1 week of flex days", "Extended company-paid health benefits that kick in day one", "Best in class parental leave and flexible arrangements", "A home office stipend to create a space that you enjoy working in", "Monthly Wifi reimbursement", "A yearly Learning & Development budget", "401K (US) or RRSP match (Canada)", "Stock Options in the company", "Competitive bonus (based on company performance) that is distributed bi-annually - we believe that the company\u2019s success should be shared with our employees often", "For roles listed within the Sales Department, there is instead a competitive commissions structure which will be outlined during your first interview with Figment", "Annual onsite company gatherings and retreats to inspire team bonding, collaboration, and fun!"]}, "job_job_title": "Data scientist", "job_posting_language": "en", "job_onet_soc": "15111100", "job_onet_job_zone": "5"}