{"job_id": "GIfxjpqCa_A0Gr8dAAAAAA==", "employer_name": "THE SHADE STORE", "employer_logo": null, "employer_website": null, "employer_company_type": null, "job_publisher": "Paycomonline.net", "job_employment_type": "FULLTIME", "job_title": "Regional Sales Director - Southern California", "job_apply_link": "https://www.paycomonline.net/v4/ats/web.php/jobs/ViewJobDetails?job=89401&clientkey=54B89EEF0C110EB0A28975D3333F99EB", "job_apply_is_direct": false, "job_apply_quality_score": 0.8014, "apply_options": [{"publisher": "Paycomonline.net", "apply_link": "https://www.paycomonline.net/v4/ats/web.php/jobs/ViewJobDetails?job=89401&clientkey=54B89EEF0C110EB0A28975D3333F99EB", "is_direct": false}, {"publisher": "ZipRecruiter", "apply_link": "https://www.ziprecruiter.com/c/THE-SHADE-STORE/Job/Regional-Sales-Director-Southern-California/-in-Los-Angeles,CA?jid=5cd13de6e462ab3c", "is_direct": false}, {"publisher": "Glassdoor", "apply_link": "https://www.glassdoor.com/job-listing/regional-sales-director-southern-california-the-shade-store-JV_IC1146821_KO0,43_KE44,59.htm?jl=1009042897607", "is_direct": true}, {"publisher": "LinkedIn", "apply_link": "https://www.linkedin.com/jobs/view/regional-sales-director-southern-california-at-the-shade-store-3786115236", "is_direct": false}, {"publisher": "Indeed", "apply_link": "https://www.indeed.com/viewjob?jk=a722066572ef5bce", "is_direct": true}, {"publisher": "SimplyHired", "apply_link": "https://www.simplyhired.com/job/KHLMFhmAmqC0Nx_Ad7aBlzIm7CFwzw0P9bm6TPj4Zcw3cXMespXq9w", "is_direct": false}, {"publisher": "BeBee", "apply_link": "https://us.bebee.com/job/20240311-fd1d66f3ae6eb3341f887644c22a84bb", "is_direct": false}, {"publisher": "Jobs Trabajo.org", "apply_link": "https://us.trabajo.org/job-2611-20240225-0ad2dac11a2772a41ecd4423f72d8dbf", "is_direct": false}], "job_description": "Job Details\n\nJob Location: Los Angeles, CA - Los Angeles, CA , CA\n\nSalary Range: Undisclosed\n\nDescription\n\nABOUT THE SHADE STORE\n\nAt The Shade Store, we have handcrafted the finest Shades, Blinds and Drapery for 75 years. We believe designing beautiful custom window treatments should be an effortless experience, so we offer outstanding services to help our customers every step of the way, from inspiration to installation.\n\nWHY WORK AT THE SHADE STORE\n\nWe set out to create a company culture that is enjoyable, rewarding, and where there is continuous upward mobility and growth opportunity. If you work hard, give the company your all, use good judgment, and have a positive attitude then the sky\u2019s the limit. In return, there are numerous perks and benefits including:\n\u2022 Competitive compensation\n\u2022 Comprehensive Medical, Dental and Vision benefits\n\u2022 Generous Paid Time Off inclusive of holidays and flexible floating holidays\n\u2022 401k retirement plan with company matching\n\nPOSITION SUMMARY: Regional Sales Director\n\nCustom made simple is what we strive for to meet our customers\u2019 needs here at The Shade Store.The Regional Director works directly with the Area Managers, Showrooms and Design Consultants to seamlessly deliver on these expectations while driving results and supporting company initiatives. As the Regional Director, you will be responsible for identifying and addressing market trends, supporting Trade initiatives/relationships, and ensuring the Field has and uses all the tools necessary to deliver on company initiatives and financial goals.\n\nWORK ACTIVITIES AND TASKS\n\u2022 Delivering Sales and Profitability\n\u2022 Responsible for Regional Sales plan including detailed Showroom and DC performance.\n\u2022 Monitor sales performance metrics, analyze data, and generate reports in conjunction with the Strategy and Analytics team to identify areas for improvement and make informed strategic decisions\n\u2022 Develop and implement a comprehensive sales strategy for the region that aligns with the company\u2019s growth objective and values.\n\u2022 Reviews Showroom P&L statements for opportunities to control expenses\n\u2022 Monitor new showroom performance and adjust plans as necessary to deliver sales performance and key metric expectations\n\u2022 Eliminate obstacles to driving sales by providing Day to Day support to the Area Managers\n\u2022 Ensure Field teams are focused on sales driving activities\n\u2022 Managing Field Team Performance\n\u2022 Conduct monthly meetings within all designated regions to reinforce corporate communication and initiatives\n\u2022 Ensures Regional compliance to all company initiatives and customer impact time sensitive tasks\n\u2022 Works closely with Operations Team to ensure proper coverage in region including DC transfers and relocations\n\u2022 Support Area Manager with new hire onboarding and on-site training\n\u2022 Interview prospective candidates and play a pivotal role in additional headcount and hiring decisions\n\u2022 Ensure continuous learning and compliance on new process/tools/products; collaborate with QA team\n\u2022 Responsible for career development and team planning across the region\n\u2022 Ensure successful showroom openings in partnership with Area Manager and Operations team\n\u2022 Influencing Market Trends/Relationships\n\u2022 Stays current with industry trends, competitor activities and market dynamics to proactively adapt sales strategies and tactics.\n\u2022 Identify and assess new market opportunities, potential clients, and emerging trends to strategically position the company for growth.\n\u2022 Supports Trade and delivers on strategic alignment and execution\n\u2022 Provide regional insights and best practices to larger corporate team\n\u2022 Facilitate meetings with cross-functional teams to ensure a seamless customer experience from lead generation, product delivery and post installation.\n\u2022 Ensure field team is equipped with necessary tools and strategies to effectively engage clients, exceed sales targets and consistently achieve showroom and key performance metrics.\n\nCORE SKILLS\n\u2022 Ability to pivot business strategies and teams based on sales trends.\n\u2022 Solicits and applies critical feedback from team members and business partners\n\u2022 Demonstrates a Growth Mindset\n\u2022 Experience in effectively leading leaders\n\u2022 Strategic thinker\n\u2022 Actively contributes to meetings as a representative and advocate for their internal/external customer\n\u2022 Action oriented leader that holds teams accountable to deliver on results and brand standards\n\u2022 Experience using sales tracking software/CRM systems\n\u2022 Excellent written, verbal, negotiating and communication skills\n\u2022 Strong attention to detail, organizational skillset and follow up skills\n\nMINIMUM QUALIFICATIONS\n\u2022 Bachelor\u2019s Degree or equivalent experience required\n\u2022 5+ years of successful experience leading, motivating and developing a multi-store team in a sales environment\n\u2022 Proven track record of success in meeting and exceeding sales objectives\n\u2022 Window treatment experience, a plus, and home d\u00e9cor retail/interior design knowledge preferred\n\u2022 Ability to travel within designated region and attend corporate meetings at company headquarters in NY and FL\n\nTHE SHADE STORE offer is contingent upon:\n\u2022 Proof of legal authorization to work in the United States for The Shade Store, which will be confirmed by E-Verify within three business days of your hire date\n\nThe Shade Store provides equal employment opportunities to all employees and applicants without regard to race, color, religion, age, sex, national origin, disability status, genetics, protected veteran status, sexual orientation, gender identity or expression, or any other characteristic protected by federal, state or local laws.\n\nQualifications", "job_is_remote": false, "job_posted_at_timestamp": 1708992000, "job_posted_at_datetime_utc": "2024-02-27T00:00:00.000Z", "job_city": "Los Angeles", "job_state": "CA", "job_country": "US", "job_latitude": 34.05491, "job_longitude": -118.242645, "job_benefits": ["health_insurance", "dental_coverage", "retirement_savings", "paid_time_off"], "job_google_link": "https://www.google.com/search?gl=us&hl=en&rciv=jb&q=sales+director&start=30&ibp=htl;jobs#fpstate=tldetail&htivrt=jobs&htiq=sales+director&htidocid=GIfxjpqCa_A0Gr8dAAAAAA%3D%3D", "job_offer_expiration_datetime_utc": null, "job_offer_expiration_timestamp": null, "job_required_experience": {"no_experience_required": false, "required_experience_in_months": 60, "experience_mentioned": true, "experience_preferred": true}, "job_required_skills": null, "job_required_education": {"postgraduate_degree": false, "professional_certification": false, "high_school": false, "associates_degree": false, "bachelors_degree": false, "degree_mentioned": true, "degree_preferred": false, "professional_certification_mentioned": false}, "job_experience_in_place_of_education": false, "job_min_salary": null, "job_max_salary": null, "job_salary_currency": null, "job_salary_period": null, "job_highlights": {"Qualifications": ["Ability to pivot business strategies and teams based on sales trends", "Experience in effectively leading leaders", "Strategic thinker", "Experience using sales tracking software/CRM systems", "Excellent written, verbal, negotiating and communication skills", "Strong attention to detail, organizational skillset and follow up skills", "Bachelor\u2019s Degree or equivalent experience required", "5+ years of successful experience leading, motivating and developing a multi-store team in a sales environment", "Proven track record of success in meeting and exceeding sales objectives", "Ability to travel within designated region and attend corporate meetings at company headquarters in NY and FL"], "Responsibilities": ["The Regional Director works directly with the Area Managers, Showrooms and Design Consultants to seamlessly deliver on these expectations while driving results and supporting company initiatives", "As the Regional Director, you will be responsible for identifying and addressing market trends, supporting Trade initiatives/relationships, and ensuring the Field has and uses all the tools necessary to deliver on company initiatives and financial goals", "WORK ACTIVITIES AND TASKS", "Delivering Sales and Profitability", "Responsible for Regional Sales plan including detailed Showroom and DC performance", "Monitor sales performance metrics, analyze data, and generate reports in conjunction with the Strategy and Analytics team to identify areas for improvement and make informed strategic decisions", "Develop and implement a comprehensive sales strategy for the region that aligns with the company\u2019s growth objective and values", "Reviews Showroom P&L statements for opportunities to control expenses", "Monitor new showroom performance and adjust plans as necessary to deliver sales performance and key metric expectations", "Eliminate obstacles to driving sales by providing Day to Day support to the Area Managers", "Ensure Field teams are focused on sales driving activities", "Managing Field Team Performance", "Conduct monthly meetings within all designated regions to reinforce corporate communication and initiatives", "Ensures Regional compliance to all company initiatives and customer impact time sensitive tasks", "Works closely with Operations Team to ensure proper coverage in region including DC transfers and relocations", "Support Area Manager with new hire onboarding and on-site training", "Interview prospective candidates and play a pivotal role in additional headcount and hiring decisions", "Ensure continuous learning and compliance on new process/tools/products; collaborate with QA team", "Responsible for career development and team planning across the region", "Ensure successful showroom openings in partnership with Area Manager and Operations team", "Influencing Market Trends/Relationships", "Stays current with industry trends, competitor activities and market dynamics to proactively adapt sales strategies and tactics", "Identify and assess new market opportunities, potential clients, and emerging trends to strategically position the company for growth", "Supports Trade and delivers on strategic alignment and execution", "Provide regional insights and best practices to larger corporate team", "Facilitate meetings with cross-functional teams to ensure a seamless customer experience from lead generation, product delivery and post installation", "Ensure field team is equipped with necessary tools and strategies to effectively engage clients, exceed sales targets and consistently achieve showroom and key performance metrics", "Solicits and applies critical feedback from team members and business partners", "Actively contributes to meetings as a representative and advocate for their internal/external customer", "Action oriented leader that holds teams accountable to deliver on results and brand standards"], "Benefits": ["Competitive compensation", "Comprehensive Medical, Dental and Vision benefits", "Generous Paid Time Off inclusive of holidays and flexible floating holidays", "401k retirement plan with company matching"]}, "job_job_title": "Sales director", "job_posting_language": "en", "job_onet_soc": "11202200", "job_onet_job_zone": "4"}