{"job_id": "7e2mub7jwXelg3_XAAAAAA==", "employer_name": "Jobot", "employer_logo": "https://encrypted-tbn0.gstatic.com/images?q=tbn:ANd9GcREBnMp_EF8_kTTbxQZGaafRjkbfFFjoPqLEjYl&s=0", "employer_website": null, "employer_company_type": null, "job_publisher": "LinkedIn", "job_employment_type": "FULLTIME", "job_title": "Vice President of Sales", "job_apply_link": "https://www.linkedin.com/jobs/view/vice-president-of-sales-at-jobot-3853989998", "job_apply_is_direct": false, "job_apply_quality_score": 0.622, "apply_options": [{"publisher": "LinkedIn", "apply_link": "https://www.linkedin.com/jobs/view/vice-president-of-sales-at-jobot-3853989998", "is_direct": false}, {"publisher": "Monster", "apply_link": "https://www.monster.com/job-openings/vice-president-of-sales-irvine-ca--b48b0320-7c0a-4a61-b194-40c7586fc5b1?mstr_dist=true", "is_direct": true}, {"publisher": "Online Career 360", "apply_link": "https://onlinecareer360.us/job/jobot-hiring-for-vice-president-of-sales-at-irvine-ca/", "is_direct": true}], "job_description": "Want to learn more about this role and Jobot? Click our Jobot logo and follow our LinkedIn page!\n\nJob details\n\nThis Jobot Job is hosted by Randy Kallick\n\nAre you a fit? Easy Apply now by clicking the \"Easy Apply\" button and sending us your resume.\n\nSalary $175,000 - $300,000 per year\n\nA Bit About Us\n\nWe provide high performance memory systems for a diverse number of industries requiring enterprise and storage class memory for critical business decisions. We have been in business for over 20 years and are a successfully traded firm with well over $100M in sales / year.\n\nDesired locations are Orange County, CA or Bay Area, CA Travel as needed for customer visits.\n\nWhy join us?\n\u2022 Competitive compensation structure! Base / Bonus / Commission\n\u2022 Excellent Benefits!\n\u2022 401K Match!\n\u2022 Career Growth!\n\u2022 Work for an expanding firm!\n\nJob Details\n\nJob Details\n\nWe are seeking a seasoned and dynamic Permanent Vice President of Sales to join our leadership team in the fast-paced technology industry. The successful candidate will be a strategic thinker, data-driven, and have a proven track record in leading sales growth, particularly in High-Performance Computing, Solid State Storage, and Modular Memory. This is an exciting opportunity to shape the future of our company, drive innovation, and make a significant impact on our business trajectory.\n\nResponsibilities\n\u2022 Develop and implement strategic sales plans to accommodate corporate goals and drive sales growth. Leading sales for North America and Europe.\n\u2022 Direct sales forecasting activities and set performance goals accordingly.\n\u2022 Review market analyses to determine customer needs, price schedules, and discount rates.\n\u2022 Direct staffing, training, and performance evaluations to develop and control sales programs.\n\u2022 Meet with key clients, assisting sales representatives with maintaining relationships and negotiating and closing deals.\n\u2022 Analyze and control expenditures of division to conform to budgetary requirements.\n\u2022 Prepare periodic sales reports showing sales volume, potential sales, and areas of proposed client base expansion.\n\u2022 Direct product simplification and standardization to eliminate unprofitable items from sales line.\n\u2022 Represent company at trade association meetings to promote product.\n\u2022 Deliver sales presentations to key clients in coordination with sales representatives.\n\u2022 Coordinate liaison between sales department and other sales-related units.\n\u2022 Assist other departments within the organization to prepare manuals and technical publications.\n\u2022 Prepare and deliver sales presentations to new and existing customers to sell new advertising programs, and to protect and increase existing advertising.\n\nQualifications\n\u2022 Bachelor's degree in Business Administration, Marketing, or related field. An MBA is a plus.\n\u2022 Minimum of 5+ years of sales leadership experience in the technology industry.\n\u2022 Must have a background in complex and technical sales, working with engineering at customers\n\u2022 Must have SSD experience, ideally with some semiconductor memory products (e.g.SK, Intel, Micron, Toshiba, Western Digital, Kioxia) will consider other semiconductor IC products. Experience with IP sales is a plus\n\u2022 Strong understanding of customer and market dynamics and requirements.\n\u2022 Proven leadership and ability to drive sales teams.\n\u2022 Exceptional negotiation skills.\n\u2022 Excellent written and verbal communication skills.\n\u2022 Ability to work collaboratively with colleagues and staff to create a results-driven, team-oriented environment.\n\u2022 Experience in strategic planning and execution. Knowledge of contracting, negotiating, and change management.\n\u2022 Experience in planning marketing strategies, advertising campaigns, and successful public relations efforts.\n\nInterested in hearing more? Easy Apply now by clicking the \"Easy Apply\" button.\n\nWant to learn more about this role and Jobot?\n\nClick our Jobot logo and follow our LinkedIn page!", "job_is_remote": false, "job_posted_at_timestamp": 1710324925, "job_posted_at_datetime_utc": "2024-03-13T10:15:25.000Z", "job_city": "Irvine", "job_state": "CA", "job_country": "US", "job_latitude": 33.684566, "job_longitude": -117.82651, "job_benefits": ["retirement_savings"], "job_google_link": "https://www.google.com/search?gl=us&hl=en&rciv=jb&q=vice+president+of+sales&start=20&ibp=htl;jobs#fpstate=tldetail&htivrt=jobs&htiq=vice+president+of+sales&htidocid=7e2mub7jwXelg3_XAAAAAA%3D%3D", "job_offer_expiration_datetime_utc": "2024-04-12T10:15:25.000Z", "job_offer_expiration_timestamp": 1712916925, "job_required_experience": {"no_experience_required": false, "required_experience_in_months": 60, "experience_mentioned": true, "experience_preferred": true}, "job_required_skills": null, "job_required_education": {"postgraduate_degree": false, "professional_certification": false, "high_school": false, "associates_degree": false, "bachelors_degree": true, "degree_mentioned": true, "degree_preferred": true, "professional_certification_mentioned": false}, "job_experience_in_place_of_education": false, "job_min_salary": 175000, "job_max_salary": 300000, "job_salary_currency": "USD", "job_salary_period": "YEAR", "job_highlights": {"Qualifications": ["The successful candidate will be a strategic thinker, data-driven, and have a proven track record in leading sales growth, particularly in High-Performance Computing, Solid State Storage, and Modular Memory", "Bachelor's degree in Business Administration, Marketing, or related field", "Minimum of 5+ years of sales leadership experience in the technology industry", "Must have a background in complex and technical sales, working with engineering at customers", "Must have SSD experience, ideally with some semiconductor memory products (e.g.SK, Intel, Micron, Toshiba, Western Digital, Kioxia) will consider other semiconductor IC products", "Strong understanding of customer and market dynamics and requirements", "Proven leadership and ability to drive sales teams", "Exceptional negotiation skills", "Excellent written and verbal communication skills", "Ability to work collaboratively with colleagues and staff to create a results-driven, team-oriented environment", "Experience in strategic planning and execution", "Knowledge of contracting, negotiating, and change management", "Experience in planning marketing strategies, advertising campaigns, and successful public relations efforts"], "Responsibilities": ["Develop and implement strategic sales plans to accommodate corporate goals and drive sales growth", "Leading sales for North America and Europe", "Direct sales forecasting activities and set performance goals accordingly", "Review market analyses to determine customer needs, price schedules, and discount rates", "Direct staffing, training, and performance evaluations to develop and control sales programs", "Meet with key clients, assisting sales representatives with maintaining relationships and negotiating and closing deals", "Analyze and control expenditures of division to conform to budgetary requirements", "Prepare periodic sales reports showing sales volume, potential sales, and areas of proposed client base expansion", "Direct product simplification and standardization to eliminate unprofitable items from sales line", "Represent company at trade association meetings to promote product", "Deliver sales presentations to key clients in coordination with sales representatives", "Coordinate liaison between sales department and other sales-related units", "Assist other departments within the organization to prepare manuals and technical publications", "Prepare and deliver sales presentations to new and existing customers to sell new advertising programs, and to protect and increase existing advertising"], "Benefits": ["Salary $175,000 - $300,000 per year", "Competitive compensation structure!", "Base / Bonus / Commission", "Excellent Benefits!", "401K Match!"]}, "job_job_title": "Vice", "job_posting_language": "en", "job_onet_soc": "11101100", "job_onet_job_zone": "5"}