{"job_id": "p6k587mZu8IO1omMAAAAAA==", "employer_name": "Boilermaker Road Race", "employer_logo": "https://boilermakerroadrace.myshopify.com/cdn/shop/files/boilermakerlogo-150.png?v=1692205046&width=266", "employer_website": null, "employer_company_type": null, "job_publisher": "LinkedIn", "job_employment_type": "FULLTIME", "job_title": "Marketing & Sponsor Manager", "job_apply_link": "https://www.linkedin.com/jobs/view/marketing-sponsor-manager-at-boilermaker-road-race-3840687567", "job_apply_is_direct": false, "job_apply_quality_score": 0.6409, "apply_options": [{"publisher": "LinkedIn", "apply_link": "https://www.linkedin.com/jobs/view/marketing-sponsor-manager-at-boilermaker-road-race-3840687567", "is_direct": false}], "job_description": "The Marketing & Sponsor Manager position is intended to fulfill multiple functions. It is a collaborative position working closely with the President & the Race Director that requires the competency to multi-task and prioritize a wide array of responsibilities in a demanding, public-facing environment.\n\nThe marketing and public relations aspect includes promotion of the Boilermaker, all of its events and programs, as well as co-marketing efforts with the organization\u2019s roster of corporate sponsors with a heavy emphasis on the use of existing and emerging social media platforms (e.g. Twitter, Instagram, TikTok, Facebook (Meta), etc.).\n\nThe sponsor management aspect involves the nurturing of existing relationships by ensuring overall satisfaction and activations following each sponsor's individual agreement throughout the year, as well as prospecting for new sponsorships across the portfolio of Boilermaker events and any potential new events going forward.\n\nThe balance of the position's responsibilities are of equal importance and cover a diverse cross-section of activities including race direction for certain Boilermaker events and being the primary user of the third-party registration software (RunSignUp & TicketSignUp) the organization uses for event and customer relationship management. Experience in graphic design and/or video editing (Adobe suite of products) and with email marketing software (i.e. MailChimp, Constant Contact, etc.) are a major plus.\n\nESSENTIAL JOB FUNCTIONS:\n\nMarketing Management\n\nIn concert with the President, responsible for the development & execution of the organization's overall marketing strategy.\n\nMedia\n\nTraditional Media\n\n~Engage with local, regional, and to the extent feasible, national media organizations to promote the Boilermaker brand.\n\n~Develop and execute all press-related activities (e.g. press releases, press conferences, etc.)\n\nSocial Media\n\n~Strategic plan development and execution for use on all existing & emerging social media platforms.\n\nRelationship Management of any 3rd party marketing firms the organization engages with.\n\nDevelopment and execution of strategic marketing plans to address:\n\n~Traditional and longtime base of Boilermaker participants\n\n~Recruitment of potential future participants (youth, expanded reach outside local, regional markets, etc.)\n\n~Email strategy, design, and overall management\n\nEvent management\n\n~Ideation, proof of concept, development & execution of potential new events\n\n~Ownership of certain existing events (planning, promotion, and execution perspective)\n\nServe as a project manager on an as-needed basis for the organization as a whole.\n\nSponsor Management\n\nIn concert with the President, responsible for the development & execution of the organization's overall sponsorship strategy.\n\n~Engage in and develop relationships with each sponsor at both the decision-maker and contact-person levels.\n\n~Work to determine the needs of each sponsor and what value their sponsorship brings to their respective organizations.\n\n~Structure annual or multi-year agreements accordingly\n\n~Serve as the front line of communication and coordination for the Boilermaker's roster of sponsors both internally and externally.\n\n~Responsible for the internal coordination and execution of sponsor-based activities and involvement at Boilermaker events.\n\n~Ensure all sponsorship agreement-based deliverables not only meet but exceed expectations. This includes, but is not limited to, sponsorship recognition (website, social media, PSAs, event-based, etc.)\n\n~Create and present sponsorship proposals (PowerPoint, etc.) for use with existing sponsors annually and new sponsor prospecting efforts.\n\n~Conduct post-event recap reports for each sponsor as needed, including quantifiable metrics (e.g. media placements, views, etc.), as well as qualitative results due to the sponsorship.\n\nOther\n\nDue to the nature of the work which requires a non-traditional schedule, Boilermaker employees are expected to:\n\n~Be available for some evening & weekend work, especially during events.\n\n~Support manual labor associated with load-in & load-out activities.\n\n~Be an accessible, consistent decision-maker and problem-solver.\n\n~Complete any other tasks as prescribed by the President and/or the Race Director.\n\nREQUIREMENTS:\n\n\u00b7 Marketing, Communications, Public Relations, or related degree and/or commensurate experience is preferred\n\n\u00b7 High level of familiarity with existing and emerging social media platforms\n\n\u00b7 Exceptional communication, organizational, project & time management skills\n\n\u00b7 Excellent oral and written communication skills (AP style writing)\n\n\u00b7 Ability to work both collaboratively & independently\n\n\u00b7 Flexibility to work some evenings, weekends & other non-traditional business hours\n\n\u00b7 Background in sports, health & fitness marketing, or media is a plus\n\n\u00b7 Marketing, sales & customer relationship experience are a plus\n\n\u00b7 Graphic design skills are a plus (Adobe suite of products, Canva, etc.)\n\nEQUIPMENT LISTING (MACHINES, TOOLS & SOFTWARE):\n\nComputer, Email, Microsoft Outlook/Excel/Word/PowerPoint, ID Flow & event registration software (RunSignUp), Printer, Copier, Fax Machine, Telephone, Scanner, Card Printer, Calculator and power tools.\n\nAdvanced personal computer & related social media skills that include the ability to send/receive e-mail messages, prepare reports, post information to a database or spreadsheet, and perform basic word processing, bookkeeping, and/or data entry.\n\nPHYSICAL ACTIVITIES AND DEMANDS:\n\nModerate Work: Exerting up to 50 pounds of force on rare occasions, up to 30 pounds of force occasionally, up to 10 pounds of force frequently to move objects.\n\nENVIRONMENTAL CONDITIONS:\n\nTypical office environment that does not subject the employee to any hazardous or unpleasant elements. Must wear required safety personal protective equipment when conducting actual race activities.", "job_is_remote": false, "job_posted_at_timestamp": 1708995038, "job_posted_at_datetime_utc": "2024-02-27T00:50:38.000Z", "job_city": null, "job_state": null, "job_country": "US", "job_latitude": 37.09024, "job_longitude": -95.71289, "job_benefits": null, "job_google_link": "https://www.google.com/search?gl=us&hl=en&rciv=jb&q=sponsorship+sales+director&start=10&ibp=htl;jobs#fpstate=tldetail&htivrt=jobs&htiq=sponsorship+sales+director&htidocid=p6k587mZu8IO1omMAAAAAA%3D%3D", "job_offer_expiration_datetime_utc": "2024-03-28T00:50:38.000Z", "job_offer_expiration_timestamp": 1711587038, "job_required_experience": {"no_experience_required": false, "required_experience_in_months": null, "experience_mentioned": true, "experience_preferred": true}, "job_required_skills": ["Events", "Digital Marketing", "Business Relationship Management", "Sponsorship Management", "Email Strategy", "Easily Adaptable", "VBA Excel", "Tiktok Marketing", "Social Media", "Public Relations"], "job_required_education": {"postgraduate_degree": false, "professional_certification": false, "high_school": false, "associates_degree": false, "bachelors_degree": true, "degree_mentioned": false, "degree_preferred": false, "professional_certification_mentioned": false}, "job_experience_in_place_of_education": false, "job_min_salary": null, "job_max_salary": null, "job_salary_currency": null, "job_salary_period": null, "job_highlights": {"Qualifications": ["Experience in graphic design and/or video editing (Adobe suite of products) and with email marketing software (i.e", "MailChimp, Constant Contact, etc.) are a major plus", "High level of familiarity with existing and emerging social media platforms", "Exceptional communication, organizational, project & time management skills", "Excellent oral and written communication skills (AP style writing)", "Ability to work both collaboratively & independently", "Flexibility to work some evenings, weekends & other non-traditional business hours", "Advanced personal computer & related social media skills that include the ability to send/receive e-mail messages, prepare reports, post information to a database or spreadsheet, and perform basic word processing, bookkeeping, and/or data entry", "Moderate Work: Exerting up to 50 pounds of force on rare occasions, up to 30 pounds of force occasionally, up to 10 pounds of force frequently to move objects"], "Responsibilities": ["It is a collaborative position working closely with the President & the Race Director that requires the competency to multi-task and prioritize a wide array of responsibilities in a demanding, public-facing environment", "The sponsor management aspect involves the nurturing of existing relationships by ensuring overall satisfaction and activations following each sponsor's individual agreement throughout the year, as well as prospecting for new sponsorships across the portfolio of Boilermaker events and any potential new events going forward", "The balance of the position's responsibilities are of equal importance and cover a diverse cross-section of activities including race direction for certain Boilermaker events and being the primary user of the third-party registration software (RunSignUp & TicketSignUp) the organization uses for event and customer relationship management", "In concert with the President, responsible for the development & execution of the organization's overall marketing strategy", "~Engage with local, regional, and to the extent feasible, national media organizations to promote the Boilermaker brand", "~Develop and execute all press-related activities (e.g. press releases, press conferences, etc.)", "~Strategic plan development and execution for use on all existing & emerging social media platforms", "Relationship Management of any 3rd party marketing firms the organization engages with", "Development and execution of strategic marketing plans to address:", "~Email strategy, design, and overall management", "~Ideation, proof of concept, development & execution of potential new events", "~Ownership of certain existing events (planning, promotion, and execution perspective)", "Serve as a project manager on an as-needed basis for the organization as a whole", "~Engage in and develop relationships with each sponsor at both the decision-maker and contact-person levels", "~Work to determine the needs of each sponsor and what value their sponsorship brings to their respective organizations", "~Serve as the front line of communication and coordination for the Boilermaker's roster of sponsors both internally and externally", "~Responsible for the internal coordination and execution of sponsor-based activities and involvement at Boilermaker events", "~Create and present sponsorship proposals (PowerPoint, etc.) for use with existing sponsors annually and new sponsor prospecting efforts", "~Conduct post-event recap reports for each sponsor as needed, including quantifiable metrics (e.g. media placements, views, etc.), as well as qualitative results due to the sponsorship", "~Be available for some evening & weekend work, especially during events", "~Support manual labor associated with load-in & load-out activities", "~Complete any other tasks as prescribed by the President and/or the Race Director"]}, "job_job_title": "Manager", "job_posting_language": "en", "job_onet_soc": "11202100", "job_onet_job_zone": "4"}