{"job_id": "rz7wjpHgDI2Z17KXAAAAAA==", "employer_name": "Vox Media", "employer_logo": "https://cdn.vox-cdn.com/thumbor/E0ggfkny12B38XzyrVrYVE5Vcyg=/1400x1050/filters:format(png)/cdn.vox-cdn.com/uploads/chorus_asset/file/19351624/Logo_Purple_BG.png", "employer_website": "http://www.voxmedia.com", "employer_company_type": "Advertising", "job_publisher": "LinkedIn", "job_employment_type": "FULLTIME", "job_title": "Director of Client Partnerships, Automotive and Growth", "job_apply_link": "https://www.linkedin.com/jobs/view/director-of-client-partnerships-automotive-and-growth-at-vox-media-3813558003", "job_apply_is_direct": false, "job_apply_quality_score": 0.6897, "apply_options": [{"publisher": "LinkedIn", "apply_link": "https://www.linkedin.com/jobs/view/director-of-client-partnerships-automotive-and-growth-at-vox-media-3813558003", "is_direct": false}, {"publisher": "Adexloan.com", "apply_link": "https://adexloan.com/?refId=5zlNns4U8hPcutvmSgWANg%3D%3D&trackingId=PeXSrg3jBhoJ0Qp3B7KJzg%3D%3D&trk=org-job-results&_=%2Fjobs%2Fview%2Fdirector-of-client-partnerships-automotive-and-growth-at-vox-media-3813558003%23KJWqMdlUlBn8PPpbXBTujI7xcY8uGFCs", "is_direct": false}], "job_description": "Who We Are\n\nVox Media\u2019s Revenue organization handles advertising and marketing partnerships with brands and agencies, as well as lines of business in consumer revenue and commerce across the organization.\n\nVox Media is the leading modern media company. We guide our audience from discovery to obsession. We inspire essential conversations about what\u2019s now, what\u2019s next, and what\u2019s possible.\n\nAs a community of journalists and storytellers, business professionals, creators and technologists, we believe it is a moral and business imperative to amplify voices: to cultivate diversity, equity, and inclusion throughout our organization and media. This applies to our candidates, our teams, our storytelling, our creative work, and our platforms, products, and partnerships.\n\nWhat You\u2019ll Do\n\nThe Director of Client Partnerships will lead a focused book of accounts to turn existing relationships with key advertisers into deep partnerships. The Director will drive revenue via partnerships that span clients\u2019 lines of business and leverage multiple Vox Media capabilities from video and display media, to branded content, experiential sponsorships, programmatic, social, and audio advertising.\n\nYou will use your expertise, knowledge, and network to unlock the full potential of brands through a unique blend of premier content offerings, high-value audiences, cutting-edge technology, and a deep product portfolio.\n\nThis is a high-energy, fast-paced job requiring persistent and persuasive interactions with clients and their agencies, deep digital, content, social and programmatic expertise, and the ability to work both independently, and collaboratively with internal teams and senior management to achieve individual as well as broader, company-wide goals.\n\u2022 Manage a book of business in the Automotive category to achieve and exceed revenue goals, with the ability to pick up accounts outside of the Automotive category\n\u2022 Maintain a partnership mindset to generate revenue growth above and beyond individual campaigns\n\u2022 Manage and expand senior-level client relationships and develop a thorough understanding of their business challenges\n\u2022 Consistently communicate market feedback to internal stakeholders as a means of innovating our products and solutions for advertisers\n\u2022 Enjoy problem solving in a fast-paced, evolving environment\n\u2022 Collaborate across internal teams like Editorial, Vox Creative, Product, and Insights to develop unique offerings, narratives and tactics to drive impact and engagement with partners\n\u2022 Effectively manage a sales pipeline, report on roadblocks and opportunities, and provide accurate forecasting and planning insights\n\u2022 Build and maintain a strong knowledge of Vox Media\u2019s advertising products and solutions, and become a champion across the organization as well as in the market\n\u2022 Consistently communicate market feedback as a means of innovating our products and solutions for advertisers\n\u2022 Contribute to a positive team culture\n\nWho You Are\n\nYou are extremely passionate about advertising and are a subject matter expert in the advertising and publishing landscape. You have a diverse, senior list of client contacts that you have worked with on multi-channel campaigns and have a demonstrated ability to build client relationships with premium brands in the Automotive category. You are highly self-motivated, a strategic problem-solver, and an excellent collaborator.\n\u2022 5+ years experience in advertising sales with a heavy focus on the Automotive vertical.\n\u2022 Proven track record of reaching and exceeding revenue goals\n\u2022 An understanding of the breadth of solutions Vox Media brings to market\n\u2022 Deep passion and knowledge of digital media, technology, the competitive landscape and the entertainment industry's key issues\n\u2022 An entrepreneurial spirit\n\u2022 Hunger and self-motivation to exceed revenue goals\n\u2022 A well established network within the advertising and entertainment industry\n\u2022 Demonstrated ability to function and communicate effectively at senior client levels\n\u2022 Exceptional communication skills including strong virtual & in-person presentation skills\n\u2022 Passion for the Vox Media portfolio of editorial brands and innovative advertising solutions\n\u2022 Strong negotiation skills and an ability to persuade at all levels of an agency or client\n\u2022 Keen ability to listen with a focus on a consultative selling approach\n\u2022 Excellent time management skills\n\u2022 Natural curiosity and never-ending desire to learn\n\u2022 Passion and knowledge of the online advertising industry\n\u2022 Willingness to travel as necessary\n\nIf you think you have what it takes, but don't meet every single point in our job posting, please apply with a cover letter to let us know how you believe you can bring your unique skills to the Vox Media team or get in touch! We would love to have a chat and see if you could be a great addition to our team. We\u2019ve hired chefs who became editors, DJs who became UX designers, and sommeliers who became writers.\n\nWHERE YOU\u2019LL WORK\n\nThis job is located in Los Angeles. We\u2019re dedicated to the health and wellbeing of all of our employees, and when we reopen, will require everyone who works from one of our offices to be fully-vaccinated against COVID-19. Employees with approved religious or medical exemptions may be subject to additional safety requirements, such as submitting to regular COVID-19 testing and/or wearing a face covering in our offices.\n\nWHY VOX MEDIA?\n\nWhat We Offer\n\nThis is a permanent, full-time position. This job is benefits-eligible. We pride ourselves in providing comprehensive benefits to support all of our employees wherever they are in life. You can find more information about our benefits here.\n\nOUR DEI+ COMMITMENT\n\nVox Media is committed to building an inclusive environment where everyone can show up as their authentic selves and create their best work. We recognize that great stories, platforms, products and services come from people with all manner of backgrounds and experiences. We recognize that our commitments require ongoing work and sustained attention, as well as adaptation to new insights and best practices. We keep our diversity data public for the sake of accountability, transparency and communication. Learn more about our values here, and our approach to corporate citizenship here.\n\nVox Media is an Equal Opportunity Employer and qualified applicants will receive consideration without regard to race, color, gender, sexual orientation, gender identity or expression, religion, disability, national origin, protected veteran status, age, or any other status protected by applicable national, federal, state, or local law. Vox Media will also consider all qualified applicants with criminal histories in accordance with applicable Fair Chance laws. We are also committed to providing reasonable accommodations as part of the application process to candidates with disabilities. If you require a reasonable accommodation as part of the application process, please contact our People & Culture team (recruitment@voxmedia.com).\n\nWhat Comes Next\n\nOur recruiting team will go through applications in a timely manner. Please note that our recruiting team will only contact you from @voxmedia.com email addresses, never via text message. Read more about how our recruiting team operates, and how to protect yourself from recruitment fraud, here.\n\nPAY TRANSPARENCY\n\nThe salary range listed below represents the minimum and maximum base pay for this position at the time of this posting. Final salary offered to the candidate selected for the position will be based on factors including but not limited to the candidate's skills and experience. In addition to a competitive base salary, this role may also include a discretionary bonus.\n\nPay Range\n\n$120,000\u2014$140,000 USD", "job_is_remote": false, "job_posted_at_timestamp": 1709900014, "job_posted_at_datetime_utc": "2024-03-08T12:13:34.000Z", "job_city": null, "job_state": null, "job_country": "US", "job_latitude": 37.09024, "job_longitude": -95.71289, "job_benefits": null, "job_google_link": "https://www.google.com/search?gl=us&hl=en&rciv=jb&q=vice+president+of+brand+partnerships&start=70&ibp=htl;jobs#fpstate=tldetail&htivrt=jobs&htiq=vice+president+of+brand+partnerships&htidocid=rz7wjpHgDI2Z17KXAAAAAA%3D%3D", "job_offer_expiration_datetime_utc": "2024-04-24T20:18:49.000Z", "job_offer_expiration_timestamp": 1713989929, "job_required_experience": {"no_experience_required": false, "required_experience_in_months": 60, "experience_mentioned": true, "experience_preferred": false}, "job_required_skills": null, "job_required_education": {"postgraduate_degree": false, "professional_certification": false, "high_school": false, "associates_degree": false, "bachelors_degree": true, "degree_mentioned": false, "degree_preferred": false, "professional_certification_mentioned": false}, "job_experience_in_place_of_education": false, "job_min_salary": null, "job_max_salary": null, "job_salary_currency": null, "job_salary_period": null, "job_highlights": {"Qualifications": ["You are extremely passionate about advertising and are a subject matter expert in the advertising and publishing landscape", "You have a diverse, senior list of client contacts that you have worked with on multi-channel campaigns and have a demonstrated ability to build client relationships with premium brands in the Automotive category", "You are highly self-motivated, a strategic problem-solver, and an excellent collaborator", "5+ years experience in advertising sales with a heavy focus on the Automotive vertical", "Proven track record of reaching and exceeding revenue goals", "An understanding of the breadth of solutions Vox Media brings to market", "Deep passion and knowledge of digital media, technology, the competitive landscape and the entertainment industry's key issues", "An entrepreneurial spirit", "Hunger and self-motivation to exceed revenue goals", "A well established network within the advertising and entertainment industry", "Demonstrated ability to function and communicate effectively at senior client levels", "Exceptional communication skills including strong virtual & in-person presentation skills", "Passion for the Vox Media portfolio of editorial brands and innovative advertising solutions", "Strong negotiation skills and an ability to persuade at all levels of an agency or client", "Keen ability to listen with a focus on a consultative selling approach", "Excellent time management skills", "Natural curiosity and never-ending desire to learn", "Passion and knowledge of the online advertising industry", "Willingness to travel as necessary"], "Responsibilities": ["The Director of Client Partnerships will lead a focused book of accounts to turn existing relationships with key advertisers into deep partnerships", "The Director will drive revenue via partnerships that span clients\u2019 lines of business and leverage multiple Vox Media capabilities from video and display media, to branded content, experiential sponsorships, programmatic, social, and audio advertising", "You will use your expertise, knowledge, and network to unlock the full potential of brands through a unique blend of premier content offerings, high-value audiences, cutting-edge technology, and a deep product portfolio", "Manage a book of business in the Automotive category to achieve and exceed revenue goals, with the ability to pick up accounts outside of the Automotive category", "Maintain a partnership mindset to generate revenue growth above and beyond individual campaigns", "Manage and expand senior-level client relationships and develop a thorough understanding of their business challenges", "Consistently communicate market feedback to internal stakeholders as a means of innovating our products and solutions for advertisers", "Enjoy problem solving in a fast-paced, evolving environment", "Collaborate across internal teams like Editorial, Vox Creative, Product, and Insights to develop unique offerings, narratives and tactics to drive impact and engagement with partners", "Effectively manage a sales pipeline, report on roadblocks and opportunities, and provide accurate forecasting and planning insights", "Build and maintain a strong knowledge of Vox Media\u2019s advertising products and solutions, and become a champion across the organization as well as in the market", "Contribute to a positive team culture"], "Benefits": ["Final salary offered to the candidate selected for the position will be based on factors including but not limited to the candidate's skills and experience", "In addition to a competitive base salary, this role may also include a discretionary bonus", "$120,000\u2014$140,000 USD"]}, "job_job_title": "Client", "job_posting_language": "en", "job_onet_soc": "11202200", "job_onet_job_zone": "4", "job_naics_code": "541810", "job_naics_name": "Advertising Agencies"}