{"job_id": "3d_FPPvCTdBUvZq_AAAAAA==", "employer_name": "Match Group LLC", "employer_logo": "https://ir.mtch.com/files/design/logo-white.png", "employer_website": "http://www.mtch.com", "employer_company_type": "Education", "job_publisher": "Professional Diversity Network", "job_employment_type": "FULLTIME", "job_title": "Senior Data Scientist (Trust and Safety)", "job_apply_link": "https://www.prodivnet.com/job/senior-data-scientist-trust-and-safety-dallas-texas-14384697", "job_apply_is_direct": false, "job_apply_quality_score": 0.5569, "apply_options": [{"publisher": "Professional Diversity Network", "apply_link": "https://www.prodivnet.com/job/senior-data-scientist-trust-and-safety-dallas-texas-14384697", "is_direct": false}, {"publisher": "Dallas Morning News", "apply_link": "https://dfwishiring.dallasnews.com/company/match-group-llc-189899/job/senior-data-scientist-trust-and-safety-in-dallas-tx-2zugj7j257w5ehaq9vr9h7xhac9zpr/", "is_direct": false}], "job_description": "Senior Data Scientist (Trust and Safety)\n\nMatch Group LLC\n\n(Dallas, TX)\n\nServe as the Subject Matter Expert for various teams to provide support for A/B test design and analysis,\nas well as data-driven insights through ad-hoc analyses, presentations, and automated reports and\ndashboards. Mentor junior data scientists on customer behavior and business performance. Oversee\njunior data scientist in the building of models to better understand the value and churn behavior of our\nusers. Evaluate data patterns and communicate insights and opportunities with executives and other\ninternal teams to reshape our current understanding of customer behavior using advanced analytical\ntechnique. Perform ongoing and ad-hoc analyses to evaluate A/B tests, build reporting infrastructure, and\nprovide analytics insights to optimize on app\u2019s Trust and Safety environment and authentication funnels.\nOversee the Integration of captured event data with other sources of customer data, including surveys, ad\npublishers, and app store data. Use strong communication skills (verbal and written) to manage the\nsupport of reporting and business intelligence needs for Product, Marketing, Engineering, and Finance\nteams. Position allows telecommuting from anywhere in the U.S. Salary: $111,500 - $191,500 per year.\n\nMinimum Requirements: Bachelor\u2019s degree or U.S. equivalent in Computer Science, Data Science,\nBusiness Analytics, Quantitative Methods, Operations Research, Statistics, Economics, or a related field\nplus 5 years of professional experience as Data Scientist, Data Analyst or any occupation/position/job title\ninvolving data wrangling services. In lieu of a Bachelor's degree plus 5 years of experience, the employer\nwill accept a Master\u2019s degree or U.S. equivalent Computer Science, Data Science, Business Analytics,\nQuantitative Methods, Operations Research, Statistics, Economics, or a related field plus 3 years of\nprofessional experience as Data Scientist, Data Analyst or any occupation/position/job title involving data\nwrangling services. Must also have the following: 3 years of professional experience providing data\nwrangling services to make data consumable for downstream purposes (including applications or\nanalytics) to interpret themes from quantitative and qualitative data to deliver data-driven insights to\noptimize growth; 3 years of professional experience scripting using programming languages (including\nPython, NumPy, or PANDAS); 3 years of professional experience using structured query language (SQL);\n3 years of professional experience with Microsoft Excel and Microsoft PowerPoint to create presentations,\nand automated reports and dashboards; 3 years professional experience with various machine\nlearning/statistical modeling data analysis tools and techniques (including sklearn, tensorflow, or keras),\nand parameters that affect their performance; 2 years of professional experience working with Product,\nMarketing, and Engineering teams; 1 year of professional experience using experimentation on Trust and\nSafety identity features; 1 year of professional experience working with common KPIs, metrics, and Trust\nand Safety experiments; 1 year of professional experience with A/B test design and analysis for software\nsystems or applications; and 1 year of professional experience using statistical methods for experimental\ndesign and analysis.\n\nPlease send resume to: Lauren.Lozano@Match.com. Please specify ad code YHLL.\n\nrecblid 88njchkgr8yl7cqxol758oznn7vzu9\n\nPDN-9b890ae7-fe48-49c8-a7cf-476c39b1d56b", "job_is_remote": false, "job_posted_at_timestamp": 1710156287, "job_posted_at_datetime_utc": "2024-03-11T11:24:47.000Z", "job_city": "Dallas", "job_state": "TX", "job_country": "US", "job_latitude": 32.776665, "job_longitude": -96.79699, "job_benefits": null, "job_google_link": "https://www.google.com/search?gl=us&hl=en&rciv=jb&q=senior+data+scientist&start=10&ibp=htl;jobs#fpstate=tldetail&htivrt=jobs&htiq=senior+data+scientist&htidocid=3d_FPPvCTdBUvZq_AAAAAA%3D%3D", "job_offer_expiration_datetime_utc": "2024-06-09T11:24:47.000Z", "job_offer_expiration_timestamp": 1717932287, "job_required_experience": {"no_experience_required": false, "required_experience_in_months": 60, "experience_mentioned": true, "experience_preferred": false}, "job_required_skills": null, "job_required_education": {"postgraduate_degree": false, "professional_certification": false, "high_school": false, "associates_degree": false, "bachelors_degree": false, "degree_mentioned": true, "degree_preferred": false, "professional_certification_mentioned": false}, "job_experience_in_place_of_education": false, "job_min_salary": null, "job_max_salary": null, "job_salary_currency": null, "job_salary_period": null, "job_highlights": {"Qualifications": ["support of reporting and business intelligence needs for Product, Marketing, Engineering, and Finance", "Minimum Requirements: Bachelor\u2019s degree or U.S. equivalent in Computer Science, Data Science,", "plus 5 years of professional experience as Data Scientist, Data Analyst or any occupation/position/job title", "In lieu of a Bachelor's degree plus 5 years of experience, the employer", "will accept a Master\u2019s degree or U.S. equivalent Computer Science, Data Science, Business Analytics,", "Quantitative Methods, Operations Research, Statistics, Economics, or a related field plus 3 years of", "Must also have the following: 3 years of professional experience providing data", "optimize growth; 3 years of professional experience scripting using programming languages (including", "Python, NumPy, or PANDAS); 3 years of professional experience using structured query language (SQL);", "3 years of professional experience with Microsoft Excel and Microsoft PowerPoint to create presentations,", "and automated reports and dashboards; 3 years professional experience with various machine", "Marketing, and Engineering teams; 1 year of professional experience using experimentation on Trust and", "Safety identity features; 1 year of professional experience working with common KPIs, metrics, and Trust", "and Safety experiments; 1 year of professional experience with A/B test design and analysis for software", "systems or applications; and 1 year of professional experience using statistical methods for experimental"], "Responsibilities": ["Serve as the Subject Matter Expert for various teams to provide support for A/B test design and analysis,", "as well as data-driven insights through ad-hoc analyses, presentations, and automated reports and", "Mentor junior data scientists on customer behavior and business performance", "junior data scientist in the building of models to better understand the value and churn behavior of our", "Evaluate data patterns and communicate insights and opportunities with executives and other", "internal teams to reshape our current understanding of customer behavior using advanced analytical", "Perform ongoing and ad-hoc analyses to evaluate A/B tests, build reporting infrastructure, and", "provide analytics insights to optimize on app\u2019s Trust and Safety environment and authentication funnels", "Oversee the Integration of captured event data with other sources of customer data, including surveys, ad", "Use strong communication skills (verbal and written) to manage the", "analytics) to interpret themes from quantitative and qualitative data to deliver data-driven insights to"], "Benefits": ["Position allows telecommuting from anywhere in the U.S", "Salary: $111,500 - $191,500 per year"]}, "job_job_title": "Data scientist", "job_posting_language": "en", "job_onet_soc": "15111100", "job_onet_job_zone": "5", "job_naics_code": "611691", "job_naics_name": "Exam Preparation and Tutoring"}