{"job_id": "j2_1d7xb06VyGJnfAAAAAA==", "employer_name": "Mortenson", "employer_logo": null, "employer_website": "http://www.mortenson.com", "employer_company_type": "Construction", "job_publisher": "Mortenson", "job_employment_type": "FULLTIME", "job_title": "Business Development Manager", "job_apply_link": "https://www.mortenson.com/careers/chicago-office/business-development-manager-15033", "job_apply_is_direct": false, "job_apply_quality_score": 0.8712, "apply_options": [{"publisher": "Mortenson", "apply_link": "https://www.mortenson.com/careers/chicago-office/business-development-manager-15033", "is_direct": false}, {"publisher": "LinkedIn", "apply_link": "https://www.linkedin.com/jobs/view/business-development-manager-at-mortenson-3800617443", "is_direct": false}, {"publisher": "Salary.com", "apply_link": "https://www.salary.com/job/mortenson-construction/business-development-manager/j202401091852583366471", "is_direct": false}, {"publisher": "Indeed", "apply_link": "https://www.indeed.com/m/viewjob?jk=758a7e1c6835a19f&from=serp&tk=1hkgdr2hpghru801&xkcb=SoBh67M3FQTjj8wxmR0ebzkdCdPP", "is_direct": false}, {"publisher": "Talent.com", "apply_link": "https://www.talent.com/view?id=adf5e08eecac", "is_direct": false}, {"publisher": "Glassdoor", "apply_link": "https://www.glassdoor.com/job-listing/business-development-manager-m-a-mortenson-company-JV_IC1128808_KO0,28_KE29,50.htm?jl=1009063934001", "is_direct": false}, {"publisher": "SimplyHired", "apply_link": "https://www.simplyhired.com/job/CiASSxxXruAAB4n1T_b2SeVCvIrXmj9Fidn-HxBJj2Plv8JQZnshJQ", "is_direct": false}, {"publisher": "Offered.AI", "apply_link": "https://www.offered.ai/jobs/clr5wifu4032h5cjpa6v2dzdn", "is_direct": false}], "job_description": "As a Top 25 builder, developer, and EPC, our expertise spans markets like sports, renewable energy, data centers, healthcare, and more. We are builders at heart, working to ensure the built environment has a lasting positive impact. | Let\u2019s Redefine Possible\u00ae\n\nABOUT MORTENSON\n\nAs a Top 25 builder, developer, and EPC, our expertise spans markets like sports, renewable energy, data centers, healthcare, and more. We are builders at heart, working to ensure the built environment has a lasting positive impact.\nLet\u2019s Redefine Possible\u00ae\n\nSUMMARY\n\nMortenson is currently seeking an experienced Business Development Manager for our Chicago Group. You will lead the creation of new project opportunities by partnering with our group and market leaders in developing and executing positioning strategies with existing and potential customers. You will support our business development strategy, public relations, communications, and relationship building. This role will be engaged in a broad range of sales enablement efforts in alignment with our overall market strategy. Excellent written and verbal interpersonal skills are vital as you will be interacting with team members, customers, and partners in an ever-changing environment. You should also display the ability to remain flexible, inventive, dedicated, and efficient with a significant amount of integrity and confidentiality.\n\nRESPONSIBILITIES\n\u2022 Be actively engaged in the market, attending conferences, speaking engagements and industry events.\n\u2022 Establish and cultivate strategic business partnerships and customer relationships.\n\u2022 Function as the liaison amongst group leadership, business development, operations, pre-construction, and marketing.\n\u2022 Participate in strategic business planning; developing strategic positioning plans for the group to win work.\n\u2022 Directly interact with your customers, leverage insights, and communicate value propositions.\n\u2022 Develop and maintain deep and trusting relationships with current and potential partners including, but not limited to targeted customers, design professionals, partner companies, community leaders, and engineering firms.\n\u2022 Support the filtering of new customers and opportunities.\n\u2022 Support the project positioning activities of the business development team.\n\u2022 Develop and produce internal and external communication strategies, marketing, branding and presentations.\n\u2022 Provide insight into market sectors; perform market trends analysis; support market sector teams.\n\u2022 In relation to client development, take the lead in supporting our market leaders in their outreach to key customers and design partners and track and manage upcoming meetings and connection events.\n\u2022 Identify new market sector opportunities and potential future customers.\n\u2022 Familiarize yourself with the customer\u2019s project designs, estimates, schedules, and key terms to facilitate discussion with the customer.\n\u2022 Lead and support proposal responses to customers and initiate customer feedback.\n\u2022 Review RFP requirements independently and communicate requirements, risks, and strategy to successfully win and execute the work.\n\u2022 Complete Request for Proposals with 100% accuracy and compliance with the owner\u2019s specifications.\n\u2022 Engage with marketing teams to help guide Social Media presence and digital campaigns. Work with Marketing teams to create content marketing pieces and develop an intentional plan for content postings over time \u2013 leveraging content already created as well as ideate any new content.\n\u2022 Oversight of our Customer Relationship Management (CRM) efforts and support our market leads and teams in accurate and timely updates.\n\nQUALIFICATIONS\n\u2022 Bachelor\u2019s degree in Business, Construction Management, Marketing, Engineering, or a related field.\n\u2022 5+ years of experience in marketing, sales operations, or related field.\n\u2022 Own and bring clarity to ambiguous information and situations, be a curious learner, develop expertise, and be an ambassador for the existing markets we serve.\n\u2022 Proven customer relationship-building skills, with developed local/regional/national business knowledge and relationships.\n\u2022 Knowledge of construction law and generally accepted business practices.\n\u2022 Detail orientation sufficient for data entry, reporting, financial projections for sales and selections, and market analysis.\n\u2022 Microsoft Office and CRM web application skills at an advanced level.\n\u2022 Proven positive and professional attitude, and strong customer service skills.\n\u2022 Current driver\u2019s license.\n\u2022 Travel of up to 30% of the time may be necessary to fulfill the objectives of the position.\n\nBENEFITS\n\nMortenson provides a comprehensive benefits program to team members and their families to support their health, build long-term financial security and provide the opportunity for work and life balance. Benefits offered to non-craft, non-union, full-time team members include:\n\u2022 Medical and prescription drug plans \u2013 the choice between two affordable HSA-eligible medical plans that include vision coverage\n\u2022 Dental plan\n\u2022 401k retirement plan with generous matching and profit-sharing contributions\n\u2022 Paid time off, holidays, and other paid leaves\n\u2022 Life, AD&D, and disability insurance\n\u2022 Employee assistance program online mental health tool and concierge\n\u2022 Tuition reimbursement\n\u2022 Adoption Assistance\n\u2022 Gym Membership Discount Program\n\u2022 Identity Theft Protection\n\nMortenson is an EOE/Affirmative Action/M/F/Veteran/Disabled employer.\n\nVisa sponsorship is not offered for this position.\n\nMortenson reserves the right to hire any individual without legal or financial obligation on unwanted solicitations. No agency emails, calls, or solicitations are accepted without a valid agreement.\n\n#LI-BF1", "job_is_remote": false, "job_posted_at_timestamp": 1704672000, "job_posted_at_datetime_utc": "2024-01-08T00:00:00.000Z", "job_city": "Chicago", "job_state": "IL", "job_country": "US", "job_latitude": 41.878113, "job_longitude": -87.6298, "job_benefits": ["paid_time_off", "dental_coverage", "health_insurance", "retirement_savings"], "job_google_link": "https://www.google.com/search?gl=us&hl=en&rciv=jb&q=manager+of+business+development&start=0&ibp=htl;jobs#fpstate=tldetail&htivrt=jobs&htiq=manager+of+business+development&htidocid=j2_1d7xb06VyGJnfAAAAAA%3D%3D", "job_offer_expiration_datetime_utc": "2024-05-07T00:00:00.000Z", "job_offer_expiration_timestamp": 1715040000, "job_required_experience": {"no_experience_required": false, "required_experience_in_months": 60, "experience_mentioned": true, "experience_preferred": false}, "job_required_skills": null, "job_required_education": {"postgraduate_degree": false, "professional_certification": false, "high_school": false, "associates_degree": false, "bachelors_degree": false, "degree_mentioned": true, "degree_preferred": true, "professional_certification_mentioned": false}, "job_experience_in_place_of_education": false, "job_min_salary": null, "job_max_salary": null, "job_salary_currency": null, "job_salary_period": null, "job_highlights": {"Qualifications": ["You should also display the ability to remain flexible, inventive, dedicated, and efficient with a significant amount of integrity and confidentiality", "Bachelor\u2019s degree in Business, Construction Management, Marketing, Engineering, or a related field", "5+ years of experience in marketing, sales operations, or related field", "Own and bring clarity to ambiguous information and situations, be a curious learner, develop expertise, and be an ambassador for the existing markets we serve", "Proven customer relationship-building skills, with developed local/regional/national business knowledge and relationships", "Knowledge of construction law and generally accepted business practices", "Detail orientation sufficient for data entry, reporting, financial projections for sales and selections, and market analysis", "Microsoft Office and CRM web application skills at an advanced level", "Proven positive and professional attitude, and strong customer service skills", "Current driver\u2019s license", "Travel of up to 30% of the time may be necessary to fulfill the objectives of the position"], "Responsibilities": ["You will lead the creation of new project opportunities by partnering with our group and market leaders in developing and executing positioning strategies with existing and potential customers", "You will support our business development strategy, public relations, communications, and relationship building", "This role will be engaged in a broad range of sales enablement efforts in alignment with our overall market strategy", "Be actively engaged in the market, attending conferences, speaking engagements and industry events", "Establish and cultivate strategic business partnerships and customer relationships", "Function as the liaison amongst group leadership, business development, operations, pre-construction, and marketing", "Participate in strategic business planning; developing strategic positioning plans for the group to win work", "Directly interact with your customers, leverage insights, and communicate value propositions", "Develop and maintain deep and trusting relationships with current and potential partners including, but not limited to targeted customers, design professionals, partner companies, community leaders, and engineering firms", "Support the filtering of new customers and opportunities", "Support the project positioning activities of the business development team", "Develop and produce internal and external communication strategies, marketing, branding and presentations", "Provide insight into market sectors; perform market trends analysis; support market sector teams", "In relation to client development, take the lead in supporting our market leaders in their outreach to key customers and design partners and track and manage upcoming meetings and connection events", "Identify new market sector opportunities and potential future customers", "Familiarize yourself with the customer\u2019s project designs, estimates, schedules, and key terms to facilitate discussion with the customer", "Lead and support proposal responses to customers and initiate customer feedback", "Review RFP requirements independently and communicate requirements, risks, and strategy to successfully win and execute the work", "Complete Request for Proposals with 100% accuracy and compliance with the owner\u2019s specifications", "Engage with marketing teams to help guide Social Media presence and digital campaigns", "Work with Marketing teams to create content marketing pieces and develop an intentional plan for content postings over time \u2013 leveraging content already created as well as ideate any new content", "Oversight of our Customer Relationship Management (CRM) efforts and support our market leads and teams in accurate and timely updates"], "Benefits": ["Mortenson provides a comprehensive benefits program to team members and their families to support their health, build long-term financial security and provide the opportunity for work and life balance", "Benefits offered to non-craft, non-union, full-time team members include:", "Medical and prescription drug plans \u2013 the choice between two affordable HSA-eligible medical plans that include vision coverage", "Dental plan", "401k retirement plan with generous matching and profit-sharing contributions", "Paid time off, holidays, and other paid leaves", "Life, AD&D, and disability insurance", "Employee assistance program online mental health tool and concierge", "Tuition reimbursement", "Adoption Assistance", "Gym Membership Discount Program", "Identity Theft Protection"]}, "job_job_title": "Development manager", "job_posting_language": "en", "job_onet_soc": "11202100", "job_onet_job_zone": "4", "job_naics_code": "237", "job_naics_name": "Heavy and Civil Engineering Construction"}