{"job_id": "5HcvI1n4OOivp7K0AAAAAA==", "employer_name": "HeyTutor", "employer_logo": "https://encrypted-tbn0.gstatic.com/images?q=tbn:ANd9GcTIrBdO_Zew08Znf-hzdk2M5q5yHBcpj6jw0VMc&s=0", "employer_website": "http://www.heytutor.com", "employer_company_type": null, "job_publisher": "LinkedIn", "job_employment_type": "FULLTIME", "job_title": "Regional Director of Partnerships", "job_apply_link": "https://www.linkedin.com/jobs/view/regional-director-of-partnerships-at-heytutor-3793523249", "job_apply_is_direct": false, "job_apply_quality_score": 0.741, "apply_options": [{"publisher": "LinkedIn", "apply_link": "https://www.linkedin.com/jobs/view/regional-director-of-partnerships-at-heytutor-3793523249", "is_direct": false}], "job_description": "Who We Are\n\nAt HeyTutor, our mission is to empower students and school districts across the country by providing customizable, accessible, and effective in-person and online tutoring solutions. We envision a future where every student has access to transformative learning experiences, empowering them to overcome academic challenges and achieve lifelong success. Our commitment to fostering a global community of confident, well-rounded individuals will shape a brighter future, unlocking limitless potential for growth and positive impact.\n\nSummary Statement\n\nThe Regional Director of Partnerships is a high performing sales manager committed to creating positive impacts in the education committee. The District Partnerships Account Manager is focused on creating and expanding opportunities within the key district that support priorities and initiatives around learning in a rapidly growing territory. This position is responsible for proactive client acquisition, management of strategic relationships, and development of territories and achievement of sales goals.\n\nTasks & Responsibilities\n\nAs a Regional Director of Partnerships, you will be responsible for performing the following duties:\n\n\u25cf Conduct a high volume of outbound cold calls to potential clients to successfully book meetings;\n\n\u25cf Create and maintain a pipeline of prospects and client information;\n\n\u25cf Present and provide information and conduct follow up calls;\n\n\u25cf Research and produce potential leads;\n\n\u25cf Possess an in depth knowledge of HeyTutor and ability to communicate that to the client;\n\n\u25cf Manage the Sales Development Representatives;\n\n\u25cf Generating sales within the assigned region (region assignment is subject to change by the CRO);\n\n\u25cf Drive sales and adoption of learning committees for programs through strategic planning and implementation;\n\n\u25cf Establish industry expertise and develop multi-level relationships through consultations, presentations, trainings, and webinars based on strong learning market knowledge;\n\n\u25cf Lead district program rollout, training and ongoing relationship support to ensure program usage and build enduring partnerships;\n\n\u25cf Achieve or exceed quarterly and annual revenue goals through new and renewal sales;\n\n\u25cf Actively represent organization at conferences and events to promote awareness and build relationships with strategic partners and clients;\n\n\u25cf Collaborate effectively with internal teams including educational partnerships, client success and support implementation and others to ensure proactive client support;\n\n\u25cf Forecast and manage pipeline activity for accurate account planning; and\n\n\u25cf Maintain accurate and well documented spreadsheets, including reporting.\n\nJob Qualifications\n\n\u25cf Bachelor\u2019s Degree required from a 4 year accredited institution\n\n\u25cf Extensive background in the educational market\n\n\u25cf Proven track record of managing complex district or client partnerships to include impactful program adoptions, effective implementations and ongoing engagement\n\n\u25cf Excellent communication skills and successful experience with group presentations\n\n\u25cf Ability to work and collaborate in office or remotely and the ability to travel as needed\n\nIndividual Characteristics\n\n\u25cf Demonstrated desire for continuous learning and improvement\n\n\u25cf Demonstrated success as a top performer, meeting or exceeding goals including new customers and/or partnerships\n\n\u25cf Enthusiastic with the ability to inspire others\n\nPhysical Requirements\n\n\u25cf Ability to stand, walk, sit, use hands, reach with hands and arms, speak and hear; may occasionally be asked to lift up to 15 pounds\n\n\u25cf Normal physical mobility that includes movement from place to place\n\n\u25cf Ability to sit for long periods of time\n\nPositions open: 2", "job_is_remote": true, "job_posted_at_timestamp": 1704322246, "job_posted_at_datetime_utc": "2024-01-03T22:50:46.000Z", "job_city": null, "job_state": null, "job_country": "US", "job_latitude": 37.09024, "job_longitude": -95.71289, "job_benefits": null, "job_google_link": "https://www.google.com/search?gl=us&hl=en&rciv=jb&q=director+of+brand+partnerships&start=60&ibp=htl;jobs#fpstate=tldetail&htivrt=jobs&htiq=director+of+brand+partnerships&htidocid=5HcvI1n4OOivp7K0AAAAAA%3D%3D", "job_offer_expiration_datetime_utc": "2024-07-01T22:50:33.000Z", "job_offer_expiration_timestamp": 1719874233, "job_required_experience": {"no_experience_required": false, "required_experience_in_months": null, "experience_mentioned": true, "experience_preferred": false}, "job_required_skills": ["ClientSuccess", "Customer Success", "Customer Acquisition", "Relationship Development", "Skill Development", "Events", "Contract Research Organization (CRO)", "Strategic Relationships", "Cold Calling", "Presentations"], "job_required_education": {"postgraduate_degree": false, "professional_certification": false, "high_school": false, "associates_degree": false, "bachelors_degree": true, "degree_mentioned": true, "degree_preferred": false, "professional_certification_mentioned": false}, "job_experience_in_place_of_education": false, "job_min_salary": null, "job_max_salary": null, "job_salary_currency": null, "job_salary_period": null, "job_highlights": {"Qualifications": ["Bachelor\u2019s Degree required from a 4 year accredited institution", "Extensive background in the educational market", "Proven track record of managing complex district or client partnerships to include impactful program adoptions, effective implementations and ongoing engagement", "Excellent communication skills and successful experience with group presentations", "Ability to work and collaborate in office or remotely and the ability to travel as needed", "Demonstrated desire for continuous learning and improvement", "Demonstrated success as a top performer, meeting or exceeding goals including new customers and/or partnerships", "Enthusiastic with the ability to inspire others", "Ability to stand, walk, sit, use hands, reach with hands and arms, speak and hear; may occasionally be asked to lift up to 15 pounds", "Normal physical mobility that includes movement from place to place", "Ability to sit for long periods of time"], "Responsibilities": ["This position is responsible for proactive client acquisition, management of strategic relationships, and development of territories and achievement of sales goals", "Conduct a high volume of outbound cold calls to potential clients to successfully book meetings;", "Create and maintain a pipeline of prospects and client information;", "Present and provide information and conduct follow up calls;", "Research and produce potential leads;", "Possess an in depth knowledge of HeyTutor and ability to communicate that to the client;", "Manage the Sales Development Representatives;", "Generating sales within the assigned region (region assignment is subject to change by the CRO);", "Drive sales and adoption of learning committees for programs through strategic planning and implementation;", "Establish industry expertise and develop multi-level relationships through consultations, presentations, trainings, and webinars based on strong learning market knowledge;", "Lead district program rollout, training and ongoing relationship support to ensure program usage and build enduring partnerships;", "Achieve or exceed quarterly and annual revenue goals through new and renewal sales;", "Actively represent organization at conferences and events to promote awareness and build relationships with strategic partners and clients;", "Collaborate effectively with internal teams including educational partnerships, client success and support implementation and others to ensure proactive client support;", "Forecast and manage pipeline activity for accurate account planning; and", "Maintain accurate and well documented spreadsheets, including reporting"]}, "job_job_title": "Regional", "job_posting_language": "en", "job_onet_soc": "11202100", "job_onet_job_zone": "4"}