{"job_id": "1y6avkb8xpS9HmLXAAAAAA==", "employer_name": "The Edens Group, LLC", "employer_logo": "https://encrypted-tbn0.gstatic.com/images?q=tbn:ANd9GcSol1iJS1XEntKS5-A4x7RnmhKkMVsivJakwMRX&s=0", "employer_website": null, "employer_company_type": null, "job_publisher": "LinkedIn", "job_employment_type": "FULLTIME", "job_title": "Senior Vice President of BD and Growth", "job_apply_link": "https://www.linkedin.com/jobs/view/senior-vice-president-of-bd-and-growth-at-the-edens-group-llc-3797470075", "job_apply_is_direct": false, "job_apply_quality_score": 0.6418, "apply_options": [{"publisher": "LinkedIn", "apply_link": "https://www.linkedin.com/jobs/view/senior-vice-president-of-bd-and-growth-at-the-edens-group-llc-3797470075", "is_direct": false}], "job_description": "As the Leader in Recruiting Intelligence, The Edens Group, LLC has been retained to identify and recruit a dynamic and experienced SVP Executive Leader to assume the role of Head of Growth, reporting directly to the COO. Our client is a customer-obsessed, non-traditional, agile business with a purposeful focus on Distributed Data Systems, Platforms at Scale, and Complex Application Development. Their headquarters are in Reston, VA. Our client boasts a range of healthy customers including innovative federal and public agencies leveraging design thinking, cutting-edge tech stacks, and cloud-native ecosystems. They build robust, disruptive, digital solutions that impact the lives of millions of Americans. Of important note, and as an engineering-first-based company, our client\u2019s core philosophy is working as a hyper-collaborative team where each team member brings a unique perspective, adding value and input that is rewarded and championed. Their devotion to the practice of innovation and collaboration coupled with the celebration of cognitive and cultural diversity makes them a truly unique entity.\n\nRole Specificity:\n\nThe SVP of BD will be responsible for our client\u2019s P&L and will drive the achievement of KPIs and business growth through targeted collaboration with the C Suite. The SVP of BD will play a critical role in continually iterating a Strategic Plan, Growth Pipeline, and organic playbooks to realize Enterprise Value using proven growth and business development performance benchmarks.\n\nThe SVP of BD will report to the COO and collaborate with the C Suite to meet strategic targets and performance benchmarks.\n\nKey Responsibilities:\n\nDesign and Implement the corporate Growth Model to include the following:\n\u2022 Work alongside the C Suite to achieve P&L objectives, driving accelerated growth in line with agreed upon target values\n\u2022 Build an in-depth understanding of the Client Growth Model (including, pricing, technology innovation, marketing, M&A, etc.) and make strategic suggestions for how to prioritize and adapt growth levers to achieve the highest and most effective growth parameters\n\u2022 Implement the Client Growth Model, driving key operational initiatives and demonstrating excellent cross-functional leadership and planning/execution expertise.\n\u2022 Strong customer mindset with an ability to link customer roadmaps to strategic growth, pipeline development, and capture account plans.\n\u2022 Build and maintain KPI dashboards and reports via the CRM to provide insight and transparency into performance; review these dashboards regularly with the C Suite and flag any potential negative leading indicators/risks/issues for slowing growth or other revenue quality issues\n\u2022 Implement and help drive adoption of the people-first operating rhythm, ensuring that our client leverages Capture Account Plans, Gate Reviews, and Proposal Development efforts from strategic planning to opportunity identification to proposal submission and award notification until transition is complete\n\u2022 Bring a mentality of continuous improvement to your work including conducting lessons learned after each proposal submission, developing a Gold Standard for business development and proposal activities, and coaching the team regarding appropriate methods to develop and retain levels of customer intimacy. Consistently evaluate current approaches and processes with the ultimate goal of seeking opportunities to drive efficiencies and improvements\n\u2022 Define Growth performance benchmarks and report to C-Suite weekly and drive accountability throughout the Growth organization\n\u2022 Extensive experience in business development, sales, marketing, or a related field, with a track record of driving growth and revenue, GTM strategy, and acquisition implementation\n\u2022 Experience working with budgets and resources and the ability to manage and allocate resources to support growth initiatives effectively.\n\nM&A Integration:\n\u2022 Work alongside C-Suite and Consultants to define selection criteria for potential acquisitions to assist with Growth goals. Lead the effort from selection to closing\n\u2022 Develop an integration playbook for potential acquisitions. Work collaboratively with C-Suite to fully integrate the acquisition based on agreed upon strategy\n\u2022 Ensure seamless integration of tuck-in acquisitions, helping accelerate the path to realized value from adding team members and additional books of business\n\u2022 Experience building presentations for potential acquisitions and presenting to investors.\n\nRelationship Management & Team:\n\u2022 Team members have a proven track record of driving revenue growth across multiple clients\n\u2022 Strong analytical and problem-solving skills with the ability to identify opportunities and make data-driven decisions\n\u2022 Excellent leadership abilities with the capacity to inspire and motivate cross-functional teams\n\u2022 Develop incentives that promote a Win mentality\n\u2022 Strong organizational, critical thinking and communication skills\n\u2022 Build meaningful relationships up and down the organization\n\u2022 Effectively, transparently communicate with relevant stakeholders, ensuring seamless collaboration on projects and day-to-day business operations\n\u2022 Serve as a thought partner to the C Suite on all Growth matters\n\u2022 Ensure that Our Client has A players in all key roles for driving future growth who consistently seek out opportunities- pounding the pavement to win the right kind of work to propel Our Client into accelerated growth and performance; backfill positions as needed\n\u2022 Evaluate talent quality and repurpose, replace, or let go of individuals who are not well equipped for the future-state scorecard/role responsibilities\n\nIntangible Characteristics Desired and Required:\n\n\u00b7 Leadership- Exhibits confidence in self and others. Inspires and motivates others to perform to the best of their ability. Effectively influences actions and opinions of others. Accepts feedback from others. Gives appropriate recognition to others. Seeks to effectively drive the decision-making process.\n\n\u00b7 Communication \u2013 Possesses the ability to convey information to others in a clear and understandable way. Responsible for communicating with employees, customers, investors, and other stakeholders.\n\n\u00b7 Strategic thinking: Bring the ability to see the big picture and understand how your work fits into the company\u2019s goals and the long-term effects of your decisions and actions.\n\n\u00b7 Professionalism- Approaches others in a tactful manner. Reacts well under pressure. Treats other with respect and consideration regardless of their status or position. Accepts responsibility for their own actions and follows through on commitments.\n\n\u00b7 Standards of Excellence- Outstanding consultative and operational abilities and excellent interpersonal and presentation skills with executive level customers and partners. Proactive, resourceful and flexible in a fast-paced work environment, excellent work ethic including high results-orientation, attention to detail, strong customer focus and an exemplary level of professionalism.\n\nClearance Requirements:\n\u2022 Ability to obtain and maintain a USG security clearance\n\nWork Location:\n\nHeadquartered in Reston, VA, our client has outgrown their current space and is looking to double the corporate HQ (nearby in NoVA) and will be adding a SCIF capability as they expand.\n\nCompensation and Benefits:\n\u2022 Highly competitive Base Salary ($250-300K), Double Digit Bonus, Equity and additional Exec perks\n\u2022 Fully covered healthcare, dental, and vision coverage + 401(k)\n\u2022 Unlimited PTO + 11 paid holidays\n\u2022 Education & training benefits, referral bonuses\n\u2022 Annual budget for your tech/gadgets needs\n\nVision Market Statement:\n\nOur client bridges the gap between humans and data through radical transparency and their true obsession with the USG\u2019s mission. Our client is known for approaching every deliverable like it's a product. As they grow, and their footprint becomes larger, teams and employees will treat each other not only as teammates but customers. They collectively agree as a company that they must live the customer-obsessed mindset, always and first. This mantra adoption will help them rapidly scale and it will translate to the interactions that their employees have with their clients and other product teams with whom they integrate. Public-sector modernization is critical for all to live in a better world. Within our client, innovating and solving complex problems is at the root of all activity where the ultimate goal is for our generation and the ones that follow to live in an efficient, and accessible world where out-of-box thinking, and collaboration is the norm.\n\nOur client is an equal opportunity employer and considers qualified applicants for employment without regard to race, color, creed, religion, national origin, sex, sexual orientation, gender identity and expression, age, disability, or other eligible veteran status, or any other protected factor.", "job_is_remote": false, "job_posted_at_timestamp": 1709130008, "job_posted_at_datetime_utc": "2024-02-28T14:20:08.000Z", "job_city": null, "job_state": null, "job_country": "US", "job_latitude": 37.09024, "job_longitude": -95.71289, "job_benefits": ["dental_coverage", "paid_time_off", "retirement_savings", "health_insurance"], "job_google_link": "https://www.google.com/search?gl=us&hl=en&rciv=jb&q=senior+director+of+business+development&start=70&ibp=htl;jobs#fpstate=tldetail&htivrt=jobs&htiq=senior+director+of+business+development&htidocid=1y6avkb8xpS9HmLXAAAAAA%3D%3D", "job_offer_expiration_datetime_utc": "2024-08-26T14:20:08.000Z", "job_offer_expiration_timestamp": 1724682008, "job_required_experience": {"no_experience_required": false, "required_experience_in_months": null, "experience_mentioned": true, "experience_preferred": false}, "job_required_skills": ["Human Capital", "Management", "Communication", "Program Management", "Leadership", "Public Policy", "Logistics Management", "Management Consulting", "Stakeholder Management", "Business Transformation"], "job_required_education": {"postgraduate_degree": false, "professional_certification": false, "high_school": false, "associates_degree": false, "bachelors_degree": true, "degree_mentioned": false, "degree_preferred": false, "professional_certification_mentioned": false}, "job_experience_in_place_of_education": false, "job_min_salary": null, "job_max_salary": null, "job_salary_currency": null, "job_salary_period": null, "job_highlights": {"Qualifications": ["Experience working with budgets and resources and the ability to manage and allocate resources to support growth initiatives effectively", "Strong analytical and problem-solving skills with the ability to identify opportunities and make data-driven decisions", "Excellent leadership abilities with the capacity to inspire and motivate cross-functional teams", "Strong organizational, critical thinking and communication skills", "Inspires and motivates others to perform to the best of their ability", "Proactive, resourceful and flexible in a fast-paced work environment, excellent work ethic including high results-orientation, attention to detail, strong customer focus and an exemplary level of professionalism", "Ability to obtain and maintain a USG security clearance"], "Responsibilities": ["The SVP of BD will be responsible for our client\u2019s P&L and will drive the achievement of KPIs and business growth through targeted collaboration with the C Suite", "The SVP of BD will play a critical role in continually iterating a Strategic Plan, Growth Pipeline, and organic playbooks to realize Enterprise Value using proven growth and business development performance benchmarks", "The SVP of BD will report to the COO and collaborate with the C Suite to meet strategic targets and performance benchmarks", "Design and Implement the corporate Growth Model to include the following:", "Work alongside the C Suite to achieve P&L objectives, driving accelerated growth in line with agreed upon target values", "Build an in-depth understanding of the Client Growth Model (including, pricing, technology innovation, marketing, M&A, etc.) and make strategic suggestions for how to prioritize and adapt growth levers to achieve the highest and most effective growth parameters", "Implement the Client Growth Model, driving key operational initiatives and demonstrating excellent cross-functional leadership and planning/execution expertise", "Strong customer mindset with an ability to link customer roadmaps to strategic growth, pipeline development, and capture account plans", "Build and maintain KPI dashboards and reports via the CRM to provide insight and transparency into performance; review these dashboards regularly with the C Suite and flag any potential negative leading indicators/risks/issues for slowing growth or other revenue quality issues", "Implement and help drive adoption of the people-first operating rhythm, ensuring that our client leverages Capture Account Plans, Gate Reviews, and Proposal Development efforts from strategic planning to opportunity identification to proposal submission and award notification until transition is complete", "Bring a mentality of continuous improvement to your work including conducting lessons learned after each proposal submission, developing a Gold Standard for business development and proposal activities, and coaching the team regarding appropriate methods to develop and retain levels of customer intimacy", "Consistently evaluate current approaches and processes with the ultimate goal of seeking opportunities to drive efficiencies and improvements", "Define Growth performance benchmarks and report to C-Suite weekly and drive accountability throughout the Growth organization", "Extensive experience in business development, sales, marketing, or a related field, with a track record of driving growth and revenue, GTM strategy, and acquisition implementation", "Lead the effort from selection to closing", "Develop an integration playbook for potential acquisitions", "Work collaboratively with C-Suite to fully integrate the acquisition based on agreed upon strategy", "Ensure seamless integration of tuck-in acquisitions, helping accelerate the path to realized value from adding team members and additional books of business", "Experience building presentations for potential acquisitions and presenting to investors", "Build meaningful relationships up and down the organization", "Effectively, transparently communicate with relevant stakeholders, ensuring seamless collaboration on projects and day-to-day business operations", "Serve as a thought partner to the C Suite on all Growth matters", "Ensure that Our Client has A players in all key roles for driving future growth who consistently seek out opportunities- pounding the pavement to win the right kind of work to propel Our Client into accelerated growth and performance; backfill positions as needed", "Evaluate talent quality and repurpose, replace, or let go of individuals who are not well equipped for the future-state scorecard/role responsibilities", "Effectively influences actions and opinions of others", "Accepts feedback from others", "Gives appropriate recognition to others", "Communication \u2013 Possesses the ability to convey information to others in a clear and understandable way", "Strategic thinking: Bring the ability to see the big picture and understand how your work fits into the company\u2019s goals and the long-term effects of your decisions and actions", "Treats other with respect and consideration regardless of their status or position", "Accepts responsibility for their own actions and follows through on commitments", "Standards of Excellence- Outstanding consultative and operational abilities and excellent interpersonal and presentation skills with executive level customers and partners"], "Benefits": ["Highly competitive Base Salary ($250-300K), Double Digit Bonus, Equity and additional Exec perks", "Fully covered healthcare, dental, and vision coverage + 401(k)", "Unlimited PTO + 11 paid holidays", "Education & training benefits, referral bonuses", "Annual budget for your tech/gadgets needs"]}, "job_job_title": "Senior vice", "job_posting_language": "en", "job_onet_soc": "11101100", "job_onet_job_zone": "5"}