{"job_id": "JIUMa7SNuimlEkWRAAAAAA==", "employer_name": "Prime Communications", "employer_logo": "https://encrypted-tbn0.gstatic.com/images?q=tbn:ANd9GcQFBmYezb8f4jVV_-zn9DM1_rzVkOAkLUu7km0K&s=0", "employer_website": null, "employer_company_type": null, "job_publisher": "Glassdoor", "job_employment_type": "FULLTIME", "job_title": "Retail Sales Consultant", "job_apply_link": "https://www.glassdoor.com/job-listing/retail-sales-consultant-prime-communications-JV_IC1130512_KO0,23_KE24,44.htm?jl=1009120318756", "job_apply_is_direct": true, "job_apply_quality_score": 0.6494, "apply_options": [{"publisher": "Glassdoor", "apply_link": "https://www.glassdoor.com/job-listing/retail-sales-consultant-prime-communications-JV_IC1130512_KO0,23_KE24,44.htm?jl=1009120318756", "is_direct": true}, {"publisher": "Indeed", "apply_link": "https://www.indeed.com/viewjob?jk=a4a0f8a154f5731e", "is_direct": true}, {"publisher": "Talent.com", "apply_link": "https://www.talent.com/view?id=40236cc53c29", "is_direct": false}], "job_description": "Apply Online: www.primecomms.com/career\n\nPrime Communications\n\nWith almost 2,000 AT&T stores coast-to coast, Prime Communications is AT&T's largest authorized wireless retailer in the United States, and we want you to join us as a Retail Sales Consultant!\n\nA Retail Sales Consultant (RSC) is an ambassador to our extraordinarily large base of customers nationwide. As an RSC, you will serve the customer by demonstrating AT&T's vast array of products, services and entertainment options, and offering them personal, valuable solutions to fit their mobility and entertainment needs.\n\nBecause we strive for the best, we offer amongst the best. Our current full-time Retail Sales Consultants earn a minimum base of ($25,000 + commission). Consultants could earn an average of $45,000 in total compensation in the first year when successfully meeting or exceeding sales goals in the first year. Commission is based on meeting outlined sales goals for a given market.\n\nYou'll also be eligible for some or all of our amazing Benefits Packages, such as:\n\u2022 We offer New Hire Ramp Up Bonus payments for the first three months\n\u2022 Training and Opportunity to grow\n\u2022 Supportive team environment\n\u2022 Medical/Dental/Vision, Paid Time Off, 401k and more\n\nNot to mention some pretty cool perks such as:\n\u2022 Paid tuition towards a bachelor's degree (after one year)\n\u2022 Latest devices and discounts on wireless service plans\n\u2022 Using our technology, gain first-hand expertise to share with our customers\n\u2022 Discounts on accessories and additional AT&T products and services, meaning you will always have access to the latest gadgets around\n\nDedication is always a good predictor of success at Prime Communications. Most Store Managers, were once RSCs, most District Managers were once Store Managers, etc. Join the community and forge your own sales path today!\n\u2022 Provide extraordinary customer service by being compassionate towards and understanding their needs\n\u2022 Build value by offering tailored and thoughtful solutions to fit each person, family or business\n\u2022 Represent our Company and the AT&T brand with the utmost professionalism and courtesy\n\u2022 Assist our leaders with store operations and duties\n\u2022 Cooperate with your fellow RSCs to achieve a team approach to sales and customer service\n\u2022 Achieve sales benchmarks and milestones (which can lead to that much needed extra bonus payment)\n\u2022 Excel in selling AT&T's products/services, including entertainment, as we are a full-service lifestyle solution\n\u2022 Work with wireless leaders to stand out, serve and succeed within the local community\n\nRequirements:Requirements\n\u2022 Clear communication skills\n\u2022 Attitude and technical aptitude - having an entrepreneurial spirit speaks volumes\n\nCommitment to exemplary customer service, honesty and integrity Background in retail sales is helpful, but not required At least 18 years old and legally able to work in the United States without restrictions.\n\u2022 * Ability to work a minimum of 32 hours per week including evenings, weekends, and holidays.\n\u2022 Strong Social Media presence preferred\n\u2022 Must have reliable transportation to location, off-site trainings, and meetings.\n\u2022 Must live within 30 minutes of home store location with flexibility to work at multiple locations within a district as needed.\n\u2022 Ability to operate a personal computer, wireless equipment, copier and fax.\n\u2022 Adhere to Team Color policy while maintaining neat and professional appearance.Working Conditions\n\u2022 Ability to lift up to 10 pounds.\n\u2022 Ability to bend, squat and stretch for purposes of inventory and stocking.\n\u2022 Requirement to stand for long periods of time in order to provide the best customer service (with or without a reasonable accommodation).\n\u2022 Ability to work in fast pace environment.\n\u2022 Ability to follow instructions to completion.\n\u2022 Ability to work under pressure, multi-task and handle customer complaints or requests.\n\u2022 Ability to adapt to fluctuating noise levels and varied sounds from multiple media sources/devices.\n\u2022 Problem solves under pressure.\n\nAPPLY ONLINE: www.primecomms.com/career\n\nJob Type: Full-time\n\nPay: $12.00 - $25.00 per hour\n\nBenefits:\n\u2022 401(k)\n\u2022 Dental insurance\n\u2022 Employee discount\n\u2022 Flexible schedule\n\u2022 Health insurance\n\u2022 Paid time off\n\u2022 Vision insurance\n\nShift:\n\u2022 8 hour shift\n\nWeekly day range:\n\u2022 Weekends as needed\n\nEducation:\n\u2022 High school or equivalent (Preferred)\n\nExperience:\n\u2022 Retail Associates & Cashiers: 1 year (Preferred)\n\nWork Location: Multiple locations", "job_is_remote": false, "job_posted_at_timestamp": 1710028800, "job_posted_at_datetime_utc": "2024-03-10T00:00:00.000Z", "job_city": "Clinton", "job_state": "MO", "job_country": "US", "job_latitude": 38.368633, "job_longitude": -93.77827, "job_benefits": ["dental_coverage", "paid_time_off", "health_insurance", "retirement_savings"], "job_google_link": "https://www.google.com/search?gl=us&hl=en&rciv=jb&q=sales+consultant&start=80&ibp=htl;jobs#fpstate=tldetail&htivrt=jobs&htiq=sales+consultant&htidocid=JIUMa7SNuimlEkWRAAAAAA%3D%3D", "job_offer_expiration_datetime_utc": "2024-07-10T00:00:00.000Z", "job_offer_expiration_timestamp": 1720569600, "job_required_experience": {"no_experience_required": false, "required_experience_in_months": null, "experience_mentioned": true, "experience_preferred": false}, "job_required_skills": null, "job_required_education": {"postgraduate_degree": false, "professional_certification": false, "high_school": false, "associates_degree": false, "bachelors_degree": false, "degree_mentioned": true, "degree_preferred": false, "professional_certification_mentioned": false}, "job_experience_in_place_of_education": false, "job_min_salary": 12, "job_max_salary": 25, "job_salary_currency": "USD", "job_salary_period": "HOUR", "job_highlights": {"Qualifications": ["Clear communication skills", "Attitude and technical aptitude - having an entrepreneurial spirit speaks volumes", "Commitment to exemplary customer service, honesty and integrity Background in retail sales is helpful, but not required At least 18 years old and legally able to work in the United States without restrictions", "Ability to work a minimum of 32 hours per week including evenings, weekends, and holidays", "Must have reliable transportation to location, off-site trainings, and meetings", "Must live within 30 minutes of home store location with flexibility to work at multiple locations within a district as needed", "Ability to operate a personal computer, wireless equipment, copier and fax", "Requirement to stand for long periods of time in order to provide the best customer service (with or without a reasonable accommodation)", "Ability to adapt to fluctuating noise levels and varied sounds from multiple media sources/devices"], "Responsibilities": ["Provide extraordinary customer service by being compassionate towards and understanding their needs", "Build value by offering tailored and thoughtful solutions to fit each person, family or business", "Represent our Company and the AT&T brand with the utmost professionalism and courtesy", "Assist our leaders with store operations and duties", "Cooperate with your fellow RSCs to achieve a team approach to sales and customer service", "Achieve sales benchmarks and milestones (which can lead to that much needed extra bonus payment)", "Work with wireless leaders to stand out, serve and succeed within the local community", "Adhere to Team Color policy while maintaining neat and professional appearance", "Ability to work under pressure, multi-task and handle customer complaints or requests", "8 hour shift"], "Benefits": ["Our current full-time Retail Sales Consultants earn a minimum base of ($25,000 + commission)", "Consultants could earn an average of $45,000 in total compensation in the first year when successfully meeting or exceeding sales goals in the first year", "We offer New Hire Ramp Up Bonus payments for the first three months", "Training and Opportunity to grow", "Supportive team environment", "Medical/Dental/Vision, Paid Time Off, 401k and more", "Paid tuition towards a bachelor's degree (after one year)", "Latest devices and discounts on wireless service plans", "Discounts on accessories and additional AT&T products and services, meaning you will always have access to the latest gadgets around", "Pay: $12.00 - $25.00 per hour", "401(k)", "Dental insurance", "Employee discount", "Flexible schedule", "Health insurance", "Vision insurance"]}, "job_job_title": "Sales consultant", "job_posting_language": "en", "job_onet_soc": "41203100", "job_onet_job_zone": "2"}