{"job_id": "hmGkP_p71yjBK8LGAAAAAA==", "employer_name": "Florida Blue", "employer_logo": null, "employer_website": null, "employer_company_type": null, "job_publisher": "Florida Blue Career", "job_employment_type": "FULLTIME", "job_title": "FBM Affinity Partner Strategist", "job_apply_link": "https://careers.floridablue.com/us/en/job/33096/FBM-Affinity-Partner-Strategist", "job_apply_is_direct": false, "job_apply_quality_score": 0.9085, "apply_options": [{"publisher": "Florida Blue Career", "apply_link": "https://careers.floridablue.com/us/en/job/33096/FBM-Affinity-Partner-Strategist", "is_direct": false}, {"publisher": "GuideWell Careers", "apply_link": "https://careers.guidewell.com/us/en/job/33096/FBM-Affinity-Partner-Strategist", "is_direct": false}, {"publisher": "LinkedIn", "apply_link": "https://www.linkedin.com/jobs/view/fbm-affinity-partner-strategist-at-florida-blue-3826524467", "is_direct": false}, {"publisher": "Glassdoor", "apply_link": "https://www.glassdoor.com/job-listing/fbm-affinity-partner-strategist-florida-blue-JV_KO0,31_KE32,44.htm?jl=1009024892064", "is_direct": false}, {"publisher": "Indeed", "apply_link": "https://www.indeed.com/viewjob?jk=d239838a89eee9e1", "is_direct": false}], "job_description": "Job Summary\nThe Affinity Partner Strategist is accountable for the end-to-end management of our Field Marketing Organizations (FMO) Partners and other Affinity partner channels in the future. The strategist requires good business acumen, legal acuity, product knowledge, project management and organizational skills. These skills, combined with a suite of competencies designed to successfully navigate the enterprise and vendor community, are necessary to build and manage a sustainable and scalable model that reviews and tracks well constructed, mid-complexity solutions and contracts balancing risk and vendor accountabilities. Candidate must be a self -starter who requires minimal supervision in performing assigned tasks and has the ability to comprehend legal, financial and business concepts.\n\nEssential Functions\n\u2022 The essential functions listed represent the major duties of this role, additional duties may be assigned.\n\u2022 Supports the Florida Blue Medicare leadership team in designing and executing FMO related business processes which meet critical business objectives. Translates strategies into tactical application for vendor execution.\n\u2022 Responsible for vendor relationship management, contract execution, contract adherence, contract performance, vendor scorecards, payment reconciliation and continuous improvement initiatives. Manages vendor program performance and adherence to established SLAs, scorecards, ROI.\n\u2022 Works collaboratively with business stakeholders, Procurement, Compliance, Legal, IT Security, Finance, Product, Actuarial, Sales Compensation and other areas to ensure vendors are held to corporate performance and compliance standards.\n\u2022 Consults with leadership and appropriate corporate departments to ensure vendor issues are quickly addressed and risks to the company are mitigated.\n\u2022 Provides input for the vendor program budget and performs vendor invoice reconciliation.\n\nQualifications\n\nRequired Work Experience\n5+ years related work experience. Experience Details: Medicare External Distribution\n\nRequired Management Experience\n3+ years direct supervisory/management experience\n\nRequired Education\nRelated Bachelor\u2019s degree or additional related equivalent work experience\n\nAdditional Required Qualifications\n\nExperience in Medicare Advantage Sales Management.\nDemonstrated communication and coordination skills managing multiple issues, including communications and planning\nProven ability to manage multiple complex business issues\nTraining/facilitation experience\nAbility to travel 50%\n\nPreferred Education\nMaster\u2019s degree Or relevant business/managed care experience.\n\nAdditional Preferred Qualifications\nVendor Management experience Program management experience Florida 215 Insurance Medicare Certification\n\nGeneral Physical Demands\nSedentary work: Exerting up to 10 pounds of force occasionally to move objects. Jobs are sedentary if traversing activities are required only occasionally.\n\nPhysical/Environmental Activities\nMust be able to travel to multiple locations for work (i.e. travel to attend meetings, events, conferences). Occasionally\n\nWhat We Offer:\nAs a Florida Blue employee, you will thrive in our Be Well, Work Well, GuideWell culture where being well as an individual, and working well as a team, are both important in serving our members and communities.\n\nTo support your wellbeing, comprehensive benefits are offered. As an employee, you will have access to:\n\n\u00b7 Medical, dental, vision, life and global travel health insurance;\n\n\u00b7 Income protection benefits: life insurance, Short- and long-term disability programs;\n\n\u00b7 Leave programs to support personal circumstances;\n\n\u00b7 Retirement Savings Plan includes employer contribution and employer match;\n\n\u00b7 Paid time off, volunteer time off, and 11 holidays\n\n\u00b7 Additional voluntary benefits available; and\n\n\u00b7 A comprehensive wellness program\nEmployee benefits are designed to align with federal and state employment laws. Benefits may vary based on the state in which work is performed. Benefits for intern, part-time and seasonal employees may differ.\n\nTo support your financial wellbeing, we offer competitive pay as well as opportunities for incentive or commission compensation. We also conduct regular annual reviews with pay for performance considerations for base pay increases.\n\nAnnualized Salary Range: $78,400 - $127,400\n\nTypical Annualized Hiring Range: $78,400 - $98,000- We would likely be looking at a higher salary entry point\n\nFinal pay will be determined with consideration of market competitiveness, internal equity, and the job-related knowledge, skills, training, and experience you bring.\n\nWe are an Equal Opportunity/Protected Veteran/Disabled Employer committed to creating a diverse, inclusive and equitable culture for our employees and communities.\n\nThis section is used for Immigration HR Notices Only.", "job_is_remote": false, "job_posted_at_timestamp": 1707436800, "job_posted_at_datetime_utc": "2024-02-09T00:00:00.000Z", "job_city": null, "job_state": null, "job_country": "US", "job_latitude": 37.09024, "job_longitude": -95.71289, "job_benefits": ["retirement_savings", "dental_coverage", "paid_time_off", "health_insurance"], "job_google_link": "https://www.google.com/search?gl=us&hl=en&rciv=jb&q=senior+manager+of+brand+partnerships&start=10&ibp=htl;jobs#fpstate=tldetail&htivrt=jobs&htiq=senior+manager+of+brand+partnerships&htidocid=hmGkP_p71yjBK8LGAAAAAA%3D%3D", "job_offer_expiration_datetime_utc": null, "job_offer_expiration_timestamp": null, "job_required_experience": {"no_experience_required": false, "required_experience_in_months": 60, "experience_mentioned": true, "experience_preferred": false}, "job_required_skills": null, "job_required_education": {"postgraduate_degree": false, "professional_certification": false, "high_school": false, "associates_degree": false, "bachelors_degree": false, "degree_mentioned": true, "degree_preferred": false, "professional_certification_mentioned": true}, "job_experience_in_place_of_education": false, "job_min_salary": null, "job_max_salary": null, "job_salary_currency": null, "job_salary_period": null, "job_highlights": {"Qualifications": ["These skills, combined with a suite of competencies designed to successfully navigate the enterprise and vendor community, are necessary to build and manage a sustainable and scalable model that reviews and tracks well constructed, mid-complexity solutions and contracts balancing risk and vendor accountabilities", "Candidate must be a self -starter who requires minimal supervision in performing assigned tasks and has the ability to comprehend legal, financial and business concepts", "Required Work Experience", "5+ years related work experience", "Experience Details: Medicare External Distribution", "Required Management Experience", "3+ years direct supervisory/management experience", "Related Bachelor\u2019s degree or additional related equivalent work experience", "Experience in Medicare Advantage Sales Management", "Demonstrated communication and coordination skills managing multiple issues, including communications and planning", "Proven ability to manage multiple complex business issues", "Training/facilitation experience", "Ability to travel 50%", "Master\u2019s degree Or relevant business/managed care experience", "Vendor Management experience Program management experience Florida 215 Insurance Medicare Certification", "Must be able to travel to multiple locations for work (i.e"], "Responsibilities": ["The strategist requires good business acumen, legal acuity, product knowledge, project management and organizational skills", "The essential functions listed represent the major duties of this role, additional duties may be assigned", "Supports the Florida Blue Medicare leadership team in designing and executing FMO related business processes which meet critical business objectives", "Translates strategies into tactical application for vendor execution", "Responsible for vendor relationship management, contract execution, contract adherence, contract performance, vendor scorecards, payment reconciliation and continuous improvement initiatives", "Manages vendor program performance and adherence to established SLAs, scorecards, ROI", "Works collaboratively with business stakeholders, Procurement, Compliance, Legal, IT Security, Finance, Product, Actuarial, Sales Compensation and other areas to ensure vendors are held to corporate performance and compliance standards", "Consults with leadership and appropriate corporate departments to ensure vendor issues are quickly addressed and risks to the company are mitigated", "Provides input for the vendor program budget and performs vendor invoice reconciliation", "Sedentary work: Exerting up to 10 pounds of force occasionally to move objects", "travel to attend meetings, events, conferences)"], "Benefits": ["To support your wellbeing, comprehensive benefits are offered", "Medical, dental, vision, life and global travel health insurance;", "Income protection benefits: life insurance, Short- and long-term disability programs;", "Leave programs to support personal circumstances;", "Retirement Savings Plan includes employer contribution and employer match;", "Paid time off, volunteer time off, and 11 holidays", "Additional voluntary benefits available; and", "A comprehensive wellness program", "Employee benefits are designed to align with federal and state employment laws", "Benefits may vary based on the state in which work is performed", "Benefits for intern, part-time and seasonal employees may differ", "To support your financial wellbeing, we offer competitive pay as well as opportunities for incentive or commission compensation", "We also conduct regular annual reviews with pay for performance considerations for base pay increases", "Typical Annualized Hiring Range: $78,400 - $98,000- We would likely be looking at a higher salary entry point"]}, "job_job_title": "Strategist", "job_posting_language": "en", "job_onet_soc": "11202100", "job_onet_job_zone": "4", "job_occupational_categories": ["Sales/Marketing"]}