{"job_id": "yuMeD_xFLhK_W4POAAAAAA==", "employer_name": "AAA-Auto Club Enterprises", "employer_logo": "https://media.licdn.com/dms/image/D560BAQFSwFqzgzmstQ/company-logo_200_200/0/1688571941229/aaa_auto_club_enterprises_logo?e=2147483647&v=beta&t=r8_C7zOm_bW137Ol_sPbOPs2mH1XQwbq6W58PFQ1R9E", "employer_website": null, "employer_company_type": null, "job_publisher": "Jobgether", "job_employment_type": "FULLTIME", "job_title": "Data Engineer", "job_apply_link": "https://jobgether.com/offer/65f9313b985db011cb50c523-data-engineer", "job_apply_is_direct": false, "job_apply_quality_score": 0.5719, "apply_options": [{"publisher": "Jobgether", "apply_link": "https://jobgether.com/offer/65f9313b985db011cb50c523-data-engineer", "is_direct": false}], "job_description": "This a Full Remote job, the offer is available from: United States\n\n\"\n\nData Engineer\n\nAs our Data Engineer, you will function as an expert in developing data solutions to help solve business challenges. You will work with closely with data scientists, data engineers, and digital focused business units.\n\nTo thrive in this role, experience in cloud and big data technologies as well as an expert in querying and processing large data sets of 200,000 rows or more, ideally in SQL, is recommended. Programming languages like Python and Spark are core languages we utilize. Be prepared to share an example of how you design and develop a solution to a business problem.\n\nWhat You\u2019ll Do\n\u2022 Work on designing and developing solutions to support our digital data technology challenges and needs. Our team\u2019s success isn\u2019t just implementing the code but seeing that the data solutions we develop enable stakeholders to gain insights and have the necessary tools to accomplish their goals.\n\u2022 Ask questions and do quality testing to understand if the solution meets the objectives of the business or the goal we set for the business. You will work side-by-side with the business to make sure it works as expected, not just as designed.\n\u2022 Partner with other data engineers on the team, and review solutions to check for quality and completeness of the solution for the business problem. Clearly communicate solutions to business owners.\n\u2022 Consistently learn and find ways to improve self and team\n\nWhat You\u2019ll Need\n\u2022 To thrive in this role, having a passion for problem-solving using data is recommended. Your experience in querying the high volumes of data and doing the data analysis must inform how you design solutions that align with the business objectives.\n\u2022 Experience in data management and strategy\n\u2022 Knowledgeable in data technologies, preferably with cloud solutions such as AWS (e.g. EC2, S3, Lambda, API Gateway, GLUE), and SaaS solutions\n\u2022 Experience in developing low friction APIs, highly responsive RESTful web U.I.s, and the backend to support them. MuleSoft experience is preferred.\n\u2022 Being proficient with SQL and programming languages such as Python and Spark is a must.\n\u2022 Experience with data integration from different sources into Big Data systems is preferrable.\n\u2022 Experience with design, coding, and quality testing. These solutions will deploy across products that are important to our customers and the business. They must be high-quality and functional.\n\u2022 A willingness to collaborate. Our best work is done when we work together - either with non-technical or technical leads. You should be interested in learning from others regardless of their role in the organization.\n\u2022 Ability to communicate effectively technically as well as broadly.\n\u2022 You have worked previously with an Agile team or understand these concepts. Expect to participate in daily standup meetings, you\u2019ll complete your projects or stories during our sprints, and you\u2019ll be ready to meet frequent deployment\n\n#LI-SJ1\n\nThe starting pay range for this position is:\n\n$104,400.00 - $139,200.00\n\nAdditionally, you will be eligible to participate in our incentive program based upon the achievement of organization, team and personal performance.\n\n.\n\nRemarkable benefits:\n\u2022 Health coverage for medical, dental, vision\n\u2022 401(K) saving plan with company match AND Pension\n\u2022 Tuition assistance\n\u2022 PTO for community volunteer programs\n\u2022 Wellness program\n\u2022 Employee discounts\n\nThe Automobile Club of Southern California is part of the largest federation of AAA clubs in the nation. We have 14,000 employees in 21 states helping 17 million members. The strength of our organization is our employees. Bringing together and supporting different cultures, backgrounds, personalities, and strengths creates a team capable of delivering legendary, lifetime service to our members. When we embrace our diversity \u2013 we win. All of Us! With our national brand recognition, long-standing reputation since 1902, and constantly growing membership, we are seeking career-minded, service-driven professionals to join our team.\n\n\u201cThrough dedicated employees we proudly deliver legendary service and beneficial products that provide members peace of mind and value.\u201d\n\nAAA is an Equal Opportunity Employer\n\nThe Automobile Club of Southern California will consider for employment all qualified applicants, including those with criminal histories, in a manner consistent with the requirements of applicable federal, state and local laws, including the City of Los Angeles\u2019 Fair Chance Initiative for Hiring Ordinance.\n\n\"This offer from \"AAA-Auto Club Enterprises\" has been enriched by Jobgether and got a 77% flex score.", "job_is_remote": true, "job_posted_at_timestamp": 1710781799, "job_posted_at_datetime_utc": "2024-03-18T17:09:59.000Z", "job_city": null, "job_state": "SD", "job_country": "US", "job_latitude": 43.969513, "job_longitude": -99.90181, "job_benefits": ["health_insurance", "dental_coverage", "paid_time_off", "retirement_savings"], "job_google_link": "https://www.google.com/search?gl=us&hl=en&rciv=jb&q=data+engineer&start=0&ibp=htl;jobs#fpstate=tldetail&htivrt=jobs&htiq=data+engineer&htidocid=yuMeD_xFLhK_W4POAAAAAA%3D%3D", "job_offer_expiration_datetime_utc": "2024-09-15T06:32:15.000Z", "job_offer_expiration_timestamp": 1726381935, "job_required_experience": {"no_experience_required": false, "required_experience_in_months": null, "experience_mentioned": true, "experience_preferred": true}, "job_required_skills": null, "job_required_education": {"postgraduate_degree": false, "professional_certification": false, "high_school": false, "associates_degree": false, "bachelors_degree": false, "degree_mentioned": false, "degree_preferred": false, "professional_certification_mentioned": false}, "job_experience_in_place_of_education": false, "job_min_salary": 104400, "job_max_salary": 139200, "job_salary_currency": "USD", "job_salary_period": "YEAR", "job_highlights": {"Qualifications": ["To thrive in this role, experience in cloud and big data technologies as well as an expert in querying and processing large data sets of 200,000 rows or more, ideally in SQL, is recommended", "To thrive in this role, having a passion for problem-solving using data is recommended", "Your experience in querying the high volumes of data and doing the data analysis must inform how you design solutions that align with the business objectives", "Experience in data management and strategy", "Knowledgeable in data technologies, preferably with cloud solutions such as AWS (e.g", "EC2, S3, Lambda, API Gateway, GLUE), and SaaS solutions", "Experience in developing low friction APIs, highly responsive RESTful web U.I.s, and the backend to support them", "They must be high-quality and functional", "Our best work is done when we work together - either with non-technical or technical leads", "You should be interested in learning from others regardless of their role in the organization", "Ability to communicate effectively technically as well as broadly", "You have worked previously with an Agile team or understand these concepts"], "Responsibilities": ["As our Data Engineer, you will function as an expert in developing data solutions to help solve business challenges", "You will work with closely with data scientists, data engineers, and digital focused business units", "Be prepared to share an example of how you design and develop a solution to a business problem", "Work on designing and developing solutions to support our digital data technology challenges and needs", "Our team\u2019s success isn\u2019t just implementing the code but seeing that the data solutions we develop enable stakeholders to gain insights and have the necessary tools to accomplish their goals", "Ask questions and do quality testing to understand if the solution meets the objectives of the business or the goal we set for the business", "You will work side-by-side with the business to make sure it works as expected, not just as designed", "Partner with other data engineers on the team, and review solutions to check for quality and completeness of the solution for the business problem", "Clearly communicate solutions to business owners", "Consistently learn and find ways to improve self and team", "These solutions will deploy across products that are important to our customers and the business"], "Benefits": ["$104,400.00 - $139,200.00", "Additionally, you will be eligible to participate in our incentive program based upon the achievement of organization, team and personal performance", "Health coverage for medical, dental, vision", "401(K) saving plan with company match AND Pension", "Tuition assistance", "PTO for community volunteer programs", "Wellness program", "Employee discounts"]}, "job_job_title": "Data engineer", "job_posting_language": "en", "job_onet_soc": "15113200", "job_onet_job_zone": "4"}