{"job_id": "ZlfDJSJ28h1jm6V6AAAAAA==", "employer_name": "Pfizer Inc.", "employer_logo": "https://encrypted-tbn0.gstatic.com/images?q=tbn:ANd9GcRSPX7X6GEWIrta56QMzA1s1DUQZQXMBA7Q9vKB&s=0", "employer_website": "http://www.pfizer.com", "employer_company_type": "Manufacturing", "job_publisher": "Karkidi", "job_employment_type": "FULLTIME", "job_title": "Senior Manager, Data Science, Business Analytics & Insights", "job_apply_link": "https://www.karkidi.com/job-details/31432-senior-manager-data-science-business-analytics-insights-job", "job_apply_is_direct": false, "job_apply_quality_score": 0.6181, "apply_options": [{"publisher": "Karkidi", "apply_link": "https://www.karkidi.com/job-details/31432-senior-manager-data-science-business-analytics-insights-job", "is_direct": false}], "job_description": "Business Analytics & Insights (BAI) harnesses the power of data to drive robust analytical insights that inform some of Pfizer's most critical business questions. With colleagues across the globe, BAI\u2019s rigorous analytical expertise is depended on as the compass and decision support for the enterprise. Our dynamic, exciting team of subject-matter experts comes from diverse backgrounds and experiences, including market research, data science, digital analytics, finance, and consulting. As a team, we partner to turn data into meaningful insights that will have a direct impact on patient's lives and the future of Pfizer as a data-driven organization.\n\nThe Senior Manager, Data Science, Business Analytics & Insights is accountable for delivering data science driven strategic and tactical support for an assigned US brand. As a strategic partner to the US Commercial and Medical team, this person will develop and implement models and data-science derived insights that drive brands\u2019 strategic priorities. This will include driving the execution and interpretation AI/ML models, framing problems, and shaping solutions. Also, this person will help shape the brands\u2019 strategies and tactics by interfacing closely with Data Science COEs to develop bespoke AI/ML models to meet evolving needs, and interface closely with omnichannel-operations to drive execution.\n\nThis role is dynamic, fast-paced, highly collaborative, and covers a broad range of strategic topics that are critical to our business. The successful candidate will join BAI colleagues worldwide that are constantly supporting business transformation through their proactive thought leadership, innovative analytical capabilities, and their ability to communicate highly complex and dynamic information in new and creative ways.\n\nROLE RESPONSIBILITIES\n\nRole definition and key accountabilities include, but are not limited to:\n\nCommercial and Medical Data Science and Insights\n\u2022 Provide data science and insights to US Commercial and Medical teams to drive brand tactic decisions\n\u2022 Act as strategic partner to frame, investigate, translate complex data related models, and answer key business questions related to the identification and evaluation of Commercial and Medical brand strategies and tactics\n\u2022 Interface with Omnichannel-operations on execution and data science bespoke analytical needs\n\u2022 Connect machine learning models and insights together to identify Medical and Commercial brand opportunities and tactics to execute\n\u2022 Guide Medical and Commercial brand teams via compelling and persuasive story and deliver clear and actionable brand tactic recommendations\n\u2022 Track and analyze impacts of Medical and Commercial brand strategies and tactics using dashboards and data products\n\nCollaborate with Data Science COE\n\u2022 Partner with Data Science COE to develop bespoke AI and machine learning models; Configure pre-built models and interpret updated results\n\u2022 Ensure alignment with Data Science COEs teams to ensure cohesive activities with stakeholders\n\nCollaboration with other BAI and Analytics teams\n\u2022 Partner with BAI brand lead to incorporate data science capabilities and insights into analytics plans and recommendations\n\u2022 Contribute to the advancement of BAI data science and consulting capabilities; seek to share knowledge and expertise with other colleagues making use of knowledge sharing platform\n\u2022 Ensure alignment across BAI Data Science teams and Data Science COE teams to ensure cohesive activities with our stakeholders\n\u2022 Partner with other analytic functions to advance the use of novel data sources, including RWD\n\nPROFESSIONAL CHARACTERISTICS\n\u2022 Analytical Thinker\n\u2022 Strong Data and Information Manager\n\u2022 Exceptional Communicator\n\u2022 Relationship Manager\n\u2022 Highly Collaborative\n\u2022 Strong Project Manager\n\u2022 Proactive Self-Starter\n\nREQUIRED BASIC QUALIFICATIONS\n\u2022 Bachelor\u2019s degree required, ideally in quantitative discipline like engineering or data science\n\u2022 4+ years\u2019 experience in business analytics function, country strategy and/or strategic consulting\n\u2022 5+ years of work experience\n\u2022 Experience using data science models to solve problems in a business environment setting\n\u2022 Experience with machine learning technology, such as: big data stack, Python, R, and visualization techniques\n\u2022 Experience in understanding brand content, strategy, and tactics\n\u2022 Ability to effectively utilize dashboards and data products to derive insights\n\u2022 Understands quantitative and qualitative research methodologies\n\u2022 Experience in management of secondary data with application of real-world data\n\u2022 Ability to partner with cross-functional teams (Commercial, Medical, Operations) to execute brand tactics\n\u2022 Proven ability to connect, integrate and synthesize analysis and data into a meaningful \u2018so what\u2019 to drive concrete strategic recommendations for brand tactics. Capable of describing relevant caveats in data or in a model and how they relate to business question\n\u2022 Ability to be flexible, prioritize multiple demands and deal with ambiguity\n\u2022 Fluent in English (written and spoken)\n\u2022 Strong MS Excel and PowerPoint skills\n\nPREFERRED QUALIFICATIONS\n\u2022 Advanced degree preferred in business administration, statistics, or other relevant field\n\u2022 Experience in Life Sciences Industry\n\nCandidate demonstrates a breadth of diverse leadership experiences and capabilities including: the ability to influence and collaborate with peers, develop and coach others, oversee and guide the work of other colleagues to achieve meaningful outcomes and create business impact.", "job_is_remote": false, "job_posted_at_timestamp": 1674864000, "job_posted_at_datetime_utc": "2023-01-28T00:00:00.000Z", "job_city": "New York", "job_state": "NY", "job_country": "US", "job_latitude": 40.712776, "job_longitude": -74.005974, "job_benefits": null, "job_google_link": "https://www.google.com/search?gl=us&hl=en&rciv=jb&q=director+of+advanced+analytics&start=70&ibp=htl;jobs#fpstate=tldetail&htivrt=jobs&htiq=director+of+advanced+analytics&htidocid=ZlfDJSJ28h1jm6V6AAAAAA%3D%3D", "job_offer_expiration_datetime_utc": null, "job_offer_expiration_timestamp": null, "job_required_experience": {"no_experience_required": false, "required_experience_in_months": 48, "experience_mentioned": true, "experience_preferred": false}, "job_required_skills": ["Java Programming"], "job_required_education": {"postgraduate_degree": false, "professional_certification": false, "high_school": false, "associates_degree": false, "bachelors_degree": false, "degree_mentioned": true, "degree_preferred": true, "professional_certification_mentioned": false}, "job_experience_in_place_of_education": false, "job_min_salary": 160000, "job_max_salary": 240000, "job_salary_currency": "USD", "job_salary_period": "YEAR", "job_highlights": {"Qualifications": ["Analytical Thinker", "Strong Data and Information Manager", "Exceptional Communicator", "Relationship Manager", "Highly Collaborative", "Strong Project Manager", "Proactive Self-Starter", "Bachelor\u2019s degree required, ideally in quantitative discipline like engineering or data science", "4+ years\u2019 experience in business analytics function, country strategy and/or strategic consulting", "5+ years of work experience", "Experience using data science models to solve problems in a business environment setting", "Experience with machine learning technology, such as: big data stack, Python, R, and visualization techniques", "Experience in understanding brand content, strategy, and tactics", "Ability to effectively utilize dashboards and data products to derive insights", "Understands quantitative and qualitative research methodologies", "Experience in management of secondary data with application of real-world data", "Ability to partner with cross-functional teams (Commercial, Medical, Operations) to execute brand tactics", "Proven ability to connect, integrate and synthesize analysis and data into a meaningful \u2018so what\u2019 to drive concrete strategic recommendations for brand tactics", "Capable of describing relevant caveats in data or in a model and how they relate to business question", "Ability to be flexible, prioritize multiple demands and deal with ambiguity", "Fluent in English (written and spoken)", "Strong MS Excel and PowerPoint skills", "Candidate demonstrates a breadth of diverse leadership experiences and capabilities including: the ability to influence and collaborate with peers, develop and coach others, oversee and guide the work of other colleagues to achieve meaningful outcomes and create business impact"], "Responsibilities": ["The Senior Manager, Data Science, Business Analytics & Insights is accountable for delivering data science driven strategic and tactical support for an assigned US brand", "As a strategic partner to the US Commercial and Medical team, this person will develop and implement models and data-science derived insights that drive brands\u2019 strategic priorities", "This will include driving the execution and interpretation AI/ML models, framing problems, and shaping solutions", "Also, this person will help shape the brands\u2019 strategies and tactics by interfacing closely with Data Science COEs to develop bespoke AI/ML models to meet evolving needs, and interface closely with omnichannel-operations to drive execution", "This role is dynamic, fast-paced, highly collaborative, and covers a broad range of strategic topics that are critical to our business", "Provide data science and insights to US Commercial and Medical teams to drive brand tactic decisions", "Act as strategic partner to frame, investigate, translate complex data related models, and answer key business questions related to the identification and evaluation of Commercial and Medical brand strategies and tactics", "Connect machine learning models and insights together to identify Medical and Commercial brand opportunities and tactics to execute", "Guide Medical and Commercial brand teams via compelling and persuasive story and deliver clear and actionable brand tactic recommendations", "Track and analyze impacts of Medical and Commercial brand strategies and tactics using dashboards and data products", "Collaborate with Data Science COE", "Partner with Data Science COE to develop bespoke AI and machine learning models; Configure pre-built models and interpret updated results", "Collaboration with other BAI and Analytics teams", "Partner with BAI brand lead to incorporate data science capabilities and insights into analytics plans and recommendations", "Contribute to the advancement of BAI data science and consulting capabilities; seek to share knowledge and expertise with other colleagues making use of knowledge sharing platform", "Ensure alignment across BAI Data Science teams and Data Science COE teams to ensure cohesive activities with our stakeholders", "Partner with other analytic functions to advance the use of novel data sources, including RWD"]}, "job_job_title": "Senior manager", "job_posting_language": "en", "job_onet_soc": "11302100", "job_onet_job_zone": "4", "job_naics_code": "325412", "job_naics_name": "Pharmaceutical Preparation Manufacturing"}