{"job_id": "mXsnrsbsAHiX3UTTAAAAAA==", "employer_name": "Walmart", "employer_logo": "https://animationvisarts.com/wp-content/uploads/2020/08/Walmart-logo-2008-Now.jpg", "employer_website": "https://www.walmart.com", "employer_company_type": "Retail", "job_publisher": "GrabJobs", "job_employment_type": "FULLTIME", "job_title": "Senior Manager/ Learning and Development", "job_apply_link": "https://grabjobs.co/us/job/full-time/retail/senior-manager-learning-and-development-42176763", "job_apply_is_direct": true, "job_apply_quality_score": 0.475, "apply_options": [{"publisher": "GrabJobs", "apply_link": "https://grabjobs.co/us/job/full-time/retail/senior-manager-learning-and-development-42176763", "is_direct": true}], "job_description": "Position Summary...\n\nWhat you'll do...\n\nWalmart Connect, Senior Manager of Learning & Development (Sales Training and Enablement)\n\nWalmart Connect is seeking an experienced education professional to lead the sales training and enablement programs for our sales organization.\n\nAs a startup within the world's largest retailer, we are quickly developing new ad tech and internal tools and systems. You will play an integral role in ensuring Walmart Connect salespeople, have the knowledge and skills be successful in their position.\n\nIn this role, you and your team will be responsible to develop courses and facilitate training for all salespeople. In addition, you will design and drive sales enablement programs to enhance sellers' revenue performance.\n\nResponsibilities:\n\u2022 Design and implement sales enablement programs\n\u2022 Lead sales workshops and training sessions\n\u2022 Collaborate with subject matter experts to develop sales training content for workshops\n\u2022 Identify and track learning metrics to ensure effectiveness and ROI of programs/initiatives, specific to sales training activities.\n\u2022 Facilitate weekly meetings with sales leaders and their teams.\n\u2022 Meet with leaders to gain alignment and feedback on new and existing training programs.\n\u2022 Conduct ongoing knowledge and skills assessments for sales associates\n\nMinimum Qualifications...\n\u2022 Minimum Qualifications Bachelor's degree\n\u2022 5+ years of experience in sales training or sales enablement\n\u2022 Minimum 2-3 years of experience in high-tech, eCommerce or Advertising industry\n\u2022 Proven success as a meeting and program facilitator\n\u2022 Strong EQ skills\n\u2022 Sales experience (B2B) 3-5 years\n\u2022 Excellent communication skills - both verbal and written\n\u2022 Excellent program management skills\n\u2022 Self-starter who thrives on the excitement and challenge to build programs and teams. Collaboration and partnership with stakeholders at all levels is key.\n\u2022 Ability to move fast, in an often ambiguous and fluid environment\n\nPreferred Qualifications...\n\u2022 Masters: Business Administration\n\u2022 Sales leadership experience\n\nAt Walmart, we offer competitive pay as well as performance-based incentive awards and other great benefits for a happier mind, body, and wallet. Health benefits include medical, vision and dental coverage. Financial benefits include 401(k), stock purchase and company-paid life insurance. Paid time off benefits include PTO (including sick leave), parental leave, family care leave, bereavement, jury duty, and voting. Other benefits include short-term and long-term disability, company discounts, Military Leave Pay, adoption and surrogacy expense reimbursement, and more.\n\nYou will also receive PTO and/or PPTO that can be used for vacation, sick leave, holidays, or other purposes. The amount you receive depends on your job classification and length of employment. It will meet or exceed the requirements of paid sick leave laws, where applicable. For information about PTO, see .\n\nLive Better U is a Walmart-paid education benefit program for full-time and part-time associates in Walmart and Sam's Club facilities. Programs range from high school completion to bachelor's degrees, including English Language Learning and short-form certificates. Tuition, books, and fees are completely paid for by Walmart.\n\nEligibility requirements apply to some benefits and may depend on your job classification and length of employment. Benefits are subject to change and may be subject to a specific plan or program terms. For information about benefits and eligibility, see One.Walmart at .\n\nThe annual salary range for this position is $108,000.00-$216,000.00\n\nAdditional compensation includes annual or quarterly performance incentives.\n\nAdditional compensation for certain positions may also include:\n\u2022 Regional Pay Zone (RPZ) (based on location)\n\u2022 Stock equity incentives\n\nMinimum Qualifications...\n\nOutlined below are the required minimum qualifications for this position. If none are listed, there are no minimum qualifications.\n\nBachelor's degree in Business, Human Resources, Communications, Education, or related field and 4 years' experience in adult learning, training content development, or related area OR 6 years' experience in adult learning, training content development, or related area.\n\nPreferred Qualifications...\n\nOutlined below are the optional preferred qualifications for this position. If none are listed, there are no preferred qualifications.\n\nInstructional Design Software, Leading cross-functional teams, Master's degree in Learning and Development, Human Resources, or related field, Project Management Certification, Project management experience, Six Sigma certification, Supervisory experience\n\nPrimary Location...\n\n221 RIVER ST, HOBOKEN, NJ 07030, United States of America\n\nWalmart, Inc. is an Equal Opportunity Employer- By Choice. We believe we are best equipped to help our associates, customers, and the communities we serve live better when we really know them. That means understanding, respecting, and valuing diversity- unique styles, experiences, identities, abilities, ideas and opinions- while being inclusive of all people.\n\nOriginal job Senior Manager/ Learning and Development posted on GrabJobs \u00a9. To flag any issues with this job please use the Report Job button on GrabJobs.", "job_is_remote": false, "job_posted_at_timestamp": 1708507564, "job_posted_at_datetime_utc": "2024-02-21T09:26:04.000Z", "job_city": "Hoboken", "job_state": "NJ", "job_country": "US", "job_latitude": 40.74399, "job_longitude": -74.032364, "job_benefits": ["retirement_savings", "paid_time_off", "dental_coverage", "health_insurance"], "job_google_link": "https://www.google.com/search?gl=us&hl=en&rciv=jb&q=senior+manager+of+sales+training&start=0&ibp=htl;jobs#fpstate=tldetail&htivrt=jobs&htiq=senior+manager+of+sales+training&htidocid=mXsnrsbsAHiX3UTTAAAAAA%3D%3D", "job_offer_expiration_datetime_utc": "2024-03-21T09:26:04.000Z", "job_offer_expiration_timestamp": 1711013164, "job_required_experience": {"no_experience_required": false, "required_experience_in_months": 72, "experience_mentioned": true, "experience_preferred": false}, "job_required_skills": null, "job_required_education": {"postgraduate_degree": false, "professional_certification": false, "high_school": false, "associates_degree": false, "bachelors_degree": false, "degree_mentioned": true, "degree_preferred": true, "professional_certification_mentioned": true}, "job_experience_in_place_of_education": false, "job_min_salary": null, "job_max_salary": null, "job_salary_currency": null, "job_salary_period": null, "job_highlights": {"Qualifications": ["Minimum Qualifications Bachelor's degree", "5+ years of experience in sales training or sales enablement", "Minimum 2-3 years of experience in high-tech, eCommerce or Advertising industry", "Proven success as a meeting and program facilitator", "Strong EQ skills", "Sales experience (B2B)", "3-5 years", "Excellent communication skills - both verbal and written", "Excellent program management skills", "Self-starter who thrives on the excitement and challenge to build programs and teams", "Bachelor's degree in Business, Human Resources, Communications, Education, or related field and 4 years' experience in adult learning, training content development, or related area OR 6 years' experience in adult learning, training content development, or related area", "Instructional Design Software, Leading cross-functional teams, Master's degree in Learning and Development, Human Resources, or related field, Project Management Certification, Project management experience, Six Sigma certification, Supervisory experience"], "Responsibilities": ["You will play an integral role in ensuring Walmart Connect salespeople, have the knowledge and skills be successful in their position", "In this role, you and your team will be responsible to develop courses and facilitate training for all salespeople", "In addition, you will design and drive sales enablement programs to enhance sellers' revenue performance", "Lead sales workshops and training sessions", "Collaborate with subject matter experts to develop sales training content for workshops", "Identify and track learning metrics to ensure effectiveness and ROI of programs/initiatives, specific to sales training activities", "Facilitate weekly meetings with sales leaders and their teams", "Meet with leaders to gain alignment and feedback on new and existing training programs", "Conduct ongoing knowledge and skills assessments for sales associates"], "Benefits": ["At Walmart, we offer competitive pay as well as performance-based incentive awards and other great benefits for a happier mind, body, and wallet", "Health benefits include medical, vision and dental coverage", "Financial benefits include 401(k), stock purchase and company-paid life insurance", "Paid time off benefits include PTO (including sick leave), parental leave, family care leave, bereavement, jury duty, and voting", "Other benefits include short-term and long-term disability, company discounts, Military Leave Pay, adoption and surrogacy expense reimbursement, and more", "You will also receive PTO and/or PPTO that can be used for vacation, sick leave, holidays, or other purposes", "The amount you receive depends on your job classification and length of employment", "It will meet or exceed the requirements of paid sick leave laws, where applicable", "Tuition, books, and fees are completely paid for by Walmart", "The annual salary range for this position is $108,000.00-$216,000.00", "Additional compensation includes annual or quarterly performance incentives", "Additional compensation for certain positions may also include:", "Regional Pay Zone (RPZ) (based on location)", "Stock equity incentives"]}, "job_job_title": "Senior manager", "job_posting_language": "en", "job_onet_soc": "11313100", "job_onet_job_zone": "4", "job_occupational_categories": ["Brand Ambassador (Retail)"], "job_naics_code": "452990", "job_naics_name": "All Other General Merchandise Stores"}