{"job_id": "wC81v5U-n24gXrTqAAAAAA==", "employer_name": "Recruiting From Scratch", "employer_logo": "https://encrypted-tbn0.gstatic.com/images?q=tbn:ANd9GcQueN_JFX34OaXHWcb7hXnkw3MSJXyv6Mz7HycR&s=0", "employer_website": null, "employer_company_type": null, "job_publisher": "SimplyHired", "job_employment_type": "FULLTIME", "job_title": "Generative AI Engineer, AI Seed Stage Startup", "job_apply_link": "https://www.simplyhired.com/job/KELKtLTq5Q-apkB_eXeIXBHXGJ49scSSm5RSDOQ2VZhvBLmfZzUC4A", "job_apply_is_direct": false, "job_apply_quality_score": 0.5223, "apply_options": [{"publisher": "SimplyHired", "apply_link": "https://www.simplyhired.com/job/KELKtLTq5Q-apkB_eXeIXBHXGJ49scSSm5RSDOQ2VZhvBLmfZzUC4A", "is_direct": false}, {"publisher": "Jobright AI", "apply_link": "https://jobright.ai/jobs/info/65eafc30764a8ca1489f6e1b", "is_direct": false}], "job_description": "Who is Recruiting from Scratch :\n\nRecruiting from Scratch is a premier talent firm that focuses on placing the best product managers, software, and hardware talent at innovative companies. Our team is 100% remote and we work with teams across the United States to help them hire. We work with companies funded by the best investors including Sequoia Capital, Lightspeed Ventures, Tiger Global Management, A16Z, Accel, DFJ, and more.\n\nAbout Our Client:\n\nThey automate the end-to-end appointment-setting process for B2B companies using AI for 1/10 of the cost of using a human.\n\nThey've built an AI SDR that can book meetings for sales teams for 10x less than hiring an agency or human SDR. The product is built to take a cold random stranger on LinkedIn or email and turn them into booked meetings.\n\nThat means - upload a list of prospects and watch the product:\n\u2022 Conduct research on each individual\n\u2022 Create hyper-relevant sequences\n\u2022 Answer prospect\u2019s questions, comments, and concerns\n\u2022 Offer times\n\u2022 Book meetings\n\nWhat You'll Do:\n\nGenAI Generalist Engineer:\n\nWork will involve building semantic search engines, LLM fine-tuning, Vector DB applications, and cutting-edge data science work. We are looking for a strong builder with a track record of building generative AI projects and a desire to learn and iterate quickly.\n\nDescription:\n\nGenAI engineer with deep LLM experience to join an early stage startup team and help build Generative AI powered solutions. Build and maintain infra to process thousands of generations per month from LLM calls. Design and implement novel AI prompts. Work closely with the CEO, CTO/Head of ML, and other Founding Engineers.\n\nHave complete ownership over the work you do \u2014 as a founding team member, you\u2019ll have the opportunity to truly own large areas of product and engineering and have direct relationships with customers.\n\nWork directly with the CEO, CTO, and other founding members and help build out our team.\n\nIndustry experience + strong fundamentals + product mindset needed, owns modules, growth mindset, enjoys building, purpose-driven organization.\n\nKey Responsibilities:\n\u2022 Design and implement novel prompts and techniques to coax the best outputs from different LLMs. We are building a new territory of enterprise AI that previously did not exist. It\u2019s up to us to discover and implement the best techniques that work for our users.\n\u2022 Innovate with the latest models and advancements in Generative AI to determine the best model for a given use case.\n\u2022 Have complete ownership over the work you do \u2014 as a founding team member, you\u2019ll have the opportunity to truly own large areas of product and engineering and have direct relationship with customers.\n\u2022 Validate prompts, try to break them, figure out ways in which a model won\u2019t work. Manage datasets and prompts.\n\u2022 Apply advanced prompt engineering techniques, insert guard rails, scale the application with Google/AWS cloud.\n\u2022 Understand business problems, making sense of the data landscape & footprint, performing a combination of Gen AI, Advanced NLP, Exploratory analysis\n\u2022 Develop generative solutions, optimize models, familiarity with frameworks like Langchain, Llama index, LLM open-source models including LLAMA and related frameworks, and proficiency in Python.\n\u2022 Assist with developing the context-aware chatbots\n\u2022 Build, and maintain, durable, scalable infrastructure capable of processing calls to LLMs and the reliability of the output.\n\nOur tech stack:\n\u2022 Python - Language\n\u2022 Tensorflow, Pytorch - ML Framework\n\u2022 Langchain/Llama Index, OpenAI Eval - Generative AI Framework\n\u2022 Sentence Transformers/ Universal Sentence Encoders/OpenAI Embeddings - Vector Embeddings\n\u2022 Pinecone/Doc-Array/Chroma - Vector Storage/Database\n\u2022 AWS/GCP/Render - ML Apps/API Deployment\n\nWhat We're Looking For:\n\u2022 Experience in AI and research with a detailed understanding of AI and its\n\u2022 application in industry.\n\u2022 Strong record of accomplishment in building highly scalable AI capabilities.\n\u2022 Advanced communication skills across a variety of audiences; ability to make the complex simple, and to win mindshare through storytelling and dialogue.\n\u2022 Prior experience with research and the industrialisation of AI into products.\n\u2022 Strong business and financial acumen; ability to conceptualize, prioritize, and manage environments; ability to deliver high-volume applications with an eye for user experience.\n\u2022 Proficiency in analyzing large datasets and proposing action plans.\n\u2022 Ability to identify patterns and trends in data.\n\u2022 Strong analytical mindset with a passion for data-driven decisions.\n\u2022 Ability to present data creatively and tell a compelling story through insights.\n\u2022 Aptitude for data and basic SQL database skills.\n\nWhat Gives You An Edge:\n\n1. Data Collection\n\u2022 Web Tracking: Using cookies and web beacons to track user behavior across websites. This can reveal which products or services a user is researching.\n\u2022 IP Identification: Identifying and tracking the IP addresses of visitors to understand which companies are showing interest in specific topics.\n\u2022 Content Syndication Networks: Gathering data from networks where companies distribute content to capture leads and gauge interest levels in specific topics.\n\nTechnologies Used:\n\u2022 JavaScript trackers on web pages\n\u2022 Web analytics platforms\n\u2022 Content management systems (CMS) with tracking capabilities\n\n2. Data Aggregation and Enrichment\n\u2022 Data Integration: Combining data from various sources to build a complete profile.\n\u2022 Data Enrichment: Adding information from external databases to enhance the understanding of each lead, such as industry data, company size, and other relevant attributes.\n\nTechnologies Used:\n\u2022 Data lakes and warehouses for storing and managing data.\n\u2022 ETL (Extract, Transform, Load) tools for data integration.\n\u2022 Third-party data providers for enrichment.\n\n3. Intent Signal Analysis\n\nML Algorithms: To process and analyze the data, looking for patterns that signify interest or intent to purchase. These include:\n\u2022 Logistic Regression, Decision Trees and Random Forests, Support Vector Machines (SVM), KNN, Clustering Algorithms (e.g., K-Means, Hierarchical Clustering)\n\u2022 Natural Language Processing (NLP): To understand the context and sentiment behind content engagement and social media interactions.\n\nTechnologies Used:\n\u2022 Machine learning frameworks like TensorFlow or PyTorch.\n\u2022 NLP libraries such as NLTK or SpaCy for processing text data.\n\n4. Predictive Modeling\n\u2022 Predictive Analytics: Utilizing statistical models and machine learning to predict future behaviors based on past actions and intent signals.\n\nTechnologies Used:\n\u2022 Predictive modeling tools and platforms.\n\u2022 Custom-built algorithms developed by data scientists.\n\n5. Integration and Activation\n\u2022 APIs and Integrations: To feed the intent data and insights directly into CRM and marketing automation platforms for personalized marketing campaigns and sales outreach.\n\u2022 Real-time Data Processing: To ensure that sales and marketing teams can act on the insights in a timely manner.\n\nLocation: West Village, NY\n\nCompensation : $100k to $140k Base Salary + $50k Equity Package w/ 1 year cliff + 4 year vest Unlimited PTO + Benefits (Gym Stipend, Dinner at Office).", "job_is_remote": false, "job_posted_at_timestamp": 1709791200, "job_posted_at_datetime_utc": "2024-03-07T06:00:00.000Z", "job_city": "San Diego", "job_state": "CA", "job_country": "US", "job_latitude": 32.715736, "job_longitude": -117.16109, "job_benefits": ["paid_time_off", "health_insurance"], "job_google_link": "https://www.google.com/search?gl=us&hl=en&rciv=jb&q=ai+engineer&start=70&ibp=htl;jobs#fpstate=tldetail&htivrt=jobs&htiq=ai+engineer&htidocid=wC81v5U-n24gXrTqAAAAAA%3D%3D", "job_offer_expiration_datetime_utc": null, "job_offer_expiration_timestamp": null, "job_required_experience": {"no_experience_required": false, "required_experience_in_months": null, "experience_mentioned": true, "experience_preferred": false}, "job_required_skills": null, "job_required_education": {"postgraduate_degree": false, "professional_certification": false, "high_school": false, "associates_degree": false, "bachelors_degree": false, "degree_mentioned": false, "degree_preferred": false, "professional_certification_mentioned": false}, "job_experience_in_place_of_education": false, "job_min_salary": null, "job_max_salary": null, "job_salary_currency": null, "job_salary_period": null, "job_highlights": {"Qualifications": ["Industry experience + strong fundamentals + product mindset needed, owns modules, growth mindset, enjoys building, purpose-driven organization", "Experience in AI and research with a detailed understanding of AI and its", "application in industry", "Strong record of accomplishment in building highly scalable AI capabilities", "Advanced communication skills across a variety of audiences; ability to make the complex simple, and to win mindshare through storytelling and dialogue", "Prior experience with research and the industrialisation of AI into products", "Strong business and financial acumen; ability to conceptualize, prioritize, and manage environments; ability to deliver high-volume applications with an eye for user experience", "Proficiency in analyzing large datasets and proposing action plans", "Ability to identify patterns and trends in data", "Strong analytical mindset with a passion for data-driven decisions", "Ability to present data creatively and tell a compelling story through insights", "Aptitude for data and basic SQL database skills", "JavaScript trackers on web pages", "Web analytics platforms", "Content management systems (CMS) with tracking capabilities", "Data Aggregation and Enrichment", "Data lakes and warehouses for storing and managing data", "Machine learning frameworks like TensorFlow or PyTorch", "NLP libraries such as NLTK or SpaCy for processing text data", "Predictive modeling tools and platforms", "Custom-built algorithms developed by data scientists", "Integration and Activation"], "Responsibilities": ["That means - upload a list of prospects and watch the product:", "Conduct research on each individual", "Create hyper-relevant sequences", "Build and maintain infra to process thousands of generations per month from LLM calls", "Work closely with the CEO, CTO/Head of ML, and other Founding Engineers", "Have complete ownership over the work you do \u2014 as a founding team member, you\u2019ll have the opportunity to truly own large areas of product and engineering and have direct relationships with customers", "Work directly with the CEO, CTO, and other founding members and help build out our team", "Design and implement novel prompts and techniques to coax the best outputs from different LLMs", "Innovate with the latest models and advancements in Generative AI to determine the best model for a given use case", "Validate prompts, try to break them, figure out ways in which a model won\u2019t work", "Manage datasets and prompts", "Apply advanced prompt engineering techniques, insert guard rails, scale the application with Google/AWS cloud", "Understand business problems, making sense of the data landscape & footprint, performing a combination of Gen AI, Advanced NLP, Exploratory analysis", "Develop generative solutions, optimize models, familiarity with frameworks like Langchain, Llama index, LLM open-source models including LLAMA and related frameworks, and proficiency in Python", "Assist with developing the context-aware chatbots", "Build, and maintain, durable, scalable infrastructure capable of processing calls to LLMs and the reliability of the output", "Web Tracking: Using cookies and web beacons to track user behavior across websites", "This can reveal which products or services a user is researching", "IP Identification: Identifying and tracking the IP addresses of visitors to understand which companies are showing interest in specific topics", "Content Syndication Networks: Gathering data from networks where companies distribute content to capture leads and gauge interest levels in specific topics", "Data Enrichment: Adding information from external databases to enhance the understanding of each lead, such as industry data, company size, and other relevant attributes", "ML Algorithms: To process and analyze the data, looking for patterns that signify interest or intent to purchase", "Real-time Data Processing: To ensure that sales and marketing teams can act on the insights in a timely manner"], "Benefits": ["Pinecone/Doc-Array/Chroma - Vector Storage/Database", "AWS/GCP/Render - ML Apps/API Deployment", "Compensation : $100k to $140k Base Salary + $50k Equity Package w/ 1 year cliff + 4 year vest Unlimited PTO + Benefits (Gym Stipend, Dinner at Office)"]}, "job_job_title": "Engineer", "job_posting_language": "en", "job_onet_soc": "15111100", "job_onet_job_zone": "5"}