{"job_id": "9g_8g8cO-jue2xsCAAAAAA==", "employer_name": "Astellas Pharma US", "employer_logo": "https://encrypted-tbn0.gstatic.com/images?q=tbn:ANd9GcR_83Bx3xk1TiiOStgH19BNuL42GG01cZgk9gcL&s=0", "employer_website": "http://www.astellas.com", "employer_company_type": "Manufacturing", "job_publisher": "LinkedIn", "job_employment_type": "FULLTIME", "job_title": "Data Scientist, Omnichannel", "job_apply_link": "https://www.linkedin.com/jobs/view/data-scientist-omnichannel-at-astellas-pharma-us-3859408313", "job_apply_is_direct": false, "job_apply_quality_score": 0.7351, "apply_options": [{"publisher": "LinkedIn", "apply_link": "https://www.linkedin.com/jobs/view/data-scientist-omnichannel-at-astellas-pharma-us-3859408313", "is_direct": false}, {"publisher": "ZipRecruiter", "apply_link": "https://www.ziprecruiter.com/c/Astellas/Job/Associate-Director,-Oncology-Omnichannel-Analytics/-in-Northbrook,IL?jid=3b50795a5d199f4b", "is_direct": false}, {"publisher": "Salary.com", "apply_link": "https://www.salary.com/job/astellas-pharma/associate-director-oncology-omnichannel-analytics/j202312232331488659395", "is_direct": false}], "job_description": "This position is based in Northbrook, Illinois. Hybrid work from certain states may be permitted in accordance with Astellas\u2019 Responsible Flexibility Guidelines. Candidates interested in hybrid work are encouraged to apply.\n\nPurpose:\n\nThe Data Scientist, Omnichannel plays a critical role in providing valuable strategic and tactical business insight and recommendations to Marketing, Agencies and Omnichannel Strategy & Operations (OSO) teams to support achievement of brand promotional and campaign objectives. This role will be responsible for leveraging data to drive insights, optimize customer experiences, and contribute to the overall success of our omnichannel initiatives. This position will be leading our Next Best Action initiative, which will including analyzing and measuring the promotional effectiveness of omnichannel activities and building recommendation systems using predictive models.\n\nThis position will work collaboratively with partners such as global/regional commercial brand teams/marketing, global/regional Commercial Insights teams, Omnichannel Strategy & Operations, Data Governance and Information Systems team and will contribute to data/metrics harmonization and insights sharing.\n\nEssential Job Responsibilities:\n\u2022 Collaborate with key brand stakeholders and cross-functional teams to understand business objectives and measurability of campaigns and develop data-driven strategies to enhance the omnichannel experience.\n\u2022 Provide consulting to the key stakeholders in the campaign design/requirements gathering phase to ensure objectives are clearly defined and can be measured, content assets are properly tagged, and the campaign data is properly sourced to ensure integrity of the measurement.\n\u2022 Provide actionable insights through on-going reporting of all omnichannel engagements and digital tactics, including personal and non-personal promotions.\n\u2022 Develop and implement machine learning algorithms to drive personalized recommendations and targeted marketing campaigns across channels based on individual preferences and behaviors.\n\u2022 Conduct in-depth analysis of various data sources (promotional and non-promotional data) and develop predictive models to forecast HCP preferences, behavior, and overall omnichannel engagement.\n\u2022 Work with various cross-functional teams (Marketing, Media Agencies, IS and Data Engineering) to integrate and consolidate all promotional data from various sources, ensuring a unified view of customer interactions and transactions.\n\u2022 Troubleshoot data quality issues and implement solutions to maintain accurate and reliable data.\n\u2022 Develop and implement key performance indicators (KPIs) to measure the effectiveness of omnichannel initiatives.\n\u2022 Develop and implement analytics plans to support brand and portfolio level ROI optimization.\n\u2022 Be a thought leader within the organization for omnichannel analytics by proposing and implementing innovative approaches to enhance the effectiveness of omnichannel data analytics.\n\u2022 Stay abreast of industry trends, emerging technologies, and best practices in data science and omnichannel strategies.\n\u2022 Manage third party providers on an as-needed basis and ensure deliverables fully meet contractual obligations and are of highest caliber.\n\u2022 Embed an Ethics and Compliance culture and Integrity in Action by proactively addressing non-compliance.\n\nQuantitative Dimensions:\n\u2022 Quality of strategic and operational support for assigned products including quality of the collaboration with key partners and copromote partners were applicable.\n\u2022 Accuracy, timeliness, effectiveness, and ease of use of production and ad hoc performance reporting, dashboards, and advanced analytics.\n\u2022 Ability to meet/exceed established key milestones related to assigned major projects.\n\u2022 Quality/timeliness of insight generation and development of actionable recommendations based on feedback from key customers and cross-functional colleagues.\n\u2022 Management of projects within approved operating budget.\n\nOrganizational Context:\n\u2022 Reports to the Director, Brand Analytics.\n\u2022 This position requires extensive collaboration across the global Commercial Insights GCA team. This role will also have broad global exposure as they partner with cross-functional colleagues (Marketing, Sales, Finance, Data Strategy/Data Engineering, Sales Operations (where applicable) and IS) within global functions and priority Commercial Divisions/markets. Additional collaboration is required with co-promotion partners (if applicable).\n\nQualifications\n\nRequired:\n\u2022 Master\u2019s or Ph.D. in Data Science, Statistics, Computer Science, or a related field.\n\u2022 Minimum 8 years of analytics/data science experience with a focus on omnichannel analytics and demonstrated success in managing projects of increasing size and complexity.\n\u2022 Possess strong interpersonal skills with the ability to effectively interact with all levels of employees including senior management.\n\u2022 Extensive proficiency with software in a Windows environment required including Microsoft Excel and PowerPoint.\n\u2022 Strong proficiency in coding language (e.g. SQL, R and/or Python)\n\u2022 Expertise in machine learning techniques, statistical analysis, and data visualization, including classification models, promotion response modeling, predictive modeling, etc.\n\u2022 Working knowledge of omnichannel concepts and data sources, e.g., impressions/click data, web data, etc..\n\u2022 Experience working with Google Analytics or Adobe Analytics\n\u2022 Excellent skills in the following areas: organization, written and verbal communication, accuracy and personal initiative.\n\u2022 Excellent organizational, planning and project management skills with a strong attention to detail and ability to effectively manage cross-functional projects.\n\u2022 Ability to work independently in a dynamic fast-paced environment, with minimal supervision.\n\u2022 Demonstrated ability in taking initiative to proactively evaluate existing sales strategies and recommend changes, when appropriate.\n\u2022 Keen analytical mind with superior problem solving and technical skills, reflecting in-depth knowledge of various secondary databases and their limitations.\n\nPreferred:\n\u2022 Pharmaceutical industry experience.\n\u2022 General understanding of other Commercial Insights functions (i.e., primary/secondary market research, forecasting, competitive intelligence)\n\u2022 Working knowledge of one or more data visualization tools such as Excel, QlikView and QlikSense\n\u2022 People leadership experience\n\u2022 Experience working with global partners\n\u2022 Knowledge of the global healthcare landscape including different access models\n\u2022 Knowledge of other healthcare data sources such as patient-level data\n\nBenefits:\n\u2022 Medical, Dental and Vision Insurance\n\u2022 Generous Paid Time Off options, including Vacation and Sick time, plus national holidays including year-end shut down\n\u2022 401(k) match and annual company contribution\n\u2022 Company paid life insurance\n\u2022 Annual Corporate Bonus and Quarterly Sales Incentive for eligible positions\n\u2022 Long Term Incentive Plan for eligible positions\n\u2022 Referral bonus program\n\nSalary Range*\n\n$140,000-190,000k/yr (*NOTE: Final salary could be more or less, based on experience)\n\nAstellas is committed to equality of opportunity in all aspects of employment.\n\nEOE including Disability/Protected Veterans", "job_is_remote": true, "job_posted_at_timestamp": 1710538567, "job_posted_at_datetime_utc": "2024-03-15T21:36:07.000Z", "job_city": null, "job_state": null, "job_country": "US", "job_latitude": 37.09024, "job_longitude": -95.71289, "job_benefits": ["paid_time_off", "dental_coverage", "health_insurance", "retirement_savings"], "job_google_link": "https://www.google.com/search?gl=us&hl=en&rciv=jb&q=data+science+leader&start=70&ibp=htl;jobs#fpstate=tldetail&htivrt=jobs&htiq=data+science+leader&htidocid=9g_8g8cO-jue2xsCAAAAAA%3D%3D", "job_offer_expiration_datetime_utc": "2024-04-14T21:36:07.000Z", "job_offer_expiration_timestamp": 1713130567, "job_required_experience": {"no_experience_required": false, "required_experience_in_months": 96, "experience_mentioned": true, "experience_preferred": false}, "job_required_skills": null, "job_required_education": {"postgraduate_degree": false, "professional_certification": false, "high_school": false, "associates_degree": false, "bachelors_degree": true, "degree_mentioned": true, "degree_preferred": false, "professional_certification_mentioned": false}, "job_experience_in_place_of_education": false, "job_min_salary": null, "job_max_salary": null, "job_salary_currency": null, "job_salary_period": null, "job_highlights": {"Qualifications": ["Master\u2019s or Ph.D. in Data Science, Statistics, Computer Science, or a related field", "Minimum 8 years of analytics/data science experience with a focus on omnichannel analytics and demonstrated success in managing projects of increasing size and complexity", "Possess strong interpersonal skills with the ability to effectively interact with all levels of employees including senior management", "Extensive proficiency with software in a Windows environment required including Microsoft Excel and PowerPoint", "Strong proficiency in coding language (e.g. SQL, R and/or Python)", "Expertise in machine learning techniques, statistical analysis, and data visualization, including classification models, promotion response modeling, predictive modeling, etc", "Working knowledge of omnichannel concepts and data sources, e.g., impressions/click data, web data, etc.", "Experience working with Google Analytics or Adobe Analytics", "Excellent skills in the following areas: organization, written and verbal communication, accuracy and personal initiative", "Excellent organizational, planning and project management skills with a strong attention to detail and ability to effectively manage cross-functional projects", "Ability to work independently in a dynamic fast-paced environment, with minimal supervision", "Demonstrated ability in taking initiative to proactively evaluate existing sales strategies and recommend changes, when appropriate", "Keen analytical mind with superior problem solving and technical skills, reflecting in-depth knowledge of various secondary databases and their limitations"], "Responsibilities": ["The Data Scientist, Omnichannel plays a critical role in providing valuable strategic and tactical business insight and recommendations to Marketing, Agencies and Omnichannel Strategy & Operations (OSO) teams to support achievement of brand promotional and campaign objectives", "This role will be responsible for leveraging data to drive insights, optimize customer experiences, and contribute to the overall success of our omnichannel initiatives", "This position will be leading our Next Best Action initiative, which will including analyzing and measuring the promotional effectiveness of omnichannel activities and building recommendation systems using predictive models", "This position will work collaboratively with partners such as global/regional commercial brand teams/marketing, global/regional Commercial Insights teams, Omnichannel Strategy & Operations, Data Governance and Information Systems team and will contribute to data/metrics harmonization and insights sharing", "Collaborate with key brand stakeholders and cross-functional teams to understand business objectives and measurability of campaigns and develop data-driven strategies to enhance the omnichannel experience", "Provide consulting to the key stakeholders in the campaign design/requirements gathering phase to ensure objectives are clearly defined and can be measured, content assets are properly tagged, and the campaign data is properly sourced to ensure integrity of the measurement", "Provide actionable insights through on-going reporting of all omnichannel engagements and digital tactics, including personal and non-personal promotions", "Develop and implement machine learning algorithms to drive personalized recommendations and targeted marketing campaigns across channels based on individual preferences and behaviors", "Conduct in-depth analysis of various data sources (promotional and non-promotional data) and develop predictive models to forecast HCP preferences, behavior, and overall omnichannel engagement", "Work with various cross-functional teams (Marketing, Media Agencies, IS and Data Engineering) to integrate and consolidate all promotional data from various sources, ensuring a unified view of customer interactions and transactions", "Troubleshoot data quality issues and implement solutions to maintain accurate and reliable data", "Develop and implement key performance indicators (KPIs) to measure the effectiveness of omnichannel initiatives", "Develop and implement analytics plans to support brand and portfolio level ROI optimization", "Be a thought leader within the organization for omnichannel analytics by proposing and implementing innovative approaches to enhance the effectiveness of omnichannel data analytics", "Stay abreast of industry trends, emerging technologies, and best practices in data science and omnichannel strategies", "Manage third party providers on an as-needed basis and ensure deliverables fully meet contractual obligations and are of highest caliber", "Embed an Ethics and Compliance culture and Integrity in Action by proactively addressing non-compliance", "Quality of strategic and operational support for assigned products including quality of the collaboration with key partners and copromote partners were applicable", "Accuracy, timeliness, effectiveness, and ease of use of production and ad hoc performance reporting, dashboards, and advanced analytics", "Ability to meet/exceed established key milestones related to assigned major projects", "Quality/timeliness of insight generation and development of actionable recommendations based on feedback from key customers and cross-functional colleagues", "Management of projects within approved operating budget", "Reports to the Director, Brand Analytics", "This position requires extensive collaboration across the global Commercial Insights GCA team", "This role will also have broad global exposure as they partner with cross-functional colleagues (Marketing, Sales, Finance, Data Strategy/Data Engineering, Sales Operations (where applicable) and IS) within global functions and priority Commercial Divisions/markets", "Additional collaboration is required with co-promotion partners (if applicable)"], "Benefits": ["Medical, Dental and Vision Insurance", "Generous Paid Time Off options, including Vacation and Sick time, plus national holidays including year-end shut down", "401(k) match and annual company contribution", "Company paid life insurance", "Annual Corporate Bonus and Quarterly Sales Incentive for eligible positions", "Long Term Incentive Plan for eligible positions", "Referral bonus program", "$140,000-190,000k/yr (*NOTE: Final salary could be more or less, based on experience)"]}, "job_job_title": "Data scientist", "job_posting_language": "en", "job_onet_soc": "15111100", "job_onet_job_zone": "5", "job_naics_code": "3254", "job_naics_name": "Pharmaceutical and Medicine Manufacturing"}