{"job_id": "8yBb6YUG1dxLJg6LAAAAAA==", "employer_name": "Green Conception, Inc.", "employer_logo": null, "employer_website": null, "employer_company_type": null, "job_publisher": "Glassdoor", "job_employment_type": "FULLTIME", "job_title": "Sales Manager", "job_apply_link": "https://www.glassdoor.com/job-listing/sales-manager-green-conception-inc-JV_KO0,13_KE14,34.htm?jl=1009178492485", "job_apply_is_direct": true, "job_apply_quality_score": 0.5642, "apply_options": [{"publisher": "Glassdoor", "apply_link": "https://www.glassdoor.com/job-listing/sales-manager-green-conception-inc-JV_KO0,13_KE14,34.htm?jl=1009178492485", "is_direct": true}], "job_description": "Job Overview:\n\nWe seek a highly motivated and experienced Sales Manager to join our team. In this role, you will directly sell to consumers, develop and implement sales strategies, analyze market trends, and build strong client relationships. This position offers a path to a Sales Director role and is ideal for those with a passion for sales, excellent leadership skills, and a proven track record in achieving sales goals.\n\nDuties:\n\u2022 Manage and close booked sales appointments to achieve targets (leads provided).\n\u2022 Develop and implement effective sales strategies to drive business growth.\n\u2022 Analyze market trends and identify new opportunities.\n\u2022 Build and maintain strong client relationships for customer satisfaction.\n\u2022 Monitor sales performance and provide regular reports to the Sales Director.\n\u2022 Collaborate with cross-functional teams to successfully execute sales initiatives.\n\u2022 Stay informed about industry developments and competitor activities.\n\nSkills:\n\u2022 Minimum of 5 years of sales experience, preferably in the solar & roofing industry.\n\u2022 Strong knowledge of Zoho CRM or other CRM software.\n\u2022 Ability to analyze market trends and identify new business opportunities.\n\u2022 Excellent communication and negotiation skills.\n\u2022 Strong leadership abilities to motivate and inspire.\n\u2022 Demonstrated success in achieving sales targets and driving business growth.\n\u2022 Experience in business development and managing client relationships.\n\u2022 Effective time management, prioritization, and meeting deadlines.\n\nDay-to-Day Operations & Requirements:\n\u2022 Daily booked appointments to contact the customer.\n\u2022 Green Conception provides an average of 3-6 appointments per day. (B2C)\n\u2022 Contact and build our \"Dealer Referral Program.\" (B2B2C) (Self Lead Gen)\n\u2022 Remote job with occasional customer visits as needed.\n\u2022 Weekly and daily Google Meet meetings with the team.\n\u2022 Quarterly face-to-face company meetings.\n\u2022 Laptop and gear provided.\n\u2022 You'll need good internet and a quiet home office setup.\n\nIf you are a results-driven individual with a passion for sales and leadership, we invite you to apply for this exciting opportunity. Join our team and contribute to our ongoing success as a Sales Manager. You will not be managing the sales team. This is a direct-to-consumer sales position.\n\nJob Type: Full-time\n\nPay: $55,000.00 - $255,000.00 per year\n\nBenefits:\n\u2022 Flexible schedule\n\u2022 Paid time off\n\u2022 Professional development assistance\n\u2022 Referral program\n\nSchedule:\n\u2022 Monday to Friday\n\u2022 Weekends as needed\n\nSupplemental pay types:\n\u2022 Bonus opportunities\n\u2022 Commission pay\n\nWork Location: Remote", "job_is_remote": true, "job_posted_at_timestamp": 1709942400, "job_posted_at_datetime_utc": "2024-03-09T00:00:00.000Z", "job_city": null, "job_state": null, "job_country": "US", "job_latitude": 37.09024, "job_longitude": -95.71289, "job_benefits": ["paid_time_off"], "job_google_link": "https://www.google.com/search?gl=us&hl=en&rciv=jb&q=sales+director&start=60&ibp=htl;jobs#fpstate=tldetail&htivrt=jobs&htiq=sales+director&htidocid=8yBb6YUG1dxLJg6LAAAAAA%3D%3D", "job_offer_expiration_datetime_utc": "2024-07-08T00:00:00.000Z", "job_offer_expiration_timestamp": 1720396800, "job_required_experience": {"no_experience_required": false, "required_experience_in_months": 60, "experience_mentioned": true, "experience_preferred": false}, "job_required_skills": null, "job_required_education": {"postgraduate_degree": false, "professional_certification": false, "high_school": false, "associates_degree": false, "bachelors_degree": false, "degree_mentioned": false, "degree_preferred": false, "professional_certification_mentioned": false}, "job_experience_in_place_of_education": false, "job_min_salary": 55000, "job_max_salary": 255000, "job_salary_currency": "USD", "job_salary_period": "YEAR", "job_highlights": {"Qualifications": ["Minimum of 5 years of sales experience, preferably in the solar & roofing industry", "Strong knowledge of Zoho CRM or other CRM software", "Ability to analyze market trends and identify new business opportunities", "Excellent communication and negotiation skills", "Strong leadership abilities to motivate and inspire", "Demonstrated success in achieving sales targets and driving business growth", "Experience in business development and managing client relationships", "Effective time management, prioritization, and meeting deadlines", "You'll need good internet and a quiet home office setup"], "Responsibilities": ["In this role, you will directly sell to consumers, develop and implement sales strategies, analyze market trends, and build strong client relationships", "This position offers a path to a Sales Director role and is ideal for those with a passion for sales, excellent leadership skills, and a proven track record in achieving sales goals", "Manage and close booked sales appointments to achieve targets (leads provided)", "Develop and implement effective sales strategies to drive business growth", "Analyze market trends and identify new opportunities", "Build and maintain strong client relationships for customer satisfaction", "Monitor sales performance and provide regular reports to the Sales Director", "Collaborate with cross-functional teams to successfully execute sales initiatives", "Stay informed about industry developments and competitor activities", "Daily booked appointments to contact the customer", "Green Conception provides an average of 3-6 appointments per day", "Remote job with occasional customer visits as needed", "You will not be managing the sales team"], "Benefits": ["Weekly and daily Google Meet meetings with the team", "Quarterly face-to-face company meetings", "Laptop and gear provided", "Pay: $55,000.00 - $255,000.00 per year", "Flexible schedule", "Paid time off", "Professional development assistance", "Referral program", "Monday to Friday", "Bonus opportunities", "Commission pay"]}, "job_job_title": "Sales manager", "job_posting_language": "en", "job_onet_soc": "11202200", "job_onet_job_zone": "4"}