{"job_id": "-T7JCg4DYgxtlTNwAAAAAA==", "employer_name": "Ryzen Solutions", "employer_logo": "https://encrypted-tbn0.gstatic.com/images?q=tbn:ANd9GcRSe13ldtq96udbdpNQlgn8hYbugVOWTR4PHXA5&s=0", "employer_website": "http://ryzen.com", "employer_company_type": null, "job_publisher": "Glassdoor", "job_employment_type": "FULLTIME", "job_title": "Business Development Manager", "job_apply_link": "https://www.glassdoor.com/job-listing/business-development-manager-ryzen-solutions-JV_IC1147400_KO0,28_KE29,44.htm?jl=1009038349609", "job_apply_is_direct": true, "job_apply_quality_score": 0.6628, "apply_options": [{"publisher": "Glassdoor", "apply_link": "https://www.glassdoor.com/job-listing/business-development-manager-ryzen-solutions-JV_IC1147400_KO0,28_KE29,44.htm?jl=1009038349609", "is_direct": true}, {"publisher": "Indeed", "apply_link": "https://www.indeed.com/viewjob?jk=0c3d6b6763185021", "is_direct": true}], "job_description": "Summary: The Business Development Manager will be responsible for developing new sales leads within their territory and proactively grow business with existing clients. Position requires regular travel away from branch office.\n\nEssential Duties and Responsibilities (including but not limited to):\n\u2022 Manage Business Development activities across assigned territory\n\u2022 Partners with Account Managers (inside sales) to develop sales strategies to meet goals\n\u2022 Identifies new accounts, retain existing clients and develop sales within existing accounts ? Represents Pencom in client meetings with integrity, professionalism and with expert knowledge of company products and services\n\u2022 Manages contract negotiations, quality complaints, and introductions or referrals to other business units\n\u2022 Provides product samples and marketing materials to clients. May deliver order to client as needed.\n\u2022 Partners with client\u2019s engineering staff for new product designs or sustaining engineering issues\n\u2022 Works with internal engineering and procurement to respond to RFQs, and develop pricing strategies to meet client requests\n\u2022 Maintains excellent cold calling efforts to drive business into new accounts and territories\n\u2022 Reports account and sales activities to management\n\u2022 Provides metrics and reporting tools to Branch Managers\n\u2022 Duties, responsibilities and activities may change at any time with or without notice by management\n\nSupervisory Responsibilities\n\u2022 Proven working experience as a business development manager, sales executive or a relevant role.\n\u2022 Strong communication and negotiation skills is essential\n\u2022 Ability to manage complex projects and multi-task\n\u2022 Excellent organizational skills and be highly detailed Business Development Manager\n\u2022 Must have excellent phone and in-person sales presentation skills\n\u2022 Able to manage competing priorities to meet client needs\n\u2022 Ability to coach and mentor Account Managers towards achieving sales targets ? Proficiency with computer software including MS Office, Order Management System, etc.\n\u2022 Valid driver license is required\n\u2022 Fluency in speaking, reading and writing in English\n\nJob Type: Full-time\n\nSalary: $80,000.00 - $82,000.00 per year\n\nSchedule:\n\u2022 8 hour shift\n\u2022 Day shift\n\u2022 Monday to Friday\n\nExperience:\n\u2022 Business development: 1 year (Preferred)\n\u2022 Sales: 1 year (Preferred)\n\nAbility to Commute:\n\u2022 San Carlos, CA 94070 (Preferred)\n\nAbility to Relocate:\n\u2022 San Carlos, CA 94070: Relocate before starting work (Preferred)\n\nWillingness to travel:\n\u2022 25% (Preferred)\n\nWork Location: In person", "job_is_remote": false, "job_posted_at_timestamp": 1708300800, "job_posted_at_datetime_utc": "2024-02-19T00:00:00.000Z", "job_city": "San Carlos", "job_state": "CA", "job_country": "US", "job_latitude": 37.50716, "job_longitude": -122.26052, "job_benefits": null, "job_google_link": "https://www.google.com/search?gl=us&hl=en&rciv=jb&q=manager+of+business+development&start=40&ibp=htl;jobs#fpstate=tldetail&htivrt=jobs&htiq=manager+of+business+development&htidocid=-T7JCg4DYgxtlTNwAAAAAA%3D%3D", "job_offer_expiration_datetime_utc": "2024-07-10T00:00:00.000Z", "job_offer_expiration_timestamp": 1720569600, "job_required_experience": {"no_experience_required": false, "required_experience_in_months": null, "experience_mentioned": true, "experience_preferred": false}, "job_required_skills": null, "job_required_education": {"postgraduate_degree": false, "professional_certification": false, "high_school": false, "associates_degree": false, "bachelors_degree": false, "degree_mentioned": false, "degree_preferred": false, "professional_certification_mentioned": false}, "job_experience_in_place_of_education": false, "job_min_salary": 80000, "job_max_salary": 82000, "job_salary_currency": "USD", "job_salary_period": "YEAR", "job_highlights": {"Qualifications": ["Proven working experience as a business development manager, sales executive or a relevant role", "Strong communication and negotiation skills is essential", "Excellent organizational skills and be highly detailed Business Development Manager", "Must have excellent phone and in-person sales presentation skills", "Proficiency with computer software including MS Office, Order Management System, etc", "Valid driver license is required", "Fluency in speaking, reading and writing in English", "Willingness to travel:"], "Responsibilities": ["Summary: The Business Development Manager will be responsible for developing new sales leads within their territory and proactively grow business with existing clients", "Position requires regular travel away from branch office", "Manage Business Development activities across assigned territory", "Partners with Account Managers (inside sales) to develop sales strategies to meet goals", "Identifies new accounts, retain existing clients and develop sales within existing accounts ?", "Represents Pencom in client meetings with integrity, professionalism and with expert knowledge of company products and services", "Manages contract negotiations, quality complaints, and introductions or referrals to other business units", "Provides product samples and marketing materials to clients", "May deliver order to client as needed", "Partners with client\u2019s engineering staff for new product designs or sustaining engineering issues", "Works with internal engineering and procurement to respond to RFQs, and develop pricing strategies to meet client requests", "Maintains excellent cold calling efforts to drive business into new accounts and territories", "Reports account and sales activities to management", "Provides metrics and reporting tools to Branch Managers", "Duties, responsibilities and activities may change at any time with or without notice by management", "Able to manage competing priorities to meet client needs", "Ability to coach and mentor Account Managers towards achieving sales targets ?"], "Benefits": ["Salary: $80,000.00 - $82,000.00 per year", "8 hour shift"]}, "job_job_title": "Development manager", "job_posting_language": "en", "job_onet_soc": "11202100", "job_onet_job_zone": "4"}