{"job_id": "E5i80RlBOnd39FfcAAAAAA==", "job_title": "Principal Machine Learning Engineer\u200b/Scenario Technology", "employer_name": "Wayve Technologies Ltd", "employer_logo": null, "employer_website": "http://wayve.ai/", "job_publisher": "Learn4Good", "job_employment_type": "Full-time", "job_employment_types": ["FULLTIME"], "job_apply_link": "https://www.learn4good.com/jobs/online_remote/info_technology/3878931596/e/?utm_campaign=google_jobs_apply&utm_source=google_jobs_apply&utm_medium=organic", "job_apply_is_direct": false, "apply_options": [{"publisher": "Learn4Good", "apply_link": "https://www.learn4good.com/jobs/online_remote/info_technology/3878931596/e/?utm_campaign=google_jobs_apply&utm_source=google_jobs_apply&utm_medium=organic", "is_direct": false}], "job_description": "Position: Principal Machine Learning Engineer (Scenario Technology)\nWhere you will have an impact\n\nWe\u2019re revolutionizing the way autonomous vehicles learn and operate, and the Scenario Technology and Coverage team plays a pivotal role in that mission by building scalable, data-driven scenarios for evaluating and validating self-driving models. As a Principal ML Engineer on the Scenario Technology and Coverage team, you'll lead the design and implementation of scalable ML-based tools that enhance our scenario pipeline\u2014from data mining and scenario generation to simulation-based evaluation.\n\nYour work will be critical in ensuring that our driving models are thoroughly tested and optimized across diverse and realistic conditions.\nChallenges you will own:\n\u2022 Lead the development of robust ML models and augmentation techniques that power our scenario generation and validation systems.\n\u2022 Architect scalable systems for mining, curating, and synthesizing data to fuel scenario databases, using both real-world and synthetic data.\n\u2022 Collaborate with cross-functional teams, including Simulation and Science, to integrate state-of-the-art technologies into our scenario pipelines.\n\u2022 Drive innovation in scenario coverage, focusing on both closed-loop and open-loop evaluations.\n\u2022 Own end-to-end technical solutions: from translating product requirements into engineering tasks to delivering high-impact ML models and infrastructure improvements.\n\u2022 Identify and address infrastructure gaps, leading initiatives to enhance our foundational tools.\n\u2022 Guide the team in navigating complex technical challenges and setting the technical direction in scenario technology.\n\u2022 Mentor engineers across teams, fostering growth and innovation in scenario-driven ML engineering.\nAbout you\n\nIn order to set you up for success as a Principal ML Engineer at Wayve, we\u2019re looking for the following skills and experience.\nEssential\n\u2022 M.S. or Ph.D. in Computer Science, Machine Learning, or related fields, with 10+ years of industry experience.\n\u2022 Proven experience in building, deploying, and scaling production-level ML solutions.\n\u2022 Deep understanding of ML fundamentals with expertise in one or more areas:\nDeep Learning, Computer Vision, Traditional ML, or Large Language Models.\n\u2022 Proficiency in Python, with a strong focus on clean, well-structured, and testable code.\n\u2022 Experience leading and executing large-scale, cross-functional projects.\n\u2022 7+ years of experience in ML engineering and 4+ years in production deployments.\n\u2022 Hands-on experience with data pipelines, SQL, and managing large-scale databases.\nDesirable\n\u2022 3+ years of experience in simulation, perception, or autonomous driving technologies.\n\u2022 Familiarity with training and evaluating autonomous vehicle models.\n\u2022 Industry experience in autonomous vehicles, robotics, transportation, or computer vision.\nWhat we offer you\n\u2022 The chance to be part of a truly mission-driven organization and an opportunity to shape the future of autonomous driving. Unlike our competitors, Wayve is still relatively small and nimble, giving you the chance to make a huge impact.\n\u2022 Competitive compensation.\n\u2022 Fully employer-covered medical, dental, and vision insurance!\n\u2022 Further benefits such as catered lunch, yummy snacks, and a variety of drinks, life insurance, employer contributed retirement account, therapy, yoga, office-wide socials, and much more.\n\u2022 A dynamic and fast-paced work environment in which you will grow every day - learning on the job, from the brightest minds in our space, and with support for more formal learning opportunities too.\n\u2022 A culture that is ego-free, respectful, and welcoming (of you and your dog) - we even eat lunch together every day.\n\u2022 This is a full-time role based in our office in California. At Wayve we want the best of all worlds so we operate a hybrid working policy that combines time together in our offices and workshops to fuel innovation, culture, relationships and learning, and time spent working from home. We also operate core working hours so you can be where you need to be for family and loved ones too.\n\nTeams determine the routines that work best for them.\n\nWe understand that everyone has a unique set of skills and experiences and that not everyone will meet all of the requirements listed above. If you\u2019re passionate\u2026", "job_is_remote": true, "job_posted_at": null, "job_posted_at_timestamp": null, "job_posted_at_datetime_utc": null, "job_location": "Sunnyvale, CA", "job_city": "Sunnyvale", "job_state": "California", "job_country": "US", "job_latitude": 37.368829999999996, "job_longitude": -122.0363496, "job_benefits": ["health_insurance", "dental_coverage"], "job_google_link": "https://www.google.com/search?q=jobs&gl=us&hl=en&udm=8#vhid=vt%3D20/docid%3DE5i80RlBOnd39FfcAAAAAA%3D%3D&vssid=jobs-detail-viewer", "job_min_salary": 200000, "job_max_salary": 250000, "job_salary_period": "YEAR", "job_highlights": {"Qualifications": ["In order to set you up for success as a Principal ML Engineer at Wayve, we\u2019re looking for the following skills and experience", "M.S. or Ph.D. in Computer Science, Machine Learning, or related fields, with 10+ years of industry experience", "Proven experience in building, deploying, and scaling production-level ML solutions", "Deep understanding of ML fundamentals with expertise in one or more areas:", "Deep Learning, Computer Vision, Traditional ML, or Large Language Models", "Proficiency in Python, with a strong focus on clean, well-structured, and testable code", "Experience leading and executing large-scale, cross-functional projects", "7+ years of experience in ML engineering and 4+ years in production deployments", "Hands-on experience with data pipelines, SQL, and managing large-scale databases", "3+ years of experience in simulation, perception, or autonomous driving technologies", "Familiarity with training and evaluating autonomous vehicle models", "Industry experience in autonomous vehicles, robotics, transportation, or computer vision"], "Benefits": ["The chance to be part of a truly mission-driven organization and an opportunity to shape the future of autonomous driving", "Competitive compensation", "Fully employer-covered medical, dental, and vision insurance!", "Further benefits such as catered lunch, yummy snacks, and a variety of drinks, life insurance, employer contributed retirement account, therapy, yoga, office-wide socials, and much more", "A dynamic and fast-paced work environment in which you will grow every day - learning on the job, from the brightest minds in our space, and with support for more formal learning opportunities too", "A culture that is ego-free, respectful, and welcoming (of you and your dog) - we even eat lunch together every day"], "Responsibilities": ["We\u2019re revolutionizing the way autonomous vehicles learn and operate, and the Scenario Technology and Coverage team plays a pivotal role in that mission by building scalable, data-driven scenarios for evaluating and validating self-driving models", "As a Principal ML Engineer on the Scenario Technology and Coverage team, you'll lead the design and implementation of scalable ML-based tools that enhance our scenario pipeline\u2014from data mining and scenario generation to simulation-based evaluation", "Your work will be critical in ensuring that our driving models are thoroughly tested and optimized across diverse and realistic conditions", "Lead the development of robust ML models and augmentation techniques that power our scenario generation and validation systems", "Architect scalable systems for mining, curating, and synthesizing data to fuel scenario databases, using both real-world and synthetic data", "Collaborate with cross-functional teams, including Simulation and Science, to integrate state-of-the-art technologies into our scenario pipelines", "Drive innovation in scenario coverage, focusing on both closed-loop and open-loop evaluations", "Own end-to-end technical solutions: from translating product requirements into engineering tasks to delivering high-impact ML models and infrastructure improvements", "Identify and address infrastructure gaps, leading initiatives to enhance our foundational tools", "Guide the team in navigating complex technical challenges and setting the technical direction in scenario technology", "Mentor engineers across teams, fostering growth and innovation in scenario-driven ML engineering"]}, "job_onet_soc": "15111100", "job_onet_job_zone": "5"}