{"job_id": "VOmtzg1DJQfgvrX-AAAAAA==", "employer_name": "KIND Snacks", "employer_logo": "https://upload.wikimedia.org/wikipedia/commons/7/77/Logo_for_KIND_Bars_Healthy_Snacks.jpg", "employer_website": "http://www.kindsnacks.com", "employer_company_type": "Foods & Beverages", "job_publisher": "Greenhouse", "job_employment_type": "FULLTIME", "job_title": "Senior Trade Marketing Manager", "job_apply_link": "https://boards.greenhouse.io/kindsnacks/jobs/4324718006", "job_apply_is_direct": false, "job_apply_quality_score": 0.7607, "apply_options": [{"publisher": "Greenhouse", "apply_link": "https://boards.greenhouse.io/kindsnacks/jobs/4324718006", "is_direct": false}, {"publisher": "ZipRecruiter", "apply_link": "https://www.ziprecruiter.com/c/KIND-Snacks/Job/Senior-Trade-Marketing-Manager/-in-New-York,NY?jid=811a04313a0711ed", "is_direct": false}, {"publisher": "Salary.com", "apply_link": "https://www.salary.com/job/kind-snacks/senior-trade-marketing-manager/j202402030127073668893", "is_direct": false}, {"publisher": "Adzuna", "apply_link": "https://www.adzuna.com/details/4603975483", "is_direct": false}, {"publisher": "Jooble", "apply_link": "https://jooble.org/jdp/-8724719301416039887", "is_direct": false}, {"publisher": "Talent.com", "apply_link": "https://www.talent.com/view?id=2d06ef82c9c2", "is_direct": false}], "job_description": "What you\u2019ll do\n\nAs the Senior Trade Marketing Manager, you will be the responsible for our overall portfolio & category strategy for our Base business. In this role, you will work cross functionally with Sales, Marketing, Finance, New Product Development, Operations and Packaging to develop, commercialize, and implement strategic initiatives for our existing portfolio to drive consistent and profitable growth. You will provide business intelligence to help shape long term strategies that will unlock consistent, profitable growth across national channels for our main base business (excluding innovation). You will also be responsible for Sales Operations initiatives across all Trade Marketing, to make sure the Sales team has the right tools and capabilities to successfully sell KIND products. You will have one direct report (Trade Marketing Coordinator) to support you on all these initiatives.\n\nAs the Senior Trade Marketing Manager, you will be the internal voice of the customer team across the entire commercialization process and the external voice of the Marketing team across the Sales team and customers. You will have many high visibility opportunities across the organization and this role will allow you to make a large impact on the business.\n\nAnd this is how you will do it\u2026\n\u2022 Developing an overall multi-channel Go-To-Market Strategy\n\u2022 You will spearhead case pack & pricing architecture across National Channels (Mass, Grocery & Ecom) partnering with SRM / Brand and Sr. Trade Marketing Manager for Growth Channels\n\u2022 Developing channel specific marketing and support initiatives\n\u2022 Partner with the innovation team (Trade Marketing and Brand) on the overall Trade Marketing Strategy\n\u2022 Leading the development of \u201cbest in class\u201d standards for respective channels (considerations include, but are not limited to packaging, design, value architecture, etc)\n\u2022 Leading the relationship with Sales from a Trade Marketing standpoint to support the different strategies by channel\n\u2022 Developing an overall Point of Sale Strategy\n\u2022 Develop and implement a Shippers Strategy that aligns with the overall KIND strategy\n\u2022 Align and partner on strategy with SRM and Perfect Store teams to maximize Promotion and PS initiatives\n\u2022 Partner with Demand Planning, Supply planning and Sales to execute strategy, maximizing Sales and minimizing waste\n\u2022 Develop other POS materials such as Racks, Half Pallets or Displays\n\u2022 Being the voice of the customer to the internal HQ team and being the voice of HQ to Sales\n\u2022 Will become lead consultant and representative for respective channels ensuring consideration of marketplace dynamics for respective customers are taken into account as projects, initiatives or issues arise\n\u2022 Will represent Sales in internal meetings such us DX, Step 1 and Step 2\n\u2022 Will provide help to Sales, building customer specific selling stories and helping with customer meeting preparation\n\u2022 Will work with Analysts and Coordinator to make sure we have right tools to support the sell-in process: Samples, Mock ups, etc\n\u2022 Leader in channel specific analytics\n\u2022 You will share insights on consumption, retailer dynamics, customer specific promotions, shelving, etc. to help inform strategic direction for the channels\n\u2022 Execute the Path to Purchase fundamentals in this channel; including but not limited to category captain insights & best in class aisle flow and organization\n\u2022 Work to commission specialized e-commerce vendors and initiatives to enhance our online presence\n\u2022 Leader in main Trade Shows of the year\n\u2022 Work with sales partners and agencies to develop the booth and overall materials for the main Trade Shows (Expo West, NACS, NAMA)\n\u2022 Partner with Sales and Coordinator on Trade Shows Execution\n\u2022 Budget management\n\nWhat you\u2019ll bring to KIND\n\nYou will bring a passion for driving growth across channels by creating and developing strategies with a customer first mentality.\n\nYou are\u2026\n\u2022 A self-starter\n\u2022 An analytical thinker\n\u2022 Proactive in your approach, constantly looking for ways to break down barriers and advance our business\n\u2022 Able to lead a cross functional team and influence key stakeholders to advance common goals\n\u2022 Genuine in your desire to help make the world a kinder place, committing to always spreading and celebrating kindness\n\nYou have\u2026\n\u2022 6+ years of Marketing and/ or Sales experience (Ideally both)\n\u2022 Cross functional exposure to other Business Operations\n\u2022 Bachelor\u2019s Degree in a related field preferred\n\u2022 Omnichannel expertise preferred\n\u2022 Good understanding of Customer Management Process\n\u2022 Proven analytical skills\n\u2022 Strong knowledge of Syndicated Data (Nielsen/IRI, Kantar, Panel Data, A&Us)\n\u2022 Strong oral, written communication, and presentation skills\n\u2022 Computer proficient (Microsoft Office)\n\u2022 Strong organizational skills\n\u2022 Good interpersonal and time management skills\n\u2022 Based in NYC area preferred, ability to travel to NYC on a regular basis if not\n\nThe salary range for this role is $107,500 - 137,700 per year.\n\nKIND intends to offer the selected candidate base pay within this range, dependent on job-related, non-discriminatory factors such as experience. Base pay is one part of the total rewards that KIND provides to compensate and recognize employees for their work. KIND salary ranges are determined by role, level and location.", "job_is_remote": false, "job_posted_at_timestamp": 1706486400, "job_posted_at_datetime_utc": "2024-01-29T00:00:00.000Z", "job_city": "New York", "job_state": "NY", "job_country": "US", "job_latitude": 40.712776, "job_longitude": -74.005974, "job_benefits": null, "job_google_link": "https://www.google.com/search?gl=us&hl=en&rciv=jb&q=senior+sales+director&start=80&ibp=htl;jobs#fpstate=tldetail&htivrt=jobs&htiq=senior+sales+director&htidocid=VOmtzg1DJQfgvrX-AAAAAA%3D%3D", "job_offer_expiration_datetime_utc": null, "job_offer_expiration_timestamp": null, "job_required_experience": {"no_experience_required": false, "required_experience_in_months": 72, "experience_mentioned": true, "experience_preferred": false}, "job_required_skills": null, "job_required_education": {"postgraduate_degree": false, "professional_certification": false, "high_school": false, "associates_degree": false, "bachelors_degree": false, "degree_mentioned": true, "degree_preferred": true, "professional_certification_mentioned": false}, "job_experience_in_place_of_education": false, "job_min_salary": null, "job_max_salary": null, "job_salary_currency": null, "job_salary_period": null, "job_highlights": {"Qualifications": ["A self-starter", "An analytical thinker", "Proactive in your approach, constantly looking for ways to break down barriers and advance our business", "Able to lead a cross functional team and influence key stakeholders to advance common goals", "Genuine in your desire to help make the world a kinder place, committing to always spreading and celebrating kindness", "6+ years of Marketing and/ or Sales experience (Ideally both)", "Cross functional exposure to other Business Operations", "Good understanding of Customer Management Process", "Proven analytical skills", "Strong knowledge of Syndicated Data (Nielsen/IRI, Kantar, Panel Data, A&Us)", "Strong oral, written communication, and presentation skills", "Computer proficient (Microsoft Office)", "Strong organizational skills", "Good interpersonal and time management skills"], "Responsibilities": ["As the Senior Trade Marketing Manager, you will be the responsible for our overall portfolio & category strategy for our Base business", "In this role, you will work cross functionally with Sales, Marketing, Finance, New Product Development, Operations and Packaging to develop, commercialize, and implement strategic initiatives for our existing portfolio to drive consistent and profitable growth", "You will provide business intelligence to help shape long term strategies that will unlock consistent, profitable growth across national channels for our main base business (excluding innovation)", "You will also be responsible for Sales Operations initiatives across all Trade Marketing, to make sure the Sales team has the right tools and capabilities to successfully sell KIND products", "You will have one direct report (Trade Marketing Coordinator) to support you on all these initiatives", "As the Senior Trade Marketing Manager, you will be the internal voice of the customer team across the entire commercialization process and the external voice of the Marketing team across the Sales team and customers", "You will have many high visibility opportunities across the organization and this role will allow you to make a large impact on the business", "Developing an overall multi-channel Go-To-Market Strategy", "You will spearhead case pack & pricing architecture across National Channels (Mass, Grocery & Ecom) partnering with SRM / Brand and Sr", "Developing channel specific marketing and support initiatives", "Partner with the innovation team (Trade Marketing and Brand) on the overall Trade Marketing Strategy", "Leading the development of \u201cbest in class\u201d standards for respective channels (considerations include, but are not limited to packaging, design, value architecture, etc)", "Leading the relationship with Sales from a Trade Marketing standpoint to support the different strategies by channel", "Developing an overall Point of Sale Strategy", "Develop and implement a Shippers Strategy that aligns with the overall KIND strategy", "Align and partner on strategy with SRM and Perfect Store teams to maximize Promotion and PS initiatives", "Partner with Demand Planning, Supply planning and Sales to execute strategy, maximizing Sales and minimizing waste", "Develop other POS materials such as Racks, Half Pallets or Displays", "Being the voice of the customer to the internal HQ team and being the voice of HQ to Sales", "Will become lead consultant and representative for respective channels ensuring consideration of marketplace dynamics for respective customers are taken into account as projects, initiatives or issues arise", "Will represent Sales in internal meetings such us DX, Step 1 and Step 2", "Will provide help to Sales, building customer specific selling stories and helping with customer meeting preparation", "Will work with Analysts and Coordinator to make sure we have right tools to support the sell-in process: Samples, Mock ups, etc", "Leader in channel specific analytics", "You will share insights on consumption, retailer dynamics, customer specific promotions, shelving, etc", "to help inform strategic direction for the channels", "Execute the Path to Purchase fundamentals in this channel; including but not limited to category captain insights & best in class aisle flow and organization", "Work to commission specialized e-commerce vendors and initiatives to enhance our online presence", "Leader in main Trade Shows of the year", "Work with sales partners and agencies to develop the booth and overall materials for the main Trade Shows (Expo West, NACS, NAMA)", "Partner with Sales and Coordinator on Trade Shows Execution"], "Benefits": ["The salary range for this role is $107,500 - 137,700 per year", "Base pay is one part of the total rewards that KIND provides to compensate and recognize employees for their work"]}, "job_job_title": "Marketing manager", "job_posting_language": "en", "job_onet_soc": "11202100", "job_onet_job_zone": "4", "job_naics_code": "3113", "job_naics_name": "Sugar and Confectionery Product Manufacturing"}