{"job_id": "BGJmbjQP9hgU5lnaAAAAAA==", "employer_name": "The Sherwin-Williams Company", "employer_logo": null, "employer_website": null, "employer_company_type": null, "job_publisher": "Jooble", "job_employment_type": "CONTRACTOR", "job_title": "Management & Sales Training Program", "job_apply_link": "https://jooble.org/jdp/-6667779230848669893", "job_apply_is_direct": false, "job_apply_quality_score": 0.5421, "apply_options": [{"publisher": "Jooble", "apply_link": "https://jooble.org/jdp/-6667779230848669893", "is_direct": false}, {"publisher": "BeBee", "apply_link": "https://us.bebee.com/job/20240229-635e856c14e0620c4b3899c41cbb22c3", "is_direct": false}, {"publisher": "Learn4Good", "apply_link": "https://www.learn4good.com/jobs/cary/north-carolina/retail/2962161905/e/", "is_direct": false}, {"publisher": "Lensa", "apply_link": "https://lensa.com/management--sales-training-program-jobs/cary/jd/c3afb7eca6eb5d0f220e2e5ad4da1ec9", "is_direct": false}, {"publisher": "Jobilize", "apply_link": "https://www.jobilize.com/job/us-nc-cary-management-sales-training-program-sherwin-williams-company", "is_direct": false}], "job_description": "The Sherwin-Williams Management & Sales Training Program is an accelerated, entry-level position designed to prepare you for a Store Management role in 18-24 months. With Sherwin-Williams' promote-from-within philosophy, you will have the opportunity to progress into an Assistant Store Manager position upon successful completion of the initial 6-8-week training.\n\nThis position's typical schedule is 44 hours per week, which may include evenings and/or weekends.\n\nDuring the program, you will collaborate with store management to oversee a million-dollar business, providing leadership and insight into the development and strategy of that store. Through the course of the program, you will learn all operations, clients, and internal strategy, allowing you to understand the significant part you'll play in the team's success. You will grow the company's market share by selling to large, commercial users such as painting contractors, purchasing agents, manufacturers, and other commercial users who need large volumes of our high-quality products.\n\nOur training experience provides you with all the skills necessary for a successful career in management and professional sales. After you complete the training program, you can count on a career trajectory with a clear beginning and an open end - meaning you shape your future!\n\nWhat you will gain:\n\nLimitless Career Opportunities\n\nThis structured program provides the support you need, including formal discussions to review your objectives & development\n\nLeadership Development\n\nYou'll develop the foundation for what it takes to become a successful leader in our organization\n\nWe'll teach you how to excel at customer service, sales, and marketing, finance, and operations\n\nProfessional Networking\n\nYou will also get out into the community and establish relationships essential to growing our business - and your success\n\nComplete training consistent with established program\nSupport business strategies to increase sales and optimize profitability\nEnsure high levels of customers satisfaction through excellent service\nBuild and maintain knowledge of all products to ensure effective customer recommendations\nBuild positive relationships with wholesale and retail customers\nComplete store administration\nEnsure compliance with policies and procedures including safety, loss prevention, and security\nMaintain outstanding store condition and visual merchandising standards, including promotional packages and sales floor displays\nSupport employee training, development, performance management, and corrective action\nRespond to and resolve any customer and/or employee complaints\nPartner with Store Manager to make outside sales calls to increase market share\n\nMinimum Requirements:\n\nMust be at least eighteen (18) years of age\nMust be legally authorized to work in the country of employment without needing sponsorship for employment work visa status now or in the future\nMust have a valid, unrestricted Driver's License\nMust have at least a bachelor's degree by the start of this development program\nMust be able, with or without reasonable accommodation, to retrieve material from shelves and floor stacks and lift and carry up to 50 lbs. frequently and up to 70 lbs. on occasion\n\nPreferred Qualifications:\n\nHave at least one (1) year experience working in a retail, sales, or customer service position\nHave at least one (1) year of experience in leadership role(s), supervising others, or leading teams\nHave previous experience working in a team-oriented setting including work experience, extracurricular activities, military service, etc.\nHave previous work experience selling paint and paint related products\nHave work experience using timekeeping and/or customer relationship management (\"CRM\") systems\nWillingness to relocate for future job opportunities\nAbility to read, write, comprehend, and communicate in more than one language\nAbility to read, write, comprehend, and communicate in Spanish", "job_is_remote": false, "job_posted_at_timestamp": 1710171031, "job_posted_at_datetime_utc": "2024-03-11T15:30:31.000Z", "job_city": "Cary", "job_state": "NC", "job_country": "US", "job_latitude": 35.79154, "job_longitude": -78.78112, "job_benefits": null, "job_google_link": "https://www.google.com/search?gl=us&hl=en&rciv=jb&q=manager+of+sales+training&start=10&ibp=htl;jobs#fpstate=tldetail&htivrt=jobs&htiq=manager+of+sales+training&htidocid=BGJmbjQP9hgU5lnaAAAAAA%3D%3D", "job_offer_expiration_datetime_utc": "2024-04-11T08:06:02.000Z", "job_offer_expiration_timestamp": 1712822762, "job_required_experience": {"no_experience_required": false, "required_experience_in_months": 12, "experience_mentioned": true, "experience_preferred": false}, "job_required_skills": null, "job_required_education": {"postgraduate_degree": false, "professional_certification": false, "high_school": false, "associates_degree": false, "bachelors_degree": false, "degree_mentioned": true, "degree_preferred": false, "professional_certification_mentioned": false}, "job_experience_in_place_of_education": false, "job_min_salary": null, "job_max_salary": null, "job_salary_currency": null, "job_salary_period": null, "job_highlights": {"Qualifications": ["Must be at least eighteen (18) years of age", "Must be legally authorized to work in the country of employment without needing sponsorship for employment work visa status now or in the future", "Must have a valid, unrestricted Driver's License", "Must have at least a bachelor's degree by the start of this development program", "Must be able, with or without reasonable accommodation, to retrieve material from shelves and floor stacks and lift and carry up to 50 lbs", "frequently and up to 70 lbs", "Have at least one (1) year experience working in a retail, sales, or customer service position", "Have at least one (1) year of experience in leadership role(s), supervising others, or leading teams", "Have previous experience working in a team-oriented setting including work experience, extracurricular activities, military service, etc", "Have previous work experience selling paint and paint related products", "Have work experience using timekeeping and/or customer relationship management (\"CRM\") systems", "Willingness to relocate for future job opportunities", "Ability to read, write, comprehend, and communicate in more than one language"], "Responsibilities": ["This position's typical schedule is 44 hours per week, which may include evenings and/or weekends", "During the program, you will collaborate with store management to oversee a million-dollar business, providing leadership and insight into the development and strategy of that store", "Through the course of the program, you will learn all operations, clients, and internal strategy, allowing you to understand the significant part you'll play in the team's success", "You will grow the company's market share by selling to large, commercial users such as painting contractors, purchasing agents, manufacturers, and other commercial users who need large volumes of our high-quality products", "You'll develop the foundation for what it takes to become a successful leader in our organization", "Complete training consistent with established program", "Support business strategies to increase sales and optimize profitability", "Ensure high levels of customers satisfaction through excellent service", "Build and maintain knowledge of all products to ensure effective customer recommendations", "Build positive relationships with wholesale and retail customers", "Complete store administration", "Ensure compliance with policies and procedures including safety, loss prevention, and security", "Maintain outstanding store condition and visual merchandising standards, including promotional packages and sales floor displays", "Support employee training, development, performance management, and corrective action", "Respond to and resolve any customer and/or employee complaints", "Partner with Store Manager to make outside sales calls to increase market share"], "Benefits": ["Limitless Career Opportunities", "This structured program provides the support you need, including formal discussions to review your objectives & development"]}, "job_job_title": "Training", "job_posting_language": "en", "job_onet_soc": "11313100", "job_onet_job_zone": "4"}