{"job_id": "0uEGPAjnVZgvq5pHAAAAAA==", "employer_name": "US Pharma Lab", "employer_logo": "https://media.licdn.com/dms/image/C4D0BAQEpE5dDM8CD2g/company-logo_200_200/0/1631309585300?e=2147483647&v=beta&t=vM1EqQfkUXid1HH03YEcNa47ahYerFRUfn1_0etH0qE", "employer_website": "http://www.uspharmalab.com", "employer_company_type": null, "job_publisher": "Salary.com", "job_employment_type": "FULLTIME", "job_title": "Vice President, Sales", "job_apply_link": "https://www.salary.com/job/us-pharma-lab/vice-president-sales/j202311200445506678194", "job_apply_is_direct": false, "job_apply_quality_score": 0.6275, "apply_options": [{"publisher": "Salary.com", "apply_link": "https://www.salary.com/job/us-pharma-lab/vice-president-sales/j202311200445506678194", "is_direct": false}, {"publisher": "Learn4Good", "apply_link": "https://www.learn4good.com/jobs/new-jersey/sales/2950308878/e/", "is_direct": false}], "job_description": "Job Description\n\nDate\n\n09/2021\n\nLocation\n\n1300 Airport Road, North Brunswick NJ\n\nTitle\n\nVice President, Sales\n\nDepartment\n\nSales\n\nReports to\n\nChief Executive Officer\n\nFLSA (Exempt or Non-Exempt\n\nExempt\n\nRole Overview\n\nThe Vice President of Sales is responsible for managing the Company\u2019s sales functions in order to achieve sales and profit goals within their prospective region. This position will report directly to our EVP and be a part of the leadership team. This person will be responsible for business development, revenue growth and for achieving the approved annual sales plan in a cost-effective manner.\n\nAreas of Responsibility\n\u2022 Develop and implement strategic programs to ensure achievement of sales targets such as: increase in market penetration, gaining new business, and retention of customers.\n\u2022 Develop a sales strategy (specific to each market being served) on a quarterly/annual basis to drive sales growth.\n\u2022 Lead, motivate, and coach the sales team to meet and exceed sales revenue plans and provide the highest level of customer service.\n\u2022 Assist and provide direct reports with career planning, training, and growth.\n\u2022 Maintain a team-based work environment to promote sales across the business and drive employee and customer retention.\n\u2022 Develop timely reports needed to monitor progress of sales team.\n\u2022 Maintain and review sales prospect pipeline and sales forecast.\n\u2022 Complete sales and negotiates contracts, as needed.\n\u2022 Participate in fiscal year business planning.\n\u2022 Conduct Quarterly Business Reviews with current customers, in conjunction with Account Executives, Account Managers (if applicable), and other designees to improve quality of service and unearth other avenues for opportunity.\n\u2022 Keep current with industry standards and knowledge by attending trade shows, seminars, and conventions.\n\u2022 Interface with senior management to accurately budget expenses and forecast future revenue, trending, and actual sales activity.\n\u2022 Prepare and present proposals and presentations as needed to senior leadership.\n\u2022 Present to ownership on monthly, quarterly, and annual basis.\n\u2022 Track, manage and approve monthly sales incentives.\n\u2022 Reviews market trends to determine customer needs, volume potential, price point, emerging technologies to develop sales strategy to accomplish growth goals of company.\n\u2022 Review unprofitable products and develop plan with Sales and Operations to achieve profitable GP%.\n\u2022 Represents company at trade association functions to promote product.\n\u2022 Creates and controls expenditures of department to conform to annual budget requirements.\n\u2022 Other Duties as Assigned.\n\nOther Responsibilities Including Safety:\n\u2022 Works in a safe and responsible manner in order to create an injury-free and incident-free workplace.\n\u2022 Complies with all job-related safety and other training requirements.\nKeeps management informed of area activities and of any significant problems.\n\u2022 Requirements\n\nEducation & Qualification:\n\u2022 4 Year Bachelor\u2019s Degree\n\u2022 10 years professional experience\n\nCertifications, Licenses, Credentials:\n\u2022 N/A\n\nSkills & Ability\n\u2022 Client-obsessed with a strong aptitude in a structured sales approach\n\u2022 Self-motivated with exceptional talent in closing deals\n\u2022 Strong knowledge in the complete end-to-end sales cycle (from prospecting to closing)\n\u2022 Exceptional prospecting/hunter skills and experience\n\u2022 Experience in pharmaceuticals and/or manufacturing environment is a plus\n\u2022 Good communication and Email writing skills\n\nPhysical Requirements (lifting, etc.):\n\u2022 Ability to navigate office, lab, and/or plant floor working environments.\n\u2022 Standard office environment without unpleasant or hazardous conditions. Physical demands involved in office work such as the ability to talk, hear, use hands to handle and feel; work on a computer up to 7 hours a day; close vision required for computer usage.\n\u2022 Must have the ability to wear applicable personal protective equipment utilized at this site, including safety glasses/goggles, hairnets, lab coats and safety shoes.\n\nWork Environment (Office, Warehouse, temperature extremes, etc.):\n\u2022 Exposed to lab and/or plant floor working environments.\n\u2022 Standard office environment without unpleasant or hazardous conditions.\nTemperature controlled for heat and air conditioning.\n\u2022 The above statements are intended to describe the general nature and level of work being performed by people assigned to this job. They are not intended to be an exhaustive list of all the job responsibilities, duties, skill, or working conditions. In addition, this document does not create an employment contract, implied or otherwise, other than an \"at will\" relationship.", "job_is_remote": false, "job_posted_at_timestamp": 1709251200, "job_posted_at_datetime_utc": "2024-03-01T00:00:00.000Z", "job_city": "North Brunswick Township", "job_state": "NJ", "job_country": "US", "job_latitude": 40.452515, "job_longitude": -74.47667, "job_benefits": null, "job_google_link": "https://www.google.com/search?gl=us&hl=en&rciv=jb&q=vice+president+of+sales&start=80&ibp=htl;jobs#fpstate=tldetail&htivrt=jobs&htiq=vice+president+of+sales&htidocid=0uEGPAjnVZgvq5pHAAAAAA%3D%3D", "job_offer_expiration_datetime_utc": "2024-03-28T00:00:00.000Z", "job_offer_expiration_timestamp": 1711584000, "job_required_experience": {"no_experience_required": false, "required_experience_in_months": 48, "experience_mentioned": true, "experience_preferred": true}, "job_required_skills": null, "job_required_education": {"postgraduate_degree": false, "professional_certification": false, "high_school": false, "associates_degree": false, "bachelors_degree": false, "degree_mentioned": true, "degree_preferred": false, "professional_certification_mentioned": true}, "job_experience_in_place_of_education": false, "job_min_salary": null, "job_max_salary": null, "job_salary_currency": null, "job_salary_period": null, "job_highlights": {"Qualifications": ["4 Year Bachelor\u2019s Degree", "10 years professional experience", "N/A", "Client-obsessed with a strong aptitude in a structured sales approach", "Self-motivated with exceptional talent in closing deals", "Strong knowledge in the complete end-to-end sales cycle (from prospecting to closing)", "Exceptional prospecting/hunter skills and experience", "Good communication and Email writing skills", "Physical Requirements (lifting, etc.):", "Ability to navigate office, lab, and/or plant floor working environments", "Standard office environment without unpleasant or hazardous conditions", "Physical demands involved in office work such as the ability to talk, hear, use hands to handle and feel; work on a computer up to 7 hours a day; close vision required for computer usage", "Must have the ability to wear applicable personal protective equipment utilized at this site, including safety glasses/goggles, hairnets, lab coats and safety shoes"], "Responsibilities": ["The Vice President of Sales is responsible for managing the Company\u2019s sales functions in order to achieve sales and profit goals within their prospective region", "This position will report directly to our EVP and be a part of the leadership team", "This person will be responsible for business development, revenue growth and for achieving the approved annual sales plan in a cost-effective manner", "Develop and implement strategic programs to ensure achievement of sales targets such as: increase in market penetration, gaining new business, and retention of customers", "Develop a sales strategy (specific to each market being served) on a quarterly/annual basis to drive sales growth", "Lead, motivate, and coach the sales team to meet and exceed sales revenue plans and provide the highest level of customer service", "Assist and provide direct reports with career planning, training, and growth", "Maintain a team-based work environment to promote sales across the business and drive employee and customer retention", "Develop timely reports needed to monitor progress of sales team", "Maintain and review sales prospect pipeline and sales forecast", "Complete sales and negotiates contracts, as needed", "Participate in fiscal year business planning", "Conduct Quarterly Business Reviews with current customers, in conjunction with Account Executives, Account Managers (if applicable), and other designees to improve quality of service and unearth other avenues for opportunity", "Keep current with industry standards and knowledge by attending trade shows, seminars, and conventions", "Interface with senior management to accurately budget expenses and forecast future revenue, trending, and actual sales activity", "Prepare and present proposals and presentations as needed to senior leadership", "Present to ownership on monthly, quarterly, and annual basis", "Track, manage and approve monthly sales incentives", "Reviews market trends to determine customer needs, volume potential, price point, emerging technologies to develop sales strategy to accomplish growth goals of company", "Review unprofitable products and develop plan with Sales and Operations to achieve profitable GP%", "Represents company at trade association functions to promote product", "Creates and controls expenditures of department to conform to annual budget requirements", "Other Duties as Assigned", "Works in a safe and responsible manner in order to create an injury-free and incident-free workplace", "Complies with all job-related safety and other training requirements", "Keeps management informed of area activities and of any significant problems"], "Benefits": ["FLSA (Exempt or Non-Exempt"]}, "job_job_title": "Vice president", "job_posting_language": "en", "job_onet_soc": "11101100", "job_onet_job_zone": "5"}