{"job_id": "4hbdimKbWdD42UcOAAAAAA==", "employer_name": "CI&T", "employer_logo": "https://dmwnh9nwzeoaa.cloudfront.net/2020-11/ciandt-logo-thumbnail.png?d=600x600", "employer_website": "http://ciandt.com", "employer_company_type": "Consulting", "job_publisher": "LinkedIn", "job_employment_type": "FULLTIME", "job_title": "Senior Sales Executive | Business Development Manager - Healthcare & Life Sciences", "job_apply_link": "https://www.linkedin.com/jobs/view/senior-sales-executive-business-development-manager-healthcare-life-sciences-at-ci-t-3848892086", "job_apply_is_direct": false, "job_apply_quality_score": 0.6311, "apply_options": [{"publisher": "LinkedIn", "apply_link": "https://www.linkedin.com/jobs/view/senior-sales-executive-business-development-manager-healthcare-life-sciences-at-ci-t-3848892086", "is_direct": false}], "job_description": "We partner with the world\u2019s most valuable brands to build digital solutions that transform businesses. As a digital native, we bring a 29-year track record of accelerating business impact through complete and scalable digital solutions. With a global presence of 6,000+ professionals in strategy, research, data science, design, and engineering, we unlock top-line growth, improve customer experience and drive operational efficiency.\n\nGeneral Description\n\nThe role of the Senior Sales Executive (Business Development Manager) is to identify, qualify and close sales opportunities for digital services and solutions within the Healthcare & Life Sciences vertical . The ideal candidate is a person who has not just built their own very successful track record in sales and business development but can uncover client pain points, create solution visions that motivate clients to engage CI&T to solve, manage the sales and internal solution development process which ultimately leads to compelling proposals that solve complex business and technical problems resulting in closed contracts and new revenue.\n\nYou have a strong grasp of B2B solutions and services sales and an understanding of the role business development plays in lead generation and lead qualification.\n\nWhat You\u2019ll Do\n\u2022 Conduct prospecting for qualified leads (organic and CI&T sourced), build a pipeline of new, well-qualified business opportunities, develop and lead the sales strategy on specific opportunities and manage the prospect to successfully close new business\n\u2022 Work closely and collaboratively with the marketing and industry vertical leadership team to develop and implement appropriate prospect communication plans\n\u2022 Drive (and develop as required) capabilities presentations or pitches for target prospects\n\u2022 Conduct needs-based discovery assessments and present insights to specific prospects leading to material new opportunities\n\nResponsibilities\n\u2022 Identify and pursue new business opportunities in the healthcare and life sciences market, both locally and nationally\n\u2022 Identify and research potential prospects/clients\n\u2022 Develop and maintain strong relationships with key decision-makers and influencers in the industry\n\u2022 Coordinate and lead the sales engineering team and the appropriate Growth Unit to develop mutually beneficial proposals\n\u2022 Negotiate and close contracts with clients and ensure customer satisfaction and retention\n\u2022 Monitor and manage legal team to ensure contracts are executed as agreed\n\u2022 Collaborate with internal teams, such as marketing, product, and delivery, to provide feedback and insights from the market and customers\n\u2022 Gather useful information from customer and competitor data to develop and implement differentiated sales strategies\n\u2022 Make and give presentations to prospective clients and internal executives\n\u2022 Create and implement processes and policies to support the overall business\n\u2022 Track, identify, cultivate and add qualified prospects to the sales pipeline\n\u2022 Develop and manage strategic industry partnerships to grow business\n\u2022 Track and report on the status of proposal components\n\u2022 Drive the end-to-end sales process\n\u2022 Coordinate with solution engineers and marketing\n\u2022 Prepare and submit proposals, SOWs and sales contracts\n\u2022 Participate in industry events, trade shows, and conferences to network and promote our brand and services\n\nRequirements\n\nWe are looking for someone with the following attributes:\n\u2022 5+ years of experience in Healthcare & Life Sciences\n\u2022 Digital Strategy\n\u2022 Product Management\n\u2022 Technology Services\n\u2022 HCP digital engagement solutions\n\u2022 Patient digital engagement solutions\n\u2022 7-10 years of sales experience within a professional services or consulting organization\n\u2022 Strong communication skills, engaging a variety of prospects and stakeholders to drive successful outcomes\n\u2022 Motivated by goals, with a strong desire to work hard and not only meet but exceed targets set for oneself\n\u2022 Willingness to learn and become a master of our Customer Relationship Management (CRM) system\n\u2022 A strong sense of self-motivation\n\u2022 The ability to think of creative solutions in the face of opposition\n\u2022 Strategic thinker\n\u2022 Track record of success\n\nLocation(s): U.S. (Preferably New Jersey, New York, Boston, Philadelphia, Chicago, SF Bay Area)\n\nWhy join us?\n\u2022 We offer incredible benefits\n\n\u25cb Competitive Salary\n\n\u25cb Generous paid vacation days\n\n\u25cb Unlimited sick time\n\n\u25cb 100% paid health & dental benefits starting day one\n\n\u25cb Retirement match\n\n\u25cb Paid parental leave\n\n\u25cb And much much more\u2026\n\n#MidSenior\n\nCI&T is an equal-opportunity employer. We celebrate and appreciate the diversity of our CI&Ters\u2019 identities and lived experiences. We are committed to building, promoting, and retaining a diverse, inclusive, and equitable company and culture focused on creating a better tomorrow.\n\nAt CI&T, we recognize that innovation and transformation only happen in diverse, inclusive, and safe work environments. Our teams are most impactful when people from all backgrounds and experiences collaborate to share, create, and hear ideas.\n\nBefore applying for our opportunities take a look at our Conflict of Interest Policy .\n\nWe strongly encourage candidates from diverse and underrepresented communities to apply for our vacancies.", "job_is_remote": false, "job_posted_at_timestamp": 1709765702, "job_posted_at_datetime_utc": "2024-03-06T22:55:02.000Z", "job_city": null, "job_state": null, "job_country": "US", "job_latitude": 37.09024, "job_longitude": -95.71289, "job_benefits": ["dental_coverage", "retirement_savings", "health_insurance", "paid_time_off"], "job_google_link": "https://www.google.com/search?gl=us&hl=en&rciv=jb&q=senior+sales+manager&start=80&ibp=htl;jobs#fpstate=tldetail&htivrt=jobs&htiq=senior+sales+manager&htidocid=4hbdimKbWdD42UcOAAAAAA%3D%3D", "job_offer_expiration_datetime_utc": "2024-04-05T22:55:02.000Z", "job_offer_expiration_timestamp": 1712357702, "job_required_experience": {"no_experience_required": false, "required_experience_in_months": null, "experience_mentioned": true, "experience_preferred": false}, "job_required_skills": null, "job_required_education": {"postgraduate_degree": false, "professional_certification": false, "high_school": false, "associates_degree": false, "bachelors_degree": false, "degree_mentioned": false, "degree_preferred": false, "professional_certification_mentioned": false}, "job_experience_in_place_of_education": false, "job_min_salary": null, "job_max_salary": null, "job_salary_currency": null, "job_salary_period": null, "job_highlights": {"Qualifications": ["The ideal candidate is a person who has not just built their own very successful track record in sales and business development but can uncover client pain points, create solution visions that motivate clients to engage CI&T to solve, manage the sales and internal solution development process which ultimately leads to compelling proposals that solve complex business and technical problems resulting in closed contracts and new revenue", "You have a strong grasp of B2B solutions and services sales and an understanding of the role business development plays in lead generation and lead qualification", "5+ years of experience in Healthcare & Life Sciences", "Digital Strategy", "7-10 years of sales experience within a professional services or consulting organization", "Strong communication skills, engaging a variety of prospects and stakeholders to drive successful outcomes", "Motivated by goals, with a strong desire to work hard and not only meet but exceed targets set for oneself", "Willingness to learn and become a master of our Customer Relationship Management (CRM) system", "A strong sense of self-motivation", "The ability to think of creative solutions in the face of opposition", "Strategic thinker"], "Responsibilities": ["The role of the Senior Sales Executive (Business Development Manager) is to identify, qualify and close sales opportunities for digital services and solutions within the Healthcare & Life Sciences vertical ", "Conduct prospecting for qualified leads (organic and CI&T sourced), build a pipeline of new, well-qualified business opportunities, develop and lead the sales strategy on specific opportunities and manage the prospect to successfully close new business", "Work closely and collaboratively with the marketing and industry vertical leadership team to develop and implement appropriate prospect communication plans", "Drive (and develop as required) capabilities presentations or pitches for target prospects", "Conduct needs-based discovery assessments and present insights to specific prospects leading to material new opportunities", "Identify and pursue new business opportunities in the healthcare and life sciences market, both locally and nationally", "Identify and research potential prospects/clients", "Develop and maintain strong relationships with key decision-makers and influencers in the industry", "Coordinate and lead the sales engineering team and the appropriate Growth Unit to develop mutually beneficial proposals", "Negotiate and close contracts with clients and ensure customer satisfaction and retention", "Monitor and manage legal team to ensure contracts are executed as agreed", "Collaborate with internal teams, such as marketing, product, and delivery, to provide feedback and insights from the market and customers", "Gather useful information from customer and competitor data to develop and implement differentiated sales strategies", "Make and give presentations to prospective clients and internal executives", "Create and implement processes and policies to support the overall business", "Track, identify, cultivate and add qualified prospects to the sales pipeline", "Develop and manage strategic industry partnerships to grow business", "Track and report on the status of proposal components", "Drive the end-to-end sales process", "Coordinate with solution engineers and marketing", "Prepare and submit proposals, SOWs and sales contracts", "Participate in industry events, trade shows, and conferences to network and promote our brand and services"], "Benefits": ["We offer incredible benefits", "\u25cb Competitive Salary", "\u25cb Generous paid vacation days", "\u25cb Unlimited sick time", "\u25cb 100% paid health & dental benefits starting day one", "\u25cb Retirement match", "\u25cb Paid parental leave"]}, "job_job_title": "Development manager", "job_posting_language": "en", "job_onet_soc": "11202100", "job_onet_job_zone": "4", "job_naics_code": "541613", "job_naics_name": "Marketing Consulting Services"}