{"job_id": "-045P6BuUxNR4yn3AAAAAA==", "employer_name": "Berkeley Research Group", "employer_logo": "https://upload.wikimedia.org/wikipedia/en/a/ac/BerkeleyResearchGrouplogo.png", "employer_website": "http://www.thinkbrg.com", "employer_company_type": "Consulting", "job_publisher": "Berkeley Research Group Careers", "job_employment_type": "FULLTIME", "job_title": "AI ML Engineer", "job_apply_link": "https://careers.thinkbrg.com/jobs/13876124-ai-ml-engineer", "job_apply_is_direct": false, "job_apply_quality_score": 0.7826, "apply_options": [{"publisher": "Berkeley Research Group Careers", "apply_link": "https://careers.thinkbrg.com/jobs/13876124-ai-ml-engineer", "is_direct": false}, {"publisher": "Glassdoor", "apply_link": "https://www.glassdoor.com/job-listing/ai-ml-engineer-berkeley-research-group-llc-JV_KO0,14_KE15,42.htm?jl=1009088038850", "is_direct": false}, {"publisher": "Jobgether", "apply_link": "https://jobgether.com/offer/65bdc183bb93d052b51afaac-ai-ml-engineer", "is_direct": false}, {"publisher": "LinkedIn", "apply_link": "https://www.linkedin.com/jobs/view/ai-ml-engineer-at-berkeley-research-group-3812940027", "is_direct": false}, {"publisher": "Indeed", "apply_link": "https://www.indeed.com/viewjob?jk=626d4107c1d11ab1", "is_direct": false}, {"publisher": "Illbeback.ai", "apply_link": "https://illbeback.ai/job/ai-ml-engineer-163/", "is_direct": false}], "job_description": "Description\n\nJob Summary:\nBRG is a company specializing in providing subject matter expertise backed by data analytics in areas including economics, mergers, litigation, damages, investment, healthcare-related insights, and others.\n\nExpert Solutions team is the liaison between business customers and IT for non-commodity IT services delivering solutions to complex business and technical problems. The goal of the Expert Solutions team is to be the focal point of technical excellence and technological innovation within BRG to help our business teams be more effective and enhance competitive advantage. Expert Solutions is a highly collaborative team responsible for designing, developing, modifying, adapting, and implementing short- and long-term solutions to information technology (IT) needs through new and existing data applications, systems architecture, network systems and data architecture.\n\nThe mid-level AI/ML Engineer position requires both technical and industry-specific knowledge, with desired skills that indicate familiarity with leading-edge technologies and platforms in the field of data analytics and AI/ML. It also requires strategic knowledge of the cloud computing technology and providers, including Platform as a Service (PaaS), Software as a Service (SaaS), and/or Infrastructure as a Service (IaaS), and the skills to configure those clouds to fit company needs. Azure, AWS, and GCP experience is a plus. The position requires analysis skills to understand and capture the business users\u2019 AI/ML and related data analytics requirements by working closely with business Experts, IT teams, and vendors.\n\nReporting Relationships:\n\u2022 Director of Information Technology & Expert Solutions\nKey Contacts:\n\u2022 This role interfaces with leaders and designees of Expert Communities (practices) throughout the firm.\n\u2022 Additionally, this role would interface heavily with internal IT staff as well as IT business partners.\nMajor Responsibilities/ Job Functions:\n\u2022 Collaboration with Business and Expert Solutions Team:\n\u2022 Engage closely with business users and other members of the Expert Solutions team to assess and define AI/ML and big data analytics requirements.\n\u2022 Utilize a deep understanding of AI/ML applications to translate business needs into technical solutions.\n\u2022 Development of Advanced Analytics and ML Models:\n\u2022 Create and demonstrate sophisticated analytics programs and machine learning models to address complex business challenges.\n\u2022 Apply statistical methods and data-driven techniques to uncover insights and drive business decisions.\n\u2022 Integration of AI/ML Technologies into Existing Workflows:\n\u2022 Integrate new AI/ML software and data management technologies into current business and data workflows.\n\u2022 Assist the transition and adoption of new technologies by providing technical guidance and support.\n\u2022 Building and Managing Data Systems and ML Pipelines:\n\u2022 Design and build efficient data systems and pipelines optimized for machine learning, supporting business users in data ingestion, organization, and storage.\n\u2022 Implement tools and processes for managing large-scale datasets used in AI/ML projects.\n\u2022 Development and Maintenance of Data and AI Architectures:\n\u2022 Develop, construct, test, and maintain architectures that support data science and machine learning projects.\n\u2022 Regularly review and realign architectures to ensure they meet evolving business requirements and industry best practices.\n\u2022 Research and Evaluation of AI/ML Tools and Technologies:\n\u2022 Conduct ongoing research to stay abreast of the latest advancements in AI/ML tools and technologies.\n\u2022 Evaluate and recommend tools that enhance the organization\u2019s AI/ML capabilities.\n\u2022 Vendor and Consulting Firm Engagement for AI/ML Solutions:\n\u2022 Assist in the selection and management of external vendors and consulting firms for AI/ML-related projects.\n\u2022 Guide and oversee external partners in the evaluation and implementation of AI/ML solutions, ensuring alignment with business objectives.\n\u2022 Ensuring Compliance and Ethical AI Practices:\n\u2022 Adhere to data privacy and security regulations.\n\u2022 Promote ethical AI practices in all machine learning and data analytics projects.\n\nKnowledge, Skills, and Behaviors - Required\n\u2022 Educational Background:\n\u2022 A Bachelor\u2019s or Master\u2019s degree in Computer Science, Engineering, Statistics, or a related field, with a specialization in machine learning, artificial intelligence, or data science.\n\u2022 Work Experience:\n\u2022 3-5 years of relevant experience in AI/ML, with a proven track record in applying machine learning techniques to real-world problems. Experience in data analytics in sectors like economics, healthcare, investment, or similar fields is highly desirable.\n\u2022 Technical Skills:\n\u2022 Proficient in programming languages such as Python, R, or Java.\n\u2022 Expertise in machine learning frameworks (e.g., TensorFlow, PyTorch) and libraries (e.g., scikit-learn, NLTK).\n\u2022 Advanced knowledge of machine learning algorithms, including supervised and unsupervised learning, deep learning, NLP, and predictive modeling.\n\u2022 Experience with Retrieval-Augmented Generation (RAG) for enhancing language models with external knowledge sources.\n\u2022 Demonstrated experience in fine-tuning pre-trained models on domain-specific data to improve performance and accuracy.\n\u2022 Hands-on experience with Large Language Models like GPT-3 or GPT-4, including using APIs like ChatGPT for integration into applications or services.\n\u2022 Experience in configuring and managing self-hosted LLMs such as LLAMA, including setup, maintenance, and optimization for specific use cases.\n\u2022 Data Analytics and Processing Skills:\n\u2022 Advanced Data Handling: Exceptional skills in managing, cleaning, and preprocessing large and complex datasets using advanced SQL techniques for complex queries, and expertise in using Python's Pandas library for data manipulation and analysis.\n\u2022 Data Processing Frameworks: Proficiency in using big data processing frameworks like Apache Spark, which enables handling of large-scale data processing and analytics over distributed systems.\n\u2022 Econometrics and Statistical Modeling: Deep understanding of econometrics methods, including time-series analysis, regression models, and hypothesis testing, to analyze economic data. Familiarity with statistical modeling techniques and their application in real-world scenarios, using tools like R or Python\u2019s statistical libraries.\n\u2022 Quantitative Methods: Expertise in applying quantitative methods like linear programming, optimization techniques, and probability theory in solving complex problems.\n\u2022 Domain Expertise:\n\u2022 Economics: Understanding of economic principles and models, and how AI/ML can be leveraged for economic forecasting, market analysis, and policy evaluation.\n\u2022 Healthcare: Knowledge of healthcare systems, electronic health records (EHR), patient data analysis, and application of AI for predictive diagnostics, treatment personalization, and drug discovery.\n\u2022 Litigation and Legal Analytics: Familiarity with the legal domain, including litigation processes, document analysis, and the use of AI for case prediction, legal research, and contract analysis.\n\u2022 Project Management and Teamwork Skills:\n\u2022 Ability to manage AI/ML projects effectively, coordinate with cross-functional teams, and deliver results within set timelines.\n\u2022 Communication Skills:\n\u2022 Excellent communication skills to explain complex AI/ML concepts to non-technical stakeholders and collaborate effectively within the organization.\n\u2022 Problem-Solving and Innovative Thinking:\n\u2022 Strong analytical and problem-solving skills, with an ability to think creatively to provide innovative solutions to complex problems.\n\u2022 Commitment to Continuous Learning:\n\u2022 Dedication to staying updated with the latest developments in AI/ML, particularly in areas like RAG, fine-tuning, and LLMs.\n\u2022 Ethical and Compliance Awareness:\n\u2022 Knowledge of ethical considerations in AI, and compliance with legal and regulatory standards, especially in handling sensitive data in areas like healthcare and finance.\n\nKnowledge, Skills, and Behaviors - Desired\n\u2022 Major Vendor SaaS Data Analytics/AI-ML Solutions:\n\u2022 Databricks: Experience with Databricks\u2019 unified analytics platform for massive-scale data engineering and collaborative data science.\n\u2022 Snowflake: Knowledge of Snowflake\u2019s cloud data platform for data warehousing, data lakes, data engineering, data science, and developing data applications.\n\u2022 Google BigQuery: Proficiency in using Google BigQuery for big data analytics, including its ML capabilities for building and operationalizing machine learning models.\n\u2022 Microsoft Azure Fabric (formerly Azure Synapse Analytics): Experience with Azure Fabric / Synapse Analytics for integrating various analytics services and managing big data and data warehouse solutions.\n\u2022 Amazon Web Services (AWS): Familiarity with AWS\u2019s suite of AI/ML services, such as Amazon SageMaker for building, training, and deploying machine learning models at scale.\n\u2022 Cloud Computing Expertise and Strategy:\n\u2022 Strategic Cloud Knowledge: Strong understanding of cloud computing technologies and their strategic application in business. This includes familiarity with various service models such as Platform as a Service (PaaS), Software as a Service (SaaS), and Infrastructure as a Service (IaaS).\n\u2022 Cloud Configuration Skills: Proven ability to configure cloud environments according to company needs, ensuring efficient and secure utilization of cloud resources. This includes setting up scalable and robust cloud infrastructures, optimizing cloud services for cost and performance, and ensuring compliance with data protection and privacy standards.\n\u2022 Experience with Major Cloud Providers: Hands-on experience with leading cloud platforms such as Azure, Amazon Web Services (AWS), and Google Cloud Platform (GCP). This includes deploying and managing applications and services, utilizing cloud-native AI/ML tools, and integrating cloud services with on-premise systems.\n\u2022 Business and IT Collaboration: Strong analytical skills to understand and capture big data and data analytics requirements from business users. Ability to work closely with business experts, IT teams, and vendors to align cloud solutions with business objectives.\n\u2022 Solution Design and Implementation: Competence in designing and implementing cloud-based solutions for data analytics and machine learning projects. This involves selecting the right cloud services and tools, creating data pipelines, and ensuring that the solutions are scalable, secure, and cost-effective.\n\u2022 Cross-Platform Integration: Skills in integrating various cloud services and platforms to create cohesive and efficient systems that leverage the strengths of each cloud provider.\n\u2022 Cloud Security and Compliance:\n\u2022 Knowledge of cloud security principles and practices, as well as experience in ensuring compliance with regulatory requirements in a cloud environment.\n\nCandidate must be able to submit verification of his/her legal right to work in the U.S., without company sponsorship.\n\nSalary Range: 115-160k\n\n#LI-AW1\n#LI-REMOTE", "job_is_remote": false, "job_posted_at_timestamp": 1710460800, "job_posted_at_datetime_utc": "2024-03-15T00:00:00.000Z", "job_city": null, "job_state": null, "job_country": "US", "job_latitude": 37.09024, "job_longitude": -95.71289, "job_benefits": null, "job_google_link": "https://www.google.com/search?gl=us&hl=en&rciv=jb&q=data+science+leader&start=10&ibp=htl;jobs#fpstate=tldetail&htivrt=jobs&htiq=data+science+leader&htidocid=-045P6BuUxNR4yn3AAAAAA%3D%3D", "job_offer_expiration_datetime_utc": null, "job_offer_expiration_timestamp": null, "job_required_experience": {"no_experience_required": false, "required_experience_in_months": 36, "experience_mentioned": true, "experience_preferred": true}, "job_required_skills": null, "job_required_education": {"postgraduate_degree": false, "professional_certification": false, "high_school": false, "associates_degree": false, "bachelors_degree": false, "degree_mentioned": true, "degree_preferred": true, "professional_certification_mentioned": false}, "job_experience_in_place_of_education": false, "job_min_salary": null, "job_max_salary": null, "job_salary_currency": null, "job_salary_period": null, "job_highlights": {"Qualifications": ["It also requires strategic knowledge of the cloud computing technology and providers, including Platform as a Service (PaaS), Software as a Service (SaaS), and/or Infrastructure as a Service (IaaS), and the skills to configure those clouds to fit company needs", "A Bachelor\u2019s or Master\u2019s degree in Computer Science, Engineering, Statistics, or a related field, with a specialization in machine learning, artificial intelligence, or data science", "3-5 years of relevant experience in AI/ML, with a proven track record in applying machine learning techniques to real-world problems", "Proficient in programming languages such as Python, R, or Java", "Expertise in machine learning frameworks (e.g., TensorFlow, PyTorch) and libraries (e.g., scikit-learn, NLTK)", "Advanced knowledge of machine learning algorithms, including supervised and unsupervised learning, deep learning, NLP, and predictive modeling", "Experience with Retrieval-Augmented Generation (RAG) for enhancing language models with external knowledge sources", "Demonstrated experience in fine-tuning pre-trained models on domain-specific data to improve performance and accuracy", "Hands-on experience with Large Language Models like GPT-3 or GPT-4, including using APIs like ChatGPT for integration into applications or services", "Experience in configuring and managing self-hosted LLMs such as LLAMA, including setup, maintenance, and optimization for specific use cases", "Data Analytics and Processing Skills:", "Advanced Data Handling: Exceptional skills in managing, cleaning, and preprocessing large and complex datasets using advanced SQL techniques for complex queries, and expertise in using Python's Pandas library for data manipulation and analysis", "Data Processing Frameworks: Proficiency in using big data processing frameworks like Apache Spark, which enables handling of large-scale data processing and analytics over distributed systems", "Econometrics and Statistical Modeling: Deep understanding of econometrics methods, including time-series analysis, regression models, and hypothesis testing, to analyze economic data", "Familiarity with statistical modeling techniques and their application in real-world scenarios, using tools like R or Python\u2019s statistical libraries", "Quantitative Methods: Expertise in applying quantitative methods like linear programming, optimization techniques, and probability theory in solving complex problems", "Excellent communication skills to explain complex AI/ML concepts to non-technical stakeholders and collaborate effectively within the organization", "Strong analytical and problem-solving skills, with an ability to think creatively to provide innovative solutions to complex problems", "Knowledge of ethical considerations in AI, and compliance with legal and regulatory standards, especially in handling sensitive data in areas like healthcare and finance", "This includes familiarity with various service models such as Platform as a Service (PaaS), Software as a Service (SaaS), and Infrastructure as a Service (IaaS)", "Cloud Configuration Skills: Proven ability to configure cloud environments according to company needs, ensuring efficient and secure utilization of cloud resources", "This includes setting up scalable and robust cloud infrastructures, optimizing cloud services for cost and performance, and ensuring compliance with data protection and privacy standards", "Experience with Major Cloud Providers: Hands-on experience with leading cloud platforms such as Azure, Amazon Web Services (AWS), and Google Cloud Platform (GCP)", "This includes deploying and managing applications and services, utilizing cloud-native AI/ML tools, and integrating cloud services with on-premise systems", "Business and IT Collaboration: Strong analytical skills to understand and capture big data and data analytics requirements from business users", "Ability to work closely with business experts, IT teams, and vendors to align cloud solutions with business objectives", "Knowledge of cloud security principles and practices, as well as experience in ensuring compliance with regulatory requirements in a cloud environment", "Candidate must be able to submit verification of his/her legal right to work in the U.S., without company sponsorship"], "Responsibilities": ["Director of Information Technology & Expert Solutions", "This role interfaces with leaders and designees of Expert Communities (practices) throughout the firm", "Additionally, this role would interface heavily with internal IT staff as well as IT business partners", "Engage closely with business users and other members of the Expert Solutions team to assess and define AI/ML and big data analytics requirements", "Utilize a deep understanding of AI/ML applications to translate business needs into technical solutions", "Development of Advanced Analytics and ML Models:", "Create and demonstrate sophisticated analytics programs and machine learning models to address complex business challenges", "Apply statistical methods and data-driven techniques to uncover insights and drive business decisions", "Integrate new AI/ML software and data management technologies into current business and data workflows", "Assist the transition and adoption of new technologies by providing technical guidance and support", "Building and Managing Data Systems and ML Pipelines:", "Design and build efficient data systems and pipelines optimized for machine learning, supporting business users in data ingestion, organization, and storage", "Implement tools and processes for managing large-scale datasets used in AI/ML projects", "Development and Maintenance of Data and AI Architectures:", "Develop, construct, test, and maintain architectures that support data science and machine learning projects", "Regularly review and realign architectures to ensure they meet evolving business requirements and industry best practices", "Conduct ongoing research to stay abreast of the latest advancements in AI/ML tools and technologies", "Evaluate and recommend tools that enhance the organization\u2019s AI/ML capabilities", "Vendor and Consulting Firm Engagement for AI/ML Solutions:", "Assist in the selection and management of external vendors and consulting firms for AI/ML-related projects", "Guide and oversee external partners in the evaluation and implementation of AI/ML solutions, ensuring alignment with business objectives", "Ensuring Compliance and Ethical AI Practices:", "Adhere to data privacy and security regulations", "Promote ethical AI practices in all machine learning and data analytics projects", "Healthcare: Knowledge of healthcare systems, electronic health records (EHR), patient data analysis, and application of AI for predictive diagnostics, treatment personalization, and drug discovery", "Litigation and Legal Analytics: Familiarity with the legal domain, including litigation processes, document analysis, and the use of AI for case prediction, legal research, and contract analysis", "Project Management and Teamwork Skills:", "Dedication to staying updated with the latest developments in AI/ML, particularly in areas like RAG, fine-tuning, and LLMs", "Cross-Platform Integration: Skills in integrating various cloud services and platforms to create cohesive and efficient systems that leverage the strengths of each cloud provider"], "Benefits": ["Salary Range: 115-160k"]}, "job_job_title": "Engineer", "job_posting_language": "en", "job_onet_soc": "15111100", "job_onet_job_zone": "5", "job_naics_code": "541613", "job_naics_name": "Marketing Consulting Services"}