{"job_id": "mQ4k3AAdhRc53rl-AAAAAA==", "employer_name": "TrustPoint HCM", "employer_logo": null, "employer_website": null, "employer_company_type": null, "job_publisher": "Salary.com", "job_employment_type": "FULLTIME", "job_title": "Business Development Manager", "job_apply_link": "https://www.salary.com/job/trustpoint-hcm/business-development-manager/j202311040648567536664", "job_apply_is_direct": false, "job_apply_quality_score": 0.6384, "apply_options": [{"publisher": "Salary.com", "apply_link": "https://www.salary.com/job/trustpoint-hcm/business-development-manager/j202311040648567536664", "is_direct": false}], "job_description": "Overview\n\nTrustPoint HCM is a leading provider of Human Capital Management (HCM), Payroll, and Timekeeping solutions. We specialize in helping businesses of all sizes streamline their HR and payroll processes, improve employee management, and enhance workforce productivity. Our technology platforms and dedicated team support clients across the USA.\n\nAs the Business Development Manager for TrustPoint, you will play a crucial role in driving new clients and revenue growth for all products and services offered by our Company. Under the President\u2019s direction, you will be responsible for identifying and cultivating relationships with potential new clients. Your goals and variable compensation will be based on expanding our client and revenue base.\n\nResponsibilities\n\nHow You Will Make an Impact\n\u2022 Prospecting & Lead Generation \u2013 Identify and target potential customers that meet our ICP (Ideal Customer Profile) through market research, cold calling, and other lead generation techniques.\n\u2022 Consultative Selling \u2013 As you engage with prospects, understanding their needs as it relates to the services offered by TrustPoint. This would include gathering and documenting information into our CRM platform such as current vendor(s) they are working with, their pain points, things that are most important to them when they consider switching vendors. Based on the information you gather; the next step would be presenting TrustPoint solutions that meet their needs / stated requirements. Your ability to provide product demonstrations as well as articulating the unique benefits of our services is an important part of this role.\n\u2022 Relationship Building \u2013 Knowing that the \u201cFortune is in the Follow Up,\u201d we expect you to have proven experience in developing strong business relationships with prospects throughout the sales process. This could include forging relationships with influencers and referral sources as well. Your ability to organize and manage many active prospects is crucial, understanding that the sales cycle for some prospects could be one year or longer.\n\u2022 Closing Sales \u2013 Handling brush-offs and objections leading to closed sales, bringing in new clients joining the roster of satisfied TrustPoint clients. Lead negotiations aligned with our pricing parameters. Meet or exceed agreed-upon revenue targets.\n\u2022 Product Knowledge \u2013 Bring to the table knowledge of our industry and each of the services offered, those being HCM, Payroll, and Timekeeping. Remain up to date with industry trends, competitors, and pricing information gained from your prospect engagement.\n\u2022 Collaboration \u2013 Work with the TrustPoint leadership team providing feedback and input on what is working, what is not, and ideas to meet revenue and new client goals.\n\nQualifications\n\nWhat You Need to Succeed\n\u2022 Proven record in B2B sales in the HCM, Payroll, and Timekeeping industry required.\n\u2022 Strong understanding of HR and payroll processes.\n\u2022 Strong communication, prospect management, negotiation, and presentation skills.\n\u2022 Driven, self-motivated, and results oriented.\n\u2022 Ability to work independently.\n\u2022 Experience with CRM platforms, email, and other prospecting tools such as LinkedIn.\n\u2022 TrustPoint uses ZOHO, experience with this CRM would be an added plus!\n\u2022 Bachelor\u2019s degree in business, Marketing, or a related field.\n\nOur Benefits\n\u2022 Competitive base salary and variable compensation (commissions & bonuses).\n\u2022 Comprehensive benefits package, including healthcare, dental, and retirement plan.\n\u2022 Ongoing training and professional development.\n\u2022 Hybrid work \u2013 although you are welcome to work in our Exton, PA office, we expect weekly in-office meetings with the balance of your time working remotely at your option.\n\u2022 Access to the CEO and leadership team at TrustPoint, each available to assist with helping you win at your role in sales!\n\nOMNI is honored to be retained in this search. We appreciate your referrals to professionals who may have an interest in this outstanding opportunity. Formal interest accepted through the OMNI Executive Career Portal. Please direct all inquiries to:\n\nOMNI Human Resource Management\n\nAnna Robinson, Senior Consultant \u2013 arobinson@omnihrm.com | 913-653-8089\n\nOMNI and our clients are Equal Opportunity Employers and seek diversity in candidates for employment. EEO Employer W/M/Vet/Disabled/Sexual Orientation/Gender Identity.", "job_is_remote": false, "job_posted_at_timestamp": 1699142400, "job_posted_at_datetime_utc": "2023-11-05T00:00:00.000Z", "job_city": "Exton", "job_state": "PA", "job_country": "US", "job_latitude": 40.03258, "job_longitude": -75.62746, "job_benefits": ["dental_coverage", "health_insurance", "retirement_savings"], "job_google_link": "https://www.google.com/search?gl=us&hl=en&rciv=jb&q=manager+of+business+development&start=40&ibp=htl;jobs#fpstate=tldetail&htivrt=jobs&htiq=manager+of+business+development&htidocid=mQ4k3AAdhRc53rl-AAAAAA%3D%3D", "job_offer_expiration_datetime_utc": "2024-11-02T00:00:00.000Z", "job_offer_expiration_timestamp": 1730505600, "job_required_experience": {"no_experience_required": false, "required_experience_in_months": null, "experience_mentioned": true, "experience_preferred": true}, "job_required_skills": null, "job_required_education": {"postgraduate_degree": false, "professional_certification": false, "high_school": false, "associates_degree": false, "bachelors_degree": false, "degree_mentioned": true, "degree_preferred": true, "professional_certification_mentioned": false}, "job_experience_in_place_of_education": false, "job_min_salary": null, "job_max_salary": null, "job_salary_currency": null, "job_salary_period": null, "job_highlights": {"Qualifications": ["Proven record in B2B sales in the HCM, Payroll, and Timekeeping industry required", "Strong understanding of HR and payroll processes", "Strong communication, prospect management, negotiation, and presentation skills", "Driven, self-motivated, and results oriented", "Ability to work independently", "Experience with CRM platforms, email, and other prospecting tools such as LinkedIn", "TrustPoint uses ZOHO, experience with this CRM would be an added plus!", "Bachelor\u2019s degree in business, Marketing, or a related field"], "Responsibilities": ["As the Business Development Manager for TrustPoint, you will play a crucial role in driving new clients and revenue growth for all products and services offered by our Company", "Under the President\u2019s direction, you will be responsible for identifying and cultivating relationships with potential new clients", "Your goals and variable compensation will be based on expanding our client and revenue base", "Prospecting & Lead Generation \u2013 Identify and target potential customers that meet our ICP (Ideal Customer Profile) through market research, cold calling, and other lead generation techniques", "Consultative Selling \u2013 As you engage with prospects, understanding their needs as it relates to the services offered by TrustPoint", "This would include gathering and documenting information into our CRM platform such as current vendor(s) they are working with, their pain points, things that are most important to them when they consider switching vendors", "Based on the information you gather; the next step would be presenting TrustPoint solutions that meet their needs / stated requirements", "Your ability to provide product demonstrations as well as articulating the unique benefits of our services is an important part of this role", "This could include forging relationships with influencers and referral sources as well", "Closing Sales \u2013 Handling brush-offs and objections leading to closed sales, bringing in new clients joining the roster of satisfied TrustPoint clients", "Collaboration \u2013 Work with the TrustPoint leadership team providing feedback and input on what is working, what is not, and ideas to meet revenue and new client goals"], "Benefits": ["Competitive base salary and variable compensation (commissions & bonuses)", "Comprehensive benefits package, including healthcare, dental, and retirement plan", "Ongoing training and professional development", "Hybrid work \u2013 although you are welcome to work in our Exton, PA office, we expect weekly in-office meetings with the balance of your time working remotely at your option", "Access to the CEO and leadership team at TrustPoint, each available to assist with helping you win at your role in sales!"]}, "job_job_title": "Development manager", "job_posting_language": "en", "job_onet_soc": "11202100", "job_onet_job_zone": "4"}