{"job_id": "dvZ9M30zfSaWlmkaAAAAAA==", "employer_name": "Employee Benefits Corporation", "employer_logo": null, "employer_website": "http://www.ebconline.co.uk", "employer_company_type": null, "job_publisher": "Milwaukee Jobs", "job_employment_type": "FULLTIME", "job_title": "Regional Sales Director", "job_apply_link": "https://www.milwaukeejobs.com/job/detail/78182234/Regional-Sales-Director", "job_apply_is_direct": false, "job_apply_quality_score": 0.5778, "apply_options": [{"publisher": "Milwaukee Jobs", "apply_link": "https://www.milwaukeejobs.com/job/detail/78182234/Regional-Sales-Director", "is_direct": false}, {"publisher": "Wisconsin Jobs - Tarta.ai", "apply_link": "https://wisconsin.tarta.ai/j/2MdW1I0BcRajQcTjWzXW0224-regional-sales-director-in-madison-wisconsin-at-employee-benefits-corporation", "is_direct": false}], "job_description": "Employee Benefits Corporation is hiring for Regional Sales Directors to help grow our business in the Upper Midwest and Mid-Atlantic regions. The Regional Sales Director works closely with brokers, agencies, carriers, employers, professional organizations, community organizations and contractors to promote and sell Employee Benefits Corporation\u2019s suite of products. This position establishes and fosters ongoing and trusted working relationships with the broker distribution channel and clients. The Regional Sales Director ensures profitable growth in sales and revenue within the assigned region by achieving established goals and assists in the operational administration of successful onboarding.\n\nResponsibilities Include:\n\u2022 Prospect and develop clients in the assigned market area\n\u2022 Consult with prospective brokers, employers, carriers and referral sources to design benefit plan solutions that include the products and services offered by Employee Benefits Corporation\n\u2022 Establish and foster working relationships with external clients and brokers, developing and sustaining a growing prospect pipeline\n\u2022 Represent company at industry events and tradeshows\n\u2022 Develop written responses to requests for proposals\n\u2022 Prepare service agreements\n\u2022 Promote and cross sell additional products and services to clients and brokers\n\u2022 Maintain and proactively manager client communications, sales activities and data within CRM database\n\nQualifications:\n\u2022 Minimum 5 years\u2019 experience selling through the broker channel\n\u2022 Must have established broker/client relationships in the Mid-Atlantic or Upper Midwest region of the United States\n\u2022 Sales experience in health experience industry\n\u2022 Prior experience in developing and implementing a business development plan\n\u2022 Exceptional relationship building skills with customer focus mindset\n\u2022 Demonstrated effective verbal and written communication skills\n\u2022 Strong organizational and time management skills\n\u2022 Intermediate proficiency with Microsoft Word, Excel, PowerPoint and Outlook\n\u2022 Experience utilizing CRM systems\n\u2022 Familiarity with training, conferencing, and virtual meeting technologies\n\u2022 Ability and willingness to travel frequently to client sites, meetings or conferences throughout the year that may require overnight stays\n\u2022 Possession of a valid driver\u2019s license and access to reliable transportation\n\nWe offer:\n\u2022 A friendly, collaborative team environment\n\u2022 A competitive compensation and benefits package\n\u2022 Opportunities for personal and professional growth\n\u2022 Flexible scheduling to encourage and support a healthy work-life balance\n\nMore About Us:\n\nEmployee Benefits Corporation administers a variety of employee benefits, from IRS-approved, tax-advantaged plans to COBRA and state-regulated continuation administration through informative education materials, dedicated reporting, creative plan design and expert customer support. We work with benefit brokers and consultants, employers and HR administrators, and benefit plan participants to offer top-notch workplace benefits and customer service.\n\nEmployee Benefits Corporation is an Equal Opportunity Employer. Qualified applicants will receive consideration for employment without regard to race, color, religion, sex, national origin, sexual orientation, gender identity, disability or protected veteran status. Our affirmative action program is available to any applicant or employee upon request.\n\nIf you need an accommodation as part of the employment process, please contact Human Resources via email at HumanResources@ebcflex.com or via phone at (608) 831-8445.\nWe are an equal-opportunity employer.", "job_is_remote": false, "job_posted_at_timestamp": 1710115200, "job_posted_at_datetime_utc": "2024-03-11T00:00:00.000Z", "job_city": "Minneapolis", "job_state": "MN", "job_country": "US", "job_latitude": 44.977753, "job_longitude": -93.26501, "job_benefits": ["health_insurance", "retirement_savings"], "job_google_link": "https://www.google.com/search?gl=us&hl=en&rciv=jb&q=sales+director&start=30&ibp=htl;jobs#fpstate=tldetail&htivrt=jobs&htiq=sales+director&htidocid=dvZ9M30zfSaWlmkaAAAAAA%3D%3D", "job_offer_expiration_datetime_utc": null, "job_offer_expiration_timestamp": null, "job_required_experience": {"no_experience_required": false, "required_experience_in_months": 60, "experience_mentioned": true, "experience_preferred": false}, "job_required_skills": null, "job_required_education": {"postgraduate_degree": false, "professional_certification": false, "high_school": false, "associates_degree": false, "bachelors_degree": false, "degree_mentioned": false, "degree_preferred": false, "professional_certification_mentioned": false}, "job_experience_in_place_of_education": false, "job_min_salary": null, "job_max_salary": null, "job_salary_currency": null, "job_salary_period": null, "job_highlights": {"Qualifications": ["Minimum 5 years\u2019 experience selling through the broker channel", "Must have established broker/client relationships in the Mid-Atlantic or Upper Midwest region of the United States", "Sales experience in health experience industry", "Prior experience in developing and implementing a business development plan", "Exceptional relationship building skills with customer focus mindset", "Demonstrated effective verbal and written communication skills", "Strong organizational and time management skills", "Intermediate proficiency with Microsoft Word, Excel, PowerPoint and Outlook", "Experience utilizing CRM systems", "Familiarity with training, conferencing, and virtual meeting technologies", "Ability and willingness to travel frequently to client sites, meetings or conferences throughout the year that may require overnight stays", "Possession of a valid driver\u2019s license and access to reliable transportation"], "Responsibilities": ["This position establishes and fosters ongoing and trusted working relationships with the broker distribution channel and clients", "The Regional Sales Director ensures profitable growth in sales and revenue within the assigned region by achieving established goals and assists in the operational administration of successful onboarding", "Prospect and develop clients in the assigned market area", "Consult with prospective brokers, employers, carriers and referral sources to design benefit plan solutions that include the products and services offered by Employee Benefits Corporation", "Establish and foster working relationships with external clients and brokers, developing and sustaining a growing prospect pipeline", "Represent company at industry events and tradeshows", "Develop written responses to requests for proposals", "Prepare service agreements", "Promote and cross sell additional products and services to clients and brokers", "Maintain and proactively manager client communications, sales activities and data within CRM database"], "Benefits": ["A friendly, collaborative team environment", "A competitive compensation and benefits package", "Opportunities for personal and professional growth", "Flexible scheduling to encourage and support a healthy work-life balance"]}, "job_job_title": "Sales director", "job_posting_language": "en", "job_onet_soc": "11202200", "job_onet_job_zone": "4"}