{"job_id": "bgQdIp8ZZsuyC_5uAAAAAA==", "employer_name": "Cognitiv", "employer_logo": "https://encrypted-tbn0.gstatic.com/images?q=tbn:ANd9GcTvbWBI5zt66nqml9GRt5G0gy-lzcVVTIELvoz3&s=0", "employer_website": null, "employer_company_type": null, "job_publisher": "LinkedIn", "job_employment_type": "FULLTIME", "job_title": "Staff Machine Learning Research Scientist", "job_apply_link": "https://www.linkedin.com/jobs/view/staff-machine-learning-research-scientist-at-cognitiv-3860526857", "job_apply_is_direct": false, "job_apply_quality_score": 0.6311, "apply_options": [{"publisher": "LinkedIn", "apply_link": "https://www.linkedin.com/jobs/view/staff-machine-learning-research-scientist-at-cognitiv-3860526857", "is_direct": false}], "job_description": "Overview\n\nAt Cognitiv, we harness deep learning AI to craft custom algorithms that precisely and effectively predict consumer purchase behavior. Understanding that each marketer's goals are distinct, we developed NeuralMind, a deep learning platform designed for the automatic construction of custom algorithms. These algorithms account for the user, context, message, and campaign objectives. Our approach merges deterministic data with sophisticated processing techniques, enabling continuous training of these algorithms to optimize our clients\u2019 key performance indicators (KPIs) and autonomously drive marketing performance across the full funnel at scale.\n\nDescription\n\nWe are seeking a Staff Machine Learning Research Scientist with specialized expertise in advanced deep learning architectures, feature enhancement, and Large Language Model (LLM) exploration. Join our seasoned adtech research science team and play a pivotal role in advancing the landscape of real-time bidding (RTB) algorithms and embedding LLM technology in adtech. Your role involves leading the development and optimization of robust, end-to-end training pipelines, significantly advancing our algorithmic approaches. This position is perfect for a deep learning enthusiast eager to leverage innovative technologies, revolutionize feature capabilities and model architectures, and tap into the potential of LLMs to reshape the adtech industry. If you are passionate about thriving in a fast-paced environment and eager to tackle complex challenges in adtech, we welcome you to our team of experts in this transformative role.\n\nThis position can be located in either Bellevue, WA or Berkeley, CA with a hybrid work schedule of 3 days in office (Mon/Tue/Wed) and 2 days remote (Thursday/Friday).\n\nCore Responsibilities\n\n\u25cf Develop and implement cutting-edge deep learning architectures aimed at boosting the performance and innovation of AdTech solutions at Cognitiv.\n\n\u25cf Stay at the forefront of Large Language Model (LLM) research, applying new findings to enhance ad targeting, real-time bidding (RTB) efficiency, and audience relevance in our machine learning models and algorithms.\n\n\u25cf Lead the development and refinement of advanced Machine Learning tools and methodologies at Cognitiv, adhering to and setting best practices in coding and engineering. Focus on designing and implementing sophisticated training, deployment, and monitoring pipelines to address complex challenges within the AdTech framework, thereby improving the efficiency and scalability of models.\n\n\u25cf Influence technical decision-making and research prioritization within Cognitiv, effectively communicating complex concepts and delivering persuasive, data-driven presentations. Manage multiple research initiatives, coordinating with diverse internal and external teams.\n\n\u25cf Drive strategic decision-making and lead significant segments of the AdTech Research roadmap, guiding high-impact ML projects. Mentor and develop top talent within the research team, fostering a culture of excellence and continuous learning, while understanding and communicating the trade-offs between technical rigor and strategic market impact.\n\nRequirements\n\n\u25cf Master's or Ph.D. in Computer Science, Statistics, Electrical Engineering, or a related field.\n\n\u25cf 5+ years of industry-level Python programming experience.\n\n\u25cf Expertise in deep learning architectures (e.g., transformers), frameworks (e.g., PyTorch), and related libraries.\n\n\u25cf Exhibit expertise in a wide array of machine learning techniques (e.g., xgboost, PCA).\n\n\u25cf Experience with Large Language Models.\n\n\u25cf Knowledge of distributed computing, cloud platforms, and big data technologies.\n\n\u25cf Proficiency in software engineering principles, algorithms, and data structures.\n\n\u25cf Excellent written and verbal communication, organizational, and negotiation skills.\n\nPreferred Qualifications\n\n\u25cf Prior experience in AdTech and RTB systems.\n\n\u25cf Strong C++ programming skills are a significant advantage.\n\nSalary\n\u2022 $230,000-$260,000 Base Salary + Equity\n\nActual compensation is based on multiple factors that are unique to each candidate, including and not limited to job-related knowledge, level of relevant experience, education and skills. Base salary is just one component of your total rewards package at Cognitiv. Employees are eligible for equity and various benefits.\n\nHere are some of the many benefits that our employees receive:\n\n\u2022 Medical, Dental and Vision coverage, including some plans that are 100% employer paid\n\n\u2022 12 weeks paid parental leave\n\n\u2022 Unlimited PTO\n\n\u2022 Hybrid work model\n\n\u2022 Lunch reimbursement\n\n\u2022 Fitness reimbursement\n\n\u2022 Cell phone reimbursement\n\n\u2022 401(k) plan\n\n\u2022 Employee Assistance Program\n\n\u2022 Pre-tax commuter benefits\n\nCognitiv has been revolutionizing the ad tech space for the last 7 years as the only programmatic buying platform to leverage Deep Learning in real-time. We use Deep Learning (the most sophisticated machine learning) to build custom algorithms for digital marketers to help grow their customer base. We have seen explosive growth and are looking for talented people who are looking to affect change in a rapidly growing organization and industry to join the team.\n\nCognitiv is an equal opportunity employer. We do not discriminate on the basis of race, color, religion, marital status, age, national origin, ancestry, physical or mental disability, medical condition, pregnancy, genetic information, gender, sexual orientation, gender identity or expression, veteran status, or any other status protected under federal, state, or local law.", "job_is_remote": false, "job_posted_at_timestamp": 1710772595, "job_posted_at_datetime_utc": "2024-03-18T14:36:35.000Z", "job_city": null, "job_state": "WA", "job_country": "US", "job_latitude": 47.606102, "job_longitude": -122.332054, "job_benefits": ["health_insurance", "dental_coverage", "retirement_savings", "paid_time_off"], "job_google_link": "https://www.google.com/search?gl=us&hl=en&rciv=jb&q=machine+learning+specialist&start=10&ibp=htl;jobs#fpstate=tldetail&htivrt=jobs&htiq=machine+learning+specialist&htidocid=bgQdIp8ZZsuyC_5uAAAAAA%3D%3D", "job_offer_expiration_datetime_utc": "2024-04-17T14:36:34.000Z", "job_offer_expiration_timestamp": 1713364594, "job_required_experience": {"no_experience_required": false, "required_experience_in_months": 60, "experience_mentioned": true, "experience_preferred": false}, "job_required_skills": null, "job_required_education": {"postgraduate_degree": false, "professional_certification": false, "high_school": false, "associates_degree": false, "bachelors_degree": true, "degree_mentioned": true, "degree_preferred": false, "professional_certification_mentioned": false}, "job_experience_in_place_of_education": false, "job_min_salary": null, "job_max_salary": null, "job_salary_currency": null, "job_salary_period": null, "job_highlights": {"Qualifications": ["Master's or Ph.D. in Computer Science, Statistics, Electrical Engineering, or a related field", "5+ years of industry-level Python programming experience", "Expertise in deep learning architectures (e.g., transformers), frameworks (e.g., PyTorch), and related libraries", "Exhibit expertise in a wide array of machine learning techniques (e.g., xgboost, PCA)", "Experience with Large Language Models", "Knowledge of distributed computing, cloud platforms, and big data technologies", "Proficiency in software engineering principles, algorithms, and data structures", "Excellent written and verbal communication, organizational, and negotiation skills"], "Responsibilities": ["Develop and implement cutting-edge deep learning architectures aimed at boosting the performance and innovation of AdTech solutions at Cognitiv", "Stay at the forefront of Large Language Model (LLM) research, applying new findings to enhance ad targeting, real-time bidding (RTB) efficiency, and audience relevance in our machine learning models and algorithms", "Lead the development and refinement of advanced Machine Learning tools and methodologies at Cognitiv, adhering to and setting best practices in coding and engineering", "Focus on designing and implementing sophisticated training, deployment, and monitoring pipelines to address complex challenges within the AdTech framework, thereby improving the efficiency and scalability of models", "Influence technical decision-making and research prioritization within Cognitiv, effectively communicating complex concepts and delivering persuasive, data-driven presentations", "Manage multiple research initiatives, coordinating with diverse internal and external teams", "Drive strategic decision-making and lead significant segments of the AdTech Research roadmap, guiding high-impact ML projects", "Mentor and develop top talent within the research team, fostering a culture of excellence and continuous learning, while understanding and communicating the trade-offs between technical rigor and strategic market impact"], "Benefits": ["$230,000-$260,000 Base Salary + Equity", "Actual compensation is based on multiple factors that are unique to each candidate, including and not limited to job-related knowledge, level of relevant experience, education and skills", "Base salary is just one component of your total rewards package at Cognitiv", "Employees are eligible for equity and various benefits", "Medical, Dental and Vision coverage, including some plans that are 100% employer paid", "12 weeks paid parental leave", "Unlimited PTO", "Hybrid work model", "Lunch reimbursement", "Fitness reimbursement", "Cell phone reimbursement", "401(k) plan", "Employee Assistance Program", "Pre-tax commuter benefits"]}, "job_job_title": "Research scientist", "job_posting_language": "en", "job_onet_soc": "15111100", "job_onet_job_zone": "5"}