{"job_id": "HQ8bHyOVfiv-OGBzAAAAAA==", "employer_name": "Oracle", "employer_logo": "https://upload.wikimedia.org/wikipedia/commons/thumb/5/50/Oracle_logo.svg/2560px-Oracle_logo.svg.png", "employer_website": "http://www.oracle.com", "employer_company_type": "Information", "job_publisher": "Jooble", "job_employment_type": "FULLTIME", "job_title": "Business Development Consultant_Burlington", "job_apply_link": "https://jooble.org/jdp/2998121972179356621", "job_apply_is_direct": false, "job_apply_quality_score": 0.5539, "apply_options": [{"publisher": "Jooble", "apply_link": "https://jooble.org/jdp/2998121972179356621", "is_direct": false}], "job_description": "Job Description\n\nOracle Class Of Business Development Consultant Program\n\nis focused on enabling you with the needed sales skills for success in the business development role and your future career in sales. The program offers the opportunity to achieve multiple levels of career progression with increasing levels of responsibility within the Oracle sales organization. Progression is based on an individual\u2019s ability to meet/exceed sales objectives, tenure, and location flexibility. The program is just the start of your long-term sales career with Oracle!\n\nAs a\n\nBusiness Development Consultant\n\nyour initial training consists of a multi-week, comprehensive program where new hires begin to learn consultative selling skills and Oracle solutions. This serves as the base of new hire learning and provides you with the tools to make an instant impact as part of a highly collaborative sales team. Oracle provides continuous training and coaching throughout your career.\n\nResponsibilities\n\nPreferred Skills/Experience\n\nWhat You\u2019ll Do\n\nA challenging, exciting role that will test your sales skills, tenacity and hunting skills, strategic thinking capabilities, ability to remain focused, and follow-through. You will be provided the tools, training, coaching, and people resources to help you be successful. Your responsibilities will include the following: generate demand for Oracle solutions through social selling and outbound cold calling, qualify Oracle prospects, produce quality leads for the Oracle Sales Team, and identify/drive product expansion opportunities via high-value relationships with existing customers.\n\nJoin a fun workplace where you\u2019ll enhance your skills and build a solid professional foundation. As a Business Development Consultant you will:\n\nCollaborate and coordinate with the sales team on territory and account strategy, demand generation activities, and desired results\n\nBuild sales pipeline using social selling, and\n\ncold calling\n\nmethodologies\n\nEnsure all data is properly maintained and updated in the Oracle CRM application\n\nGain in-depth knowledge of Oracle technologies, territories, accounts, competitors, industry trends, etc.\n\nDevelop strong customer relationships to identify and drive product expansion/upsell opportunities\n\nWhat You\u2019ll Bring\n\nLet\u2019s see what you can achieve when you dare to be yourself. What we are looking for:\n\nMotivated and eager to build a long-term career in Sales\n\nBachelor's degree with a GPA of 3.0 or higher preferred\n\n1-3 years of work experience\n\nStrong communication skills both written and verbal\n\nCompetitive, persuasive, professional, and confident leader\n\nOrganized, possesses great time management skills\n\nProblem solver; interest in technology, process improvement, and customer interaction\n\nGoal Oriented; able to complete individual goals as well as work in a team environment\n\nAble to demonstrate critical thinking skills to acquire a higher level understanding of the role, processes, technical concepts and, procedures\n\nA high level of initiative\n\nApply Now\n\nCreate the future with us. Apply now.\n\nVisit oracle.com/campus to apply.\n\nAs part of Oracle's standard employment process, candidates will undergo a complete background check prior to an offer being extended. These background checks are conducted by a professional third party firm at no charge to the applicant and include: prior employment verification, education verification, social security trace, criminal background check and motor vehicles records (where required for position).Oracle is an Equal Employment Opportunity Employer. All qualified applicants will receive consideration for employment without regard to race, color, religion, sex, national origin, sexual orientation, gender identity or expression, disability and protected veterans status or any other characteristic protected by law.\n\n_If you are interested in working at Oracle and you have more than 2 years of professional full-time work experience (excluding internships, research and/or teaching assistant roles, and/or military experience), please apply to Oracle\u2019s experienced job openings. For information on currently open positions at Oracle, please visit\n\nDisclaimer:\n\nCertain US customer or client-facing roles may be required to comply with applicable requirements, such as immunization and occupational health mandates.\n\nRange and benefit information provided in this posting are specific to the stated locations only\n\nUS: Hiring Range: from $18.41 to $28.80 per hour; from $38,300 to $59,900 per annum. Eligible for commission with an estimated pay mix of 65/35 - 90/10.\n\nOracle maintains broad salary ranges for its roles in order to account for variations in knowledge, skills, experience, market conditions and locations, as well as reflect Oracle\u2019s differing products, industries and lines of business.\n\nCandidates are typically placed into the range based on the preceding factors as well as internal peer equity.\n\nOracle US offers a comprehensive benefits package which includes the following:\n\nMedical, dental, and vision insurance, including expert medical opinion\n\nShort term disability and long term disability\n\nLife insurance and AD&D\n\nSupplemental life insurance (Employee/Spouse/Child)\n\nHealth care and dependent care Flexible Spending Accounts\n\nPre-tax commuter and parking benefits\n\n401(k) Savings and Investment Plan with company match\n\nPaid time off: Flexible Vacation is provided to all eligible employees assigned to a salaried (non-overtime eligible) position. Accrued Vacation is provided to all other employees eligible for vacation benefits. For employees working at least 35 hours per week, the vacation accrual rate is 13 days annually for the first three years of employment and 18 days annually for subsequent years of employment. Vacation accrual is prorated for employees working between 20 and 34 hours per week. Employees working fewer than 20 hours per week are not eligible for vacation.\n\n11 paid holidays\n\nPaid sick leave: 72 hours of paid sick leave upon date of hire. Refreshes each calendar year. Unused balance will carry over each year up to a maximum cap of 112 hours.\n\nPaid parental leave\n\nAdoption assistance\n\nEmployee Stock Purchase Plan\n\nFinancial planning and group legal\n\nVoluntary benefits including auto, homeowner and pet insurance\n\nAbout Us\n\nAs a world leader in cloud solutions, Oracle uses tomorrow\u2019s technology to tackle today\u2019s problems. True innovation starts with diverse perspectives and various abilities and backgrounds.\n\nWhen everyone\u2019s voice is heard, we\u2019re inspired to go beyond what\u2019s been done before. It\u2019s why we\u2019re committed to expanding our inclusive workforce that promotes diverse insights and perspectives.\n\nWe\u2019ve partnered with industry-leaders in almost every sector\u2014and continue to thrive after 40+ years of change by operating with integrity.\n\nOracle careers open the door to global opportunities where work-life balance flourishes. We offer a highly competitive suite of employee benefits designed on the principles of parity and consistency. We put our people first with flexible medical, life insurance and retirement options. We also encourage employees to give back to their communities through our volunteer programs.\n\nWe\u2019re committed to including people with disabilities at all stages of the employment process. If you require accessibility assistance or accommodation for a disability at any point, let us know by calling View phone number on click.appcast.io, option one.\n\nDisclaimer:\n\nOracle is an Equal Employment Opportunity Employer*. All qualified applicants will receive consideration for employment without regard to race, color, religion, sex, national origin, sexual orientation, gender identity, disability and protected veterans\u2019 status, or any other characteristic protected by law. Oracle will consider for employment qualified applicants with arrest and conviction records pursuant to applicable law.\n\u2022 ** Which includes being a United States Affirmative Action Employer**", "job_is_remote": false, "job_posted_at_timestamp": 1710170517, "job_posted_at_datetime_utc": "2024-03-11T15:21:57.000Z", "job_city": "Sacramento", "job_state": "CA", "job_country": "US", "job_latitude": 38.581573, "job_longitude": -121.4944, "job_benefits": ["health_insurance", "paid_time_off", "retirement_savings", "dental_coverage"], "job_google_link": "https://www.google.com/search?gl=us&hl=en&rciv=jb&q=manager+of+business+development&start=30&ibp=htl;jobs#fpstate=tldetail&htivrt=jobs&htiq=manager+of+business+development&htidocid=HQ8bHyOVfiv-OGBzAAAAAA%3D%3D", "job_offer_expiration_datetime_utc": "2024-04-11T07:38:35.000Z", "job_offer_expiration_timestamp": 1712821115, "job_required_experience": {"no_experience_required": false, "required_experience_in_months": 24, "experience_mentioned": true, "experience_preferred": false}, "job_required_skills": null, "job_required_education": {"postgraduate_degree": false, "professional_certification": false, "high_school": false, "associates_degree": false, "bachelors_degree": false, "degree_mentioned": true, "degree_preferred": false, "professional_certification_mentioned": false}, "job_experience_in_place_of_education": false, "job_min_salary": null, "job_max_salary": null, "job_salary_currency": null, "job_salary_period": null, "job_highlights": {"Qualifications": ["Motivated and eager to build a long-term career in Sales", "1-3 years of work experience", "Strong communication skills both written and verbal", "Competitive, persuasive, professional, and confident leader", "Organized, possesses great time management skills", "Problem solver; interest in technology, process improvement, and customer interaction", "Goal Oriented; able to complete individual goals as well as work in a team environment", "Able to demonstrate critical thinking skills to acquire a higher level understanding of the role, processes, technical concepts and, procedures", "A high level of initiative", "** Which includes being a United States Affirmative Action Employer**"], "Responsibilities": ["is focused on enabling you with the needed sales skills for success in the business development role and your future career in sales", "A challenging, exciting role that will test your sales skills, tenacity and hunting skills, strategic thinking capabilities, ability to remain focused, and follow-through", "You will be provided the tools, training, coaching, and people resources to help you be successful", "Your responsibilities will include the following: generate demand for Oracle solutions through social selling and outbound cold calling, qualify Oracle prospects, produce quality leads for the Oracle Sales Team, and identify/drive product expansion opportunities via high-value relationships with existing customers", "Collaborate and coordinate with the sales team on territory and account strategy, demand generation activities, and desired results", "Build sales pipeline using social selling, and", "Ensure all data is properly maintained and updated in the Oracle CRM application", "Gain in-depth knowledge of Oracle technologies, territories, accounts, competitors, industry trends, etc", "Develop strong customer relationships to identify and drive product expansion/upsell opportunities"], "Benefits": ["US: Hiring Range: from $18.41 to $28.80 per hour; from $38,300 to $59,900 per annum", "Eligible for commission with an estimated pay mix of 65/35 - 90/10", "Medical, dental, and vision insurance, including expert medical opinion", "Short term disability and long term disability", "Life insurance and AD&D", "Supplemental life insurance (Employee/Spouse/Child)", "Health care and dependent care Flexible Spending Accounts", "Pre-tax commuter and parking benefits", "401(k) Savings and Investment Plan with company match", "Paid time off: Flexible Vacation is provided to all eligible employees assigned to a salaried (non-overtime eligible) position", "Accrued Vacation is provided to all other employees eligible for vacation benefits", "For employees working at least 35 hours per week, the vacation accrual rate is 13 days annually for the first three years of employment and 18 days annually for subsequent years of employment", "Vacation accrual is prorated for employees working between 20 and 34 hours per week", "Employees working fewer than 20 hours per week are not eligible for vacation", "11 paid holidays", "Paid sick leave: 72 hours of paid sick leave upon date of hire", "Unused balance will carry over each year up to a maximum cap of 112 hours", "Paid parental leave", "Adoption assistance", "Employee Stock Purchase Plan", "Financial planning and group legal", "Voluntary benefits including auto, homeowner and pet insurance", "We offer a highly competitive suite of employee benefits designed on the principles of parity and consistency"]}, "job_job_title": "Business", "job_posting_language": "en", "job_onet_soc": "41401400", "job_onet_job_zone": null, "job_naics_code": "511210", "job_naics_name": "Software Publishers"}