{"job_id": "U3cr8laDEnc0fBh4AAAAAA==", "employer_name": "Cass Commercial Bank", "employer_logo": "https://www.cassbank.com/wp-content/uploads/2017/09/Cass-Bank-Logo-RGB.png", "employer_website": "http://www.cassbank.com", "employer_company_type": null, "job_publisher": "Ladders", "job_employment_type": "FULLTIME", "job_title": "Director, Business Development", "job_apply_link": "https://www.theladders.com/job/director-business-development-cass-commercial-bank-saint-louis-mo_67519107", "job_apply_is_direct": false, "job_apply_quality_score": 0.5335, "apply_options": [{"publisher": "Ladders", "apply_link": "https://www.theladders.com/job/director-business-development-cass-commercial-bank-saint-louis-mo_67519107", "is_direct": false}], "job_description": "REPORTS TO: President, Cass Commercial Bank\n\nFUNCTION:\n\nThe Director, Business Development, in collaboration with business-line directors, develops, executes, and maintains marketing strategies to meet organizational objectives and support profitable business growth. This position is responsible for the development and execution of the bank's annual marketing plan and budget, as well as leading all marketing efforts including research and development; creation of innovative marketing campaigns; brand management; content development; advertising; event management; website; charitable giving; and marketing automation tools. Additionally, the Director, Business Development is responsible for creating new business lines and will also act as a Sr. Relationship Manager for select key clients.\n\nPRINCIPAL RESPONSIBILITIES AND DUTIES:\n\u2022 Working with the Bank President, Chief Credit Officer, and business-line directors, establishes marketing goals to ensure share of market, profitability of products/services, and deepening of existing client relationships.\n\u2022 Develops and executes quarterly/annual marketing plan and budget in accordance with overall business objectives and goals.\n\u2022 Applies knowledge of the sales process to generate ideas for new content and serves as a point of contact to Relationship Managers for product information.\n\u2022 Develops and maintains relationships with external service providers to facilitate marketing campaigns and overall branding, including copy, design, layout, and production of all content.\n\u2022 Negotiates pricing and proposals with all third-party vendors as needed.\n\u2022 Prepares marketing reports and general updates for management.\n\u2022 Determines the strategy and distribution of charitable giving from the budgeted funds allocated to the bank for such purposes.\n\u2022 Remains fully versed in new marketing tools, techniques and strategies that can be leveraged by the bank to gain competitive advantages in the markets we serve.\n\u2022 Maintains a portfolio of select clients, performing duties of a Sr. Relationship Manager, including processing and servicing loans, conducting complex credit analysis, and providing advice and counsel to clients.\n\u2022 Develops and executes plans to create additional lines of business to increase profitability.\n\u2022 Leads assigned team members to support overall strategy.\n\u2022 Performs special projects as requested.\n\u2022 Other duties as needed or assigned.\n\nSKILLS AND ABILITIES REQUIRED:\n\u2022 High level of accountability; willing to take ownership and solve problems.\n\u2022 Strong desire to work with people and accomplish objectives through the efforts of others.\n\u2022 Team player that understands success rests on helping other to be successful.\n\u2022 Able to motivate others and create a positive work environment where employees feel comfortable discussing issues and concerns.\n\u2022 Experience in sales and marketing systems (Salesforce, Pardot, Word Press, etc.) preferred.\n\u2022 Effective communication skills including excellent listening skills and the ability to communicate professionally with all levels of an organization both verbally and in writing.\n\u2022 A high level of analytical skills to conduct complex and strategic analysis and convey that understanding both internally and with clients.\n\nMINIMUM LEVEL OF PREPARATION AND TRAINING NORMALLY REQUIRED:\n\u2022 A technical level of knowledge normally acquired through completion of advances studies or special developmental/educational executive programs in business administration, finance and marketing or equivalent experience.\n\u2022 5+ years of experience in all aspects of developing and implementing targeted marketing strategies.\n\n3. 10+ years of progressively increasing responsibility for commercial lending including credit underwriting and loan documentation or equivalent experience\n\nEqual Opportunity Employer/Protected Veterans/Individuals with Disabilities\n\nThe contractor will not discharge or in any other manner discriminate against employees or applicants because they have inquired about, discussed, or disclosed their own pay or the pay of another employee or applicant. However, employees who have access to the compensation information of other employees or applicants as a part of their essential job functions cannot disclose the pay of other employees or applicants to individuals who do not otherwise have access to compensation information, unless the disclosure is (a) in response to a formal complaint or charge, (b) in furtherance of an investigation, proceeding, hearing, or action, including an investigation conducted by the employer, or (c) consistent with the contractor's legal duty to furnish information. 41 CFR 60-1.35(c)", "job_is_remote": false, "job_posted_at_timestamp": 1707116758, "job_posted_at_datetime_utc": "2024-02-05T07:05:58.000Z", "job_city": "St. Louis", "job_state": "MO", "job_country": "US", "job_latitude": 38.627003, "job_longitude": -90.1994, "job_benefits": null, "job_google_link": "https://www.google.com/search?gl=us&hl=en&rciv=jb&q=director+of+business+development&start=80&ibp=htl;jobs#fpstate=tldetail&htivrt=jobs&htiq=director+of+business+development&htidocid=U3cr8laDEnc0fBh4AAAAAA%3D%3D", "job_offer_expiration_datetime_utc": null, "job_offer_expiration_timestamp": null, "job_required_experience": {"no_experience_required": false, "required_experience_in_months": null, "experience_mentioned": true, "experience_preferred": true}, "job_required_skills": null, "job_required_education": {"postgraduate_degree": false, "professional_certification": false, "high_school": false, "associates_degree": false, "bachelors_degree": false, "degree_mentioned": false, "degree_preferred": false, "professional_certification_mentioned": false}, "job_experience_in_place_of_education": false, "job_min_salary": 108415, "job_max_salary": 162623, "job_salary_currency": "USD", "job_salary_period": "YEAR", "job_highlights": {"Qualifications": ["High level of accountability; willing to take ownership and solve problems", "Strong desire to work with people and accomplish objectives through the efforts of others", "Team player that understands success rests on helping other to be successful", "Able to motivate others and create a positive work environment where employees feel comfortable discussing issues and concerns", "Effective communication skills including excellent listening skills and the ability to communicate professionally with all levels of an organization both verbally and in writing", "A high level of analytical skills to conduct complex and strategic analysis and convey that understanding both internally and with clients", "A technical level of knowledge normally acquired through completion of advances studies or special developmental/educational executive programs in business administration, finance and marketing or equivalent experience", "5+ years of experience in all aspects of developing and implementing targeted marketing strategies", "10+ years of progressively increasing responsibility for commercial lending including credit underwriting and loan documentation or equivalent experience"], "Responsibilities": ["The Director, Business Development, in collaboration with business-line directors, develops, executes, and maintains marketing strategies to meet organizational objectives and support profitable business growth", "This position is responsible for the development and execution of the bank's annual marketing plan and budget, as well as leading all marketing efforts including research and development; creation of innovative marketing campaigns; brand management; content development; advertising; event management; website; charitable giving; and marketing automation tools", "Additionally, the Director, Business Development is responsible for creating new business lines and will also act as a Sr", "Relationship Manager for select key clients", "Working with the Bank President, Chief Credit Officer, and business-line directors, establishes marketing goals to ensure share of market, profitability of products/services, and deepening of existing client relationships", "Develops and executes quarterly/annual marketing plan and budget in accordance with overall business objectives and goals", "Applies knowledge of the sales process to generate ideas for new content and serves as a point of contact to Relationship Managers for product information", "Develops and maintains relationships with external service providers to facilitate marketing campaigns and overall branding, including copy, design, layout, and production of all content", "Negotiates pricing and proposals with all third-party vendors as needed", "Prepares marketing reports and general updates for management", "Determines the strategy and distribution of charitable giving from the budgeted funds allocated to the bank for such purposes", "Remains fully versed in new marketing tools, techniques and strategies that can be leveraged by the bank to gain competitive advantages in the markets we serve", "Maintains a portfolio of select clients, performing duties of a Sr", "Relationship Manager, including processing and servicing loans, conducting complex credit analysis, and providing advice and counsel to clients", "Develops and executes plans to create additional lines of business to increase profitability", "Leads assigned team members to support overall strategy", "Performs special projects as requested", "Other duties as needed or assigned"]}, "job_job_title": "Director", "job_posting_language": "en", "job_onet_soc": "11202100", "job_onet_job_zone": "4"}