{"job_id": "z0GjO8pFC2ngPqAcAAAAAA==", "employer_name": "CareerBuilder", "employer_logo": null, "employer_website": null, "employer_company_type": null, "job_publisher": "CareerBuilder", "job_employment_type": "FULLTIME", "job_title": "Division 28 Security Consultant Business Development Manager", "job_apply_link": "https://www.careerbuilder.com/job/J3T7XQ6HDYMZQN7KT0C", "job_apply_is_direct": false, "job_apply_quality_score": 0.6552, "apply_options": [{"publisher": "CareerBuilder", "apply_link": "https://www.careerbuilder.com/job/J3T7XQ6HDYMZQN7KT0C", "is_direct": false}, {"publisher": "Learn4Good", "apply_link": "https://www.learn4good.com/jobs/missouri/engineering/2798897244/e/", "is_direct": false}, {"publisher": "Gobimarketing.com", "apply_link": "https://gobimarketing.com/career/job/division-28-security-consultant-business-development-manager-at-allegion-canada-inc-california-mo-R0hQM0pmTThxTHZxUXRraHBVYzl1MlNCclE9PQ==", "is_direct": false}, {"publisher": "Vista Healthcare Supply", "apply_link": "https://vistahealthcaresupply.com/job-listing/job/division-28-security-consultant-business-development-manager-at-allegion-canada-inc-california-mo-VHE1d2pISUNUaURtUFNlWGJxMzM5cTZFRlE9PQ==", "is_direct": false}, {"publisher": "Arcus Industries", "apply_link": "https://arcusindustries.com.au/samples/job/division-28-security-consultant-business-development-manager-at-allegion-canada-inc-california-mo-OTllajNBNFN2RjZPTDlWc28vRmJMdWljVFE9PQ==", "is_direct": false}], "job_description": "Division 28 Security Consultant Business Development Manager page is loaded\n\nDivision 28 Security Consultant Business Development Manager\n\nApply\n\nlocations\n\nRemote, California\n\ntime type\n\nFull time\n\nposted on\n\nPosted 2 Days Ago\n\njob requisition id\n\nJR27956\n\nCreating Peace of Mind by Pioneering Safety and Security\n\nAt Allegion, we help keep the people you know and love safe and secure where they live, work and visit. With more than 30 brands, 11,000+ employees globally and products sold in 130 countries, we specialize in security around the doorway and beyond.\nDivision 28 Security Consultant Business Development Manager-Remote California\n(Territory includes Southern California)\nJob Scope\nThe Business Development Manager DIV28 Security Consultant position will have overall responsibility to develop and implement a comprehensive strategy driving growth with the Division 28 Electronic Security Specifiers and Consultants in the North America market. The roles primary focus includes developing relationships with key influencers for Division 28 specifications, writing Division 28 subsections relevant to Allegion solutions, identifying new opportunities and partnerships for Allegion, and increasing the close ratio of electronics sales into projects initiated through Division 8710\n\nspecifications.\n\nIn addition, this individual will develop relationships with the PACs A&E Security Consulting Teams to drive adoption of Allegion solutions and value-added services.\nWhat You Will Do:\nAssist in the evolution of the existing Division 8 to Division 28 collaboration strategy in an effort to increase program effectiveness and close ratio with Allegion Project and Channel sales teams.\n\nCultivate new relationships with Division 28 security specifiers across the A&E community, coordinate with local RSO.\n\nWrite Division 28 specifications for all relevant subsections while working through the project security consultant or direct with end users.\n\nLead the project response team for large electronics RFPs.\n\nManage and coordinate industry events targeting electronic security specifiers as need for networking, market analysis and prospecting\n\nProvide electronics SME support to existing Allegion specification writers, ACA team, and provide training as necessary\n\nProvide direction at Regional Sales Offices (ESE, ISC & End User Consultants) to enable local support for A&E Security\n\nConsultant/Specifiers\n\nto coordinate efforts for the adoption of both Allegions Electronics portfolio and collaboration within the Overtur Specification Service\n\nPartner with Allegion PACS team to develop and grow the A&E Program through collaboration with the Allegion PACs Partners respective A&E Teams for the adoption of Allegions Electronics portfolio.\n\nLead education efforts for electronic security specifiers encompassing Allegions value-added services and adoption of Schlages Credential and Hardware Open Interoperability Platform.\n\nWhat You Will Need to Succeed:\nBachelors degree in business or related field preferred\n\n5 years writing Division 28 specifications for electronic security preferred\n\nWorking knowledge of new construction and aftermarket distribution business models\n\nWorking knowledge of access control and video management systems\n\nAbility to think strategically and problem solve with entrepreneurial commitment to achieving goals\n\nDemonstrated ability to collaborate with local and strategic sales teams and other Allegion functions\n\nExcellent verbal and written communication skills\n\nDemonstrated experience influencing others with a bias for action\n\nStrong presentation skills required\n\nTravel up to 50%\n\nPreferred Experience & Certifications\nExperience and understanding of Division 8 and Division 27 specifications preferred\n\nExperience with complex access control reader & credential system deployment including high frequency smart & mobile credentials\n\nAbility to create electrical elevation & riser diagrams as required for project specification support\n\nRelevant certifications: PE, CSEIP, PSP, CSPM, CCNA/RCDD, DCDC, CDT\n\nWhy Work for Us?\nAllegion is a Great Place to Grow your Career if:\nYou're seeking a rewarding opportunity that allows you to truly help others. With thousands of employees and customers around the world, theres plenty of room to make an impact. As our values state, this is your business, run with it.\n\nYoure looking for a company that will invest in your professional development. As we grow, we want you to grow with us.\n\nYou want a culture that promotes work-life balance. Our employees enjoy generous paid time off, because at Allegion we recognize that you have a full life outside of work!\n\nWhat Youll Get from Us:\nHealth, dental and vision insurance coverage, helping you be safe, be healthy\n\nUnlimited Paid Time Off\n\nA commitment to your future with a 401K plan, which currently offers a 6% company match and no vesting period\n\nHealth Savings Accounts Tax-advantaged savings account used for healthcare expenses\n\nFlexible Spending Accounts Tax-advantaged spending accounts for healthcare and/or dependent daycare expenses\n\nDisability Insurance Short-Term and Long-Term coverage, paid for by Allegion, provides income replacement for illness or injury\n\nLife Insurance Term life coverage with the option to purchase supplemental coverage\n\nTuition\n\nReimbursement\n\nVoluntary Wellness Program Simply complete wellness activities and earn up to $2,000 in rewards\n\nEmployee Discounts through\n\nPerks at Work\n\nCommunity involvement and opportunities to give back so you can serve others, not yourself\n\nOpportunities to leverage your unique strengths through CliftonStrengths assessment & coaching\n\nCompensation:\n\nThis range is provided by Allegion. Your actual pay will be based on your skills and\n\nexperience.\nThe expected Base Salary Range: $67,800 to $126,000. The actual compensation will be determined based on experience and other factors permitted by law.\n\nBonus Eligible: Yes\n\nApply Today!\nJoin our team of experts today and help us make tomorrows world a safer place!\nNot sure if your experience perfectly aligns with the role?\n\nStudies have shown that some people are less likely to apply to jobs unless they meet every single qualification\n\nand\n\nevery single preferred qualification of a job posting. At Allegion, we are dedicated to building a diverse, inclusive, and authentic workplace. So, if youre excited about this role but your past experience doesnt align perfectly with every item in the job description, we encourage you to apply anyway. You may be just the right candidate for this role.\n#LI-TB1\n#LI-Remote\nWe Celebrate Who We Are!\n\nAllegion is committed to building and maintaining a diverse and inclusive workplace. Together, we embrace all differences and similarities among colleagues, as well as the differences and similarities within the relationships that we foster with customers, suppliers and the communities where we live and work. Whatever your background, experience, race, color, national origin, religion, age, gender, gender identity, disability status, sexual orientation, protected veteran status, or any other characteristic protected by law, we will make sure that you have every opportunity to impress us in your application and the opportunity to give your best at work, not because were required to, but because its the right thing to do. We are also committed to providing accommodations for persons with disabilities. If for any reason you cannot apply through our career site and require an accommodation or assistance, please\n\ncontact our Talent Acquisition Team\n\n.\nAllegion plc, 2023 | Block D, Iveagh Court, Harcourt Road, Dublin 2, Co. Dublin, Ireland\nREGISTERED IN IRELAND WITH LIMITED LIABILITY REGISTERED NUMBER 527370\nAllegion is an equal opportunity and affirmative action employer\nPrivacy Policy\n\nWe believe in anticipating opportunities\nby sharpening our skills\nand finding new answers\nthrough collaboration.\nWe believe in a safer, more secure world.\nWe believe in providing peace of mind.\nWe believe in being true to ourselves and to those\n\n#J-18808-Ljbffr", "job_is_remote": false, "job_posted_at_timestamp": 1709856000, "job_posted_at_datetime_utc": "2024-03-08T00:00:00.000Z", "job_city": "California", "job_state": "MO", "job_country": "US", "job_latitude": 38.62753, "job_longitude": -92.56658, "job_benefits": ["dental_coverage", "paid_time_off", "health_insurance", "retirement_savings"], "job_google_link": "https://www.google.com/search?gl=us&hl=en&rciv=jb&q=business+development+consultant&start=20&ibp=htl;jobs#fpstate=tldetail&htivrt=jobs&htiq=business+development+consultant&htidocid=z0GjO8pFC2ngPqAcAAAAAA%3D%3D", "job_offer_expiration_datetime_utc": "2024-04-07T00:00:00.000Z", "job_offer_expiration_timestamp": 1712448000, "job_required_experience": {"no_experience_required": false, "required_experience_in_months": null, "experience_mentioned": true, "experience_preferred": true}, "job_required_skills": null, "job_required_education": {"postgraduate_degree": false, "professional_certification": false, "high_school": false, "associates_degree": false, "bachelors_degree": false, "degree_mentioned": true, "degree_preferred": true, "professional_certification_mentioned": true}, "job_experience_in_place_of_education": false, "job_min_salary": null, "job_max_salary": null, "job_salary_currency": null, "job_salary_period": null, "job_highlights": {"Qualifications": ["Working knowledge of access control and video management systems", "Ability to think strategically and problem solve with entrepreneurial commitment to achieving goals", "Demonstrated ability to collaborate with local and strategic sales teams and other Allegion functions", "Excellent verbal and written communication skills", "Demonstrated experience influencing others with a bias for action", "Strong presentation skills required", "Travel up to 50%", "Experience with complex access control reader & credential system deployment including high frequency smart & mobile credentials", "Ability to create electrical elevation & riser diagrams as required for project specification support", "Relevant certifications: PE, CSEIP, PSP, CSPM, CCNA/RCDD, DCDC, CDT"], "Responsibilities": ["The Business Development Manager DIV28 Security Consultant position will have overall responsibility to develop and implement a comprehensive strategy driving growth with the Division 28 Electronic Security Specifiers and Consultants in the North America market", "The roles primary focus includes developing relationships with key influencers for Division 28 specifications, writing Division 28 subsections relevant to Allegion solutions, identifying new opportunities and partnerships for Allegion, and increasing the close ratio of electronics sales into projects initiated through Division 8710", "Assist in the evolution of the existing Division 8 to Division 28 collaboration strategy in an effort to increase program effectiveness and close ratio with Allegion Project and Channel sales teams", "Cultivate new relationships with Division 28 security specifiers across the A&E community, coordinate with local RSO", "Write Division 28 specifications for all relevant subsections while working through the project security consultant or direct with end users", "Lead the project response team for large electronics RFPs", "Manage and coordinate industry events targeting electronic security specifiers as need for networking, market analysis and prospecting", "Provide electronics SME support to existing Allegion specification writers, ACA team, and provide training as necessary", "Provide direction at Regional Sales Offices (ESE, ISC & End User Consultants) to enable local support for A&E Security", "to coordinate efforts for the adoption of both Allegions Electronics portfolio and collaboration within the Overtur Specification Service", "Partner with Allegion PACS team to develop and grow the A&E Program through collaboration with the Allegion PACs Partners respective A&E Teams for the adoption of Allegions Electronics portfolio", "Lead education efforts for electronic security specifiers encompassing Allegions value-added services and adoption of Schlages Credential and Hardware Open Interoperability Platform"], "Benefits": ["You want a culture that promotes work-life balance", "Our employees enjoy generous paid time off, because at Allegion we recognize that you have a full life outside of work!", "Health, dental and vision insurance coverage, helping you be safe, be healthy", "Unlimited Paid Time Off", "A commitment to your future with a 401K plan, which currently offers a 6% company match and no vesting period", "Health Savings Accounts Tax-advantaged savings account used for healthcare expenses", "Flexible Spending Accounts Tax-advantaged spending accounts for healthcare and/or dependent daycare expenses", "Disability Insurance Short-Term and Long-Term coverage, paid for by Allegion, provides income replacement for illness or injury", "Life Insurance Term life coverage with the option to purchase supplemental coverage", "Tuition", "Reimbursement", "Voluntary Wellness Program Simply complete wellness activities and earn up to $2,000 in rewards", "Employee Discounts through", "Perks at Work", "Community involvement and opportunities to give back so you can serve others, not yourself", "Opportunities to leverage your unique strengths through CliftonStrengths assessment & coaching", "This range is provided by Allegion", "Your actual pay will be based on your skills and", "The expected Base Salary Range: $67,800 to $126,000", "The actual compensation will be determined based on experience and other factors permitted by law"]}, "job_job_title": "Development manager", "job_posting_language": "en", "job_onet_soc": "49209800", "job_onet_job_zone": "3"}