{"job_id": "M0ljXIZxjj3_P2jLAAAAAA==", "employer_name": "Haworth Marketing + Media", "employer_logo": "http://www.haworthmedia.com/wp-content/uploads/2021/09/H-Mark-White-with-Circle-Stroke_Blue-background.png", "employer_website": "http://www.haworthmedia.com", "employer_company_type": null, "job_publisher": "LinkedIn", "job_employment_type": "FULLTIME", "job_title": "Partnership Development Director", "job_apply_link": "https://www.linkedin.com/jobs/view/partnership-development-director-at-haworth-marketing-%2B-media-3846351002", "job_apply_is_direct": false, "job_apply_quality_score": 0.7398, "apply_options": [{"publisher": "LinkedIn", "apply_link": "https://www.linkedin.com/jobs/view/partnership-development-director-at-haworth-marketing-%2B-media-3846351002", "is_direct": false}], "job_description": "Step into Haworth, where marketing is our passion, and paid media is our playground.\n\nThe + in our full name \u2013 Haworth Marketing + Media \u2013 symbolizes our unique blend of media expertise and marketing ingenuity. Haworth is a marketing-led, creative-driven, digital-first modern media agency. We value the individuality and independence of our employee shareholders \u2013 and with our 50-year history of integrity as a cornerstone, we\u2019ve cultivated authentic partnerships with an impressive roster of clients.\n\nHeadquartered in Minneapolis with a nationwide network of remote workers, Haworth fosters a dynamic, inclusive environment where individuality thrives. Our casual atmosphere and hybrid work model is filled with thinkers, doers, and overachievers. Haworthians are hard-working individuals who thrive on challenging the norms, driven by a passion for delivering exceptional client work and making a positive impact on our communities.\n\nHaworth's suite of services is crafted to meet the evolving needs of today\u2019s clients. Join us in shaping businesses and leveraging our services to create impactful growth strategies together.\n\nPARTNERSHIP (NEW BUSINESS) DEVELOPMENT DIRECTOR\n\nThe Partnership Development Director is a critical part of our agency growth roadmap. This position is accountable for stewarding Haworth teams through growth initiatives aligned to the company\u2019s best opportunities. The scope of work includes creating relationships with top-tier marketers, stewarding RFPs and pitch development.\n\nRESPONSIBILITIES\n\nResponding to and creating new business leads\n\u2022 Define lead generation outreach plan to ensure quality leads are acquired (SEM, Events, partner agencies, C-suite relationships, etc.)\n\u2022 Source agency introduction meetings and lead development of presentation materials\n\u2022 Evaluate and respond to incoming opportunities sourced from professional agency recruitment services and consultants\n\u2022 Collaborate closely with leadership to tailor and refine outbound narrative based on each audience\n\nRFI & RFP Stewardship & Development\n\u2022 Collaborate with internal stakeholders to respond to RFI and RFP submissions\n\u2022 Steward entire RFP process with confidence and a bold perspective\n\u2022 Lead strategy and planning solutions when a deliverable is part of the RFP\n\u2022 Utilize media partnerships to bolster value propositions and strengthen RFP submissions\n\u2022 Manage new partner procurement end-to-end and transition wins to the working team\n\nExternal Reputation Development\n\u2022 Identify relevant events & experiences to market Haworth to prospective clients and employees; represent our company well and generate awareness of Haworth services\n\u2022 Attend select events and networking opportunities to represent Haworth\n\u2022 Participate in panel discussions or similar speaking opportunities\n\u2022 Own and steward Haworth social media content strategy & execution along with supporting team\n\u2022 Present and explain Haworth services, positioning, and sales approach to internal staff, fostering a comprehensive understanding and alignment across the agency\n\nREQUIREMENTS\n\u2022 Entrepreneurial mindset\n\u2022 Unpretentiously exude confidence instilling trust and credibility\n\u2022 Curious, inventive, collaborative spirit\n\u2022 Ability to manage, captivate and inspire\n\u2022 Comfortably command attention, adept at engaging audiences to deliver impactful presentations\n\u2022 Thrive working in high-pressure situations\n\u2022 Self-motivated, ability to prioritize workloads, and solution-oriented\n\u2022 Superior written & verbal communication skills to facilitate clear and persuasive expression of ideas\n\u2022 Proven ability to develop/maintain strong professional relationships with clients/colleagues/vendors\n\u2022 Demonstrated expertise developing integrated marketing communication plans, incorporating both traditional and non-traditional media strategies\n\u2022 Confidently leverage big data sets to inform and shape strategies & plans\n\nEXPERIENCE\n\u2022 At least 3 years participating in growth initiatives and sales in media and/or marketing technology, demonstrating a solid understanding of industry dynamics\n\u2022 8+ years of experience in media planning including a minimum of 3-5 years in a managerial capacity\n\u2022 Understanding of agency services and a POV on Haworth\u2019s differentiation on social & digital media\n\u2022 Fluent in holistic media planning (i.e. aware of research tools, capabilities in media, etc.)\n\u2022 Proven track record of thought leadership and innovation in media, ideally in agency transformation, underscoring a capacity for driving change and staying ahead of industry trends\n\nCompetitive compensation and casual, team-oriented working environment. Qualified candidates in remote locations considered. Please forward your resume and salary requirements to: hr@haworthmedia.com", "job_is_remote": false, "job_posted_at_timestamp": 1709586687, "job_posted_at_datetime_utc": "2024-03-04T21:11:27.000Z", "job_city": null, "job_state": null, "job_country": "US", "job_latitude": 37.09024, "job_longitude": -95.71289, "job_benefits": null, "job_google_link": "https://www.google.com/search?gl=us&hl=en&rciv=jb&q=director+of+brand+partnerships&start=50&ibp=htl;jobs#fpstate=tldetail&htivrt=jobs&htiq=director+of+brand+partnerships&htidocid=M0ljXIZxjj3_P2jLAAAAAA%3D%3D", "job_offer_expiration_datetime_utc": "2024-04-03T21:11:26.000Z", "job_offer_expiration_timestamp": 1712178686, "job_required_experience": {"no_experience_required": false, "required_experience_in_months": 96, "experience_mentioned": true, "experience_preferred": false}, "job_required_skills": null, "job_required_education": {"postgraduate_degree": false, "professional_certification": false, "high_school": false, "associates_degree": false, "bachelors_degree": true, "degree_mentioned": false, "degree_preferred": false, "professional_certification_mentioned": false}, "job_experience_in_place_of_education": false, "job_min_salary": null, "job_max_salary": null, "job_salary_currency": null, "job_salary_period": null, "job_highlights": {"Qualifications": ["Entrepreneurial mindset", "Unpretentiously exude confidence instilling trust and credibility", "Curious, inventive, collaborative spirit", "Ability to manage, captivate and inspire", "Comfortably command attention, adept at engaging audiences to deliver impactful presentations", "Thrive working in high-pressure situations", "Self-motivated, ability to prioritize workloads, and solution-oriented", "Superior written & verbal communication skills to facilitate clear and persuasive expression of ideas", "Proven ability to develop/maintain strong professional relationships with clients/colleagues/vendors", "Demonstrated expertise developing integrated marketing communication plans, incorporating both traditional and non-traditional media strategies", "Confidently leverage big data sets to inform and shape strategies & plans", "At least 3 years participating in growth initiatives and sales in media and/or marketing technology, demonstrating a solid understanding of industry dynamics", "8+ years of experience in media planning including a minimum of 3-5 years in a managerial capacity", "Understanding of agency services and a POV on Haworth\u2019s differentiation on social & digital media", "Fluent in holistic media planning (i.e", "aware of research tools, capabilities in media, etc.)", "Proven track record of thought leadership and innovation in media, ideally in agency transformation, underscoring a capacity for driving change and staying ahead of industry trends"], "Responsibilities": ["Responding to and creating new business leads", "Define lead generation outreach plan to ensure quality leads are acquired (SEM, Events, partner agencies, C-suite relationships, etc.)", "Source agency introduction meetings and lead development of presentation materials", "Evaluate and respond to incoming opportunities sourced from professional agency recruitment services and consultants", "Collaborate closely with leadership to tailor and refine outbound narrative based on each audience", "RFI & RFP Stewardship & Development", "Collaborate with internal stakeholders to respond to RFI and RFP submissions", "Steward entire RFP process with confidence and a bold perspective", "Lead strategy and planning solutions when a deliverable is part of the RFP", "Utilize media partnerships to bolster value propositions and strengthen RFP submissions", "Manage new partner procurement end-to-end and transition wins to the working team", "External Reputation Development", "Identify relevant events & experiences to market Haworth to prospective clients and employees; represent our company well and generate awareness of Haworth services", "Attend select events and networking opportunities to represent Haworth", "Participate in panel discussions or similar speaking opportunities", "Own and steward Haworth social media content strategy & execution along with supporting team", "Present and explain Haworth services, positioning, and sales approach to internal staff, fostering a comprehensive understanding and alignment across the agency"], "Benefits": ["Competitive compensation and casual, team-oriented working environment"]}, "job_job_title": "Development director", "job_posting_language": "en", "job_onet_soc": "11202100", "job_onet_job_zone": "4"}