{"job_id": "AUPfuvIfxZcNXfC6AAAAAA==", "employer_name": "Wyndham Destinations", "employer_logo": "https://d1io3yog0oux5.cloudfront.net/_025b1039d7fd14c76d8f04b86c1dbff7/travelandleisureco/logo.png", "employer_website": "http://www.travelandleisureco.com", "employer_company_type": "Accommodation", "job_publisher": "Jooble", "job_employment_type": "FULLTIME", "job_title": "Director, Brand Business Partner", "job_apply_link": "https://jooble.org/jdp/-4188142589055063461", "job_apply_is_direct": false, "job_apply_quality_score": 0.5724, "apply_options": [{"publisher": "Jooble", "apply_link": "https://jooble.org/jdp/-4188142589055063461", "is_direct": false}], "job_description": "We Put the World on Vacation\nAt Travel + Leisure Co., our mission is simple: to put the world on vacation. With a focus on vacation ownership, travel memberships, and exchange programs, we\u2019re shaping the future of leisure travel by creating new possibilities for vacationers. Innovation and growth keep our work interesting and fun. Every day is a chance to learn something new and turn vacation inspiration into exceptional experiences for millions of travelers worldwide.\n\nThe Director, Brand Business Partner is a critical role as part of the Brand Strategy team in the Global Brand, Communications, and Digital organization. The role consists of partnering with the various business lines on annual planning as it relates to brand, partnerships, communications, insights and digital support. This leader will help manifest the Travel + Leisure enterprise promise \u2013 \u201c We put the world on vacation \u201d \u2013 through supporting strong performance of our existing business lines. The Director, Brand Business Partner will be focused on partnering with the business and the brand, partnerships, communications, insights and digital organizations to facilitate aligned planning, resources and support of the business. The leader identifies opportunities, based on organizational objectives and coordinates a multidisciplinary approach to review, gain approval across stakeholders, and ensure implementation. Success in the position demands a driving focus on creation of shareholder value and earnings, as well as a passion to champion business opportunities that build brand equity, drive financial performance, and yield organizational efficiencies. At times, this position may also support special projects for the Chief Brand, Communications and Digital Officer. The position reports into the SVP, Brand Strategy.\n\nHow You'll Shine\n\u2022 Brand Business Partner (45%): Collaborate with senior leaders and their teams from each business unit to support business and new growth strategies from a brand, partnerships, insights, communications and digital perspective through annual planning and performance focused QBRs.\n\u2022 Internal Planning (30%): Collaborate with the brand, partnerships, insights, communications and digital teams to prioritize and execute against annual plans for each business unit. Ensure plan is aligned with and supports enterprise priorities.\n\u2022 KPI Tracking (25%): Develop a method by which all brand organization functions can provide rollup reporting on metrics for analysis and communication back to business unit stakeholders. Manage related budget and resourcing plans, and be a fiduciary steward of the company.\n\nWhat You'll Bring\n\nEducation\n\u2022 BA in Business, Marketing, Hospitality or related field. Master\u2019s degree preferred.\n\nKnowledge and skills\n\u2022 Expert understanding of branding and marketing practices and structure.\n\u2022 Ability to identify key drivers and alignment opportunities in the business.\n\u2022 Ability to develop, monitor and communicate key performance indicators and measurement.\n\u2022 Problem solver and a visionary to see beyond the day-to-day and offer new solutions versus the status quo.\n\u2022 Leadership, influence, and communications skills at all levels of the organization in a collaborative way that builds credibility.\n\u2022 Develop authentic, productive relationships with internal and external partners.\n\u2022 Build consensus and alignment but not afraid to push ahead on the vision.\n\u2022 Passionate about leading, managing and inspiring people and solutions.\n\u2022 Strong emotional intelligence to lead and develop others in a fast-paced and changing environment.\n\nTechnical Skills\n\u2022 Proficiency in Microsoft Office Suite and various data and insights analysis tools.\n\nJob experience\n\u2022 7+ years of leadership experience in travel, leisure, hospitality and/or lifestyle brands. Experience in vacation ownership business and/or subscription segment would be preferred.\n\u2022 9+ years of leadership experience in business strategy, brand marketing, innovation or related function, demonstrating progressive career growth and pattern of exceptional performance. Strong understanding of brand or portfolio strategy, marketing and performance measurement.\n\nExperience equivalent to the education requirement may be accepted in lieu of the education requirement.\n\nHow You'll Be Rewarded:\n\nWe offer a diverse range of comprehensive health and welfare benefits to associates who work 30 or more hours per week to meet your needs and support you throughout your career with us. Travel + Leisure Co. benefits include:\n\nNote: Temporary and/or seasonal associates are ineligible for Paid Time Off.\n\u2022 Medical\n\u2022 Dental\n\u2022 Vision\n\u2022 Flexible spending accounts\n\u2022 Life and accident coverage\n\u2022 Disability\n\u2022 Depending on position, paid time off, parental leave and holidays (speak to your recruiter for additional information)\n\u2022 Wish day paid time to volunteer at an approved organization of your choice\n\u2022 401k with employer match (subject to eligibility requirements, including tenure - speak to your recruiter for additional information)\n\u2022 Legal and identify theft plan\n\u2022 Voluntary income protection benefits\n\u2022 Wellness program (subject to provider availability)\n\u2022 Employee Assistance Program\n\nWhere Memories Start with You\n\nHospitality is at the heart of all we do at Travel + Leisure Co. Here, you\u2019ll find an inclusive environment where we deliver excellence and take time to have fun, celebrate together, and support one another. We're always looking ahead to what\u2019s next and how we can strengthen our business, its neighboring communities, and the customer experience. Join our global team and build a career where memories start with you.\n\nWe are an equal opportunity employer, and all applications will be considered for employment without attention to their membership in any protected class. If you require any reasonable accommodation to complete your application or any part of the recruiting process, please email your request to View email address on careers.travelandleisureco.com , including the title and location of the position for which you are applying.", "job_is_remote": false, "job_posted_at_timestamp": 1708698129, "job_posted_at_datetime_utc": "2024-02-23T14:22:09.000Z", "job_city": "Hopewell", "job_state": "FL", "job_country": "US", "job_latitude": 27.92833, "job_longitude": -82.12389, "job_benefits": ["paid_time_off", "health_insurance", "retirement_savings"], "job_google_link": "https://www.google.com/search?gl=us&hl=en&rciv=jb&q=director+of+brand+partnerships&start=50&ibp=htl;jobs#fpstate=tldetail&htivrt=jobs&htiq=director+of+brand+partnerships&htidocid=AUPfuvIfxZcNXfC6AAAAAA%3D%3D", "job_offer_expiration_datetime_utc": "2024-03-30T11:01:35.000Z", "job_offer_expiration_timestamp": 1711796495, "job_required_experience": {"no_experience_required": false, "required_experience_in_months": 84, "experience_mentioned": true, "experience_preferred": true}, "job_required_skills": null, "job_required_education": {"postgraduate_degree": false, "professional_certification": false, "high_school": false, "associates_degree": false, "bachelors_degree": false, "degree_mentioned": true, "degree_preferred": true, "professional_certification_mentioned": false}, "job_experience_in_place_of_education": false, "job_min_salary": null, "job_max_salary": null, "job_salary_currency": null, "job_salary_period": null, "job_highlights": {"Qualifications": ["BA in Business, Marketing, Hospitality or related field", "Expert understanding of branding and marketing practices and structure", "Ability to identify key drivers and alignment opportunities in the business", "Ability to develop, monitor and communicate key performance indicators and measurement", "Problem solver and a visionary to see beyond the day-to-day and offer new solutions versus the status quo", "Leadership, influence, and communications skills at all levels of the organization in a collaborative way that builds credibility", "Build consensus and alignment but not afraid to push ahead on the vision", "Passionate about leading, managing and inspiring people and solutions", "Strong emotional intelligence to lead and develop others in a fast-paced and changing environment", "Proficiency in Microsoft Office Suite and various data and insights analysis tools", "7+ years of leadership experience in travel, leisure, hospitality and/or lifestyle brands", "Strong understanding of brand or portfolio strategy, marketing and performance measurement", "Experience equivalent to the education requirement may be accepted in lieu of the education requirement"], "Responsibilities": ["The role consists of partnering with the various business lines on annual planning as it relates to brand, partnerships, communications, insights and digital support", "This leader will help manifest the Travel + Leisure enterprise promise \u2013 \u201c We put the world on vacation \u201d \u2013 through supporting strong performance of our existing business lines", "The Director, Brand Business Partner will be focused on partnering with the business and the brand, partnerships, communications, insights and digital organizations to facilitate aligned planning, resources and support of the business", "The leader identifies opportunities, based on organizational objectives and coordinates a multidisciplinary approach to review, gain approval across stakeholders, and ensure implementation", "Success in the position demands a driving focus on creation of shareholder value and earnings, as well as a passion to champion business opportunities that build brand equity, drive financial performance, and yield organizational efficiencies", "Brand Business Partner (45%): Collaborate with senior leaders and their teams from each business unit to support business and new growth strategies from a brand, partnerships, insights, communications and digital perspective through annual planning and performance focused QBRs", "Internal Planning (30%): Collaborate with the brand, partnerships, insights, communications and digital teams to prioritize and execute against annual plans for each business unit", "Ensure plan is aligned with and supports enterprise priorities", "KPI Tracking (25%): Develop a method by which all brand organization functions can provide rollup reporting on metrics for analysis and communication back to business unit stakeholders", "Manage related budget and resourcing plans, and be a fiduciary steward of the company"], "Benefits": ["We offer a diverse range of comprehensive health and welfare benefits to associates who work 30 or more hours per week to meet your needs and support you throughout your career with us", "Travel + Leisure Co", "Flexible spending accounts", "Life and accident coverage", "Depending on position, paid time off, parental leave and holidays (speak to your recruiter for additional information)", "Wish day paid time to volunteer at an approved organization of your choice", "401k with employer match (subject to eligibility requirements, including tenure - speak to your recruiter for additional information)", "Legal and identify theft plan", "Voluntary income protection benefits", "Wellness program (subject to provider availability)"]}, "job_job_title": "Director", "job_posting_language": "en", "job_onet_soc": "11202100", "job_onet_job_zone": "4", "job_naics_code": "7211", "job_naics_name": "Traveler Accommodation"}