{"job_id": "0DF6DlImGBBR83YMAAAAAA==", "employer_name": "Yusen Logistics (Americas) Inc.", "employer_logo": "https://encrypted-tbn0.gstatic.com/images?q=tbn:ANd9GcR40V0l_RqgSwTZdFpu1F2eOZIOffRLHk_OJXT6&s=0", "employer_website": "http://www.yusen-logistics.com/us_en", "employer_company_type": null, "job_publisher": "LinkedIn", "job_employment_type": "FULLTIME", "job_title": "Sr. Sales Executive", "job_apply_link": "https://www.linkedin.com/jobs/view/sr-sales-executive-at-yusen-logistics-americas-inc-3823649372", "job_apply_is_direct": false, "job_apply_quality_score": 0.6921, "apply_options": [{"publisher": "LinkedIn", "apply_link": "https://www.linkedin.com/jobs/view/sr-sales-executive-at-yusen-logistics-americas-inc-3823649372", "is_direct": false}, {"publisher": "Jobs In Logistics", "apply_link": "https://www.jobsinlogistics.com/cgi-local/search.cgi?action=ViewJobDetails&JobIndNum=27061175", "is_direct": false}, {"publisher": "SimplyHired", "apply_link": "https://www.simplyhired.com/job/mMpiZ6juxCD5ZhjkRp1t-YXIELOoCuzQ6cY5O3Kr_mldeMWlTDqeHQ", "is_direct": false}, {"publisher": "Adzuna", "apply_link": "https://www.adzuna.com/details/4561014943", "is_direct": false}], "job_description": "Overview\n\nSalary Range: $82,245 - $123,140\n\nPosition Summary\n\nThe Senior Sales Executive is responsible for selling and matching Yusen Logistics Americas solutions for local accounts within an assigned territory and maintaining and expanding service offerings within new and existing accounts. This position is located in a branch office of the International Freight Forwarding (IFF) Group. The position works with the branch operations, the product teams, and the Sales Coordinator to achieve revenue generation, account management, and customer satisfaction goals for assigned middle and large size accounts.\n\nResponsibilities\n\nJob Responsibilities\n\nNew Business Development\n\u2022 Develop and Hunt new business opportunities through research, prospecting, and qualifying new opportunities. This will include customer visits and developing relationships within the defined geographical area or market.\n\u2022 Focus activity on accounts within the mid to large size customer group with an annual gross profit between $50,000-$200,000. This includes on-boarding 3-8 new clients per year, maintaining an active pipeline of 25 customers within this range with a heavy focus on prospective clients that align with Yusens Logitcis targeted industry verticals.\n\u2022 Increase market share by closing new business and on-boarding new customers within assigned national territory while achieving assigned financial budget for volume, revenue, and profit.\n\u2022 Prepare and present proposals, recommend new services, extensions, or enhancements, and overcome objections to closure.\n\u2022 Work collaboratively on push/pull sales leads with international offices.\n\u2022 Expected to meet Sales Targets assigned by management.\n\nMaintain And Develop Existing Accounts\n\u2022 Increase market share within the existing and inactive customer base.\n\u2022 Support any transportation issues by acting as liaison between operations and client.\n\u2022 Work with existing customers on service proposals, rate quotations, and air/ocean transportation schedules for new destinations. Manage ad hoc pricing requests.\n\u2022 Provide subject matter expertise, guidance, and solution offering for customer regarding export regulations, loading methods, crating, handling freight, and special equipment availability.\n\nCoordinate And Liaise With YLA Branch Operations And Customers\n\u2022 Liaise with the branch operations team on behalf of the customers.\n\u2022 Coordinate with the credit department to establish lines of credit for new accounts and\n\nnegotiate letters of credit and collections of outstanding invoices. Coordinate with the credit department to establish lines of credit for new accounts and negotiate letters of credit and collections of outstanding invoices.\n\u2022 Provide reports on rates, use of carriers, and significant operational problems.\n\u2022 May assist, communicate, and follow up with other U.S. and foreign offices regarding targeted or joint customers.\n\u2022 Proactively establish and maintain effective working team relationships with all branch operations departments.\n\u2022 Participates and contributes to the development of educational programs offered to clients.\n\u2022 Maintains accurate records of all sales and prospecting activities, including sales calls, presentations, closed sales, and follow-up activities within CRM.\n\u2022 Participate in local business activities and events to gain networking opportunities and expose the local market to the Yusen brand and value proposition.\n\u2022 Coordinate with operations to manage the account receivable to ensure it stays current and help operations collect account receivables within the terms set forth .\n\nQualifications\n\nMinimum Required Qualifications\n\u2022 Bachelor\u2019s degree in a related logistics field preferred and/or five or more years of related experience in freight forwarding, International Operations, logistics, or equivalent combination of education and experience.\n\u2022 High level of organizational and time management skills\n\u2022 Is a self-starter that displays strong customer interaction and is customer centric.\n\u2022 Outstanding interpersonal skills including being persuasive and influential with customer contacts.\n\nEssential Job Functions\n\u2022 Maintain regular and punctual attendance.\n\u2022 Travel overnight as required up to 35-40%.\n\u2022 Interact with employees and customers in an appropriate manner.\n\u2022 Use a computer for tasks such as making updates to CRM, communicating via email and voice.\n\u2022 Present to customers and other stakeholders in a professional and effective manner.\n\u2022 Comply with all Company policies and procedures.\n\u2022 Proficient in Microsoft Office.\n\nThe above statements are intended to describe the general nature of work being performed. They are not to be construed as an exhaustive list of all responsibilities, duties and skills required.\n\nBenefits\n\nYusen offers a generous Employee Benefits Package including:\n\u2022 Medical, Dental, and Vision beginning the 1 st of the month following start date\n\u2022 401k with a company match\n\u2022 Flexible Spending Accounts, Life and Accidental Death & Dismemberment Insurance, Short & Long Term Disability, Tuition Assistance Program, Commuter Benefits, vacation , and much more.\n\nAny and all benefits offered are subject to the eligibility requirements, terms, and provisions set forth in the respective policies and plan documents, which you may request from Human Resources.\n\nAbout Yusen Logistics (Americas )\n\nYusen Logistics is working to become the world\u2019s preferred supply chain logistics company. Our complete offer is designed to forge better connections between businesses, customers and communities \u2013 through innovative supply chain management, freight forwarding, warehousing and distribution services. As a company we\u2019re dedicated to a culture of continuous improvement, ensuring everyone who works with us is committed, connected and creative in making us the world\u2019s preferred choice.\n\nwww.yusen-logistics.com/\n\nYusen Logistics (Americas) Inc. values each individual employee and is committed to a diverse and inclusive workforce by providing equal employment opportunities for all applicants without regard to race, religion, color, sex, national origin, citizenship status, uniform service member status, age, disability, sexual and gender orientation, genetic information, or any other protected status in accordance with all applicable federal, state and local laws.\n\nJILPOST", "job_is_remote": false, "job_posted_at_timestamp": 1707231020, "job_posted_at_datetime_utc": "2024-02-06T14:50:20.000Z", "job_city": "New York", "job_state": "NY", "job_country": "US", "job_latitude": 40.712776, "job_longitude": -74.005974, "job_benefits": ["dental_coverage", "health_insurance", "retirement_savings", "paid_time_off"], "job_google_link": "https://www.google.com/search?gl=us&hl=en&rciv=jb&q=senior+sales+director&start=70&ibp=htl;jobs#fpstate=tldetail&htivrt=jobs&htiq=senior+sales+director&htidocid=0DF6DlImGBBR83YMAAAAAA%3D%3D", "job_offer_expiration_datetime_utc": "2024-04-03T14:50:30.000Z", "job_offer_expiration_timestamp": 1712155830, "job_required_experience": {"no_experience_required": false, "required_experience_in_months": 60, "experience_mentioned": true, "experience_preferred": false}, "job_required_skills": null, "job_required_education": {"postgraduate_degree": false, "professional_certification": false, "high_school": false, "associates_degree": false, "bachelors_degree": false, "degree_mentioned": true, "degree_preferred": true, "professional_certification_mentioned": false}, "job_experience_in_place_of_education": false, "job_min_salary": null, "job_max_salary": null, "job_salary_currency": null, "job_salary_period": null, "job_highlights": {"Qualifications": ["High level of organizational and time management skills", "Is a self-starter that displays strong customer interaction and is customer centric", "Outstanding interpersonal skills including being persuasive and influential with customer contacts", "Proficient in Microsoft Office"], "Responsibilities": ["The position works with the branch operations, the product teams, and the Sales Coordinator to achieve revenue generation, account management, and customer satisfaction goals for assigned middle and large size accounts", "Develop and Hunt new business opportunities through research, prospecting, and qualifying new opportunities", "This will include customer visits and developing relationships within the defined geographical area or market", "Focus activity on accounts within the mid to large size customer group with an annual gross profit between $50,000-$200,000", "This includes on-boarding 3-8 new clients per year, maintaining an active pipeline of 25 customers within this range with a heavy focus on prospective clients that align with Yusens Logitcis targeted industry verticals", "Increase market share by closing new business and on-boarding new customers within assigned national territory while achieving assigned financial budget for volume, revenue, and profit", "Prepare and present proposals, recommend new services, extensions, or enhancements, and overcome objections to closure", "Work collaboratively on push/pull sales leads with international offices", "Expected to meet Sales Targets assigned by management", "Maintain And Develop Existing Accounts", "Increase market share within the existing and inactive customer base", "Support any transportation issues by acting as liaison between operations and client", "Work with existing customers on service proposals, rate quotations, and air/ocean transportation schedules for new destinations", "Manage ad hoc pricing requests", "Provide subject matter expertise, guidance, and solution offering for customer regarding export regulations, loading methods, crating, handling freight, and special equipment availability", "Coordinate And Liaise With YLA Branch Operations And Customers", "Liaise with the branch operations team on behalf of the customers", "Coordinate with the credit department to establish lines of credit for new accounts and negotiate letters of credit and collections of outstanding invoices", "Provide reports on rates, use of carriers, and significant operational problems", "May assist, communicate, and follow up with other U.S. and foreign offices regarding targeted or joint customers", "Proactively establish and maintain effective working team relationships with all branch operations departments", "Participates and contributes to the development of educational programs offered to clients", "Maintains accurate records of all sales and prospecting activities, including sales calls, presentations, closed sales, and follow-up activities within CRM", "Participate in local business activities and events to gain networking opportunities and expose the local market to the Yusen brand and value proposition", "Coordinate with operations to manage the account receivable to ensure it stays current and help operations collect account receivables within the terms set forth ", "Maintain regular and punctual attendance", "Travel overnight as required up to 35-40%", "Interact with employees and customers in an appropriate manner", "Use a computer for tasks such as making updates to CRM, communicating via email and voice", "Present to customers and other stakeholders in a professional and effective manner", "Comply with all Company policies and procedures"], "Benefits": ["Salary Range: $82,245 - $123,140", "Yusen offers a generous Employee Benefits Package including:", "Medical, Dental, and Vision beginning the 1 st of the month following start date", "401k with a company match", "Flexible Spending Accounts, Life and Accidental Death & Dismemberment Insurance, Short & Long Term Disability, Tuition Assistance Program, Commuter Benefits, vacation , and much more", "Any and all benefits offered are subject to the eligibility requirements, terms, and provisions set forth in the respective policies and plan documents, which you may request from Human Resources"]}, "job_job_title": "Sales executive", "job_posting_language": "en", "job_onet_soc": "41401200", "job_onet_job_zone": "4"}