{"job_id": "FupOwZ9THbQjZeTtAAAAAA==", "employer_name": "Best Buy", "employer_logo": "https://upload.wikimedia.org/wikipedia/commons/c/c4/Best_Buy_logo_2018.svg", "employer_website": "http://www.bestbuy.com", "employer_company_type": "Retail", "job_publisher": "Jobrapido.com", "job_employment_type": "FULLTIME", "job_title": "Director, Marketing Advanced Analytics", "job_apply_link": "https://us.jobrapido.com/jobpreview/3211825938", "job_apply_is_direct": false, "job_apply_quality_score": 0.4409, "apply_options": [{"publisher": "Jobrapido.com", "apply_link": "https://us.jobrapido.com/jobpreview/3211825938", "is_direct": false}], "job_description": "Director, Marketing Advanced Analytics\n\n11202100\n1\n\nAs the Director of Marketing Advanced Analytics, you\u2019ll be responsible for the strategy, execution and adoption of marketing analytics, optimization, reporting and high impact insights. You\u2019ll advance marketing analytics to fuel data-driven decisions across media, brand, category marketing and the Best Buy advertising business. In this role, you will blend experience with advanced analytics tools, thought leadership in analytic strategy and a proven ability to work across technology and business teams to design and deliver new solutions. You\u2019ll partner with the Chief Marketing Officer and Marketing Leadership Team, as well as cross-functional partners such as finance, technology and other Advanced analytics teams.\nThis role is hybrid, which means you will work some days on site at a Best Buy location and some days from home or other non-Best Buy location. The specific work arrangements vary by role and team. The recruiter or hiring manager will provide more details during the hiring process.\nWhat you\u2019ll do\n\u2022 Develop marketing analytics strategies that advance data and analytics applications\n\u2022 Manage and evolve a portfolio of marketing effectiveness and optimization capabilities to meet the changing needs of media and advertising partners\n\u2022 Lead and coach a diverse and high-performing team to expand and advance the role and impact of marketing analytics throughout Best Buy\n\u2022 Blend strong analytical aptitude with business acumen to understand marketing strategy, objectives and drive data-driven analyses that serve the customer first\n\u2022 Develop and carryout different types of experiment design, such as A/B and multivariate test, to influence marketing strategies\n\u2022 Proactively deliver insights to marketing leaders that positively impact the business through increased adoption of data-driven decision making\n\u2022 Stay up to date on industry best practices and think beyond current knowledge to develop new solutions, applications and strategies\n\u2022 Develop a strategic vision for the team and participate in budgeting and the annual planning process\n\nBasic qualifications\n\u2022 Bachelor's degree in statistics, mathematics, economics, engineering, the physical sciences, computer science, marketing/business or similar field with quantitative rigor\n\u2022 11 years of experience in retail, analytics business or related areas\n\u2022 5 years of experience applying analytical techniques to answer business questions or scientific questions\n\u2022 6 years of direct or indirect managerial or leadership experience\n\nPreferred qualifications\n\u2022 Master\u2019s degree in business, statistics, mathematics, economics, engineering, the physical sciences, computer science or similar field with quantitative rigor\n\u2022 5 years of experience working with marketing measurement or media optimization used to impact marketing channel strategy\n\u2022 Demonstrated success collaborating with cross functional business teams\n\u2022 5 years of experience leveraging data science and data visualization tools, such as SQL, Tableau/Power BI, SAS, R or Python\n\u2022 3 years of influencing and presenting to executives\n\u2022 High financial acumen with understanding of concepts such as ROI and incrementality\n\nWhat\u2019s in it for you\nWe\u2019re committed to helping our people thrive at work and at home. We offer generous benefits that address your total well-being and provide support as you need it, especially key moments in your life.\nOur benefits include:\n\u2022 Competitive pay\n\u2022 Generous employee discount\n\u2022 Financial savings and retirement resources\n\u2022 Support for your physical and mental well-being\nAbout us\nAs part of the Best Buy team, you\u2019ll help us fulfill our purpose to enrich lives through technology. We bring that to life every day by humanizing and personalizing tech solutions for every stage of life \u2014 in our stores, online and in customers\u2019 homes.\nOur culture is built on deeply supporting and valuing our amazing employees who make it all possible. We\u2019re committed to being a great place to work, where you can unlock unique career possibilities. Above all, we aim to provide a place where you can bring your full, authentic self to work now and into the future. Tomorrow works here.\u2122", "job_is_remote": false, "job_posted_at_timestamp": 1710374400, "job_posted_at_datetime_utc": "2024-03-14T00:00:00.000Z", "job_city": null, "job_state": "MN", "job_country": "US", "job_latitude": 46.729553, "job_longitude": -94.6859, "job_benefits": ["retirement_savings"], "job_google_link": "https://www.google.com/search?gl=us&hl=en&rciv=jb&q=manager+of+marketing+analytics&start=50&ibp=htl;jobs#fpstate=tldetail&htivrt=jobs&htiq=manager+of+marketing+analytics&htidocid=FupOwZ9THbQjZeTtAAAAAA%3D%3D", "job_offer_expiration_datetime_utc": null, "job_offer_expiration_timestamp": null, "job_required_experience": {"no_experience_required": false, "required_experience_in_months": 132, "experience_mentioned": true, "experience_preferred": false}, "job_required_skills": null, "job_required_education": {"postgraduate_degree": false, "professional_certification": false, "high_school": false, "associates_degree": false, "bachelors_degree": false, "degree_mentioned": true, "degree_preferred": true, "professional_certification_mentioned": false}, "job_experience_in_place_of_education": false, "job_min_salary": null, "job_max_salary": null, "job_salary_currency": null, "job_salary_period": null, "job_highlights": {"Qualifications": ["Bachelor's degree in statistics, mathematics, economics, engineering, the physical sciences, computer science, marketing/business or similar field with quantitative rigor", "11 years of experience in retail, analytics business or related areas", "5 years of experience applying analytical techniques to answer business questions or scientific questions", "6 years of direct or indirect managerial or leadership experience"], "Responsibilities": ["As the Director of Marketing Advanced Analytics, you\u2019ll be responsible for the strategy, execution and adoption of marketing analytics, optimization, reporting and high impact insights", "You\u2019ll advance marketing analytics to fuel data-driven decisions across media, brand, category marketing and the Best Buy advertising business", "In this role, you will blend experience with advanced analytics tools, thought leadership in analytic strategy and a proven ability to work across technology and business teams to design and deliver new solutions", "You\u2019ll partner with the Chief Marketing Officer and Marketing Leadership Team, as well as cross-functional partners such as finance, technology and other Advanced analytics teams", "This role is hybrid, which means you will work some days on site at a Best Buy location and some days from home or other non-Best Buy location", "Develop marketing analytics strategies that advance data and analytics applications", "Manage and evolve a portfolio of marketing effectiveness and optimization capabilities to meet the changing needs of media and advertising partners", "Lead and coach a diverse and high-performing team to expand and advance the role and impact of marketing analytics throughout Best Buy", "Blend strong analytical aptitude with business acumen to understand marketing strategy, objectives and drive data-driven analyses that serve the customer first", "Develop and carryout different types of experiment design, such as A/B and multivariate test, to influence marketing strategies", "Proactively deliver insights to marketing leaders that positively impact the business through increased adoption of data-driven decision making", "Stay up to date on industry best practices and think beyond current knowledge to develop new solutions, applications and strategies", "Develop a strategic vision for the team and participate in budgeting and the annual planning process"], "Benefits": ["We offer generous benefits that address your total well-being and provide support as you need it, especially key moments in your life", "Competitive pay", "Generous employee discount", "Financial savings and retirement resources", "Support for your physical and mental well-being"]}, "job_job_title": "Director", "job_posting_language": "en", "job_onet_soc": "11302100", "job_onet_job_zone": "4", "job_naics_code": "452990", "job_naics_name": "All Other General Merchandise Stores"}