{"job_id": "OkBmUZVR3McUauatAAAAAA==", "employer_name": "Highsnobiety", "employer_logo": "https://avatars.githubusercontent.com/u/13017291?s=200&v=4", "employer_website": "http://www.titelmedia.com", "employer_company_type": null, "job_publisher": "Salary.com", "job_employment_type": "FULLTIME", "job_title": "Brand Partnerships Director (d/f/m)", "job_apply_link": "https://www.salary.com/job/highsnobiety/brand-partnerships-director-d-f-m/j202310190152018518587", "job_apply_is_direct": false, "job_apply_quality_score": 0.6259, "apply_options": [{"publisher": "Salary.com", "apply_link": "https://www.salary.com/job/highsnobiety/brand-partnerships-director-d-f-m/j202310190152018518587", "is_direct": false}], "job_description": "Highsnobiety is a brand dedicated to the latest in style, culture, and the community pushing them forward. We don't just report on what's happening \u2014 we are shaping it. From industry deep dives to product curations to our very own in-house garments, our goal is to bring you not anything and everything, but only the best of the best on all fronts. And we want you to be a part of that!\n\nWe are looking for a Brand Partnerships Director based in our Berlin office, where the person will be working alongside our Senior Brand Partnerships Director.\n\nThe aim of the role will be to continue developing Highsnobiety's presence in the European/ DACH market both from a revenue and brand positioning perspective. The primary focus of the candidate should be to drive revenue growth and profitability for all digital, print and offline activations, with a strong focus on global client partners based in Italy and across different categories.\n\nTo be considered, you should have a strong network of senior leaders at the Director level and above across Marketing, PR and Communications functions of key brands as well as access to C-suite level stakeholders. Superior knowledge of the client base in this category and a proven track record of deals and partnerships with relevant clients is imperative. Since Highsnobiety sells custom work and in addition to media, a successful candidate must be able to go deep at an account level and learn how to answer needs in creative, casting, strategy, social, media, events and other areas through marketing-led cultural consultancy. You should be able to successfully motivate and partner with internal teams across Europe, as well as have a passion for great content and storytelling, and an interest in style and culture.\n\nYOUR MISSION:\n\u2022 Managing current DACH based accounts/clients\n\u2022 Prospecting and breaking new European/ DACH based accounts/clients utilizing your own contact book to drive revenue\n\u2022 Developing marketplace and competitor knowledge to identify opportunities\n\u2022 Briefing the creative services team and pitching creative marketing strategies to clients\n\u2022 Understanding and utilizing contracts and pricing structures\n\u2022 Monitoring existing and potential campaigns\n\u2022 Creating new opportunities to drive revenue\n\u2022 Achieving sales target\n\u2022 Supporting the Highsnobiety Brand team in creating new opportunities to activate our brand in the DACH region\n\nYOUR SKILLS:\n\u2022 Minimum 5 years of Sales/Account management experience\n\u2022 Good knowledge of Media business, Digital Marketing and Editorial world\n\u2022 Fluent in English is a must, fluent in German a big plus\n\u2022 Proven track record within a relevant publishing group, agency or brand (or brand group)\n\u2022 Experienced in negotiating with senior professionals on the client and agency side\n\nWHAT WE OFFER:\n\u2022 A comprehensive COVID-19 remote work plan and related sustainable business model\n\u2022 A bright and spacious Design office, which reflects our brand and focuses on employee well-being, located in the upcoming and vibrant district of Sch\u00f6neberg\n\u2022 Motivating, international and creative work atmosphere\n\u2022 High degree of responsibility, creativity, originality, independence and creative leeway\n\u2022 The opportunity to proactively shape a company and help build a global brand\n\u2022 Competitive compensation\n\u2022 Attractive employee benefits (e.g. various discounts)\n\nWe\u2019re looking forward to hearing from you!!\n\nDon\u2019t meet every single requirement? Studies have shown that women and people of color are less likely to apply to jobs unless they meet every single qualification. Highsnobiety is a global community of independent-minded creatives & professionals: Every perspective matters. That\u2019s why we\u2019re proud to be an equal opportunity employer. We do not discriminate on the basis of race, color, ethnicity, religion, sex, national origin, sexual orientation, age, citizenship status, marital status, disability, gender identity, gender expression, or genetic information. So if you\u2019re excited about this role but your past experience doesn\u2019t align perfectly with every qualification in the job description, we encourage you to apply anyways.", "job_is_remote": false, "job_posted_at_timestamp": 1697760000, "job_posted_at_datetime_utc": "2023-10-20T00:00:00.000Z", "job_city": null, "job_state": null, "job_country": "US", "job_latitude": 37.09024, "job_longitude": -95.71289, "job_benefits": null, "job_google_link": "https://www.google.com/search?gl=us&hl=en&rciv=jb&q=director+of+brand+partnerships&start=0&ibp=htl;jobs#fpstate=tldetail&htivrt=jobs&htiq=director+of+brand+partnerships&htidocid=OkBmUZVR3McUauatAAAAAA%3D%3D", "job_offer_expiration_datetime_utc": "2024-04-19T00:00:00.000Z", "job_offer_expiration_timestamp": 1713484800, "job_required_experience": {"no_experience_required": false, "required_experience_in_months": 60, "experience_mentioned": true, "experience_preferred": false}, "job_required_skills": null, "job_required_education": {"postgraduate_degree": false, "professional_certification": false, "high_school": false, "associates_degree": false, "bachelors_degree": false, "degree_mentioned": false, "degree_preferred": false, "professional_certification_mentioned": false}, "job_experience_in_place_of_education": false, "job_min_salary": null, "job_max_salary": null, "job_salary_currency": null, "job_salary_period": null, "job_highlights": {"Qualifications": ["Since Highsnobiety sells custom work and in addition to media, a successful candidate must be able to go deep at an account level and learn how to answer needs in creative, casting, strategy, social, media, events and other areas through marketing-led cultural consultancy", "Minimum 5 years of Sales/Account management experience", "Good knowledge of Media business, Digital Marketing and Editorial world", "Fluent in English is a must, fluent in German a big plus", "Proven track record within a relevant publishing group, agency or brand (or brand group)", "Experienced in negotiating with senior professionals on the client and agency side", "High degree of responsibility, creativity, originality, independence and creative leeway"], "Responsibilities": ["The aim of the role will be to continue developing Highsnobiety's presence in the European/ DACH market both from a revenue and brand positioning perspective", "The primary focus of the candidate should be to drive revenue growth and profitability for all digital, print and offline activations, with a strong focus on global client partners based in Italy and across different categories", "Managing current DACH based accounts/clients", "Prospecting and breaking new European/ DACH based accounts/clients utilizing your own contact book to drive revenue", "Developing marketplace and competitor knowledge to identify opportunities", "Briefing the creative services team and pitching creative marketing strategies to clients", "Understanding and utilizing contracts and pricing structures", "Monitoring existing and potential campaigns", "Creating new opportunities to drive revenue", "Achieving sales target", "Supporting the Highsnobiety Brand team in creating new opportunities to activate our brand in the DACH region"], "Benefits": ["A comprehensive COVID-19 remote work plan and related sustainable business model", "A bright and spacious Design office, which reflects our brand and focuses on employee well-being, located in the upcoming and vibrant district of Sch\u00f6neberg", "Motivating, international and creative work atmosphere", "The opportunity to proactively shape a company and help build a global brand", "Competitive compensation", "Attractive employee benefits (e.g. various discounts)"]}, "job_job_title": "Director", "job_posting_language": "en", "job_onet_soc": "11202100", "job_onet_job_zone": "4"}