{"job_id": "-lHlvcW3HSU5DoETAAAAAA==", "employer_name": "LMI Consulting, LLC", "employer_logo": null, "employer_website": "http://lmiconsultinginc.com/en/About/Overview", "employer_company_type": null, "job_publisher": "Snagajob", "job_employment_type": "FULLTIME", "job_title": "AI Engineer Intern (Summer 2024)", "job_apply_link": "https://www.snagajob.com/jobs/895280322", "job_apply_is_direct": false, "job_apply_quality_score": 0.634, "apply_options": [{"publisher": "Snagajob", "apply_link": "https://www.snagajob.com/jobs/895280322", "is_direct": false}, {"publisher": "Latinx Jobs", "apply_link": "https://www.latinxjobs.com/job/ai-engineer-intern-summer-2024-164275", "is_direct": false}, {"publisher": "Engineer Jobs Engineering Canada Tech IT Computer Remote Work", "apply_link": "https://jobsinengineering.ca/job/data-operations-intern-summer-2024/", "is_direct": false}], "job_description": "AI Engineer Intern (Summer 2024)\n\nJob Locations\n\nUS-VA-Tysons\n\nJob ID\n\n2024-10793\n\n# of Openings\n\n2\n\nCategory\n\nData/Analytics\n\nOverview\n\nAt LMI, we're reimagining the path from insight to outcome at The New Speed of Possible. Combining a legacy of over 60 years of federal expertise with our innovation ecosystem, we minimize time to value and accelerate mission success. We energize the brightest minds with emerging technologies to inspire creative solutioning and push the boundaries of capability. LMI advances the pace of progress, enabling our customers to thrive while adapting to evolving mission needs.\n\nThe AI Engineer Intern will work with Forge, LMI's internal technology accelerator and innovation hub, to develop technology solutions for LMI and its federal government clients. This position will apply machine learning and data science approaches to initiate, develop, and deliver AI within web-based applications. The AI Engineer Intern will work within a team of data scientists, computer scientists, application developers, product managers, and designers to integrate AI/ML into applications to automate and improve business processes, data quality, and user experience. The ideal candidate will have a passion for solving challenging problems by applying a diverse set of technical capabilities to program, develop models, and deploy services consumed by user applications.\n\u2022 This position is currently full-time telework with the ability to periodically work out of our Tysons, VA HQ*\n\nLMI has been named a 2024 Campus Foward Award Winner! This Award recognizes excellence in early career hiring, celebrating the teams that embrace innovative recruiting strategies, care deeply about the candidate experience, are making significant investments in DEIA, and are supporting the next generation of talent through impactful internships and entry-level programs.\n\nResponsibilities\n\nIdentify opportunities where AI/ML or modeling and simulation can generate business insights or improve business processes\n\u2022 Develop and implement digital and analytic approaches\n\u2022 Work with product designers, application developers, infrastructure engineers, and other data scientists to integrate predictive and prescriptive models with web-based applications\n\u2022 Research algorithms in machine learning to identify viable approaches to meet business requirements\n\u2022 Apply machine learning methods, such as natural language processing (NLP), computer vision, regression, clustering, classification, and deep learning\n\u2022 Design solution prototypes that connect to data sources and deploy through services, such as service functions in web applications or application programming interfaces (APIs)\n\u2022 Become familiar with DevSecOps principles to continuously deliver high-quality software\n\u2022 Work with Docker to develop and deploy containerized versions of models\n\u2022 Participate in design and code reviews, and collaborate with a strong, passionate engineering team\n\u2022 Provide input to UX/UI designers and front-end application developers on how to effectively deliver model outcomes to users\n\u2022 Interface with customer stakeholders to provide technical explanations and support\n\nQualifications\n\u2022 Pursuit of a Bachelor's degree (Graduate student highly preferred) in engineering, mathematics, computer science, or related technical discipline required.\n\u2022 Currently enrolled in a Graduate (Masters) program highly preferred\n\u2022 Pursuing a post-graduate or undergrad degree in engineering, mathematics, computer science, modeling and simulation, operations research, or related technical discipline\n\u2022 Must be able to work for a minimum of 10-12 weeks beginning in Summer 2024 (May/June)\n\u2022 Comfortable working with agile teams, developing prototypes and functionality in short development sprints\n\u2022 Ability to work independently and collaborate effectively with a project team in an agile research and development environment\n\u2022 Comfortable using Atlassian products, including JIRA, Bamboo, Confluence, FishEye, Crucible, and Bitbucket\n\u2022 Ability to think critically to propose tractable solutions to complex problems\n\u2022 Effective written and verbal communication skills\n\u2022 Ability to communicate complex concepts to both technical and business-focused audiences\n\u2022 Familiarity or desire to excel with modern programming languages appropriate for machine learning prototyping; Python is preferred, but experience with other languages such as Java, C++, C#, JavaScript and R demonstrate the necessary ability\n\u2022 Familiarity with the underlying mathematics of machine learning\n\u2022 Knowledge of data structures and data management principles, methods, and tools\n\u2022 Desire to explore machine learning frameworks and libraries, such as scikit-learn, TensorFlow, and Spark ML\n\u2022 Ability to work with integrated development environments, such as Jupyter, JupyterLab, JetBrains IntelliJ IDEA, JetBrains PyCharm, JetBrains CLion, and Visual Studio Code\n\u2022 Ability to collaborate with a team that develops applications using web development frameworks, such as Angular (1.x/2+), React, and Ember, and server frameworks, such as Node.js and Express.js\n\u2022 Ability to consume or interface with cloud computing and storage services, including Amazon Web Services (AWS), Microsoft Azure, or Google Cloud\n\u2022 Familiarity or desire to become familiar with containerization technologies, such as Docker, Kubernetes, Amazon Elastic Container Service (ECS), and Amazon Elastic Kubernetes Service (EKS)\n\nLMI is an Equal Opportunity Employer. LMI is committed to the fair treatment of all and to our policy of providing applicants and employees with equal employment opportunities. LMI recruits, hires, trains, and promotes people without regard to race, color, religion, sex, sexual orientation, gender identity, national origin, pregnancy, disability, age, protected veteran status, citizenship status, genetic information, or any other characteristic protected by applicable federal, state, or local law. If you are a person with a disability needing assistance with the application process, please contact accommodations@lmi.org\n\nNeed help finding the right job?\n\nWe can recommend jobs specifically for you!\n\nClick here to get started.", "job_is_remote": false, "job_posted_at_timestamp": 1710790912, "job_posted_at_datetime_utc": "2024-03-18T19:41:52.000Z", "job_city": "Tysons", "job_state": "VA", "job_country": "US", "job_latitude": 38.918724, "job_longitude": -77.231094, "job_benefits": null, "job_google_link": "https://www.google.com/search?gl=us&hl=en&rciv=jb&q=ai+engineer&start=70&ibp=htl;jobs#fpstate=tldetail&htivrt=jobs&htiq=ai+engineer&htidocid=-lHlvcW3HSU5DoETAAAAAA%3D%3D", "job_offer_expiration_datetime_utc": "2024-05-13T07:17:29.000Z", "job_offer_expiration_timestamp": 1715584649, "job_required_experience": {"no_experience_required": false, "required_experience_in_months": null, "experience_mentioned": true, "experience_preferred": false}, "job_required_skills": null, "job_required_education": {"postgraduate_degree": false, "professional_certification": false, "high_school": false, "associates_degree": false, "bachelors_degree": true, "degree_mentioned": true, "degree_preferred": true, "professional_certification_mentioned": false}, "job_experience_in_place_of_education": false, "job_min_salary": null, "job_max_salary": null, "job_salary_currency": null, "job_salary_period": null, "job_highlights": {"Qualifications": ["The ideal candidate will have a passion for solving challenging problems by applying a diverse set of technical capabilities to program, develop models, and deploy services consumed by user applications", "Pursuing a post-graduate or undergrad degree in engineering, mathematics, computer science, modeling and simulation, operations research, or related technical discipline", "Must be able to work for a minimum of 10-12 weeks beginning in Summer 2024 (May/June)", "Comfortable working with agile teams, developing prototypes and functionality in short development sprints", "Ability to work independently and collaborate effectively with a project team in an agile research and development environment", "Comfortable using Atlassian products, including JIRA, Bamboo, Confluence, FishEye, Crucible, and Bitbucket", "Ability to think critically to propose tractable solutions to complex problems", "Effective written and verbal communication skills", "Ability to communicate complex concepts to both technical and business-focused audiences", "Familiarity with the underlying mathematics of machine learning", "Knowledge of data structures and data management principles, methods, and tools", "Desire to explore machine learning frameworks and libraries, such as scikit-learn, TensorFlow, and Spark ML", "Ability to work with integrated development environments, such as Jupyter, JupyterLab, JetBrains IntelliJ IDEA, JetBrains PyCharm, JetBrains CLion, and Visual Studio Code", "Ability to collaborate with a team that develops applications using web development frameworks, such as Angular (1.x/2+), React, and Ember, and server frameworks, such as Node.js and Express.js", "Ability to consume or interface with cloud computing and storage services, including Amazon Web Services (AWS), Microsoft Azure, or Google Cloud", "Familiarity or desire to become familiar with containerization technologies, such as Docker, Kubernetes, Amazon Elastic Container Service (ECS), and Amazon Elastic Kubernetes Service (EKS)"], "Responsibilities": ["The AI Engineer Intern will work within a team of data scientists, computer scientists, application developers, product managers, and designers to integrate AI/ML into applications to automate and improve business processes, data quality, and user experience", "Identify opportunities where AI/ML or modeling and simulation can generate business insights or improve business processes", "Develop and implement digital and analytic approaches", "Work with product designers, application developers, infrastructure engineers, and other data scientists to integrate predictive and prescriptive models with web-based applications", "Research algorithms in machine learning to identify viable approaches to meet business requirements", "Apply machine learning methods, such as natural language processing (NLP), computer vision, regression, clustering, classification, and deep learning", "Design solution prototypes that connect to data sources and deploy through services, such as service functions in web applications or application programming interfaces (APIs)", "Become familiar with DevSecOps principles to continuously deliver high-quality software", "Work with Docker to develop and deploy containerized versions of models", "Participate in design and code reviews, and collaborate with a strong, passionate engineering team", "Provide input to UX/UI designers and front-end application developers on how to effectively deliver model outcomes to users", "Interface with customer stakeholders to provide technical explanations and support"]}, "job_job_title": "Engineer", "job_posting_language": "en", "job_onet_soc": "15111100", "job_onet_job_zone": "5"}