{"job_id": "Oy7-nIrJA0OG-6fRAAAAAA==", "employer_name": "USAA", "employer_logo": "https://content.usaa.com/mcontent/static_assets/Media/schema-logo-blue-on-white.svg", "employer_website": "http://www.usaa.com", "employer_company_type": "Finance", "job_publisher": "USAA Careers", "job_employment_type": "FULLTIME", "job_title": "Data Scientist Senior \u2013 Pricing Solutions & Methods", "job_apply_link": "https://www.usaajobs.com/job/san-antonio/data-scientist-senior-pricing-solutions-and-methods/1207/62804842160", "job_apply_is_direct": false, "job_apply_quality_score": 0.7239, "apply_options": [{"publisher": "USAA Careers", "apply_link": "https://www.usaajobs.com/job/san-antonio/data-scientist-senior-pricing-solutions-and-methods/1207/62804842160", "is_direct": false}, {"publisher": "Karkidi", "apply_link": "https://www.karkidi.com/job-details/61819-data-scientist-senior-telematics-and-internet-of-things-iot-job", "is_direct": false}, {"publisher": "Ladders", "apply_link": "https://www.theladders.com/job/data-scientist-senior-usaa-san-antonio-tx_68262923", "is_direct": false}], "job_description": "Why USAA?\nAt USAA, we have an important mission: facilitating the financial security of millions of U.S. military members and their families. Not all of our employees served in our nation\u2019s military, but we all share in the mission to give back to those who did. We\u2019re working as one to build a great experience and make a real impact for our members.\n\nWe believe in our core values of honesty, integrity, loyalty and service. They\u2019re what guides everything we do \u2013 from how we treat our members to how we treat each other. Come be a part of what makes us so special!\n\nThe Opportunity\n\nWe offer a flexible work environment that requires an individual to be in the office 4 days per week. This position can be based in one of the following locations: San Antonio, TX; Phoenix, AZ; Colorado Springs, CO; Plano, TX or Tampa, FL.\n\nRelocation assistance is not available for this position.\n\nUSAA P&C is offering an invaluable opportunity for individuals with passion for data science and interest in the insurance industry to work on Auto and Property pricing model development with the top talent in the industry. The candidate must be a quick learner and detail-oriented individual with sense of urgency, resilience to pressure, can-do attitude, and high curiosity.\n\nTranslates business problems into applied statistical, machine learning, simulation, and optimization solutions to inform actionable business insights and drive business value through automation, revenue generation, and expense and risk reduction. In collaboration with engineering partners, delivers solutions at scale, and enables customer-facing applications. Leverages database, cloud, and programming knowledge to build analytical modeling solutions using statistical and machine learning techniques. Collaborates with other data scientists to improve USAA\u2019s tooling, expanding the company\u2019s library of internal packages and applications. Works with model risk management to validate the results and stability of models before being pushed to production at scale.\n\nWhat you\u2019ll do:\n\u2022 Captures, interprets, and manipulates structured and unstructured data to enable advanced analytical solutions for the business.\n\u2022 Develops scalable, automated solutions using machine learning, simulation, and optimization to deliver business insights and business value.\n\u2022 Selects the appropriate modeling technique and/or technology with consideration to data limitations, application, and business needs.\n\u2022 Develops and deploys models within the Model Development Control (MDC) and Model Risk Management (MRM) framework.\n\u2022 Composes, and assists peers with composing, technical documents for knowledge persistence, risk management, and technical review audiences.\n\u2022 Assesses business needs to propose/recommend analytical and modeling projects to add business value. Works with business and analytics leaders to prioritize analytics and modeling problems/research efforts.\n\u2022 Builds and maintains a robust library of reusable, production-quality algorithms and supporting code, to ensure model development and research efforts are transparent and based on the highest quality data.\n\u2022 Translates complex business request(s) into specific analytical questions, executes on the analysis and/or modeling, and then communicates outcomes to non-technical business colleagues with focus on business action and recommendations.\n\u2022 Manages project milestones, risks, and impediments. Escalates potential issues that could limit project success or implementation.\n\u2022 Develops best practices for engaging with Data Engineering and IT to deploy production-ready analytical assets consistent with modeling best practices and model risk management standards.\n\u2022 Maintains expertise and awareness of cutting-edge techniques. Actively seeks opportunities and materials to learn new techniques, technologies, and methodologies.\n\u2022 Serves as a mentor to junior data scientists in modeling, analytics, and computer science tasks.\n\u2022 Participates in internal communities that drive the maintenance and transformation of data science technologies and culture.\n\u2022 Ensures risks associated with business activities are effectively identified, measured, monitored, and controlled in accordance with risk and compliance policies and procedures.\n\nWhat you have:\n\u2022 Bachelor\u2019s degree in mathematics, computer science, statistics, economics, finance, actuarial sciences, science and engineering, or other similar quantitative discipline; OR 4 years of experience in statistics, mathematics, quantitative analytics, or related experience (in addition to the minimum years of experience required) may be substituted in lieu of degree.\n\u2022 6 years of experience in a predictive analytics or data analysis OR advanced degree (e.g., Master\u2019s, PhD) in mathematics, computer science, statistics, economics, finance, actuarial sciences, science and engineering, or other similar quantitative discipline and 4 years of experience in predictive analytics or data analysis.\n\u2022 4 years of experience in training and validating statistical, physical, machine learning, and other advanced analytics models.\n\u2022 4 years of experience in one or more dynamic scripted language (such as Python, R, etc.) for performing statistical analyses and/or building and scoring AI/ML models.\n\u2022 Proven experience writing code that is easy to follow, well documented, and commented where necessary to explain logic (high code transparency).\n\u2022 Strong experience in querying and preprocessing data from structured and/or unstructured databases using query languages such as SQL, HQL, NoSQL, etc.\n\u2022 Strong experience in working with structured, semi-structured, and unstructured data files such as delimited numeric data files, JSON/XML files, and/or text documents, images, etc.\n\u2022 Demonstrated skill in performing ad-hoc analytics using descriptive, diagnostic, and inferential statistics.\n\u2022 Ability to assess and articulate regulatory implications and expectations of distinct modeling efforts.\n\u2022 Advanced experience with the concepts and technologies associated with classical supervised modeling for prediction such as linear/logistic regression, discriminant analysis, support vector machines, decision trees, forest models, etc.\n\u2022 Advanced experience with the concepts and technologies associated with unsupervised modeling such as k-means clustering, hierarchical/agglomerative clustering, neighbors algorithms, DBSCAN, etc.\n\u2022 Experience guiding and mentoring junior technical staff in business interactions and model building.\n\u2022 Experience communicating analytical and modeling results to non-technical business partners with emphasis on business recommendations and actionable applications of results.\n\nWhat sets you apart:\n\u2022 Master\u2019s degree in a STEM major (math, statistics, or data science) is preferred.\n\u2022 Highly efficient in working on large-sized datasets with heterogeneous data types by using SQL and Python.\n\u2022 Both conceptual understanding and working knowledge of predictive modeling are required, including but not limited to GLM, GBM, Feature Selection, Parameter Tuning, Model Diagnostics, and Performance Evaluation.\n\u2022 Hands-on experience in using various Python packages for the predictive modeling development, including but not limited to H2O, sklearn, statsmodels, scipy, numpy, and pandas.\n\nThe above description reflects the details considered necessary to describe the principal functions of the job and should not be construed as a detailed description of all the work requirements that may be performed in the job.\n\nWhat we offer:\n\nCompensation: USAA has an effective process for assessing market data and establishing ranges to ensure we remain competitive. You are paid within the salary range based on your experience and market data of the position. The actual salary for this role may vary by location. The salary range for this position is: $138,230 - $248,810.\n\nEmployees may be eligible for pay incentives based on overall corporate and individual performance and at the discretion of the USAA Board of Directors.\n\nBenefits: At USAA our employees enjoy best-in-class benefits to support their physical, financial, and emotional wellness. These benefits include comprehensive medical, dental and vision plans, 401(k), pension, life insurance, parental benefits, adoption assistance, paid time off program with paid holidays plus 16 paid volunteer hours, and various wellness programs. Additionally, our career path planning and continuing education assists employees with their professional goals.\n\nFor more details on our outstanding benefits, please visit our benefits page on USAAjobs.com.\n\nApplications for this position are accepted on an ongoing basis, this posting will remain open until the position is filled. Thus, interested candidates are encouraged to apply the same day they view this posting.\n\nUSAA is an Equal Opportunity Employer. All qualified applicants will receive consideration for employment without regard to race, color, religion, sex, sexual orientation, gender identity, national origin, disability, or status as a protected veteran.", "job_is_remote": false, "job_posted_at_timestamp": 1710806400, "job_posted_at_datetime_utc": "2024-03-19T00:00:00.000Z", "job_city": "San Antonio", "job_state": "TX", "job_country": "US", "job_latitude": 29.42519, "job_longitude": -98.49459, "job_benefits": ["dental_coverage", "paid_time_off", "retirement_savings", "health_insurance"], "job_google_link": "https://www.google.com/search?gl=us&hl=en&rciv=jb&q=data+scientist&start=0&ibp=htl;jobs#fpstate=tldetail&htivrt=jobs&htiq=data+scientist&htidocid=Oy7-nIrJA0OG-6fRAAAAAA%3D%3D", "job_offer_expiration_datetime_utc": null, "job_offer_expiration_timestamp": null, "job_required_experience": {"no_experience_required": false, "required_experience_in_months": 72, "experience_mentioned": true, "experience_preferred": false}, "job_required_skills": null, "job_required_education": {"postgraduate_degree": false, "professional_certification": false, "high_school": false, "associates_degree": false, "bachelors_degree": false, "degree_mentioned": true, "degree_preferred": true, "professional_certification_mentioned": false}, "job_experience_in_place_of_education": false, "job_min_salary": null, "job_max_salary": null, "job_salary_currency": null, "job_salary_period": null, "job_highlights": {"Qualifications": ["The candidate must be a quick learner and detail-oriented individual with sense of urgency, resilience to pressure, can-do attitude, and high curiosity", "Bachelor\u2019s degree in mathematics, computer science, statistics, economics, finance, actuarial sciences, science and engineering, or other similar quantitative discipline; OR 4 years of experience in statistics, mathematics, quantitative analytics, or related experience (in addition to the minimum years of experience required) may be substituted in lieu of degree", "6 years of experience in a predictive analytics or data analysis OR advanced degree (e.g., Master\u2019s, PhD) in mathematics, computer science, statistics, economics, finance, actuarial sciences, science and engineering, or other similar quantitative discipline and 4 years of experience in predictive analytics or data analysis", "4 years of experience in training and validating statistical, physical, machine learning, and other advanced analytics models", "4 years of experience in one or more dynamic scripted language (such as Python, R, etc.) for performing statistical analyses and/or building and scoring AI/ML models", "Proven experience writing code that is easy to follow, well documented, and commented where necessary to explain logic (high code transparency)", "Strong experience in querying and preprocessing data from structured and/or unstructured databases using query languages such as SQL, HQL, NoSQL, etc", "Strong experience in working with structured, semi-structured, and unstructured data files such as delimited numeric data files, JSON/XML files, and/or text documents, images, etc", "Demonstrated skill in performing ad-hoc analytics using descriptive, diagnostic, and inferential statistics", "Ability to assess and articulate regulatory implications and expectations of distinct modeling efforts", "Advanced experience with the concepts and technologies associated with classical supervised modeling for prediction such as linear/logistic regression, discriminant analysis, support vector machines, decision trees, forest models, etc", "Advanced experience with the concepts and technologies associated with unsupervised modeling such as k-means clustering, hierarchical/agglomerative clustering, neighbors algorithms, DBSCAN, etc", "Experience guiding and mentoring junior technical staff in business interactions and model building", "Experience communicating analytical and modeling results to non-technical business partners with emphasis on business recommendations and actionable applications of results", "Highly efficient in working on large-sized datasets with heterogeneous data types by using SQL and Python", "Both conceptual understanding and working knowledge of predictive modeling are required, including but not limited to GLM, GBM, Feature Selection, Parameter Tuning, Model Diagnostics, and Performance Evaluation", "Hands-on experience in using various Python packages for the predictive modeling development, including but not limited to H2O, sklearn, statsmodels, scipy, numpy, and pandas"], "Responsibilities": ["In collaboration with engineering partners, delivers solutions at scale, and enables customer-facing applications", "Leverages database, cloud, and programming knowledge to build analytical modeling solutions using statistical and machine learning techniques", "Collaborates with other data scientists to improve USAA\u2019s tooling, expanding the company\u2019s library of internal packages and applications", "Works with model risk management to validate the results and stability of models before being pushed to production at scale", "Captures, interprets, and manipulates structured and unstructured data to enable advanced analytical solutions for the business", "Develops scalable, automated solutions using machine learning, simulation, and optimization to deliver business insights and business value", "Selects the appropriate modeling technique and/or technology with consideration to data limitations, application, and business needs", "Develops and deploys models within the Model Development Control (MDC) and Model Risk Management (MRM) framework", "Composes, and assists peers with composing, technical documents for knowledge persistence, risk management, and technical review audiences", "Assesses business needs to propose/recommend analytical and modeling projects to add business value", "Works with business and analytics leaders to prioritize analytics and modeling problems/research efforts", "Builds and maintains a robust library of reusable, production-quality algorithms and supporting code, to ensure model development and research efforts are transparent and based on the highest quality data", "Translates complex business request(s) into specific analytical questions, executes on the analysis and/or modeling, and then communicates outcomes to non-technical business colleagues with focus on business action and recommendations", "Manages project milestones, risks, and impediments", "Escalates potential issues that could limit project success or implementation", "Develops best practices for engaging with Data Engineering and IT to deploy production-ready analytical assets consistent with modeling best practices and model risk management standards", "Maintains expertise and awareness of cutting-edge techniques", "Actively seeks opportunities and materials to learn new techniques, technologies, and methodologies", "Serves as a mentor to junior data scientists in modeling, analytics, and computer science tasks", "Participates in internal communities that drive the maintenance and transformation of data science technologies and culture", "Ensures risks associated with business activities are effectively identified, measured, monitored, and controlled in accordance with risk and compliance policies and procedures"], "Benefits": ["We offer a flexible work environment that requires an individual to be in the office 4 days per week", "You are paid within the salary range based on your experience and market data of the position", "The actual salary for this role may vary by location", "The salary range for this position is: $138,230 - $248,810", "Employees may be eligible for pay incentives based on overall corporate and individual performance and at the discretion of the USAA Board of Directors", "Benefits: At USAA our employees enjoy best-in-class benefits to support their physical, financial, and emotional wellness", "These benefits include comprehensive medical, dental and vision plans, 401(k), pension, life insurance, parental benefits, adoption assistance, paid time off program with paid holidays plus 16 paid volunteer hours, and various wellness programs", "Additionally, our career path planning and continuing education assists employees with their professional goals"]}, "job_job_title": "Senior", "job_posting_language": "en", "job_onet_soc": "15111100", "job_onet_job_zone": "5", "job_naics_code": "522120", "job_naics_name": "Savings Institutions"}