{"job_id": "VQ_veJ2GHcL5wOGRAAAAAA==", "employer_name": "Cardinal Health", "employer_logo": "https://www.cardinalhealth.com/content/dam/corp/web/logos/logo-main.png", "employer_website": "http://www.cardinal.com", "employer_company_type": "Wholesale", "job_publisher": "Jooble", "job_employment_type": "FULLTIME", "job_title": "Senior Business Development Consultant - Independent Reference Lab", "job_apply_link": "https://jooble.org/jdp/-5656529518721738266", "job_apply_is_direct": false, "job_apply_quality_score": 0.6409, "apply_options": [{"publisher": "Jooble", "apply_link": "https://jooble.org/jdp/-5656529518721738266", "is_direct": false}], "job_description": "What Account Management contributes to Cardinal Health\nDirect Sales is responsible for driving sales and services to new and/or existing customers through face-to-face or telephone contact to meet individual and organizational sales objectives.\n\nAccount Management is responsible for cultivating and maintaining on-going customer relationships with an assigned set of customers. Provides new and existing customers with the best possible service and recommendations in relation to billing inquiries, service requests, improvements to internal and external processes, and other areas of opportunity. Provides product service information to customers and identifies upselling opportunities to maintain and increase income streams from customer relationships.\n\nJob Summary\n\nThe Senior Business Development Consultant will be instrumental in developing and growing corporate relationships within the Independent Reference Laboratory (IRL) Market for the East region. This individual will foster key relationships at the C-suite level, serve as a key stakeholder in the deal modeling process, and serve as a subject matter expert in product, kitting, service, and distribution capabilities for their assigned accounts.\n\nResponsibilities\n\u2022 Utilize performance measurement tools to track and sustain continuous improvement for initiatives and routine business needs.\n\u2022 Review and address contract compliance by Cardinal Health and customer.\n\u2022 Facilitate communication between customer and Cardinal Health sales, operations, customer service and field service to maintain and grow relationship between customer and Cardinal Health.\n\u2022 Define and measure performance of potential/implemented solutions.\n\u2022 Share industry and customer knowledge with Cardinal Health internal customers/Business Units.\n\u2022 Demonstrate comprehensive knowledge of Cardinal Health and customer industry (ex. Terminology, technology, reimbursement, and govt. regulation, etc.)\n\u2022 Take lead role in delivering complex broad-based portfolios of solutions that meet Cardinal Health and customer goals.\n\u2022 Develop and direct implementation of programs designed to address customer profitability, safety, and business continuity objectives.\n\u2022 Conduct customer discovery to identify customer needs and resulting opportunities.\n\u2022 Identify process improvement opportunities for both the customer and Cardinal Health to reduce the \u201ctotal delivered cost.\u201d\n\u2022 Facilitate request for data between customer and Cardinal Health.\n\u2022 Design and facilitate implementation of Service Excellence programs to drive significant service performance improvements for customer including inventory/sourcing, supply chain quality, pricing management and customer service.\n\u2022 Lead all customer acquisition implementations and manage the process with cross functional teams.\n\u2022 Collaboratively work with Cardinal Hospital Lab and Aero-med IRL teams bridging the gaps on channel shift activity while also working to retain all Cardinal brand via the transition.\n\u2022 Drive in-channel customer profitability via product conversions to Cardinal Brand products by successfully utilizing data and analytics tools to help drive savings for the customer and more profitability for Cardinal Health.\n\u2022 Responsible for driving new distribution sales within the Independent Reference Labs market.\n\u2022 Responsible to drive new kitting revenue in assigned territory.\n\u2022 Primary owner/POC of the Corporate relationship with the Independent Reference Lab customer and work collaboratively with both the Aero-med Account Management teams as well as Cardinal Laboratory representatives.\n\nQualifications\n\u2022 Bachelor's degree preferred, or equivalent work experience.\n\u2022 6+ years sales and business development experience highly preferred.\n\u2022 Healthcare industry experience highly preferred in the non-acute, lab, GPO, or kitting space.\n\u2022 Critical thinker and problem solver.\n\u2022 Entrepreneurial approach and mindset.\n\u2022 Strong executive presence.\n\u2022 Must reside in the East region.\n\u2022 Ability and willingness to travel at least 25% in the East Region.\n\nAnticipated pay range: $144,667 - $206,833 includes targeted variable pay\n\nBonus eligible: Yes\n\nBenefits: Cardinal Health offers a wide variety of benefits and programs to support health and well-being.\n\u2022 Medical, dental and vision coverage\n\u2022 Paid time off plan\n\u2022 Health savings account (HSA)\n\u2022 401k savings plan\n\u2022 Access to wages before pay day with myFlexPay\n\u2022 Flexible spending accounts (FSAs)\n\u2022 Short- and long-term disability coverage\n\u2022 Work-Life resources\n\u2022 Paid parental leave\n\u2022 Healthy lifestyle programs\n\nApplication window anticipated to close: 02/08/2024 *if interested in opportunity, please submit application as soon as possible.\n\nCandidates who are back-to-work, people with disabilities, without a college degree, and Veterans are encouraged to apply.\n\nCardinal Health supports an inclusive workplace that values diversity of thought, experience and background. We celebrate the power of our differences to create better solutions for our customers by ensuring employees can be their authentic selves each day. Cardinal Health is an Equal Opportunity/Affirmative Action employer. All qualified applicants will receive consideration for employment without regard to race, religion, color, national origin, ancestry, age, physical or mental disability, sex, sexual orientation, gender identity/expression, pregnancy, veteran status, marital status, creed, status with regard to public assistance, genetic status or any other status protected by federal, state or local law.", "job_is_remote": false, "job_posted_at_timestamp": 1706085343, "job_posted_at_datetime_utc": "2024-01-24T08:35:43.000Z", "job_city": "Delaware", "job_state": "OH", "job_country": "US", "job_latitude": 40.29867, "job_longitude": -83.06796, "job_benefits": ["health_insurance", "retirement_savings", "paid_time_off", "dental_coverage"], "job_google_link": "https://www.google.com/search?gl=us&hl=en&rciv=jb&q=business+development+consultant&start=10&ibp=htl;jobs#fpstate=tldetail&htivrt=jobs&htiq=business+development+consultant&htidocid=VQ_veJ2GHcL5wOGRAAAAAA%3D%3D", "job_offer_expiration_datetime_utc": "2024-04-08T11:29:15.000Z", "job_offer_expiration_timestamp": 1712575755, "job_required_experience": {"no_experience_required": false, "required_experience_in_months": 72, "experience_mentioned": true, "experience_preferred": true}, "job_required_skills": null, "job_required_education": {"postgraduate_degree": false, "professional_certification": false, "high_school": false, "associates_degree": false, "bachelors_degree": false, "degree_mentioned": true, "degree_preferred": false, "professional_certification_mentioned": false}, "job_experience_in_place_of_education": false, "job_min_salary": null, "job_max_salary": null, "job_salary_currency": null, "job_salary_period": null, "job_highlights": {"Qualifications": ["Critical thinker and problem solver", "Entrepreneurial approach and mindset", "Strong executive presence", "Must reside in the East region", "Ability and willingness to travel at least 25% in the East Region"], "Responsibilities": ["Direct Sales is responsible for driving sales and services to new and/or existing customers through face-to-face or telephone contact to meet individual and organizational sales objectives", "Account Management is responsible for cultivating and maintaining on-going customer relationships with an assigned set of customers", "Provides new and existing customers with the best possible service and recommendations in relation to billing inquiries, service requests, improvements to internal and external processes, and other areas of opportunity", "Provides product service information to customers and identifies upselling opportunities to maintain and increase income streams from customer relationships", "The Senior Business Development Consultant will be instrumental in developing and growing corporate relationships within the Independent Reference Laboratory (IRL) Market for the East region", "This individual will foster key relationships at the C-suite level, serve as a key stakeholder in the deal modeling process, and serve as a subject matter expert in product, kitting, service, and distribution capabilities for their assigned accounts", "Utilize performance measurement tools to track and sustain continuous improvement for initiatives and routine business needs", "Review and address contract compliance by Cardinal Health and customer", "Facilitate communication between customer and Cardinal Health sales, operations, customer service and field service to maintain and grow relationship between customer and Cardinal Health", "Define and measure performance of potential/implemented solutions", "Share industry and customer knowledge with Cardinal Health internal customers/Business Units", "Demonstrate comprehensive knowledge of Cardinal Health and customer industry (ex", "Take lead role in delivering complex broad-based portfolios of solutions that meet Cardinal Health and customer goals", "Develop and direct implementation of programs designed to address customer profitability, safety, and business continuity objectives", "Conduct customer discovery to identify customer needs and resulting opportunities", "Identify process improvement opportunities for both the customer and Cardinal Health to reduce the \u201ctotal delivered cost.\u201d", "Facilitate request for data between customer and Cardinal Health", "Design and facilitate implementation of Service Excellence programs to drive significant service performance improvements for customer including inventory/sourcing, supply chain quality, pricing management and customer service", "Lead all customer acquisition implementations and manage the process with cross functional teams", "Collaboratively work with Cardinal Hospital Lab and Aero-med IRL teams bridging the gaps on channel shift activity while also working to retain all Cardinal brand via the transition", "Drive in-channel customer profitability via product conversions to Cardinal Brand products by successfully utilizing data and analytics tools to help drive savings for the customer and more profitability for Cardinal Health", "Responsible for driving new distribution sales within the Independent Reference Labs market", "Responsible to drive new kitting revenue in assigned territory", "Primary owner/POC of the Corporate relationship with the Independent Reference Lab customer and work collaboratively with both the Aero-med Account Management teams as well as Cardinal Laboratory representatives"], "Benefits": ["Anticipated pay range: $144,667 - $206,833 includes targeted variable pay", "Bonus eligible: Yes", "Benefits: Cardinal Health offers a wide variety of benefits and programs to support health and well-being", "Medical, dental and vision coverage", "Paid time off plan", "Health savings account (HSA)", "401k savings plan", "Access to wages before pay day with myFlexPay", "Flexible spending accounts (FSAs)", "Short- and long-term disability coverage", "Work-Life resources", "Paid parental leave", "Healthy lifestyle programs"]}, "job_job_title": "Development consultant", "job_posting_language": "en", "job_onet_soc": "11912100", "job_onet_job_zone": "5", "job_naics_code": "424210", "job_naics_name": "Drugs and Druggists' Sundries Merchant Wholesalers"}