{"job_id": "nHFVliKqEtNy1Gk6AAAAAA==", "employer_name": "Technology Partners", "employer_logo": null, "employer_website": null, "employer_company_type": null, "job_publisher": "Technology Partners", "job_employment_type": "CONTRACTOR", "job_title": "Data Engineer", "job_apply_link": "https://technologypartners.net/jobs/data-engineer-45783/", "job_apply_is_direct": true, "job_apply_quality_score": 0.7707, "apply_options": [{"publisher": "Technology Partners", "apply_link": "https://technologypartners.net/jobs/data-engineer-45783/", "is_direct": true}, {"publisher": "Learn4Good", "apply_link": "https://www.learn4good.com/jobs/maryland-heights/missouri/info_technology/2959874797/e/", "is_direct": false}], "job_description": "Technology Partners is currently seeking a talented Data Engineer. Do you have experience with Golang and building and maintaining data-intensive APIs using a RESTful approach? Let us help you make your next big career move a reality!\n\nWhat You Will Be Doing:\n\nWe are seeking a talented Data Engineer to join our team and play a critical role in transforming complex scientific datasets into innovative software solutions. As a senior member of our data engineering team, you will be responsible for creating distributed analysis capabilities around a wide variety of datasets, contributing to software craftsmanship, and solving unique challenges with real-world impact.\n\nKey Responsibilities:\n\u2022 Collaborate with a team of top-level talent to create distributed analysis capabilities.\n\u2022 Apply deep knowledge of algorithms and data structures to continuously improve and innovate.\n\u2022 Explore relevant technology stacks to find the best fit for each dataset.\n\u2022 Present work at relevant technical conferences.\n\u2022 Build and maintain cloud-based infrastructure on major cloud providers.\n\u2022 Design data models for large-scale databases, either relational or NoSQL.\n\u2022 Maintain containerized application deployments with platforms like Docker.\n\u2022 Utilize stream processing tools like Apache Kafka.\n\u2022 Develop and maintain data-intensive APIs using a RESTful approach.\n\nRequired Skills & Experience:\n\u2022 Bachelor's Degree in Computer Science, Engineering, or a related field.\n\u2022 At least 7 years of experience in software engineering.\n\u2022 At least 2 years of experience with Go.\n\u2022 Proven experience building and maintaining data-intensive APIs using a RESTful approach (minimum 2 years).\n\u2022 Experience with stream processing using Apache Kafka.\n\u2022 Comfort with Unit Testing and Test Driven Development methodologies.\n\u2022 Familiarity with containerized application deployments with Docker.\n\u2022 Ability to build and maintain cloud-based infrastructure on major cloud providers like AWS, Azure, or Google Cloud Platform.\n\u2022 Experience with data modeling for large-scale databases, either relational or NoSQL.\n\nDesired Skills & Experience:\n\u2022 Experience with protocol buffers and gRPC.\n\u2022 Experience with Google Cloud Platform, Apache Beam, Google Cloud Dataflow, Google Kubernetes Engine, or Kubernetes.\n\u2022 Experience working with scientific datasets or quantitative science applied to business problems.\n\u2022 Bioinformatics experience, especially large-scale storage and data mining.\n\nPay: $78.40 - $112 /hr.\n\nWe are interested in every qualified candidate who is eligible to work in the United States. However, we are not able to provide sponsorship at this time or accept candidates who would require a corp-to-corp agreement.\n\nIf this position sounds like you, WE SHOULD TALK!\n\nWe realize our people are our most valuable asset, that is why we offer the following benefits:\n\u2022 Health, Dental, and Vision insurance\n\u2022 401(k) retirement plan\n\u2022 Long and Short-Term disability\n\u2022 Life insurance\n\u2022 Direct deposit\n\u2022 Referral program\n\nYour better future is ready, and we want to put the right tools in your hands to get you there. Let's go!\n\nKeywords: Data Engineering, Software engineer, Cloud Platforms, APIs, Big Data, Scientific Datasets, Agriculture, Go, Docker, Kubernetes, Kafka, SQL, NoSQL, Machine Learning\n\nLooking for more opportunities with Technology Partners? Check out technologypartners.net/jobs!\n\nTechnology Partners is an Equal Opportunity Employer. Technology Partners does not discriminate on the basis of race, color, religion, sex, national origin, age, disability or any other characteristic protected by applicable state or federal civil rights laws.\n\nAll offers of employment at Technology Partners are contingent upon clear results of a thorough background check and drug screening that meet corresponding laws and regulations at the city, state and federal level.\n\nPay ranges are influenced by candidate qualifications, experience, and role specifics, with the actual rate determined considering skills, market conditions, and are subject to change by the employer; pay negotiations follow all state and federal legal guidelines.", "job_is_remote": false, "job_posted_at_timestamp": 1709323941, "job_posted_at_datetime_utc": "2024-03-01T20:12:21.000Z", "job_city": "Maryland Heights", "job_state": "MO", "job_country": "US", "job_latitude": 38.713108, "job_longitude": -90.42984, "job_benefits": ["retirement_savings", "health_insurance", "dental_coverage"], "job_google_link": "https://www.google.com/search?gl=us&hl=en&rciv=jb&q=data+engineering&start=20&ibp=htl;jobs#fpstate=tldetail&htivrt=jobs&htiq=data+engineering&htidocid=nHFVliKqEtNy1Gk6AAAAAA%3D%3D", "job_offer_expiration_datetime_utc": "2025-03-02T10:00:00.000Z", "job_offer_expiration_timestamp": 1740909600, "job_required_experience": {"no_experience_required": false, "required_experience_in_months": 84, "experience_mentioned": true, "experience_preferred": false}, "job_required_skills": null, "job_required_education": {"postgraduate_degree": false, "professional_certification": false, "high_school": false, "associates_degree": false, "bachelors_degree": false, "degree_mentioned": true, "degree_preferred": true, "professional_certification_mentioned": false}, "job_experience_in_place_of_education": false, "job_min_salary": null, "job_max_salary": null, "job_salary_currency": null, "job_salary_period": null, "job_highlights": {"Qualifications": ["Bachelor's Degree in Computer Science, Engineering, or a related field", "At least 7 years of experience in software engineering", "At least 2 years of experience with Go", "Proven experience building and maintaining data-intensive APIs using a RESTful approach (minimum 2 years)", "Experience with stream processing using Apache Kafka", "Comfort with Unit Testing and Test Driven Development methodologies", "Familiarity with containerized application deployments with Docker", "Ability to build and maintain cloud-based infrastructure on major cloud providers like AWS, Azure, or Google Cloud Platform", "Experience with data modeling for large-scale databases, either relational or NoSQL"], "Responsibilities": ["As a senior member of our data engineering team, you will be responsible for creating distributed analysis capabilities around a wide variety of datasets, contributing to software craftsmanship, and solving unique challenges with real-world impact", "Collaborate with a team of top-level talent to create distributed analysis capabilities", "Apply deep knowledge of algorithms and data structures to continuously improve and innovate", "Explore relevant technology stacks to find the best fit for each dataset", "Present work at relevant technical conferences", "Build and maintain cloud-based infrastructure on major cloud providers", "Design data models for large-scale databases, either relational or NoSQL", "Maintain containerized application deployments with platforms like Docker", "Utilize stream processing tools like Apache Kafka", "Develop and maintain data-intensive APIs using a RESTful approach"], "Benefits": ["Pay: $78.40 - $112 /hr", "Health, Dental, and Vision insurance", "401(k) retirement plan", "Long and Short-Term disability", "Life insurance", "Direct deposit", "Referral program"]}, "job_job_title": "Data engineer", "job_posting_language": "en", "job_onet_soc": "15113200", "job_onet_job_zone": "4", "job_occupational_categories": ["Technology"]}