{"job_id": "HAtp3gCJ3ZuVygDHAAAAAA==", "employer_name": "Yum! Brands", "employer_logo": "https://upload.wikimedia.org/wikipedia/commons/thumb/5/59/Yum%21_Brands_logo.svg/1200px-Yum%21_Brands_logo.svg.png", "employer_website": "http://www.yum.com", "employer_company_type": "Restaurant", "job_publisher": "Built In", "job_employment_type": "FULLTIME", "job_title": "Manager, Customer & Marketing Analytics | Data", "job_apply_link": "https://builtin.com/job/manager-customer-marketing-analytics-data/2363681", "job_apply_is_direct": false, "job_apply_quality_score": 0.688, "apply_options": [{"publisher": "Built In", "apply_link": "https://builtin.com/job/manager-customer-marketing-analytics-data/2363681", "is_direct": false}], "job_description": "Job Description\n\nWe are searching for a Marketing & Customer Analytics expert with a deep technical foundation and a knack for translating complex analyses into actionable business insights. As a Manager of Marketing Analytics, you will lead Pizza Hut to new heights by owning and executing comprehensive analyses and projects from start to finish. This encompasses everything from opportunity identification and problem scoping to analysis execution and synthesizing results for stakeholders and leadership.\n\nWithin the Marketing & Customer Analytics group, you'll play a pivotal role in leveraging data and technology for strategic decision-making across the organization. Your work will span the full spectrum of Marketing Analytics, including market testing of new products, evaluation of disruptive value constructs through full experimental design, and gaining deeper customer insights using our new Customer Data Platform.\n\nResponsibilities\n\u2022 Own end-to-end identification of opportunities, development, and execution of advanced modeling for customer behavior (Churn model, Customer Lifetime value, Causal Inference for Treatment variables)\n\u2022 Execute, improve, and streamline data processes to enhance understanding of our business health and performance using SQL, Python/R, and Excel among other analytical tools.\n\u2022 Develop a comprehensive view of our customers, integrating data from our Customer Data Platform to inform strategic decisions.\n\u2022 Lead market testing for new products and value constructs, employing full experimental design to validate business strategies.\n\u2022 Craft and deliver presentations that translate complex analytical findings into clear, impactful business statements and conclusions.\n\u2022 Foster strong partnerships with stakeholders, providing actionable insights to drive business opportunities.\n\u2022 Stay at the forefront of industry trends, continuously updating your toolkit with new analytics tools and techniques.\n\u2022 Collaborate with cross-functional teams to uncover business opportunities and influence strategy through data-driven insights.\n\nMinimum Requirements\n\nEducation: 8+ years with a Bachelor's degree, or 5+ years with a Master's Degree, or 3+ years with a Doctorate in Computer Science, Statistics, Mathematics, or a related field.\n\nExperience & Skills: Required\n\u2022 7+ years of experience in analytics, with a specialized focus on marketing and/or customer analytics.\n\u2022 Demonstrated technical expertise in SQL, with the ability to conduct sophisticated analyses using Python or R, and proficiency in Excel.\n\u2022 Understanding and Experience applying advanced statistical methods to inform business strategies, while validating the underlying assumptions\n\u2022 Exceptional ability to communicate technical subjects clearly and concisely, turning complex analyses into pithy, business-oriented statements and conclusions.\n\u2022 Strong analytical and problem-solving skills, capable of breaking down complex issues into manageable components while focusing on critical business objectives.\n\u2022 Experience with data management and manipulation tools, with a willingness to broaden this skill set.\n\u2022 Experience in developing and maintaining dashboard-based reporting through BI tools (Tableau or Power BI, with a preference for Tableau).\n\nKey Characteristics:\n\u2022 Outstanding stakeholder management and partnership capabilities.\n\u2022 Visionary thinking, with the ability to always see the bigger picture.\n\u2022 Proficiency in building decks and translating intricate details into understandable takeaways.\n\u2022 Technically astute, with a strong grounding in SQL and the conversion of insights to practical applications\n\nWe are looking for a candidate who is not only passionate about customer and marketing analytics but also possesses a strong analytical mindset and a desire to drive significant impact in a dynamic environment. If you excel at turning data into strategic insights and are eager to lead in the realm of Marketing Analytics, Pizza Hut welcomes you to apply.\n\nSalary Range: $127,300 to $149,800 annually + bonus eligibility. This is the expected salary range for this position. Ultimately, in determining pay, we'll consider the successful candidate's location, experience, and other job-related factors.\n\nBenefits: Employees (and their eligible family members) may enroll in the following types of insurance coverage: medical, dental, vision, legal, and accidental death and dismemberment, as well as FSA/HSA (depending on enrolled medical plan). Yum! also provides short-term disability, long-term disability, and life insurance. Employees may enroll in our 401(k) plan. Yum! provides 4 weeks of vacation, paid sick leave, 10 paid holidays, a floating day off and 2 paid days for volunteer time each calendar year. To learn more about working at Yum! -Click here.\n\nAt Yum!, one of our core values is to Believe in ALL People. This means seeing the value in everyone and unlocking their full potential to be their best self. YUM! Brands, Inc. (including its subsidiaries Yum Restaurant Services Group, LLC (\"YRSG\") and Yum Connect, LLC (\"Yum Digital and Technology\")(collectively, \"Yum\") is proud to be an equal opportunity employer and is committed to equity, inclusion, and belonging for all dimensions of diversity. We do not discriminate based on race, color, religion, sex, sexual orientation, gender identity, national origin, veteran status, disability status, age, or any other protected characteristic. Yum! is committed to working with and providing reasonable accommodation to applicants with disabilities or special needs.\n\nUS Job Seekers/Employees - Click here to view the \"Know Your Rights\" poster and supplement and the Pay Transparency Policy Statement.\n\nAbout Us\n\nWho We Are\n\nFounded in 1958, Pizza Hut - a subsidiary of Yum! Brands, Inc. - now operates more than 18,000 restaurants in more than 100 countries. Pizza Hut is leading the way in providing customers with great experiences, innovating with technology and new products, as well as delivering exceptional service.\n\nOur People & Culture\n\nWe're looking for people who LOVE pizza and thrive in a fun, past paced, and customer-centric environment. At our corporate campuses, Pizza Hut has created the perfect place for you to grow your career. Every day, you'll work to support our franchisees and teams across the U.S., continuously challenging yourself to feed more possibilities. In return, we'll provide professional development and career growth opportunities so that you can become your best and achieve your goals. And we'll sweeten the deal by immersing you in our world-class recognition culture and providing a robust array of benefits, some highlights include:\n\u2022 Hybrid work schedule and year-round half day Friday's\n\u2022 Onsite childcare through Bright Horizons\n\u2022 Onsite dining center\n\u2022 Onsite dry cleaning and laundry services\n\u2022 24/7 Onsite gym with fitness classes and personal trainer sessions\n\u2022 4 weeks of vacation per year plus holidays and time off for volunteering\n\u2022 Tuition reimbursement and education benefits\n\u2022 Generous parental leave for all new parents and adoption assistance program\n\u2022 401(k) with a 6% matching contribution from Yum! Brands with immediate vesting\n\u2022 Comprehensive medical & dental including prescription drug benefits and 100% preventive care\n\u2022 And more honestly to many to name, visit here for more info\n\nGiving Back\n\nAs a global company, Pizza Hut aims to make the world better by acting responsibly with respect to food, planet and people. Whether it's donating food through the Harvest Program or supporting literacy with the Pizza Hut BOOK IT! Program - the company, our franchisees and our team members are committed to improving the communities we serve.\n\nPizza Hut is an equal opportunity workplace and committed to fostering an inclusive, diverse culture. All qualified applicants will receive consideration for employment without regard to race, color, religion, sex (including pregnancy, sexual orientation, or gender identity), national origin, age, disability and genetic information (including family medical history).", "job_is_remote": false, "job_posted_at_timestamp": 1709788500, "job_posted_at_datetime_utc": "2024-03-07T05:15:00.000Z", "job_city": null, "job_state": "TX", "job_country": "US", "job_latitude": 32.707874, "job_longitude": -96.92091, "job_benefits": ["retirement_savings", "health_insurance", "dental_coverage", "paid_time_off"], "job_google_link": "https://www.google.com/search?gl=us&hl=en&rciv=jb&q=manager+of+marketing+analytics&start=30&ibp=htl;jobs#fpstate=tldetail&htivrt=jobs&htiq=manager+of+marketing+analytics&htidocid=HAtp3gCJ3ZuVygDHAAAAAA%3D%3D", "job_offer_expiration_datetime_utc": "2024-04-06T00:00:00.000Z", "job_offer_expiration_timestamp": 1712361600, "job_required_experience": {"no_experience_required": false, "required_experience_in_months": 84, "experience_mentioned": true, "experience_preferred": false}, "job_required_skills": null, "job_required_education": {"postgraduate_degree": false, "professional_certification": false, "high_school": false, "associates_degree": false, "bachelors_degree": true, "degree_mentioned": true, "degree_preferred": false, "professional_certification_mentioned": false}, "job_experience_in_place_of_education": false, "job_min_salary": 127300, "job_max_salary": 149800, "job_salary_currency": "USD", "job_salary_period": "YEAR", "job_highlights": {"Qualifications": ["Education: 8+ years with a Bachelor's degree, or 5+ years with a Master's Degree, or 3+ years with a Doctorate in Computer Science, Statistics, Mathematics, or a related field", "7+ years of experience in analytics, with a specialized focus on marketing and/or customer analytics", "Demonstrated technical expertise in SQL, with the ability to conduct sophisticated analyses using Python or R, and proficiency in Excel", "Understanding and Experience applying advanced statistical methods to inform business strategies, while validating the underlying assumptions", "Exceptional ability to communicate technical subjects clearly and concisely, turning complex analyses into pithy, business-oriented statements and conclusions", "Strong analytical and problem-solving skills, capable of breaking down complex issues into manageable components while focusing on critical business objectives", "Experience with data management and manipulation tools, with a willingness to broaden this skill set", "Experience in developing and maintaining dashboard-based reporting through BI tools (Tableau or Power BI, with a preference for Tableau)", "Outstanding stakeholder management and partnership capabilities", "Visionary thinking, with the ability to always see the bigger picture", "Proficiency in building decks and translating intricate details into understandable takeaways", "Technically astute, with a strong grounding in SQL and the conversion of insights to practical applications", "We are looking for a candidate who is not only passionate about customer and marketing analytics but also possesses a strong analytical mindset and a desire to drive significant impact in a dynamic environment"], "Responsibilities": ["As a Manager of Marketing Analytics, you will lead Pizza Hut to new heights by owning and executing comprehensive analyses and projects from start to finish", "This encompasses everything from opportunity identification and problem scoping to analysis execution and synthesizing results for stakeholders and leadership", "Within the Marketing & Customer Analytics group, you'll play a pivotal role in leveraging data and technology for strategic decision-making across the organization", "Your work will span the full spectrum of Marketing Analytics, including market testing of new products, evaluation of disruptive value constructs through full experimental design, and gaining deeper customer insights using our new Customer Data Platform", "Own end-to-end identification of opportunities, development, and execution of advanced modeling for customer behavior (Churn model, Customer Lifetime value, Causal Inference for Treatment variables)", "Execute, improve, and streamline data processes to enhance understanding of our business health and performance using SQL, Python/R, and Excel among other analytical tools", "Develop a comprehensive view of our customers, integrating data from our Customer Data Platform to inform strategic decisions", "Lead market testing for new products and value constructs, employing full experimental design to validate business strategies", "Craft and deliver presentations that translate complex analytical findings into clear, impactful business statements and conclusions", "Foster strong partnerships with stakeholders, providing actionable insights to drive business opportunities", "Stay at the forefront of industry trends, continuously updating your toolkit with new analytics tools and techniques", "Collaborate with cross-functional teams to uncover business opportunities and influence strategy through data-driven insights", "is committed to working with and providing reasonable accommodation to applicants with disabilities or special needs"], "Benefits": ["Salary Range: $127,300 to $149,800 annually + bonus eligibility", "This is the expected salary range for this position", "Ultimately, in determining pay, we'll consider the successful candidate's location, experience, and other job-related factors", "Benefits: Employees (and their eligible family members) may enroll in the following types of insurance coverage: medical, dental, vision, legal, and accidental death and dismemberment, as well as FSA/HSA (depending on enrolled medical plan)", "also provides short-term disability, long-term disability, and life insurance", "Employees may enroll in our 401(k) plan", "provides 4 weeks of vacation, paid sick leave, 10 paid holidays, a floating day off and 2 paid days for volunteer time each calendar year", "Hybrid work schedule and year-round half day Friday's", "Onsite childcare through Bright Horizons", "24/7 Onsite gym with fitness classes and personal trainer sessions", "Tuition reimbursement and education benefits", "Generous parental leave for all new parents and adoption assistance program", "401(k) with a 6% matching contribution from Yum!", "Brands with immediate vesting", "Comprehensive medical & dental including prescription drug benefits and 100% preventive care"]}, "job_job_title": "Manager", "job_posting_language": "en", "job_onet_soc": "11202100", "job_onet_job_zone": "4", "job_naics_code": "722", "job_naics_name": "Restaurant"}