{"job_id": "IaoQbR76y-5Sd8ImAAAAAA==", "employer_name": "Altair Engineering, Inc.", "employer_logo": "https://www.altair.com/images/icons/Altair.svg", "employer_website": "http://www.altair.com", "employer_company_type": "Information", "job_publisher": "Salary.com", "job_employment_type": "FULLTIME", "job_title": "Field Marketing Manager Data Analytics, EMEA", "job_apply_link": "https://www.salary.com/job/altair-engineering-inc/field-marketing-manager-data-analytics-emea/j202310140136221323806", "job_apply_is_direct": false, "job_apply_quality_score": 0.6153, "apply_options": [{"publisher": "Salary.com", "apply_link": "https://www.salary.com/job/altair-engineering-inc/field-marketing-manager-data-analytics-emea/j202310140136221323806", "is_direct": false}], "job_description": "Transforming the Future with the Convergence of Simulation and Data\n\nField Marketing Manager Data Analytics, EMEA\n\nJob Summary\n\nFunction/Team:\n\nField Marketing Team\n\nLocation:\n\nLondon, Paris or Munich a possibility\n\nContract Type:\n\nPermanent\n\nReporting Line:\n\nDirector of Marketing, Data Analytics\n\nWork Hours:\n\n40 hours per week\n\nWho We Are\n\nAltair is leading the global convergence evolution toward smart, connected everything by delivering ground-breaking solutions in data analytics, simulation, high-performance computing, and smart connected products (IoT).\n\nYou will find a different culture at Altair in the way we work, how we interact and the collaborative approach we bring to projects. We pride ourselves on a business culture that enables open, creative thinking, and we deeply value our employees and their contributions towards our clients' success, as well as our own. Your ideas are heard, your efforts are visible and your work impacts company growth. Communication is open and teamwork is encouraged.\n\nWhat You Will Do\n\nReporting to the Global Director of Marketing, Data Analytics the Field Marketing Manager DA, EMEA is responsible for the creation and execution of marketing strategies, campaigns and events for Altair\u2019s data analytics business branch in EMEA.\n\nAs part of the Altair data analytics field marketing team, you will collaborate closely with all Altair marketing teams (field, IMC, solutions), sales enablement and the data analytics sales leadership. Qualified candidates must be strategic thinkers and creative, while being hands on in executing campaigns. They should have a good market understanding of the data analytics marketing in EMEA, be strong communicators and team spirited.\n\nThe importance of creating and managing global campaigns has increased dramatically as the focus of marketing is shifting towards engagement creation, contextual marketing and lifecycle marketing. At Altair we are building upon our global campaign approach to innovate and execute global campaigns through multichannel marketing.\n\nThis Field Marketing Manager DA, EMEA will have manage one additional team member and be responsible for designing and executing integrated, GDPR compliant marketing campaigns, driving awareness and lead generation activities that support the EMEA business plan. This includes developing a mix of promotional creative content and activities including online events, live-events, seminars, direct mail, email, advertising and others as need determines to drive lead generation and awareness for all global regions and reporting out on success of those activities.\n\nResponsibilities:\n\n\u00b7 Accountable for campaign architecture, execution, delivery and measurement for EMEA region.\n\n\u00b7 Responsible for creating EMEA campaigns tied to business segment, personas and the customer journey lifecycle.\n\n\u00b7 Campaign plan design and execution tied to corporate goals/themes and measuring effectiveness & success of those programs; analytical skills required.\n\n\u00b7 Balance project scope and budget\n\n\u00b7 Develop bill of materials per campaign to include an integrated marketing mix of offline and online elements.\n\n\u00b7 Collaborating with other marketing team members and regional stakeholders to develop campaign assets on time,\n\n\u00b7 Working with the Sales organization to ensure appropriate and timely follow-up of marketing generated leads.\n\n\u00b7 Support channel partner/vendor relationships and Altair partner marketing teams to ensure seamless implementation of new marketing initiatives\n\n\u00b7 Plan and manage Partner Marketing programs in region\n\n\u00b7 Analyzing campaign effectiveness, delivering results to all stakeholders and management\n\n\u00b7 Coordination of regional event logistics and key strategic decisions with the regional marketing teams to ensure successful execution and ROI.\n\n\u00b7 Manage lead upload and measurement process, process, analyze results and create reporting for event campaigns. Utilize these reports to make approval recommendations for future events.\n\n\u00b7 Initiate recommendations to improve marketing and event processes and increasing overall efficiencies. Actively researches, learns and incorporates new means and methods whenever and wherever possible to improve processes.\n\n\u00b7 Confident in leading multiple projects.\n\nWhat You Will Need\n\n\u00b7 Bachelor\u2019s Degree required in Marketing, Communications, or a related discipline. Minimum of 3 years\u2019 experience for a software or technology provider; Minimum of 5 years\u2019 experience working with technology partners of various types and managing relationships.\n\n\u00b7 Knowledge of GDPR and creating campaigns that are GDPR compliant.\n\n\u00b7 Experience in software marketing.\n\n\u00b7 Experience in software marketing for data analytics is a plus.\n\n\u00b7 Proven track record of successfully creating customer campaign content.\n\n\u00b7 An understanding of powerful story-telling with a creative eye for design.\n\n\u00b7 Modern sales and marketing technology & tools understanding like the use of CRM systems, marketing automation systems, google analytics and techniques to create SEM, SEO, retargeting, banner, display advertisement and landing pages a plus. Ideally experienced with HubSpot, SalesForce etc.\n\n\u00b7 Exceptional communication skills: must be able to articulate a clear, persuasive argument and present data in an effective and actionable manner orally and in writing with both internal and external teams.\n\n\u00b7 Excellent collaboration, organizational and project management skills\n\n\u00b7 Ability to effectively manage time, prioritize tasks, deliver high-quality work, under extreme pressure at times, within a dynamic organization.\n\n\u00b7 Ability to effectively analyze and report out on campaign results and leverage data when developing new campaigns\n\nPlace of work\n\nThe future Field Marketing Manager DA, EMEA will be located in London, Paris or Munich.\n\nMust have flexibility for travel up to 20% of the time.\n\nHow You Will Be Successful:\n\n\u00b7 Envision the Future\n\n\u00b7 Communicate Honestly and Broadly\n\n\u00b7 Seek Technology and Business \u201cFirsts\u201d\n\n\u00b7 Embrace Diversity and Take Risks\n\nWhat We Offer:\n\n\u00b7 Competitive salary on offer (flexible dependent on experience of candidate).\n\n\u00b7 25 days annual leave entitlement plus local bank holidays and 3 days Christmas shutdown (pro-rata based on full time hours).\n\n\u00b7 Flexible / hybrid working environment.\n\n\u00b7 Competitive benefits package post-probationary period including but not limited to:\n\u2022 Comprehensive pension scheme with enhanced employer contribution \u2013 10%.\n\u2022 Monthly gym membership for self\n\u2022 Health Insurance for self and family\n\u2022 Optical/Dental Cashplan for self and spouse\n\u2022 Life Insurance at 4x salary benefit\n\u2022 Income protection and comprehensive sick pay cover/enhanced statutory schemes\n\u2022 Regular team rewards including team building events/dinners/activities.\n\n\u00b7 Training and development opportunities\n\n\u00b7 Additional Charity Day for each employee\n\n\u00b7 Eligibility for our Employee Stock Purchase Program (ESPP)\n\nWhy Work with Us:\n\nAltair is a global technology company that provides software and cloud solutions in the areas of data analytics, product development, and high-performance computing (HPC). Altair enables organizations in nearly every industry to compete more effectively in a connected world, while creating a more sustainable future. With more than 3,000 engineers, scientists and creative thinkers in 25 countries, we help solve our customer\u2019s toughest challenges and deliver unparalleled service, helping the innovators innovate, drive better decisions, and turn today\u2019s problems into tomorrow\u2019s opportunities.\n\nOur vision is to transform customer decision making with data analytics, simulation, and high-performance computing.\n\nFor more than 30 years, we have been helping our customers integrate electronics and controls with mechanical design to expand product value, develop AI, simulation and data-driven digital twins to drive better decisions, and deliver advanced HPC and cloud solutions to support unlimited idea exploration. To learn more, please visit altair.com .\n\nReady to go? #ONLYFORWARD", "job_is_remote": false, "job_posted_at_timestamp": 1697328000, "job_posted_at_datetime_utc": "2023-10-15T00:00:00.000Z", "job_city": null, "job_state": null, "job_country": "US", "job_latitude": 37.09024, "job_longitude": -95.71289, "job_benefits": ["health_insurance"], "job_google_link": "https://www.google.com/search?gl=us&hl=en&rciv=jb&q=manager+of+marketing+analytics&start=60&ibp=htl;jobs#fpstate=tldetail&htivrt=jobs&htiq=manager+of+marketing+analytics&htidocid=IaoQbR76y-5Sd8ImAAAAAA%3D%3D", "job_offer_expiration_datetime_utc": "2024-04-14T00:00:00.000Z", "job_offer_expiration_timestamp": 1713052800, "job_required_experience": {"no_experience_required": false, "required_experience_in_months": 60, "experience_mentioned": true, "experience_preferred": true}, "job_required_skills": null, "job_required_education": {"postgraduate_degree": false, "professional_certification": false, "high_school": false, "associates_degree": false, "bachelors_degree": false, "degree_mentioned": true, "degree_preferred": false, "professional_certification_mentioned": false}, "job_experience_in_place_of_education": false, "job_min_salary": null, "job_max_salary": null, "job_salary_currency": null, "job_salary_period": null, "job_highlights": {"Qualifications": ["Qualified candidates must be strategic thinkers and creative, while being hands on in executing campaigns", "They should have a good market understanding of the data analytics marketing in EMEA, be strong communicators and team spirited", "Bachelor\u2019s Degree required in Marketing, Communications, or a related discipline", "Minimum of 3 years\u2019 experience for a software or technology provider; Minimum of 5 years\u2019 experience working with technology partners of various types and managing relationships", "Knowledge of GDPR and creating campaigns that are GDPR compliant", "Experience in software marketing", "Proven track record of successfully creating customer campaign content", "An understanding of powerful story-telling with a creative eye for design", "Ideally experienced with HubSpot, SalesForce etc", "Exceptional communication skills: must be able to articulate a clear, persuasive argument and present data in an effective and actionable manner orally and in writing with both internal and external teams", "Excellent collaboration, organizational and project management skills", "Ability to effectively manage time, prioritize tasks, deliver high-quality work, under extreme pressure at times, within a dynamic organization", "Ability to effectively analyze and report out on campaign results and leverage data when developing new campaigns", "Must have flexibility for travel up to 20% of the time"], "Responsibilities": ["Reporting to the Global Director of Marketing, Data Analytics the Field Marketing Manager DA, EMEA is responsible for the creation and execution of marketing strategies, campaigns and events for Altair\u2019s data analytics business branch in EMEA", "As part of the Altair data analytics field marketing team, you will collaborate closely with all Altair marketing teams (field, IMC, solutions), sales enablement and the data analytics sales leadership", "The importance of creating and managing global campaigns has increased dramatically as the focus of marketing is shifting towards engagement creation, contextual marketing and lifecycle marketing", "At Altair we are building upon our global campaign approach to innovate and execute global campaigns through multichannel marketing", "This Field Marketing Manager DA, EMEA will have manage one additional team member and be responsible for designing and executing integrated, GDPR compliant marketing campaigns, driving awareness and lead generation activities that support the EMEA business plan", "This includes developing a mix of promotional creative content and activities including online events, live-events, seminars, direct mail, email, advertising and others as need determines to drive lead generation and awareness for all global regions and reporting out on success of those activities", "Accountable for campaign architecture, execution, delivery and measurement for EMEA region", "Responsible for creating EMEA campaigns tied to business segment, personas and the customer journey lifecycle", "Campaign plan design and execution tied to corporate goals/themes and measuring effectiveness & success of those programs; analytical skills required", "Balance project scope and budget", "Develop bill of materials per campaign to include an integrated marketing mix of offline and online elements", "Collaborating with other marketing team members and regional stakeholders to develop campaign assets on time,", "Working with the Sales organization to ensure appropriate and timely follow-up of marketing generated leads", "Support channel partner/vendor relationships and Altair partner marketing teams to ensure seamless implementation of new marketing initiatives", "Plan and manage Partner Marketing programs in region", "Analyzing campaign effectiveness, delivering results to all stakeholders and management", "Coordination of regional event logistics and key strategic decisions with the regional marketing teams to ensure successful execution and ROI", "Manage lead upload and measurement process, process, analyze results and create reporting for event campaigns", "Utilize these reports to make approval recommendations for future events", "Initiate recommendations to improve marketing and event processes and increasing overall efficiencies", "Actively researches, learns and incorporates new means and methods whenever and wherever possible to improve processes", "Confident in leading multiple projects", "Communicate Honestly and Broadly"], "Benefits": ["40 hours per week", "Competitive salary on offer (flexible dependent on experience of candidate)", "25 days annual leave entitlement plus local bank holidays and 3 days Christmas shutdown (pro-rata based on full time hours)", "Flexible / hybrid working environment", "Competitive benefits package post-probationary period including but not limited to:", "Comprehensive pension scheme with enhanced employer contribution \u2013 10%", "Monthly gym membership for self", "Health Insurance for self and family", "Optical/Dental Cashplan for self and spouse", "Life Insurance at 4x salary benefit", "Income protection and comprehensive sick pay cover/enhanced statutory schemes", "Regular team rewards including team building events/dinners/activities", "Training and development opportunities", "Additional Charity Day for each employee", "Eligibility for our Employee Stock Purchase Program (ESPP)"]}, "job_job_title": "Marketing manager", "job_posting_language": "en", "job_onet_soc": "11202100", "job_onet_job_zone": "4", "job_naics_code": "5112", "job_naics_name": "Software Publishers"}