{"job_id": "vKa8kkXVHnYu2c8WAAAAAA==", "employer_name": "Sony Electronics, Inc.", "employer_logo": null, "employer_website": null, "employer_company_type": null, "job_publisher": "Jooble", "job_employment_type": "TEMPORARY", "job_title": "Senior Director, Sales", "job_apply_link": "https://jooble.org/jdp/-505841642143661703", "job_apply_is_direct": false, "job_apply_quality_score": 0.6536, "apply_options": [{"publisher": "Jooble", "apply_link": "https://jooble.org/jdp/-505841642143661703", "is_direct": false}, {"publisher": "LinkedIn", "apply_link": "https://www.linkedin.com/jobs/view/senior-director-sales-at-sony-biotechnology-inc-3760321627", "is_direct": false}, {"publisher": "Salary.com", "apply_link": "https://www.salary.com/job/sony-corporation-of-america/senior-director-sales/j202311211937559769607", "is_direct": false}, {"publisher": "Milwaukee Jobs", "apply_link": "https://www.milwaukeejobs.com/job/detail/77289100/Senior-Director-Sales", "is_direct": false}, {"publisher": "BeBee", "apply_link": "https://us.bebee.com/job/20240225-24bdc651c39351d9b2f8abc7d3dcdf76", "is_direct": false}, {"publisher": "Talentify", "apply_link": "https://www.talentify.io/job/senior-director-sales-san-jose-california-sony-jr-115470", "is_direct": false}, {"publisher": "Paragoncapllc.com", "apply_link": "https://paragoncapllc.com/gig/job/senior-director-sales-at-knewin-san-jose-ca-aW53dmdjZ0ZnSjNRc0s0L0FkZzNZWStwc2c9PQ==", "is_direct": false}, {"publisher": "Learn4Good", "apply_link": "https://www.learn4good.com/jobs/san-jose/california/sales/2953947425/e/", "is_direct": false}], "job_description": "Sony Biotechnology Inc., based in San Jose, California, supplies advanced flow cytometry analysis and sorting technology for use in life science research. It markets products to private and public research institutions, pharmaceutical and biotechnology companies, and large medical centers. Over the years, Sony Biotechnology products have received numerous outstanding new product awards as well as technology awards including the Frost & Sullivan Emerging Technology award, and the Milestone Award. To learn more:\n\nPOSITION SUMMARY\n\nThe Senior Director, Sales will be responsible for managing and developing a highly skilled team of Sales Specialists and Field Applications Specialist. The role reports directly to the Chief Executive Officer.\n\nIn conjunction with the Marketing department, the incumbent will be accountable for developing sales strategies to meet overall sales growth for instruments, reagents/consumables and service. In addition, the Senior Director, Sales will be responsible for implementing strategies to build and maintain relationships with key customers and maintain a high degree of customer satisfaction.\n\nJOB RESPONSIBILITIES\n\u2022 Responsible for developing, implementing and driving the North American sales strategy.\n\u2022 Collaborate with other departments, such as Marketing, Customer Service and Operations to meet, align and implement initiatives to ensure continued growth.\n\u2022 Develop and execute effective tactical plans and territory development/growth strategies to increase market share and drive revenue growth.\n\u2022 Proficient in use of CRM (preferably Salesforce.com) to manage field Sales activities.\n\u2022 Responsible for analyzing sales metrics to determine effectiveness of sales tactics and growth initiatives\n\u2022 Responsible for the regional demand forecast process to deliver on business KPIs.\n\u2022 Build and maintain strong relationships with key industry stakeholders, customers & partners.\n\u2022 Responsible for presenting the sales strategy and progress to Sr. Management.\n\u2022 Demonstrated success in ability to balance the need to achieve current business goals with planning and investment for future growth.\n\u2022 Attend and present at external customer meetings and internal meetings with other company functions necessary to perform duties and aid business development.\n\u2022 Attend training and develop relevant knowledge, techniques and skills.\n\u2022 Staying abreast of and reporting on industry trends, competitive landscape, and regulatory changes to inform sales strategies and tactics.\n\u2022 Support contracts/proposals/quotations within company guidelines.\n\u2022 Lead, mentor, and manage a high-performing sales and field application team, fostering a culture of excellence and accountability.\n\u2022 Successfully attract, develop, and retain highly qualified field associates.\n\u2022 Travel required as per the business needs.\n\nQUALIFICATIONS FOR POSITION\n\nYour qualifications and experience should include:\n\u2022 A minimum of 10 years of leadership experience in a complex, dynamic, commercial environment operating across the Americas region\n\u2022 Bachelor's degree in Business, Life Sciences, or a related field. An MBA or other advanced degree is a plus.\n\u2022 A results-oriented mindset, with a strong drive to exceed sales targets and contribute to business growth.\n\u2022 Proven experience in leading enterprise sales and implementing go-to-market strategies.\n\u2022 Deep understanding of the life sciences & technology industry, including trends, challenges, and opportunities.\n\u2022 Proficiency in using Salesforce.com or a similar Customer relationship management system.\n\u2022 Strong leadership skills with a proven ability to influence, inspire and lead change in a high performing Sales team\n\u2022 Excellent communication (verbal and written) skills\n\u2022 Well-developed relationship-building skills, with the ability to engage effectively with a wide range of stakeholders.\n\u2022 Proven ability to deal with difficult problems or issues; an ability to provide a balanced perspective that optimizes the trade-offs between the business financials, the business opportunities, the company strategy, and the external environment\n\nIn addition to competitive pay and benefits, we offer an environment and culture that promotes Diversity, Equity, and Inclusion. We are committed to creating an inclusive employee experience for you to thrive as part of Sony's purpose to \"fill the world with emotion through the power of creativity and technology\".\n\nBenefits:\n\nSCA offers benefits-eligible employees (generally regular employees scheduled to work 20 or more hours a week) a comprehensive benefits program that offers coverage and support for employees and their family's physical, emotional, and financial well-being.\n\nWhat we offer you:\n\u2022 Comprehensive medical, prescription drug, dental, and vision coverage with coverage for spouses/domestic partners and child dependents, including access to a Health Savings Account (HSA) and Flexible Spending Account (FSA)\n\u2022 Employee assistance plan and comprehensive behavioral health benefits\n\u2022 Fertility benefits, including surrogacy, and adoption assistance programs\n\u2022 Basic and supplemental life insurance for employees as well as supplemental life insurance coverage for their spouses/domestic partners and children\n\u2022 Voluntary benefits such as group legal, identity theft protection, accident, and hospital indemnity insurance\n\u2022 Short-term & long-term disability plans\n\u2022 Paid parental and caregiver leave\n\u2022 401(k) Plan with pre-tax, Roth, and after-tax options and company match which vests immediately\n\u2022 Education assistance and student loan programs\n\nOther Programs:\n\u2022 Time off to include vacation, paid holidays, sick leave, Summer Fridays (early release), and a winter break between Christmas and New Year's Day (based on business needs)\n\u2022 Referral bonuses (subject to eligibility)\n\u2022 Matching gift program\n\u2022 A wide variety of employee business resource groups (EBRGs)\n\u2022 Special discounts on Sony products, offered exclusively to Sony employees\n\u2022 Employee stock purchase plan (Sony covers commissions and fees for your Sony stock purchases made through after-tax payroll deductions)\n\u2022 Annual incentive bonus\n\nThe anticipated annual base salary for this position is $250,000 to $260,000. This range does not include any other compensation components or other benefits that an individual may be eligible for. The actual base salary offered depends on a variety of factors, which may include as applicable, the qualifications of the individual applicant for the position, years of relevant experience, specific and unique skills, level of education attained, certifications or other professional licenses held, and the location in which the applicant lives and/or from which they will be performing the job.\n\n#LI-KD1\n\nSony is an Equal Opportunity Employer. All qualified applicants will receive consideration for employment without regard to race, color, religious creed, sex (including pregnancy), gender, national origin, citizenship, ancestry, age, physical or mental disability, military status, status as a veteran or disabled veteran, sexual orientation, gender identity or expression, marital or family status, genetic information, medical condition, or any other basis protected by applicable federal, state, or local law, ordinance, or regulation.\n\nDisability Accommodation for Applicants to Sony Corporation of America\n\nSony Corporation of America provides reasonable accommodation for qualified individuals with disabilities and disabled veterans in job application procedures. For reasonable accommodation requests, please contact us by email at View email address on click.appcast.io or by mail to: Sony Corporation of America, Human Resources Department, 25 Madison Avenue, New York, NY 10010. Please indicate the position you are applying for.\n\nEEO is the Law\n\nEEO is the Law Supplement\n\nRight to Work (English/Spanish)\n\nE-Verify Participation (English/Spanish)\n\nThe company requires individuals in customer-facing roles to be fully vaccinated against COVID-19. The Company will consider requests for reasonable accommodations for documented medical reasons and for sincerely held religious beliefs in accordance with applicable law. Please do not include proof of vaccination status or any indication of a possible request for a vaccination accommodation when submitting your application materials. If applicable, the Company will follow up with you directly to request proof of vaccination and to discuss any potential accommodations.", "job_is_remote": false, "job_posted_at_timestamp": 1710115200, "job_posted_at_datetime_utc": "2024-03-11T00:00:00.000Z", "job_city": "San Jose", "job_state": "CA", "job_country": "US", "job_latitude": 37.33874, "job_longitude": -121.885254, "job_benefits": ["paid_time_off", "dental_coverage", "retirement_savings", "health_insurance"], "job_google_link": "https://www.google.com/search?gl=us&hl=en&rciv=jb&q=senior+sales+director&start=0&ibp=htl;jobs#fpstate=tldetail&htivrt=jobs&htiq=senior+sales+director&htidocid=vKa8kkXVHnYu2c8WAAAAAA%3D%3D", "job_offer_expiration_datetime_utc": "2024-04-10T07:46:04.000Z", "job_offer_expiration_timestamp": 1712735164, "job_required_experience": {"no_experience_required": false, "required_experience_in_months": 120, "experience_mentioned": true, "experience_preferred": false}, "job_required_skills": null, "job_required_education": {"postgraduate_degree": false, "professional_certification": false, "high_school": false, "associates_degree": false, "bachelors_degree": false, "degree_mentioned": true, "degree_preferred": true, "professional_certification_mentioned": true}, "job_experience_in_place_of_education": false, "job_min_salary": null, "job_max_salary": null, "job_salary_currency": null, "job_salary_period": null, "job_highlights": {"Qualifications": ["A minimum of 10 years of leadership experience in a complex, dynamic, commercial environment operating across the Americas region", "Bachelor's degree in Business, Life Sciences, or a related field", "A results-oriented mindset, with a strong drive to exceed sales targets and contribute to business growth", "Proven experience in leading enterprise sales and implementing go-to-market strategies", "Deep understanding of the life sciences & technology industry, including trends, challenges, and opportunities", "Proficiency in using Salesforce.com or a similar Customer relationship management system", "Strong leadership skills with a proven ability to influence, inspire and lead change in a high performing Sales team", "Excellent communication (verbal and written) skills", "Well-developed relationship-building skills, with the ability to engage effectively with a wide range of stakeholders", "Proven ability to deal with difficult problems or issues; an ability to provide a balanced perspective that optimizes the trade-offs between the business financials, the business opportunities, the company strategy, and the external environment"], "Responsibilities": ["The Senior Director, Sales will be responsible for managing and developing a highly skilled team of Sales Specialists and Field Applications Specialist", "The role reports directly to the Chief Executive Officer", "In conjunction with the Marketing department, the incumbent will be accountable for developing sales strategies to meet overall sales growth for instruments, reagents/consumables and service", "In addition, the Senior Director, Sales will be responsible for implementing strategies to build and maintain relationships with key customers and maintain a high degree of customer satisfaction", "Responsible for developing, implementing and driving the North American sales strategy", "Collaborate with other departments, such as Marketing, Customer Service and Operations to meet, align and implement initiatives to ensure continued growth", "Develop and execute effective tactical plans and territory development/growth strategies to increase market share and drive revenue growth", "Proficient in use of CRM (preferably Salesforce.com) to manage field Sales activities", "Responsible for analyzing sales metrics to determine effectiveness of sales tactics and growth initiatives", "Responsible for the regional demand forecast process to deliver on business KPIs", "Build and maintain strong relationships with key industry stakeholders, customers & partners", "Responsible for presenting the sales strategy and progress to Sr", "Demonstrated success in ability to balance the need to achieve current business goals with planning and investment for future growth", "Attend and present at external customer meetings and internal meetings with other company functions necessary to perform duties and aid business development", "Attend training and develop relevant knowledge, techniques and skills", "Staying abreast of and reporting on industry trends, competitive landscape, and regulatory changes to inform sales strategies and tactics", "Support contracts/proposals/quotations within company guidelines", "Lead, mentor, and manage a high-performing sales and field application team, fostering a culture of excellence and accountability", "Successfully attract, develop, and retain highly qualified field associates", "Travel required as per the business needs"], "Benefits": ["In addition to competitive pay and benefits, we offer an environment and culture that promotes Diversity, Equity, and Inclusion", "SCA offers benefits-eligible employees (generally regular employees scheduled to work 20 or more hours a week) a comprehensive benefits program that offers coverage and support for employees and their family's physical, emotional, and financial well-being", "Comprehensive medical, prescription drug, dental, and vision coverage with coverage for spouses/domestic partners and child dependents, including access to a Health Savings Account (HSA) and Flexible Spending Account (FSA)", "Employee assistance plan and comprehensive behavioral health benefits", "Fertility benefits, including surrogacy, and adoption assistance programs", "Basic and supplemental life insurance for employees as well as supplemental life insurance coverage for their spouses/domestic partners and children", "Voluntary benefits such as group legal, identity theft protection, accident, and hospital indemnity insurance", "Short-term & long-term disability plans", "Paid parental and caregiver leave", "401(k) Plan with pre-tax, Roth, and after-tax options and company match which vests immediately", "Education assistance and student loan programs", "Time off to include vacation, paid holidays, sick leave, Summer Fridays (early release), and a winter break between Christmas and New Year's Day (based on business needs)", "Referral bonuses (subject to eligibility)", "Matching gift program", "A wide variety of employee business resource groups (EBRGs)", "Special discounts on Sony products, offered exclusively to Sony employees", "Employee stock purchase plan (Sony covers commissions and fees for your Sony stock purchases made through after-tax payroll deductions)", "Annual incentive bonus", "The anticipated annual base salary for this position is $250,000 to $260,000", "This range does not include any other compensation components or other benefits that an individual may be eligible for", "The actual base salary offered depends on a variety of factors, which may include as applicable, the qualifications of the individual applicant for the position, years of relevant experience, specific and unique skills, level of education attained, certifications or other professional licenses held, and the location in which the applicant lives and/or from which they will be performing the job"]}, "job_job_title": "Senior director", "job_posting_language": "en", "job_onet_soc": "11202200", "job_onet_job_zone": "4"}