{"job_id": "bLqlHVRIgZvV0C1DAAAAAA==", "employer_name": "ServiceTitan", "employer_logo": "https://encrypted-tbn0.gstatic.com/images?q=tbn:ANd9GcRlB5cRwE839FcqIbsDYR4OIKpecdxotnF2Owrn&s=0", "employer_website": "http://servicetitan.com", "employer_company_type": null, "job_publisher": "Dream Startup Job", "job_employment_type": "FULLTIME", "job_title": "Lead Data Scientist", "job_apply_link": "https://dreamstartupjob.com/job/47844/lead-data-scientist/", "job_apply_is_direct": false, "job_apply_quality_score": 0.5102, "apply_options": [{"publisher": "Dream Startup Job", "apply_link": "https://dreamstartupjob.com/job/47844/lead-data-scientist/", "is_direct": false}], "job_description": "Ready to be a Titan?\n\nAs a member of the Operations data science team supporting the post-sales organization, you will build NLP/GenAI applications that transform our support and CSM operations. Your work will go directly to customers as part of ServiceTitan\u2019s Help Center and drive internal processes. The ideal candidate will have excellent data science/MLOps skills and be able to translate business needs into data science approaches.\n\nThis is a rare opportunity to boost sales growth at a firm that is at scale but still growing rapidly.\n\nWhat you'll do:\n\u2022 Partner with key business stakeholders at ServiceTitan\n\u2022 Build machine learning systems from the ground up and design scalable data science systems\n\u2022 Deliver cutting edge NLP expertise, driving best practices across all of our NLP projects (including GenAI applications)\n\u2022 Transform insights gained from data into actionable business recommendations\n\u2022 Champion and execute long-term strategic projects that grow ServiceTitan\u2019s platform in the Home Service industry\n\u2022 Invent bold and creative solutions that aim to solve our current and future business problems\n\nWhat you\u2019ll need:\n\u2022 MS/Ph.D in Data Science, Statistics, Applied Mathematics, Engineering, or similar quantitative discipline required\n\u2022 7+ years experience as a data scientist developing predictive business models with at least 5 years of experience in NLP applications\n\u2022 Strong background using data science python packages like transformers, pytorch, scikit-learn, and H2O\n\u2022 Expertise using pytorch or other similar packages to train from scratch or alter model architectures of open source LLMs for a variety of downstream tasks (text generation, classification, etc.)\n\u2022 Experience deploying NLP applications in a production environment\n\u2022 Able to seamlessly work with engineering as a co-creator of production solutions\n\u2022 A proven track record of using advanced data solutions to produce effective business results\n\u2022 Able to partner with the business and execute a project from end to end\n\u2022 Great communication skills including communicating complex concepts to business stakeholders\n\u2022 A passion for discovery, problem solving and practical business outcomes\n\u2022 Experience using cloud computing platforms (e.g. Azure) for modern machine learning operations\n\nPreferred experience:\n\u2022 History of contributing to open source projects\n\u2022 Peer reviewed publications on NLP/deep learning\n\nBe Human With Us:\n\nBeing human isn\u2019t about checking every box on a list. It\u2019s about the experiences we have, people we meet, and the perspectives we share. So, if you have the skills but are hesitant to apply because of your background, apply anyway. We need amazing people like you to help us challenge the conventional and think differently about the problems that we\u2019re solving. We\u2019re in this together. Come be human, with us.\n\nWhat We Offer:\n\nWhen you join our team, you\u2019re not just accepting a job. You\u2019re making a career move. Here\u2019s how we\u2019ll support you in doing some of the most impactful work of your career:\n\u2022 Flextime, recognition, and support for autonomous work: Flexible time off with ample learning and development opportunities to continue growing your career. We offer a comprehensive onboarding program, leadership training for Titans at all levels, and other programs and events. Great work is rewarded through Bonusly, peer-nominated awards, and more.\n\u2022 Holistic health and wellness benefits: Company-paid medical, dental, and vision (with 100% employer paid options and 90% coverage for dependents), FSA and HSA, 401k match, and telehealth options including memberships to Headspace, Galileo, One Medical, Ginger and more.\n\u2022 Support for Titans at all stages of life: Parental leave and support, up to $20k in adoption reimbursement, on demand maternity support through Maven Maternity, free breast milk shipping through Maven Milk, pet insurance, legal advisory services, financial planning tools, and more.\n\nAt ServiceTitan, we celebrate individuality and uniqueness. We believe that the convergence of fresh perspectives and experiences from all walks of life is what makes our product and culture so great. We strongly encourage people from underrepresented groups to apply. We do not discriminate against employees based on race, color, religion, sex, national origin, gender identity or expression, age, disability, pregnancy (including childbirth, breastfeeding, or related medical condition), genetic information, protected military or veteran status, sexual orientation, or any other characteristic protected by applicable federal, state or local laws.\n\nServiceTitan is committed to fair and equitable compensation for all of our employees. We thoughtfully consider a wide range of factors when determining individual compensation. The expected salary range for this role for candidates residing in the United States is between $154,000 USD - $220,000 USD. Compensation for candidates residing outside the United States will vary by location and the specific salary range will be discussed during the hiring process. Actual compensation for an individual may vary depending on skills, performance over time, qualifications, experience, and location. In addition to the base salary, the total compensation package also includes an annual bonus, equity and a holistic suite of benefits.", "job_is_remote": false, "job_posted_at_timestamp": 1709347330, "job_posted_at_datetime_utc": "2024-03-02T02:42:10.000Z", "job_city": "Remote", "job_state": "OR", "job_country": "US", "job_latitude": 43.005947, "job_longitude": -123.89259, "job_benefits": ["health_insurance", "retirement_savings", "dental_coverage"], "job_google_link": "https://www.google.com/search?gl=us&hl=en&rciv=jb&q=lead+data+scientist&start=50&ibp=htl;jobs#fpstate=tldetail&htivrt=jobs&htiq=lead+data+scientist&htidocid=bLqlHVRIgZvV0C1DAAAAAA%3D%3D", "job_offer_expiration_datetime_utc": null, "job_offer_expiration_timestamp": null, "job_required_experience": {"no_experience_required": false, "required_experience_in_months": null, "experience_mentioned": true, "experience_preferred": false}, "job_required_skills": null, "job_required_education": {"postgraduate_degree": false, "professional_certification": false, "high_school": false, "associates_degree": false, "bachelors_degree": false, "degree_mentioned": true, "degree_preferred": false, "professional_certification_mentioned": false}, "job_experience_in_place_of_education": false, "job_min_salary": null, "job_max_salary": null, "job_salary_currency": null, "job_salary_period": null, "job_highlights": {"Qualifications": ["MS/Ph.D in Data Science, Statistics, Applied Mathematics, Engineering, or similar quantitative discipline required", "7+ years experience as a data scientist developing predictive business models with at least 5 years of experience in NLP applications", "Strong background using data science python packages like transformers, pytorch, scikit-learn, and H2O", "Expertise using pytorch or other similar packages to train from scratch or alter model architectures of open source LLMs for a variety of downstream tasks (text generation, classification, etc.)", "Experience deploying NLP applications in a production environment", "Able to seamlessly work with engineering as a co-creator of production solutions", "A proven track record of using advanced data solutions to produce effective business results", "Able to partner with the business and execute a project from end to end", "Great communication skills including communicating complex concepts to business stakeholders", "A passion for discovery, problem solving and practical business outcomes", "Experience using cloud computing platforms (e.g. Azure) for modern machine learning operations"], "Responsibilities": ["As a member of the Operations data science team supporting the post-sales organization, you will build NLP/GenAI applications that transform our support and CSM operations", "Your work will go directly to customers as part of ServiceTitan\u2019s Help Center and drive internal processes", "Partner with key business stakeholders at ServiceTitan", "Build machine learning systems from the ground up and design scalable data science systems", "Deliver cutting edge NLP expertise, driving best practices across all of our NLP projects (including GenAI applications)", "Transform insights gained from data into actionable business recommendations", "Champion and execute long-term strategic projects that grow ServiceTitan\u2019s platform in the Home Service industry", "Invent bold and creative solutions that aim to solve our current and future business problems"], "Benefits": ["Flextime, recognition, and support for autonomous work: Flexible time off with ample learning and development opportunities to continue growing your career", "We offer a comprehensive onboarding program, leadership training for Titans at all levels, and other programs and events", "Holistic health and wellness benefits: Company-paid medical, dental, and vision (with 100% employer paid options and 90% coverage for dependents), FSA and HSA, 401k match, and telehealth options including memberships to Headspace, Galileo, One Medical, Ginger and more", "Support for Titans at all stages of life: Parental leave and support, up to $20k in adoption reimbursement, on demand maternity support through Maven Maternity, free breast milk shipping through Maven Milk, pet insurance, legal advisory services, financial planning tools, and more", "The expected salary range for this role for candidates residing in the United States is between $154,000 USD - $220,000 USD", "Compensation for candidates residing outside the United States will vary by location and the specific salary range will be discussed during the hiring process", "Actual compensation for an individual may vary depending on skills, performance over time, qualifications, experience, and location", "In addition to the base salary, the total compensation package also includes an annual bonus, equity and a holistic suite of benefits"]}, "job_job_title": "Data scientist", "job_posting_language": "en", "job_onet_soc": "15111100", "job_onet_job_zone": "5", "job_occupational_categories": ["Data"]}