{"job_id": "gE23BrMdI3WaBkC7AAAAAA==", "employer_name": "Natera", "employer_logo": "https://upload.wikimedia.org/wikipedia/commons/d/db/Natera_logo.png", "employer_website": "http://www.natera.com", "employer_company_type": "Research", "job_publisher": "The Muse", "job_employment_type": "FULLTIME", "job_title": "Senior Data Scientist", "job_apply_link": "https://www.themuse.com/jobs/natera/senior-data-scientist-a9f0bb", "job_apply_is_direct": false, "job_apply_quality_score": 0.6623, "apply_options": [{"publisher": "The Muse", "apply_link": "https://www.themuse.com/jobs/natera/senior-data-scientist-a9f0bb", "is_direct": false}], "job_description": "POSITION SUMMARY\n\nSuccessful applicants for this position must be fully vaccinated against COVID-19 as a condition of employment. Vaccine verification will be required.\n\nPOSITION SUMMARY\n\nNatera is seeking a highly motivated senior data scientist to join our rapidly growing company. As a member of the data group you will participate in the design and prototyping of cutting edge algorithms for analysis of genetic and clinical data. You will perform data analysis, algorithm design, contribute to our intellectual property portfolio, and interact closely with R&D and product teams to define the requirements and improve the products and processes.\n\nPOSITION LOCATION: Austin, TX, San Carlos, CA or Remote, USA\n\nPRIMARY RESPONSIBILITIES\n\n\u2022 Participate in research efforts into building probabilistic models for next generation sequence platforms\n\n\u2022 Leverage accurate probability models to build the next round of algorithms and products\n\n\u2022 Move products through the full development process, from research through commercial launch\n\n\u2022 Contribute to our intellectual property portfolio\n\n\u2022 Drive rigorous data analysis effort and support group efforts toward high quality documentation\n\n\u2022 Help develop and guide molecular biology experiments\n\nQUALIFICATIONS\n\nRequirements:\n\n\u2022 Masters or Ph.D. in quantitative field (Computer Science, Applied Mathematics, Statistics, Engineering, or similar)\n\n\u2022 Extensive knowledge and practical experience in several of the following areas: machine learning, statistics, deep learning,\n\n\u2022 At least five years' experience in data analysis using scripting languages such as Python (could be replaced by extensive experience in a procedural language such as C++)\n\n\u2022 Experience in large scale data processing\n\n\u2022 Experience with a database query language such as SQL\n\n\u2022 Experience with scalable data processing tools (Spark, Dataflow or similar)\n\n\u2022 Proven ability to apply mathematical principles to solve real estimation problems and implement practical solutions\n\n\u2022 Excellent communication skills and the desire to work in a dynamic and collaborative environment\n\n\u2022 Desire to learn about genetics, sequencing technologies, etc.\n\nDesirable but not required:\n\n\u2022 Previous experience in healthcare\n\n\u2022 Previous exposure to next-generation sequencing analysis\n\nKNOWLEDGE, SKILLS, AND ABILITIES\n\n\u2022 Experience in using Python, R in data analysis\n\n\u2022 Excellent communication skills and the desire to work in a dynamic and collaborative environment\n\n\u2022 Desire to learn about human genetics and sequencing technologies\n\nPHYSICAL DEMANDS & WORK ENVIRONMENT:\n\u2022 This position primarily works in an office environment. It requires frequent sitting, standing and walking.\n\u2022 Daily use of a computer is required. May stand for extended periods when facilitating meetings or walking in the facilities.\n\u2022 The physical demands of the position described herein are essential functions of the job and employees must be able to successfully perform these tasks for extended periods.\n\nOUR OPPORTUNITY\nDriven by the passion for elevating the science and utility of genetic testing, Natera is committed to helping families identify and manage genetic diseases. Natera is a rapidly-growing diagnostics company with proprietary bioinformatics and molecular technology for analyzing DNA. Our complex technology has been proven clinically and commercially in the prenatal testing space and we are actively researching its applications in the liquid biopsy space for developing products with oncology applications.\n\nThe Natera team consists of highly dedicated statisticians, geneticists, doctors, laboratory scientists, business professionals, software engineers and many other professionals from world-class institutions, who care deeply for our work and each other. When you join Natera, you'll work hard and grow quickly. Working alongside the elite of the industry, you'll be stretched and challenged, and take pride in being part of a company that is changing the landscape of genetic disease management.\n\nWHAT WE OFFER\nCompetitive Benefits. Healthy catered lunches, Premium snacks and beverages, Onsite gym with cardio and weight-training equipment, Game room with satellite TV, Onsite dry cleaning and alteration service with pick-up and delivery, Employee-organized sport leagues, Happy hours and BBQs, Generous Employee Referral program.\n\nFor more information, visit www.natera.com.\n\nNatera is proud to be an Equal Opportunity Employer. We are committed to ensuring a diverse and inclusive workplace environment, and welcome people of different backgrounds, experiences, abilities and perspectives. Inclusive collaboration benefits our employees, our community and our patients, and is critical to our mission of changing the management of disease worldwide.\n\nAll qualified applicants are encouraged to apply, and will be considered without regard to race, color, religion, gender, gender identity or expression, sexual orientation, national origin, genetics, age, veteran status, disability or any other legally protected status. We also consider qualified applicants regardless of criminal histories, consistent with applicable laws.", "job_is_remote": false, "job_posted_at_timestamp": 1635031752, "job_posted_at_datetime_utc": "2021-10-23T23:29:12.000Z", "job_city": null, "job_state": null, "job_country": "US", "job_latitude": 37.09024, "job_longitude": -95.71289, "job_benefits": null, "job_google_link": "https://www.google.com/search?gl=us&hl=en&rciv=jb&q=senior+data+scientist&start=60&ibp=htl;jobs#fpstate=tldetail&htivrt=jobs&htiq=senior+data+scientist&htidocid=gE23BrMdI3WaBkC7AAAAAA%3D%3D", "job_offer_expiration_datetime_utc": null, "job_offer_expiration_timestamp": null, "job_required_experience": {"no_experience_required": false, "required_experience_in_months": 60, "experience_mentioned": true, "experience_preferred": false}, "job_required_skills": null, "job_required_education": {"postgraduate_degree": false, "professional_certification": false, "high_school": false, "associates_degree": false, "bachelors_degree": false, "degree_mentioned": true, "degree_preferred": false, "professional_certification_mentioned": false}, "job_experience_in_place_of_education": false, "job_min_salary": null, "job_max_salary": null, "job_salary_currency": null, "job_salary_period": null, "job_highlights": {"Qualifications": ["Masters or Ph.D. in quantitative field (Computer Science, Applied Mathematics, Statistics, Engineering, or similar)", "Extensive knowledge and practical experience in several of the following areas: machine learning, statistics, deep learning,", "At least five years' experience in data analysis using scripting languages such as Python (could be replaced by extensive experience in a procedural language such as C++)", "Experience in large scale data processing", "Experience with a database query language such as SQL", "Experience with scalable data processing tools (Spark, Dataflow or similar)", "Proven ability to apply mathematical principles to solve real estimation problems and implement practical solutions", "Excellent communication skills and the desire to work in a dynamic and collaborative environment", "Desire to learn about genetics, sequencing technologies, etc", "Previous experience in healthcare", "Previous exposure to next-generation sequencing analysis"], "Responsibilities": ["As a member of the data group you will participate in the design and prototyping of cutting edge algorithms for analysis of genetic and clinical data", "You will perform data analysis, algorithm design, contribute to our intellectual property portfolio, and interact closely with R&D and product teams to define the requirements and improve the products and processes", "Participate in research efforts into building probabilistic models for next generation sequence platforms", "Leverage accurate probability models to build the next round of algorithms and products", "Move products through the full development process, from research through commercial launch", "Drive rigorous data analysis effort and support group efforts toward high quality documentation", "Help develop and guide molecular biology experiments", "This position primarily works in an office environment", "Daily use of a computer is required", "May stand for extended periods when facilitating meetings or walking in the facilities"], "Benefits": ["Competitive Benefits", "Healthy catered lunches, Premium snacks and beverages, Onsite gym with cardio and weight-training equipment, Game room with satellite TV, Onsite dry cleaning and alteration service with pick-up and delivery, Employee-organized sport leagues, Happy hours and BBQs, Generous Employee Referral program"]}, "job_job_title": "Data scientist", "job_posting_language": "en", "job_onet_soc": "15111100", "job_onet_job_zone": "5", "job_naics_code": "541711", "job_naics_name": "Research and Development in Biotechnology"}