{"job_id": "nmTcvO0ZQB8iJs-QAAAAAA==", "employer_name": "Grocery Outlet", "employer_logo": "https://www.groceryoutlet.com/wp-content/themes/digital_attic/images/grocery-outlet-bargain-market.png", "employer_website": "http://www.groceryoutlet.com", "employer_company_type": "Retail", "job_publisher": "Media Bistro", "job_employment_type": "FULLTIME", "job_title": "Marketing Analytics Manager", "job_apply_link": "https://www.mediabistro.com/jobs/210941146-marketing-analytics-manager", "job_apply_is_direct": false, "job_apply_quality_score": 0.5605, "apply_options": [{"publisher": "Media Bistro", "apply_link": "https://www.mediabistro.com/jobs/210941146-marketing-analytics-manager", "is_direct": false}], "job_description": "About Grocery Outlet:Our Mission:Touching lives for the betterOur Vision:Touching lives by being the first choice for bargain-minded consumers in the U.S.Our Values & Behaviors:Achievement, Diversity, Entrepreneurship, Family, Fun, Integrity & ServiceAbout the Team:The members of our Marketing Team are fun, objective, risk takers, innovative and strong communicators. We are always looking for the next trend in Marketing, willing to test and learn, open to feedback, treat the rest of the organization as our clients and enjoy working on many different projects. Additions to the team bring a sense of humor, dedication, hard-work, and the ability to communicate at all levels.About the Role:The Marketing Analytics Manager will play a pivotal role in shaping our marketing strategies through data analysis and insights. The successful candidate will be responsible for collecting, analyzing, and interpreting marketing, customer and market data to inform marketing strategies, drive business decisions, and measure the performance of marketing initiatives. This role reports to the VP of Marketing.Responsibilities Include:Data Analysis and Reporting:Collect and analyze data across marketing platforms to identify trends, opportunities, and challenges.Generate regular reports on marketing campaign performance and customer behavior.Translate complex data findings into understandable and actionable marketing campaigns.Develop and track key performance indicators (KPIs) to measure marketing effectiveness and ROI.Market Research:Partner with Strategy on market research to understand market trends, competitive landscape, and customer preferences.Provide actionable insights based on market research to support marketing strategies.Media Analytics:Utilize Media Mix Modeling to forecast marketing trends and consumer behavior.Create customer segmentation models to tailor marketing strategies to different audience segments.Marketing Strategy:Collaborate with the marketing team to develop and optimize marketing strategies based on findings.Recommend changes to marketing strategies based on data and trends.Cross-functional Collaboration:Work closely with Business Technology, Strategy, and other departments to ensure data quality and the integration of analytics into all marketing activities.Assist with the establishment of best practices in analytics and data-driven decision-making across the company.Technology and Tools:Stay up-to-date with the latest analytics tools and technologies; recommend new tools to enhance analytics capabilities.Manage and ensure the proper integration of marketing analytics tools and software.About the Pay:Base Salary Range: $90,000 - $110,000Annual Bonus ProgramEquity401(k) Profit SharingMedical, Dental, Vision & More!Final compensation will be determined based upon experience and skills and may vary based on location.About You:Bachelor\u2019s or Master\u2019s degree in Marketing, Statistics, Mathematics, Economics, Computer Science, Information Management, or a related field5-7 years proven experience as a Marketing Analytics Manager or Data Analyst within the retail or grocery sectorStrong analytical skills with the ability to collect, organize, analyze, and disseminate significant amounts of information with attention to detail and accuracyExperience in statistical analysis and the use of statistical packages for analyzing datasets (Excel, APT-Mastercard Test & Learn.)Proficiency with marketing analytics and CRM tools (Google Analytics, Domo, Appsflyer/Branch, Braze, Optimine etc.)Familiarity with customer segmentation, predictive modeling, and market research techniquesExcellent communication and presentation skillsTo learn about how we collect, use and secure your personal information. Click here to see our privacy policy.", "job_is_remote": false, "job_posted_at_timestamp": 1710165600, "job_posted_at_datetime_utc": "2024-03-11T14:00:00.000Z", "job_city": null, "job_state": null, "job_country": "US", "job_latitude": 37.09024, "job_longitude": -95.71289, "job_benefits": null, "job_google_link": "https://www.google.com/search?gl=us&hl=en&rciv=jb&q=manager+of+marketing+analytics&start=60&ibp=htl;jobs#fpstate=tldetail&htivrt=jobs&htiq=manager+of+marketing+analytics&htidocid=nmTcvO0ZQB8iJs-QAAAAAA%3D%3D", "job_offer_expiration_datetime_utc": null, "job_offer_expiration_timestamp": null, "job_required_experience": {"no_experience_required": false, "required_experience_in_months": 60, "experience_mentioned": true, "experience_preferred": false}, "job_required_skills": null, "job_required_education": {"postgraduate_degree": false, "professional_certification": false, "high_school": false, "associates_degree": false, "bachelors_degree": false, "degree_mentioned": true, "degree_preferred": true, "professional_certification_mentioned": false}, "job_experience_in_place_of_education": false, "job_min_salary": null, "job_max_salary": null, "job_salary_currency": null, "job_salary_period": null, "job_highlights": {"Qualifications": ["About You:Bachelor\u2019s or Master\u2019s degree in Marketing, Statistics, Mathematics, Economics, Computer Science, Information Management, or a related field5-7 years proven experience as a Marketing Analytics Manager or Data Analyst within the retail or grocery sector", "Strong analytical skills with the ability to collect, organize, analyze, and disseminate significant amounts of information with attention to detail and accuracy", "Experience in statistical analysis and the use of statistical packages for analyzing datasets (Excel, APT-Mastercard Test & Learn.)", "Proficiency with marketing analytics and CRM tools (Google Analytics, Domo, Appsflyer/Branch, Braze, Optimine etc.)Familiarity with customer segmentation, predictive modeling, and market research techniques", "Excellent communication and presentation skills"], "Responsibilities": ["About the Role:The Marketing Analytics Manager will play a pivotal role in shaping our marketing strategies through data analysis and insights", "The successful candidate will be responsible for collecting, analyzing, and interpreting marketing, customer and market data to inform marketing strategies, drive business decisions, and measure the performance of marketing initiatives", "This role reports to the VP of Marketing", "Responsibilities Include:Data Analysis and Reporting:Collect and analyze data across marketing platforms to identify trends, opportunities, and challenges", "Generate regular reports on marketing campaign performance and customer behavior", "Translate complex data findings into understandable and actionable marketing campaigns", "Develop and track key performance indicators (KPIs) to measure marketing effectiveness and ROI", "Market Research:Partner with Strategy on market research to understand market trends, competitive landscape, and customer preferences", "Provide actionable insights based on market research to support marketing strategies", "Media Analytics:Utilize Media Mix Modeling to forecast marketing trends and consumer behavior", "Create customer segmentation models to tailor marketing strategies to different audience segments", "Marketing Strategy:Collaborate with the marketing team to develop and optimize marketing strategies based on findings", "Recommend changes to marketing strategies based on data and trends.Cross-functional Collaboration:Work closely with Business Technology, Strategy, and other departments to ensure data quality and the integration of analytics into all marketing activities", "Assist with the establishment of best practices in analytics and data-driven decision-making across the company", "Technology and Tools:Stay up-to-date with the latest analytics tools and technologies; recommend new tools to enhance analytics capabilities", "Manage and ensure the proper integration of marketing analytics tools and software"], "Benefits": ["About the Pay:Base Salary Range: $90,000 - $110,000Annual Bonus ProgramEquity401(k) Profit SharingMedical, Dental, Vision & More!", "Final compensation will be determined based upon experience and skills and may vary based on location"]}, "job_job_title": "Analytics manager", "job_posting_language": "en", "job_onet_soc": "11202100", "job_onet_job_zone": "4", "job_naics_code": "445110", "job_naics_name": "Supermarkets and Other Grocery (except Convenience) Stores"}