{"job_id": "_b8ij_wDmZDKsk2vAAAAAA==", "employer_name": "AEG", "employer_logo": "https://www.aeg.de/siteassets/common-assets/11.-framework/logo2.svg", "employer_website": null, "employer_company_type": "Manufacturing", "job_publisher": "Ladders", "job_employment_type": "FULLTIME", "job_title": "Director, Corporate Partnerships", "job_apply_link": "https://www.theladders.com/job/director-corporate-partnerships-aeg-washington-dc_67246172", "job_apply_is_direct": false, "job_apply_quality_score": 0.5374, "apply_options": [{"publisher": "Ladders", "apply_link": "https://www.theladders.com/job/director-corporate-partnerships-aeg-washington-dc_67246172", "is_direct": false}, {"publisher": "Tarta.ai", "apply_link": "https://jobs.tarta.ai/j/9viCY40BcRajQcTj1nXY0124-director-corporate-partnerships-in-washington-district-of-columbia-at-washington-nationals", "is_direct": false}], "job_description": "In order to be considered for this role, after clicking \"apply now\" above and being redirected, you must fully complete the application process on the follow-up screen.\n\nSummary: Reporting to the Vice President of Corporate Partnerships, the Director of Corporate Partnerships will be responsible for generating revenue through the sale of corporate partnerships that incorporate all marketing assets controlled by the Washington Nationals. These assets include, but are not limited to, traditional signage, radio, print, corporate hospitality, social media, promotional giveaways, experiential opportunities and special events. He/she will manage the sales staff and a collection of team accounts. The Nationals are a military-friendly organization actively recruiting veterans and spouses. Essential Duties and Responsibilities:\n\u2022 Identify prospects on local, regional and national levels.\n\u2022 Establish new corporate partnerships and renew existing accounts to achieve departmental revenue goals.\n\u2022 Prepare and present corporate partnerships sales proposals to key clients and prospects.\n\u2022 Manage sales staff, assist sales staff and VP's with prospecting, pitching and closing business.\n\u2022 Meet with sales team on a weekly basis to review pipeline and assist with sales strategy.\n\u2022 Work closely with department staff to ensure stellar fulfillment of partnership contracts.\n\u2022 Collaborate with all members of the corporate partnerships and marketing departments, in addition to other key internal departments, in order to identify new assets and develop new activation programs.\n\u2022 Monitor available sponsorship inventory and adjust pricing as necessary.\n\u2022 Host and entertain corporate partners and prospects in suite and hospitality settings.\n\u2022 Other duties as assigned.\nRequirements: Minimum Education and Experience Requirements\n\u2022 Bachelor's Degree.\n\u2022 5+ years of sports sponsorship sales experience.\n\u2022 2+ years of demonstrated experience leading and managing a sales staff.\n\u2022 Solutions-based sales experience focused on metrics and ROI.\nKnowledge, Skills, and Abilities necessary to perform essential functions\n\u2022 Comfortable working with and presenting to senior executives.\n\u2022 Customer-focused, team player - ability to lead sales staff.\n\u2022 Excellent business research and problem solving skills.\n\u2022 Flexible schedule with ability to work evenings, weekends and holidays.\n\u2022 Proven revenue generator with collection of senior brand and agency contacts.\n\u2022 Effective verbal, written and presentation skills.\n\u2022 Strong prospecting and leadership skills.\n\u2022 Strong organizational skills and ability to multi task.\n\u2022 Ability to meet challenging sales objectives in a high profile, competitive marketplace.\n\u2022 Demonstrated ability to develop strategic activation programs.\n\u2022 Track record of providing exceptional customer-service.\n\u2022 Computer proficiency with MS Word, Excel and PowerPoint.\n\u2022 Previous formal sales training preferred.\nPhysical/Environmental Requirements\n\u2022 Office: Working conditions are normal for an office environment. Work requires occasional weekend and/or evening work.\n\u2022 Gameday: Job requires employee to function in a high activity and heavily crowded outdoor professional sports venue. Employee will be exposed to inclement weather of varying degrees. While performing the duties of this job, the employee is regularly required to stand for long periods of time, walk long distances, and climb up/down stairs. The employee is required to stoop, kneel, crouch, or sit and must lift and/or move up to 45 pounds.", "job_is_remote": false, "job_posted_at_timestamp": 1706491604, "job_posted_at_datetime_utc": "2024-01-29T01:26:44.000Z", "job_city": "Washington", "job_state": "DC", "job_country": "US", "job_latitude": 38.907192, "job_longitude": -77.03687, "job_benefits": null, "job_google_link": "https://www.google.com/search?gl=us&hl=en&rciv=jb&q=vice+president+of+brand+partnerships&start=50&ibp=htl;jobs#fpstate=tldetail&htivrt=jobs&htiq=vice+president+of+brand+partnerships&htidocid=_b8ij_wDmZDKsk2vAAAAAA%3D%3D", "job_offer_expiration_datetime_utc": null, "job_offer_expiration_timestamp": null, "job_required_experience": {"no_experience_required": false, "required_experience_in_months": 60, "experience_mentioned": true, "experience_preferred": false}, "job_required_skills": null, "job_required_education": {"postgraduate_degree": false, "professional_certification": false, "high_school": false, "associates_degree": false, "bachelors_degree": false, "degree_mentioned": true, "degree_preferred": false, "professional_certification_mentioned": false}, "job_experience_in_place_of_education": false, "job_min_salary": 86732, "job_max_salary": 130099, "job_salary_currency": "USD", "job_salary_period": "YEAR", "job_highlights": {"Qualifications": ["Bachelor's Degree", "5+ years of sports sponsorship sales experience", "2+ years of demonstrated experience leading and managing a sales staff", "Solutions-based sales experience focused on metrics and ROI", "Knowledge, Skills, and Abilities necessary to perform essential functions", "Comfortable working with and presenting to senior executives", "Customer-focused, team player - ability to lead sales staff", "Excellent business research and problem solving skills", "Flexible schedule with ability to work evenings, weekends and holidays", "Proven revenue generator with collection of senior brand and agency contacts", "Effective verbal, written and presentation skills", "Strong prospecting and leadership skills", "Strong organizational skills and ability to multi task", "Ability to meet challenging sales objectives in a high profile, competitive marketplace", "Demonstrated ability to develop strategic activation programs", "Track record of providing exceptional customer-service", "Computer proficiency with MS Word, Excel and PowerPoint", "Office: Working conditions are normal for an office environment"], "Responsibilities": ["Summary: Reporting to the Vice President of Corporate Partnerships, the Director of Corporate Partnerships will be responsible for generating revenue through the sale of corporate partnerships that incorporate all marketing assets controlled by the Washington Nationals", "These assets include, but are not limited to, traditional signage, radio, print, corporate hospitality, social media, promotional giveaways, experiential opportunities and special events", "He/she will manage the sales staff and a collection of team accounts", "Identify prospects on local, regional and national levels", "Establish new corporate partnerships and renew existing accounts to achieve departmental revenue goals", "Prepare and present corporate partnerships sales proposals to key clients and prospects", "Manage sales staff, assist sales staff and VP's with prospecting, pitching and closing business", "Meet with sales team on a weekly basis to review pipeline and assist with sales strategy", "Work closely with department staff to ensure stellar fulfillment of partnership contracts", "Collaborate with all members of the corporate partnerships and marketing departments, in addition to other key internal departments, in order to identify new assets and develop new activation programs", "Monitor available sponsorship inventory and adjust pricing as necessary", "Host and entertain corporate partners and prospects in suite and hospitality settings", "Other duties as assigned", "Gameday: Job requires employee to function in a high activity and heavily crowded outdoor professional sports venue", "Employee will be exposed to inclement weather of varying degrees", "While performing the duties of this job, the employee is regularly required to stand for long periods of time, walk long distances, and climb up/down stairs"]}, "job_job_title": "Director", "job_posting_language": "en", "job_onet_soc": "11203100", "job_onet_job_zone": "4", "job_naics_code": "3352", "job_naics_name": "Household Appliance Manufacturing"}