{"job_id": "S6vr7_2h0mkqU-NsAAAAAA==", "employer_name": "Encore Event Technologies LLP", "employer_logo": null, "employer_website": null, "employer_company_type": null, "job_publisher": "Jooble", "job_employment_type": "FULLTIME", "job_title": "Senior Sales Manager, Events - JW Marriott Turnberry Resort, Aventura FL", "job_apply_link": "https://jooble.org/jdp/5366812394792932320", "job_apply_is_direct": false, "job_apply_quality_score": 0.6501, "apply_options": [{"publisher": "Jooble", "apply_link": "https://jooble.org/jdp/5366812394792932320", "is_direct": false}], "job_description": "\u2022 *Senior Sales Manager, Events - JW Marriott Turnberry Resort, Aventura FL**\n\nApply Later **Job ID** SENIO011425 **Date posted** 02/08/2022 **Location** Aventura , Florida **Position Type** Full Time Position Overview\n\nThe Sr. Sales Manager leads the sales process for assigned groups and directs staff to effectively guide customers through their event experiences. Identifies solutions that meet customer goals and objectives, and utilizes all available tools to ensure maximum event and revenue capture from assigned customer base. Cultivates and maintains relationships with key hotel personnel to enhance the overall business relationship with hotel. Serves as a resource for large, high-end event production in venue location/region and supports team as needed with guidance and training. Leads and supports Company initiatives, business strategies and Core Values. This position supervises the Sales Manager and reports to the Sales Director or Director, Event Technology.\n\nKey Job Responsibilities\n\nRevenue Generation\n\nDrive Results by soliciting and securing business through a proactive, consultative sales approach, utilizing Encores sales process and methodology.\n\nMaximize revenue opportunity for assigned customers by creating effective strategies for per-event revenue growth, including upsell and cross-sell opportunities.\n\nCreate high-end, large event, advanced technology solutions for Encores existing and potential customers.\n\nPrepare and deliver compelling presentations that convey the value of Encore and effectively solve customer challenges.\n\nEffectively collaborate with vendors and other departments/divisions of the company to capture and service events.\n\nAttend site visits, pre-conference planning meetings, and appropriate venue meetings as necessary to support the customer event experience.\n\nUnderstand event cost structure and incorporates into solution designs according to established profitability guidelines.\n\nRelationship Management\n\nDeliver World-Class Service by cultivating and maintaining relationships with customers, venue personnel and various Encore supporting functions and departments.\n\nThoroughly research and understand customer history and previous experiences, in order to create more personalized customer experiences.\n\nLead sales meetings, deliver group presentations, and facilitate budgeting and forecasting discussions with hotel partners.\n\nValue People by attending internal and external customer meetings, understanding their goals and responding to their questions, concerns, and challenges.\n\nAddress customer complaints and concerns, and effectively resolve issues.\n\nDo the Right Thing by ensuring all customer information is up to date and accurate in the Customer Relationship Management system (CRM) at all times.\n\nActively refer and guide customers through the Encore network, leveraging contacts to secure additional opportunities with existing customers.\n\nSales Accountability\n\nMaintain a healthy pipeline at all times that ensures achievement of established revenue targets.\n\nEnsure all known opportunities are in CRM and completely accurate and updated at all times.\n\nSee the Big Picture by supporting the sales forecasting efforts at home location, ensuring they are accurate and submitted timely.\n\nAssist Director in setting sales quotas and assigning leads.\n\nLearn and adopt all SOPs related to the role and any new initiatives/programs that are implemented.\n\nMaintain knowledge of new product/service offerings and emerging technology supporting meetings and events.\n\nSupport sales team members with pipeline management, creating effective sales strategies, and implementing best practices.\n\nPeople Development\n\nProvide direct leadership and guidance to Sales Team members.\n\nTrain, mentor and coach sales team members.\n\nPartner with Sales Team members to provide support and guidance on large complex events.\n\nValue People by promoting a culture of high performance, accountability and continuous improvement that values learning and a commitment to quality.\n\nParticipate in regional or national committees as requested by sales leadership.\n\nFacilitate training at location or within home region as needed to increase the sales teams skills.\n\nJob Qualifications\n\nBS/BA or 3+ years of Encore or equivalent experience required\n\nMinimum 2+ years of sales experience required\n\nPrior sales experience in audiovisual, technology or hospitality experience preferred\n\nKnowledge of sales process required in addition to the ability to read and decipher financial reports and records\n\nTechnical aptitude, computer proficiency and CRM knowledge required. Prefer CAD and Oracle knowledge\n\nSuperior communication and presentation skills\n\nCompetencies (by Core Values)\n\nDirects Work\n\nManages Complexity\n\nFinancial Acumen\n\nBalance Stakeholders\n\nCollaborates\n\nDevelops Talent\n\nBuilds Networks\n\nDrives Quality Results\n\nOptimizes Work Processes\n\nManages Ambiguity\n\nWork Environment\n\nHotel\n\nWork is performed in a hotel/convention center environment with moderate exposure to outdoor temperatures and to dirt, sand and/or dust. The working conditions will vary between moderately quiet to noisy volumes. Team members will use high-end audio visual equipment and electrical components, and will be exposed to heights via lifts and ladders. Team members may be asked to work in multiple hotel locations. Working times will include irregular hours and on-call status including days, evenings, weekends and holidays. Team members must adhere to appearance guidelines as defined by Encore based on an individual hotel or a representation of hotels in that city or area.\n\nApply Later **Career Path Opportunities**\n\nDiscover everywhere you can go and the impact you can have. Your career is never limited to one location with Encore.\n\u2022 *What to Expect**\n\nWe want to give you a window into our recruitment process to ensure that your journey to becoming a Encore team member is a positive experience.\n\u2022 *Benefits**\n\nYoull find some of the best rewards in the industry from comprehensive insurance options and generous PTO to a company-matching 401(k).", "job_is_remote": false, "job_posted_at_timestamp": 1710201600, "job_posted_at_datetime_utc": "2024-03-12T00:00:00.000Z", "job_city": null, "job_state": null, "job_country": "US", "job_latitude": 62.41136, "job_longitude": -149.07297, "job_benefits": ["paid_time_off", "health_insurance", "retirement_savings"], "job_google_link": "https://www.google.com/search?gl=us&hl=en&rciv=jb&q=senior+sales+director&start=70&ibp=htl;jobs#fpstate=tldetail&htivrt=jobs&htiq=senior+sales+director&htidocid=S6vr7_2h0mkqU-NsAAAAAA%3D%3D", "job_offer_expiration_datetime_utc": "2024-04-12T03:42:52.000Z", "job_offer_expiration_timestamp": 1712893372, "job_required_experience": {"no_experience_required": false, "required_experience_in_months": 36, "experience_mentioned": true, "experience_preferred": true}, "job_required_skills": null, "job_required_education": {"postgraduate_degree": false, "professional_certification": false, "high_school": false, "associates_degree": false, "bachelors_degree": false, "degree_mentioned": true, "degree_preferred": true, "professional_certification_mentioned": false}, "job_experience_in_place_of_education": false, "job_min_salary": null, "job_max_salary": null, "job_salary_currency": null, "job_salary_period": null, "job_highlights": {"Qualifications": ["BS/BA or 3+ years of Encore or equivalent experience required", "Minimum 2+ years of sales experience required", "Knowledge of sales process required in addition to the ability to read and decipher financial reports and records", "Technical aptitude, computer proficiency and CRM knowledge required", "Prefer CAD and Oracle knowledge", "Superior communication and presentation skills"], "Responsibilities": ["Sales Manager leads the sales process for assigned groups and directs staff to effectively guide customers through their event experiences", "Identifies solutions that meet customer goals and objectives, and utilizes all available tools to ensure maximum event and revenue capture from assigned customer base", "Cultivates and maintains relationships with key hotel personnel to enhance the overall business relationship with hotel", "Serves as a resource for large, high-end event production in venue location/region and supports team as needed with guidance and training", "Leads and supports Company initiatives, business strategies and Core Values", "This position supervises the Sales Manager and reports to the Sales Director or Director, Event Technology", "Drive Results by soliciting and securing business through a proactive, consultative sales approach, utilizing Encores sales process and methodology", "Maximize revenue opportunity for assigned customers by creating effective strategies for per-event revenue growth, including upsell and cross-sell opportunities", "Create high-end, large event, advanced technology solutions for Encores existing and potential customers", "Prepare and deliver compelling presentations that convey the value of Encore and effectively solve customer challenges", "Effectively collaborate with vendors and other departments/divisions of the company to capture and service events", "Attend site visits, pre-conference planning meetings, and appropriate venue meetings as necessary to support the customer event experience", "Understand event cost structure and incorporates into solution designs according to established profitability guidelines", "Deliver World-Class Service by cultivating and maintaining relationships with customers, venue personnel and various Encore supporting functions and departments", "Thoroughly research and understand customer history and previous experiences, in order to create more personalized customer experiences", "Lead sales meetings, deliver group presentations, and facilitate budgeting and forecasting discussions with hotel partners", "Value People by attending internal and external customer meetings, understanding their goals and responding to their questions, concerns, and challenges", "Address customer complaints and concerns, and effectively resolve issues", "Do the Right Thing by ensuring all customer information is up to date and accurate in the Customer Relationship Management system (CRM) at all times", "Actively refer and guide customers through the Encore network, leveraging contacts to secure additional opportunities with existing customers", "Sales Accountability", "Maintain a healthy pipeline at all times that ensures achievement of established revenue targets", "Ensure all known opportunities are in CRM and completely accurate and updated at all times", "See the Big Picture by supporting the sales forecasting efforts at home location, ensuring they are accurate and submitted timely", "Assist Director in setting sales quotas and assigning leads", "Learn and adopt all SOPs related to the role and any new initiatives/programs that are implemented", "Maintain knowledge of new product/service offerings and emerging technology supporting meetings and events", "Support sales team members with pipeline management, creating effective sales strategies, and implementing best practices", "Provide direct leadership and guidance to Sales Team members", "Train, mentor and coach sales team members", "Partner with Sales Team members to provide support and guidance on large complex events", "Value People by promoting a culture of high performance, accountability and continuous improvement that values learning and a commitment to quality", "Participate in regional or national committees as requested by sales leadership", "Facilitate training at location or within home region as needed to increase the sales teams skills", "Manages Complexity", "Optimizes Work Processes", "Working times will include irregular hours and on-call status including days, evenings, weekends and holidays", "Team members must adhere to appearance guidelines as defined by Encore based on an individual hotel or a representation of hotels in that city or area"], "Benefits": ["Youll find some of the best rewards in the industry from comprehensive insurance options and generous PTO to a company-matching 401(k)"]}, "job_job_title": "Sales manager", "job_posting_language": "en", "job_onet_soc": "11202200", "job_onet_job_zone": "4"}