{"job_id": "cPPOPbKmUbyYfjiyAAAAAA==", "employer_name": "Piano", "employer_logo": "https://mma.prnewswire.com/media/691003/Piano_Logo.jpg?p=facebook", "employer_website": "http://www.piano.io", "employer_company_type": null, "job_publisher": "Salary.com", "job_employment_type": "FULLTIME", "job_title": "Senior Sales Director, UK", "job_apply_link": "https://www.salary.com/job/piano/senior-sales-director-uk/j202309281236463200661", "job_apply_is_direct": false, "job_apply_quality_score": 0.6252, "apply_options": [{"publisher": "Salary.com", "apply_link": "https://www.salary.com/job/piano/senior-sales-director-uk/j202309281236463200661", "is_direct": false}], "job_description": "Piano Overview\n\nPiano\u2019s Digital Experience Cloud empowers organizations to understand and influence customer behavior. By unifying customer data, analyzing behavior metrics, and creating personalized customer journeys, Piano helps brands launch campaigns and products faster, strengthen customer engagement and drive personalization at scale from a single platform. Headquartered in Amsterdam with offices across the Americas, Europe, and Asia Pacific, Piano serves a global client base, including Air France, the BBC, CBS, IBM, Kirin Holdings, Jaguar Land Rover, LinkedIn, Nielsen, The Wall Street Journal, and more. Piano has been recognized as one of the fastest-growing, most innovative technology companies in the world by World Economic Forum, Red Herring, Inc., and Deloitte. For more information, visit piano.io.\n\nPosition Overview\n\nAs a Senior Sales Director, you are responsible for growing our client base with a focus on enterprise brands across UK & Ireland. You are committed to winning and taking advantage of the untapped customer base that could benefit from Piano\u2019s product offering. Individuals should have a proven track record of consultative SaaS sales; the ability to negotiate complex six and seven-figure contracts; a strong understanding of the digital landscape and a willingness to embrace disruptive, fast-paced technology companies.\n\nWhat You'll Do\n\u2022 Build, lead and grow your own book of business, selling to our top accounts and working with blue chip Fortune 500 companies;\n\u2022 Drive significant growth in the EMEA market for both existing and new clients, achieving or exceeding individual quota;\n\u2022 Manage complete and complex sales cycles presenting to C-level executives the value of our product;\n\u2022 Define, execute, and own an engagement plan for key prospects, leverage marketing, product, and leadership to prospect effectively;\n\u2022 Develop and manage strong relationships within our Enterprise market segment, looking for opportunities to add value for the customer and develop additional revenue;\n\u2022 Territory/Vertical identification and research, to formalize a go to market strategy and create qualified target accounts;\n\u2022 Forecast sales activity and revenue achievement, while creating satisfied and referenceable customers;\n\u2022 Partner with the pre-sales and marketing teams to maximize revenue-generating opportunities.\n\nRequired Skills & Attributes:\n\u2022 5-10 years SaaS, digital experience, or technology sales;\n\u2022 Ability to reach and develop relationships with C-level executives in key verticals;\n\u2022 Understanding of digital ecosystem landscape and relationships;\n\u2022 Track record of success in carrying a quota, closing six-figure deals;\n\u2022 Experience from AdTech, SaaS, or digital agency;\n\u2022 Successful history of net direct new business sales, with the ability to prove consistent delivery against targets;\n\u2022 A track record of success in selling business applications and complex solutions;\n\u2022 Track record of over-achieving quota (top 10-20% of company) in past positions;\n\u2022 Experience managing and closing complex sales cycles- demonstrated ownership of all aspects of territory management;\n\u2022 Experience in bringing innovative/market-defining products to market;\n\u2022 Must work well in a team selling environment;\n\u2022 Ability to travel;\n\u2022 BA/BS degree or similar college-level education. In lieu of a degree, relevant skills, or equivalent experience.\n\nWhat we can offer:\n\u2022 Hybrid Work;\n\u2022 Company MacBook;\n\u2022 Training Programs;\n\u2022 Competitive salary;\n\u2022 Working in a truly international company;\n\u2022 Fun working atmosphere.\n\nNote:\n\nAll persons hired must be eligible to work in the United Kingdom without requiring sponsorship from the company.", "job_is_remote": false, "job_posted_at_timestamp": 1695945600, "job_posted_at_datetime_utc": "2023-09-29T00:00:00.000Z", "job_city": null, "job_state": null, "job_country": "US", "job_latitude": 37.09024, "job_longitude": -95.71289, "job_benefits": ["retirement_savings"], "job_google_link": "https://www.google.com/search?gl=us&hl=en&rciv=jb&q=senior+sales+director&start=0&ibp=htl;jobs#fpstate=tldetail&htivrt=jobs&htiq=senior+sales+director&htidocid=cPPOPbKmUbyYfjiyAAAAAA%3D%3D", "job_offer_expiration_datetime_utc": "2024-03-28T00:00:00.000Z", "job_offer_expiration_timestamp": 1711584000, "job_required_experience": {"no_experience_required": false, "required_experience_in_months": null, "experience_mentioned": true, "experience_preferred": false}, "job_required_skills": null, "job_required_education": {"postgraduate_degree": false, "professional_certification": false, "high_school": false, "associates_degree": false, "bachelors_degree": false, "degree_mentioned": true, "degree_preferred": true, "professional_certification_mentioned": false}, "job_experience_in_place_of_education": false, "job_min_salary": null, "job_max_salary": null, "job_salary_currency": null, "job_salary_period": null, "job_highlights": {"Qualifications": ["5-10 years SaaS, digital experience, or technology sales;", "Ability to reach and develop relationships with C-level executives in key verticals;", "Understanding of digital ecosystem landscape and relationships;", "Track record of success in carrying a quota, closing six-figure deals;", "Experience from AdTech, SaaS, or digital agency;", "Successful history of net direct new business sales, with the ability to prove consistent delivery against targets;", "A track record of success in selling business applications and complex solutions;", "Track record of over-achieving quota (top 10-20% of company) in past positions;", "Experience managing and closing complex sales cycles- demonstrated ownership of all aspects of territory management;", "Experience in bringing innovative/market-defining products to market;", "Must work well in a team selling environment;", "Ability to travel;", "BA/BS degree or similar college-level education", "In lieu of a degree, relevant skills, or equivalent experience"], "Responsibilities": ["Piano\u2019s Digital Experience Cloud empowers organizations to understand and influence customer behavior", "By unifying customer data, analyzing behavior metrics, and creating personalized customer journeys, Piano helps brands launch campaigns and products faster, strengthen customer engagement and drive personalization at scale from a single platform", "As a Senior Sales Director, you are responsible for growing our client base with a focus on enterprise brands across UK & Ireland", "You are committed to winning and taking advantage of the untapped customer base that could benefit from Piano\u2019s product offering", "Build, lead and grow your own book of business, selling to our top accounts and working with blue chip Fortune 500 companies;", "Drive significant growth in the EMEA market for both existing and new clients, achieving or exceeding individual quota;", "Manage complete and complex sales cycles presenting to C-level executives the value of our product;", "Define, execute, and own an engagement plan for key prospects, leverage marketing, product, and leadership to prospect effectively;", "Develop and manage strong relationships within our Enterprise market segment, looking for opportunities to add value for the customer and develop additional revenue;", "Territory/Vertical identification and research, to formalize a go to market strategy and create qualified target accounts;", "Forecast sales activity and revenue achievement, while creating satisfied and referenceable customers;", "Partner with the pre-sales and marketing teams to maximize revenue-generating opportunities"], "Benefits": ["Hybrid Work;", "Company MacBook;", "Training Programs;", "Competitive salary;", "Working in a truly international company;"]}, "job_job_title": "Sales director", "job_posting_language": "en", "job_onet_soc": "11202200", "job_onet_job_zone": "4"}