{"job_id": "XSNUEX-W9vX7NU_cAAAAAA==", "employer_name": "Grote Industries", "employer_logo": null, "employer_website": "http://www.grote.com", "employer_company_type": "Manufacturing", "job_publisher": "ZipRecruiter", "job_employment_type": "FULLTIME", "job_title": "Director of Business Development and Product Management", "job_apply_link": "https://www.ziprecruiter.com/c/Grote-Industries/Job/Director-of-Business-Development-and-Product-Management/-in-Madison,IN?jid=45b2ec83f94f6e8f", "job_apply_is_direct": false, "job_apply_quality_score": 0.7222, "apply_options": [{"publisher": "ZipRecruiter", "apply_link": "https://www.ziprecruiter.com/c/Grote-Industries/Job/Director-of-Business-Development-and-Product-Management/-in-Madison,IN?jid=45b2ec83f94f6e8f", "is_direct": false}, {"publisher": "Glassdoor", "apply_link": "https://www.glassdoor.com/job-listing/director-of-business-development-and-product-management-grote-industries-JV_IC1145164_KO0,55_KE56,72.htm?jl=1009113081737", "is_direct": false}, {"publisher": "Dayforce HCM", "apply_link": "https://globalus232.dayforcehcm.com/CandidatePortal/en-US/groteindustries/Posting/View/736", "is_direct": false}, {"publisher": "LinkedIn", "apply_link": "https://www.linkedin.com/jobs/view/director-of-business-development-and-product-management-at-grote-industries-3823828481", "is_direct": false}, {"publisher": "Indeed", "apply_link": "https://www.indeed.com/viewjob?jk=2ae5ad71fc1aa103", "is_direct": false}, {"publisher": "SimplyHired", "apply_link": "https://www.simplyhired.com/job/1omB0WooZeBbIJQT7rYbiJmjneJ5pdz4SMS-Bj1SNbIW02zb9KacUA", "is_direct": false}, {"publisher": "FactoryFix", "apply_link": "https://jobs.factoryfix.com/jobs/director-of-business-development-and-product-management--madison--in--1407942307--V2", "is_direct": false}, {"publisher": "Learn4Good", "apply_link": "https://www.learn4good.com/jobs/madison/indiana/business/2905839748/e/", "is_direct": false}], "job_description": "Director of Business Development and Product Management\n\nMadison, IN, USA Req #496\nTuesday, February 6, 2024\n\nJob Title: Director of Business Development and Product Management\n\nCreation date: 1/16/2024\n\nSalary Grade:\n\nClassification: Exempt\n\nSupervises Others: Yes\n\nReports to: Chief Operating Officer\n\nJob Role/Summary:\n\nThe Director of Business Development and Product Management is responsible for monetizing market insight and overseeing the growth and evolution of the company through effective go to market and market acquisition strategy and product portfolio management.\n\nThis role requires relevant skills and experience in market analytics (including customer, competition, and product offerings), business building and product management. Drives company to a market orientation that gets Grote closer to its customers.\n\nThis role will oversee the product life cycle and work with sales, engineering, and manufacturing to make decisions on end of life, improvements, and other product changes as are necessary to meet the business needs.\n\nJob Responsibilities:\n\nPEOPLE\n\u2022 Team building and development\n\u2022 Performance management\n\u2022 Creation of the intellectual capital required for effective Business Development and Product Management\n\nPROCESS and TOOLS\n\u2022 Go to Market Strategy\n\u2022 Market Acquisition Strategy\n\u2022 Product Management\n\u2022 Value Proposition Canvas\n\nOUTCOMES\n\nSecondary\n\nQuality:\n\u2022 Develop and maintain the quality and integrity of BD and PM intellectual capital.\n\nResponsibility & Customer-Focused:\n\u2022 Develop and execute business development plans to drive revenue growth and expand the customer base.\n\u2022 Ability to teach Business Development tools and processes as well as lead a BD team.\n\u2022 Identify market trends and customer needs to inform product development and enhancement strategies.\n\u2022 Conduct competitive analyses to identify opportunities for differentiation and positioning of the company's products.\n\u2022 Collaborate with cross-functional teams, including sales, marketing, and operations, to drive alignment and effective execution of product strategies.\n\u2022 Develop and manage strategic partnerships and alliances to expand the company's reach and market share.\n\u2022 Monitor and evaluate industry trends and competitor activities to identify potential threats and opportunities.\n\u2022 Develop pricing strategies and value propositions that maximize profitability and customer satisfaction.\n\u2022 Define and track key performance indicators to measure the success of business development and product management initiatives.\n\u2022 Manage the product lifecycle, from ideation and development to launch and post-launch support.\n\u2022 Lead a team of product managers and business development professionals, providing guidance and support to achieve departmental goals.\n\u2022 Collaborate with all locations and necessary stakeholders to create and present a 3-5-year strategic plan for product development and expected customer needs and requirements.\n\nIntegrity:\n\u2022 Timely execution of project plans, programs and insight development.\n\u2022 Completes special projects with intent of achieving corporate plans and goals.\n\nOther Functions:\n\u2022 Required to follow any other instructions and to perform any other duties as requested by supervisor.\n\nAttributes and Competencies:\n\u2022 Quality Driven\n\u2022 Respectful\n\u2022 Honesty\n\u2022 Customer Driven\n\u2022 Responsible\n\u2022 Innovative\n\u2022 Responsible Corporate Citizen\n\u2022 Team Player\n\u2022 Building Winning Teams\n\u2022 Positive Attitude\n\u2022 Detail Oriented\n\u2022 Effective Communication\n\u2022 Results Oriented\n\u2022 Process Improvement\n\nCompetencies:\n\u2022 Market Analytics (tools and processes that expose risk and exploit revenue stream opportunities - ie. monetize market insight through product and service revenue streams).\n\u2022 Product Management\n\u2022 Networking - partner development\n\u2022 Business building - analytics, modelling and scaling\n\u2022 Building winning teams (this extends beyond the BD/PM function to internal x-functional, supplier and customer collaboration)\n\u2022 Education, Experience, Training, Certifications and Licenses:\n\nDegree or equivalent experience:\n\u2022 Bachelor's degree in business administration, marketing, or a related field. Master's degree preferred.\n\nYears of experience:\n\u2022 7+ years of industry experience required in Business Development and Product Management (min 3 years in a leadership capacity)\n\u2022 BD and PM Methods and Tools development and implementation at scale\n\u2022 Strategy deployment (Hoshin, OKR, BSC)\n\u2022 Lean / Agile product and service development\n\u2022 M&A\n\nMust successfully pass any pre-screening test(s).\n\nKnowledge, Skills, and Abilities:\n\nKnowledge in:\n\u2022 BD methods and tools, such as Business Market Canvas, Customer Journey Map, Value Proposition Canvas, Competitive analysis, marketing and sales (ie. pitching and closing), others\n\u2022 Product Management - vision (value prop/ BMC), design (mapping, PRD), strategy (product/market fit), and execution (OKR)\n\u2022 product management principles, including market research, competitive analysis, and product lifecycle management\n\nSkills in:\n\u2022 Strong analytical and strategic thinking skills, with the ability to interpret market data and trends to inform business decisions.\n\u2022 Excellent communication and interpersonal skills, with the ability to build and maintain relationships with key stakeholders.\n\u2022 Proven leadership abilities, with experience managing teams and driving cross-functional collaboration.\n\u2022 Strong negotiation and influencing skills to drive partnerships and alliances.\n\nDemonstrated ability to:\n\u2022 Ability to interact with all levels of employees.\n\u2022 Work at a highly motivated level with a sense of urgency and dedication to accomplishing tasks. < self-directed\n\u2022 Adapt to frequent changes in work environment & prioritization.\n\u2022 Work with general or minimal supervision.\n\nExperience with:\n\u2022 Conflict resolution\n\u2022 In-depth problem identification, analysis and resolution\n\u2022 Prioritizing and executing multiple projects\n\nOther:\n\u2022 Must be proficient with Microsoft 365 / Office applications and data analysis tools.\n\u2022 Social media (omni-channel) platforms, collaboration and project management platforms (MS Teams and Smartsheet), analytics (PowerBI, CRM)\n\u2022 Travel:\n\u2022 As needed\n\nOther details\n\u2022 Job Family Executive - US\n\u2022 Pay Type Salary\n\u2022 Travel Required Yes\n\u2022 Required Education Bachelor's Degree\nApply Now", "job_is_remote": false, "job_posted_at_timestamp": 1710116880, "job_posted_at_datetime_utc": "2024-03-11T00:28:00.000Z", "job_city": "Madison", "job_state": "IN", "job_country": "US", "job_latitude": 38.735893, "job_longitude": -85.37996, "job_benefits": ["retirement_savings"], "job_google_link": "https://www.google.com/search?gl=us&hl=en&rciv=jb&q=director+of+business+development&start=10&ibp=htl;jobs#fpstate=tldetail&htivrt=jobs&htiq=director+of+business+development&htidocid=XSNUEX-W9vX7NU_cAAAAAA%3D%3D", "job_offer_expiration_datetime_utc": "2024-04-09T00:00:00.000Z", "job_offer_expiration_timestamp": 1712620800, "job_required_experience": {"no_experience_required": false, "required_experience_in_months": 84, "experience_mentioned": true, "experience_preferred": false}, "job_required_skills": null, "job_required_education": {"postgraduate_degree": false, "professional_certification": false, "high_school": false, "associates_degree": false, "bachelors_degree": false, "degree_mentioned": true, "degree_preferred": true, "professional_certification_mentioned": true}, "job_experience_in_place_of_education": false, "job_min_salary": null, "job_max_salary": null, "job_salary_currency": null, "job_salary_period": null, "job_highlights": {"Qualifications": ["Creation of the intellectual capital required for effective Business Development and Product Management", "Quality Driven", "Respectful", "Honesty", "Customer Driven", "Innovative", "Responsible Corporate Citizen", "Building Winning Teams", "Positive Attitude", "Detail Oriented", "Effective Communication", "Results Oriented", "Process Improvement", "Market Analytics (tools and processes that expose risk and exploit revenue stream opportunities - ie", "Bachelor's degree in business administration, marketing, or a related field", "7+ years of industry experience required in Business Development and Product Management (min 3 years in a leadership capacity)", "BD and PM Methods and Tools development and implementation at scale", "Strategy deployment (Hoshin, OKR, BSC)", "Lean / Agile product and service development", "Must successfully pass any pre-screening test(s)", "BD methods and tools, such as Business Market Canvas, Customer Journey Map, Value Proposition Canvas, Competitive analysis, marketing and sales (ie", "Strong analytical and strategic thinking skills, with the ability to interpret market data and trends to inform business decisions", "Excellent communication and interpersonal skills, with the ability to build and maintain relationships with key stakeholders", "Proven leadership abilities, with experience managing teams and driving cross-functional collaboration", "Strong negotiation and influencing skills to drive partnerships and alliances", "Ability to interact with all levels of employees", "Work at a highly motivated level with a sense of urgency and dedication to accomplishing tasks", "Conflict resolution", "In-depth problem identification, analysis and resolution", "Prioritizing and executing multiple projects", "Must be proficient with Microsoft 365 / Office applications and data analysis tools", "Social media (omni-channel) platforms, collaboration and project management platforms (MS Teams and Smartsheet), analytics (PowerBI, CRM)", "Required Education Bachelor's Degree"], "Responsibilities": ["Supervises Others: Yes", "Reports to: Chief Operating Officer", "The Director of Business Development and Product Management is responsible for monetizing market insight and overseeing the growth and evolution of the company through effective go to market and market acquisition strategy and product portfolio management", "This role requires relevant skills and experience in market analytics (including customer, competition, and product offerings), business building and product management", "Drives company to a market orientation that gets Grote closer to its customers", "This role will oversee the product life cycle and work with sales, engineering, and manufacturing to make decisions on end of life, improvements, and other product changes as are necessary to meet the business needs", "Value Proposition Canvas", "Develop and maintain the quality and integrity of BD and PM intellectual capital", "Develop and execute business development plans to drive revenue growth and expand the customer base", "Ability to teach Business Development tools and processes as well as lead a BD team", "Identify market trends and customer needs to inform product development and enhancement strategies", "Conduct competitive analyses to identify opportunities for differentiation and positioning of the company's products", "Collaborate with cross-functional teams, including sales, marketing, and operations, to drive alignment and effective execution of product strategies", "Develop and manage strategic partnerships and alliances to expand the company's reach and market share", "Monitor and evaluate industry trends and competitor activities to identify potential threats and opportunities", "Develop pricing strategies and value propositions that maximize profitability and customer satisfaction", "Define and track key performance indicators to measure the success of business development and product management initiatives", "Manage the product lifecycle, from ideation and development to launch and post-launch support", "Lead a team of product managers and business development professionals, providing guidance and support to achieve departmental goals", "Collaborate with all locations and necessary stakeholders to create and present a 3-5-year strategic plan for product development and expected customer needs and requirements", "Completes special projects with intent of achieving corporate plans and goals", "Required to follow any other instructions and to perform any other duties as requested by supervisor", "monetize market insight through product and service revenue streams)", "Networking - partner development", "Business building - analytics, modelling and scaling", "Building winning teams (this extends beyond the BD/PM function to internal x-functional, supplier and customer collaboration)", "pitching and closing), others", "Product Management - vision (value prop/ BMC), design (mapping, PRD), strategy (product/market fit), and execution (OKR)", "Adapt to frequent changes in work environment & prioritization"], "Benefits": ["Pay Type Salary"]}, "job_job_title": "Management", "job_posting_language": "en", "job_onet_soc": "11202100", "job_onet_job_zone": "4", "job_occupational_categories": ["41-1012.00: First-Line Supervisors of Non-Retail Sales Workers"], "job_naics_code": "3351", "job_naics_name": "Electric Lighting Equipment Manufacturing"}