{"job_id": "8d8mz68x8y-YAcIFAAAAAA==", "employer_name": "Trellix", "employer_logo": "https://www.trellix.com/en-us/assets/logos/trellix-logo.svg", "employer_website": "http://www.fireeye.com", "employer_company_type": "Information", "job_publisher": "Adzuna", "job_employment_type": "FULLTIME", "job_title": "Vice President Sales - Americas", "job_apply_link": "https://www.adzuna.com/details/4601128682", "job_apply_is_direct": false, "job_apply_quality_score": 0.5155, "apply_options": [{"publisher": "Adzuna", "apply_link": "https://www.adzuna.com/details/4601128682", "is_direct": false}], "job_description": "Job Title:\nVice President Sales - Americas\nRole Overview:\nReporting to the Chief Revenue Officer, you will be responsible for owning the entire revenue generation process and exceeding company revenue targets for the Americas. You will lead a sales team and be held accountable for building long term relationships with clients and partners to solve strategic issues and generate opportunities. This role will be both strategic and hands-on, managing and working with senior management to develop and advance current and new revenue models. The ideal candidate will have previous work experience as a member of a corporate sales team and a career track record of exceeding multi-million-dollar sales quotas.\nAbout Skyhigh Security\nSkyhigh Security is a dynamic, fast-paced, cloud company that is a leader in the security industry. Our mission is to protect the world's data, and because of this, we live and breathe security. We value learning at our core, underpinned by openness and transparency.\nSince 2011, organizations have trusted us to provide them with a complete, market-leading security platform built on a modern cloud stack. Our industry-leading suite of products radically simplifies data security through easy-to-use, cloud-based, Zero Trust solutions that are managed in a single dashboard, powered by hundreds of employees across the world. With offices in Santa Clara, Aylesbury, Paderborn, Bengaluru, Sydney, Tokyo and more, our employees are the heart and soul of our company.\nSkyhigh Security Is more than a company; here, when you invest your career with us, we commit to investing in you. We embrace a hybrid work model, creating the flexibility and freedom you need from your work environment to reach your potential. From our employee recognition program, to our 'Blast Talks' learning series, and team celebrations (we love to have fun!), we strive to be an interactive and engaging place where you can be your authentic self.\nWe are on these too! Follow us on LinkedIn (https://www.linkedin.com/company/skyhighsecurity/mycompany/) and Twitter@SkyhighSecurity (https://twitter.com/SkyhighSecurity?ref_src=twsrc%5Egoogle%7Ctwcamp%5Eserp%7Ctwgr%5Eauthor) .\nAbout The Role\nReporting to the Chief Revenue Officer, you will be responsible for owning the entire revenue generation process and exceeding company revenue targets for the Americas. You will lead a sales team and be held accountable for building long term relationships with clients and partners to solve strategic issues and generate opportunities. This role will be both strategic and hands-on, managing and working with senior management to develop and advance current and new revenue models. The ideal candidate will have previous work experience as a member of a corporate sales team and a career track record of exceeding multi-million-dollar sales quotas.\nYou will execute an operational strategy to land new customers in Skyhigh Security's ideal customer profile (ICP). We will rely on you to refine and execute a go-to-market strategy that maximizes Annual Recurring Revenue (ARR) growth and minimizes churn. You will maintain key customer relationships and implement strategies for expanding the company's customer base. Planning and managing at a strategic and operational level, you will support the growth of the Americas by nurturing executive relationships with a vision for expansion with purpose, driving customer success during a critical stage in our growth.\nIn this role, you will work cross-functionally to create and close new business, building relationships with stakeholders at all levels - from the front desk to the executive suite. Your presence will ensure that our customers adopt and realize the value of our solutions. Your day-to-day will involve developing and executing sales strategies to achieve sales targets, including creating a consistent rolling three quarter pipeline. You will generate direct customer meetings and qualify opportunities, forecasting revenue on a quarterly basis to deliver against revenue targets.\n- Build and lead a high performance, accountable, sales-driven culture with a focus on vision, strategy and business plan execution that leads to predictable growth.\n- Implement and drive sales pipeline activities and forecasts using a proven sales methodology.\n- Recruit, hire, develop and inspire sales teams, as well as address sales performance issues.\n- Develop winning strategies and partnership programs for top/key growth accounts.\n- Build and maintain channel of high-quality client relationships and partnerships.\n- Provide accurate and timely management information, revenue forecasts, reports and analysis, and ensure clear communication to executive leadership team and stakeholders.\nAbout You\n- 10+ years of enterprise level sales experience, selling security solutions to Fortune 1000/Global 2000 companies and leading teams of 20-40 people.\n- Track record of developing sustainable new business within the security space.\n- Experience working in early-stage start-up or hyper-growth companies is a must.\n- A team player, able to work effectively cross functionally across the organization.\n- In-depth knowledge of implementing GTM strategies, as well as employee motivation techniques.\n- Strong knowledge of the company's products, competitive products, and the market.\n- Excellent leadership, communication, and customer success skills.\n- Demonstrated ability to work in a fast-changing environment and able to work under pressure.\n- Strong sense of urgency and personal accountability.\n- In depth knowledge of sales tools (i.e. salesforce.com).\n- MEDPICC sales methodology\n- Security industry experience.\n- Willingness to travel up to 50%.\nCompany Benefits and Perks:\nWe work hard to embrace diversity and inclusion and encourage everyone to bring their authentic selves to work every day. We offer a variety of social programs, flexible work hours and family-friendly benefits to all of our employees.\n- Retirement Plans\n- Medical, Dental and Vision Coverage\n- Paid Time Off\n- Paid Parental Leave\n- Support for Community Involvement\nWe're serious about our commitment to diversity which is why we prohibit discrimination based on race, color, religion, gender, national origin, age, disability, veteran status, marital status, pregnancy, gender expression or identity, sexual orientation or any other legally protected status.\nTrellix is a global company redefining the future of cybersecurity. The company's open and native extended detection and response (XDR) platform helps organizations confronted by today's most advanced threats gain confidence in the protection and resilience of their operations. Trellix's security experts, along with an extensive partner ecosystem, accelerate technology innovation through machine learning and automation to empower over 40,000 business and government customers. More at https://trellix.com .", "job_is_remote": false, "job_posted_at_timestamp": 1709979130, "job_posted_at_datetime_utc": "2024-03-09T10:12:10.000Z", "job_city": "Springfield", "job_state": "IL", "job_country": "US", "job_latitude": 39.781723, "job_longitude": -89.65015, "job_benefits": ["dental_coverage", "paid_time_off", "retirement_savings", "health_insurance"], "job_google_link": "https://www.google.com/search?gl=us&hl=en&rciv=jb&q=vice+president+of+sales&start=10&ibp=htl;jobs#fpstate=tldetail&htivrt=jobs&htiq=vice+president+of+sales&htidocid=8d8mz68x8y-YAcIFAAAAAA%3D%3D", "job_offer_expiration_datetime_utc": "2024-03-23T20:10:36.000Z", "job_offer_expiration_timestamp": 1711224636, "job_required_experience": {"no_experience_required": false, "required_experience_in_months": 120, "experience_mentioned": true, "experience_preferred": false}, "job_required_skills": null, "job_required_education": {"postgraduate_degree": false, "professional_certification": false, "high_school": false, "associates_degree": false, "bachelors_degree": false, "degree_mentioned": false, "degree_preferred": false, "professional_certification_mentioned": false}, "job_experience_in_place_of_education": false, "job_min_salary": null, "job_max_salary": null, "job_salary_currency": null, "job_salary_period": null, "job_highlights": {"Qualifications": ["The ideal candidate will have previous work experience as a member of a corporate sales team and a career track record of exceeding multi-million-dollar sales quotas", "10+ years of enterprise level sales experience, selling security solutions to Fortune 1000/Global 2000 companies and leading teams of 20-40 people", "Track record of developing sustainable new business within the security space", "Experience working in early-stage start-up or hyper-growth companies is a must", "A team player, able to work effectively cross functionally across the organization", "In-depth knowledge of implementing GTM strategies, as well as employee motivation techniques", "Strong knowledge of the company's products, competitive products, and the market", "Excellent leadership, communication, and customer success skills", "Demonstrated ability to work in a fast-changing environment and able to work under pressure", "Strong sense of urgency and personal accountability", "In depth knowledge of sales tools (i.e. salesforce.com)", "MEDPICC sales methodology", "Security industry experience", "Willingness to travel up to 50%"], "Responsibilities": ["Reporting to the Chief Revenue Officer, you will be responsible for owning the entire revenue generation process and exceeding company revenue targets for the Americas", "You will lead a sales team and be held accountable for building long term relationships with clients and partners to solve strategic issues and generate opportunities", "This role will be both strategic and hands-on, managing and working with senior management to develop and advance current and new revenue models", "You will execute an operational strategy to land new customers in Skyhigh Security's ideal customer profile (ICP)", "We will rely on you to refine and execute a go-to-market strategy that maximizes Annual Recurring Revenue (ARR) growth and minimizes churn", "You will maintain key customer relationships and implement strategies for expanding the company's customer base", "Planning and managing at a strategic and operational level, you will support the growth of the Americas by nurturing executive relationships with a vision for expansion with purpose, driving customer success during a critical stage in our growth", "In this role, you will work cross-functionally to create and close new business, building relationships with stakeholders at all levels - from the front desk to the executive suite", "Your presence will ensure that our customers adopt and realize the value of our solutions", "Your day-to-day will involve developing and executing sales strategies to achieve sales targets, including creating a consistent rolling three quarter pipeline", "You will generate direct customer meetings and qualify opportunities, forecasting revenue on a quarterly basis to deliver against revenue targets", "Build and lead a high performance, accountable, sales-driven culture with a focus on vision, strategy and business plan execution that leads to predictable growth", "Implement and drive sales pipeline activities and forecasts using a proven sales methodology", "Recruit, hire, develop and inspire sales teams, as well as address sales performance issues", "Develop winning strategies and partnership programs for top/key growth accounts", "Build and maintain channel of high-quality client relationships and partnerships", "Provide accurate and timely management information, revenue forecasts, reports and analysis, and ensure clear communication to executive leadership team and stakeholders"], "Benefits": ["We offer a variety of social programs, flexible work hours and family-friendly benefits to all of our employees", "Retirement Plans", "Medical, Dental and Vision Coverage", "Paid Time Off", "Paid Parental Leave", "Support for Community Involvement"]}, "job_job_title": "Vice president", "job_posting_language": "en", "job_onet_soc": "11101100", "job_onet_job_zone": "5", "job_naics_code": "511210", "job_naics_name": "Software Publishers"}